Workbook
Name jop: #REF!
Name kol: #REF!
Name OLE_LINK19: Balance!$D$32
Name TwentyLargestData: #REF!
Name Е: #REF!

Sheet Balance
A1: БАНК БАЛАНСИ ТАРКИБИ | E1: 1-жадвал | G1: №1
B2: =IF(D3>0," "&TEXT(D3,"д ММММ, гггг"),"Число,Месяц,Год") -> 31 Декабрь, 2024
B3: Банк номи | D3: 45657 | E3: минг сўмда
A4: № | B4: АКТИВЛАР | C4: Жами | D4: Миллий валютада | E4: Хорижий валютада (сўм экв.)
A5: 1 | B5: Кассадаги нақд пул ва бошқа тўлов ҳужжатлари | C5: =+D5+E5 -> 510025015 | D5: =+'Bank Assets Analysis'!T6 -> 230334913 | E5: =+'Bank Assets Analysis'!U6 -> 279690102 | J5: =+C5-D5-E5 -> 0
A6: 2 | B6: Банкнинг Марказий банкдаги маблағлари | C6: =+D6+E6 -> 1828213292 | D6: =+'Bank Assets Analysis'!T7+'Bank Assets Analysis'!T8 -> 1828213292 | E6: =+'Bank Assets Analysis'!U7+'Bank Assets Analysis'!U8 -> 0 | J6: =+C6-D6-E6 -> 0
A7: 3 | B7: Бошқа банклар ва молиявий ташкилотлардан олиниши лозим бўлган маблағлар, соф | C7: =+'Bank Assets Analysis'!S9 -> 893895010 | D7: =+'Bank Assets Analysis'!T9 -> 255178602 | E7: =+'Bank Assets Analysis'!U9 -> 638716408 | J7: =+C7-D7-E7 -> 0
A8: 3.1 | B8: Бошқа банклар ва молиявий ташкилотлардан олиниши лозим бўлган маблағлар, брутто | C8: =+D8+E8 -> 893895010 | D8: 255178602 | E8: 638716408 | J8: =+C8-D8-E8 -> 0
A9: 3.2 | B9: Минус: Кўрилиши мумкин бўлган зарарларни қоплаш захираси | C9: =+D9+E9 -> 0 | D9: 0 | E9: 0 | J9: =+C9-D9-E9 -> 0
A10: 4 | B10: Қимматли қоғозлар ва уларга қилинган инвестициялар, соф | C10: =+D10+E10 -> 2113772835 | D10: =+'Investment Securities'!C29 -> 2113772835 | E10: =+'Investment Securities'!D29 -> 0 | J10: =+C10-D10-E10 -> 0
A11: 4.1 | B11: Қимматли қоғозлар ва уларга қилинган инвестициялар, брутто | C11: =+D11+E11 -> 2166910000 | D11: =+'Investment Securities'!C26 -> 2166910000 | E11: =+'Investment Securities'!D26 -> 0 | J11: =+C11-D11-E11 -> 0
A12: 4.2 | B12: Қимматли қоғозлар бўйича харажатлар, дисконт, мукофот ва уларнинг ҳаққоний қийматининг ўзгариши | C12: =+D12+E12 -> -53137165 | D12: =+'Investment Securities'!C27 -> -53137165 | E12: =+'Investment Securities'!D27 -> 0 | J12: =+C12-D12-E12 -> 0
A13: 4.3 | B13: Минус: Кўрилиши мумкин бўлган зарарларни қоплаш захираси | C13: =+D13+E13 -> 0 | D13: =+'Investment Securities'!C28 -> 0 | E13: =+'Investment Securities'!D28 -> 0 | J13: =+C13-D13-E13 -> 0
A14: 5 | B14: Қимматбаҳо металлар, тошлар ва тангалар, соф | C14: =+C15-C16 -> 251 | D14: =+'Investment Securities'!C39 -> 251 | E14: =+'Investment Securities'!D39 -> 0 | J14: =+C14-D14-E14 -> 0
A15: 5.1 | B15: Қимматбаҳо металлар, тошлар ва тангалар, брутто | C15: =+D15+E15 -> 251 | D15: =+'Investment Securities'!C37 -> 251 | E15: =+'Investment Securities'!D37 -> 0 | J15: =+C15-D15-E15 -> 0
A16: 5.2 | B16: Минус: Кўрилиши мумкин бўлган зарарларни қоплаш захираси | C16: =+D16+E16 -> 0 | D16: =+'Investment Securities'!C38 -> 0 | E16: =+'Investment Securities'!D38 -> 0 | J16: =+C16-D16-E16 -> 0
A17: 6 | B17: Инвестициялар, соф | C17: =+'Investment Securities'!B15 -> 391688858 | D17: =+'Investment Securities'!C15 -> 391688858 | E17: =+'Investment Securities'!D15 -> 0 | J17: =+C17-D17-E17 -> 0
A18: 6.1 | B18: Инвестициялар, брутто | C18: =+D18+E18 -> 391688858 | D18: =+'Investment Securities'!C12 -> 391688858 | E18: =+'Investment Securities'!D12 -> 0 | J18: =+C18-D18-E18 -> 0
A19: 6.2 | B19: Инвестициялар бўйича харажатлар, дисконт ва мукофот | C19: =+D19+E19 -> 0 | D19: =+'Investment Securities'!C13 -> 0 | E19: =+'Investment Securities'!D13 -> 0 | J19: =+C19-D19-E19 -> 0
A20: 6.3 | B20: Минус: Кўрилиши мумкин бўлган зарарларни қоплаш захираси | C20: =+D20+E20 -> 0 | D20: =+'Investment Securities'!C14 -> 0 | E20: =+'Investment Securities'!D14 -> 0 | J20: =+C20-D20-E20 -> 0
A21: 7 | B21: РЕПО битимлари бўйича сотиб олинган қимматли қоғозлар, соф | C21: =+'Bank Assets Analysis'!S34 -> 0 | D21: =+'Bank Assets Analysis'!T34 -> 0 | E21: =+'Bank Assets Analysis'!U34 -> 0 | J21: =+C21-D21-E21 -> 0
A22: 7.1 | B22: РЕПО битимлари бўйича сотиб олинган қимматли қоғозлар, брутто | C22: =+D22+E22 -> 0 | D22: 0 | E22: 0 | J22: =+C22-D22-E22 -> 0
A23: 7.2 | B23: Минус: Кўрилиши мумкин бўлган зарарларни қоплаш захираси | C23: =+D23+E23 -> 0 | D23: 0 | E23: 0 | J23: =+C23-D23-E23 -> 0
A24: 8 | B24: Кредит ва лизинг операциялари, соф | C24: =+'Bank Assets Analysis'!S29+'Bank Assets Analysis'!S30+'Bank Assets Analysis'!S32 -> 12690227947 | D24: =+'Bank Assets Analysis'!T29+'Bank Assets Analysis'!T30+'Bank Assets Analysis'!T32 -> 8933517184 | E24: =+'Bank Assets Analysis'!U29+'Bank Assets Analysis'!U30+'Bank Assets Analysis'!U32 -> 3756710763 | J24: =+C24-D24-E24 -> 0
A25: 8.1 | B25: Кредит ва лизинг операциялари, брутто | C25: =+D25+E25 -> 12944272857 | D25: 9106658434 | E25: 3837614423 | J25: =+C25-D25-E25 -> 0
A26: 8.2 | B26: Минус: Кўрилиши мумкин бўлган зарарларни қоплаш захираси | C26: =+D26+E26 -> 254044910 | D26: 173141250 | E26: 80903660 | J26: =+C26-D26-E26 -> 0
A27: 9 | B27: Молиявий инструментлар бўйича мижозларнинг мажбуриятлари, соф | C27: =+'Bank Assets Analysis'!S26+'Bank Assets Analysis'!S27 -> 38090268 | D27: =+'Bank Assets Analysis'!T26+'Bank Assets Analysis'!T27 -> 0 | E27: =+'Bank Assets Analysis'!U26+'Bank Assets Analysis'!U27 -> 38090268 | J27: =+C27-D27-E27 -> 0
A28: 9.1 | B28: Молиявий инструментлар бўйича мижозларнинг мажбуриятлари, брутто | C28: =+D28+E28 -> 38090268 | D28: 0 | E28: 38090268 | J28: =+C28-D28-E28 -> 0
A29: 9.2 | B29: Минус: Кўрилиши мумкин бўлган зарарларни қоплаш захираси | C29: =+D29+E29 -> 0 | D29: 0 | E29: 0 | J29: =+C29-D29-E29 -> 0
A30: 10 | B30: Асосий воситалар, соф | C30: =+'Bank Assets Analysis'!S37 -> 2578342217 | D30: =+'Bank Assets Analysis'!T37 -> 2578342217 | E30: =+'Bank Assets Analysis'!U37 -> 0 | J30: =+C30-D30-E30 -> 0
A31: 11 | B31: Жами ҳисобланган фоизли ва фоизсиз даромадлар, соф | C31: =+C32+C33-C34 -> 486332855 | D31: =+D32+D33-D34 -> 318212092 | E31: =+E32+E33-E34 -> 168120763 | J31: =+C31-D31-E31 -> 0
A32: 11.1 | B32: Ҳисобланган фоизли даромадлар, брутто | C32: =+D32+E32 -> 476688413 | D32: 311169988 | E32: 165518425 | J32: =+C32-D32-E32 -> 0
A33: 11.2 | B33: Ҳисобланган фоизсиз даромадлар, брутто | C33: =+D33+E33 -> 48870351 | D33: 37626771 | E33: 11243580 | J33: =+C33-D33-E33 -> 0
A34: 11.2.1 | B34: Минус: Кўрилиши мумкин бўлган зарарларни қоплаш захираси | C34: =+D34+E34 -> 39225909 | D34: 30584667 | E34: 8641242 | J34: =+C34-D34-E34 -> 0
A35: 12 | B35: Банкнинг бошқа хусусий мулклари, соф | C35: =+'Bank Assets Analysis'!S38 -> 348511262 | D35: =+'Bank Assets Analysis'!T38 -> 348511262 | E35: =+'Bank Assets Analysis'!U38 -> 0 | J35: =+C35-D35-E35 -> 0
A36: 12.1 | B36: Кредит ва лизинг бўйича гаров ҳисобидан ундирилган бошқа мулклар, брутто | C36: =+D36+E36 -> 159319537 | D36: 159319537 | E36: 0 | J36: =+C36-D36-E36 -> 0
A37: 12.2 | B37: Банкнинг бошқа хусусий мулклари, брутто | C37: =+D37+E37 -> 230311372 | D37: 230311372 | E37: 0 | J37: =+C37-D37-E37 -> 0
A38: 12.3 | B38: Минус: Йиғилган эскириш суммаси ва кўрилиши мумкин бўлган зарарларни қоплаш захираси | C38: =+D38+E38 -> 41119647 | D38: 41119647 | E38: 0 | J38: =+C38-D38-E38 -> 0
A39: 13 | B39: Стандарт деб таснифланган активлар бўйича яратилган захиралар | C39: =+D39+E39 -> 152699838 | D39: =+D40+D41+D42 -> 152699838 | E39: =+E40+E41+E42 -> 0 | J39: =+C39-D39-E39 -> 0
A40: 13.1 | B40: Стандарт деб таснифланган кредитлар, лизинг ва факторинг бўйича захира | C40: =+D40+E40 -> 111553656 | D40: 111553656 | E40: 0 | J40: =+C40-D40-E40 -> 0
A41: 13.2 | B41: Стандарт деб таснифланган бошқа активлар бўйича захира | C41: =+D41+E41 -> 31836628 | D41: 31836628 | E41: 0 | J41: =+C41-D41-E41 -> 0
A42: 13.3 | B42: Стандарт деб таснифланган активлар бўйича фоизлар ва воситачилик ҳақларига оид захира | C42: =+D42+E42 -> 9309554 | D42: 9309554 | E42: 0 | J42: =+C42-D42-E42 -> 0
A43: 14 | B43: Бошқа активлар, соф | C43: =+C44-C45+C46 -> 1524874715 | D43: =+D44-D45+D46 -> 1497357738 | E43: =+E44-E45+E46 -> 27516977 | J43: =+C43-D43-E43 -> 0
A44: 14.1 | B44: Бошқа активлар, брутто | C44: =+D44+E44 -> 1525252623 | D44: 1497734443 | E44: 27518180 | J44: =+C44-D44-E44 -> 0
A45: 14.2 | B45: Минус: Кўрилиши мумкин бўлган зарарларни қоплаш захираси | C45: =+D45+E45 -> 377908 | D45: 376705 | E45: 1203 | J45: =+C45-D45-E45 -> 0
A46: 14.3 | B46: Валюталар савдоси ва валюта позициялари | C46: 0 | J46: =+C46-D46-E46 -> 0
A47: 15 | B47: Жами активлар | C47: =+D47+E47 -> 23251274687 | D47: =+D5+D6+D7+D10+D14+D17+D21+D24+D27+D30+D31+D35-D39+D43 -> 18342429406 | E47: =+E5+E6+E7+E10+E14+E17+E21+E24+E27+E30+E31+E35-E39+E43 -> 4908845281 | F47: =+'Bank Assets Analysis'!S47 -> 23251274687 | G47: =+'Bank Assets Analysis'!T47 -> 18342429406 | H47: =+'Bank Assets Analysis'!U47 -> 4908845281 | J47: =+C47-D47-E47 -> 0
B49: МАЖБУРИЯТЛАР
A50: 16 | B50: Талаб қилиб олингунча сақланадиган депозитлар | C50: =+'Deposits by Client'!C11 -> 4052800159 | D50: =+'Bank Liabilities Analysis'!T15+'Bank Liabilities Analysis'!T7 -> 3420188590 | E50: =+'Bank Liabilities Analysis'!U15+'Bank Liabilities Analysis'!U7 -> 632611569 | J50: =+C50-D50-E50 -> 0
A51: 17 | B51: Муддатли депозитлар | C51: =+'Deposits by Client'!C20 -> 9761874655 | D51: =+'Bank Liabilities Analysis'!T12 -> 8890716389 | E51: =+'Bank Liabilities Analysis'!U12 -> 871158266 | J51: =+C51-D51-E51 -> 0
A52: 18 | B52: Марказий банкка тўланиши лозим бўлган маблағлар | C52: =+'Bank Liabilities Analysis'!S21 -> 424511118 | D52: =+'Bank Liabilities Analysis'!T21 -> 424511118 | E52: =+'Bank Liabilities Analysis'!U21 -> 0 | J52: =+C52-D52-E52 -> 0
A53: 19 | B53: Бошқа банклар ва молиявий ташкилотларнинг ҳисобварақлари | C53: =+'Bank Liabilities Analysis'!S23 -> 1328179724 | D53: =+'Bank Liabilities Analysis'!T23 -> 592101871 | E53: =+'Bank Liabilities Analysis'!U23 -> 736077853 | J53: =+C53-D53-E53 -> 0
A54: 20 | B54: РЕПО битимлари бўйича сотилган қимматли қоғозлар | C54: =+'Bank Liabilities Analysis'!S33 -> 801459811 | D54: =+'Bank Liabilities Analysis'!T33 -> 801459811 | E54: =+'Bank Liabilities Analysis'!U33 -> 0 | J54: =+C54-D54-E54 -> 0
A55: 21 | B55: Кредит ва лизинг операциялари бўйича мажбуриятлар | C55: =+D55+E55 -> 3099281224 | D55: 638589830 | E55: 2460691394 | J55: =+C55-D55-E55 -> 0
A56: 22 | B56: Банк томонидан чиқарилган қимматли қоғозлар | C56: =+D56+E56 -> 0 | D56: 0 | E56: 0 | J56: =+C56-D56-E56 -> 0
A57: 23 | B57: Субординар қарз | C57: =+D57+E57 -> 167901638 | D57: 0 | E57: 167901638 | J57: =+C57-D57-E57 -> 0
A58: 24 | B58: Тўланиши лозим бўлган ҳисобланган фоизлар | C58: =+'Bank Liabilities Analysis'!S38+'Bank Liabilities Analysis'!S39+'Bank Liabilities Analysis'!S40 -> 114739048 | D58: =+'Bank Liabilities Analysis'!T38+'Bank Liabilities Analysis'!T39+'Bank Liabilities Analysis'!T40 -> 58275691 | E58: =+'Bank Liabilities Analysis'!U38+'Bank Liabilities Analysis'!U39+'Bank Liabilities Analysis'!U40 -> 56463357 | J58: =+C58-D58-E58 -> 0
A59: 25 | B59: Ҳисобланган солиқлар бўйича мажбуриятлар | C59: =+D59+E59 -> 109486702 | D59: 109486702 | E59: 0 | J59: =+C59-D59-E59 -> 0
A60: 26 | B60: Клиринг транзакциялари | C60: =+'Bank Liabilities Analysis'!S37 -> 787274 | D60: =+'Bank Liabilities Analysis'!T37 -> 35574 | E60: =+'Bank Liabilities Analysis'!U37 -> 751700 | J60: =+C60-D60-E60 -> 0
A61: 27 | B61: Стандарт деб таснифланган балансдан ташқари моддаларга яратилган захиралар | C61: =+D61+E61 -> 0 | D61: 0 | E61: 0 | J61: =+C61-D61-E61 -> 0
A62: 28 | B62: Бошқа мажбуриятлар | C62: =+D62+E62 -> 308012759 | D62: 199449324 | E62: 108563435 | J62: =+C62-D62-E62 -> 0
A63: 29 | B63: Жами мажбуриятлар | C63: =+D63+E63 -> 20169034112 | D63: =SUM(D50:D62) -> 15134814900 | E63: =SUM(E50:E62) -> 5034219212 | F63: =+'Bank Liabilities Analysis'!S42 -> 20169034112 | G63: =+'Bank Liabilities Analysis'!T42 -> 15134814900 | H63: =+'Bank Liabilities Analysis'!U42 -> 5034219212 | J63: =+C63-D63-E63 -> 0
B65: ХУСУСИЙ КАПИТАЛ
A67: 30 | B67: Устав капитали | C67: =+C68+C69 -> 2318223047 | D67: =+D68+D69 -> 2318223047 | E67: =+E68+E69 -> 0 | J67: =+C67-D67-E67 -> 0
A68: 30.1 | B68: Aкциялар – оддий | C68: =+D68+E68 -> 2314533047 | D68: 2314533047 | E68: 0 | J68: =+C68-D68-E68 -> 0
A69: 30.2 | B69: Aкциялар – имтиёзли | C69: =+D69+E69 -> 3690000 | D69: 3690000 | E69: 0 | J69: =+C69-D69-E69 -> 0
A70: 31 | B70: Қўшилган капитал | C70: =+D70+E70 -> 3906139 | D70: 3906139 | E70: 0 | J70: =+C70-D70-E70 -> 0
A71: 32 | B71: Захира капитали | C71: =+C72+C73+C74 -> 556093546 | D71: =+D72+D73+D74 -> 556093546 | E71: =+E72+E73+E74 -> 0 | J71: =+C71-D71-E71 -> 0
A72: 32.1 | B72: Умумий захира фонди | C72: =+D72+E72 -> 552492626 | D72: 552492626 | E72: 0 | J72: =+C72-D72-E72 -> 0
A73: 32.2 | B73: Девальвация учун захира | C73: =+D73+E73 -> 0 | D73: 0 | E73: 0 | J73: =+C73-D73-E73 -> 0
A74: 32.3 | B74: Бошқа захира фондлари | C74: =+D74+E74 -> 3600920 | D74: 3600920 | E74: 0 | J74: =+C74-D74-E74 -> 0
A75: 33 | B75: Тақсимланмаган фойда | C75: =+D75+E75 -> 204017843 | D75: 204017843 | E75: 0 | J75: =+C75-D75-E75 -> 0
A76: 33.1 | B76: шундан, жорий йил соф фойдаси (зарари) | C76: =+D76+E76 -> 189972487 | D76: 189972487 | E76: 0 | J76: =+C76-D76-E76 -> 0
A77: 34 | B77: Жами хусусий капитал | C77: =+C67+C70+C71+C75 -> 3082240575 | D77: =+D67+D70+D71+D75 -> 3082240575 | E77: =+E67+E70+E71+E75 -> 0 | J77: =+C77-D77-E77 -> 0
A78: 35 | B78: Жами мажбуриятлар ва хусусий капитал | C78: =+D78+E78 -> 23251274687 | D78: =+D63+D77 -> 18217055475 | E78: =+E63+E77 -> 5034219212 | J78: =+C78-D78-E78 -> 0
B80: Бошқарув Раис имзоси:
B82: Бош бухгалтер имзоси:
C86: =+C47-C78 -> 0

Sheet Bank Capital Calc (2)
A1: РАСЧЕТ РЕГУЛЯТИВНОГО КАПИТАЛА БАНКА | C1: Таблица-5
B3: =Balance!B3 -> Банк номи | C3: =+Balance!D3 -> 45657
A4: № | B4: Характеристики | C4: Итого капитала
A5: I. | B5: КАПИТАЛ УРОВНЯ 1
A6: 1 | B6: ОСНОВНОЙ КАПИТАЛ УРОВНЯ 1
A7: 1.1. | B7: Обыкновенные Акции, чистые | C7: Формула
A8: a | B8: Полностью оплаченные обыкновенные акции
A9: б | B9: Минус: Обратно Выкупленные обыкновенные акции
A10: 1.2. | B10: Добавленный капитал - Обыкновенные | C10: 0
A11: 1.3. | B11: Нераспределенная прибыль (убыток), в том числе капитальные резервы | C11: Формула
A12: а | B12: Капитальные резервы
A13: б | B13: Нераспределенная прибыль
A14: в | B14: Убыток за предыдущие периоды
A15: г | B15: Убыток за текущий год
A16: 1.4. | B16: Интерес меньшинства в консолидированных дочерних компаниях (согласно МБС)
A17: 1.5. | B17: Резерв на девальвацию
B18: Итого основного капитала уровня I до вычетов | C18: Формула
A19: 1.6. | B19: Вычеты из суммы основного капитала уровня I | C19: Формула
A20: а | B20: Нематериальные активы
A21: б | B21: Все инвестиции в капитал неконсолидированных хозяйствующих субъектов, в том числе в долговые обязательства, которые образуют капитал хозяйствующих субъектов
A22: в | B22: Инвестиции в капитал других банков
A23: I | B23: ВСЕГО СКОРРЕКТИРОВАННЫЙ ОСНОВНОЙ КАПИТАЛ УРОВНЯ I | C23: Формула
A24: 2 | B24: ДОБАВЛЕННЫЙ КАПИТАЛ УРОВНЯ 1
A25: 2.1. | B25: Некумулятивные бессрочные привилегированные акции | C25: =+C26+C27 -> 0
A26: а | B26: Полностью оплаченные привилегированные акции
A27: б | B27: Минус: Обратно Выкупленные привилегированные акции
A28: 2.2. | B28: Добавленный капитал - Привилегированные | C28: 0
A29: 2.3. | B29: Интерес меньшинства в консолидированных дочерних компаниях | C29: 0
A30: 2.4. | B30: Доля участия дочерних предприятий (выпущенные дочерними предприятиями и находящиеся во владении третьих лиц инструменты, приравненные к капиталу) | C30: 0
A31: II | B31: ВСЕГО ДОБАВЛЕННЫЙ КАПИТАЛ УРОВНЯ I | C31: =+C25+C28+C29+C30 -> 0
A32: III | B32: ВСЕГО СКОРРЕКТИРОВАННЫЙ КАПИТАЛ УРОВНЯ I | C32: Формула
B33: КАПИТАЛ УРОВНЯ II
A34: 3.1. | B34: Прибыль за текущий год
A35: 3.2. | B35: Резервы, создаваемые на стандартные кредиты (активы), в размере не более 1.25% от общей суммы активов, взвешенных с учетом риска | C35: =IF(Balance!#REF!<(C43*1.25%),Balance!#REF!,(C43*1.25%)) -> #REF!
A36: 3.3. | B36: Излишки оценочной стоимости прироста над первоначальной стоимостью
A37: 3.4. | B37: Другие инструменты капитала (не более 1/3 части капитала 1 уровня после вычетов)
A38: 3.5. | B38: Субординированный долг
A39: 3.6. | B39: Вычеты превышения Капитала Уровня II над Капиталом Уровня I | C39: Формула
B40: Итого капитала Уровня II | C40: =SUM(C34:C38) -> #REF!
A41: IV | B41: СКОРРЕКТИРОВАННЫЙ КАПИТАЛ УРОВНЯ II | C41: Формула
A42: V | B42: ВСЕГО РЕГУЛЯТИВНЫЙ КАПИТАЛ | C42: Формула
A43: VI | B43: ОБЩАЯ СУММА АКТИВОВ ВЗВЕШЕННЫХ С УЧЕТОМ РИСКА | C43: =+C44+C45+C46 -> #REF!
A44: а | B44: Сумма балансовых и забалансовых активов, взвешенных с учетом риска | C44: =+#REF! -> #REF!
A45: б | B45: Операционный риск | C45: =+#REF! -> #REF!
A46: в | B46: Рыночный риск | C46: =+#REF! -> #REF! | E46: =+#REF! -> #REF!
A47: VII | B47: КОЭФФИЦИЕНТ ОСНОВНОГО КАПИТАЛА УРОВНЯ I (I/VI) | C47: Формула
A48: VIII | B48: КОЭФФИЦИЕНТ КАПИТАЛА УРОВНЯ I (III/VI) | C48: Формула
A49: IX | B49: КОЭФФИЦИЕНТ ОБЩЕЙ СУММЫ КАПИТАЛА, ОСНОВАННОГО НА РИСКЕ (V/VI) | C49: Формула
A50: X | B50: Активы для расчета левеража | C50: Формула
A51: а | B51: Общие активы | C51: =+Balance!C47 -> 23251274687
A52: б | B52: Забалансовые инструменты | C52: =SUM(#REF!) -> #REF! | D52: =+#REF! -> #REF!
A53: в | B53: Деривативные (производные) инструменты | C53: =SUM(#REF!) -> #REF!
A54: г | B54: Минус: Строка 1.6. Итого вычетов из суммы основного капитала Уровня 1 | C54: =+C19 -> Формула
A55: XI | B55: Коэффициент левеража | C55: Формула
B57: Подпись Председателя правления:
B59: Подпись Главного Бухгалтера:

Sheet Liquidity Analysis
A1: ЛИКВИДЛИЛИК ТАҲЛИЛИ | E1: 16-жадвал
B2: =Balance!B3 -> Банк номи | D2: =+Balance!D3 -> 45657 | E2: минг сўмда
A3: № | B3: Ликвид активлар | C3: Жами | D3: Миллий валютада | E3: Хорижий валютада
B4: 1-қисм. Юқори ликвидли активлар | C4: фоизда
A5: 1.1 | B5: Кассадаги нақд пул ва бошқа тўлов ҳужжатлари | C5: =+'Bank Assets Analysis'!S6 -> 510025015 | D5: =+'Bank Assets Analysis'!T6 -> 230334913 | E5: =+'Bank Assets Analysis'!U6 -> 279690102
A6: 1.2 | B6: Банкнинг Марказий банкдаги маблағлар (мажбурий захираларсиз) | C6: =+'Bank Assets Analysis'!S7 -> 1828213292 | D6: =+'Bank Assets Analysis'!T7 -> 1828213292 | E6: =+'Bank Assets Analysis'!U7 -> 0
A7: 1.3 | B7: Ўзбекистон Республикаси Ҳукумати ва Марказий банки томонидан чиқарилган қимматли қоғозлар | C7: =+'Bank Assets Analysis'!S19 -> 2113772835 | D7: =+'Bank Assets Analysis'!T19 -> 2113772835 | E7: =+'Bank Assets Analysis'!U19 -> 0
A8: 1.4 | B8: Инвестиция даражасидан паст бўлмаган рейтингга эга хорижий банкларда ва кредит рейтингига эга маҳаллий банкларда очилган вакиллик ҳисобварақларидаги маблағлар | C8: =+E8 -> 541712643 | E8: =+'Bank Assets Analysis'!D10+'Bank Assets Analysis'!D11 -> 541712643
A9: 1.5 | B9: Инвестиция даражасидан паст бўлмаган рейтингга эга бўлган мамлакатлардаги банкларда чет-эл валютасида овернайт шарти асосида жойлаштирилган депозитлар | C9: =+E9 -> 0 | E9: =+'Bank Assets Analysis'!F13 -> 0
A10: 1.6 | B10: ХВФ, Жаҳон банки гуруҳи, Осиё тараққиёт банки, Осиё инфратузилма ва инвестиция банки, ЕТTБ, Европа инвестиция банки, Европа инвестиция жамғармаси, Ислом тараққиёт банки ва Европа Кенгашининг тараққиёт банки томонидан чиқарилган қимматли қоғозлар | C10: =+'Bank Assets Analysis'!S21 -> 0 | D10: =+'Bank Assets Analysis'!T21 -> 0 | E10: =+'Bank Assets Analysis'!U21 -> 0
A11: 1.7 | B11: Таваккалчилик даражаси паст бўлган мамлакатлар ҳукуматлари ва Марказий банклари томонидан чиқарилган қимматли қоғозлар | C11: =+'Bank Assets Analysis'!S20 -> 0 | D11: =+'Bank Assets Analysis'!T20 -> 0 | E11: =+'Bank Assets Analysis'!U20 -> 0
A12: 1.8 | B12: Қайтариб олинмайдиган кредит линиялари (ўзлаштирилмаган қисми) | C12: =+D12 -> 0 | D12: 0 | G12: Мазкур қатор ЎзР. Марказий банки билан тегишли кредит шартнома тузилганда тўлдириши керак. Ҳисобот даврига банкнинг нетто активларининг 2 % акс эттирилади.
A13: 1.9 | B13: Ипотекани қайта молиялаштириш ташкилотлари томонидан чиқарилган корпоратив облигациялар ва таъминланган қарз муносабатларини тасдиқловчи бошқа қимматли қоғозлар | C13: =+'Bank Assets Analysis'!S24+('Bank Assets Analysis'!S23*0.8) -> 0 | D13: =+'Bank Assets Analysis'!T24+('Bank Assets Analysis'!T23*0.8) -> 0 | E13: =+'Bank Assets Analysis'!U24+('Bank Assets Analysis'!U23*0.8) -> 0
A14: 1.10 | B14: РЕПО битимлари бўйича сотиб олинган юқори ликвидли қимматли қоғозлар | C14: =+'Bank Assets Analysis'!S35 -> 0 | D14: =+'Bank Assets Analysis'!T35 -> 0 | E14: =+'Bank Assets Analysis'!U35 -> 0
A15: 1.11 | B15: Гаровга қўйилган юқори ликвидли активлар | C15: =+'Bank Assets Analysis'!S18+'Bank Assets Analysis'!S46 -> 801459811 | D15: =+'Bank Assets Analysis'!T18+'Bank Assets Analysis'!T46 -> 801459811 | E15: =+'Bank Assets Analysis'!U18+'Bank Assets Analysis'!U46 -> 0
A16: 1.12 | B16: Жами юқори ликвидли активлар | C16: =SUM(C5:C14)-'Bank Liabilities Analysis'!S22-'Bank Liabilities Analysis'!T25-C15 -> 3767752856 | D16: =SUM(D5:D14)-'Bank Liabilities Analysis'!T22-'Bank Liabilities Analysis'!T25-D15 -> 2946350111 | E16: =SUM(E5:E14)-'Bank Liabilities Analysis'!U22-E15 -> 821402745
B17: 2-қисм. Иқтисодий меъёрлар - Ликвидлилик
A18: 2.1 | B18: Юқори ликвидли активларнинг жами активларга нисбати | C18: =IFERROR((+C19/C20),0) -> 0.16783002 | D18: =IFERROR((+D19/D20),0) -> 0.16796963 | E18: =IFERROR((+E19/E20),0) -> 0.16733115
A19: 2.1.1 | B19: Юқори ликвидли активлар | C19: =+C16 -> 3767752856 | D19: =+D16 -> 2946350111 | E19: =+E16 -> 821402745
A20: 2.1.2 | B20: Жами активлар (РЕПО битимлари айрилган ҳолда) | C20: =Balance!C47-'Bank Liabilities Analysis'!S34 -> 22449814876 | D20: =Balance!D47-'Bank Liabilities Analysis'!T34 -> 17540969595 | E20: =Balance!E47-'Bank Liabilities Analysis'!U34 -> 4908845281
A21: 2.2 | B21: Юқори ликвидли активларнинг қисқа муддатли мажбуриятларга нисбати | C21: =IFERROR((+C22/C23),0) -> 0.32701871 | D21: =IFERROR((+D22/D23),0) -> 0.3306778 | E21: =IFERROR((+E22/E23),0) -> 0.3145344
A22: 2.2.1 | B22: Юқори ликвидли активлар | C22: =+C16 -> 3767752856 | D22: =+D16 -> 2946350111 | E22: =+E16 -> 821402745
A23: 2.2.2 | B23: Қисқа муддатли мажбуриятлар (РЕПО битимлари айрилган ҳолда) | C23: =+'Bank Liabilities Analysis'!C42+'Bank Liabilities Analysis'!E42+'Bank Liabilities Analysis'!G42+'Bank Liabilities Analysis'!I42+'Bank Liabilities Analysis'!K42+'Bank Liabilities Analysis'!M42-'Bank Liabilities Analysis'!C34-'Bank Liabilities Analysis'!E34-'Bank Liabilities Analysis'!G34-'Bank Liabilities Analysis'!I34-'Bank Liabilities Analysis'!K34-'Bank Liabilities Analysis'!M34 -> 11521520765 | D23: =+C23-E23 -> 8910032986 | E23: =+'Bank Liabilities Analysis'!D42+'Bank Liabilities Analysis'!F42+'Bank Liabilities Analysis'!H42+'Bank Liabilities Analysis'!J42+'Bank Liabilities Analysis'!L42+'Bank Liabilities Analysis'!N42-'Bank Liabilities Analysis'!D34-'Bank Liabilities Analysis'!F34-'Bank Liabilities Analysis'!H34-'Bank Liabilities Analysis'!J34-'Bank Liabilities Analysis'!L34-'Bank Liabilities Analysis'!N34 -> 2611487779
A24: 2.3 | B24: Ликвидлиликни қоплаш меъёри коэффициенти | C24: =IFERROR((+C25/C26),0) -> 1.4441706 | D24: =IFERROR((+D25/D26),0) -> 1.5079395 | E24: =IFERROR((+E25/E26),0) -> 1.2539591
A25: 2.3.1 | B25: Юқори ликвидли активлар | C25: =+C16 -> 3767752856 | D25: =+D16 -> 2946350111 | E25: =+E16 -> 821402745
A26: 2.3.2 | B26: Кейинги 30 кун ичида соф чиқим | C26: =+'Bank Assets Analysis'!X65 -> 2.6089389e+09 | D26: =+'Bank Assets Analysis (нац)'!P61 -> 1.9538914e+09 | E26: =+'Bank Assets Analysis'!Z65 -> 6.5504748e+08
B27: 30 кунлик чиқим суммаси | C27: =+'Bank Assets Analysis'!X67 -> 3.9289161e+09 | D27: =+'Bank Assets Analysis (нац)'!P63 -> 3.0968053e+09 | E27: =+'Bank Assets Analysis'!Z67 -> 8.3211085e+08
B28: 30 кунлик кирим суммаси | C28: =+'Bank Assets Analysis'!X70 -> 1319977238 | D28: =+'Bank Assets Analysis (нац)'!P65 -> 1142913859 | E28: =+'Bank Assets Analysis'!Z70 -> 177063379
A29: 2.4 | B29: Соф барқарор молиялаштириш меъёри | C29: =IFERROR((C30/C35),0) -> 1.0657209 | D29: =IFERROR((D30/D35),0) -> 1.0624503 | E29: =IFERROR((E30/E35),0) -> 1.0775351
A30: 2.5 | B30: Барқарор молиялаштиришнинг мавжуд суммаси | C30: =SUM(C31:C34) -> 1.4625188e+10 | D30: =SUM(D31:D34) -> 1.1419011e+10 | E30: =SUM(E31:E34) -> 3.2061778e+09
A31: 2.5.1 | B31: Хусусий капитал | C31: =Balance!C77 -> 3082240575 | D31: =Balance!D77 -> 3082240575 | E31: =Balance!E77 -> 0
A32: 2.5.2 | B32: Бир йилдан ортиқ муддатли мажбуриятлар | C32: ='Bank Liabilities Analysis'!O42+'Bank Liabilities Analysis'!Q42 -> 7846053536 | D32: =+'Bank Liabilities Analysis (нац)'!I43+'Bank Liabilities Analysis (нац)'!J43 -> 5423322103 | E32: ='Bank Liabilities Analysis'!P42+'Bank Liabilities Analysis'!R42 -> 2422731433
A33: 2.5.3 | B33: Бошқа муддатсиз мажбуриятларнинг 30 фоизи | C33: =+('Bank Liabilities Analysis'!C42)*0.3 -> 1.4958821e+09 | D33: =+('Bank Liabilities Analysis (нац)'!C43)*0.3 -> 1240277055 | E33: =+('Bank Liabilities Analysis'!D42)*0.3 -> 2.5560504e+08
A34: 2.5.4 | B34: Бир йилдан кам муддатли жами мажбуриятларнинг 30 фоизи | C34: =+('Bank Liabilities Analysis'!E42+'Bank Liabilities Analysis'!G42+'Bank Liabilities Analysis'!I42+'Bank Liabilities Analysis'!K42+'Bank Liabilities Analysis'!M42)*0.3 -> 2201012079 | D34: =+('Bank Liabilities Analysis (нац)'!D43+'Bank Liabilities Analysis (нац)'!E43+'Bank Liabilities Analysis (нац)'!F43+'Bank Liabilities Analysis (нац)'!G43+'Bank Liabilities Analysis (нац)'!H43)*0.3 -> 1.6731708e+09 | E34: =+('Bank Liabilities Analysis'!F42+'Bank Liabilities Analysis'!H42+'Bank Liabilities Analysis'!J42+'Bank Liabilities Analysis'!L42+'Bank Liabilities Analysis'!N42)*0.3 -> 5.2784129e+08
A35: 2.6 | B35: Барқарор молиялаштиришнинг зарур суммаси | C35: =SUM(C36:C41) -> 1.3723281e+10 | D35: =SUM(D36:D41) -> 1.0747807e+10 | E35: =SUM(E36:E41) -> 2.9754742e+09
A36: 2.6.1 | B36: Бир йилдан ортиқ муддатли активлар | C36: =+'Bank Assets Analysis'!O47-'Bank Assets Analysis'!O37+'Bank Assets Analysis'!Q47-'Bank Assets Analysis'!Q37-'Bank Assets Analysis'!O19-'Bank Assets Analysis'!Q19 -> 8700048987 | D36: =+C36-E36 -> 6495043058 | E36: =+'Bank Assets Analysis'!P47-'Bank Assets Analysis'!P40-'Bank Assets Analysis'!P37+'Bank Assets Analysis'!R47-'Bank Assets Analysis'!R40-'Bank Assets Analysis'!R37-'Bank Assets Analysis'!P19-'Bank Assets Analysis'!R19 -> 2205005929
A37: 2.6.2 | B37: Қайтариш муддати бир йилдан ортиқ бўлган номолиявий активлар (ер участкалари, бинолар, мебель, компьютерлар ва автомашиналар) | C37: =+'Bank Assets Analysis'!O37+'Bank Assets Analysis'!Q37 -> 2578342217 | D37: =+C37-E37 -> 2578342217 | E37: =+'Bank Assets Analysis'!P37+'Bank Assets Analysis'!R37 -> 0
A38: 2.6.3 | B38: Суд жараёнида бўлган ёки белгиланган тартибда ундирилмаган кредит ва лизинглар, соф | C38: =+'Bank Assets Analysis'!C28+'Bank Assets Analysis'!C29+'Bank Assets Analysis'!C30+'Bank Assets Analysis'!C32 -> 151954223 | D38: =+'Bank Assets Analysis (нац)'!C28+'Bank Assets Analysis (нац)'!C29+'Bank Assets Analysis (нац)'!C30+'Bank Assets Analysis (нац)'!C32 -> 136125042 | E38: =+'Bank Assets Analysis'!D28+'Bank Assets Analysis'!D29+'Bank Assets Analysis'!D30+'Bank Assets Analysis'!D32 -> 15829181
A39: 2.6.4 | B39: Суд жараёнида бўлган ёки белгиланган тартибда ундирилмаган активлар, соф (2.6.3-қаторда кўрсатилмаган қисми) | C39: =+D39+E39 -> 0 | D39: 0 | E39: 0
A40: 2.6.5 | B40: Қайтариш муддати 1 йилдан кам бўлган бошқа активлар суммасининг 30 фоизи (қайтариш муддати 1 йилдан кам бўлган ёки муддатсиз ликвидли активлар бундан мустасно) | C40: =((+'Bank Assets Analysis'!S47-'Bank Assets Analysis'!O47-'Bank Assets Analysis'!Q47-('Liquidity Analysis'!C58-'Bank Assets Analysis'!O19-'Bank Assets Analysis'!Q19))*0.3) -> 2.01287e+09 | D40: =('Bank Assets Analysis (нац)'!K47-'Bank Assets Analysis (нац)'!I47-'Bank Assets Analysis (нац)'!J47-('Liquidity Analysis'!D58-'Bank Assets Analysis (нац)'!I19-'Bank Assets Analysis (нац)'!J19))*0.3 -> 1.4675497e+09 | E40: =(('Bank Assets Analysis'!U47-'Bank Assets Analysis'!P47-'Bank Assets Analysis'!R47-('Liquidity Analysis'!E58-'Bank Assets Analysis'!P19-'Bank Assets Analysis'!R19))*0.3) -> 5.4532021e+08
A41: 2.6.6 | B41: Балансдан ташқари активларнинг 15 фоизи | C41: =+ROUND(SUM(Commitments!C4-Commitments!C5+Commitments!C7-Commitments!C8+Commitments!C10-'Bank Liabilities Analysis'!S18)*15%,0) -> 280066014 | D41: =+ROUND(SUM(Commitments!D4-Commitments!D5+Commitments!D7-Commitments!D8+Commitments!D10-'Bank Liabilities Analysis'!T18)*15%,0) -> 70747177 | E41: =+ROUND(SUM(Commitments!E4-Commitments!E5+Commitments!E7-Commitments!E8+Commitments!E10-'Bank Liabilities Analysis'!U18)*15%,0) -> 209318837
B43: Бошқарув Раис имзоси:
B45: Бош бухгалтер имзоси:
A50: № | B50: Ликвидли активлар | C50: Жами | D50: Миллий валютада | E50: Хорижий валютада
A51: 1. | B51: Кассадаги нақд пул ва бошқа тўлов ҳужжатлари ва қимматбаҳо металлар | C51: =+'Bank Assets Analysis'!S6+'Investment Securities'!B39 -> 510025266 | D51: =+'Bank Assets Analysis'!T6+'Investment Securities'!C39 -> 230335164 | E51: =+'Bank Assets Analysis'!U6+'Investment Securities'!D39 -> 279690102
A52: 2. | B52: Банкнинг Марказий банкдаги маблағлар | C52: =+'Bank Assets Analysis'!S7+'Bank Assets Analysis'!S8 -> 1828213292 | D52: =+'Bank Assets Analysis'!T7+'Bank Assets Analysis'!T8 -> 1828213292 | E52: =+'Bank Assets Analysis'!U7+'Bank Assets Analysis'!U8 -> 0
A53: 3. | B53: Бошқа банклар ва молиявий ташкилотлардан олиниши лозим бўлган маблағлар | C53: ='Bank Assets Analysis'!C10+'Bank Assets Analysis'!C11+'Bank Assets Analysis'!C12+'Bank Assets Analysis'!C15+'Bank Assets Analysis'!C16+'Bank Assets Analysis'!E16+'Bank Assets Analysis'!G16 -> 667338473 | D53: =+C53-E53 -> 112407715 | E53: ='Bank Assets Analysis'!D10+'Bank Assets Analysis'!D11+'Bank Assets Analysis'!D15+'Bank Assets Analysis'!D16+'Bank Assets Analysis'!F16+'Bank Assets Analysis'!H16 -> 554930758
A54: 3.1. | B54: Бошқа банклар ва молиявий ташкилотлардан олиниши лозим бўлган маблағлар - соф депозитлар | C54: =IF(F54>0,F54,0) -> 90829938 | D54: =IF(G54>0,G54,0) -> 39345488 | E54: =IF(H54>0,H54,0) -> 51484450 | F54: =(('Bank Assets Analysis'!E10+'Bank Assets Analysis'!E12+'Bank Assets Analysis'!G10+'Bank Assets Analysis'!C14+'Bank Assets Analysis'!E14+'Bank Assets Analysis'!G14)-'Bank Liabilities Analysis'!C26-'Bank Liabilities Analysis'!E26-'Bank Liabilities Analysis'!G26) -> 90829938 | G54: =+('Bank Assets Analysis'!E10-'Bank Assets Analysis'!F10+'Bank Assets Analysis'!G10-'Bank Assets Analysis'!H10+'Bank Assets Analysis'!E12-'Bank Assets Analysis'!F12+'Bank Assets Analysis'!C14-'Bank Assets Analysis'!D14+'Bank Assets Analysis'!E14-'Bank Assets Analysis'!F14+'Bank Assets Analysis'!G14-'Bank Assets Analysis'!H14)-('Bank Liabilities Analysis'!C26-'Bank Liabilities Analysis'!D26+'Bank Liabilities Analysis'!E26-'Bank Liabilities Analysis'!F26+'Bank Liabilities Analysis'!G26-'Bank Liabilities Analysis'!H26) -> 39345488 | H54: =(('Bank Assets Analysis'!F10+'Bank Assets Analysis'!F12+'Bank Assets Analysis'!H10+'Bank Assets Analysis'!D14+'Bank Assets Analysis'!F14+'Bank Assets Analysis'!H14)-'Bank Liabilities Analysis'!D26-'Bank Liabilities Analysis'!F26-'Bank Liabilities Analysis'!H26) -> 51484450
A55: 4. | B55: Ўзбекистон Республикаси Ҳукумати ва Марказий банк тамонидан чиқарилган қимматли қоғозлар (векселлар, облигациялар ва бошқа қимматли қоғозлар) | C55: =+'Investment Securities'!B5+'Investment Securities'!B6+'Investment Securities'!B19+'Investment Securities'!B20+'Investment Securities'!B21 -> 2166910000 | D55: =+'Investment Securities'!C5+'Investment Securities'!C6+'Investment Securities'!C19+'Investment Securities'!C20+'Investment Securities'!C21 -> 2166910000 | E55: =+'Investment Securities'!D5+'Investment Securities'!D6+'Investment Securities'!D19+'Investment Securities'!D20+'Investment Securities'!D21 -> 0
A56: 5. | B56: Таваккалчилик даражаси паст бўлган мамлакатлар томонидан чиқарилган қимматли қоғозлар
A57: 6. | B57: Бошқа осон сотиладиган қимматли қоғозлар
A58: 7. | B58: Жами ликвид активлар | C58: =SUM(C51:C57) -> 5263316969 | D58: =SUM(D51:D57) -> 4377211659 | E58: =SUM(E51:E57) -> 886105310

Sheet Bank Assets Analysis
A1: БАНК АКТИВЛАРИ ТАҲЛИЛИ | X1: 17-жадвал
B2: =Balance!B3 -> Банк номи | X2: =+Balance!D3 -> 45657 | Z2: минг сўмда
A3: № | B3: Кўрсаткичлар | C3: Сўндириш муддати (кунларда) | S3: Жами | T3: шундан, | V3: Ликвидлиликни қоплаш меёри ҳисоб китоби
C4: Муддатсиз | E4: 1 дан 7 гача | G4: 8 дан 30 гача | I4: 31 дан 90 гача | K4: 91 дан 180 гача | M4: 181 дан 365 гача | O4: 366 дан 730 гача | Q4: 2 йилдан ортиқ
C5: Сумма | D5: шундан, хорижий валютада (сўм экв.) | E5: Сумма | F5: шундан, хорижий валютада (сўм экв.) | G5: Сумма | H5: шундан, хорижий валютада (сўм экв.) | I5: Сумма | J5: шундан, хорижий валютада (сўм экв.) | K5: Сумма | L5: шундан, хорижий валютада (сўм экв.) | M5: Сумма | N5: шундан, хорижий валютада (сўм экв.) | O5: Сумма | P5: шундан, хорижий валютада (сўм экв.) | Q5: Сумма | R5: шундан, хорижий валютада (сўм экв.) | T5: миллий валютада | U5: хорижий валютада (сўм экв.) | V5: Коэффициент | W5: Активлар | X5: Юқори ликвидли активлар/кирим | Y5: Активлар (хорижий валютада) | Z5: Юқори ликвидли активлар/кирим (хорижий валютада)
A6: 1 | B6: Кассадаги нақд пул ва бошқа тўлов ҳужжатлари | C6: 510025015 | D6: 279690102 | E6: 0 | F6: 0 | G6: 0 | H6: 0 | I6: 0 | J6: 0 | K6: 0 | L6: 0 | M6: 0 | N6: 0 | O6: 0 | P6: 0 | Q6: 0 | R6: 0 | S6: =+C6+E6+G6+I6+K6+M6+O6+Q6 -> 510025015 | T6: =+S6-U6 -> 230334913 | U6: =+D6+F6+H6+J6+L6+N6+P6+R6 -> 279690102 | V6: 1 | W6: =+S6 -> 510025015 | X6: =+W6*V6 -> 510025015 | Y6: =+U6 -> 279690102 | Z6: =+Y6*V6 -> 279690102
A7: 2 | B7: Банкнинг Марказий банкдаги маблағлари (мажбурий захирасиз) | C7: 1828213292 | D7: 0 | E7: 0 | F7: 0 | G7: 0 | H7: 0 | I7: 0 | J7: 0 | K7: 0 | L7: 0 | M7: 0 | N7: 0 | O7: 0 | P7: 0 | Q7: 0 | R7: 0 | S7: =+C7+E7+G7+I7+K7+M7+O7+Q7 -> 1828213292 | T7: =+S7-U7 -> 1828213292 | U7: =+D7+F7+H7+J7+L7+N7+P7+R7 -> 0 | V7: 1 | W7: =S7 -> 1828213292 | X7: =+W7*V7 -> 1828213292 | Y7: =+U7 -> 0 | Z7: =+Y7*V7 -> 0
A8: 2.1 | B8: Банкнинг Марказий банкдаги мажбурий захира ҳисобварағидаги маблағлар | C8: 0 | D8: 0 | E8: 0 | F8: 0 | G8: 0 | H8: 0 | I8: 0 | J8: 0 | K8: 0 | L8: 0 | M8: 0 | N8: 0 | O8: 0 | P8: 0 | Q8: 0 | R8: 0 | S8: =+C8+E8+G8+I8+K8+M8+O8+Q8 -> 0 | T8: =+S8-U8 -> 0 | U8: =+D8+F8+H8+J8+L8+N8+P8+R8 -> 0 | V8: 0
A9: 3 | B9: Бошқа банклар ва молиявий ташкилотлардан олиниши лозим бўлган маблағлар | C9: =SUM(C10:C16)-C13 -> 693184433 | D9: =SUM(D10:D16)-D13 -> 580771718 | E9: =SUM(E10:E16)-E13 -> 0 | F9: =SUM(F10:F16)-F13 -> 0 | G9: =SUM(G10:G16)-G13 -> 65643490 | H9: =SUM(H10:H16)-H13 -> 25643490 | I9: =SUM(I10:I16)-I13 -> 32301200 | J9: =SUM(J10:J16)-J13 -> 32301200 | ... R9: =SUM(R10:R16)-R13 -> 0 | S9: =+C9+E9+G9+I9+K9+M9+O9+Q9 -> 893895010 | T9: =+S9-U9 -> 255178602 | U9: =+D9+F9+H9+J9+L9+N9+P9+R9 -> 638716408
A10: 3.1 | B10: Таваккалчилик даражаси паст банклардаги вакиллик ҳисобварақлари (ностро) | C10: 64873827 | D10: 64873827 | E10: 0 | F10: 0 | G10: 0 | H10: 0 | I10: 0 | J10: 0 | K10: 0 | L10: 0 | M10: 0 | N10: 0 | O10: 0 | P10: 0 | Q10: 0 | R10: 0 | S10: =+C10+E10+G10+I10+K10+M10+O10+Q10 -> 64873827 | T10: =+S10-U10 -> 0 | U10: =+D10+F10+H10+J10+L10+N10+P10+R10 -> 64873827 | V10: 1 | W10: =+C10 -> 64873827 | X10: =+W10*V10 -> 64873827 | Y10: =+D10 -> 64873827 | Z10: =+Y10*V10 -> 64873827
A11: 3.2 | B11: Маҳаллий банклардаги вакиллик ҳисобварақлари (ностро) | C11: 476838816 | D11: 476838816 | S11: =+C11 -> 476838816 | T11: =+S11-U11 -> 0 | U11: =+D11 -> 476838816 | V11: 1 | W11: =+C11 -> 476838816 | X11: =+W11*V11 -> 476838816 | Y11: =+D11 -> 476838816 | Z11: =+Y11*V11 -> 476838816
A12: 3.3 | B12: Овернайт шарти билан жойлаштирилган депозитлар | E12: 0 | S12: =+E12 -> 0 | T12: =+S12-U12 -> 0 | U12: =+F12 -> 0 | V12: 1 | W12: =+E12-E13 -> 0 | X12: =+W12*V12 -> 0 | Y12: =+F12-F13 -> 0 | Z12: =+Y12*V12 -> 0
A13: 3.3.1. | B13: шундан, инвестицион даражадан паст бўлмаган рейтингга эга банкларга овернайт шарти билан жойлаштирилган хорижий валютадаги депозитлар | S13: =+E13 -> 0 | T13: =+S13-U13 -> 0 | U13: =+F13 -> 0 | V13: 1 | W13: =+F13 -> 0 | X13: =+W13*V13 -> 0 | Y13: =+F13 -> 0 | Z13: =+Y13*V13 -> 0
A14: 3.4 | B14: Банкнинг бошқа банклар/молиявий ташкилотлардаги ҳисобварақлари | C14: 25845960 | D14: 25840960 | E14: 0 | F14: 0 | G14: 65643490 | H14: 25643490 | I14: 32301200 | J14: 32301200 | K14: 24409360 | L14: 0 | M14: 24409360 | N14: 0 | O14: 37522553 | P14: 0 | Q14: 16424614 | R14: 0 | S14: =+C14+E14+G14+I14+K14+M14+O14+Q14 -> 226556537 | T14: =+S14-U14 -> 142770887 | U14: =+D14+F14+H14+J14+L14+N14+P14+R14 -> 83785650 | V14: 1 | W14: =+C14+E14+G14+E10+G10+E11+G11 -> 91489450 | X14: =+W14*V14 -> 91489450 | Y14: =+D14+F14+H14+F10+H10+F11+H11 -> 51484450 | Z14: =+Y14*V14 -> 51484450
A15: 3.5 | B15: Пластик карталардан амалга оширилган тўловлар бўйича бошқа банклардан олиниши лозим бўлган маблағлар | C15: 112407715 | D15: 0 | E15: 0 | F15: 0 | G15: 0 | H15: 0 | I15: 0 | J15: 0 | K15: 0 | L15: 0 | M15: 0 | N15: 0 | O15: 0 | P15: 0 | Q15: 0 | R15: 0 | S15: =+C15+E15+G15+I15+K15+M15+O15+Q15 -> 112407715 | T15: =+S15-U15 -> 112407715 | U15: =+D15+F15+H15+J15+L15+N15+P15+R15 -> 0 | V15: 1 | W15: =+C15+E15+G15 -> 112407715 | X15: =+W15*V15 -> 112407715 | Y15: =+D15+F15+H15 -> 0 | Z15: =+Y15*V15 -> 0
A16: 3.6 | B16: Бошқа моддалар | C16: 13218115 | D16: 13218115 | E16: 0 | F16: 0 | G16: 0 | H16: 0 | I16: 0 | J16: 0 | K16: 0 | L16: 0 | M16: 0 | N16: 0 | O16: 0 | P16: 0 | Q16: 0 | R16: 0 | S16: =+C16+E16+G16+I16+K16+M16+O16+Q16 -> 13218115 | T16: =+S16-U16 -> 0 | U16: =+D16+F16+H16+J16+L16+N16+P16+R16 -> 13218115 | V16: 1 | W16: =+C16+E16+G16 -> 13218115 | X16: =+W16*V16 -> 13218115 | Y16: =+D16+F16+H16 -> 13218115 | Z16: =+Y16*V16 -> 13218115
A17: 4 | B17: Қимматли қоғозлар ва уларга қилинган инвестициялар, соф | C17: =SUM(C19:C25) -> 251 | D17: =SUM(D19:D25) -> 0 | E17: =SUM(E19:E25) -> 0 | F17: =SUM(F19:F25) -> 0 | G17: =SUM(G19:G25) -> 199447829 | H17: =SUM(H19:H25) -> 0 | I17: =SUM(I19:I25) -> 461830511 | J17: =SUM(J19:J25) -> 0 | ... R17: =SUM(R19:R25) -> 0 | S17: =+C17+E17+G17+I17+K17+M17+O17+Q17 -> 2113773086 | T17: =+S17-U17 -> 2113773086 | U17: =+D17+F17+H17+J17+L17+N17+P17+R17 -> 0
A18: 4a | B18: шу жумладан, таъминот остидаги юқори ликвидли қимматли қоғозлар | C18: =+'Bank Liabilities Analysis'!C34 -> 0 | D18: =+'Bank Liabilities Analysis'!D34 -> 0 | E18: =+'Bank Liabilities Analysis'!E34 -> 801459811 | F18: =+'Bank Liabilities Analysis'!F34 -> 0 | G18: =+'Bank Liabilities Analysis'!G34 -> 0 | H18: =+'Bank Liabilities Analysis'!H34 -> 0 | I18: =+'Bank Liabilities Analysis'!I34 -> 0 | J18: =+'Bank Liabilities Analysis'!J34 -> 0 | ... R18: =+'Bank Liabilities Analysis'!R34 -> 0 | S18: =+C18+E18+G18+I18+K18+M18+O18+Q18 -> 801459811 | T18: =+S18-U18 -> 801459811 | U18: =+D18+F18+H18+J18+L18+N18+P18+R18 -> 0 | V18: 1 | W18: =+C18+E18+G18 -> 801459811 | X18: =+W18*V18 -> 801459811 | Y18: =+D18+F18+H18 -> 0 | Z18: =+Y18*V18 -> 0
A19: 4.1 | B19: Ўзбекистон Республикаси Ҳукумати ва Марказий банк томонидан чиқарилган қимматли қоғозлар (векселлар, облигациялар ва бошқа қарз қимматли қоғозлар) | C19: 0 | D19: 0 | E19: 0 | F19: 0 | G19: 199447829 | H19: 0 | I19: 461830511 | J19: 0 | K19: 0 | L19: 0 | M19: 160140364 | N19: 0 | O19: 928910901 | P19: 0 | Q19: 363443230 | R19: 0 | S19: =+C19+E19+G19+I19+K19+M19+O19+Q19 -> 2113772835 | T19: =+S19-U19 -> 2113772835 | U19: =+D19+F19+H19+J19+L19+N19+P19+R19 -> 0 | V19: 1 | W19: =+S19 -> 2113772835 | X19: =+W19*V19 -> 2113772835 | Y19: =+U19 -> 0 | Z19: =+Y19*V19 -> 0
A20: 4.2 | B20: Таваккалчилик даражаси паст бўлган мамлакатларнинг қимматли қоғозлари | C20: 0 | D20: 0 | E20: 0 | F20: 0 | G20: 0 | H20: 0 | I20: 0 | J20: 0 | K20: 0 | L20: 0 | M20: 0 | N20: 0 | O20: 0 | P20: 0 | Q20: 0 | R20: 0 | S20: =+C20+E20+G20+I20+K20+M20+O20+Q20 -> 0 | T20: =+S20-U20 -> 0 | U20: =+D20+F20+H20+J20+L20+N20+P20+R20 -> 0 | V20: 1 | W20: =+S20 -> 0 | X20: =+W20*V20 -> 0 | Y20: =+U20 -> 0 | Z20: =+Y20*V20 -> 0
A21: 4.3 | B21: ХВФ, Жаҳон банки гуруҳи, Осиё тараққиёт банки, Осиё инфраструктура инвестиция банки, ЕТТБ, Европа инвестиция банки, Европа инвестиция жамғармаси, Ислом тараққиёт банки ва Европа Кенгашининг тараққиёт банки томонидан чиқарилган қимматли қоғозлар | C21: 0 | D21: 0 | E21: 0 | F21: 0 | G21: 0 | H21: 0 | I21: 0 | J21: 0 | K21: 0 | L21: 0 | M21: 0 | N21: 0 | O21: 0 | P21: 0 | Q21: 0 | R21: 0 | S21: =+C21+E21+G21+I21+K21+M21+O21+Q21 -> 0 | T21: =+S21-U21 -> 0 | U21: =+D21+F21+H21+J21+L21+N21+P21+R21 -> 0 | V21: 1 | W21: =+S21 -> 0 | X21: =+W21*V21 -> 0 | Y21: =+U21 -> 0 | Z21: =+Y21*V21 -> 0
A22: 4.4 | B22: Таваккалчилик даражаси паст бўлган мамлакатларнинг етакчи компаниялари қимматли қоғозлари | C22: 0 | D22: 0 | E22: 0 | F22: 0 | G22: 0 | H22: 0 | I22: 0 | J22: 0 | K22: 0 | L22: 0 | M22: 0 | N22: 0 | O22: 0 | P22: 0 | Q22: 0 | R22: 0 | S22: =+C22+E22+G22+I22+K22+M22+O22+Q22 -> 0 | T22: =+S22-U22 -> 0 | U22: =+D22+F22+H22+J22+L22+N22+P22+R22 -> 0 | V22: 1 | W22: =+S22 -> 0 | X22: =+W22*V22 -> 0 | Y22: =+U22 -> 0 | Z22: =+Y22*V22 -> 0
A23: 4.5 | B23: Ипотекани қайта молиялаштириш ташкилотлари томонидан чиқарилган корпоратив облигациялар | C23: 0 | D23: 0 | E23: 0 | F23: 0 | G23: 0 | H23: 0 | I23: 0 | J23: 0 | K23: 0 | L23: 0 | M23: 0 | N23: 0 | O23: 0 | P23: 0 | Q23: 0 | R23: 0 | S23: =+C23+E23+G23+I23+K23+M23+O23+Q23 -> 0 | T23: =+S23-U23 -> 0 | U23: =+D23+F23+H23+J23+L23+N23+P23+R23 -> 0 | V23: 0.8 | W23: =+S23 -> 0 | X23: =+W23*V23 -> 0 | Y23: =+U23 -> 0 | Z23: =+Y23*V23 -> 0
A24: 4.6 | B24: Ипотекани қайта молиялаштириш ташкилотлари томонидан чиқарилган таъминланган қарз муносабатларини тасдиқловчи бошқа қимматли қоғозлар | C24: 0 | D24: 0 | E24: 0 | F24: 0 | G24: 0 | H24: 0 | I24: 0 | J24: 0 | K24: 0 | L24: 0 | M24: 0 | N24: 0 | O24: 0 | P24: 0 | Q24: 0 | R24: 0 | S24: =+C24+E24+G24+I24+K24+M24+O24+Q24 -> 0 | T24: =+S24-U24 -> 0 | U24: =+D24+F24+H24+J24+L24+N24+P24+R24 -> 0 | V24: 1 | W24: =+S24 -> 0 | X24: =+W24*V24 -> 0 | Y24: =+U24 -> 0 | Z24: =+Y24*V24 -> 0
A25: 4.7 | B25: Бошқалар | C25: 251 | D25: 0 | E25: 0 | F25: 0 | G25: 0 | H25: 0 | I25: 0 | J25: 0 | K25: 0 | L25: 0 | M25: 0 | N25: 0 | O25: 0 | P25: 0 | Q25: 0 | R25: 0 | S25: =+C25+E25+G25+I25+K25+M25+O25+Q25 -> 251 | T25: =+S25-U25 -> 251 | U25: =+D25+F25+H25+J25+L25+N25+P25+R25 -> 0 | V25: 1 | W25: =+C25+E25+G25 -> 251 | X25: =+W25*V25 -> 251 | Y25: =+D25+F25+H25 -> 0 | Z25: =+Y25*V25 -> 0
A26: 5 | B26: Мижозларнинг аккредитив ва траст ҳужжатлари билан кафолатланган тратталари бўйича мажбуриятлари, соф | C26: 12185606 | D26: 12185606 | E26: 405860 | F26: 405860 | G26: 667550 | H26: 667550 | I26: 2146821 | J26: 2146821 | K26: 10739107 | L26: 10739107 | M26: 2288544 | N26: 2288544 | O26: 0 | P26: 0 | Q26: 9656780 | R26: 9656780 | S26: =+C26+E26+G26+I26+K26+M26+O26+Q26 -> 38090268 | T26: =+S26-U26 -> 0 | U26: =+D26+F26+H26+J26+L26+N26+P26+R26 -> 38090268 | V26: 0.5 | W26: =+E26+G26 -> 1073410 | X26: =+W26*V26 -> 536705 | Y26: =+F26+H26 -> 1073410 | Z26: =+Y26*V26 -> 536705
A27: 6 | B27: Мижозларнинг банк олдидаги тўланмаган акцептлари бўйича мажбуриятлари, соф | C27: 0 | D27: 0 | E27: 0 | F27: 0 | G27: 0 | H27: 0 | I27: 0 | J27: 0 | K27: 0 | L27: 0 | M27: 0 | N27: 0 | O27: 0 | P27: 0 | Q27: 0 | R27: 0 | S27: =+C27+E27+G27+I27+K27+M27+O27+Q27 -> 0 | T27: =+S27-U27 -> 0 | U27: =+D27+F27+H27+J27+L27+N27+P27+R27 -> 0 | V27: 0.5 | W27: =+E27+G27 -> 0 | X27: =+W27*V27 -> 0 | Y27: =+F27+H27 -> 0 | Z27: =+Y27*V27 -> 0
A28: 7 | B28: Марказий банкка берилган кредит ва лизинглар, соф | C28: 0 | D28: 0 | E28: 0 | F28: 0 | G28: 0 | H28: 0 | I28: 0 | J28: 0 | K28: 0 | L28: 0 | M28: 0 | N28: 0 | O28: 0 | P28: 0 | Q28: 0 | R28: 0 | S28: =+C28+E28+G28+I28+K28+M28+O28+Q28 -> 0 | T28: =+S28-U28 -> 0 | U28: =+D28+F28+H28+J28+L28+N28+P28+R28 -> 0 | V28: 1 | W28: =+C28+E28+G28 -> 0 | X28: =+W28*V28 -> 0 | Y28: =+D28+F28+H28 -> 0 | Z28: =+Y28*V28 -> 0
A29: 8 | B29: Бошқа банкларга берилган кредит ва лизинглар, соф | C29: 0 | D29: 0 | E29: 0 | F29: 0 | G29: 0 | H29: 0 | I29: 0 | J29: 0 | K29: 0 | L29: 0 | M29: 0 | N29: 0 | O29: 0 | P29: 0 | Q29: 0 | R29: 0 | S29: =+C29+E29+G29+I29+K29+M29+O29+Q29 -> 0 | T29: =+S29-U29 -> 0 | U29: =+D29+F29+H29+J29+L29+N29+P29+R29 -> 0 | V29: 0.5 | W29: =+E29+G29 -> 0 | X29: =+W29*V29 -> 0 | Y29: =+F29+H29 -> 0 | Z29: =+Y29*V29 -> 0
A30: 9 | B30: Мижозларга берилган кредит ва лизинглар, соф | C30: 47395262 | D30: 14440130 | E30: 17779505 | F30: 0 | G30: 330819821 | H30: 105385025 | I30: 883912834 | J30: 314730802 | K30: 1256500595 | L30: 432342301 | M30: 2118405283 | N30: 702864857 | O30: 2396518421 | P30: 679206071 | Q30: 5534337265 | R30: 1506352526 | S30: =+C30+E30+G30+I30+K30+M30+O30+Q30 -> 12585668986 | T30: =+S30-U30 -> 8830347274 | U30: =+D30+F30+H30+J30+L30+N30+P30+R30 -> 3755321712 | V30: 0.5 | W30: =+E30+G30 -> 348599326 | X30: =+W30*V30 -> 174299663 | Y30: =+F30+H30 -> 105385025 | Z30: =+Y30*V30 -> 52692512
A31: 9.1 | B31: шу жумладан, жисмоний шахсларга берилган кредит ва лизинглар | C31: 12195138 | D31: 0 | E31: 17112476 | F31: 0 | G31: 62264947 | H31: 0 | I31: 169210038 | J31: 0 | K31: 245989398 | L31: 0 | M31: 486153885 | N31: 0 | O31: 850968665 | P31: 0 | Q31: 2204833140 | R31: 0 | S31: =+C31+E31+G31+I31+K31+M31+O31+Q31 -> 4048727687 | T31: =+S31-U31 -> 4048727687 | U31: =+D31+F31+H31+J31+L31+N31+P31+R31 -> 0 | V31: 0 | W31: =+E31+G31 -> 79377423 | X31: =+W31*V31 -> 0 | Y31: =+F31+H31 -> 0 | Z31: =+Y31*V31 -> 0
A32: 10 | B32: Суд ёки ижро иши юритиш жараёнидаги кредитлар ва лизинг, соф | C32: 104558961 | D32: 1389051 | S32: =+C32+E32+G32+I32+K32+M32+O32+Q32 -> 104558961 | T32: =+S32-U32 -> 103169910 | U32: =+D32+F32+H32+J32+L32+N32+P32+R32 -> 1389051 | V32: 0 | W32: =+E32+G32 -> 0 | X32: =+W32*V32 -> 0 | Y32: =+F32+H32 -> 0 | Z32: =+Y32*V32 -> 0
A33: 11 | B33: Инвестициялар, соф | C33: 0 | D33: 0 | E33: 0 | F33: 0 | G33: 0 | H33: 0 | I33: 0 | J33: 0 | K33: 0 | L33: 0 | M33: 0 | N33: 0 | O33: 0 | P33: 0 | Q33: 391688858 | R33: 0 | S33: =+C33+E33+G33+I33+K33+M33+O33+Q33 -> 391688858 | T33: =+S33-U33 -> 391688858 | U33: =+D33+F33+H33+J33+L33+N33+P33+R33 -> 0 | V33: 0 | W33: =+E33+G33 -> 0 | X33: =+W33*V33 -> 0 | Y33: =+F33+H33 -> 0 | Z33: =+Y33*V33 -> 0
A34: 12 | B34: РЕПО битимлари бўйича сотиб олинган қимматли қоғозлар | C34: =+C35+C36 -> 0 | D34: =+D35+D36 -> 0 | E34: =+E35+E36 -> 0 | F34: =+F35+F36 -> 0 | G34: =+G35+G36 -> 0 | H34: =+H35+H36 -> 0 | I34: =+I35+I36 -> 0 | J34: =+J35+J36 -> 0 | ... R34: =+R35+R36 -> 0 | S34: =+C34+E34+G34+I34+K34+M34+O34+Q34 -> 0 | T34: =+S34-U34 -> 0 | U34: =+D34+F34+H34+J34+L34+N34+P34+R34 -> 0 | V34: 0 | W34: =+E34+G34 -> 0 | X34: =+W34*V34 -> 0 | Y34: =+F34+H34 -> 0 | Z34: =+Y34*V34 -> 0
A35: 12.1 | B35: РЕПО битимлари бўйича сотиб олинган юқори ликвидли қимматли қоғозлар | S35: =+C35+E35+G35+I35+K35+M35+O35+Q35 -> 0 | T35: =+S35-U35 -> 0 | U35: =+D35+F35+H35+J35+L35+N35+P35+R35 -> 0 | V35: 1 | W35: =+S35 -> 0 | X35: =+W35*V35 -> 0 | Y35: =+U35 -> 0 | Z35: =+Y35*V35 -> 0
A36: 12.2 | B36: РЕПО битимлари бўйича сотиб олинган бошқа қимматли қоғозлар | S36: =+C36+E36+G36+I36+K36+M36+O36+Q36 -> 0 | T36: =+S36-U36 -> 0 | U36: =+D36+F36+H36+J36+L36+N36+P36+R36 -> 0 | V36: 0
A37: 13 | B37: Aсосий воситалар, соф | C37: 0 | D37: 0 | E37: 0 | F37: 0 | G37: 0 | H37: 0 | I37: 0 | J37: 0 | K37: 0 | L37: 0 | M37: 0 | N37: 0 | O37: 0 | P37: 0 | Q37: 2578342217 | R37: 0 | S37: =+C37+E37+G37+I37+K37+M37+O37+Q37 -> 2578342217 | T37: =+S37-U37 -> 2578342217 | U37: =+D37+F37+H37+J37+L37+N37+P37+R37 -> 0 | V37: 0
A38: 14 | B38: Банкнинг бошқа хусусий мулклари, соф | C38: 119934391 | E38: 0 | G38: 1494238 | I38: 2790886 | K38: 4633427 | M38: 8254794 | O38: 14671150 | Q38: 196732376 | S38: =+C38+E38+G38+I38+K38+M38+O38+Q38 -> 348511262 | T38: =+S38-U38 -> 348511262 | U38: =+D38+F38+H38+J38+L38+N38+P38+R38 -> 0 | V38: 0
A39: 15 | B39: Ҳосилавий инструментларнинг ревальвацияси натижасида ўзлаштирилмаган фойда | C39: 0 | D39: 0 | E39: 0 | F39: 0 | G39: 0 | H39: 0 | I39: 0 | J39: 0 | K39: 0 | L39: 0 | M39: 0 | N39: 0 | O39: 0 | P39: 0 | Q39: 1561 | R39: 0 | S39: =+C39+E39+G39+I39+K39+M39+O39+Q39 -> 1561 | T39: =+S39-U39 -> 1561 | U39: =+D39+F39+H39+J39+L39+N39+P39+R39 -> 0 | V39: 0
A40: 16 | B40: Валюта савдоси ва валюта позициялари | C40: 0 | E40: 0 | G40: 0 | I40: 0 | K40: 0 | M40: 0 | O40: 0 | Q40: 0 | S40: =+C40+E40+G40+I40+K40+M40+O40+Q40 -> 0 | T40: =+S40-U40 -> 0 | U40: =+D40+F40+H40+J40+L40+N40+P40+R40 -> 0 | V40: 0
A41: 17 | B41: Транзит ҳисобварақлари | C41: 0 | D41: 0 | E41: 0 | F41: 0 | G41: 0 | H41: 0 | I41: 0 | J41: 0 | K41: 0 | L41: 0 | M41: 0 | N41: 0 | O41: 0 | P41: 0 | Q41: 0 | R41: 0 | S41: =+C41+E41+G41+I41+K41+M41+O41+Q41 -> 0 | T41: =+S41-U41 -> 0 | U41: =+D41+F41+H41+J41+L41+N41+P41+R41 -> 0 | V41: 0
A42: 18 | B42: Олиниши лозим бўлган ҳисобланган фоизлар | C42: 72404860 | D42: 21234260 | E42: 11581374 | F42: 0 | G42: 241549682 | H42: 118263193 | I42: 23749294 | J42: 8290010 | K42: 8631591 | L42: 7930148 | M42: 12462178 | N42: 1856046 | O42: 61409867 | P42: 0 | Q42: 13777435 | R42: 0 | S42: =+C42+E42+G42+I42+K42+M42+O42+Q42 -> 445566281 | T42: =+S42-U42 -> 287992624 | U42: =+D42+F42+H42+J42+L42+N42+P42+R42 -> 157573657 | V42: 0.5 | W42: =+E42+G42 -> 253131056 | X42: =+W42*V42 -> 126565528 | Y42: =+F42+H42 -> 118263193 | Z42: =+Y42*V42 -> 59131596
A43: 18.1 | B43: Бош офис/филиалдан олиниши лозим бўлган ҳисобланган фоизлар | S43: =+C43+E43+G43+I43+K43+M43+O43+Q43 -> 0 | T43: =+S43-U43 -> 0 | U43: =+D43+F43+H43+J43+L43+N43+P43+R43 -> 0 | V43: 1 | W43: =+E43+G43 -> 0 | X43: =+W43*V43 -> 0 | Y43: =+F43+H43 -> 0 | Z43: =+Y43*V43 -> 0
A44: 18.2 | B44: Бошқа банклардан олиниши лозим бўлган ҳисобланган фоизлар | S44: =+C44+E44+G44+I44+K44+M44+O44+Q44 -> 0 | T44: =+S44-U44 -> 0 | U44: =+D44+F44+H44+J44+L44+N44+P44+R44 -> 0 | V44: 1 | W44: =+E44+G44 -> 0 | X44: =+W44*V44 -> 0 | Y44: =+F44+H44 -> 0 | Z44: =+Y44*V44 -> 0
A45: 19 | B45: Бошқа активлар | C45: 1382890982 | D45: 27104757 | E45: 33709 | F45: 16423 | G45: 238193 | H45: 272 | I45: 438314 | J45: 178151 | K45: 1074338 | L45: 509114 | M45: 956247 | N45: 464814 | O45: 3367670 | P45: 1025671 | Q45: 23940437 | R45: 8764881 | S45: =+C45+E45+G45+I45+K45+M45+O45+Q45 -> 1412939890 | T45: =+S45-U45 -> 1374875807 | U45: =+D45+F45+H45+J45+L45+N45+P45+R45 -> 38064083 | V45: 0
A46: 20 | B46: Гаровга қўйилган юқори ликвидли активлар, 4a бундан мустасно | C46: 0 | D46: 0 | E46: 0 | F46: 0 | G46: 0 | H46: 0 | I46: 0 | J46: 0 | K46: 0 | L46: 0 | M46: 0 | N46: 0 | O46: 0 | P46: 0 | Q46: 0 | R46: 0 | S46: =+C46+E46+G46+I46+K46+M46+O46+Q46 -> 0 | T46: =+S46-U46 -> 0 | U46: =+D46+F46+H46+J46+L46+N46+P46+R46 -> 0 | V46: 1 | W46: =+C46+E46+G46 -> 0 | X46: =+W46*V46 -> 0 | Y46: =+D46+F46+H46 -> 0 | Z46: =+Y46*V46 -> 0
A47: 21 | B47: ЖAМИ АКТИВЛАР | C47: =SUM(C6:C45)-C9-C13-C17-C18-C31-C34 -> 4770793053 | D47: =SUM(D6:D45)-D9-D13-D17-D18-D31-D34 -> 936815624 | E47: =SUM(E6:E45)-E9-E13-E17-E18-E31-E34 -> 29800448 | F47: =SUM(F6:F45)-F9-F13-F17-F18-F31-F34 -> 422283 | G47: =SUM(G6:G45)-G9-G13-G17-G18-G31-G34 -> 839860803 | H47: =SUM(H6:H45)-H9-H13-H17-H18-H31-H34 -> 249959530 | I47: =SUM(I6:I45)-I9-I13-I17-I18-I31-I34 -> 1407169860 | J47: =SUM(J6:J45)-J9-J13-J17-J18-J31-J34 -> 357646984 | ... R47: =SUM(R6:R45)-R9-R13-R17-R18-R31-R34 -> 1524774187 | S47: =+C47+E47+G47+I47+K47+M47+O47+Q47 -> 23251274687 | T47: =+S47-U47 -> 18342429406 | U47: =+D47+F47+H47+J47+L47+N47+P47+R47 -> 4908845281 | X47: =+X12+X14+X15+X16+X18+X25+X26+X27+X28+X29+X30+X42+X46+(T23*0.2)+X43+X44 -> 1319977238 | Z47: =+Z12+Z14+Z15+Z16+Z18+Z25+Z26+Z27+Z28+Z29+Z30+Z42+Z46+(U23*0.2)+Z43+Z44 -> 177063379 | AA47: =+Balance!C47 -> 23251274687 | AB47: =+Balance!D47 -> 18342429406 | AC47: =+Balance!E47 -> 4908845281
B48: Балансдан ташқари мажбуриятлар | AA48: =+AA47-S47 -> 0 | AB48: =+AB47-T47 -> 0 | AC48: =+AC47-U47 -> 0
A49: 1 | B49: Банкнинг кредит ва лизинг бериш бўйича мажбуриятлари (91809) | C49: 128630 | D49: 0 | E49: 59406361 | F49: 0 | G49: 0 | H49: 0 | I49: 583858 | J49: 533858 | K49: 48702046 | L49: 47399485 | M49: 154855966 | N49: 48193390 | O49: 74290480 | P49: 3563468 | Q49: 502064975 | R49: 303287237 | S49: =+C49+E49+G49+I49+K49+M49+O49+Q49 -> 840032316 | T49: =+S49-U49 -> 437054878 | U49: =+D49+F49+H49+J49+L49+N49+P49+R49 -> 402977438 | AA49: =+Commitments!C4 -> 840032316 | AB49: =+Commitments!D4 -> 437054878 | AC49: =+Commitments!E4 -> 402977438 | AD49: =+AA49-S49 -> 0 | AE49: =+AB49-T49 -> 0 | AF49: =+AC49-U49 -> 0
B50: шундан, ХМИ, Молия вазирлиги, фондлар ва бошқа ташкилотларнинг депозитлари билан таъминланган | C50: 0 | D50: 0 | E50: 0 | F50: 0 | G50: 0 | H50: 0 | I50: 0 | J50: 0 | K50: 0 | L50: 0 | M50: 0 | N50: 0 | O50: 0 | P50: 0 | Q50: 2704256 | R50: 2704256 | S50: =+C50+E50+G50+I50+K50+M50+O50+Q50 -> 2704256 | T50: =+S50-U50 -> 0 | U50: =+D50+F50+H50+J50+L50+N50+P50+R50 -> 2704256 | AA50: =+Commitments!C5 -> 2704256 | AB50: =+Commitments!D5 -> 0 | AC50: =+Commitments!E5 -> 2704256
A51: 2 | B51: Кафолат ва кафилликлар (90993) | C51: 0 | D51: 0 | E51: 0 | F51: 0 | G51: 1154145 | H51: 0 | I51: 136048164 | J51: 128375481 | K51: 64955346 | L51: 39189203 | M51: 138477803 | N51: 138477803 | O51: 92999000 | P51: 92999000 | Q51: 402010399 | R51: 402010399 | S51: =+C51+E51+G51+I51+K51+M51+O51+Q51 -> 835644857 | T51: =+S51-U51 -> 34592971 | U51: =+D51+F51+H51+J51+L51+N51+P51+R51 -> 801051886 | AA51: =+Commitments!C7 -> 835644857 | AB51: =+Commitments!D7 -> 34592971 | AC51: =+Commitments!E7 -> 801051886 | AD51: =+AA51-S51 -> 0 | AE51: =+AB51-T51 -> 0 | AF51: =+AC51-U51 -> 0
B52: - шундан, алоҳида блокланган ҳисобварақлардаги депозитлар билан таъминланган кафолат ва кафилликлар | C52: 0 | D52: 0 | E52: 0 | F52: 0 | G52: 0 | H52: 0 | I52: 0 | J52: 0 | K52: 0 | L52: 0 | M52: 0 | N52: 0 | O52: 0 | P52: 0 | Q52: 0 | R52: 0 | S52: =+C52+E52+G52+I52+K52+M52+O52+Q52 -> 0 | T52: =+S52-U52 -> 0 | U52: =+D52+F52+H52+J52+L52+N52+P52+R52 -> 0 | AA52: =+Commitments!C8 -> 0 | AB52: =+Commitments!D8 -> 0 | AC52: =+Commitments!E8 -> 0
A53: 3 | B53: Аккредитивлар (90908-90958) | C53: 0 | D53: 0 | E53: 1568703 | F53: 1568703 | G53: 667550 | H53: 667550 | I53: 2939880 | J53: 2939880 | K53: 3220231 | L53: 3220231 | M53: 225455420 | N53: 225455420 | O53: 53045369 | P53: 53045369 | Q53: 0 | R53: 0 | S53: =+C53+E53+G53+I53+K53+M53+O53+Q53 -> 286897153 | T53: =+S53-U53 -> 0 | U53: =+D53+F53+H53+J53+L53+N53+P53+R53 -> 286897153 | AA53: =+Commitments!C10 -> 286897153 | AB53: =+Commitments!D10 -> 0 | AC53: =+Commitments!E10 -> 286897153 | AD53: =+AA53-S53 -> 0 | AE53: =+AB53-T53 -> 0 | AF53: =+AC53-U53 -> 0
B54: - шундан, 22602 баланс ҳисобварағида депозит билан таъминланганлар кўрсатилади | C54: 0 | D54: 0 | E54: 1162843 | F54: 1162843 | G54: 0 | H54: 0 | I54: 793059 | J54: 793059 | K54: 0 | L54: 0 | M54: 37762040 | N54: 37762040 | O54: 53045367 | P54: 53045367 | Q54: 0 | R54: 0 | S54: =+C54+E54+G54+I54+K54+M54+O54+Q54 -> 92763309 | T54: =+S54-U54 -> 0 | U54: =+D54+F54+H54+J54+L54+N54+P54+R54 -> 92763309
B56: Бошқарув Раис имзоси:
B58: Бош бухгалтер имзоси:
W60: По новым расчетам
W61: =+Balance!C47 -> 23251274687 | X61: =+Balance!D47 -> 18342429406 | Y61: =+Balance!E47 -> 4908845281
W62: Всего | Y62: Ин вал
W63: Приток | X63: =+X47 -> 1319977238 | Y63: Приток | Z63: =+Z47 -> 177063379
W64: Высоко-ликвидные активы | X64: =+X6+X7+X10+X11+X13+X19+X20+X21+X22+X24+X35-X46-X18 -> 4192263974 | Y64: Высоко-ликвидные активы | Z64: =+Z6+Z7+Z10+Z11+Z13+Z19+Z20+Z21+Z22+Z24+Z35-Z46-Z18 -> 821402745
W65: Чистый отток за 30 дней | X65: =+X67-X70 -> 2.6089389e+09 | Y65: Чистый отток за 30 дней | Z65: =+Z67-Z70 -> 6.5504748e+08
W67: Всего отток | X67: =+'Bank Liabilities Analysis'!W42+'Liquidity Analysis'!C41 -> 3.9289161e+09 | Y67: Отток | Z67: =+'Bank Liabilities Analysis'!X42+'Liquidity Analysis'!E41 -> 8.3211085e+08
W68: в том числе отток по внебалансу | X68: =+'Liquidity Analysis'!C41 -> 280066014 | Y68: в том числе отток по внебалансу | Z68: =+'Liquidity Analysis'!E41 -> 209318837
W70: Приток по положению | X70: =IF(X63>(X67*0.75),X67*0.75,X63) -> 1319977238 | Y70: Приток по положению | Z70: =IF(Z63>(Z67*0.75),Z67*0.75,Z63) -> 177063379

Sheet Bank Assets Analysis (нац)
A2: МИЛЛИЙ ВАЛЮТАДАГИ БАНК АКТИВЛАРИ ТАҲЛИЛИ | L2: 17 А-жадвал
B3: =Balance!B3 -> Банк номи | K3: =+Balance!D3 -> 45657 | N3: =+Balance!E3 -> минг сўмда
A4: № | B4: Кўрсаткичлар | C4: Сўндириш муддати (кунларда) | K4: Жами | L4: Ликвидлиликни қоплаш меёри ҳисоб китоби
C5: Муддатсиз | D5: 1 дан 7 гача | E5: 8 дан 30 гача | F5: 31 дан 90 гача | G5: 91 дан 180 гача | H5: 181 дан 365 гача | I5: 366 дан 730 гача | J5: 2 йилдан ортиқ | L5: Коэффициент | M5: Активлар | N5: Юқори ликвидли активлар/кирим
A6: 1 | B6: Кассадаги нақд пул ва бошқа тўлов ҳужжатлари | C6: =+'Bank Assets Analysis'!C6-'Bank Assets Analysis'!D6 -> 230334913 | D6: =+'Bank Assets Analysis'!E6-'Bank Assets Analysis'!F6 -> 0 | E6: =+'Bank Assets Analysis'!G6-'Bank Assets Analysis'!H6 -> 0 | F6: =+'Bank Assets Analysis'!I6-'Bank Assets Analysis'!J6 -> 0 | G6: =+'Bank Assets Analysis'!K6-'Bank Assets Analysis'!L6 -> 0 | H6: =+'Bank Assets Analysis'!M6-'Bank Assets Analysis'!N6 -> 0 | I6: =+'Bank Assets Analysis'!O6-'Bank Assets Analysis'!P6 -> 0 | J6: =+'Bank Assets Analysis'!Q6-'Bank Assets Analysis'!R6 -> 0 | K6: =+C6+D6+E6+F6+G6+H6+I6+J6 -> 230334913 | L6: 1 | M6: =+K6 -> 230334913 | N6: =+M6*L6 -> 230334913
A7: 2 | B7: Банкнинг Марказий банкдаги маблағлари (мажбурий захирасиз) | C7: =+'Bank Assets Analysis'!C7-'Bank Assets Analysis'!D7 -> 1828213292 | D7: =+'Bank Assets Analysis'!E7-'Bank Assets Analysis'!F7 -> 0 | E7: =+'Bank Assets Analysis'!G7-'Bank Assets Analysis'!H7 -> 0 | F7: =+'Bank Assets Analysis'!I7-'Bank Assets Analysis'!J7 -> 0 | G7: =+'Bank Assets Analysis'!K7-'Bank Assets Analysis'!L7 -> 0 | H7: =+'Bank Assets Analysis'!M7-'Bank Assets Analysis'!N7 -> 0 | I7: =+'Bank Assets Analysis'!O7-'Bank Assets Analysis'!P7 -> 0 | J7: =+'Bank Assets Analysis'!Q7-'Bank Assets Analysis'!R7 -> 0 | K7: =+C7+D7+E7+F7+G7+H7+I7+J7 -> 1828213292 | L7: 1 | M7: =+K7 -> 1828213292 | N7: =+M7*L7 -> 1828213292
A8: 2.1 | B8: Банкнинг Марказий банкдаги мажбурий захира ҳисобварағидаги маблағлар | C8: =+'Bank Assets Analysis'!C8-'Bank Assets Analysis'!D8 -> 0 | D8: =+'Bank Assets Analysis'!E8-'Bank Assets Analysis'!F8 -> 0 | E8: =+'Bank Assets Analysis'!G8-'Bank Assets Analysis'!H8 -> 0 | F8: =+'Bank Assets Analysis'!I8-'Bank Assets Analysis'!J8 -> 0 | G8: =+'Bank Assets Analysis'!K8-'Bank Assets Analysis'!L8 -> 0 | H8: =+'Bank Assets Analysis'!M8-'Bank Assets Analysis'!N8 -> 0 | I8: =+'Bank Assets Analysis'!O8-'Bank Assets Analysis'!P8 -> 0 | J8: =+'Bank Assets Analysis'!Q8-'Bank Assets Analysis'!R8 -> 0 | K8: =+C8+D8+E8+F8+G8+H8+I8+J8 -> 0 | L8: 0 | N8: =+M8*L8 -> 0
A9: 3 | B9: Бошқа банклар ва молиявий ташкилотлардан олиниши лозим бўлган маблағлар | C9: =SUM(C10:C16)-C13 -> 112412715 | D9: =SUM(D10:D16)-D13 -> 0 | E9: =SUM(E10:E16)-E13 -> 40000000 | F9: =SUM(F10:F16)-F13 -> 0 | G9: =SUM(G10:G16)-G13 -> 24409360 | H9: =SUM(H10:H16)-H13 -> 24409360 | I9: =SUM(I10:I16)-I13 -> 37522553 | J9: =SUM(J10:J16)-J13 -> 16424614 | K9: =+C9+D9+E9+F9+G9+H9+I9+J9 -> 255178602 | N9: =+M9*L9 -> 0
A10: 3.1 | B10: Таваккалчилик даражаси паст банклардаги вакиллик ҳисобварақлари (ностро) | C10: =+'Bank Assets Analysis'!C10-'Bank Assets Analysis'!D10 -> 0 | D10: =+'Bank Assets Analysis'!E10-'Bank Assets Analysis'!F10 -> 0 | E10: =+'Bank Assets Analysis'!G10-'Bank Assets Analysis'!H10 -> 0 | F10: =+'Bank Assets Analysis'!I10-'Bank Assets Analysis'!J10 -> 0 | G10: =+'Bank Assets Analysis'!K10-'Bank Assets Analysis'!L10 -> 0 | H10: =+'Bank Assets Analysis'!M10-'Bank Assets Analysis'!N10 -> 0 | I10: =+'Bank Assets Analysis'!O10-'Bank Assets Analysis'!P10 -> 0 | J10: =+'Bank Assets Analysis'!Q10-'Bank Assets Analysis'!R10 -> 0 | K10: =+C10+D10+E10+F10+G10+H10+I10+J10 -> 0 | L10: 1 | M10: =+C10 -> 0 | N10: =+M10*L10 -> 0
A11: 3.2 | B11: Маҳаллий банклардаги вакиллик ҳисобварақлари (ностро) | C11: =+'Bank Assets Analysis'!C11-'Bank Assets Analysis'!D11 -> 0 | D11: =+'Bank Assets Analysis'!E11-'Bank Assets Analysis'!F11 -> 0 | E11: =+'Bank Assets Analysis'!G11-'Bank Assets Analysis'!H11 -> 0 | F11: =+'Bank Assets Analysis'!I11-'Bank Assets Analysis'!J11 -> 0 | G11: =+'Bank Assets Analysis'!K11-'Bank Assets Analysis'!L11 -> 0 | H11: =+'Bank Assets Analysis'!M11-'Bank Assets Analysis'!N11 -> 0 | I11: =+'Bank Assets Analysis'!O11-'Bank Assets Analysis'!P11 -> 0 | J11: =+'Bank Assets Analysis'!Q11-'Bank Assets Analysis'!R11 -> 0 | K11: =+C11+D11+E11+F11+G11+H11+I11+J11 -> 0 | L11: 1 | M11: =+C11 -> 0 | N11: =+M11*L11 -> 0
A12: 3.3 | B12: Овернайт шарти билан жойлаштирилган депозитлар | C12: =+'Bank Assets Analysis'!C12-'Bank Assets Analysis'!D12 -> 0 | D12: =+'Bank Assets Analysis'!E12-'Bank Assets Analysis'!F12 -> 0 | E12: =+'Bank Assets Analysis'!G12-'Bank Assets Analysis'!H12 -> 0 | F12: =+'Bank Assets Analysis'!I12-'Bank Assets Analysis'!J12 -> 0 | G12: =+'Bank Assets Analysis'!K12-'Bank Assets Analysis'!L12 -> 0 | H12: =+'Bank Assets Analysis'!M12-'Bank Assets Analysis'!N12 -> 0 | I12: =+'Bank Assets Analysis'!O12-'Bank Assets Analysis'!P12 -> 0 | J12: =+'Bank Assets Analysis'!Q12-'Bank Assets Analysis'!R12 -> 0 | K12: =+C12+D12+E12+F12+G12+H12+I12+J12 -> 0 | L12: 1 | M12: =+D12-D13 -> 0 | N12: =+M12*L12 -> 0
A13: 3.3.1. | B13: шундан, инвестицион даражадан паст бўлмаган рейтингга эга банкларга овернайт шарти билан жойлаштирилган хорижий валютадаги депозитлар | C13: =+'Bank Assets Analysis'!C13-'Bank Assets Analysis'!D13 -> 0 | D13: =+'Bank Assets Analysis'!E13-'Bank Assets Analysis'!F13 -> 0 | E13: =+'Bank Assets Analysis'!G13-'Bank Assets Analysis'!H13 -> 0 | F13: =+'Bank Assets Analysis'!I13-'Bank Assets Analysis'!J13 -> 0 | G13: =+'Bank Assets Analysis'!K13-'Bank Assets Analysis'!L13 -> 0 | H13: =+'Bank Assets Analysis'!M13-'Bank Assets Analysis'!N13 -> 0 | I13: =+'Bank Assets Analysis'!O13-'Bank Assets Analysis'!P13 -> 0 | J13: =+'Bank Assets Analysis'!Q13-'Bank Assets Analysis'!R13 -> 0 | K13: =+C13+D13+E13+F13+G13+H13+I13+J13 -> 0 | L13: 1 | M13: =+D13 -> 0 | N13: =+M13*L13 -> 0
A14: 3.4 | B14: Банкнинг бошқа банклар/молиявий ташкилотлардаги ҳисобварақлари | C14: =+'Bank Assets Analysis'!C14-'Bank Assets Analysis'!D14 -> 5000 | D14: =+'Bank Assets Analysis'!E14-'Bank Assets Analysis'!F14 -> 0 | E14: =+'Bank Assets Analysis'!G14-'Bank Assets Analysis'!H14 -> 40000000 | F14: =+'Bank Assets Analysis'!I14-'Bank Assets Analysis'!J14 -> 0 | G14: =+'Bank Assets Analysis'!K14-'Bank Assets Analysis'!L14 -> 24409360 | H14: =+'Bank Assets Analysis'!M14-'Bank Assets Analysis'!N14 -> 24409360 | I14: =+'Bank Assets Analysis'!O14-'Bank Assets Analysis'!P14 -> 37522553 | J14: =+'Bank Assets Analysis'!Q14-'Bank Assets Analysis'!R14 -> 16424614 | K14: =+C14+D14+E14+F14+G14+H14+I14+J14 -> 142770887 | L14: 1 | M14: =+C14+D14+E14+D10+D11 -> 40005000 | N14: =+M14*L14 -> 40005000
A15: 3.5 | B15: Пластик карталардан амалга оширилган тўловлар бўйича бошқа банклардан олиниши лозим бўлган маблағлар | C15: =+'Bank Assets Analysis'!C15-'Bank Assets Analysis'!D15 -> 112407715 | D15: =+'Bank Assets Analysis'!E15-'Bank Assets Analysis'!F15 -> 0 | E15: =+'Bank Assets Analysis'!G15-'Bank Assets Analysis'!H15 -> 0 | F15: =+'Bank Assets Analysis'!I15-'Bank Assets Analysis'!J15 -> 0 | G15: =+'Bank Assets Analysis'!K15-'Bank Assets Analysis'!L15 -> 0 | H15: =+'Bank Assets Analysis'!M15-'Bank Assets Analysis'!N15 -> 0 | I15: =+'Bank Assets Analysis'!O15-'Bank Assets Analysis'!P15 -> 0 | J15: =+'Bank Assets Analysis'!Q15-'Bank Assets Analysis'!R15 -> 0 | K15: =+C15+D15+E15+F15+G15+H15+I15+J15 -> 112407715 | L15: 1 | M15: =+C15+D15+E15 -> 112407715 | N15: =+M15*L15 -> 112407715
A16: 3.6 | B16: Бошқа моддалар | C16: =+'Bank Assets Analysis'!C16-'Bank Assets Analysis'!D16 -> 0 | D16: =+'Bank Assets Analysis'!E16-'Bank Assets Analysis'!F16 -> 0 | E16: =+'Bank Assets Analysis'!G16-'Bank Assets Analysis'!H16 -> 0 | F16: =+'Bank Assets Analysis'!I16-'Bank Assets Analysis'!J16 -> 0 | G16: =+'Bank Assets Analysis'!K16-'Bank Assets Analysis'!L16 -> 0 | H16: =+'Bank Assets Analysis'!M16-'Bank Assets Analysis'!N16 -> 0 | I16: =+'Bank Assets Analysis'!O16-'Bank Assets Analysis'!P16 -> 0 | J16: =+'Bank Assets Analysis'!Q16-'Bank Assets Analysis'!R16 -> 0 | K16: =+C16+D16+E16+F16+G16+H16+I16+J16 -> 0 | L16: 1 | M16: =+C16+D16+E16 -> 0 | N16: =+M16*L16 -> 0
A17: 4 | B17: Қимматли қоғозлар ва уларга қилинган инвестициялар, соф | C17: =+'Bank Assets Analysis'!C17-'Bank Assets Analysis'!D17 -> 251 | D17: =+'Bank Assets Analysis'!E17-'Bank Assets Analysis'!F17 -> 0 | E17: =+'Bank Assets Analysis'!G17-'Bank Assets Analysis'!H17 -> 199447829 | F17: =+'Bank Assets Analysis'!I17-'Bank Assets Analysis'!J17 -> 461830511 | G17: =+'Bank Assets Analysis'!K17-'Bank Assets Analysis'!L17 -> 0 | H17: =+'Bank Assets Analysis'!M17-'Bank Assets Analysis'!N17 -> 160140364 | I17: =+'Bank Assets Analysis'!O17-'Bank Assets Analysis'!P17 -> 928910901 | J17: =+'Bank Assets Analysis'!Q17-'Bank Assets Analysis'!R17 -> 363443230 | K17: =+C17+D17+E17+F17+G17+H17+I17+J17 -> 2113773086 | N17: =+M17*L17 -> 0
A18: 4a | B18: шу жумладан, таъминот остидаги юқори ликвидли қимматли қоғозлар | C18: =+'Bank Assets Analysis'!C18-'Bank Assets Analysis'!D18 -> 0 | D18: =+'Bank Assets Analysis'!E18-'Bank Assets Analysis'!F18 -> 801459811 | E18: =+'Bank Assets Analysis'!G18-'Bank Assets Analysis'!H18 -> 0 | F18: =+'Bank Assets Analysis'!I18-'Bank Assets Analysis'!J18 -> 0 | G18: =+'Bank Assets Analysis'!K18-'Bank Assets Analysis'!L18 -> 0 | H18: =+'Bank Assets Analysis'!M18-'Bank Assets Analysis'!N18 -> 0 | I18: =+'Bank Assets Analysis'!O18-'Bank Assets Analysis'!P18 -> 0 | J18: =+'Bank Assets Analysis'!Q18-'Bank Assets Analysis'!R18 -> 0 | K18: =+C18+D18+E18+F18+G18+H18+I18+J18 -> 801459811 | L18: 1 | M18: =SUM(C18:E18) -> 801459811 | N18: =+M18*L18 -> 801459811
A19: 4.1 | B19: Ўзбекистон Республикаси Ҳукумати ва Марказий банк томонидан чиқарилган қимматли қоғозлар (векселлар, облигациялар ва бошқа қарз қимматли қоғозлар) | C19: =+'Bank Assets Analysis'!C19-'Bank Assets Analysis'!D19 -> 0 | D19: =+'Bank Assets Analysis'!E19-'Bank Assets Analysis'!F19 -> 0 | E19: =+'Bank Assets Analysis'!G19-'Bank Assets Analysis'!H19 -> 199447829 | F19: =+'Bank Assets Analysis'!I19-'Bank Assets Analysis'!J19 -> 461830511 | G19: =+'Bank Assets Analysis'!K19-'Bank Assets Analysis'!L19 -> 0 | H19: =+'Bank Assets Analysis'!M19-'Bank Assets Analysis'!N19 -> 160140364 | I19: =+'Bank Assets Analysis'!O19-'Bank Assets Analysis'!P19 -> 928910901 | J19: =+'Bank Assets Analysis'!Q19-'Bank Assets Analysis'!R19 -> 363443230 | K19: =+C19+D19+E19+F19+G19+H19+I19+J19 -> 2113772835 | L19: 1 | M19: =+K19 -> 2113772835 | N19: =+M19*L19 -> 2113772835
A20: 4.2 | B20: Таваккалчилик даражаси паст бўлган мамлакатларнинг қимматли қоғозлари | C20: =+'Bank Assets Analysis'!C20-'Bank Assets Analysis'!D20 -> 0 | D20: =+'Bank Assets Analysis'!E20-'Bank Assets Analysis'!F20 -> 0 | E20: =+'Bank Assets Analysis'!G20-'Bank Assets Analysis'!H20 -> 0 | F20: =+'Bank Assets Analysis'!I20-'Bank Assets Analysis'!J20 -> 0 | G20: =+'Bank Assets Analysis'!K20-'Bank Assets Analysis'!L20 -> 0 | H20: =+'Bank Assets Analysis'!M20-'Bank Assets Analysis'!N20 -> 0 | I20: =+'Bank Assets Analysis'!O20-'Bank Assets Analysis'!P20 -> 0 | J20: =+'Bank Assets Analysis'!Q20-'Bank Assets Analysis'!R20 -> 0 | K20: =+C20+D20+E20+F20+G20+H20+I20+J20 -> 0 | L20: 1 | M20: =+K20 -> 0 | N20: =+M20*L20 -> 0
A21: 4.3 | B21: ХВФ, Жаҳон банки гуруҳи, Осиё тараққиёт банки, Осиё инфраструктура инвестиция банки, ЕТТБ, Европа инвестиция банки, Европа инвестиция жамғармаси, Ислом тараққиёт банки ва Европа Кенгашининг тараққиёт банки томонидан чиқарилган қимматли қоғозлар | C21: =+'Bank Assets Analysis'!C21-'Bank Assets Analysis'!D21 -> 0 | D21: =+'Bank Assets Analysis'!E21-'Bank Assets Analysis'!F21 -> 0 | E21: =+'Bank Assets Analysis'!G21-'Bank Assets Analysis'!H21 -> 0 | F21: =+'Bank Assets Analysis'!I21-'Bank Assets Analysis'!J21 -> 0 | G21: =+'Bank Assets Analysis'!K21-'Bank Assets Analysis'!L21 -> 0 | H21: =+'Bank Assets Analysis'!M21-'Bank Assets Analysis'!N21 -> 0 | I21: =+'Bank Assets Analysis'!O21-'Bank Assets Analysis'!P21 -> 0 | J21: =+'Bank Assets Analysis'!Q21-'Bank Assets Analysis'!R21 -> 0 | K21: =+C21+D21+E21+F21+G21+H21+I21+J21 -> 0 | L21: 1 | M21: =+K21 -> 0 | N21: =+M21*L21 -> 0
A22: 4.4 | B22: Таваккалчилик даражаси паст бўлган мамлакатларнинг етакчи компаниялари қимматли қоғозлари | C22: =+'Bank Assets Analysis'!C22-'Bank Assets Analysis'!D22 -> 0 | D22: =+'Bank Assets Analysis'!E22-'Bank Assets Analysis'!F22 -> 0 | E22: =+'Bank Assets Analysis'!G22-'Bank Assets Analysis'!H22 -> 0 | F22: =+'Bank Assets Analysis'!I22-'Bank Assets Analysis'!J22 -> 0 | G22: =+'Bank Assets Analysis'!K22-'Bank Assets Analysis'!L22 -> 0 | H22: =+'Bank Assets Analysis'!M22-'Bank Assets Analysis'!N22 -> 0 | I22: =+'Bank Assets Analysis'!O22-'Bank Assets Analysis'!P22 -> 0 | J22: =+'Bank Assets Analysis'!Q22-'Bank Assets Analysis'!R22 -> 0 | K22: =+C22+D22+E22+F22+G22+H22+I22+J22 -> 0 | L22: 1 | M22: =+D22+E22 -> 0 | N22: =+M22*L22 -> 0
A23: 4.5 | B23: Ипотекани қайта молиялаштириш ташкилотлари томонидан чиқарилган корпоратив облигациялар | C23: =+'Bank Assets Analysis'!C23-'Bank Assets Analysis'!D23 -> 0 | D23: =+'Bank Assets Analysis'!E23-'Bank Assets Analysis'!F23 -> 0 | E23: =+'Bank Assets Analysis'!G23-'Bank Assets Analysis'!H23 -> 0 | F23: =+'Bank Assets Analysis'!I23-'Bank Assets Analysis'!J23 -> 0 | G23: =+'Bank Assets Analysis'!K23-'Bank Assets Analysis'!L23 -> 0 | H23: =+'Bank Assets Analysis'!M23-'Bank Assets Analysis'!N23 -> 0 | I23: =+'Bank Assets Analysis'!O23-'Bank Assets Analysis'!P23 -> 0 | J23: =+'Bank Assets Analysis'!Q23-'Bank Assets Analysis'!R23 -> 0 | K23: =+C23+D23+E23+F23+G23+H23+I23+J23 -> 0 | L23: 0.8 | M23: =+C23+D23+E23 -> 0 | N23: =+M23*L23 -> 0
A24: 4.6 | B24: Ипотекани қайта молиялаштириш ташкилотлари томонидан чиқарилган таъминланган қарз муносабатларини тасдиқловчи бошқа қимматли қоғозлар | C24: =+'Bank Assets Analysis'!C24-'Bank Assets Analysis'!D24 -> 0 | D24: =+'Bank Assets Analysis'!E24-'Bank Assets Analysis'!F24 -> 0 | E24: =+'Bank Assets Analysis'!G24-'Bank Assets Analysis'!H24 -> 0 | F24: =+'Bank Assets Analysis'!I24-'Bank Assets Analysis'!J24 -> 0 | G24: =+'Bank Assets Analysis'!K24-'Bank Assets Analysis'!L24 -> 0 | H24: =+'Bank Assets Analysis'!M24-'Bank Assets Analysis'!N24 -> 0 | I24: =+'Bank Assets Analysis'!O24-'Bank Assets Analysis'!P24 -> 0 | J24: =+'Bank Assets Analysis'!Q24-'Bank Assets Analysis'!R24 -> 0 | K24: =+C24+D24+E24+F24+G24+H24+I24+J24 -> 0 | L24: 1 | M24: =+D24+E24 -> 0 | N24: =+M24*L24 -> 0
A25: 4.7 | B25: Бошқалар | C25: =+'Bank Assets Analysis'!C25-'Bank Assets Analysis'!D25 -> 251 | D25: =+'Bank Assets Analysis'!E25-'Bank Assets Analysis'!F25 -> 0 | E25: =+'Bank Assets Analysis'!G25-'Bank Assets Analysis'!H25 -> 0 | F25: =+'Bank Assets Analysis'!I25-'Bank Assets Analysis'!J25 -> 0 | G25: =+'Bank Assets Analysis'!K25-'Bank Assets Analysis'!L25 -> 0 | H25: =+'Bank Assets Analysis'!M25-'Bank Assets Analysis'!N25 -> 0 | I25: =+'Bank Assets Analysis'!O25-'Bank Assets Analysis'!P25 -> 0 | J25: =+'Bank Assets Analysis'!Q25-'Bank Assets Analysis'!R25 -> 0 | K25: =+C25+D25+E25+F25+G25+H25+I25+J25 -> 251 | L25: 1 | M25: =+C25+D25+E25 -> 251 | N25: =+M25*L25 -> 251
A26: 5 | B26: Мижозларнинг аккредитив ва траст ҳужжатлари билан кафолатланган тратталари бўйича мажбуриятлари, соф | C26: =+'Bank Assets Analysis'!C26-'Bank Assets Analysis'!D26 -> 0 | D26: =+'Bank Assets Analysis'!E26-'Bank Assets Analysis'!F26 -> 0 | E26: =+'Bank Assets Analysis'!G26-'Bank Assets Analysis'!H26 -> 0 | F26: =+'Bank Assets Analysis'!I26-'Bank Assets Analysis'!J26 -> 0 | G26: =+'Bank Assets Analysis'!K26-'Bank Assets Analysis'!L26 -> 0 | H26: =+'Bank Assets Analysis'!M26-'Bank Assets Analysis'!N26 -> 0 | I26: =+'Bank Assets Analysis'!O26-'Bank Assets Analysis'!P26 -> 0 | J26: =+'Bank Assets Analysis'!Q26-'Bank Assets Analysis'!R26 -> 0 | K26: =+C26+D26+E26+F26+G26+H26+I26+J26 -> 0 | L26: 0.5 | M26: =+D26+E26 -> 0 | N26: =+M26*L26 -> 0
A27: 6 | B27: Мижозларнинг банк олдидаги тўланмаган акцептлари бўйича мажбуриятлари, соф | C27: =+'Bank Assets Analysis'!C27-'Bank Assets Analysis'!D27 -> 0 | D27: =+'Bank Assets Analysis'!E27-'Bank Assets Analysis'!F27 -> 0 | E27: =+'Bank Assets Analysis'!G27-'Bank Assets Analysis'!H27 -> 0 | F27: =+'Bank Assets Analysis'!I27-'Bank Assets Analysis'!J27 -> 0 | G27: =+'Bank Assets Analysis'!K27-'Bank Assets Analysis'!L27 -> 0 | H27: =+'Bank Assets Analysis'!M27-'Bank Assets Analysis'!N27 -> 0 | I27: =+'Bank Assets Analysis'!O27-'Bank Assets Analysis'!P27 -> 0 | J27: =+'Bank Assets Analysis'!Q27-'Bank Assets Analysis'!R27 -> 0 | K27: =+C27+D27+E27+F27+G27+H27+I27+J27 -> 0 | L27: 0.5 | M27: =+D27+E27 -> 0 | N27: =+M27*L27 -> 0
A28: 7 | B28: Марказий банкка берилган кредит ва лизинглар, соф | C28: =+'Bank Assets Analysis'!C28-'Bank Assets Analysis'!D28 -> 0 | D28: =+'Bank Assets Analysis'!E28-'Bank Assets Analysis'!F28 -> 0 | E28: =+'Bank Assets Analysis'!G28-'Bank Assets Analysis'!H28 -> 0 | F28: =+'Bank Assets Analysis'!I28-'Bank Assets Analysis'!J28 -> 0 | G28: =+'Bank Assets Analysis'!K28-'Bank Assets Analysis'!L28 -> 0 | H28: =+'Bank Assets Analysis'!M28-'Bank Assets Analysis'!N28 -> 0 | I28: =+'Bank Assets Analysis'!O28-'Bank Assets Analysis'!P28 -> 0 | J28: =+'Bank Assets Analysis'!Q28-'Bank Assets Analysis'!R28 -> 0 | K28: =+C28+D28+E28+F28+G28+H28+I28+J28 -> 0 | L28: 1 | M28: =C28+D28+E28 -> 0 | N28: =+M28*L28 -> 0
A29: 8 | B29: Бошқа банкларга берилган кредит ва лизинглар, соф | C29: =+'Bank Assets Analysis'!C29-'Bank Assets Analysis'!D29 -> 0 | D29: =+'Bank Assets Analysis'!E29-'Bank Assets Analysis'!F29 -> 0 | E29: =+'Bank Assets Analysis'!G29-'Bank Assets Analysis'!H29 -> 0 | F29: =+'Bank Assets Analysis'!I29-'Bank Assets Analysis'!J29 -> 0 | G29: =+'Bank Assets Analysis'!K29-'Bank Assets Analysis'!L29 -> 0 | H29: =+'Bank Assets Analysis'!M29-'Bank Assets Analysis'!N29 -> 0 | I29: =+'Bank Assets Analysis'!O29-'Bank Assets Analysis'!P29 -> 0 | J29: =+'Bank Assets Analysis'!Q29-'Bank Assets Analysis'!R29 -> 0 | K29: =+C29+D29+E29+F29+G29+H29+I29+J29 -> 0 | L29: 0.5 | M29: =+D29+E29 -> 0 | N29: =+M29*L29 -> 0
A30: 9 | B30: Мижозларга берилган кредит ва лизинглар, соф | C30: =+'Bank Assets Analysis'!C30-'Bank Assets Analysis'!D30 -> 32955132 | D30: =+'Bank Assets Analysis'!E30-'Bank Assets Analysis'!F30 -> 17779505 | E30: =+'Bank Assets Analysis'!G30-'Bank Assets Analysis'!H30 -> 225434796 | F30: =+'Bank Assets Analysis'!I30-'Bank Assets Analysis'!J30 -> 569182032 | G30: =+'Bank Assets Analysis'!K30-'Bank Assets Analysis'!L30 -> 824158294 | H30: =+'Bank Assets Analysis'!M30-'Bank Assets Analysis'!N30 -> 1415540426 | I30: =+'Bank Assets Analysis'!O30-'Bank Assets Analysis'!P30 -> 1717312350 | J30: =+'Bank Assets Analysis'!Q30-'Bank Assets Analysis'!R30 -> 4027984739 | K30: =+C30+D30+E30+F30+G30+H30+I30+J30 -> 8830347274 | L30: 0.5 | M30: =+D30+E30 -> 243214301 | N30: =+M30*L30 -> 1.2160715e+08
A31: 9.1 | B31: шу жумладан, жисмоний шахсларга берилган кредит ва лизинглар | C31: =+'Bank Assets Analysis'!C31-'Bank Assets Analysis'!D31 -> 12195138 | D31: =+'Bank Assets Analysis'!E31-'Bank Assets Analysis'!F31 -> 17112476 | E31: =+'Bank Assets Analysis'!G31-'Bank Assets Analysis'!H31 -> 62264947 | F31: =+'Bank Assets Analysis'!I31-'Bank Assets Analysis'!J31 -> 169210038 | G31: =+'Bank Assets Analysis'!K31-'Bank Assets Analysis'!L31 -> 245989398 | H31: =+'Bank Assets Analysis'!M31-'Bank Assets Analysis'!N31 -> 486153885 | I31: =+'Bank Assets Analysis'!O31-'Bank Assets Analysis'!P31 -> 850968665 | J31: =+'Bank Assets Analysis'!Q31-'Bank Assets Analysis'!R31 -> 2204833140 | K31: =+C31+D31+E31+F31+G31+H31+I31+J31 -> 4048727687 | L31: 0 | M31: =+D31+E31 -> 79377423 | N31: =+M31*L31 -> 0
A32: 10 | B32: Суд ёки ижро иши юритиш жараёнидаги кредитлар ва лизинг, соф | C32: =+'Bank Assets Analysis'!C32-'Bank Assets Analysis'!D32 -> 103169910 | D32: =+'Bank Assets Analysis'!E32-'Bank Assets Analysis'!F32 -> 0 | E32: =+'Bank Assets Analysis'!G32-'Bank Assets Analysis'!H32 -> 0 | F32: =+'Bank Assets Analysis'!I32-'Bank Assets Analysis'!J32 -> 0 | G32: =+'Bank Assets Analysis'!K32-'Bank Assets Analysis'!L32 -> 0 | H32: =+'Bank Assets Analysis'!M32-'Bank Assets Analysis'!N32 -> 0 | I32: =+'Bank Assets Analysis'!O32-'Bank Assets Analysis'!P32 -> 0 | J32: =+'Bank Assets Analysis'!Q32-'Bank Assets Analysis'!R32 -> 0 | K32: =+C32+D32+E32+F32+G32+H32+I32+J32 -> 103169910 | L32: 0 | M32: =+D32+E32 -> 0 | N32: =+M32*L32 -> 0
A33: 11 | B33: Инвестициялар, соф | C33: =+'Bank Assets Analysis'!C33-'Bank Assets Analysis'!D33 -> 0 | D33: =+'Bank Assets Analysis'!E33-'Bank Assets Analysis'!F33 -> 0 | E33: =+'Bank Assets Analysis'!G33-'Bank Assets Analysis'!H33 -> 0 | F33: =+'Bank Assets Analysis'!I33-'Bank Assets Analysis'!J33 -> 0 | G33: =+'Bank Assets Analysis'!K33-'Bank Assets Analysis'!L33 -> 0 | H33: =+'Bank Assets Analysis'!M33-'Bank Assets Analysis'!N33 -> 0 | I33: =+'Bank Assets Analysis'!O33-'Bank Assets Analysis'!P33 -> 0 | J33: =+'Bank Assets Analysis'!Q33-'Bank Assets Analysis'!R33 -> 391688858 | K33: =+C33+D33+E33+F33+G33+H33+I33+J33 -> 391688858 | L33: 0 | M33: =+D33+E33 -> 0 | N33: =+M33*L33 -> 0
A34: 12 | B34: РЕПО битимлари бўйича сотиб олинган қимматли қоғозлар | C34: =+C35+C36 -> 0 | D34: =+D35+D36 -> 0 | E34: =+E35+E36 -> 0 | F34: =+F35+F36 -> 0 | G34: =+G35+G36 -> 0 | H34: =+H35+H36 -> 0 | I34: =+I35+I36 -> 0 | J34: =+J35+J36 -> 0 | K34: =+C34+D34+E34+F34+G34+H34+I34+J34 -> 0 | L34: 0 | M34: =+D34+E34 -> 0 | N34: =+M34*L34 -> 0
A35: 12.1 | B35: РЕПО битимлари бўйича сотиб олинган юқори ликвидли қимматли қоғозлар | C35: =+'Bank Assets Analysis'!C35-'Bank Assets Analysis'!D35 -> 0 | D35: =+'Bank Assets Analysis'!E35-'Bank Assets Analysis'!F35 -> 0 | E35: =+'Bank Assets Analysis'!G35-'Bank Assets Analysis'!H35 -> 0 | F35: =+'Bank Assets Analysis'!I35-'Bank Assets Analysis'!J35 -> 0 | G35: =+'Bank Assets Analysis'!K35-'Bank Assets Analysis'!L35 -> 0 | H35: =+'Bank Assets Analysis'!M35-'Bank Assets Analysis'!N35 -> 0 | I35: =+'Bank Assets Analysis'!O35-'Bank Assets Analysis'!P35 -> 0 | J35: =+'Bank Assets Analysis'!Q35-'Bank Assets Analysis'!R35 -> 0 | K35: =+C35+D35+E35+F35+G35+H35+I35+J35 -> 0 | L35: 1 | M35: =+K35 -> 0 | N35: =+M35*L35 -> 0
A36: 12.2 | B36: РЕПО битимлари бўйича сотиб олинган бошқа қимматли қоғозлар | C36: =+'Bank Assets Analysis'!C36-'Bank Assets Analysis'!D36 -> 0 | D36: =+'Bank Assets Analysis'!E36-'Bank Assets Analysis'!F36 -> 0 | E36: =+'Bank Assets Analysis'!G36-'Bank Assets Analysis'!H36 -> 0 | F36: =+'Bank Assets Analysis'!I36-'Bank Assets Analysis'!J36 -> 0 | G36: =+'Bank Assets Analysis'!K36-'Bank Assets Analysis'!L36 -> 0 | H36: =+'Bank Assets Analysis'!M36-'Bank Assets Analysis'!N36 -> 0 | I36: =+'Bank Assets Analysis'!O36-'Bank Assets Analysis'!P36 -> 0 | J36: =+'Bank Assets Analysis'!Q36-'Bank Assets Analysis'!R36 -> 0 | K36: =+C36+D36+E36+F36+G36+H36+I36+J36 -> 0 | L36: 0 | N36: =+M36*L36 -> 0
A37: 13 | B37: Aсосий воситалар, соф | C37: =+'Bank Assets Analysis'!C37-'Bank Assets Analysis'!D37 -> 0 | D37: =+'Bank Assets Analysis'!E37-'Bank Assets Analysis'!F37 -> 0 | E37: =+'Bank Assets Analysis'!G37-'Bank Assets Analysis'!H37 -> 0 | F37: =+'Bank Assets Analysis'!I37-'Bank Assets Analysis'!J37 -> 0 | G37: =+'Bank Assets Analysis'!K37-'Bank Assets Analysis'!L37 -> 0 | H37: =+'Bank Assets Analysis'!M37-'Bank Assets Analysis'!N37 -> 0 | I37: =+'Bank Assets Analysis'!O37-'Bank Assets Analysis'!P37 -> 0 | J37: =+'Bank Assets Analysis'!Q37-'Bank Assets Analysis'!R37 -> 2578342217 | K37: =+C37+D37+E37+F37+G37+H37+I37+J37 -> 2578342217 | L37: 0 | N37: =+M37*L37 -> 0
A38: 14 | B38: Банкнинг бошқа хусусий мулклари, соф | C38: =+'Bank Assets Analysis'!C38-'Bank Assets Analysis'!D38 -> 119934391 | D38: =+'Bank Assets Analysis'!E38-'Bank Assets Analysis'!F38 -> 0 | E38: =+'Bank Assets Analysis'!G38-'Bank Assets Analysis'!H38 -> 1494238 | F38: =+'Bank Assets Analysis'!I38-'Bank Assets Analysis'!J38 -> 2790886 | G38: =+'Bank Assets Analysis'!K38-'Bank Assets Analysis'!L38 -> 4633427 | H38: =+'Bank Assets Analysis'!M38-'Bank Assets Analysis'!N38 -> 8254794 | I38: =+'Bank Assets Analysis'!O38-'Bank Assets Analysis'!P38 -> 14671150 | J38: =+'Bank Assets Analysis'!Q38-'Bank Assets Analysis'!R38 -> 196732376 | K38: =+C38+D38+E38+F38+G38+H38+I38+J38 -> 348511262 | L38: 0 | N38: =+M38*L38 -> 0
A39: 15 | B39: Ҳосилавий инструментларнинг ревальвацияси натижасида ўзлаштирилмаган фойда | C39: =+'Bank Assets Analysis'!C39-'Bank Assets Analysis'!D39 -> 0 | D39: =+'Bank Assets Analysis'!E39-'Bank Assets Analysis'!F39 -> 0 | E39: =+'Bank Assets Analysis'!G39-'Bank Assets Analysis'!H39 -> 0 | F39: =+'Bank Assets Analysis'!I39-'Bank Assets Analysis'!J39 -> 0 | G39: =+'Bank Assets Analysis'!K39-'Bank Assets Analysis'!L39 -> 0 | H39: =+'Bank Assets Analysis'!M39-'Bank Assets Analysis'!N39 -> 0 | I39: =+'Bank Assets Analysis'!O39-'Bank Assets Analysis'!P39 -> 0 | J39: =+'Bank Assets Analysis'!Q39-'Bank Assets Analysis'!R39 -> 1561 | K39: =+C39+D39+E39+F39+G39+H39+I39+J39 -> 1561 | L39: 0 | N39: =+M39*L39 -> 0
A40: 16 | B40: Валюта савдоси ва валюта позициялари | K40: =+C40+D40+E40+F40+G40+H40+I40+J40 -> 0 | L40: 0 | N40: =+M40*L40 -> 0
A41: 17 | B41: Транзит ҳисобварақлари | C41: =+'Bank Assets Analysis'!C41-'Bank Assets Analysis'!D41 -> 0 | D41: =+'Bank Assets Analysis'!E41-'Bank Assets Analysis'!F41 -> 0 | E41: =+'Bank Assets Analysis'!G41-'Bank Assets Analysis'!H41 -> 0 | F41: =+'Bank Assets Analysis'!I41-'Bank Assets Analysis'!J41 -> 0 | G41: =+'Bank Assets Analysis'!K41-'Bank Assets Analysis'!L41 -> 0 | H41: =+'Bank Assets Analysis'!M41-'Bank Assets Analysis'!N41 -> 0 | I41: =+'Bank Assets Analysis'!O41-'Bank Assets Analysis'!P41 -> 0 | J41: =+'Bank Assets Analysis'!Q41-'Bank Assets Analysis'!R41 -> 0 | K41: =+C41+D41+E41+F41+G41+H41+I41+J41 -> 0 | L41: 0 | N41: =+M41*L41 -> 0
A42: 18 | B42: Олиниши лозим бўлган ҳисобланган фоизлар | C42: =+'Bank Assets Analysis'!C42-'Bank Assets Analysis'!D42 -> 51170600 | D42: =+'Bank Assets Analysis'!E42-'Bank Assets Analysis'!F42 -> 11581374 | E42: =+'Bank Assets Analysis'!G42-'Bank Assets Analysis'!H42 -> 123286489 | F42: =+'Bank Assets Analysis'!I42-'Bank Assets Analysis'!J42 -> 15459284 | G42: =+'Bank Assets Analysis'!K42-'Bank Assets Analysis'!L42 -> 701443 | H42: =+'Bank Assets Analysis'!M42-'Bank Assets Analysis'!N42 -> 10606132 | I42: =+'Bank Assets Analysis'!O42-'Bank Assets Analysis'!P42 -> 61409867 | J42: =+'Bank Assets Analysis'!Q42-'Bank Assets Analysis'!R42 -> 13777435 | K42: =+C42+D42+E42+F42+G42+H42+I42+J42 -> 287992624 | L42: 0.5 | M42: =+D42+E42 -> 134867863 | N42: =+M42*L42 -> 67433932
A43: 18.1 | B43: Бош офис/филиалдан олиниши лозим бўлган ҳисобланган фоизлар | C43: =+'Bank Assets Analysis'!C43-'Bank Assets Analysis'!D43 -> 0 | D43: =+'Bank Assets Analysis'!E43-'Bank Assets Analysis'!F43 -> 0 | E43: =+'Bank Assets Analysis'!G43-'Bank Assets Analysis'!H43 -> 0 | F43: =+'Bank Assets Analysis'!I43-'Bank Assets Analysis'!J43 -> 0 | G43: =+'Bank Assets Analysis'!K43-'Bank Assets Analysis'!L43 -> 0 | H43: =+'Bank Assets Analysis'!M43-'Bank Assets Analysis'!N43 -> 0 | I43: =+'Bank Assets Analysis'!O43-'Bank Assets Analysis'!P43 -> 0 | J43: =+'Bank Assets Analysis'!Q43-'Bank Assets Analysis'!R43 -> 0 | K43: =+C43+D43+E43+F43+G43+H43+I43+J43 -> 0 | L43: 1 | M43: =+D43+E43 -> 0 | N43: =+M43*L43 -> 0
A44: 18.2 | B44: Бошқа банклардан олиниши лозим бўлган ҳисобланган фоизлар | C44: =+'Bank Assets Analysis'!C44-'Bank Assets Analysis'!D44 -> 0 | D44: =+'Bank Assets Analysis'!E44-'Bank Assets Analysis'!F44 -> 0 | E44: =+'Bank Assets Analysis'!G44-'Bank Assets Analysis'!H44 -> 0 | F44: =+'Bank Assets Analysis'!I44-'Bank Assets Analysis'!J44 -> 0 | G44: =+'Bank Assets Analysis'!K44-'Bank Assets Analysis'!L44 -> 0 | H44: =+'Bank Assets Analysis'!M44-'Bank Assets Analysis'!N44 -> 0 | I44: =+'Bank Assets Analysis'!O44-'Bank Assets Analysis'!P44 -> 0 | J44: =+'Bank Assets Analysis'!Q44-'Bank Assets Analysis'!R44 -> 0 | K44: =+C44+D44+E44+F44+G44+H44+I44+J44 -> 0 | L44: 1 | M44: =+D44+E44 -> 0 | N44: =+M44*L44 -> 0
A45: 19 | B45: Бошқа активлар | C45: =+'Bank Assets Analysis'!C45-'Bank Assets Analysis'!D45 -> 1355786225 | D45: =+'Bank Assets Analysis'!E45-'Bank Assets Analysis'!F45 -> 17286 | E45: =+'Bank Assets Analysis'!G45-'Bank Assets Analysis'!H45 -> 237921 | F45: =+'Bank Assets Analysis'!I45-'Bank Assets Analysis'!J45 -> 260163 | G45: =+'Bank Assets Analysis'!K45-'Bank Assets Analysis'!L45 -> 565224 | H45: =+'Bank Assets Analysis'!M45-'Bank Assets Analysis'!N45 -> 491433 | I45: =+'Bank Assets Analysis'!O45-'Bank Assets Analysis'!P45 -> 2341999 | J45: =+'Bank Assets Analysis'!Q45-'Bank Assets Analysis'!R45 -> 15175556 | K45: =+C45+D45+E45+F45+G45+H45+I45+J45 -> 1374875807 | L45: 0 | N45: =+M45*L45 -> 0
A46: 20 | B46: Гаровга қўйилган юқори ликвидли активлар, 4.1.1. бундан мустасно | C46: =+'Bank Assets Analysis'!C46-'Bank Assets Analysis'!D46 -> 0 | D46: =+'Bank Assets Analysis'!E46-'Bank Assets Analysis'!F46 -> 0 | E46: =+'Bank Assets Analysis'!G46-'Bank Assets Analysis'!H46 -> 0 | F46: =+'Bank Assets Analysis'!I46-'Bank Assets Analysis'!J46 -> 0 | G46: =+'Bank Assets Analysis'!K46-'Bank Assets Analysis'!L46 -> 0 | H46: =+'Bank Assets Analysis'!M46-'Bank Assets Analysis'!N46 -> 0 | I46: =+'Bank Assets Analysis'!O46-'Bank Assets Analysis'!P46 -> 0 | J46: =+'Bank Assets Analysis'!Q46-'Bank Assets Analysis'!R46 -> 0 | K46: =+C46+D46+E46+F46+G46+H46+I46+J46 -> 0 | L46: 1 | M46: =+C46+D46+E46 -> 0 | N46: =+M46*L46 -> 0
A47: 21 | B47: ЖAМИ АКТИВЛАР | C47: =SUM(C6:C45)-C9-C13-C17-C18-C31-C34 -> 3833977429 | D47: =SUM(D6:D45)-D9-D13-D17-D18-D31-D34 -> 29378165 | E47: =SUM(E6:E45)-E9-E13-E17-E18-E31-E34 -> 589901273 | F47: =SUM(F6:F45)-F9-F13-F17-F18-F31-F34 -> 1049522876 | G47: =SUM(G6:G45)-G9-G13-G17-G18-G31-G34 -> 854467748 | H47: =SUM(H6:H45)-H9-H13-H17-H18-H31-H34 -> 1619442509 | I47: =SUM(I6:I45)-I9-I13-I17-I18-I31-I34 -> 2762168820 | J47: =SUM(J6:J45)-J9-J13-J17-J18-J31-J34 -> 7603570586 | K47: =SUM(C47:J47) -> 18342429406 | M47: =SUM(M6:M45)-M9-M34 -> 5583653404 | N47: =+N12+N13+N14+N15+N16+N18+N26+N27+N28+N29+N30+N42+N46+N25+(K23*0.2)+N43+N44 -> 1142913859 | O47: =+Balance!D47 -> 18342429406 | P47: =+K47-O47 -> 0 | R47: =+O47 -> 18342429406 | S47: =+K47-R47 -> 0
B48: Балансдан ташқари мажбуриятлар
A49: 1 | B49: Банкнинг кредит ва лизинг бериш бўйича мажбуриятлари (91809) | C49: =+'Bank Assets Analysis'!C49-'Bank Assets Analysis'!D49 -> 128630 | D49: =+'Bank Assets Analysis'!E49-'Bank Assets Analysis'!F49 -> 59406361 | E49: =+'Bank Assets Analysis'!G49-'Bank Assets Analysis'!H49 -> 0 | F49: =+'Bank Assets Analysis'!I49-'Bank Assets Analysis'!J49 -> 50000 | G49: =+'Bank Assets Analysis'!K49-'Bank Assets Analysis'!L49 -> 1302561 | H49: =+'Bank Assets Analysis'!M49-'Bank Assets Analysis'!N49 -> 106662576 | I49: =+'Bank Assets Analysis'!O49-'Bank Assets Analysis'!P49 -> 70727012 | J49: =+'Bank Assets Analysis'!Q49-'Bank Assets Analysis'!R49 -> 198777738 | K49: =+C49+D49+E49+F49+G49+H49+I49+J49 -> 437054878
B50: шундан, ХМИ, Молия вазирлиги, фондлар ва бошқа ташкилотларнинг депозитлари билан таъминланган | C50: =+'Bank Assets Analysis'!C50-'Bank Assets Analysis'!D50 -> 0 | D50: =+'Bank Assets Analysis'!E50-'Bank Assets Analysis'!F50 -> 0 | E50: =+'Bank Assets Analysis'!G50-'Bank Assets Analysis'!H50 -> 0 | F50: =+'Bank Assets Analysis'!I50-'Bank Assets Analysis'!J50 -> 0 | G50: =+'Bank Assets Analysis'!K50-'Bank Assets Analysis'!L50 -> 0 | H50: =+'Bank Assets Analysis'!M50-'Bank Assets Analysis'!N50 -> 0 | I50: =+'Bank Assets Analysis'!O50-'Bank Assets Analysis'!P50 -> 0 | J50: =+'Bank Assets Analysis'!Q50-'Bank Assets Analysis'!R50 -> 0 | K50: =+C50+D50+E50+F50+G50+H50+I50+J50 -> 0
A51: 2 | B51: Кафолат ва кафилликлар (90993) | C51: =+'Bank Assets Analysis'!C51-'Bank Assets Analysis'!D51 -> 0 | D51: =+'Bank Assets Analysis'!E51-'Bank Assets Analysis'!F51 -> 0 | E51: =+'Bank Assets Analysis'!G51-'Bank Assets Analysis'!H51 -> 1154145 | F51: =+'Bank Assets Analysis'!I51-'Bank Assets Analysis'!J51 -> 7672683 | G51: =+'Bank Assets Analysis'!K51-'Bank Assets Analysis'!L51 -> 25766143 | H51: =+'Bank Assets Analysis'!M51-'Bank Assets Analysis'!N51 -> 0 | I51: =+'Bank Assets Analysis'!O51-'Bank Assets Analysis'!P51 -> 0 | J51: =+'Bank Assets Analysis'!Q51-'Bank Assets Analysis'!R51 -> 0 | K51: =+C51+D51+E51+F51+G51+H51+I51+J51 -> 34592971
B52: - шундан, алоҳида блокланган ҳисобварақлардаги депозитлар билан таъминланган кафолат ва кафилликлар | C52: =+'Bank Assets Analysis'!C52-'Bank Assets Analysis'!D52 -> 0 | D52: =+'Bank Assets Analysis'!E52-'Bank Assets Analysis'!F52 -> 0 | E52: =+'Bank Assets Analysis'!G52-'Bank Assets Analysis'!H52 -> 0 | F52: =+'Bank Assets Analysis'!I52-'Bank Assets Analysis'!J52 -> 0 | G52: =+'Bank Assets Analysis'!K52-'Bank Assets Analysis'!L52 -> 0 | H52: =+'Bank Assets Analysis'!M52-'Bank Assets Analysis'!N52 -> 0 | I52: =+'Bank Assets Analysis'!O52-'Bank Assets Analysis'!P52 -> 0 | J52: =+'Bank Assets Analysis'!Q52-'Bank Assets Analysis'!R52 -> 0 | K52: =+C52+D52+E52+F52+G52+H52+I52+J52 -> 0
A53: 3 | B53: Аккредитивлар (90908-90958) | C53: =+'Bank Assets Analysis'!C53-'Bank Assets Analysis'!D53 -> 0 | D53: =+'Bank Assets Analysis'!E53-'Bank Assets Analysis'!F53 -> 0 | E53: =+'Bank Assets Analysis'!G53-'Bank Assets Analysis'!H53 -> 0 | F53: =+'Bank Assets Analysis'!I53-'Bank Assets Analysis'!J53 -> 0 | G53: =+'Bank Assets Analysis'!K53-'Bank Assets Analysis'!L53 -> 0 | H53: =+'Bank Assets Analysis'!M53-'Bank Assets Analysis'!N53 -> 0 | I53: =+'Bank Assets Analysis'!O53-'Bank Assets Analysis'!P53 -> 0 | J53: =+'Bank Assets Analysis'!Q53-'Bank Assets Analysis'!R53 -> 0 | K53: =+C53+D53+E53+F53+G53+H53+I53+J53 -> 0
B54: - шундан, 22602 баланс ҳисобварағида депозит билан таъминланганлар кўрсатилади | C54: =+'Bank Assets Analysis'!C54-'Bank Assets Analysis'!D54 -> 0 | D54: =+'Bank Assets Analysis'!E54-'Bank Assets Analysis'!F54 -> 0 | E54: =+'Bank Assets Analysis'!G54-'Bank Assets Analysis'!H54 -> 0 | F54: =+'Bank Assets Analysis'!I54-'Bank Assets Analysis'!J54 -> 0 | G54: =+'Bank Assets Analysis'!K54-'Bank Assets Analysis'!L54 -> 0 | H54: =+'Bank Assets Analysis'!M54-'Bank Assets Analysis'!N54 -> 0 | I54: =+'Bank Assets Analysis'!O54-'Bank Assets Analysis'!P54 -> 0 | J54: =+'Bank Assets Analysis'!Q54-'Bank Assets Analysis'!R54 -> 0 | K54: =+C54+D54+E54+F54+G54+H54+I54+J54 -> 0
B56: Бошқарув Раис имзоси:
B58: Бош бухгалтер имзоси:
O59: Ликвидные активы | P59: =+N47 -> 1142913859
O60: Высоко-ликвидные активы | P60: =+N6+N7+N10+N11+N19+N20+N21+N22+N24+N35-N46-N18 -> 3370861229
O61: Чистый отток за 30 дней | P61: =+P63-P65 -> 1.9538914e+09
O63: всего отток | P63: ='Bank Liabilities Analysis (нац)'!M43+P64 -> 3.0968053e+09
O64: в том числе отток по внебалансу | P64: =+'Liquidity Analysis'!D41 -> 70747177
O65: Приток по положению | P65: =IF(P59>(P63*0.75),P63*0.75,P59) -> 1142913859

Sheet Bank Liabilities Analysis
A1: БАНК МАЖБУРИЯТЛАРИ ТАҲЛИЛИ | W1: 18-жадвал
B2: =Balance!B3 -> Банк номи | V2: =+Balance!D3 -> 45657 | X2: минг сўмда
A3: № | B3: Кўрсаткичлар | C3: Сўндириш муддати (кунларда) | S3: Жами | T3: шундан, | V3: Ликвидлиликни қоплаш меёри ҳисоб китоби
C4: Муддатсиз | E4: 1 дан 7 гача | G4: 8 дан 30 гача | I4: 31 дан 90 гача | K4: 91 дан 180 гача | M4: 181 дан 365 гача | O4: 366 дан 730 гача | Q4: 2 йилдан ортиқ
C5: Сумма | D5: шундан, хорижий валютада (сўм экв.) | E5: Сумма | F5: шундан, хорижий валютада (сўм экв.) | G5: Сумма | H5: шундан, хорижий валютада (сўм экв.) | I5: Сумма | J5: шундан, хорижий валютада (сўм экв.) | K5: Сумма | L5: шундан, хорижий валютада (сўм экв.) | M5: Сумма | N5: шундан, хорижий валютада (сўм экв.) | O5: Сумма | P5: шундан, хорижий валютада (сўм экв.) | Q5: Сумма | R5: шундан, хорижий валютада (сўм экв.) | T5: миллий валютада | U5: хорижий валютада (сўм экв.) | V5: Коэффициент | W5: 30 кунлик чиқим суммаси | X5: 30 кунлик чиқим суммаси (хорижий валютада)
A6: 1. | B6: ДЕПОЗИТЛАР
A7: 1.1 | B7: Талаб қилиб олингунча депозитлар | C7: =SUM(C8:C11) -> 2521364958 | D7: =SUM(D8:D11) -> 344643238 | E7: =SUM(E8:E11) -> 0 | F7: =SUM(F8:F11) -> 0 | G7: =SUM(G8:G11) -> 0 | H7: =SUM(H8:H11) -> 0 | I7: =SUM(I8:I11) -> 0 | J7: =SUM(J8:J11) -> 0 | ... R7: =SUM(R8:R11) -> 0 | S7: =+C7+E7+G7+I7+K7+M7+O7+Q7 -> 2521364958 | T7: =+S7-U7 -> 2176721720 | U7: =+D7+F7+H7+J7+L7+N7+P7+R7 -> 344643238
A8: 1.1.1 | B8: Aҳолининг талаб қилиб олингунча омонатлари | C8: 79456017 | D8: 49004778 | E8: 0 | F8: 0 | G8: 0 | H8: 0 | I8: 0 | J8: 0 | K8: 0 | L8: 0 | M8: 0 | N8: 0 | O8: 0 | P8: 0 | Q8: 0 | R8: 0 | S8: =+C8+E8+G8+I8+K8+M8+O8+Q8 -> 79456017 | T8: =+S8-U8 -> 30451239 | U8: =+D8+F8+H8+J8+L8+N8+P8+R8 -> 49004778
A9: 1.1.2 | B9: Кредит таъминоти сифатида жалб этилган aҳоли омонатлари | C9: 229780 | D9: 0 | E9: 0 | F9: 0 | G9: 0 | H9: 0 | I9: 0 | J9: 0 | K9: 0 | L9: 0 | M9: 0 | N9: 0 | O9: 0 | P9: 0 | Q9: 0 | R9: 0 | S9: =+C9+E9+G9+I9+K9+M9+O9+Q9 -> 229780 | T9: =+S9-U9 -> 229780 | U9: =+D9+F9+H9+J9+L9+N9+P9+R9 -> 0
A10: 1.1.3 | B10: Кредит таъминоти сифатида жалб этилган бошқа депозитлар | C10: 0 | D10: 0 | E10: 0 | F10: 0 | G10: 0 | H10: 0 | I10: 0 | J10: 0 | K10: 0 | L10: 0 | M10: 0 | N10: 0 | O10: 0 | P10: 0 | Q10: 0 | R10: 0 | S10: =+C10+E10+G10+I10+K10+M10+O10+Q10 -> 0 | T10: =+S10-U10 -> 0 | U10: =+D10+F10+H10+J10+L10+N10+P10+R10 -> 0
A11: 1.1.4 | B11: Талаб қилиб олингунча бошқа депозитлар | C11: 2441679161 | D11: 295638460 | E11: 0 | F11: 0 | G11: 0 | H11: 0 | I11: 0 | J11: 0 | K11: 0 | L11: 0 | M11: 0 | N11: 0 | O11: 0 | P11: 0 | Q11: 0 | R11: 0 | S11: =+C11+E11+G11+I11+K11+M11+O11+Q11 -> 2441679161 | T11: =+S11-U11 -> 2146040701 | U11: =+D11+F11+H11+J11+L11+N11+P11+R11 -> 295638460
A12: 1.2 | B12: Муддатли депозитлар | C12: 0 | D12: 0 | E12: 73197768 | F12: 862265 | G12: 165588075 | H12: 1029418 | I12: 294525052 | J12: 9173170 | K12: 1437789058 | L12: 24651112 | M12: 2655221338 | N12: 281718877 | O12: 3808959552 | P12: 313144086 | Q12: 1326593812 | R12: 240579338 | S12: =+C12+E12+G12+I12+K12+M12+O12+Q12 -> 9761874655 | T12: =+S12-U12 -> 8890716389 | U12: =+D12+F12+H12+J12+L12+N12+P12+R12 -> 871158266
A13: 1.2.1 | B13: Аҳоли омонатлари | C13: 0 | D13: 0 | E13: 17565074 | F13: 487571 | G13: 39351409 | H13: 1029418 | I13: 82009916 | J13: 9049133 | K13: 836640788 | L13: 21420992 | M13: 1019225833 | N13: 55344841 | O13: 1875603924 | P13: 95455044 | Q13: 35522527 | R13: 0 | S13: =+C13+E13+G13+I13+K13+M13+O13+Q13 -> 3905919471 | T13: =+S13-U13 -> 3723132472 | U13: =+D13+F13+H13+J13+L13+N13+P13+R13 -> 182786999
A14: 1.2.2 | B14: Чиқарилган депозит сертификатлари | C14: 0 | D14: 0 | E14: 0 | F14: 0 | G14: 0 | H14: 0 | I14: 0 | J14: 0 | K14: 0 | L14: 0 | M14: 0 | N14: 0 | O14: 0 | P14: 0 | Q14: 0 | R14: 0 | S14: =+C14+E14+G14+I14+K14+M14+O14+Q14 -> 0 | T14: =+S14-U14 -> 0 | U14: =+D14+F14+H14+J14+L14+N14+P14+R14 -> 0
A15: 1.3 | B15: Мижозларнинг бошқа депозитлари | C15: =SUM(C16:C19) -> 1438671891 | D15: =SUM(D16:D19) -> 195205021 | E15: =SUM(E16:E19) -> 1162843 | F15: =SUM(F16:F19) -> 1162843 | G15: =SUM(G16:G19) -> 0 | H15: =SUM(H16:H19) -> 0 | I15: =SUM(I16:I19) -> 793059 | J15: =SUM(J16:J19) -> 793059 | ... R15: =SUM(R16:R19) -> 0 | S15: =+C15+E15+G15+I15+K15+M15+O15+Q15 -> 1531435201 | T15: =+S15-U15 -> 1243466870 | U15: =+D15+F15+H15+J15+L15+N15+P15+R15 -> 287968331
A16: 1.3.1 | B16: Жисмоний шахсларнинг банк пластик карталаридаги маблағлари | C16: 1243732354 | D16: 171728599 | E16: 0 | F16: 0 | G16: 0 | H16: 0 | I16: 0 | J16: 0 | K16: 0 | L16: 0 | M16: 0 | N16: 0 | O16: 0 | P16: 0 | Q16: 0 | R16: 0 | S16: =+C16+E16+G16+I16+K16+M16+O16+Q16 -> 1243732354 | T16: =+S16-U16 -> 1072003755 | U16: =+D16+F16+H16+J16+L16+N16+P16+R16 -> 171728599
A17: 1.3.2 | B17: Бошқа мижозларнинг банк пластик карталаридаги маблағлари | C17: 11141274 | D17: 1051081 | E17: 0 | F17: 0 | G17: 0 | H17: 0 | I17: 0 | J17: 0 | K17: 0 | L17: 0 | M17: 0 | N17: 0 | O17: 0 | P17: 0 | Q17: 0 | R17: 0 | S17: =+C17+E17+G17+I17+K17+M17+O17+Q17 -> 11141274 | T17: =+S17-U17 -> 10090193 | U17: =+D17+F17+H17+J17+L17+N17+P17+R17 -> 1051081
A18: 1.3.3 | B18: Мижозларнинг аккредитив бўйича депозитлари | C18: 0 | D18: 0 | E18: 1162843 | F18: 1162843 | G18: 0 | H18: 0 | I18: 793059 | J18: 793059 | K18: 0 | L18: 0 | M18: 37762040 | N18: 37762040 | O18: 53045368 | P18: 53045368 | Q18: 0 | R18: 0 | S18: =+C18+E18+G18+I18+K18+M18+O18+Q18 -> 92763310 | T18: =+S18-U18 -> 0 | U18: =+D18+F18+H18+J18+L18+N18+P18+R18 -> 92763310
A19: 1.3.4 | B19: Бошқалар | C19: 183798263 | D19: 22425341 | E19: 0 | F19: 0 | G19: 0 | H19: 0 | I19: 0 | J19: 0 | K19: 0 | L19: 0 | M19: 0 | N19: 0 | O19: 0 | P19: 0 | Q19: 0 | R19: 0 | S19: =+C19+E19+G19+I19+K19+M19+O19+Q19 -> 183798263 | T19: =+S19-U19 -> 161372922 | U19: =+D19+F19+H19+J19+L19+N19+P19+R19 -> 22425341
A20: 1.4 | B20: Жами депозитлар | C20: =+C7+C12+C15 -> 3960036849 | D20: =+D7+D12+D15 -> 539848259 | E20: =+E7+E12+E15 -> 74360611 | F20: =+F7+F12+F15 -> 2025108 | G20: =+G7+G12+G15 -> 165588075 | H20: =+H7+H12+H15 -> 1029418 | I20: =+I7+I12+I15 -> 295318111 | J20: =+J7+J12+J15 -> 9966229 | ... R20: =+R7+R12+R15 -> 240579338 | S20: =+C20+E20+G20+I20+K20+M20+O20+Q20 -> 13814674814 | T20: =+S20-U20 -> 12310904979 | U20: =+D20+F20+H20+J20+L20+N20+P20+R20 -> 1503769835 | V20: 0.15 | W20: =+X20+'Bank Liabilities Analysis (нац)'!M21 -> 2.0373159e+09 | X20: =(U20-(J46+L46+N46+P46+R46))*V20 -> 1.9068018e+08 | Y20: =+'Deposits by Client'!C22 -> 13814674814 | Z20: =+Y20-AA20 -> 12310904979 | AA20: =+'Deposits by Client'!D22 -> 1503769835
A21: 2. | B21: Марказий банкка тўланиши лозим бўлган маблағлар | C21: 424511118 | D21: 0 | E21: 0 | F21: 0 | G21: 0 | H21: 0 | I21: 0 | J21: 0 | K21: 0 | L21: 0 | M21: 0 | N21: 0 | O21: 0 | P21: 0 | Q21: 0 | R21: 0 | S21: =+C21+E21+G21+I21+K21+M21+O21+Q21 -> 424511118 | T21: =+S21-U21 -> 424511118 | U21: =+D21+F21+H21+J21+L21+N21+P21+R21 -> 0 | V21: 1 | W21: =(C21+E21+G21-C22-E22-G22)*V21 -> 0 | X21: =(D21+F21+H21-D22-F22-H22)*V21 -> 0 | Y21: =+S20-Y20 -> 0 | Z21: =+T20-Z20 -> 0 | AA21: =+U20-AA20 -> 0
A22: 2.1. | B22: шу жумладан, Марказий банкка тўланиши лозим бўлган маблағлар -Тезкор тўловлар ҳамда клиринг тизимлари | C22: 424511118 | D22: 0 | E22: 0 | F22: 0 | G22: 0 | H22: 0 | I22: 0 | J22: 0 | K22: 0 | L22: 0 | M22: 0 | N22: 0 | O22: 0 | P22: 0 | Q22: 0 | R22: 0 | S22: =+C22+E22+G22+I22+K22+M22+O22+Q22 -> 424511118 | T22: =+S22-U22 -> 424511118 | U22: =+D22+F22+H22+J22+L22+N22+P22+R22 -> 0
A23: 3. | B23: Бошқа банклар ва молиявий ташкилотларга тўланиши лозим бўлган маблағлар | C23: =SUM(C24:C28)-C25 -> 224996623 | D23: =SUM(D24:D28)-D25 -> 219258653 | E23: =SUM(E24:E28)-E25 -> 0 | F23: =SUM(F24:F28)-F25 -> 0 | G23: =SUM(G24:G28)-G25 -> 249512 | H23: =SUM(H24:H28)-H25 -> 0 | I23: =SUM(I24:I28)-I25 -> 180000000 | J23: =SUM(J24:J28)-J25 -> 0 | ... R23: =SUM(R24:R28)-R25 -> 0 | S23: =+C23+E23+G23+I23+K23+M23+O23+Q23 -> 1328179724 | T23: =+S23-U23 -> 592101871 | U23: =+D23+F23+H23+J23+L23+N23+P23+R23 -> 736077853
A24: 3.1 | B24: Бошқа банкларнинг вакиллик ҳисобварақларига тўланиши лозим бўлган маблағлар | C24: 219824692 | D24: 219236815 | S24: =+C24 -> 219824692 | T24: =+S24-U24 -> 587877 | U24: =+D24 -> 219236815 | V24: 1 | W24: =X24+'Bank Liabilities Analysis (нац)'!M25 -> 158311817 | X24: =(U24-U25)*V24 -> 157723940
A25: 3.1.1 | B25: шу жумладан, махаллий банкларнинг вакиллик ҳисобварақларига тўланиши лозим бўлган маблағлар | C25: 61512875 | D25: 61512875 | S25: =+C25 -> 61512875 | T25: =+S25-U25 -> 0 | U25: =+D25 -> 61512875 | V25: 1 | W25: =(U25*V25) -> 61512875 | X25: =(U25*V25) -> 61512875
A26: 3.2 | B26: Бошқа банкларнинг ҳисобварақлари - Депозитлар | C26: 410000 | D26: 0 | E26: 0 | F26: 0 | G26: 249512 | H26: 0 | I26: 180000000 | J26: 0 | K26: 156923400 | L26: 64602400 | M26: 76321154 | N26: 64602400 | O26: 541770311 | P26: 387614400 | Q26: 147918724 | R26: 0 | S26: =+C26+E26+G26+I26+K26+M26+O26+Q26 -> 1103593101 | T26: =+S26-U26 -> 586773901 | U26: =+D26+F26+H26+J26+L26+N26+P26+R26 -> 516819200 | V26: 1 | W26: =(C26+E26+G26)*V26 -> 659512 | X26: =(D26+F26+H26)*V26 -> 0
A27: 3.3 | B27: Банк карталаридан амалга оширилган тўловлар бўйича банкларга тўланиши лозим бўлган маблағлар | C27: 4761931 | D27: 21838 | E27: 0 | F27: 0 | G27: 0 | H27: 0 | I27: 0 | J27: 0 | K27: 0 | L27: 0 | M27: 0 | N27: 0 | O27: 0 | P27: 0 | Q27: 0 | R27: 0 | S27: =+C27+E27+G27+I27+K27+M27+O27+Q27 -> 4761931 | T27: =+S27-U27 -> 4740093 | U27: =+D27+F27+H27+J27+L27+N27+P27+R27 -> 21838 | V27: 1 | W27: =(C27+E27+G27)*V27 -> 4761931 | X27: =(D27+F27+H27)*V27 -> 21838
A28: 3.4 | B28: Бошқа моддалар | C28: 0 | D28: 0 | E28: 0 | F28: 0 | G28: 0 | H28: 0 | I28: 0 | J28: 0 | K28: 0 | L28: 0 | M28: 0 | N28: 0 | O28: 0 | P28: 0 | Q28: 0 | R28: 0 | S28: =+C28+E28+G28+I28+K28+M28+O28+Q28 -> 0 | T28: =+S28-U28 -> 0 | U28: =+D28+F28+H28+J28+L28+N28+P28+R28 -> 0 | V28: 1 | W28: =(C28+E28+G28)*V28 -> 0 | X28: =(D28+F28+H28)*V28 -> 0
A29: 4. | B29: Банкнинг тўланмаган акцептлари | C29: 0 | D29: 0 | E29: 0 | F29: 0 | G29: 0 | H29: 0 | I29: 0 | J29: 0 | K29: 0 | L29: 0 | M29: 0 | N29: 0 | O29: 0 | P29: 0 | Q29: 0 | R29: 0 | S29: =+C29+E29+G29+I29+K29+M29+O29+Q29 -> 0 | T29: =+S29-U29 -> 0 | U29: =+D29+F29+H29+J29+L29+N29+P29+R29 -> 0 | V29: 1 | W29: =(C29+E29+G29)*V29 -> 0 | X29: =(D29+F29+H29)*V29 -> 0
A30: 5. | B30: Олинган кредит ва лизинглар (молиявий ижара) бўйича мажбуриятлар | C30: 0 | D30: 0 | E30: 0 | F30: 0 | G30: 18044708 | H30: 15912066 | I30: 166630164 | J30: 159419032 | K30: 698866242 | L30: 650888099 | M30: 447344232 | N30: 388518879 | O30: 271441376 | P30: 143361000 | Q30: 1496954502 | R30: 1102592319 | S30: =+C30+E30+G30+I30+K30+M30+O30+Q30 -> 3099281224 | T30: =+S30-U30 -> 638589829 | U30: =+D30+F30+H30+J30+L30+N30+P30+R30 -> 2460691395 | V30: 0.05 | W30: =X30+'Bank Liabilities Analysis (нац)'!M31 -> 1.4873007e+08 | X30: =(U30-(J51+L51+N51+P51+R51))*V30 -> 1.1680058e+08
A31: 6. | B31: Банк томонидан чиқарилган қимматли қоғозлар | C31: 0 | D31: 0 | E31: 0 | F31: 0 | G31: 0 | H31: 0 | I31: 0 | J31: 0 | K31: 0 | L31: 0 | M31: 0 | N31: 0 | O31: 0 | P31: 0 | Q31: 0 | R31: 0 | S31: =+C31+E31+G31+I31+K31+M31+O31+Q31 -> 0 | T31: =+S31-U31 -> 0 | U31: =+D31+F31+H31+J31+L31+N31+P31+R31 -> 0 | V31: 1 | W31: =(C31+E31+G31)*V31 -> 0 | X31: =(D31+F31+H31)*V31 -> 0
A32: 7. | B32: Субординар қарз мажбуриятлари | C32: 0 | D32: 0 | E32: 0 | F32: 0 | G32: 0 | H32: 0 | I32: 0 | J32: 0 | K32: 0 | L32: 0 | M32: 0 | N32: 0 | O32: 0 | P32: 0 | Q32: 167901638 | R32: 167901638 | S32: =+C32+E32+G32+I32+K32+M32+O32+Q32 -> 167901638 | T32: =+S32-U32 -> 0 | U32: =+D32+F32+H32+J32+L32+N32+P32+R32 -> 167901638 | V32: 1 | W32: =(C32+E32+G32)*V32 -> 0 | X32: =(D32+F32+H32)*V32 -> 0
A33: 8. | B33: РЕПО битимлари бўйича сотилган қимматли қоғозлар | C33: =+C34+C35 -> 0 | D33: =+D34+D35 -> 0 | E33: =+E34+E35 -> 801459811 | F33: =+F34+F35 -> 0 | G33: =+G34+G35 -> 0 | H33: =+H34+H35 -> 0 | I33: =+I34+I35 -> 0 | J33: =+J34+J35 -> 0 | ... R33: =+R34+R35 -> 0 | S33: =+C33+E33+G33+I33+K33+M33+O33+Q33 -> 801459811 | T33: =+S33-U33 -> 801459811 | U33: =+D33+F33+H33+J33+L33+N33+P33+R33 -> 0
A34: 8.1 | B34: РЕПО битимлари бўйича сотилган юқори ликвидли қимматли қоғозлар | C34: 0 | D34: 0 | E34: 801459811 | F34: 0 | G34: 0 | H34: 0 | I34: 0 | J34: 0 | K34: 0 | L34: 0 | M34: 0 | N34: 0 | O34: 0 | P34: 0 | Q34: 0 | R34: 0 | S34: =+C34+E34+G34+I34+K34+M34+O34+Q34 -> 801459811 | T34: =+S34-U34 -> 801459811 | U34: =+D34+F34+H34+J34+L34+N34+P34+R34 -> 0 | V34: 1 | W34: =(C34+E34+G34)*V34 -> 801459811 | X34: =(D34+F34+H34)*V34 -> 0
A35: 8.2 | B35: РЕПО битимлари бўйича сотилган бошқа қимматли қоғозлар | C35: 0 | D35: 0 | E35: 0 | F35: 0 | G35: 0 | H35: 0 | I35: 0 | J35: 0 | K35: 0 | L35: 0 | M35: 0 | N35: 0 | O35: 0 | P35: 0 | Q35: 0 | R35: 0 | S35: =+C35+E35+G35+I35+K35+M35+O35+Q35 -> 0 | T35: =+S35-U35 -> 0 | U35: =+D35+F35+H35+J35+L35+N35+P35+R35 -> 0 | V35: 1 | W35: =(C35+E35+G35)*V35 -> 0 | X35: =(D35+F35+H35)*V35 -> 0
A36: 9. | B36: Ҳосилавий инструментлар бўйича ревальвация натижасида амалга ошмаган зарарлар ва бошқа муддати узайтирилган даромадлар | C36: 7955 | D36: 0 | E36: 0 | F36: 0 | G36: 0 | H36: 0 | I36: 0 | J36: 0 | K36: 8983935 | L36: 0 | M36: 0 | N36: 0 | O36: 0 | P36: 0 | Q36: 0 | R36: 0 | S36: =+C36+E36+G36+I36+K36+M36+O36+Q36 -> 8991890 | T36: =+S36-U36 -> 8991890 | U36: =+D36+F36+H36+J36+L36+N36+P36+R36 -> 0 | V36: 1 | W36: =(S36)*V36 -> 8991890 | X36: =(U36)*V36 -> 0
A37: 10. | B37: Клиринг транзакциялари | C37: 752024 | D37: 751700 | E37: 35250 | F37: 0 | G37: 0 | H37: 0 | I37: 0 | J37: 0 | K37: 0 | L37: 0 | M37: 0 | N37: 0 | O37: 0 | P37: 0 | Q37: 0 | R37: 0 | S37: =+C37+E37+G37+I37+K37+M37+O37+Q37 -> 787274 | T37: =+S37-U37 -> 35574 | U37: =+D37+F37+H37+J37+L37+N37+P37+R37 -> 751700 | V37: 1 | W37: =(S37)*V37 -> 787274 | X37: =(U37)*V37 -> 751700
A38: 11. | B38: Тўланиши лозим бўлган ҳисобланган фоизлар | C38: 4051071 | D38: 30381 | E38: 13355658 | F38: 156571 | G38: 26858081 | H38: 1881232 | I38: 23923199 | J38: 16687207 | K38: 25188366 | L38: 24432762 | M38: 1860669 | N38: 1724471 | O38: 225876 | P38: 129205 | Q38: 4970455 | R38: 23770 | S38: =+C38+E38+G38+I38+K38+M38+O38+Q38 -> 100433375 | T38: =+S38-U38 -> 55367776 | U38: =+D38+F38+H38+J38+L38+N38+P38+R38 -> 45065599 | W38: =(C38+E38+G38) -> 44264810 | X38: =D38+F38+H38 -> 2068184
A39: 11.1 | B39: Бош банк/филиалдан олинган ресурслар бўйича тўланиши лозим бўлган ҳисобланган фоизлар | S39: =+C39+E39+G39+I39+K39+M39+O39+Q39 -> 0 | T39: =+S39-U39 -> 0 | U39: =+D39+F39+H39+J39+L39+N39+P39+R39 -> 0 | W39: =C39+E39+G39 -> 0 | X39: =D39+F39+H39 -> 0
A40: 11.2 | B40: Бошқа банкларга тўланиши лозим бўлган ҳисобланган фоизлар | C40: 0 | D40: 0 | E40: 0 | F40: 0 | G40: 0 | H40: 0 | I40: 5968 | J40: 987 | K40: 4508055 | L40: 3003203 | M40: 8393568 | N40: 8393568 | O40: 406945 | P40: 0 | Q40: 991137 | R40: 0 | S40: =+C40+E40+G40+I40+K40+M40+O40+Q40 -> 14305673 | T40: =+S40-U40 -> 2907915 | U40: =+D40+F40+H40+J40+L40+N40+P40+R40 -> 11397758 | W40: =C40+E40+G40 -> 0 | X40: =D40+F40+H40 -> 0
A41: 12. | B41: Бошқа мажбуриятлар | C41: 371918006 | D41: 92127803 | E41: 10117085 | F41: 1104917 | G41: 19108 | H41: 0 | I41: 177511 | J41: 55074 | K41: 983385 | L41: 854901 | M41: 418636 | N41: 80430 | O41: 2971270 | P41: 0 | Q41: 21902570 | R41: 14340309 | S41: =+C41+E41+G41+I41+K41+M41+O41+Q41 -> 408507571 | T41: =+S41-U41 -> 299944137 | U41: =+D41+F41+H41+J41+L41+N41+P41+R41 -> 108563434 | V41: 1 | W41: =(C41+E41+G41)*V41 -> 382054199 | X41: =(D41+F41+H41)*V41 -> 93232720
A42: 13 | B42: ЖАМИ МАЖБУРИЯТЛАР | C42: =+C20+C21+C23+C29+C30+C31+C32+C33+C36+C37+C38+C39+C40+C41 -> 4986273646 | D42: =+D20+D21+D23+D29+D30+D31+D32+D33+D36+D37+D38+D39+D40+D41 -> 852016796 | E42: =+E20+E21+E23+E29+E30+E31+E32+E33+E36+E37+E38+E39+E40+E41 -> 899328415 | F42: =+F20+F21+F23+F29+F30+F31+F32+F33+F36+F37+F38+F39+F40+F41 -> 3286596 | G42: =+G20+G21+G23+G29+G30+G31+G32+G33+G36+G37+G38+G39+G40+G41 -> 210759484 | H42: =+H20+H21+H23+H29+H30+H31+H32+H33+H36+H37+H38+H39+H40+H41 -> 18822716 | I42: =+I20+I21+I23+I29+I30+I31+I32+I33+I36+I37+I38+I39+I40+I41 -> 666054953 | J42: =+J20+J21+J23+J29+J30+J31+J32+J33+J36+J37+J38+J39+J40+J41 -> 186128529 | ... U42: =+U20+U21+U23+U29+U30+U31+U32+U33+U36+U37+U38+U39+U40+U41 -> 5034219212 | V42: отток | W42: =SUM(W8:W41) -> 3.6488501e+09 | X42: =SUM(X8:X41) -> 6.2279202e+08 | Y42: =+Balance!C63 -> 20169034112 | Z42: =+Balance!D63 -> 15134814900 | AA42: =+Balance!E63 -> 5034219212
B43: шундан, | S43: =+C43+E43+G43+I43+K43+M43+O43+Q43 -> 0 | T43: =+S43-U43 -> 0 | U43: =+D43+F43+H43+J43+L43+N43+P43+R43 -> 0 | Y43: =+S42-Y42 -> 0 | Z43: =+T42-Z42 -> 0 | AA43: =+U42-AA42 -> 0
B44: Ўзбекистон Республикаси Молия вазирлиги маблағлари, шундан | C44: =+C45+C46 -> 0 | D44: =+D45+D46 -> 0 | E44: =+E45+E46 -> 50000000 | F44: =+F45+F46 -> 0 | G44: =+G45+G46 -> 123325387 | H44: =+H45+H46 -> 12916130 | I44: =+I45+I46 -> 60624463 | J44: =+J45+J46 -> 59958032 | ... R44: =+R45+R46 -> 675197802 | S44: =+C44+E44+G44+I44+K44+M44+O44+Q44 -> 2675080785 | T44: =+S44-U44 -> 1727716909 | U44: =+D44+F44+H44+J44+L44+N44+P44+R44 -> 947363876
B45: Кредит ва лизинглар | C45: 0 | D45: 0 | E45: 0 | F45: 0 | G45: 13158720 | H45: 12916130 | I45: 60624463 | J45: 59958032 | K45: 49479849 | L45: 48796008 | M45: 115009616 | N45: 112966417 | O45: 41342835 | P45: 37529487 | Q45: 548541120 | R45: 442629162 | S45: =+C45+E45+G45+I45+K45+M45+O45+Q45 -> 828156603 | T45: =+S45-U45 -> 113361367 | U45: =+D45+F45+H45+J45+L45+N45+P45+R45 -> 714795236
B46: Депозит маблағлар | C46: 0 | D46: 0 | E46: 50000000 | F46: 0 | G46: 110166667 | H46: 0 | I46: 0 | J46: 0 | K46: 265000000 | L46: 0 | M46: 494400000 | N46: 0 | O46: 6999999 | P46: 0 | Q46: 920357516 | R46: 232568640 | S46: =+C46+E46+G46+I46+K46+M46+O46+Q46 -> 1846924182 | T46: =+S46-U46 -> 1614355542 | U46: =+D46+F46+H46+J46+L46+N46+P46+R46 -> 232568640 | Y46: 20202, 20402, 20602
B47: Бюджетдан ташқари фондларнинг маблағлари, шундан | C47: =+C48+C49 -> 0 | D47: =+D48+D49 -> 0 | E47: =+E48+E49 -> 0 | F47: =+F48+F49 -> 0 | G47: =+G48+G49 -> 0 | H47: =+H48+H49 -> 0 | I47: =+I48+I49 -> 0 | J47: =+J48+J49 -> 0 | ... R47: =+R48+R49 -> 0 | S47: =+C47+E47+G47+I47+K47+M47+O47+Q47 -> 0 | T47: =+S47-U47 -> 0 | U47: =+D47+F47+H47+J47+L47+N47+P47+R47 -> 0
B48: Кредит ва лизинглар | C48: 0 | D48: 0 | E48: 0 | F48: 0 | G48: 0 | H48: 0 | I48: 0 | J48: 0 | K48: 0 | L48: 0 | M48: 0 | N48: 0 | O48: 0 | P48: 0 | Q48: 0 | R48: 0 | S48: =+C48+E48+G48+I48+K48+M48+O48+Q48 -> 0 | T48: =+S48-U48 -> 0 | U48: =+D48+F48+H48+J48+L48+N48+P48+R48 -> 0
B49: Депозит маблағлар | C49: 0 | D49: 0 | E49: 0 | F49: 0 | G49: 0 | H49: 0 | I49: 0 | J49: 0 | K49: 0 | L49: 0 | M49: 0 | N49: 0 | O49: 0 | P49: 0 | Q49: 0 | R49: 0 | S49: =+C49+E49+G49+I49+K49+M49+O49+Q49 -> 0 | T49: =+S49-U49 -> 0 | U49: =+D49+F49+H49+J49+L49+N49+P49+R49 -> 0
B50: Ўзбекистон тикланиш ва тараққиёт фонди (ФРРУ), шундан | C50: =+C51+C52 -> 0 | D50: =+D51+D52 -> 0 | E50: =+E51+E52 -> 0 | F50: =+F51+F52 -> 0 | G50: =+G51+G52 -> 0 | H50: =+H51+H52 -> 0 | I50: =+I51+I52 -> 0 | J50: =+J51+J52 -> 0 | ... R50: =+R51+R52 -> 123281505 | S50: =+C50+E50+G50+I50+K50+M50+O50+Q50 -> 528930653 | T50: =+S50-U50 -> 404250884 | U50: =+D50+F50+H50+J50+L50+N50+P50+R50 -> 124679769
B51: Кредит ва лизинглар | C51: 0 | D51: 0 | E51: 0 | F51: 0 | G51: 0 | H51: 0 | I51: 0 | J51: 0 | K51: 40801111 | L51: 0 | M51: 41267199 | N51: 466088 | O51: 96647694 | P51: 932176 | Q51: 350214649 | R51: 123281505 | S51: =+C51+E51+G51+I51+K51+M51+O51+Q51 -> 528930653 | T51: =+S51-U51 -> 404250884 | U51: =+D51+F51+H51+J51+L51+N51+P51+R51 -> 124679769
B52: Депозит маблағлар | C52: 0 | D52: 0 | E52: 0 | F52: 0 | G52: 0 | H52: 0 | I52: 0 | J52: 0 | K52: 0 | L52: 0 | M52: 0 | N52: 0 | O52: 0 | P52: 0 | Q52: 0 | R52: 0 | S52: =+C52+E52+G52+I52+K52+M52+O52+Q52 -> 0 | T52: =+S52-U52 -> 0 | U52: =+D52+F52+H52+J52+L52+N52+P52+R52 -> 0
B53: Хорижий банклар, шундан | C53: =+C54+C55 -> 0 | D53: =+D54+D55 -> 0 | E53: =+E54+E55 -> 0 | F53: =+F54+F55 -> 0 | G53: =+G54+G55 -> 0 | H53: =+H54+H55 -> 0 | I53: =+I54+I55 -> 69464130 | J53: =+J54+J55 -> 69464130 | ... R53: =+R54+R55 -> 365861485 | S53: =+C53+E53+G53+I53+K53+M53+O53+Q53 -> 1106303770 | T53: =+S53-U53 -> 0 | U53: =+D53+F53+H53+J53+L53+N53+P53+R53 -> 1106303770
B54: Кредит ва лизинглар | C54: 0 | D54: 0 | E54: 0 | F54: 0 | G54: 0 | H54: 0 | I54: 69464130 | J54: 69464130 | K54: 568020075 | L54: 568020075 | M54: 45697772 | N54: 45697772 | O54: 57260308 | P54: 57260308 | Q54: 365861485 | R54: 365861485 | S54: =+C54+E54+G54+I54+K54+M54+O54+Q54 -> 1106303770 | T54: =+S54-U54 -> 0 | U54: =+D54+F54+H54+J54+L54+N54+P54+R54 -> 1106303770
B55: Депозит маблағлар | C55: 0 | D55: 0 | E55: 0 | F55: 0 | G55: 0 | H55: 0 | I55: 0 | J55: 0 | K55: 0 | L55: 0 | M55: 0 | N55: 0 | O55: 0 | P55: 0 | Q55: 0 | R55: 0 | S55: =+C55+E55+G55+I55+K55+M55+O55+Q55 -> 0 | T55: =+S55-U55 -> 0 | U55: =+D55+F55+H55+J55+L55+N55+P55+R55 -> 0
B56: Бошқа халқаро молия ташкилотлари маблағлари, шундан, | C56: =+C57+C58 -> 0 | D56: =+D57+D58 -> 0 | E56: =+E57+E58 -> 0 | F56: =+F57+F58 -> 0 | G56: =+G57+G58 -> 0 | H56: =+H57+H58 -> 0 | I56: =+I57+I58 -> 0 | J56: =+J57+J58 -> 0 | ... R56: =+R57+R58 -> 0 | S56: =+C56+E56+G56+I56+K56+M56+O56+Q56 -> 180886720 | T56: =+S56-U56 -> 0 | U56: =+D56+F56+H56+J56+L56+N56+P56+R56 -> 180886720
B57: Кредит ва лизинглар | C57: 0 | D57: 0 | E57: 0 | F57: 0 | G57: 0 | H57: 0 | I57: 0 | J57: 0 | K57: 0 | L57: 0 | M57: 180886720 | N57: 180886720 | O57: 0 | P57: 0 | Q57: 0 | R57: 0 | S57: =+C57+E57+G57+I57+K57+M57+O57+Q57 -> 180886720 | T57: =+S57-U57 -> 0 | U57: =+D57+F57+H57+J57+L57+N57+P57+R57 -> 180886720
B58: Депозит маблағлар | C58: 0 | D58: 0 | E58: 0 | F58: 0 | G58: 0 | H58: 0 | I58: 0 | J58: 0 | K58: 0 | L58: 0 | M58: 0 | N58: 0 | O58: 0 | P58: 0 | Q58: 0 | R58: 0 | S58: =+C58+E58+G58+I58+K58+M58+O58+Q58 -> 0 | T58: =+S58-U58 -> 0 | U58: =+D58+F58+H58+J58+L58+N58+P58+R58 -> 0
B59: Активлар ва мажбуриятлар муддатлари мувофиқлиги таҳлили
B60: Активы | C60: ='Bank Assets Analysis'!C47-'Bank Assets Analysis'!C30-'Bank Assets Analysis'!C32-'Bank Assets Analysis'!C33-'Bank Assets Analysis'!C37-'Bank Assets Analysis'!C38-'Bank Assets Analysis'!C42-'Bank Assets Analysis'!C45 -> 3043608597 | D60: ='Bank Assets Analysis'!D47-'Bank Assets Analysis'!D30-'Bank Assets Analysis'!D32-'Bank Assets Analysis'!D33-'Bank Assets Analysis'!D37-'Bank Assets Analysis'!D38-'Bank Assets Analysis'!D42-'Bank Assets Analysis'!D45 -> 872647426 | E60: ='Bank Assets Analysis'!E47 -> 29800448 | F60: ='Bank Assets Analysis'!F47 -> 422283 | G60: ='Bank Assets Analysis'!G47 -> 839860803 | H60: ='Bank Assets Analysis'!H47 -> 249959530 | I60: ='Bank Assets Analysis'!I47 -> 1407169860 | J60: ='Bank Assets Analysis'!J47 -> 357646984 | K60: ='Bank Assets Analysis'!K47 -> 1305988418 | L60: ='Bank Assets Analysis'!L47 -> 451520670 | ... N60: ='Bank Assets Analysis'!N47 -> 707474261 | O60: ='Bank Assets Analysis'!O47-'Bank Assets Analysis'!O37 -> 3442400562 | P60: ='Bank Assets Analysis'!P47-'Bank Assets Analysis'!P37 -> 680231742 | Q60: ='Bank Assets Analysis'!Q47-'Bank Assets Analysis'!Q37 -> 6550002556 | R60: ='Bank Assets Analysis'!R47-'Bank Assets Analysis'!R37 -> 1524774187
B61: Внебаланс | C61: =(+'Bank Assets Analysis'!C49-'Bank Assets Analysis'!C50)+('Bank Assets Analysis'!C51-'Bank Assets Analysis'!C52)+('Bank Assets Analysis'!C53-'Bank Assets Analysis'!C54) -> 128630 | D61: =(+'Bank Assets Analysis'!D49-'Bank Assets Analysis'!D50)+('Bank Assets Analysis'!D51-'Bank Assets Analysis'!D52)+('Bank Assets Analysis'!D53-'Bank Assets Analysis'!D54) -> 0 | E61: =(+'Bank Assets Analysis'!E49-'Bank Assets Analysis'!E50)+('Bank Assets Analysis'!E51-'Bank Assets Analysis'!E52)+('Bank Assets Analysis'!E53-'Bank Assets Analysis'!E54) -> 59812221 | F61: =(+'Bank Assets Analysis'!F49-'Bank Assets Analysis'!F50)+('Bank Assets Analysis'!F51-'Bank Assets Analysis'!F52)+('Bank Assets Analysis'!F53-'Bank Assets Analysis'!F54) -> 405860 | G61: =(+'Bank Assets Analysis'!G49-'Bank Assets Analysis'!G50)+('Bank Assets Analysis'!G51-'Bank Assets Analysis'!G52)+('Bank Assets Analysis'!G53-'Bank Assets Analysis'!G54) -> 1821695 | H61: =(+'Bank Assets Analysis'!H49-'Bank Assets Analysis'!H50)+('Bank Assets Analysis'!H51-'Bank Assets Analysis'!H52)+('Bank Assets Analysis'!H53-'Bank Assets Analysis'!H54) -> 667550 | I61: =(+'Bank Assets Analysis'!I49-'Bank Assets Analysis'!I50)+('Bank Assets Analysis'!I51-'Bank Assets Analysis'!I52)+('Bank Assets Analysis'!I53-'Bank Assets Analysis'!I54) -> 138778843 | J61: =(+'Bank Assets Analysis'!J49-'Bank Assets Analysis'!J50)+('Bank Assets Analysis'!J51-'Bank Assets Analysis'!J52)+('Bank Assets Analysis'!J53-'Bank Assets Analysis'!J54) -> 131056160 | ... R61: =(+'Bank Assets Analysis'!R49-'Bank Assets Analysis'!R50)+('Bank Assets Analysis'!R51-'Bank Assets Analysis'!R52)+('Bank Assets Analysis'!R53-'Bank Assets Analysis'!R54) -> 702593380
B62: Мажбурият | C62: ='Bank Liabilities Analysis'!C42 -> 4986273646 | D62: ='Bank Liabilities Analysis'!D42 -> 852016796 | E62: ='Bank Liabilities Analysis'!E42 -> 899328415 | F62: ='Bank Liabilities Analysis'!F42 -> 3286596 | G62: ='Bank Liabilities Analysis'!G42 -> 210759484 | H62: ='Bank Liabilities Analysis'!H42 -> 18822716 | I62: ='Bank Liabilities Analysis'!I42 -> 666054953 | J62: ='Bank Liabilities Analysis'!J42 -> 186128529 | ... R62: ='Bank Liabilities Analysis'!R42 -> 1525437374
B63: GAP | C63: =+C60-C62-C61 -> -1942793679 | D63: =+D60-D62-D61 -> 20630630 | E63: =+E60-E62-E61 -> -929340188 | F63: =+F60-F62-F61 -> -3270173 | G63: =+G60-G62-G61 -> 627279624 | H63: =+H60-H62-H61 -> 230469264 | I63: =+I60-I62-I61 -> 602336064 | J63: =+J60-J62-J61 -> 40462295 | ... R63: =+R60-R62-R61 -> -703256567
B64: кум Gap | C64: =+C63 -> -1942793679 | D64: =+D63 -> 20630630 | E64: =E63+C64 -> -2872133867 | F64: =+F63+D64 -> 17360457 | G64: =G63+E64 -> -2244854243 | H64: =+H63+F64 -> 247829721 | I64: =I63+G64 -> -1642518179 | J64: =+J63+H64 -> 288292016 | K64: =K63+I64 -> -2786649825 | L64: =+L63+J64 -> -118428710 | M64: =M63+K64 -> -4168081841 | N64: =+N63+L64 -> -568119687 | O64: =O63+M64 -> -5571791459 | P64: =+P63+N64 -> -881744474 | Q64: =Q63+O64 -> -3090392859 | R64: =+R63+P64 -> -1585001041
B66: Бошқарув Раис имзоси:
B68: Бош бухгалтер имзоси:

Sheet Bank Liabilities Analysis (нац)
A2: МИЛЛИЙ ВАЛЮТАДА БАНК МАЖБУРИЯТЛАРИ ТАҲЛИЛИ | L2: 18 А-жадвал
B3: =Balance!B3 -> Банк номи | K3: =+Balance!D3 -> 45657 | M3: =+Balance!E3 -> минг сўмда
A4: № | B4: Кўрсаткичлар | C4: Сўндириш муддати (кунларда) | K4: Жами | L4: Ликвидлиликни қоплаш меёри ҳисоб китоби
C5: Муддатсиз | D5: 1 дан 7 гача | E5: 8 дан 30 гача | F5: 31 дан 90 гача | G5: 91 дан 180 гача | H5: 181 дан 365 гача | I5: 366 дан 730 гача | J5: 2 йилдан ортиқ
L6: Коэффициент | M6: 30 кунлик чиқим суммаси
A7: 1. | B7: ДЕПОЗИТЛАР
A8: 1.1 | B8: Талаб қилиб олингунча депозитлар | C8: =SUM(C9:C12) -> 2176721720 | D8: =SUM(D9:D12) -> 0 | E8: =SUM(E9:E12) -> 0 | F8: =SUM(F9:F12) -> 0 | G8: =SUM(G9:G12) -> 0 | H8: =SUM(H9:H12) -> 0 | I8: =SUM(I9:I12) -> 0 | J8: =SUM(J9:J12) -> 0 | K8: =+C8+D8+E8+F8+G8+H8+I8+J8 -> 2176721720
A9: 1.1.1 | B9: Aҳолининг талаб қилиб олингунча омонатлари | C9: =+'Bank Liabilities Analysis'!C8-'Bank Liabilities Analysis'!D8 -> 30451239 | D9: =+'Bank Liabilities Analysis'!E8-'Bank Liabilities Analysis'!F8 -> 0 | E9: =+'Bank Liabilities Analysis'!G8-'Bank Liabilities Analysis'!H8 -> 0 | F9: =+'Bank Liabilities Analysis'!I8-'Bank Liabilities Analysis'!J8 -> 0 | G9: =+'Bank Liabilities Analysis'!K8-'Bank Liabilities Analysis'!L8 -> 0 | H9: =+'Bank Liabilities Analysis'!M8-'Bank Liabilities Analysis'!N8 -> 0 | I9: =+'Bank Liabilities Analysis'!O8-'Bank Liabilities Analysis'!P8 -> 0 | J9: =+'Bank Liabilities Analysis'!Q8-'Bank Liabilities Analysis'!R8 -> 0 | K9: =+C9+D9+E9+F9+G9+H9+I9+J9 -> 30451239
A10: 1.1.2 | B10: Кредит таъминоти сифатида жалб этилган aҳоли омонатлари | C10: =+'Bank Liabilities Analysis'!C9-'Bank Liabilities Analysis'!D9 -> 229780 | D10: =+'Bank Liabilities Analysis'!E9-'Bank Liabilities Analysis'!F9 -> 0 | E10: =+'Bank Liabilities Analysis'!G9-'Bank Liabilities Analysis'!H9 -> 0 | F10: =+'Bank Liabilities Analysis'!I9-'Bank Liabilities Analysis'!J9 -> 0 | G10: =+'Bank Liabilities Analysis'!K9-'Bank Liabilities Analysis'!L9 -> 0 | H10: =+'Bank Liabilities Analysis'!M9-'Bank Liabilities Analysis'!N9 -> 0 | I10: =+'Bank Liabilities Analysis'!O9-'Bank Liabilities Analysis'!P9 -> 0 | J10: =+'Bank Liabilities Analysis'!Q9-'Bank Liabilities Analysis'!R9 -> 0 | K10: =+C10+D10+E10+F10+G10+H10+I10+J10 -> 229780
A11: 1.1.3 | B11: Кредит таъминоти сифатида жалб этилган бошқа депозитлар | C11: =+'Bank Liabilities Analysis'!C10-'Bank Liabilities Analysis'!D10 -> 0 | D11: =+'Bank Liabilities Analysis'!E10-'Bank Liabilities Analysis'!F10 -> 0 | E11: =+'Bank Liabilities Analysis'!G10-'Bank Liabilities Analysis'!H10 -> 0 | F11: =+'Bank Liabilities Analysis'!I10-'Bank Liabilities Analysis'!J10 -> 0 | G11: =+'Bank Liabilities Analysis'!K10-'Bank Liabilities Analysis'!L10 -> 0 | H11: =+'Bank Liabilities Analysis'!M10-'Bank Liabilities Analysis'!N10 -> 0 | I11: =+'Bank Liabilities Analysis'!O10-'Bank Liabilities Analysis'!P10 -> 0 | J11: =+'Bank Liabilities Analysis'!Q10-'Bank Liabilities Analysis'!R10 -> 0 | K11: =+C11+D11+E11+F11+G11+H11+I11+J11 -> 0
A12: 1.1.4 | B12: Талаб қилиб олингунча бошқа депозитлар | C12: =+'Bank Liabilities Analysis'!C11-'Bank Liabilities Analysis'!D11 -> 2146040701 | D12: =+'Bank Liabilities Analysis'!E11-'Bank Liabilities Analysis'!F11 -> 0 | E12: =+'Bank Liabilities Analysis'!G11-'Bank Liabilities Analysis'!H11 -> 0 | F12: =+'Bank Liabilities Analysis'!I11-'Bank Liabilities Analysis'!J11 -> 0 | G12: =+'Bank Liabilities Analysis'!K11-'Bank Liabilities Analysis'!L11 -> 0 | H12: =+'Bank Liabilities Analysis'!M11-'Bank Liabilities Analysis'!N11 -> 0 | I12: =+'Bank Liabilities Analysis'!O11-'Bank Liabilities Analysis'!P11 -> 0 | J12: =+'Bank Liabilities Analysis'!Q11-'Bank Liabilities Analysis'!R11 -> 0 | K12: =+C12+D12+E12+F12+G12+H12+I12+J12 -> 2146040701
A13: 1.2 | B13: Муддатли депозитлар | C13: =+'Bank Liabilities Analysis'!C12-'Bank Liabilities Analysis'!D12 -> 0 | D13: =+'Bank Liabilities Analysis'!E12-'Bank Liabilities Analysis'!F12 -> 72335503 | E13: =+'Bank Liabilities Analysis'!G12-'Bank Liabilities Analysis'!H12 -> 164558657 | F13: =+'Bank Liabilities Analysis'!I12-'Bank Liabilities Analysis'!J12 -> 285351882 | G13: =+'Bank Liabilities Analysis'!K12-'Bank Liabilities Analysis'!L12 -> 1413137946 | H13: =+'Bank Liabilities Analysis'!M12-'Bank Liabilities Analysis'!N12 -> 2373502461 | I13: =+'Bank Liabilities Analysis'!O12-'Bank Liabilities Analysis'!P12 -> 3495815466 | J13: =+'Bank Liabilities Analysis'!Q12-'Bank Liabilities Analysis'!R12 -> 1086014474 | K13: =+C13+D13+E13+F13+G13+H13+I13+J13 -> 8890716389
A14: 1.2.1 | B14: Аҳоли омонатлари | C14: =+'Bank Liabilities Analysis'!C13-'Bank Liabilities Analysis'!D13 -> 0 | D14: =+'Bank Liabilities Analysis'!E13-'Bank Liabilities Analysis'!F13 -> 17077503 | E14: =+'Bank Liabilities Analysis'!G13-'Bank Liabilities Analysis'!H13 -> 38321991 | F14: =+'Bank Liabilities Analysis'!I13-'Bank Liabilities Analysis'!J13 -> 72960783 | G14: =+'Bank Liabilities Analysis'!K13-'Bank Liabilities Analysis'!L13 -> 815219796 | H14: =+'Bank Liabilities Analysis'!M13-'Bank Liabilities Analysis'!N13 -> 963880992 | I14: =+'Bank Liabilities Analysis'!O13-'Bank Liabilities Analysis'!P13 -> 1780148880 | J14: =+'Bank Liabilities Analysis'!Q13-'Bank Liabilities Analysis'!R13 -> 35522527 | K14: =+C14+D14+E14+F14+G14+H14+I14+J14 -> 3723132472
A15: 1.2.2 | B15: Чиқарилган депозит сертификатлари | C15: =+'Bank Liabilities Analysis'!C14-'Bank Liabilities Analysis'!D14 -> 0 | D15: =+'Bank Liabilities Analysis'!E14-'Bank Liabilities Analysis'!F14 -> 0 | E15: =+'Bank Liabilities Analysis'!G14-'Bank Liabilities Analysis'!H14 -> 0 | F15: =+'Bank Liabilities Analysis'!I14-'Bank Liabilities Analysis'!J14 -> 0 | G15: =+'Bank Liabilities Analysis'!K14-'Bank Liabilities Analysis'!L14 -> 0 | H15: =+'Bank Liabilities Analysis'!M14-'Bank Liabilities Analysis'!N14 -> 0 | I15: =+'Bank Liabilities Analysis'!O14-'Bank Liabilities Analysis'!P14 -> 0 | J15: =+'Bank Liabilities Analysis'!Q14-'Bank Liabilities Analysis'!R14 -> 0 | K15: =+C15+D15+E15+F15+G15+H15+I15+J15 -> 0
A16: 1.3 | B16: Мижозларнинг бошқа депозитлари | C16: =SUM(C17:C20) -> 1243466870 | D16: =SUM(D17:D20) -> 0 | E16: =SUM(E17:E20) -> 0 | F16: =SUM(F17:F20) -> 0 | G16: =SUM(G17:G20) -> 0 | H16: =SUM(H17:H20) -> 0 | I16: =SUM(I17:I20) -> 0 | J16: =SUM(J17:J20) -> 0 | K16: =+C16+D16+E16+F16+G16+H16+I16+J16 -> 1243466870
A17: 1.3.1 | B17: Жисмоний шахсларнинг банк пластик карталаридаги маблағлари | C17: =+'Bank Liabilities Analysis'!C16-'Bank Liabilities Analysis'!D16 -> 1072003755 | D17: =+'Bank Liabilities Analysis'!E16-'Bank Liabilities Analysis'!F16 -> 0 | E17: =+'Bank Liabilities Analysis'!G16-'Bank Liabilities Analysis'!H16 -> 0 | F17: =+'Bank Liabilities Analysis'!I16-'Bank Liabilities Analysis'!J16 -> 0 | G17: =+'Bank Liabilities Analysis'!K16-'Bank Liabilities Analysis'!L16 -> 0 | H17: =+'Bank Liabilities Analysis'!M16-'Bank Liabilities Analysis'!N16 -> 0 | I17: =+'Bank Liabilities Analysis'!O16-'Bank Liabilities Analysis'!P16 -> 0 | J17: =+'Bank Liabilities Analysis'!Q16-'Bank Liabilities Analysis'!R16 -> 0 | K17: =+C17+D17+E17+F17+G17+H17+I17+J17 -> 1072003755
A18: 1.3.2 | B18: Бошқа мижозларнинг банк пластик карталаридаги маблағлари | C18: =+'Bank Liabilities Analysis'!C17-'Bank Liabilities Analysis'!D17 -> 10090193 | D18: =+'Bank Liabilities Analysis'!E17-'Bank Liabilities Analysis'!F17 -> 0 | E18: =+'Bank Liabilities Analysis'!G17-'Bank Liabilities Analysis'!H17 -> 0 | F18: =+'Bank Liabilities Analysis'!I17-'Bank Liabilities Analysis'!J17 -> 0 | G18: =+'Bank Liabilities Analysis'!K17-'Bank Liabilities Analysis'!L17 -> 0 | H18: =+'Bank Liabilities Analysis'!M17-'Bank Liabilities Analysis'!N17 -> 0 | I18: =+'Bank Liabilities Analysis'!O17-'Bank Liabilities Analysis'!P17 -> 0 | J18: =+'Bank Liabilities Analysis'!Q17-'Bank Liabilities Analysis'!R17 -> 0 | K18: =+C18+D18+E18+F18+G18+H18+I18+J18 -> 10090193
A19: 1.3.3 | B19: Мижозларнинг аккредитив бўйича депозитлари | C19: =+'Bank Liabilities Analysis'!C18-'Bank Liabilities Analysis'!D18 -> 0 | D19: =+'Bank Liabilities Analysis'!E18-'Bank Liabilities Analysis'!F18 -> 0 | E19: =+'Bank Liabilities Analysis'!G18-'Bank Liabilities Analysis'!H18 -> 0 | F19: =+'Bank Liabilities Analysis'!I18-'Bank Liabilities Analysis'!J18 -> 0 | G19: =+'Bank Liabilities Analysis'!K18-'Bank Liabilities Analysis'!L18 -> 0 | H19: =+'Bank Liabilities Analysis'!M18-'Bank Liabilities Analysis'!N18 -> 0 | I19: =+'Bank Liabilities Analysis'!O18-'Bank Liabilities Analysis'!P18 -> 0 | J19: =+'Bank Liabilities Analysis'!Q18-'Bank Liabilities Analysis'!R18 -> 0 | K19: =+C19+D19+E19+F19+G19+H19+I19+J19 -> 0
A20: 1.3.4 | B20: Бошқалар | C20: =+'Bank Liabilities Analysis'!C19-'Bank Liabilities Analysis'!D19 -> 161372922 | D20: =+'Bank Liabilities Analysis'!E19-'Bank Liabilities Analysis'!F19 -> 0 | E20: =+'Bank Liabilities Analysis'!G19-'Bank Liabilities Analysis'!H19 -> 0 | F20: =+'Bank Liabilities Analysis'!I19-'Bank Liabilities Analysis'!J19 -> 0 | G20: =+'Bank Liabilities Analysis'!K19-'Bank Liabilities Analysis'!L19 -> 0 | H20: =+'Bank Liabilities Analysis'!M19-'Bank Liabilities Analysis'!N19 -> 0 | I20: =+'Bank Liabilities Analysis'!O19-'Bank Liabilities Analysis'!P19 -> 0 | J20: =+'Bank Liabilities Analysis'!Q19-'Bank Liabilities Analysis'!R19 -> 0 | K20: =+C20+D20+E20+F20+G20+H20+I20+J20 -> 161372922
A21: 1.4 | B21: Жами депозитлар | C21: =+C8+C13+C16 -> 3420188590 | D21: =+D8+D13+D16 -> 72335503 | E21: =+E8+E13+E16 -> 164558657 | F21: =+F8+F13+F16 -> 285351882 | G21: =+G8+G13+G16 -> 1413137946 | H21: =+H8+H13+H16 -> 2373502461 | I21: =+I8+I13+I16 -> 3495815466 | J21: =+J8+J13+J16 -> 1086014474 | K21: =+C21+D21+E21+F21+G21+H21+I21+J21 -> 12310904979 | L21: 0.15 | M21: =+K21*L21 -> 1.8466357e+09
A22: 2. | B22: Марказий банкка тўланиши лозим бўлган маблағлар | C22: =+'Bank Liabilities Analysis'!C21-'Bank Liabilities Analysis'!D21 -> 424511118 | D22: =+'Bank Liabilities Analysis'!E21-'Bank Liabilities Analysis'!F21 -> 0 | E22: =+'Bank Liabilities Analysis'!G21-'Bank Liabilities Analysis'!H21 -> 0 | F22: =+'Bank Liabilities Analysis'!I21-'Bank Liabilities Analysis'!J21 -> 0 | G22: =+'Bank Liabilities Analysis'!K21-'Bank Liabilities Analysis'!L21 -> 0 | H22: =+'Bank Liabilities Analysis'!M21-'Bank Liabilities Analysis'!N21 -> 0 | I22: =+'Bank Liabilities Analysis'!O21-'Bank Liabilities Analysis'!P21 -> 0 | J22: =+'Bank Liabilities Analysis'!Q21-'Bank Liabilities Analysis'!R21 -> 0 | K22: =+C22+D22+E22+F22+G22+H22+I22+J22 -> 424511118 | L22: 1 | M22: =(C22+D22+E22-C23-D23-E23)*L22 -> 0
A23: 2.1. | B23: шу жумладан, Марказий банкка тўланиши лозим бўлган маблағлар -Тезкор тўловлар ҳамда клиринг тизими | C23: =+'Bank Liabilities Analysis'!C22-'Bank Liabilities Analysis'!D22 -> 424511118 | D23: =+'Bank Liabilities Analysis'!E22-'Bank Liabilities Analysis'!F22 -> 0 | E23: =+'Bank Liabilities Analysis'!G22-'Bank Liabilities Analysis'!H22 -> 0 | F23: =+'Bank Liabilities Analysis'!I22-'Bank Liabilities Analysis'!J22 -> 0 | G23: =+'Bank Liabilities Analysis'!K22-'Bank Liabilities Analysis'!L22 -> 0 | H23: =+'Bank Liabilities Analysis'!M22-'Bank Liabilities Analysis'!N22 -> 0 | I23: =+'Bank Liabilities Analysis'!O22-'Bank Liabilities Analysis'!P22 -> 0 | J23: =+'Bank Liabilities Analysis'!Q22-'Bank Liabilities Analysis'!R22 -> 0 | K23: =+C23+D23+E23+F23+G23+H23+I23+J23 -> 424511118
A24: 3. | B24: Бошқа банклар ва молиявий ташкилотларга тўланиши лозим бўлган маблағлар | C24: =SUM(C25:C29)-C26 -> 5737970 | D24: =SUM(D25:D29)-D26 -> 0 | E24: =SUM(E25:E29)-E26 -> 249512 | F24: =SUM(F25:F29)-F26 -> 180000000 | G24: =SUM(G25:G29)-G26 -> 92321000 | H24: =SUM(H25:H29)-H26 -> 11718754 | I24: =SUM(I25:I29)-I26 -> 154155911 | J24: =SUM(J25:J29)-J26 -> 147918724 | K24: =+C24+D24+E24+F24+G24+H24+I24+J24 -> 592101871
A25: 3.1 | B25: Бошқа банкларнинг вакиллик ҳисобварақларига тўланиши лозим бўлган маблағлар | C25: =+'Bank Liabilities Analysis'!C24-'Bank Liabilities Analysis'!D24 -> 587877 | D25: =+'Bank Liabilities Analysis'!E24-'Bank Liabilities Analysis'!F24 -> 0 | E25: =+'Bank Liabilities Analysis'!G24-'Bank Liabilities Analysis'!H24 -> 0 | F25: =+'Bank Liabilities Analysis'!I24-'Bank Liabilities Analysis'!J24 -> 0 | G25: =+'Bank Liabilities Analysis'!K24-'Bank Liabilities Analysis'!L24 -> 0 | H25: =+'Bank Liabilities Analysis'!M24-'Bank Liabilities Analysis'!N24 -> 0 | I25: =+'Bank Liabilities Analysis'!O24-'Bank Liabilities Analysis'!P24 -> 0 | J25: =+'Bank Liabilities Analysis'!Q24-'Bank Liabilities Analysis'!R24 -> 0 | K25: =+C25+D25+E25+F25+G25+H25+I25+J25 -> 587877 | L25: 1 | M25: =C25*L25 -> 587877
A26: 3.1.1 | B26: шу жумладан, махаллий банкларнинг вакиллик ҳисобварақларига тўланиши лозим бўлган маблағлар | C26: =+'Bank Liabilities Analysis'!C25-'Bank Liabilities Analysis'!D25 -> 0 | D26: =+'Bank Liabilities Analysis'!E25-'Bank Liabilities Analysis'!F25 -> 0 | E26: =+'Bank Liabilities Analysis'!G25-'Bank Liabilities Analysis'!H25 -> 0 | F26: =+'Bank Liabilities Analysis'!I25-'Bank Liabilities Analysis'!J25 -> 0 | G26: =+'Bank Liabilities Analysis'!K25-'Bank Liabilities Analysis'!L25 -> 0 | H26: =+'Bank Liabilities Analysis'!M25-'Bank Liabilities Analysis'!N25 -> 0 | I26: =+'Bank Liabilities Analysis'!O25-'Bank Liabilities Analysis'!P25 -> 0 | J26: =+'Bank Liabilities Analysis'!Q25-'Bank Liabilities Analysis'!R25 -> 0 | K26: =+C26+D26+E26+F26+G26+H26+I26+J26 -> 0
A27: 3.2 | B27: Бошқа банкларнинг ҳисобварақлари - Депозитлар | C27: =+'Bank Liabilities Analysis'!C26-'Bank Liabilities Analysis'!D26 -> 410000 | D27: =+'Bank Liabilities Analysis'!E26-'Bank Liabilities Analysis'!F26 -> 0 | E27: =+'Bank Liabilities Analysis'!G26-'Bank Liabilities Analysis'!H26 -> 249512 | F27: =+'Bank Liabilities Analysis'!I26-'Bank Liabilities Analysis'!J26 -> 180000000 | G27: =+'Bank Liabilities Analysis'!K26-'Bank Liabilities Analysis'!L26 -> 92321000 | H27: =+'Bank Liabilities Analysis'!M26-'Bank Liabilities Analysis'!N26 -> 11718754 | I27: =+'Bank Liabilities Analysis'!O26-'Bank Liabilities Analysis'!P26 -> 154155911 | J27: =+'Bank Liabilities Analysis'!Q26-'Bank Liabilities Analysis'!R26 -> 147918724 | K27: =+C27+D27+E27+F27+G27+H27+I27+J27 -> 586773901 | L27: 1 | M27: =(C27+D27+E27)*L27 -> 659512
A28: 3.3 | B28: Банк карталаридан амалга оширилган тўловлар бўйича банкларга тўланиши лозим бўлган маблағлар | C28: =+'Bank Liabilities Analysis'!C27-'Bank Liabilities Analysis'!D27 -> 4740093 | D28: =+'Bank Liabilities Analysis'!E27-'Bank Liabilities Analysis'!F27 -> 0 | E28: =+'Bank Liabilities Analysis'!G27-'Bank Liabilities Analysis'!H27 -> 0 | F28: =+'Bank Liabilities Analysis'!I27-'Bank Liabilities Analysis'!J27 -> 0 | G28: =+'Bank Liabilities Analysis'!K27-'Bank Liabilities Analysis'!L27 -> 0 | H28: =+'Bank Liabilities Analysis'!M27-'Bank Liabilities Analysis'!N27 -> 0 | I28: =+'Bank Liabilities Analysis'!O27-'Bank Liabilities Analysis'!P27 -> 0 | J28: =+'Bank Liabilities Analysis'!Q27-'Bank Liabilities Analysis'!R27 -> 0 | K28: =+C28+D28+E28+F28+G28+H28+I28+J28 -> 4740093 | L28: 1 | M28: =(C28+D28+E28)*L28 -> 4740093
A29: 3.4 | B29: Бошқа моддалар | C29: =+'Bank Liabilities Analysis'!C28-'Bank Liabilities Analysis'!D28 -> 0 | D29: =+'Bank Liabilities Analysis'!E28-'Bank Liabilities Analysis'!F28 -> 0 | E29: =+'Bank Liabilities Analysis'!G28-'Bank Liabilities Analysis'!H28 -> 0 | F29: =+'Bank Liabilities Analysis'!I28-'Bank Liabilities Analysis'!J28 -> 0 | G29: =+'Bank Liabilities Analysis'!K28-'Bank Liabilities Analysis'!L28 -> 0 | H29: =+'Bank Liabilities Analysis'!M28-'Bank Liabilities Analysis'!N28 -> 0 | I29: =+'Bank Liabilities Analysis'!O28-'Bank Liabilities Analysis'!P28 -> 0 | J29: =+'Bank Liabilities Analysis'!Q28-'Bank Liabilities Analysis'!R28 -> 0 | K29: =+C29+D29+E29+F29+G29+H29+I29+J29 -> 0 | L29: 1 | M29: =(C29+D29+E29)*L29 -> 0
A30: 4. | B30: Банкнинг тўланмаган акцептлари | C30: =+'Bank Liabilities Analysis'!C29-'Bank Liabilities Analysis'!D29 -> 0 | D30: =+'Bank Liabilities Analysis'!E29-'Bank Liabilities Analysis'!F29 -> 0 | E30: =+'Bank Liabilities Analysis'!G29-'Bank Liabilities Analysis'!H29 -> 0 | F30: =+'Bank Liabilities Analysis'!I29-'Bank Liabilities Analysis'!J29 -> 0 | G30: =+'Bank Liabilities Analysis'!K29-'Bank Liabilities Analysis'!L29 -> 0 | H30: =+'Bank Liabilities Analysis'!M29-'Bank Liabilities Analysis'!N29 -> 0 | I30: =+'Bank Liabilities Analysis'!O29-'Bank Liabilities Analysis'!P29 -> 0 | J30: =+'Bank Liabilities Analysis'!Q29-'Bank Liabilities Analysis'!R29 -> 0 | K30: =+C30+D30+E30+F30+G30+H30+I30+J30 -> 0 | L30: 1 | M30: =(C30+D30+E30)*L30 -> 0
A31: 5. | B31: Олинган кредит ва лизинглар (молиявий ижара) бўйича мажбуриятлар | C31: =+'Bank Liabilities Analysis'!C30-'Bank Liabilities Analysis'!D30 -> 0 | D31: =+'Bank Liabilities Analysis'!E30-'Bank Liabilities Analysis'!F30 -> 0 | E31: =+'Bank Liabilities Analysis'!G30-'Bank Liabilities Analysis'!H30 -> 2132642 | F31: =+'Bank Liabilities Analysis'!I30-'Bank Liabilities Analysis'!J30 -> 7211132 | G31: =+'Bank Liabilities Analysis'!K30-'Bank Liabilities Analysis'!L30 -> 47978143 | H31: =+'Bank Liabilities Analysis'!M30-'Bank Liabilities Analysis'!N30 -> 58825353 | I31: =+'Bank Liabilities Analysis'!O30-'Bank Liabilities Analysis'!P30 -> 128080376 | J31: =+'Bank Liabilities Analysis'!Q30-'Bank Liabilities Analysis'!R30 -> 394362183 | K31: =+C31+D31+E31+F31+G31+H31+I31+J31 -> 638589829 | L31: 0.05 | M31: =+K31*L31 -> 31929491
A32: 6. | B32: Банк томонидан чиқарилган қимматли қоғозлар | C32: =+'Bank Liabilities Analysis'!C31-'Bank Liabilities Analysis'!D31 -> 0 | D32: =+'Bank Liabilities Analysis'!E31-'Bank Liabilities Analysis'!F31 -> 0 | E32: =+'Bank Liabilities Analysis'!G31-'Bank Liabilities Analysis'!H31 -> 0 | F32: =+'Bank Liabilities Analysis'!I31-'Bank Liabilities Analysis'!J31 -> 0 | G32: =+'Bank Liabilities Analysis'!K31-'Bank Liabilities Analysis'!L31 -> 0 | H32: =+'Bank Liabilities Analysis'!M31-'Bank Liabilities Analysis'!N31 -> 0 | I32: =+'Bank Liabilities Analysis'!O31-'Bank Liabilities Analysis'!P31 -> 0 | J32: =+'Bank Liabilities Analysis'!Q31-'Bank Liabilities Analysis'!R31 -> 0 | K32: =+C32+D32+E32+F32+G32+H32+I32+J32 -> 0 | L32: 1 | M32: =(C32+D32+E32)*L32 -> 0
A33: 7. | B33: Субординар қарз мажбуриятлари | C33: =+'Bank Liabilities Analysis'!C32-'Bank Liabilities Analysis'!D32 -> 0 | D33: =+'Bank Liabilities Analysis'!E32-'Bank Liabilities Analysis'!F32 -> 0 | E33: =+'Bank Liabilities Analysis'!G32-'Bank Liabilities Analysis'!H32 -> 0 | F33: =+'Bank Liabilities Analysis'!I32-'Bank Liabilities Analysis'!J32 -> 0 | G33: =+'Bank Liabilities Analysis'!K32-'Bank Liabilities Analysis'!L32 -> 0 | H33: =+'Bank Liabilities Analysis'!M32-'Bank Liabilities Analysis'!N32 -> 0 | I33: =+'Bank Liabilities Analysis'!O32-'Bank Liabilities Analysis'!P32 -> 0 | J33: =+'Bank Liabilities Analysis'!Q32-'Bank Liabilities Analysis'!R32 -> 0 | K33: =+C33+D33+E33+F33+G33+H33+I33+J33 -> 0 | L33: 1 | M33: =(C33+D33+E33)*L33 -> 0
A34: 8. | B34: РЕПО битимлари бўйича сотилган қимматли қоғозлар | C34: =+'Bank Liabilities Analysis'!C33-'Bank Liabilities Analysis'!D33 -> 0 | D34: =+'Bank Liabilities Analysis'!E33-'Bank Liabilities Analysis'!F33 -> 801459811 | E34: =+'Bank Liabilities Analysis'!G33-'Bank Liabilities Analysis'!H33 -> 0 | F34: =+'Bank Liabilities Analysis'!I33-'Bank Liabilities Analysis'!J33 -> 0 | G34: =+'Bank Liabilities Analysis'!K33-'Bank Liabilities Analysis'!L33 -> 0 | H34: =+'Bank Liabilities Analysis'!M33-'Bank Liabilities Analysis'!N33 -> 0 | I34: =+'Bank Liabilities Analysis'!O33-'Bank Liabilities Analysis'!P33 -> 0 | J34: =+'Bank Liabilities Analysis'!Q33-'Bank Liabilities Analysis'!R33 -> 0 | K34: =+C34+D34+E34+F34+G34+H34+I34+J34 -> 801459811
A35: 8.1 | B35: РЕПО битимлари бўйича сотилган юқори ликвидли қимматли қоғозлар | C35: =+'Bank Liabilities Analysis'!C34-'Bank Liabilities Analysis'!D34 -> 0 | D35: =+'Bank Liabilities Analysis'!E34-'Bank Liabilities Analysis'!F34 -> 801459811 | E35: =+'Bank Liabilities Analysis'!G34-'Bank Liabilities Analysis'!H34 -> 0 | F35: =+'Bank Liabilities Analysis'!I34-'Bank Liabilities Analysis'!J34 -> 0 | G35: =+'Bank Liabilities Analysis'!K34-'Bank Liabilities Analysis'!L34 -> 0 | H35: =+'Bank Liabilities Analysis'!M34-'Bank Liabilities Analysis'!N34 -> 0 | I35: =+'Bank Liabilities Analysis'!O34-'Bank Liabilities Analysis'!P34 -> 0 | J35: =+'Bank Liabilities Analysis'!Q34-'Bank Liabilities Analysis'!R34 -> 0 | K35: =+C35+D35+E35+F35+G35+H35+I35+J35 -> 801459811 | L35: 1 | M35: =(C35+D35+E35)*L35 -> 801459811
A36: 8.2 | B36: РЕПО битимлари бўйича сотилган бошқа қимматли қоғозлар | C36: =+'Bank Liabilities Analysis'!C35-'Bank Liabilities Analysis'!D35 -> 0 | D36: =+'Bank Liabilities Analysis'!E35-'Bank Liabilities Analysis'!F35 -> 0 | E36: =+'Bank Liabilities Analysis'!G35-'Bank Liabilities Analysis'!H35 -> 0 | F36: =+'Bank Liabilities Analysis'!I35-'Bank Liabilities Analysis'!J35 -> 0 | G36: =+'Bank Liabilities Analysis'!K35-'Bank Liabilities Analysis'!L35 -> 0 | H36: =+'Bank Liabilities Analysis'!M35-'Bank Liabilities Analysis'!N35 -> 0 | I36: =+'Bank Liabilities Analysis'!O35-'Bank Liabilities Analysis'!P35 -> 0 | J36: =+'Bank Liabilities Analysis'!Q35-'Bank Liabilities Analysis'!R35 -> 0 | K36: =+C36+D36+E36+F36+G36+H36+I36+J36 -> 0 | L36: 1 | M36: =(C36+D36+E36)*L36 -> 0
A37: 9. | B37: Ҳосилавий инструментлар бўйича ревальвация натижасида амалга ошмаган зарарлар ва бошқа муддати узайтирилган даромадлар | C37: =+'Bank Liabilities Analysis'!C36-'Bank Liabilities Analysis'!D36 -> 7955 | D37: =+'Bank Liabilities Analysis'!E36-'Bank Liabilities Analysis'!F36 -> 0 | E37: =+'Bank Liabilities Analysis'!G36-'Bank Liabilities Analysis'!H36 -> 0 | F37: =+'Bank Liabilities Analysis'!I36-'Bank Liabilities Analysis'!J36 -> 0 | G37: =+'Bank Liabilities Analysis'!K36-'Bank Liabilities Analysis'!L36 -> 8983935 | H37: =+'Bank Liabilities Analysis'!M36-'Bank Liabilities Analysis'!N36 -> 0 | I37: =+'Bank Liabilities Analysis'!O36-'Bank Liabilities Analysis'!P36 -> 0 | J37: =+'Bank Liabilities Analysis'!Q36-'Bank Liabilities Analysis'!R36 -> 0 | K37: =+C37+D37+E37+F37+G37+H37+I37+J37 -> 8991890 | L37: 1 | M37: =+K37*L37 -> 8991890
A38: 10. | B38: Клиринг транзакциялари | C38: =+'Bank Liabilities Analysis'!C37-'Bank Liabilities Analysis'!D37 -> 324 | D38: =+'Bank Liabilities Analysis'!E37-'Bank Liabilities Analysis'!F37 -> 35250 | E38: =+'Bank Liabilities Analysis'!G37-'Bank Liabilities Analysis'!H37 -> 0 | F38: =+'Bank Liabilities Analysis'!I37-'Bank Liabilities Analysis'!J37 -> 0 | G38: =+'Bank Liabilities Analysis'!K37-'Bank Liabilities Analysis'!L37 -> 0 | H38: =+'Bank Liabilities Analysis'!M37-'Bank Liabilities Analysis'!N37 -> 0 | I38: =+'Bank Liabilities Analysis'!O37-'Bank Liabilities Analysis'!P37 -> 0 | J38: =+'Bank Liabilities Analysis'!Q37-'Bank Liabilities Analysis'!R37 -> 0 | K38: =+C38+D38+E38+F38+G38+H38+I38+J38 -> 35574 | L38: 1 | M38: =+K38*L38 -> 35574
A39: 11. | B39: Тўланиши лозим бўлган ҳисобланган фоизлар | C39: =+'Bank Liabilities Analysis'!C38-'Bank Liabilities Analysis'!D38 -> 4020690 | D39: =+'Bank Liabilities Analysis'!E38-'Bank Liabilities Analysis'!F38 -> 13199087 | E39: =+'Bank Liabilities Analysis'!G38-'Bank Liabilities Analysis'!H38 -> 24976849 | F39: =+'Bank Liabilities Analysis'!I38-'Bank Liabilities Analysis'!J38 -> 7235992 | G39: =+'Bank Liabilities Analysis'!K38-'Bank Liabilities Analysis'!L38 -> 755604 | H39: =+'Bank Liabilities Analysis'!M38-'Bank Liabilities Analysis'!N38 -> 136198 | I39: =+'Bank Liabilities Analysis'!O38-'Bank Liabilities Analysis'!P38 -> 96671 | J39: =+'Bank Liabilities Analysis'!Q38-'Bank Liabilities Analysis'!R38 -> 4946685 | K39: =+C39+D39+E39+F39+G39+H39+I39+J39 -> 55367776 | M39: =+C39+D39+E39 -> 42196626
A40: 11.1 | B40: Бош банк/филиалдан олинган ресурслар бўйича тўланиши лозим бўлган ҳисобланган фоизлар | C40: =+'Bank Liabilities Analysis'!C39-'Bank Liabilities Analysis'!D39 -> 0 | D40: =+'Bank Liabilities Analysis'!E39-'Bank Liabilities Analysis'!F39 -> 0 | E40: =+'Bank Liabilities Analysis'!G39-'Bank Liabilities Analysis'!H39 -> 0 | F40: =+'Bank Liabilities Analysis'!I39-'Bank Liabilities Analysis'!J39 -> 0 | G40: =+'Bank Liabilities Analysis'!K39-'Bank Liabilities Analysis'!L39 -> 0 | H40: =+'Bank Liabilities Analysis'!M39-'Bank Liabilities Analysis'!N39 -> 0 | I40: =+'Bank Liabilities Analysis'!O39-'Bank Liabilities Analysis'!P39 -> 0 | J40: =+'Bank Liabilities Analysis'!Q39-'Bank Liabilities Analysis'!R39 -> 0 | K40: =+C40+D40+E40+F40+G40+H40+I40+J40 -> 0 | M40: =+C40+D40+E40 -> 0
A41: 11.2 | B41: Бошқа банкларга тўланиши лозим бўлган ҳисобланган фоизлар | C41: =+'Bank Liabilities Analysis'!C40-'Bank Liabilities Analysis'!D40 -> 0 | D41: =+'Bank Liabilities Analysis'!E40-'Bank Liabilities Analysis'!F40 -> 0 | E41: =+'Bank Liabilities Analysis'!G40-'Bank Liabilities Analysis'!H40 -> 0 | F41: =+'Bank Liabilities Analysis'!I40-'Bank Liabilities Analysis'!J40 -> 4981 | G41: =+'Bank Liabilities Analysis'!K40-'Bank Liabilities Analysis'!L40 -> 1504852 | H41: =+'Bank Liabilities Analysis'!M40-'Bank Liabilities Analysis'!N40 -> 0 | I41: =+'Bank Liabilities Analysis'!O40-'Bank Liabilities Analysis'!P40 -> 406945 | J41: =+'Bank Liabilities Analysis'!Q40-'Bank Liabilities Analysis'!R40 -> 991137 | K41: =+C41+D41+E41+F41+G41+H41+I41+J41 -> 2907915 | M41: =+C41+D41+E41 -> 0
A42: 12. | B42: Бошқа мажбуриятлар | C42: =+'Bank Liabilities Analysis'!C41-'Bank Liabilities Analysis'!D41 -> 279790203 | D42: =+'Bank Liabilities Analysis'!E41-'Bank Liabilities Analysis'!F41 -> 9012168 | E42: =+'Bank Liabilities Analysis'!G41-'Bank Liabilities Analysis'!H41 -> 19108 | F42: =+'Bank Liabilities Analysis'!I41-'Bank Liabilities Analysis'!J41 -> 122437 | G42: =+'Bank Liabilities Analysis'!K41-'Bank Liabilities Analysis'!L41 -> 128484 | H42: =+'Bank Liabilities Analysis'!M41-'Bank Liabilities Analysis'!N41 -> 338206 | I42: =+'Bank Liabilities Analysis'!O41-'Bank Liabilities Analysis'!P41 -> 2971270 | J42: =+'Bank Liabilities Analysis'!Q41-'Bank Liabilities Analysis'!R41 -> 7562261 | K42: =+C42+D42+E42+F42+G42+H42+I42+J42 -> 299944137 | L42: 1 | M42: =(C42+D42+E42)*L42 -> 288821479
A43: 13 | B43: ЖАМИ МАЖБУРИЯТЛАР | C43: =+C21+C22+C24+C30+C31+C32+C33+C34+C37+C38+C39+C40+C41+C42 -> 4134256850 | D43: =+D21+D22+D24+D30+D31+D32+D33+D34+D37+D38+D39+D40+D41+D42 -> 896041819 | E43: =+E21+E22+E24+E30+E31+E32+E33+E34+E37+E38+E39+E40+E41+E42 -> 191936768 | F43: =+F21+F22+F24+F30+F31+F32+F33+F34+F37+F38+F39+F40+F41+F42 -> 479926424 | G43: =+G21+G22+G24+G30+G31+G32+G33+G34+G37+G38+G39+G40+G41+G42 -> 1564809964 | H43: =+H21+H22+H24+H30+H31+H32+H33+H34+H37+H38+H39+H40+H41+H42 -> 2444520972 | I43: =+I21+I22+I24+I30+I31+I32+I33+I34+I37+I38+I39+I40+I41+I42 -> 3781526639 | J43: =+J21+J22+J24+J30+J31+J32+J33+J34+J37+J38+J39+J40+J41+J42 -> 1641795464 | K43: =+K21+K22+K24+K30+K31+K32+K33+K34+K37+K38+K39+K40+K41+K42 -> 15134814900 | L43: отток | M43: =SUM(M8:M42) -> 3.0260581e+09 | N43: =+Balance!D63 -> 15134814900
B44: шундан, | K44: =+C44+D44+E44+F44+G44+H44+I44+J44 -> 0 | N44: =+K43-N43 -> 0
B45: Ўзбекистон Республикаси Молия вазирлиги маблағлари, шундан | C45: =+C46+C47 -> 0 | D45: =+D46+D47 -> 50000000 | E45: =+E46+E47 -> 110409257 | F45: =+F46+F47 -> 666431 | G45: =+G46+G47 -> 265683841 | H45: =+H46+H47 -> 496443199 | I45: =+I46+I47 -> 10813347 | J45: =+J46+J47 -> 793700834 | K45: =+C45+D45+E45+F45+G45+H45+I45+J45 -> 1727716909
B46: Кредит ва лизинглар | C46: =+'Bank Liabilities Analysis'!C45-'Bank Liabilities Analysis'!D45 -> 0 | D46: =+'Bank Liabilities Analysis'!E45-'Bank Liabilities Analysis'!F45 -> 0 | E46: =+'Bank Liabilities Analysis'!G45-'Bank Liabilities Analysis'!H45 -> 242590 | F46: =+'Bank Liabilities Analysis'!I45-'Bank Liabilities Analysis'!J45 -> 666431 | G46: =+'Bank Liabilities Analysis'!K45-'Bank Liabilities Analysis'!L45 -> 683841 | H46: =+'Bank Liabilities Analysis'!M45-'Bank Liabilities Analysis'!N45 -> 2043199 | I46: =+'Bank Liabilities Analysis'!O45-'Bank Liabilities Analysis'!P45 -> 3813348 | J46: =+'Bank Liabilities Analysis'!Q45-'Bank Liabilities Analysis'!R45 -> 105911958 | K46: =+C46+D46+E46+F46+G46+H46+I46+J46 -> 113361367
B47: Депозит маблағлар | C47: =+'Bank Liabilities Analysis'!C46-'Bank Liabilities Analysis'!D46 -> 0 | D47: =+'Bank Liabilities Analysis'!E46-'Bank Liabilities Analysis'!F46 -> 50000000 | E47: =+'Bank Liabilities Analysis'!G46-'Bank Liabilities Analysis'!H46 -> 110166667 | F47: =+'Bank Liabilities Analysis'!I46-'Bank Liabilities Analysis'!J46 -> 0 | G47: =+'Bank Liabilities Analysis'!K46-'Bank Liabilities Analysis'!L46 -> 265000000 | H47: =+'Bank Liabilities Analysis'!M46-'Bank Liabilities Analysis'!N46 -> 494400000 | I47: =+'Bank Liabilities Analysis'!O46-'Bank Liabilities Analysis'!P46 -> 6999999 | J47: =+'Bank Liabilities Analysis'!Q46-'Bank Liabilities Analysis'!R46 -> 687788876 | K47: =+C47+D47+E47+F47+G47+H47+I47+J47 -> 1614355542
B48: Бюджетдан ташқари фондларнинг маблағлари, шундан | C48: =+C49+C50 -> 0 | D48: =+D49+D50 -> 0 | E48: =+E49+E50 -> 0 | F48: =+F49+F50 -> 0 | G48: =+G49+G50 -> 0 | H48: =+H49+H50 -> 0 | I48: =+I49+I50 -> 0 | J48: =+J49+J50 -> 0 | K48: =+C48+D48+E48+F48+G48+H48+I48+J48 -> 0
B49: Кредит ва лизинглар | C49: =+'Bank Liabilities Analysis'!C48-'Bank Liabilities Analysis'!D48 -> 0 | D49: =+'Bank Liabilities Analysis'!E48-'Bank Liabilities Analysis'!F48 -> 0 | E49: =+'Bank Liabilities Analysis'!G48-'Bank Liabilities Analysis'!H48 -> 0 | F49: =+'Bank Liabilities Analysis'!I48-'Bank Liabilities Analysis'!J48 -> 0 | G49: =+'Bank Liabilities Analysis'!K48-'Bank Liabilities Analysis'!L48 -> 0 | H49: =+'Bank Liabilities Analysis'!M48-'Bank Liabilities Analysis'!N48 -> 0 | I49: =+'Bank Liabilities Analysis'!O48-'Bank Liabilities Analysis'!P48 -> 0 | J49: =+'Bank Liabilities Analysis'!Q48-'Bank Liabilities Analysis'!R48 -> 0 | K49: =+C49+D49+E49+F49+G49+H49+I49+J49 -> 0
B50: Депозит маблағлар | C50: =+'Bank Liabilities Analysis'!C49-'Bank Liabilities Analysis'!D49 -> 0 | D50: =+'Bank Liabilities Analysis'!E49-'Bank Liabilities Analysis'!F49 -> 0 | E50: =+'Bank Liabilities Analysis'!G49-'Bank Liabilities Analysis'!H49 -> 0 | F50: =+'Bank Liabilities Analysis'!I49-'Bank Liabilities Analysis'!J49 -> 0 | G50: =+'Bank Liabilities Analysis'!K49-'Bank Liabilities Analysis'!L49 -> 0 | H50: =+'Bank Liabilities Analysis'!M49-'Bank Liabilities Analysis'!N49 -> 0 | I50: =+'Bank Liabilities Analysis'!O49-'Bank Liabilities Analysis'!P49 -> 0 | J50: =+'Bank Liabilities Analysis'!Q49-'Bank Liabilities Analysis'!R49 -> 0 | K50: =+C50+D50+E50+F50+G50+H50+I50+J50 -> 0
B51: Ўзбекистон тикланиш ва тараққиёт фонди (ФРРУ), шундан | C51: =+C52+C53 -> 0 | D51: =+D52+D53 -> 0 | E51: =+E52+E53 -> 0 | F51: =+F52+F53 -> 0 | G51: =+G52+G53 -> 40801111 | H51: =+H52+H53 -> 40801111 | I51: =+I52+I53 -> 95715518 | J51: =+J52+J53 -> 226933144 | K51: =+C51+D51+E51+F51+G51+H51+I51+J51 -> 404250884
B52: Кредит ва лизинглар | C52: =+'Bank Liabilities Analysis'!C51-'Bank Liabilities Analysis'!D51 -> 0 | D52: =+'Bank Liabilities Analysis'!E51-'Bank Liabilities Analysis'!F51 -> 0 | E52: =+'Bank Liabilities Analysis'!G51-'Bank Liabilities Analysis'!H51 -> 0 | F52: =+'Bank Liabilities Analysis'!I51-'Bank Liabilities Analysis'!J51 -> 0 | G52: =+'Bank Liabilities Analysis'!K51-'Bank Liabilities Analysis'!L51 -> 40801111 | H52: =+'Bank Liabilities Analysis'!M51-'Bank Liabilities Analysis'!N51 -> 40801111 | I52: =+'Bank Liabilities Analysis'!O51-'Bank Liabilities Analysis'!P51 -> 95715518 | J52: =+'Bank Liabilities Analysis'!Q51-'Bank Liabilities Analysis'!R51 -> 226933144 | K52: =+C52+D52+E52+F52+G52+H52+I52+J52 -> 404250884
B53: Депозит маблағлар | C53: =+'Bank Liabilities Analysis'!C52-'Bank Liabilities Analysis'!D52 -> 0 | D53: =+'Bank Liabilities Analysis'!E52-'Bank Liabilities Analysis'!F52 -> 0 | E53: =+'Bank Liabilities Analysis'!G52-'Bank Liabilities Analysis'!H52 -> 0 | F53: =+'Bank Liabilities Analysis'!I52-'Bank Liabilities Analysis'!J52 -> 0 | G53: =+'Bank Liabilities Analysis'!K52-'Bank Liabilities Analysis'!L52 -> 0 | H53: =+'Bank Liabilities Analysis'!M52-'Bank Liabilities Analysis'!N52 -> 0 | I53: =+'Bank Liabilities Analysis'!O52-'Bank Liabilities Analysis'!P52 -> 0 | J53: =+'Bank Liabilities Analysis'!Q52-'Bank Liabilities Analysis'!R52 -> 0 | K53: =+C53+D53+E53+F53+G53+H53+I53+J53 -> 0
B54: Хорижий банклар, шундан | C54: =+C55+C56 -> 0 | D54: =+D55+D56 -> 0 | E54: =+E55+E56 -> 0 | F54: =+F55+F56 -> 0 | G54: =+G55+G56 -> 0 | H54: =+H55+H56 -> 0 | I54: =+I55+I56 -> 0 | J54: =+J55+J56 -> 0 | K54: =+C54+D54+E54+F54+G54+H54+I54+J54 -> 0
B55: Кредит ва лизинглар | C55: =+'Bank Liabilities Analysis'!C54-'Bank Liabilities Analysis'!D54 -> 0 | D55: =+'Bank Liabilities Analysis'!E54-'Bank Liabilities Analysis'!F54 -> 0 | E55: =+'Bank Liabilities Analysis'!G54-'Bank Liabilities Analysis'!H54 -> 0 | F55: =+'Bank Liabilities Analysis'!I54-'Bank Liabilities Analysis'!J54 -> 0 | G55: =+'Bank Liabilities Analysis'!K54-'Bank Liabilities Analysis'!L54 -> 0 | H55: =+'Bank Liabilities Analysis'!M54-'Bank Liabilities Analysis'!N54 -> 0 | I55: =+'Bank Liabilities Analysis'!O54-'Bank Liabilities Analysis'!P54 -> 0 | J55: =+'Bank Liabilities Analysis'!Q54-'Bank Liabilities Analysis'!R54 -> 0 | K55: =+C55+D55+E55+F55+G55+H55+I55+J55 -> 0
B56: Депозит маблағлар | C56: =+'Bank Liabilities Analysis'!C55-'Bank Liabilities Analysis'!D55 -> 0 | D56: =+'Bank Liabilities Analysis'!E55-'Bank Liabilities Analysis'!F55 -> 0 | E56: =+'Bank Liabilities Analysis'!G55-'Bank Liabilities Analysis'!H55 -> 0 | F56: =+'Bank Liabilities Analysis'!I55-'Bank Liabilities Analysis'!J55 -> 0 | G56: =+'Bank Liabilities Analysis'!K55-'Bank Liabilities Analysis'!L55 -> 0 | H56: =+'Bank Liabilities Analysis'!M55-'Bank Liabilities Analysis'!N55 -> 0 | I56: =+'Bank Liabilities Analysis'!O55-'Bank Liabilities Analysis'!P55 -> 0 | J56: =+'Bank Liabilities Analysis'!Q55-'Bank Liabilities Analysis'!R55 -> 0 | K56: =+C56+D56+E56+F56+G56+H56+I56+J56 -> 0
B57: Бошқа халқаро молия ташкилотлари маблағлари, шундан, | C57: =+C58+C59 -> 0 | D57: =+D58+D59 -> 0 | E57: =+E58+E59 -> 0 | F57: =+F58+F59 -> 0 | G57: =+G58+G59 -> 0 | H57: =+H58+H59 -> 0 | I57: =+I58+I59 -> 0 | J57: =+J58+J59 -> 0 | K57: =+C57+D57+E57+F57+G57+H57+I57+J57 -> 0
B58: Кредит ва лизинглар | C58: =+'Bank Liabilities Analysis'!C57-'Bank Liabilities Analysis'!D57 -> 0 | D58: =+'Bank Liabilities Analysis'!E57-'Bank Liabilities Analysis'!F57 -> 0 | E58: =+'Bank Liabilities Analysis'!G57-'Bank Liabilities Analysis'!H57 -> 0 | F58: =+'Bank Liabilities Analysis'!I57-'Bank Liabilities Analysis'!J57 -> 0 | G58: =+'Bank Liabilities Analysis'!K57-'Bank Liabilities Analysis'!L57 -> 0 | H58: =+'Bank Liabilities Analysis'!M57-'Bank Liabilities Analysis'!N57 -> 0 | I58: =+'Bank Liabilities Analysis'!O57-'Bank Liabilities Analysis'!P57 -> 0 | J58: =+'Bank Liabilities Analysis'!Q57-'Bank Liabilities Analysis'!R57 -> 0 | K58: =+C58+D58+E58+F58+G58+H58+I58+J58 -> 0
B59: Депозит маблағлар | C59: =+'Bank Liabilities Analysis'!C58-'Bank Liabilities Analysis'!D58 -> 0 | D59: =+'Bank Liabilities Analysis'!E58-'Bank Liabilities Analysis'!F58 -> 0 | E59: =+'Bank Liabilities Analysis'!G58-'Bank Liabilities Analysis'!H58 -> 0 | F59: =+'Bank Liabilities Analysis'!I58-'Bank Liabilities Analysis'!J58 -> 0 | G59: =+'Bank Liabilities Analysis'!K58-'Bank Liabilities Analysis'!L58 -> 0 | H59: =+'Bank Liabilities Analysis'!M58-'Bank Liabilities Analysis'!N58 -> 0 | I59: =+'Bank Liabilities Analysis'!O58-'Bank Liabilities Analysis'!P58 -> 0 | J59: =+'Bank Liabilities Analysis'!Q58-'Bank Liabilities Analysis'!R58 -> 0 | K59: =+C59+D59+E59+F59+G59+H59+I59+J59 -> 0
B61: Бошқарув Раис имзоси:
B63: Бош бухгалтер имзоси:

Sheet Commitments
A1: БАЛАНСДАН ТАШҚАРИ ҲИСОБВАРАҚЛАР ТЎҒРИСИДА ҲИСОБОТ | E1: 19-жадвал
B2: =Balance!B3 -> Банк номи | C2: =+Balance!D3 -> 45657 | E2: =+Balance!E3 -> минг сўмда
A3: № | B3: Кўрсаткичлар | C3: Жами | D3: миллий валютада | E3: хорижий валютада (сўм экв.)
A4: 1. | B4: Банкнинг кредит ва лизинг бериш бўйича мажбуриятлари | C4: =+D4+E4 -> 840032316 | D4: 437054878 | E4: 402977438 | F4: =+'Bank Assets Analysis'!S49 -> 840032316 | G4: =+'Bank Assets Analysis'!T49 -> 437054878 | H4: =+'Bank Assets Analysis'!U49 -> 402977438
A5: 1.1. | B5: шу жумладан, кредит линиялар маблағлари ҳисобидан (махсус шартлар билан) | C5: =+D5+E5 -> 2704256 | D5: 0 | E5: 2704256 | F5: =+'Bank Assets Analysis'!S50 -> 2704256 | G5: =+'Bank Assets Analysis'!T50 -> 0 | H5: =+'Bank Assets Analysis'!U50 -> 2704256
A7: 2. | B7: Кафолат ва кафилликлар | C7: =+D7+E7 -> 835644857 | D7: 34592971 | E7: 801051886 | F7: =+'Bank Assets Analysis'!S51 -> 835644857 | G7: =+'Bank Assets Analysis'!T51 -> 34592971 | H7: =+'Bank Assets Analysis'!U51 -> 801051886
A8: 2.1. | B8: шу жумладан депозитлар билан таъминланган | C8: =+D8+E8 -> 0 | D8: 0 | E8: 0 | F8: =+'Bank Assets Analysis'!S52 -> 0 | G8: =+'Bank Assets Analysis'!T52 -> 0 | H8: =+'Bank Assets Analysis'!U52 -> 0
A10: 3. | B10: Жами аккредитивлар | C10: =+D10+E10 -> 286897153 | D10: =SUM(D11:D14) -> 0 | E10: =SUM(E11:E14) -> 286897153
A11: 3.1. | B11: Тўловчи томонидан банкда очилган қопланган аккредитив | C11: =+D11+E11 -> 91600467 | D11: 0 | E11: 91600467
A12: 3.2. | B12: Тақдим этувчига тратталарни тўлаган ҳолдаги импорт билан боғлиқ тўланмаган аккредитивлар | C12: =+D12+E12 -> 0 | D12: 0 | E12: 0
A13: 3.3. | B13: Муддатли тратталарга қарши қўйилган, импорт билан боғлиқ тўланмаган аккредитивлар | C13: =+D13+E13 -> 0 | D13: 0 | E13: 0
A14: 3.4. | B14: Бошқа аккредитивлар | C14: =+D14+E14 -> 195296686 | D14: 0 | E14: 195296686
A16: 4. | B16: Факторинг, инкассо ва савдони молиялаштириш | C16: =+D16+E16 -> 20696973 | D16: 20696973 | E16: 0
A18: 5. | B18: Жами бошқа барча балансдан ташқари ҳисобварақлар | C18: =+D18+E18 -> 2445917371 | D18: =SUM(D19:D24) -> 817029147 | E18: =SUM(E19:E24) -> 1628888224
A19: 5.1. | B19: Чет эл валюталари билан спот операциялари | C19: =+D19+E19 -> 0 | D19: 0 | E19: 0
A20: 5.2. | B20: Фоиз свопларининг шартли қиймати | C20: =+D20+E20 -> 0 | D20: 0 | E20: 0
A21: 5.3. | B21: Aйирбошлаш свопининг шартли қиймати (Валюта свопи) | C21: =+D21+E21 -> 0 | D21: 0 | E21: 0
A22: 5.4. | B22: Фьючерс, форвард ва опцион шартномалари | C22: =+D22+E22 -> 715785546 | D22: 0 | E22: 715785546
A23: 5.5. | B23: Кредитлар, қимматли қоғозлар ва бошқа активларни сотиб олиш бўйича мажбуриятлар | C23: =+D23+E23 -> 801459811 | D23: 801459811 | E23: 0
A24: 5.6. | B24: Бошқа балансдан ташқари ҳисобварақлар | C24: =+D24+E24 -> 928672014 | D24: 15569336 | E24: 913102678
A26: 6. | B26: Жами балансдан ташқари ҳисобварақлар | C26: =+C4+C7+C10+C16+C18 -> 4429188670 | D26: =+D4+D7+D10+D16+D18 -> 1309373969 | E26: =+E4+E7+E10+E16+E18 -> 3119814701
B28: Бошқарув Раис имзоси:
B30: Бош бухгалтер имзоси:

Sheet Deposits by Client
A1: МИЖОЗЛАР ТУРЛАРИГА КЎРА ДЕПОЗИТЛАР | D1: 14-жадвал
B2: =+Balance!B3 -> Банк номи | C2: =+Balance!D3 -> 45657 | D2: минг сўмда
A3: № | B3: Кўрсаткичлар | C3: Жами | D3: шундан, хорижий валютада (сўм экв.)
A4: 1. | B4: Талаб қилиб олингунча сақланадиган ва бошқа депозитлар
A5: а. | B5: Ҳукумат | C5: 163081976 | D5: 1272017
A6: б. | B6: Жисмоний шахслар | C6: 1323418146 | D6: 220733373
A7: в. | B7: Давлат корхоналари | C7: 661659333 | D7: 126022369
A8: г. | B8: Чет эл капитали иштирокидаги корхоналар | C8: 162835882 | D8: 35082496
A9: д. | B9: Хусусий корхоналар | C9: 788753734 | D9: 97445478
A10: е. | B10: Бошқа талаб қилиб олингунча депозитлар | C10: 953051088 | D10: 152055836
A11: ж. | B11: Жами талаб қилиб олингунча сақланадиган ва бошқа депозитлар | C11: =SUM(C5:C10) -> 4052800159 | D11: =SUM(D5:D10) -> 632611569 | E11: =+'Bank Liabilities Analysis'!S15+'Bank Liabilities Analysis'!S7 -> 4052800159 | F11: =+'Bank Liabilities Analysis'!T15+'Bank Liabilities Analysis'!T7 -> 3420188590 | G11: =+'Bank Liabilities Analysis'!U15+'Bank Liabilities Analysis'!U7 -> 632611569
A13: 2. | B13: Муддатли депозитлар | E13: =+C11-E11 -> 0 | G13: =+D11-G11 -> 0
A14: а. | B14: Ҳукумат | C14: 3313945054 | D14: 421207648
A15: б. | B15: Жисмоний шахслар | C15: 3905919470 | D15: 182786996
A16: в. | B16: Давлат корхоналари | C16: 824875387 | D16: 0
A17: г. | B17: Чет эл капитали иштирокидаги корхоналар | C17: 124163981 | D17: 47418162
A18: д. | B18: Хусусий корхоналар | C18: 608862416 | D18: 14436459
A19: е. | B19: Бошқа муддатли депозитлар | C19: 984108347 | D19: 205309001
A20: ж. | B20: Жами муддатли депозитлар | C20: =SUM(C14:C19) -> 9761874655 | D20: =SUM(D14:D19) -> 871158266 | E20: =+'Bank Liabilities Analysis'!S12 -> 9761874655 | F20: =+'Bank Liabilities Analysis'!T12 -> 8890716389 | G20: =+'Bank Liabilities Analysis'!U12 -> 871158266
E21: =+C20-E20 -> 0 | G21: =+D20-G20 -> 0
A22: 3. | B22: Жами депозитлар | C22: =+C11+C20 -> 13814674814 | D22: =+D11+D20 -> 1503769835 | E22: =+'Bank Liabilities Analysis'!S20 -> 13814674814 | F22: =+'Bank Liabilities Analysis'!T20 -> 12310904979 | G22: =+'Bank Liabilities Analysis'!U20 -> 1503769835
E23: =+C22-E22 -> 0 | G23: =+D22-G22 -> 0
B24: Бошқарув Раис имзоси:
B26: Бош бухгалтер имзоси:

Sheet Investment Securities
A1: ҚИММАТЛИ ҚОҒОЗЛАР ВА УЛАРГА ҚИЛИНГАН ИНВЕСТИЦИЯЛАР ТЎҒРИСИДА ҲИСОБОТ | E1: 15-жадвал
A2: =Balance!B3 -> Банк номи | C2: =+Balance!D3 -> 45657 | E2: =+Balance!E3 -> минг сўмда
A3: Қисм 1 – Қарам хўжалик жамиятларига қилинган ҳамда амортизацияланган қиймати бўйича баҳоланадиган қарз қимматли қоғозларига қилинган инвестициялар | B3: Баланс қиймати | C3: шундан, | E3: Бозор қиймати
C4: миллий валютада | D4: хорижий валютада (сўм экв.)
A5: 1. Давлат қимматли қоғозлари | B5: =+C5+D5 -> 0 | C5: 0 | D5: 0 | E5: 0
A6: 2. Марказий банкнинг облигация ва бошқа қарз қимматли қоғозлари | B6: =+C6+D6 -> 0 | C6: 0 | D6: 0 | E6: 0
A7: 3. Корхоналарнинг қарз қимматли қоғозлари | B7: =+C7+D7 -> 0 | C7: 0 | D7: 0 | E7: 0
A8: 4. Еврооблигациялар | B8: =+C8+D8 -> 0 | C8: 0 | D8: 0 | E8: 0
A9: 5. Давлат улушига эга корхоналар акцияларига инвестициялар | B9: =+C9+D9 -> 86978807 | C9: 86978807 | D9: 0 | E9: 86978807
A10: 6. Хусусий корхоналар акцияларига инвестициялар | B10: =+C10+D10 -> 5603011 | C10: 5603011 | D10: 0 | E10: 5603011
A11: 7. Бошқа қимматли қоғозларга инвестициялар | B11: =+C11+D11 -> 299107040 | C11: 299107040 | D11: 0 | E11: 299107040
A12: 8. Жами инвестициялар | B12: =+C12+D12 -> 391688858 | C12: =SUM(C5:C11) -> 391688858 | D12: =SUM(D5:D11) -> 0 | E12: =SUM(E5:E11) -> 391688858
A13: 9. Инвестициялар бўйича харажатлар, дисконт ва мукофот | B13: =+C13+D13 -> 0 | C13: 0 | D13: 0 | E13: 0
A14: 10. Минус: Эҳтимолий йўқотишларга қарши захиралар | B14: =+C14+D14 -> 0 | C14: 0 | D14: 0
A15: 11. Инвестицияларнинг соф баланс қиймати | B15: =+C15+D15 -> 391688858 | C15: =C12+C13-C14 -> 391688858 | D15: =D12+D13-D14 -> 0
A17: Қисм – 2. Қимматли қоғозлар ва уларга қилинган инвестициялар | B17: Баланс қиймати | C17: шундан, | E17: Бозор қиймати
C18: миллий валютада | D18: хорижий валютада (сўм экв.)
A19: 1. Давлат хазина векселлари | B19: =+C19+D19 -> 0 | C19: 0 | D19: 0 | E19: 0
A20: 2. Давлат облигациялари | B20: =+C20+D20 -> 2166910000 | C20: 2166910000 | D20: 0 | E20: 2166910000
A21: 3. Марказий банкнинг облигациялари ва бошқа қарз қимматли қоғозлари | B21: =+C21+D21 -> 0 | C21: 0 | D21: 0 | E21: 0
A22: 4. Давлат улушига эга корхоналар қимматли қоғозлари | B22: =+C22+D22 -> 0 | C22: 0 | D22: 0 | E22: 0
A23: 5. Еврооблигациялар | B23: =+C23+D23 -> 0 | C23: 0 | D23: 0 | E23: 0
A24: 6. Корхоналар қимматли қоғозлари | B24: =+C24+D24 -> 0 | C24: 0 | D24: 0 | E24: 0
A25: 7. Бошқа қимматли қоғозлар | B25: =+C25+D25 -> 0 | C25: 0 | D25: 0 | E25: 0
A26: 8. Жами қимматли қоғозлар ва уларга қилинган инвестициялар | B26: =+C26+D26 -> 2166910000 | C26: =SUM(C19:C25) -> 2166910000 | D26: =SUM(D19:D25) -> 0 | E26: =SUM(E19:E25) -> 2166910000
A27: 9. Қимматли қоғозлар бўйича харажатлар, дисконт, мукофот ва уларнинг ҳаққоний қийматининг ўзгариши | B27: =+C27+D27 -> -53137165 | C27: -53137165 | D27: 0 | E27: -53137165
A28: 10. Минус: Эҳтимолий йўқотишларга қарши захиралар | B28: =+C28+D28 -> 0 | C28: 0 | D28: 0
A29: 11. Қимматли қоғозлар ва уларга қилинган инвестициялар, соф баланс қиймати | B29: =+C29+D29 -> 2113772835 | C29: =+C26+C27-C28 -> 2113772835 | D29: =+D26+D27-D28 -> 0
A31: Қисм – 3. Олди-сотдига мўлжалланган қимматбаҳо металлар, тошлар ва тангалар | B31: Баланс қиймати | C31: шундан, | E31: Бозор қиймати
C32: миллий валютада | D32: хорижий валютада (сўм экв.)
A34: 1. Қимматбаҳо металлар | B34: =+C34+D34 -> 0 | C34: 0 | D34: 0 | E34: 0
A35: 2. Қимматбаҳо тошлар | B35: =+C35+D35 -> 0 | C35: 0 | D35: 0 | E35: 0
A36: 3. Қимматбаҳо тангалар | B36: =+C36+D36 -> 251 | C36: 251 | D36: 0 | E36: 251
A37: 4. Қимматбаҳо металлар, тошлар ва тангалар жами | B37: =+C37+D37 -> 251 | C37: =SUM(C34:C36) -> 251 | D37: =SUM(D34:D36) -> 0 | E37: =SUM(E34:E36) -> 251
A38: 5. Минус: Эҳтимолий йўқотишларга қарши захиралар | B38: =+C38+D38 -> 0 | C38: 0 | D38: 0
A39: 6. Олди-сотдига мўлжалланган қимматбаҳо металлар, тошлар ва тангаларнинг соф баланс қиймати | B39: =+C39+D39 -> 251 | C39: =C37-C38 -> 251 | D39: =D37-D38 -> 0
A41: Бошқарув Раис имзоси:
A43: Бош бухгалтер имзоси:
