Workbook
Name jop: #REF!
Name kol: #REF!
Name RISKTOTASS: SUM('[6]Calculation of Risk Weighted As'!$C$38:$F$38)
Name RISKTOTASS: SUM('[7]Calculation of Risk Weighted As'!$C$41:$G$41)
Name TwentyLargestData: #REF!
Name Е: #REF!

Sheet Asset quality
A1: ИНФОРМАЦИЯ О КАЧЕСТВЕ АКТИВОВ, ОЦЕНИВАЕМЫХ В ЦЕЛЯХ СОЗДАНИЯ РЕЗЕРВА НА ВОЗМОЖНЫЕ ПОТЕРИ | R1: Таблица-2 | U1: №4
B3: "Микрокредитбанк" | P3: 44560 | S3: тыс. сум
A4: № | B4: Состав активов* | C4: Остаток | D4: Категория качества | I4: Просроченная задолженность (брутто) | N4: Резерв на возможные потери
I5: итого | J5: до 30 дней | K5: от 31 до 90 дней | L5: от 91 до 180 дней | M5: свыше 180 дней | N5: фактически сформированный
N6: итого | O6: по категориям качества
D7: I | E7: II | F7: III | G7: IV | H7: V | O7: I | P7: II | Q7: III | R7: IV | S7: V
A8: А | B8: Б | C8: В | D8: Г | E8: Д | F8: Е | G8: Ж | H8: З | I8: И | J8: К | K8: Л | L8: М | M8: Н | N8: О | O8: П | P8: Р | Q8: С | R8: Т | S8: У
B9: ВСЕГО АКТИВОВ | C9: =SUM(C10:C60) -> 13483353628 | D9: =SUM(D10:D60) -> 12077945561 | E9: =SUM(E10:E60) -> 987112434 | F9: =SUM(F10:F60) -> 238045786 | G9: =SUM(G10:G60) -> 79824583 | H9: =SUM(H10:H60) -> 324379884 | I9: =SUM(I10:I60) -> 5.2554761e+08 | J9: =SUM(J10:J60) -> 29459953 | ... S9: =SUM(S10:S60) -> 58157915
A10: 1 | B10: Кассовая наличность и другие платежные документы | C10: =SUM(D10:H10)-N10+O10 -> 296970170 | D10: 296970170 | I10: =SUM(J10:M10) -> 0 | N10: =SUM(O10:S10) -> 0 | T10: 10100
A11: 2 | B11: К получению из ЦБРУ | C11: =SUM(D11:H11)-N11+O11 -> 580486618 | D11: 580486618 | I11: =SUM(J11:M11) -> 0 | N11: =SUM(O11:S11) -> 0 | T11: 10300
A12: 3 | B12: К получению из других банков | C12: =SUM(D12:H12)-N12+O12 -> 530524890 | D12: 531246576 | I12: =SUM(J12:M12) -> 0 | N12: =SUM(O12:S12) -> 721686 | P12: 721686 | T12: 10500
A13: 4 | B13: Ценные бумаги для купли и продажи | C13: =SUM(D13:H13)-N13+O13 -> 507168618 | D13: 507168618 | I13: =SUM(J13:M13) -> 0 | N13: =SUM(O13:S13) -> 0 | T13: 10700
A14: 5 | B14: Инвестиции в ценные бумаги, имеющиеся в наличии для продажи | C14: =SUM(D14:H14)-N14+O14 -> 0 | I14: =SUM(J14:M14) -> 0 | N14: =SUM(O14:S14) -> 0 | T14: 10800
A15: 6 | B15: Драгоценные металлы, камни и монеты для купли и продажи | C15: =SUM(D15:H15)-N15+O15 -> 175 | D15: 175 | I15: =SUM(J15:M15) -> 0 | N15: =SUM(O15:S15) -> 0 | T15: 10900
A16: 7 | B16: Купленные дебиторские задолженности - Факторинг | C16: =SUM(D16:H16)-N16+O16 -> 88085139 | D16: 86150000 | E16: 146063 | F16: 2213814 | G16: 0 | H16: -150000 | I16: =SUM(J16:M16) -> 2657377 | J16: 0 | K16: 0 | L16: 0 | M16: 2657377 | N16: =SUM(O16:S16) -> 274738 | O16: 0 | P16: 18357 | Q16: 246381 | R16: 0 | S16: 10000 | T16: 11100
A17: 8 | B17: Купленные векселя | C17: =SUM(D17:H17)-N17+O17 -> 0 | I17: =SUM(J17:M17) -> 0 | N17: =SUM(O17:S17) -> 0 | T17: 11300
A18: 9 | B18: Обязательства клиентов по траттам под аккредитив и/или трастовые документы | C18: =SUM(D18:H18)-N18+O18 -> 0 | I18: =SUM(J18:M18) -> 0 | N18: =SUM(O18:S18) -> 0 | T18: 11500
A19: 10 | B19: Обязательства лиентов по непогашенным акцептам банка | C19: =SUM(D19:H19)-N19+O19 -> 0 | I19: =SUM(J19:M19) -> 0 | N19: =SUM(O19:S19) -> 0 | T19: 11700
A20: 11 | B20: Купленные по сделкам РЕПО ценные бумаги | C20: =SUM(D20:H20)-N20+O20 -> 0 | I20: =SUM(J20:M20) -> 0 | N20: =SUM(O20:S20) -> 0 | T20: 11800
A21: 12 | B21: Краткосрочные кредиты, предоставленные ЦБРУ | C21: =SUM(D21:H21)-N21+O21 -> 0 | I21: =SUM(J21:M21) -> 0 | N21: =SUM(O21:S21) -> 0 | T21: 11900
A22: 13 | B22: Краткосрочные кредиты, предоставленные другим банкам | C22: =SUM(D22:H22)-N22+O22 -> 0 | I22: =SUM(J22:M22) -> 0 | N22: =SUM(O22:S22) -> 0 | T22: 12100
A23: 14 | B23: Краткосрочные кредиты, предоставленные правительству | C23: =SUM(D23:H23)-N23+O23 -> 0 | I23: =SUM(J23:M23) -> 0 | N23: =SUM(O23:S23) -> 0 | T23: 12300
A24: 15 | B24: Краткосрочные кредиты, предоставленные бюджетным организациям | C24: =SUM(D24:H24)-N24+O24 -> 0 | I24: =SUM(J24:M24) -> 0 | N24: =SUM(O24:S24) -> 0 | T24: 12400
A25: 16 | B25: Краткосрочные кредиты, предоставленные физическим лицам | C25: =SUM(D25:H25)-N25+O25 -> 223618998 | D25: 215030215 | E25: 6153590 | F25: 1059885 | G25: 613516 | H25: 6496805 | I25: =SUM(J25:M25) -> 11422396 | J25: 769491.31 | K25: 994300.39 | L25: 1209303 | M25: 8449301.8 | N25: =SUM(O25:S25) -> 5735013 | P25: 624744 | Q25: 264971 | R25: 306758 | S25: 4538540 | T25: 12500
A26: 17 | B26: Краткосрочные кредиты, предоставленные индивидуальным предпринимателям | C26: =SUM(D26:H26)-N26+O26 -> 58425837 | D26: 56422695 | E26: 1714441 | F26: 223298 | G26: 3284 | H26: 547243 | I26: =SUM(J26:M26) -> 2215730.8 | J26: 176420.07 | K26: 368824.22 | L26: 414783.01 | M26: 1255703.5 | N26: =SUM(O26:S26) -> 485124 | P26: 171444 | Q26: 55824 | R26: 1642 | S26: 256214 | T26: 12600
A27: 18 | B27: Краткосрочные кредиты, предоставленные государственным предприятиям, организациям и учреждениям | C27: =SUM(D27:H27)-N27+O27 -> 194269273 | D27: 188555881 | E27: 3244733 | F27: 2555556 | G27: 0 | H27: 183333 | I27: =SUM(J27:M27) -> 6428066.1 | J27: 0 | K27: 0 | L27: 444444.45 | M27: 5983621.7 | N27: =SUM(O27:S27) -> 270230 | P27: 14674 | Q27: 255556 | R27: 0 | S27: 0 | T27: 12700
A28: 19 | B28: Краткосрочные кредиты, предоставленные при содействии Государственного фонда поддержки развития предпринимательской деятельности | C28: =SUM(D28:H28)-N28+O28 -> 0 | I28: =SUM(J28:M28) -> 0 | N28: =SUM(O28:S28) -> 0 | T28: 12800
A29: 20 | B29: Краткосрочные кредиты, предоставленные предприятиям с участием иностранного капитала | C29: =SUM(D29:H29)-N29+O29 -> 3119234 | D29: 3004325 | E29: 127677 | F29: 0 | G29: 0 | H29: 0 | I29: =SUM(J29:M29) -> 0 | J29: 0 | K29: 0 | L29: 0 | M29: 0 | N29: =SUM(O29:S29) -> 12768 | P29: 12768 | Q29: 0 | R29: 0 | S29: 0 | T29: 12900
A30: 21 | B30: Краткосрочные кредиты, предоставленные негосударственным некоммерческим организациям | C30: =SUM(D30:H30)-N30+O30 -> 35783 | D30: 35783 | I30: =SUM(J30:M30) -> 0 | N30: =SUM(O30:S30) -> 0 | T30: 13000
A31: 22 | B31: Краткосрочные кредиты, предоставленные частным предприятиям, хозяйственным товариществам и обществам | C31: =SUM(D31:H31)-N31+O31 -> 605381210 | D31: 543208972 | E31: 53402042 | F31: 9718689 | G31: 4001 | H31: 7417828 | I31: =SUM(J31:M31) -> 75150752 | J31: 3365231.2 | K31: 15904653 | L31: 13772101 | M31: 42108767 | N31: =SUM(O31:S31) -> 8370322 | P31: 7506446 | Q31: 609345 | R31: 2001 | S31: 252530 | T31: 13100
A32: 23 | B32: Краткосрочные кредиты, предоставленные небанковским финансовым институтам | C32: =SUM(D32:H32)-N32+O32 -> 21600 | D32: 21600 | E32: 0 | F32: 0 | G32: 0 | H32: 0 | I32: =SUM(J32:M32) -> 0 | J32: 0 | K32: 0 | L32: 0 | M32: 0 | N32: =SUM(O32:S32) -> 0 | P32: 0 | Q32: 0 | R32: 0 | S32: 0 | T32: 13200
A33: 24 | B33: Краткосрочные кредиты, предоставленные для производства сельскохозяйственной продукции, закупаемой для государственных нужд | C33: =SUM(D33:H33)-N33+O33 -> 0 | I33: =SUM(J33:M33) -> 0 | N33: =SUM(O33:S33) -> 0 | T33: 13300
A34: 25 | B34: Долгосрочные кредиты, предоставленные для производства сельскохозяйственной продукции, закупаемой для государственных нужд | C34: =SUM(D34:H34)-N34+O34 -> 0 | I34: =SUM(J34:M34) -> 0 | N34: =SUM(O34:S34) -> 0 | T34: 14300
A35: 26 | B35: Долгосрочные кредиты, предоставленные при содействии Государственного фонда поддержки развития предпринимательской деятельности | C35: =SUM(D35:H35)-N35+O35 -> 73822747 | D35: 73635161 | E35: 63680 | F35: 42823 | G35: 0 | H35: 98157 | I35: =SUM(J35:M35) -> 204660.47 | J35: 0 | K35: 63680.021 | L35: 42823.289 | M35: 98157.16 | N35: =SUM(O35:S35) -> 17074 | P35: 6368 | Q35: 10706 | R35: 0 | S35: 0 | T35: 14400
A36: 27 | B36: Долгосрочные кредиты, предоставленные другим банкам | C36: =SUM(D36:H36)-N36+O36 -> 0 | I36: =SUM(J36:M36) -> 0 | N36: =SUM(O36:S36) -> 0 | T36: 14500
A37: 28 | B37: Долгосрочные кредиты, предоставленные правительству | C37: =SUM(D37:H37)-N37+O37 -> 0 | I37: =SUM(J37:M37) -> 0 | N37: =SUM(O37:S37) -> 0 | T37: 14700
A38: 29 | B38: Долгосрочные кредиты, предоставленные бюджетным организациям | C38: =SUM(D38:H38)-N38+O38 -> 0 | I38: =SUM(J38:M38) -> 0 | N38: =SUM(O38:S38) -> 0 | T38: 14800
A39: 30 | B39: Долгосрочные кредиты, предоставленные физическим лицам | C39: =SUM(D39:H39)-N39+O39 -> 2740002132 | D39: 2241664352 | E39: 273179063 | F39: 49463882 | G39: 60496634 | H39: 230323975 | I39: =SUM(J39:M39) -> 1.7312444e+08 | J39: 7731407.5 | K39: 24738799 | L39: 30219634 | M39: 1.104346e+08 | N39: =SUM(O39:S39) -> 115125774 | P39: 27298146 | Q39: 11987298 | R39: 29070764 | S39: 46769566 | T39: 14900
A40: 31 | B40: Долгосрочные кредиты, предоставленные индивидуальным предпринимателям | C40: =SUM(D40:H40)-N40+O40 -> 233254582 | D40: 175109896 | E40: 22450098 | F40: 3626845 | G40: 7413242 | H40: 34877578 | I40: =SUM(J40:M40) -> 44494777 | J40: 1087054.7 | K40: 3573730.8 | L40: 5430489.6 | M40: 34403502 | N40: =SUM(O40:S40) -> 10223077 | P40: 2090826 | Q40: 876059 | R40: 3577727 | S40: 3678465 | T40: 15000
A41: 32 | B41: Долгосрочные кредиты, предоставленные государственным предприятиям, организациям и учреждениям | C41: =SUM(D41:H41)-N41+O41 -> 126208157 | D41: 70827876 | E41: 59950526 | F41: 1282051 | G41: 0 | H41: 270962 | I41: =SUM(J41:M41) -> 4807129.6 | J41: 206250 | K41: 0 | L41: 3047866.8 | M41: 1553012.8 | N41: =SUM(O41:S41) -> 6123258 | P41: 5995053 | Q41: 128205 | R41: 0 | S41: 0 | T41: 15100
A42: 33 | B42: Долгосрочные кредиты, предоставленные негосударственным некоммерческим организациям | C42: =SUM(D42:H42)-N42+O42 -> 3171509 | D42: 2829627 | E42: 379869 | F42: 0 | G42: 0 | H42: 0 | I42: =SUM(J42:M42) -> 35783.093 | J42: 0 | K42: 35783.093 | L42: 0 | M42: 0 | N42: =SUM(O42:S42) -> 37987 | P42: 37987 | Q42: 0 | R42: 0 | S42: 0 | T42: 15200
A43: 34 | B43: Долгосрочные кредиты, предоставленные предприятиям с участием иностранного капитала | C43: =SUM(D43:H43)-N43+O43 -> 254570130 | D43: 210968429 | E43: 48446335 | F43: 0 | G43: 0 | H43: 0 | I43: =SUM(J43:M43) -> 1926573.4 | J43: 0 | K43: 82176.232 | L43: 0 | M43: 1844397.1 | N43: =SUM(O43:S43) -> 4844634 | P43: 4844634 | Q43: 0 | R43: 0 | S43: 0 | T43: 15300
A44: 35 | B44: Долгосрочные кредиты, предоставленные небанковским финансовым институтам | C44: =SUM(D44:H44)-N44+O44 -> 0 | I44: =SUM(J44:M44) -> 0 | N44: =SUM(O44:S44) -> 0 | T44: 15400
A45: 36 | B45: Долгосрочные кредиты, предоставленные частным предприятиям, хозяйственным товариществам и обществам | C45: =SUM(D45:H45)-N45+O45 -> 5985350048 | D45: 5313862002 | E45: 517633469 | F45: 167858943 | G45: 11293906 | H45: 44204915 | I45: =SUM(J45:M45) -> 2.029314e+08 | J45: 16124098 | K45: 32291973 | L45: 36292197 | M45: 1.1822313e+08 | N45: =SUM(O45:S45) -> 69503187 | P45: 47460401 | Q45: 14144785 | R45: 5308430 | S45: 2589571 | T45: 15500
A46: 37 | B46: Лизинг (Финансовая аренда) | C46: =SUM(D46:H46)-N46+O46 -> 5439332 | D46: 5194510 | E46: 220848 | F46: 0 | G46: 0 | H46: 109088 | I46: =SUM(J46:M46) -> 148524.97 | J46: 0 | K46: 0 | L46: 39437.135 | M46: 109087.83 | N46: =SUM(O46:S46) -> 85114 | O46: 0 | P46: 22085 | Q46: 0 | R46: 0 | S46: 63029 | T46: 15600
A47: 38 | B47: Кредиты и лизинг, находящиеся в процессе судебного разбирательства | C47: =SUM(D47:H47)-N47+O47 -> 0 | I47: =SUM(J47:M47) -> 0 | N47: =SUM(O47:S47) -> 0 | T47: 15700
A48: 39 | B48: Инвестиции в зависимые хозяйственные общества, совместные предприятия и дочерние хозяйственные общества | C48: =SUM(D48:H48)-N48+O48 -> 107220 | D48: 107220 | I48: =SUM(J48:M48) -> 0 | N48: =SUM(O48:S48) -> 0 | T48: 15800
A49: 40 | B49: Инвестиции в долговые ценные бумаги, удерживаемые до погашения | C49: =SUM(D49:H49)-N49+O49 -> 0 | I49: =SUM(J49:M49) -> 0 | N49: =SUM(O49:S49) -> 0 | T49: 15900
A50: 41 | B50: Начисленные проценты к получению | C50: =SUM(D50:H50)-N50+O50 -> 409671285 | D50: 409671285 | I50: =SUM(J50:M50) -> 0 | N50: =SUM(O50:S50) -> 0 | T50: 16300
A51: 42 | B51: Начисленные беспроцентные доходы к получению | C51: =SUM(D51:H51)-N51+O51 -> 183842 | D51: 183842 | I51: =SUM(J51:M51) -> 0 | N51: =SUM(O51:S51) -> 0 | T51: 16400
A52: 43 | B52: Основные средства | C52: =SUM(D52:H52)-N52+O52 -> 243315263 | D52: 243315263 | I52: =SUM(J52:M52) -> 0 | N52: =SUM(O52:S52) -> 0 | T52: 16500
A53: 44 | B53: Нематериальные активы | C53: =SUM(D53:H53)-N53+O53 -> 1666881 | D53: 1666881 | I53: =SUM(J53:M53) -> 0 | N53: =SUM(O53:S53) -> 0 | T53: 16600
A54: 45 | B54: Другое собственное имущество банка | C54: =SUM(D54:H54)-N54+O54 -> 60193814 | D54: 60193814 | I54: =SUM(J54:M54) -> 0 | N54: =SUM(O54:S54) -> 0 | T54: 16700
A55: 46 | B55: Отсроченная дебиторская задолженность | C55: =SUM(D55:H55)-N55+O55 -> 41560922 | D55: 43561403 | I55: =SUM(J55:M55) -> 0 | N55: =SUM(O55:S55) -> 2000481 | P55: 2000481 | T55: 16800
A56: 47 | B56: Нереализованная прибыль при ревальвации производных инструментов | C56: =SUM(D56:H56)-N56+O56 -> 0 | I56: =SUM(J56:M56) -> 0 | N56: =SUM(O56:S56) -> 0 | T56: 16900
A57: 48 | B57: Купля-продажа валюты и валютные позиции | C57: =SUM(D57:H57)-N57+O57 -> 0 | I57: =SUM(J57:M57) -> 0 | N57: =SUM(O57:S57) -> 0 | T57: 17100
A58: 49 | B58: Транзитные счета | C58: =SUM(D58:H58)-N58+O58 -> 0 | I58: =SUM(J58:M58) -> 0 | N58: =SUM(O58:S58) -> 0 | T58: 17300
A59: 50 | B59: Транзитные счета по средствам к списанию с пластиковых карт клиентов | C59: =SUM(D59:H59)-N59+O59 -> 4511304 | D59: 4511304 | I59: =SUM(J59:M59) -> 0 | N59: =SUM(O59:S59) -> 0 | T59: 17400
A60: 51 | B60: Другие активы | C60: =SUM(D60:H60)-N60+O60 -> 212216915 | D60: 212341068 | I60: =SUM(J60:M60) -> 0 | N60: =SUM(O60:S60) -> 48842312 | O60: 48718159 | P60: 124153 | T60: 19900
B62: ЗАБАЛАНСОВЫЕ СТАТЬИ | C62: =SUM(D62:H62) -> 220858819 | D62: =SUM(D63:D64) -> 220858819 | E62: =SUM(E63:E64) -> 0 | F62: =SUM(F63:F64) -> 0 | G62: =SUM(G63:G64) -> 0 | H62: =SUM(H63:H64) -> 0 | I62: =SUM(J62:M62) -> 0 | J62: =SUM(J63:J64) -> 0 | K62: =SUM(K63:K64) -> 0 | L62: =SUM(L63:L64) -> 0 | M62: =SUM(M63:M64) -> 0 | N62: =SUM(N63:N64) -> 0 | O62: =SUM(O63:O64) -> 0 | P62: =SUM(P63:P64) -> 0 | Q62: =SUM(Q63:Q64) -> 0 | ... S62: =SUM(S63:S64) -> 0
A63: 1 | B63: Аккредитивы | C63: =SUM(D63:H63)-N63+O63 -> 39430828 | D63: 39430828 | I63: =SUM(J63:M63) -> 0 | N63: =SUM(O63:S63) -> 0 | T63: 90908-90958
A64: 2 | B64: Гарантии и поручетельства | C64: =SUM(D64:H64)-N64+O64 -> 181427991 | D64: 181427991 | I64: =SUM(J64:M64) -> 0 | N64: =SUM(O64:S64) -> 0 | T64: 90993
B67: Подпись Председателя правления:
B69: Подпись Главного Бухгалтера:
B71: Состав активов банка формируется в соответсвии с Планом счетов
C72: =+[8]Balance!$C$45 -> 13483353628

Sheet Income 
B1: ОТЧЕТ О ФИНАНСОВЫХ РЕЗУЛЬТАТАХ | D1: Таблица-3
B3: =+'Asset quality'!B3 -> "Микрокредитбанк" | C3: =+'Asset quality'!P3 -> 44560 | E3: в тыс. сум
A4: № | B4: Категории | C4: Итого | D4: в национальной валюте | E4: в иностранной валюте (в экв. в сумах)
A5: 1. | B5: 1. ПРОЦЕНТНЫЕ ДОХОДЫ
A6: a. | B6: Процентные доходы по счетам в ЦБРУ | C6: =+D6+E6 -> 11869803 | D6: 11869803
A7: б. | B7: Процентные доходы по счетам в других банках | C7: =+D7+E7 -> 28944280 | D7: 28944280
A8: в. | B8: Процентные доходы по купленным векселям | C8: =+D8+E8 -> 0 | D8: 0
A9: г. | B9: Процентные доходы по инвестициям | C9: =+D9+E9 -> 0 | D9: 0
A10: д. | B10: Процентные доходы по счетам купли-продажи ценных бумаг | C10: =+D10+E10 -> 44382395 | D10: 44382395
A11: е. | B11: Процентные доходы по обязательствам клиентов | C11: =+D11+E11 -> 0 | D11: 0
A12: ж. | B12: Процентные доходы по обяз-вам клиентов по непогашенным акцептам этого банка | C12: =+D12+E12 -> 0 | D12: 0
A13: з. | B13: Процент, Дисконт (Скидки) и взносы по кредитным и лизинговым операциям | C13: =+D13+E13 -> 1385765541 | D13: 1385765541
A14: и. | B14: Процентные доходы по соглашениям о покупке ценных бумаг с обратным выкупом | C14: =+D14+E14 -> 0 | D14: 0
A15: к. | B15: Другие процентные доходы | C15: =+D15+E15 -> 721832881 | D15: 721832881
A16: л. | B16: Итого процентных доходов | C16: =SUM(C6:C15) -> 2192794900 | D16: =SUM(D6:D15) -> 2192794900 | E16: =SUM(E6:E15) -> 0 | G16: =+'Analysis of Interest'!C42 -> 2192794900
A18: 2. | B18: ПРОЦЕНТНЫЕ РАСХОДЫ
A19: а. | B19: Процентные расходы по депозитам до востребования | C19: =+D19+E19 -> 10598750 | D19: 10598750
A20: б. | B20: Процентные расходы по срочным депозитам | C20: =+D20+E20 -> 315483464 | D20: 315483464
A21: в. | B21: Процентные расходы по счетам к оплате в ЦБРУ | C21: =+D21+E21 -> 0 | D21: 0
A22: г. | B22: Процентные расходы по счетам к оплате в другие банки | C22: =+D22+E22 -> 153216785 | D22: 153216785
A23: д. | B23: Итого процентных расходов по депозитам | C23: =SUM(C19:C22) -> 479298999 | D23: =SUM(D19:D22) -> 479298999 | E23: =SUM(E19:E22) -> 0
A24: е. | B24: Процентные расходы по кредитам к оплате | C24: =+D24+E24 -> 368022621 | D24: 368022621
A25: ж. | B25: Процентные расходы по соглашениям о продаже ц/б с последующим выкупом | C25: =+D25+E25 -> 0 | D25: 0
A26: з. | B26: Другие процентные расходы | C26: =+D26+E26 -> 720214053 | D26: 720214053
A27: и. | B27: Итого процентных расходов по займам | C27: =SUM(C24:C26) -> 1088236674 | D27: =SUM(D24:D26) -> 1088236674 | E27: =SUM(E24:E26) -> 0
A28: л. | B28: Итого процентных расходов | C28: =C27+C23 -> 1567535673 | D28: =D27+D23 -> 1567535673 | E28: =E27+E23 -> 0 | G28: =+'Analysis of Interest'!C72 -> 1567535673
A30: 3. | B30: ЧИСТЫЕ ПРОЦЕНТНЫЕ ДОХОДЫ ДО ОЦЕНКИ ВОЗМОЖНЫХ УБЫТКОВ ПО АКТИВАМ | C30: =C16-C28 -> 625259227 | D30: =D16-D28 -> 625259227 | E30: =E16-E28 -> 0
A31: а. | B31: Минус: Оценка возможных убытков по кредитам и лизингу | C31: =+D31+E31 -> 432519815 | D31: 432519815
A32: б. | B32: Минус: Оценка возможных убытков по в ценным бумагам | C32: =+D32+E32 -> 0 | D32: 0 | E32: 0
A33: в. | B33: Минус: Оценка возможных убытков по инвестициям | C33: =+D33+E33 -> 0 | D33: 0 | E33: 0
A34: г. | B34: Минус: Оценка возможных убытков по другим активам | C34: =+D34+E34 -> 2000 | D34: 2000 | E34: 0
A35: д. | B35: Чистые процентные доходы после оценки возможных убытков по кредитам и лизингу | C35: =C30-C31-C32-C33-C34 -> 192737412 | D35: =D30-D31-D32-D33-D34 -> 192737412 | E35: =E30-E31-E32-E33-E34 -> 0
A37: 4. | B37: БЕСПРОЦЕНТНЫЕ ДОХОДЫ
A38: а. | B38: Доходы от комиссий и платы за услуги | C38: =+D38+E38 -> 125051652 | D38: 125051652
A39: б. | B39: Прибыль в иностранной валюте | C39: =+D39+E39 -> 186840469 | D39: 0 | E39: 186840469
A40: в. | B40: Прибыль от коммерческих операций | C40: =+D40+E40 -> 0 | D40: 0
A41: г. | B41: Прибыль и дивиденды от инвестиций | C41: =+D41+E41 -> 167042 | D41: 167042
A42: д. | B42: Другие беспроцентные доходы | C42: =+D42+E42 -> 236403493 | D42: 236403493
B43: в том числе | D43: 0
A44: д1. | B44: Возврат резервов, с формированных на покрытие потерь по активам | C44: =+D44+E44 -> 0 | D44: 0
A45: д2. | B45: Возврат списанных кредитов | C45: =+D45+E45 -> 221460341 | D45: 221460341
A46: е. | B46: Итого беспроцентных доходов | C46: =SUM(C38:C42) -> 548462656 | D46: =SUM(D38:D42) -> 361622187 | E46: =SUM(E38:E42) -> 186840469
A48: 5. | B48: БЕСПРОЦЕНТНЫЕ РАСХОДЫ
A49: а. | B49: Комиссионные расходы и расходы за услуги | C49: =+D49+E49 -> 45959836 | D49: 45959836
A50: б. | B50: Убытки в иностранной валюте | C50: =+D50+E50 -> 159587935 | D50: 0 | E50: 159587935
A51: в. | B51: Убытки по счетам купли-продажи | C51: =+D51+E51 -> 2938240 | D51: 2938240
A52: г. | B52: Убытки от инвестиций | C52: =+D52+E52 -> 0 | D52: 0
A53: д. | B53: Другие беспроцентные расходы | C53: =+D53+E53 -> 9376941 | D53: 9376941
A54: е. | B54: Итого беспроцентных расходов | C54: =SUM(C49:C53) -> 217862952 | D54: =SUM(D49:D53) -> 58275017 | E54: =SUM(E49:E53) -> 159587935
A56: 6. | B56: ЧИСТЫЙ ДОХОД ДО ОПЕРАЦИОННЫХ РАСХОДОВ | C56: =C35+C46-C54 -> 523337116 | D56: =D35+D46-D54 -> 496084582 | E56: =E35+E46-E54 -> 27252534
A58: 7. | B58: ОПЕРАЦИОННЫЕ РАСХОДЫ
A59: а. | B59: Заработная плата и другие расходы на сотрудников | C59: =+D59 -> 307104792 | D59: 307104792
A60: а1) | B60: из них, выплаты основному руководящему персоналу | D60: 0
A61: б. | B61: Аренда и содержание | C61: =+D61 -> 59709427 | D61: 59709427
A62: в. | B62: Командировочные и транспортные расходы | C62: =+D62 -> 7143829 | D62: 7143829
A63: г. | B63: Административные расходы | C63: =+D63 -> 15030488 | D63: 15030488
A64: д. | B64: Репрезентация и благотворительность | C64: =+D64 -> 17579865 | D64: 17579865
A65: е. | B65: Расходы на износ | C65: =+D65 -> 36238549 | D65: 36238549
A66: ж. | B66: Страхование | C66: =+D66 -> 15006383 | D66: 15006383
A67: з. | B67: Налоги | C67: =+D67 -> 7388096 | D67: 7388096
A68: и. | B68: Штрафы и пеня | C68: =+D68 -> 0 | D68: 0
A69: к. | B69: Другие операционные расходы | C69: =+D69 -> 6778920 | D69: 6778920
A70: л. | B70: Итого операционных расходов | C70: =SUM(C59:C69)-C60 -> 471980349 | D70: =SUM(D59:D69)-D60 -> 471980349
A72: 8. | B72: ЧИСТАЯ ПРИБЫЛЬ ДО УПЛАТЫ НАЛОГОВ И ДРУГИХ ПОПРАВОК | C72: =C56-C70 -> 51356767 | D72: =D56-D70 -> 24104233 | E72: =+E56-(C70-D70) -> 27252534
A73: а. | B73: Оценка налога на прибыль | C73: =+D73 -> 12913681 | D73: 12913681
A75: 9. | B75: ДОХОД ДО ВВЕДЕНИЯ ПОПРАВОК | C75: =C72-C73 -> 38443086 | D75: =D72-D73 -> 11190552 | E75: =E72-E73 -> 27252534
A76: а. | B76: Непредвиденные доходы или убытки, чистые | C76: =+D76+E76 -> 0 | D76: 0 | E76: 0
A77: б. | B77: Другие поправки к прибыли, чистые | C77: =+D77+E77 -> 0 | D77: 0 | E77: 0
A79: 10. | B79: ЧИСТАЯ ПРИБЫЛЬ (УБЫТКИ) | C79: =C75+C76+C77 -> 38443086 | D79: =D75+D76+D77 -> 11190552 | E79: =E75+E76+E77 -> 27252534
B81: Подпись Председателя правления:
B83: Подпись Главного Бухгалтера:

Sheet Analysis of Interest
B1: АНАЛИЗ ПРОЦЕНТНЫХ ДОХОДОВ И РАСХОДОВ | C1: Таблица-4
B3: =+'Asset quality'!B3 -> "Микрокредитбанк" | C3: =+'Asset quality'!P3 -> 44560
A4: № | B4: Категория | C4: в тыс. сум
A5: 1 . | B5: ПРОЦЕНТНЫЕ ДОХОДЫ ПО КРЕДИТНЫМ И ЛИЗИНГОВЫМ ОПЕРАЦИЯМ
A6: a. | B6: Кредиты и лизинговые операции ЦБРУ | C6: 0
A7: б. | B7: Кредиты и лизинговые операции другим банкам | C7: 11697
A8: в. | B8: Кредиты и лизинговые операции Правительству | C8: 32083
A9: г. | B9: Кредиты и лизинговые операции физическим лицам | C9: 496488310
A10: д. | B10: Кредиты и лизинговые операции государственным предприятиям | C10: 25507020
A11: е. | B11: Кредиты и лизинговые операции совместным и иностранным предприятиям | C11: 30412235
A12: ж. | B12: Кредиты и лизинговые операции частным товариществам и корпорациям | C12: 778891183
A13: з. | B13: Другие кредиты и лизинговые операции | C13: 54423014
A14: и. | B14: ИТОГО ПРОЦЕНТНЫХ ДОХОДОВ ПО КРЕДИТНЫМ И ЛИЗИНГОВЫМ ОПЕРАЦИЯМ | C14: =SUM(C6:C13) -> 1385765542
A16: 2. | B16: ПРОЦЕНТНЫЕ ДОХОДЫ ПО КОРРЕСПОНДЕНТСКИМ СЧЕТАМ
A17: a. | B17: К получению из ЦБРУ | C17: 11869803
A18: б. | B18: К получению из других банков | C18: 28944280
B19: ИТОГО ПРОЦЕНТНЫХ ДОХОДОВ ПО КОРРЕСПОНДЕНТСКИМ СЧЕТАМ | C19: =SUM(C17:C18) -> 40814083
A21: 3. | B21: ПРОЦЕНТНЫЕ ДОХОДЫ ПО СЧЕТАМ КУПЛИ-ПРОДАЖИ Ц/Б
A22: a. | B22: Государственные казначейские ценные бумаги | C22: 13519097
A23: б. | B23: Облигации и ценные бумаги ЦБРУ | C23: 30863299
A24: в. | B24: Ценные бумаги государственных корпораций | C24: 0
A25: г. | B25: Еврооблигации | C25: 0
A26: д. | B26: Частные ценные бумаги | C26: 0
A27: е. | B27: Другие ценные бумаги | C27: 0
A28: ж. | B28: ИТОГО ПРОЦЕНТНЫХ ДОХОДОВ ПО СЧЕТАМ КУПЛИ-ПРОДАЖИ Ц/Б | C28: =SUM(C22:C27) -> 44382396
A30: 4. | B30: ПРОЦЕНТНЫЕ ДОХОДЫ ПО ИНВЕСТИЦИЯМ
A31: a. | B31: Государственные облигации | C31: 0
A32: б. | B32: Облигации и ценные бумаги ЦБРУ | C32: 0
A33: в. | B33: Частные облигации | C33: 0
A34: г. | B34: Еврооблигации | C34: 0
A35: д. | B35: Другие ценные бумаги | C35: 0
A36: е. | B36: ИТОГО ПРОЦЕНТНЫХ ДОХОДОВ ПО ИНВЕСТИЦИЯМ | C36: =SUM(C31:C35) -> 0
A38: 5. | B38: ДРУГИЕ ПРОЦЕНТНЫЕ ДОХОДЫ
A39: a. | B39: Процентные доходы по соглашениям о покупке ц/б c обратным выкупом | C39: 0
A40: б. | B40: Другие процентные доходы | C40: 721832879
A42: 6. | B42: ИТОГО ПРОЦЕНТНЫХ ДОХОДОВ | C42: =C14+C19+C28+C36+C39+C40 -> 2192794900
A44: 7. | B44: ПРОЦЕНТНЫЕ РАСХОДЫ ПО ДЕПОЗИТАМ
A45: A. | B45: Депозиты до востребования
A46: a. | B46: Правительство | C46: 0
A47: б. | B47: Физические лица | C47: 125439
A48: в. | B48: Государственные предприятия | C48: 9492301
A49: г. | B49: Совместные и иностранные предприятия | C49: 0
A50: д. | B50: Частные товарищества и корпорации | C50: 0
A51: е. | B51: Другие депозиты | C51: 981010
A52: ж. | B52: Итого процентных расходов по депозитам до востребования | C52: =SUM(C46:C51) -> 10598750
A54: Б. | B54: Срочные депозиты
A55: a. | B55: Правительство | C55: 168405508
A56: б. | B56: Физические лица | C56: 88670823
A57: в. | B57: Государственные предприятия | C57: 16151336
A58: г. | B58: Совместные и иностранные предприятия | C58: 409000
A59: д. | B59: Частные товарищества и корпорации | C59: 21905472
A60: е. | B60: Другие депозиты | C60: 19941324
A61: ж. | B61: Итого процентных расходов по срочным депозитам | C61: =SUM(C55:C60) -> 315483463
A63: В. | B63: ИТОГО ПРОЦЕНТНЫХ РАСХОДОВ ПО ДЕПОЗИТАМ | C63: =C52+C61 -> 326082213
A65: 8. | B65: ПРОЦЕНТНЫЕ РАСХОДЫ ПО ДРУГИМ ОБЯЗАТЕЛЬСТВАМ
A66: а. | B66: Процентные расходы по непогашенным акцептам | C66: 0
A67: б. | B67: Процентные расходы по кредитам к оплате | C67: 368022621
A68: в. | B68: Процентные расходы по соглашениям о продаже ц/б с последующим выкупом | C68: 0
A69: г. | B69: Другие процентные расходы | C69: 873430839
A70: д. | B70: ИТОГО ПРОЦЕНТНЫХ РАСХОДОВ ПО ДРУГИМ ОБЯЗАТЕЛЬСТВАМ | C70: =SUM(C66:C69) -> 1241453460
A72: 9. | B72: ИТОГО ПРОЦЕНТНЫХ РАСХОДОВ | C72: =C63+C70 -> 1567535673
B74: Подпись Председателя правления:
B76: Подпись Главного Бухгалтера:

Sheet Changes in Equity
B1: ИЗМЕНЕНИЯ В СОБСТВЕННОМ КАПИТАЛЕ | C1: Таблица-7
B3: =+'Asset quality'!B3 -> "Микрокредитбанк" | C3: =+'Asset quality'!P3 -> 44560
A4: № | B4: Категория | C4: в тыс. сум
A5: 1. | B5: Итого собственного капитала первоначально определенного за прошлый год | C5: 1625105476
A6: 2. | B6: Исправления в собственном капитале не показанные в отчете за прошлый год, чистые | C6: 0
A7: 3. | B7: Исправленный баланс на конец прошлого календарного года (сумма строк 1 и 2) | C7: =SUM(C5:C6) -> 1625105476
A8: 4. | B8: Чистый прибыль (убыток) по состоянию на дату от начала года | C8: =+'Income '!C79 -> 38443086 | D8: =+[8]Balance!$C$76 -> 38443086
A9: 5. | B9: Продажа, Обмен, Приобретение или выкуп акций, за текущий год (чистая выручка) | C9: 555413966
A10: 6. | B10: Изменения в оценочной стоимости прироста над первонач. стоимостью, за текущий год (чистые) | C10: 8940159
A11: 7. | B11: МИНУС: Денежные дивиденды объявленные по привилегированным акциям | C11: 0
A12: 8. | B12: МИНУС: Денежные дивиденды объявленные по обыкновенным акциям | C12: 0
A13: 9. | B13: Другие статьи влияющие на собственный капитал за текущий год (чистые) | C13: 93193543
A14: 10. | B14: Итого собственного капитала на конец текущего периода (сумма строк с 3 по 10) | C14: =C7+SUM(C8:C10)-SUM(C11:C12)+C13 -> 2321096230 | D14: =+[8]Balance!$C$77 -> 2321096230
B16: Подпись Председателя правления:
B18: Подпись Главного Бухгалтера:

Sheet Loans Receivable
A1: КРЕДИТЫ И ЛИЗИНГИ К ПОЛУЧЕНИЮ ПО ОТРАСЛЯМ ЭКОНОМИКИ, ТИПАМ КЛИЕНТОВ И ПО ТИПУ ОБЕСПЕЧЕНИЯ | W1: Таблица-8
B3: =+'Asset quality'!B3 -> "Микрокредитбанк" | T3: =+'Asset quality'!P3 -> 44560 | X3: тыс. сум
A4: № | B4: Отрасль экономики | C4: Сумма кредита | D4: в национальной валюте | F4: в иностранной валюте (в экв. в сумах) | H4: из них | J4: из них
D5: Сумма | E5: средне-взвешенные процентные ставки | F5: Сумма | G5: средне-взвешенные процентные ставки | H5: Начисляемые кредиты | I5: Кредиты переведённые в статус ненаращивания процентов | J5: Депозиты | K5: Гарантированные Правительством Республики Узбекистан | L5: из них | M5: Транспортные средства | N5: Инвентарь | O5: Недвижимость | P5: из них | R5: Оборудование | S5: Векселя (облигации) | T5: Акции | U5: Гарантия третьей стороны | V5: Поручительства третьей стороны | W5: Страховой полис | X5: Необеспеченные | Y5: Другое обеспечение
L6: Гарантированные Правительством Республики Узбекистан в иностранной валюте (экв.сум) | P6: жилая недвижимость | Q6: коммерческая недвижимость
A7: Код | B7: (А) | C7: (Б) | D7: (Б1) | E7: (Б2) | F7: (Б3) | G7: (Б4) | H7: (В) | I7: (Г) | J7: (Д) | K7: (Е) | L7: (Е1) | M7: (Ж) | N7: (З) | O7: (И) | P7: (И1) | Q7: (И2) | R7: (К) | S7: (Л) | T7: (М) | U7: (Н) | V7: (О) | W7: (П) | X7: (Р) | Y7: (С)
B8: Промышленность
A9: 10 | B9: Физические лица | C9: =SUM(J9:Y9)-L9-P9-Q9 -> 317557 | D9: 317557 | E9: 0.069527593 | F9: 0 | G9: 0 | H9: 317557 | J9: 0 | K9: 0 | L9: 0 | M9: 0 | N9: 0 | O9: =+P9+Q9 -> 15608 | P9: 8242 | Q9: 7366 | R9: 0 | S9: 0 | T9: 0 | U9: 0 | V9: 301948 | W9: 1 | X9: 0 | Y9: 0
A10: =A9+10 -> 20 | B10: Государственные предприятия | C10: =SUM(J10:Y10)-L10-P10-Q10 -> 22820466 | D10: 22820466 | E10: 0.14019927 | F10: 0 | G10: 0 | H10: 22820466 | I10: 0 | J10: 0 | K10: 0 | L10: 0 | M10: 0 | N10: 0 | O10: =+P10+Q10 -> 22787466 | P10: 75790 | Q10: 22711676 | R10: 0 | S10: 0 | T10: 0 | U10: 0 | V10: 0 | W10: 0 | X10: 0 | Y10: 33000
A11: =A10+10 -> 30 | B11: Совместные и иностранные предприятия | C11: =SUM(J11:Y11)-L11-P11-Q11 -> 137504047 | D11: 59208913 | E11: 0.19965753 | F11: 78295134 | G11: 0.10209576 | H11: 137504047 | I11: 0 | J11: 0 | K11: 0 | L11: 0 | M11: 2102759 | N11: 0 | O11: =+P11+Q11 -> 114120728 | P11: 532057 | Q11: 113588671 | R11: 0 | S11: 0 | T11: 0 | U11: 0 | V11: 3658743 | W11: 17621817 | X11: 0 | Y11: 0
A12: =A11+10 -> 40 | B12: Частные товарищества и корпорации | C12: =SUM(J12:Y12)-L12-P12-Q12 -> 1778208889 | D12: 569285347 | E12: 0.15047854 | F12: 1208923542 | G12: 0.092408985 | H12: 1778208889 | I12: 0 | J12: 0 | K12: 0 | L12: 0 | M12: 85786723 | N12: 193542 | O12: =+P12+Q12 -> 1395778149 | P12: 244109980 | Q12: 1151668169 | R12: 6392129 | S12: 0 | T12: 0 | U12: 2398337 | V12: 65874031 | W12: 221658892 | X12: 0 | Y12: 127086
A13: =A12+10 -> 50 | B13: Правительство | C13: =SUM(J13:Y13)-L13-P13-Q13 -> 0 | D13: 0 | E13: 0 | F13: 0 | G13: 0 | H13: 0 | J13: 0 | K13: 0 | L13: 0 | M13: 0 | N13: 0 | O13: =+P13+Q13 -> 0 | P13: 0 | Q13: 0 | R13: 0 | S13: 0 | T13: 0 | U13: 0 | V13: 0 | W13: 0 | X13: 0 | Y13: 0
A14: =A13+10 -> 60 | B14: Прочие | C14: =SUM(J14:Y14)-L14-P14-Q14 -> 0 | D14: 0 | E14: 0 | F14: 0 | G14: 0 | H14: 0 | J14: 0 | K14: 0 | L14: 0 | M14: 0 | N14: 0 | O14: =+P14+Q14 -> 0 | P14: 0 | Q14: 0 | R14: 0 | S14: 0 | T14: 0 | U14: 0 | V14: 0 | W14: 0 | X14: 0 | Y14: 0
A15: =A14+10 -> 70 | B15: Итого по промышленности | C15: =SUM(J15:Y15)-L15-P15-Q15 -> 1938850959 | D15: =SUM(D9:D14) -> 651632283 | E15: =IFERROR(((D9*E9)/D15)+((D10*E10)/D15)+((D11*E11)/D15)+((D12*E12)/D15)+((D13*E13)/D15)+((D14*E14)/D15),0) -> 0.15454763 | F15: =SUM(F9:F14) -> 1287218676 | G15: =IFERROR(((F9*G9)/F15)+((F10*G10)/F15)+((F11*G11)/F15)+((F12*G12)/F15)+((F13*G13)/F15)+((F14*G14)/F15),0) -> 0.092998183 | H15: =SUM(H9:H14) -> 1938850959 | I15: =SUM(I9:I14) -> 0 | J15: =SUM(J9:J14) -> 0 | K15: =SUM(K9:K14) -> 0 | L15: =SUM(L9:L14) -> 0 | M15: =SUM(M9:M14) -> 87889482 | N15: =SUM(N9:N14) -> 193542 | O15: =SUM(O9:O14) -> 1532701951 | ... Y15: =SUM(Y9:Y14) -> 160086
B16: Сельское хозяйство
A17: =A15+10 -> 80 | B17: Физические лица | C17: =SUM(J17:Y17)-L17-P17-Q17 -> 718619875 | D17: 718619875 | E17: 0.12699006 | F17: 0 | G17: 0 | H17: 718619875 | J17: 0 | K17: 0 | L17: 0 | M17: 105660 | N17: 0 | O17: =+P17+Q17 -> 31919 | P17: 2362 | Q17: 29557 | R17: 0 | S17: 0 | T17: 0 | U17: 0 | V17: 42013547 | W17: 676468749 | X17: 0 | Y17: 0
A18: =A17+10 -> 90 | B18: Государственные предприятия | C18: =SUM(J18:Y18)-L18-P18-Q18 -> 60257114 | D18: 60257114 | E18: 0.06010176 | F18: 0 | G18: 0 | H18: 60257114 | J18: 0 | K18: 0 | L18: 0 | M18: 0 | N18: 0 | O18: =+P18+Q18 -> 0 | P18: 0 | Q18: 0 | R18: 0 | S18: 0 | T18: 0 | U18: 0 | V18: 60257114 | W18: 0 | X18: 0 | Y18: 0
A19: =A18+10 -> 100 | B19: Совместные и иностранные предприятия | C19: =SUM(J19:Y19)-L19-P19-Q19 -> 186094751 | D19: 54086623 | E19: 0.18239675 | F19: 132008128 | G19: 0.07468252 | H19: 186094751 | J19: 0 | K19: 0 | L19: 0 | M19: 2354384 | N19: 0 | O19: =+P19+Q19 -> 181552478 | P19: 124613918 | Q19: 56938560 | R19: 0 | S19: 0 | T19: 0 | U19: 0 | V19: 1529230 | W19: 658659 | X19: 0 | Y19: 0
A20: =A19+10 -> 110 | B20: Частные товарищества и корпорации | C20: =SUM(J20:Y20)-L20-P20-Q20 -> 1241497805 | D20: 747400850 | E20: 0.16824605 | F20: 494096955 | G20: 0.074502216 | H20: 1241497805 | J20: 182126 | K20: 0 | L20: 0 | M20: 78812903 | N20: 0 | O20: =+P20+Q20 -> 1121491152 | P20: 78658888 | Q20: 1042832264 | R20: 1688445 | S20: 0 | T20: 0 | U20: 3149182 | V20: 12886598 | W20: 22505399 | X20: 0 | Y20: 782000
A21: =A20+10 -> 120 | B21: Фермерское хозяйство | C21: =SUM(J21:Y21)-L21-P21-Q21 -> 261233028 | D21: 183647166 | E21: 0.17259636 | F21: 77585862 | G21: 0.058612516 | H21: 261233028 | J21: 0 | K21: 0 | L21: 0 | M21: 18195003 | N21: 0 | O21: =+P21+Q21 -> 238623096 | P21: 18218837 | Q21: 220404259 | R21: 689586 | S21: 0 | T21: 0 | U21: 254467 | V21: 2962803 | W21: 508073 | X21: 0 | Y21: 0
A22: =A21+10 -> 130 | B22: Правительство | C22: =SUM(J22:Y22)-L22-P22-Q22 -> 0 | D22: 0 | E22: 0 | F22: 0 | G22: 0 | H22: 0 | J22: 0 | K22: 0 | L22: 0 | M22: 0 | N22: 0 | O22: =+P22+Q22 -> 0 | P22: 0 | Q22: 0 | R22: 0 | S22: 0 | T22: 0 | U22: 0 | V22: 0 | W22: 0 | X22: 0 | Y22: 0
A23: =A22+10 -> 140 | B23: Прочие | C23: =SUM(J23:Y23)-L23-P23-Q23 -> 0 | D23: 0 | E23: 0 | F23: 0 | G23: 0 | H23: 0 | I23: 0 | J23: 0 | K23: 0 | L23: 0 | M23: 0 | N23: 0 | O23: =+P23+Q23 -> 0 | P23: 0 | Q23: 0 | R23: 0 | S23: 0 | T23: 0 | U23: 0 | V23: 0 | W23: 0 | X23: 0 | Y23: 0
A24: =A23+10 -> 150 | B24: Итого по сельскому хозяйству | C24: =SUM(J24:Y24)-L24-P24-Q24 -> 2467702573 | D24: =SUM(D17:D23) -> 1764011628 | E24: =IFERROR(((D17*E17)/D24)+((D18*E18)/D24)+((D19*E19)/D24)+((D20*E20)/D24)+((D21*E21)/D24)+((D22*E22)/D24)+((D23*E23)/D24),0) -> 0.14863192 | F24: =SUM(F17:F23) -> 703690945 | G24: =IFERROR(((F17*G17)/F24)+((F18*G18)/F24)+((F19*G19)/F24)+((F20*G20)/F24)+((F21*G21)/F24)+((F22*G22)/F24)+((F23*G23)/F24),0) -> 0.072784112 | H24: =SUM(H17:H23) -> 2467702573 | I24: =SUM(I17:I23) -> 0 | J24: =SUM(J17:J23) -> 182126 | K24: =SUM(K17:K23) -> 0 | L24: =SUM(L17:L23) -> 0 | M24: =SUM(M17:M23) -> 99467950 | N24: =SUM(N17:N23) -> 0 | O24: =SUM(O17:O23) -> 1541698645 | ... Y24: =SUM(Y17:Y23) -> 782000
B25: Транспорт и коммуникации
A26: =A24+10 -> 160 | B26: Физические лица | C26: =SUM(J26:Y26)-L26-P26-Q26 -> 81876843 | D26: 81876843 | E26: 0.26392372 | F26: 0 | G26: 0 | H26: 81876843 | I26: 0 | J26: 0 | K26: 0 | L26: 0 | M26: 74458738 | N26: 0 | O26: =+P26+Q26 -> 7232 | P26: 0 | Q26: 7232 | R26: 0 | S26: 0 | T26: 0 | U26: 0 | V26: 2699930 | W26: 4680999 | X26: 0 | Y26: 29944
A27: =A26+10 -> 170 | B27: Государственные предприятия | C27: =SUM(J27:Y27)-L27-P27-Q27 -> 177970 | D27: 177970 | E27: 0.24357156 | F27: 0 | G27: 0 | H27: 177970 | I27: 0 | J27: 0 | K27: 0 | L27: 0 | M27: 177970 | N27: 0 | O27: =+P27+Q27 -> 0 | P27: 0 | Q27: 0 | R27: 0 | S27: 0 | T27: 0 | U27: 0 | V27: 0 | W27: 0 | X27: 0 | Y27: 0
A28: =A27+10 -> 180 | B28: Совместные и иностранные предприятия | C28: =SUM(J28:Y28)-L28-P28-Q28 -> 51350503 | D28: 4748565 | E28: 0.25153388 | F28: 46601938 | G28: 0.09 | H28: 51350503 | I28: 0 | J28: 0 | K28: 0 | L28: 0 | M28: 1316965 | N28: 0 | O28: =+P28+Q28 -> 50025005 | P28: 46736581 | Q28: 3288424 | R28: 0 | S28: 0 | T28: 0 | U28: 0 | V28: 8533 | W28: 0 | X28: 0 | Y28: 0
A29: =A28+10 -> 190 | B29: Частные товарищества и корпорации | C29: =SUM(J29:Y29)-L29-P29-Q29 -> 217089423 | D29: 109957217 | E29: 0.21988682 | F29: 107132206 | G29: 0.10715919 | H29: 217089423 | I29: 0 | J29: 0 | K29: 0 | L29: 0 | M29: 76743633 | N29: 0 | O29: =+P29+Q29 -> 133991772 | P29: 25915845 | Q29: 108075927 | R29: 0 | S29: 0 | T29: 0 | U29: 2493110 | V29: 2082997 | W29: 1777911 | X29: 0 | Y29: 0
A30: =A29+10 -> 200 | B30: Правительство | C30: =SUM(J30:Y30)-L30-P30-Q30 -> 0 | D30: 0 | E30: 0 | F30: 0 | G30: 0 | H30: 0 | I30: 0 | J30: 0 | K30: 0 | L30: 0 | M30: 0 | N30: 0 | O30: =+P30+Q30 -> 0 | P30: 0 | Q30: 0 | R30: 0 | S30: 0 | T30: 0 | U30: 0 | V30: 0 | W30: 0 | X30: 0 | Y30: 0
A31: =A30+10 -> 210 | B31: Прочие | C31: =SUM(J31:Y31)-L31-P31-Q31 -> 0 | D31: 0 | E31: 0 | F31: 0 | G31: 0 | H31: 0 | I31: 0 | J31: 0 | K31: 0 | L31: 0 | M31: 0 | N31: 0 | O31: =+P31+Q31 -> 0 | P31: 0 | Q31: 0 | R31: 0 | S31: 0 | T31: 0 | U31: 0 | V31: 0 | W31: 0 | X31: 0 | Y31: 0
A32: =A31+10 -> 220 | B32: Итого по транспорту и коммуникациям | C32: =SUM(J32:Y32)-L32-P32-Q32 -> 350494739 | D32: =SUM(D26:D31) -> 196760595 | E32: =IFERROR(((D26*E26)/D32)+((D27*E27)/D32)+((D28*E28)/D32)+((D29*E29)/D32)+((D30*E30)/D32)+((D31*E31)/D32),0) -> 0.23899683 | F32: =SUM(F26:F31) -> 153734144 | G32: =IFERROR(((F26*G26)/F32)+((F27*G27)/F32)+((F28*G28)/F32)+((F29*G29)/F32)+((F30*G30)/F32)+((F31*G31)/F32),0) -> 0.10195767 | H32: =SUM(H26:H31) -> 350494739 | I32: =SUM(I26:I31) -> 0 | J32: =SUM(J26:J31) -> 0 | K32: =SUM(K26:K31) -> 0 | L32: =SUM(L26:L31) -> 0 | M32: =SUM(M26:M31) -> 152697306 | N32: =SUM(N26:N31) -> 0 | O32: =SUM(O26:O31) -> 184024009 | ... Y32: =SUM(Y26:Y31) -> 29944
B33: Строительство
A34: =A32+10 -> 230 | B34: Физические лица | C34: =SUM(J34:Y34)-L34-P34-Q34 -> 100075 | D34: 100075 | E34: 0.15 | F34: 0 | G34: 0 | H34: 100075 | I34: 0 | J34: 0 | K34: 0 | L34: 0 | M34: 0 | N34: 0 | O34: =+P34+Q34 -> 0 | P34: 0 | Q34: 0 | R34: 0 | S34: 0 | T34: 0 | U34: 0 | V34: 0 | W34: 100075 | X34: 0 | Y34: 0
A35: =A34+10 -> 240 | B35: Государственные предприятия | C35: =SUM(J35:Y35)-L35-P35-Q35 -> 0 | D35: 0 | E35: 0 | F35: 0 | G35: 0 | H35: 0 | I35: 0 | J35: 0 | K35: 0 | L35: 0 | M35: 0 | N35: 0 | O35: =+P35+Q35 -> 0 | P35: 0 | Q35: 0 | R35: 0 | S35: 0 | T35: 0 | U35: 0 | V35: 0 | W35: 0 | X35: 0 | Y35: 0
A36: =A35+10 -> 250 | B36: Совместные и иностранные предприятия | C36: =SUM(J36:Y36)-L36-P36-Q36 -> 6302115 | D36: 6302115 | E36: 0.21840345 | F36: 0 | G36: 0 | H36: 6302115 | I36: 0 | J36: 0 | K36: 0 | L36: 0 | M36: 0 | N36: 0 | O36: =+P36+Q36 -> 2455000 | P36: 0 | Q36: 2455000 | R36: 0 | S36: 0 | T36: 0 | U36: 3833334 | V36: 3763 | W36: 10018 | X36: 0 | Y36: 0
A37: =A36+10 -> 260 | B37: Частные товарищества и корпорации | C37: =SUM(J37:Y37)-L37-P37-Q37 -> 333663985 | D37: 315322973 | E37: 0.13051106 | F37: 18341012 | G37: 0.076986422 | H37: 333663985 | I37: 0 | J37: 0 | K37: 0 | L37: 0 | M37: 3310867 | N37: 0 | O37: =+P37+Q37 -> 327755173 | P37: 51181312 | Q37: 276573861 | R37: 1587702 | S37: 0 | T37: 0 | U37: 49958 | V37: 133086 | W37: 827199 | X37: 0 | Y37: 0
A38: =A37+10 -> 270 | B38: Правительство | C38: =SUM(J38:Y38)-L38-P38-Q38 -> 0 | D38: 0 | E38: 0 | F38: 0 | G38: 0 | H38: 0 | I38: 0 | J38: 0 | K38: 0 | L38: 0 | M38: 0 | N38: 0 | O38: =+P38+Q38 -> 0 | P38: 0 | Q38: 0 | R38: 0 | S38: 0 | T38: 0 | U38: 0 | V38: 0 | W38: 0 | X38: 0 | Y38: 0
A39: =A38+10 -> 280 | B39: Прочие | C39: =SUM(J39:Y39)-L39-P39-Q39 -> 0 | D39: 0 | E39: 0 | F39: 0 | G39: 0 | H39: 0 | I39: 0 | J39: 0 | K39: 0 | L39: 0 | M39: 0 | N39: 0 | O39: =+P39+Q39 -> 0 | P39: 0 | Q39: 0 | R39: 0 | S39: 0 | T39: 0 | U39: 0 | V39: 0 | W39: 0 | X39: 0 | Y39: 0
A40: =A39+10 -> 290 | B40: Итого по строительству | C40: =SUM(J40:Y40)-L40-P40-Q40 -> 340066175 | D40: =SUM(D34:D39) -> 321725163 | E40: =IFERROR(((D34*E34)/D40)+((D35*E35)/D40)+((D36*E36)/D40)+((D37*E37)/D40)+((D38*E38)/D40)+((D39*E39)/D40),0) -> 0.1322388 | F40: =SUM(F34:F39) -> 18341012 | G40: =IFERROR(((F34*G34)/F40)+((F35*G35)/F40)+((F36*G36)/F40)+((F37*G37)/F40)+((F38*G38)/F40)+((F39*G39)/F40),0) -> 0.076986422 | H40: =SUM(H34:H39) -> 340066175 | I40: =SUM(I34:I39) -> 0 | J40: =SUM(J34:J39) -> 0 | K40: =SUM(K34:K39) -> 0 | L40: =SUM(L34:L39) -> 0 | M40: =SUM(M34:M39) -> 3310867 | N40: =SUM(N34:N39) -> 0 | O40: =SUM(O34:O39) -> 330210173 | ... Y40: =SUM(Y34:Y39) -> 0
B41: Торговля и общественное питание
A42: =A40+10 -> 300 | B42: Физические лица | C42: =SUM(J42:Y42)-L42-P42-Q42 -> 0 | D42: 0 | E42: 0 | F42: 0 | G42: 0 | H42: 0 | I42: 0 | J42: 0 | K42: 0 | L42: 0 | M42: 0 | N42: 0 | O42: =+P42+Q42 -> 0 | P42: 0 | Q42: 0 | R42: 0 | S42: 0 | T42: 0 | U42: 0 | V42: 0 | W42: 0 | X42: 0 | Y42: 0
A43: =A42+10 -> 310 | B43: Государственные предприятия | C43: =SUM(J43:Y43)-L43-P43-Q43 -> 68030502 | D43: 13842180 | E43: 0.1343552 | F43: 54188322 | G43: 0.06 | H43: 68030502 | I43: 0 | J43: 0 | K43: 0 | L43: 0 | M43: 0 | N43: 0 | O43: =+P43+Q43 -> 3615375 | P43: 444444 | Q43: 3170931 | R43: 7631250 | S43: 0 | T43: 0 | U43: 0 | V43: 2595555 | W43: 0 | X43: 0 | Y43: 54188322
A44: =A43+10 -> 320 | B44: Совместные и иностранные предприятия | C44: =SUM(J44:Y44)-L44-P44-Q44 -> 16566175 | D44: 16566175 | E44: 0.20154989 | F44: 0 | G44: 0 | H44: 16566175 | I44: 0 | J44: 0 | K44: 0 | L44: 0 | M44: 1157753 | N44: 0 | O44: =+P44+Q44 -> 12400562 | P44: 4500941 | Q44: 7899621 | R44: 1844397 | S44: 0 | T44: 0 | U44: 0 | V44: 456610 | W44: 239588 | X44: 467265 | Y44: 0
A45: =A44+10 -> 330 | B45: Частные товарищества и корпорации | C45: =SUM(J45:Y45)-L45-P45-Q45 -> 1067589159 | D45: 644340494 | E45: 0.19252747 | F45: 423248665 | G45: 0.081192906 | H45: 1067589159 | I45: 0 | J45: 0 | K45: 0 | L45: 0 | M45: 67931354 | N45: 626 | O45: =+P45+Q45 -> 795788912 | P45: 163452117 | Q45: 632336795 | R45: 453667 | S45: 0 | T45: 0 | U45: 5255000 | V45: 21919719 | W45: 150410250 | X45: 23389108 | Y45: 2440523
A46: =A45+10 -> 340 | B46: Правительство | C46: =SUM(J46:Y46)-L46-P46-Q46 -> 0 | D46: 0 | E46: 0 | F46: 0 | G46: 0 | H46: 0 | I46: 0 | J46: 0 | K46: 0 | L46: 0 | M46: 0 | N46: 0 | O46: =+P46+Q46 -> 0 | P46: 0 | Q46: 0 | R46: 0 | S46: 0 | T46: 0 | U46: 0 | V46: 0 | W46: 0 | X46: 0 | Y46: 0
A47: =A46+10 -> 350 | B47: Прочие | C47: =SUM(J47:Y47)-L47-P47-Q47 -> 0 | D47: 0 | E47: 0 | F47: 0 | G47: 0 | H47: 0 | I47: 0 | J47: 0 | K47: 0 | L47: 0 | M47: 0 | N47: 0 | O47: =+P47+Q47 -> 0 | P47: 0 | Q47: 0 | R47: 0 | S47: 0 | T47: 0 | U47: 0 | V47: 0 | W47: 0 | X47: 0 | Y47: 0
A48: =A47+10 -> 360 | B48: Итого по торговле и общественному питанию | C48: =SUM(J48:Y48)-L48-P48-Q48 -> 1152185836 | D48: =SUM(D42:D47) -> 674748849 | E48: =IFERROR(((D42*E42)/D48)+((D43*E43)/D48)+((D44*E44)/D48)+((D45*E45)/D48)+((D46*E46)/D48)+((D47*E47)/D48),0) -> 0.19155561 | F48: =SUM(F42:F47) -> 477436987 | G48: =IFERROR(((F42*G42)/F48)+((F43*G43)/F48)+((F44*G44)/F48)+((F45*G45)/F48)+((F46*G46)/F48)+((F47*G47)/F48),0) -> 0.078787546 | H48: =SUM(H42:H47) -> 1152185836 | I48: =SUM(I42:I47) -> 0 | J48: =SUM(J42:J47) -> 0 | K48: =SUM(K42:K47) -> 0 | L48: =SUM(L42:L47) -> 0 | M48: =SUM(M42:M47) -> 69089107 | N48: =SUM(N42:N47) -> 626 | O48: =SUM(O42:O47) -> 811804849 | ... Y48: =SUM(Y42:Y47) -> 56628845
B49: Материально-техническое снабжение и сбыт
A50: =A48+10 -> 370 | B50: Физические лица | C50: =SUM(J50:Y50)-L50-P50-Q50 -> 10944080 | D50: 10944080 | E50: 0.12689851 | F50: 0 | G50: 0 | H50: 10944080 | I50: 0 | J50: 0 | K50: 0 | L50: 0 | M50: 0 | N50: 0 | O50: =+P50+Q50 -> 0 | P50: 0 | Q50: 0 | R50: 0 | S50: 0 | T50: 0 | U50: 0 | V50: 907531 | W50: 10036549 | X50: 0 | Y50: 0
A51: =A50+10 -> 380 | B51: Государственные предприятия | C51: =SUM(J51:Y51)-L51-P51-Q51 -> 80000 | D51: 80000 | E51: 0.24 | F51: 0 | G51: 0 | H51: 80000 | I51: 0 | J51: 0 | K51: 0 | L51: 0 | M51: 0 | N51: 0 | O51: =+P51+Q51 -> 80000 | P51: 0 | Q51: 80000 | R51: 0 | S51: 0 | T51: 0 | U51: 0 | V51: 0 | W51: 0 | X51: 0 | Y51: 0
A52: =A51+10 -> 390 | B52: Совместные и иностранные предприятия | C52: =SUM(J52:Y52)-L52-P52-Q52 -> 15830266 | D52: 15339978 | E52: 0.18151768 | F52: 490288 | G52: 0.12 | H52: 15830266 | I52: 0 | J52: 0 | K52: 0 | L52: 0 | M52: 1681828 | N52: 0 | O52: =+P52+Q52 -> 12981636 | P52: 640000 | Q52: 12341636 | R52: 0 | S52: 0 | T52: 0 | U52: 0 | V52: 944272 | W52: 222530 | X52: 0 | Y52: 0
A53: =A52+10 -> 400 | B53: Частные товарищества и корпорации | C53: =SUM(J53:Y53)-L53-P53-Q53 -> 1350698465 | D53: 531865122 | E53: 0.17521519 | F53: 818833343 | G53: 0.088638632 | H53: 1350698465 | I53: 0 | J53: 0 | K53: 0 | L53: 0 | M53: 63032575 | N53: 0 | O53: =+P53+Q53 -> 839794025 | P53: 106975888 | Q53: 732818137 | R53: 0 | S53: 0 | T53: 0 | U53: 4868463 | V53: 46278418 | W53: 396540794 | X53: 0 | Y53: 184190
A54: =A53+10 -> 410 | B54: Правительство | C54: =SUM(J54:Y54)-L54-P54-Q54 -> 0 | D54: 0 | E54: 0 | F54: 0 | G54: 0 | H54: 0 | I54: 0 | J54: 0 | K54: 0 | L54: 0 | M54: 0 | N54: 0 | O54: =+P54+Q54 -> 0 | P54: 0 | Q54: 0 | R54: 0 | S54: 0 | T54: 0 | U54: 0 | V54: 0 | W54: 0 | X54: 0 | Y54: 0
A55: =A54+10 -> 420 | B55: Прочие | C55: =SUM(J55:Y55)-L55-P55-Q55 -> 0 | D55: 0 | E55: 0 | F55: 0 | G55: 0 | H55: 0 | I55: 0 | J55: 0 | K55: 0 | L55: 0 | M55: 0 | N55: 0 | O55: =+P55+Q55 -> 0 | P55: 0 | Q55: 0 | R55: 0 | S55: 0 | T55: 0 | U55: 0 | V55: 0 | W55: 0 | X55: 0 | Y55: 0
A56: =A55+10 -> 430 | B56: Итого по материально-техническому снабжению и сбыту | C56: =SUM(J56:Y56)-L56-P56-Q56 -> 1377552811 | D56: =SUM(D50:D55) -> 558229180 | E56: =IFERROR(((D50*E50)/D56)+((D51*E51)/D56)+((D52*E52)/D56)+((D53*E53)/D56)+((D54*E54)/D56)+((D55*E55)/D56),0) -> 0.17445041 | F56: =SUM(F50:F55) -> 819323631 | G56: =IFERROR(((F50*G50)/F56)+((F51*G51)/F56)+((F52*G52)/F56)+((F53*G53)/F56)+((F54*G54)/F56)+((F55*G55)/F56),0) -> 0.088657399 | H56: =SUM(H50:H55) -> 1377552811 | I56: =SUM(I50:I55) -> 0 | J56: =SUM(J50:J55) -> 0 | K56: =SUM(K50:K55) -> 0 | L56: =SUM(L50:L55) -> 0 | M56: =SUM(M50:M55) -> 64714403 | N56: =SUM(N50:N55) -> 0 | O56: =SUM(O50:O55) -> 852855661 | ... Y56: =SUM(Y50:Y55) -> 184190
B57: Жилищно-коммунальные услуги
A58: =A56+10 -> 440 | B58: Физические лица | C58: =SUM(J58:Y58)-L58-P58-Q58 -> 0 | D58: 0 | E58: 0 | F58: 0 | G58: 0 | H58: 0 | I58: 0 | J58: 0 | K58: 0 | L58: 0 | M58: 0 | N58: 0 | O58: =+P58+Q58 -> 0 | P58: 0 | Q58: 0 | R58: 0 | S58: 0 | T58: 0 | U58: 0 | V58: 0 | W58: 0 | X58: 0 | Y58: 0
A59: =A58+10 -> 450 | B59: Государственные предприятия | C59: =SUM(J59:Y59)-L59-P59-Q59 -> 0 | D59: 0 | E59: 0 | F59: 0 | G59: 0 | H59: 0 | I59: 0 | J59: 0 | K59: 0 | L59: 0 | M59: 0 | N59: 0 | O59: =+P59+Q59 -> 0 | P59: 0 | Q59: 0 | R59: 0 | S59: 0 | T59: 0 | U59: 0 | V59: 0 | W59: 0 | X59: 0 | Y59: 0
A60: =A59+10 -> 460 | B60: Совместные и иностранные предприятия | C60: =SUM(J60:Y60)-L60-P60-Q60 -> 0 | D60: 0 | E60: 0 | F60: 0 | G60: 0 | H60: 0 | I60: 0 | J60: 0 | K60: 0 | L60: 0 | M60: 0 | N60: 0 | O60: =+P60+Q60 -> 0 | P60: 0 | Q60: 0 | R60: 0 | S60: 0 | T60: 0 | U60: 0 | V60: 0 | W60: 0 | X60: 0 | Y60: 0
A61: =A60+10 -> 470 | B61: Частные товарищества и корпорации | C61: =SUM(J61:Y61)-L61-P61-Q61 -> 1286460 | D61: 1286460 | E61: 0.12480131 | F61: 0 | G61: 0 | H61: 1286460 | I61: 0 | J61: 0 | K61: 0 | L61: 0 | M61: 0 | N61: 0 | O61: =+P61+Q61 -> 0 | P61: 0 | Q61: 0 | R61: 0 | S61: 0 | T61: 0 | U61: 376348 | V61: 0 | W61: 910112 | X61: 0 | Y61: 0
A62: =A61+10 -> 480 | B62: Правительство | C62: =SUM(J62:Y62)-L62-P62-Q62 -> 0 | D62: 0 | E62: 0 | F62: 0 | G62: 0 | H62: 0 | I62: 0 | J62: 0 | K62: 0 | L62: 0 | M62: 0 | N62: 0 | O62: =+P62+Q62 -> 0 | P62: 0 | Q62: 0 | R62: 0 | S62: 0 | T62: 0 | U62: 0 | V62: 0 | W62: 0 | X62: 0 | Y62: 0
A63: 485 | B63: Негосударственные некоммерческие организации | C63: =SUM(J63:Y63)-L63-P63-Q63 -> 795722 | D63: 795722 | E63: 0.14 | F63: 0 | G63: 0 | H63: 795722 | I63: 0 | J63: 0 | K63: 0 | L63: 0 | M63: 0 | N63: 0 | O63: =+P63+Q63 -> 0 | P63: 0 | Q63: 0 | R63: 0 | S63: 0 | T63: 0 | U63: 514718 | V63: 1 | W63: 281003 | X63: 0 | Y63: 0
A64: =A62+10 -> 490 | B64: Прочие | C64: =SUM(J64:Y64)-L64-P64-Q64 -> 0 | D64: 0 | E64: 0 | F64: 0 | G64: 0 | H64: 0 | I64: 0 | J64: 0 | K64: 0 | L64: 0 | M64: 0 | N64: 0 | O64: =+P64+Q64 -> 0 | P64: 0 | Q64: 0 | R64: 0 | S64: 0 | T64: 0 | U64: 0 | V64: 0 | W64: 0 | X64: 0 | Y64: 0
A65: =A64+10 -> 500 | B65: Итого по жилищно-коммунальным услугам | C65: =SUM(J65:Y65)-L65-P65-Q65 -> 2082182 | D65: =SUM(D58:D64) -> 2082182 | E65: =IFERROR(((D58*E58)/D65)+((D59*E59)/D65)+((D60*E60)/D65)+((D61*E61)/D65)+((D62*E62)/D65)+((D63*E63)/D65)+((D64*E64)/D65),0) -> 0.13060961 | F65: =SUM(F58:F64) -> 0 | G65: =IFERROR(((F58*G58)/F65)+((F59*G59)/F65)+((F60*G60)/F65)+((F61*G61)/F65)+((F62*G62)/F65)+((F63*G63)/F65)+((F64*G64)/F65),0) -> 0 | H65: =SUM(H58:H64) -> 2082182 | I65: =SUM(I58:I64) -> 0 | J65: =SUM(J58:J64) -> 0 | K65: =SUM(K58:K64) -> 0 | L65: =SUM(L58:L64) -> 0 | M65: =SUM(M58:M64) -> 0 | N65: =SUM(N58:N64) -> 0 | O65: =SUM(O58:O64) -> 0 | ... Y65: =SUM(Y58:Y64) -> 0
B66: Другие отрасли
A67: =A65+10 -> 510 | B67: Физические лица | C67: =SUM(J67:Y67)-L67-P67-Q67 -> 2272623487 | D67: 2272623487 | E67: 0.16503952 | F67: 0 | G67: 0 | H67: 2272623487 | I67: 0 | J67: 0 | K67: 0 | L67: 0 | M67: 7853875 | N67: 0 | O67: =+P67+Q67 -> 479697622 | P67: 389070907 | Q67: 90626715 | R67: 0 | S67: 0 | T67: 0 | U67: 0 | V67: 377298317 | W67: 1377956006 | X67: 29564115 | Y67: 253552
A68: =A67+10 -> 520 | B68: Государственные предприятия | C68: =SUM(J68:Y68)-L68-P68-Q68 -> 86603814 | D68: 86603814 | E68: 0.031789378 | F68: 0 | G68: 0 | H68: 86603814 | I68: 0 | J68: 0 | K68: 0 | L68: 0 | M68: 0 | N68: 0 | O68: =+P68+Q68 -> 0 | P68: 0 | Q68: 0 | R68: 0 | S68: 0 | T68: 0 | U68: 0 | V68: 2213814 | W68: 0 | X68: 0 | Y68: 84390000
A69: =A68+10 -> 530 | B69: Совместные и иностранные предприятия | C69: =SUM(J69:Y69)-L69-P69-Q69 -> 41973096 | D69: 10820800 | E69: 0.13132371 | F69: 31152296 | G69: 0.083730193 | H69: 41973096 | I69: 0 | J69: 0 | K69: 0 | L69: 0 | M69: 1026522 | N69: 0 | O69: =+P69+Q69 -> 39290661 | P69: 13266280 | Q69: 26024381 | R69: 0 | S69: 0 | T69: 0 | U69: 0 | V69: 824431 | W69: 831482 | X69: 0 | Y69: 0
A70: =A69+10 -> 540 | B70: Частные товарищества и корпорации | C70: =SUM(J70:Y70)-L70-P70-Q70 -> 782919068 | D70: 663032645 | E70: 0.15608943 | F70: 119886423 | G70: 0.068457281 | H70: 782919068 | I70: 0 | J70: 0 | K70: 0 | L70: 0 | M70: 56467243 | N70: 2774 | O70: =+P70+Q70 -> 446017483 | P70: 71312527 | Q70: 374704956 | R70: 1629773 | S70: 0 | T70: 0 | U70: 28557087 | V70: 50471386 | W70: 16884896 | X70: 0 | Y70: 182888426
A71: =A70+10 -> 550 | B71: Центральный банк | C71: =SUM(J71:Y71)-L71-P71-Q71 -> 0 | D71: 0 | E71: 0 | F71: 0 | G71: 0 | H71: 0 | I71: 0 | J71: 0 | K71: 0 | L71: 0 | M71: 0 | N71: 0 | O71: =+P71+Q71 -> 0 | P71: 0 | Q71: 0 | R71: 0 | S71: 0 | T71: 0 | U71: 0 | V71: 0 | W71: 0 | X71: 0 | Y71: 0
A72: =A71+10 -> 560 | B72: Другие банки | C72: =SUM(J72:Y72)-L72-P72-Q72 -> 0 | D72: 0 | E72: 0 | F72: 0 | G72: 0 | H72: 0 | I72: 0 | J72: 0 | K72: 0 | L72: 0 | M72: 0 | N72: 0 | O72: =+P72+Q72 -> 0 | P72: 0 | Q72: 0 | R72: 0 | S72: 0 | T72: 0 | U72: 0 | V72: 0 | W72: 0 | X72: 0 | Y72: 0
A73: =A72+10 -> 570 | B73: Правительство | C73: =SUM(J73:Y73)-L73-P73-Q73 -> 0 | D73: 0 | E73: 0 | F73: 0 | G73: 0 | H73: 0 | I73: 0 | J73: 0 | K73: 0 | L73: 0 | M73: 0 | N73: 0 | O73: =+P73+Q73 -> 0 | P73: 0 | Q73: 0 | R73: 0 | S73: 0 | T73: 0 | U73: 0 | V73: 0 | W73: 0 | X73: 0 | Y73: 0
A74: =A73+10 -> 580 | B74: Небанковские финансовые институты | C74: =SUM(J74:Y74)-L74-P74-Q74 -> 0 | D74: 0 | E74: 0 | F74: 0 | G74: 0 | H74: 0 | I74: 0 | J74: 0 | K74: 0 | L74: 0 | M74: 0 | N74: 0 | O74: =+P74+Q74 -> 0 | P74: 0 | Q74: 0 | R74: 0 | S74: 0 | T74: 0 | U74: 0 | V74: 0 | W74: 0 | X74: 0 | Y74: 0
A75: =A74+10 -> 590 | B75: Негосударственные некоммерческие организации | C75: =SUM(J75:Y75)-L75-P75-Q75 -> 2808180 | D75: 1997606 | E75: 0.15758686 | F75: 810574 | G75: 0.09 | H75: 2808180 | I75: 0 | J75: 0 | K75: 0 | L75: 0 | M75: 18876 | N75: 0 | O75: =+P75+Q75 -> 2754731 | P75: 0 | Q75: 2754731 | R75: 0 | S75: 0 | T75: 0 | U75: 0 | V75: 34573 | W75: 0 | X75: 0 | Y75: 0
A76: =A75+10 -> 600 | B76: Бюджетные организации | C76: =SUM(J76:Y76)-L76-P76-Q76 -> 0 | D76: 0 | E76: 0 | F76: 0 | G76: 0 | H76: 0 | I76: 0 | J76: 0 | K76: 0 | L76: 0 | M76: 0 | N76: 0 | O76: =+P76+Q76 -> 0 | P76: 0 | Q76: 0 | R76: 0 | S76: 0 | T76: 0 | U76: 0 | V76: 0 | W76: 0 | X76: 0 | Y76: 0
A77: =A76+10 -> 610 | B77: Прочие | C77: =SUM(J77:Y77)-L77-P77-Q77 -> 21091 | D77: 21091 | E77: 0.14 | F77: 0 | G77: 0 | H77: 21091 | I77: 0 | J77: 0 | K77: 0 | L77: 0 | M77: 0 | N77: 0 | O77: =+P77+Q77 -> 0 | P77: 0 | Q77: 0 | R77: 0 | S77: 0 | T77: 0 | U77: 0 | V77: 0 | W77: 21091 | X77: 0 | Y77: 0
A78: =A77+10 -> 620 | B78: Итого по другим отраслям | C78: =SUM(J78:Y78)-L78-P78-Q78 -> 3186948736 | D78: =SUM(D67:D77) -> 3035099443 | E78: =IFERROR(((D67*E67)/D78)+((D68*E68)/D78)+((D69*E69)/D78)+((D70*E70)/D78)+((D71*E71)/D78)+((D72*E72)/D78)+((D73*E73)/D78)+((D74*E74)/D78)+((D75*E75)/D78)+((D76*E76)/D78)+((D77*E77)/D78),0) -> 0.15915687 | F78: =SUM(F67:F77) -> 151849293 | G78: =IFERROR(((F67*G67)/F78)+((F68*G68)/F78)+((F69*G69)/F78)+((F70*G70)/F78)+((F71*G71)/F78)+((F72*G72)/F78)+((F73*G73)/F78)+((F74*G74)/F78)+((F75*G75)/F78)+((F76*G76)/F78)+((F77*G77)/F78),0) -> 0.071705556 | H78: =SUM(H67:H77) -> 3186948736 | I78: =SUM(I67:I77) -> 0 | J78: =SUM(J67:J77) -> 0 | K78: =SUM(K67:K77) -> 0 | L78: =SUM(L67:L77) -> 0 | M78: =SUM(M67:M77) -> 65366516 | N78: =SUM(N67:N77) -> 2774 | O78: =SUM(O67:O77) -> 967760497 | ... Y78: =SUM(Y67:Y77) -> 267531978
B79: Кредитные и лизинговые операции
A80: =A78+10 -> 630 | B80: Физические лица | C80: =SUM(J80:Y80)-L80-P80-Q80 -> 3084481917 | D80: =D9+D17+D26+D34+D42+D50+D58+D67 -> 3084481917 | E80: =IFERROR(((D9*E9)/D80)+((D17*E17)/D80)+((D26*E26)/D80)+((D34*E34)/D80)+((D42*E42)/D80)+((D50*E50)/D80)+((D58*E58)/D80)+((D67*E67)/D80),0) -> 0.158654 | F80: =F9+F17+F26+F34+F42+F50+F58+F67 -> 0 | G80: =IFERROR(((F9*G9)/F80)+((F17*G17)/F80)+((F26*G26)/F80)+((F34*G34)/F80)+((F42*G42)/F80)+((F50*G50)/F80)+((F58*G58)/F80)+((F67*G67)/F80),0) -> 0 | H80: =H9+H17+H26+H34+H42+H50+H58+H67 -> 3084481917 | I80: =I9+I17+I26+I34+I42+I50+I58+I67 -> 0 | J80: =J9+J17+J26+J34+J42+J50+J58+J67 -> 0 | K80: =K9+K17+K26+K34+K42+K50+K58+K67 -> 0 | L80: =L9+L17+L26+L34+L42+L50+L58+L67 -> 0 | M80: =M9+M17+M26+M34+M42+M50+M58+M67 -> 82418273 | N80: =N9+N17+N26+N34+N42+N50+N58+N67 -> 0 | O80: =O9+O17+O26+O34+O42+O50+O58+O67 -> 479752381 | ... Y80: =Y9+Y17+Y26+Y34+Y42+Y50+Y58+Y67 -> 283496
A81: =A80+10 -> 640 | B81: Государственные предприятия | C81: =SUM(J81:Y81)-L81-P81-Q81 -> 237969866 | D81: =D10+D18+D27+D35+D43+D51+D59+D68 -> 183781544 | E81: =IFERROR(((D10*E10)/D81)+((D18*E18)/D81)+((D27*E27)/D81)+((D35*E35)/D81)+((D43*E43)/D81)+((D51*E51)/D81)+((D59*E59)/D81)+((D68*E68)/D81),0) -> 0.06255454 | F81: =F10+F18+F27+F35+F43+F51+F59+F68 -> 54188322 | G81: =IFERROR(((F10*G10)/F81)+((F18*G18)/F81)+((F27*G27)/F81)+((F35*G35)/F81)+((F43*G43)/F81)+((F51*G51)/F81)+((F59*G59)/F81)+((F68*G68)/F81),0) -> 0.06 | H81: =H10+H18+H27+H35+H43+H51+H59+H68 -> 237969866 | I81: =I10+I18+I27+I35+I43+I51+I59+I68 -> 0 | J81: =J10+J18+J27+J35+J43+J51+J59+J68 -> 0 | K81: =K10+K18+K27+K35+K43+K51+K59+K68 -> 0 | L81: =L10+L18+L27+L35+L43+L51+L59+L68 -> 0 | M81: =M10+M18+M27+M35+M43+M51+M59+M68 -> 177970 | N81: =N10+N18+N27+N35+N43+N51+N59+N68 -> 0 | O81: =O10+O18+O27+O35+O43+O51+O59+O68 -> 26482841 | ... Y81: =Y10+Y18+Y27+Y35+Y43+Y51+Y59+Y68 -> 138611322
A82: =A81+10 -> 650 | B82: Совместные и иностранные предприятия | C82: =SUM(J82:Y82)-L82-P82-Q82 -> 455620953 | D82: =D11+D19+D28+D36+D44+D52+D60+D69 -> 167073169 | E82: =IFERROR(((D11*E11)/D82)+((D19*E19)/D82)+((D28*E28)/D82)+((D36*E36)/D82)+((D44*E44)/D82)+((D52*E52)/D82)+((D60*E60)/D82)+((D69*E69)/D82),0) -> 0.19034758 | F82: =F11+F19+F28+F36+F44+F52+F60+F69 -> 288547784 | G82: =IFERROR(((F11*G11)/F82)+((F19*G19)/F82)+((F28*G28)/F82)+((F36*G36)/F82)+((F44*G44)/F82)+((F52*G52)/F82)+((F60*G60)/F82)+((F69*G69)/F82),0) -> 0.085648543 | H82: =H11+H19+H28+H36+H44+H52+H60+H69 -> 455620953 | I82: =I11+I19+I28+I36+I44+I52+I60+I69 -> 0 | J82: =J11+J19+J28+J36+J44+J52+J60+J69 -> 0 | K82: =K11+K19+K28+K36+K44+K52+K60+K69 -> 0 | L82: =L11+L19+L28+L36+L44+L52+L60+L69 -> 0 | M82: =M11+M19+M28+M36+M44+M52+M60+M69 -> 9640211 | N82: =N11+N19+N28+N36+N44+N52+N60+N69 -> 0 | O82: =O11+O19+O28+O36+O44+O52+O60+O69 -> 412826070 | ... Y82: =Y11+Y19+Y28+Y36+Y44+Y52+Y60+Y69 -> 0
A83: =A82+10 -> 660 | B83: Частные товарищества и корпорации | C83: =SUM(J83:Y83)-L83-P83-Q83 -> 6772953254 | D83: =D12+D20+D29+D37+D45+D53+D61+D70 -> 3582491108 | E83: =IFERROR(((D12*E12)/D83)+((D20*E20)/D83)+((D29*E29)/D83)+((D37*E37)/D83)+((D45*E45)/D83)+((D53*E53)/D83)+((D61*E61)/D83)+((D70*E70)/D83),0) -> 0.16682268 | F83: =F12+F20+F29+F37+F45+F53+F61+F70 -> 3190462146 | G83: =IFERROR(((F12*G12)/F83)+((F20*G20)/F83)+((F29*G29)/F83)+((F37*G37)/F83)+((F45*G45)/F83)+((F53*G53)/F83)+((F61*G61)/F83)+((F70*G70)/F83),0) -> 0.08668684 | H83: =H12+H20+H29+H37+H45+H53+H61+H70 -> 6772953254 | I83: =I12+I20+I29+I37+I45+I53+I61+I70 -> 0 | J83: =J12+J20+J29+J37+J45+J53+J61+J70 -> 182126 | K83: =K12+K20+K29+K37+K45+K53+K61+K70 -> 0 | L83: =L12+L20+L29+L37+L45+L53+L61+L70 -> 0 | M83: =M12+M20+M29+M37+M45+M53+M61+M70 -> 432085298 | N83: =N12+N20+N29+N37+N45+N53+N61+N70 -> 196942 | O83: =O12+O20+O29+O37+O45+O53+O61+O70 -> 5060616666 | ... Y83: =Y12+Y20+Y29+Y37+Y45+Y53+Y61+Y70 -> 186422225
A84: =A83+10 -> 670 | B84: Фермерское хозяйство | C84: =SUM(J84:Y84)-L84-P84-Q84 -> 261233028 | D84: =D21 -> 183647166 | E84: =IFERROR(E21,0) -> 0.17259636 | F84: =F21 -> 77585862 | G84: =IFERROR(G21,0) -> 0.058612516 | H84: =H21 -> 261233028 | I84: =I21 -> 0 | J84: =J21 -> 0 | K84: =K21 -> 0 | L84: =L21 -> 0 | M84: =M21 -> 18195003 | N84: =N21 -> 0 | O84: =O21 -> 238623096 | ... Y84: =Y21 -> 0
A85: =A84+10 -> 680 | B85: Другие банки | C85: =SUM(J85:Y85)-L85-P85-Q85 -> 0 | D85: =D72 -> 0 | E85: =E72 -> 0 | F85: =F72 -> 0 | G85: =G72 -> 0 | H85: =H72 -> 0 | I85: =I72 -> 0 | J85: =J72 -> 0 | K85: =K72 -> 0 | ... Y85: =Y72 -> 0
A86: =A85+10 -> 690 | B86: Центральный банк | C86: =SUM(J86:Y86)-L86-P86-Q86 -> 0 | D86: =D71 -> 0 | E86: =E71 -> 0 | F86: =F71 -> 0 | G86: =G71 -> 0 | H86: =H71 -> 0 | I86: =I71 -> 0 | J86: =J71 -> 0 | K86: =K71 -> 0 | ... Y86: =Y71 -> 0
A87: =A86+10 -> 700 | B87: Правительство | C87: =SUM(J87:Y87)-L87-P87-Q87 -> 0 | D87: =D13+D22+D30+D38+D46+D54+D62+D73 -> 0 | E87: =IFERROR(((D13*E13)/D87)+((D22*E22)/D87)+((D30*E30)/D87)+((D38*E38)/D87)+((D46*E46)/D87)+((D54*E54)/D87)+((D62*E62)/D87)+((D73*E73)/D87),0) -> 0 | F87: =F13+F22+F30+F38+F46+F54+F62+F73 -> 0 | G87: =IFERROR(((F13*G13)/F87)+((F22*G22)/F87)+((F30*G30)/F87)+((F38*G38)/F87)+((F46*G46)/F87)+((F54*G54)/F87)+((F62*G62)/F87)+((F73*G73)/F87),0) -> 0 | H87: =H13+H22+H30+H38+H46+H54+H62+H73 -> 0 | I87: =I13+I22+I30+I38+I46+I54+I62+I73 -> 0 | J87: =J13+J22+J30+J38+J46+J54+J62+J73 -> 0 | K87: =K13+K22+K30+K38+K46+K54+K62+K73 -> 0 | L87: =L13+L22+L30+L38+L46+L54+L62+L73 -> 0 | M87: =M13+M22+M30+M38+M46+M54+M62+M73 -> 0 | N87: =N13+N22+N30+N38+N46+N54+N62+N73 -> 0 | O87: =O13+O22+O30+O38+O46+O54+O62+O73 -> 0 | ... Y87: =Y13+Y22+Y30+Y38+Y46+Y54+Y62+Y73 -> 0
A88: =A87+10 -> 710 | B88: Небанковские финансовые институты | C88: =SUM(J88:Y88)-L88-P88-Q88 -> 0 | D88: =D74 -> 0 | E88: =E74 -> 0 | F88: =F74 -> 0 | G88: =G74 -> 0 | H88: =H74 -> 0 | I88: =I74 -> 0 | J88: =J74 -> 0 | K88: =K74 -> 0 | ... Y88: =Y74 -> 0
A89: =A88+10 -> 720 | B89: Негосударственные некоммерческие организации | C89: =SUM(J89:Y89)-L89-P89-Q89 -> 3603902 | D89: =+D63+D75 -> 2793328 | E89: =IFERROR(((D75*E75)/D78)+((D63*E63)/D65),0) -> 0.053605804 | F89: =+F63+F75 -> 810574 | G89: =IFERROR(((F75*G75)/F78)+((F63*G63)/F65),0) -> 0 | H89: =+H63+H75 -> 3603902 | I89: =+I63+I75 -> 0 | J89: =+J63+J75 -> 0 | K89: =+K63+K75 -> 0 | L89: =+L63+L75 -> 0 | M89: =+M63+M75 -> 18876 | N89: =+N63+N75 -> 0 | O89: =+O63+O75 -> 2754731 | ... Y89: =+Y63+Y75 -> 0
A90: =A89+10 -> 730 | B90: Бюджетные организации | C90: =SUM(J90:Y90)-L90-P90-Q90 -> 0 | D90: =D76 -> 0 | E90: =E76 -> 0 | F90: =F76 -> 0 | G90: =G76 -> 0 | H90: =H76 -> 0 | I90: =I76 -> 0 | J90: =J76 -> 0 | K90: =K76 -> 0 | ... Y90: =Y76 -> 0
A91: =A90+10 -> 740 | B91: Прочие | C91: =SUM(J91:Y91)-L91-P91-Q91 -> 21091 | D91: =D14+D23+D31+D39+D47+D55+D64+D77 -> 21091 | E91: =IFERROR(((D14*E14)/D91)+((D23*E23)/D91)+((D31*E31)/D91)+((D39*E39)/D91)+((D47*E47)/D91)+((D55*E55)/D91)+((D64*E64)/D91)+((D77*E77)/D91),0) -> 0.14 | F91: =F14+F23+F31+F39+F47+F55+F64+F77 -> 0 | G91: =IFERROR(((F14*G14)/F91)+((F23*G23)/F91)+((F31*G31)/F91)+((F39*G39)/F91)+((F47*G47)/F91)+((F55*G55)/F91)+((F64*G64)/F91)+((F77*G77)/F91),0) -> 0 | H91: =H14+H23+H31+H39+H47+H55+H64+H77 -> 21091 | I91: =I14+I23+I31+I39+I47+I55+I64+I77 -> 0 | J91: =J14+J23+J31+J39+J47+J55+J64+J77 -> 0 | K91: =K14+K23+K31+K39+K47+K55+K64+K77 -> 0 | L91: =L14+L23+L31+L39+L47+L55+L64+L77 -> 0 | M91: =M14+M23+M31+M39+M47+M55+M64+M77 -> 0 | N91: =N14+N23+N31+N39+N47+N55+N64+N77 -> 0 | O91: =O14+O23+O31+O39+O47+O55+O64+O77 -> 0 | ... Y91: =Y14+Y23+Y31+Y39+Y47+Y55+Y64+Y77 -> 0
A92: =A91+10 -> 750 | B92: Итого кредита и лизинга | C92: =SUM(J92:Y92)-L92-P92-Q92 -> 10815884011 | D92: =SUM(D80:D91) -> 7204289323 | E92: =IFERROR(((D80*E80)/D92)+((D81*E81)/D92)+((D82*E82)/D92)+((D83*E83)/D92)+((D84*E84)/D92)+((D85*E85)/D92)+((D86*E86)/D92)+((D87*E87)/D92)+((D88*E88)/D92)+((D89*E89)/D92)+((D90*E90)/D92)+((D91*E91)/D92),0) -> 0.16131418 | F92: =SUM(F80:F91) -> 3611594688 | G92: =IFERROR(((F80*G80)/F92)+((F81*G81)/F92)+((F82*G82)/F92)+((F83*G83)/F92)+((F84*G84)/F92)+((F85*G85)/F92)+((F86*G86)/F92)+((F87*G87)/F92)+((F88*G88)/F92)+((F89*G89)/F92)+((F90*G90)/F92)+((F91*G91)/F92),0) -> 0.085580915 | H92: =SUM(H80:H91) -> 10815884011 | I92: =SUM(I80:I91) -> 0 | J92: =SUM(J80:J91) -> 182126 | K92: =SUM(K80:K91) -> 0 | L92: =SUM(L80:L91) -> 0 | M92: =SUM(M80:M91) -> 542535631 | N92: =SUM(N80:N91) -> 196942 | O92: =SUM(O80:O91) -> 6221055785 | ... Y92: =SUM(Y80:Y91) -> 325317043
B95: Подпись Председателя правления:
B97: Подпись Главного Бухгалтера:
C99: =+[8]Balance!$C$24 -> 10815884011
C100: =+C92-C99 -> 0

Sheet Aging Analysis
A1: АНАЛИЗ ПРОСРОЧЕННЫХ КРЕДИТОВ И ФИНАНСОВОГО ЛИЗИНГА К ПОЛУЧЕНИЮ | X1: Таблица-9
B3: =+'Asset quality'!B3 -> "Микрокредитбанк" | T3: =+'Asset quality'!P3 -> 44560 | X3: тыс. сум
A4: № | B4: Характеристики | C4: Всего задолжность по кредитам | D4: % | E4: Реструктуризированные кредиты | F4: % | G4: В ходе судебного разбирательства | H4: % | I4: Просроченная задолжность | K4: % | L4: в том числе, анализ временной задолженности
L5: 1-30 дней | N5: 31-60 дней | P5: 61-90 дней | R5: 91-180 дней | T5: 181-365 дней | V5: 366-730 дней | X5: Свыше 2 лет
I6: основной долг | J6: процент | L6: основной долг | M6: процент | N6: основной долг | O6: процент | P6: основной долг | Q6: процент | R6: основной долг | S6: процент | T6: основной долг | U6: процент | V6: основной долг | W6: процент | X6: основной долг | Y6: процент
B7: (А) | C7: (Б) | D7: (В) | E7: (Г) | F7: (Д) | G7: (Е) | H7: (Ж) | I7: (З) | J7: (З1) | K7: (И) | L7: (К) | M7: (К1) | N7: (Л) | O7: (Л1) | P7: (М) | Q7: (М1) | R7: (Н) | S7: (Н1) | T7: (О) | U7: (О1) | V7: (П) | W7: (П1) | X7: (Р) | Y7: (Р1)
B8: По типу клиента
A9: 1 | B9: Центральный банк | C9: =+'Loans Receivable'!C86 -> 0 | D9: =IF(C$22=0,"",C9/C$22) -> 0 | E9: 0 | F9: =IF(E$22=0,"",E9/E$22) -> 0 | H9: =IF($G$22=0,"",G9/$G$22) | I9: =+L9+N9+P9+R9+T9+V9+X9 -> 0 | J9: =+M9+O9+T9+S9+U9+W9+Y9 -> 0 | K9: =IF($Z$22=0,"",Z9/$Z$22) -> 0 | Z9: =+I9+J9 -> 0
A10: 2 | B10: Другие банки | C10: =+'Loans Receivable'!C85 -> 0 | D10: =IF(C$22=0,"",C10/C$22) -> 0 | E10: 0 | F10: =IF(E$22=0,"",E10/E$22) -> 0 | H10: =IF($G$22=0,"",G10/$G$22) | I10: =+L10+N10+P10+R10+T10+V10+X10 -> 0 | J10: =+M10+O10+Q10+S10+U10+W10+Y10 -> 0 | K10: =IF($Z$22=0,"",Z10/$Z$22) -> 0 | Z10: =+I10+J10 -> 0
A11: 3 | B11: Правительство | C11: =+'Loans Receivable'!C87 -> 0 | D11: =IF(C$22=0,"",C11/C$22) -> 0 | E11: 0 | F11: =IF(E$22=0,"",E11/E$22) -> 0 | H11: =IF($G$22=0,"",G11/$G$22) | I11: =+L11+N11+P11+R11+T11+V11+X11 -> 0 | J11: =+M11+O11+Q11+S11+U11+W11+Y11 -> 0 | K11: =IF($Z$22=0,"",Z11/$Z$22) -> 0 | Z11: =+I11+J11 -> 0
A12: 4 | B12: Физические лица | C12: =+'Loans Receivable'!C80 -> 3084481917 | D12: =IF(C$22=0,"",C12/C$22) -> 0.28518075 | E12: 0 | F12: =IF(E$22=0,"",E12/E$22) -> 0 | G12: 0 | H12: =IF($G$22=0,"",G12/$G$22) | I12: =+L12+N12+P12+R12+T12+V12+X12 -> 1.8454683e+08 | J12: =+M12+O12+Q12+S12+U12+W12+Y12 -> 65998931 | K12: =IF($Z$22=0,"",Z12/$Z$22) -> 0.33068994 | L12: 8500898.8 | M12: 2916788 | N12: 13429970 | O12: 3207650.7 | P12: 12303129 | Q12: 3448255.4 | R12: 31428937 | S12: 14084377 | T12: 84155549 | U12: 21885432 | V12: 34717330 | W12: 20450813 | X12: 11020.92 | Y12: 5614.9629 | Z12: =+I12+J12 -> 2.5054577e+08
A13: 5 | B13: Государственные предприятия | C13: =+'Loans Receivable'!C81 -> 237969866 | D13: =IF(C$22=0,"",C13/C$22) -> 0.022001888 | E13: 0 | F13: =IF(E$22=0,"",E13/E$22) -> 0 | H13: =IF($G$22=0,"",G13/$G$22) | I13: =+L13+N13+P13+R13+T13+V13+X13 -> 10614906 | J13: =+M13+O13+Q13+S13+U13+W13+Y13 -> 1227032.8 | K13: =IF($Z$22=0,"",Z13/$Z$22) -> 0.015629919 | L13: 206250 | M13: 42092.973 | N13: 0 | O13: 0 | P13: 0 | R13: 3492311.2 | S13: 66301 | T13: 6916345.1 | U13: 1118638.8 | Z13: =+I13+J13 -> 11841939
A14: 6 | B14: Совместные и иностранные предприятия | C14: =+'Loans Receivable'!C82 -> 455620953 | D14: =IF(C$22=0,"",C14/C$22) -> 0.04212517 | E14: 127677 | F14: =IF(E$22=0,"",E14/E$22) -> 0.0036195308 | H14: =IF($G$22=0,"",G14/$G$22) | I14: =+L14+N14+P14+R14+T14+V14+X14 -> 10634713 | J14: =+M14+O14+Q14+S14+U14+W14+Y14 -> 4365814.1 | K14: =IF($Z$22=0,"",Z14/$Z$22) -> 0.019798871 | L14: 138203.16 | M14: 222599.53 | N14: 366822.17 | O14: 544433.64 | P14: 445825.42 | Q14: 554470.33 | R14: 1390799 | S14: 836387 | T14: 5277431.6 | U14: 328359.57 | V14: 3015631.4 | W14: 1879564 | X14: 0 | Y14: 0 | Z14: =+I14+J14 -> 15000527
A15: 7 | B15: Частные товарищества и корпорации | C15: =+'Loans Receivable'!C83 -> 6772953254 | D15: =IF(C$22=0,"",C15/C$22) -> 0.62620432 | E15: 34975065 | F15: =IF(E$22=0,"",E15/E$22) -> 0.99151236 | G15: 0 | H15: =IF($G$22=0,"",G15/$G$22) | I15: =+L15+N15+P15+R15+T15+V15+X15 -> 3.1147711e+08 | J15: =+M15+O15+Q15+S15+U15+W15+Y15 -> 1.5170629e+08 | K15: =IF($Z$22=0,"",Z15/$Z$22) -> 0.61134576 | L15: 20305619 | M15: 7658085.6 | N15: 27658030 | O15: 19250147 | P15: 21441601 | Q15: 12827965 | R15: 53387292 | S15: 48361062 | T15: 1.2554405e+08 | U15: 26975578 | V15: 62500448 | W15: 35805099 | X15: 640075.11 | Y15: 828354.1 | Z15: =+I15+J15 -> 4.631834e+08
A16: 8 | B16: Фермерское хозяйство | C16: =+'Loans Receivable'!C84 -> 261233028 | D16: =IF(C$22=0,"",C16/C$22) -> 0.024152721 | E16: 171720 | F16: =IF(E$22=0,"",E16/E$22) -> 0.0048681111 | G16: 0 | H16: =IF($G$22=0,"",G16/$G$22) | I16: =+L16+N16+P16+R16+T16+V16+X16 -> 8213758.5 | J16: =+M16+O16+Q16+S16+U16+W16+Y16 -> 5222760.1 | K16: =IF($Z$22=0,"",Z16/$Z$22) -> 0.01773457 | L16: 308981.67 | M16: 248770.43 | N16: 1493994.3 | O16: 313670.3 | P16: 854264.51 | Q16: 958830.08 | R16: 1213740.1 | S16: 2090631 | T16: 3343139.2 | U16: 611642.07 | V16: 999638.71 | W16: 821599 | X16: 0 | Y16: 177617.18 | Z16: =+I16+J16 -> 13436519
A17: 9 | B17: Небанковские финансовые институты | C17: =+'Loans Receivable'!C88 -> 0 | D17: =IF(C$22=0,"",C17/C$22) -> 0 | E17: 0 | F17: =IF(E$22=0,"",E17/E$22) -> 0 | H17: =IF($G$22=0,"",G17/$G$22) | I17: =+L17+N17+P17+R17+T17+V17+X17 -> 0 | J17: =+M17+O17+Q17+S17+U17+W17+Y17 -> 0 | K17: =IF($Z$22=0,"",Z17/$Z$22) -> 0 | Z17: =+I17+J17 -> 0
A18: 10 | B18: Негосударственные некоммерческие организации | C18: =+'Loans Receivable'!C89 -> 3603902 | D18: =IF(C$22=0,"",C18/C$22) -> 0.00033320457 | E18: 0 | F18: =IF(E$22=0,"",E18/E$22) -> 0 | H18: =IF($G$22=0,"",G18/$G$22) | I18: =+L18+N18+P18+R18+T18+V18+X18 -> 60283.094 | J18: =+M18+O18+Q18+S18+U18+W18+Y18 -> 9822.2658 | K18: =IF($Z$22=0,"",Z18/$Z$22) -> 9.2530549e-05 | M18: 235.4941 | N18: 35783.093 | P18: 24500.001 | Q18: 9586.7717 | Z18: =+I18+J18 -> 70105.36
A19: 11 | B19: Бюджетные организации | C19: =+'Loans Receivable'!C90 -> 0 | D19: =IF(C$22=0,"",C19/C$22) -> 0 | E19: 0 | F19: =IF(E$22=0,"",E19/E$22) -> 0 | H19: =IF($G$22=0,"",G19/$G$22) | I19: =+L19+N19+P19+R19+T19+V19+X19 -> 0 | J19: =+M19+O19+Q19+S19+U19+W19+Y19 -> 0 | K19: =IF($Z$22=0,"",Z19/$Z$22) -> 0 | Z19: =+I19+J19 -> 0
A20: 12 | B20: Прочие | C20: =+'Loans Receivable'!C91 -> 21091 | D20: =IF(C$22=0,"",C20/C$22) -> 1.9500024e-06 | E20: 0 | F20: =IF(E$22=0,"",E20/E$22) -> 0 | H20: =IF($G$22=0,"",G20/$G$22) | I20: =+L20+N20+P20+R20+T20+V20+X20 -> 0 | J20: =+M20+O20+Q20+S20+U20+W20+Y20 -> 3567304.9 | K20: =IF($Z$22=0,"",Z20/$Z$22) -> 0.0047084086 | M20: 3567304.9 | Z20: =+I20+J20 -> 3567304.9
Z21: =+I21+J21 -> 0
A22: 13 | B22: Итого кредита и лизинга | C22: =SUM(C9:C20) -> 10815884011 | D22: =IF(C$22=0,"",C22/C$22) -> 1 | E22: =SUM(E9:E20) -> 35274462 | F22: =IF(E$22=0,"",E22/E$22) -> 1 | G22: =SUM(G9:G20) -> 0 | H22: =IF($G$22=0,"",G22/$G$22) | I22: =SUM(I9:I20) -> 5.2554761e+08 | J22: =SUM(J9:J20) -> 2.3209796e+08 | K22: =IF($Z$22=0,"",Z22/$Z$22) -> 1 | L22: =SUM(L9:L20) -> 29459953 | M22: =SUM(M9:M20) -> 14655877 | N22: =SUM(N9:N20) -> 42984600 | O22: =SUM(O9:O20) -> 23315902 | P22: =SUM(P9:P20) -> 35069321 | Q22: =SUM(Q9:Q20) -> 17799108 | R22: =SUM(R9:R20) -> 90913078 | S22: =SUM(S9:S20) -> 65438758 | ... Y22: =SUM(Y9:Y20) -> 1011586.2 | Z22: =+I22+J22 -> 7.5764556e+08
Z23: =+I23+J23 -> 0
B24: По сектору экономики | F24: =IF(E$22=0,"",E24/E$22) -> 0 | Z24: =+I24+J24 -> 0
A25: 14 | B25: Промышленность | C25: =+'Loans Receivable'!C15 -> 1938850959 | D25: =IF(C$34=0,"",C25/C$34) -> 0.17925959 | F25: =IF($E$34=0,"",E25/$E$34) -> 0 | G25: 0 | H25: =IF($G$34=0,"",G25/$G$34) | I25: =+L25+N25+P25+R25+T25+V25+X25 -> 97234274 | J25: =+M25+O25+Q25+S25+U25+W25+Y25 -> 44950490 | K25: =IF($Z$34=0,"",Z25/$Z$34) -> 0.1876666 | L25: 7299629.8 | M25: 3400527.5 | N25: 4822803.5 | O25: 10415508 | P25: 3490382 | Q25: 2000018.1 | R25: 12161596 | S25: 5877150 | T25: 35757105 | U25: 7447424.6 | V25: 33604172 | W25: 15795144 | X25: 98585.5 | Y25: 14718.538 | Z25: =+I25+J25 -> 1.4218476e+08
A26: 15 | B26: Сельское хозяйство | C26: =+'Loans Receivable'!C24 -> 2467702573 | D26: =IF(C$34=0,"",C26/C$34) -> 0.22815542 | E26: 2147373 | F26: =IF($E$34=0,"",E26/$E$34) -> 0.060876138 | G26: 0 | H26: =IF($G$34=0,"",G26/$G$34) | I26: =+L26+N26+P26+R26+T26+V26+X26 -> 1.4343956e+08 | J26: =+M26+O26+Q26+S26+U26+W26+Y26 -> 59134309 | K26: =IF($Z$34=0,"",Z26/$Z$34) -> 0.26737287 | L26: 3645928.6 | M26: 1919905.3 | N26: 9491083.7 | O26: 3472339.9 | P26: 7786073.7 | Q26: 4639978.9 | R26: 28983127 | S26: 21754408 | T26: 68553677 | U26: 11054462 | V26: 24977226 | W26: 15995510 | X26: 2445.5278 | Y26: 297704.19 | Z26: =+I26+J26 -> 2.0257387e+08
A27: 16 | B27: Транспорт и коммуникации | C27: =+'Loans Receivable'!C32 -> 350494739 | D27: =IF(C$34=0,"",C27/C$34) -> 0.032405556 | F27: =IF($E$34=0,"",E27/$E$34) -> 0 | G27: 0 | H27: =IF($G$34=0,"",G27/$G$34) | I27: =+L27+N27+P27+R27+T27+V27+X27 -> 20970386 | J27: =+M27+O27+Q27+S27+U27+W27+Y27 -> 9307263.2 | K27: =IF($Z$34=0,"",Z27/$Z$34) -> 0.039962815 | L27: 3216056.5 | M27: 652730.72 | N27: 1739359.6 | O27: 776794.77 | P27: 1157110.3 | Q27: 419073.93 | R27: 2614850.6 | S27: 3168542 | T27: 6923476.8 | U27: 1457673.4 | V27: 4778043 | W27: 2473836 | X27: 541489.61 | Y27: 358612.47 | Z27: =+I27+J27 -> 30277650
A28: 17 | B28: Строительство | C28: =+'Loans Receivable'!C40 -> 340066175 | D28: =IF(C$34=0,"",C28/C$34) -> 0.031441367 | E28: 15089714 | F28: =IF($E$34=0,"",E28/$E$34) -> 0.42778013 | G28: 0 | H28: =IF($G$34=0,"",G28/$G$34) | I28: =+L28+N28+P28+R28+T28+V28+X28 -> 23008527 | J28: =+M28+O28+Q28+S28+U28+W28+Y28 -> 14218009 | K28: =IF($Z$34=0,"",Z28/$Z$34) -> 0.0491345 | L28: 436391.56 | M28: 190574.64 | N28: 2658900.4 | O28: 394605.56 | P28: 1515937.6 | Q28: 1742662.6 | R28: 3248678 | S28: 7100816 | T28: 14052126 | U28: 2631654.8 | V28: 1096493.7 | W28: 2045473 | X28: 0 | Y28: 112221.89 | Z28: =+I28+J28 -> 37226536
A29: 18 | B29: Торговля и общественное питание | C29: =+'Loans Receivable'!C48 -> 1152185836 | D29: =IF(C$34=0,"",C29/C$34) -> 0.1065272 | E29: 17026031 | F29: =IF($E$34=0,"",E29/$E$34) -> 0.48267302 | G29: 0 | H29: =IF($G$34=0,"",G29/$G$34) | I29: =+L29+N29+P29+R29+T29+V29+X29 -> 97009727 | J29: =+M29+O29+Q29+S29+U29+W29+Y29 -> 29835886 | K29: =IF($Z$34=0,"",Z29/$Z$34) -> 0.16742078 | L29: 5334362.4 | M29: 807857 | N29: 8603582.3 | O29: 1834895.6 | P29: 7643971.2 | Q29: 3849088.4 | R29: 15089228 | S29: 6403911 | T29: 46579887 | U29: 7904119.7 | V29: 13758696 | W29: 8813300 | X29: 0 | Y29: 222714.2 | Z29: =+I29+J29 -> 1.2684561e+08
A30: 19 | B30: Материально-техническое снабжение и сбыт | C30: =+'Loans Receivable'!C56 -> 1377552811 | D30: =IF(C$34=0,"",C30/C$34) -> 0.12736387 | E30: 1011344 | F30: =IF($E$34=0,"",E30/$E$34) -> 0.028670714 | G30: 0 | H30: =IF($G$34=0,"",G30/$G$34) | I30: =+L30+N30+P30+R30+T30+V30+X30 -> 47293183 | J30: =+M30+O30+Q30+S30+U30+W30+Y30 -> 26183070 | K30: =IF($Z$34=0,"",Z30/$Z$34) -> 0.096979718 | L30: 2155998.9 | M30: 1434120.2 | N30: 3858075 | O30: 2788353 | P30: 4225188.6 | Q30: 1692237.5 | R30: 11649451 | S30: 7092444 | T30: 17668342 | U30: 6276899.1 | V30: 7736126.7 | W30: 6899016 | X30: 0 | Y30: 0 | Z30: =+I30+J30 -> 73476253
A31: 20 | B31: Жилищно-коммунальные услуги | C31: =+'Loans Receivable'!C65 -> 2082182 | D31: =IF(C$34=0,"",C31/C$34) -> 0.00019251149 | F31: =IF($E$34=0,"",E31/$E$34) -> 0 | G31: 0 | H31: =IF($G$34=0,"",G31/$G$34) | I31: =+L31+N31+P31+R31+T31+V31+X31 -> 24500.001 | J31: =+M31+O31+Q31+S31+U31+W31+Y31 -> 192165.9 | K31: =IF($Z$34=0,"",Z31/$Z$34) -> 0.00028597264 | M31: 182579.13 | O31: 0 | P31: 24500.001 | Q31: 9586.7717 | S31: 0 | U31: 0 | W31: 0 | Y31: 0 | Z31: =+I31+J31 -> 216665.9
A32: 21 | B32: Другие сектора | C32: =+'Loans Receivable'!C78 -> 3186948736 | D32: =IF(C$34=0,"",C32/C$34) -> 0.29465449 | F32: =IF($E$34=0,"",E32/$E$34) -> 0 | G32: 0 | H32: =IF($G$34=0,"",G32/$G$34) | I32: =+L32+N32+P32+R32+T32+V32+X32 -> 96567447 | J32: =+M32+O32+Q32+S32+U32+W32+Y32 -> 48276763 | K32: =IF($Z$34=0,"",Z32/$Z$34) -> 0.19117674 | L32: 7371585.4 | M32: 6067582.4 | N32: 11810795 | O32: 3633405.7 | P32: 9226157.2 | Q32: 3446461.4 | R32: 17166147 | S32: 14041487 | T32: 35701897 | U32: 14147416 | V32: 15282290 | W32: 6934796 | X32: 8575.3919 | Y32: 5614.9629 | Z32: =+I32+J32 -> 1.4484421e+08
S33: 0 | Z33: =+I33+J33 -> 0
A34: 22 | B34: Итого кредита и лизинга | C34: =SUM(C25:C32) -> 10815884011 | D34: =IF(C$34=0,"",C34/C$34) -> 1 | E34: =SUM(E25:E32) -> 35274462 | F34: =IF($E$34=0,"",E34/$E$34) -> 1 | G34: =SUM(G25:G32) -> 0 | H34: =IF($G$34=0,"",G34/$G$34) | I34: =SUM(I25:I32) -> 5.2554761e+08 | J34: =SUM(J25:J32) -> 2.3209796e+08 | K34: =IF($Z$34=0,"",Z34/$Z$34) -> 1 | L34: =SUM(L25:L32) -> 29459953 | M34: =SUM(M25:M32) -> 14655877 | N34: =SUM(N25:N32) -> 42984600 | O34: =SUM(O25:O32) -> 23315902 | P34: =SUM(P25:P32) -> 35069321 | Q34: =SUM(Q25:Q32) -> 17799108 | R34: =SUM(R25:R32) -> 90913078 | S34: =SUM(S25:S32) -> 65438758 | ... Y34: =SUM(Y25:Y32) -> 1011586.2 | Z34: =+I34+J34 -> 7.5764556e+08
B37: Подпись Председателя правления:
B39: Подпись Главного Бухгалтера:

Sheet Asset Classification
A1: ОТЧЕТ О КЛАССИФИКАЦИИ АКТИВОВ ПО СТЕПЕНИ РИСКА | W1: Таблица-10
B2: =+'Asset quality'!B3 -> "Микрокредитбанк" | U2: =+'Asset quality'!P3 -> 44560 | Z2: тыс. сум
A3: № | B3: Статьи баланса | C3: Общая сумма | D3: из них, в иностранной валюте (в экв. в сумах) | E3: Стандартные | F3: из них, в иностранной валюте (в экв. в сумах) | G3: Общие резервы (1%) | H3: из них, в иностранной валюте (в экв. в сумах) | I3: Субстандартные | J3: из них, в иностранной валюте (в экв. в сумах) | K3: Специальные резервы (мин 10%) | L3: из них, в иностранной валюте (в экв. в сумах) | M3: Неудовлетворительные | N3: из них, в иностранной валюте (в экв. в сумах) | O3: Специальные резервы (мин 25%) | P3: из них, в иностранной валюте (в экв. в сумах) | Q3: Сомнительные | R3: из них, в иностранной валюте (в экв. в сумах) | S3: Специальные резервы (мин 50%) | T3: из них, в иностранной валюте (в экв. в сумах) | U3: Безнадежные | V3: из них, в иностранной валюте (в экв. в сумах) | W3: Специальные резервы (100%) | X3: из них, в иностранной валюте (в экв. в сумах) | Y3: Совокупная сумма специальных резервов | Z3: из них, в иностранной валюте (в экв. в сумах) | AA3: списанные кредиты за баланс в отчётном месяце | AB3: возврат списанных кредитов в отчётном месяце
A4: (А) | B4: (Б) | C4: (В) | D4: (В1) | E4: (Г) | F4: (Г1) | G4: (Д) | H4: (Д1) | I4: (Е) | J4: (Е1) | K4: (Ж) | L4: (Ж1) | M4: (З) | N4: (З1) | O4: (И) | P4: (И1) | Q4: (К) | R4: (К1) | S4: (Л) | T4: (Л1) | U4: (М) | V4: (М1) | W4: (Н) | X4: (Н1) | Y4: О=Ж+И+Л+Н | Z4: (О1)=(Ж1)+(И1)+(Л1)+(Н1) | AA4: П | AB4: Р
B5: По типу клиента
A6: 1 | B6: Центральный банк | C6: =E6+I6+M6+Q6+U6 -> 0 | D6: =F6+J6+N6+R6+V6 -> 0 | Y6: =+W6+S6+O6+K6 -> 0 | Z6: =+X6+T6+P6+L6 -> 0 | AC6: =+'Aging Analysis'!C9 -> 0
B7: из них необеспеченные | C7: =E7+I7+M7+Q7+U7 -> 0 | D7: =F7+J7+N7+R7+V7 -> 0 | Y7: =+W7+S7+O7+K7 -> 0 | Z7: =+X7+T7+P7+L7 -> 0
A8: 2 | B8: Другие банки | C8: =E8+I8+M8+Q8+U8 -> 0 | D8: =F8+J8+N8+R8+V8 -> 0 | Y8: =+W8+S8+O8+K8 -> 0 | Z8: =+X8+T8+P8+L8 -> 0 | AC8: =+'Aging Analysis'!C10 -> 0
B9: из них необеспеченные | C9: =E9+I9+M9+Q9+U9 -> 0 | D9: =F9+J9+N9+R9+V9 -> 0 | Y9: =+W9+S9+O9+K9 -> 0 | Z9: =+X9+T9+P9+L9 -> 0
A10: 3 | B10: Правительство | C10: =E10+I10+M10+Q10+U10 -> 0 | D10: =F10+J10+N10+R10+V10 -> 0 | Y10: =+W10+S10+O10+K10 -> 0 | Z10: =+X10+T10+P10+L10 -> 0 | AC10: =+'Aging Analysis'!C11 -> 0
B11: из них необеспеченные | C11: =E11+I11+M11+Q11+U11 -> 0 | D11: =F11+J11+N11+R11+V11 -> 0 | Y11: =+W11+S11+O11+K11 -> 0 | Z11: =+X11+T11+P11+L11 -> 0
A12: 4 | B12: Физические лица | C12: =E12+I12+M12+Q12+U12 -> 3084481917 | D12: =F12+J12+N12+R12+V12 -> 0 | E12: 2457104568 | F12: 0 | G12: 0 | H12: 0 | I12: 279332652 | J12: 0 | K12: 27922889 | L12: 0 | M12: 50523767 | N12: 0 | O12: 12252269 | P12: 0 | Q12: 60700150 | R12: 0 | S12: 29377522 | T12: 0 | U12: 236820780 | V12: 0 | W12: 51308106 | X12: 0 | Y12: =+W12+S12+O12+K12 -> 120860786 | Z12: =+X12+T12+P12+L12 -> 0 | AC12: =+'Aging Analysis'!C12 -> 3084481917
B13: из них необеспеченные | C13: =E13+I13+M13+Q13+U13 -> 0 | D13: =F13+J13+N13+R13+V13 -> 0 | Y13: =+W13+S13+O13+K13 -> 0 | Z13: =+X13+T13+P13+L13 -> 0
A14: 5 | B14: Государственные предприятия | C14: =E14+I14+M14+Q14+U14 -> 237969866 | D14: =F14+J14+N14+R14+V14 -> 54188322 | E14: 171352995 | F14: 54188322 | G14: 0 | H14: 0 | I14: 60111156 | J14: 0 | K14: 6011116 | L14: 0 | M14: 6051420 | N14: 0 | O14: 630142 | P14: 0 | Q14: 0 | R14: 0 | S14: 0 | T14: 0 | U14: 454295 | V14: 0 | W14: 0 | X14: 0 | Y14: =+W14+S14+O14+K14 -> 6641258 | Z14: =+X14+T14+P14+L14 -> 0 | AC14: =+'Aging Analysis'!C13 -> 237969866
B15: из них необеспеченные | C15: =E15+I15+M15+Q15+U15 -> 0 | D15: =F15+J15+N15+R15+V15 -> 0 | Y15: =+W15+S15+O15+K15 -> 0 | Z15: =+X15+T15+P15+L15 -> 0
A16: 6 | B16: Совместные и иностранные предприятия | C16: =E16+I16+M16+Q16+U16 -> 455620953 | D16: =F16+J16+N16+R16+V16 -> 288547784 | E16: 388512721 | F16: 241016272 | G16: 0 | H16: 0 | I16: 60958145 | J16: 47531512 | K16: 5965799 | L16: 4753151 | M16: 1011514 | N16: 0 | O16: 252879 | P16: 0 | Q16: 900280 | R16: 0 | S16: 433465 | T16: 0 | U16: 4238293 | V16: 0 | W16: 197308 | X16: 0 | Y16: =+W16+S16+O16+K16 -> 6849451 | Z16: =+X16+T16+P16+L16 -> 4753151 | AC16: =+'Aging Analysis'!C14 -> 455620953
B17: из них необеспеченные | C17: =E17+I17+M17+Q17+U17 -> 0 | D17: =F17+J17+N17+R17+V17 -> 0 | Y17: =+W17+S17+O17+K17 -> 0 | Z17: =+X17+T17+P17+L17 -> 0
A18: 7 | B18: Частные товарищества и корпорации | C18: =E18+I18+M18+Q18+U18 -> 6772953254 | D18: =F18+J18+N18+R18+V18 -> 3190462147 | E18: 5927930415 | F18: 2888927032 | G18: 0 | H18: 38811 | I18: 569159880 | J18: 181288795 | K18: 54493731 | L18: 17300828 | M18: 176884326 | N18: 119725254 | O18: 15050150 | P18: 7674629 | Q18: 18143746 | R18: 0 | S18: 8416131 | T18: 0 | U18: 80834887 | V18: 521066 | W18: 6575278 | X18: 0 | Y18: =+W18+S18+O18+K18 -> 84535290 | Z18: =+X18+T18+P18+L18 -> 24975457 | AC18: =+'Aging Analysis'!C15 -> 6772953254
B19: из них необеспеченные | C19: =E19+I19+M19+Q19+U19 -> 0 | D19: =F19+J19+N19+R19+V19 -> 0 | Y19: =+W19+S19+O19+K19 -> 0 | Z19: =+X19+T19+P19+L19 -> 0
A20: 8 | B20: Фермерское хозяйство | C20: =E20+I20+M20+Q20+U20 -> 261233028 | D20: =F20+J20+N20+R20+V20 -> 77585862 | E20: 238375501 | F20: 76152219 | G20: 0 | H20: 0 | I20: 17170732 | J20: 1433643 | K20: 1672411 | L20: 143364 | M20: 3574759 | N20: 0 | O20: 393690 | P20: 0 | Q20: 80407 | R20: 0 | S20: 40204 | T20: 0 | U20: 2031629 | V20: 0 | W20: 77223 | X20: 0 | Y20: =+W20+S20+O20+K20 -> 2183528 | Z20: =+X20+T20+P20+L20 -> 143364 | AC20: =+'Aging Analysis'!C16 -> 261233028
B21: из них необеспеченные | C21: =E21+I21+M21+Q21+U21 -> 0 | D21: =F21+J21+N21+R21+V21 -> 0 | Y21: =+W21+S21+O21+K21 -> 0 | Z21: =+X21+T21+P21+L21 -> 0
A22: 9 | B22: Небанковские финансовые институты | C22: =E22+I22+M22+Q22+U22 -> 0 | D22: =F22+J22+N22+R22+V22 -> 0 | E22: 0 | F22: 0 | G22: 0 | H22: 0 | I22: 0 | J22: 0 | K22: 0 | L22: 0 | M22: 0 | N22: 0 | O22: 0 | P22: 0 | Q22: 0 | R22: 0 | S22: 0 | T22: 0 | U22: 0 | V22: 0 | W22: 0 | X22: 0 | Y22: =+W22+S22+O22+K22 -> 0 | Z22: =+X22+T22+P22+L22 -> 0 | AC22: =+'Aging Analysis'!C17 -> 0
B23: из них необеспеченные | C23: =E23+I23+M23+Q23+U23 -> 0 | D23: =F23+J23+N23+R23+V23 -> 0 | Y23: =+W23+S23+O23+K23 -> 0 | Z23: =+X23+T23+P23+L23 -> 0
A24: 10 | B24: Негосударственные некоммерческие организации | C24: =E24+I24+M24+Q24+U24 -> 3603902 | D24: =F24+J24+N24+R24+V24 -> 810574 | E24: 3224033 | F24: 810574 | G24: 0 | H24: 0 | I24: 379869 | J24: 0 | K24: 37987 | L24: 0 | M24: 0 | N24: 0 | O24: 0 | P24: 0 | Q24: 0 | R24: 0 | S24: 0 | T24: 0 | U24: 0 | V24: 0 | W24: 0 | X24: 0 | Y24: =+W24+S24+O24+K24 -> 37987 | Z24: =+X24+T24+P24+L24 -> 0 | AC24: =+'Aging Analysis'!C18 -> 3603902
B25: из них необеспеченные | C25: =E25+I25+M25+Q25+U25 -> 0 | D25: =F25+J25+N25+R25+V25 -> 0 | Y25: =+W25+S25+O25+K25 -> 0 | Z25: =+X25+T25+P25+L25 -> 0
A26: 11 | B26: Бюджетные организации | C26: =E26+I26+M26+Q26+U26 -> 0 | D26: =F26+J26+N26+R26+V26 -> 0 | E26: 0 | F26: 0 | G26: 0 | H26: 0 | I26: 0 | J26: 0 | K26: 0 | L26: 0 | M26: 0 | N26: 0 | O26: 0 | P26: 0 | Q26: 0 | R26: 0 | S26: 0 | T26: 0 | U26: 0 | V26: 0 | W26: 0 | X26: 0 | Y26: =+W26+S26+O26+K26 -> 0 | Z26: =+X26+T26+P26+L26 -> 0 | AC26: =+'Aging Analysis'!C19 -> 0
B27: из них необеспеченные | C27: =E27+I27+M27+Q27+U27 -> 0 | D27: =F27+J27+N27+R27+V27 -> 0 | Y27: =+W27+S27+O27+K27 -> 0 | Z27: =+X27+T27+P27+L27 -> 0
A28: 12 | B28: Прочие | C28: =E28+I28+M28+Q28+U28 -> 21091 | D28: =F28+J28+N28+R28+V28 -> 0 | E28: 21091 | F28: 0 | G28: 0 | H28: 0 | I28: 0 | J28: 0 | K28: 0 | L28: 0 | M28: 0 | N28: 0 | O28: 0 | P28: 0 | Q28: 0 | R28: 0 | S28: 0 | T28: 0 | U28: 0 | V28: 0 | W28: 0 | X28: 0 | Y28: =+W28+S28+O28+K28 -> 0 | Z28: =+X28+T28+P28+L28 -> 0 | AC28: =+'Aging Analysis'!C20 -> 21091
B29: из них необеспеченные | C29: =E29+I29+M29+Q29+U29 -> 0 | D29: =F29+J29+N29+R29+V29 -> 0 | Y29: =+W29+S29+O29+K29 -> 0 | Z29: =+X29+T29+P29+L29 -> 0
A30: 13 | B30: Итого кредита и лизинга | C30: =+C6+C8+C10+C12+C14+C16+C18+C20+C22+C24+C26+C28 -> 10815884011 | D30: =+D6+D8+D10+D12+D14+D16+D18+D20+D22+D24+D26+D28 -> 3611594689 | E30: =+E6+E8+E10+E12+E14+E16+E18+E20+E22+E24+E26+E28 -> 9186521324 | F30: =+F6+F8+F10+F12+F14+F16+F18+F20+F22+F24+F26+F28 -> 3261094419 | G30: =+G6+G8+G10+G12+G14+G16+G18+G20+G22+G24+G26+G28 -> 0 | H30: =+H6+H8+H10+H12+H14+H16+H18+H20+H22+H24+H26+H28 -> 38811 | I30: =+I6+I8+I10+I12+I14+I16+I18+I20+I22+I24+I26+I28 -> 987112434 | J30: =+J6+J8+J10+J12+J14+J16+J18+J20+J22+J24+J26+J28 -> 230253950 | ... AB30: =+AB6+AB8+AB10+AB12+AB14+AB16+AB18+AB20+AB22+AB24+AB26+AB28 -> 0
B31: из них необеспеченные | C31: =+C7+C9+C11+C13+C15+C17+C19+C21+C23+C25+C27+C29 -> 0 | D31: =+D7+D9+D11+D13+D15+D17+D19+D21+D23+D25+D27+D29 -> 0 | E31: =+E7+E9+E11+E13+E15+E17+E19+E21+E23+E25+E27+E29 -> 0 | F31: =+F7+F9+F11+F13+F15+F17+F19+F21+F23+F25+F27+F29 -> 0 | G31: =+G7+G9+G11+G13+G15+G17+G19+G21+G23+G25+G27+G29 -> 0 | H31: =+H7+H9+H11+H13+H15+H17+H19+H21+H23+H25+H27+H29 -> 0 | I31: =+I7+I9+I11+I13+I15+I17+I19+I21+I23+I25+I27+I29 -> 0 | J31: =+J7+J9+J11+J13+J15+J17+J19+J21+J23+J25+J27+J29 -> 0 | ... Z31: =+Z7+Z9+Z11+Z13+Z15+Z17+Z19+Z21+Z23+Z25+Z27+Z29 -> 0
B32: По сектору экономики
A34: 14 | B34: Промышленность | C34: =E34+I34+M34+Q34+U34 -> 1938850959 | D34: =F34+J34+N34+R34+V34 -> 1287218675 | E34: 1636572171 | F34: 1125442854 | H34: 0 | I34: 193126203 | J34: 115657283 | K34: 18363338 | L34: 11171082 | M34: 53481866 | N34: 46118538 | O34: 1765442 | P34: 21340 | Q34: 8424291 | R34: 0 | S34: 4091953 | T34: 0 | U34: 47246428 | V34: 0 | W34: 3941714 | X34: 0 | Y34: =+W34+S34+O34+K34 -> 28162447 | Z34: =+X34+T34+P34+L34 -> 11192422 | AC34: =+'Aging Analysis'!C25 -> 1938850959
B35: из них необеспеченные | C35: =E35+I35+M35+Q35+U35 -> 0 | D35: =F35+J35+N35+R35+V35 -> 0 | Y35: =+W35+S35+O35+K35 -> 0 | Z35: =+X35+T35+P35+L35 -> 0
A36: 15 | B36: Сельское хозяйство | C36: =E36+I36+M36+Q36+U36 -> 2467702573 | D36: =F36+J36+N36+R36+V36 -> 703690946 | E36: 1926908101 | F36: 626566883 | H36: 38811 | I36: 240229065 | J36: 12098103 | K36: 23081064 | L36: 1209810 | M36: 103752467 | N36: 65025960 | O36: 14066613 | P36: 6502596 | Q36: 43652661 | R36: 0 | S36: 21398402 | T36: 0 | U36: 153160279 | V36: 0 | W36: 22895718 | X36: 0 | Y36: =+W36+S36+O36+K36 -> 81441797 | Z36: =+X36+T36+P36+L36 -> 7712406 | AC36: =+'Aging Analysis'!C26 -> 2467702573
B37: из них необеспеченные | C37: =E37+I37+M37+Q37+U37 -> 0 | D37: =F37+J37+N37+R37+V37 -> 0 | Y37: =+W37+S37+O37+K37 -> 0 | Z37: =+X37+T37+P37+L37 -> 0
A38: 16 | B38: Транспорт и коммуникации | C38: =E38+I38+M38+Q38+U38 -> 350494739 | D38: =F38+J38+N38+R38+V38 -> 153734143 | E38: 253658047 | F38: 92194055 | H38: 0 | I38: 88039198 | J38: 61019022 | K38: 8373065 | L38: 5668496 | M38: 3977748 | N38: 0 | O38: 539029 | P38: 0 | Q38: 887324 | R38: 0 | S38: 443760 | T38: 0 | U38: 3932422 | V38: 521066 | W38: 243352 | X38: 0 | Y38: =+W38+S38+O38+K38 -> 9599206 | Z38: =+X38+T38+P38+L38 -> 5668496 | AC38: =+'Aging Analysis'!C27 -> 350494739
B39: из них необеспеченные | C39: =E39+I39+M39+Q39+U39 -> 0 | D39: =F39+J39+N39+R39+V39 -> 0 | Y39: =+W39+S39+O39+K39 -> 0 | Z39: =+X39+T39+P39+L39 -> 0
A40: 17 | B40: Строительство | C40: =E40+I40+M40+Q40+U40 -> 340066175 | D40: =F40+J40+N40+R40+V40 -> 18341012 | E40: 247611897 | F40: 3251298 | H40: 0 | I40: 85154264 | J40: 15089714 | K40: 8304225 | L40: 1508971 | M40: 5319433 | N40: 0 | O40: 84132 | P40: 0 | Q40: 36986 | R40: 0 | S40: 4493 | T40: 0 | U40: 1943595 | V40: 0 | W40: 0 | X40: 0 | Y40: =+W40+S40+O40+K40 -> 8392850 | Z40: =+X40+T40+P40+L40 -> 1508971 | AC40: =+'Aging Analysis'!C28 -> 340066175
B41: из них необеспеченные | C41: =E41+I41+M41+Q41+U41 -> 0 | D41: =F41+J41+N41+R41+V41 -> 0 | Y41: =+W41+S41+O41+K41 -> 0 | Z41: =+X41+T41+P41+L41 -> 0
A42: 18 | B42: Торговля и общественное питание | C42: =E42+I42+M42+Q42+U42 -> 1152185836 | D42: =F42+J42+N42+R42+V42 -> 477436986 | E42: 1047523185 | F42: 473098121 | H42: 0 | I42: 75975819 | J42: 2388086 | K42: 7339238 | L42: 238809 | M42: 16627269 | N42: 1950779 | O42: 1760848 | P42: 487695 | Q42: 103011 | R42: 0 | S42: 51506 | T42: 0 | U42: 11956552 | V42: 0 | W42: 1315849 | X42: 0 | Y42: =+W42+S42+O42+K42 -> 10467441 | Z42: =+X42+T42+P42+L42 -> 726504 | AC42: =+'Aging Analysis'!C29 -> 1152185836
B43: из них необеспеченные | C43: =E43+I43+M43+Q43+U43 -> 0 | D43: =F43+J43+N43+R43+V43 -> 0 | Y43: =+W43+S43+O43+K43 -> 0 | Z43: =+X43+T43+P43+L43 -> 0
A44: 19 | B44: Материально-техническое снабжение и сбыт | C44: =E44+I44+M44+Q44+U44 -> 1377552811 | D44: =F44+J44+N44+R44+V44 -> 819323630 | E44: 1239632977 | F44: 789412185 | H44: 0 | I44: 102074601 | J44: 23281468 | K44: 10444323 | L44: 2328147 | M44: 21460608 | N44: 6629977 | O44: 3080425 | P44: 662998 | Q44: 2243274 | R44: 0 | S44: 861323 | T44: 0 | U44: 12141351 | V44: 0 | W44: 1815847 | X44: 0 | Y44: =+W44+S44+O44+K44 -> 16201918 | Z44: =+X44+T44+P44+L44 -> 2991145 | AC44: =+'Aging Analysis'!C30 -> 1377552811
B45: из них необеспеченные | C45: =E45+I45+M45+Q45+U45 -> 0 | D45: =F45+J45+N45+R45+V45 -> 0 | Y45: =+W45+S45+O45+K45 -> 0 | Z45: =+X45+T45+P45+L45 -> 0
A46: 20 | B46: Жилищно-коммунальные услуги | C46: =E46+I46+M46+Q46+U46 -> 2082182 | D46: =F46+J46+N46+R46+V46 -> 0 | E46: 795721 | F46: 0 | H46: 0 | I46: 1286461 | J46: 0 | K46: 128646 | L46: 0 | M46: 0 | N46: 0 | O46: 0 | P46: 0 | Q46: 0 | R46: 0 | S46: 0 | T46: 0 | U46: 0 | V46: 0 | W46: 0 | X46: 0 | Y46: =+W46+S46+O46+K46 -> 128646 | Z46: =+X46+T46+P46+L46 -> 0 | AC46: =+'Aging Analysis'!C31 -> 2082182
B47: из них необеспеченные | C47: =E47+I47+M47+Q47+U47 -> 0 | D47: =F47+J47+N47+R47+V47 -> 0 | Y47: =+W47+S47+O47+K47 -> 0 | Z47: =+X47+T47+P47+L47 -> 0
A48: 21 | B48: Другие сектора | C48: =E48+I48+M48+Q48+U48 -> 3186948736 | D48: =F48+J48+N48+R48+V48 -> 151849297 | E48: 2833819225 | F48: 151129023 | H48: 0 | I48: 201226823 | J48: 720274 | K48: 20070034 | L48: 72028 | M48: 33426395 | N48: 0 | O48: 7282641 | P48: 0 | Q48: 24477036 | R48: 0 | S48: 11415885 | T48: 0 | U48: 93999257 | V48: 0 | W48: 27945435 | X48: 0 | Y48: =+W48+S48+O48+K48 -> 66713995 | Z48: =+X48+T48+P48+L48 -> 72028 | AC48: =+'Aging Analysis'!C32 -> 3186948736
B49: из них необеспеченные | C49: =E49+I49+M49+Q49+U49 -> 0 | D49: =F49+J49+N49+R49+V49 -> 0 | Y49: =+W49+S49+O49+K49 -> 0 | Z49: =+X49+T49+P49+L49 -> 0
A50: 22 | B50: Итого кредита и лизинга | C50: =+C34+C36+C38+C40+C42+C44+C46+C48 -> 10815884011 | D50: =+D34+D36+D38+D40+D42+D44+D46+D48 -> 3611594689 | E50: =+E34+E36+E38+E40+E42+E44+E46+E48 -> 9186521324 | F50: =+F34+F36+F38+F40+F42+F44+F46+F48 -> 3261094419 | G50: =+G34+G36+G38+G40+G42+G44+G46+G48 -> 0 | H50: =+H34+H36+H38+H40+H42+H44+H46+H48 -> 38811 | I50: =+I34+I36+I38+I40+I42+I44+I46+I48 -> 987112434 | J50: =+J34+J36+J38+J40+J42+J44+J46+J48 -> 230253950 | ... AB50: =+AB34+AB36+AB38+AB40+AB42+AB44+AB46+AB48 -> 0
B51: из них необеспеченные | C51: =+C35+C37+C39+C41+C43+C45+C47+C49 -> 0 | D51: =+D35+D37+D39+D41+D43+D45+D47+D49 -> 0 | E51: =+E35+E37+E39+E41+E43+E45+E47+E49 -> 0 | F51: =+F35+F37+F39+F41+F43+F45+F47+F49 -> 0 | G51: =+G35+G37+G39+G41+G43+G45+G47+G49 -> 0 | H51: =+H35+H37+H39+H41+H43+H45+H47+H49 -> 0 | I51: =+I35+I37+I39+I41+I43+I45+I47+I49 -> 0 | J51: =+J35+J37+J39+J41+J43+J45+J47+J49 -> 0 | ... AB51: =+AB35+AB37+AB39+AB41+AB43+AB45+AB47+AB49 -> 0
B52: По регионам
A54: 23 | B54: Республика Каракалпакстан | C54: =E54+I54+M54+Q54+U54 -> 501683978 | D54: =F54+J54+N54+R54+V54 -> 50567730 | E54: 464321265 | F54: 50567730 | G54: 0 | H54: 0 | I54: 19802585 | J54: 0 | K54: 3384658 | L54: 0 | M54: 2889737 | N54: 0 | O54: 703934 | P54: 0 | Q54: 1065014 | R54: 0 | S54: 484678 | T54: 0 | U54: 13605377 | V54: 0 | W54: 5734210 | X54: 0 | Y54: =+W54+S54+O54+K54 -> 10307480 | Z54: =+X54+T54+P54+L54 -> 0
A55: 24 | B55: Андижанская область | C55: =E55+I55+M55+Q55+U55 -> 625117886 | D55: =F55+J55+N55+R55+V55 -> 160940402 | E55: 467590960 | F55: 131796818 | G55: 0 | H55: 0 | I55: 94412775 | J55: 29143584 | K55: 8862866 | L55: 2739760 | M55: 12343857 | N55: 0 | O55: 1873092 | P55: 0 | Q55: 8345505 | R55: 0 | S55: 4098723 | T55: 0 | U55: 42424789 | V55: 0 | W55: 12118561 | X55: 0 | Y55: =+W55+S55+O55+K55 -> 26953242 | Z55: =+X55+T55+P55+L55 -> 2739760
A56: 25 | B56: Бухарская область | C56: =E56+I56+M56+Q56+U56 -> 666034507 | D56: =F56+J56+N56+R56+V56 -> 120235623 | E56: 601172632 | F56: 106714776 | G56: 0 | H56: 0 | I56: 47520384 | J56: 11570068 | K56: 4030466 | L56: 503553 | M56: 5890837 | N56: 1950779 | O56: 1419098 | P56: 487695 | Q56: 4747144 | R56: 0 | S56: 2357072 | T56: 0 | U56: 6703510 | V56: 0 | W56: 540476 | X56: 0 | Y56: =+W56+S56+O56+K56 -> 8347112 | Z56: =+X56+T56+P56+L56 -> 991248
A57: 26 | B57: Джизакская область | C57: =E57+I57+M57+Q57+U57 -> 425494579 | D57: =F57+J57+N57+R57+V57 -> 61987422 | E57: 295520829 | F57: 21001913 | G57: 0 | H57: 0 | I57: 65265378 | J57: 5221231 | K57: 6192019 | L57: 522123 | M57: 39382295 | N57: 35764278 | O57: 885762 | P57: 0 | Q57: 5537263 | R57: 0 | S57: 2662471 | T57: 0 | U57: 19788814 | V57: 0 | W57: 3249391 | X57: 0 | Y57: =+W57+S57+O57+K57 -> 12989643 | Z57: =+X57+T57+P57+L57 -> 522123
A58: 27 | B58: Кашкадарьинская область | C58: =E58+I58+M58+Q58+U58 -> 684241355 | D58: =F58+J58+N58+R58+V58 -> 106625834 | E58: 537402677 | F58: 63349326 | G58: 0 | H58: 38811 | I58: 105352104 | J58: 43276508 | K58: 10465606 | L58: 4327651 | M58: 12224501 | N58: 0 | O58: 2955513 | P58: 0 | Q58: 6933556 | R58: 0 | S58: 3181887 | T58: 0 | U58: 22328517 | V58: 0 | W58: 3824454 | X58: 0 | Y58: =+W58+S58+O58+K58 -> 20427460 | Z58: =+X58+T58+P58+L58 -> 4327651
A59: 28 | B59: Навоийская область | C59: =E59+I59+M59+Q59+U59 -> 349421475 | D59: =F59+J59+N59+R59+V59 -> 15706155 | E59: 288235642 | F59: 15030087 | G59: 0 | H59: 0 | I59: 37133412 | J59: 676068 | K59: 3717125 | L59: 67607 | M59: 3635392 | N59: 0 | O59: 819313 | P59: 0 | Q59: 4165499 | R59: 0 | S59: 2023529 | T59: 0 | U59: 16251530 | V59: 0 | W59: 1809241 | X59: 0 | Y59: =+W59+S59+O59+K59 -> 8369208 | Z59: =+X59+T59+P59+L59 -> 67607
A60: 29 | B60: Наманганская область | C60: =E60+I60+M60+Q60+U60 -> 673183998 | D60: =F60+J60+N60+R60+V60 -> 65655927 | E60: 508053827 | F60: 64380234 | G60: 0 | H60: 0 | I60: 59776842 | J60: 1275693 | K60: 5221085 | L60: 127569 | M60: 18464288 | N60: 0 | O60: 3009226 | P60: 0 | Q60: 17810689 | R60: 0 | S60: 8532384 | T60: 0 | U60: 69078352 | V60: 0 | W60: 12433202 | X60: 0 | Y60: =+W60+S60+O60+K60 -> 29195897 | Z60: =+X60+T60+P60+L60 -> 127569
A61: 30 | B61: Самаркандская область | C61: =E61+I61+M61+Q61+U61 -> 823311565 | D61: =F61+J61+N61+R61+V61 -> 43003810 | E61: 659158890 | F61: 35491829 | G61: 0 | H61: 0 | I61: 93870679 | J61: 7511981 | K61: 8828156 | L61: 751198 | M61: 8205747 | N61: 0 | O61: 1778476 | P61: 0 | Q61: 7401557 | R61: 0 | S61: 3533088 | T61: 0 | U61: 54674692 | V61: 0 | W61: 7729633 | X61: 0 | Y61: =+W61+S61+O61+K61 -> 21869353 | Z61: =+X61+T61+P61+L61 -> 751198
A62: 31 | B62: Сурхандарьинская область | C62: =E62+I62+M62+Q62+U62 -> 1119643274 | D62: =F62+J62+N62+R62+V62 -> 350386278 | E62: 925011259 | F62: 304798234 | G62: 0 | H62: 0 | I62: 122438405 | J62: 35319145 | K62: 12029577 | L62: 3531914 | M62: 35712380 | N62: 10268899 | O62: 4019503 | P62: 0 | Q62: 10864077 | R62: 0 | S62: 5149233 | T62: 0 | U62: 25617153 | V62: 0 | W62: 3704869 | X62: 0 | Y62: =+W62+S62+O62+K62 -> 24903182 | Z62: =+X62+T62+P62+L62 -> 3531914
A63: 32 | B63: Сырдарьинская область | C63: =E63+I63+M63+Q63+U63 -> 678359198 | D63: =F63+J63+N63+R63+V63 -> 259219342 | E63: 589224065 | F63: 241888712 | G63: 0 | H63: 0 | I63: 63600096 | J63: 16809564 | K63: 6072791 | L63: 1680957 | M63: 9142115 | N63: 0 | O63: 1218887 | P63: 0 | Q63: 2746743 | R63: 0 | S63: 1336924 | T63: 0 | U63: 13646179 | V63: 521066 | W63: 1046040 | X63: 0 | Y63: =+W63+S63+O63+K63 -> 9674642 | Z63: =+X63+T63+P63+L63 -> 1680957
A64: 33 | B64: г. Ташкент | C64: =E64+I64+M64+Q64+U64 -> 2152730961 | D64: =F64+J64+N64+R64+V64 -> 1467291763 | E64: 1957102905 | F64: 1336604211 | G64: 0 | H64: 0 | I64: 122538641 | J64: 59031615 | K64: 12233964 | L64: 5903161 | M64: 71877385 | N64: 71655937 | O64: 7220957 | P64: 7165594 | Q64: 185470 | R64: 0 | S64: 81740 | T64: 0 | U64: 1026560 | V64: 0 | W64: 225410 | X64: 0 | Y64: =+W64+S64+O64+K64 -> 19762071 | Z64: =+X64+T64+P64+L64 -> 13068755
A65: 34 | B65: Ташкентская область | C65: =E65+I65+M65+Q65+U65 -> 960004513 | D65: =F65+J65+N65+R65+V65 -> 498905946 | E65: 835711883 | F65: 479425229 | G65: 0 | H65: 0 | I65: 90665510 | J65: 19395356 | K65: 8733337 | L65: 1939536 | M65: 12463067 | N65: 85361 | O65: 1249015 | P65: 21340 | Q65: 4090445 | R65: 0 | S65: 1965819 | T65: 0 | U65: 17073608 | V65: 0 | W65: 2376039 | X65: 0 | Y65: =+W65+S65+O65+K65 -> 14324210 | Z65: =+X65+T65+P65+L65 -> 1960876
... A67: 36 | B67: Хорезмская область | C67: =E67+I67+M67+Q67+U67 -> 576289061 | D67: =F67+J67+N67+R67+V67 -> 231441471 | E67: 527272550 | F67: 230578294 | G67: 0 | H67: 0 | I67: 35474008 | J67: 863177 | K67: 3436812 | L67: 86318 | M67: 2266224 | N67: 0 | O67: 559823 | P67: 0 | Q67: 2747815 | R67: 0 | S67: 1295009 | T67: 0 | U67: 8528464 | V67: 0 | W67: 1533682 | X67: 0 | Y67: =+W67+S67+O67+K67 -> 6825326 | Z67: =+X67+T67+P67+L67 -> 86318
A68: 37 | B68: Итого кредита и лизинга | C68: =SUM(C54:C67) -> 10815884011 | D68: =SUM(D54:D67) -> 3611594689 | E68: =SUM(E54:E67) -> 9186521324 | F68: =SUM(F54:F67) -> 3261094419 | G68: =SUM(G54:G67) -> 0 | H68: =SUM(H54:H67) -> 38811 | I68: =SUM(I54:I67) -> 987112434 | J68: =SUM(J54:J67) -> 230253950 | ... AB68: =SUM(AB54:AB67) -> 0
A69: 38 | B69: Другие классифицированные активы | C69: =E69+I69+M69+Q69+U69 -> 1698718091 | D69: =F69+J69+N69+R69+V69 -> 0 | E69: 1698718091 | G69: 48718159 | K69: 2846320 | Y69: =+W69+S69+O69+K69 -> 2846320 | Z69: =+X69+T69+P69+L69 -> 0
B70: из них необеспеченные | C70: =E70+I70+M70+Q70+U70 -> 0 | D70: =F70+J70+N70+R70+V70 -> 0 | Y70: =+W70+S70+O70+K70 -> 0 | Z70: =+X70+T70+P70+L70 -> 0
A71: 39 | B71: Всего классифицированных активов | C71: =+C50+C69 -> 12514602102 | D71: =+D50+D69 -> 3611594689 | E71: =+E50+E69 -> 10885239415 | F71: =+F50+F69 -> 3261094419 | G71: =+G50+G69 -> 48718159 | H71: =+H50+H69 -> 38811 | I71: =+I50+I69 -> 987112434 | J71: =+J50+J69 -> 230253950 | ... AB71: =+AB50+AB69 -> 0
B74: Подпись Председателя правления:
B76: Подпись Главного Бухгалтера:
E77: =SUM('Asset quality'!D21:D47)+'Asset quality'!D16 -> 9186521324 | G77: =SUM('Asset quality'!O21:O47)+'Asset quality'!O16 -> 0 | I77: =SUM('Asset quality'!E21:E47)+'Asset quality'!E16 -> 987112434 | K77: =SUM('Asset quality'!P21:P47)+'Asset quality'!P16 -> 96103933 | M77: =SUM('Asset quality'!F21:F47)+'Asset quality'!F16 -> 238045786 | O77: =SUM('Asset quality'!Q21:Q47)+'Asset quality'!Q16 -> 28579130 | Q77: =SUM('Asset quality'!G21:G47)+'Asset quality'!G16 -> 79824583 | S77: =SUM('Asset quality'!R21:R47)+'Asset quality'!R16 -> 38267322 | U77: =SUM('Asset quality'!H21:H47)+'Asset quality'!H16 -> 324379884 | W77: =SUM('Asset quality'!S21:S47)+'Asset quality'!S16 -> 58157915 | Y77: =+W77+S77+O77+K77 -> 221108300
G78: =+'Asset quality'!O9+'Asset quality'!O62 -> 48718159 | K78: =+'Asset quality'!P9+'Asset quality'!P62 -> 98950253 | O78: =+'Asset quality'!Q9+'Asset quality'!Q62 -> 28579130 | S78: =+'Asset quality'!R9+'Asset quality'!R62 -> 38267322 | W78: =+'Asset quality'!S9+'Asset quality'!S62 -> 58157915 | Y78: =+W78+S78+O78+K78 -> 223954620
E79: =+E77-E50 -> 0 | G79: =+G77-G50 -> 0 | I79: =+I77-I50 -> 0 | K79: =+K77-K50 -> 0 | M79: =+M77-M50 -> 0 | O79: =+O77-O50 -> 0 | Q79: =+Q77-Q50 -> 0 | S79: =+S77-S50 -> 0 | U79: =+U77-U50 -> 0 | W79: =+W77-W50 -> 0 | Y79: =+Y77-Y50 -> 0
G80: =+G78-G71 -> 0 | K80: =+K78-K71 -> 0 | O80: =+O78-O71 -> 0 | S80: =+S78-S71 -> 0 | W80: =+W78-W71 -> 0 | Y80: =+Y78-Y71 -> 0

Sheet loans type
Z1: Таблица-20 А
A2: Информация о структуре кредитного портфеля
B3: =+'Asset quality'!B3 -> "Микрокредитбанк" | V3: =+'Asset quality'!P3 -> 44560 | Z3: тыс. сум
A4: № | B4: Виды кредитования | C4: всего | I4: Сроки | N4: Категория качества | S4: Резерв на возможные потери | Y4: Списанные на внебаланс | Z4: Реструктуризи-рованные кредиты
I5: до 1 года | J5: От 1 до 5 лет | K5: От 5 до 10 лет | L5: От 10 до 15 лет | M5: Свыше 15 лет | S5: итого | T5: по категориям качества
C6: Остаток | D6: средневзвешенные % ставки | E6: в нацвалюте | F6: средневзвешенные % ставки | G6: в инвалюте | H6: средневзвешенные % ставки | N6: I | O6: II | P6: III | Q6: IV | R6: V | T6: I | U6: II | V6: III | W6: IV | X6: V | AB6: I | AC6: II | AD6: III | AE6: IV | AF6: V
B7: А | C7: Б | D7: В | E7: Г | F7: Д | G7: Е | H7: Ж | I7: З | J7: И | K7: К | L7: Л | M7: М | N7: Н | O7: О | P7: П | Q7: Р | R7: С | S7: Т | T7: У | U7: Ф | V7: Х | W7: Ц | X7: Ч | Y7: Ш | Z7: Щ
B8: ВСЕГО | C8: =+C9+C25 -> 10815884011 | D8: =IFERROR(((C9*D9)/C8)+((C25*D25)/C8),0) -> 0.12849568 | E8: =+E9+E25 -> 7204289323 | F8: =IFERROR(((E9*F9)/E8)+((E25*F25)/E8),0) -> 0.14999923 | G8: =+G9+G25 -> 3611594688 | H8: =IFERROR(((G9*H9)/G8)+((G25*H25)/G8),0) -> 0.085601115 | I8: =+I9+I25 -> 1882781339 | J8: =+J9+J25 -> 7196391815 | K8: =+K9+K25 -> 1127745122 | L8: =+L9+L25 -> 320076399 | M8: =+M9+M25 -> 288889336 | N8: =+N9+N25 -> 9186521324 | O8: =+O9+O25 -> 987112434 | P8: =+P9+P25 -> 238045786 | ... Z8: =+Z9+Z25 -> 0 | AA8: =+'Loans Receivable'!C92 -> 10815884011 | AB8: =+'Asset Classification'!G30 -> 0 | AC8: =+'Asset Classification'!K30 -> 96103933 | AD8: =+'Asset Classification'!O50 -> 28579130 | AE8: =+'Asset Classification'!S50 -> 38267322 | AF8: =+'Asset Classification'!W50 -> 58157915
A9: I | B9: Физические лица | C9: =+C11+C16+C21+C22+C24 -> 3084481917 | D9: =IFERROR(((C11*D11)/C9)+((C16*D16)/C9)+((C21*D21)/C9)+((C22*D22)/C9)+((C24*D24)/C9),0) -> 0.13213654 | E9: =+E11+E16+E21+E22+E24 -> 3084481917 | F9: =IFERROR(((E11*F11)/E9)+((E16*F16)/E9)+((E21*F21)/E9)+((E22*F22)/E9)+((E24*F24)/E9),0) -> 0.13213654 | G9: =+G11+G16+G21+G22+G24 -> 0 | H9: =IFERROR(((G11*H11)/G9)+((G16*H16)/G9)+((G21*H21)/G9)+((G22*H22)/G9)+((G24*H24)/G9),0) -> 0 | I9: =+I11+I16+I21+I22+I24 -> 316489565 | J9: =+J11+J16+J21+J22+J24 -> 2257635694 | K9: =+K11+K16+K21+K22+K24 -> 52246904 | L9: =+L11+L16+L21+L22+L24 -> 169220418 | M9: =+M11+M16+M21+M22+M24 -> 288889336 | N9: =+N11+N16+N21+N22+N24 -> 2457104567 | O9: =+O11+O16+O21+O22+O24 -> 279332652 | P9: =+P11+P16+P21+P22+P24 -> 50523766 | ... Z9: =+Z11+Z16+Z21+Z22+Z24 -> 0 | AA9: =+'Loans Receivable'!C80 -> 3084481917 | AB9: =+'Asset Classification'!E30 -> 9186521324 | AC9: =+'Asset Classification'!I30 -> 987112434 | AD9: =+'Asset Classification'!M30 -> 238045786 | AE9: =+'Asset Classification'!Q30 -> 79824583 | AF9: =+'Asset Classification'!U30 -> 324379884
B10: в том числе | AB10: =+N8-AB9 -> 0 | AC10: =+O8-AC9 -> 0 | AD10: =+P8-AD9 -> 0 | AE10: =+Q8-AE9 -> 0 | AF10: =+R8-AF9 -> 0
A11: 1 | B11: Ипотечные кредиты (льготные) в том числе: | C11: =SUM(C12:C15) -> 22828512 | D11: =IFERROR(((C12*D12)/C11)+((C13*D13)/C11)+((C14*D14)/C11)+((C15*D15)/C11),0) -> 0.095631003 | E11: =SUM(E12:E15) -> 22828512 | F11: =IFERROR(((E12*F12)/E11)+((E13*F13)/E11)+((E14*F14)/E11)+((E15*F15)/E11),0) -> 0.095631003 | G11: =SUM(G12:G15) -> 0 | H11: =IFERROR(((G12*H12)/G11)+((G13*H13)/G11)+((G14*H14)/G11)+((G15*H15)/G11),0) -> 0 | I11: =SUM(I12:I15) -> 6351 | J11: =SUM(J12:J15) -> 2016883 | K11: =SUM(K12:K15) -> 4883052 | L11: =SUM(L12:L15) -> 4061818 | M11: =SUM(M12:M15) -> 11860408 | N11: =SUM(N12:N15) -> 20971970 | O11: =SUM(O12:O15) -> 1526660 | P11: =SUM(P12:P15) -> 141194 | ... Z11: =SUM(Z12:Z15) -> 0 | AA11: =+'loans_av rate'!C10 -> 22828512 | AB11: =+'loans_av rate'!E10 -> 22828512 | AC11: =+'loans_av rate'!G10 -> 0
A12: 1.1. | B12: на приобретение недвижимого имущества | C12: =+E12+G12 -> 22828512 | D12: 0.095631003 | E12: 22828512 | F12: 0.095631003 | I12: 6351 | J12: 2016883 | K12: 4883052 | L12: 4061818 | M12: 11860408 | N12: 20971970 | O12: 1526660 | P12: 141194 | Q12: 18 | R12: 188670 | S12: =SUM(T12:X12) -> 209689 | T12: 0 | U12: 152666 | V12: 35299 | W12: 9 | X12: 21715
A13: 1.2. | B13: на ремонт недвижимого имущества | C13: =+E13+G13 -> 0 | D13: 0.17191684 | E13: 0 | F13: 0.17191684 | S13: =SUM(T13:X13) -> 8533422 | T13: 0 | U13: 3789693 | V13: 1696712 | W13: 0 | X13: 3047017
A14: 1.3. | B14: на реконструкцию недвижимого имущества | C14: =+E14+G14 -> 0 | S14: =SUM(T14:X14) -> 0
A15: 1.4. | B15: на строительство недвижимого имущества | C15: =+E15+G15 -> 0 | S15: =SUM(T15:X15) -> 0
A16: 2 | B16: Ипотечные кредиты (коммерческие) в том числе: | C16: =SUM(C17:C20) -> 480100952 | D16: =IFERROR(((C17*D17)/C16)+((C18*D18)/C16)+((C19*D19)/C16)+((C20*D20)/C16),0) -> 0 | E16: =SUM(E17:E20) -> 480100952 | F16: =IFERROR(((E17*F17)/E16)+((E18*F18)/E16)+((E19*F19)/E16)+((E20*F20)/E16),0) -> 0 | G16: =SUM(G17:G20) -> 0 | H16: =IFERROR(((G17*H17)/G16)+((G18*H18)/G16)+((G19*H19)/G16)+((G20*H20)/G16),0) -> 0 | I16: =SUM(I17:I20) -> 34179 | J16: =SUM(J17:J20) -> 2398432 | K16: =SUM(K17:K20) -> 42633276 | L16: =SUM(L17:L20) -> 158006137 | M16: =SUM(M17:M20) -> 277028928 | N16: =SUM(N17:N20) -> 428114947 | O16: =SUM(O17:O20) -> 35984906 | P16: =SUM(P17:P20) -> 6786850 | ... Z16: =SUM(Z17:Z20) -> 0 | AA16: =+'loans_av rate'!C18 -> 480100952 | AB16: =+'loans_av rate'!E18 -> 480100952 | AC16: =+'loans_av rate'!G18 -> 0
A17: 2.1. | B17: на приобретение недвижимого имущества | C17: =+E17+G17 -> 480100952 | E17: 480100952 | I17: 34179 | J17: 2398432 | K17: 42633276 | L17: 158006137 | M17: 277028928 | N17: 428114947 | O17: 35984906 | P17: 6786850 | Q17: 0 | R17: 9214249 | S17: =SUM(T17:X17) -> 0
A18: 2.2. | B18: на ремонт недвижимого имущества | C18: =+E18+G18 -> 0 | S18: =SUM(T18:X18) -> 0
A19: 2.3. | B19: на реконструкцию недвижимого имущества | C19: =+E19+G19 -> 0 | S19: =SUM(T19:X19) -> 0
A20: 2.4. | B20: на строительство недвижимого имущества | C20: =+E20+G20 -> 0 | S20: =SUM(T20:X20) -> 0
A21: 3 | B21: микрозайм (все нецелевые кредиты) | C21: =+E21+G21 -> 181848390 | D21: 0.25010767 | E21: 181848390 | F21: 0.25010767 | I21: 101378441 | J21: 80469949 | K21: 0 | L21: 0 | M21: 0 | N21: 145581378 | O21: 23694726 | P21: 1499747 | Q21: 628028 | R21: 10444511 | S21: =SUM(T21:X21) -> 8546750 | T21: 0 | U21: 2370175 | V21: 368816 | W21: 314015 | X21: 5493744 | AA21: =+'loans_av rate'!C12+'loans_av rate'!C20 -> 181848390 | AB21: =+'loans_av rate'!E12+'loans_av rate'!E20 -> 181848390 | AC21: =+'loans_av rate'!G12+'loans_av rate'!G20 -> 0
A22: 4 | B22: потребительские кредиты | C22: =+E22+G22 -> 257666893 | D22: 0.27508806 | E22: 257666893 | F22: 0.27508806 | I22: 38830229 | J22: 218836664 | K22: 0 | L22: 0 | M22: 0 | N22: 213285187 | O22: 24438641 | P22: 2500933 | Q22: 1382687 | R22: 16059445 | S22: =SUM(T22:X22) -> 13950536 | T22: 0 | U22: 2447345 | V22: 617787 | W22: 672354 | X22: 10213050 | AA22: =+'loans_av rate'!C11+'loans_av rate'!C13+'loans_av rate'!C19+'loans_av rate'!C21 -> 257666893 | AB22: =+'loans_av rate'!E11+'loans_av rate'!E13+'loans_av rate'!E19+'loans_av rate'!E21 -> 257666893
A23: 4.1. | B23: из них на приобретения автомобиля | C23: =+E23+G23 -> 84557811 | D23: 0.26628017 | E23: 84557811 | F23: 0.26628017 | I23: 12624048 | J23: 71933763 | K23: 0 | L23: 0 | M23: 0 | N23: 78021183 | O23: 4838596 | P23: 287573 | Q23: 18178 | R23: 1392281 | S23: =SUM(T23:X23) -> 734432 | T23: 0 | U23: 483084 | V23: 64447 | W23: 9089 | X23: 177812 | AA23: =+'loans_av rate'!C11+'loans_av rate'!C19 -> 84557811 | AB23: =+'loans_av rate'!E11+'loans_av rate'!E19 -> 84557811 | AC23: =+'loans_av rate'!G11+'loans_av rate'!G19 -> 0
A24: 5 | B24: другие кредиты физическим лицам | C24: =+E24+G24 -> 2142037170 | D24: 0.13493085 | E24: 2142037170 | F24: 0.13493085 | I24: 176240365 | J24: 1953913766 | K24: 4730576 | L24: 7152463 | M24: 0 | N24: 1649151085 | O24: 193687719 | P24: 39595042 | Q24: 58689417 | R24: 200913907 | S24: =SUM(T24:X24) -> 89620391 | T24: 0 | U24: 19163010 | V24: 9533656 | W24: 28391145 | X24: 32532580 | AA24: =+'loans_av rate'!C14+'loans_av rate'!C22 -> 2142037170 | AB24: =+'loans_av rate'!E14+'loans_av rate'!E22 -> 2142037170
A25: II | B25: Юридические лица | C25: =+C26 -> 7731402094 | D25: =IFERROR(((C27*D27)/C25)+((C28*D28)/C25)+((C29*D29)/C25)+((C30*D30)/C25)+((C31*D31)/C25)+((C32*D32)/C25),0) -> 0.12704314 | E25: =+E26 -> 4119807406 | F25: =IFERROR(((E27*F27)/E25)+((E28*F28)/E25)+((E29*F29)/E25)+((E30*F30)/E25)+((E31*F31)/E25)+((E32*F32)/E25),0) -> 0.16337294 | G25: =+G26 -> 3611594688 | H25: =IFERROR(((G27*H27)/G25)+((G28*H28)/G25)+((G29*H29)/G25)+((G30*H30)/G25)+((G31*H31)/G25)+((G32*H32)/G25),0) -> 0.085601115 | I25: =+I26 -> 1566291774 | J25: =+J26 -> 4938756121 | K25: =+K26 -> 1075498218 | L25: =+L26 -> 150855981 | M25: =+M26 -> 0 | N25: =+N26 -> 6729416757 | O25: =+O26 -> 707779782 | P25: =+P26 -> 187522020 | ... Z25: =+Z26 -> 0 | AA25: =+'loans_av rate'!C24+'loans_av rate'!C33 -> 7731402094 | AB25: =+'loans_av rate'!E24+'loans_av rate'!E33 -> 4119807406 | AC25: =+'loans_av rate'!G24+'loans_av rate'!G33 -> 3611594688
B26: в том числе по видам кредитования | C26: =SUM(C27:C32) -> 7731402094 | D26: =IFERROR(((C28*D28)/C26)+((C29*D29)/C26)+((C30*D30)/C26)+((C31*D31)/C26)+((C32*D32)/C26),0) -> 0.1147258 | E26: =SUM(E27:E32) -> 4119807406 | F26: =IFERROR(((E28*F28)/E26)+((E29*F29)/E26)+((E30*F30)/E26)+((E31*F31)/E26)+((E32*F32)/E26),0) -> 0.14028709 | G26: =SUM(G27:G32) -> 3611594688 | H26: =IFERROR(((G28*H28)/G26)+((G29*H29)/G26)+((G30*H30)/G26)+((G31*H31)/G26)+((G32*H32)/G26),0) -> 0.085567589 | I26: =SUM(I27:I32) -> 1566291774 | J26: =SUM(J27:J32) -> 4938756121 | K26: =SUM(K27:K32) -> 1075498218 | L26: =SUM(L27:L32) -> 150855981 | M26: =SUM(M27:M32) -> 0 | N26: =SUM(N27:N32) -> 6729416757 | O26: =SUM(O27:O32) -> 707779782 | P26: =SUM(P27:P32) -> 187522020 | ... Z26: =SUM(Z27:Z32) -> 0
A27: 1 | B27: микрокредит | C27: =+E27+G27 -> 680502483 | D27: 0.13994118 | E27: 678722491 | F27: 0.14012979 | G27: 1779992 | H27: 0.06802262 | I27: 104528321 | J27: 532721580 | K27: 41882082 | L27: 1370500 | M27: 0 | N27: 538961893 | O27: 61888587 | P27: 8862548 | Q27: 12388659 | R27: 58400796 | S27: =SUM(T27:X27) -> 17849119 | T27: 0 | U27: 5456950 | V27: 2053582 | W27: 5848562 | X27: 4490025 | AA27: =+'loans_av rate'!C26+'loans_av rate'!C35 -> 680502483 | AB27: =+'loans_av rate'!E26+'loans_av rate'!E35 -> 678722491 | AC27: =+'loans_av rate'!G26+'loans_av rate'!G35 -> 1779992
A28: 2 | B28: синдицированные кредит | C28: =+E28+G28 -> 0 | I28: 0 | J28: 0 | K28: 0 | L28: 0 | M28: 0 | N28: 0 | O28: 0 | P28: 0 | Q28: 0 | R28: 0 | S28: =SUM(T28:X28) -> 0 | AA28: =+'loans_av rate'!C27+'loans_av rate'!C36 -> 0 | AB28: =+'loans_av rate'!E27+'loans_av rate'!E36 -> 0 | AC28: =+'loans_av rate'!G27+'loans_av rate'!G36 -> 0
A29: 3 | B29: лизинг | C29: =+E29+G29 -> 5524447 | D29: 0.10510397 | E29: 340794 | F29: 0.18273802 | G29: 5183653 | H29: 0.1 | I29: 119946 | J29: 5404501 | K29: 0 | L29: 0 | M29: 0 | N29: 5194511 | O29: 220848 | P29: 0 | Q29: 0 | R29: 109088 | S29: =SUM(T29:X29) -> 85114 | T29: 0 | U29: 22085 | V29: 0 | W29: 0 | X29: 63029 | AA29: =+'loans_av rate'!C28+'loans_av rate'!C37 -> 5524447 | AB29: =+'loans_av rate'!E28+'loans_av rate'!E37 -> 340794 | AC29: =+'loans_av rate'!G28+'loans_av rate'!G37 -> 5183653
A30: 4 | B30: факторинг | C30: =+E30+G30 -> 86599877 | D30: 0.03204382 | E30: 86599877 | F30: 0.03204382 | G30: 0 | H30: 0 | I30: 86599877 | J30: 0 | K30: 0 | L30: 0 | M30: 0 | N30: 84390000 | O30: 146063 | P30: 2213814 | Q30: 0 | R30: -150000 | S30: =SUM(T30:X30) -> 274737 | T30: 0 | U30: 18356 | V30: 246381 | W30: 0 | X30: 10000 | AA30: =+'loans_av rate'!C29+'loans_av rate'!C38 -> 86599877 | AB30: =+'loans_av rate'!E29+'loans_av rate'!E38 -> 86599877 | AC30: =+'loans_av rate'!G29+'loans_av rate'!G38 -> 0
A31: 5 | B31: межбанковский кредит | C31: =+E31+G31 -> 0 | I31: 0 | J31: 0 | K31: 0 | L31: 0 | M31: 0 | S31: =SUM(T31:X31) -> 0 | AA31: =+'loans_av rate'!C30+'loans_av rate'!C39 -> 0 | AB31: =+'loans_av rate'!E30+'loans_av rate'!E39 -> 0 | AC31: =+'loans_av rate'!G30+'loans_av rate'!G39 -> 0
A32: 6 | B32: другие виды кредитования | C32: =+E32+G32 -> 6958775287 | D32: 0.12698149 | E32: 3354144244 | F32: 0.17146506 | G32: 3604631043 | H32: 0.085589089 | I32: 1375043630 | J32: 4400630040 | K32: 1033616136 | L32: 149485481 | M32: 0 | N32: 6100870353 | O32: 645524284 | P32: 176445658 | Q32: 6735774 | R32: 29199218 | S32: =SUM(T32:X32) -> 82038542 | T32: 0 | U32: 62683653 | V32: 14026897 | W32: 3041237 | X32: 2286755 | AA32: =+'loans_av rate'!C31+'loans_av rate'!C40 -> 6958775287 | AB32: =+'loans_av rate'!E31+'loans_av rate'!E40 -> 3354144244 | AC32: =+'loans_av rate'!G31+'loans_av rate'!G40 -> 3604631043
B33: в том числе по цели кредитования | C33: =SUM(C34:C39) -> 7731402094 | D33: =IFERROR(((C35*D35)/C33)+((C36*D36)/C33)+((C37*D37)/C33)+((C38*D38)/C33)+((C39*D39)/C33),0) -> 0.11853855 | E33: =SUM(E34:E39) -> 4119807406 | F33: =IFERROR(((E35*F35)/E33)+((E36*F36)/E33)+((E37*F37)/E33)+((E38*F38)/E33)+((E39*F39)/E33),0) -> 0.14741289 | G33: =SUM(G34:G39) -> 3611594688 | H33: =IFERROR(((G35*H35)/G33)+((G36*H36)/G33)+((G37*H37)/G33)+((G38*H38)/G33)+((G39*H39)/G33),0) -> 0.066910769 | I33: =SUM(I34:I39) -> 1566291774 | J33: =SUM(J34:J39) -> 4938756121 | K33: =SUM(K34:K39) -> 1075498218 | L33: =SUM(L34:L39) -> 150855981 | M33: =SUM(M34:M39) -> 0 | N33: =SUM(N34:N39) -> 6729416757 | O33: =SUM(O34:O39) -> 707779782 | P33: =SUM(P34:P39) -> 187522020 | ... Z33: =SUM(Z34:Z39) -> 0
A34: 1 | B34: кредиты, выданные на формирование стартового капитала | C34: =+E34+G34 -> 603135265 | D34: 0.10901758 | E34: 603135265 | F34: 0.10901758 | H34: 0 | I34: 60685060 | J34: 432126488 | K34: 1278758 | L34: 109044959 | M34: 0 | N34: 469453753 | O34: 85466748 | P34: 7280336 | Q34: 7539025 | R34: 33395403 | S34: =SUM(T34:X34) -> 13412537 | T34: 0 | U34: 7383428 | V34: 1741694 | W34: 3505841 | X34: 781574
A35: 2 | B35: кредиты на пополнение оборотных средств | C35: =+E35+G35 -> 2492217841 | D35: 0.13622472 | E35: 1631324443 | F35: 0.16673551 | G35: 860893398 | H35: 0 | I35: 1032163362 | J35: 1291491153 | K35: 164352646 | L35: 4210680 | M35: 0 | N35: 2346440252 | O35: 103781762 | P35: 27820945 | Q35: 764644 | R35: 13410238 | S35: =SUM(T35:X35) -> 14714051 | T35: 0 | U35: 10087245 | V35: 3257079 | W35: 374172 | X35: 995555
A36: 3 | B36: кредиты, выданные на приобретение, модернизацию или приватизацию основных средств | C36: =+E36+G36 -> 1928178606 | D36: 0.11338282 | E36: 550275271 | F36: 0.17067523 | G36: 1377903335 | H36: 0.090502693 | I36: 209641873 | J36: 1326782891 | K36: 387565410 | L36: 4188432 | M36: 0 | N36: 1500030959 | O36: 339318765 | P36: 54966306 | Q36: 4992184 | R36: 28870392 | S36: =SUM(T36:X36) -> 40685320 | T36: 0 | U36: 32585291 | V36: 1732992 | W36: 2419245 | X36: 3947792
A37: 4 | B37: кредиты, выданные на покрытие затрат, связанных с импортом и экспортом продукции | C37: =+E37+G37 -> 0 | D37: 0 | E37: 0 | F37: 0 | G37: 0 | H37: 0 | I37: 0 | J37: 0 | K37: 0 | L37: 0 | M37: 0 | N37: 0 | O37: 0 | P37: 0 | Q37: 0 | R37: 0 | S37: =SUM(T37:X37) -> 0 | T37: 0 | U37: 0 | V37: 0 | W37: 0 | X37: 0
A38: 5 | B38: кредиты, выданные по отдельным решениям правительства | C38: =+E38+G38 -> 74717333 | D38: 0.13045099 | E38: 74717333 | F38: 0.13045099 | G38: 0 | H38: 0 | I38: 0 | J38: 72842333 | K38: 1875000 | L38: 0 | M38: 0 | N38: 74657333 | O38: 60000 | P38: 0 | Q38: 0 | R38: 0 | S38: =SUM(T38:X38) -> 6000 | T38: 0 | U38: 6000 | V38: 0 | W38: 0 | X38: 0
A39: 6 | B39: другие цели кредитования | C39: =+E39+G39 -> 2633153049 | D39: 0.13238816 | E39: 1260355094 | F39: 0.18379556 | G39: 1372797955 | H39: 0.085191426 | I39: 263801479 | J39: 1815513256 | K39: 520426404 | L39: 33411910 | M39: 0 | N39: 2338834460 | O39: 179152507 | P39: 97454433 | Q39: 5828580 | R39: 11883069 | S39: =SUM(T39:X39) -> 31429604 | T39: 0 | U39: 18119080 | V39: 9595095 | W39: 2590541 | X39: 1124888
B41: Подпись Председателя правления:
B43: Подпись Главного Бухгалтера:

Sheet Transactions of related parties
A1: ОТЧЕТ О СДЕЛКАХ, ЗАКЛЮЧЕННЫХ СО СВЯЗАННЫМИ ЛИЦАМИ | Y1: Таблица-11
B3: =+'Asset quality'!B3 -> "Микрокредитбанк" | U3: =+'Asset quality'!P3 -> 44560 | V3: =+#REF! -> #REF! | Y3: тыс. сум
A4: № | B4: Наименования клиента | C4: ИНН | D4: Вид деятельности | E4: Код валюты | F4: Номер группы | G4: Текущая задолженность, брутто | H4: из них | T4: Пересмотрения | U4: Вычеты из норматива | W4: Классификация | X4: Резерв | Y4: Источник кредита | Z4: Текущая задолженность, нетто
H5: балансовые | L5: внебалансовые
H6: Межбанковские кредиты и депозиты, остатки на кор счетах, средства для межбанковских взаиморасчетов, другие размещенные средства (кроме овернайта и клиринговых операций) и доходы по ним | I6: Кредиты/лизинги/факторинги и доходы по ним | J6: Инвестиции и доходы по ним | K6: Другие активы доходы по ним | L6: Аккредитивы и доходы по ним | N6: Гарантии/поручительства и доходы по ним | P6: Неиспользованные кредитные линии/безотзывные обязательства/ другие обязательства по выдаче кредитов доходы по ним | R6: Другие активы доходы по ним | U6: Вид обеспечения | V6: Сумма
L7: остаток | M7: по степени риска | N7: остаток | O7: по степени риска | P7: остаток | Q7: по степени риска | R7: остаток | S7: по степени риска
B8: А | C8: Б | D8: В | E8: Г | F8: Д | G8: Е | H8: Е1 | I8: Е2 | J8: Е3 | K8: Е4 | L8: Е5 | N8: Е6 | P8: Е7 | R8: Е8 | T8: Ж | U8: З | V8: И | W8: К | X8: Л | Y8: М | Z8: Н
A9: 1 | B9: Исматуллоев Акрам Акмалович | C9: AA5013105 | D9: Физлица | E9: 000 | F9: 1 | G9: =+H9+I9+J9+K9+M9+O9+Q9+S9 -> 208306.74 | I9: 208306.74 | Z9: =+G9-V9-X9 -> 208306.74 | AA9: =SUMIF($F$9:$F$63,$F9,$Z$9:$Z$63) -> 2156652.4
A10: 2 | B10: KHOLOV TAKHIR SADULLAYEVICH | C10: AA1598158 | D10: Физлица | E10: 000 | F10: 1 | G10: =+H10+I10+J10+K10+M10+O10+Q10+S10 -> 200445.8 | I10: 200445.8 | Z10: =+G10-V10-X10 -> 200445.8 | AA10: =SUMIF($F$9:$F$63,$F10,$Z$9:$Z$63) -> 2156652.4
A11: 3 | B11: SIDDIKOV SHOKHRUKH IBRAGIMJONOVICH | C11: AA0281567 | D11: Физлица | E11: 000 | F11: 1 | G11: =+H11+I11+J11+K11+M11+O11+Q11+S11 -> 87128.079 | I11: 87128.079 | Z11: =+G11-V11-X11 -> 87128.079 | AA11: =SUMIF($F$9:$F$63,$F11,$Z$9:$Z$63) -> 2156652.4
A12: 4 | B12: MUQIMOV AZAMAT SAIDOVICH | C12: AA0093700 | D12: Физлица | E12: 000 | F12: 1 | G12: =+H12+I12+J12+K12+M12+O12+Q12+S12 -> 87128.079 | I12: 87128.079 | Z12: =+G12-V12-X12 -> 87128.079 | AA12: =SUMIF($F$9:$F$63,$F12,$Z$9:$Z$63) -> 2156652.4
A13: 5 | B13: TAYLAKOV ISMOIL RAMIZOVICH | C13: AA4589423 | D13: Физлица | E13: 000 | F13: 1 | G13: =+H13+I13+J13+K13+M13+O13+Q13+S13 -> 83899.463 | I13: 83899.463 | Z13: =+G13-V13-X13 -> 83899.463 | AA13: =SUMIF($F$9:$F$63,$F13,$Z$9:$Z$63) -> 2156652.4
A14: 6 | B14: SOLIEV SARDORBEK XOLMIRZAYEVICH | C14: AA1507783 | D14: Физлица | E14: 000 | F14: 1 | G14: =+H14+I14+J14+K14+M14+O14+Q14+S14 -> 82196.3 | I14: 82196.3 | Z14: =+G14-V14-X14 -> 82196.3 | AA14: =SUMIF($F$9:$F$63,$F14,$Z$9:$Z$63) -> 2156652.4
A15: 7 | B15: BESHIMOV AZAMAT XAMROBOYEVICH | C15: AB9725681 | D15: Физлица | E15: 000 | F15: 1 | G15: =+H15+I15+J15+K15+M15+O15+Q15+S15 -> 12976.891 | I15: 12976.891 | Z15: =+G15-V15-X15 -> 12976.891 | AA15: =SUMIF($F$9:$F$63,$F15,$Z$9:$Z$63) -> 2156652.4
A16: 8 | B16: ARAMOV RASHID RAVSHANOVICH | C16: AA1574588 | D16: Физлица | E16: 000 | F16: 1 | G16: =+H16+I16+J16+K16+M16+O16+Q16+S16 -> 55980 | I16: 55980 | Z16: =+G16-V16-X16 -> 55980 | AA16: =SUMIF($F$9:$F$63,$F16,$Z$9:$Z$63) -> 2156652.4
A17: 9 | B17: MADUMAROV XUSNIDDIN KOMILOVICH | C17: AA0620069 | D17: Физлица | E17: 000 | F17: 1 | G17: =+H17+I17+J17+K17+M17+O17+Q17+S17 -> 76031.016 | I17: 76031.016 | Z17: =+G17-V17-X17 -> 76031.016 | AA17: =SUMIF($F$9:$F$63,$F17,$Z$9:$Z$63) -> 2156652.4
A18: 10 | B18: ESHMATOV MASRUR QURBONOVICH | C18: AA1344338 | D18: Физлица | E18: 000 | F18: 1 | G18: =+H18+I18+J18+K18+M18+O18+Q18+S18 -> 79056.539 | I18: 79056.539 | Z18: =+G18-V18-X18 -> 79056.539 | AA18: =SUMIF($F$9:$F$63,$F18,$Z$9:$Z$63) -> 2156652.4
A19: 11 | B19: JUMAYEV NURALI ISOXONOVICH | C19: AA1395310 | D19: Физлица | E19: 000 | F19: 1 | G19: =+H19+I19+J19+K19+M19+O19+Q19+S19 -> 74452.12 | I19: 74452.12 | Z19: =+G19-V19-X19 -> 74452.12 | AA19: =SUMIF($F$9:$F$63,$F19,$Z$9:$Z$63) -> 2156652.4
A20: 12 | B20: OMONOV OTAJON JURAQULOVICH | C20: AA8332674 | D20: Физлица | E20: 000 | F20: 1 | G20: =+H20+I20+J20+K20+M20+O20+Q20+S20 -> 89517.991 | I20: 89517.991 | Z20: =+G20-V20-X20 -> 89517.991 | AA20: =SUMIF($F$9:$F$63,$F20,$Z$9:$Z$63) -> 2156652.4
... A62: 54 | B62: SHARIPOV JAMSHID NORQOBILOVICH | C62: AA1115939 | D62: Физлица | E62: 000 | F62: 1 | G62: =+H62+I62+J62+K62+M62+O62+Q62+S62 -> 998.81754 | I62: 998.81754 | Z62: =+G62-V62-X62 -> 998.81754 | AA62: =SUMIF($F$9:$F$63,$F62,$Z$9:$Z$63) -> 2156652.4
A63: 55 | G63: =+H63+I63+J63+K63+M63+O63+Q63+S63 -> 0 | Z63: =+G63-V63-X63 -> 0 | AA63: =SUMIF($F$9:$F$63,$F63,$Z$9:$Z$63) -> 0
A64: ИТОГО СДЕЛКИ СО СВЯЗАННЫМИ ЛИЦАМИ | G64: =SUM(G9:G63) -> 2307941.8 | H64: =SUM(H9:H63) -> 0 | I64: =SUM(I9:I63) -> 2307941.8 | J64: =SUM(J9:J63) -> 0 | K64: =SUM(K9:K63) -> 0 | L64: =SUM(L9:L63) -> 0 | M64: =SUM(M9:M63) -> 0 | N64: =SUM(N9:N63) -> 0 | ... T64: =SUM(T9:T63) -> 0 | V64: =SUM(V9:V63) -> 0 | X64: =SUM(X9:X63) -> 0 | Y64: =SUM(Y9:Y63) -> 0 | Z64: =SUM(Z9:Z63) -> 2307941.8
A65: САМАЯ КРУПНАЯ СДЕЛКА, ЗАКЛЮЧЁННАЯ С ОДНИМ СВЯЗАННЫМ ЛИЦОМ | G65: =+SUMIF($F$9:$F$63,$AA$65,$G$9:$G$63) -> 2156652.4 | H65: =+SUMIF($F$9:$F$63,$AA$65,$H$9:$H$63) -> 0 | I65: =+SUMIF($F$9:$F$63,$AA$65,$I$9:$I$63) -> 2156652.4 | J65: =+SUMIF($F$9:$F$63,$AA$65,$J$9:$J$63) -> 0 | K65: =+SUMIF($F$9:$F$63,$AA$65,$K$9:$K$63) -> 0 | L65: =+SUMIF($F$9:$F$63,$AA$65,$L$9:$L$63) -> 0 | M65: =+SUMIF($F$9:$F$63,$AA$65,$M$9:$M$63) -> 0 | N65: =+SUMIF($F$9:$F$63,$AA$65,$N$9:$N$63) -> 0 | O65: =+SUMIF($F$9:$F$63,$AA$65,$O$9:$O$63) -> 0 | P65: =+SUMIF($F$9:$F$63,$AA$65,$P$9:$P$63) -> 0 | Q65: =+SUMIF($F$9:$F$63,$AA$65,$Q$9:$Q$63) -> 0 | R65: =+SUMIF($F$9:$F$63,$AA$65,$R$9:$R$63) -> 0 | S65: =+SUMIF($F$9:$F$63,$AA$65,$S$9:$S$63) -> 0 | T65: =+SUMIF($F$9:$F$63,$AA$65,$T$9:$T$63) -> 0 | V65: =+SUMIF($F$9:$F$63,$AA$65,$V$9:$V$63) -> 0 | X65: =+SUMIF($F$9:$F$63,$AA$65,$X$9:$X$63) -> 0 | Y65: =+SUMIF($F$9:$F$63,$AA$65,$Y$9:$Y$63) -> 0 | Z65: =+MAX(AA9:AA63) -> 2156652.4 | AA65: =INDEX($F$9:$F$63,MATCH($Z65,$AA$9:$AA$63,0)) -> 1
B68: Подпись Председателя Правления:
B70: Подпись Главного Бухгалтера:

Sheet  Largest risk
A1: ОТЧЕТ О КРУПНЫХ РИСКАХ | Y1: Таблица-12
B3: =+'Asset quality'!B3 -> "Микрокредитбанк" | U3: =+'Asset quality'!P3 -> 44560 | V3: =+#REF! -> #REF! | Y3: тыс. сум
A4: № | B4: Наименования клиента | C4: ИНН | D4: Вид деятельности | E4: Код валюты | F4: Номер группы | G4: Текущая задолженность, брутто | H4: из них | T4: Пересмотрения | U4: Вычеты из норматива | W4: Классификация | X4: Резерв | Y4: Источник кредита | Z4: Текущая задолженность, нетто
H5: балансовые | L5: внебалансовые
H6: Межбанковские кредиты и депозиты, остатки на кор счетах, средства для межбанковских взаиморасчетов, другие размещенные средства (кроме овернайта и клиринговых операций) и доходы по ним | I6: Кредиты/лизинги/факторинги и доходы по ним | J6: Инвестиции и доходы по ним | K6: Другие активы доходы по ним | L6: Аккредитивы и доходы по ним | N6: Гарантии/поручительства и доходы по ним | P6: Неиспользованные кредитные линии/безотзывные обязательства/ другие обязательства по выдаче кредитов доходы по ним | R6: Другие активы доходы по ним | U6: Вид обеспечения | V6: Сумма
L7: остаток | M7: по степени риска | N7: остаток | O7: по степени риска | P7: остаток | Q7: по степени риска | R7: остаток | S7: по степени риска
B8: А | C8: Б | D8: В | E8: Г | F8: Д | G8: Е | H8: Е1 | I8: Е2 | J8: Е3 | K8: Е4 | L8: Е5 | N8: Е6 | P8: Е7 | R8: Е8 | T8: Ж | U8: З | V8: И | W8: К | X8: Л | Y8: М | Z8: Н
A9: 1 | B9: ООО "SESAME" | C9: 306892604 | D9: нефт | E9: 978 | F9: 1 | G9: =+H9+I9+J9+K9+M9+O9+Q9+S9 -> 416775671 | I9: 416775671 | J9: 0 | K9: 0 | Z9: =+G9-V9-X9 -> 416775671 | AA9: =SUMIF($F$9:$F$63,$F9,$Z$9:$Z$63) -> 416775671
A10: 2 | B10: ИП ООО "EPSILON DEVELOPMENT COMPANY" | C10: 305922787 | D10: нефт | E10: 978 | F10: 2 | G10: =+H10+I10+J10+K10+M10+O10+Q10+S10 -> 371127209 | I10: 371127209 | J10: 0 | K10: 0 | Z10: =+G10-V10-X10 -> 371127209 | AA10: =SUMIF($F$9:$F$63,$F10,$Z$9:$Z$63) -> 371127209
A11: 3 | G11: =+H11+I11+J11+K11+M11+O11+Q11+S11 -> 0 | Z11: =+G11-V11-X11 -> 0 | AA11: =SUMIF($F$9:$F$63,$F11,$Z$9:$Z$63) -> 0
A12: 4 | G12: =+H12+I12+J12+K12+M12+O12+Q12+S12 -> 0 | Z12: =+G12-V12-X12 -> 0 | AA12: =SUMIF($F$9:$F$63,$F12,$Z$9:$Z$63) -> 0
A13: 5 | G13: =+H13+I13+J13+K13+M13+O13+Q13+S13 -> 0 | Z13: =+G13-V13-X13 -> 0 | AA13: =SUMIF($F$9:$F$63,$F13,$Z$9:$Z$63) -> 0
A14: 6 | G14: =+H14+I14+J14+K14+M14+O14+Q14+S14 -> 0 | Z14: =+G14-V14-X14 -> 0 | AA14: =SUMIF($F$9:$F$63,$F14,$Z$9:$Z$63) -> 0
A15: 7 | G15: =+H15+I15+J15+K15+M15+O15+Q15+S15 -> 0 | Z15: =+G15-V15-X15 -> 0 | AA15: =SUMIF($F$9:$F$63,$F15,$Z$9:$Z$63) -> 0
A16: 8 | G16: =+H16+I16+J16+K16+M16+O16+Q16+S16 -> 0 | Z16: =+G16-V16-X16 -> 0 | AA16: =SUMIF($F$9:$F$63,$F16,$Z$9:$Z$63) -> 0
A17: 9 | G17: =+H17+I17+J17+K17+M17+O17+Q17+S17 -> 0 | Z17: =+G17-V17-X17 -> 0 | AA17: =SUMIF($F$9:$F$63,$F17,$Z$9:$Z$63) -> 0
A18: 10 | G18: =+H18+I18+J18+K18+M18+O18+Q18+S18 -> 0 | Z18: =+G18-V18-X18 -> 0 | AA18: =SUMIF($F$9:$F$63,$F18,$Z$9:$Z$63) -> 0
A19: 11 | G19: =+H19+I19+J19+K19+M19+O19+Q19+S19 -> 0 | Z19: =+G19-V19-X19 -> 0 | AA19: =SUMIF($F$9:$F$63,$F19,$Z$9:$Z$63) -> 0
A20: 12 | G20: =+H20+I20+J20+K20+M20+O20+Q20+S20 -> 0 | Z20: =+G20-V20-X20 -> 0 | AA20: =SUMIF($F$9:$F$63,$F20,$Z$9:$Z$63) -> 0
A21: 13 | G21: =+H21+I21+J21+K21+M21+O21+Q21+S21 -> 0 | Z21: =+G21-V21-X21 -> 0 | AA21: =SUMIF($F$9:$F$63,$F21,$Z$9:$Z$63) -> 0
A22: 14 | G22: =+H22+I22+J22+K22+M22+O22+Q22+S22 -> 0 | Z22: =+G22-V22-X22 -> 0 | AA22: =SUMIF($F$9:$F$63,$F22,$Z$9:$Z$63) -> 0
... A63: 55 | G63: =+H63+I63+J63+K63+M63+O63+Q63+S63 -> 0 | Z63: =+G63-V63-X63 -> 0 | AA63: =SUMIF($F$9:$F$63,$F63,$Z$9:$Z$63) -> 0
B64: ИТОГО КРУПНЫХ АКТИВОВ | G64: =SUM(G9:G63) -> 787902880 | H64: =SUM(H9:H63) -> 0 | I64: =SUM(I9:I63) -> 787902880 | J64: =SUM(J9:J63) -> 0 | K64: =SUM(K9:K63) -> 0 | L64: =SUM(L9:L63) -> 0 | M64: =SUM(M9:M63) -> 0 | N64: =SUM(N9:N63) -> 0 | ... T64: =SUM(T9:T63) -> 0 | V64: =SUM(V9:V63) -> 0 | X64: =SUM(X9:X63) -> 0 | Y64: =SUM(Y9:Y63) -> 0 | Z64: =SUM(Z9:Z63) -> 787902880
B65: САМЫЙ КРУПНЫЙ АКТИВ, ВЫДАННЫЙ БАНКОМ | G65: =+SUMIF($F$9:$F$63,$AA$65,$G$9:$G$63) -> 416775671 | H65: =+SUMIF($F$9:$F$63,$AA$65,$H$9:$H$63) -> 0 | I65: =+SUMIF($F$9:$F$63,$AA$65,$I$9:$I$63) -> 416775671 | J65: =+SUMIF($F$9:$F$63,$AA$65,$J$9:$J$63) -> 0 | K65: =+SUMIF($F$9:$F$63,$AA$65,$K$9:$K$63) -> 0 | L65: =+SUMIF($F$9:$F$63,$AA$65,$L$9:$L$63) -> 0 | M65: =+SUMIF($F$9:$F$63,$AA$65,$M$9:$M$63) -> 0 | N65: =+SUMIF($F$9:$F$63,$AA$65,$N$9:$N$63) -> 0 | O65: =+SUMIF($F$9:$F$63,$AA$65,$O$9:$O$63) -> 0 | P65: =+SUMIF($F$9:$F$63,$AA$65,$P$9:$P$63) -> 0 | Q65: =+SUMIF($F$9:$F$63,$AA$65,$Q$9:$Q$63) -> 0 | R65: =+SUMIF($F$9:$F$63,$AA$65,$R$9:$R$63) -> 0 | S65: =+SUMIF($F$9:$F$63,$AA$65,$S$9:$S$63) -> 0 | T65: =+SUMIF($F$9:$F$63,$AA$65,$T$9:$T$63) -> 0 | V65: =+SUMIF($F$9:$F$63,$AA$65,$V$9:$V$63) -> 0 | X65: =+SUMIF($F$9:$F$63,$AA$65,$X$9:$X$63) -> 0 | Y65: =+SUMIF($F$9:$F$63,$AA$65,$Y$9:$Y$63) -> 0 | Z65: =+MAX(AA9:AA63) -> 416775671 | AA65: =INDEX($F$9:$F$63,MATCH($Z65,$AA$9:$AA$63,0)) -> 1
B68: Подпись Председателя правления:
B70: Подпись Главного Бухгалтера:

Sheet Charge-offs and Recoveries
A1: ОТЧЕТ О CПИСАННЫХ И ВОЗВРАЩЕННЫХ КРЕДИТАХ И ЛИЗИНГАХ, А ТАКЖЕ РЕЗЕРВАХ ПО НИМ | J1: Таблица-13
A3: Часть 1 Списания и возврат сумму кредитов и лизинга за последние 12 месяцев | I3: =+'Asset quality'!P3 -> 44560
A4: № | B4: Отрасли экономики и виды кредитования | C4: ="Остаток списаных кредита и лизинга на"&" "&DAY(I3)&"."&IF(LEN(MONTH(I3))<2,"0"&MONTH(I3),MONTH(I3))&"."&YEAR(I3)-1&"г" -> Остаток списаных кредита и лизинга на 30.12.2020г | D4: Списания и возврат кредитов и лизингов | J4: ="Остаток списаных кредита и лизинга на"&" "&DAY(I3)&"."&IF(LEN(MONTH(I3))<2,"0"&MONTH(I3),MONTH(I3))&"."&YEAR(I3)&"г" -> Остаток списаных кредита и лизинга на 30.12.2021г
D5: Списанние на забалансовый счет | F5: Возврат из забалансового счета | H5: Итоговое списанние из забалансового счета
D6: Всего | E6: в иностранной валюте | F6: Всего | G6: в иностранной валюте | H6: Всего | I6: в иностранной валюте
B7: А | C7: Б | D7: В | E7: Г | F7: Д | G7: Е | H7: Ж | I7: З | J7: И
A8: 1 | B8: Юридические лица | C8: =SUM(C10:C17) -> 1.0776449e+08 | D8: =SUM(D10:D17) -> 36544482 | E8: =SUM(E10:E17) -> 0 | F8: =SUM(F10:F17) -> 2.3338026e+08 | G8: =SUM(G10:G17) -> 0 | H8: =SUM(H10:H17) -> 0 | I8: =SUM(I10:I17) -> 0 | J8: =SUM(J10:J17) -> 3.0460027e+08
B9: из них
A10: 1.1. | B10: Промышленность
A11: 1.2. | B11: Сельское хозяйство | C11: 55588095 | F11: 2.3222182e+08 | J11: 2.8780991e+08
A12: 1.3. | B12: Транспорт и коммуникации | C12: 3422144.1 | D12: 1630475.8 | F12: 0 | J12: 1791668.3
A13: 1.4. | B13: Строительство | F13: 0
A14: 1.5. | B14: Торговля и общественное питание | C14: 14771712 | D14: 14512301 | F14: 0 | J14: 259410.86
A15: 1.6. | B15: Материально-техническое снабжение и сбыт | F15: 101104.35 | J15: 101104.35
A16: 1.7. | B16: Жилищно-коммунальные услуги | C16: 311167 | F16: 1057334.2 | J16: 1368501.2
A17: 1.8. | B17: Другие сектора | C17: 33671372 | D17: 20401705 | F17: 0 | J17: 13269667
A18: 2 | B18: Физические лица | C18: =SUM(C20:C24) -> 4576151.4 | D18: =SUM(D20:D24) -> 1878860.1 | E18: =SUM(E20:E24) -> 0 | F18: =SUM(F20:F24) -> 2317281.5 | G18: =SUM(G20:G24) -> 0 | H18: =SUM(H20:H24) -> 0 | I18: =SUM(I20:I24) -> 0 | J18: =SUM(J20:J24) -> 5067353.5
B19: из них
A20: 2.1. | B20: Ипотечный кредит | C20: 1232815.5 | F20: 2317281.5 | J20: 3550097
A21: 2.2. | B21: Автокредит | J21: 52780.589
A22: 2.3. | B22: Микрозаймы и овердрафты (все нецелевые кредиты) | C22: 987079.43 | D22: 408816.1 | J22: 578263.33
A23: 2.4. | B23: потребительские кредиты | C23: 1267098.7 | D23: 585901.42 | J23: 681197.33
A24: 2.5. | B24: другие кредиты физическим лицам | C24: 1089157.7 | D24: 884142.56 | J24: 205015.18
A25: 3 | B25: Итого | C25: =+C18+C8 -> 1.1234064e+08 | D25: =+D18+D8 -> 38423342 | E25: =+E18+E8 -> 0 | F25: =+F18+F8 -> 2.3569754e+08 | G25: =+G18+G8 -> 0 | H25: =+H18+H8 -> 0 | I25: =+I18+I8 -> 0 | J25: =+J18+J8 -> 3.0966762e+08
A27: Часть 2 Списанные и возвращенные резервы по кредитам и лизингам за последние 12 месяцев
A28: № | B28: Отрасли экономики и виды кредитования | C28: ="Резервы возможных потерь по кредитам и лизингу на"&" "&DAY(I3)&"."&IF(LEN(MONTH(I3))<2,"0"&MONTH(I3),MONTH(I3))&"."&YEAR(I3)-1&"г" -> Резервы возможных потерь по кредитам и лизингу на 30.12.2020г | D28: Списания и возврат резервов по кредитам и лизингам | H28: Движение по резервам за последние 12 месяцев | I28: ="Резервы возможных потерь по кредитам и лизингу на"&" "&DAY(I3)&"."&IF(LEN(MONTH(I3))<2,"0"&MONTH(I3),MONTH(I3))&"."&YEAR(I3)&"г" -> Резервы возможных потерь по кредитам и лизингу на 30.12.2021г
D29: Списание резервов | F29: Возврат резервов
D30: Всего | E30: в иностранной валюте | F30: Всего | G30: в иностранной валюте
B31: А | C31: Б | D31: В | E31: Г | F31: Д | G31: Е | H31: Ж | I31: З
A32: 1 | B32: Юридические лица | C32: =SUM(C34:C41) -> 1.500549e+08 | D32: =SUM(D34:D41) -> 10479759 | E32: =SUM(E34:E41) -> 0 | F32: =SUM(F34:F41) -> 60287143 | G32: =SUM(G34:G41) -> 0 | H32: =SUM(H34:H41) -> 0 | I32: =SUM(I34:I41) -> 1.0024751e+08
B33: из них
A34: 1.1. | B34: Промышленность | C34: 17386796 | D34: 10479759 | I34: 27866555
A35: 1.2. | B35: Сельское хозяйство | C35: 33372999 | F35: =+C35-I35 -> 6928963.5 | I35: 26444036
A36: 1.3. | B36: Транспорт и коммуникации | C36: 22942648 | F36: =+C36-I36 -> 14341864 | I36: 8600783.4
A37: 1.4. | B37: Строительство | C37: 19048260 | F37: =+C37-I37 -> 10655410 | I37: 8392850
A38: 1.5. | B38: Торговля и общественное питание | C38: 18618713 | F38: =+C38-I38 -> 8151271.9 | I38: 10467441
A39: 1.6. | B39: Материально-техническое снабжение и сбыт | C39: 17621513 | F39: =+C39-I39 -> 2060802.4 | I39: 15560710
A40: 1.7. | B40: Жилищно-коммунальные услуги | C40: 16721843 | F40: =+C40-I40 -> 16593196 | I40: 128646.06
A41: 1.8. | B41: Другие сектора | C41: 4342124.2 | F41: =+C41-I41 -> 1555634 | I41: 2786490.1
A42: 2 | B42: Физические лица | C42: =SUM(C44:C48) -> 47339257 | D42: =SUM(D44:D48) -> 95810783 | E42: =SUM(E44:E48) -> 0 | F42: =SUM(F44:F48) -> 22289252 | G42: =SUM(G44:G48) -> 0 | H42: =SUM(H44:H48) -> 0 | I42: =SUM(I44:I48) -> 1.2086079e+08
B43: из них
A44: 2.1. | B44: Ипотечный кредит | C44: 10886247 | F44: =+C44-I44 -> 2143137.4 | I44: 8743110
A45: 2.2. | B45: Автокредит | C45: 3369130.3 | F45: =+C45-I45 -> 2634698.2 | I45: 734432.13
A46: 2.3. | B46: Микрозаймы и овердрафты (все нецелевые кредиты) | C46: 26140345 | F46: =+C46-I46 -> 17511416 | I46: 8628928.7
A47: 2.4. | B47: потребительские кредиты | C47: 4997474.8 | D47: 8218629.2 | I47: 13216104
A48: 2.5. | B48: другие кредиты физическим лицам | C48: 1946058.9 | D48: 87592154 | I48: 89538213
A49: 3 | B49: Итого | C49: =+C42+C32 -> 1.9739415e+08 | D49: =+D42+D32 -> 1.0629054e+08 | E49: =+E42+E32 -> 0 | F49: =+F42+F32 -> 82576395 | G49: =+G42+G32 -> 0 | H49: =+H42+H32 -> 0 | I49: =+I42+I32 -> 2.211083e+08
B51: Подпись Председателя правления:
B53: Подпись Главного Бухгалтера:

Sheet loans_av rate
A1: ДАННЫЕ О СРЕДНЕВЗВЕШЕННЫХ ПРОЦЕНТНЫХ СТАВКАХ ПО КРЕДИТАМ | H1: Таблица-20
B3: =+'Asset quality'!B3 -> "Микрокредитбанк" | F3: =+'Asset quality'!P3 -> 44560 | H3: тыс. сум
A4: № | B4: Виды кредитования | C4: всего | E4: в том числе
E5: в национальный валюте | G5: в иностранной валюте
C6: остаток всего | D6: средневзвешенные процентные ставки | E6: остаток всего | F6: средневзвешенные процентные ставки | G6: остаток всего | H6: средневзвешенные процентные ставки
B7: А | C7: Б | D7: В | E7: Г | F7: Д | G7: Е | H7: Ж
A8: 1 | B8: Физические лица (льготные кредиты) | C8: =SUM(C10:C14) -> 1749358606 | D8: =IFERROR(((C10*D10)/C8)+((C11*D11)/C8)+((C12*D12)/C8)+((C13*D13)/C8)+((C14*D14)/C8),0) -> 0.13012905 | E8: =SUM(E10:E14) -> 1749358606 | F8: =IFERROR(((E10*F10)/E8)+((E11*F11)/E8)+((E12*F12)/E8)+((E13*F13)/E8)+((E14*F14)/E8),0) -> 0.13012905 | G8: =SUM(G10:G14) -> 0 | H8: =IFERROR(((G10*H10)/G8)+((G11*H11)/G8)+((G12*H12)/G8)+((G13*H13)/G8)+((G14*H14)/G8),0) -> 0 | J8: =+C8+C16+C24+C33 -> 10815884011 | K8: =+E8+E16+E24+E33 -> 7204289323 | L8: =+G8+G16+G24+G33 -> 3611594688
B9: в том числе | J9: =+'loans type'!C8 -> 10815884011 | K9: =+'loans type'!E8 -> 7204289323 | L9: =+'loans type'!G8 -> 3611594688
A10: 1.1. | B10: ипотечный кредит | C10: =+E10+G10 -> 22828512 | D10: 0.095631003 | E10: 22828512 | F10: 0.095631003 | G10: 0 | H10: 0 | J10: =+J8-J9 -> 0 | K10: =+K8-K9 -> 0 | L10: =+L8-L9 -> 0
A11: 1.2. | B11: автокредит | C11: =+E11+G11 -> 0 | D11: 0 | E11: 0 | F11: 0 | G11: 0 | H11: 0
A12: 1.3. | B12: микрозайм (все нецелевые кредиты) | C12: =+E12+G12 -> 470352 | D12: 0.13952229 | E12: 470352 | F12: 0.13952229 | G12: 0 | H12: 0
A13: 1.4. | B13: потребительские кредиты | C13: =+E13+G13 -> 3159304 | D13: 0.063398726 | E13: 3159304 | F13: 0.063398726 | G13: 0 | H13: 0
A14: 1.5. | B14: другие кредиты физическим лицам | C14: =+E14+G14 -> 1722900438 | D14: 0.13070595 | E14: 1722900438 | F14: 0.13070595 | G14: 0 | H14: 0
A16: 2 | B16: Физические лица (коммерческие кредиты) | C16: =SUM(C18:C22) -> 1335123311 | D16: =IFERROR(((C18*D18)/C16)+((C19*D19)/C16)+((C20*D20)/C16)+((C21*D21)/C16)+((C22*D22)/C16),0) -> 0.19602915 | E16: =SUM(E18:E22) -> 1335123311 | F16: =IFERROR(((E18*F18)/E16)+((E19*F19)/E16)+((E20*F20)/E16)+((E21*F21)/E16)+((E22*F22)/E16),0) -> 0.19602915 | G16: =SUM(G18:G22) -> 0 | H16: =IFERROR(((G18*H18)/G16)+((G19*H19)/G16)+((G20*H20)/G16)+((G21*H21)/G16)+((G22*H22)/G16),0) -> 0
B17: в том числе
A18: 2.1. | B18: ипотечный кредит | C18: =+E18+G18 -> 480100952 | D18: 0.17191684 | E18: 480100952 | F18: 0.17191684 | G18: 0 | H18: 0
A19: 2.2. | B19: автокредит | C19: =+E19+G19 -> 84557811 | D19: 0.26628017 | E19: 84557811 | F19: 0.26628017 | G19: 0 | H19: 0
A20: 2.3. | B20: микрозайм (все нецелевые кредиты) | C20: =+E20+G20 -> 181378038 | D20: 0.25039444 | E20: 181378038 | F20: 0.25039444 | G20: 0 | H20: 0
A21: 2.4. | B21: потребительские кредиты | C21: =+E21+G21 -> 169949778 | D21: 0.27902329 | E21: 169949778 | F21: 0.27902329 | G21: 0 | H21: 0
A22: 2.5. | B22: другие кредиты физическим лицам | C22: =+E22+G22 -> 419136732 | D22: 0.15229774 | E22: 419136732 | F22: 0.15229774 | G22: 0 | H22: 0
A24: 3 | B24: Юридические лица (льготные кредиты) | C24: =SUM(C26:C31) -> 1652980345 | D24: =IFERROR(((C26*D26)/C24)+((C27*D27)/C24)+((C28*D28)/C24)+((C29*D29)/C24)+((C30*D30)/C24)+((C31*D31)/C24),0) -> 0 | E24: =SUM(E26:E31) -> 1652980345 | F24: =IFERROR(((E26*F26)/E24)+((E27*F27)/E24)+((E28*F28)/E24)+((E29*F29)/E24)+((E30*F30)/E24)+((E31*F31)/E24),0) -> 0.11454891 | G24: =SUM(G26:G31) -> 0 | H24: =IFERROR(((G26*H26)/G24)+((G27*H27)/G24)+((G28*H28)/G24)+((G29*H29)/G24)+((G30*H30)/G24)+((G31*H31)/G24),0) -> 0
B25: в том числе
A26: 3.1. | B26: микрокредит | C26: =+E26+G26 -> 385193135 | D26: 0 | E26: 385193135 | F26: 0.12189887 | G26: 0 | H26: 0
A27: 3.2. | B27: синдицированные кредит | C27: =+E27+G27 -> 0 | D27: 0 | E27: 0 | F27: 0 | G27: 0 | H27: 0
A28: 3.3. | B28: лизинг | C28: =+E28+G28 -> 19801 | D28: 0 | E28: 19801 | F28: 0.14 | G28: 0 | H28: 0
A29: 3.4. | B29: факторинг | C29: =+E29+G29 -> 0 | D29: 0 | E29: 0 | F29: 0 | G29: 0 | H29: 0
A30: 3.5. | B30: межбанковский кредит | C30: =+E30+G30 -> 0 | D30: 0 | E30: 0 | F30: 0 | G30: 0 | H30: 0
A31: 3.6. | B31: другие кредиты юридическим лицам | C31: =+E31+G31 -> 1267767409 | D31: 0 | E31: 1267767409 | F31: 0.11231533 | G31: 0 | H31: 0
A33: 4 | B33: Юридические лица (коммерческие кредиты) | C33: =SUM(C35:C40) -> 6078421749 | D33: =IFERROR(((C35*D35)/C33)+((C36*D36)/C33)+((C37*D37)/C33)+((C38*D38)/C33)+((C39*D39)/C33)+((C40*D40)/C33),0) -> 0.20278222 | E33: =SUM(E35:E40) -> 2466827061 | F33: =IFERROR(((E35*F35)/E33)+((E36*F36)/E33)+((E37*F37)/E33)+((E38*F38)/E33)+((E39*F39)/E33)+((E40*F40)/E33),0) -> 0.1960891 | G33: =SUM(G35:G40) -> 3611594688 | H33: =IFERROR(((G35*H35)/G33)+((G36*H36)/G33)+((G37*H37)/G33)+((G38*H38)/G33)+((G39*H39)/G33)+((G40*H40)/G33),0) -> 0
B34: в том числе
A35: 4.1. | B35: микрокредит | C35: =+E35+G35 -> 295309348 | D35: 0.1640539 | E35: 293529356 | F35: 0.1640539 | G35: 1779992 | H35: 0
A36: 4.2. | B36: синдицированные кредит | C36: =+E36+G36 -> 0 | D36: 0 | E36: 0 | F36: 0 | G36: 0 | H36: 0
A37: 4.3. | B37: лизинг | C37: =+E37+G37 -> 5504646 | D37: 0.18537442 | E37: 320993 | F37: 0.18537442 | G37: 5183653 | H37: 0
A38: 4.4. | B38: факторинг | C38: =+E38+G38 -> 86599877 | D38: 0.03204382 | E38: 86599877 | F38: 0.03204382 | G38: 0 | H38: 0
A39: 4.5. | B39: межбанковский кредит | C39: =+E39+G39 -> 0 | D39: 0 | E39: 0 | F39: 0 | G39: 0 | H39: 0
A40: 4.6. | B40: другие кредиты юридическим лицам | C40: =+E40+G40 -> 5691007878 | D40: 0.20740681 | E40: 2086376835 | F40: 0.20740681 | G40: 3604631043 | H40: 0
B43: Подпись Председателя правления:
B45: Подпись Главного Бухгалтера:
B47: Всего | C47: =+C8+C16+C24+C33 -> 10815884011 | E47: =+E8+E16+E24+E33 -> 7204289323 | G47: =+G8+G16+G24+G33 -> 3611594688
C48: =+C50+C54 -> 10815884011 | E48: =+E9+E17+E25+E34 -> 0 | G48: =+G50+G54 -> 3611594689
B50: Физлица | C50: =+'Asset Classification'!C12 -> 3084481917 | G50: =+'Asset Classification'!D12 -> 0
C51: =C8+C16 -> 3084481917 | G51: =G8+G16 -> 0
C52: =+C50-C51 -> 0 | G52: =+G50-G51 -> 0
B54: Юрзлица | C54: =+'Asset Classification'!C30-'Asset Classification'!C12 -> 7731402094 | G54: =+'Asset Classification'!D30-'Asset Classification'!D12 -> 3611594689
C55: =C24+C33 -> 7731402094 | G55: =G24+G33 -> 3611594688
C56: =+C54-C55 -> 0 | G56: =+G54-G55 -> 1

Sheet Bank Capital Calc (2)
A1: РАСЧЕТ РЕГУЛЯТИВНОГО КАПИТАЛА БАНКА | C1: Таблица-5
B3: =#REF! -> #REF! | C3: =+#REF! -> #REF!
A4: № | B4: Характеристики | C4: Итого капитала
A5: I. | B5: КАПИТАЛ УРОВНЯ 1
A6: 1 | B6: ОСНОВНОЙ КАПИТАЛ УРОВНЯ 1
A7: 1.1. | B7: Обыкновенные Акции, чистые | C7: Формула
A8: a | B8: Полностью оплаченные обыкновенные акции
A9: б | B9: Минус: Обратно Выкупленные обыкновенные акции
A10: 1.2. | B10: Добавленный капитал - Обыкновенные | C10: 0
A11: 1.3. | B11: Нераспределенная прибыль (убыток), в том числе капитальные резервы | C11: Формула
A12: а | B12: Капитальные резервы
A13: б | B13: Нераспределенная прибыль
A14: в | B14: Убыток за предыдущие периоды
A15: г | B15: Убыток за текущий год
A16: 1.4. | B16: Интерес меньшинства в консолидированных дочерних компаниях (согласно МБС)
A17: 1.5. | B17: Резерв на девальвацию
B18: Итого основного капитала уровня I до вычетов | C18: Формула
A19: 1.6. | B19: Вычеты из суммы основного капитала уровня I | C19: Формула
A20: а | B20: Нематериальные активы
A21: б | B21: Все инвестиции в капитал неконсолидированных хозяйствующих субъектов, в том числе в долговые обязательства, которые образуют капитал хозяйствующих субъектов
A22: в | B22: Инвестиции в капитал других банков
A23: I | B23: ВСЕГО СКОРРЕКТИРОВАННЫЙ ОСНОВНОЙ КАПИТАЛ УРОВНЯ I | C23: Формула
A24: 2 | B24: ДОБАВЛЕННЫЙ КАПИТАЛ УРОВНЯ 1
A25: 2.1. | B25: Некумулятивные бессрочные привилегированные акции | C25: =+C26+C27 -> 0
A26: а | B26: Полностью оплаченные привилегированные акции
A27: б | B27: Минус: Обратно Выкупленные привилегированные акции
A28: 2.2. | B28: Добавленный капитал - Привилегированные | C28: 0
A29: 2.3. | B29: Интерес меньшинства в консолидированных дочерних компаниях | C29: 0
A30: 2.4. | B30: Доля участия дочерних предприятий (выпущенные дочерними предприятиями и находящиеся во владении третьих лиц инструменты, приравненные к капиталу) | C30: 0
A31: II | B31: ВСЕГО ДОБАВЛЕННЫЙ КАПИТАЛ УРОВНЯ I | C31: =+C25+C28+C29+C30 -> 0
A32: III | B32: ВСЕГО СКОРРЕКТИРОВАННЫЙ КАПИТАЛ УРОВНЯ I | C32: Формула
B33: КАПИТАЛ УРОВНЯ II
A34: 3.1. | B34: Прибыль за текущий год
A35: 3.2. | B35: Резервы, создаваемые на стандартные кредиты (активы), в размере не более 1.25% от общей суммы активов, взвешенных с учетом риска | C35: =IF(#REF!<(C43*1.25%),#REF!,(C43*1.25%)) -> #REF!
A36: 3.3. | B36: Излишки оценочной стоимости прироста над первоначальной стоимостью
A37: 3.4. | B37: Другие инструменты капитала (не более 1/3 части капитала 1 уровня после вычетов)
A38: 3.5. | B38: Субординированный долг
A39: 3.6. | B39: Вычеты превышения Капитала Уровня II над Капиталом Уровня I | C39: Формула
B40: Итого капитала Уровня II | C40: =SUM(C34:C38) -> #REF!
A41: IV | B41: СКОРРЕКТИРОВАННЫЙ КАПИТАЛ УРОВНЯ II | C41: Формула
A42: V | B42: ВСЕГО РЕГУЛЯТИВНЫЙ КАПИТАЛ | C42: Формула
A43: VI | B43: ОБЩАЯ СУММА АКТИВОВ ВЗВЕШЕННЫХ С УЧЕТОМ РИСКА | C43: =+C44+C45+C46 -> #REF!
A44: а | B44: Сумма балансовых и забалансовых активов, взвешенных с учетом риска | C44: =+#REF! -> #REF!
A45: б | B45: Операционный риск | C45: =+#REF! -> #REF!
A46: в | B46: Рыночный риск | C46: =+#REF! -> #REF! | E46: =+#REF! -> #REF!
A47: VII | B47: КОЭФФИЦИЕНТ ОСНОВНОГО КАПИТАЛА УРОВНЯ I (I/VI) | C47: Формула
A48: VIII | B48: КОЭФФИЦИЕНТ КАПИТАЛА УРОВНЯ I (III/VI) | C48: Формула
A49: IX | B49: КОЭФФИЦИЕНТ ОБЩЕЙ СУММЫ КАПИТАЛА, ОСНОВАННОГО НА РИСКЕ (V/VI) | C49: Формула
A50: X | B50: Активы для расчета левеража | C50: Формула
A51: а | B51: Общие активы | C51: =+#REF! -> #REF!
A52: б | B52: Забалансовые инструменты | C52: =SUM(#REF!) -> #REF! | D52: =+#REF! -> #REF!
A53: в | B53: Деривативные (производные) инструменты | C53: =SUM(#REF!) -> #REF!
A54: г | B54: Минус: Строка 1.6. Итого вычетов из суммы основного капитала Уровня 1 | C54: =+C19 -> Формула
A55: XI | B55: Коэффициент левеража | C55: Формула
B57: Подпись Председателя правления:
B59: Подпись Главного Бухгалтера:

Sheet Deposits_av rate
A1: ДАННЫЕ О СРЕДНЕВЗВЕШЕННЫХ ПРОЦЕНТНЫХ СТАВКАХ ПО ПРИВЛЕЧЕННЫМ ДЕПОЗИТАМ БАНКОВ | N1: Таблица-21
B2: =+'Asset quality'!B3 -> "Микрокредитбанк" | K2: =+'loans_av rate'!F3 -> 44560 | N2: тыс. сум
A3: № | B3: Сроки, погашения средств | C3: Вклады (депозиты) физических лиц | I3: Вклады (депозиты) юридических лиц
C4: общая сумма (тыс. сум) | D4: средневзвешенные процентные ставки | E4: в том числе | I4: общая сумма (тыс. сум) | J4: средневзвешенные процентные ставки | K4: в том числе
E5: в национальный валюте | G5: в иностранной валюте | K5: в национальный валюте | M5: в иностранной валюте
E6: остаток всего | F6: средневзвешенные процентные ставки | G6: остаток всего | H6: средневзвешенные процентные ставки | K6: остаток всего | L6: средневзвешенные процентные ставки | M6: остаток всего | N6: средневзвешенные процентные ставки
B7: А | C7: Б | D7: В | E7: Г | F7: Д | G7: Е | H7: Ж | I7: З | J7: И | K7: К | L7: Л | M7: М | N7: Н
A8: 1 | B8: Бессрочные | C8: =+E8+G8 -> 202800634 | D8: =+(E8*F8+G8*H8)/(E8+G8) -> 0 | E8: 195708915 | F8: 0 | G8: 7091719 | H8: 0 | I8: =+K8+M8 -> 487847877 | J8: =+(K8*L8+M8*N8)/(K8+M8) -> 0.0061810815 | K8: 432279259 | L8: 0.0069756469 | M8: 55568618 | N8: 0 | P8: =+'[8]Bank Liabilities Analysis'!$C$22 -> 690648511 | Q8: =+P8-C8-I8 -> 0
A9: 2 | B9: От 1 до 7 дней | C9: =+E9+G9 -> 11117249 | D9: =+(E9*F9+G9*H9)/(E9+G9) -> 0.1334469 | E9: 7914207 | F9: 0.16721957 | G9: 3203042 | H9: 0.05 | I9: =+K9+M9 -> 119084437 | J9: =+(K9*L9+M9*N9)/(K9+M9) -> 0.16652174 | K9: 119084437 | L9: 0.16652174 | M9: 0 | N9: 0 | P9: =+'[8]Bank Liabilities Analysis'!$E$22 -> 130201686 | Q9: =+P9-C9-I9 -> 0
A10: 3 | B10: От 8 до 30 дней | C10: =+E10+G10 -> 17331571 | D10: =+(E10*F10+G10*H10)/(E10+G10) -> 0.12721294 | E10: 11247910 | F10: 0.16883738 | G10: 6083661 | H10: 0.050254691 | I10: =+K10+M10 -> 38500000 | J10: =+(K10*L10+M10*N10)/(K10+M10) -> 0.15524 | K10: 38500000 | L10: 0.15524 | M10: 0 | N10: 0 | P10: =+'[8]Bank Liabilities Analysis'!$G$22 -> 55831571 | Q10: =+P10-C10-I10 -> 0
A11: 4 | B11: От 31 до 90 дней | C11: =+E11+G11 -> 128073638 | D11: =+(E11*F11+G11*H11)/(E11+G11) -> 0.1537701 | E11: 114065616 | F11: 0.16640878 | G11: 14008022 | H11: 0.050854876 | I11: =+K11+M11 -> 416285977 | J11: =+(K11*L11+M11*N11)/(K11+M11) -> 0.099633181 | K11: 260223432 | L11: 0.12447967 | M11: 156062545 | N11: 0.058203384 | P11: =+'[8]Bank Liabilities Analysis'!$I$22 -> 544359615 | Q11: =+P11-C11-I11 -> 0
A12: 5 | B12: От 91 до 180 дней | C12: =+E12+G12 -> 180055631 | D12: =+(E12*F12+G12*H12)/(E12+G12) -> 0.18019 | E12: 148283740 | F12: 0.20820203 | G12: 31771891 | H12: 0.049454056 | I12: =+K12+M12 -> 57123822 | J12: =+(K12*L12+M12*N12)/(K12+M12) -> 0.16894821 | K12: 57123822 | L12: 0.16894821 | M12: 0 | N12: 0 | P12: =+'[8]Bank Liabilities Analysis'!$K$22 -> 237179453 | Q12: =+P12-C12-I12 -> 0
A13: 6 | B13: От 181 до 365 дней | C13: =+E13+G13 -> 209613208 | D13: =+(E13*F13+G13*H13)/(E13+G13) -> 0.20371779 | E13: 200282167 | F13: 0.21084569 | G13: 9331041 | H13: 0.050724072 | I13: =+K13+M13 -> 280006150 | J13: =+(K13*L13+M13*N13)/(K13+M13) -> 0.16273093 | K13: 267271899 | L13: 0.16810203 | M13: 12734251 | N13: 0.05 | P13: =+'[8]Bank Liabilities Analysis'!$M$22 -> 489619358 | Q13: =+P13-C13-I13 -> 0
A14: 7 | B14: От 366 до 730 дней | C14: =+E14+G14 -> 24129175 | D14: =+(E14*F14+G14*H14)/(E14+G14) -> 0.21000882 | E14: 23856386 | F14: 0.21183846 | G14: 272789 | H14: 0.05 | I14: =+K14+M14 -> 58223977 | J14: =+(K14*L14+M14*N14)/(K14+M14) -> 0.10965299 | K14: 41967487 | L14: 0.13276012 | M14: 16256490 | N14: 0.05 | P14: =+'[8]Bank Liabilities Analysis'!$O$22 -> 82353152 | Q14: =+P14-C14-I14 -> 0
A15: 8 | B15: Свыше 2 лет | C15: =+E15+G15 -> 2180763 | D15: =+(E15*F15+G15*H15)/(E15+G15) -> 0.18796292 | E15: 2180763 | F15: 0.18796292 | G15: 0 | H15: 0 | I15: =+K15+M15 -> 921301030 | J15: =+(K15*L15+M15*N15)/(K15+M15) -> 0.102795 | K15: 646371271 | L15: 0.13070418 | M15: 274929759 | N15: 0.03717936 | P15: =+'[8]Bank Liabilities Analysis'!$Q$22 -> 923481793 | Q15: =+P15-C15-I15 -> 0
A16: 9 | B16: Итого (сумма строк 1, 2, 3, 4, 5, 6, 7, 8 ) | C16: =SUM(C8:C15) -> 775301869 | D16: =IFERROR(((C8*D8)/C16)+((C9*D9)/C16)+((C10*D10)/C16)+((C11*D11)/C16)+((C12*D12)/C16)+((C13*D13)/C16)+((C14*D14)/C16)+((C15*D15)/C16),0) -> 0.13414861 | E16: =SUM(E8:E15) -> 703539704 | F16: =IFERROR(((E8*F8)/E16)+((E9*F9)/E16)+((E10*F10)/E16)+((E11*F11)/E16)+((E12*F12)/E16)+((E13*F13)/E16)+((E14*F14)/E16)+((E15*F15)/E16),0) -> 0.14323173 | G16: =SUM(G8:G15) -> 71762165 | H16: =IFERROR(((G8*H8)/G16)+((G9*H9)/G16)+((G10*H10)/G16)+((G11*H11)/G16)+((G12*H12)/G16)+((G13*H13)/G16)+((G14*H14)/G16)+((G15*H15)/G16),0) -> 0.045099776 | I16: =SUM(I8:I15) -> 2378373270 | J16: =IFERROR(((I8*J8)/I16)+((I9*J9)/I16)+((I10*J10)/I16)+((I11*J11)/I16)+((I12*J12)/I16)+((I13*J13)/I16)+((I14*J14)/I16)+((I15*J15)/I16),0) -> 0.095277059 | K16: =SUM(K8:K15) -> 1862821607 | L16: =IFERROR(((K8*L8)/K16)+((K9*L9)/K16)+((K10*L10)/K16)+((K11*L11)/K16)+((K12*L12)/K16)+((K13*L13)/K16)+((K14*L14)/K16)+((K15*L15)/K16),0) -> 0.1105043 | M16: =SUM(M8:M15) -> 515551663 | N16: =IFERROR(((M8*N8)/M16)+((M9*N9)/M16)+((M10*N10)/M16)+((M11*N11)/M16)+((M12*N12)/M16)+((M13*N13)/M16)+((M14*N14)/M16)+((M15*N15)/M16),0) -> 0.040257105 | P16: =+'[8]Bank Liabilities Analysis'!$S$22 -> 3153675139 | Q16: =+P16-C16-I16 -> 0
B19: Подпись Председателя правления:
B21: Подпись Главного Бухгалтера:
B24: Физлица | C24: =+'[8]Deposits by Client'!$C$6+'[8]Deposits by Client'!$C$15 -> 775301869 | G24: =+'[8]Deposits by Client'!$D$6+'[8]Deposits by Client'!$D$15 -> 71762165
C25: =+C16 -> 775301869 | G25: =+G16 -> 71762165
C26: =+C24-C25 -> 0 | G26: =+G24-G25 -> 0
B27: Юрзлица | I27: =+'[8]Deposits by Client'!$C$22-'[8]Deposits by Client'!$C$6-'[8]Deposits by Client'!$C$15 -> 2378373270 | M27: =+'[8]Deposits by Client'!$D$22-'[8]Deposits by Client'!$D$6-'[8]Deposits by Client'!$D$15 -> 515551663
I28: =+I16 -> 2378373270 | M28: =+M16 -> 515551663
I29: =+I27-I28 -> 0 | M29: =+M27-M28 -> 0

Sheet Economic Normatives
A1: РАСЧЕТ ПРУДЕНЦИАЛЬНЫХ НОРМАТИВОВ | I1: Таблица-22
B2: =+'Asset quality'!B3 -> "Микрокредитбанк" | I2: =+'Asset quality'!P3 -> 44560
A4: № | B4: Наименование экономического норматива | F4: Формула | I4: Фактическое значение | J4: Нормативное значение | K4: Отклонение
B5: A | F5: Б | I5: В | J5: Г | K5: Д
A6: 1 | B6: Показатели достаточности капитала
A7: 1.1 | B7: Коэффициент достаточности капитала | F7: Скорректированная общая капитала, основанного на риске | I7: =+'[9]Bank Capital Calc'!$C$51 -> 0.13760027 | J7: Мин | K7: =IF(I7="",0-J8,(IF((I7-J8)>0,"",I7-J8)))
F8: Активы с учетом риска | J8: 0.13
A9: 1.2 | B9: Коэффициент достаточности Капитала Уровня 1 | F9: Капитал Уровня I | I9: =+'[9]Bank Capital Calc'!$C$50 -> 0.13217901 | J9: Мин | K9: =IF(I9="",0-J10,(IF((I9-J10)>0,"",I9-J10)))
F10: Активы с учетом риска | J10: 0.1
A11: 1.3 | B11: Коэффициент достаточности основного Капитала Уровня 1 | F11: Основной капитал Уровня I | I11: =+'[9]Bank Capital Calc'!$C$49 -> 0.13217044 | J11: Мин | K11: =IF(I11="",0-J12,(IF((I11-J12)>0,"",I11-J12)))
F12: Активы с учетом риска | J12: 0.08
A13: 1.4 | B13: Левераж | F13: Капитал Уровня I | I13: =+'[9]Bank Capital Calc'!$C$57 -> 0.18388278 | J13: Мин | K13: =IF(I13="",0-J14,(IF((I13-J14)>0,"",I13-J14)))
F14: Активы + забалансовые инструменты+ деривативные (производные) инструменты - вычеты из суммы основного капитала уровня I | J14: 0.06
A15: 2 | B15: Показатели ликвидности
A16: 2.1 | B16: Коэффициент покрытия ликвидности | E16: Всего | F16: Высоколиквидные активы | I16: =IFERROR((+'[8]Liquidity Analysis'!$C$23),0) -> 1.651834 | J16: Мин | K16: =IF(I16="",0-$J$18,(IF((I16-$J$18)>0,"",I16-$J$18)))
E17: в национальной валюте | I17: =IFERROR((+'[8]Liquidity Analysis'!$D$23),0) -> 1.7392091 | K17: =IF(I17="",0-$J$18,(IF((I17-$J$18)>0,"",I17-$J$18)))
E18: в иностранной валюте | F18: Чистый отток в последующие 30 дней | I18: =IFERROR((+'[8]Liquidity Analysis'!$E$23),0) -> 1.5338096 | J18: 1 | K18: =IF(I18="",0-$J$18,(IF((I18-$J$18)>0,"",I18-$J$18)))
A19: 2.2 | B19: Норма чистого стабильного финансирования | E19: Всего | F19: Доступная сумма стабильного финансирования | I19: =IFERROR((+'[8]Liquidity Analysis'!$C$28),0) -> 1.1713699 | J19: Мин | K19: =IF(I19="",0-$J$21,(IF((I19-$J$21)>0,"",I19-$J$21)))
E20: в национальной валюте | I20: =IFERROR((+'[8]Liquidity Analysis'!$D$28),0) -> 1.1994253 | K20: =IF(I20="",0-$J$21,(IF((I20-$J$21)>0,"",I20-$J$21)))
E21: в иностранной валюте | F21: Необходимая сумма стабильного финансирования | I21: =IFERROR((+'[8]Liquidity Analysis'!$E$28),0) -> 1.1134913 | J21: 1 | K21: =IF(I21="",0-$J$21,(IF((I21-$J$21)>0,"",I21-$J$21)))
A22: 3 | B22: Нормативы по операциям с заемщиками
A23: 3.1 | B23: Максимальный размер риска на одного заемщика или группу взаимосвязанных заемщиков, обеспеченные | F23: Максимальный размер риска на одного заемщика или группу взаимосвязанных заемщиков,обеспеченные | I23: =IFERROR((+' Largest risk'!Z65/'[9]Bank Capital Calc'!$C$34),0) -> 0.18746482 | J23: Макс | K23: =IF(I23="","",IF(I23<0,"ОТР",IF((I23-J24)<0,"",I23-J24)))
F24: Капитал Уровня I | J24: 0.25
A25: 3.2 | B25: Максимальный размер риска на один банк или группу взаимосвязанных банков-заемщиков по межбанковским операциям | F25: Максимальный размер риска на один банк или группу взаимосвязанных банков-заемщиков по межбанковским операциям | I25: 0.007 | J25: Макс | K25: =IF(I25<0,"ОТР",IF((I25-J26)<0,"",I25-J26)) | M25: Заполняется в ручную
F26: Капитал Уровня I | J26: 0.25
A27: 3.3 | B27: Максимальный размер необеспеченного актива на одного заемщика или группу взаимосвязанных заемщиков (не включая риски по межбанковским операциям) | F27: Максимальный размер необеспеченного актива на одного заемщика или группу взаимосвязанных заемщиков (не включая риски по межбанковским операциям) | I27: 0 | J27: Макс | K27: =IF(I27<0,"ОТР",IF((I27-J28)<0,"",I27-J28)) | M27: Заполняется в ручную
F28: Капитал Уровня I | J28: 0.05
A29: 3.4 | B29: Совокупная сумма всех крупных рисков | F29: Совокупная сумма всех крупных рисков | I29: =IFERROR((+' Largest risk'!Z64/'[9]Bank Capital Calc'!$C$34),0) -> 0.35439706 | J29: Макс | K29: =IF(I29="","",IF(I29<0,"ОТР",IF((I29-J30)<0,"",I29-J30)))
F30: Капитал Уровня I | J30: 5
A31: 4 | B31: Нормативы по операциям с ценными бумагами
A32: 4.1 | B32: Максимальный размер инвестиций в ценные бумаги одного эмитента | F32: Инвестиции в негосударственные ценные бумаги одного эмитента | I32: 0 | J32: Макс | K32: =IF(I32<0,"ОТР",IF((I32-J33)<0,"",I32-J33)) | M32: Заполняется в ручную
F33: Капитал Уровня I | J33: 0.15
A34: 4.2 | B34: Максимальный общий размер инвестиций в ценные бумаги для купли- продажи | F34: Общий размер инвестиций в ценные бумаги для купли- продажи | I34: =IFERROR((+('[8]Investment Securities'!$B$22+'[8]Investment Securities'!$B$23+'[8]Investment Securities'!$B$24+'[8]Investment Securities'!$B$25-'[8]Investment Securities'!$B$28)/'[9]Bank Capital Calc'!$C$34),0) -> 0 | J34: Макс | K34: =IF(I34="","",IF(I34<0,"ОТР",IF((I34-J35)<0,"",I34-J35)))
F35: Капитал Уровня I | J35: 0.25
A36: 4.3 | B36: Максимальный общий размер инвестиций в уставной капитал и другие ценные бумаги всех эмитентов | F36: Общий размер инвестиций в уставной капитал и другие ценные бумаги всех эмитентов | I36: =IFERROR((+(+'[8]Investment Securities'!$B$15-'[8]Investment Securities'!$B$6-'[8]Investment Securities'!$B$7+'[8]Investment Securities'!$B$22+'[8]Investment Securities'!$B$23+'[8]Investment Securities'!$B$24+'[8]Investment Securities'!$B$25-'[8]Investment Securities'!$B$28)/'[9]Bank Capital Calc'!$C$34),0) -> 4.822733e-05 | J36: Макс | K36: =IF(I36="","",IF(I36<0,"ОТР",IF((I36-J37)<0,"",I36-J37)))
F37: Капитал Уровня I | J37: 0.5
A38: 5 | B38: Нормативы по операциям со связанными с банком лицами
A39: 5.1 | B39: Максимальный размер риска на одного связанного с банком лица, обеспеченные | F39: Максимальный размер риска на одного связанного с банком лица, обеспеченные | I39: =IFERROR(((+'Transactions of related parties'!Z65-'[9]Bank Capital Calc'!$C$24)/'[9]Bank Capital Calc'!$C$34),0) -> 0.00097005772 | J39: Макс | K39: =IF(I39="","",IF(I39<0,"ОТР",IF((I39-J40)<0,"",I39-J40)))
F40: Капитал Уровня I | J40: 0.25
A41: 5.2 | B41: Совокупная сумма рисков по всем связанным с банком лицам | F41: Совокупная сумма рисков по всем связанным с банком лицам | I41: =IFERROR(((+'Transactions of related parties'!Z64-'[9]Bank Capital Calc'!$C$24)/'[9]Bank Capital Calc'!$C$34),0) -> 0.0010381073 | J41: Макс | K41: =IF(I41="","",IF(I41<0,"ОТР",IF((I41-J42)<0,"",I41-J42)))
F42: Капитал Уровня I | J42: 0.5
A43: 6 | B43: Нормативный показатель по инвестициям банка в недвижимость
A44: 6.1 | B44: Совокупная сумма всех инвестиций банка в недвижимость | F44: Сумма всех инвестиций банка в недвижимость | I44: 0 | J44: Макс | K44: =IF(I44="","",IF(I44<0,"ОТР",IF((I44-J45)<0,"",I44-J45))) | M44: Заполняется в ручную
F45: Капитал Уровня I | J45: 1
D47: Подпись Председателя правления:
D49: Подпись Главного Бухгалтера:

Sheet Miscellaneous
B1: РАЗНАЯ ИНФОРМАЦИЯ | C1: Таблица-23
B2: =+'Asset quality'!B3 -> "Микрокредитбанк" | C2: тыс. сум
A3: 1. | B3: Численность работников банка, включая административный, филиалы, и представительства банка. | C3: 2558
A4: а | B4: Численность работников банка по штатному расписанию | C4: 3708
A5: б | B5: Фактическая численность работников банка | C5: 3575
A6: 2. | B6: Общее количество отделений банка, включая административный, филиалы, и представительства банка.
B7: из них,
A8: а | B8: Количество филиалов | C8: 71
A9: б | B9: Количество мини банков | C9: 24
A10: в | B10: Количество розничных касс вне банка (филиалы) | C10: 24
A11: г | B11: Количество центров банковских услуг | C11: 87
A12: 3. | B12: Клиенская база банка | C12: =C14+C15+C16 -> 2026344
B13: из них,
A14: а | B14: Физические лица | C14: 1282401
A15: б | B15: Индивидуальные предприниматели | C15: 210012
A16: в | B16: Юридические лица | C16: =+C18+C19+C20+C21+C22 -> 533931 | E16: в этой строке указываются количество всех юридических лиц
B17: в том числе имеющие основной счет в банке | E17: в этой строке указываются количество юридических лиц, которые имеют основной счет в банке
A18: - | B18: Государственные предприятия | C18: 1076
A19: - | B19: Частные товарищества и корпорации | C19: 486342
A20: - | B20: Фермерское хозяйство | C20: 3812
A21: - | B21: Правительство | C21: 0
A22: - | B22: Прочие | C22: 42701
A23: 4. | B23: Рейтинг банка | C23: ВВ-
A24: а | B24: Названия рейтинговой компании | C24: Фитч Рейтингс
A25: б | B25: Оценка рейтинга банка | C25: ВВ-
B28: Подпись Председателя правления:
B30: Подпись Главного Бухгалтера:

Sheet ПФУ
A1: Показатели финансовой устойчивости
A2: =+'Asset quality'!B3 -> "Микрокредитбанк" | B2: тыс. сум | C2: Месяц
A3: Основные показатели | B3: =+'Asset quality'!P3 -> 44560 | K3: Месяц | L3: Актив | M3: Капитал | O3: Всего активы (средний за период) | P3: Совокупный капитал (средний за период)
A4: Регулятивный капитал к активам взвешанных с учетом риска | B4: =IFERROR((B5/B6),0) -> 0.13760027 | J4: 1 января | K4: 1 | L4: 10282915665 | M4: 1738289532
A5: Всего Регулятивный капитал | B5: =+'[9]Bank Capital Calc'!$C$44 -> 2314405041 | J5: 1 февраль | K5: 2 | L5: 10462381502 | M5: 1776207829 | N5: 1 | O5: =+(L4+L5)/2 -> 1.0372649e+10 | P5: =+(M4+M5)/2 -> 1.7572487e+09
A6: Активы взвешанные с учетом риска | B6: =+'[9]Bank Capital Calc'!$C$45 -> 1.6819772e+10 | J6: 1 март | K6: 3 | L6: 10551550910 | M6: 1773838218 | N6: 2 | O6: =+(L4+L5+L6)/3 -> 1.0432283e+10 | P6: =+(M4+M5+M6)/3 -> 1.7627785e+09
A7: Регулятивный капитал 1 - уровня к Активам взвешанных с учетом риска | B7: =IFERROR((B8/B9),0) -> 0.13217901 | J7: 1 апрель | K7: 4 | L7: 10645189610 | M7: 1774167357 | N7: 3 | O7: =+(L4+L7)/2 -> 1.0464053e+10 | P7: =+(M4+M7)/2 -> 1.7562284e+09
A8: Регулятивный капитал 1- уровня | B8: =+'[9]Bank Capital Calc'!$C$34 -> 2223220725 | J8: 1 май | K8: 5 | L8: 11182732279 | M8: 1768540700 | N8: 4 | O8: =+(+L4+L5+L6+L7+L8)/5 -> 1.0624954e+10 | P8: =+(+M4+M5+M6+M7+M8)/5 -> 1.7662087e+09
A9: Активы взвешанные с учетом риска | B9: =+'[9]Bank Capital Calc'!$C$45 -> 1.6819772e+10 | J9: 1 июнь | K9: 6 | L9: 11550881753 | M9: 1770979785 | N9: 5 | O9: =+(+L4+L5+L6+L7+L8+L9)/6 -> 1.0779275e+10 | P9: =+(+M4+M5+M6+M7+M8+M9)/6 -> 1.7670039e+09
A10: Недействующие ссуды за вычетом резервов/общий объем капитала | B10: =IFERROR((B11/B12),0) -> 0.22284552 | J10: 1 июль | K10: 7 | L10: 12715256100 | M10: 2170115463 | N10: 6 | O10: =+(L4+L7+L10)/3 -> 1.1214454e+10 | P10: =+(M4+M7+M10)/3 -> 1894190784
A11: Недействующие ссуды за вычетом резервов | B11: =+('Asset Classification'!M50-'Asset Classification'!O50+'Asset Classification'!Q50-'Asset Classification'!S50+'Asset Classification'!U50-'Asset Classification'!W50) -> 517245886 | J11: 1 август | K11: 8 | L11: 12614107193 | M11: 2171574828 | N11: 7 | O11: =(L4+L5+L6+L7+L8+L9+L10+L11)/8 -> 1.1250627e+10 | P11: =(M4+M5+M6+M7+M8+M9+M10+M11)/8 -> 1867964214
A12: Совокупный капитал на конец периода | B12: =+B35 -> 2321096230 | J12: 1 сентябрь | K12: 9 | L12: 12678935359 | M12: 2337862088 | N12: 8 | O12: =(L4+L5+L6+L7+L8+L9+L10+L11+L12)/9 -> 11409327819 | P12: =(M4+M5+M6+M7+M8+M9+M10+M11+M12)/9 -> 1.9201751e+09
A13: Недействующие ссуды/общая сумма ссуд | B13: =IFERROR((B14/B15),0) -> 0.059380283 | J13: 1 октябрь | K13: 10 | L13: 12733558140 | M13: 2304429434 | N13: 9 | O13: =+(L4+L7+L10+L13)/4 -> 1.159423e+10 | P13: =+(M4+M7+M10+M13)/4 -> 1.9967504e+09
A14: Недействующие ссуды | B14: =+('Asset Classification'!M50+'Asset Classification'!Q50+'Asset Classification'!U50) -> 642250253 | J14: 1 ноябрь | K14: 11 | L14: 13001343679 | M14: 2306845268 | N14: 10 | O14: =(+L4+L5+L6+L7+L8+L9+L10+L11+L12+L13+L14)/11 -> 1.1674441e+10 | P14: =(+M4+M5+M6+M7+M8+M9+M10+M11+M12+M13+M14)/11 -> 1.9902591e+09
A15: Общая сумма ссуд | B15: =+'Loans Receivable'!C92 -> 10815884011 | J15: 1 декабрь | K15: 12 | L15: 13114369198 | M15: 2319234197 | N15: 11 | O15: =(+L4+L5+L6+L7+L8+L9+L10+L11+L12+L13+L14+L15)/12 -> 1.1794435e+10 | P15: =(+M4+M5+M6+M7+M8+M9+M10+M11+M12+M13+M14+M15)/12 -> 2.0176737e+09
A16: Рентабельность активов | B16: =IFERROR((B17/B18),0) -> 0.0042897204 | J16: 1 январь | K16: 13 | L16: 13483353628 | M16: 2321096230 | N16: 12 | O16: =+(L4+L7+L10+L13+L16)/5 -> 1.1972055e+10 | P16: =+(M4+M7+M10+M13+M16)/5 -> 2.0616196e+09
A17: Чистая прибыль до уплаты налогов | B17: =(+'Income '!C72)/MONTH(B3)*12 -> 51356767
A18: Всего активы (средний за период) | B18: =VLOOKUP(MONTH(B3),$N$4:$P$16,2,0) -> 1.1972055e+10
A19: Рентабельность капитала | B19: =IFERROR((B20/B21),0) -> 0.018647032
A20: Чистая прибыль | B20: =(+'Income '!C79)/MONTH(B3)*12 -> 38443086
A21: Совокупный капитал (средний за период) | B21: =VLOOKUP(MONTH(B3),$N$4:$P$16,3,0) -> 2.0616196e+09
A22: Процентная маржа/валовой доход | B22: =IFERROR((B23/B24),0) -> 0.53271498
A23: Процентная маржа | B23: =+'Income '!C30 -> 625259227
A24: Валовой доход | B24: =+B27 -> 1173721883
A25: Непроцентные расходы/валовой доход | B25: =IFERROR((B26/B27),0) -> 0.58774
A26: Непроцентные расходы | B26: =+'Income '!C54+'Income '!C70 -> 689843301
A27: Валовой доход | B27: =+'Income '!C30+'Income '!C46 -> 1173721883
A28: Ликвидные активы/всего активы | B28: =IFERROR((B29/B30),0) -> 0.1223575
A29: Ликвидные активы | B29: =+B32 -> 1649789456
A30: Всего активы | B30: =+B36 -> 13483353628
A31: Ликвидные активы/краткосрочные обязательства | B31: =IFERROR((B29/B33),0) -> 0.30937436
A32: Ликвидные активы | B32: =+B54 -> 1649789456
A33: Краткосрочные обязательства | B33: =+('[8]Bank Liabilities Analysis'!$C$39+'[8]Bank Liabilities Analysis'!$E$39+'[8]Bank Liabilities Analysis'!$G$39+'[8]Bank Liabilities Analysis'!$I$39+'[8]Bank Liabilities Analysis'!$K$39+'[8]Bank Liabilities Analysis'!$M$39) -> 5332663796
A34: Совокупный капитал на конец периода/Всего активы | B34: =IFERROR((B35/B36),0) -> 0.17214532
A35: Совокупный капитал на конец периода | B35: =+[8]Balance!$C$77 -> 2321096230
A36: Всего активы | B36: =+[8]Balance!$C$45 -> 13483353628
A37: Чистая открытая валютная позиция /Совокупный капитал на конец периода | B37: =IFERROR((B38/B39),0) -> 0.06547159
A38: Чистая открытая валютная позиция | B38: =+'[9]Calculation of Risk'!$C$26 -> 151965860
A39: Совокупный капитал на конец периода | B39: =+B35 -> 2321096230
A42: Подпись Председателя правления:
A44: Подпись Главного Бухгалтера:
A46: Ликвидные активы | B46: Сумма | C46: Нацвалюта | D46: Инвалюта
A47: Наличные денежные средства и Драгоценные металлы | B47: =+'[8]Liquidity Analysis'!C50 -> 296970345 | C47: =+'[8]Liquidity Analysis'!D50 -> 140098936 | D47: =+'[8]Liquidity Analysis'!E50 -> 156871409 | E47: 1.
A48: К получению из ЦБРУ | B48: =+'[8]Liquidity Analysis'!C51 -> 580486619 | C48: =+'[8]Liquidity Analysis'!D51 -> 354325926 | D48: =+'[8]Liquidity Analysis'!E51 -> 226160693 | E48: 2.
A49: К получению из других банков | B49: =+'[8]Liquidity Analysis'!C52 -> 255752492 | C49: =+'[8]Liquidity Analysis'!D52 -> 2708695 | D49: =+'[8]Liquidity Analysis'!E52 -> 253043797 | E49: 3.
A50: К получению из других банков - Депозиты (чистые) | B50: =+'[8]Liquidity Analysis'!C53 -> 0 | C50: =+'[8]Liquidity Analysis'!D53 -> 3082007 | D50: =+'[8]Liquidity Analysis'!E53 -> 0 | E50: 3.1.
A51: Ценные бумаги, выпущенные Правительством Республики Узбекистан и ЦБРУ (векселя, облигации и другие долговые ценные бумаги) | B51: =+'[8]Liquidity Analysis'!C54 -> 516580000 | C51: =+'[8]Liquidity Analysis'!D54 -> 516580000 | D51: =+'[8]Liquidity Analysis'!E54 -> 0 | E51: 4.
A52: Ценные бумаги, выпущенные странами с низким уровня риска | B52: =+'[8]Liquidity Analysis'!C55 -> 0 | C52: =+'[8]Liquidity Analysis'!D55 -> 0 | D52: =+'[8]Liquidity Analysis'!E55 -> 0 | E52: 5.
A53: Другие легко реализуемые ценные бумаги | B53: =+'[8]Liquidity Analysis'!C56 -> 0 | C53: =+'[8]Liquidity Analysis'!D56 -> 0 | D53: =+'[8]Liquidity Analysis'!E56 -> 0 | E53: 6.
A54: Итого ликвидных активов | B54: =+'[8]Liquidity Analysis'!C57 -> 1649789456 | C54: =+'[8]Liquidity Analysis'!D57 -> 1016795564 | D54: =+'[8]Liquidity Analysis'!E57 -> 636075899 | E54: 7.
