Workbook
Name OLE_LINK19: Balance!$D$32

Sheet Balance
A1: БАНК БАЛАНСИ ТАРКИБИ | E1: 1-жадвал | G1: №2
B2: =IF(D3>0," "&TEXT(D3,"д ММММ, гггг"),"Число,Месяц,Год") -> 30 Декабрь, 2025
B3: "MKBANK" | D3: 46021 | E3: минг сўмда
A4: № | B4: АКТИВЛАР | C4: Жами | D4: Миллий валютада | E4: Хорижий валютада (сўм экв.)
A5: 1 | B5: Кассадаги нақд пул ва бошқа тўлов ҳужжатлари | C5: =+D5+E5 -> 703550546 | D5: =+'Bank Assets Analysis'!T6 -> 538991500 | E5: =+'Bank Assets Analysis'!U6 -> 164559046 | J5: =+C5-D5-E5 -> 0
A6: 2 | B6: Банкнинг Марказий банкдаги маблағлари | C6: =+D6+E6 -> 584034134 | D6: =+'Bank Assets Analysis'!T7+'Bank Assets Analysis'!T8 -> 584034134 | E6: =+'Bank Assets Analysis'!U7+'Bank Assets Analysis'!U8 -> 0 | J6: =+C6-D6-E6 -> 0
A7: 3 | B7: Бошқа банклар ва молиявий ташкилотлардан олиниши лозим бўлган маблағлар, соф | C7: =+'Bank Assets Analysis'!S9 -> 3466881057 | D7: =+'Bank Assets Analysis'!T9 -> 61516243 | E7: =+'Bank Assets Analysis'!U9 -> 3405364814 | J7: =+C7-D7-E7 -> 0
A8: 3.1 | B8: Бошқа банклар ва молиявий ташкилотлардан олиниши лозим бўлган маблағлар, брутто | C8: =+D8+E8 -> 3466881057 | D8: 61516243 | E8: 3405364814 | J8: =+C8-D8-E8 -> 0
A9: 3.2 | B9: Минус: Кўрилиши мумкин бўлган зарарларни қоплаш захираси | C9: =+D9+E9 -> 0 | D9: 0 | E9: 0 | J9: =+C9-D9-E9 -> 0
A10: 4 | B10: Қимматли қоғозлар ва уларга қилинган инвестициялар, соф | C10: =+D10+E10 -> 518169320 | D10: =+'Investment Securities'!C29 -> 518169320 | E10: =+'Investment Securities'!D29 -> 0 | J10: =+C10-D10-E10 -> 0
A11: 4.1 | B11: Қимматли қоғозлар ва уларга қилинган инвестициялар, брутто | C11: =+D11+E11 -> 524100000 | D11: =+'Investment Securities'!C26 -> 524100000 | E11: =+'Investment Securities'!D26 -> 0 | J11: =+C11-D11-E11 -> 0
A12: 4.2 | B12: Қимматли қоғозлар бўйича харажатлар, дисконт, мукофот ва уларнинг ҳаққоний қийматининг ўзгариши | C12: =+D12+E12 -> -5930680 | D12: =+'Investment Securities'!C27 -> -5930680 | E12: =+'Investment Securities'!D27 -> 0 | J12: =+C12-D12-E12 -> 0
A13: 4.3 | B13: Минус: Кўрилиши мумкин бўлган зарарларни қоплаш захираси | C13: =+D13+E13 -> 0 | D13: =+'Investment Securities'!C28 -> 0 | E13: =+'Investment Securities'!D28 -> 0 | J13: =+C13-D13-E13 -> 0
A14: 5 | B14: Қимматбаҳо металлар, тошлар ва тангалар, соф | C14: =+C15-C16 -> 175 | D14: =+'Investment Securities'!C39 -> 175 | E14: =+'Investment Securities'!D39 -> 0 | J14: =+C14-D14-E14 -> 0
A15: 5.1 | B15: Қимматбаҳо металлар, тошлар ва тангалар, брутто | C15: =+D15+E15 -> 175 | D15: =+'Investment Securities'!C37 -> 175 | E15: =+'Investment Securities'!D37 -> 0 | J15: =+C15-D15-E15 -> 0
A16: 5.2 | B16: Минус: Кўрилиши мумкин бўлган зарарларни қоплаш захираси | C16: =+D16+E16 -> 0 | D16: =+'Investment Securities'!C38 -> 0 | E16: =+'Investment Securities'!D38 -> 0 | J16: =+C16-D16-E16 -> 0
A17: 6 | B17: Инвестициялар, соф | C17: =+'Investment Securities'!B15 -> 925002773 | D17: =+'Investment Securities'!C15 -> 925002773 | E17: =+'Investment Securities'!D15 -> 0 | J17: =+C17-D17-E17 -> 0
A18: 6.1 | B18: Инвестициялар, брутто | C18: =+D18+E18 -> 925002773 | D18: =+'Investment Securities'!C12 -> 925002773 | E18: =+'Investment Securities'!D12 -> 0 | J18: =+C18-D18-E18 -> 0
A19: 6.2 | B19: Инвестициялар бўйича харажатлар, дисконт ва мукофот | C19: =+D19+E19 -> 0 | D19: =+'Investment Securities'!C13 -> 0 | E19: =+'Investment Securities'!D13 -> 0 | J19: =+C19-D19-E19 -> 0
A20: 6.3 | B20: Минус: Кўрилиши мумкин бўлган зарарларни қоплаш захираси | C20: =+D20+E20 -> 0 | D20: =+'Investment Securities'!C14 -> 0 | E20: =+'Investment Securities'!D14 -> 0 | J20: =+C20-D20-E20 -> 0
A21: 7 | B21: РЕПО битимлари бўйича сотиб олинган қимматли қоғозлар, соф | C21: =+'Bank Assets Analysis'!S34 -> 0 | D21: =+'Bank Assets Analysis'!T34 -> 0 | E21: =+'Bank Assets Analysis'!U34 -> 0 | J21: =+C21-D21-E21 -> 0
A22: 7.1 | B22: РЕПО битимлари бўйича сотиб олинган қимматли қоғозлар, брутто | C22: =+D22+E22 -> 0 | D22: 0 | E22: 0 | J22: =+C22-D22-E22 -> 0
A23: 7.2 | B23: Минус: Кўрилиши мумкин бўлган зарарларни қоплаш захираси | C23: =+D23+E23 -> 0 | D23: 0 | E23: 0 | J23: =+C23-D23-E23 -> 0
A24: 8 | B24: Кредит ва лизинг операциялари, соф | C24: =+'Bank Assets Analysis'!S29+'Bank Assets Analysis'!S30+'Bank Assets Analysis'!S32 -> 20150194733 | D24: =+'Bank Assets Analysis'!T29+'Bank Assets Analysis'!T30+'Bank Assets Analysis'!T32 -> 16435905946 | E24: =+'Bank Assets Analysis'!U29+'Bank Assets Analysis'!U30+'Bank Assets Analysis'!U32 -> 3714288787 | J24: =+C24-D24-E24 -> 0
A25: 8.1 | B25: Кредит ва лизинг операциялари, брутто | C25: =+D25+E25 -> 20277891345 | D25: 16539892398 | E25: 3737998947 | J25: =+C25-D25-E25 -> 0
A26: 8.2 | B26: Минус: Кўрилиши мумкин бўлган зарарларни қоплаш захираси | C26: =+D26+E26 -> 127696612 | D26: 103986452 | E26: 23710160 | J26: =+C26-D26-E26 -> 0
A27: 9 | B27: Молиявий инструментлар бўйича мижозларнинг мажбуриятлари, соф | C27: =+'Bank Assets Analysis'!S26+'Bank Assets Analysis'!S27 -> 38191497 | D27: =+'Bank Assets Analysis'!T26+'Bank Assets Analysis'!T27 -> 1400024 | E27: =+'Bank Assets Analysis'!U26+'Bank Assets Analysis'!U27 -> 36791473 | J27: =+C27-D27-E27 -> 0
A28: 9.1 | B28: Молиявий инструментлар бўйича мижозларнинг мажбуриятлари, брутто | C28: =+D28+E28 -> 38191497 | D28: 1400024 | E28: 36791473 | J28: =+C28-D28-E28 -> 0
A29: 9.2 | B29: Минус: Кўрилиши мумкин бўлган зарарларни қоплаш захираси | C29: =+D29+E29 -> 0 | D29: 0 | E29: 0 | J29: =+C29-D29-E29 -> 0
A30: 10 | B30: Асосий воситалар, соф | C30: =+'Bank Assets Analysis'!S37 -> 903999652 | D30: =+'Bank Assets Analysis'!T37 -> 903999652 | E30: =+'Bank Assets Analysis'!U37 -> 0 | J30: =+C30-D30-E30 -> 0
A31: 11 | B31: Жами ҳисобланган фоизли ва фоизсиз даромадлар, соф | C31: =+C32+C33-C34 -> 1872921101 | D31: =+D32+D33-D34 -> 1365363123 | E31: =+E32+E33-E34 -> 507557978 | J31: =+C31-D31-E31 -> 0
A32: 11.1 | B32: Ҳисобланган фоизли даромадлар, брутто | C32: =+D32+E32 -> 1877283913 | D32: 1369725935 | E32: 507557978 | J32: =+C32-D32-E32 -> 0
A33: 11.2 | B33: Ҳисобланган фоизсиз даромадлар, брутто | C33: =+D33+E33 -> 2431865 | D33: 2431865 | E33: 0 | J33: =+C33-D33-E33 -> 0
A34: 11.2.1 | B34: Минус: Кўрилиши мумкин бўлган зарарларни қоплаш захираси | C34: =+D34+E34 -> 6794677 | D34: 6794677 | E34: 0 | J34: =+C34-D34-E34 -> 0
A35: 12 | B35: Банкнинг бошқа хусусий мулклари, соф | C35: =+'Bank Assets Analysis'!S38 -> 790493963 | D35: =+'Bank Assets Analysis'!T38 -> 790493963 | E35: =+'Bank Assets Analysis'!U38 -> 0 | J35: =+C35-D35-E35 -> 0
A36: 12.1 | B36: Кредит ва лизинг бўйича гаров ҳисобидан ундирилган бошқа мулклар, брутто | C36: =+D36+E36 -> 795720074 | D36: 795720074 | E36: 0 | J36: =+C36-D36-E36 -> 0
A37: 12.2 | B37: Банкнинг бошқа хусусий мулклари, брутто | C37: =+D37+E37 -> 44817300 | D37: 44817300 | E37: 0 | J37: =+C37-D37-E37 -> 0
A38: 12.3 | B38: Минус: Йиғилган эскириш суммаси ва кўрилиши мумкин бўлган зарарларни қоплаш захираси | C38: =+D38+E38 -> 50043411 | D38: 50043411 | E38: 0 | J38: =+C38-D38-E38 -> 0
A39: 13 | B39: Стандарт деб таснифланган активлар бўйича яратилган захиралар | C39: =+D39+E39 -> 123374035 | D39: =+D40+D41+D42 -> 123374035 | E39: =+E40+E41+E42 -> 0 | J39: =+C39-D39-E39 -> 0
A40: 13.1 | B40: Стандарт деб таснифланган кредитлар, лизинг ва факторинг бўйича захира | C40: =+D40+E40 -> 123374035 | D40: 123374035 | E40: 0 | J40: =+C40-D40-E40 -> 0
A41: 13.2 | B41: Стандарт деб таснифланган бошқа активлар бўйича захира | C41: =+D41+E41 -> 0 | D41: 0 | E41: 0 | J41: =+C41-D41-E41 -> 0
A42: 13.3 | B42: Стандарт деб таснифланган активлар бўйича фоизлар ва воситачилик ҳақларига оид захира | C42: =+D42+E42 -> 0 | D42: 0 | E42: 0 | J42: =+C42-D42-E42 -> 0
A43: 14 | B43: Бошқа активлар, соф | C43: =+C44-C45+C46 -> 898722264 | D43: =+D44-D45+D46 -> 868238934 | E43: =+E44-E45+E46 -> 30483330 | J43: =+C43-D43-E43 -> 0
A44: 14.1 | B44: Бошқа активлар, брутто | C44: =+D44+E44 -> 903094016 | D44: 872610686 | E44: 30483330 | J44: =+C44-D44-E44 -> 0
A45: 14.2 | B45: Минус: Кўрилиши мумкин бўлган зарарларни қоплаш захираси | C45: =+D45+E45 -> 4371752 | D45: 4371752 | E45: 0 | J45: =+C45-D45-E45 -> 0
A46: 14.3 | B46: Валюталар савдоси ва валюта позициялари | C46: 0 | J46: =+C46-D46-E46 -> 0
A47: 15 | B47: Жами активлар | C47: =+D47+E47 -> 30728787180 | D47: =+D5+D6+D7+D10+D14+D17+D21+D24+D27+D30+D31+D35-D39+D43 -> 22869741752 | E47: =+E5+E6+E7+E10+E14+E17+E21+E24+E27+E30+E31+E35-E39+E43 -> 7859045428 | F47: =+'Bank Assets Analysis'!S47 -> 30728787180 | G47: =+'Bank Assets Analysis'!T47 -> 22869741752 | H47: =+'Bank Assets Analysis'!U47 -> 7859045428 | J47: =+C47-D47-E47 -> 0
B49: МАЖБУРИЯТЛАР
A50: 16 | B50: Талаб қилиб олингунча сақланадиган депозитлар | C50: =+'Deposits by Client'!C11 -> 916450291 | D50: =+'Bank Liabilities Analysis'!T15+'Bank Liabilities Analysis'!T7 -> 849557398 | E50: =+'Bank Liabilities Analysis'!U15+'Bank Liabilities Analysis'!U7 -> 66892893 | J50: =+C50-D50-E50 -> 0
A51: 17 | B51: Муддатли депозитлар | C51: =+'Deposits by Client'!C20 -> 8810218869 | D51: =+'Bank Liabilities Analysis'!T12 -> 8055102480 | E51: =+'Bank Liabilities Analysis'!U12 -> 755116389 | J51: =+C51-D51-E51 -> 0
A52: 18 | B52: Марказий банкка тўланиши лозим бўлган маблағлар | C52: =+'Bank Liabilities Analysis'!S21 -> 442535 | D52: =+'Bank Liabilities Analysis'!T21 -> 442535 | E52: =+'Bank Liabilities Analysis'!U21 -> 0 | J52: =+C52-D52-E52 -> 0
A53: 19 | B53: Бошқа банклар ва молиявий ташкилотларнинг ҳисобварақлари | C53: =+'Bank Liabilities Analysis'!S23 -> 2044939904 | D53: =+'Bank Liabilities Analysis'!T23 -> 1550743496 | E53: =+'Bank Liabilities Analysis'!U23 -> 494196408 | J53: =+C53-D53-E53 -> 0
A54: 20 | B54: РЕПО битимлари бўйича сотилган қимматли қоғозлар | C54: =+'Bank Liabilities Analysis'!S33 -> 0 | D54: =+'Bank Liabilities Analysis'!T33 -> 0 | E54: =+'Bank Liabilities Analysis'!U33 -> 0 | J54: =+C54-D54-E54 -> 0
A55: 21 | B55: Кредит ва лизинг операциялари бўйича мажбуриятлар | C55: =+D55+E55 -> 12083353501 | D55: 5672254099 | E55: 6411099402 | J55: =+C55-D55-E55 -> 0
A56: 22 | B56: Банк томонидан чиқарилган қимматли қоғозлар | C56: =+D56+E56 -> 0 | D56: 0 | E56: 0 | J56: =+C56-D56-E56 -> 0
A57: 23 | B57: Субординар қарз | C57: =+D57+E57 -> 703058234 | D57: 703058234 | E57: 0 | J57: =+C57-D57-E57 -> 0
A58: 24 | B58: Тўланиши лозим бўлган ҳисобланган фоизлар | C58: =+'Bank Liabilities Analysis'!S38+'Bank Liabilities Analysis'!S39+'Bank Liabilities Analysis'!S40 -> 255861805 | D58: =+'Bank Liabilities Analysis'!T38+'Bank Liabilities Analysis'!T39+'Bank Liabilities Analysis'!T40 -> 162963281 | E58: =+'Bank Liabilities Analysis'!U38+'Bank Liabilities Analysis'!U39+'Bank Liabilities Analysis'!U40 -> 92898524 | J58: =+C58-D58-E58 -> 0
A59: 25 | B59: Ҳисобланган солиқлар бўйича мажбуриятлар | C59: =+D59+E59 -> 31523799 | D59: 31523799 | E59: 0 | J59: =+C59-D59-E59 -> 0
A60: 26 | B60: Клиринг транзакциялари | C60: =+'Bank Liabilities Analysis'!S37 -> 12445613 | D60: =+'Bank Liabilities Analysis'!T37 -> 12445613 | E60: =+'Bank Liabilities Analysis'!U37 -> 0 | J60: =+C60-D60-E60 -> 0
A61: 27 | B61: Стандарт деб таснифланган балансдан ташқари моддаларга яратилган захиралар | C61: =+D61+E61 -> 0 | D61: 0 | E61: 0 | J61: =+C61-D61-E61 -> 0
A62: 28 | B62: Бошқа мажбуриятлар | C62: =+D62+E62 -> 131281683 | D62: 101607163 | E62: 29674520 | J62: =+C62-D62-E62 -> 0
A63: 29 | B63: Жами мажбуриятлар | C63: =+D63+E63 -> 24989576234 | D63: =SUM(D50:D62) -> 17139698098 | E63: =SUM(E50:E62) -> 7849878136 | F63: =+'Bank Liabilities Analysis'!S42 -> 24989576234 | G63: =+'Bank Liabilities Analysis'!T42 -> 17139698098 | H63: =+'Bank Liabilities Analysis'!U42 -> 7849878136 | J63: =+C63-D63-E63 -> 0
B65: ХУСУСИЙ КАПИТАЛ
A67: 30 | B67: Устав капитали | C67: =+C68+C69 -> 7145336800 | D67: =+D68+D69 -> 7145336800 | E67: =+E68+E69 -> 0 | J67: =+C67-D67-E67 -> 0
A68: 30.1 | B68: Aкциялар – оддий | C68: =+D68+E68 -> 7145161149 | D68: 7145161149 | E68: 0 | J68: =+C68-D68-E68 -> 0
A69: 30.2 | B69: Aкциялар – имтиёзли | C69: =+D69+E69 -> 175651 | D69: 175651 | E69: 0 | J69: =+C69-D69-E69 -> 0
A70: 31 | B70: Қўшилган капитал | C70: =+D70+E70 -> 0 | D70: 0 | E70: 0 | J70: =+C70-D70-E70 -> 0
A71: 32 | B71: Захира капитали | C71: =+C72+C73+C74 -> 32499244 | D71: =+D72+D73+D74 -> 32499244 | E71: =+E72+E73+E74 -> 0 | J71: =+C71-D71-E71 -> 0
A72: 32.1 | B72: Умумий захира фонди | C72: =+D72+E72 -> 27827555 | D72: 27827555 | E72: 0 | J72: =+C72-D72-E72 -> 0
A73: 32.2 | B73: Девальвация учун захира | C73: =+D73+E73 -> 0 | D73: 0 | E73: 0 | J73: =+C73-D73-E73 -> 0
A74: 32.3 | B74: Бошқа захира фондлари | C74: =+D74+E74 -> 4671689 | D74: 4671689 | E74: 0 | J74: =+C74-D74-E74 -> 0
A75: 33 | B75: Тақсимланмаган фойда | C75: =+D75+E75 -> -1438625098 | D75: -1438625098 | E75: 0 | J75: =+C75-D75-E75 -> 0
A76: 33.1 | B76: шундан, жорий йил соф фойдаси (зарари) | C76: =+D76+E76 -> 160802633 | D76: 160802633 | E76: 0 | J76: =+C76-D76-E76 -> 0
A77: 34 | B77: Жами хусусий капитал | C77: =+C67+C70+C71+C75 -> 5739210946 | D77: =+D67+D70+D71+D75 -> 5739210946 | E77: =+E67+E70+E71+E75 -> 0 | J77: =+C77-D77-E77 -> 0
A78: 35 | B78: Жами мажбуриятлар ва хусусий капитал | C78: =+D78+E78 -> 30728787180 | D78: =+D63+D77 -> 22878909044 | E78: =+E63+E77 -> 7849878136 | J78: =+C78-D78-E78 -> 0
B80: Бошқарув Раис имзоси:
B82: Бош бухгалтер имзоси:
C86: =+C47-C78 -> 0

Sheet Liquidity Analysis
A1: ЛИКВИДЛИЛИК ТАҲЛИЛИ | E1: 16-жадвал
B2: =Balance!B3 -> "MKBANK" | D2: =+Balance!D3 -> 46021 | E2: минг сўмда
A3: № | B3: Ликвид активлар | C3: Жами | D3: Миллий валютада | E3: Хорижий валютада
B4: 1-қисм. Юқори ликвидли активлар | C4: фоизда
A5: 1.1 | B5: Кассадаги нақд пул ва бошқа тўлов ҳужжатлари | C5: =+'Bank Assets Analysis'!S6 -> 703550546 | D5: =+'Bank Assets Analysis'!T6 -> 538991500 | E5: =+'Bank Assets Analysis'!U6 -> 164559046
A6: 1.2 | B6: Банкнинг Марказий банкдаги маблағлар (мажбурий захираларсиз) | C6: =+'Bank Assets Analysis'!S7 -> 584034134 | D6: =+'Bank Assets Analysis'!T7 -> 584034134 | E6: =+'Bank Assets Analysis'!U7 -> 0
A7: 1.3 | B7: Ўзбекистон Республикаси Ҳукумати ва Марказий банки томонидан чиқарилган қимматли қоғозлар | C7: =+'Bank Assets Analysis'!S19 -> 508169320 | D7: =+'Bank Assets Analysis'!T19 -> 508169320 | E7: =+'Bank Assets Analysis'!U19 -> 0
A8: 1.4 | B8: Инвестиция даражасидан паст бўлмаган рейтингга эга хорижий банкларда ва кредит рейтингига эга маҳаллий банкларда очилган вакиллик ҳисобварақларидаги маблағлар | C8: =+E8 -> 1986921643 | E8: =+'Bank Assets Analysis'!D10+'Bank Assets Analysis'!D11 -> 1986921643
A9: 1.5 | B9: Инвестиция даражасидан паст бўлмаган рейтингга эга бўлган мамлакатлардаги банкларда чет-эл валютасида овернайт шарти асосида жойлаштирилган депозитлар | C9: =+E9 -> 0 | E9: =+'Bank Assets Analysis'!F13 -> 0
A10: 1.6 | B10: ХВФ, Жаҳон банки гуруҳи, Осиё тараққиёт банки, Осиё инфратузилма ва инвестиция банки, ЕТTБ, Европа инвестиция банки, Европа инвестиция жамғармаси, Ислом тараққиёт банки ва Европа Кенгашининг тараққиёт банки томонидан чиқарилган қимматли қоғозлар | C10: =+'Bank Assets Analysis'!S21 -> 0 | D10: =+'Bank Assets Analysis'!T21 -> 0 | E10: =+'Bank Assets Analysis'!U21 -> 0
A11: 1.7 | B11: Таваккалчилик даражаси паст бўлган мамлакатлар ҳукуматлари ва Марказий банклари томонидан чиқарилган қимматли қоғозлар | C11: =+'Bank Assets Analysis'!S20 -> 0 | D11: =+'Bank Assets Analysis'!T20 -> 0 | E11: =+'Bank Assets Analysis'!U20 -> 0
A12: 1.8 | B12: Қайтариб олинмайдиган кредит линиялари (ўзлаштирилмаган қисми) | C12: =+D12 -> 0 | D12: 0 | G12: Мазкур қатор ЎзР. Марказий банки билан тегишли кредит шартнома тузилганда тўлдириши керак. Ҳисобот даврига банкнинг нетто активларининг 2 % акс эттирилади.
A13: 1.9 | B13: Ипотекани қайта молиялаштириш ташкилотлари томонидан чиқарилган корпоратив облигациялар ва таъминланган қарз муносабатларини тасдиқловчи бошқа қимматли қоғозлар | C13: =+'Bank Assets Analysis'!S24+('Bank Assets Analysis'!S23*0.8) -> 8000000 | D13: =+'Bank Assets Analysis'!T24+('Bank Assets Analysis'!T23*0.8) -> 8000000 | E13: =+'Bank Assets Analysis'!U24+('Bank Assets Analysis'!U23*0.8) -> 0
A14: 1.10 | B14: РЕПО битимлари бўйича сотиб олинган юқори ликвидли қимматли қоғозлар | C14: =+'Bank Assets Analysis'!S35 -> 0 | D14: =+'Bank Assets Analysis'!T35 -> 0 | E14: =+'Bank Assets Analysis'!U35 -> 0
A15: 1.11 | B15: Гаровга қўйилган юқори ликвидли активлар | C15: =+'Bank Assets Analysis'!S18+'Bank Assets Analysis'!S46 -> 0 | D15: =+'Bank Assets Analysis'!T18+'Bank Assets Analysis'!T46 -> 0 | E15: =+'Bank Assets Analysis'!U18+'Bank Assets Analysis'!U46 -> 0
A16: 1.12 | B16: Жами юқори ликвидли активлар | C16: =SUM(C5:C14)-'Bank Liabilities Analysis'!S22-'Bank Liabilities Analysis'!T25-C15 -> 3790233108 | D16: =SUM(D5:D14)-'Bank Liabilities Analysis'!T22-'Bank Liabilities Analysis'!T25-D15 -> 1638752419 | E16: =SUM(E5:E14)-'Bank Liabilities Analysis'!U22-E15 -> 2151480689
B17: 2-қисм. Иқтисодий меъёрлар - Ликвидлилик
A18: 2.1 | B18: Юқори ликвидли активларнинг жами активларга нисбати | C18: =IFERROR((+C19/C20),0) -> 0.1233447 | D18: =IFERROR((+D19/D20),0) -> 0.071655921 | E18: =IFERROR((+E19/E20),0) -> 0.27375853
A19: 2.1.1 | B19: Юқори ликвидли активлар | C19: =+C16 -> 3790233108 | D19: =+D16 -> 1638752419 | E19: =+E16 -> 2151480689
A20: 2.1.2 | B20: Жами активлар (РЕПО битимлари айрилган ҳолда) | C20: =Balance!C47-'Bank Liabilities Analysis'!S34 -> 30728787180 | D20: =Balance!D47-'Bank Liabilities Analysis'!T34 -> 22869741752 | E20: =Balance!E47-'Bank Liabilities Analysis'!U34 -> 7859045428
A21: 2.2 | B21: Юқори ликвидли активларнинг қисқа муддатли мажбуриятларга нисбати | C21: =IFERROR((+C22/C23),0) -> 0.30763614 | D21: =IFERROR((+D22/D23),0) -> 0.20981303 | E21: =IFERROR((+E22/E23),0) -> 0.47704989
A22: 2.2.1 | B22: Юқори ликвидли активлар | C22: =+C16 -> 3790233108 | D22: =+D16 -> 1638752419 | E22: =+E16 -> 2151480689
A23: 2.2.2 | B23: Қисқа муддатли мажбуриятлар (РЕПО битимлари айрилган ҳолда) | C23: =+'Bank Liabilities Analysis'!C42+'Bank Liabilities Analysis'!E42+'Bank Liabilities Analysis'!G42+'Bank Liabilities Analysis'!I42+'Bank Liabilities Analysis'!K42+'Bank Liabilities Analysis'!M42-'Bank Liabilities Analysis'!C34-'Bank Liabilities Analysis'!E34-'Bank Liabilities Analysis'!G34-'Bank Liabilities Analysis'!I34-'Bank Liabilities Analysis'!K34-'Bank Liabilities Analysis'!M34 -> 12320506818 | D23: =+C23-E23 -> 7810536784 | E23: =+'Bank Liabilities Analysis'!D42+'Bank Liabilities Analysis'!F42+'Bank Liabilities Analysis'!H42+'Bank Liabilities Analysis'!J42+'Bank Liabilities Analysis'!L42+'Bank Liabilities Analysis'!N42-'Bank Liabilities Analysis'!D34-'Bank Liabilities Analysis'!F34-'Bank Liabilities Analysis'!H34-'Bank Liabilities Analysis'!J34-'Bank Liabilities Analysis'!L34-'Bank Liabilities Analysis'!N34 -> 4509970034
A24: 2.3 | B24: Ликвидлиликни қоплаш меъёри коэффициенти | C24: =IFERROR((+C25/C26),0) -> 2.3192898 | D24: =IFERROR((+D25/D26),0) -> 1.175669 | E24: =IFERROR((+E25/E26),0) -> 8.9521132
A25: 2.3.1 | B25: Юқори ликвидли активлар | C25: =+C16 -> 3790233108 | D25: =+D16 -> 1638752419 | E25: =+E16 -> 2151480689
A26: 2.3.2 | B26: Кейинги 30 кун ичида соф чиқим | C26: =+D26+E26 -> 1.6342214e+09 | D26: =+'Bank Assets Analysis (нац)'!P61 -> 1.3938893e+09 | E26: =+'Bank Assets Analysis'!Z65 -> 2.4033216e+08
B27: 30 кунлик чиқим суммаси | C27: =+D27+E27 -> 2.8484712e+09 | D27: =+'Bank Assets Analysis (нац)'!P63 -> 1.8871426e+09 | E27: =+'Bank Assets Analysis'!Z67 -> 9.6132864e+08
B28: 30 кунлик кирим суммаси | C28: =+D28+E28 -> 1.2142498e+09 | D28: =+'Bank Assets Analysis (нац)'!P65 -> 4.9325333e+08 | E28: =+'Bank Assets Analysis'!Z70 -> 7.2099648e+08
A29: 2.4 | B29: Соф барқарор молиялаштириш меъёри | C29: =IFERROR((C30/C35),0) -> 1.1303173 | D29: =IFERROR((D30/D35),0) -> 1.0960871 | E29: =IFERROR((E30/E35),0) -> 1.2784471
A30: 2.5 | B30: Барқарор молиялаштиришнинг мавжуд суммаси | C30: =SUM(C31:C34) -> 2.2104432e+10 | D30: =SUM(D31:D34) -> 1.7411533e+10 | E30: =SUM(E31:E34) -> 4.6928991e+09
A31: 2.5.1 | B31: Хусусий капитал | C31: =Balance!C77 -> 5739210946 | D31: =Balance!D77 -> 5739210946 | E31: =Balance!E77 -> 0
A32: 2.5.2 | B32: Бир йилдан ортиқ муддатли мажбуриятлар | C32: ='Bank Liabilities Analysis'!O42+'Bank Liabilities Analysis'!Q42 -> 12669069416 | D32: =+'Bank Liabilities Analysis (нац)'!I43+'Bank Liabilities Analysis (нац)'!J43 -> 9329161314 | E32: ='Bank Liabilities Analysis'!P42+'Bank Liabilities Analysis'!R42 -> 3339908102
A33: 2.5.3 | B33: Бошқа муддатсиз мажбуриятларнинг 30 фоизи | C33: =+('Bank Liabilities Analysis'!C42)*0.3 -> 3.3437018e+08 | D33: =+('Bank Liabilities Analysis (нац)'!C43)*0.3 -> 3.064686e+08 | E33: =+('Bank Liabilities Analysis'!D42)*0.3 -> 27901574
A34: 2.5.4 | B34: Бир йилдан кам муддатли жами мажбуриятларнинг 30 фоизи | C34: =+('Bank Liabilities Analysis'!E42+'Bank Liabilities Analysis'!G42+'Bank Liabilities Analysis'!I42+'Bank Liabilities Analysis'!K42+'Bank Liabilities Analysis'!M42)*0.3 -> 3.3617819e+09 | D34: =+('Bank Liabilities Analysis (нац)'!D43+'Bank Liabilities Analysis (нац)'!E43+'Bank Liabilities Analysis (нац)'!F43+'Bank Liabilities Analysis (нац)'!G43+'Bank Liabilities Analysis (нац)'!H43)*0.3 -> 2.0366924e+09 | E34: =+('Bank Liabilities Analysis'!F42+'Bank Liabilities Analysis'!H42+'Bank Liabilities Analysis'!J42+'Bank Liabilities Analysis'!L42+'Bank Liabilities Analysis'!N42)*0.3 -> 1.3250894e+09
A35: 2.6 | B35: Барқарор молиялаштиришнинг зарур суммаси | C35: =SUM(C36:C41) -> 1.9555954e+10 | D35: =SUM(D36:D41) -> 1.5885173e+10 | E35: =SUM(E36:E41) -> 3.6707809e+09
A36: 2.6.1 | B36: Бир йилдан ортиқ муддатли активлар | C36: =+'Bank Assets Analysis'!O47-'Bank Assets Analysis'!O37+'Bank Assets Analysis'!Q47-'Bank Assets Analysis'!Q37-'Bank Assets Analysis'!O19-'Bank Assets Analysis'!Q19 -> 13930610361 | D36: =+C36-E36 -> 11708376444 | E36: =+'Bank Assets Analysis'!P47-'Bank Assets Analysis'!P40-'Bank Assets Analysis'!P37+'Bank Assets Analysis'!R47-'Bank Assets Analysis'!R40-'Bank Assets Analysis'!R37-'Bank Assets Analysis'!P19-'Bank Assets Analysis'!R19 -> 2222233917
A37: 2.6.2 | B37: Қайтариш муддати бир йилдан ортиқ бўлган номолиявий активлар (ер участкалари, бинолар, мебель, компьютерлар ва автомашиналар) | C37: =+'Bank Assets Analysis'!O37+'Bank Assets Analysis'!Q37 -> 903999652 | D37: =+C37-E37 -> 903999652 | E37: =+'Bank Assets Analysis'!P37+'Bank Assets Analysis'!R37 -> 0
A38: 2.6.3 | B38: Суд жараёнида бўлган ёки белгиланган тартибда ундирилмаган кредит ва лизинглар, соф | C38: =+'Bank Assets Analysis'!C28+'Bank Assets Analysis'!C29+'Bank Assets Analysis'!C30+'Bank Assets Analysis'!C32 -> 890363230 | D38: =+'Bank Assets Analysis (нац)'!C28+'Bank Assets Analysis (нац)'!C29+'Bank Assets Analysis (нац)'!C30+'Bank Assets Analysis (нац)'!C32 -> 614668269 | E38: =+'Bank Assets Analysis'!D28+'Bank Assets Analysis'!D29+'Bank Assets Analysis'!D30+'Bank Assets Analysis'!D32 -> 275694961
A39: 2.6.4 | B39: Суд жараёнида бўлган ёки белгиланган тартибда ундирилмаган активлар, соф (2.6.3-қаторда кўрсатилмаган қисми) | C39: =+D39+E39 -> 0 | D39: 0 | E39: 0
A40: 2.6.5 | B40: Қайтариш муддати 1 йилдан кам бўлган бошқа активлар суммасининг 30 фоизи (қайтариш муддати 1 йилдан кам бўлган ёки муддатсиз ликвидли активлар бундан мустасно) | C40: =((+'Bank Assets Analysis'!S47-'Bank Assets Analysis'!O47-'Bank Assets Analysis'!Q47-'Liquidity Analysis'!C60)*0.3) -> 3.5113335e+09 | D40: =+C40-E40 -> 2.5818037e+09 | E40: =((+'Bank Assets Analysis'!U47-'Bank Assets Analysis'!P47-'Bank Assets Analysis'!R47-'Liquidity Analysis'!E60)*0.3) -> 9.2952987e+08
A41: 2.6.6 | B41: Балансдан ташқари активларнинг 15 фоизи | C41: =+ROUND(SUM(Commitments!C4-Commitments!C5+Commitments!C7-Commitments!C8+Commitments!C10-'Bank Liabilities Analysis'!S18)*15%,0) -> 319646898 | D41: =+ROUND(SUM(Commitments!D4-Commitments!D5+Commitments!D7-Commitments!D8+Commitments!D10-'Bank Liabilities Analysis'!T18)*15%,0) -> 76324762 | E41: =+ROUND(SUM(Commitments!E4-Commitments!E5+Commitments!E7-Commitments!E8+Commitments!E10-'Bank Liabilities Analysis'!U18)*15%,0) -> 243322136
B43: Бошқарув Раис имзоси:
B45: Бош бухгалтер имзоси:
A50: № | B50: Ликвидли активлар | C50: Жами | D50: Миллий валютада | E50: Хорижий валютада
A51: 1. | B51: Кассадаги нақд пул ва бошқа тўлов ҳужжатлари ва қимматбаҳо металлар | C51: =+'Bank Assets Analysis'!S6+'Investment Securities'!B39 -> 703550721 | D51: =+'Bank Assets Analysis'!T6+'Investment Securities'!C39 -> 538991675 | E51: =+'Bank Assets Analysis'!U6+'Investment Securities'!D39 -> 164559046
A52: 2. | B52: Банкнинг Марказий банкдаги маблағлар | C52: =+'Bank Assets Analysis'!S7+'Bank Assets Analysis'!S8 -> 584034134 | D52: =+'Bank Assets Analysis'!T7+'Bank Assets Analysis'!T8 -> 584034134 | E52: =+'Bank Assets Analysis'!U7+'Bank Assets Analysis'!U8 -> 0
A53: 3. | B53: Бошқа банклар ва молиявий ташкилотлардан олиниши лозим бўлган маблағлар | C53: ='Bank Assets Analysis'!C10+'Bank Assets Analysis'!C11+'Bank Assets Analysis'!C12+'Bank Assets Analysis'!C15+'Bank Assets Analysis'!C16+'Bank Assets Analysis'!E16+'Bank Assets Analysis'!G16 -> 1998666149 | D53: =+C53-E53 -> 10418050 | E53: ='Bank Assets Analysis'!D10+'Bank Assets Analysis'!D11+'Bank Assets Analysis'!D15+'Bank Assets Analysis'!D16+'Bank Assets Analysis'!F16+'Bank Assets Analysis'!H16 -> 1988248099
A54: 3.1. | B54: Бошқа банклар ва молиявий ташкилотлардан олиниши лозим бўлган маблағлар - соф депозитлар | C54: =IF(F54>0,F54,0) -> 385311765 | D54: =IF(G54>0,G54,0) -> 0 | E54: =IF(H54>0,H54,0) -> 385571470 | F54: =(('Bank Assets Analysis'!E10+'Bank Assets Analysis'!E12+'Bank Assets Analysis'!G10+'Bank Assets Analysis'!C14+'Bank Assets Analysis'!E14+'Bank Assets Analysis'!G14)-'Bank Liabilities Analysis'!C26-'Bank Liabilities Analysis'!E26-'Bank Liabilities Analysis'!G26) -> 385311765 | G54: =+('Bank Assets Analysis'!E10-'Bank Assets Analysis'!F10+'Bank Assets Analysis'!G10-'Bank Assets Analysis'!H10+'Bank Assets Analysis'!E12-'Bank Assets Analysis'!F12+'Bank Assets Analysis'!C14-'Bank Assets Analysis'!D14+'Bank Assets Analysis'!E14-'Bank Assets Analysis'!F14+'Bank Assets Analysis'!G14-'Bank Assets Analysis'!H14)-('Bank Liabilities Analysis'!C26-'Bank Liabilities Analysis'!D26+'Bank Liabilities Analysis'!E26-'Bank Liabilities Analysis'!F26+'Bank Liabilities Analysis'!G26-'Bank Liabilities Analysis'!H26) -> -259705 | H54: =(('Bank Assets Analysis'!F10+'Bank Assets Analysis'!F12+'Bank Assets Analysis'!H10+'Bank Assets Analysis'!D14+'Bank Assets Analysis'!F14+'Bank Assets Analysis'!H14)-'Bank Liabilities Analysis'!D26-'Bank Liabilities Analysis'!F26-'Bank Liabilities Analysis'!H26) -> 385571470
A55: 4. | B55: Ўзбекистон Республикаси Ҳукумати ва Марказий банк тамонидан чиқарилган қимматли қоғозлар (векселлар, облигациялар ва бошқа қимматли қоғозлар) | C55: =+'Bank Assets Analysis'!C19+'Bank Assets Analysis'!E19+'Bank Assets Analysis'!G19+'Bank Assets Analysis'!I19+'Bank Assets Analysis'!K19+'Bank Assets Analysis'!M19 -> 508169320 | D55: =+C55-E55 -> 508169320 | E55: =+'Bank Assets Analysis'!D19+'Bank Assets Analysis'!F19+'Bank Assets Analysis'!H19+'Bank Assets Analysis'!J19+'Bank Assets Analysis'!L19+'Bank Assets Analysis'!N19 -> 0
A56: 5. | B56: Таваккалчилик даражаси паст бўлган мамлакатлар томонидан чиқарилган қимматли қоғозлар
A57: 6. | B57: Бошқа осон сотиладиган қимматли қоғозлар
A58: 7. | B58: =+'Bank Assets Analysis'!B23 -> Ипотекани қайта молиялаштириш ташкилотлари томонидан чиқарилган корпоратив облигациялар | C58: =+'Bank Assets Analysis'!C23+'Bank Assets Analysis'!E23+'Bank Assets Analysis'!G23+'Bank Assets Analysis'!I23+'Bank Assets Analysis'!K23+'Bank Assets Analysis'!M23 -> 10000000 | D58: =+C58-E58 -> 10000000 | E58: =+'Bank Assets Analysis'!D23+'Bank Assets Analysis'!F23+'Bank Assets Analysis'!H23+'Bank Assets Analysis'!J23+'Bank Assets Analysis'!L23+'Bank Assets Analysis'!N23 -> 0
A59: 8. | B59: =+'Bank Assets Analysis'!B24 -> Ипотекани қайта молиялаштириш ташкилотлари томонидан чиқарилган таъминланган қарз муносабатларини тасдиқловчи бошқа қимматли қоғозлар | C59: =+'Bank Assets Analysis'!C24+'Bank Assets Analysis'!E24+'Bank Assets Analysis'!G24+'Bank Assets Analysis'!I24+'Bank Assets Analysis'!K24+'Bank Assets Analysis'!M24 -> 0 | D59: =+C59-E59 -> 0 | E59: =+'Bank Assets Analysis'!D24+'Bank Assets Analysis'!F24+'Bank Assets Analysis'!H24+'Bank Assets Analysis'!J24+'Bank Assets Analysis'!L24+'Bank Assets Analysis'!N24 -> 0
A60: 7. | B60: Жами ликвид активлар | C60: =SUM(C51:C59) -> 4189732089 | D60: =SUM(D51:D59) -> 1651613179 | E60: =SUM(E51:E59) -> 2538378615

Sheet Bank Assets Analysis
A1: БАНК АКТИВЛАРИ ТАҲЛИЛИ | X1: 17-жадвал
B2: =Balance!B3 -> "MKBANK" | X2: =+Balance!D3 -> 46021 | Z2: минг сўмда
A3: № | B3: Кўрсаткичлар | C3: Сўндириш муддати (кунларда) | S3: Жами | T3: шундан, | V3: Ликвидлиликни қоплаш меёри ҳисоб китоби
C4: Муддатсиз | E4: 1 дан 7 гача | G4: 8 дан 30 гача | I4: 31 дан 90 гача | K4: 91 дан 180 гача | M4: 181 дан 365 гача | O4: 366 дан 730 гача | Q4: 2 йилдан ортиқ
C5: Сумма | D5: шундан, хорижий валютада (сўм экв.) | E5: Сумма | F5: шундан, хорижий валютада (сўм экв.) | G5: Сумма | H5: шундан, хорижий валютада (сўм экв.) | I5: Сумма | J5: шундан, хорижий валютада (сўм экв.) | K5: Сумма | L5: шундан, хорижий валютада (сўм экв.) | M5: Сумма | N5: шундан, хорижий валютада (сўм экв.) | O5: Сумма | P5: шундан, хорижий валютада (сўм экв.) | Q5: Сумма | R5: шундан, хорижий валютада (сўм экв.) | T5: миллий валютада | U5: хорижий валютада (сўм экв.) | V5: Коэффициент | W5: Активлар | X5: Юқори ликвидли активлар/кирим | Y5: Активлар (хорижий валютада) | Z5: Юқори ликвидли активлар/кирим (хорижий валютада)
A6: 1 | B6: Кассадаги нақд пул ва бошқа тўлов ҳужжатлари | C6: 703550546 | D6: 164559046 | E6: 0 | F6: 0 | G6: 0 | H6: 0 | I6: 0 | J6: 0 | K6: 0 | L6: 0 | M6: 0 | N6: 0 | O6: 0 | P6: 0 | Q6: 0 | R6: 0 | S6: =+C6+E6+G6+I6+K6+M6+O6+Q6 -> 703550546 | T6: =+S6-U6 -> 538991500 | U6: =+D6+F6+H6+J6+L6+N6+P6+R6 -> 164559046 | V6: 1 | W6: =+S6 -> 703550546 | X6: =+W6*V6 -> 703550546 | Y6: =+U6 -> 164559046 | Z6: =+Y6*V6 -> 164559046
A7: 2 | B7: Банкнинг Марказий банкдаги маблағлари (мажбурий захирасиз) | C7: 324034134 | D7: 0 | E7: 260000000 | F7: 0 | G7: 0 | H7: 0 | I7: 0 | J7: 0 | K7: 0 | L7: 0 | M7: 0 | N7: 0 | O7: 0 | P7: 0 | Q7: 0 | R7: 0 | S7: =+C7+E7+G7+I7+K7+M7+O7+Q7 -> 584034134 | T7: =+S7-U7 -> 584034134 | U7: =+D7+F7+H7+J7+L7+N7+P7+R7 -> 0 | V7: 1 | W7: =S7 -> 584034134 | X7: =+W7*V7 -> 584034134 | Y7: =+U7 -> 0 | Z7: =+Y7*V7 -> 0
A8: 2.1 | B8: Банкнинг Марказий банкдаги мажбурий захира ҳисобварағидаги маблағлар | C8: 0 | D8: 0 | E8: 0 | F8: 0 | G8: 0 | H8: 0 | I8: 0 | J8: 0 | K8: 0 | L8: 0 | M8: 0 | N8: 0 | O8: 0 | P8: 0 | Q8: 0 | R8: 0 | S8: =+C8+E8+G8+I8+K8+M8+O8+Q8 -> 0 | T8: =+S8-U8 -> 0 | U8: =+D8+F8+H8+J8+L8+N8+P8+R8 -> 0 | V8: 0
A9: 3 | B9: Бошқа банклар ва молиявий ташкилотлардан олиниши лозим бўлган маблағлар | C9: =SUM(C10:C16)-C13 -> 2008145194 | D9: =SUM(D10:D16)-D13 -> 1997011849 | E9: =SUM(E10:E16)-E13 -> 348734570 | F9: =SUM(F10:F16)-F13 -> 348734570 | G9: =SUM(G10:G16)-G13 -> 242131600 | H9: =SUM(H10:H16)-H13 -> 240506600 | I9: =SUM(I10:I16)-I13 -> 650385753 | J9: =SUM(J10:J16)-J13 -> 649969087 | ... R9: =SUM(R10:R16)-R13 -> 0 | S9: =+C9+E9+G9+I9+K9+M9+O9+Q9 -> 3466881057 | T9: =+S9-U9 -> 61516243 | U9: =+D9+F9+H9+J9+L9+N9+P9+R9 -> 3405364814
A10: 3.1 | B10: Таваккалчилик даражаси паст банклардаги вакиллик ҳисобварақлари (ностро) | C10: 1408974684 | D10: 1408974684 | S10: =+C10+E10+G10+I10+K10+M10+O10+Q10 -> 1408974684 | T10: =+S10-U10 -> 0 | U10: =+D10+F10+H10+J10+L10+N10+P10+R10 -> 1408974684 | V10: 1 | W10: =+C10 -> 1408974684 | X10: =+W10*V10 -> 1408974684 | Y10: =+D10 -> 1408974684 | Z10: =+Y10*V10 -> 1408974684
A11: 3.2 | B11: Маҳаллий банклардаги вакиллик ҳисобварақлари (ностро) | C11: 577946964 | D11: 577946959 | S11: =+C11 -> 577946964 | T11: =+S11-U11 -> 5 | U11: =+D11 -> 577946959 | V11: 1 | W11: =+C11 -> 577946964 | X11: =+W11*V11 -> 577946964 | Y11: =+D11 -> 577946959 | Z11: =+Y11*V11 -> 577946959
A12: 3.3 | B12: Овернайт шарти билан жойлаштирилган депозитлар | E12: 0 | F12: 0 | S12: =+E12 -> 0 | T12: =+S12-U12 -> 0 | U12: =+F12 -> 0 | V12: 1 | W12: =+E12-E13 -> 0 | X12: =+W12*V12 -> 0 | Y12: =+F12-F13 -> 0 | Z12: =+Y12*V12 -> 0
A13: 3.3.1. | B13: шундан, инвестицион даражадан паст бўлмаган рейтингга эга банкларга овернайт шарти билан жойлаштирилган хорижий валютадаги депозитлар | E13: 0 | F13: 0 | S13: =+E13 -> 0 | T13: =+S13-U13 -> 0 | U13: =+F13 -> 0 | V13: 1 | W13: =+F13 -> 0 | X13: =+W13*V13 -> 0 | Y13: =+F13 -> 0 | Z13: =+Y13*V13 -> 0
A14: 3.4 | B14: Банкнинг бошқа банклар/молиявий ташкилотлардаги ҳисобварақлари | C14: 9479045 | D14: 8763750 | E14: 348734570 | F14: 348734570 | G14: 242131600 | H14: 240506600 | I14: 650385753 | J14: 649969087 | K14: 76413948 | L14: 71911473 | M14: 48006858 | N14: 39683589 | O14: 66323123 | P14: 57547646 | Q14: 26740011 | R14: 0 | S14: =+C14+E14+G14+I14+K14+M14+O14+Q14 -> 1468214908 | T14: =+S14-U14 -> 51098193 | U14: =+D14+F14+H14+J14+L14+N14+P14+R14 -> 1417116715 | V14: 1 | W14: =+C14+E14+G14+E10+G10+E11+G11 -> 600345215 | X14: =+W14*V14 -> 600345215 | Y14: =+D14+F14+H14+F10+H10+F11+H11 -> 598004920 | Z14: =+Y14*V14 -> 598004920
A15: 3.5 | B15: Пластик карталардан амалга оширилган тўловлар бўйича бошқа банклардан олиниши лозим бўлган маблағлар | C15: 11744501 | D15: 1326456 | E15: 0 | F15: 0 | G15: 0 | H15: 0 | I15: 0 | J15: 0 | K15: 0 | L15: 0 | M15: 0 | N15: 0 | O15: 0 | P15: 0 | Q15: 0 | R15: 0 | S15: =+C15+E15+G15+I15+K15+M15+O15+Q15 -> 11744501 | T15: =+S15-U15 -> 10418045 | U15: =+D15+F15+H15+J15+L15+N15+P15+R15 -> 1326456 | V15: 1 | W15: =+C15+E15+G15 -> 11744501 | X15: =+W15*V15 -> 11744501 | Y15: =+D15+F15+H15 -> 1326456 | Z15: =+Y15*V15 -> 1326456
A16: 3.6 | B16: Бошқа моддалар | C16: 0 | D16: 0 | S16: =+C16+E16+G16+I16+K16+M16+O16+Q16 -> 0 | T16: =+S16-U16 -> 0 | U16: =+D16+F16+H16+J16+L16+N16+P16+R16 -> 0 | V16: 1 | W16: =+C16+E16+G16 -> 0 | X16: =+W16*V16 -> 0 | Y16: =+D16+F16+H16 -> 0 | Z16: =+Y16*V16 -> 0
A17: 4 | B17: Қимматли қоғозлар ва уларга қилинган инвестициялар, соф | C17: =SUM(C19:C25) -> 175 | D17: =SUM(D19:D25) -> 0 | E17: =SUM(E19:E25) -> 399999665 | F17: =SUM(F19:F25) -> 0 | G17: =SUM(G19:G25) -> 0 | H17: =SUM(H19:H25) -> 0 | I17: =SUM(I19:I25) -> 0 | J17: =SUM(J19:J25) -> 0 | ... R17: =SUM(R19:R25) -> 0 | S17: =+C17+E17+G17+I17+K17+M17+O17+Q17 -> 518169495 | T17: =+S17-U17 -> 518169495 | U17: =+D17+F17+H17+J17+L17+N17+P17+R17 -> 0
A18: 4a | B18: шу жумладан, таъминот остидаги юқори ликвидли қимматли қоғозлар | C18: =+'Bank Liabilities Analysis'!C34 -> 0 | D18: =+'Bank Liabilities Analysis'!D34 -> 0 | E18: =+'Bank Liabilities Analysis'!E34 -> 0 | F18: =+'Bank Liabilities Analysis'!F34 -> 0 | G18: =+'Bank Liabilities Analysis'!G34 -> 0 | H18: =+'Bank Liabilities Analysis'!H34 -> 0 | I18: =+'Bank Liabilities Analysis'!I34 -> 0 | J18: =+'Bank Liabilities Analysis'!J34 -> 0 | ... R18: =+'Bank Liabilities Analysis'!R34 -> 0 | S18: =+C18+E18+G18+I18+K18+M18+O18+Q18 -> 0 | T18: =+S18-U18 -> 0 | U18: =+D18+F18+H18+J18+L18+N18+P18+R18 -> 0 | V18: 1 | W18: =+C18+E18+G18 -> 0 | X18: =+W18*V18 -> 0 | Y18: =+D18+F18+H18 -> 0 | Z18: =+Y18*V18 -> 0
A19: 4.1 | B19: Ўзбекистон Республикаси Ҳукумати ва Марказий банк томонидан чиқарилган қимматли қоғозлар (векселлар, облигациялар ва бошқа қарз қимматли қоғозлар) | C19: 0 | D19: 0 | E19: 399999665 | F19: 0 | G19: 0 | H19: 0 | I19: 0 | J19: 0 | K19: 54745360 | L19: 0 | M19: 53424295 | N19: 0 | O19: 0 | P19: 0 | Q19: 0 | R19: 0 | S19: =+C19+E19+G19+I19+K19+M19+O19+Q19 -> 508169320 | T19: =+S19-U19 -> 508169320 | U19: =+D19+F19+H19+J19+L19+N19+P19+R19 -> 0 | V19: 1 | W19: =+S19 -> 508169320 | X19: =+W19*V19 -> 508169320 | Y19: =+U19 -> 0 | Z19: =+Y19*V19 -> 0
A20: 4.2 | B20: Таваккалчилик даражаси паст бўлган мамлакатларнинг қимматли қоғозлари | C20: 0 | D20: 0 | E20: 0 | F20: 0 | G20: 0 | H20: 0 | I20: 0 | J20: 0 | K20: 0 | L20: 0 | M20: 0 | N20: 0 | O20: 0 | P20: 0 | Q20: 0 | R20: 0 | S20: =+C20+E20+G20+I20+K20+M20+O20+Q20 -> 0 | T20: =+S20-U20 -> 0 | U20: =+D20+F20+H20+J20+L20+N20+P20+R20 -> 0 | V20: 1 | W20: =+S20 -> 0 | X20: =+W20*V20 -> 0 | Y20: =+U20 -> 0 | Z20: =+Y20*V20 -> 0
A21: 4.3 | B21: ХВФ, Жаҳон банки гуруҳи, Осиё тараққиёт банки, Осиё инфраструктура инвестиция банки, ЕТТБ, Европа инвестиция банки, Европа инвестиция жамғармаси, Ислом тараққиёт банки ва Европа Кенгашининг тараққиёт банки томонидан чиқарилган қимматли қоғозлар | C21: 0 | D21: 0 | E21: 0 | F21: 0 | G21: 0 | H21: 0 | I21: 0 | J21: 0 | K21: 0 | L21: 0 | M21: 0 | N21: 0 | O21: 0 | P21: 0 | Q21: 0 | R21: 0 | S21: =+C21+E21+G21+I21+K21+M21+O21+Q21 -> 0 | T21: =+S21-U21 -> 0 | U21: =+D21+F21+H21+J21+L21+N21+P21+R21 -> 0 | V21: 1 | W21: =+S21 -> 0 | X21: =+W21*V21 -> 0 | Y21: =+U21 -> 0 | Z21: =+Y21*V21 -> 0
A22: 4.4 | B22: Таваккалчилик даражаси паст бўлган мамлакатларнинг етакчи компаниялари қимматли қоғозлари | C22: 0 | D22: 0 | E22: 0 | F22: 0 | G22: 0 | H22: 0 | I22: 0 | J22: 0 | K22: 0 | L22: 0 | M22: 0 | N22: 0 | O22: 0 | P22: 0 | Q22: 0 | R22: 0 | S22: =+C22+E22+G22+I22+K22+M22+O22+Q22 -> 0 | T22: =+S22-U22 -> 0 | U22: =+D22+F22+H22+J22+L22+N22+P22+R22 -> 0 | V22: 1 | W22: =+S22 -> 0 | X22: =+W22*V22 -> 0 | Y22: =+U22 -> 0 | Z22: =+Y22*V22 -> 0
A23: 4.5 | B23: Ипотекани қайта молиялаштириш ташкилотлари томонидан чиқарилган корпоратив облигациялар | C23: 0 | D23: 0 | E23: 0 | F23: 0 | G23: 0 | H23: 0 | I23: 0 | J23: 0 | K23: 0 | L23: 0 | M23: 10000000 | N23: 0 | O23: 0 | P23: 0 | Q23: 0 | R23: 0 | S23: =+C23+E23+G23+I23+K23+M23+O23+Q23 -> 10000000 | T23: =+S23-U23 -> 10000000 | U23: =+D23+F23+H23+J23+L23+N23+P23+R23 -> 0 | V23: 0.8 | W23: =+S23 -> 10000000 | X23: =+W23*V23 -> 8000000 | Y23: =+U23 -> 0 | Z23: =+Y23*V23 -> 0
A24: 4.6 | B24: Ипотекани қайта молиялаштириш ташкилотлари томонидан чиқарилган таъминланган қарз муносабатларини тасдиқловчи бошқа қимматли қоғозлар | C24: 0 | D24: 0 | E24: 0 | F24: 0 | G24: 0 | H24: 0 | I24: 0 | J24: 0 | K24: 0 | L24: 0 | M24: 0 | N24: 0 | O24: 0 | P24: 0 | Q24: 0 | R24: 0 | S24: =+C24+E24+G24+I24+K24+M24+O24+Q24 -> 0 | T24: =+S24-U24 -> 0 | U24: =+D24+F24+H24+J24+L24+N24+P24+R24 -> 0 | V24: 1 | W24: =+S24 -> 0 | X24: =+W24*V24 -> 0 | Y24: =+U24 -> 0 | Z24: =+Y24*V24 -> 0
A25: 4.7 | B25: Бошқалар | C25: 175 | D25: 0 | E25: 0 | F25: 0 | G25: 0 | H25: 0 | I25: 0 | J25: 0 | K25: 0 | L25: 0 | M25: 0 | N25: 0 | O25: 0 | P25: 0 | Q25: 0 | R25: 0 | S25: =+C25+E25+G25+I25+K25+M25+O25+Q25 -> 175 | T25: =+S25-U25 -> 175 | U25: =+D25+F25+H25+J25+L25+N25+P25+R25 -> 0 | V25: 1 | W25: =+C25+E25+G25 -> 175 | X25: =+W25*V25 -> 175 | Y25: =+D25+F25+H25 -> 0 | Z25: =+Y25*V25 -> 0
A26: 5 | B26: Мижозларнинг аккредитив ва траст ҳужжатлари билан кафолатланган тратталари бўйича мажбуриятлари, соф | C26: 38191497 | D26: 36791473 | E26: 0 | F26: 0 | G26: 0 | H26: 0 | I26: 0 | J26: 0 | K26: 0 | L26: 0 | M26: 0 | N26: 0 | O26: 0 | P26: 0 | Q26: 0 | R26: 0 | S26: =+C26+E26+G26+I26+K26+M26+O26+Q26 -> 38191497 | T26: =+S26-U26 -> 1400024 | U26: =+D26+F26+H26+J26+L26+N26+P26+R26 -> 36791473 | V26: 0.5 | W26: =+E26+G26 -> 0 | X26: =+W26*V26 -> 0 | Y26: =+F26+H26 -> 0 | Z26: =+Y26*V26 -> 0
A27: 6 | B27: Мижозларнинг банк олдидаги тўланмаган акцептлари бўйича мажбуриятлари, соф | C27: 0 | D27: 0 | E27: 0 | F27: 0 | G27: 0 | H27: 0 | I27: 0 | J27: 0 | K27: 0 | L27: 0 | M27: 0 | N27: 0 | O27: 0 | P27: 0 | Q27: 0 | R27: 0 | S27: =+C27+E27+G27+I27+K27+M27+O27+Q27 -> 0 | T27: =+S27-U27 -> 0 | U27: =+D27+F27+H27+J27+L27+N27+P27+R27 -> 0 | V27: 0.5 | W27: =+E27+G27 -> 0 | X27: =+W27*V27 -> 0 | Y27: =+F27+H27 -> 0 | Z27: =+Y27*V27 -> 0
A28: 7 | B28: Марказий банкка берилган кредит ва лизинглар, соф | C28: 0 | D28: 0 | E28: 0 | F28: 0 | G28: 0 | H28: 0 | I28: 0 | J28: 0 | K28: 0 | L28: 0 | M28: 0 | N28: 0 | O28: 0 | P28: 0 | Q28: 0 | R28: 0 | S28: =+C28+E28+G28+I28+K28+M28+O28+Q28 -> 0 | T28: =+S28-U28 -> 0 | U28: =+D28+F28+H28+J28+L28+N28+P28+R28 -> 0 | V28: 1 | W28: =+C28+E28+G28 -> 0 | X28: =+W28*V28 -> 0 | Y28: =+D28+F28+H28 -> 0 | Z28: =+Y28*V28 -> 0
A29: 8 | B29: Бошқа банкларга берилган кредит ва лизинглар, соф | C29: 0 | D29: 0 | E29: 0 | F29: 0 | G29: 0 | H29: 0 | I29: 0 | J29: 0 | K29: 0 | L29: 0 | M29: 0 | N29: 0 | O29: 0 | P29: 0 | Q29: 0 | R29: 0 | S29: =+C29+E29+G29+I29+K29+M29+O29+Q29 -> 0 | T29: =+S29-U29 -> 0 | U29: =+D29+F29+H29+J29+L29+N29+P29+R29 -> 0 | V29: 0.5 | W29: =+E29+G29 -> 0 | X29: =+W29*V29 -> 0 | Y29: =+F29+H29 -> 0 | Z29: =+Y29*V29 -> 0
A30: 9 | B30: Мижозларга берилган кредит ва лизинглар, соф | C30: 722399993 | D30: 156876272 | E30: 456014131 | F30: 174527449 | G30: 51922273 | H30: 27337825 | I30: 1251417781 | J30: 501695140 | K30: 1486202948 | L30: 202825015 | M30: 2510791502 | N30: 367522126 | O30: 3976105452 | P30: 633910092 | Q30: 9527377416 | R30: 1530776179 | S30: =+C30+E30+G30+I30+K30+M30+O30+Q30 -> 19982231496 | T30: =+S30-U30 -> 16386761398 | U30: =+D30+F30+H30+J30+L30+N30+P30+R30 -> 3595470098 | V30: 0.5 | W30: =+E30+G30 -> 507936404 | X30: =+W30*V30 -> 253968202 | Y30: =+F30+H30 -> 201865274 | Z30: =+Y30*V30 -> 100932637
A31: 9.1 | B31: шу жумладан, жисмоний шахсларга берилган кредит ва лизинглар | C31: 256533113 | D31: 0 | E31: 166921211 | F31: 0 | G31: 3090440 | H31: 0 | I31: 382102269 | J31: 0 | K31: 535515298 | L31: 0 | M31: 1032977100 | N31: 0 | O31: 1785137355 | P31: 0 | Q31: 4244209601 | R31: 0 | S31: =+C31+E31+G31+I31+K31+M31+O31+Q31 -> 8406486387 | T31: =+S31-U31 -> 8406486387 | U31: =+D31+F31+H31+J31+L31+N31+P31+R31 -> 0 | V31: 0 | W31: =+E31+G31 -> 170011651 | X31: =+W31*V31 -> 0 | Y31: =+F31+H31 -> 0 | Z31: =+Y31*V31 -> 0
A32: 10 | B32: Суд ёки ижро иши юритиш жараёнидаги кредитлар ва лизинг, соф | C32: 167963237 | D32: 118818689 | S32: =+C32+E32+G32+I32+K32+M32+O32+Q32 -> 167963237 | T32: =+S32-U32 -> 49144548 | U32: =+D32+F32+H32+J32+L32+N32+P32+R32 -> 118818689 | V32: 0 | W32: =+E32+G32 -> 0 | X32: =+W32*V32 -> 0 | Y32: =+F32+H32 -> 0 | Z32: =+Y32*V32 -> 0
A33: 11 | B33: Инвестициялар, соф | C33: 925002773 | D33: 0 | E33: 0 | F33: 0 | G33: 0 | H33: 0 | I33: 0 | J33: 0 | K33: 0 | L33: 0 | M33: 0 | N33: 0 | O33: 0 | P33: 0 | Q33: 0 | R33: 0 | S33: =+C33+E33+G33+I33+K33+M33+O33+Q33 -> 925002773 | T33: =+S33-U33 -> 925002773 | U33: =+D33+F33+H33+J33+L33+N33+P33+R33 -> 0 | V33: 0 | W33: =+E33+G33 -> 0 | X33: =+W33*V33 -> 0 | Y33: =+F33+H33 -> 0 | Z33: =+Y33*V33 -> 0
A34: 12 | B34: РЕПО битимлари бўйича сотиб олинган қимматли қоғозлар | C34: =+C35+C36 -> 0 | D34: =+D35+D36 -> 0 | E34: =+E35+E36 -> 0 | F34: =+F35+F36 -> 0 | G34: =+G35+G36 -> 0 | H34: =+H35+H36 -> 0 | I34: =+I35+I36 -> 0 | J34: =+J35+J36 -> 0 | ... R34: =+R35+R36 -> 0 | S34: =+C34+E34+G34+I34+K34+M34+O34+Q34 -> 0 | T34: =+S34-U34 -> 0 | U34: =+D34+F34+H34+J34+L34+N34+P34+R34 -> 0 | V34: 0 | W34: =+E34+G34 -> 0 | X34: =+W34*V34 -> 0 | Y34: =+F34+H34 -> 0 | Z34: =+Y34*V34 -> 0
A35: 12.1 | B35: РЕПО битимлари бўйича сотиб олинган юқори ликвидли қимматли қоғозлар | C35: 0 | D35: 0 | E35: 0 | F35: 0 | G35: 0 | H35: 0 | I35: 0 | J35: 0 | K35: 0 | L35: 0 | M35: 0 | N35: 0 | O35: 0 | P35: 0 | Q35: 0 | R35: 0 | S35: =+C35+E35+G35+I35+K35+M35+O35+Q35 -> 0 | T35: =+S35-U35 -> 0 | U35: =+D35+F35+H35+J35+L35+N35+P35+R35 -> 0 | V35: 1 | W35: =+S35 -> 0 | X35: =+W35*V35 -> 0 | Y35: =+U35 -> 0 | Z35: =+Y35*V35 -> 0
A36: 12.2 | B36: РЕПО битимлари бўйича сотиб олинган бошқа қимматли қоғозлар | C36: 0 | D36: 0 | E36: 0 | F36: 0 | G36: 0 | H36: 0 | I36: 0 | J36: 0 | K36: 0 | L36: 0 | M36: 0 | N36: 0 | O36: 0 | P36: 0 | Q36: 0 | R36: 0 | S36: =+C36+E36+G36+I36+K36+M36+O36+Q36 -> 0 | T36: =+S36-U36 -> 0 | U36: =+D36+F36+H36+J36+L36+N36+P36+R36 -> 0 | V36: 0
A37: 13 | B37: Aсосий воситалар, соф | C37: 0 | D37: 0 | E37: 0 | F37: 0 | G37: 0 | H37: 0 | I37: 0 | J37: 0 | K37: 0 | L37: 0 | M37: 0 | N37: 0 | O37: 0 | P37: 0 | Q37: 903999652 | R37: 0 | S37: =+C37+E37+G37+I37+K37+M37+O37+Q37 -> 903999652 | T37: =+S37-U37 -> 903999652 | U37: =+D37+F37+H37+J37+L37+N37+P37+R37 -> 0 | V37: 0
A38: 14 | B38: Банкнинг бошқа хусусий мулклари, соф | C38: 790493963 | D38: 0 | E38: 0 | F38: 0 | G38: 0 | H38: 0 | I38: 0 | J38: 0 | K38: 0 | L38: 0 | M38: 0 | N38: 0 | O38: 0 | P38: 0 | Q38: 0 | R38: 0 | S38: =+C38+E38+G38+I38+K38+M38+O38+Q38 -> 790493963 | T38: =+S38-U38 -> 790493963 | U38: =+D38+F38+H38+J38+L38+N38+P38+R38 -> 0 | V38: 0
A39: 15 | B39: Ҳосилавий инструментларнинг ревальвацияси натижасида ўзлаштирилмаган фойда | C39: 0 | D39: 0 | E39: 0 | F39: 0 | G39: 0 | H39: 0 | I39: 0 | J39: 0 | K39: 0 | L39: 0 | M39: 0 | N39: 0 | O39: 0 | P39: 0 | Q39: 0 | R39: 0 | S39: =+C39+E39+G39+I39+K39+M39+O39+Q39 -> 0 | T39: =+S39-U39 -> 0 | U39: =+D39+F39+H39+J39+L39+N39+P39+R39 -> 0 | V39: 0
A40: 16 | B40: Валюта савдоси ва валюта позициялари | C40: 0 | E40: 0 | G40: 0 | I40: 0 | K40: 0 | M40: 0 | O40: 0 | Q40: 0 | S40: =+C40+E40+G40+I40+K40+M40+O40+Q40 -> 0 | T40: =+S40-U40 -> 0 | U40: =+D40+F40+H40+J40+L40+N40+P40+R40 -> 0 | V40: 0
A41: 17 | B41: Транзит ҳисобварақлари | C41: 0 | D41: 0 | E41: 0 | F41: 0 | G41: 0 | H41: 0 | I41: 0 | J41: 0 | K41: 0 | L41: 0 | M41: 0 | N41: 0 | O41: 0 | P41: 0 | Q41: 0 | R41: 0 | S41: =+C41+E41+G41+I41+K41+M41+O41+Q41 -> 0 | T41: =+S41-U41 -> 0 | U41: =+D41+F41+H41+J41+L41+N41+P41+R41 -> 0 | V41: 0
A42: 18 | B42: Олиниши лозим бўлган ҳисобланган фоизлар | C42: 850172105 | D42: 138030356 | E42: 0 | F42: 0 | G42: 1018228812 | H42: 367568287 | I42: 0 | J42: 0 | K42: 0 | L42: 0 | M42: 0 | N42: 0 | O42: 0 | P42: 0 | Q42: 0 | R42: 0 | S42: =+C42+E42+G42+I42+K42+M42+O42+Q42 -> 1868400917 | T42: =+S42-U42 -> 1362802274 | U42: =+D42+F42+H42+J42+L42+N42+P42+R42 -> 505598643 | V42: 0.5 | W42: =+E42+G42 -> 1018228812 | X42: =+W42*V42 -> 509114406 | Y42: =+F42+H42 -> 367568287 | Z42: =+Y42*V42 -> 1.8378414e+08
A43: 18.1 | B43: Бош офис/филиалдан олиниши лозим бўлган ҳисобланган фоизлар | C43: 0 | D43: 0 | E43: 0 | F43: 0 | G43: 2 | H43: 2 | I43: 0 | J43: 0 | K43: 0 | L43: 0 | M43: 0 | N43: 0 | O43: 0 | P43: 0 | Q43: 0 | R43: 0 | S43: =+C43+E43+G43+I43+K43+M43+O43+Q43 -> 2 | T43: =+S43-U43 -> 0 | U43: =+D43+F43+H43+J43+L43+N43+P43+R43 -> 2 | V43: 1 | W43: =+E43+G43 -> 2 | X43: =+W43*V43 -> 2 | Y43: =+F43+H43 -> 2 | Z43: =+Y43*V43 -> 2
A44: 18.2 | B44: Бошқа банклардан олиниши лозим бўлган ҳисобланган фоизлар | C44: 0 | D44: 0 | E44: 0 | F44: 0 | G44: 2088316 | H44: 1959333 | I44: 0 | J44: 0 | K44: 0 | L44: 0 | M44: 0 | N44: 0 | O44: 0 | P44: 0 | Q44: 0 | R44: 0 | S44: =+C44+E44+G44+I44+K44+M44+O44+Q44 -> 2088316 | T44: =+S44-U44 -> 128983 | U44: =+D44+F44+H44+J44+L44+N44+P44+R44 -> 1959333 | V44: 1 | W44: =+E44+G44 -> 2088316 | X44: =+W44*V44 -> 2088316 | Y44: =+F44+H44 -> 1959333 | Z44: =+Y44*V44 -> 1959333
A45: 19 | B45: Бошқа активлар | C45: 359867846 | D45: 30483330 | E45: 0 | F45: 0 | G45: 6987324 | H45: 0 | I45: 13974648 | J45: 0 | K45: 20961973 | L45: 0 | M45: 41923945 | N45: 0 | O45: 81740401 | P45: 0 | Q45: 252323958 | R45: 0 | S45: =+C45+E45+G45+I45+K45+M45+O45+Q45 -> 777780095 | T45: =+S45-U45 -> 747296765 | U45: =+D45+F45+H45+J45+L45+N45+P45+R45 -> 30483330 | V45: 0
A46: 20 | B46: Гаровга қўйилган юқори ликвидли активлар, 4a бундан мустасно | C46: 0 | D46: 0 | E46: 0 | F46: 0 | G46: 0 | H46: 0 | I46: 0 | J46: 0 | K46: 0 | L46: 0 | M46: 0 | N46: 0 | O46: 0 | P46: 0 | Q46: 0 | R46: 0 | S46: =+C46+E46+G46+I46+K46+M46+O46+Q46 -> 0 | T46: =+S46-U46 -> 0 | U46: =+D46+F46+H46+J46+L46+N46+P46+R46 -> 0 | V46: 1 | W46: =+C46+E46+G46 -> 0 | X46: =+W46*V46 -> 0 | Y46: =+D46+F46+H46 -> 0 | Z46: =+Y46*V46 -> 0
A47: 21 | B47: ЖAМИ АКТИВЛАР | C47: =SUM(C6:C45)-C9-C13-C17-C18-C31-C34 -> 6889821463 | D47: =SUM(D6:D45)-D9-D13-D17-D18-D31-D34 -> 2642571015 | E47: =SUM(E6:E45)-E9-E13-E17-E18-E31-E34 -> 1464748366 | F47: =SUM(F6:F45)-F9-F13-F17-F18-F31-F34 -> 523262019 | G47: =SUM(G6:G45)-G9-G13-G17-G18-G31-G34 -> 1321358327 | H47: =SUM(H6:H45)-H9-H13-H17-H18-H31-H34 -> 637372047 | I47: =SUM(I6:I45)-I9-I13-I17-I18-I31-I34 -> 1915778182 | J47: =SUM(J6:J45)-J9-J13-J17-J18-J31-J34 -> 1151664227 | ... R47: =SUM(R6:R45)-R9-R13-R17-R18-R31-R34 -> 1530776179 | S47: =+C47+E47+G47+I47+K47+M47+O47+Q47 -> 30728787180 | T47: =+S47-U47 -> 22869741752 | U47: =+D47+F47+H47+J47+L47+N47+P47+R47 -> 7859045428 | X47: =+X12+X14+X15+X16+X18+X25+X26+X27+X28+X29+X30+X42+X46+(T23*0.2)+X43+X44 -> 1379260817 | Z47: =+Z12+Z14+Z15+Z16+Z18+Z25+Z26+Z27+Z28+Z29+Z30+Z42+Z46+(U23*0.2)+Z43+Z44 -> 8.8600749e+08 | AA47: =+Balance!C47 -> 30728787180 | AB47: =+Balance!D47 -> 22869741752 | AC47: =+Balance!E47 -> 7859045428
B48: Балансдан ташқари мажбуриятлар | AA48: =+AA47-S47 -> 0 | AB48: =+AB47-T47 -> 0 | AC48: =+AC47-U47 -> 0
A49: 1 | B49: Банкнинг кредит ва лизинг бериш бўйича мажбуриятлари (91809) | C49: 67080319 | D49: 0 | E49: 543288 | F49: 0 | G49: 467610 | H49: 0 | I49: 4499707 | J49: 0 | K49: 24236196 | L49: 0 | M49: 160969981 | N49: 20370613 | O49: 40608933 | P49: 9422212 | Q49: 608565839 | R49: 292754194 | S49: =+C49+E49+G49+I49+K49+M49+O49+Q49 -> 906971873 | T49: =+S49-U49 -> 584424854 | U49: =+D49+F49+H49+J49+L49+N49+P49+R49 -> 322547019 | AA49: =+Commitments!C4 -> 906971873 | AB49: =+Commitments!D4 -> 584424854 | AC49: =+Commitments!E4 -> 322547019 | AD49: =+AA49-S49 -> 0 | AE49: =+AB49-T49 -> 0 | AF49: =+AC49-U49 -> 0
B50: шундан, ХМИ, Молия вазирлиги, фондлар ва бошқа ташкилотларнинг депозитлари билан таъминланган | C50: 305000 | D50: 0 | E50: 0 | F50: 0 | G50: 0 | H50: 0 | I50: 0 | J50: 0 | K50: 0 | L50: 0 | M50: 0 | N50: 0 | O50: 1056042.5 | P50: 0 | Q50: 1.290024e+08 | R50: 51770339 | S50: =+C50+E50+G50+I50+K50+M50+O50+Q50 -> 1.3036345e+08 | T50: =+S50-U50 -> 78593107 | U50: =+D50+F50+H50+J50+L50+N50+P50+R50 -> 51770339 | AA50: =+Commitments!C5 -> 1.3036345e+08 | AB50: =+Commitments!D5 -> 78593107 | AC50: =+Commitments!E5 -> 51770339
A51: 2 | B51: Кафолат ва кафилликлар (90993) | C51: 0 | D51: 0 | E51: 0 | F51: 0 | G51: 0 | H51: 0 | I51: 0 | J51: 0 | K51: 0 | L51: 0 | M51: 4285596 | N51: 4285596 | O51: 261696408 | P51: 258696408 | Q51: 179124237 | R51: 179124237 | S51: =+C51+E51+G51+I51+K51+M51+O51+Q51 -> 445106241 | T51: =+S51-U51 -> 3000000 | U51: =+D51+F51+H51+J51+L51+N51+P51+R51 -> 442106241 | AA51: =+Commitments!C7 -> 445106241 | AB51: =+Commitments!D7 -> 3000000 | AC51: =+Commitments!E7 -> 442106241 | AD51: =+AA51-S51 -> 0 | AE51: =+AB51-T51 -> 0 | AF51: =+AC51-U51 -> 0
B52: - шундан, алоҳида блокланган ҳисобварақлардаги депозитлар билан таъминланган кафолат ва кафилликлар | C52: 0 | D52: 0 | E52: 0 | F52: 0 | G52: 0 | H52: 0 | I52: 0 | J52: 0 | K52: 0 | L52: 0 | M52: 0 | N52: 0 | O52: 115327725 | P52: 115327725 | Q52: 0 | R52: 0 | S52: =+C52+E52+G52+I52+K52+M52+O52+Q52 -> 115327725 | T52: =+S52-U52 -> 0 | U52: =+D52+F52+H52+J52+L52+N52+P52+R52 -> 115327725 | AA52: =+Commitments!C8 -> 115327725 | AB52: =+Commitments!D8 -> 0 | AC52: =+Commitments!E8 -> 115327725
A53: 3 | B53: Аккредитивлар (90908-90958) | C53: 1346837 | D53: 1346837 | E53: 0 | F53: 0 | G53: 461709092 | H53: 461709092 | I53: 52854710 | J53: 52854710 | K53: 3840797 | L53: 3840797 | M53: 301658187 | N53: 301658187 | O53: 208029069 | P53: 208029069 | Q53: 0 | R53: 0 | S53: =+C53+E53+G53+I53+K53+M53+O53+Q53 -> 1029438692 | T53: =+S53-U53 -> 0 | U53: =+D53+F53+H53+J53+L53+N53+P53+R53 -> 1029438692 | AA53: =+Commitments!C10 -> 1029438692 | AB53: =+Commitments!D10 -> 0 | AC53: =+Commitments!E10 -> 1029438692 | AD53: =+AA53-S53 -> 0 | AE53: =+AB53-T53 -> 0 | AF53: =+AC53-U53 -> 0
B54: - шундан, 22602 баланс ҳисобварағида депозит билан таъминланганлар кўрсатилади | C54: 0 | D54: 0 | E54: 0 | F54: 0 | G54: 0 | H54: 0 | I54: 1005518 | J54: 1005518 | K54: 3840797 | L54: 3840797 | M54: 0 | N54: 0 | O54: 0 | P54: 0 | Q54: 0 | R54: 0 | S54: =+C54+E54+G54+I54+K54+M54+O54+Q54 -> 4846315 | T54: =+S54-U54 -> 0 | U54: =+D54+F54+H54+J54+L54+N54+P54+R54 -> 4846315
B56: Бошқарув Раис имзоси:
B58: Бош бухгалтер имзоси:
W60: По новым расчетам
Y61: =+Balance!E47 -> 7859045428
W62: Всего | Y62: Ин вал
W63: Приток | Y63: Приток | Z63: =+Z47 -> 8.8600749e+08
W64: Высоко-ликвидные активы | Y64: Высоко-ликвидные активы | Z64: =+Z6+Z7+Z10+Z11+Z13+Z19+Z20+Z21+Z22+Z24+Z35-Z46-Z18 -> 2151480689
W65: Чистый отток за 30 дней | Y65: Чистый отток за 30 дней | Z65: =+Z67-Z70 -> 2.4033216e+08
W67: Всего отток | Y67: Отток | Z67: =+'Bank Liabilities Analysis'!X42+'Liquidity Analysis'!E41 -> 9.6132864e+08
W68: в том числе отток по внебалансу | Y68: в том числе отток по внебалансу | Z68: =+'Liquidity Analysis'!E41 -> 243322136
W70: Приток по положению | Y70: Приток по положению | Z70: =IF(Z63>(Z67*0.75),Z67*0.75,Z63) -> 7.2099648e+08

Sheet Bank Assets Analysis (нац)
A2: МИЛЛИЙ ВАЛЮТАДАГИ БАНК АКТИВЛАРИ ТАҲЛИЛИ | L2: 17 А-жадвал
B3: =Balance!B3 -> "MKBANK" | K3: =+Balance!D3 -> 46021 | N3: =+Balance!E3 -> минг сўмда
A4: № | B4: Кўрсаткичлар | C4: Сўндириш муддати (кунларда) | K4: Жами | L4: Ликвидлиликни қоплаш меёри ҳисоб китоби
C5: Муддатсиз | D5: 1 дан 7 гача | E5: 8 дан 30 гача | F5: 31 дан 90 гача | G5: 91 дан 180 гача | H5: 181 дан 365 гача | I5: 366 дан 730 гача | J5: 2 йилдан ортиқ | L5: Коэффициент | M5: Активлар | N5: Юқори ликвидли активлар/кирим
A6: 1 | B6: Кассадаги нақд пул ва бошқа тўлов ҳужжатлари | C6: =+'Bank Assets Analysis'!C6-'Bank Assets Analysis'!D6 -> 538991500 | D6: =+'Bank Assets Analysis'!E6-'Bank Assets Analysis'!F6 -> 0 | E6: =+'Bank Assets Analysis'!G6-'Bank Assets Analysis'!H6 -> 0 | F6: =+'Bank Assets Analysis'!I6-'Bank Assets Analysis'!J6 -> 0 | G6: =+'Bank Assets Analysis'!K6-'Bank Assets Analysis'!L6 -> 0 | H6: =+'Bank Assets Analysis'!M6-'Bank Assets Analysis'!N6 -> 0 | I6: =+'Bank Assets Analysis'!O6-'Bank Assets Analysis'!P6 -> 0 | J6: =+'Bank Assets Analysis'!Q6-'Bank Assets Analysis'!R6 -> 0 | K6: =+C6+D6+E6+F6+G6+H6+I6+J6 -> 538991500 | L6: 1 | M6: =+K6 -> 538991500 | N6: =+M6*L6 -> 538991500
A7: 2 | B7: Банкнинг Марказий банкдаги маблағлари (мажбурий захирасиз) | C7: =+'Bank Assets Analysis'!C7-'Bank Assets Analysis'!D7 -> 324034134 | D7: =+'Bank Assets Analysis'!E7-'Bank Assets Analysis'!F7 -> 260000000 | E7: =+'Bank Assets Analysis'!G7-'Bank Assets Analysis'!H7 -> 0 | F7: =+'Bank Assets Analysis'!I7-'Bank Assets Analysis'!J7 -> 0 | G7: =+'Bank Assets Analysis'!K7-'Bank Assets Analysis'!L7 -> 0 | H7: =+'Bank Assets Analysis'!M7-'Bank Assets Analysis'!N7 -> 0 | I7: =+'Bank Assets Analysis'!O7-'Bank Assets Analysis'!P7 -> 0 | J7: =+'Bank Assets Analysis'!Q7-'Bank Assets Analysis'!R7 -> 0 | K7: =+C7+D7+E7+F7+G7+H7+I7+J7 -> 584034134 | L7: 1 | M7: =+K7 -> 584034134 | N7: =+M7*L7 -> 584034134
A8: 2.1 | B8: Банкнинг Марказий банкдаги мажбурий захира ҳисобварағидаги маблағлар | C8: =+'Bank Assets Analysis'!C8-'Bank Assets Analysis'!D8 -> 0 | D8: =+'Bank Assets Analysis'!E8-'Bank Assets Analysis'!F8 -> 0 | E8: =+'Bank Assets Analysis'!G8-'Bank Assets Analysis'!H8 -> 0 | F8: =+'Bank Assets Analysis'!I8-'Bank Assets Analysis'!J8 -> 0 | G8: =+'Bank Assets Analysis'!K8-'Bank Assets Analysis'!L8 -> 0 | H8: =+'Bank Assets Analysis'!M8-'Bank Assets Analysis'!N8 -> 0 | I8: =+'Bank Assets Analysis'!O8-'Bank Assets Analysis'!P8 -> 0 | J8: =+'Bank Assets Analysis'!Q8-'Bank Assets Analysis'!R8 -> 0 | K8: =+C8+D8+E8+F8+G8+H8+I8+J8 -> 0 | L8: 0 | N8: =+M8*L8 -> 0
A9: 3 | B9: Бошқа банклар ва молиявий ташкилотлардан олиниши лозим бўлган маблағлар | C9: =SUM(C10:C16)-C13 -> 11133345 | D9: =SUM(D10:D16)-D13 -> 0 | E9: =SUM(E10:E16)-E13 -> 1625000 | F9: =SUM(F10:F16)-F13 -> 416666 | G9: =SUM(G10:G16)-G13 -> 4502475 | H9: =SUM(H10:H16)-H13 -> 8323269 | I9: =SUM(I10:I16)-I13 -> 8775477 | J9: =SUM(J10:J16)-J13 -> 26740011 | K9: =+C9+D9+E9+F9+G9+H9+I9+J9 -> 61516243 | N9: =+M9*L9 -> 0
A10: 3.1 | B10: Таваккалчилик даражаси паст банклардаги вакиллик ҳисобварақлари (ностро) | C10: =+'Bank Assets Analysis'!C10-'Bank Assets Analysis'!D10 -> 0 | D10: =+'Bank Assets Analysis'!E10-'Bank Assets Analysis'!F10 -> 0 | E10: =+'Bank Assets Analysis'!G10-'Bank Assets Analysis'!H10 -> 0 | F10: =+'Bank Assets Analysis'!I10-'Bank Assets Analysis'!J10 -> 0 | G10: =+'Bank Assets Analysis'!K10-'Bank Assets Analysis'!L10 -> 0 | H10: =+'Bank Assets Analysis'!M10-'Bank Assets Analysis'!N10 -> 0 | I10: =+'Bank Assets Analysis'!O10-'Bank Assets Analysis'!P10 -> 0 | J10: =+'Bank Assets Analysis'!Q10-'Bank Assets Analysis'!R10 -> 0 | K10: =+C10+D10+E10+F10+G10+H10+I10+J10 -> 0 | L10: 1 | M10: =+C10 -> 0 | N10: =+M10*L10 -> 0
A11: 3.2 | B11: Маҳаллий банклардаги вакиллик ҳисобварақлари (ностро) | C11: =+'Bank Assets Analysis'!C11-'Bank Assets Analysis'!D11 -> 5 | D11: =+'Bank Assets Analysis'!E11-'Bank Assets Analysis'!F11 -> 0 | E11: =+'Bank Assets Analysis'!G11-'Bank Assets Analysis'!H11 -> 0 | F11: =+'Bank Assets Analysis'!I11-'Bank Assets Analysis'!J11 -> 0 | G11: =+'Bank Assets Analysis'!K11-'Bank Assets Analysis'!L11 -> 0 | H11: =+'Bank Assets Analysis'!M11-'Bank Assets Analysis'!N11 -> 0 | I11: =+'Bank Assets Analysis'!O11-'Bank Assets Analysis'!P11 -> 0 | J11: =+'Bank Assets Analysis'!Q11-'Bank Assets Analysis'!R11 -> 0 | K11: =+C11+D11+E11+F11+G11+H11+I11+J11 -> 5 | L11: 1 | M11: =+C11 -> 5 | N11: =+M11*L11 -> 5
A12: 3.3 | B12: Овернайт шарти билан жойлаштирилган депозитлар | C12: =+'Bank Assets Analysis'!C12-'Bank Assets Analysis'!D12 -> 0 | D12: =+'Bank Assets Analysis'!E12-'Bank Assets Analysis'!F12 -> 0 | E12: =+'Bank Assets Analysis'!G12-'Bank Assets Analysis'!H12 -> 0 | F12: =+'Bank Assets Analysis'!I12-'Bank Assets Analysis'!J12 -> 0 | G12: =+'Bank Assets Analysis'!K12-'Bank Assets Analysis'!L12 -> 0 | H12: =+'Bank Assets Analysis'!M12-'Bank Assets Analysis'!N12 -> 0 | I12: =+'Bank Assets Analysis'!O12-'Bank Assets Analysis'!P12 -> 0 | J12: =+'Bank Assets Analysis'!Q12-'Bank Assets Analysis'!R12 -> 0 | K12: =+C12+D12+E12+F12+G12+H12+I12+J12 -> 0 | L12: 1 | M12: =+D12-D13 -> 0 | N12: =+M12*L12 -> 0
A13: 3.3.1. | B13: шундан, инвестицион даражадан паст бўлмаган рейтингга эга банкларга овернайт шарти билан жойлаштирилган хорижий валютадаги депозитлар | C13: =+'Bank Assets Analysis'!C13-'Bank Assets Analysis'!D13 -> 0 | D13: =+'Bank Assets Analysis'!E13-'Bank Assets Analysis'!F13 -> 0 | E13: =+'Bank Assets Analysis'!G13-'Bank Assets Analysis'!H13 -> 0 | F13: =+'Bank Assets Analysis'!I13-'Bank Assets Analysis'!J13 -> 0 | G13: =+'Bank Assets Analysis'!K13-'Bank Assets Analysis'!L13 -> 0 | H13: =+'Bank Assets Analysis'!M13-'Bank Assets Analysis'!N13 -> 0 | I13: =+'Bank Assets Analysis'!O13-'Bank Assets Analysis'!P13 -> 0 | J13: =+'Bank Assets Analysis'!Q13-'Bank Assets Analysis'!R13 -> 0 | K13: =+C13+D13+E13+F13+G13+H13+I13+J13 -> 0 | L13: 1 | M13: =+D13 -> 0 | N13: =+M13*L13 -> 0
A14: 3.4 | B14: Банкнинг бошқа банклар/молиявий ташкилотлардаги ҳисобварақлари | C14: =+'Bank Assets Analysis'!C14-'Bank Assets Analysis'!D14 -> 715295 | D14: =+'Bank Assets Analysis'!E14-'Bank Assets Analysis'!F14 -> 0 | E14: =+'Bank Assets Analysis'!G14-'Bank Assets Analysis'!H14 -> 1625000 | F14: =+'Bank Assets Analysis'!I14-'Bank Assets Analysis'!J14 -> 416666 | G14: =+'Bank Assets Analysis'!K14-'Bank Assets Analysis'!L14 -> 4502475 | H14: =+'Bank Assets Analysis'!M14-'Bank Assets Analysis'!N14 -> 8323269 | I14: =+'Bank Assets Analysis'!O14-'Bank Assets Analysis'!P14 -> 8775477 | J14: =+'Bank Assets Analysis'!Q14-'Bank Assets Analysis'!R14 -> 26740011 | K14: =+C14+D14+E14+F14+G14+H14+I14+J14 -> 51098193 | L14: 1 | M14: =+C14+D14+E14+D10+D11 -> 2340295 | N14: =+M14*L14 -> 2340295
A15: 3.5 | B15: Пластик карталардан амалга оширилган тўловлар бўйича бошқа банклардан олиниши лозим бўлган маблағлар | C15: =+'Bank Assets Analysis'!C15-'Bank Assets Analysis'!D15 -> 10418045 | D15: =+'Bank Assets Analysis'!E15-'Bank Assets Analysis'!F15 -> 0 | E15: =+'Bank Assets Analysis'!G15-'Bank Assets Analysis'!H15 -> 0 | F15: =+'Bank Assets Analysis'!I15-'Bank Assets Analysis'!J15 -> 0 | G15: =+'Bank Assets Analysis'!K15-'Bank Assets Analysis'!L15 -> 0 | H15: =+'Bank Assets Analysis'!M15-'Bank Assets Analysis'!N15 -> 0 | I15: =+'Bank Assets Analysis'!O15-'Bank Assets Analysis'!P15 -> 0 | J15: =+'Bank Assets Analysis'!Q15-'Bank Assets Analysis'!R15 -> 0 | K15: =+C15+D15+E15+F15+G15+H15+I15+J15 -> 10418045 | L15: 1 | M15: =+C15+D15+E15 -> 10418045 | N15: =+M15*L15 -> 10418045
A16: 3.6 | B16: Бошқа моддалар | C16: =+'Bank Assets Analysis'!C16-'Bank Assets Analysis'!D16 -> 0 | D16: =+'Bank Assets Analysis'!E16-'Bank Assets Analysis'!F16 -> 0 | E16: =+'Bank Assets Analysis'!G16-'Bank Assets Analysis'!H16 -> 0 | F16: =+'Bank Assets Analysis'!I16-'Bank Assets Analysis'!J16 -> 0 | G16: =+'Bank Assets Analysis'!K16-'Bank Assets Analysis'!L16 -> 0 | H16: =+'Bank Assets Analysis'!M16-'Bank Assets Analysis'!N16 -> 0 | I16: =+'Bank Assets Analysis'!O16-'Bank Assets Analysis'!P16 -> 0 | J16: =+'Bank Assets Analysis'!Q16-'Bank Assets Analysis'!R16 -> 0 | K16: =+C16+D16+E16+F16+G16+H16+I16+J16 -> 0 | L16: 1 | M16: =+C16+D16+E16 -> 0 | N16: =+M16*L16 -> 0
A17: 4 | B17: Қимматли қоғозлар ва уларга қилинган инвестициялар, соф | C17: =+'Bank Assets Analysis'!C17-'Bank Assets Analysis'!D17 -> 175 | D17: =+'Bank Assets Analysis'!E17-'Bank Assets Analysis'!F17 -> 399999665 | E17: =+'Bank Assets Analysis'!G17-'Bank Assets Analysis'!H17 -> 0 | F17: =+'Bank Assets Analysis'!I17-'Bank Assets Analysis'!J17 -> 0 | G17: =+'Bank Assets Analysis'!K17-'Bank Assets Analysis'!L17 -> 54745360 | H17: =+'Bank Assets Analysis'!M17-'Bank Assets Analysis'!N17 -> 63424295 | I17: =+'Bank Assets Analysis'!O17-'Bank Assets Analysis'!P17 -> 0 | J17: =+'Bank Assets Analysis'!Q17-'Bank Assets Analysis'!R17 -> 0 | K17: =+C17+D17+E17+F17+G17+H17+I17+J17 -> 518169495 | N17: =+M17*L17 -> 0
A18: 4a | B18: шу жумладан, таъминот остидаги юқори ликвидли қимматли қоғозлар | C18: =+'Bank Assets Analysis'!C18-'Bank Assets Analysis'!D18 -> 0 | D18: =+'Bank Assets Analysis'!E18-'Bank Assets Analysis'!F18 -> 0 | E18: =+'Bank Assets Analysis'!G18-'Bank Assets Analysis'!H18 -> 0 | F18: =+'Bank Assets Analysis'!I18-'Bank Assets Analysis'!J18 -> 0 | G18: =+'Bank Assets Analysis'!K18-'Bank Assets Analysis'!L18 -> 0 | H18: =+'Bank Assets Analysis'!M18-'Bank Assets Analysis'!N18 -> 0 | I18: =+'Bank Assets Analysis'!O18-'Bank Assets Analysis'!P18 -> 0 | J18: =+'Bank Assets Analysis'!Q18-'Bank Assets Analysis'!R18 -> 0 | K18: =+C18+D18+E18+F18+G18+H18+I18+J18 -> 0 | L18: 1 | M18: =SUM(C18:E18) -> 0 | N18: =+M18*L18 -> 0
A19: 4.1 | B19: Ўзбекистон Республикаси Ҳукумати ва Марказий банк томонидан чиқарилган қимматли қоғозлар (векселлар, облигациялар ва бошқа қарз қимматли қоғозлар) | C19: =+'Bank Assets Analysis'!C19-'Bank Assets Analysis'!D19 -> 0 | D19: =+'Bank Assets Analysis'!E19-'Bank Assets Analysis'!F19 -> 399999665 | E19: =+'Bank Assets Analysis'!G19-'Bank Assets Analysis'!H19 -> 0 | F19: =+'Bank Assets Analysis'!I19-'Bank Assets Analysis'!J19 -> 0 | G19: =+'Bank Assets Analysis'!K19-'Bank Assets Analysis'!L19 -> 54745360 | H19: =+'Bank Assets Analysis'!M19-'Bank Assets Analysis'!N19 -> 53424295 | I19: =+'Bank Assets Analysis'!O19-'Bank Assets Analysis'!P19 -> 0 | J19: =+'Bank Assets Analysis'!Q19-'Bank Assets Analysis'!R19 -> 0 | K19: =+C19+D19+E19+F19+G19+H19+I19+J19 -> 508169320 | L19: 1 | M19: =+K19 -> 508169320 | N19: =+M19*L19 -> 508169320
A20: 4.2 | B20: Таваккалчилик даражаси паст бўлган мамлакатларнинг қимматли қоғозлари | C20: =+'Bank Assets Analysis'!C20-'Bank Assets Analysis'!D20 -> 0 | D20: =+'Bank Assets Analysis'!E20-'Bank Assets Analysis'!F20 -> 0 | E20: =+'Bank Assets Analysis'!G20-'Bank Assets Analysis'!H20 -> 0 | F20: =+'Bank Assets Analysis'!I20-'Bank Assets Analysis'!J20 -> 0 | G20: =+'Bank Assets Analysis'!K20-'Bank Assets Analysis'!L20 -> 0 | H20: =+'Bank Assets Analysis'!M20-'Bank Assets Analysis'!N20 -> 0 | I20: =+'Bank Assets Analysis'!O20-'Bank Assets Analysis'!P20 -> 0 | J20: =+'Bank Assets Analysis'!Q20-'Bank Assets Analysis'!R20 -> 0 | K20: =+C20+D20+E20+F20+G20+H20+I20+J20 -> 0 | L20: 1 | M20: =+K20 -> 0 | N20: =+M20*L20 -> 0
A21: 4.3 | B21: ХВФ, Жаҳон банки гуруҳи, Осиё тараққиёт банки, Осиё инфраструктура инвестиция банки, ЕТТБ, Европа инвестиция банки, Европа инвестиция жамғармаси, Ислом тараққиёт банки ва Европа Кенгашининг тараққиёт банки томонидан чиқарилган қимматли қоғозлар | C21: =+'Bank Assets Analysis'!C21-'Bank Assets Analysis'!D21 -> 0 | D21: =+'Bank Assets Analysis'!E21-'Bank Assets Analysis'!F21 -> 0 | E21: =+'Bank Assets Analysis'!G21-'Bank Assets Analysis'!H21 -> 0 | F21: =+'Bank Assets Analysis'!I21-'Bank Assets Analysis'!J21 -> 0 | G21: =+'Bank Assets Analysis'!K21-'Bank Assets Analysis'!L21 -> 0 | H21: =+'Bank Assets Analysis'!M21-'Bank Assets Analysis'!N21 -> 0 | I21: =+'Bank Assets Analysis'!O21-'Bank Assets Analysis'!P21 -> 0 | J21: =+'Bank Assets Analysis'!Q21-'Bank Assets Analysis'!R21 -> 0 | K21: =+C21+D21+E21+F21+G21+H21+I21+J21 -> 0 | L21: 1 | M21: =+K21 -> 0 | N21: =+M21*L21 -> 0
A22: 4.4 | B22: Таваккалчилик даражаси паст бўлган мамлакатларнинг етакчи компаниялари қимматли қоғозлари | C22: =+'Bank Assets Analysis'!C22-'Bank Assets Analysis'!D22 -> 0 | D22: =+'Bank Assets Analysis'!E22-'Bank Assets Analysis'!F22 -> 0 | E22: =+'Bank Assets Analysis'!G22-'Bank Assets Analysis'!H22 -> 0 | F22: =+'Bank Assets Analysis'!I22-'Bank Assets Analysis'!J22 -> 0 | G22: =+'Bank Assets Analysis'!K22-'Bank Assets Analysis'!L22 -> 0 | H22: =+'Bank Assets Analysis'!M22-'Bank Assets Analysis'!N22 -> 0 | I22: =+'Bank Assets Analysis'!O22-'Bank Assets Analysis'!P22 -> 0 | J22: =+'Bank Assets Analysis'!Q22-'Bank Assets Analysis'!R22 -> 0 | K22: =+C22+D22+E22+F22+G22+H22+I22+J22 -> 0 | L22: 1 | M22: =+D22+E22 -> 0 | N22: =+M22*L22 -> 0
A23: 4.5 | B23: Ипотекани қайта молиялаштириш ташкилотлари томонидан чиқарилган корпоратив облигациялар | C23: =+'Bank Assets Analysis'!C23-'Bank Assets Analysis'!D23 -> 0 | D23: =+'Bank Assets Analysis'!E23-'Bank Assets Analysis'!F23 -> 0 | E23: =+'Bank Assets Analysis'!G23-'Bank Assets Analysis'!H23 -> 0 | F23: =+'Bank Assets Analysis'!I23-'Bank Assets Analysis'!J23 -> 0 | G23: =+'Bank Assets Analysis'!K23-'Bank Assets Analysis'!L23 -> 0 | H23: =+'Bank Assets Analysis'!M23-'Bank Assets Analysis'!N23 -> 10000000 | I23: =+'Bank Assets Analysis'!O23-'Bank Assets Analysis'!P23 -> 0 | J23: =+'Bank Assets Analysis'!Q23-'Bank Assets Analysis'!R23 -> 0 | K23: =+C23+D23+E23+F23+G23+H23+I23+J23 -> 10000000 | L23: 0.8 | M23: =+C23+D23+E23 -> 0 | N23: =+M23*L23 -> 0
A24: 4.6 | B24: Ипотекани қайта молиялаштириш ташкилотлари томонидан чиқарилган таъминланган қарз муносабатларини тасдиқловчи бошқа қимматли қоғозлар | C24: =+'Bank Assets Analysis'!C24-'Bank Assets Analysis'!D24 -> 0 | D24: =+'Bank Assets Analysis'!E24-'Bank Assets Analysis'!F24 -> 0 | E24: =+'Bank Assets Analysis'!G24-'Bank Assets Analysis'!H24 -> 0 | F24: =+'Bank Assets Analysis'!I24-'Bank Assets Analysis'!J24 -> 0 | G24: =+'Bank Assets Analysis'!K24-'Bank Assets Analysis'!L24 -> 0 | H24: =+'Bank Assets Analysis'!M24-'Bank Assets Analysis'!N24 -> 0 | I24: =+'Bank Assets Analysis'!O24-'Bank Assets Analysis'!P24 -> 0 | J24: =+'Bank Assets Analysis'!Q24-'Bank Assets Analysis'!R24 -> 0 | K24: =+C24+D24+E24+F24+G24+H24+I24+J24 -> 0 | L24: 1 | M24: =+D24+E24 -> 0 | N24: =+M24*L24 -> 0
A25: 4.7 | B25: Бошқалар | C25: =+'Bank Assets Analysis'!C25-'Bank Assets Analysis'!D25 -> 175 | D25: =+'Bank Assets Analysis'!E25-'Bank Assets Analysis'!F25 -> 0 | E25: =+'Bank Assets Analysis'!G25-'Bank Assets Analysis'!H25 -> 0 | F25: =+'Bank Assets Analysis'!I25-'Bank Assets Analysis'!J25 -> 0 | G25: =+'Bank Assets Analysis'!K25-'Bank Assets Analysis'!L25 -> 0 | H25: =+'Bank Assets Analysis'!M25-'Bank Assets Analysis'!N25 -> 0 | I25: =+'Bank Assets Analysis'!O25-'Bank Assets Analysis'!P25 -> 0 | J25: =+'Bank Assets Analysis'!Q25-'Bank Assets Analysis'!R25 -> 0 | K25: =+C25+D25+E25+F25+G25+H25+I25+J25 -> 175 | L25: 1 | M25: =+C25+D25+E25 -> 175 | N25: =+M25*L25 -> 175
A26: 5 | B26: Мижозларнинг аккредитив ва траст ҳужжатлари билан кафолатланган тратталари бўйича мажбуриятлари, соф | C26: =+'Bank Assets Analysis'!C26-'Bank Assets Analysis'!D26 -> 1400024 | D26: =+'Bank Assets Analysis'!E26-'Bank Assets Analysis'!F26 -> 0 | E26: =+'Bank Assets Analysis'!G26-'Bank Assets Analysis'!H26 -> 0 | F26: =+'Bank Assets Analysis'!I26-'Bank Assets Analysis'!J26 -> 0 | G26: =+'Bank Assets Analysis'!K26-'Bank Assets Analysis'!L26 -> 0 | H26: =+'Bank Assets Analysis'!M26-'Bank Assets Analysis'!N26 -> 0 | I26: =+'Bank Assets Analysis'!O26-'Bank Assets Analysis'!P26 -> 0 | J26: =+'Bank Assets Analysis'!Q26-'Bank Assets Analysis'!R26 -> 0 | K26: =+C26+D26+E26+F26+G26+H26+I26+J26 -> 1400024 | L26: 0.5 | M26: =+D26+E26 -> 0 | N26: =+M26*L26 -> 0
A27: 6 | B27: Мижозларнинг банк олдидаги тўланмаган акцептлари бўйича мажбуриятлари, соф | C27: =+'Bank Assets Analysis'!C27-'Bank Assets Analysis'!D27 -> 0 | D27: =+'Bank Assets Analysis'!E27-'Bank Assets Analysis'!F27 -> 0 | E27: =+'Bank Assets Analysis'!G27-'Bank Assets Analysis'!H27 -> 0 | F27: =+'Bank Assets Analysis'!I27-'Bank Assets Analysis'!J27 -> 0 | G27: =+'Bank Assets Analysis'!K27-'Bank Assets Analysis'!L27 -> 0 | H27: =+'Bank Assets Analysis'!M27-'Bank Assets Analysis'!N27 -> 0 | I27: =+'Bank Assets Analysis'!O27-'Bank Assets Analysis'!P27 -> 0 | J27: =+'Bank Assets Analysis'!Q27-'Bank Assets Analysis'!R27 -> 0 | K27: =+C27+D27+E27+F27+G27+H27+I27+J27 -> 0 | L27: 0.5 | M27: =+D27+E27 -> 0 | N27: =+M27*L27 -> 0
A28: 7 | B28: Марказий банкка берилган кредит ва лизинглар, соф | C28: =+'Bank Assets Analysis'!C28-'Bank Assets Analysis'!D28 -> 0 | D28: =+'Bank Assets Analysis'!E28-'Bank Assets Analysis'!F28 -> 0 | E28: =+'Bank Assets Analysis'!G28-'Bank Assets Analysis'!H28 -> 0 | F28: =+'Bank Assets Analysis'!I28-'Bank Assets Analysis'!J28 -> 0 | G28: =+'Bank Assets Analysis'!K28-'Bank Assets Analysis'!L28 -> 0 | H28: =+'Bank Assets Analysis'!M28-'Bank Assets Analysis'!N28 -> 0 | I28: =+'Bank Assets Analysis'!O28-'Bank Assets Analysis'!P28 -> 0 | J28: =+'Bank Assets Analysis'!Q28-'Bank Assets Analysis'!R28 -> 0 | K28: =+C28+D28+E28+F28+G28+H28+I28+J28 -> 0 | L28: 1 | M28: =C28+D28+E28 -> 0 | N28: =+M28*L28 -> 0
A29: 8 | B29: Бошқа банкларга берилган кредит ва лизинглар, соф | C29: =+'Bank Assets Analysis'!C29-'Bank Assets Analysis'!D29 -> 0 | D29: =+'Bank Assets Analysis'!E29-'Bank Assets Analysis'!F29 -> 0 | E29: =+'Bank Assets Analysis'!G29-'Bank Assets Analysis'!H29 -> 0 | F29: =+'Bank Assets Analysis'!I29-'Bank Assets Analysis'!J29 -> 0 | G29: =+'Bank Assets Analysis'!K29-'Bank Assets Analysis'!L29 -> 0 | H29: =+'Bank Assets Analysis'!M29-'Bank Assets Analysis'!N29 -> 0 | I29: =+'Bank Assets Analysis'!O29-'Bank Assets Analysis'!P29 -> 0 | J29: =+'Bank Assets Analysis'!Q29-'Bank Assets Analysis'!R29 -> 0 | K29: =+C29+D29+E29+F29+G29+H29+I29+J29 -> 0 | L29: 0.5 | M29: =+D29+E29 -> 0 | N29: =+M29*L29 -> 0
A30: 9 | B30: Мижозларга берилган кредит ва лизинглар, соф | C30: =+'Bank Assets Analysis'!C30-'Bank Assets Analysis'!D30 -> 565523721 | D30: =+'Bank Assets Analysis'!E30-'Bank Assets Analysis'!F30 -> 281486682 | E30: =+'Bank Assets Analysis'!G30-'Bank Assets Analysis'!H30 -> 24584448 | F30: =+'Bank Assets Analysis'!I30-'Bank Assets Analysis'!J30 -> 749722641 | G30: =+'Bank Assets Analysis'!K30-'Bank Assets Analysis'!L30 -> 1283377933 | H30: =+'Bank Assets Analysis'!M30-'Bank Assets Analysis'!N30 -> 2143269376 | I30: =+'Bank Assets Analysis'!O30-'Bank Assets Analysis'!P30 -> 3342195360 | J30: =+'Bank Assets Analysis'!Q30-'Bank Assets Analysis'!R30 -> 7996601237 | K30: =+C30+D30+E30+F30+G30+H30+I30+J30 -> 16386761398 | L30: 0.5 | M30: =+D30+E30 -> 306071130 | N30: =+M30*L30 -> 153035565
A31: 9.1 | B31: шу жумладан, жисмоний шахсларга берилган кредит ва лизинглар | C31: =+'Bank Assets Analysis'!C31-'Bank Assets Analysis'!D31 -> 256533113 | D31: =+'Bank Assets Analysis'!E31-'Bank Assets Analysis'!F31 -> 166921211 | E31: =+'Bank Assets Analysis'!G31-'Bank Assets Analysis'!H31 -> 3090440 | F31: =+'Bank Assets Analysis'!I31-'Bank Assets Analysis'!J31 -> 382102269 | G31: =+'Bank Assets Analysis'!K31-'Bank Assets Analysis'!L31 -> 535515298 | H31: =+'Bank Assets Analysis'!M31-'Bank Assets Analysis'!N31 -> 1032977100 | I31: =+'Bank Assets Analysis'!O31-'Bank Assets Analysis'!P31 -> 1785137355 | J31: =+'Bank Assets Analysis'!Q31-'Bank Assets Analysis'!R31 -> 4244209601 | K31: =+C31+D31+E31+F31+G31+H31+I31+J31 -> 8406486387 | L31: 0 | M31: =+D31+E31 -> 170011651 | N31: =+M31*L31 -> 0
A32: 10 | B32: Суд ёки ижро иши юритиш жараёнидаги кредитлар ва лизинг, соф | C32: =+'Bank Assets Analysis'!C32-'Bank Assets Analysis'!D32 -> 49144548 | D32: =+'Bank Assets Analysis'!E32-'Bank Assets Analysis'!F32 -> 0 | E32: =+'Bank Assets Analysis'!G32-'Bank Assets Analysis'!H32 -> 0 | F32: =+'Bank Assets Analysis'!I32-'Bank Assets Analysis'!J32 -> 0 | G32: =+'Bank Assets Analysis'!K32-'Bank Assets Analysis'!L32 -> 0 | H32: =+'Bank Assets Analysis'!M32-'Bank Assets Analysis'!N32 -> 0 | I32: =+'Bank Assets Analysis'!O32-'Bank Assets Analysis'!P32 -> 0 | J32: =+'Bank Assets Analysis'!Q32-'Bank Assets Analysis'!R32 -> 0 | K32: =+C32+D32+E32+F32+G32+H32+I32+J32 -> 49144548 | L32: 0 | M32: =+D32+E32 -> 0 | N32: =+M32*L32 -> 0
A33: 11 | B33: Инвестициялар, соф | C33: =+'Bank Assets Analysis'!C33-'Bank Assets Analysis'!D33 -> 925002773 | D33: =+'Bank Assets Analysis'!E33-'Bank Assets Analysis'!F33 -> 0 | E33: =+'Bank Assets Analysis'!G33-'Bank Assets Analysis'!H33 -> 0 | F33: =+'Bank Assets Analysis'!I33-'Bank Assets Analysis'!J33 -> 0 | G33: =+'Bank Assets Analysis'!K33-'Bank Assets Analysis'!L33 -> 0 | H33: =+'Bank Assets Analysis'!M33-'Bank Assets Analysis'!N33 -> 0 | I33: =+'Bank Assets Analysis'!O33-'Bank Assets Analysis'!P33 -> 0 | J33: =+'Bank Assets Analysis'!Q33-'Bank Assets Analysis'!R33 -> 0 | K33: =+C33+D33+E33+F33+G33+H33+I33+J33 -> 925002773 | L33: 0 | M33: =+D33+E33 -> 0 | N33: =+M33*L33 -> 0
A34: 12 | B34: РЕПО битимлари бўйича сотиб олинган қимматли қоғозлар | C34: =+C35+C36 -> 0 | D34: =+D35+D36 -> 0 | E34: =+E35+E36 -> 0 | F34: =+F35+F36 -> 0 | G34: =+G35+G36 -> 0 | H34: =+H35+H36 -> 0 | I34: =+I35+I36 -> 0 | J34: =+J35+J36 -> 0 | K34: =+C34+D34+E34+F34+G34+H34+I34+J34 -> 0 | L34: 0 | M34: =+D34+E34 -> 0 | N34: =+M34*L34 -> 0
A35: 12.1 | B35: РЕПО битимлари бўйича сотиб олинган юқори ликвидли қимматли қоғозлар | C35: =+'Bank Assets Analysis'!C35-'Bank Assets Analysis'!D35 -> 0 | D35: =+'Bank Assets Analysis'!E35-'Bank Assets Analysis'!F35 -> 0 | E35: =+'Bank Assets Analysis'!G35-'Bank Assets Analysis'!H35 -> 0 | F35: =+'Bank Assets Analysis'!I35-'Bank Assets Analysis'!J35 -> 0 | G35: =+'Bank Assets Analysis'!K35-'Bank Assets Analysis'!L35 -> 0 | H35: =+'Bank Assets Analysis'!M35-'Bank Assets Analysis'!N35 -> 0 | I35: =+'Bank Assets Analysis'!O35-'Bank Assets Analysis'!P35 -> 0 | J35: =+'Bank Assets Analysis'!Q35-'Bank Assets Analysis'!R35 -> 0 | K35: =+C35+D35+E35+F35+G35+H35+I35+J35 -> 0 | L35: 1 | M35: =+K35 -> 0 | N35: =+M35*L35 -> 0
A36: 12.2 | B36: РЕПО битимлари бўйича сотиб олинган бошқа қимматли қоғозлар | C36: =+'Bank Assets Analysis'!C36-'Bank Assets Analysis'!D36 -> 0 | D36: =+'Bank Assets Analysis'!E36-'Bank Assets Analysis'!F36 -> 0 | E36: =+'Bank Assets Analysis'!G36-'Bank Assets Analysis'!H36 -> 0 | F36: =+'Bank Assets Analysis'!I36-'Bank Assets Analysis'!J36 -> 0 | G36: =+'Bank Assets Analysis'!K36-'Bank Assets Analysis'!L36 -> 0 | H36: =+'Bank Assets Analysis'!M36-'Bank Assets Analysis'!N36 -> 0 | I36: =+'Bank Assets Analysis'!O36-'Bank Assets Analysis'!P36 -> 0 | J36: =+'Bank Assets Analysis'!Q36-'Bank Assets Analysis'!R36 -> 0 | K36: =+C36+D36+E36+F36+G36+H36+I36+J36 -> 0 | L36: 0 | N36: =+M36*L36 -> 0
A37: 13 | B37: Aсосий воситалар, соф | C37: =+'Bank Assets Analysis'!C37-'Bank Assets Analysis'!D37 -> 0 | D37: =+'Bank Assets Analysis'!E37-'Bank Assets Analysis'!F37 -> 0 | E37: =+'Bank Assets Analysis'!G37-'Bank Assets Analysis'!H37 -> 0 | F37: =+'Bank Assets Analysis'!I37-'Bank Assets Analysis'!J37 -> 0 | G37: =+'Bank Assets Analysis'!K37-'Bank Assets Analysis'!L37 -> 0 | H37: =+'Bank Assets Analysis'!M37-'Bank Assets Analysis'!N37 -> 0 | I37: =+'Bank Assets Analysis'!O37-'Bank Assets Analysis'!P37 -> 0 | J37: =+'Bank Assets Analysis'!Q37-'Bank Assets Analysis'!R37 -> 903999652 | K37: =+C37+D37+E37+F37+G37+H37+I37+J37 -> 903999652 | L37: 0 | N37: =+M37*L37 -> 0
A38: 14 | B38: Банкнинг бошқа хусусий мулклари, соф | C38: =+'Bank Assets Analysis'!C38-'Bank Assets Analysis'!D38 -> 790493963 | D38: =+'Bank Assets Analysis'!E38-'Bank Assets Analysis'!F38 -> 0 | E38: =+'Bank Assets Analysis'!G38-'Bank Assets Analysis'!H38 -> 0 | F38: =+'Bank Assets Analysis'!I38-'Bank Assets Analysis'!J38 -> 0 | G38: =+'Bank Assets Analysis'!K38-'Bank Assets Analysis'!L38 -> 0 | H38: =+'Bank Assets Analysis'!M38-'Bank Assets Analysis'!N38 -> 0 | I38: =+'Bank Assets Analysis'!O38-'Bank Assets Analysis'!P38 -> 0 | J38: =+'Bank Assets Analysis'!Q38-'Bank Assets Analysis'!R38 -> 0 | K38: =+C38+D38+E38+F38+G38+H38+I38+J38 -> 790493963 | L38: 0 | N38: =+M38*L38 -> 0
A39: 15 | B39: Ҳосилавий инструментларнинг ревальвацияси натижасида ўзлаштирилмаган фойда | C39: =+'Bank Assets Analysis'!C39-'Bank Assets Analysis'!D39 -> 0 | D39: =+'Bank Assets Analysis'!E39-'Bank Assets Analysis'!F39 -> 0 | E39: =+'Bank Assets Analysis'!G39-'Bank Assets Analysis'!H39 -> 0 | F39: =+'Bank Assets Analysis'!I39-'Bank Assets Analysis'!J39 -> 0 | G39: =+'Bank Assets Analysis'!K39-'Bank Assets Analysis'!L39 -> 0 | H39: =+'Bank Assets Analysis'!M39-'Bank Assets Analysis'!N39 -> 0 | I39: =+'Bank Assets Analysis'!O39-'Bank Assets Analysis'!P39 -> 0 | J39: =+'Bank Assets Analysis'!Q39-'Bank Assets Analysis'!R39 -> 0 | K39: =+C39+D39+E39+F39+G39+H39+I39+J39 -> 0 | L39: 0 | N39: =+M39*L39 -> 0
A40: 16 | B40: Валюта савдоси ва валюта позициялари | K40: =+C40+D40+E40+F40+G40+H40+I40+J40 -> 0 | L40: 0 | N40: =+M40*L40 -> 0
A41: 17 | B41: Транзит ҳисобварақлари | C41: =+'Bank Assets Analysis'!C41-'Bank Assets Analysis'!D41 -> 0 | D41: =+'Bank Assets Analysis'!E41-'Bank Assets Analysis'!F41 -> 0 | E41: =+'Bank Assets Analysis'!G41-'Bank Assets Analysis'!H41 -> 0 | F41: =+'Bank Assets Analysis'!I41-'Bank Assets Analysis'!J41 -> 0 | G41: =+'Bank Assets Analysis'!K41-'Bank Assets Analysis'!L41 -> 0 | H41: =+'Bank Assets Analysis'!M41-'Bank Assets Analysis'!N41 -> 0 | I41: =+'Bank Assets Analysis'!O41-'Bank Assets Analysis'!P41 -> 0 | J41: =+'Bank Assets Analysis'!Q41-'Bank Assets Analysis'!R41 -> 0 | K41: =+C41+D41+E41+F41+G41+H41+I41+J41 -> 0 | L41: 0 | N41: =+M41*L41 -> 0
A42: 18 | B42: Олиниши лозим бўлган ҳисобланган фоизлар | C42: =+'Bank Assets Analysis'!C42-'Bank Assets Analysis'!D42 -> 712141749 | D42: =+'Bank Assets Analysis'!E42-'Bank Assets Analysis'!F42 -> 0 | E42: =+'Bank Assets Analysis'!G42-'Bank Assets Analysis'!H42 -> 650660525 | F42: =+'Bank Assets Analysis'!I42-'Bank Assets Analysis'!J42 -> 0 | G42: =+'Bank Assets Analysis'!K42-'Bank Assets Analysis'!L42 -> 0 | H42: =+'Bank Assets Analysis'!M42-'Bank Assets Analysis'!N42 -> 0 | I42: =+'Bank Assets Analysis'!O42-'Bank Assets Analysis'!P42 -> 0 | J42: =+'Bank Assets Analysis'!Q42-'Bank Assets Analysis'!R42 -> 0 | K42: =+C42+D42+E42+F42+G42+H42+I42+J42 -> 1362802274 | L42: 0.5 | M42: =+D42+E42 -> 650660525 | N42: =+M42*L42 -> 3.2533026e+08
A43: 18.1 | B43: Бош офис/филиалдан олиниши лозим бўлган ҳисобланган фоизлар | C43: =+'Bank Assets Analysis'!C43-'Bank Assets Analysis'!D43 -> 0 | D43: =+'Bank Assets Analysis'!E43-'Bank Assets Analysis'!F43 -> 0 | E43: =+'Bank Assets Analysis'!G43-'Bank Assets Analysis'!H43 -> 0 | F43: =+'Bank Assets Analysis'!I43-'Bank Assets Analysis'!J43 -> 0 | G43: =+'Bank Assets Analysis'!K43-'Bank Assets Analysis'!L43 -> 0 | H43: =+'Bank Assets Analysis'!M43-'Bank Assets Analysis'!N43 -> 0 | I43: =+'Bank Assets Analysis'!O43-'Bank Assets Analysis'!P43 -> 0 | J43: =+'Bank Assets Analysis'!Q43-'Bank Assets Analysis'!R43 -> 0 | K43: =+C43+D43+E43+F43+G43+H43+I43+J43 -> 0 | L43: 1 | M43: =+D43+E43 -> 0 | N43: =+M43*L43 -> 0
A44: 18.2 | B44: Бошқа банклардан олиниши лозим бўлган ҳисобланган фоизлар | C44: =+'Bank Assets Analysis'!C44-'Bank Assets Analysis'!D44 -> 0 | D44: =+'Bank Assets Analysis'!E44-'Bank Assets Analysis'!F44 -> 0 | E44: =+'Bank Assets Analysis'!G44-'Bank Assets Analysis'!H44 -> 128983 | F44: =+'Bank Assets Analysis'!I44-'Bank Assets Analysis'!J44 -> 0 | G44: =+'Bank Assets Analysis'!K44-'Bank Assets Analysis'!L44 -> 0 | H44: =+'Bank Assets Analysis'!M44-'Bank Assets Analysis'!N44 -> 0 | I44: =+'Bank Assets Analysis'!O44-'Bank Assets Analysis'!P44 -> 0 | J44: =+'Bank Assets Analysis'!Q44-'Bank Assets Analysis'!R44 -> 0 | K44: =+C44+D44+E44+F44+G44+H44+I44+J44 -> 128983 | L44: 1 | M44: =+D44+E44 -> 128983 | N44: =+M44*L44 -> 128983
A45: 19 | B45: Бошқа активлар | C45: =+'Bank Assets Analysis'!C45-'Bank Assets Analysis'!D45 -> 329384516 | D45: =+'Bank Assets Analysis'!E45-'Bank Assets Analysis'!F45 -> 0 | E45: =+'Bank Assets Analysis'!G45-'Bank Assets Analysis'!H45 -> 6987324 | F45: =+'Bank Assets Analysis'!I45-'Bank Assets Analysis'!J45 -> 13974648 | G45: =+'Bank Assets Analysis'!K45-'Bank Assets Analysis'!L45 -> 20961973 | H45: =+'Bank Assets Analysis'!M45-'Bank Assets Analysis'!N45 -> 41923945 | I45: =+'Bank Assets Analysis'!O45-'Bank Assets Analysis'!P45 -> 81740401 | J45: =+'Bank Assets Analysis'!Q45-'Bank Assets Analysis'!R45 -> 252323958 | K45: =+C45+D45+E45+F45+G45+H45+I45+J45 -> 747296765 | L45: 0 | N45: =+M45*L45 -> 0
A46: 20 | B46: Гаровга қўйилган юқори ликвидли активлар, 4.1.1. бундан мустасно | C46: =+'Bank Assets Analysis'!C46-'Bank Assets Analysis'!D46 -> 0 | D46: =+'Bank Assets Analysis'!E46-'Bank Assets Analysis'!F46 -> 0 | E46: =+'Bank Assets Analysis'!G46-'Bank Assets Analysis'!H46 -> 0 | F46: =+'Bank Assets Analysis'!I46-'Bank Assets Analysis'!J46 -> 0 | G46: =+'Bank Assets Analysis'!K46-'Bank Assets Analysis'!L46 -> 0 | H46: =+'Bank Assets Analysis'!M46-'Bank Assets Analysis'!N46 -> 0 | I46: =+'Bank Assets Analysis'!O46-'Bank Assets Analysis'!P46 -> 0 | J46: =+'Bank Assets Analysis'!Q46-'Bank Assets Analysis'!R46 -> 0 | K46: =+C46+D46+E46+F46+G46+H46+I46+J46 -> 0 | L46: 1 | M46: =+C46+D46+E46 -> 0 | N46: =+M46*L46 -> 0
A47: 21 | B47: ЖAМИ АКТИВЛАР | C47: =SUM(C6:C45)-C9-C13-C17-C18-C31-C34 -> 4247250448 | D47: =SUM(D6:D45)-D9-D13-D17-D18-D31-D34 -> 941486347 | E47: =SUM(E6:E45)-E9-E13-E17-E18-E31-E34 -> 683986280 | F47: =SUM(F6:F45)-F9-F13-F17-F18-F31-F34 -> 764113955 | G47: =SUM(G6:G45)-G9-G13-G17-G18-G31-G34 -> 1363587741 | H47: =SUM(H6:H45)-H9-H13-H17-H18-H31-H34 -> 2256940885 | I47: =SUM(I6:I45)-I9-I13-I17-I18-I31-I34 -> 3432711238 | J47: =SUM(J6:J45)-J9-J13-J17-J18-J31-J34 -> 9179664858 | K47: =SUM(C47:J47) -> 22869741752 | M47: =SUM(M6:M45)-M9-M34 -> 2770825763 | N47: =+N12+N13+N14+N15+N16+N18+N26+N27+N28+N29+N30+N42+N46+N25+(K23*0.2)+N43+N44 -> 4.9325333e+08 | O47: =+Balance!D47 -> 22869741752 | P47: =+K47-O47 -> 0 | R47: =+O47 -> 22869741752 | S47: =+K47-R47 -> 0
B48: Балансдан ташқари мажбуриятлар
A49: 1 | B49: Банкнинг кредит ва лизинг бериш бўйича мажбуриятлари (91809) | C49: =+'Bank Assets Analysis'!C49-'Bank Assets Analysis'!D49 -> 67080319 | D49: =+'Bank Assets Analysis'!E49-'Bank Assets Analysis'!F49 -> 543288 | E49: =+'Bank Assets Analysis'!G49-'Bank Assets Analysis'!H49 -> 467610 | F49: =+'Bank Assets Analysis'!I49-'Bank Assets Analysis'!J49 -> 4499707 | G49: =+'Bank Assets Analysis'!K49-'Bank Assets Analysis'!L49 -> 24236196 | H49: =+'Bank Assets Analysis'!M49-'Bank Assets Analysis'!N49 -> 140599368 | I49: =+'Bank Assets Analysis'!O49-'Bank Assets Analysis'!P49 -> 31186721 | J49: =+'Bank Assets Analysis'!Q49-'Bank Assets Analysis'!R49 -> 315811645 | K49: =+C49+D49+E49+F49+G49+H49+I49+J49 -> 584424854
B50: шундан, ХМИ, Молия вазирлиги, фондлар ва бошқа ташкилотларнинг депозитлари билан таъминланган | C50: =+'Bank Assets Analysis'!C50-'Bank Assets Analysis'!D50 -> 305000 | D50: =+'Bank Assets Analysis'!E50-'Bank Assets Analysis'!F50 -> 0 | E50: =+'Bank Assets Analysis'!G50-'Bank Assets Analysis'!H50 -> 0 | F50: =+'Bank Assets Analysis'!I50-'Bank Assets Analysis'!J50 -> 0 | G50: =+'Bank Assets Analysis'!K50-'Bank Assets Analysis'!L50 -> 0 | H50: =+'Bank Assets Analysis'!M50-'Bank Assets Analysis'!N50 -> 0 | I50: =+'Bank Assets Analysis'!O50-'Bank Assets Analysis'!P50 -> 1056042.5 | J50: =+'Bank Assets Analysis'!Q50-'Bank Assets Analysis'!R50 -> 77232065 | K50: =+C50+D50+E50+F50+G50+H50+I50+J50 -> 78593107
A51: 2 | B51: Кафолат ва кафилликлар (90993) | C51: =+'Bank Assets Analysis'!C51-'Bank Assets Analysis'!D51 -> 0 | D51: =+'Bank Assets Analysis'!E51-'Bank Assets Analysis'!F51 -> 0 | E51: =+'Bank Assets Analysis'!G51-'Bank Assets Analysis'!H51 -> 0 | F51: =+'Bank Assets Analysis'!I51-'Bank Assets Analysis'!J51 -> 0 | G51: =+'Bank Assets Analysis'!K51-'Bank Assets Analysis'!L51 -> 0 | H51: =+'Bank Assets Analysis'!M51-'Bank Assets Analysis'!N51 -> 0 | I51: =+'Bank Assets Analysis'!O51-'Bank Assets Analysis'!P51 -> 3000000 | J51: =+'Bank Assets Analysis'!Q51-'Bank Assets Analysis'!R51 -> 0 | K51: =+C51+D51+E51+F51+G51+H51+I51+J51 -> 3000000
B52: - шундан, алоҳида блокланган ҳисобварақлардаги депозитлар билан таъминланган кафолат ва кафилликлар | C52: =+'Bank Assets Analysis'!C52-'Bank Assets Analysis'!D52 -> 0 | D52: =+'Bank Assets Analysis'!E52-'Bank Assets Analysis'!F52 -> 0 | E52: =+'Bank Assets Analysis'!G52-'Bank Assets Analysis'!H52 -> 0 | F52: =+'Bank Assets Analysis'!I52-'Bank Assets Analysis'!J52 -> 0 | G52: =+'Bank Assets Analysis'!K52-'Bank Assets Analysis'!L52 -> 0 | H52: =+'Bank Assets Analysis'!M52-'Bank Assets Analysis'!N52 -> 0 | I52: =+'Bank Assets Analysis'!O52-'Bank Assets Analysis'!P52 -> 0 | J52: =+'Bank Assets Analysis'!Q52-'Bank Assets Analysis'!R52 -> 0 | K52: =+C52+D52+E52+F52+G52+H52+I52+J52 -> 0
A53: 3 | B53: Аккредитивлар (90908-90958) | C53: =+'Bank Assets Analysis'!C53-'Bank Assets Analysis'!D53 -> 0 | D53: =+'Bank Assets Analysis'!E53-'Bank Assets Analysis'!F53 -> 0 | E53: =+'Bank Assets Analysis'!G53-'Bank Assets Analysis'!H53 -> 0 | F53: =+'Bank Assets Analysis'!I53-'Bank Assets Analysis'!J53 -> 0 | G53: =+'Bank Assets Analysis'!K53-'Bank Assets Analysis'!L53 -> 0 | H53: =+'Bank Assets Analysis'!M53-'Bank Assets Analysis'!N53 -> 0 | I53: =+'Bank Assets Analysis'!O53-'Bank Assets Analysis'!P53 -> 0 | J53: =+'Bank Assets Analysis'!Q53-'Bank Assets Analysis'!R53 -> 0 | K53: =+C53+D53+E53+F53+G53+H53+I53+J53 -> 0
B54: - шундан, 22602 баланс ҳисобварағида депозит билан таъминланганлар кўрсатилади | C54: =+'Bank Assets Analysis'!C54-'Bank Assets Analysis'!D54 -> 0 | D54: =+'Bank Assets Analysis'!E54-'Bank Assets Analysis'!F54 -> 0 | E54: =+'Bank Assets Analysis'!G54-'Bank Assets Analysis'!H54 -> 0 | F54: =+'Bank Assets Analysis'!I54-'Bank Assets Analysis'!J54 -> 0 | G54: =+'Bank Assets Analysis'!K54-'Bank Assets Analysis'!L54 -> 0 | H54: =+'Bank Assets Analysis'!M54-'Bank Assets Analysis'!N54 -> 0 | I54: =+'Bank Assets Analysis'!O54-'Bank Assets Analysis'!P54 -> 0 | J54: =+'Bank Assets Analysis'!Q54-'Bank Assets Analysis'!R54 -> 0 | K54: =+C54+D54+E54+F54+G54+H54+I54+J54 -> 0
B56: Бошқарув Раис имзоси:
B58: Бош бухгалтер имзоси:
O59: Ликвидные активы | P59: =+N47 -> 4.9325333e+08
O60: Высоко-ликвидные активы | P60: =+N6+N7+N10+N11+N19+N20+N21+N22+N24+N35-N46-N18 -> 1631194959
O61: Чистый отток за 30 дней | P61: =+P63-P65 -> 1.3938893e+09
O63: всего отток | P63: ='Bank Liabilities Analysis (нац)'!M43+P64 -> 1.8871426e+09
O64: в том числе отток по внебалансу | P64: =+'Liquidity Analysis'!D41 -> 76324762
O65: Приток по положению | P65: =IF(P59>(P63*0.75),P63*0.75,P59) -> 4.9325333e+08

Sheet Bank Liabilities Analysis
A1: БАНК МАЖБУРИЯТЛАРИ ТАҲЛИЛИ | W1: 18-жадвал
B2: =Balance!B3 -> "MKBANK" | V2: =+Balance!D3 -> 46021 | X2: минг сўмда
A3: № | B3: Кўрсаткичлар | C3: Сўндириш муддати (кунларда) | S3: Жами | T3: шундан, | V3: Ликвидлиликни қоплаш меёри ҳисоб китоби
C4: Муддатсиз | E4: 1 дан 7 гача | G4: 8 дан 30 гача | I4: 31 дан 90 гача | K4: 91 дан 180 гача | M4: 181 дан 365 гача | O4: 366 дан 730 гача | Q4: 2 йилдан ортиқ
C5: Сумма | D5: шундан, хорижий валютада (сўм экв.) | E5: Сумма | F5: шундан, хорижий валютада (сўм экв.) | G5: Сумма | H5: шундан, хорижий валютада (сўм экв.) | I5: Сумма | J5: шундан, хорижий валютада (сўм экв.) | K5: Сумма | L5: шундан, хорижий валютада (сўм экв.) | M5: Сумма | N5: шундан, хорижий валютада (сўм экв.) | O5: Сумма | P5: шундан, хорижий валютада (сўм экв.) | Q5: Сумма | R5: шундан, хорижий валютада (сўм экв.) | T5: миллий валютада | U5: хорижий валютада (сўм экв.) | V5: Коэффициент | W5: 30 кунлик чиқим суммаси | X5: 30 кунлик чиқим суммаси (хорижий валютада)
A6: 1. | B6: ДЕПОЗИТЛАР
A7: 1.1 | B7: Талаб қилиб олингунча депозитлар | C7: =SUM(C8:C11) -> 569468847 | D7: =SUM(D8:D11) -> 35054777 | E7: =SUM(E8:E11) -> 0 | F7: =SUM(F8:F11) -> 0 | G7: =SUM(G8:G11) -> 0 | H7: =SUM(H8:H11) -> 0 | I7: =SUM(I8:I11) -> 0 | J7: =SUM(J8:J11) -> 0 | ... R7: =SUM(R8:R11) -> 0 | S7: =+C7+E7+G7+I7+K7+M7+O7+Q7 -> 569468847 | T7: =+S7-U7 -> 534414070 | U7: =+D7+F7+H7+J7+L7+N7+P7+R7 -> 35054777
A8: 1.1.1 | B8: Aҳолининг талаб қилиб олингунча омонатлари | C8: 10712094 | D8: 2845949 | E8: 0 | F8: 0 | G8: 0 | H8: 0 | I8: 0 | J8: 0 | K8: 0 | L8: 0 | M8: 0 | N8: 0 | O8: 0 | P8: 0 | Q8: 0 | R8: 0 | S8: =+C8+E8+G8+I8+K8+M8+O8+Q8 -> 10712094 | T8: =+S8-U8 -> 7866145 | U8: =+D8+F8+H8+J8+L8+N8+P8+R8 -> 2845949
A9: 1.1.2 | B9: Кредит таъминоти сифатида жалб этилган aҳоли омонатлари | C9: 1529328 | D9: 1529328 | E9: 0 | F9: 0 | G9: 0 | H9: 0 | I9: 0 | J9: 0 | K9: 0 | L9: 0 | M9: 0 | N9: 0 | O9: 0 | P9: 0 | Q9: 0 | R9: 0 | S9: =+C9+E9+G9+I9+K9+M9+O9+Q9 -> 1529328 | T9: =+S9-U9 -> 0 | U9: =+D9+F9+H9+J9+L9+N9+P9+R9 -> 1529328
A10: 1.1.3 | B10: Кредит таъминоти сифатида жалб этилган бошқа депозитлар | C10: 0 | D10: 0 | E10: 0 | F10: 0 | G10: 0 | H10: 0 | I10: 0 | J10: 0 | K10: 0 | L10: 0 | M10: 0 | N10: 0 | O10: 0 | P10: 0 | Q10: 0 | R10: 0 | S10: =+C10+E10+G10+I10+K10+M10+O10+Q10 -> 0 | T10: =+S10-U10 -> 0 | U10: =+D10+F10+H10+J10+L10+N10+P10+R10 -> 0
A11: 1.1.4 | B11: Талаб қилиб олингунча бошқа депозитлар | C11: 557227425 | D11: 30679500 | E11: 0 | F11: 0 | G11: 0 | H11: 0 | I11: 0 | J11: 0 | K11: 0 | L11: 0 | M11: 0 | N11: 0 | O11: 0 | P11: 0 | Q11: 0 | R11: 0 | S11: =+C11+E11+G11+I11+K11+M11+O11+Q11 -> 557227425 | T11: =+S11-U11 -> 526547925 | U11: =+D11+F11+H11+J11+L11+N11+P11+R11 -> 30679500
A12: 1.2 | B12: Муддатли депозитлар | C12: 15227289 | D12: 1720192 | E12: 238212391 | F12: 0 | G12: 132243992 | H12: 0 | I12: 774742663 | J12: 657076 | K12: 2044235614 | L12: 386034401 | M12: 2126369895 | N12: 244996838 | O12: 1216979765 | P12: 100768400 | Q12: 2262207260 | R12: 20939482 | S12: =+C12+E12+G12+I12+K12+M12+O12+Q12 -> 8810218869 | T12: =+S12-U12 -> 8055102480 | U12: =+D12+F12+H12+J12+L12+N12+P12+R12 -> 755116389
A13: 1.2.1 | B13: Аҳоли омонатлари | C13: 11915601 | D13: 337279 | E13: 7405261 | F13: 0 | G13: 29723296 | H13: 0 | I13: 457559172 | J13: 657076 | K13: 679808897 | L13: 98792443 | M13: 833425787 | N13: 67522208 | O13: 770664639 | P13: 30636675 | Q13: 104245381 | R13: 20939482 | S13: =+C13+E13+G13+I13+K13+M13+O13+Q13 -> 2894748034 | T13: =+S13-U13 -> 2675862871 | U13: =+D13+F13+H13+J13+L13+N13+P13+R13 -> 218885163
A14: 1.2.2 | B14: Чиқарилган депозит сертификатлари | C14: 0 | D14: 0 | E14: 0 | F14: 0 | G14: 0 | H14: 0 | I14: 0 | J14: 0 | K14: 0 | L14: 0 | M14: 0 | N14: 0 | O14: 0 | P14: 0 | Q14: 0 | R14: 0 | S14: =+C14+E14+G14+I14+K14+M14+O14+Q14 -> 0 | T14: =+S14-U14 -> 0 | U14: =+D14+F14+H14+J14+L14+N14+P14+R14 -> 0
A15: 1.3 | B15: Мижозларнинг бошқа депозитлари | C15: =SUM(C16:C19) -> 342135129 | D15: =SUM(D16:D19) -> 26991801 | E15: =SUM(E16:E19) -> 0 | F15: =SUM(F16:F19) -> 0 | G15: =SUM(G16:G19) -> 0 | H15: =SUM(H16:H19) -> 0 | I15: =SUM(I16:I19) -> 1005518 | J15: =SUM(J16:J19) -> 1005518 | ... R15: =SUM(R16:R19) -> 0 | S15: =+C15+E15+G15+I15+K15+M15+O15+Q15 -> 346981444 | T15: =+S15-U15 -> 315143328 | U15: =+D15+F15+H15+J15+L15+N15+P15+R15 -> 31838116
A16: 1.3.1 | B16: Жисмоний шахсларнинг банк пластик карталаридаги маблағлари | C16: 317215437 | D16: 22678936 | E16: 0 | F16: 0 | G16: 0 | H16: 0 | I16: 0 | J16: 0 | K16: 0 | L16: 0 | M16: 0 | N16: 0 | O16: 0 | P16: 0 | Q16: 0 | R16: 0 | S16: =+C16+E16+G16+I16+K16+M16+O16+Q16 -> 317215437 | T16: =+S16-U16 -> 294536501 | U16: =+D16+F16+H16+J16+L16+N16+P16+R16 -> 22678936
A17: 1.3.2 | B17: Бошқа мижозларнинг банк пластик карталаридаги маблағлари | C17: 6812095 | D17: 20674 | E17: 0 | F17: 0 | G17: 0 | H17: 0 | I17: 0 | J17: 0 | K17: 0 | L17: 0 | M17: 0 | N17: 0 | O17: 0 | P17: 0 | Q17: 0 | R17: 0 | S17: =+C17+E17+G17+I17+K17+M17+O17+Q17 -> 6812095 | T17: =+S17-U17 -> 6791421 | U17: =+D17+F17+H17+J17+L17+N17+P17+R17 -> 20674
A18: 1.3.3 | B18: Мижозларнинг аккредитив бўйича депозитлари | C18: 0 | D18: 0 | E18: 0 | F18: 0 | G18: 0 | H18: 0 | I18: 1005518 | J18: 1005518 | K18: 3840797 | L18: 3840797 | M18: 0 | N18: 0 | O18: 0 | P18: 0 | Q18: 0 | R18: 0 | S18: =+C18+E18+G18+I18+K18+M18+O18+Q18 -> 4846315 | T18: =+S18-U18 -> 0 | U18: =+D18+F18+H18+J18+L18+N18+P18+R18 -> 4846315
A19: 1.3.4 | B19: Бошқалар | C19: 18107597 | D19: 4292191 | E19: 0 | F19: 0 | G19: 0 | H19: 0 | I19: 0 | J19: 0 | K19: 0 | L19: 0 | M19: 0 | N19: 0 | O19: 0 | P19: 0 | Q19: 0 | R19: 0 | S19: =+C19+E19+G19+I19+K19+M19+O19+Q19 -> 18107597 | T19: =+S19-U19 -> 13815406 | U19: =+D19+F19+H19+J19+L19+N19+P19+R19 -> 4292191
A20: 1.4 | B20: Жами депозитлар | C20: =+C7+C12+C15 -> 926831265 | D20: =+D7+D12+D15 -> 63766770 | E20: =+E7+E12+E15 -> 238212391 | F20: =+F7+F12+F15 -> 0 | G20: =+G7+G12+G15 -> 132243992 | H20: =+H7+H12+H15 -> 0 | I20: =+I7+I12+I15 -> 775748181 | J20: =+J7+J12+J15 -> 1662594 | ... R20: =+R7+R12+R15 -> 20939482 | S20: =+C20+E20+G20+I20+K20+M20+O20+Q20 -> 9726669160 | T20: =+S20-U20 -> 8904659878 | U20: =+D20+F20+H20+J20+L20+N20+P20+R20 -> 822009282 | V20: 0.15 | W20: =+X20+'Bank Liabilities Analysis (нац)'!M21 -> 1459000374 | X20: =(U20-(J46+L46+N46+P46+R46))*V20 -> 1.2330139e+08 | Y20: =+'Deposits by Client'!C22 -> 9726669160 | Z20: =+Y20-AA20 -> 8904659878 | AA20: =+'Deposits by Client'!D22 -> 822009282
A21: 2. | B21: Марказий банкка тўланиши лозим бўлган маблағлар | C21: 442535 | D21: 0 | E21: 0 | F21: 0 | G21: 0 | H21: 0 | I21: 0 | J21: 0 | K21: 0 | L21: 0 | M21: 0 | N21: 0 | O21: 0 | P21: 0 | Q21: 0 | R21: 0 | S21: =+C21+E21+G21+I21+K21+M21+O21+Q21 -> 442535 | T21: =+S21-U21 -> 442535 | U21: =+D21+F21+H21+J21+L21+N21+P21+R21 -> 0 | V21: 1 | W21: =(C21+E21+G21-C22-E22-G22)*V21 -> 0 | X21: =(D21+F21+H21-D22-F22-H22)*V21 -> 0 | Y21: =+S20-Y20 -> 0 | Z21: =+T20-Z20 -> 0 | AA21: =+U20-AA20 -> 0
A22: 2.1. | B22: шу жумладан, Марказий банкка тўланиши лозим бўлган маблағлар -Тезкор тўловлар ҳамда клиринг тизимлари | C22: 442535 | D22: 0 | E22: 0 | F22: 0 | G22: 0 | H22: 0 | I22: 0 | J22: 0 | K22: 0 | L22: 0 | M22: 0 | N22: 0 | O22: 0 | P22: 0 | Q22: 0 | R22: 0 | S22: =+C22+E22+G22+I22+K22+M22+O22+Q22 -> 442535 | T22: =+S22-U22 -> 442535 | U22: =+D22+F22+H22+J22+L22+N22+P22+R22 -> 0
A23: 3. | B23: Бошқа банклар ва молиявий ташкилотларга тўланиши лозим бўлган маблағлар | C23: =SUM(C24:C28)-C25 -> 32703 | D23: =SUM(D24:D28)-D25 -> 168 | E23: =SUM(E24:E28)-E25 -> 2600000 | F23: =SUM(F24:F28)-F25 -> 0 | G23: =SUM(G24:G28)-G25 -> 212433450 | H23: =SUM(H24:H28)-H25 -> 212433450 | I23: =SUM(I24:I28)-I25 -> 703020867 | J23: =SUM(J24:J28)-J25 -> 0 | ... R23: =SUM(R24:R28)-R25 -> 209083084 | S23: =+C23+E23+G23+I23+K23+M23+O23+Q23 -> 2044939904 | T23: =+S23-U23 -> 1550743496 | U23: =+D23+F23+H23+J23+L23+N23+P23+R23 -> 494196408
A24: 3.1 | B24: Бошқа банкларнинг вакиллик ҳисобварақларига тўланиши лозим бўлган маблағлар | C24: 0 | D24: 0 | S24: =+C24 -> 0 | T24: =+S24-U24 -> 0 | U24: =+D24 -> 0 | V24: 1 | W24: =X24+'Bank Liabilities Analysis (нац)'!M25 -> 0 | X24: =(U24-U25)*V24 -> 0
A25: 3.1.1 | B25: шу жумладан, махаллий банкларнинг вакиллик ҳисобварақларига тўланиши лозим бўлган маблағлар | C25: 0 | D25: 0 | S25: =+C25 -> 0 | T25: =+S25-U25 -> 0 | U25: =+D25 -> 0 | V25: 1 | W25: =(U25*V25) -> 0 | X25: =(U25*V25) -> 0
A26: 3.2 | B26: Бошқа банкларнинг ҳисобварақлари - Депозитлар | C26: 0 | D26: 0 | E26: 2600000 | F26: 0 | G26: 212433450 | H26: 212433450 | I26: 703020867 | J26: 0 | K26: 263404500 | L26: 70811150 | M26: 41922444 | N26: 373711 | O26: 134925207 | P26: 1494845 | Q26: 686600733 | R26: 209083084 | S26: =+C26+E26+G26+I26+K26+M26+O26+Q26 -> 2044907201 | T26: =+S26-U26 -> 1550710961 | U26: =+D26+F26+H26+J26+L26+N26+P26+R26 -> 494196240 | V26: 1 | W26: =(C26+E26+G26)*V26 -> 215033450 | X26: =(D26+F26+H26)*V26 -> 212433450
A27: 3.3 | B27: Банк карталаридан амалга оширилган тўловлар бўйича банкларга тўланиши лозим бўлган маблағлар | C27: 32703 | D27: 168 | E27: 0 | F27: 0 | G27: 0 | H27: 0 | I27: 0 | J27: 0 | K27: 0 | L27: 0 | M27: 0 | N27: 0 | O27: 0 | P27: 0 | Q27: 0 | R27: 0 | S27: =+C27+E27+G27+I27+K27+M27+O27+Q27 -> 32703 | T27: =+S27-U27 -> 32535 | U27: =+D27+F27+H27+J27+L27+N27+P27+R27 -> 168 | V27: 1 | W27: =(C27+E27+G27)*V27 -> 32703 | X27: =(D27+F27+H27)*V27 -> 168
A28: 3.4 | B28: Бошқа моддалар | C28: 0 | D28: 0 | E28: 0 | F28: 0 | G28: 0 | H28: 0 | I28: 0 | J28: 0 | K28: 0 | L28: 0 | M28: 0 | N28: 0 | O28: 0 | P28: 0 | Q28: 0 | R28: 0 | S28: =+C28+E28+G28+I28+K28+M28+O28+Q28 -> 0 | T28: =+S28-U28 -> 0 | U28: =+D28+F28+H28+J28+L28+N28+P28+R28 -> 0 | V28: 1 | W28: =(C28+E28+G28)*V28 -> 0 | X28: =(D28+F28+H28)*V28 -> 0
A29: 4. | B29: Банкнинг тўланмаган акцептлари | C29: 15502130 | D29: 15502130 | E29: 0 | F29: 0 | G29: 0 | H29: 0 | I29: 0 | J29: 0 | K29: 0 | L29: 0 | M29: 0 | N29: 0 | O29: 0 | P29: 0 | Q29: 0 | R29: 0 | S29: =+C29+E29+G29+I29+K29+M29+O29+Q29 -> 15502130 | T29: =+S29-U29 -> 0 | U29: =+D29+F29+H29+J29+L29+N29+P29+R29 -> 15502130 | V29: 1 | W29: =(C29+E29+G29)*V29 -> 15502130 | X29: =(D29+F29+H29)*V29 -> 15502130
A30: 5. | B30: Олинган кредит ва лизинглар (молиявий ижара) бўйича мажбуриятлар | C30: 2359851 | D30: 0 | E30: 11390347 | F30: 8181293 | G30: 15862148 | H30: 757343 | I30: 220549033 | J30: 62353679 | K30: 1242307752 | L30: 836032374 | M30: 2936800925 | N30: 2497085738 | O30: 2178630944 | P30: 1443842355 | Q30: 5475452501 | R30: 1562846620 | S30: =+C30+E30+G30+I30+K30+M30+O30+Q30 -> 12083353501 | T30: =+S30-U30 -> 5672254099 | U30: =+D30+F30+H30+J30+L30+N30+P30+R30 -> 6411099402 | V30: 0.05 | W30: =X30+'Bank Liabilities Analysis (нац)'!M31 -> 6.025643e+08 | X30: =(U30-(J51+L51+N51+P51+R51))*V30 -> 3.1895159e+08
A31: 6. | B31: Банк томонидан чиқарилган қимматли қоғозлар | C31: 0 | D31: 0 | E31: 0 | F31: 0 | G31: 0 | H31: 0 | I31: 0 | J31: 0 | K31: 0 | L31: 0 | M31: 0 | N31: 0 | O31: 0 | P31: 0 | Q31: 0 | R31: 0 | S31: =+C31+E31+G31+I31+K31+M31+O31+Q31 -> 0 | T31: =+S31-U31 -> 0 | U31: =+D31+F31+H31+J31+L31+N31+P31+R31 -> 0 | V31: 1 | W31: =(C31+E31+G31)*V31 -> 0 | X31: =(D31+F31+H31)*V31 -> 0
A32: 7. | B32: Субординар қарз мажбуриятлари | C32: 0 | D32: 0 | E32: 0 | F32: 0 | G32: 0 | H32: 0 | I32: 0 | J32: 0 | K32: 0 | L32: 0 | M32: 0 | N32: 0 | O32: 0 | P32: 0 | Q32: 703058234 | R32: 0 | S32: =+C32+E32+G32+I32+K32+M32+O32+Q32 -> 703058234 | T32: =+S32-U32 -> 703058234 | U32: =+D32+F32+H32+J32+L32+N32+P32+R32 -> 0 | V32: 1 | W32: =(C32+E32+G32)*V32 -> 0 | X32: =(D32+F32+H32)*V32 -> 0
A33: 8. | B33: РЕПО битимлари бўйича сотилган қимматли қоғозлар | C33: =+C34+C35 -> 0 | D33: =+D34+D35 -> 0 | E33: =+E34+E35 -> 0 | F33: =+F34+F35 -> 0 | G33: =+G34+G35 -> 0 | H33: =+H34+H35 -> 0 | I33: =+I34+I35 -> 0 | J33: =+J34+J35 -> 0 | ... R33: =+R34+R35 -> 0 | S33: =+C33+E33+G33+I33+K33+M33+O33+Q33 -> 0 | T33: =+S33-U33 -> 0 | U33: =+D33+F33+H33+J33+L33+N33+P33+R33 -> 0
A34: 8.1 | B34: РЕПО битимлари бўйича сотилган юқори ликвидли қимматли қоғозлар | C34: 0 | D34: 0 | E34: 0 | F34: 0 | G34: 0 | H34: 0 | I34: 0 | J34: 0 | K34: 0 | L34: 0 | M34: 0 | N34: 0 | O34: 0 | P34: 0 | Q34: 0 | R34: 0 | S34: =+C34+E34+G34+I34+K34+M34+O34+Q34 -> 0 | T34: =+S34-U34 -> 0 | U34: =+D34+F34+H34+J34+L34+N34+P34+R34 -> 0 | V34: 1 | W34: =(C34+E34+G34)*V34 -> 0 | X34: =(D34+F34+H34)*V34 -> 0
A35: 8.2 | B35: РЕПО битимлари бўйича сотилган бошқа қимматли қоғозлар | C35: 0 | D35: 0 | E35: 0 | F35: 0 | G35: 0 | H35: 0 | I35: 0 | J35: 0 | K35: 0 | L35: 0 | M35: 0 | N35: 0 | O35: 0 | P35: 0 | Q35: 0 | R35: 0 | S35: =+C35+E35+G35+I35+K35+M35+O35+Q35 -> 0 | T35: =+S35-U35 -> 0 | U35: =+D35+F35+H35+J35+L35+N35+P35+R35 -> 0 | V35: 1 | W35: =(C35+E35+G35)*V35 -> 0 | X35: =(D35+F35+H35)*V35 -> 0
A36: 9. | B36: Ҳосилавий инструментлар бўйича ревальвация натижасида амалга ошмаган зарарлар ва бошқа муддати узайтирилган даромадлар | C36: 1817 | D36: 0 | E36: 0 | F36: 0 | G36: 0 | H36: 0 | I36: 0 | J36: 0 | K36: 0 | L36: 0 | M36: 0 | N36: 0 | O36: 0 | P36: 0 | Q36: 0 | R36: 0 | S36: =+C36+E36+G36+I36+K36+M36+O36+Q36 -> 1817 | T36: =+S36-U36 -> 1817 | U36: =+D36+F36+H36+J36+L36+N36+P36+R36 -> 0 | V36: 1 | W36: =(S36)*V36 -> 1817 | X36: =(U36)*V36 -> 0
A37: 10. | B37: Клиринг транзакциялари | C37: 12445613 | D37: 0 | E37: 0 | F37: 0 | G37: 0 | H37: 0 | I37: 0 | J37: 0 | K37: 0 | L37: 0 | M37: 0 | N37: 0 | O37: 0 | P37: 0 | Q37: 0 | R37: 0 | S37: =+C37+E37+G37+I37+K37+M37+O37+Q37 -> 12445613 | T37: =+S37-U37 -> 12445613 | U37: =+D37+F37+H37+J37+L37+N37+P37+R37 -> 0 | V37: 1 | W37: =(S37)*V37 -> 12445613 | X37: =(U37)*V37 -> 0
A38: 11. | B38: Тўланиши лозим бўлган ҳисобланган фоизлар | C38: 20864582 | D38: 497102 | E38: 24046427 | F38: 695830 | G38: 42448581 | H38: 32767425 | I38: 137929733 | J38: 45627438 | K38: 29774902 | L38: 12692393 | M38: 0 | N38: 0 | O38: 0 | P38: 0 | Q38: 0 | R38: 0 | S38: =+C38+E38+G38+I38+K38+M38+O38+Q38 -> 255064225 | T38: =+S38-U38 -> 162784037 | U38: =+D38+F38+H38+J38+L38+N38+P38+R38 -> 92280188 | W38: =(C38+E38+G38) -> 87359590 | X38: =D38+F38+H38 -> 33960357
A39: 11.1 | B39: Бош банк/филиалдан олинган ресурслар бўйича тўланиши лозим бўлган ҳисобланган фоизлар | C39: 2 | D39: 2 | E39: 0 | F39: 0 | G39: 0 | H39: 0 | I39: 0 | J39: 0 | K39: 0 | L39: 0 | M39: 0 | N39: 0 | O39: 0 | P39: 0 | Q39: 0 | R39: 0 | S39: =+C39+E39+G39+I39+K39+M39+O39+Q39 -> 2 | T39: =+S39-U39 -> 0 | U39: =+D39+F39+H39+J39+L39+N39+P39+R39 -> 2 | W39: =C39+E39+G39 -> 2 | X39: =D39+F39+H39 -> 2
A40: 11.2 | B40: Бошқа банкларга тўланиши лозим бўлган ҳисобланган фоизлар | C40: 0 | D40: 0 | E40: 0 | F40: 0 | G40: 797578 | H40: 618334 | I40: 0 | J40: 0 | K40: 0 | L40: 0 | M40: 0 | N40: 0 | O40: 0 | P40: 0 | Q40: 0 | R40: 0 | S40: =+C40+E40+G40+I40+K40+M40+O40+Q40 -> 797578 | T40: =+S40-U40 -> 179244 | U40: =+D40+F40+H40+J40+L40+N40+P40+R40 -> 618334 | W40: =C40+E40+G40 -> 797578 | X40: =D40+F40+H40 -> 618334
A41: 12. | B41: Бошқа мажбуриятлар | C41: 136086763 | D41: 13239074 | E41: 0 | F41: 0 | G41: 0 | H41: 0 | I41: 0 | J41: 0 | K41: 0 | L41: 0 | M41: 0 | N41: 0 | O41: 11214772 | P41: 933316 | Q41: 0 | R41: 0 | S41: =+C41+E41+G41+I41+K41+M41+O41+Q41 -> 147301535 | T41: =+S41-U41 -> 133129145 | U41: =+D41+F41+H41+J41+L41+N41+P41+R41 -> 14172390 | V41: 1 | W41: =(C41+E41+G41)*V41 -> 136086763 | X41: =(D41+F41+H41)*V41 -> 13239074
A42: 13 | B42: ЖАМИ МАЖБУРИЯТЛАР | C42: =+C20+C21+C23+C29+C30+C31+C32+C33+C36+C37+C38+C39+C40+C41 -> 1114567261 | D42: =+D20+D21+D23+D29+D30+D31+D32+D33+D36+D37+D38+D39+D40+D41 -> 93005246 | E42: =+E20+E21+E23+E29+E30+E31+E32+E33+E36+E37+E38+E39+E40+E41 -> 276249165 | F42: =+F20+F21+F23+F29+F30+F31+F32+F33+F36+F37+F38+F39+F40+F41 -> 8877123 | G42: =+G20+G21+G23+G29+G30+G31+G32+G33+G36+G37+G38+G39+G40+G41 -> 403785749 | H42: =+H20+H21+H23+H29+H30+H31+H32+H33+H36+H37+H38+H39+H40+H41 -> 246576552 | I42: =+I20+I21+I23+I29+I30+I31+I32+I33+I36+I37+I38+I39+I40+I41 -> 1837247814 | J42: =+J20+J21+J23+J29+J30+J31+J32+J33+J36+J37+J38+J39+J40+J41 -> 109643711 | ... U42: =+U20+U21+U23+U29+U30+U31+U32+U33+U36+U37+U38+U39+U40+U41 -> 7849878136 | V42: отток | W42: =SUM(W8:W41) -> 2.5288243e+09 | X42: =SUM(X8:X41) -> 7.180065e+08 | Y42: =+Balance!C63 -> 24989576234 | Z42: =+Balance!D63 -> 17139698098 | AA42: =+Balance!E63 -> 7849878136
B43: шундан, | S43: =+C43+E43+G43+I43+K43+M43+O43+Q43 -> 0 | T43: =+S43-U43 -> 0 | U43: =+D43+F43+H43+J43+L43+N43+P43+R43 -> 0 | Y43: =+S42-Y42 -> 0 | Z43: =+T42-Z42 -> 0 | AA43: =+U42-AA42 -> 0
B44: Ўзбекистон Республикаси Молия вазирлиги маблағлари, шундан | C44: =+C45+C46 -> 0 | D44: =+D45+D46 -> 0 | E44: =+E45+E46 -> 9547130 | F44: =+F45+F46 -> 0 | G44: =+G45+G46 -> 51044732 | H44: =+H45+H46 -> 0 | I44: =+I45+I46 -> 23138745 | J44: =+J45+J46 -> 0 | ... R44: =+R45+R46 -> 38652846 | S44: =+C44+E44+G44+I44+K44+M44+O44+Q44 -> 2405828683 | T44: =+S44-U44 -> 2351714698 | U44: =+D44+F44+H44+J44+L44+N44+P44+R44 -> 54113985
B45: Кредит ва лизинглар | C45: 0 | D45: 0 | E45: 0 | F45: 0 | G45: 592378 | H45: 0 | I45: 1305254 | J45: 0 | K45: 1835535 | L45: 0 | M45: 3862994 | N45: 0 | O45: 23552264 | P45: 15461139 | Q45: 46630201 | R45: 38652846 | S45: =+C45+E45+G45+I45+K45+M45+O45+Q45 -> 77778626 | T45: =+S45-U45 -> 23664641 | U45: =+D45+F45+H45+J45+L45+N45+P45+R45 -> 54113985
B46: Депозит маблағлар | C46: 0 | D46: 0 | E46: 9547130 | F46: 0 | G46: 50452354 | H46: 0 | I46: 21833491 | J46: 0 | K46: 109333804 | L46: 0 | M46: 63555261 | N46: 0 | O46: 47991138 | P46: 0 | Q46: 2025336879 | R46: 0 | S46: =+C46+E46+G46+I46+K46+M46+O46+Q46 -> 2328050057 | T46: =+S46-U46 -> 2328050057 | U46: =+D46+F46+H46+J46+L46+N46+P46+R46 -> 0 | Y46: 20202, 20402, 20602
B47: Бюджетдан ташқари фондларнинг маблағлари, шундан | C47: =+C48+C49 -> 51817 | D47: =+D48+D49 -> 0 | E47: =+E48+E49 -> 96360 | F47: =+F48+F49 -> 0 | G47: =+G48+G49 -> 5654062 | H47: =+H48+H49 -> 0 | I47: =+I48+I49 -> 10776489 | J47: =+J48+J49 -> 0 | ... R47: =+R48+R49 -> 0 | S47: =+C47+E47+G47+I47+K47+M47+O47+Q47 -> 314276381 | T47: =+S47-U47 -> 314276381 | U47: =+D47+F47+H47+J47+L47+N47+P47+R47 -> 0
B48: Кредит ва лизинглар | C48: 51817 | D48: 0 | E48: 96360 | F48: 0 | G48: 5654062 | H48: 0 | I48: 10776489 | J48: 0 | K48: 14716105 | L48: 0 | M48: 29002325 | N48: 0 | O48: 51121788 | P48: 0 | Q48: 154907435 | R48: 0 | S48: =+C48+E48+G48+I48+K48+M48+O48+Q48 -> 266326381 | T48: =+S48-U48 -> 266326381 | U48: =+D48+F48+H48+J48+L48+N48+P48+R48 -> 0
B49: Депозит маблағлар | C49: 0 | D49: 0 | E49: 0 | F49: 0 | G49: 0 | H49: 0 | I49: 0 | J49: 0 | K49: 15000000 | L49: 0 | M49: 14000000 | N49: 0 | O49: 18950000 | P49: 0 | Q49: 0 | R49: 0 | S49: =+C49+E49+G49+I49+K49+M49+O49+Q49 -> 47950000 | T49: =+S49-U49 -> 47950000 | U49: =+D49+F49+H49+J49+L49+N49+P49+R49 -> 0
B50: Ўзбекистон тикланиш ва тараққиёт фонди (ФРРУ), шундан | C50: =+C51+C52 -> 0 | D50: =+D51+D52 -> 0 | E50: =+E51+E52 -> 0 | F50: =+F51+F52 -> 0 | G50: =+G51+G52 -> 0 | H50: =+H51+H52 -> 0 | I50: =+I51+I52 -> 46295181 | J50: =+J51+J52 -> 334037 | ... R50: =+R51+R52 -> 30731399 | S50: =+C50+E50+G50+I50+K50+M50+O50+Q50 -> 1910716929 | T50: =+S50-U50 -> 1878649382 | U50: =+D50+F50+H50+J50+L50+N50+P50+R50 -> 32067547
B51: Кредит ва лизинглар | C51: 0 | D51: 0 | E51: 0 | F51: 0 | G51: 0 | H51: 0 | I51: 46295181 | J51: 334037 | K51: 92211902 | L51: 0 | M51: 144792749 | N51: 334037 | O51: 335998745 | P51: 668074 | Q51: 1291418352 | R51: 30731399 | S51: =+C51+E51+G51+I51+K51+M51+O51+Q51 -> 1910716929 | T51: =+S51-U51 -> 1878649382 | U51: =+D51+F51+H51+J51+L51+N51+P51+R51 -> 32067547
B52: Депозит маблағлар | C52: 0 | D52: 0 | E52: 0 | F52: 0 | G52: 0 | H52: 0 | I52: 0 | J52: 0 | K52: 0 | L52: 0 | M52: 0 | N52: 0 | O52: 0 | P52: 0 | Q52: 0 | R52: 0 | S52: =+C52+E52+G52+I52+K52+M52+O52+Q52 -> 0 | T52: =+S52-U52 -> 0 | U52: =+D52+F52+H52+J52+L52+N52+P52+R52 -> 0
B53: Хорижий банклар, шундан | C53: =+C54+C55 -> 0 | D53: =+D54+D55 -> 0 | E53: =+E54+E55 -> 0 | F53: =+F54+F55 -> 0 | G53: =+G54+G55 -> 0 | H53: =+H54+H55 -> 0 | I53: =+I54+I55 -> 42040366 | J53: =+J54+J55 -> 42040366 | ... R53: =+R54+R55 -> 459007704 | S53: =+C53+E53+G53+I53+K53+M53+O53+Q53 -> 1921627573 | T53: =+S53-U53 -> 416095087 | U53: =+D53+F53+H53+J53+L53+N53+P53+R53 -> 1505532486
B54: Кредит ва лизинглар | C54: 0 | D54: 0 | E54: 0 | F54: 0 | G54: 0 | H54: 0 | I54: 42040366 | J54: 42040366 | K54: 234814423 | L54: 202189784 | M54: 61069263 | N54: 28444625 | O54: 850881744 | P54: 773850007 | Q54: 732821777 | R54: 459007704 | S54: =+C54+E54+G54+I54+K54+M54+O54+Q54 -> 1921627573 | T54: =+S54-U54 -> 416095087 | U54: =+D54+F54+H54+J54+L54+N54+P54+R54 -> 1505532486
B55: Депозит маблағлар | C55: 0 | D55: 0 | E55: 0 | F55: 0 | G55: 0 | H55: 0 | I55: 0 | J55: 0 | K55: 0 | L55: 0 | M55: 0 | N55: 0 | O55: 0 | P55: 0 | Q55: 0 | R55: 0 | S55: =+C55+E55+G55+I55+K55+M55+O55+Q55 -> 0 | T55: =+S55-U55 -> 0 | U55: =+D55+F55+H55+J55+L55+N55+P55+R55 -> 0
B56: Бошқа халқаро молия ташкилотлари маблағлари, шундан, | C56: =+C57+C58 -> 0 | D56: =+D57+D58 -> 0 | E56: =+E57+E58 -> 0 | F56: =+F57+F58 -> 0 | G56: =+G57+G58 -> 0 | H56: =+H57+H58 -> 0 | I56: =+I57+I58 -> 1533434 | J56: =+J57+J58 -> 801549 | ... R56: =+R57+R58 -> 976638983 | S56: =+C56+E56+G56+I56+K56+M56+O56+Q56 -> 6283562705 | T56: =+S56-U56 -> 1587648265 | U56: =+D56+F56+H56+J56+L56+N56+P56+R56 -> 4695914440
B57: Кредит ва лизинглар | C57: 0 | D57: 0 | E57: 0 | F57: 0 | G57: 0 | H57: 0 | I57: 1533434 | J57: 801549 | K57: 645289816 | L57: 620627185 | M57: 2481172283 | N57: 2455655890 | O57: 712732874 | P57: 642190833 | Q57: 2442834298 | R57: 976638983 | S57: =+C57+E57+G57+I57+K57+M57+O57+Q57 -> 6283562705 | T57: =+S57-U57 -> 1587648265 | U57: =+D57+F57+H57+J57+L57+N57+P57+R57 -> 4695914440
B58: Депозит маблағлар | C58: 0 | D58: 0 | E58: 0 | F58: 0 | G58: 0 | H58: 0 | I58: 0 | J58: 0 | K58: 0 | L58: 0 | M58: 0 | N58: 0 | O58: 0 | P58: 0 | Q58: 0 | R58: 0 | S58: =+C58+E58+G58+I58+K58+M58+O58+Q58 -> 0 | T58: =+S58-U58 -> 0 | U58: =+D58+F58+H58+J58+L58+N58+P58+R58 -> 0
B59: Активлар ва мажбуриятлар муддатлари мувофиқлиги таҳлили
B60: Активы | C60: ='Bank Assets Analysis'!C47-'Bank Assets Analysis'!C30-'Bank Assets Analysis'!C32-'Bank Assets Analysis'!C33-'Bank Assets Analysis'!C37-'Bank Assets Analysis'!C38-'Bank Assets Analysis'!C42-'Bank Assets Analysis'!C45 -> 3073921546 | D60: ='Bank Assets Analysis'!D47-'Bank Assets Analysis'!D30-'Bank Assets Analysis'!D32-'Bank Assets Analysis'!D33-'Bank Assets Analysis'!D37-'Bank Assets Analysis'!D38-'Bank Assets Analysis'!D42-'Bank Assets Analysis'!D45 -> 2198362368 | E60: ='Bank Assets Analysis'!E47 -> 1464748366 | F60: ='Bank Assets Analysis'!F47 -> 523262019 | G60: ='Bank Assets Analysis'!G47 -> 1321358327 | H60: ='Bank Assets Analysis'!H47 -> 637372047 | I60: ='Bank Assets Analysis'!I47 -> 1915778182 | J60: ='Bank Assets Analysis'!J47 -> 1151664227 | K60: ='Bank Assets Analysis'!K47 -> 1638324229 | L60: ='Bank Assets Analysis'!L47 -> 274736488 | ... N60: ='Bank Assets Analysis'!N47 -> 407205715 | O60: ='Bank Assets Analysis'!O47-'Bank Assets Analysis'!O37 -> 4124168976 | P60: ='Bank Assets Analysis'!P47-'Bank Assets Analysis'!P37 -> 691457738 | Q60: ='Bank Assets Analysis'!Q47-'Bank Assets Analysis'!Q37 -> 9806441385 | R60: ='Bank Assets Analysis'!R47-'Bank Assets Analysis'!R37 -> 1530776179
B61: Внебаланс | C61: =(+'Bank Assets Analysis'!C49-'Bank Assets Analysis'!C50)+('Bank Assets Analysis'!C51-'Bank Assets Analysis'!C52)+('Bank Assets Analysis'!C53-'Bank Assets Analysis'!C54) -> 68122156 | D61: =(+'Bank Assets Analysis'!D49-'Bank Assets Analysis'!D50)+('Bank Assets Analysis'!D51-'Bank Assets Analysis'!D52)+('Bank Assets Analysis'!D53-'Bank Assets Analysis'!D54) -> 1346837 | E61: =(+'Bank Assets Analysis'!E49-'Bank Assets Analysis'!E50)+('Bank Assets Analysis'!E51-'Bank Assets Analysis'!E52)+('Bank Assets Analysis'!E53-'Bank Assets Analysis'!E54) -> 543288 | F61: =(+'Bank Assets Analysis'!F49-'Bank Assets Analysis'!F50)+('Bank Assets Analysis'!F51-'Bank Assets Analysis'!F52)+('Bank Assets Analysis'!F53-'Bank Assets Analysis'!F54) -> 0 | G61: =(+'Bank Assets Analysis'!G49-'Bank Assets Analysis'!G50)+('Bank Assets Analysis'!G51-'Bank Assets Analysis'!G52)+('Bank Assets Analysis'!G53-'Bank Assets Analysis'!G54) -> 462176702 | H61: =(+'Bank Assets Analysis'!H49-'Bank Assets Analysis'!H50)+('Bank Assets Analysis'!H51-'Bank Assets Analysis'!H52)+('Bank Assets Analysis'!H53-'Bank Assets Analysis'!H54) -> 461709092 | I61: =(+'Bank Assets Analysis'!I49-'Bank Assets Analysis'!I50)+('Bank Assets Analysis'!I51-'Bank Assets Analysis'!I52)+('Bank Assets Analysis'!I53-'Bank Assets Analysis'!I54) -> 56348899 | J61: =(+'Bank Assets Analysis'!J49-'Bank Assets Analysis'!J50)+('Bank Assets Analysis'!J51-'Bank Assets Analysis'!J52)+('Bank Assets Analysis'!J53-'Bank Assets Analysis'!J54) -> 51849192 | ... R61: =(+'Bank Assets Analysis'!R49-'Bank Assets Analysis'!R50)+('Bank Assets Analysis'!R51-'Bank Assets Analysis'!R52)+('Bank Assets Analysis'!R53-'Bank Assets Analysis'!R54) -> 4.2010809e+08
B62: Мажбурият | C62: ='Bank Liabilities Analysis'!C42 -> 1114567261 | D62: ='Bank Liabilities Analysis'!D42 -> 93005246 | E62: ='Bank Liabilities Analysis'!E42 -> 276249165 | F62: ='Bank Liabilities Analysis'!F42 -> 8877123 | G62: ='Bank Liabilities Analysis'!G42 -> 403785749 | H62: ='Bank Liabilities Analysis'!H42 -> 246576552 | I62: ='Bank Liabilities Analysis'!I42 -> 1837247814 | J62: ='Bank Liabilities Analysis'!J42 -> 109643711 | ... R62: ='Bank Liabilities Analysis'!R42 -> 1792869186
B63: GAP | C63: =+C60-C62-C61 -> 1891232129 | D63: =+D60-D62-D61 -> 2104010285 | E63: =+E60-E62-E61 -> 1187955913 | F63: =+F60-F62-F61 -> 514384896 | G63: =+G60-G62-G61 -> 455395876 | H63: =+H60-H62-H61 -> -70913597 | I63: =+I60-I62-I61 -> 22181469 | J63: =+J60-J62-J61 -> 990171324 | ... R63: =+R60-R62-R61 -> -6.822011e+08
B64: кум Gap | C64: =+C63 -> 1891232129 | D64: =+D63 -> 2104010285 | E64: =E63+C64 -> 3079188042 | F64: =+F63+D64 -> 2618395181 | G64: =G63+E64 -> 3534583918 | H64: =+H63+F64 -> 2547481584 | I64: =I63+G64 -> 3556765387 | J64: =+J63+H64 -> 3537652908 | K64: =K63+I64 -> 1587289855 | L64: =+L63+J64 -> 2502978281 | M64: =M63+K64 -> -1320570573 | N64: =+N63+L64 -> -158586687 | O64: =O63+M64 -> -1.1321029e+09 | P64: =+P63+N64 -> -1374987829 | Q64: =Q63+O64 -> -1.1116679e+09 | R64: =+R63+P64 -> -2.0571889e+09
B66: Бошқарув Раис имзоси:
B68: Бош бухгалтер имзоси:

Sheet Bank Liabilities Analysis (нац)
A2: МИЛЛИЙ ВАЛЮТАДА БАНК МАЖБУРИЯТЛАРИ ТАҲЛИЛИ | L2: 18 А-жадвал
B3: =Balance!B3 -> "MKBANK" | K3: =+Balance!D3 -> 46021 | M3: =+Balance!E3 -> минг сўмда
A4: № | B4: Кўрсаткичлар | C4: Сўндириш муддати (кунларда) | K4: Жами | L4: Ликвидлиликни қоплаш меёри ҳисоб китоби
C5: Муддатсиз | D5: 1 дан 7 гача | E5: 8 дан 30 гача | F5: 31 дан 90 гача | G5: 91 дан 180 гача | H5: 181 дан 365 гача | I5: 366 дан 730 гача | J5: 2 йилдан ортиқ
L6: Коэффициент | M6: 30 кунлик чиқим суммаси
A7: 1. | B7: ДЕПОЗИТЛАР
A8: 1.1 | B8: Талаб қилиб олингунча депозитлар | C8: =SUM(C9:C12) -> 534414070 | D8: =SUM(D9:D12) -> 0 | E8: =SUM(E9:E12) -> 0 | F8: =SUM(F9:F12) -> 0 | G8: =SUM(G9:G12) -> 0 | H8: =SUM(H9:H12) -> 0 | I8: =SUM(I9:I12) -> 0 | J8: =SUM(J9:J12) -> 0 | K8: =+C8+D8+E8+F8+G8+H8+I8+J8 -> 534414070
A9: 1.1.1 | B9: Aҳолининг талаб қилиб олингунча омонатлари | C9: =+'Bank Liabilities Analysis'!C8-'Bank Liabilities Analysis'!D8 -> 7866145 | D9: =+'Bank Liabilities Analysis'!E8-'Bank Liabilities Analysis'!F8 -> 0 | E9: =+'Bank Liabilities Analysis'!G8-'Bank Liabilities Analysis'!H8 -> 0 | F9: =+'Bank Liabilities Analysis'!I8-'Bank Liabilities Analysis'!J8 -> 0 | G9: =+'Bank Liabilities Analysis'!K8-'Bank Liabilities Analysis'!L8 -> 0 | H9: =+'Bank Liabilities Analysis'!M8-'Bank Liabilities Analysis'!N8 -> 0 | I9: =+'Bank Liabilities Analysis'!O8-'Bank Liabilities Analysis'!P8 -> 0 | J9: =+'Bank Liabilities Analysis'!Q8-'Bank Liabilities Analysis'!R8 -> 0 | K9: =+C9+D9+E9+F9+G9+H9+I9+J9 -> 7866145
A10: 1.1.2 | B10: Кредит таъминоти сифатида жалб этилган aҳоли омонатлари | C10: =+'Bank Liabilities Analysis'!C9-'Bank Liabilities Analysis'!D9 -> 0 | D10: =+'Bank Liabilities Analysis'!E9-'Bank Liabilities Analysis'!F9 -> 0 | E10: =+'Bank Liabilities Analysis'!G9-'Bank Liabilities Analysis'!H9 -> 0 | F10: =+'Bank Liabilities Analysis'!I9-'Bank Liabilities Analysis'!J9 -> 0 | G10: =+'Bank Liabilities Analysis'!K9-'Bank Liabilities Analysis'!L9 -> 0 | H10: =+'Bank Liabilities Analysis'!M9-'Bank Liabilities Analysis'!N9 -> 0 | I10: =+'Bank Liabilities Analysis'!O9-'Bank Liabilities Analysis'!P9 -> 0 | J10: =+'Bank Liabilities Analysis'!Q9-'Bank Liabilities Analysis'!R9 -> 0 | K10: =+C10+D10+E10+F10+G10+H10+I10+J10 -> 0
A11: 1.1.3 | B11: Кредит таъминоти сифатида жалб этилган бошқа депозитлар | C11: =+'Bank Liabilities Analysis'!C10-'Bank Liabilities Analysis'!D10 -> 0 | D11: =+'Bank Liabilities Analysis'!E10-'Bank Liabilities Analysis'!F10 -> 0 | E11: =+'Bank Liabilities Analysis'!G10-'Bank Liabilities Analysis'!H10 -> 0 | F11: =+'Bank Liabilities Analysis'!I10-'Bank Liabilities Analysis'!J10 -> 0 | G11: =+'Bank Liabilities Analysis'!K10-'Bank Liabilities Analysis'!L10 -> 0 | H11: =+'Bank Liabilities Analysis'!M10-'Bank Liabilities Analysis'!N10 -> 0 | I11: =+'Bank Liabilities Analysis'!O10-'Bank Liabilities Analysis'!P10 -> 0 | J11: =+'Bank Liabilities Analysis'!Q10-'Bank Liabilities Analysis'!R10 -> 0 | K11: =+C11+D11+E11+F11+G11+H11+I11+J11 -> 0
A12: 1.1.4 | B12: Талаб қилиб олингунча бошқа депозитлар | C12: =+'Bank Liabilities Analysis'!C11-'Bank Liabilities Analysis'!D11 -> 526547925 | D12: =+'Bank Liabilities Analysis'!E11-'Bank Liabilities Analysis'!F11 -> 0 | E12: =+'Bank Liabilities Analysis'!G11-'Bank Liabilities Analysis'!H11 -> 0 | F12: =+'Bank Liabilities Analysis'!I11-'Bank Liabilities Analysis'!J11 -> 0 | G12: =+'Bank Liabilities Analysis'!K11-'Bank Liabilities Analysis'!L11 -> 0 | H12: =+'Bank Liabilities Analysis'!M11-'Bank Liabilities Analysis'!N11 -> 0 | I12: =+'Bank Liabilities Analysis'!O11-'Bank Liabilities Analysis'!P11 -> 0 | J12: =+'Bank Liabilities Analysis'!Q11-'Bank Liabilities Analysis'!R11 -> 0 | K12: =+C12+D12+E12+F12+G12+H12+I12+J12 -> 526547925
A13: 1.2 | B13: Муддатли депозитлар | C13: =+'Bank Liabilities Analysis'!C12-'Bank Liabilities Analysis'!D12 -> 13507097 | D13: =+'Bank Liabilities Analysis'!E12-'Bank Liabilities Analysis'!F12 -> 238212391 | E13: =+'Bank Liabilities Analysis'!G12-'Bank Liabilities Analysis'!H12 -> 132243992 | F13: =+'Bank Liabilities Analysis'!I12-'Bank Liabilities Analysis'!J12 -> 774085587 | G13: =+'Bank Liabilities Analysis'!K12-'Bank Liabilities Analysis'!L12 -> 1658201213 | H13: =+'Bank Liabilities Analysis'!M12-'Bank Liabilities Analysis'!N12 -> 1881373057 | I13: =+'Bank Liabilities Analysis'!O12-'Bank Liabilities Analysis'!P12 -> 1116211365 | J13: =+'Bank Liabilities Analysis'!Q12-'Bank Liabilities Analysis'!R12 -> 2241267778 | K13: =+C13+D13+E13+F13+G13+H13+I13+J13 -> 8055102480
A14: 1.2.1 | B14: Аҳоли омонатлари | C14: =+'Bank Liabilities Analysis'!C13-'Bank Liabilities Analysis'!D13 -> 11578322 | D14: =+'Bank Liabilities Analysis'!E13-'Bank Liabilities Analysis'!F13 -> 7405261 | E14: =+'Bank Liabilities Analysis'!G13-'Bank Liabilities Analysis'!H13 -> 29723296 | F14: =+'Bank Liabilities Analysis'!I13-'Bank Liabilities Analysis'!J13 -> 456902096 | G14: =+'Bank Liabilities Analysis'!K13-'Bank Liabilities Analysis'!L13 -> 581016454 | H14: =+'Bank Liabilities Analysis'!M13-'Bank Liabilities Analysis'!N13 -> 765903579 | I14: =+'Bank Liabilities Analysis'!O13-'Bank Liabilities Analysis'!P13 -> 740027964 | J14: =+'Bank Liabilities Analysis'!Q13-'Bank Liabilities Analysis'!R13 -> 83305899 | K14: =+C14+D14+E14+F14+G14+H14+I14+J14 -> 2675862871
A15: 1.2.2 | B15: Чиқарилган депозит сертификатлари | C15: =+'Bank Liabilities Analysis'!C14-'Bank Liabilities Analysis'!D14 -> 0 | D15: =+'Bank Liabilities Analysis'!E14-'Bank Liabilities Analysis'!F14 -> 0 | E15: =+'Bank Liabilities Analysis'!G14-'Bank Liabilities Analysis'!H14 -> 0 | F15: =+'Bank Liabilities Analysis'!I14-'Bank Liabilities Analysis'!J14 -> 0 | G15: =+'Bank Liabilities Analysis'!K14-'Bank Liabilities Analysis'!L14 -> 0 | H15: =+'Bank Liabilities Analysis'!M14-'Bank Liabilities Analysis'!N14 -> 0 | I15: =+'Bank Liabilities Analysis'!O14-'Bank Liabilities Analysis'!P14 -> 0 | J15: =+'Bank Liabilities Analysis'!Q14-'Bank Liabilities Analysis'!R14 -> 0 | K15: =+C15+D15+E15+F15+G15+H15+I15+J15 -> 0
A16: 1.3 | B16: Мижозларнинг бошқа депозитлари | C16: =SUM(C17:C20) -> 315143328 | D16: =SUM(D17:D20) -> 0 | E16: =SUM(E17:E20) -> 0 | F16: =SUM(F17:F20) -> 0 | G16: =SUM(G17:G20) -> 0 | H16: =SUM(H17:H20) -> 0 | I16: =SUM(I17:I20) -> 0 | J16: =SUM(J17:J20) -> 0 | K16: =+C16+D16+E16+F16+G16+H16+I16+J16 -> 315143328
A17: 1.3.1 | B17: Жисмоний шахсларнинг банк пластик карталаридаги маблағлари | C17: =+'Bank Liabilities Analysis'!C16-'Bank Liabilities Analysis'!D16 -> 294536501 | D17: =+'Bank Liabilities Analysis'!E16-'Bank Liabilities Analysis'!F16 -> 0 | E17: =+'Bank Liabilities Analysis'!G16-'Bank Liabilities Analysis'!H16 -> 0 | F17: =+'Bank Liabilities Analysis'!I16-'Bank Liabilities Analysis'!J16 -> 0 | G17: =+'Bank Liabilities Analysis'!K16-'Bank Liabilities Analysis'!L16 -> 0 | H17: =+'Bank Liabilities Analysis'!M16-'Bank Liabilities Analysis'!N16 -> 0 | I17: =+'Bank Liabilities Analysis'!O16-'Bank Liabilities Analysis'!P16 -> 0 | J17: =+'Bank Liabilities Analysis'!Q16-'Bank Liabilities Analysis'!R16 -> 0 | K17: =+C17+D17+E17+F17+G17+H17+I17+J17 -> 294536501
A18: 1.3.2 | B18: Бошқа мижозларнинг банк пластик карталаридаги маблағлари | C18: =+'Bank Liabilities Analysis'!C17-'Bank Liabilities Analysis'!D17 -> 6791421 | D18: =+'Bank Liabilities Analysis'!E17-'Bank Liabilities Analysis'!F17 -> 0 | E18: =+'Bank Liabilities Analysis'!G17-'Bank Liabilities Analysis'!H17 -> 0 | F18: =+'Bank Liabilities Analysis'!I17-'Bank Liabilities Analysis'!J17 -> 0 | G18: =+'Bank Liabilities Analysis'!K17-'Bank Liabilities Analysis'!L17 -> 0 | H18: =+'Bank Liabilities Analysis'!M17-'Bank Liabilities Analysis'!N17 -> 0 | I18: =+'Bank Liabilities Analysis'!O17-'Bank Liabilities Analysis'!P17 -> 0 | J18: =+'Bank Liabilities Analysis'!Q17-'Bank Liabilities Analysis'!R17 -> 0 | K18: =+C18+D18+E18+F18+G18+H18+I18+J18 -> 6791421
A19: 1.3.3 | B19: Мижозларнинг аккредитив бўйича депозитлари | C19: =+'Bank Liabilities Analysis'!C18-'Bank Liabilities Analysis'!D18 -> 0 | D19: =+'Bank Liabilities Analysis'!E18-'Bank Liabilities Analysis'!F18 -> 0 | E19: =+'Bank Liabilities Analysis'!G18-'Bank Liabilities Analysis'!H18 -> 0 | F19: =+'Bank Liabilities Analysis'!I18-'Bank Liabilities Analysis'!J18 -> 0 | G19: =+'Bank Liabilities Analysis'!K18-'Bank Liabilities Analysis'!L18 -> 0 | H19: =+'Bank Liabilities Analysis'!M18-'Bank Liabilities Analysis'!N18 -> 0 | I19: =+'Bank Liabilities Analysis'!O18-'Bank Liabilities Analysis'!P18 -> 0 | J19: =+'Bank Liabilities Analysis'!Q18-'Bank Liabilities Analysis'!R18 -> 0 | K19: =+C19+D19+E19+F19+G19+H19+I19+J19 -> 0
A20: 1.3.4 | B20: Бошқалар | C20: =+'Bank Liabilities Analysis'!C19-'Bank Liabilities Analysis'!D19 -> 13815406 | D20: =+'Bank Liabilities Analysis'!E19-'Bank Liabilities Analysis'!F19 -> 0 | E20: =+'Bank Liabilities Analysis'!G19-'Bank Liabilities Analysis'!H19 -> 0 | F20: =+'Bank Liabilities Analysis'!I19-'Bank Liabilities Analysis'!J19 -> 0 | G20: =+'Bank Liabilities Analysis'!K19-'Bank Liabilities Analysis'!L19 -> 0 | H20: =+'Bank Liabilities Analysis'!M19-'Bank Liabilities Analysis'!N19 -> 0 | I20: =+'Bank Liabilities Analysis'!O19-'Bank Liabilities Analysis'!P19 -> 0 | J20: =+'Bank Liabilities Analysis'!Q19-'Bank Liabilities Analysis'!R19 -> 0 | K20: =+C20+D20+E20+F20+G20+H20+I20+J20 -> 13815406
A21: 1.4 | B21: Жами депозитлар | C21: =+C8+C13+C16 -> 863064495 | D21: =+D8+D13+D16 -> 238212391 | E21: =+E8+E13+E16 -> 132243992 | F21: =+F8+F13+F16 -> 774085587 | G21: =+G8+G13+G16 -> 1658201213 | H21: =+H8+H13+H16 -> 1881373057 | I21: =+I8+I13+I16 -> 1116211365 | J21: =+J8+J13+J16 -> 2241267778 | K21: =+C21+D21+E21+F21+G21+H21+I21+J21 -> 8904659878 | L21: 0.15 | M21: =+K21*L21 -> 1.335699e+09
A22: 2. | B22: Марказий банкка тўланиши лозим бўлган маблағлар | C22: =+'Bank Liabilities Analysis'!C21-'Bank Liabilities Analysis'!D21 -> 442535 | D22: =+'Bank Liabilities Analysis'!E21-'Bank Liabilities Analysis'!F21 -> 0 | E22: =+'Bank Liabilities Analysis'!G21-'Bank Liabilities Analysis'!H21 -> 0 | F22: =+'Bank Liabilities Analysis'!I21-'Bank Liabilities Analysis'!J21 -> 0 | G22: =+'Bank Liabilities Analysis'!K21-'Bank Liabilities Analysis'!L21 -> 0 | H22: =+'Bank Liabilities Analysis'!M21-'Bank Liabilities Analysis'!N21 -> 0 | I22: =+'Bank Liabilities Analysis'!O21-'Bank Liabilities Analysis'!P21 -> 0 | J22: =+'Bank Liabilities Analysis'!Q21-'Bank Liabilities Analysis'!R21 -> 0 | K22: =+C22+D22+E22+F22+G22+H22+I22+J22 -> 442535 | L22: 1 | M22: =(C22+D22+E22-C23-D23-E23)*L22 -> 0
A23: 2.1. | B23: шу жумладан, Марказий банкка тўланиши лозим бўлган маблағлар -Тезкор тўловлар ҳамда клиринг тизими | C23: =+'Bank Liabilities Analysis'!C22-'Bank Liabilities Analysis'!D22 -> 442535 | D23: =+'Bank Liabilities Analysis'!E22-'Bank Liabilities Analysis'!F22 -> 0 | E23: =+'Bank Liabilities Analysis'!G22-'Bank Liabilities Analysis'!H22 -> 0 | F23: =+'Bank Liabilities Analysis'!I22-'Bank Liabilities Analysis'!J22 -> 0 | G23: =+'Bank Liabilities Analysis'!K22-'Bank Liabilities Analysis'!L22 -> 0 | H23: =+'Bank Liabilities Analysis'!M22-'Bank Liabilities Analysis'!N22 -> 0 | I23: =+'Bank Liabilities Analysis'!O22-'Bank Liabilities Analysis'!P22 -> 0 | J23: =+'Bank Liabilities Analysis'!Q22-'Bank Liabilities Analysis'!R22 -> 0 | K23: =+C23+D23+E23+F23+G23+H23+I23+J23 -> 442535
A24: 3. | B24: Бошқа банклар ва молиявий ташкилотларга тўланиши лозим бўлган маблағлар | C24: =SUM(C25:C29)-C26 -> 32535 | D24: =SUM(D25:D29)-D26 -> 2600000 | E24: =SUM(E25:E29)-E26 -> 0 | F24: =SUM(F25:F29)-F26 -> 703020867 | G24: =SUM(G25:G29)-G26 -> 192593350 | H24: =SUM(H25:H29)-H26 -> 41548733 | I24: =SUM(I25:I29)-I26 -> 133430362 | J24: =SUM(J25:J29)-J26 -> 477517649 | K24: =+C24+D24+E24+F24+G24+H24+I24+J24 -> 1550743496
A25: 3.1 | B25: Бошқа банкларнинг вакиллик ҳисобварақларига тўланиши лозим бўлган маблағлар | C25: =+'Bank Liabilities Analysis'!C24-'Bank Liabilities Analysis'!D24 -> 0 | D25: =+'Bank Liabilities Analysis'!E24-'Bank Liabilities Analysis'!F24 -> 0 | E25: =+'Bank Liabilities Analysis'!G24-'Bank Liabilities Analysis'!H24 -> 0 | F25: =+'Bank Liabilities Analysis'!I24-'Bank Liabilities Analysis'!J24 -> 0 | G25: =+'Bank Liabilities Analysis'!K24-'Bank Liabilities Analysis'!L24 -> 0 | H25: =+'Bank Liabilities Analysis'!M24-'Bank Liabilities Analysis'!N24 -> 0 | I25: =+'Bank Liabilities Analysis'!O24-'Bank Liabilities Analysis'!P24 -> 0 | J25: =+'Bank Liabilities Analysis'!Q24-'Bank Liabilities Analysis'!R24 -> 0 | K25: =+C25+D25+E25+F25+G25+H25+I25+J25 -> 0 | L25: 1 | M25: =C25*L25 -> 0
A26: 3.1.1 | B26: шу жумладан, махаллий банкларнинг вакиллик ҳисобварақларига тўланиши лозим бўлган маблағлар | C26: =+'Bank Liabilities Analysis'!C25-'Bank Liabilities Analysis'!D25 -> 0 | D26: =+'Bank Liabilities Analysis'!E25-'Bank Liabilities Analysis'!F25 -> 0 | E26: =+'Bank Liabilities Analysis'!G25-'Bank Liabilities Analysis'!H25 -> 0 | F26: =+'Bank Liabilities Analysis'!I25-'Bank Liabilities Analysis'!J25 -> 0 | G26: =+'Bank Liabilities Analysis'!K25-'Bank Liabilities Analysis'!L25 -> 0 | H26: =+'Bank Liabilities Analysis'!M25-'Bank Liabilities Analysis'!N25 -> 0 | I26: =+'Bank Liabilities Analysis'!O25-'Bank Liabilities Analysis'!P25 -> 0 | J26: =+'Bank Liabilities Analysis'!Q25-'Bank Liabilities Analysis'!R25 -> 0 | K26: =+C26+D26+E26+F26+G26+H26+I26+J26 -> 0
A27: 3.2 | B27: Бошқа банкларнинг ҳисобварақлари - Депозитлар | C27: =+'Bank Liabilities Analysis'!C26-'Bank Liabilities Analysis'!D26 -> 0 | D27: =+'Bank Liabilities Analysis'!E26-'Bank Liabilities Analysis'!F26 -> 2600000 | E27: =+'Bank Liabilities Analysis'!G26-'Bank Liabilities Analysis'!H26 -> 0 | F27: =+'Bank Liabilities Analysis'!I26-'Bank Liabilities Analysis'!J26 -> 703020867 | G27: =+'Bank Liabilities Analysis'!K26-'Bank Liabilities Analysis'!L26 -> 192593350 | H27: =+'Bank Liabilities Analysis'!M26-'Bank Liabilities Analysis'!N26 -> 41548733 | I27: =+'Bank Liabilities Analysis'!O26-'Bank Liabilities Analysis'!P26 -> 133430362 | J27: =+'Bank Liabilities Analysis'!Q26-'Bank Liabilities Analysis'!R26 -> 477517649 | K27: =+C27+D27+E27+F27+G27+H27+I27+J27 -> 1550710961 | L27: 1 | M27: =(C27+D27+E27)*L27 -> 2600000
A28: 3.3 | B28: Банк карталаридан амалга оширилган тўловлар бўйича банкларга тўланиши лозим бўлган маблағлар | C28: =+'Bank Liabilities Analysis'!C27-'Bank Liabilities Analysis'!D27 -> 32535 | D28: =+'Bank Liabilities Analysis'!E27-'Bank Liabilities Analysis'!F27 -> 0 | E28: =+'Bank Liabilities Analysis'!G27-'Bank Liabilities Analysis'!H27 -> 0 | F28: =+'Bank Liabilities Analysis'!I27-'Bank Liabilities Analysis'!J27 -> 0 | G28: =+'Bank Liabilities Analysis'!K27-'Bank Liabilities Analysis'!L27 -> 0 | H28: =+'Bank Liabilities Analysis'!M27-'Bank Liabilities Analysis'!N27 -> 0 | I28: =+'Bank Liabilities Analysis'!O27-'Bank Liabilities Analysis'!P27 -> 0 | J28: =+'Bank Liabilities Analysis'!Q27-'Bank Liabilities Analysis'!R27 -> 0 | K28: =+C28+D28+E28+F28+G28+H28+I28+J28 -> 32535 | L28: 1 | M28: =(C28+D28+E28)*L28 -> 32535
A29: 3.4 | B29: Бошқа моддалар | C29: =+'Bank Liabilities Analysis'!C28-'Bank Liabilities Analysis'!D28 -> 0 | D29: =+'Bank Liabilities Analysis'!E28-'Bank Liabilities Analysis'!F28 -> 0 | E29: =+'Bank Liabilities Analysis'!G28-'Bank Liabilities Analysis'!H28 -> 0 | F29: =+'Bank Liabilities Analysis'!I28-'Bank Liabilities Analysis'!J28 -> 0 | G29: =+'Bank Liabilities Analysis'!K28-'Bank Liabilities Analysis'!L28 -> 0 | H29: =+'Bank Liabilities Analysis'!M28-'Bank Liabilities Analysis'!N28 -> 0 | I29: =+'Bank Liabilities Analysis'!O28-'Bank Liabilities Analysis'!P28 -> 0 | J29: =+'Bank Liabilities Analysis'!Q28-'Bank Liabilities Analysis'!R28 -> 0 | K29: =+C29+D29+E29+F29+G29+H29+I29+J29 -> 0 | L29: 1 | M29: =(C29+D29+E29)*L29 -> 0
A30: 4. | B30: Банкнинг тўланмаган акцептлари | C30: =+'Bank Liabilities Analysis'!C29-'Bank Liabilities Analysis'!D29 -> 0 | D30: =+'Bank Liabilities Analysis'!E29-'Bank Liabilities Analysis'!F29 -> 0 | E30: =+'Bank Liabilities Analysis'!G29-'Bank Liabilities Analysis'!H29 -> 0 | F30: =+'Bank Liabilities Analysis'!I29-'Bank Liabilities Analysis'!J29 -> 0 | G30: =+'Bank Liabilities Analysis'!K29-'Bank Liabilities Analysis'!L29 -> 0 | H30: =+'Bank Liabilities Analysis'!M29-'Bank Liabilities Analysis'!N29 -> 0 | I30: =+'Bank Liabilities Analysis'!O29-'Bank Liabilities Analysis'!P29 -> 0 | J30: =+'Bank Liabilities Analysis'!Q29-'Bank Liabilities Analysis'!R29 -> 0 | K30: =+C30+D30+E30+F30+G30+H30+I30+J30 -> 0 | L30: 1 | M30: =(C30+D30+E30)*L30 -> 0
A31: 5. | B31: Олинган кредит ва лизинглар (молиявий ижара) бўйича мажбуриятлар | C31: =+'Bank Liabilities Analysis'!C30-'Bank Liabilities Analysis'!D30 -> 2359851 | D31: =+'Bank Liabilities Analysis'!E30-'Bank Liabilities Analysis'!F30 -> 3209054 | E31: =+'Bank Liabilities Analysis'!G30-'Bank Liabilities Analysis'!H30 -> 15104805 | F31: =+'Bank Liabilities Analysis'!I30-'Bank Liabilities Analysis'!J30 -> 158195354 | G31: =+'Bank Liabilities Analysis'!K30-'Bank Liabilities Analysis'!L30 -> 406275378 | H31: =+'Bank Liabilities Analysis'!M30-'Bank Liabilities Analysis'!N30 -> 439715187 | I31: =+'Bank Liabilities Analysis'!O30-'Bank Liabilities Analysis'!P30 -> 734788589 | J31: =+'Bank Liabilities Analysis'!Q30-'Bank Liabilities Analysis'!R30 -> 3912605881 | K31: =+C31+D31+E31+F31+G31+H31+I31+J31 -> 5672254099 | L31: 0.05 | M31: =+K31*L31 -> 2.836127e+08
A32: 6. | B32: Банк томонидан чиқарилган қимматли қоғозлар | C32: =+'Bank Liabilities Analysis'!C31-'Bank Liabilities Analysis'!D31 -> 0 | D32: =+'Bank Liabilities Analysis'!E31-'Bank Liabilities Analysis'!F31 -> 0 | E32: =+'Bank Liabilities Analysis'!G31-'Bank Liabilities Analysis'!H31 -> 0 | F32: =+'Bank Liabilities Analysis'!I31-'Bank Liabilities Analysis'!J31 -> 0 | G32: =+'Bank Liabilities Analysis'!K31-'Bank Liabilities Analysis'!L31 -> 0 | H32: =+'Bank Liabilities Analysis'!M31-'Bank Liabilities Analysis'!N31 -> 0 | I32: =+'Bank Liabilities Analysis'!O31-'Bank Liabilities Analysis'!P31 -> 0 | J32: =+'Bank Liabilities Analysis'!Q31-'Bank Liabilities Analysis'!R31 -> 0 | K32: =+C32+D32+E32+F32+G32+H32+I32+J32 -> 0 | L32: 1 | M32: =(C32+D32+E32)*L32 -> 0
A33: 7. | B33: Субординар қарз мажбуриятлари | C33: =+'Bank Liabilities Analysis'!C32-'Bank Liabilities Analysis'!D32 -> 0 | D33: =+'Bank Liabilities Analysis'!E32-'Bank Liabilities Analysis'!F32 -> 0 | E33: =+'Bank Liabilities Analysis'!G32-'Bank Liabilities Analysis'!H32 -> 0 | F33: =+'Bank Liabilities Analysis'!I32-'Bank Liabilities Analysis'!J32 -> 0 | G33: =+'Bank Liabilities Analysis'!K32-'Bank Liabilities Analysis'!L32 -> 0 | H33: =+'Bank Liabilities Analysis'!M32-'Bank Liabilities Analysis'!N32 -> 0 | I33: =+'Bank Liabilities Analysis'!O32-'Bank Liabilities Analysis'!P32 -> 0 | J33: =+'Bank Liabilities Analysis'!Q32-'Bank Liabilities Analysis'!R32 -> 703058234 | K33: =+C33+D33+E33+F33+G33+H33+I33+J33 -> 703058234 | L33: 1 | M33: =(C33+D33+E33)*L33 -> 0
A34: 8. | B34: РЕПО битимлари бўйича сотилган қимматли қоғозлар | C34: =+'Bank Liabilities Analysis'!C33-'Bank Liabilities Analysis'!D33 -> 0 | D34: =+'Bank Liabilities Analysis'!E33-'Bank Liabilities Analysis'!F33 -> 0 | E34: =+'Bank Liabilities Analysis'!G33-'Bank Liabilities Analysis'!H33 -> 0 | F34: =+'Bank Liabilities Analysis'!I33-'Bank Liabilities Analysis'!J33 -> 0 | G34: =+'Bank Liabilities Analysis'!K33-'Bank Liabilities Analysis'!L33 -> 0 | H34: =+'Bank Liabilities Analysis'!M33-'Bank Liabilities Analysis'!N33 -> 0 | I34: =+'Bank Liabilities Analysis'!O33-'Bank Liabilities Analysis'!P33 -> 0 | J34: =+'Bank Liabilities Analysis'!Q33-'Bank Liabilities Analysis'!R33 -> 0 | K34: =+C34+D34+E34+F34+G34+H34+I34+J34 -> 0
A35: 8.1 | B35: РЕПО битимлари бўйича сотилган юқори ликвидли қимматли қоғозлар | C35: =+'Bank Liabilities Analysis'!C34-'Bank Liabilities Analysis'!D34 -> 0 | D35: =+'Bank Liabilities Analysis'!E34-'Bank Liabilities Analysis'!F34 -> 0 | E35: =+'Bank Liabilities Analysis'!G34-'Bank Liabilities Analysis'!H34 -> 0 | F35: =+'Bank Liabilities Analysis'!I34-'Bank Liabilities Analysis'!J34 -> 0 | G35: =+'Bank Liabilities Analysis'!K34-'Bank Liabilities Analysis'!L34 -> 0 | H35: =+'Bank Liabilities Analysis'!M34-'Bank Liabilities Analysis'!N34 -> 0 | I35: =+'Bank Liabilities Analysis'!O34-'Bank Liabilities Analysis'!P34 -> 0 | J35: =+'Bank Liabilities Analysis'!Q34-'Bank Liabilities Analysis'!R34 -> 0 | K35: =+C35+D35+E35+F35+G35+H35+I35+J35 -> 0 | L35: 1 | M35: =(C35+D35+E35)*L35 -> 0
A36: 8.2 | B36: РЕПО битимлари бўйича сотилган бошқа қимматли қоғозлар | C36: =+'Bank Liabilities Analysis'!C35-'Bank Liabilities Analysis'!D35 -> 0 | D36: =+'Bank Liabilities Analysis'!E35-'Bank Liabilities Analysis'!F35 -> 0 | E36: =+'Bank Liabilities Analysis'!G35-'Bank Liabilities Analysis'!H35 -> 0 | F36: =+'Bank Liabilities Analysis'!I35-'Bank Liabilities Analysis'!J35 -> 0 | G36: =+'Bank Liabilities Analysis'!K35-'Bank Liabilities Analysis'!L35 -> 0 | H36: =+'Bank Liabilities Analysis'!M35-'Bank Liabilities Analysis'!N35 -> 0 | I36: =+'Bank Liabilities Analysis'!O35-'Bank Liabilities Analysis'!P35 -> 0 | J36: =+'Bank Liabilities Analysis'!Q35-'Bank Liabilities Analysis'!R35 -> 0 | K36: =+C36+D36+E36+F36+G36+H36+I36+J36 -> 0 | L36: 1 | M36: =(C36+D36+E36)*L36 -> 0
A37: 9. | B37: Ҳосилавий инструментлар бўйича ревальвация натижасида амалга ошмаган зарарлар ва бошқа муддати узайтирилган даромадлар | C37: =+'Bank Liabilities Analysis'!C36-'Bank Liabilities Analysis'!D36 -> 1817 | D37: =+'Bank Liabilities Analysis'!E36-'Bank Liabilities Analysis'!F36 -> 0 | E37: =+'Bank Liabilities Analysis'!G36-'Bank Liabilities Analysis'!H36 -> 0 | F37: =+'Bank Liabilities Analysis'!I36-'Bank Liabilities Analysis'!J36 -> 0 | G37: =+'Bank Liabilities Analysis'!K36-'Bank Liabilities Analysis'!L36 -> 0 | H37: =+'Bank Liabilities Analysis'!M36-'Bank Liabilities Analysis'!N36 -> 0 | I37: =+'Bank Liabilities Analysis'!O36-'Bank Liabilities Analysis'!P36 -> 0 | J37: =+'Bank Liabilities Analysis'!Q36-'Bank Liabilities Analysis'!R36 -> 0 | K37: =+C37+D37+E37+F37+G37+H37+I37+J37 -> 1817 | L37: 1 | M37: =+K37*L37 -> 1817
A38: 10. | B38: Клиринг транзакциялари | C38: =+'Bank Liabilities Analysis'!C37-'Bank Liabilities Analysis'!D37 -> 12445613 | D38: =+'Bank Liabilities Analysis'!E37-'Bank Liabilities Analysis'!F37 -> 0 | E38: =+'Bank Liabilities Analysis'!G37-'Bank Liabilities Analysis'!H37 -> 0 | F38: =+'Bank Liabilities Analysis'!I37-'Bank Liabilities Analysis'!J37 -> 0 | G38: =+'Bank Liabilities Analysis'!K37-'Bank Liabilities Analysis'!L37 -> 0 | H38: =+'Bank Liabilities Analysis'!M37-'Bank Liabilities Analysis'!N37 -> 0 | I38: =+'Bank Liabilities Analysis'!O37-'Bank Liabilities Analysis'!P37 -> 0 | J38: =+'Bank Liabilities Analysis'!Q37-'Bank Liabilities Analysis'!R37 -> 0 | K38: =+C38+D38+E38+F38+G38+H38+I38+J38 -> 12445613 | L38: 1 | M38: =+K38*L38 -> 12445613
A39: 11. | B39: Тўланиши лозим бўлган ҳисобланган фоизлар | C39: =+'Bank Liabilities Analysis'!C38-'Bank Liabilities Analysis'!D38 -> 20367480 | D39: =+'Bank Liabilities Analysis'!E38-'Bank Liabilities Analysis'!F38 -> 23350597 | E39: =+'Bank Liabilities Analysis'!G38-'Bank Liabilities Analysis'!H38 -> 9681156 | F39: =+'Bank Liabilities Analysis'!I38-'Bank Liabilities Analysis'!J38 -> 92302295 | G39: =+'Bank Liabilities Analysis'!K38-'Bank Liabilities Analysis'!L38 -> 17082509 | H39: =+'Bank Liabilities Analysis'!M38-'Bank Liabilities Analysis'!N38 -> 0 | I39: =+'Bank Liabilities Analysis'!O38-'Bank Liabilities Analysis'!P38 -> 0 | J39: =+'Bank Liabilities Analysis'!Q38-'Bank Liabilities Analysis'!R38 -> 0 | K39: =+C39+D39+E39+F39+G39+H39+I39+J39 -> 162784037 | M39: =+C39+D39+E39 -> 53399233
A40: 11.1 | B40: Бош банк/филиалдан олинган ресурслар бўйича тўланиши лозим бўлган ҳисобланган фоизлар | C40: =+'Bank Liabilities Analysis'!C39-'Bank Liabilities Analysis'!D39 -> 0 | D40: =+'Bank Liabilities Analysis'!E39-'Bank Liabilities Analysis'!F39 -> 0 | E40: =+'Bank Liabilities Analysis'!G39-'Bank Liabilities Analysis'!H39 -> 0 | F40: =+'Bank Liabilities Analysis'!I39-'Bank Liabilities Analysis'!J39 -> 0 | G40: =+'Bank Liabilities Analysis'!K39-'Bank Liabilities Analysis'!L39 -> 0 | H40: =+'Bank Liabilities Analysis'!M39-'Bank Liabilities Analysis'!N39 -> 0 | I40: =+'Bank Liabilities Analysis'!O39-'Bank Liabilities Analysis'!P39 -> 0 | J40: =+'Bank Liabilities Analysis'!Q39-'Bank Liabilities Analysis'!R39 -> 0 | K40: =+C40+D40+E40+F40+G40+H40+I40+J40 -> 0 | M40: =+C40+D40+E40 -> 0
A41: 11.2 | B41: Бошқа банкларга тўланиши лозим бўлган ҳисобланган фоизлар | C41: =+'Bank Liabilities Analysis'!C40-'Bank Liabilities Analysis'!D40 -> 0 | D41: =+'Bank Liabilities Analysis'!E40-'Bank Liabilities Analysis'!F40 -> 0 | E41: =+'Bank Liabilities Analysis'!G40-'Bank Liabilities Analysis'!H40 -> 179244 | F41: =+'Bank Liabilities Analysis'!I40-'Bank Liabilities Analysis'!J40 -> 0 | G41: =+'Bank Liabilities Analysis'!K40-'Bank Liabilities Analysis'!L40 -> 0 | H41: =+'Bank Liabilities Analysis'!M40-'Bank Liabilities Analysis'!N40 -> 0 | I41: =+'Bank Liabilities Analysis'!O40-'Bank Liabilities Analysis'!P40 -> 0 | J41: =+'Bank Liabilities Analysis'!Q40-'Bank Liabilities Analysis'!R40 -> 0 | K41: =+C41+D41+E41+F41+G41+H41+I41+J41 -> 179244 | M41: =+C41+D41+E41 -> 179244
A42: 12. | B42: Бошқа мажбуриятлар | C42: =+'Bank Liabilities Analysis'!C41-'Bank Liabilities Analysis'!D41 -> 122847689 | D42: =+'Bank Liabilities Analysis'!E41-'Bank Liabilities Analysis'!F41 -> 0 | E42: =+'Bank Liabilities Analysis'!G41-'Bank Liabilities Analysis'!H41 -> 0 | F42: =+'Bank Liabilities Analysis'!I41-'Bank Liabilities Analysis'!J41 -> 0 | G42: =+'Bank Liabilities Analysis'!K41-'Bank Liabilities Analysis'!L41 -> 0 | H42: =+'Bank Liabilities Analysis'!M41-'Bank Liabilities Analysis'!N41 -> 0 | I42: =+'Bank Liabilities Analysis'!O41-'Bank Liabilities Analysis'!P41 -> 10281456 | J42: =+'Bank Liabilities Analysis'!Q41-'Bank Liabilities Analysis'!R41 -> 0 | K42: =+C42+D42+E42+F42+G42+H42+I42+J42 -> 133129145 | L42: 1 | M42: =(C42+D42+E42)*L42 -> 122847689
A43: 13 | B43: ЖАМИ МАЖБУРИЯТЛАР | C43: =+C21+C22+C24+C30+C31+C32+C33+C34+C37+C38+C39+C40+C41+C42 -> 1021562015 | D43: =+D21+D22+D24+D30+D31+D32+D33+D34+D37+D38+D39+D40+D41+D42 -> 267372042 | E43: =+E21+E22+E24+E30+E31+E32+E33+E34+E37+E38+E39+E40+E41+E42 -> 157209197 | F43: =+F21+F22+F24+F30+F31+F32+F33+F34+F37+F38+F39+F40+F41+F42 -> 1727604103 | G43: =+G21+G22+G24+G30+G31+G32+G33+G34+G37+G38+G39+G40+G41+G42 -> 2274152450 | H43: =+H21+H22+H24+H30+H31+H32+H33+H34+H37+H38+H39+H40+H41+H42 -> 2362636977 | I43: =+I21+I22+I24+I30+I31+I32+I33+I34+I37+I38+I39+I40+I41+I42 -> 1994711772 | J43: =+J21+J22+J24+J30+J31+J32+J33+J34+J37+J38+J39+J40+J41+J42 -> 7334449542 | K43: =+K21+K22+K24+K30+K31+K32+K33+K34+K37+K38+K39+K40+K41+K42 -> 17139698098 | L43: отток | M43: =SUM(M8:M42) -> 1.8108178e+09 | N43: =+Balance!D63 -> 17139698098
B44: шундан, | K44: =+C44+D44+E44+F44+G44+H44+I44+J44 -> 0 | N44: =+K43-N43 -> 0
B45: Ўзбекистон Республикаси Молия вазирлиги маблағлари, шундан | C45: =+C46+C47 -> 0 | D45: =+D46+D47 -> 9547130 | E45: =+E46+E47 -> 51044732 | F45: =+F46+F47 -> 23138745 | G45: =+G46+G47 -> 111169339 | H45: =+H46+H47 -> 67418255 | I45: =+I46+I47 -> 56082263 | J45: =+J46+J47 -> 2033314234 | K45: =+C45+D45+E45+F45+G45+H45+I45+J45 -> 2351714698
B46: Кредит ва лизинглар | C46: =+'Bank Liabilities Analysis'!C45-'Bank Liabilities Analysis'!D45 -> 0 | D46: =+'Bank Liabilities Analysis'!E45-'Bank Liabilities Analysis'!F45 -> 0 | E46: =+'Bank Liabilities Analysis'!G45-'Bank Liabilities Analysis'!H45 -> 592378 | F46: =+'Bank Liabilities Analysis'!I45-'Bank Liabilities Analysis'!J45 -> 1305254 | G46: =+'Bank Liabilities Analysis'!K45-'Bank Liabilities Analysis'!L45 -> 1835535 | H46: =+'Bank Liabilities Analysis'!M45-'Bank Liabilities Analysis'!N45 -> 3862994 | I46: =+'Bank Liabilities Analysis'!O45-'Bank Liabilities Analysis'!P45 -> 8091125 | J46: =+'Bank Liabilities Analysis'!Q45-'Bank Liabilities Analysis'!R45 -> 7977355 | K46: =+C46+D46+E46+F46+G46+H46+I46+J46 -> 23664641
B47: Депозит маблағлар | C47: =+'Bank Liabilities Analysis'!C46-'Bank Liabilities Analysis'!D46 -> 0 | D47: =+'Bank Liabilities Analysis'!E46-'Bank Liabilities Analysis'!F46 -> 9547130 | E47: =+'Bank Liabilities Analysis'!G46-'Bank Liabilities Analysis'!H46 -> 50452354 | F47: =+'Bank Liabilities Analysis'!I46-'Bank Liabilities Analysis'!J46 -> 21833491 | G47: =+'Bank Liabilities Analysis'!K46-'Bank Liabilities Analysis'!L46 -> 109333804 | H47: =+'Bank Liabilities Analysis'!M46-'Bank Liabilities Analysis'!N46 -> 63555261 | I47: =+'Bank Liabilities Analysis'!O46-'Bank Liabilities Analysis'!P46 -> 47991138 | J47: =+'Bank Liabilities Analysis'!Q46-'Bank Liabilities Analysis'!R46 -> 2025336879 | K47: =+C47+D47+E47+F47+G47+H47+I47+J47 -> 2328050057
B48: Бюджетдан ташқари фондларнинг маблағлари, шундан | C48: =+C49+C50 -> 51817 | D48: =+D49+D50 -> 96360 | E48: =+E49+E50 -> 5654062 | F48: =+F49+F50 -> 10776489 | G48: =+G49+G50 -> 29716105 | H48: =+H49+H50 -> 43002325 | I48: =+I49+I50 -> 70071788 | J48: =+J49+J50 -> 154907435 | K48: =+C48+D48+E48+F48+G48+H48+I48+J48 -> 314276381
B49: Кредит ва лизинглар | C49: =+'Bank Liabilities Analysis'!C48-'Bank Liabilities Analysis'!D48 -> 51817 | D49: =+'Bank Liabilities Analysis'!E48-'Bank Liabilities Analysis'!F48 -> 96360 | E49: =+'Bank Liabilities Analysis'!G48-'Bank Liabilities Analysis'!H48 -> 5654062 | F49: =+'Bank Liabilities Analysis'!I48-'Bank Liabilities Analysis'!J48 -> 10776489 | G49: =+'Bank Liabilities Analysis'!K48-'Bank Liabilities Analysis'!L48 -> 14716105 | H49: =+'Bank Liabilities Analysis'!M48-'Bank Liabilities Analysis'!N48 -> 29002325 | I49: =+'Bank Liabilities Analysis'!O48-'Bank Liabilities Analysis'!P48 -> 51121788 | J49: =+'Bank Liabilities Analysis'!Q48-'Bank Liabilities Analysis'!R48 -> 154907435 | K49: =+C49+D49+E49+F49+G49+H49+I49+J49 -> 266326381
B50: Депозит маблағлар | C50: =+'Bank Liabilities Analysis'!C49-'Bank Liabilities Analysis'!D49 -> 0 | D50: =+'Bank Liabilities Analysis'!E49-'Bank Liabilities Analysis'!F49 -> 0 | E50: =+'Bank Liabilities Analysis'!G49-'Bank Liabilities Analysis'!H49 -> 0 | F50: =+'Bank Liabilities Analysis'!I49-'Bank Liabilities Analysis'!J49 -> 0 | G50: =+'Bank Liabilities Analysis'!K49-'Bank Liabilities Analysis'!L49 -> 15000000 | H50: =+'Bank Liabilities Analysis'!M49-'Bank Liabilities Analysis'!N49 -> 14000000 | I50: =+'Bank Liabilities Analysis'!O49-'Bank Liabilities Analysis'!P49 -> 18950000 | J50: =+'Bank Liabilities Analysis'!Q49-'Bank Liabilities Analysis'!R49 -> 0 | K50: =+C50+D50+E50+F50+G50+H50+I50+J50 -> 47950000
B51: Ўзбекистон тикланиш ва тараққиёт фонди (ФРРУ), шундан | C51: =+C52+C53 -> 0 | D51: =+D52+D53 -> 0 | E51: =+E52+E53 -> 0 | F51: =+F52+F53 -> 45961144 | G51: =+G52+G53 -> 92211902 | H51: =+H52+H53 -> 144458712 | I51: =+I52+I53 -> 335330671 | J51: =+J52+J53 -> 1260686953 | K51: =+C51+D51+E51+F51+G51+H51+I51+J51 -> 1878649382
B52: Кредит ва лизинглар | C52: =+'Bank Liabilities Analysis'!C51-'Bank Liabilities Analysis'!D51 -> 0 | D52: =+'Bank Liabilities Analysis'!E51-'Bank Liabilities Analysis'!F51 -> 0 | E52: =+'Bank Liabilities Analysis'!G51-'Bank Liabilities Analysis'!H51 -> 0 | F52: =+'Bank Liabilities Analysis'!I51-'Bank Liabilities Analysis'!J51 -> 45961144 | G52: =+'Bank Liabilities Analysis'!K51-'Bank Liabilities Analysis'!L51 -> 92211902 | H52: =+'Bank Liabilities Analysis'!M51-'Bank Liabilities Analysis'!N51 -> 144458712 | I52: =+'Bank Liabilities Analysis'!O51-'Bank Liabilities Analysis'!P51 -> 335330671 | J52: =+'Bank Liabilities Analysis'!Q51-'Bank Liabilities Analysis'!R51 -> 1260686953 | K52: =+C52+D52+E52+F52+G52+H52+I52+J52 -> 1878649382
B53: Депозит маблағлар | C53: =+'Bank Liabilities Analysis'!C52-'Bank Liabilities Analysis'!D52 -> 0 | D53: =+'Bank Liabilities Analysis'!E52-'Bank Liabilities Analysis'!F52 -> 0 | E53: =+'Bank Liabilities Analysis'!G52-'Bank Liabilities Analysis'!H52 -> 0 | F53: =+'Bank Liabilities Analysis'!I52-'Bank Liabilities Analysis'!J52 -> 0 | G53: =+'Bank Liabilities Analysis'!K52-'Bank Liabilities Analysis'!L52 -> 0 | H53: =+'Bank Liabilities Analysis'!M52-'Bank Liabilities Analysis'!N52 -> 0 | I53: =+'Bank Liabilities Analysis'!O52-'Bank Liabilities Analysis'!P52 -> 0 | J53: =+'Bank Liabilities Analysis'!Q52-'Bank Liabilities Analysis'!R52 -> 0 | K53: =+C53+D53+E53+F53+G53+H53+I53+J53 -> 0
B54: Хорижий банклар, шундан | C54: =+C55+C56 -> 0 | D54: =+D55+D56 -> 0 | E54: =+E55+E56 -> 0 | F54: =+F55+F56 -> 0 | G54: =+G55+G56 -> 32624639 | H54: =+H55+H56 -> 32624638 | I54: =+I55+I56 -> 77031737 | J54: =+J55+J56 -> 273814073 | K54: =+C54+D54+E54+F54+G54+H54+I54+J54 -> 416095087
B55: Кредит ва лизинглар | C55: =+'Bank Liabilities Analysis'!C54-'Bank Liabilities Analysis'!D54 -> 0 | D55: =+'Bank Liabilities Analysis'!E54-'Bank Liabilities Analysis'!F54 -> 0 | E55: =+'Bank Liabilities Analysis'!G54-'Bank Liabilities Analysis'!H54 -> 0 | F55: =+'Bank Liabilities Analysis'!I54-'Bank Liabilities Analysis'!J54 -> 0 | G55: =+'Bank Liabilities Analysis'!K54-'Bank Liabilities Analysis'!L54 -> 32624639 | H55: =+'Bank Liabilities Analysis'!M54-'Bank Liabilities Analysis'!N54 -> 32624638 | I55: =+'Bank Liabilities Analysis'!O54-'Bank Liabilities Analysis'!P54 -> 77031737 | J55: =+'Bank Liabilities Analysis'!Q54-'Bank Liabilities Analysis'!R54 -> 273814073 | K55: =+C55+D55+E55+F55+G55+H55+I55+J55 -> 416095087
B56: Депозит маблағлар | C56: =+'Bank Liabilities Analysis'!C55-'Bank Liabilities Analysis'!D55 -> 0 | D56: =+'Bank Liabilities Analysis'!E55-'Bank Liabilities Analysis'!F55 -> 0 | E56: =+'Bank Liabilities Analysis'!G55-'Bank Liabilities Analysis'!H55 -> 0 | F56: =+'Bank Liabilities Analysis'!I55-'Bank Liabilities Analysis'!J55 -> 0 | G56: =+'Bank Liabilities Analysis'!K55-'Bank Liabilities Analysis'!L55 -> 0 | H56: =+'Bank Liabilities Analysis'!M55-'Bank Liabilities Analysis'!N55 -> 0 | I56: =+'Bank Liabilities Analysis'!O55-'Bank Liabilities Analysis'!P55 -> 0 | J56: =+'Bank Liabilities Analysis'!Q55-'Bank Liabilities Analysis'!R55 -> 0 | K56: =+C56+D56+E56+F56+G56+H56+I56+J56 -> 0
B57: Бошқа халқаро молия ташкилотлари маблағлари, шундан, | C57: =+C58+C59 -> 0 | D57: =+D58+D59 -> 0 | E57: =+E58+E59 -> 0 | F57: =+F58+F59 -> 731885 | G57: =+G58+G59 -> 24662631 | H57: =+H58+H59 -> 25516393 | I57: =+I58+I59 -> 70542041 | J57: =+J58+J59 -> 1466195315 | K57: =+C57+D57+E57+F57+G57+H57+I57+J57 -> 1587648265
B58: Кредит ва лизинглар | C58: =+'Bank Liabilities Analysis'!C57-'Bank Liabilities Analysis'!D57 -> 0 | D58: =+'Bank Liabilities Analysis'!E57-'Bank Liabilities Analysis'!F57 -> 0 | E58: =+'Bank Liabilities Analysis'!G57-'Bank Liabilities Analysis'!H57 -> 0 | F58: =+'Bank Liabilities Analysis'!I57-'Bank Liabilities Analysis'!J57 -> 731885 | G58: =+'Bank Liabilities Analysis'!K57-'Bank Liabilities Analysis'!L57 -> 24662631 | H58: =+'Bank Liabilities Analysis'!M57-'Bank Liabilities Analysis'!N57 -> 25516393 | I58: =+'Bank Liabilities Analysis'!O57-'Bank Liabilities Analysis'!P57 -> 70542041 | J58: =+'Bank Liabilities Analysis'!Q57-'Bank Liabilities Analysis'!R57 -> 1466195315 | K58: =+C58+D58+E58+F58+G58+H58+I58+J58 -> 1587648265
B59: Депозит маблағлар | C59: =+'Bank Liabilities Analysis'!C58-'Bank Liabilities Analysis'!D58 -> 0 | D59: =+'Bank Liabilities Analysis'!E58-'Bank Liabilities Analysis'!F58 -> 0 | E59: =+'Bank Liabilities Analysis'!G58-'Bank Liabilities Analysis'!H58 -> 0 | F59: =+'Bank Liabilities Analysis'!I58-'Bank Liabilities Analysis'!J58 -> 0 | G59: =+'Bank Liabilities Analysis'!K58-'Bank Liabilities Analysis'!L58 -> 0 | H59: =+'Bank Liabilities Analysis'!M58-'Bank Liabilities Analysis'!N58 -> 0 | I59: =+'Bank Liabilities Analysis'!O58-'Bank Liabilities Analysis'!P58 -> 0 | J59: =+'Bank Liabilities Analysis'!Q58-'Bank Liabilities Analysis'!R58 -> 0 | K59: =+C59+D59+E59+F59+G59+H59+I59+J59 -> 0
B61: Бошқарув Раис имзоси:
B63: Бош бухгалтер имзоси:

Sheet Commitments
A1: БАЛАНСДАН ТАШҚАРИ ҲИСОБВАРАҚЛАР ТЎҒРИСИДА ҲИСОБОТ | E1: 19-жадвал
B2: =Balance!B3 -> "MKBANK" | C2: =+Balance!D3 -> 46021 | E2: =+Balance!E3 -> минг сўмда
A3: № | B3: Кўрсаткичлар | C3: Жами | D3: миллий валютада | E3: хорижий валютада (сўм экв.)
A4: 1. | B4: Банкнинг кредит ва лизинг бериш бўйича мажбуриятлари | C4: =+D4+E4 -> 906971873 | D4: 584424854 | E4: 322547019 | F4: =+'Bank Assets Analysis'!S49 -> 906971873 | G4: =+'Bank Assets Analysis'!T49 -> 584424854 | H4: =+'Bank Assets Analysis'!U49 -> 322547019
A5: 1.1. | B5: шу жумладан, кредит линиялар маблағлари ҳисобидан (махсус шартлар билан) | C5: =+D5+E5 -> 1.3036345e+08 | D5: 78593107 | E5: 51770339 | F5: =+'Bank Assets Analysis'!S50 -> 1.3036345e+08 | G5: =+'Bank Assets Analysis'!T50 -> 78593107 | H5: =+'Bank Assets Analysis'!U50 -> 51770339
A7: 2. | B7: Кафолат ва кафилликлар | C7: =+D7+E7 -> 445106241 | D7: 3000000 | E7: 442106241 | F7: =+'Bank Assets Analysis'!S51 -> 445106241 | G7: =+'Bank Assets Analysis'!T51 -> 3000000 | H7: =+'Bank Assets Analysis'!U51 -> 442106241
A8: 2.1. | B8: шу жумладан депозитлар билан таъминланган | C8: =+D8+E8 -> 115327725 | D8: 0 | E8: 115327725 | F8: =+'Bank Assets Analysis'!S52 -> 115327725 | G8: =+'Bank Assets Analysis'!T52 -> 0 | H8: =+'Bank Assets Analysis'!U52 -> 115327725
A10: 3. | B10: Жами аккредитивлар | C10: =+D10+E10 -> 1029438692 | D10: =SUM(D11:D14) -> 0 | E10: =SUM(E11:E14) -> 1029438692
A11: 3.1. | B11: Тўловчи томонидан банкда очилган қопланган аккредитив | C11: =+D11+E11 -> 4846315 | D11: 0 | E11: 4846315
A12: 3.2. | B12: Тақдим этувчига тратталарни тўлаган ҳолдаги импорт билан боғлиқ тўланмаган аккредитивлар | C12: =+D12+E12 -> 549987796 | D12: 0 | E12: 549987796
A13: 3.3. | B13: Муддатли тратталарга қарши қўйилган, импорт билан боғлиқ тўланмаган аккредитивлар | C13: =+D13+E13 -> 0 | D13: 0 | E13: 0
A14: 3.4. | B14: Бошқа аккредитивлар | C14: =+D14+E14 -> 474604581 | D14: 0 | E14: 474604581
A16: 4. | B16: Факторинг, инкассо ва савдони молиялаштириш | C16: =+D16+E16 -> 327047890 | D16: 264214621 | E16: 62833269
A18: 5. | B18: Жами бошқа барча балансдан ташқари ҳисобварақлар | C18: =+D18+E18 -> 31870919 | D18: =SUM(D19:D24) -> 29253221 | E18: =SUM(E19:E24) -> 2617698
A19: 5.1. | B19: Чет эл валюталари билан спот операциялари | C19: =+D19+E19 -> 0 | D19: 0 | E19: 0
A20: 5.2. | B20: Фоиз свопларининг шартли қиймати | C20: =+D20+E20 -> 0 | D20: 0 | E20: 0
A21: 5.3. | B21: Aйирбошлаш свопининг шартли қиймати (Валюта свопи) | C21: =+D21+E21 -> 0 | D21: 0 | E21: 0
A22: 5.4. | B22: Фьючерс, форвард ва опцион шартномалари | C22: =+D22+E22 -> 0 | D22: 0 | E22: 0
A23: 5.5. | B23: Кредитлар, қимматли қоғозлар ва бошқа активларни сотиб олиш бўйича мажбуриятлар | C23: =+D23+E23 -> 0 | D23: 0 | E23: 0
A24: 5.6. | B24: Бошқа балансдан ташқари ҳисобварақлар | C24: =+D24+E24 -> 31870919 | D24: 29253221 | E24: 2617698
A26: 6. | B26: Жами балансдан ташқари ҳисобварақлар | C26: =+C4+C7+C10+C16+C18 -> 2740435615 | D26: =+D4+D7+D10+D16+D18 -> 880892696 | E26: =+E4+E7+E10+E16+E18 -> 1859542919
B28: Бошқарув Раис имзоси:
B30: Бош бухгалтер имзоси:

Sheet Deposits by Client
A1: МИЖОЗЛАР ТУРЛАРИГА КЎРА ДЕПОЗИТЛАР | D1: 14-жадвал
B2: =+Balance!B3 -> "MKBANK" | C2: =+Balance!D3 -> 46021 | D2: минг сўмда
A3: № | B3: Кўрсаткичлар | C3: Жами | D3: шундан, хорижий валютада (сўм экв.)
A4: 1. | B4: Талаб қилиб олингунча сақланадиган ва бошқа депозитлар
A5: а. | B5: Ҳукумат | C5: 517609 | D5: 7
A6: б. | B6: Жисмоний шахслар | C6: 329456858 | D6: 27054213
A7: в. | B7: Давлат корхоналари | C7: 67843365 | D7: 4379464
A8: г. | B8: Чет эл капитали иштирокидаги корхоналар | C8: 23639310 | D8: 3834210
A9: д. | B9: Хусусий корхоналар | C9: 425317182 | D9: 21891851
A10: е. | B10: Бошқа талаб қилиб олингунча депозитлар | C10: 69675967 | D10: 9733148
A11: ж. | B11: Жами талаб қилиб олингунча сақланадиган ва бошқа депозитлар | C11: =SUM(C5:C10) -> 916450291 | D11: =SUM(D5:D10) -> 66892893 | E11: =+'Bank Liabilities Analysis'!S15+'Bank Liabilities Analysis'!S7 -> 916450291 | F11: =+'Bank Liabilities Analysis'!T15+'Bank Liabilities Analysis'!T7 -> 849557398 | G11: =+'Bank Liabilities Analysis'!U15+'Bank Liabilities Analysis'!U7 -> 66892893
A13: 2. | B13: Муддатли депозитлар | E13: =+C11-E11 -> 0 | G13: =+D11-G11 -> 0
A14: а. | B14: Ҳукумат | C14: 4537349186 | D14: 287241959
A15: б. | B15: Жисмоний шахслар | C15: 2894748034 | D15: 218885163
A16: в. | B16: Давлат корхоналари | C16: 1010910379 | D16: 115327725
A17: г. | B17: Чет эл капитали иштирокидаги корхоналар | C17: 136653630 | D17: 132278630
A18: д. | B18: Хусусий корхоналар | C18: 131922688 | D18: 1382912
A19: е. | B19: Бошқа муддатли депозитлар | C19: 98634952 | D19: 0
A20: ж. | B20: Жами муддатли депозитлар | C20: =SUM(C14:C19) -> 8810218869 | D20: =SUM(D14:D19) -> 755116389 | E20: =+'Bank Liabilities Analysis'!S12 -> 8810218869 | F20: =+'Bank Liabilities Analysis'!T12 -> 8055102480 | G20: =+'Bank Liabilities Analysis'!U12 -> 755116389
E21: =+C20-E20 -> 0 | G21: =+D20-G20 -> 0
A22: 3. | B22: Жами депозитлар | C22: =+C11+C20 -> 9726669160 | D22: =+D11+D20 -> 822009282 | E22: =+'Bank Liabilities Analysis'!S20 -> 9726669160 | F22: =+'Bank Liabilities Analysis'!T20 -> 8904659878 | G22: =+'Bank Liabilities Analysis'!U20 -> 822009282
E23: =+C22-E22 -> 0 | G23: =+D22-G22 -> 0
B24: Бошқарув Раис имзоси:
B26: Бош бухгалтер имзоси:

Sheet Investment Securities
A1: ҚИММАТЛИ ҚОҒОЗЛАР ВА УЛАРГА ҚИЛИНГАН ИНВЕСТИЦИЯЛАР ТЎҒРИСИДА ҲИСОБОТ | E1: 15-жадвал
A2: =Balance!B3 -> "MKBANK" | C2: =+Balance!D3 -> 46021 | E2: =+Balance!E3 -> минг сўмда
A3: Қисм 1 – Қарам хўжалик жамиятларига қилинган ҳамда амортизацияланган қиймати бўйича баҳоланадиган қарз қимматли қоғозларига қилинган инвестициялар | B3: Баланс қиймати | C3: шундан, | E3: Бозор қиймати
C4: миллий валютада | D4: хорижий валютада (сўм экв.)
A5: 1. Давлат қимматли қоғозлари | B5: =+C5+D5 -> 0 | C5: 0 | D5: 0 | E5: 0
A6: 2. Марказий банкнинг облигация ва бошқа қарз қимматли қоғозлари | B6: =+C6+D6 -> 0 | C6: 0 | D6: 0 | E6: 0
A7: 3. Корхоналарнинг қарз қимматли қоғозлари | B7: =+C7+D7 -> 0 | C7: 0 | D7: 0 | E7: 0
A8: 4. Еврооблигациялар | B8: =+C8+D8 -> 0 | C8: 0 | D8: 0 | E8: 0
A9: 5. Давлат улушига эга корхоналар акцияларига инвестициялар | B9: =+C9+D9 -> 52178810 | C9: 52178810 | D9: 0 | E9: =+C9 -> 52178810
A10: 6. Хусусий корхоналар акцияларига инвестициялар | B10: =+C10+D10 -> 872410142 | C10: 872410142 | D10: 0 | E10: 0
A11: 7. Бошқа қимматли қоғозларга инвестициялар | B11: =+C11+D11 -> 413821 | C11: 413821 | E11: =C11 -> 413821
A12: 8. Жами инвестициялар | B12: =+C12+D12 -> 925002773 | C12: =SUM(C5:C11) -> 925002773 | D12: =SUM(D5:D11) -> 0 | E12: =SUM(E5:E11) -> 52592631
A13: 9. Инвестициялар бўйича харажатлар, дисконт ва мукофот | B13: =+C13+D13 -> 0 | C13: 0 | D13: 0 | E13: 0
A14: 10. Минус: Эҳтимолий йўқотишларга қарши захиралар | B14: =+C14+D14 -> 0 | C14: 0 | D14: 0
A15: 11. Инвестицияларнинг соф баланс қиймати | B15: =+C15+D15 -> 925002773 | C15: =C12+C13-C14 -> 925002773 | D15: =D12+D13-D14 -> 0
A17: Қисм – 2. Қимматли қоғозлар ва уларга қилинган инвестициялар | B17: Баланс қиймати | C17: шундан, | E17: Бозор қиймати
C18: миллий валютада | D18: хорижий валютада (сўм экв.)
A19: 1. Давлат хазина векселлари | B19: =+C19+D19 -> 0 | C19: 0 | D19: 0 | E19: 0
A20: 2. Давлат облигациялари | B20: =+C20+D20 -> 113400000 | C20: 113400000 | D20: 0 | E20: =+C20 -> 113400000
A21: 3. Марказий банкнинг облигациялари ва бошқа қарз қимматли қоғозлари | B21: =+C21+D21 -> 400700000 | C21: 400700000 | D21: 0 | E21: =+C21 -> 400700000
A22: 4. Давлат улушига эга корхоналар қимматли қоғозлари | B22: =+C22+D22 -> 10000000 | C22: 10000000 | D22: 0 | E22: 0
A23: 5. Еврооблигациялар | B23: =+C23+D23 -> 0 | C23: 0 | D23: 0 | E23: 0
A24: 6. Корхоналар қимматли қоғозлари | B24: =+C24+D24 -> 0 | C24: 0 | D24: 0 | E24: =+C24 -> 0
A25: 7. Бошқа қимматли қоғозлар | B25: =+C25+D25 -> 0 | C25: 0 | D25: 0 | E25: 0
A26: 8. Жами қимматли қоғозлар ва уларга қилинган инвестициялар | B26: =+C26+D26 -> 524100000 | C26: =SUM(C19:C25) -> 524100000 | D26: =SUM(D19:D25) -> 0 | E26: =SUM(E19:E25) -> 514100000
A27: 9. Қимматли қоғозлар бўйича харажатлар, дисконт, мукофот ва уларнинг ҳаққоний қийматининг ўзгариши | B27: =+C27+D27 -> -5930680 | C27: -5930680 | D27: 0 | E27: =+B27 -> -5930680
A28: 10. Минус: Эҳтимолий йўқотишларга қарши захиралар | B28: =+C28+D28 -> 0 | C28: 0 | D28: 0
A29: 11. Қимматли қоғозлар ва уларга қилинган инвестициялар, соф баланс қиймати | B29: =+C29+D29 -> 518169320 | C29: =+C26+C27-C28 -> 518169320 | D29: =+D26+D27-D28 -> 0
A31: Қисм – 3. Олди-сотдига мўлжалланган қимматбаҳо металлар, тошлар ва тангалар | B31: Баланс қиймати | C31: шундан, | E31: Бозор қиймати
C32: миллий валютада | D32: хорижий валютада (сўм экв.)
A34: 1. Қимматбаҳо металлар | B34: =+C34+D34 -> 0 | C34: 0 | D34: 0 | E34: =+C34 -> 0
A35: 2. Қимматбаҳо тошлар | B35: =+C35+D35 -> 0 | C35: 0 | D35: 0 | E35: =+C35 -> 0
A36: 3. Қимматбаҳо тангалар | B36: =+C36+D36 -> 175 | C36: 175 | D36: 0 | E36: =+C36 -> 175
A37: 4. Қимматбаҳо металлар, тошлар ва тангалар жами | B37: =+C37+D37 -> 175 | C37: =SUM(C34:C36) -> 175 | D37: =SUM(D34:D36) -> 0 | E37: =SUM(E34:E36) -> 175
A38: 5. Минус: Эҳтимолий йўқотишларга қарши захиралар | B38: =+C38+D38 -> 0 | C38: 0 | D38: 0
A39: 6. Олди-сотдига мўлжалланган қимматбаҳо металлар, тошлар ва тангаларнинг соф баланс қиймати | B39: =+C39+D39 -> 175 | C39: =C37-C38 -> 175 | D39: =D37-D38 -> 0
A41: Бошқарув Раис имзоси:
A43: Бош бухгалтер имзоси:
