Workbook
Name jop: #REF!
Name kol: #REF!
Name TwentyLargestData: #REF!
Name Е: #REF!

Sheet Bank Capital Calc
A1: БАНКНИНГ РЕГУЛЯТИВ КАПИТАЛИ ҲИСОБ-КИТОБИ | C1: 5-жадвал | E1: №2
B3: MKBANK | C3: 46021
A4: № | B4: Кўрсаткичлар | C4: минг сўмда
A5: I. | B5: I ДАРАЖАЛИ КАПИТАЛ
A6: 1 | B6: I ДАРАЖАЛИ АСОСИЙ КАПИТАЛ
A7: 1.1. | B7: Оддий акциялар, нетто | C7: =+C8-C9 -> 7145161149
A8: a | B8: Тўлиқ тўланган оддий акциялар | C8: 7145161149
A9: б | B9: Минус: Қайта сотиб олинган оддий акциялар | C9: 0
A10: 1.2. | B10: Қўшимча капитал (оддий)
A11: 1.3. | B11: Тақсимланмаган фойда (зарар), шу жумладан капитал захиралар | C11: =+C12+C13-C14-C15 -> -1571600175
A12: а | B12: Капитал ва бошқа захиралар | C12: 27827555
A13: б | B13: Тақсимланмаган фойда | C13: 0
A14: в | B14: Ўтган даврлар (йиллар) учун зарарлар | C14: 1599427730
A15: г | B15: Жорий йил учун зарар | C15: 0
A16: 1.4. | B16: Озчилик улуш эгаларининг банк йиғма балансига бирлашадиган корхоналардаги улушлари | C16: 0
A17: 1.5. | B17: Девальвация захираси | C17: 0
A18: 1.6. | B18: Чегирмалар ҳисоблангунга қадар жами I даражали асосий капитал | C18: =+C7+C10+C11+C16+C17 -> 5573560974
A19: 1.7. | B19: I даражали асосий капиталдан чегирмалар | C19: =C20+C21+C22+C23+C24 -> 6889119
A20: а | B20: Номоддий активлар (бундан банкнинг дастурий таъминотлари мустасно) | C20: 6889119 | H20: бирлашмаган молиявий бўлмаган битта ташкилот устав фондидаги (устав капиталидаги) улушлар ва (ёки) акцияларга инвестицияларнинг банк I даражали асосий капиталининг 15 фоизидан ошган қисми
A21: б | B21: Бирлашмаган молиявий бўлмаган ташкилотлар капиталига қилинган инвестициялар | C21: =+G20+G21 -> 0 | G21: 0 | H21: бирлашмаган молиявий бўлмаган барча ташкилотлар устав фондидаги (устав капиталидаги) улушлар ва (ёки) акцияларга инвестициялар йиғиндисининг (бунда инвестициянинг мазкур банднинг «д»- кичик банди иккинчи хатбошисига кўра чегирилган қисми ҳисобга олинмайди) банк I даражали асосий капиталининг 50 фоизидан ошган қисми
A22: в | B22: Бирлашмаган молиявий бўлган ташкилотлар капиталига қилинган инвестициялар | C22: =+G22+G23 -> 0 | H22: бирлашмаган молиявий ташкилот устав фондидаги (устав капиталидаги) улушлар ва (ёки) акцияларга инвестициялар натижасида банкнинг ушбу ташкилотдаги улуши 10 фоиздан ошмаган бўлса, бундай ташкилотларга жами инвестициялар йиғиндисининг банк I даражали асосий капиталининг 10 фоизидан ошган қисми
A23: г | B23: Банк томонидан муаммоли активлар бўйича қўшимча шакллантирилиши лозим бўлган захиралар | C23: 0 | H23: бирлашмаган молиявий ташкилот устав фондидаги (устав капиталидаги) улушлар ва (ёки) акцияларга инвестициялар натижасида банкнинг ушбу ташкилотдаги улуши 10 фоиздан ошган бўлса, бундай ташкилотларга жами инвестициялар йиғиндисининг банк I даражали асосий капиталининг 10 фоизидан ошган қисми
A24: д | B24: Банкка алоқадор бир ёки барча шахслар учун таваккалчиликнинг белгиланган энг кўп миқдоридан ортиқ қиймати | C24: =+IF(MAX('[6]Transactions of related parties'!$Z$90-E25*25%,'[6]Transactions of related parties'!$Z$89-E25*50%)<0,0,MAX('[6]Transactions of related parties'!$Z$90-E25*25%,'[6]Transactions of related parties'!$Z$89-E25*50%)) -> 0 | E24: =+'[6]Transactions of related parties'!$Z$89 -> 2179274
A25: I | B25: I ДАРАЖАЛИ АСОСИЙ КАПИТАЛ | C25: =+C18-C19 -> 5566671855 | E25: =C18-C20-C21-C22-C23 -> 5566671855
A26: 2 | B26: I ДАРАЖАЛИ ҚЎШИМЧА КАПИТАЛ
A27: 2.1. | B27: Нокумулятив муддатсиз имтиёзли акциялар | C27: =+C28-C29 -> 175651
A28: а | B28: Тўлиқ тўланган имтиёзли акциялар | C28: 175651
A29: б | B29: Минус: Қайтиб сотиб олинган имтиёзли акциялар | C29: 0
A30: 2.2. | B30: Қўшилган капитал (имтиёзли) | C30: 0
A31: 2.3. | B31: Озчилик улуш эгаларининг банк йиғма балансига бирлашадиган корхоналардаги улушлари | C31: 0
A32: 2.4. | B32: Шўъба корхоналарнинг улушлари (шўъба корхоналар томонидан чиқарилган ва капиталга тенглаштирилган учинчи шахслар эгалик қиладиган воситалар) | C32: 0
A33: II | B33: ЖАМИ I ДАРАЖАЛИ ҚЎШИМЧА КАПИТАЛ | C33: =+C27+C30+C31+C32 -> 175651
A34: III | B34: ЖАМИ ТЎҒРИЛАНГАН I ДАРАЖАЛИ КАПИТАЛ | C34: =+C25+C33 -> 5566847506 | E34: =+C44/2 -> 3.1348333e+09
B35: II ДАРАЖАЛИ КАПИТАЛ
A36: 3.1. | B36: Жорий йил соф фойдаси | C36: 160802633
A37: 3.2. | B37: Стандарт активларга яратилган захиралар | C37: =IF(F37<(C45*1.25%),F37,(C45*1.25%)) -> 123374035 | E37: Резервы созданные по стандартным активам | F37: 123374035
A38: 3.3. | B38: Чегирмалардан сўнг I даражали капиталнинг учдан бир қисмидан ошмаган миқдорда аралаш турдаги мажбуриятлар | C38: 0 | F38: =+[7]Balance!$C$39+[7]Balance!$C$61 -> 123374035
A39: 3.4. | B39: Субординар қарз | C39: 416540075 | F39: =+F37-F38 -> 0
A40: 3.5. | B40: Активларнинг бошланғич қийматига нисбатан баҳолаш қийматининг ошган суммасининг 45 фоизи миқдори | C40: 2102260
A41: 3.6. | B41: II даражали капиталнинг I даражали капиталдан ортиқча қисми (чегирмаси) | C41: =IF($C$34>=SUM($C$36:$C$40),0,(SUM($C$36:$C$40)-$C$34))*-1 -> 0
B42: Жами II даражали капитал | C42: =SUM(C36:C40) -> 702819003
A43: IV | B43: ЧЕГИРМАЛАРНИ ҲИСОБГА ОЛГАН ҲОЛДАГИ II ДАРАЖАЛИ КАПИТАЛ | C43: =+C41+C42 -> 702819003
A44: V | B44: ЖАМИ РЕГУЛЯТИВ КАПИТАЛ | C44: =+C34+C41+C42 -> 6269666509
A45: VI | B45: ТАВАККАЛЧИЛИККА ТОРТИЛГАН АКТИВЛАР УМУМИЙ СУММАСИ | C45: =+C46+C47+C48 -> 3.3966335e+10
A46: а | B46: Баланс ва балансдан ташқари активларнинг таваккалчиликни ҳисобга олган ҳолдаги активларнинг умумий суммаси | C46: =+'Calculation of Risk Weighted As'!L92 -> 3.2468651e+10
A47: б | B47: Операцион таваккалчилик | C47: =+'Calculation of Risk'!C21 -> 1.4906331e+09
A48: в | B48: Бозор таваккалчилиги | C48: =+'Calculation of Risk'!C27 -> 7051763.1
A49: VII | B49: I ДАРАЖАЛИ АСОСИЙ КАПИТАЛНИНГ МОНАНДЛИК КОЭФФИЦИЕНТИ (I/VI) | C49: =IFERROR((+C25/C45),0) -> 0.16388791
A50: VIII | B50: I ДАРАЖАЛИ КАПИТАЛНИНГ МОНАНДЛИК КОЭФФИЦИЕНТИ (III/VI) | C50: =IFERROR((+C34/C45),0) -> 0.16389309
A51: IX | B51: РЕГУЛЯТИВ КАПИТАЛНИНГ МОНАНДЛИК КОЭФФИЦИЕНТИ (V/VI) | C51: =IFERROR((+C44/C45),0) -> 0.18458472
A52: X | B52: Левераж ҳисоб-китоби учун активлар | C52: =SUM(C53:C55)-C56 -> 33103414867
A53: а | B53: Жами активлар | C53: =+[7]Balance!$C$47 -> 30728787180
A54: б | B54: Балансдан ташқари активлар | C54: =SUM('Calculation of Risk Weighted As'!D71:L79) -> 2381516806
A55: в | B55: Ҳосилавий (дереватив) воситалар | C55: =+('Calculation of Risk Weighted As'!D82*'Calculation of Risk Weighted As'!$C$82*'Calculation of Risk Weighted As'!$D$3)+('Calculation of Risk Weighted As'!D83*'Calculation of Risk Weighted As'!$C$83*'Calculation of Risk Weighted As'!$D$3)+('Calculation of Risk Weighted As'!D84*'Calculation of Risk Weighted As'!$C$84*'Calculation of Risk Weighted As'!$D$3)+('Calculation of Risk Weighted As'!D86*'Calculation of Risk Weighted As'!$C$86*'Calculation of Risk Weighted As'!$D$3)+('Calculation of Risk Weighted As'!D87*'Calculation of Risk Weighted As'!$C$87*'Calculation of Risk Weighted As'!$D$3)+('Calculation of Risk Weighted As'!D88*'Calculation of Risk Weighted As'!$C$88*'Calculation of Risk Weighted As'!$D$3)+('Calculation of Risk Weighted As'!E82*'Calculation of Risk Weighted As'!$C$82*'Calculation of Risk Weighted As'!$E$3)+('Calculation of Risk Weighted As'!E83*'Calculation of Risk Weighted As'!$C$83*'Calculation of Risk Weighted As'!$E$3)+('Calculation of Risk Weighted As'!E84*'Calculation of Risk Weighted As'!$C$84*'Calculation of Risk Weighted As'!$E$3)+('Calculation of Risk Weighted As'!E86*'Calculation of Risk Weighted As'!$C$86*'Calculation of Risk Weighted As'!$E$3)+('Calculation of Risk Weighted As'!E87*'Calculation of Risk Weighted As'!$C$87*'Calculation of Risk Weighted As'!$E$3)+('Calculation of Risk Weighted As'!E88*'Calculation of Risk Weighted As'!$C$88*'Calculation of Risk Weighted As'!$E$3)+('Calculation of Risk Weighted As'!F82*'Calculation of Risk Weighted As'!$C$82*'Calculation of Risk Weighted As'!$F$3)+('Calculation of Risk Weighted As'!F83*$C$66*$F$3)+('Calculation of Risk Weighted As'!F84*$C$67*$F$3)+('Calculation of Risk Weighted As'!F86*$C$69*$F$3)+('Calculation of Risk Weighted As'!F87*$C$70*$F$3)+('Calculation of Risk Weighted As'!F88*$C$71*$F$3)+('Calculation of Risk Weighted As'!G82*'Calculation of Risk Weighted As'!$C$82*'Calculation of Risk Weighted As'!$G$3)+('Calculation of Risk Weighted As'!G83*'Calculation of Risk Weighted As'!$C$83*'Calculation of Risk Weighted As'!$G$3)+('Calculation of Risk Weighted As'!G84*'Calculation of Risk Weighted As'!$C$84*'Calculation of Risk Weighted As'!$G$3)+('Calculation of Risk Weighted As'!G86*'Calculation of Risk Weighted As'!$C$86*'Calculation of Risk Weighted As'!$G$3)+('Calculation of Risk Weighted As'!G87*'Calculation of Risk Weighted As'!$C$87*'Calculation of Risk Weighted As'!$G$3)+('Calculation of Risk Weighted As'!G88*'Calculation of Risk Weighted As'!$C$88*'Calculation of Risk Weighted As'!$G$3)+('Calculation of Risk Weighted As'!I82*'Calculation of Risk Weighted As'!$C$82*'Calculation of Risk Weighted As'!$I$3)+('Calculation of Risk Weighted As'!I83*'Calculation of Risk Weighted As'!$C$83*'Calculation of Risk Weighted As'!$I$3)+('Calculation of Risk Weighted As'!I84*'Calculation of Risk Weighted As'!$C$84*'Calculation of Risk Weighted As'!$I$3)+('Calculation of Risk Weighted As'!I86*'Calculation of Risk Weighted As'!$C$86*'Calculation of Risk Weighted As'!$I$3)+('Calculation of Risk Weighted As'!I87*'Calculation of Risk Weighted As'!$C$87*'Calculation of Risk Weighted As'!$I$3)+('Calculation of Risk Weighted As'!I88*'Calculation of Risk Weighted As'!$C$88*'Calculation of Risk Weighted As'!$I$3)+('Calculation of Risk Weighted As'!J82*'Calculation of Risk Weighted As'!$C$82*'Calculation of Risk Weighted As'!$J$3)+('Calculation of Risk Weighted As'!J83*'Calculation of Risk Weighted As'!$C$83*'Calculation of Risk Weighted As'!$J$3)+('Calculation of Risk Weighted As'!J84*'Calculation of Risk Weighted As'!$C$84*'Calculation of Risk Weighted As'!$J$3)+('Calculation of Risk Weighted As'!J86*'Calculation of Risk Weighted As'!$C$86*'Calculation of Risk Weighted As'!$J$3)+('Calculation of Risk Weighted As'!J87*'Calculation of Risk Weighted As'!$C$87*'Calculation of Risk Weighted As'!$J$3)+('Calculation of Risk Weighted As'!J88*'Calculation of Risk Weighted As'!$C$88*'Calculation of Risk Weighted As'!$J$3)+('Calculation of Risk Weighted As'!L82*'Calculation of Risk Weighted As'!$C$82*'Calculation of Risk Weighted As'!$L$3)+('Calculation of Risk Weighted As'!L83*'Calculation of Risk Weighted As'!$C$83*'Calculation of Risk Weighted As'!$L$3)+('Calculation of Risk Weighted As'!L84*'Calculation of Risk Weighted As'!$C$84*'Calculation of Risk Weighted As'!$L$3)+('Calculation of Risk Weighted As'!L86*'Calculation of Risk Weighted As'!$C$86*'Calculation of Risk Weighted As'!$L$3)+('Calculation of Risk Weighted As'!L87*'Calculation of Risk Weighted As'!$C$87*'Calculation of Risk Weighted As'!$L$3)+('Calculation of Risk Weighted As'!L88*'Calculation of Risk Weighted As'!$C$88*'Calculation of Risk Weighted As'!$L$3) -> 0
A56: г | B56: Минус: 1.7-қатор. Жами I даражали асосий капиталдан чегирмалар | C56: =+C19 -> 6889119
A57: XI | B57: Левераж коэффициенти | C57: =IFERROR((+C34/C52),0) -> 0.16816535
B59: Бошқарув Раис имзоси:
B61: Бош бухгалтер имзоси:

Sheet Bank Capital Calc (2)
A1: РАСЧЕТ РЕГУЛЯТИВНОГО КАПИТАЛА БАНКА | C1: Таблица-5
B3: =#REF! -> #REF! | C3: =+#REF! -> #REF!
A4: № | B4: Характеристики | C4: Итого капитала
A5: I. | B5: КАПИТАЛ УРОВНЯ 1
A6: 1 | B6: ОСНОВНОЙ КАПИТАЛ УРОВНЯ 1
A7: 1.1. | B7: Обыкновенные Акции, чистые | C7: Формула
A8: a | B8: Полностью оплаченные обыкновенные акции
A9: б | B9: Минус: Обратно Выкупленные обыкновенные акции
A10: 1.2. | B10: Добавленный капитал - Обыкновенные | C10: 0
A11: 1.3. | B11: Нераспределенная прибыль (убыток), в том числе капитальные резервы | C11: Формула
A12: а | B12: Капитальные резервы
A13: б | B13: Нераспределенная прибыль
A14: в | B14: Убыток за предыдущие периоды
A15: г | B15: Убыток за текущий год
A16: 1.4. | B16: Интерес меньшинства в консолидированных дочерних компаниях (согласно МБС)
A17: 1.5. | B17: Резерв на девальвацию
B18: Итого основного капитала уровня I до вычетов | C18: Формула
A19: 1.6. | B19: Вычеты из суммы основного капитала уровня I | C19: Формула
A20: а | B20: Нематериальные активы
A21: б | B21: Все инвестиции в капитал неконсолидированных хозяйствующих субъектов, в том числе в долговые обязательства, которые образуют капитал хозяйствующих субъектов
A22: в | B22: Инвестиции в капитал других банков
A23: I | B23: ВСЕГО СКОРРЕКТИРОВАННЫЙ ОСНОВНОЙ КАПИТАЛ УРОВНЯ I | C23: Формула
A24: 2 | B24: ДОБАВЛЕННЫЙ КАПИТАЛ УРОВНЯ 1
A25: 2.1. | B25: Некумулятивные бессрочные привилегированные акции | C25: =+C26+C27 -> 0
A26: а | B26: Полностью оплаченные привилегированные акции
A27: б | B27: Минус: Обратно Выкупленные привилегированные акции
A28: 2.2. | B28: Добавленный капитал - Привилегированные | C28: 0
A29: 2.3. | B29: Интерес меньшинства в консолидированных дочерних компаниях | C29: 0
A30: 2.4. | B30: Доля участия дочерних предприятий (выпущенные дочерними предприятиями и находящиеся во владении третьих лиц инструменты, приравненные к капиталу) | C30: 0
A31: II | B31: ВСЕГО ДОБАВЛЕННЫЙ КАПИТАЛ УРОВНЯ I | C31: =+C25+C28+C29+C30 -> 0
A32: III | B32: ВСЕГО СКОРРЕКТИРОВАННЫЙ КАПИТАЛ УРОВНЯ I | C32: Формула
B33: КАПИТАЛ УРОВНЯ II
A34: 3.1. | B34: Прибыль за текущий год
A35: 3.2. | B35: Резервы, создаваемые на стандартные кредиты (активы), в размере не более 1.25% от общей суммы активов, взвешенных с учетом риска | C35: =IF(#REF!<(C43*1.25%),#REF!,(C43*1.25%)) -> #REF!
A36: 3.3. | B36: Излишки оценочной стоимости прироста над первоначальной стоимостью
A37: 3.4. | B37: Другие инструменты капитала (не более 1/3 части капитала 1 уровня после вычетов)
A38: 3.5. | B38: Субординированный долг
A39: 3.6. | B39: Вычеты превышения Капитала Уровня II над Капиталом Уровня I | C39: Формула
B40: Итого капитала Уровня II | C40: =SUM(C34:C38) -> #REF!
A41: IV | B41: СКОРРЕКТИРОВАННЫЙ КАПИТАЛ УРОВНЯ II | C41: Формула
A42: V | B42: ВСЕГО РЕГУЛЯТИВНЫЙ КАПИТАЛ | C42: Формула
A43: VI | B43: ОБЩАЯ СУММА АКТИВОВ ВЗВЕШЕННЫХ С УЧЕТОМ РИСКА | C43: =+C44+C45+C46 -> #REF!
A44: а | B44: Сумма балансовых и забалансовых активов, взвешенных с учетом риска | C44: =+'Calculation of Risk Weighted As'!#REF! -> #REF!
A45: б | B45: Операционный риск | C45: =+'Calculation of Risk'!C21 -> 1.4906331e+09
A46: в | B46: Рыночный риск | C46: =+'Calculation of Risk'!C27 -> 7051763.1 | E46: =+'Calculation of Risk'!G12 -> 0
A47: VII | B47: КОЭФФИЦИЕНТ ОСНОВНОГО КАПИТАЛА УРОВНЯ I (I/VI) | C47: Формула
A48: VIII | B48: КОЭФФИЦИЕНТ КАПИТАЛА УРОВНЯ I (III/VI) | C48: Формула
A49: IX | B49: КОЭФФИЦИЕНТ ОБЩЕЙ СУММЫ КАПИТАЛА, ОСНОВАННОГО НА РИСКЕ (V/VI) | C49: Формула
A50: X | B50: Активы для расчета левеража | C50: Формула
A51: а | B51: Общие активы | C51: =+#REF! -> #REF!
A52: б | B52: Забалансовые инструменты | C52: =SUM('Calculation of Risk Weighted As'!D71:G79) -> 483914187 | D52: =+'Calculation of Risk Weighted As'!#REF! -> #REF!
A53: в | B53: Деривативные (производные) инструменты | C53: =SUM('Calculation of Risk Weighted As'!#REF!) -> #REF!
A54: г | B54: Минус: Строка 1.6. Итого вычетов из суммы основного капитала Уровня 1 | C54: =+C19 -> Формула
A55: XI | B55: Коэффициент левеража | C55: Формула
B57: Подпись Председателя правления:
B59: Подпись Главного Бухгалтера:

Sheet Calculation of Risk Weighted As
A1: ТАВАККАЛЧИЛИКНИ ҲИСОБГА ОЛГАН ҲОЛДАГИ АКТИВЛАР | L1: 6-жадвал | M1: №2
B2: =+'Bank Capital Calc'!B3 -> MKBANK | J2: =+'Bank Capital Calc'!C3 -> 46021 | L2: минг сўмда
A3: № | B3: Кўрсаткичлар | D3: 0 | E3: 0.2 | F3: 0.35 | G3: 0.5 | H3: 0.75 | I3: 1 | J3: 1.5 | K3: 2 | L3: 2.5
D4: Таваккалчилик | E4: Таваккалчилик | F4: Таваккалчилик | G4: Таваккалчилик | H4: Таваккалчилик | I4: Таваккалчилик | J4: Таваккалчилик | K4: Таваккалчилик | L4: Таваккалчилик
D5: I гуруҳ | E5: II гуруҳ | F5: III гуруҳ | G5: IV гуруҳ | H5: V гуруҳ | I5: VI гуруҳ | J5: VII гуруҳ | K5: VIII гуруҳ | L5: IX гуруҳ
B6: (A) | D6: (Б) | E6: (В) | F6: (Г) | G6: (Д) | H6: (Е) | I6: (Ж) | J6: (З) | K6: (И) | L6: (K)
B7: I. БАЛАНС АКТИВЛАРИ
A8: 1. | B8: Кассадаги нақд пул ва бошқа тўлов ҳужжатлари ва қимматбаҳо металлар | D8: 416486264
A9: 2. | B9: Йўлдаги нақд пуллар ва бошқа тўлов ҳужжатлари | E9: 287064457
A10: 3. | B10: Банкнинг Марказий банкдаги маблағлар | D10: 584034134 | E10: 0
A11: 4. | B11: Бошқа банкларга жойлаштирилган пул маблағлари, жумладан вакиллик ҳисобварақлари, депозитлар ва кредитлар | E11: 2002567177 | G11: 709223347 | I11: 50382898 | J11: 704707635
A12: 5. | B12: Қимматли қоғозлар (соф)
A13: а | B13: Ўзбекистон Республикаси Ҳукумати ва Марказий банки томонидан чиқарилган қимматли қоғозлар | D13: 508169320 | E13: 0
A14: б | B14: Ипотекани қайта молиялаштириш ташкилотлари томонидан чиқарилган қимматли қоғозлар | D14: 0 | E14: 10000000
A15: в | B15: Хорижий давлатларининг ҳукуматлари ва марказий банклари томонидан чиқарилган қимматли қоғозлар, шунингдек ушбу мамлакатларнинг марказий банклари ва ҳукуматларига нисбатан бошқа талаблар | D15: 0 | E15: 0
A16: г | B16: Ўзбекистон Республикаси ҳудудида чиқарилган бошқа қимматли қоғозлар | D16: 0 | E16: 0
A17: д | B17: Ўзбекистон Республикаси ҳудудидан ташқарида чиқарилган бошқа қимматли қоғозлар | D17: 0 | E17: 0
A18: е | B18: РЕПО битимлари бўйича сотиб олинган қимматли қоғозлар | D18: 0 | E18: 0
A19: 6. | B19: Миллий валютага деноминация қилинмаган ва миллий валютада молиялаштириш суммасидан ошиб кетган активлар
A20: 7. | B20: Хорижий давлатларнинг давлат секторлари (ҳукуматлар ва марказий банклар бундан мустасно) ва хорижий компаниялар бўйича банк талаблари, шунингдек уларнинг қимматли қоғозлари билан таъминланган ёки кафолатланган активлар (кредитлар ва қимматли қоғозлар бундан мустасно) | D20: 0 | E20: 0
A21: 8. | B21: Кредит ва лизинглар, соф
A22: 8.1. | B22: Юридик шахсларга ажратилган кредит ва лизинглар, соф
A23: а | B23: Ўзбекистон Республикаси ҳукумати ва Марказий банкига тўғридан-тўғри берилган кредитлар | D23: 0
A24: б | B24: Халқаро молия институтларига берилган кредитлар, халқаро молия ташкилотларининг қимматли қоғозлари билан таъминланган ёки улар томонидан кафолатланган кредитлар | D24: 0
A25: в | B25: Кредитларнинг депозит билан таъминланган қисми | D25: 0 | E25: 0
A26: г | B26: Жорий бозор қийматида баҳоланган ва ЎзР Ҳукумати, ЎзР Марказий банки томонидан эмиссия қилинган ёки кафолатланган қимматли қоғозлар кўринишидаги гаров билан таъминланган ёки кафолатланган кредитлар, уларнинг қисмлари | D26: 0
A27: д | B27: Дастлабки гаров ҳуқуқи банкка тегишли бўлмаган кредитлар | I27: 0
A28: е | B28: Қайта тикланадиган энергия манбалари учун ажратилган кредитлар | D28: 25146470 | I28: 13589939 | J28: 0 | K28: 0
A29: ж | B29: 2024 йил 1 апрелдан бошлаб 2025 йил 1 июнга қадар доимий даромадга эга бўлган, шунингдек камида олти ой давомида банк ҳисобварағида, шу жумладан банк картасида маблағлар айланмасига эга бўлган кичик тадбиркорлик субъектларига микромолиялаштириш фаолияти доирасида кўрсатилган хизматлар (оилавий тадбиркорликни ривожлантириш дастурлари доирасида ажратилган кредитлар мустасно) | H29: 0
A30: з | B30: 2024 йил 1 апрелдан бошлаб 2025 йил 1 июнга қадар мазкур жадвалнинг 8.1.ж-қаторида қайд этилган хизматларни кўрсатиш мақсадида микромолия ташкилотларига ажратилган кредитлар | H30: 0
A31: и | B31: 2025 йил 1 июндан бошлаб кичик тадбиркорлик субъектларига ажратилган жами қолдиқ суммаси банк регулятив капиталининг 0,2 фоизидан ошмаган, бироқ энг кўпи билан 15 млрд. сўмгача кредитлар (оилавий тадбиркорликни ривожлантириш дастурлари доирасида ажратилган кредитлар мустасно) | H31: 882500809
A32: к | B32: Юридик шахсларга ажратилган бошқа барча кредит, лизинг ва кўрсатилган факторинг хизматлари | I32: 8986784184 | J32: 906804172 | K32: 541134414
A33: л | B33: Юридик шахсларнинг муаммоли кредит ва лизинглари, соф | K33: 384144464
A34: 8.2. | B34: Жисмоний шахсларга ажратилган кредитлар, соф
A35: а | B35: Дастлабки гаров ҳуқуқи банкка тегишли бўлмаган кредитлар
A36: б | B36: Кредитларнинг (микроқарзларнинг) депозит билан таъминланган қисми
A37: в | B37: 2024 йил 1 июлга қадар ажратилган ипотека кредитлари | F37: 41905153 | G37: 194137077 | I37: 505205459 | J37: 10438662
A38: г | B38: 2024 йил 1 июлдан бошлаб ажратилган ипотека кредитлари | F38: 4046099 | G38: 21718576 | I38: 276640869 | J38: 417098745
A39: д | B39: 2023 йил 20 августга қадар автомобиль сотиб олиш учун ажратилган кредитлар | I39: 20449913 | J39: 26624915 | K39: 3883155
A40: е | B40: 2023 йил 20 августдан бошлаб 2024 йил 1 июлга қадар жисмоний шахсларга автомобиль сотиб олиш учун ажратилган кредитлар | I40: 146576121 | J40: 139324014 | K40: 11962343
A41: ж | B41: 2024 йил 1 июлдан бошлаб жисмоний шахсларга автомобиль сотиб олиш учун ажратилган кредитлар | I41: 12042338 | J41: 130625841 | K41: 148569577
A42: з | B42: 2024 йил 1 июлдан бошлаб 2025 йил 1 январга қадар қарз юки 60 фоиз ва ундан паст ҳолда жисмоний шахсларга ажратилган кредитлар (микроқарзлар) (автокредит, ипотека, оилавий тадбиркорликни ривожлантириш ва таълим дастурлари кредитлари мустасно) | I42: 67137973
A43: и | B43: 2024 йил 1 июлдан бошлаб 2025 йил 1 январга қадар қарз юки 60 фоиздан юқори бўлган ёки қарз юки аниқлаш имкони бўлмаган жисмоний шахсларга берилган кредитлар (микроқарзлар) (автокредит, ипотека, оилавий тадбиркорликни ривожлантириш ва таълим дастурлари кредитлари мустасно) | J43: 85604940
A44: к | B44: 2025 йил 1 январдан бошлаб қарз юки 50 фоиз ва ундан паст ҳолда жисмоний шахсларга ажратилган кредитлар (микроқарзлар) (автокредит, ипотека, оилавий тадбиркорликни ривожлантириш ва таълим дастурлари кредитлари мустасно) | I44: 183881829
A45: л | B45: 2025 йил 1 январдан бошлаб қарз юки 50 фоиздан юқори бўлган ёки қарз юки аниқлаш имкони бўлмаган жисмоний шахсларга берилган кредитлар (микроқарзлар) (автокредит, ипотека, оилавий тадбиркорликни ривожлантириш ва таълим дастурлари кредитлари мустасно) | J45: 1402448735
A46: м | B46: Қайта тикланадиган энергия манбалари учун ажратилган кредитлар | D46: 36460134 | I46: 36649817 | J46: 3897599 | K46: 0
A47: н | B47: 2024 йил 1 апрелдан бошлаб 2025 йил 1 июнга қадар доимий даромадга эга бўлган, шунингдек камида олти ой давомида банк ҳисобварағида, шу жумладан банк картасида маблағлар айланмасига эга бўлган ўзини ўзи банд қилган шахсларга микромолиялаштириш фаолияти доирасида кўрсатилган хизматлар (оилавий тадбиркорликни ривожлантириш дастурлари доирасида ажратилган кредитлар мустасно) | H47: 0
A48: о | B48: 2025 йил 1 июндан бошлаб доимий даромадга эга бўлган ёки камида охирги узлуксиз олти ой давомида ҳар ой банк ҳисобварағида, шу жумладан банк картасида маблағлар айланмасига эга бўлган ўзини ўзи банд қилган шахсларга ажратилган кредитлар | H48: 0 | I48: 0 | J48: 0 | K48: 0
A49: п | B49: 2025 йил 1 июндан бошлаб доимий даромадга эга бўлмаган ёки охирги узлуксиз олти ой давомида ҳар ой банк ҳисобварағида, шу жумладан банк картасида маблағлар айланмасига эга бўлмаган ёки қарз йуки кўрсаткичи 50 фоиздан ошган ёхуд мазкур кўрсаткични аниқлаш имкони бўлмаган ўзини ўзи банд қилган шахсларга ажратилган кредитлар | J49: 0 | K49: 0
A50: р | B50: Жисмоний шахсларга ажратилган юқорида кўрсатилмаган бошқа барча кредитлар | I50: 3990266686 | J50: 9448406 | K50: 79269994
A51: с | B51: Жисмоний шахсларнинг муаммоли кредитлари, соф | K51: 403775311
A52: 9. | B52: Банкнинг асосий воситалари ва бошқа хусусий мол-мулклари
A53: а | B53: Банк фаолиятидаги фойдаланиладиган асосий воситалар (амортизацияни чегирган ҳолда) | I53: 888291934
A54: б | B54: Банкнинг бошқа хусусий мулклари | I54: 0
A55: в | B55: Қарздорликни тўлиқ ёки қисман ундириш мақсадида банк балансига қабул қилинган кўчмас мулк | J55: 621395723 | K55: 169098240
A56: г | B56: Икки йилдан ортиқ вақт мобайнида банк фойдаланмаётган банкнинг кўчмас мулки | J56: 0 | K56: 0
A57: 10. | B57: Молиявий бўлган фаолият билан шуғулланувчи хўжалик юритувчи субъектларнинг капиталига қилинган барча инвестициялар, соф | D57: 0 | J57: 52178810 | K57: 0 | L57: 28452400
A58: 11. | B58: Молиявий бўлмаган фаолият билан шуғулланувчи хўжалик юритувчи субъектларнинг капиталига қилинган барча инвестициялар, соф | D58: 789839000 | J58: 54532563 | K58: 0
A59: 12. | B59: Номоддий активлар, соф | D59: =+'Bank Capital Calc'!C20 -> 6889119 | I59: 8818599
A60: 13. | B60: Молиявий инструментлар бўйича мижозларнинг мажбуриятлари, соф | D60: 0 | E60: 0 | I60: 38191497 | K60: 0
A61: 14. | B61: Бошқа муаммоли активлар | K61: 1479249
A62: 15. | B62: Стандарт деб таснифланган активлар бўйича яратилган захиралар | D62: =+[7]Balance!$C$39 -> 123374035 | M62: =+D62 -> 123374035 | N62: =+[7]Balance!$C$39 -> 123374035 | O62: =+M62-N62 -> 0
A63: 16. | B63: Бошқа активлар, соф | D63: 1893420 | F63: 1335429 | G63: 5070712 | H63: 20265015 | I63: 1752221194 | J63: 113263493 | K63: 876114853
A64: 17. | B64: Баланс активларининг умумий миқдори | D64: =SUM(D8:D61)+D63-D62 -> 2245543826 | E64: =SUM(E8:E61)+E63-E62 -> 2299631634 | F64: =SUM(F8:F61)+F63-F62 -> 47286681 | G64: =SUM(G8:G61)+G63-G62 -> 930149712 | H64: =SUM(H8:H61)+H63-H62 -> 902765824 | I64: =SUM(I8:I61)+I63-I62 -> 16977131250 | J64: =SUM(J8:J61)+J63-J62 -> 4678394253 | K64: =SUM(K8:K61)+K63-K62 -> 2619431600 | L64: =SUM(L8:L61)+L63-L62 -> 28452400 | M64: =SUM(D64:L64) -> 30728787180 | N64: =+[7]Balance!$C$47 -> 30728787180 | O64: =+M64-N64 -> 0
A65: 18. | B65: Таваккалчилик гурухларига асосан рискка (таваккалчиликка) тортилган активларининг умумий миқдори | E65: =E64*E3 -> 4.5992633e+08 | F65: =F64*F3 -> 16550338 | G65: =G64*G3 -> 465074856 | H65: =H64*H3 -> 677074368 | I65: =I64*I3 -> 16977131250 | J65: =J64*J3 -> 7.0175914e+09 | K65: =K64*K3 -> 5238863200 | L65: =L64*L3 -> 71131000
A66: 19. | B66: Баланс активларининг таваккалчиликка тортилган умумий миқдори | L66: =SUM(D65:L65) -> 3.0923343e+10
A69: № | B69: II. БАЛАНСДАН ТАШҚАРИ АКТИВЛАР | C69: Кредитни қайта ҳисоблаш омили | D69: 0 | E69: 0.2 | F69: 0.35 | G69: 0.5 | H69: 0.75 | I69: 1 | J69: 1.5 | K69: 2 | L69: 2.5
A70: 1 | B70: Банкнинг кредит ва лизинг бериш мажбурияти
A71: a | B71: Бир йилдан ортиқ муддатга | C71: 0.5 | D71: 761000 | F71: 5610973 | G71: 2909476 | H71: 12142161 | I71: 482689091 | J71: 169143381 | K71: 8869562
A72: б | B72: Бир йил ёки ундан кам муддатга | C72: 0.2 | D72: 25002 | F72: 3155 | G72: 0 | H72: 58338746 | I72: 137399217 | J72: 25857714 | K72: 3222395 | M72: =SUM(D71:L72) -> 906971873 | N72: =+[7]Commitments!$C$4 -> 906971873 | O72: =+M72-N72 -> 0
A73: 2 | B73: Қимматли қоғозларни сотиб олиш бўйича муддатли битимлар (шу жумладан, қайта сотиб олиш шартномалари бўйича сотилган активлар) | C73: 1 | I73: 0
A74: 3 | B74: Кафолат ва кафилликлар | C74: 1 | I74: 445106241 | J74: 0 | K74: 0 | M74: =SUM(D74:L74) -> 445106241 | N74: =+[7]Commitments!$C$7 -> 445106241 | O74: =+M74-N74 -> 0
A75: 4 | B75: Aккредитивлар
A76: a | B76: Тўғридан-тўғри кредит ўрнини босувчи воситалар | C76: 1 | G76: 0 | I76: 0 | K76: 0
A77: б | B77: Битимлар билан боғлиқ аккредитивлар | C77: 0.5 | G77: 474604581 | I77: 0 | K77: 0
A78: в | B78: Савдога тегишли аккредитивлар | C78: 0.2 | G78: 0 | I78: 0 | K78: 0
A79: г | B79: Бошқа аккредитивлар | C79: 1 | G79: 0 | I79: 554834111 | K79: 0 | M79: =SUM(D76:L79) -> 1029438692 | N79: =+[7]Commitments!$C$10 -> 1029438692 | O79: =+M79-N79 -> 0
A80: 5 | B80: Форвард шартномалар, спот, своплар, опционлар ва шунга ўхшаш мажбуриятлар
A81: a | B81: Фоиз ставкалари бўйича шартномалар
A82: а1 | B82: Бир йил муддатгача | C82: 0.005 | I82: 0
A83: а2 | B83: Бир йилдан икки йил муддатгача | C83: 0.01 | I83: 0
A84: а3 | B84: Икки йилдан уч йил муддатгача | C84: 0.02 | I84: 0
A85: б | B85: Валюта шартномалари ва олтин
A86: б1 | B86: Бир йилгача бўлган муддатда қайтариш | C86: 0.02 | I86: 0
A87: б2 | B87: Бир йилдан икки йилгача бўлган муддатда қайтариш | C87: 0.05 | I87: 0
A88: б3 | B88: Икки йилдан уч йилгача бўлган муддатда қайтариш | C88: 0.08 | I88: 0
A89: 6 | B89: Балансдан ташқари активларнинг умумий миқдори | D89: =SUM(D71:D88) -> 786002 | E89: =SUM(E71:E88) -> 0 | F89: =SUM(F71:F88) -> 5614128 | G89: =SUM(G71:G88) -> 477514057 | H89: =SUM(H71:H88) -> 70480907 | I89: =SUM(I71:I88) -> 1620028660 | J89: =SUM(J71:J88) -> 195001095 | K89: =SUM(K71:K88) -> 12091957
A90: 7 | B90: Таваккалчилик қиймати | D90: =+(D71*$C$71*$D$3)+(D72*$C$72*$D$3)+(D73*$C$73*$D$3)+(D74*$C$74*$D$3)+(D76*$C$76*$D$3)+(D77*$C$77*$D$3)+(D78*$C$78*$D$3)+(D79*$C$79*$D$3)+(D82*$C$82*$D$3)+(D83*$C$83*$D$3)+(D84*$C$84*$D$3)+(D86*$C$86*$D$3)+(D87*$C$87*$D$3)+(D88*$C$88*$D$3) -> 0 | E90: =+(E71*$C$71*$E$3)+(E72*$C$72*$E$3)+(E73*$C$73*$E$3)+(E74*$C$74*$E$3)+(E76*$C$76*$E$3)+(E77*$C$77*$E$3)+(E78*$C$78*$E$3)+(E79*$C$79*$E$3)+(E82*$C$82*$E$3)+(E83*$C$83*$E$3)+(E84*$C$84*$E$3)+(E86*$C$86*$E$3)+(E87*$C$87*$E$3)+(E88*$C$88*$E$3) -> 0 | F90: =+(F71*$C$71*$F$3)+(F72*$C$72*$F$3)+(F73*$C$73*$F$3)+(F74*$C$74*$F$3)+(F76*$C$76*$F$3)+(F77*$C$77*$F$3)+(F78*$C$78*$F$3)+(F79*$C$79*$F$3)+(F82*$C$82*$F$3)+(F83*$C$83*$F$3)+(F84*$C$84*$F$3)+(F86*$C$86*$F$3)+(F87*$C$87*$F$3)+(F88*$C$88*$F$3) -> 982141.12 | G90: =+(G71*$C$71*$G$3)+(G72*$C$72*$G$3)+(G73*$C$73*$G$3)+(G74*$C$74*$G$3)+(G76*$C$76*$G$3)+(G77*$C$77*$G$3)+(G78*$C$78*$G$3)+(G79*$C$79*$G$3)+(G82*$C$82*$G$3)+(G83*$C$83*$G$3)+(G84*$C$84*$G$3)+(G86*$C$86*$G$3)+(G87*$C$87*$G$3)+(G88*$C$88*$G$3) -> 1.1937851e+08 | H90: =+(H71*$C$71*$G$3)+(H72*$C$72*$G$3)+(H73*$C$73*$G$3)+(H74*$C$74*$G$3)+(H76*$C$76*$G$3)+(H77*$C$77*$G$3)+(H78*$C$78*$G$3)+(H79*$C$79*$G$3)+(H82*$C$82*$G$3)+(H83*$C$83*$G$3)+(H84*$C$84*$G$3)+(H86*$C$86*$G$3)+(H87*$C$87*$G$3)+(H88*$C$88*$G$3) -> 8869414.9 | I90: =+(I71*$C$71*$I$3)+(I72*$C$72*$I$3)+(I73*$C$73*$I$3)+(I74*$C$74*$I$3)+(I76*$C$76*$I$3)+(I77*$C$77*$I$3)+(I78*$C$78*$I$3)+(I79*$C$79*$I$3)+(I82*$C$82*$I$3)+(I83*$C$83*$I$3)+(I84*$C$84*$I$3)+(I86*$C$86*$I$3)+(I87*$C$87*$I$3)+(I88*$C$88*$I$3) -> 1.2687647e+09 | J90: =+(J71*$C$71*$J$3)+(J72*$C$72*$J$3)+(J73*$C$73*$J$3)+(J74*$C$74*$J$3)+(J76*$C$76*$J$3)+(J77*$C$77*$J$3)+(J78*$C$78*$J$3)+(J79*$C$79*$J$3)+(J82*$C$82*$J$3)+(J83*$C$83*$J$3)+(J84*$C$84*$J$3)+(J86*$C$86*$J$3)+(J87*$C$87*$J$3)+(J88*$C$88*$J$3) -> 1.3461485e+08 | K90: =+(K71*$C$71*$L$3)+(K72*$C$72*$L$3)+(K73*$C$73*$L$3)+(K74*$C$74*$L$3)+(K76*$C$76*$L$3)+(K77*$C$77*$L$3)+(K78*$C$78*$L$3)+(K79*$C$79*$L$3)+(K82*$C$82*$L$3)+(K83*$C$83*$L$3)+(K84*$C$84*$L$3)+(K86*$C$86*$L$3)+(K87*$C$87*$L$3)+(K88*$C$88*$L$3) -> 12698150
A91: 8 | B91: Жами балансдан ташқари активларнинг таваккалчиликка тортилган қиймати | L91: =SUM(D90:L90) -> 1.5453078e+09
A92: 9 | B92: Жами активларнинг таваккалчиликка тортилган қиймати | L92: =SUM(L91+L66) -> 3.2468651e+10
B94: Бошқарув Раис имзоси:
B96: Бош бухгалтер имзоси:

Sheet Calculation of Risk Weighte нац
A1: МИЛЛИЙ ВАЛЮТАДА ТАВАККАЛЧИЛИКНИ ҲИСОБГА ОЛГАН ҲОЛДАГИ АКТИВЛАР | L1: 6.1-жадвал
B2: =+'Bank Capital Calc'!B3 -> MKBANK | J2: =+'Bank Capital Calc'!C3 -> 46021 | L2: минг сўмда
A3: № | B3: Кўрсаткичлар | D3: 0 | E3: 0.2 | F3: 0.35 | G3: 0.5 | H3: 0.75 | I3: 1 | J3: 1.5 | K3: 2 | L3: 2.5
D4: Таваккалчилик | E4: Таваккалчилик | F4: Таваккалчилик | G4: Таваккалчилик | H4: Таваккалчилик | I4: Таваккалчилик | J4: Таваккалчилик | K4: Таваккалчилик | L4: Таваккалчилик
D5: I гуруҳ | E5: II гуруҳ | F5: III гуруҳ | G5: IV гуруҳ | H5: V гуруҳ | I5: VI гуруҳ | J5: VII гуруҳ | K5: VIII гуруҳ | L5: IX гуруҳ
B6: (A) | D6: (Б) | E6: (В) | F6: (Г) | G6: (Д) | H6: (Е) | I6: (Ж) | J6: (З) | K6: (И) | L6: (K)
B7: I. БАЛАНС АКТИВЛАРИ
A8: 1. | B8: Кассадаги нақд пул ва бошқа тўлов ҳужжатлари ва қимматбаҳо металлар | D8: 350206926
A9: 2. | B9: Йўлдаги нақд пуллар ва бошқа тўлов ҳужжатлари | E9: 188784749
A10: 3. | B10: Банкнинг Марказий банкдаги маблағлар | D10: 584034134 | E10: 0
A11: 4. | B11: Бошқа банкларга жойлаштирилган пул маблағлари, жумладан вакиллик ҳисобварақлари, депозитлар ва кредитлар | E11: 0 | G11: 11133345 | I11: 50382898 | J11: 0
A12: 5. | B12: Қимматли қоғозлар (соф)
A13: а | B13: Ўзбекистон Республикаси Ҳукумати ва Марказий банки томонидан чиқарилган қимматли қоғозлар | D13: 508169320 | E13: 0
A14: б | B14: Ипотекани қайта молиялаштириш ташкилотлари томонидан чиқарилган қимматли қоғозлар | D14: 0 | E14: 10000000
A15: в | B15: Хорижий давлатларининг ҳукуматлари ва марказий банклари томонидан чиқарилган қимматли қоғозлар, шунингдек ушбу мамлакатларнинг марказий банклари ва ҳукуматларига нисбатан бошқа талаблар | D15: 0 | E15: 0 | G15: 0 | I15: 0 | J15: 0
A16: г | B16: Ўзбекистон Республикаси ҳудудида чиқарилган бошқа қимматли қоғозлар | D16: 0 | E16: 0 | G16: 0 | I16: 0 | J16: 0
A17: д | B17: Ўзбекистон Республикаси ҳудудидан ташқарида чиқарилган бошқа қимматли қоғозлар | D17: 0 | E17: 0 | G17: 0 | I17: 0 | J17: 0
A18: е | B18: РЕПО битимлари бўйича сотиб олинган қимматли қоғозлар | D18: 0 | E18: 0 | G18: 0 | I18: 0 | J18: 0
A19: 6. | B19: Миллий валютага деноминация қилинмаган ва миллий валютада молиялаштириш суммасидан ошиб кетган активлар | I19: 0
A20: 7. | B20: Хорижий давлатларнинг давлат секторлари (ҳукуматлар ва марказий банклар бундан мустасно) ва хорижий компаниялар бўйича банк талаблари, шунингдек уларнинг қимматли қоғозлари билан таъминланган ёки кафолатланган активлар (кредитлар ва қимматли қоғозлар бундан мустасно) | D20: 0 | E20: 0 | G20: 0 | I20: 0 | J20: 0
A21: 8. | B21: Кредит ва лизинглар, соф
A22: 8.1. | B22: Юридик шахсларга ажратилган кредит ва лизинглар, соф
A23: а | B23: Ўзбекистон Республикаси ҳукумати ва Марказий банкига тўғридан-тўғри берилган кредитлар | D23: 0
A24: б | B24: Халқаро молия институтларига берилган кредитлар, халқаро молия ташкилотларининг қимматли қоғозлари билан таъминланган ёки улар томонидан кафолатланган кредитлар | D24: 0
A25: в | B25: Кредитларнинг депозит билан таъминланган қисми | D25: 0 | E25: 0
A26: г | B26: Жорий бозор қийматида баҳоланган ва ЎзР Ҳукумати, ЎзР Марказий банки томонидан эмиссия қилинган ёки кафолатланган қимматли қоғозлар кўринишидаги гаров билан таъминланган ёки кафолатланган кредитлар, уларнинг қисмлари | D26: 0
A27: д | B27: Дастлабки гаров ҳуқуқи банкка тегишли бўлмаган кредитлар | I27: 0
A28: е | B28: Қайта тикланадиган энергия манбалари учун ажратилган кредитлар | D28: 25146470 | I28: 13589939 | J28: 0 | K28: 0
A29: ж | B29: 2024 йил 1 апрелдан бошлаб 2025 йил 1 июнга қадар доимий даромадга эга бўлган, шунингдек камида олти ой давомида банк ҳисобварағида, шу жумладан банк картасида маблағлар айланмасига эга бўлган кичик тадбиркорлик субъектларига микромолиялаштириш фаолияти доирасида кўрсатилган хизматлар (оилавий тадбиркорликни ривожлантириш дастурлари доирасида ажратилган кредитлар мустасно) | H29: 0
A30: з | B30: 2024 йил 1 апрелдан бошлаб 2025 йил 1 июнга қадар мазкур жадвалнинг 8.1.ж-қаторида қайд этилган хизматларни кўрсатиш мақсадида микромолия ташкилотларига ажратилган кредитлар | H30: 0
A31: и | B31: 2025 йил 1 июндан бошлаб кичик тадбиркорлик субъектларига ажратилган жами қолдиқ суммаси банк регулятив капиталининг 0,2 фоизидан ошмаган, бироқ энг кўпи билан 15 млрд. сўмгача кредитлар (оилавий тадбиркорликни ривожлантириш дастурлари доирасида ажратилган кредитлар мустасно) | H31: 870639551
A32: к | B32: Юридик шахсларга ажратилган бошқа барча кредит, лизинг ва кўрсатилган факторинг хизматлари | I32: 6061797156 | J32: 466859789 | K32: 287232270
A33: л | B33: Юридик шахсларнинг муаммоли кредит ва лизинглари, соф | K33: 300550490
A34: 8.2. | B34: Жисмоний шахсларга ажратилган кредитлар, соф
A35: а | B35: Дастлабки гаров ҳуқуқи банкка тегишли бўлмаган кредитлар | I35: 0
A36: б | B36: Кредитларнинг (микроқарзларнинг) депозит билан таъминланган қисми | D36: 0 | E36: 0
A37: в | B37: 2024 йил 1 июлга қадар ажратилган ипотека кредитлари | F37: 41905153 | G37: 194137077 | I37: 505205459 | J37: 10438662
A38: г | B38: 2024 йил 1 июлдан бошлаб ажратилган ипотека кредитлари | F38: 4046099 | G38: 21718576 | I38: 276640869 | J38: 417098745
A39: д | B39: 2023 йил 20 августга қадар автомобиль сотиб олиш учун ажратилган кредитлар | I39: 20449913 | J39: 26624915 | K39: 3883155
A40: е | B40: 2023 йил 20 августдан бошлаб 2024 йил 1 июлга қадар жисмоний шахсларга автомобиль сотиб олиш учун ажратилган кредитлар | I40: 146576121 | J40: 139324014 | K40: 11962343
A41: ж | B41: 2024 йил 1 июлдан бошлаб жисмоний шахсларга автомобиль сотиб олиш учун ажратилган кредитлар | I41: 12042338 | J41: 130625841 | K41: 148569577
A42: з | B42: 2024 йил 1 июлдан бошлаб 2025 йил 1 январга қадар қарз юки 60 фоиз ва ундан паст ҳолда жисмоний шахсларга ажратилган кредитлар (микроқарзлар) (автокредит, ипотека, оилавий тадбиркорликни ривожлантириш ва таълим дастурлари кредитлари мустасно) | I42: 67137973
A43: и | B43: 2024 йил 1 июлдан бошлаб 2025 йил 1 январга қадар қарз юки 60 фоиздан юқори бўлган ёки қарз юки аниқлаш имкони бўлмаган жисмоний шахсларга берилган кредитлар (микроқарзлар) (автокредит, ипотека, оилавий тадбиркорликни ривожлантириш ва таълим дастурлари кредитлари мустасно) | J43: 85604940
A44: к | B44: 2025 йил 1 январдан бошлаб қарз юки 50 фоиз ва ундан паст ҳолда жисмоний шахсларга ажратилган кредитлар (микроқарзлар) (автокредит, ипотека, оилавий тадбиркорликни ривожлантириш ва таълим дастурлари кредитлари мустасно) | I44: 183881829
A45: л | B45: 2025 йил 1 январдан бошлаб қарз юки 50 фоиздан юқори бўлган ёки қарз юки аниқлаш имкони бўлмаган жисмоний шахсларга берилган кредитлар (микроқарзлар) (автокредит, ипотека, оилавий тадбиркорликни ривожлантириш ва таълим дастурлари кредитлари мустасно) | J45: 1402448735
A46: м | B46: Қайта тикланадиган энергия манбалари учун ажратилган кредитлар | D46: 36460134 | I46: 36649817 | J46: 3897599 | K46: 0
A47: н | B47: 2024 йил 1 апрелдан бошлаб 2025 йил 1 июнга қадар доимий даромадга эга бўлган, шунингдек камида олти ой давомида банк ҳисобварағида, шу жумладан банк картасида маблағлар айланмасига эга бўлган ўзини ўзи банд қилган шахсларга микромолиялаштириш фаолияти доирасида кўрсатилган хизматлар (оилавий тадбиркорликни ривожлантириш дастурлари доирасида ажратилган кредитлар мустасно) | H47: 0
A48: о | B48: 2025 йил 1 июндан бошлаб доимий даромадга эга бўлган ёки камида охирги узлуксиз олти ой давомида ҳар ой банк ҳисобварағида, шу жумладан банк картасида маблағлар айланмасига эга бўлган ўзини ўзи банд қилган шахсларга ажратилган кредитлар | H48: 0 | I48: 0 | J48: 0 | K48: 0
A49: п | B49: 2025 йил 1 июндан бошлаб доимий даромадга эга бўлмаган ёки охирги узлуксиз олти ой давомида ҳар ой банк ҳисобварағида, шу жумладан банк картасида маблағлар айланмасига эга бўлмаган ёки қарз йуки кўрсаткичи 50 фоиздан ошган ёхуд мазкур кўрсаткични аниқлаш имкони бўлмаган ўзини ўзи банд қилган шахсларга ажратилган кредитлар | J49: 0 | K49: 0
A50: р | B50: Жисмоний шахсларга ажратилган юқорида кўрсатилмаган бошқа барча кредитлар | I50: 3990266686 | J50: 9448406 | K50: 79269994
A51: с | B51: Жисмоний шахсларнинг муаммоли кредитлари, соф | K51: 403775311
A52: 9. | B52: Банкнинг асосий воситалари ва бошқа хусусий мол-мулклари
A53: а | B53: Банк фаолиятидаги фойдаланиладиган асосий воситалар (амортизацияни чегирган ҳолда) | I53: 888291934
A54: б | B54: Банкнинг бошқа хусусий мулклари | I54: 0
A55: в | B55: Қарздорликни тўлиқ ёки қисман ундириш мақсадида банк балансига қабул қилинган кўчмас мулк | J55: 621395723 | K55: 169098240
A56: г | B56: Икки йилдан ортиқ вақт мобайнида банк фойдаланмаётган банкнинг кўчмас мулки | J56: 0 | K56: 0
A57: 10. | B57: Молиявий бўлган фаолият билан шуғулланувчи хўжалик юритувчи субъектларнинг капиталига қилинган барча инвестициялар, соф | D57: 0 | J57: 52178810 | K57: 0 | L57: 28452400
A58: 11. | B58: Молиявий бўлмаган фаолият билан шуғулланувчи хўжалик юритувчи субъектларнинг капиталига қилинган барча инвестициялар, соф | D58: 789839000 | J58: 54532563 | K58: 0
A59: 12. | B59: Номоддий активлар, соф | D59: =+'Bank Capital Calc'!C20 -> 6889119 | I59: 8818599
A60: 13. | B60: Молиявий инструментлар бўйича мижозларнинг мажбуриятлари, соф | D60: 0 | E60: 0 | I60: 1400024 | K60: 0
A61: 14. | B61: Бошқа муаммоли активлар | K61: 1479249
A62: 15. | B62: Стандарт деб таснифланган активлар бўйича яратилган захиралар | D62: =+[7]Balance!$D$39 -> 123374035 | M62: =+D62 -> 123374035 | N62: =+[7]Balance!$D$39 -> 123374035 | O62: =+M62-N62 -> 0
A63: 16. | B63: Бошқа активлар, соф | D63: 1893420 | F63: 1335429 | G63: 5070712 | H63: 20140782 | I63: 1301003018 | J63: 85543630 | K63: 817135817
A64: 17. | B64: Баланс активларининг умумий миқдори | D64: =SUM(D8:D61)+D63-D62 -> 2179264488 | E64: =SUM(E8:E61)+E63-E62 -> 198784749 | F64: =SUM(F8:F61)+F63-F62 -> 47286681 | G64: =SUM(G8:G61)+G63-G62 -> 232059710 | H64: =SUM(H8:H61)+H63-H62 -> 890780333 | I64: =SUM(I8:I61)+I63-I62 -> 13564134573 | J64: =SUM(J8:J61)+J63-J62 -> 3506022372 | K64: =SUM(K8:K61)+K63-K62 -> 2222956446 | L64: =SUM(L8:L61)+L63-L62 -> 28452400 | M64: =SUM(D64:L64) -> 22869741752 | N64: =+[7]Balance!$D$47 -> 22869741752 | O64: =+M64-N64 -> 0
A65: 18. | B65: Таваккалчилик гурухларига асосан рискка (таваккалчиликка) тортилган активларининг умумий миқдори | E65: =E64*E3 -> 39756950 | F65: =F64*F3 -> 16550338 | G65: =G64*G3 -> 116029855 | H65: =H64*H3 -> 6.6808525e+08 | I65: =I64*I3 -> 13564134573 | J65: =J64*J3 -> 5259033558 | K65: =K64*K3 -> 4445912892 | L65: =L64*L3 -> 71131000
A66: 19. | B66: Баланс активларининг таваккалчиликка тортилган умумий миқдори | L66: =SUM(D65:L65) -> 2.4180634e+10
A69: № | B69: II. БАЛАНСДАН ТАШҚАРИ АКТИВЛАР | C69: Кредитни қайта ҳисоблаш омили | D69: 0 | E69: 0.2 | F69: 0.35 | G69: 0.5 | H69: 0.75 | I69: 1 | J69: 1.5 | K69: 2 | L69: 2.5
A70: 1 | B70: Банкнинг кредит ва лизинг бериш мажбурияти
A71: a | B71: Бир йилдан ортиқ муддатга | C71: 0.5 | D71: 761000 | F71: 5610973 | G71: 2909476 | H71: 12112098 | I71: 269745448 | J71: 80343895 | K71: 8466348
A72: б | B72: Бир йил ёки ундан кам муддатга | C72: 0.2 | D72: 25002 | F72: 3155 | G72: 0 | H72: 58338746 | I72: 137371078 | J72: 5605243 | K72: 3132392 | M72: =SUM(D71:L72) -> 584424854 | N72: =+[7]Commitments!$D$4 -> 584424854 | O72: =+M72-N72 -> 0
A73: 2 | B73: Қимматли қоғозларни сотиб олиш бўйича муддатли битимлар (шу жумладан, қайта сотиб олиш шартномалари бўйича сотилган активлар) | C73: 1 | I73: 0
A74: 3 | B74: Кафолат ва кафилликлар | C74: 1 | I74: 3000000 | M74: =SUM(D74:L74) -> 3000000 | N74: =+[7]Commitments!$D$7 -> 3000000 | O74: =+M74-N74 -> 0
A75: 4 | B75: Aккредитивлар
A76: a | B76: Тўғридан-тўғри кредит ўрнини босувчи воситалар | C76: 1 | I76: 0
A77: б | B77: Битимлар билан боғлиқ аккредитивлар | C77: 0.5 | G77: 0 | I77: 0
A78: в | B78: Савдога тегишли аккредитивлар | C78: 0.2 | I78: 0
A79: г | B79: Бошқа аккредитивлар | C79: 1 | I79: 0 | M79: =SUM(D76:L79) -> 0 | N79: =+[7]Commitments!$D$10 -> 0 | O79: =+M79-N79 -> 0
A80: 5 | B80: Форвард шартномалар, спот, своплар, опционлар ва шунга ўхшаш мажбуриятлар
A81: a | B81: Фоиз ставкалари бўйича шартномалар
A82: а1 | B82: Бир йил муддатгача | C82: 0.005
A83: а2 | B83: Бир йилдан икки йил муддатгача | C83: 0.01
A84: а3 | B84: Икки йилдан уч йил муддатгача | C84: 0.02
A85: б | B85: Валюта шартномалари ва олтин
A86: б1 | B86: Бир йилгача бўлган муддатда қайтариш | C86: 0.02
A87: б2 | B87: Бир йилдан икки йилгача бўлган муддатда қайтариш | C87: 0.05
A88: б3 | B88: Икки йилдан уч йилгача бўлган муддатда қайтариш | C88: 0.08
A89: 6 | B89: Балансдан ташқари активларнинг умумий миқдори | D89: =SUM(D71:D88) -> 786002 | E89: =SUM(E71:E88) -> 0 | F89: =SUM(F71:F88) -> 5614128 | G89: =SUM(G71:G88) -> 2909476 | H89: =SUM(H71:H88) -> 70450844 | I89: =SUM(I71:I88) -> 410116526 | J89: =SUM(J71:J88) -> 85949138 | K89: =SUM(K71:K88) -> 11598740
A90: 7 | B90: Таваккалчилик қиймати | D90: =+(D71*$C$71*$D$3)+(D72*$C$72*$D$3)+(D73*$C$73*$D$3)+(D74*$C$74*$D$3)+(D76*$C$76*$D$3)+(D77*$C$77*$D$3)+(D78*$C$78*$D$3)+(D79*$C$79*$D$3)+(D82*$C$82*$D$3)+(D83*$C$83*$D$3)+(D84*$C$84*$D$3)+(D86*$C$86*$D$3)+(D87*$C$87*$D$3)+(D88*$C$88*$D$3) -> 0 | E90: =+(E71*$C$71*$E$3)+(E72*$C$72*$E$3)+(E73*$C$73*$E$3)+(E74*$C$74*$E$3)+(E76*$C$76*$E$3)+(E77*$C$77*$E$3)+(E78*$C$78*$E$3)+(E79*$C$79*$E$3)+(E82*$C$82*$E$3)+(E83*$C$83*$E$3)+(E84*$C$84*$E$3)+(E86*$C$86*$E$3)+(E87*$C$87*$E$3)+(E88*$C$88*$E$3) -> 0 | F90: =+(F71*$C$71*$F$3)+(F72*$C$72*$F$3)+(F73*$C$73*$F$3)+(F74*$C$74*$F$3)+(F76*$C$76*$F$3)+(F77*$C$77*$F$3)+(F78*$C$78*$F$3)+(F79*$C$79*$F$3)+(F82*$C$82*$F$3)+(F83*$C$83*$F$3)+(F84*$C$84*$F$3)+(F86*$C$86*$F$3)+(F87*$C$87*$F$3)+(F88*$C$88*$F$3) -> 982141.12 | G90: =+(G71*$C$71*$G$3)+(G72*$C$72*$G$3)+(G73*$C$73*$G$3)+(G74*$C$74*$G$3)+(G76*$C$76*$G$3)+(G77*$C$77*$G$3)+(G78*$C$78*$G$3)+(G79*$C$79*$G$3)+(G82*$C$82*$G$3)+(G83*$C$83*$G$3)+(G84*$C$84*$G$3)+(G86*$C$86*$G$3)+(G87*$C$87*$G$3)+(G88*$C$88*$G$3) -> 727369 | H90: =+(H71*$C$71*$G$3)+(H72*$C$72*$G$3)+(H73*$C$73*$G$3)+(H74*$C$74*$G$3)+(H76*$C$76*$G$3)+(H77*$C$77*$G$3)+(H78*$C$78*$G$3)+(H79*$C$79*$G$3)+(H82*$C$82*$G$3)+(H83*$C$83*$G$3)+(H84*$C$84*$G$3)+(H86*$C$86*$G$3)+(H87*$C$87*$G$3)+(H88*$C$88*$G$3) -> 8861899.1 | I90: =+(I71*$C$71*$I$3)+(I72*$C$72*$I$3)+(I73*$C$73*$I$3)+(I74*$C$74*$I$3)+(I76*$C$76*$I$3)+(I77*$C$77*$I$3)+(I78*$C$78*$I$3)+(I79*$C$79*$I$3)+(I82*$C$82*$I$3)+(I83*$C$83*$I$3)+(I84*$C$84*$I$3)+(I86*$C$86*$I$3)+(I87*$C$87*$I$3)+(I88*$C$88*$I$3) -> 1.6534694e+08 | J90: =+(J71*$C$71*$J$3)+(J72*$C$72*$J$3)+(J73*$C$73*$J$3)+(J74*$C$74*$J$3)+(J76*$C$76*$J$3)+(J77*$C$77*$J$3)+(J78*$C$78*$J$3)+(J79*$C$79*$J$3)+(J82*$C$82*$J$3)+(J83*$C$83*$J$3)+(J84*$C$84*$J$3)+(J86*$C$86*$J$3)+(J87*$C$87*$J$3)+(J88*$C$88*$J$3) -> 61939494 | K90: =+(K71*$C$71*$L$3)+(K72*$C$72*$L$3)+(K73*$C$73*$L$3)+(K74*$C$74*$L$3)+(K76*$C$76*$L$3)+(K77*$C$77*$L$3)+(K78*$C$78*$L$3)+(K79*$C$79*$L$3)+(K82*$C$82*$L$3)+(K83*$C$83*$L$3)+(K84*$C$84*$L$3)+(K86*$C$86*$L$3)+(K87*$C$87*$L$3)+(K88*$C$88*$L$3) -> 12149131
A91: 8 | B91: Жами балансдан ташқари активларнинг таваккалчиликка тортилган қиймати | L91: =SUM(D90:L90) -> 2.5000697e+08
A92: 9 | B92: Жами активларнинг таваккалчиликка тортилган қиймати | L92: =SUM(L91+L66) -> 2.4430641e+10
B94: Бошқарув Раис имзоси:
B96: Бош бухгалтер имзоси:

Sheet Calculation of Risk Weighte ин
A1: ХОРИЖИЙ ВАЛЮТАДА ТАВАККАЛЧИЛИКНИ ҲИСОБГА ОЛГАН ҲОЛДАГИ АКТИВЛАР | L1: 6.2-жадвал
B2: =+'Bank Capital Calc'!B3 -> MKBANK | J2: =+'Bank Capital Calc'!C3 -> 46021 | L2: минг сўмда
A3: № | B3: Кўрсаткичлар | D3: 0 | E3: 0.2 | F3: 0.35 | G3: 0.5 | H3: 0.75 | I3: 1 | J3: 1.5 | K3: 2 | L3: 2.5
D4: Таваккалчилик | E4: Таваккалчилик | F4: Таваккалчилик | G4: Таваккалчилик | H4: Таваккалчилик | I4: Таваккалчилик | J4: Таваккалчилик | K4: Таваккалчилик | L4: Таваккалчилик
D5: I гуруҳ | E5: II гуруҳ | F5: III гуруҳ | G5: IV гуруҳ | H5: V гуруҳ | I5: VI гуруҳ | J5: VII гуруҳ | K5: VIII гуруҳ | L5: IX гуруҳ
B6: (A) | D6: (Б) | E6: (В) | F6: (Г) | G6: (Д) | H6: (Е) | I6: (Ж) | J6: (З) | K6: (И) | L6: (K)
B7: I. БАЛАНС АКТИВЛАРИ
A8: 1. | B8: Кассадаги нақд пул ва бошқа тўлов ҳужжатлари ва қимматбаҳо металлар | D8: =+'Calculation of Risk Weighted As'!D8-'Calculation of Risk Weighte нац'!D8 -> 66279338
A9: 2. | B9: Йўлдаги нақд пуллар ва бошқа тўлов ҳужжатлари | E9: =+'Calculation of Risk Weighted As'!E9-'Calculation of Risk Weighte нац'!E9 -> 98279708
A10: 3. | B10: Банкнинг Марказий банкдаги маблағлар | D10: =+'Calculation of Risk Weighted As'!D10-'Calculation of Risk Weighte нац'!D10 -> 0 | E10: =+'Calculation of Risk Weighted As'!E10-'Calculation of Risk Weighte нац'!E10 -> 0
A11: 4. | B11: Бошқа банкларга жойлаштирилган пул маблағлари, жумладан вакиллик ҳисобварақлари, депозитлар ва кредитлар | E11: =+'Calculation of Risk Weighted As'!E11-'Calculation of Risk Weighte нац'!E11 -> 2002567177 | G11: =+'Calculation of Risk Weighted As'!G11-'Calculation of Risk Weighte нац'!G11 -> 698090002 | I11: =+'Calculation of Risk Weighted As'!I11-'Calculation of Risk Weighte нац'!I11 -> 0 | J11: =+'Calculation of Risk Weighted As'!J11-'Calculation of Risk Weighte нац'!J11 -> 704707635
A12: 5. | B12: Қимматли қоғозлар (соф)
A13: а | B13: Ўзбекистон Республикаси Ҳукумати ва Марказий банки томонидан чиқарилган қимматли қоғозлар | D13: =+'Calculation of Risk Weighted As'!D13-'Calculation of Risk Weighte нац'!D13 -> 0 | E13: =+'Calculation of Risk Weighted As'!E13-'Calculation of Risk Weighte нац'!E13 -> 0
A14: б | B14: Ипотекани қайта молиялаштириш ташкилотлари томонидан чиқарилган қимматли қоғозлар | D14: =+'Calculation of Risk Weighted As'!D14-'Calculation of Risk Weighte нац'!D14 -> 0 | E14: =+'Calculation of Risk Weighted As'!E14-'Calculation of Risk Weighte нац'!E14 -> 0
A15: в | B15: Хорижий давлатларининг ҳукуматлари ва марказий банклари томонидан чиқарилган қимматли қоғозлар, шунингдек ушбу мамлакатларнинг марказий банклари ва ҳукуматларига нисбатан бошқа талаблар | D15: =+'Calculation of Risk Weighted As'!D15-'Calculation of Risk Weighte нац'!D15 -> 0 | E15: =+'Calculation of Risk Weighted As'!E15-'Calculation of Risk Weighte нац'!E15 -> 0 | G15: =+'Calculation of Risk Weighted As'!G15-'Calculation of Risk Weighte нац'!G15 -> 0 | I15: =+'Calculation of Risk Weighted As'!I15-'Calculation of Risk Weighte нац'!I15 -> 0 | J15: =+'Calculation of Risk Weighted As'!J15-'Calculation of Risk Weighte нац'!J15 -> 0
A16: г | B16: Ўзбекистон Республикаси ҳудудида чиқарилган бошқа қимматли қоғозлар | D16: =+'Calculation of Risk Weighted As'!D16-'Calculation of Risk Weighte нац'!D16 -> 0 | E16: =+'Calculation of Risk Weighted As'!E16-'Calculation of Risk Weighte нац'!E16 -> 0 | G16: =+'Calculation of Risk Weighted As'!G16-'Calculation of Risk Weighte нац'!G16 -> 0 | I16: =+'Calculation of Risk Weighted As'!I16-'Calculation of Risk Weighte нац'!I16 -> 0 | J16: =+'Calculation of Risk Weighted As'!J16-'Calculation of Risk Weighte нац'!J16 -> 0
A17: д | B17: Ўзбекистон Республикаси ҳудудидан ташқарида чиқарилган бошқа қимматли қоғозлар | D17: =+'Calculation of Risk Weighted As'!D17-'Calculation of Risk Weighte нац'!D17 -> 0 | E17: =+'Calculation of Risk Weighted As'!E17-'Calculation of Risk Weighte нац'!E17 -> 0 | G17: =+'Calculation of Risk Weighted As'!G17-'Calculation of Risk Weighte нац'!G17 -> 0 | I17: =+'Calculation of Risk Weighted As'!I17-'Calculation of Risk Weighte нац'!I17 -> 0 | J17: =+'Calculation of Risk Weighted As'!J17-'Calculation of Risk Weighte нац'!J17 -> 0
A18: е | B18: РЕПО битимлари бўйича сотиб олинган қимматли қоғозлар | D18: =+'Calculation of Risk Weighted As'!D18-'Calculation of Risk Weighte нац'!D18 -> 0 | E18: =+'Calculation of Risk Weighted As'!E18-'Calculation of Risk Weighte нац'!E18 -> 0 | G18: =+'Calculation of Risk Weighted As'!G18-'Calculation of Risk Weighte нац'!G18 -> 0 | I18: =+'Calculation of Risk Weighted As'!I18-'Calculation of Risk Weighte нац'!I18 -> 0 | J18: =+'Calculation of Risk Weighted As'!J18-'Calculation of Risk Weighte нац'!J18 -> 0
A19: 6. | B19: Миллий валютага деноминация қилинмаган ва миллий валютада молиялаштириш суммасидан ошиб кетган активлар | I19: =+'Calculation of Risk Weighted As'!I19-'Calculation of Risk Weighte нац'!I19 -> 0
A20: 7. | B20: Хорижий давлатларнинг давлат секторлари (ҳукуматлар ва марказий банклар бундан мустасно) ва хорижий компаниялар бўйича банк талаблари, шунингдек уларнинг қимматли қоғозлари билан таъминланган ёки кафолатланган активлар (кредитлар ва қимматли қоғозлар бундан мустасно) | D20: =+'Calculation of Risk Weighted As'!D20-'Calculation of Risk Weighte нац'!D20 -> 0 | E20: =+'Calculation of Risk Weighted As'!E20-'Calculation of Risk Weighte нац'!E20 -> 0 | G20: =+'Calculation of Risk Weighted As'!G20-'Calculation of Risk Weighte нац'!G20 -> 0 | I20: =+'Calculation of Risk Weighted As'!I20-'Calculation of Risk Weighte нац'!I20 -> 0 | J20: =+'Calculation of Risk Weighted As'!J20-'Calculation of Risk Weighte нац'!J20 -> 0
A21: 8. | B21: Кредит ва лизинглар, соф
A22: 8.1. | B22: Юридик шахсларга ажратилган кредит ва лизинглар, соф
A23: а | B23: Ўзбекистон Республикаси ҳукумати ва Марказий банкига тўғридан-тўғри берилган кредитлар | D23: =+'Calculation of Risk Weighted As'!D23-'Calculation of Risk Weighte нац'!D23 -> 0
A24: б | B24: Халқаро молия институтларига берилган кредитлар, халқаро молия ташкилотларининг қимматли қоғозлари билан таъминланган ёки улар томонидан кафолатланган кредитлар | D24: =+'Calculation of Risk Weighted As'!D24-'Calculation of Risk Weighte нац'!D24 -> 0
A25: в | B25: Кредитларнинг депозит билан таъминланган қисми | D25: =+'Calculation of Risk Weighted As'!D25-'Calculation of Risk Weighte нац'!D25 -> 0 | E25: =+'Calculation of Risk Weighted As'!E25-'Calculation of Risk Weighte нац'!E25 -> 0
A26: г | B26: Жорий бозор қийматида баҳоланган ва ЎзР Ҳукумати, ЎзР Марказий банки томонидан эмиссия қилинган ёки кафолатланган қимматли қоғозлар кўринишидаги гаров билан таъминланган ёки кафолатланган кредитлар, уларнинг қисмлари | D26: =+'Calculation of Risk Weighted As'!D26-'Calculation of Risk Weighte нац'!D26 -> 0
A27: д | B27: Дастлабки гаров ҳуқуқи банкка тегишли бўлмаган кредитлар | I27: =+'Calculation of Risk Weighted As'!I27-'Calculation of Risk Weighte нац'!I27 -> 0
A28: е | B28: Қайта тикланадиган энергия манбалари учун ажратилган кредитлар | D28: =+'Calculation of Risk Weighted As'!D28-'Calculation of Risk Weighte нац'!D28 -> 0 | I28: =+'Calculation of Risk Weighted As'!I28-'Calculation of Risk Weighte нац'!I28 -> 0 | J28: =+'Calculation of Risk Weighted As'!J28-'Calculation of Risk Weighte нац'!J28 -> 0 | K28: =+'Calculation of Risk Weighted As'!K28-'Calculation of Risk Weighte нац'!K28 -> 0
A29: ж | B29: 2024 йил 1 апрелдан бошлаб 2025 йил 1 июнга қадар доимий даромадга эга бўлган, шунингдек камида олти ой давомида банк ҳисобварағида, шу жумладан банк картасида маблағлар айланмасига эга бўлган кичик тадбиркорлик субъектларига микромолиялаштириш фаолияти доирасида кўрсатилган хизматлар (оилавий тадбиркорликни ривожлантириш дастурлари доирасида ажратилган кредитлар мустасно) | H29: =+'Calculation of Risk Weighted As'!H29-'Calculation of Risk Weighte нац'!H29 -> 0
A30: з | B30: 2024 йил 1 апрелдан бошлаб 2025 йил 1 июнга қадар мазкур жадвалнинг 8.1.ж-қаторида қайд этилган хизматларни кўрсатиш мақсадида микромолия ташкилотларига ажратилган кредитлар | H30: =+'Calculation of Risk Weighted As'!H30-'Calculation of Risk Weighte нац'!H30 -> 0
A31: и | B31: 2025 йил 1 июндан бошлаб кичик тадбиркорлик субъектларига ажратилган жами қолдиқ суммаси банк регулятив капиталининг 0,2 фоизидан ошмаган, бироқ энг кўпи билан 15 млрд. сўмгача кредитлар (оилавий тадбиркорликни ривожлантириш дастурлари доирасида ажратилган кредитлар мустасно) | H31: =+'Calculation of Risk Weighted As'!H31-'Calculation of Risk Weighte нац'!H31 -> 11861258
A32: к | B32: Юридик шахсларга ажратилган бошқа барча кредит, лизинг ва кўрсатилган факторинг хизматлари | I32: =+'Calculation of Risk Weighted As'!I32-'Calculation of Risk Weighte нац'!I32 -> 2924987028 | J32: =+'Calculation of Risk Weighted As'!J32-'Calculation of Risk Weighte нац'!J32 -> 439944383 | K32: =+'Calculation of Risk Weighted As'!K32-'Calculation of Risk Weighte нац'!K32 -> 253902144
A33: л | B33: Юридик шахсларнинг муаммоли кредит ва лизинглари, соф | K33: =+'Calculation of Risk Weighted As'!K33-'Calculation of Risk Weighte нац'!K33 -> 83593974
A34: 8.2. | B34: Жисмоний шахсларга ажратилган кредитлар, соф
A35: а | B35: Дастлабки гаров ҳуқуқи банкка тегишли бўлмаган кредитлар | I35: =+'Calculation of Risk Weighted As'!I35-'Calculation of Risk Weighte нац'!I35 -> 0
A36: б | B36: Кредитларнинг (микроқарзларнинг) депозит билан таъминланган қисми | D36: =+'Calculation of Risk Weighted As'!D36-'Calculation of Risk Weighte нац'!D36 -> 0 | E36: =+'Calculation of Risk Weighted As'!E36-'Calculation of Risk Weighte нац'!E36 -> 0
A37: в | B37: 2024 йил 1 июлга қадар ажратилган ипотека кредитлари | F37: =+'Calculation of Risk Weighted As'!F37-'Calculation of Risk Weighte нац'!F37 -> 0 | G37: =+'Calculation of Risk Weighted As'!G37-'Calculation of Risk Weighte нац'!G37 -> 0 | I37: =+'Calculation of Risk Weighted As'!I37-'Calculation of Risk Weighte нац'!I37 -> 0 | J37: =+'Calculation of Risk Weighted As'!J37-'Calculation of Risk Weighte нац'!J37 -> 0
A38: г | B38: 2024 йил 1 июлдан бошлаб ажратилган ипотека кредитлари | F38: =+'Calculation of Risk Weighted As'!F38-'Calculation of Risk Weighte нац'!F38 -> 0 | G38: =+'Calculation of Risk Weighted As'!G38-'Calculation of Risk Weighte нац'!G38 -> 0 | I38: =+'Calculation of Risk Weighted As'!I38-'Calculation of Risk Weighte нац'!I38 -> 0 | J38: =+'Calculation of Risk Weighted As'!J38-'Calculation of Risk Weighte нац'!J38 -> 0
A39: д | B39: 2023 йил 20 августга қадар автомобиль сотиб олиш учун ажратилган кредитлар | I39: =+'Calculation of Risk Weighted As'!I39-'Calculation of Risk Weighte нац'!I39 -> 0 | J39: =+'Calculation of Risk Weighted As'!J39-'Calculation of Risk Weighte нац'!J39 -> 0 | K39: =+'Calculation of Risk Weighted As'!K39-'Calculation of Risk Weighte нац'!K39 -> 0
A40: е | B40: 2023 йил 20 августдан бошлаб 2024 йил 1 июлга қадар жисмоний шахсларга автомобиль сотиб олиш учун ажратилган кредитлар | I40: =+'Calculation of Risk Weighted As'!I40-'Calculation of Risk Weighte нац'!I40 -> 0 | J40: =+'Calculation of Risk Weighted As'!J40-'Calculation of Risk Weighte нац'!J40 -> 0 | K40: =+'Calculation of Risk Weighted As'!K40-'Calculation of Risk Weighte нац'!K40 -> 0
A41: ж | B41: 2024 йил 1 июлдан бошлаб жисмоний шахсларга автомобиль сотиб олиш учун ажратилган кредитлар | I41: =+'Calculation of Risk Weighted As'!I41-'Calculation of Risk Weighte нац'!I41 -> 0 | J41: =+'Calculation of Risk Weighted As'!J41-'Calculation of Risk Weighte нац'!J41 -> 0 | K41: =+'Calculation of Risk Weighted As'!K41-'Calculation of Risk Weighte нац'!K41 -> 0
A42: з | B42: 2024 йил 1 июлдан бошлаб 2025 йил 1 январга қадар қарз юки 60 фоиз ва ундан паст ҳолда жисмоний шахсларга ажратилган кредитлар (микроқарзлар) (автокредит, ипотека, оилавий тадбиркорликни ривожлантириш ва таълим дастурлари кредитлари мустасно) | I42: =+'Calculation of Risk Weighted As'!I42-'Calculation of Risk Weighte нац'!I42 -> 0
A43: и | B43: 2024 йил 1 июлдан бошлаб 2025 йил 1 январга қадар қарз юки 60 фоиздан юқори бўлган ёки қарз юки аниқлаш имкони бўлмаган жисмоний шахсларга берилган кредитлар (микроқарзлар) (автокредит, ипотека, оилавий тадбиркорликни ривожлантириш ва таълим дастурлари кредитлари мустасно) | J43: =+'Calculation of Risk Weighted As'!J43-'Calculation of Risk Weighte нац'!J43 -> 0
A44: к | B44: 2025 йил 1 январдан бошлаб қарз юки 50 фоиз ва ундан паст ҳолда жисмоний шахсларга ажратилган кредитлар (микроқарзлар) (автокредит, ипотека, оилавий тадбиркорликни ривожлантириш ва таълим дастурлари кредитлари мустасно) | I44: =+'Calculation of Risk Weighted As'!I44-'Calculation of Risk Weighte нац'!I44 -> 0
A45: л | B45: 2025 йил 1 январдан бошлаб қарз юки 50 фоиздан юқори бўлган ёки қарз юки аниқлаш имкони бўлмаган жисмоний шахсларга берилган кредитлар (микроқарзлар) (автокредит, ипотека, оилавий тадбиркорликни ривожлантириш ва таълим дастурлари кредитлари мустасно) | J45: =+'Calculation of Risk Weighted As'!J45-'Calculation of Risk Weighte нац'!J45 -> 0
A46: м | B46: Қайта тикланадиган энергия манбалари учун ажратилган кредитлар | D46: =+'Calculation of Risk Weighted As'!D46-'Calculation of Risk Weighte нац'!D46 -> 0 | I46: =+'Calculation of Risk Weighted As'!I46-'Calculation of Risk Weighte нац'!I46 -> 0 | J46: =+'Calculation of Risk Weighted As'!J46-'Calculation of Risk Weighte нац'!J46 -> 0 | K46: =+'Calculation of Risk Weighted As'!K46-'Calculation of Risk Weighte нац'!K46 -> 0
A47: н | B47: 2024 йил 1 апрелдан бошлаб 2025 йил 1 июнга қадар доимий даромадга эга бўлган, шунингдек камида олти ой давомида банк ҳисобварағида, шу жумладан банк картасида маблағлар айланмасига эга бўлган ўзини ўзи банд қилган шахсларга микромолиялаштириш фаолияти доирасида кўрсатилган хизматлар (оилавий тадбиркорликни ривожлантириш дастурлари доирасида ажратилган кредитлар мустасно) | H47: =+'Calculation of Risk Weighted As'!H47-'Calculation of Risk Weighte нац'!H47 -> 0
A48: о | B48: 2025 йил 1 июндан бошлаб доимий даромадга эга бўлган ёки камида охирги узлуксиз олти ой давомида ҳар ой банк ҳисобварағида, шу жумладан банк картасида маблағлар айланмасига эга бўлган ўзини ўзи банд қилган шахсларга ажратилган кредитлар | H48: =+'Calculation of Risk Weighted As'!H48-'Calculation of Risk Weighte нац'!H48 -> 0 | I48: =+'Calculation of Risk Weighted As'!I48-'Calculation of Risk Weighte нац'!I48 -> 0 | J48: =+'Calculation of Risk Weighted As'!J48-'Calculation of Risk Weighte нац'!J48 -> 0 | K48: =+'Calculation of Risk Weighted As'!K48-'Calculation of Risk Weighte нац'!K48 -> 0
A49: п | B49: 2025 йил 1 июндан бошлаб доимий даромадга эга бўлмаган ёки охирги узлуксиз олти ой давомида ҳар ой банк ҳисобварағида, шу жумладан банк картасида маблағлар айланмасига эга бўлмаган ёки қарз йуки кўрсаткичи 50 фоиздан ошган ёхуд мазкур кўрсаткични аниқлаш имкони бўлмаган ўзини ўзи банд қилган шахсларга ажратилган кредитлар | J49: =+'Calculation of Risk Weighted As'!J49-'Calculation of Risk Weighte нац'!J49 -> 0 | K49: =+'Calculation of Risk Weighted As'!K49-'Calculation of Risk Weighte нац'!K49 -> 0
A50: р | B50: Жисмоний шахсларга ажратилган юқорида кўрсатилмаган бошқа барча кредитлар | I50: =+'Calculation of Risk Weighted As'!I50-'Calculation of Risk Weighte нац'!I50 -> 0 | J50: =+'Calculation of Risk Weighted As'!J50-'Calculation of Risk Weighte нац'!J50 -> 0 | K50: =+'Calculation of Risk Weighted As'!K50-'Calculation of Risk Weighte нац'!K50 -> 0
A51: с | B51: Жисмоний шахсларнинг муаммоли кредитлари, соф | K51: =+'Calculation of Risk Weighted As'!K51-'Calculation of Risk Weighte нац'!K51 -> 0
A52: 9. | B52: Банкнинг асосий воситалари ва бошқа хусусий мол-мулклари
A53: а | B53: Банк фаолиятидаги фойдаланиладиган асосий воситалар (амортизацияни чегирган ҳолда) | I53: =+'Calculation of Risk Weighted As'!I53-'Calculation of Risk Weighte нац'!I53 -> 0
A54: б | B54: Банкнинг бошқа хусусий мулклари | I54: =+'Calculation of Risk Weighted As'!I54-'Calculation of Risk Weighte нац'!I54 -> 0
A55: в | B55: Қарздорликни тўлиқ ёки қисман ундириш мақсадида банк балансига қабул қилинган кўчмас мулк | J55: =+'Calculation of Risk Weighted As'!J55-'Calculation of Risk Weighte нац'!J55 -> 0 | K55: =+'Calculation of Risk Weighted As'!K55-'Calculation of Risk Weighte нац'!K55 -> 0
A56: г | B56: Икки йилдан ортиқ вақт мобайнида банк фойдаланмаётган банкнинг кўчмас мулки | J56: =+'Calculation of Risk Weighted As'!J56-'Calculation of Risk Weighte нац'!J56 -> 0 | K56: =+'Calculation of Risk Weighted As'!K56-'Calculation of Risk Weighte нац'!K56 -> 0
A57: 10. | B57: Молиявий бўлган фаолият билан шуғулланувчи хўжалик юритувчи субъектларнинг капиталига қилинган барча инвестициялар, соф | D57: =+'Calculation of Risk Weighted As'!D57-'Calculation of Risk Weighte нац'!D57 -> 0 | J57: =+'Calculation of Risk Weighted As'!J57-'Calculation of Risk Weighte нац'!J57 -> 0 | K57: =+'Calculation of Risk Weighted As'!K57-'Calculation of Risk Weighte нац'!K57 -> 0 | L57: =+'Calculation of Risk Weighted As'!L57-'Calculation of Risk Weighte нац'!L57 -> 0
A58: 11. | B58: Молиявий бўлмаган фаолият билан шуғулланувчи хўжалик юритувчи субъектларнинг капиталига қилинган барча инвестициялар, соф | D58: =+'Calculation of Risk Weighted As'!D58-'Calculation of Risk Weighte нац'!D58 -> 0 | J58: =+'Calculation of Risk Weighted As'!J58-'Calculation of Risk Weighte нац'!J58 -> 0 | K58: =+'Calculation of Risk Weighted As'!K58-'Calculation of Risk Weighte нац'!K58 -> 0
A59: 12. | B59: Номоддий активлар, соф | D59: =+'Calculation of Risk Weighted As'!D59-'Calculation of Risk Weighte нац'!D59 -> 0 | I59: =+'Calculation of Risk Weighted As'!I59-'Calculation of Risk Weighte нац'!I59 -> 0
A60: 13. | B60: Молиявий инструментлар бўйича мижозларнинг мажбуриятлари, соф | D60: =+'Calculation of Risk Weighted As'!D60-'Calculation of Risk Weighte нац'!D60 -> 0 | E60: =+'Calculation of Risk Weighted As'!E60-'Calculation of Risk Weighte нац'!E60 -> 0 | I60: =+'Calculation of Risk Weighted As'!I60-'Calculation of Risk Weighte нац'!I60 -> 36791473 | K60: =+'Calculation of Risk Weighted As'!K60-'Calculation of Risk Weighte нац'!K60 -> 0
A61: 14. | B61: Бошқа муаммоли активлар | K61: =+'Calculation of Risk Weighted As'!K61-'Calculation of Risk Weighte нац'!K61 -> 0
A62: 15. | B62: Стандарт деб таснифланган активлар бўйича яратилган захиралар | D62: =+'Calculation of Risk Weighted As'!D62-'Calculation of Risk Weighte нац'!D62 -> 0
A63: 16. | B63: Бошқа активлар, соф | D63: =+'Calculation of Risk Weighted As'!D63-'Calculation of Risk Weighte нац'!D63 -> 0 | E63: =+'Calculation of Risk Weighted As'!E63-'Calculation of Risk Weighte нац'!E63 -> 0 | F63: =+'Calculation of Risk Weighted As'!F63-'Calculation of Risk Weighte нац'!F63 -> 0 | G63: =+'Calculation of Risk Weighted As'!G63-'Calculation of Risk Weighte нац'!G63 -> 0 | H63: =+'Calculation of Risk Weighted As'!H63-'Calculation of Risk Weighte нац'!H63 -> 124233 | I63: =+'Calculation of Risk Weighted As'!I63-'Calculation of Risk Weighte нац'!I63 -> 451218176 | J63: =+'Calculation of Risk Weighted As'!J63-'Calculation of Risk Weighte нац'!J63 -> 27719863 | K63: =+'Calculation of Risk Weighted As'!K63-'Calculation of Risk Weighte нац'!K63 -> 58979036 | L63: =+'Calculation of Risk Weighted As'!L63-'Calculation of Risk Weighte нац'!L63 -> 0
A64: 17. | B64: Баланс активларининг умумий миқдори | D64: =SUM(D8:D61)+D63-D62 -> 66279338 | E64: =SUM(E8:E61)+E63-E62 -> 2100846885 | F64: =SUM(F8:F61)+F63-F62 -> 0 | G64: =SUM(G8:G61)+G63-G62 -> 698090002 | H64: =SUM(H8:H61)+H63-H62 -> 11985491 | I64: =SUM(I8:I61)+I63-I62 -> 3412996677 | J64: =SUM(J8:J61)+J63-J62 -> 1172371881 | K64: =SUM(K8:K61)+K63-K62 -> 396475154 | L64: =SUM(L8:L61)+L63-L62 -> 0 | M64: =SUM(D64:L64) -> 7859045428 | N64: =+[7]Balance!$E$47 -> 7859045428 | O64: =+M64-N64 -> 0
A65: 18. | B65: Таваккалчилик гурухларига асосан рискка (таваккалчиликка) тортилган активларининг умумий миқдори | E65: =E64*E3 -> 420169377 | F65: =F64*F3 -> 0 | G65: =G64*G3 -> 349045001 | H65: =H64*H3 -> 8989118.2 | I65: =I64*I3 -> 3412996677 | J65: =J64*J3 -> 1.7585578e+09 | K65: =K64*K3 -> 792950308 | L65: =L64*L3 -> 0
A66: 19. | B66: Баланс активларининг таваккалчиликка тортилган умумий миқдори | L66: =SUM(D65:L65) -> 6.7427083e+09
A69: № | B69: II. БАЛАНСДАН ТАШҚАРИ АКТИВЛАР | C69: Кредитни қайта ҳисоблаш омили | D69: 0 | E69: 0.2 | F69: 0.35 | G69: 0.5 | H69: 0.75 | I69: 1 | J69: 1.5 | K69: 2 | L69: 2.5
A70: 1 | B70: Банкнинг кредит ва лизинг бериш мажбурияти
A71: a | B71: Бир йилдан ортиқ муддатга | C71: 0.5 | D71: =+'Calculation of Risk Weighted As'!D71-'Calculation of Risk Weighte нац'!D71 -> 0 | E71: =+'Calculation of Risk Weighted As'!E71-'Calculation of Risk Weighte нац'!E71 -> 0 | F71: =+'Calculation of Risk Weighted As'!F71-'Calculation of Risk Weighte нац'!F71 -> 0 | G71: =+'Calculation of Risk Weighted As'!G71-'Calculation of Risk Weighte нац'!G71 -> 0 | H71: =+'Calculation of Risk Weighted As'!H71-'Calculation of Risk Weighte нац'!H71 -> 30063 | I71: =+'Calculation of Risk Weighted As'!I71-'Calculation of Risk Weighte нац'!I71 -> 212943643 | J71: =+'Calculation of Risk Weighted As'!J71-'Calculation of Risk Weighte нац'!J71 -> 88799486 | K71: =+'Calculation of Risk Weighted As'!K71-'Calculation of Risk Weighte нац'!K71 -> 403214
A72: б | B72: Бир йил ёки ундан кам муддатга | C72: 0.2 | D72: =+'Calculation of Risk Weighted As'!D72-'Calculation of Risk Weighte нац'!D72 -> 0 | E72: =+'Calculation of Risk Weighted As'!E72-'Calculation of Risk Weighte нац'!E72 -> 0 | F72: =+'Calculation of Risk Weighted As'!F72-'Calculation of Risk Weighte нац'!F72 -> 0 | G72: =+'Calculation of Risk Weighted As'!G72-'Calculation of Risk Weighte нац'!G72 -> 0 | H72: =+'Calculation of Risk Weighted As'!H72-'Calculation of Risk Weighte нац'!H72 -> 0 | I72: =+'Calculation of Risk Weighted As'!I72-'Calculation of Risk Weighte нац'!I72 -> 28139 | J72: =+'Calculation of Risk Weighted As'!J72-'Calculation of Risk Weighte нац'!J72 -> 20252471 | K72: =+'Calculation of Risk Weighted As'!K72-'Calculation of Risk Weighte нац'!K72 -> 90003 | M72: =SUM(D71:L72) -> 322547019 | N72: =+[7]Commitments!$E$4 -> 322547019 | O72: =+M72-N72 -> 0
A73: 2 | B73: Қимматли қоғозларни сотиб олиш бўйича муддатли битимлар (шу жумладан, қайта сотиб олиш шартномалари бўйича сотилган активлар) | C73: 1 | D73: =+'Calculation of Risk Weighted As'!D73-'Calculation of Risk Weighte нац'!D73 -> 0 | E73: =+'Calculation of Risk Weighted As'!E73-'Calculation of Risk Weighte нац'!E73 -> 0 | G73: =+'Calculation of Risk Weighted As'!G73-'Calculation of Risk Weighte нац'!G73 -> 0 | I73: =+'Calculation of Risk Weighted As'!I73-'Calculation of Risk Weighte нац'!I73 -> 0
A74: 3 | B74: Кафолат ва кафилликлар | C74: 1 | D74: =+'Calculation of Risk Weighted As'!D74-'Calculation of Risk Weighte нац'!D74 -> 0 | E74: =+'Calculation of Risk Weighted As'!E74-'Calculation of Risk Weighte нац'!E74 -> 0 | G74: =+'Calculation of Risk Weighted As'!G74-'Calculation of Risk Weighte нац'!G74 -> 0 | I74: =+'Calculation of Risk Weighted As'!I74-'Calculation of Risk Weighte нац'!I74 -> 442106241 | J74: =+'Calculation of Risk Weighted As'!J74-'Calculation of Risk Weighte нац'!J74 -> 0 | K74: =+'Calculation of Risk Weighted As'!J74-'Calculation of Risk Weighte нац'!J74 -> 0 | M74: =SUM(D74:L74) -> 442106241 | N74: =+[7]Commitments!$E$7 -> 442106241 | O74: =+M74-N74 -> 0
A75: 4 | B75: Aккредитивлар
A76: a | B76: Тўғридан-тўғри кредит ўрнини босувчи воситалар | C76: 1 | D76: =+'Calculation of Risk Weighted As'!D76-'Calculation of Risk Weighte нац'!D76 -> 0 | E76: =+'Calculation of Risk Weighted As'!E76-'Calculation of Risk Weighte нац'!E76 -> 0 | G76: =+'Calculation of Risk Weighted As'!G76-'Calculation of Risk Weighte нац'!G76 -> 0 | I76: =+'Calculation of Risk Weighted As'!I76-'Calculation of Risk Weighte нац'!I76 -> 0 | K76: =+'Calculation of Risk Weighted As'!J76-'Calculation of Risk Weighte нац'!J76 -> 0
A77: б | B77: Битимлар билан боғлиқ аккредитивлар | C77: 0.5 | D77: =+'Calculation of Risk Weighted As'!D77-'Calculation of Risk Weighte нац'!D77 -> 0 | E77: =+'Calculation of Risk Weighted As'!E77-'Calculation of Risk Weighte нац'!E77 -> 0 | G77: =+'Calculation of Risk Weighted As'!G77-'Calculation of Risk Weighte нац'!G77 -> 474604581 | I77: =+'Calculation of Risk Weighted As'!I77-'Calculation of Risk Weighte нац'!I77 -> 0 | K77: =+'Calculation of Risk Weighted As'!J77-'Calculation of Risk Weighte нац'!J77 -> 0
A78: в | B78: Савдога тегишли аккредитивлар | C78: 0.2 | D78: =+'Calculation of Risk Weighted As'!D78-'Calculation of Risk Weighte нац'!D78 -> 0 | E78: =+'Calculation of Risk Weighted As'!E78-'Calculation of Risk Weighte нац'!E78 -> 0 | G78: =+'Calculation of Risk Weighted As'!G78-'Calculation of Risk Weighte нац'!G78 -> 0 | I78: =+'Calculation of Risk Weighted As'!I78-'Calculation of Risk Weighte нац'!I78 -> 0 | K78: =+'Calculation of Risk Weighted As'!J78-'Calculation of Risk Weighte нац'!J78 -> 0
A79: г | B79: Бошқа аккредитивлар | C79: 1 | D79: =+'Calculation of Risk Weighted As'!D79-'Calculation of Risk Weighte нац'!D79 -> 0 | E79: =+'Calculation of Risk Weighted As'!E79-'Calculation of Risk Weighte нац'!E79 -> 0 | G79: =+'Calculation of Risk Weighted As'!G79-'Calculation of Risk Weighte нац'!G79 -> 0 | I79: =+'Calculation of Risk Weighted As'!I79-'Calculation of Risk Weighte нац'!I79 -> 554834111 | K79: =+'Calculation of Risk Weighted As'!J79-'Calculation of Risk Weighte нац'!J79 -> 0 | M79: =SUM(D76:L79) -> 1029438692 | N79: =+[7]Commitments!$E$10 -> 1029438692 | O79: =+M79-N79 -> 0
A80: 5 | B80: Форвард шартномалар, спот, своплар, опционлар ва шунга ўхшаш мажбуриятлар
A81: a | B81: Фоиз ставкалари бўйича шартномалар
A82: а1 | B82: Бир йил муддатгача | C82: 0.005 | D82: =+'Calculation of Risk Weighted As'!D82-'Calculation of Risk Weighte нац'!D82 -> 0 | E82: =+'Calculation of Risk Weighted As'!E82-'Calculation of Risk Weighte нац'!E82 -> 0 | G82: =+'Calculation of Risk Weighted As'!G82-'Calculation of Risk Weighte нац'!G82 -> 0 | I82: =+'Calculation of Risk Weighted As'!I82-'Calculation of Risk Weighte нац'!I82 -> 0
A83: а2 | B83: Бир йилдан икки йил муддатгача | C83: 0.01 | D83: =+'Calculation of Risk Weighted As'!D83-'Calculation of Risk Weighte нац'!D83 -> 0 | E83: =+'Calculation of Risk Weighted As'!E83-'Calculation of Risk Weighte нац'!E83 -> 0 | G83: =+'Calculation of Risk Weighted As'!G83-'Calculation of Risk Weighte нац'!G83 -> 0 | I83: =+'Calculation of Risk Weighted As'!I83-'Calculation of Risk Weighte нац'!I83 -> 0
A84: а3 | B84: Икки йилдан уч йил муддатгача | C84: 0.02 | D84: =+'Calculation of Risk Weighted As'!D84-'Calculation of Risk Weighte нац'!D84 -> 0 | E84: =+'Calculation of Risk Weighted As'!E84-'Calculation of Risk Weighte нац'!E84 -> 0 | G84: =+'Calculation of Risk Weighted As'!G84-'Calculation of Risk Weighte нац'!G84 -> 0 | I84: =+'Calculation of Risk Weighted As'!I84-'Calculation of Risk Weighte нац'!I84 -> 0
A85: б | B85: Валюта шартномалари ва олтин
A86: б1 | B86: Бир йилгача бўлган муддатда қайтариш | C86: 0.02 | D86: =+'Calculation of Risk Weighted As'!D86-'Calculation of Risk Weighte нац'!D86 -> 0 | E86: =+'Calculation of Risk Weighted As'!E86-'Calculation of Risk Weighte нац'!E86 -> 0 | G86: =+'Calculation of Risk Weighted As'!G86-'Calculation of Risk Weighte нац'!G86 -> 0 | I86: =+'Calculation of Risk Weighted As'!I86-'Calculation of Risk Weighte нац'!I86 -> 0
A87: б2 | B87: Бир йилдан икки йилгача бўлган муддатда қайтариш | C87: 0.05 | D87: =+'Calculation of Risk Weighted As'!D87-'Calculation of Risk Weighte нац'!D87 -> 0 | E87: =+'Calculation of Risk Weighted As'!E87-'Calculation of Risk Weighte нац'!E87 -> 0 | G87: =+'Calculation of Risk Weighted As'!G87-'Calculation of Risk Weighte нац'!G87 -> 0 | I87: =+'Calculation of Risk Weighted As'!I87-'Calculation of Risk Weighte нац'!I87 -> 0
A88: б3 | B88: Икки йилдан уч йилгача бўлган муддатда қайтариш | C88: 0.08 | D88: =+'Calculation of Risk Weighted As'!D88-'Calculation of Risk Weighte нац'!D88 -> 0 | E88: =+'Calculation of Risk Weighted As'!E88-'Calculation of Risk Weighte нац'!E88 -> 0 | G88: =+'Calculation of Risk Weighted As'!G88-'Calculation of Risk Weighte нац'!G88 -> 0 | I88: =+'Calculation of Risk Weighted As'!I88-'Calculation of Risk Weighte нац'!I88 -> 0
A89: 6 | B89: Балансдан ташқари активларнинг умумий миқдори | D89: =SUM(D71:D88) -> 0 | E89: =SUM(E71:E88) -> 0 | F89: =SUM(F71:F88) -> 0 | G89: =SUM(G71:G88) -> 474604581 | H89: =SUM(H71:H88) -> 30063 | I89: =SUM(I71:I88) -> 1209912134 | J89: =SUM(J71:J88) -> 109051957 | K89: =SUM(K71:K88) -> 493217
A90: 7 | B90: Таваккалчилик қиймати | D90: =+(D71*$C$71*$D$3)+(D72*$C$72*$D$3)+(D73*$C$73*$D$3)+(D74*$C$74*$D$3)+(D76*$C$76*$D$3)+(D77*$C$77*$D$3)+(D78*$C$78*$D$3)+(D79*$C$79*$D$3)+(D82*$C$82*$D$3)+(D83*$C$83*$D$3)+(D84*$C$84*$D$3)+(D86*$C$86*$D$3)+(D87*$C$87*$D$3)+(D88*$C$88*$D$3) -> 0 | E90: =+(E71*$C$71*$E$3)+(E72*$C$72*$E$3)+(E73*$C$73*$E$3)+(E74*$C$74*$E$3)+(E76*$C$76*$E$3)+(E77*$C$77*$E$3)+(E78*$C$78*$E$3)+(E79*$C$79*$E$3)+(E82*$C$82*$E$3)+(E83*$C$83*$E$3)+(E84*$C$84*$E$3)+(E86*$C$86*$E$3)+(E87*$C$87*$E$3)+(E88*$C$88*$E$3) -> 0 | F90: =+(F71*$C$71*$F$3)+(F72*$C$72*$F$3)+(F73*$C$73*$F$3)+(F74*$C$74*$F$3)+(F76*$C$76*$F$3)+(F77*$C$77*$F$3)+(F78*$C$78*$F$3)+(F79*$C$79*$F$3)+(F82*$C$82*$F$3)+(F83*$C$83*$F$3)+(F84*$C$84*$F$3)+(F86*$C$86*$F$3)+(F87*$C$87*$F$3)+(F88*$C$88*$F$3) -> 0 | G90: =+(G71*$C$71*$G$3)+(G72*$C$72*$G$3)+(G73*$C$73*$G$3)+(G74*$C$74*$G$3)+(G76*$C$76*$G$3)+(G77*$C$77*$G$3)+(G78*$C$78*$G$3)+(G79*$C$79*$G$3)+(G82*$C$82*$G$3)+(G83*$C$83*$G$3)+(G84*$C$84*$G$3)+(G86*$C$86*$G$3)+(G87*$C$87*$G$3)+(G88*$C$88*$G$3) -> 1.1865115e+08 | H90: =+(H71*$C$71*$G$3)+(H72*$C$72*$G$3)+(H73*$C$73*$G$3)+(H74*$C$74*$G$3)+(H76*$C$76*$G$3)+(H77*$C$77*$G$3)+(H78*$C$78*$G$3)+(H79*$C$79*$G$3)+(H82*$C$82*$G$3)+(H83*$C$83*$G$3)+(H84*$C$84*$G$3)+(H86*$C$86*$G$3)+(H87*$C$87*$G$3)+(H88*$C$88*$G$3) -> 7515.75 | I90: =+(I71*$C$71*$I$3)+(I72*$C$72*$I$3)+(I73*$C$73*$I$3)+(I74*$C$74*$I$3)+(I76*$C$76*$I$3)+(I77*$C$77*$I$3)+(I78*$C$78*$I$3)+(I79*$C$79*$I$3)+(I82*$C$82*$I$3)+(I83*$C$83*$I$3)+(I84*$C$84*$I$3)+(I86*$C$86*$I$3)+(I87*$C$87*$I$3)+(I88*$C$88*$I$3) -> 1.1034178e+09 | J90: =+(J71*$C$71*$J$3)+(J72*$C$72*$J$3)+(J73*$C$73*$J$3)+(J74*$C$74*$J$3)+(J76*$C$76*$J$3)+(J77*$C$77*$J$3)+(J78*$C$78*$J$3)+(J79*$C$79*$J$3)+(J82*$C$82*$J$3)+(J83*$C$83*$J$3)+(J84*$C$84*$J$3)+(J86*$C$86*$J$3)+(J87*$C$87*$J$3)+(J88*$C$88*$J$3) -> 72675356 | K90: =+(K71*$C$71*$L$3)+(K72*$C$72*$L$3)+(K73*$C$73*$L$3)+(K74*$C$74*$L$3)+(K76*$C$76*$L$3)+(K77*$C$77*$L$3)+(K78*$C$78*$L$3)+(K79*$C$79*$L$3)+(K82*$C$82*$L$3)+(K83*$C$83*$L$3)+(K84*$C$84*$L$3)+(K86*$C$86*$L$3)+(K87*$C$87*$L$3)+(K88*$C$88*$L$3) -> 549019
A91: 8 | B91: Жами балансдан ташқари активларнинг таваккалчиликка тортилган қиймати | L91: =SUM(D90:L90) -> 1.2953008e+09
A92: 9 | B92: Жами активларнинг таваккалчиликка тортилган қиймати | L92: =SUM(L91+L66) -> 8.0380091e+09
B94: Бошқарув Раис имзоси:
B96: Бош бухгалтер имзоси:

Sheet Calculation of Risk
A1: ОПЕРАЦИОН ВА БОЗОР ТАВАККАЛЧИЛИКЛАРИ ҲИСОБ-КИТОБИ | C1: 6а-жадвал
B2: =IF(C3>0," "&TEXT(C3,"гггг"),"Число,Месяц,Год") -> 2025
B3: =+'Bank Capital Calc'!B3 -> MKBANK | C3: =+'Bank Capital Calc'!C3 -> 46021
A4: № | B4: Кўрсаткичлар номи | C4: минг сўмда
A5: 1. | B5: =+""&(D$6-3)&" йилдаги банкнинг ялпи даромади" -> 2022 йилдаги банкнинг ялпи даромади | C5: =+C6+C8-C7-C9 -> 1287894464
A6: а. | B6: фоизли даромад | C6: 2589031954 | D6: =+B2 -> 2025 | E6: 13
A7: б. | B7: фоизли харажат | C7: 1758289358
A8: в. | B8: фоизсиз даромад | C8: 886968966
A9: г. | B9: фоизсиз харажат | C9: 429817098
A10: 2. | B10: =+""&(D$6-2)&" йилдаги банкнинг ялпи даромади" -> 2023 йилдаги банкнинг ялпи даромади | C10: =+C11+C13-C12-C14 -> 1322545992
A11: а. | B11: фоизли даромад | C11: 3219716484
A12: б. | B12: фоизли харажат | C12: 2475830862
A13: в. | B13: фоизсиз даромад | C13: 1479529469
A14: г. | B14: фоизсиз харажат | C14: 900869099
A15: 3. | B15: =+""&(D$6-1)&" йилдаги банкнинг ялпи даромади" -> 2024 йилдаги банкнинг ялпи даромади | C15: =+C16+C18-C17-C19 -> 1265205603
A16: а. | B16: фоизли даромад | C16: 4027791395
A17: б. | B17: фоизли харажат | C17: 3239799931
A18: в. | B18: фоизсиз даромад | C18: 1228713951
A19: г. | B19: фоизсиз харажат | C19: 751499812
A20: 4. | B20: Банкнинг ўртача ялпи даромади (оҳирги уч йил давомида) | C20: =(C5+C10+C15)/3 -> 1.291882e+09
A21: 5. | B21: Операцион таваккалчиликлар қиймати | C21: =+(100/C28)*C20*15% -> 1.4906331e+09
A23: 6. | B23: Валюта позицияси ҳисобварақлари | C23: 9167292 | E23: сўм қисми
A24: 7. | B24: Кўзда тутилмаган ҳолатлар бўйича талаблар | C24: 0 | D24: 92503, 92705, 92716, 92717, 92728, 92732 | E24: чет эл валютасидаги қолдиқларининг эквиваленти
A25: 8. | B25: Кўзда тутилмаган ҳолатлар бўйича мажбуриятлар | C25: 0 | D25: 92501, 92701, 92709, 92710, 92724, 92736 | E25: чет эл валютасидаги қолдиқларининг эквиваленти
A26: 9. | B26: Очиқ валюта позицияси, жами | C26: =ABS(C23+(C24-C25)) -> 9167292 | D26: =+C26*0.1 -> 916729.2
A27: 10. | B27: Бозор таваккалчилиги суммаси | C27: =+(100/C28)*(C26*10%) -> 7051763.1
A28: 11. | B28: Капитал монандлигига бўлган амалдаги минимал талаб | C28: =VLOOKUP($D$6,$D$6:$E$6,2,0) -> 13
B30: Бошқарув Раис имзоси:
B32: Бош бухгалтер имзоси:
