Workbook
Name jop: #REF!
Name kol: #REF!
Name TwentyLargestData: #REF!
Name Е: #REF!

Sheet Bank Capital Calc
A1: БАНКНИНГ РЕГУЛЯТИВ КАПИТАЛИ ҲИСОБ-КИТОБИ | C1: 5-жадвал | E1: №1
B3: "Ўзсаноатқурилишбанк" АТБ | C3: 45653
A4: № | B4: Кўрсаткичлар | C4: минг сўмда
A5: I. | B5: I ДАРАЖАЛИ КАПИТАЛ
A6: 1 | B6: I ДАРАЖАЛИ АСОСИЙ КАПИТАЛ
A7: 1.1. | B7: Оддий акциялар, нетто | C7: =+C8-C9 -> 4621911928
A8: a | B8: Тўлиқ тўланган оддий акциялар | C8: 4621911928
A9: б | B9: Минус: Қайта сотиб олинган оддий акциялар | C9: 0
A10: 1.2. | B10: Қўшимча капитал (оддий)
A11: 1.3. | B11: Тақсимланмаган фойда (зарар), шу жумладан капитал захиралар | C11: =+C12+C13-C14-C15 -> 4079440274
A12: а | B12: Капитал ва бошқа захиралар | C12: 1778603852
A13: б | B13: Тақсимланмаган фойда | C13: 2300836422
A14: в | B14: Ўтган даврлар (йиллар) учун зарарлар
A15: г | B15: Жорий йил учун зарар
A16: 1.4. | B16: Озчилик улуш эгаларининг банк йиғма балансига бирлашадиган корхоналардаги улушлари
A17: 1.5. | B17: Девальвация захираси
A18: 1.6. | B18: Чегирмалар ҳисоблангунга қадар жами I даражали асосий капитал | C18: =+C7+C10+C11+C16+C17 -> 8701352202
A19: 1.7. | B19: I даражали асосий капиталдан чегирмалар | C19: =C20+C21+C22+C23+C24 -> 122398482
A20: а | B20: Номоддий активлар (бундан банкнинг дастурий таъминотлари мустасно) | C20: 21378472
A21: б | B21: Бирлашмаган (консолидация қилинмаган) молиявий бўлган фаолият билан шуғулланувчи хўжалик юритувчи субъектларнинг капиталига қилинган инвестициялар | C21: =975097244-67066760-'Calculation of Risk Weighted As'!K55 -> 101020010
A22: в | B22: Бошқа банкларнинг капиталига қилинган инвестициялар
A23: г | B23: Банк томонидан муаммоли активлар бўйича қўшимча шакллантирилиши лозим бўлган захиралар
A24: д | B24: Банкка алоқадор бир ёки барча шахслар учун таваккалчиликнинг белгиланган энг кўп миқдоридан ортиқ қиймати | E24: =+'[6]Transactions of related parties'!$Z$89 -> 1385182301
A25: I | B25: I ДАРАЖАЛИ АСОСИЙ КАПИТАЛ | C25: =+C18-C19 -> 8578953720 | E25: =C18-C20-C21-C22-C23 -> 8578953720
A26: 2 | B26: I ДАРАЖАЛИ ҚЎШИМЧА КАПИТАЛ
A27: 2.1. | B27: Нокумулятив муддатсиз имтиёзли акциялар | C27: =+C28-C29 -> 7030000
A28: а | B28: Тўлиқ тўланган имтиёзли акциялар | C28: 7030000
A29: б | B29: Минус: Қайтиб сотиб олинган имтиёзли акциялар | C29: 0
A30: 2.2. | B30: Қўшилган капитал (имтиёзли) | C30: 696121
A31: 2.3. | B31: Озчилик улуш эгаларининг банк йиғма балансига бирлашадиган корхоналардаги улушлари | C31: 0
A32: 2.4. | B32: Шўъба корхоналарнинг улушлари (шўъба корхоналар томонидан чиқарилган ва капиталга тенглаштирилган учинчи шахслар эгалик қиладиган воситалар) | C32: 0
A33: II | B33: ЖАМИ I ДАРАЖАЛИ ҚЎШИМЧА КАПИТАЛ | C33: =+C27+C30+C31+C32 -> 7726121
A34: III | B34: ЖАМИ ТЎҒРИЛАНГАН I ДАРАЖАЛИ КАПИТАЛ | C34: =+C25+C33 -> 8586679841
B35: II ДАРАЖАЛИ КАПИТАЛ
A36: 3.1. | B36: Жорий йил соф фойдаси | C36: 1303171680
A37: 3.2. | B37: Стандарт активларга яратилган захиралар | C37: =IF(F37<(C45*1.25%),F37,(C45*1.25%)) -> 640100207 | E37: Резервы созданные по стандартным активам | F37: =[7]Balance!$C$39+[7]Balance!$C$61 -> 640100207
A38: 3.3. | B38: Чегирмалардан сўнг I даражали капиталнинг учдан бир қисмидан ошмаган миқдорда аралаш турдаги мажбуриятлар | F38: =+[7]Balance!$C$39+[7]Balance!$C$61 -> 640100207
A39: 3.4. | B39: Субординар қарз | C39: 2053007156 | F39: =+F37-F38 -> 0
A40: 3.5. | B40: Активларнинг бошланғич қийматига нисбатан баҳолаш қийматининг ошган суммасининг 45 фоизи миқдори | C40: 5938360
A41: 3.6. | B41: II даражали капиталнинг I даражали капиталдан ортиқча қисми (чегирмаси) | C41: =IF($C$34>=SUM($C$36:$C$40),0,(SUM($C$36:$C$40)-$C$34))*-1 -> 0
B42: Жами II даражали капитал | C42: =SUM(C36:C40) -> 4002217403
A43: IV | B43: ЧЕГИРМАЛАРНИ ҲИСОБГА ОЛГАН ҲОЛДАГИ II ДАРАЖАЛИ КАПИТАЛ | C43: =+C41+C42 -> 4002217403
A44: V | B44: ЖАМИ РЕГУЛЯТИВ КАПИТАЛ | C44: =+C34+C41+C42 -> 12588897244
A45: VI | B45: ТАВАККАЛЧИЛИККА ТОРТИЛГАН АКТИВЛАР УМУМИЙ СУММАСИ | C45: =+C46+C47+C48 -> 8.0786256e+10
A46: а | B46: Баланс ва балансдан ташқари активларнинг таваккалчиликни ҳисобга олган ҳолдаги активларнинг умумий суммаси | C46: =+'Calculation of Risk Weighted As'!K89 -> 7.5115179e+10
A47: б | B47: Операцион таваккалчилик | C47: =+'Calculation of Risk'!C21 -> 5.114329e+09
A48: в | B48: Бозор таваккалчилиги | C48: =+'Calculation of Risk'!C27 -> 5.56748e+08
A49: VII | B49: I ДАРАЖАЛИ АСОСИЙ КАПИТАЛНИНГ МОНАНДЛИК КОЭФФИЦИЕНТИ (I/VI) | C49: =IFERROR((+C25/C45),0) -> 0.10619323
A50: VIII | B50: I ДАРАЖАЛИ КАПИТАЛНИНГ МОНАНДЛИК КОЭФФИЦИЕНТИ (III/VI) | C50: =IFERROR((+C34/C45),0) -> 0.10628887
A51: IX | B51: РЕГУЛЯТИВ КАПИТАЛНИНГ МОНАНДЛИК КОЭФФИЦИЕНТИ (V/VI) | C51: =IFERROR((+C44/C45),0) -> 0.15582969
A52: X | B52: Левераж ҳисоб-китоби учун активлар | C52: =SUM(C53:C55)-C56 -> 94430545547
A53: а | B53: Жами активлар | C53: =+[7]Balance!$C$47 -> 87596989839
A54: б | B54: Балансдан ташқари активлар | C54: =SUM('Calculation of Risk Weighted As'!D68:K76) -> 6955954190
A55: в | B55: Ҳосилавий (дереватив) воситалар | C55: =+('Calculation of Risk Weighted As'!D79*'Calculation of Risk Weighted As'!$C$79*'Calculation of Risk Weighted As'!$D$3)+('Calculation of Risk Weighted As'!D80*'Calculation of Risk Weighted As'!$C$80*'Calculation of Risk Weighted As'!$D$3)+('Calculation of Risk Weighted As'!D81*'Calculation of Risk Weighted As'!$C$81*'Calculation of Risk Weighted As'!$D$3)+('Calculation of Risk Weighted As'!D83*'Calculation of Risk Weighted As'!$C$83*'Calculation of Risk Weighted As'!$D$3)+('Calculation of Risk Weighted As'!D84*'Calculation of Risk Weighted As'!$C$84*'Calculation of Risk Weighted As'!$D$3)+('Calculation of Risk Weighted As'!D85*'Calculation of Risk Weighted As'!$C$85*'Calculation of Risk Weighted As'!$D$3)+('Calculation of Risk Weighted As'!E79*'Calculation of Risk Weighted As'!$C$79*'Calculation of Risk Weighted As'!$E$3)+('Calculation of Risk Weighted As'!E80*'Calculation of Risk Weighted As'!$C$80*'Calculation of Risk Weighted As'!$E$3)+('Calculation of Risk Weighted As'!E81*'Calculation of Risk Weighted As'!$C$81*'Calculation of Risk Weighted As'!$E$3)+('Calculation of Risk Weighted As'!E83*'Calculation of Risk Weighted As'!$C$83*'Calculation of Risk Weighted As'!$E$3)+('Calculation of Risk Weighted As'!E84*'Calculation of Risk Weighted As'!$C$84*'Calculation of Risk Weighted As'!$E$3)+('Calculation of Risk Weighted As'!E85*'Calculation of Risk Weighted As'!$C$85*'Calculation of Risk Weighted As'!$E$3)+('Calculation of Risk Weighted As'!F79*'Calculation of Risk Weighted As'!$C$79*'Calculation of Risk Weighted As'!$F$3)+('Calculation of Risk Weighted As'!F80*$C$66*$F$3)+('Calculation of Risk Weighted As'!F81*$C$67*$F$3)+('Calculation of Risk Weighted As'!F83*$C$69*$F$3)+('Calculation of Risk Weighted As'!F84*$C$70*$F$3)+('Calculation of Risk Weighted As'!F85*$C$71*$F$3)+('Calculation of Risk Weighted As'!G79*'Calculation of Risk Weighted As'!$C$79*'Calculation of Risk Weighted As'!$G$3)+('Calculation of Risk Weighted As'!G80*'Calculation of Risk Weighted As'!$C$80*'Calculation of Risk Weighted As'!$G$3)+('Calculation of Risk Weighted As'!G81*'Calculation of Risk Weighted As'!$C$81*'Calculation of Risk Weighted As'!$G$3)+('Calculation of Risk Weighted As'!G83*'Calculation of Risk Weighted As'!$C$83*'Calculation of Risk Weighted As'!$G$3)+('Calculation of Risk Weighted As'!G84*'Calculation of Risk Weighted As'!$C$84*'Calculation of Risk Weighted As'!$G$3)+('Calculation of Risk Weighted As'!G85*'Calculation of Risk Weighted As'!$C$85*'Calculation of Risk Weighted As'!$G$3)+('Calculation of Risk Weighted As'!I79*'Calculation of Risk Weighted As'!$C$79*'Calculation of Risk Weighted As'!$I$3)+('Calculation of Risk Weighted As'!I80*'Calculation of Risk Weighted As'!$C$80*'Calculation of Risk Weighted As'!$I$3)+('Calculation of Risk Weighted As'!I81*'Calculation of Risk Weighted As'!$C$81*'Calculation of Risk Weighted As'!$I$3)+('Calculation of Risk Weighted As'!I83*'Calculation of Risk Weighted As'!$C$83*'Calculation of Risk Weighted As'!$I$3)+('Calculation of Risk Weighted As'!I84*'Calculation of Risk Weighted As'!$C$84*'Calculation of Risk Weighted As'!$I$3)+('Calculation of Risk Weighted As'!I85*'Calculation of Risk Weighted As'!$C$85*'Calculation of Risk Weighted As'!$I$3)+('Calculation of Risk Weighted As'!J79*'Calculation of Risk Weighted As'!$C$79*'Calculation of Risk Weighted As'!$J$3)+('Calculation of Risk Weighted As'!J80*'Calculation of Risk Weighted As'!$C$80*'Calculation of Risk Weighted As'!$J$3)+('Calculation of Risk Weighted As'!J81*'Calculation of Risk Weighted As'!$C$81*'Calculation of Risk Weighted As'!$J$3)+('Calculation of Risk Weighted As'!J83*'Calculation of Risk Weighted As'!$C$83*'Calculation of Risk Weighted As'!$J$3)+('Calculation of Risk Weighted As'!J84*'Calculation of Risk Weighted As'!$C$84*'Calculation of Risk Weighted As'!$J$3)+('Calculation of Risk Weighted As'!J85*'Calculation of Risk Weighted As'!$C$85*'Calculation of Risk Weighted As'!$J$3)+('Calculation of Risk Weighted As'!K79*'Calculation of Risk Weighted As'!$C$79*'Calculation of Risk Weighted As'!$K$3)+('Calculation of Risk Weighted As'!K80*'Calculation of Risk Weighted As'!$C$80*'Calculation of Risk Weighted As'!$K$3)+('Calculation of Risk Weighted As'!K81*'Calculation of Risk Weighted As'!$C$81*'Calculation of Risk Weighted As'!$K$3)+('Calculation of Risk Weighted As'!K83*'Calculation of Risk Weighted As'!$C$83*'Calculation of Risk Weighted As'!$K$3)+('Calculation of Risk Weighted As'!K84*'Calculation of Risk Weighted As'!$C$84*'Calculation of Risk Weighted As'!$K$3)+('Calculation of Risk Weighted As'!K85*'Calculation of Risk Weighted As'!$C$85*'Calculation of Risk Weighted As'!$K$3) -> 0
A56: г | B56: Минус: 1.7-қатор. Жами I даражали асосий капиталдан чегирмалар | C56: =+C19 -> 122398482
A57: XI | B57: Левераж коэффициенти | C57: =IFERROR((+C34/C52),0) -> 0.090931168
B59: Бошқарув Раис имзоси:
B61: Бош бухгалтер имзоси:

Sheet Лист1
B4: =+'Bank Capital Calc'!C34+'Bank Capital Calc'!C36 -> 9889851521 | D4: =+B4+993400000+671300000 -> 11554551521 | F4: =+D4+'Bank Capital Calc'!C43 -> 15556768924
B5: 8.0786256e+10 | D5: =+D4/B5 -> 0.1430262 | F5: =+F4/B5 -> 0.19256702
B6: =+B4/B5 -> 0.12241998

Sheet Bank Capital Calc (2)
A1: РАСЧЕТ РЕГУЛЯТИВНОГО КАПИТАЛА БАНКА | C1: Таблица-5
B3: =#REF! -> #REF! | C3: =+#REF! -> #REF!
A4: № | B4: Характеристики | C4: Итого капитала
A5: I. | B5: КАПИТАЛ УРОВНЯ 1
A6: 1 | B6: ОСНОВНОЙ КАПИТАЛ УРОВНЯ 1
A7: 1.1. | B7: Обыкновенные Акции, чистые | C7: Формула
A8: a | B8: Полностью оплаченные обыкновенные акции
A9: б | B9: Минус: Обратно Выкупленные обыкновенные акции
A10: 1.2. | B10: Добавленный капитал - Обыкновенные | C10: 0
A11: 1.3. | B11: Нераспределенная прибыль (убыток), в том числе капитальные резервы | C11: Формула
A12: а | B12: Капитальные резервы
A13: б | B13: Нераспределенная прибыль
A14: в | B14: Убыток за предыдущие периоды
A15: г | B15: Убыток за текущий год
A16: 1.4. | B16: Интерес меньшинства в консолидированных дочерних компаниях (согласно МБС)
A17: 1.5. | B17: Резерв на девальвацию
B18: Итого основного капитала уровня I до вычетов | C18: Формула
A19: 1.6. | B19: Вычеты из суммы основного капитала уровня I | C19: Формула
A20: а | B20: Нематериальные активы
A21: б | B21: Все инвестиции в капитал неконсолидированных хозяйствующих субъектов, в том числе в долговые обязательства, которые образуют капитал хозяйствующих субъектов
A22: в | B22: Инвестиции в капитал других банков
A23: I | B23: ВСЕГО СКОРРЕКТИРОВАННЫЙ ОСНОВНОЙ КАПИТАЛ УРОВНЯ I | C23: Формула
A24: 2 | B24: ДОБАВЛЕННЫЙ КАПИТАЛ УРОВНЯ 1
A25: 2.1. | B25: Некумулятивные бессрочные привилегированные акции | C25: =+C26+C27 -> 0
A26: а | B26: Полностью оплаченные привилегированные акции
A27: б | B27: Минус: Обратно Выкупленные привилегированные акции
A28: 2.2. | B28: Добавленный капитал - Привилегированные | C28: 0
A29: 2.3. | B29: Интерес меньшинства в консолидированных дочерних компаниях | C29: 0
A30: 2.4. | B30: Доля участия дочерних предприятий (выпущенные дочерними предприятиями и находящиеся во владении третьих лиц инструменты, приравненные к капиталу) | C30: 0
A31: II | B31: ВСЕГО ДОБАВЛЕННЫЙ КАПИТАЛ УРОВНЯ I | C31: =+C25+C28+C29+C30 -> 0
A32: III | B32: ВСЕГО СКОРРЕКТИРОВАННЫЙ КАПИТАЛ УРОВНЯ I | C32: Формула
B33: КАПИТАЛ УРОВНЯ II
A34: 3.1. | B34: Прибыль за текущий год
A35: 3.2. | B35: Резервы, создаваемые на стандартные кредиты (активы), в размере не более 1.25% от общей суммы активов, взвешенных с учетом риска | C35: =IF(#REF!<(C43*1.25%),#REF!,(C43*1.25%)) -> #REF!
A36: 3.3. | B36: Излишки оценочной стоимости прироста над первоначальной стоимостью
A37: 3.4. | B37: Другие инструменты капитала (не более 1/3 части капитала 1 уровня после вычетов)
A38: 3.5. | B38: Субординированный долг
A39: 3.6. | B39: Вычеты превышения Капитала Уровня II над Капиталом Уровня I | C39: Формула
B40: Итого капитала Уровня II | C40: =SUM(C34:C38) -> #REF!
A41: IV | B41: СКОРРЕКТИРОВАННЫЙ КАПИТАЛ УРОВНЯ II | C41: Формула
A42: V | B42: ВСЕГО РЕГУЛЯТИВНЫЙ КАПИТАЛ | C42: Формула
A43: VI | B43: ОБЩАЯ СУММА АКТИВОВ ВЗВЕШЕННЫХ С УЧЕТОМ РИСКА | C43: =+C44+C45+C46 -> #REF!
A44: а | B44: Сумма балансовых и забалансовых активов, взвешенных с учетом риска | C44: =+'Calculation of Risk Weighted As'!#REF! -> #REF!
A45: б | B45: Операционный риск | C45: =+'Calculation of Risk'!C21 -> 5.114329e+09
A46: в | B46: Рыночный риск | C46: =+'Calculation of Risk'!C27 -> 5.56748e+08 | E46: =+'Calculation of Risk'!G12 -> 0
A47: VII | B47: КОЭФФИЦИЕНТ ОСНОВНОГО КАПИТАЛА УРОВНЯ I (I/VI) | C47: Формула
A48: VIII | B48: КОЭФФИЦИЕНТ КАПИТАЛА УРОВНЯ I (III/VI) | C48: Формула
A49: IX | B49: КОЭФФИЦИЕНТ ОБЩЕЙ СУММЫ КАПИТАЛА, ОСНОВАННОГО НА РИСКЕ (V/VI) | C49: Формула
A50: X | B50: Активы для расчета левеража | C50: Формула
A51: а | B51: Общие активы | C51: =+#REF! -> #REF!
A52: б | B52: Забалансовые инструменты | C52: =SUM('Calculation of Risk Weighted As'!D68:G76) -> 2101837112 | D52: =+'Calculation of Risk Weighted As'!#REF! -> #REF!
A53: в | B53: Деривативные (производные) инструменты | C53: =SUM('Calculation of Risk Weighted As'!#REF!) -> #REF!
A54: г | B54: Минус: Строка 1.6. Итого вычетов из суммы основного капитала Уровня 1 | C54: =+C19 -> Формула
A55: XI | B55: Коэффициент левеража | C55: Формула
B57: Подпись Председателя правления:
B59: Подпись Главного Бухгалтера:

Sheet Calculation of Risk Weighted As
A1: ТАВАККАЛЧИЛИКНИ ҲИСОБГА ОЛГАН ҲОЛДАГИ АКТИВЛАР | K1: 6-жадвал
B2: =+'Bank Capital Calc'!B3 -> "Ўзсаноатқурилишбанк" АТБ | I2: =+'Bank Capital Calc'!C3 -> 45653 | K2: минг сўмда
A3: № | B3: Кўрсаткичлар | D3: 0 | E3: 0.2 | F3: 0.35 | G3: 0.5 | H3: 0.75 | I3: 1 | J3: 1.5 | K3: 2
D4: Таваккалчилик | E4: Таваккалчилик | F4: Таваккалчилик | G4: Таваккалчилик | H4: Таваккалчилик | I4: Таваккалчилик | J4: Таваккалчилик | K4: Таваккалчилик
D5: I гуруҳ | E5: II гуруҳ | F5: III гуруҳ | G5: IV гуруҳ | H5: V гуруҳ | I5: VI гуруҳ | J5: VII гуруҳ | K5: VIII гуруҳ
B6: (A) | D6: (Б) | E6: (В) | F6: (Г) | G6: (Д) | H6: (Е) | I6: (Ж) | J6: (З) | K6: (И)
B7: I. БАЛАНС АКТИВЛАРИ
A8: 1. | B8: Кассадаги нақд пул ва бошқа тўлов ҳужжатлари ва қимматбаҳо металлар | D8: 1416743956
A9: 2. | B9: Йўлдаги нақд пуллар ва бошқа тўлов ҳужжатлари | E9: 293353682
A10: 3. | B10: Банкнинг Марказий банкдаги маблағлар | D10: 1125552298 | E10: 12551594
A11: 4. | B11: Бошқа банкларга жойлаштирилган пул маблағлари, жумладан вакиллик ҳисобварақлари, депозитлар ва кредитлар | E11: 3859174272 | G11: 1282463643 | I11: 1274018427 | J11: 38391322
A12: 5. | B12: Қимматли қоғозлар (соф)
A13: а | B13: Ўзбекистон Республикаси Ҳукумати ва Марказий банки томонидан чиқарилган қимматли қоғозлар | D13: 4188044732
A14: б | B14: Ипотекани қайта молиялаштириш ташкилотлари томонидан чиқарилган қимматли қоғозлар | E14: 65000000
A15: в | B15: Хорижий давлатларининг ҳукуматлари ва марказий банклари томонидан чиқарилган қимматли қоғозлар, шунингдек ушбу мамлакатларнинг марказий банклари ва ҳукуматларига нисбатан бошқа талаблар
A16: г | B16: Ўзбекистон Республикаси ҳудудида чиқарилган бошқа қимматли қоғозлар | J16: 10050000
A17: д | B17: Ўзбекистон Республикаси ҳудудидан ташқарида чиқарилган бошқа қимматли қоғозлар
A18: е | B18: РЕПО битимлари бўйича сотиб олинган қимматли қоғозлар | D18: 451663257
A19: 6. | B19: Миллий валютага деноминация қилинмаган ва миллий валютада молиялаштириш суммасидан ошиб кетган активлар
A20: 7. | B20: Хорижий давлатларнинг давлат секторлари (ҳукуматлар ва марказий банклар бундан мустасно) ва хорижий компаниялар бўйича банк талаблари, шунингдек уларнинг қимматли қоғозлари билан таъминланган ёки кафолатланган активлар (кредитлар ва қимматли қоғозлар бундан мустасно)
A21: 8. | B21: Кредит ва лизинглар, соф
A22: 8.1. | B22: Юридик шахсларга ажратилган кредит ва лизинглар, соф
A23: а | B23: Ўзбекистон Республикаси ҳукумати ва Марказий банкига тўғридан-тўғри берилган кредитлар | D23: 0
A24: б | B24: Халқаро молия институтларига берилган кредитлар, халқаро молия ташкилотларининг қимматли қоғозлари билан таъминланган ёки улар томонидан кафолатланган кредитлар | D24: 10836545
A25: в | B25: Кредитларнинг депозит билан таъминланган қисми | D25: 771903 | E25: 0
A26: г | B26: Жорий бозор қийматида баҳоланган ва ЎзР Ҳукумати, ЎзР Марказий банки томонидан эмиссия қилинган ёки кафолатланган қимматли қоғозлар кўринишидаги гаров билан таъминланган ёки кафолатланган кредитлар, уларнинг қисмлари | D26: 12353975293
A27: д | B27: Дастлабки гаров ҳуқуқи банкка тегишли бўлмаган кредитлар | I27: 111276553
A28: е | B28: Қайта тикланадиган энергия манбалари учун ажратилган кредитлар | D28: 9452501 | I28: 2520753 | J28: 5173636 | K28: 0
A29: ж | B29: 2024 йил 1 апрелдан бошлаб доимий даромадга эга бўлган, шунингдек камида олти ой давомида банк ҳисобварағида, шу жумладан банк картасида маблағлар айланмасига эга бўлган кичик тадбиркорлик субъектларига микромолиялаштириш фаолияти доирасида кўрсатилган хизматлар (оилавий тадбиркорликни ривожлантириш дастурлари доирасида ажратилган кредитлар мустасно) | H29: 0
A30: з | B30: 2024 йил 1 апрелдан бошлаб мазкур жадвалнинг 8.1.ж-қаторида қайд этилган хизматларни кўрсатиш мақсадида микромолия ташкилотларига ажратилган кредитлар | H30: 0
A31: и | B31: Юридик шахсларга ажратилган бошқа барча кредит, лизинг ва кўрсатилган факторинг хизматлари | I31: 34473688661 | J31: 4386605708 | K31: 1834469891
A32: к | B32: Юридик шахсларнинг муаммоли кредит ва лизинглари, соф | K32: 822604657
A33: 8.2. | B33: Жисмоний шахсларга ажратилган кредитлар, соф
A34: а | B34: Дастлабки гаров ҳуқуқи банкка тегишли бўлмаган кредитлар | I34: 0
A35: б | B35: Кредитларнинг (микроқарзларнинг) депозит билан таъминланган қисми | D35: 0 | E35: 0
A36: в | B36: 2024 йил 1 июлга қадар ажратилган ипотека кредитлари | F36: 283860692 | G36: 2271678794 | I36: 2356413851 | J36: 49418158
A37: г | B37: 2024 йил 1 июлдан бошлаб ажратилган ипотека кредитлари | F37: 370689 | G37: 5066855 | I37: 47967689 | J37: 720283523
A38: д | B38: 2023 йил 20 августга қадар автомобиль сотиб олиш учун ажратилган кредитлар | I38: 125995101 | J38: 180528906 | K38: 26755
A39: е | B39: 2023 йил 20 августдан бошлаб 2024 йил 1 июлга қадар жисмоний шахсларга автомобиль сотиб олиш учун ажратилган кредитлар | I39: 6089144 | J39: 68890830 | K39: 53538285
A40: ж | B40: 2024 йил 1 июлдан бошлаб жисмоний шахсларга автомобиль сотиб олиш учун ажратилган кредитлар | I40: 738876 | J40: 12206645 | K40: 1562393
A41: з | B41: 2024 йил 1 июлдан бошлаб 2025 йил 1 январга қадар қарз юки 60 фоиз ва ундан паст ҳолда жисмоний шахсларга ажратилган кредитлар (микроқарзлар) (автокредит, ипотека, оилавий тадбиркорликни ривожлантириш ва таълим дастурлари кредитлари мустасно) | I41: 249681552
A42: и | B42: 2024 йил 1 июлдан бошлаб 2025 йил 1 январга қадар қарз юки 60 фоиздан юқори бўлган ёки қарз юки аниқлаш имкони бўлмаган жисмоний шахсларга берилган кредитлар (микроқарзлар) (автокредит, ипотека, оилавий тадбиркорликни ривожлантириш ва таълим дастурлари кредитлари мустасно) | J42: 1104194319
A43: к | B43: 2025 йил 1 январдан бошлаб қарз юки 50 фоиз ва ундан паст ҳолда жисмоний шахсларга ажратилган кредитлар (микроқарзлар) (автокредит, ипотека, оилавий тадбиркорликни ривожлантириш ва таълим дастурлари кредитлари мустасно) | I43: 0
A44: л | B44: 2025 йил 1 январдан бошлаб қарз юки 50 фоиздан юқори бўлган ёки қарз юки аниқлаш имкони бўлмаган жисмоний шахсларга берилган кредитлар (микроқарзлар) (автокредит, ипотека, оилавий тадбиркорликни ривожлантириш ва таълим дастурлари кредитлари мустасно) | J44: 0
A45: м | B45: Қайта тикланадиган энергия манбалари учун ажратилган кредитлар | D45: 3650489 | I45: 0 | J45: 0 | K45: 0
A46: н | B46: 2024 йил 1 апрелдан бошлаб доимий даромадга эга бўлган, шунингдек камида олти ой давомида банк ҳисобварағида, шу жумладан банк картасида маблағлар айланмасига эга бўлган ўзини ўзи банд қилган шахсларга микромолиялаштириш фаолияти доирасида кўрсатилган хизматлар (оилавий тадбиркорликни ривожлантириш дастурлари доирасида ажратилган кредитлар мустасно) | H46: 0
A47: о | B47: Жисмоний шахсларга ажратилган юқорида кўрсатилмаган бошқа барча кредитлар | I47: 311979510 | J47: 109002843 | K47: 1534999985
A48: п | B48: Жисмоний шахсларнинг муаммоли кредитлари, соф | K48: 203411682
A49: 9. | B49: Банкнинг асосий воситалари ва бошқа хусусий мол-мулклари
A50: а | B50: Банк фаолиятидаги фойдаланиладиган асосий воситалар (амортизацияни чегирган ҳолда) | I50: 3641694109
A51: б | B51: Банкнинг бошқа хусусий мулклари | I51: =661533730-J52-K52-J53-K53 -> 0
A52: в | B52: Қарздорликни тўлиқ ёки қисман ундириш мақсадида банк балансига қабул қилинган кўчмас мулк | J52: 661493906 | K52: 0
A53: г | B53: Икки йилдан ортиқ вақт мобайнида банк фойдаланмаётган банкнинг кўчмас мулки | J53: 39824 | K53: 0
A54: 10. | B54: Молиявий бўлган фаолият билан шуғулланувчи хўжалик юритувчи субъектларнинг капиталига қилинган барча инвестициялар, соф | D54: 168086770
A55: 11. | B55: Молиявий бўлмаган фаолият билан шуғулланувчи хўжалик юритувчи субъектларнинг капиталига қилинган барча инвестициялар, соф | D55: 0 | K55: 807010474
A56: 12. | B56: Номоддий активлар, соф | D56: =+'Bank Capital Calc'!C20 -> 21378472 | I56: =55050616-D56 -> 33672144
A57: 13. | B57: Молиявий инструментлар бўйича мижозларнинг мажбуриятлари, соф | K57: 109734946
A58: 14. | B58: Бошқа муаммоли активлар | K58: 0
A59: 15. | B59: Стандарт деб таснифланган активлар бўйича яратилган захиралар | D59: =+[7]Balance!$C$39 -> 615338207 | L59: =+D59 -> 615338207 | M59: =+[7]Balance!$C$39 -> 615338207 | N59: =+L59-M59 -> 0
A60: 16. | B60: Бошқа активлар, соф | D60: 458707842 | E60: 83099952 | F60: 11250860 | G60: 24327050 | H60: 0 | I60: 3675150920 | J60: 434999852 | K60: 351740075
A61: 17. | B61: Баланс активларининг умумий миқдори | D61: =SUM(D8:D58)+D60-D59 -> 19593525851 | E61: =SUM(E8:E58)+E60-E59 -> 4313179500 | F61: =SUM(F8:F58)+F60-F59 -> 295482241 | G61: =SUM(G8:G58)+G60-G59 -> 3583536342 | H61: =SUM(H8:H58)+H60-H59 -> 0 | I61: =SUM(I8:I58)+I60-I59 -> 46310887290 | J61: =SUM(J8:J58)+J60-J59 -> 7781279472 | K61: =SUM(K8:K58)+K60-K59 -> 5719099143 | L61: =SUM(D61:K61) -> 87596989839 | M61: =+[7]Balance!$C$47 -> 87596989839 | N61: =+L61-M61 -> 0
A62: 18. | B62: Таваккалчилик гурухларига асосан рискка (таваккалчиликка) тортилган активларининг умумий миқдори | E62: =E61*E3 -> 862635900 | F62: =F61*F3 -> 1.0341878e+08 | G62: =G61*G3 -> 1791768171 | H62: =H61*H3 -> 0 | I62: =I61*I3 -> 46310887290 | J62: =J61*J3 -> 11671919208 | K62: =K61*K3 -> 11438198286
A63: 19. | B63: Баланс активларининг таваккалчиликка тортилган умумий миқдори | K63: =SUM(E62:K62) -> 7.2178828e+10
A66: № | B66: II. БАЛАНСДАН ТАШҚАРИ АКТИВЛАР | C66: Кредитни қайта ҳисоблаш омили | D66: 0 | E66: 0.2 | F66: 0.35 | G66: 0.5 | H66: 0.75 | I66: 1 | J66: 1.5 | K66: 2
A67: 1 | B67: Банкнинг кредит ва лизинг бериш мажбурияти
A68: a | B68: Бир йилдан ортиқ муддатга | C68: 0.5 | I68: 1211558591 | J68: 0 | K68: 1347118
A69: б | B69: Бир йил ёки ундан кам муддатга | C69: 0.2 | I69: 1002728635 | J69: 0 | K69: 20084 | L69: =SUM(D68:K69) -> 2215654428 | M69: =+[7]Commitments!$C$4 -> 2215654428 | N69: =+L69-M69 -> 0
A70: 2 | B70: Қимматли қоғозларни сотиб олиш бўйича муддатли битимлар (шу жумладан, қайта сотиб олиш шартномалари бўйича сотилган активлар) | C70: 1 | D70: 507164188
A71: 3 | B71: Кафолат ва кафилликлар | C71: 1 | D71: 206992592 | I71: =1900015491 -> 1900015491 | J71: 0 | K71: 44981244 | L71: =SUM(D71:K71) -> 2151989327 | M71: =+[7]Commitments!$C$7 -> 2151989327 | N71: =+L71-M71 -> 0
A72: 4 | B72: Aккредитивлар
A73: a | B73: Тўғридан-тўғри кредит ўрнини босувчи воситалар | C73: 1
A74: б | B74: Битимлар билан боғлиқ аккредитивлар | C74: 0.5
A75: в | B75: Савдога тегишли аккредитивлар | C75: 0.2 | D75: =1369023159+18657173 -> 1387680332 | I75: =693465915 -> 693465915 | K75: 0
A76: г | B76: Бошқа аккредитивлар | C76: 1 | L76: =SUM(D73:K76) -> 2081146247 | M76: =+[7]Commitments!$C$10 -> 2081146247 | N76: =+L76-M76 -> 0
A77: 5 | B77: Форвард шартномалар, спот, своплар, опционлар ва шунга ўхшаш мажбуриятлар
A78: a | B78: Фоиз ставкалари бўйича шартномалар
A79: а1 | B79: Бир йил муддатгача | C79: 0.005
A80: а2 | B80: Бир йилдан икки йил муддатгача | C80: 0.01
A81: а3 | B81: Икки йилдан уч йил муддатгача | C81: 0.02
A82: б | B82: Валюта шартномалари ва олтин
A83: б1 | B83: Бир йилгача бўлган муддатда қайтариш | C83: 0.02 | D83: 329472240
A84: б2 | B84: Бир йилдан икки йилгача бўлган муддатда қайтариш | C84: 0.05
A85: б3 | B85: Икки йилдан уч йилгача бўлган муддатда қайтариш | C85: 0.08
A86: 6 | B86: Балансдан ташқари активларнинг умумий миқдори | D86: =SUM(D68:D85) -> 2431309352 | E86: =SUM(E68:E85) -> 0 | F86: =SUM(F68:F85) -> 0 | G86: =SUM(G68:G85) -> 0 | H86: =SUM(H68:H85) -> 0 | I86: =SUM(I68:I85) -> 4807768632 | J86: =SUM(J68:J85) -> 0 | K86: =SUM(K68:K85) -> 46348446
A87: 7 | B87: Таваккалчилик қиймати | D87: =+(D68*$C$68*$D$3)+(D69*$C$69*$D$3)+(D70*$C$70*$D$3)+(D71*$C$71*$D$3)+(D73*$C$73*$D$3)+(D74*$C$74*$D$3)+(D75*$C$75*$D$3)+(D76*$C$76*$D$3)+(D79*$C$79*$D$3)+(D80*$C$80*$D$3)+(D81*$C$81*$D$3)+(D83*$C$83*$D$3)+(D84*$C$84*$D$3)+(D85*$C$85*$D$3) -> 0 | E87: =+(E68*$C$68*$E$3)+(E69*$C$69*$E$3)+(E70*$C$70*$E$3)+(E71*$C$71*$E$3)+(E73*$C$73*$E$3)+(E74*$C$74*$E$3)+(E75*$C$75*$E$3)+(E76*$C$76*$E$3)+(E79*$C$79*$E$3)+(E80*$C$80*$E$3)+(E81*$C$81*$E$3)+(E83*$C$83*$E$3)+(E84*$C$84*$E$3)+(E85*$C$85*$E$3) -> 0 | F87: =+(F68*$C$68*$F$3)+(F69*$C$69*$F$3)+(F70*$C$70*$F$3)+(F71*$C$71*$F$3)+(F73*$C$73*$F$3)+(F74*$C$74*$F$3)+(F75*$C$75*$F$3)+(F76*$C$76*$F$3)+(F79*$C$79*$F$3)+(F80*$C$80*$F$3)+(F81*$C$81*$F$3)+(F83*$C$83*$F$3)+(F84*$C$84*$F$3)+(F85*$C$85*$F$3) -> 0 | G87: =+(G68*$C$68*$G$3)+(G69*$C$69*$G$3)+(G70*$C$70*$G$3)+(G71*$C$71*$G$3)+(G73*$C$73*$G$3)+(G74*$C$74*$G$3)+(G75*$C$75*$G$3)+(G76*$C$76*$G$3)+(G79*$C$79*$G$3)+(G80*$C$80*$G$3)+(G81*$C$81*$G$3)+(G83*$C$83*$G$3)+(G84*$C$84*$G$3)+(G85*$C$85*$G$3) -> 0 | H87: =+(H68*$C$68*$G$3)+(H69*$C$69*$G$3)+(H70*$C$70*$G$3)+(H71*$C$71*$G$3)+(H73*$C$73*$G$3)+(H74*$C$74*$G$3)+(H75*$C$75*$G$3)+(H76*$C$76*$G$3)+(H79*$C$79*$G$3)+(H80*$C$80*$G$3)+(H81*$C$81*$G$3)+(H83*$C$83*$G$3)+(H84*$C$84*$G$3)+(H85*$C$85*$G$3) -> 0 | I87: =+(I68*$C$68*$I$3)+(I69*$C$69*$I$3)+(I70*$C$70*$I$3)+(I71*$C$71*$I$3)+(I73*$C$73*$I$3)+(I74*$C$74*$I$3)+(I75*$C$75*$I$3)+(I76*$C$76*$I$3)+(I79*$C$79*$I$3)+(I80*$C$80*$I$3)+(I81*$C$81*$I$3)+(I83*$C$83*$I$3)+(I84*$C$84*$I$3)+(I85*$C$85*$I$3) -> 2.8450337e+09 | J87: =+(J68*$C$68*$J$3)+(J69*$C$69*$J$3)+(J70*$C$70*$J$3)+(J71*$C$71*$J$3)+(J73*$C$73*$J$3)+(J74*$C$74*$J$3)+(J75*$C$75*$J$3)+(J76*$C$76*$J$3)+(J79*$C$79*$J$3)+(J80*$C$80*$J$3)+(J81*$C$81*$J$3)+(J83*$C$83*$J$3)+(J84*$C$84*$J$3)+(J85*$C$85*$J$3) -> 0 | K87: =+(K68*$C$68*$K$3)+(K69*$C$69*$K$3)+(K70*$C$70*$K$3)+(K71*$C$71*$K$3)+(K73*$C$73*$K$3)+(K74*$C$74*$K$3)+(K75*$C$75*$K$3)+(K76*$C$76*$K$3)+(K79*$C$79*$K$3)+(K80*$C$80*$K$3)+(K81*$C$81*$K$3)+(K83*$C$83*$K$3)+(K84*$C$84*$K$3)+(K85*$C$85*$K$3) -> 91317640
A88: 8 | B88: Жами балансдан ташқари активларнинг таваккалчиликка тортилган қиймати | K88: =SUM(D87:K87) -> 2.9363513e+09
A89: 9 | B89: Жами активларнинг таваккалчиликка тортилган қиймати | K89: =SUM(K88+K63) -> 7.5115179e+10
B91: Бошқарув Раис имзоси:
B93: Бош бухгалтер имзоси:

Sheet Calculation of Risk Weighte нац
A1: ТАВАККАЛЧИЛИКНИ ҲИСОБГА ОЛГАН ҲОЛДАГИ АКТИВЛАР | K1: 6.1-жадвал
B2: =+'Bank Capital Calc'!B3 -> "Ўзсаноатқурилишбанк" АТБ | I2: =+'Bank Capital Calc'!C3 -> 45653 | K2: минг сўмда
A3: № | B3: Кўрсаткичлар | D3: 0 | E3: 0.2 | F3: 0.35 | G3: 0.5 | H3: 0.75 | I3: 1 | J3: 1.5 | K3: 2
D4: Таваккалчилик | E4: Таваккалчилик | F4: Таваккалчилик | G4: Таваккалчилик | H4: Таваккалчилик | I4: Таваккалчилик | J4: Таваккалчилик | K4: Таваккалчилик
D5: I гуруҳ | E5: II гуруҳ | F5: III гуруҳ | G5: IV гуруҳ | H5: V гуруҳ | I5: VI гуруҳ | J5: VII гуруҳ | K5: VIII гуруҳ
B6: (A) | D6: (Б) | E6: (В) | F6: (Г) | G6: (Д) | H6: (Е) | I6: (Ж) | J6: (З) | K6: (И)
B7: I. БАЛАНС АКТИВЛАРИ
A8: 1. | B8: Кассадаги нақд пул ва бошқа тўлов ҳужжатлари ва қимматбаҳо металлар | D8: 350533865
A9: 2. | B9: Йўлдаги нақд пуллар ва бошқа тўлов ҳужжатлари | E9: 193951540
A10: 3. | B10: Банкнинг Марказий банкдаги маблағлар | D10: ='Calculation of Risk Weighted As'!D10 -> 1125552298 | E10: 0
A11: 4. | B11: Бошқа банкларга жойлаштирилган пул маблағлари, жумладан вакиллик ҳисобварақлари, депозитлар ва кредитлар | E11: 0 | G11: 247225427 | I11: 385736977 | J11: 275906
A12: 5. | B12: Қимматли қоғозлар (соф)
A13: а | B13: Ўзбекистон Республикаси Ҳукумати ва Марказий банки томонидан чиқарилган қимматли қоғозлар | D13: 3555704010
A14: б | B14: Ипотекани қайта молиялаштириш ташкилотлари томонидан чиқарилган қимматли қоғозлар | E14: 65000000
A15: в | B15: Хорижий давлатларининг ҳукуматлари ва марказий банклари томонидан чиқарилган қимматли қоғозлар, шунингдек ушбу мамлакатларнинг марказий банклари ва ҳукуматларига нисбатан бошқа талаблар
A16: г | B16: Ўзбекистон Республикаси ҳудудида чиқарилган бошқа қимматли қоғозлар | J16: 10050000
A17: д | B17: Ўзбекистон Республикаси ҳудудидан ташқарида чиқарилган бошқа қимматли қоғозлар
A18: е | B18: РЕПО битимлари бўйича сотиб олинган қимматли қоғозлар | D18: 451663257
A19: 6. | B19: Миллий валютага деноминация қилинмаган ва миллий валютада молиялаштириш суммасидан ошиб кетган активлар
A20: 7. | B20: Хорижий давлатларнинг давлат секторлари (ҳукуматлар ва марказий банклар бундан мустасно) ва хорижий компаниялар бўйича банк талаблари, шунингдек уларнинг қимматли қоғозлари билан таъминланган ёки кафолатланган активлар (кредитлар ва қимматли қоғозлар бундан мустасно)
A21: 8. | B21: Кредит ва лизинглар, соф
A22: 8.1. | B22: Юридик шахсларга ажратилган кредит ва лизинглар, соф
A23: а | B23: Ўзбекистон Республикаси ҳукумати ва Марказий банкига тўғридан-тўғри берилган кредитлар | D23: 0
A24: б | B24: Халқаро молия институтларига берилган кредитлар, халқаро молия ташкилотларининг қимматли қоғозлари билан таъминланган ёки улар томонидан кафолатланган кредитлар | D24: 0
A25: в | B25: Кредитларнинг депозит билан таъминланган қисми | D25: 0 | E25: 0
A26: г | B26: Жорий бозор қийматида баҳоланган ва ЎзР Ҳукумати, ЎзР Марказий банки томонидан эмиссия қилинган ёки кафолатланган қимматли қоғозлар кўринишидаги гаров билан таъминланган ёки кафолатланган кредитлар, уларнинг қисмлари | D26: 4449758958
A27: д | B27: Дастлабки гаров ҳуқуқи банкка тегишли бўлмаган кредитлар | I27: 111276553
A28: е | B28: Қайта тикланадиган энергия манбалари учун ажратилган кредитлар | D28: 9452501 | I28: 2520753 | J28: 5173636 | K28: 0
A29: ж | B29: 2024 йил 1 апрелдан бошлаб доимий даромадга эга бўлган, шунингдек камида олти ой давомида банк ҳисобварағида, шу жумладан банк картасида маблағлар айланмасига эга бўлган кичик тадбиркорлик субъектларига микромолиялаштириш фаолияти доирасида кўрсатилган хизматлар (оилавий тадбиркорликни ривожлантириш дастурлари доирасида ажратилган кредитлар мустасно) | H29: 0
A30: з | B30: 2024 йил 1 апрелдан бошлаб мазкур жадвалнинг 8.1.ж-қаторида қайд этилган хизматларни кўрсатиш мақсадида микромолия ташкилотларига ажратилган кредитлар | H30: 0
A31: и | B31: Юридик шахсларга ажратилган бошқа барча кредит, лизинг ва кўрсатилган факторинг хизматлари | I31: 6563926526 | J31: 1664398948 | K31: 1012783037
A32: к | B32: Юридик шахсларнинг муаммоли кредит ва лизинглари, соф | K32: 299466702
A33: 8.2. | B33: Жисмоний шахсларга ажратилган кредитлар, соф
A34: а | B34: Дастлабки гаров ҳуқуқи банкка тегишли бўлмаган кредитлар | I34: 0
A35: б | B35: Кредитларнинг (микроқарзларнинг) депозит билан таъминланган қисми | D35: 0 | E35: 0
A36: в | B36: 2024 йил 1 июлга қадар ажратилган ипотека кредитлари | F36: 283860692 | G36: 2271678794 | I36: 2356413851 | J36: 49418158
A37: г | B37: 2024 йил 1 июлдан бошлаб ажратилган ипотека кредитлари | F37: 370689 | G37: 5066855 | I37: 47967689 | J37: 720283523
A38: д | B38: 2023 йил 20 августга қадар автомобиль сотиб олиш учун ажратилган кредитлар | I38: 125995101 | J38: 180528906 | K38: 26755
A39: е | B39: 2023 йил 20 августдан бошлаб 2024 йил 1 июлга қадар жисмоний шахсларга автомобиль сотиб олиш учун ажратилган кредитлар | I39: 6089144 | J39: 68890830 | K39: 53538285
A40: ж | B40: 2024 йил 1 июлдан бошлаб жисмоний шахсларга автомобиль сотиб олиш учун ажратилган кредитлар | I40: 738876 | J40: 12206645 | K40: 1562393
A41: з | B41: 2024 йил 1 июлдан бошлаб 2025 йил 1 январга қадар қарз юки 60 фоиз ва ундан паст ҳолда жисмоний шахсларга ажратилган кредитлар (микроқарзлар) (автокредит, ипотека, оилавий тадбиркорликни ривожлантириш ва таълим дастурлари кредитлари мустасно) | I41: 249681552
A42: и | B42: 2024 йил 1 июлдан бошлаб 2025 йил 1 январга қадар қарз юки 60 фоиздан юқори бўлган ёки қарз юки аниқлаш имкони бўлмаган жисмоний шахсларга берилган кредитлар (микроқарзлар) (автокредит, ипотека, оилавий тадбиркорликни ривожлантириш ва таълим дастурлари кредитлари мустасно) | J42: 1104194319
A43: к | B43: 2025 йил 1 январдан бошлаб қарз юки 50 фоиз ва ундан паст ҳолда жисмоний шахсларга ажратилган кредитлар (микроқарзлар) (автокредит, ипотека, оилавий тадбиркорликни ривожлантириш ва таълим дастурлари кредитлари мустасно) | I43: 0
A44: л | B44: 2025 йил 1 январдан бошлаб қарз юки 50 фоиздан юқори бўлган ёки қарз юки аниқлаш имкони бўлмаган жисмоний шахсларга берилган кредитлар (микроқарзлар) (автокредит, ипотека, оилавий тадбиркорликни ривожлантириш ва таълим дастурлари кредитлари мустасно) | J44: 0
A45: м | B45: Қайта тикланадиган энергия манбалари учун ажратилган кредитлар | D45: 3650489 | I45: 0 | J45: 0 | K45: 0
A46: н | B46: 2024 йил 1 апрелдан бошлаб доимий даромадга эга бўлган, шунингдек камида олти ой давомида банк ҳисобварағида, шу жумладан банк картасида маблағлар айланмасига эга бўлган ўзини ўзи банд қилган шахсларга микромолиялаштириш фаолияти доирасида кўрсатилган хизматлар (оилавий тадбиркорликни ривожлантириш дастурлари доирасида ажратилган кредитлар мустасно) | H46: 0
A47: о | B47: Жисмоний шахсларга ажратилган юқорида кўрсатилмаган бошқа барча кредитлар | I47: 311979510 | J47: 109002843 | K47: 1534999985
A48: п | B48: Жисмоний шахсларнинг муаммоли кредитлари, соф | K48: 203411682
A49: 9. | B49: Банкнинг асосий воситалари ва бошқа хусусий мол-мулклари
A50: а | B50: Банк фаолиятидаги фойдаланиладиган асосий воситалар (амортизацияни чегирган ҳолда) | I50: ='Calculation of Risk Weighted As'!I50 -> 3641694109
A51: б | B51: Банкнинг бошқа хусусий мулклари | I51: ='Calculation of Risk Weighted As'!I51 -> 0
A52: в | B52: Қарздорликни тўлиқ ёки қисман ундириш мақсадида банк балансига қабул қилинган кўчмас мулк | J52: ='Calculation of Risk Weighted As'!J52 -> 661493906 | K52: ='Calculation of Risk Weighted As'!K52 -> 0
A53: г | B53: Икки йилдан ортиқ вақт мобайнида банк фойдаланмаётган банкнинг кўчмас мулки | J53: ='Calculation of Risk Weighted As'!J53 -> 39824 | K53: ='Calculation of Risk Weighted As'!K53 -> 0
A54: 10. | B54: Молиявий бўлган фаолият билан шуғулланувчи хўжалик юритувчи субъектларнинг капиталига қилинган барча инвестициялар, соф | D54: 164772977
A55: 11. | B55: Молиявий бўлмаган фаолият билан шуғулланувчи хўжалик юритувчи субъектларнинг капиталига қилинган барча инвестициялар, соф | D55: 0 | K55: 807010474
A56: 12. | B56: Номоддий активлар, соф | D56: =+'Bank Capital Calc'!C20 -> 21378472 | I56: ='Calculation of Risk Weighted As'!I56 -> 33672144
A57: 13. | B57: Молиявий инструментлар бўйича мижозларнинг мажбуриятлари, соф | D57: 0 | E57: 0 | I57: 0 | K57: 0
A58: 14. | B58: Бошқа муаммоли активлар | K58: 0
A59: 15. | B59: Стандарт деб таснифланган активлар бўйича яратилган захиралар | D59: =+[7]Balance!$D$39 -> 615338207 | L59: =+D59 -> 615338207 | M59: =+[7]Balance!$D$39 -> 615338207 | N59: =+L59-M59 -> 0
A60: 16. | B60: Бошқа активлар, соф | D60: 363458950 | E60: 276125 | F60: 11250860 | G60: 24327050 | H60: 0 | I60: 1887410594 | J60: 104082430 | K60: 158199056
A61: 17. | B61: Баланс активларининг умумий миқдори | D61: =SUM(D8:D58)+D60-D59 -> 9880587570 | E61: =SUM(E8:E58)+E60-E59 -> 259227665 | F61: =SUM(F8:F58)+F60-F59 -> 295482241 | G61: =SUM(G8:G58)+G60-G59 -> 2548298126 | H61: =SUM(H8:H58)+H60-H59 -> 0 | I61: =SUM(I8:I58)+I60-I59 -> 15725103379 | J61: =SUM(J8:J58)+J60-J59 -> 4690039874 | K61: =SUM(K8:K58)+K60-K59 -> 4070998369 | L61: =SUM(D61:K61) -> 37469737224 | M61: =+[7]Balance!$D$47 -> 37469737224 | N61: =+L61-M61 -> 0
A62: 18. | B62: Таваккалчилик гурухларига асосан рискка (таваккалчиликка) тортилган активларининг умумий миқдори | E62: =E61*E3 -> 51845533 | F62: =F61*F3 -> 1.0341878e+08 | G62: =G61*G3 -> 1274149063 | H62: =H61*H3 -> 0 | I62: =I61*I3 -> 15725103379 | J62: =J61*J3 -> 7035059811 | K62: =K61*K3 -> 8141996738
A63: 19. | B63: Баланс активларининг таваккалчиликка тортилган умумий миқдори | K63: =SUM(E62:K62) -> 3.2331573e+10
A66: № | B66: II. БАЛАНСДАН ТАШҚАРИ АКТИВЛАР | C66: Кредитни қайта ҳисоблаш омили | D66: 0 | E66: 0.2 | F66: 0.35 | G66: 0.5 | H66: 0.75 | I66: 1 | J66: 1.5 | K66: 2
A67: 1 | B67: Банкнинг кредит ва лизинг бериш мажбурияти
A68: a | B68: Бир йилдан ортиқ муддатга | C68: 0.5 | I68: 357711710 | K68: 1347118
A69: б | B69: Бир йил ёки ундан кам муддатга | C69: 0.2 | I69: 470497151 | K69: 20084 | L69: =SUM(D68:K69) -> 829576063 | M69: =+[7]Commitments!$D$4 -> 829576063 | N69: =+L69-M69 -> 0
A70: 2 | B70: Қимматли қоғозларни сотиб олиш бўйича муддатли битимлар (шу жумладан, қайта сотиб олиш шартномалари бўйича сотилган активлар) | C70: 1 | D70: 507164188
A71: 3 | B71: Кафолат ва кафилликлар | C71: 1 | I71: 93135689 | L71: =SUM(D71:K71) -> 93135689 | M71: =+[7]Commitments!$D$7 -> 93135689 | N71: =+L71-M71 -> 0
A72: 4 | B72: Aккредитивлар
A73: a | B73: Тўғридан-тўғри кредит ўрнини босувчи воситалар | C73: 1
A74: б | B74: Битимлар билан боғлиқ аккредитивлар | C74: 0.5
A75: в | B75: Савдога тегишли аккредитивлар | C75: 0.2
A76: г | B76: Бошқа аккредитивлар | C76: 1 | L76: =SUM(D73:K76) -> 0 | M76: =+[7]Commitments!$D$10 -> 0 | N76: =+L76-M76 -> 0
A77: 5 | B77: Форвард шартномалар, спот, своплар, опционлар ва шунга ўхшаш мажбуриятлар
A78: a | B78: Фоиз ставкалари бўйича шартномалар
A79: а1 | B79: Бир йил муддатгача | C79: 0.005
A80: а2 | B80: Бир йилдан икки йил муддатгача | C80: 0.01
A81: а3 | B81: Икки йилдан уч йил муддатгача | C81: 0.02
A82: б | B82: Валюта шартномалари ва олтин
A83: б1 | B83: Бир йилгача бўлган муддатда қайтариш | C83: 0.02
A84: б2 | B84: Бир йилдан икки йилгача бўлган муддатда қайтариш | C84: 0.05
A85: б3 | B85: Икки йилдан уч йилгача бўлган муддатда қайтариш | C85: 0.08
A86: 6 | B86: Балансдан ташқари активларнинг умумий миқдори | D86: =SUM(D68:D85) -> 507164188 | E86: =SUM(E68:E85) -> 0 | F86: =SUM(F68:F85) -> 0 | G86: =SUM(G68:G85) -> 0 | H86: =SUM(H68:H85) -> 0 | I86: =SUM(I68:I85) -> 921344550 | J86: =SUM(J68:J85) -> 0 | K86: =SUM(K68:K85) -> 1367202
A87: 7 | B87: Таваккалчилик қиймати | D87: =+(D68*$C$68*$D$3)+(D69*$C$69*$D$3)+(D70*$C$70*$D$3)+(D71*$C$71*$D$3)+(D73*$C$73*$D$3)+(D74*$C$74*$D$3)+(D75*$C$75*$D$3)+(D76*$C$76*$D$3)+(D79*$C$79*$D$3)+(D80*$C$80*$D$3)+(D81*$C$81*$D$3)+(D83*$C$83*$D$3)+(D84*$C$84*$D$3)+(D85*$C$85*$D$3) -> 0 | E87: =+(E68*$C$68*$E$3)+(E69*$C$69*$E$3)+(E70*$C$70*$E$3)+(E71*$C$71*$E$3)+(E73*$C$73*$E$3)+(E74*$C$74*$E$3)+(E75*$C$75*$E$3)+(E76*$C$76*$E$3)+(E79*$C$79*$E$3)+(E80*$C$80*$E$3)+(E81*$C$81*$E$3)+(E83*$C$83*$E$3)+(E84*$C$84*$E$3)+(E85*$C$85*$E$3) -> 0 | F87: =+(F68*$C$68*$F$3)+(F69*$C$69*$F$3)+(F70*$C$70*$F$3)+(F71*$C$71*$F$3)+(F73*$C$73*$F$3)+(F74*$C$74*$F$3)+(F75*$C$75*$F$3)+(F76*$C$76*$F$3)+(F79*$C$79*$F$3)+(F80*$C$80*$F$3)+(F81*$C$81*$F$3)+(F83*$C$83*$F$3)+(F84*$C$84*$F$3)+(F85*$C$85*$F$3) -> 0 | G87: =+(G68*$C$68*$G$3)+(G69*$C$69*$G$3)+(G70*$C$70*$G$3)+(G71*$C$71*$G$3)+(G73*$C$73*$G$3)+(G74*$C$74*$G$3)+(G75*$C$75*$G$3)+(G76*$C$76*$G$3)+(G79*$C$79*$G$3)+(G80*$C$80*$G$3)+(G81*$C$81*$G$3)+(G83*$C$83*$G$3)+(G84*$C$84*$G$3)+(G85*$C$85*$G$3) -> 0 | H87: =+(H68*$C$68*$G$3)+(H69*$C$69*$G$3)+(H70*$C$70*$G$3)+(H71*$C$71*$G$3)+(H73*$C$73*$G$3)+(H74*$C$74*$G$3)+(H75*$C$75*$G$3)+(H76*$C$76*$G$3)+(H79*$C$79*$G$3)+(H80*$C$80*$G$3)+(H81*$C$81*$G$3)+(H83*$C$83*$G$3)+(H84*$C$84*$G$3)+(H85*$C$85*$G$3) -> 0 | I87: =+(I68*$C$68*$I$3)+(I69*$C$69*$I$3)+(I70*$C$70*$I$3)+(I71*$C$71*$I$3)+(I73*$C$73*$I$3)+(I74*$C$74*$I$3)+(I75*$C$75*$I$3)+(I76*$C$76*$I$3)+(I79*$C$79*$I$3)+(I80*$C$80*$I$3)+(I81*$C$81*$I$3)+(I83*$C$83*$I$3)+(I84*$C$84*$I$3)+(I85*$C$85*$I$3) -> 3.6609097e+08 | J87: =+(J68*$C$68*$J$3)+(J69*$C$69*$J$3)+(J70*$C$70*$J$3)+(J71*$C$71*$J$3)+(J73*$C$73*$J$3)+(J74*$C$74*$J$3)+(J75*$C$75*$J$3)+(J76*$C$76*$J$3)+(J79*$C$79*$J$3)+(J80*$C$80*$J$3)+(J81*$C$81*$J$3)+(J83*$C$83*$J$3)+(J84*$C$84*$J$3)+(J85*$C$85*$J$3) -> 0 | K87: =+(K68*$C$68*$K$3)+(K69*$C$69*$K$3)+(K70*$C$70*$K$3)+(K71*$C$71*$K$3)+(K73*$C$73*$K$3)+(K74*$C$74*$K$3)+(K75*$C$75*$K$3)+(K76*$C$76*$K$3)+(K79*$C$79*$K$3)+(K80*$C$80*$K$3)+(K81*$C$81*$K$3)+(K83*$C$83*$K$3)+(K84*$C$84*$K$3)+(K85*$C$85*$K$3) -> 1355151.6
A88: 8 | B88: Жами балансдан ташқари активларнинг таваккалчиликка тортилган қиймати | K88: =SUM(D87:K87) -> 3.6744613e+08
A89: 9 | B89: Жами активларнинг таваккалчиликка тортилган қиймати | K89: =SUM(K88+K63) -> 3.2699019e+10
B91: Бошқарув Раис имзоси:
B93: Бош бухгалтер имзоси:

Sheet Calculation of Risk Weighte ин
A1: ТАВАККАЛЧИЛИКНИ ҲИСОБГА ОЛГАН ҲОЛДАГИ АКТИВЛАР | K1: 6.2-жадвал
B2: =+'Bank Capital Calc'!B3 -> "Ўзсаноатқурилишбанк" АТБ | I2: =+'Bank Capital Calc'!C3 -> 45653 | K2: минг сўмда
A3: № | B3: Кўрсаткичлар | D3: 0 | E3: 0.2 | F3: 0.35 | G3: 0.5 | H3: 0.75 | I3: 1 | J3: 1.5 | K3: 2
D4: Таваккалчилик | E4: Таваккалчилик | F4: Таваккалчилик | G4: Таваккалчилик | H4: Таваккалчилик | I4: Таваккалчилик | J4: Таваккалчилик | K4: Таваккалчилик
D5: I гуруҳ | E5: II гуруҳ | F5: III гуруҳ | G5: IV гуруҳ | H5: V гуруҳ | I5: VI гуруҳ | J5: VII гуруҳ | K5: VIII гуруҳ
B6: (A) | D6: (Б) | E6: (В) | F6: (Г) | G6: (Д) | H6: (Е) | I6: (Ж) | J6: (З) | K6: (И)
B7: I. БАЛАНС АКТИВЛАРИ
A8: 1. | B8: Кассадаги нақд пул ва бошқа тўлов ҳужжатлари ва қимматбаҳо металлар | D8: =+'Calculation of Risk Weighted As'!D8-'Calculation of Risk Weighte нац'!D8 -> 1066210091
A9: 2. | B9: Йўлдаги нақд пуллар ва бошқа тўлов ҳужжатлари | E9: =+'Calculation of Risk Weighted As'!E9-'Calculation of Risk Weighte нац'!E9 -> 99402142
A10: 3. | B10: Банкнинг Марказий банкдаги маблағлар | D10: =+'Calculation of Risk Weighted As'!D10-'Calculation of Risk Weighte нац'!D10 -> 0 | E10: =+'Calculation of Risk Weighted As'!E10-'Calculation of Risk Weighte нац'!E10 -> 12551594
A11: 4. | B11: Бошқа банкларга жойлаштирилган пул маблағлари, жумладан вакиллик ҳисобварақлари, депозитлар ва кредитлар | E11: =+'Calculation of Risk Weighted As'!E11-'Calculation of Risk Weighte нац'!E11 -> 3859174272 | G11: =+'Calculation of Risk Weighted As'!G11-'Calculation of Risk Weighte нац'!G11 -> 1035238216 | I11: =+'Calculation of Risk Weighted As'!I11-'Calculation of Risk Weighte нац'!I11 -> 888281450 | J11: =+'Calculation of Risk Weighted As'!J11-'Calculation of Risk Weighte нац'!J11 -> 38115416
A12: 5. | B12: Қимматли қоғозлар (соф)
A13: а | B13: Ўзбекистон Республикаси Ҳукумати ва Марказий банки томонидан чиқарилган қимматли қоғозлар | D13: =+'Calculation of Risk Weighted As'!D13-'Calculation of Risk Weighte нац'!D13 -> 632340722 | E13: =+'Calculation of Risk Weighted As'!E13-'Calculation of Risk Weighte нац'!E13 -> 0
A14: б | B14: Ипотекани қайта молиялаштириш ташкилотлари томонидан чиқарилган қимматли қоғозлар | D14: =+'Calculation of Risk Weighted As'!D14-'Calculation of Risk Weighte нац'!D14 -> 0 | E14: =+'Calculation of Risk Weighted As'!E14-'Calculation of Risk Weighte нац'!E14 -> 0
A15: в | B15: Хорижий давлатларининг ҳукуматлари ва марказий банклари томонидан чиқарилган қимматли қоғозлар, шунингдек ушбу мамлакатларнинг марказий банклари ва ҳукуматларига нисбатан бошқа талаблар | D15: =+'Calculation of Risk Weighted As'!D15-'Calculation of Risk Weighte нац'!D15 -> 0 | E15: =+'Calculation of Risk Weighted As'!E15-'Calculation of Risk Weighte нац'!E15 -> 0 | G15: =+'Calculation of Risk Weighted As'!G15-'Calculation of Risk Weighte нац'!G15 -> 0 | I15: =+'Calculation of Risk Weighted As'!I15-'Calculation of Risk Weighte нац'!I15 -> 0 | J15: =+'Calculation of Risk Weighted As'!J15-'Calculation of Risk Weighte нац'!J15 -> 0
A16: г | B16: Ўзбекистон Республикаси ҳудудида чиқарилган бошқа қимматли қоғозлар | D16: =+'Calculation of Risk Weighted As'!D16-'Calculation of Risk Weighte нац'!D16 -> 0 | E16: =+'Calculation of Risk Weighted As'!E16-'Calculation of Risk Weighte нац'!E16 -> 0 | G16: =+'Calculation of Risk Weighted As'!G16-'Calculation of Risk Weighte нац'!G16 -> 0 | I16: =+'Calculation of Risk Weighted As'!I16-'Calculation of Risk Weighte нац'!I16 -> 0 | J16: =+'Calculation of Risk Weighted As'!J16-'Calculation of Risk Weighte нац'!J16 -> 0
A17: д | B17: Ўзбекистон Республикаси ҳудудидан ташқарида чиқарилган бошқа қимматли қоғозлар | D17: =+'Calculation of Risk Weighted As'!D17-'Calculation of Risk Weighte нац'!D17 -> 0 | E17: =+'Calculation of Risk Weighted As'!E17-'Calculation of Risk Weighte нац'!E17 -> 0 | G17: =+'Calculation of Risk Weighted As'!G17-'Calculation of Risk Weighte нац'!G17 -> 0 | I17: =+'Calculation of Risk Weighted As'!I17-'Calculation of Risk Weighte нац'!I17 -> 0 | J17: =+'Calculation of Risk Weighted As'!J17-'Calculation of Risk Weighte нац'!J17 -> 0
A18: е | B18: РЕПО битимлари бўйича сотиб олинган қимматли қоғозлар | D18: =+'Calculation of Risk Weighted As'!D18-'Calculation of Risk Weighte нац'!D18 -> 0 | E18: =+'Calculation of Risk Weighted As'!E18-'Calculation of Risk Weighte нац'!E18 -> 0 | G18: =+'Calculation of Risk Weighted As'!G18-'Calculation of Risk Weighte нац'!G18 -> 0 | I18: =+'Calculation of Risk Weighted As'!I18-'Calculation of Risk Weighte нац'!I18 -> 0 | J18: =+'Calculation of Risk Weighted As'!J18-'Calculation of Risk Weighte нац'!J18 -> 0
A19: 6. | B19: Миллий валютага деноминация қилинмаган ва миллий валютада молиялаштириш суммасидан ошиб кетган активлар | I19: =+'Calculation of Risk Weighted As'!I19-'Calculation of Risk Weighte нац'!I19 -> 0
A20: 7. | B20: Хорижий давлатларнинг давлат секторлари (ҳукуматлар ва марказий банклар бундан мустасно) ва хорижий компаниялар бўйича банк талаблари, шунингдек уларнинг қимматли қоғозлари билан таъминланган ёки кафолатланган активлар (кредитлар ва қимматли қоғозлар бундан мустасно) | D20: =+'Calculation of Risk Weighted As'!D20-'Calculation of Risk Weighte нац'!D20 -> 0 | E20: =+'Calculation of Risk Weighted As'!E20-'Calculation of Risk Weighte нац'!E20 -> 0 | G20: =+'Calculation of Risk Weighted As'!G20-'Calculation of Risk Weighte нац'!G20 -> 0 | I20: =+'Calculation of Risk Weighted As'!I20-'Calculation of Risk Weighte нац'!I20 -> 0 | J20: =+'Calculation of Risk Weighted As'!J20-'Calculation of Risk Weighte нац'!J20 -> 0
A21: 8. | B21: Кредит ва лизинглар, соф
A22: 8.1. | B22: Юридик шахсларга ажратилган кредит ва лизинглар, соф
A23: а | B23: Ўзбекистон Республикаси ҳукумати ва Марказий банкига тўғридан-тўғри берилган кредитлар | D23: =+'Calculation of Risk Weighted As'!D23-'Calculation of Risk Weighte нац'!D23 -> 0
A24: б | B24: Халқаро молия институтларига берилган кредитлар, халқаро молия ташкилотларининг қимматли қоғозлари билан таъминланган ёки улар томонидан кафолатланган кредитлар | D24: =+'Calculation of Risk Weighted As'!D24-'Calculation of Risk Weighte нац'!D24 -> 10836545
A25: в | B25: Кредитларнинг депозит билан таъминланган қисми | D25: =+'Calculation of Risk Weighted As'!D25-'Calculation of Risk Weighte нац'!D25 -> 771903 | E25: =+'Calculation of Risk Weighted As'!E25-'Calculation of Risk Weighte нац'!E25 -> 0
A26: г | B26: Жорий бозор қийматида баҳоланган ва ЎзР Ҳукумати, ЎзР Марказий банки томонидан эмиссия қилинган ёки кафолатланган қимматли қоғозлар кўринишидаги гаров билан таъминланган ёки кафолатланган кредитлар, уларнинг қисмлари | D26: =+'Calculation of Risk Weighted As'!D26-'Calculation of Risk Weighte нац'!D26 -> 7904216335
A27: д | B27: Дастлабки гаров ҳуқуқи банкка тегишли бўлмаган кредитлар | I27: =+'Calculation of Risk Weighted As'!I27-'Calculation of Risk Weighte нац'!I27 -> 0
A28: е | B28: Қайта тикланадиган энергия манбалари учун ажратилган кредитлар | D28: =+'Calculation of Risk Weighted As'!D28-'Calculation of Risk Weighte нац'!D28 -> 0 | I28: =+'Calculation of Risk Weighted As'!I28-'Calculation of Risk Weighte нац'!I28 -> 0 | J28: =+'Calculation of Risk Weighted As'!J28-'Calculation of Risk Weighte нац'!J28 -> 0 | K28: =+'Calculation of Risk Weighted As'!K28-'Calculation of Risk Weighte нац'!K28 -> 0
A29: ж | B29: 2024 йил 1 апрелдан бошлаб доимий даромадга эга бўлган, шунингдек камида олти ой давомида банк ҳисобварағида, шу жумладан банк картасида маблағлар айланмасига эга бўлган кичик тадбиркорлик субъектларига микромолиялаштириш фаолияти доирасида кўрсатилган хизматлар (оилавий тадбиркорликни ривожлантириш дастурлари доирасида ажратилган кредитлар мустасно) | H29: =+'Calculation of Risk Weighted As'!H29-'Calculation of Risk Weighte нац'!H29 -> 0
A30: з | B30: 2024 йил 1 апрелдан бошлаб мазкур жадвалнинг 8.1.ж-қаторида қайд этилган хизматларни кўрсатиш мақсадида микромолия ташкилотларига ажратилган кредитлар | H30: =+'Calculation of Risk Weighted As'!H30-'Calculation of Risk Weighte нац'!H30 -> 0
A31: и | B31: Юридик шахсларга ажратилган бошқа барча кредит, лизинг ва кўрсатилган факторинг хизматлари | I31: =+'Calculation of Risk Weighted As'!I31-'Calculation of Risk Weighte нац'!I31 -> 27909762135 | J31: =+'Calculation of Risk Weighted As'!J31-'Calculation of Risk Weighte нац'!J31 -> 2722206760 | K31: =+'Calculation of Risk Weighted As'!K31-'Calculation of Risk Weighte нац'!K31 -> 821686854
A32: к | B32: Юридик шахсларнинг муаммоли кредит ва лизинглари, соф | K32: =+'Calculation of Risk Weighted As'!K32-'Calculation of Risk Weighte нац'!K32 -> 523137955
A33: 8.2. | B33: Жисмоний шахсларга ажратилган кредитлар, соф
A34: а | B34: Дастлабки гаров ҳуқуқи банкка тегишли бўлмаган кредитлар | I34: =+'Calculation of Risk Weighted As'!I34-'Calculation of Risk Weighte нац'!I34 -> 0
A35: б | B35: Кредитларнинг (микроқарзларнинг) депозит билан таъминланган қисми | D35: =+'Calculation of Risk Weighted As'!D35-'Calculation of Risk Weighte нац'!D35 -> 0 | E35: =+'Calculation of Risk Weighted As'!E35-'Calculation of Risk Weighte нац'!E35 -> 0
A36: в | B36: 2024 йил 1 июлга қадар ажратилган ипотека кредитлари | F36: =+'Calculation of Risk Weighted As'!F36-'Calculation of Risk Weighte нац'!F36 -> 0 | G36: =+'Calculation of Risk Weighted As'!G36-'Calculation of Risk Weighte нац'!G36 -> 0 | I36: =+'Calculation of Risk Weighted As'!I36-'Calculation of Risk Weighte нац'!I36 -> 0 | J36: =+'Calculation of Risk Weighted As'!J36-'Calculation of Risk Weighte нац'!J36 -> 0
A37: г | B37: 2024 йил 1 июлдан бошлаб ажратилган ипотека кредитлари | F37: =+'Calculation of Risk Weighted As'!F37-'Calculation of Risk Weighte нац'!F37 -> 0 | G37: =+'Calculation of Risk Weighted As'!G37-'Calculation of Risk Weighte нац'!G37 -> 0 | I37: =+'Calculation of Risk Weighted As'!I37-'Calculation of Risk Weighte нац'!I37 -> 0 | J37: =+'Calculation of Risk Weighted As'!J37-'Calculation of Risk Weighte нац'!J37 -> 0
A38: д | B38: 2023 йил 20 августга қадар автомобиль сотиб олиш учун ажратилган кредитлар | I38: =+'Calculation of Risk Weighted As'!I38-'Calculation of Risk Weighte нац'!I38 -> 0 | J38: =+'Calculation of Risk Weighted As'!J38-'Calculation of Risk Weighte нац'!J38 -> 0 | K38: =+'Calculation of Risk Weighted As'!K38-'Calculation of Risk Weighte нац'!K38 -> 0
A39: е | B39: 2023 йил 20 августдан бошлаб 2024 йил 1 июлга қадар жисмоний шахсларга автомобиль сотиб олиш учун ажратилган кредитлар | I39: =+'Calculation of Risk Weighted As'!I39-'Calculation of Risk Weighte нац'!I39 -> 0 | J39: =+'Calculation of Risk Weighted As'!J39-'Calculation of Risk Weighte нац'!J39 -> 0 | K39: =+'Calculation of Risk Weighted As'!K39-'Calculation of Risk Weighte нац'!K39 -> 0
A40: ж | B40: 2024 йил 1 июлдан бошлаб жисмоний шахсларга автомобиль сотиб олиш учун ажратилган кредитлар | I40: =+'Calculation of Risk Weighted As'!I40-'Calculation of Risk Weighte нац'!I40 -> 0 | J40: =+'Calculation of Risk Weighted As'!J40-'Calculation of Risk Weighte нац'!J40 -> 0 | K40: =+'Calculation of Risk Weighted As'!K40-'Calculation of Risk Weighte нац'!K40 -> 0
A41: з | B41: 2024 йил 1 июлдан бошлаб 2025 йил 1 январга қадар қарз юки 60 фоиз ва ундан паст ҳолда жисмоний шахсларга ажратилган кредитлар (микроқарзлар) (автокредит, ипотека, оилавий тадбиркорликни ривожлантириш ва таълим дастурлари кредитлари мустасно) | I41: =+'Calculation of Risk Weighted As'!I41-'Calculation of Risk Weighte нац'!I41 -> 0
A42: и | B42: 2024 йил 1 июлдан бошлаб 2025 йил 1 январга қадар қарз юки 60 фоиздан юқори бўлган ёки қарз юки аниқлаш имкони бўлмаган жисмоний шахсларга берилган кредитлар (микроқарзлар) (автокредит, ипотека, оилавий тадбиркорликни ривожлантириш ва таълим дастурлари кредитлари мустасно) | J42: =+'Calculation of Risk Weighted As'!J42-'Calculation of Risk Weighte нац'!J42 -> 0
A43: к | B43: 2025 йил 1 январдан бошлаб қарз юки 50 фоиз ва ундан паст ҳолда жисмоний шахсларга ажратилган кредитлар (микроқарзлар) (автокредит, ипотека, оилавий тадбиркорликни ривожлантириш ва таълим дастурлари кредитлари мустасно) | I43: 0
A44: л | B44: 2025 йил 1 январдан бошлаб қарз юки 50 фоиздан юқори бўлган ёки қарз юки аниқлаш имкони бўлмаган жисмоний шахсларга берилган кредитлар (микроқарзлар) (автокредит, ипотека, оилавий тадбиркорликни ривожлантириш ва таълим дастурлари кредитлари мустасно) | J44: 0
A45: м | B45: Қайта тикланадиган энергия манбалари учун ажратилган кредитлар | D45: =+'Calculation of Risk Weighted As'!D45-'Calculation of Risk Weighte нац'!D45 -> 0 | I45: =+'Calculation of Risk Weighted As'!I45-'Calculation of Risk Weighte нац'!I45 -> 0 | J45: =+'Calculation of Risk Weighted As'!J45-'Calculation of Risk Weighte нац'!J45 -> 0 | K45: =+'Calculation of Risk Weighted As'!K45-'Calculation of Risk Weighte нац'!K45 -> 0
A46: н | B46: 2024 йил 1 апрелдан бошлаб доимий даромадга эга бўлган, шунингдек камида олти ой давомида банк ҳисобварағида, шу жумладан банк картасида маблағлар айланмасига эга бўлган ўзини ўзи банд қилган шахсларга микромолиялаштириш фаолияти доирасида кўрсатилган хизматлар (оилавий тадбиркорликни ривожлантириш дастурлари доирасида ажратилган кредитлар мустасно) | H46: =+'Calculation of Risk Weighted As'!H46-'Calculation of Risk Weighte нац'!H46 -> 0
A47: о | B47: Жисмоний шахсларга ажратилган юқорида кўрсатилмаган бошқа барча кредитлар | I47: =+'Calculation of Risk Weighted As'!I47-'Calculation of Risk Weighte нац'!I47 -> 0 | J47: =+'Calculation of Risk Weighted As'!J47-'Calculation of Risk Weighte нац'!J47 -> 0 | K47: =+'Calculation of Risk Weighted As'!K47-'Calculation of Risk Weighte нац'!K47 -> 0
A48: п | B48: Жисмоний шахсларнинг муаммоли кредитлари, соф | K48: =+'Calculation of Risk Weighted As'!K48-'Calculation of Risk Weighte нац'!K48 -> 0
A49: 9. | B49: Банкнинг асосий воситалари ва бошқа хусусий мол-мулклари
A50: а | B50: Банк фаолиятидаги фойдаланиладиган асосий воситалар (амортизацияни чегирган ҳолда) | I50: =+'Calculation of Risk Weighted As'!I50-'Calculation of Risk Weighte нац'!I50 -> 0
A51: б | B51: Банкнинг бошқа хусусий мулклари | I51: =+'Calculation of Risk Weighted As'!I51-'Calculation of Risk Weighte нац'!I51 -> 0
A52: в | B52: Қарздорликни тўлиқ ёки қисман ундириш мақсадида банк балансига қабул қилинган кўчмас мулк | J52: =+'Calculation of Risk Weighted As'!J52-'Calculation of Risk Weighte нац'!J52 -> 0 | K52: =+'Calculation of Risk Weighted As'!K52-'Calculation of Risk Weighte нац'!K52 -> 0
A53: г | B53: Икки йилдан ортиқ вақт мобайнида банк фойдаланмаётган банкнинг кўчмас мулки | J53: =+'Calculation of Risk Weighted As'!J53-'Calculation of Risk Weighte нац'!J53 -> 0 | K53: =+'Calculation of Risk Weighted As'!K53-'Calculation of Risk Weighte нац'!K53 -> 0
A54: 10. | B54: Молиявий бўлган фаолият билан шуғулланувчи хўжалик юритувчи субъектларнинг капиталига қилинган барча инвестициялар, соф | D54: =+'Calculation of Risk Weighted As'!D54-'Calculation of Risk Weighte нац'!D54 -> 3313793
A55: 11. | B55: Молиявий бўлмаган фаолият билан шуғулланувчи хўжалик юритувчи субъектларнинг капиталига қилинган барча инвестициялар, соф | D55: =+'Calculation of Risk Weighted As'!D55-'Calculation of Risk Weighte нац'!D55 -> 0 | K55: =+'Calculation of Risk Weighted As'!K55-'Calculation of Risk Weighte нац'!K55 -> 0
A56: 12. | B56: Номоддий активлар, соф | D56: =+'Calculation of Risk Weighted As'!D56-'Calculation of Risk Weighte нац'!D56 -> 0 | I56: =+'Calculation of Risk Weighted As'!I56-'Calculation of Risk Weighte нац'!I56 -> 0
A57: 13. | B57: Молиявий инструментлар бўйича мижозларнинг мажбуриятлари, соф | D57: =+'Calculation of Risk Weighted As'!D57-'Calculation of Risk Weighte нац'!D57 -> 0 | E57: =+'Calculation of Risk Weighted As'!E57-'Calculation of Risk Weighte нац'!E57 -> 0 | I57: =+'Calculation of Risk Weighted As'!I57-'Calculation of Risk Weighte нац'!I57 -> 0 | K57: =+'Calculation of Risk Weighted As'!K57-'Calculation of Risk Weighte нац'!K57 -> 109734946
A58: 14. | B58: Бошқа муаммоли активлар | K58: =+'Calculation of Risk Weighted As'!K58-'Calculation of Risk Weighte нац'!K58 -> 0
A59: 15. | B59: Стандарт деб таснифланган активлар бўйича яратилган захиралар | D59: =+'Calculation of Risk Weighted As'!D59-'Calculation of Risk Weighte нац'!D59 -> 0
A60: 16. | B60: Бошқа активлар, соф | D60: =+'Calculation of Risk Weighted As'!D60-'Calculation of Risk Weighte нац'!D60 -> 95248892 | E60: =+'Calculation of Risk Weighted As'!E60-'Calculation of Risk Weighte нац'!E60 -> 82823827 | F60: =+'Calculation of Risk Weighted As'!F60-'Calculation of Risk Weighte нац'!F60 -> 0 | G60: =+'Calculation of Risk Weighted As'!G60-'Calculation of Risk Weighte нац'!G60 -> 0 | H60: =+'Calculation of Risk Weighted As'!H60-'Calculation of Risk Weighte нац'!H60 -> 0 | I60: =+'Calculation of Risk Weighted As'!I60-'Calculation of Risk Weighte нац'!I60 -> 1787740326 | J60: =+'Calculation of Risk Weighted As'!J60-'Calculation of Risk Weighte нац'!J60 -> 330917422 | K60: =+'Calculation of Risk Weighted As'!K60-'Calculation of Risk Weighte нац'!K60 -> 193541019
A61: 17. | B61: Баланс активларининг умумий миқдори | D61: =SUM(D8:D58)+D60-D59 -> 9712938281 | E61: =SUM(E8:E58)+E60-E59 -> 4053951835 | F61: =SUM(F8:F58)+F60-F59 -> 0 | G61: =SUM(G8:G58)+G60-G59 -> 1035238216 | H61: =SUM(H8:H58)+H60-H59 -> 0 | I61: =SUM(I8:I58)+I60-I59 -> 30585783911 | J61: =SUM(J8:J58)+J60-J59 -> 3091239598 | K61: =SUM(K8:K58)+K60-K59 -> 1648100774 | L61: =SUM(D61:K61) -> 50127252615 | M61: =+[7]Balance!$E$47 -> 50127252615 | N61: =+L61-M61 -> 0
A62: 18. | B62: Таваккалчилик гурухларига асосан рискка (таваккалчиликка) тортилган активларининг умумий миқдори | E62: =E61*E3 -> 810790367 | F62: =F61*F3 -> 0 | G62: =G61*G3 -> 517619108 | H62: =H61*H3 -> 0 | I62: =I61*I3 -> 30585783911 | J62: =J61*J3 -> 4636859397 | K62: =K61*K3 -> 3296201548
A63: 19. | B63: Баланс активларининг таваккалчиликка тортилган умумий миқдори | K63: =SUM(E62:K62) -> 39847254331
A66: № | B66: II. БАЛАНСДАН ТАШҚАРИ АКТИВЛАР | C66: Кредитни қайта ҳисоблаш омили | D66: 0 | E66: 0.2 | F66: 0.35 | G66: 0.5 | H66: 0.75 | I66: 1 | J66: 1.5 | K66: 2
A67: 1 | B67: Банкнинг кредит ва лизинг бериш мажбурияти
A68: a | B68: Бир йилдан ортиқ муддатга | C68: 0.5 | D68: =+'Calculation of Risk Weighted As'!D68-'Calculation of Risk Weighte нац'!D68 -> 0 | E68: =+'Calculation of Risk Weighted As'!E68-'Calculation of Risk Weighte нац'!E68 -> 0 | F68: =+'Calculation of Risk Weighted As'!F68-'Calculation of Risk Weighte нац'!F68 -> 0 | G68: =+'Calculation of Risk Weighted As'!G68-'Calculation of Risk Weighte нац'!G68 -> 0 | H68: =+'Calculation of Risk Weighted As'!H68-'Calculation of Risk Weighte нац'!H68 -> 0 | I68: =+'Calculation of Risk Weighted As'!I68-'Calculation of Risk Weighte нац'!I68 -> 853846881 | J68: =+'Calculation of Risk Weighted As'!J68-'Calculation of Risk Weighte нац'!J68 -> 0 | K68: =+'Calculation of Risk Weighted As'!K68-'Calculation of Risk Weighte нац'!K68 -> 0
A69: б | B69: Бир йил ёки ундан кам муддатга | C69: 0.2 | D69: =+'Calculation of Risk Weighted As'!D69-'Calculation of Risk Weighte нац'!D69 -> 0 | E69: =+'Calculation of Risk Weighted As'!E69-'Calculation of Risk Weighte нац'!E69 -> 0 | F69: =+'Calculation of Risk Weighted As'!F69-'Calculation of Risk Weighte нац'!F69 -> 0 | G69: =+'Calculation of Risk Weighted As'!G69-'Calculation of Risk Weighte нац'!G69 -> 0 | H69: =+'Calculation of Risk Weighted As'!H69-'Calculation of Risk Weighte нац'!H69 -> 0 | I69: =+'Calculation of Risk Weighted As'!I69-'Calculation of Risk Weighte нац'!I69 -> 532231484 | J69: =+'Calculation of Risk Weighted As'!J69-'Calculation of Risk Weighte нац'!J69 -> 0 | K69: =+'Calculation of Risk Weighted As'!K69-'Calculation of Risk Weighte нац'!K69 -> 0 | L69: =SUM(D68:K69) -> 1386078365 | M69: =+[7]Commitments!$E$4 -> 1386078365 | N69: =+L69-M69 -> 0
A70: 2 | B70: Қимматли қоғозларни сотиб олиш бўйича муддатли битимлар (шу жумладан, қайта сотиб олиш шартномалари бўйича сотилган активлар) | C70: 1 | D70: =+'Calculation of Risk Weighted As'!D70-'Calculation of Risk Weighte нац'!D70 -> 0 | E70: =+'Calculation of Risk Weighted As'!E70-'Calculation of Risk Weighte нац'!E70 -> 0 | G70: =+'Calculation of Risk Weighted As'!G70-'Calculation of Risk Weighte нац'!G70 -> 0 | I70: =+'Calculation of Risk Weighted As'!I70-'Calculation of Risk Weighte нац'!I70 -> 0
A71: 3 | B71: Кафолат ва кафилликлар | C71: 1 | D71: =+'Calculation of Risk Weighted As'!D71-'Calculation of Risk Weighte нац'!D71 -> 206992592 | E71: =+'Calculation of Risk Weighted As'!E71-'Calculation of Risk Weighte нац'!E71 -> 0 | G71: =+'Calculation of Risk Weighted As'!G71-'Calculation of Risk Weighte нац'!G71 -> 0 | I71: =+'Calculation of Risk Weighted As'!I71-'Calculation of Risk Weighte нац'!I71 -> 1806879802 | J71: =+'Calculation of Risk Weighted As'!J71-'Calculation of Risk Weighte нац'!J71 -> 0 | K71: =+'Calculation of Risk Weighted As'!K71-'Calculation of Risk Weighte нац'!K71 -> 44981244 | L71: =SUM(D71:K71) -> 2058853638 | M71: =+[7]Commitments!$E$7 -> 2058853638 | N71: =+L71-M71 -> 0
A72: 4 | B72: Aккредитивлар
A73: a | B73: Тўғридан-тўғри кредит ўрнини босувчи воситалар | C73: 1 | D73: =+'Calculation of Risk Weighted As'!D73-'Calculation of Risk Weighte нац'!D73 -> 0 | E73: =+'Calculation of Risk Weighted As'!E73-'Calculation of Risk Weighte нац'!E73 -> 0 | G73: =+'Calculation of Risk Weighted As'!G73-'Calculation of Risk Weighte нац'!G73 -> 0 | I73: =+'Calculation of Risk Weighted As'!I73-'Calculation of Risk Weighte нац'!I73 -> 0 | K73: =+'Calculation of Risk Weighted As'!K73-'Calculation of Risk Weighte нац'!K73 -> 0
A74: б | B74: Битимлар билан боғлиқ аккредитивлар | C74: 0.5 | D74: =+'Calculation of Risk Weighted As'!D74-'Calculation of Risk Weighte нац'!D74 -> 0 | E74: =+'Calculation of Risk Weighted As'!E74-'Calculation of Risk Weighte нац'!E74 -> 0 | G74: =+'Calculation of Risk Weighted As'!G74-'Calculation of Risk Weighte нац'!G74 -> 0 | I74: =+'Calculation of Risk Weighted As'!I74-'Calculation of Risk Weighte нац'!I74 -> 0 | K74: =+'Calculation of Risk Weighted As'!K74-'Calculation of Risk Weighte нац'!K74 -> 0
A75: в | B75: Савдога тегишли аккредитивлар | C75: 0.2 | D75: =+'Calculation of Risk Weighted As'!D75-'Calculation of Risk Weighte нац'!D75 -> 1387680332 | E75: =+'Calculation of Risk Weighted As'!E75-'Calculation of Risk Weighte нац'!E75 -> 0 | G75: =+'Calculation of Risk Weighted As'!G75-'Calculation of Risk Weighte нац'!G75 -> 0 | I75: =+'Calculation of Risk Weighted As'!I75-'Calculation of Risk Weighte нац'!I75 -> 693465915 | K75: =+'Calculation of Risk Weighted As'!K75-'Calculation of Risk Weighte нац'!K75 -> 0
A76: г | B76: Бошқа аккредитивлар | C76: 1 | D76: =+'Calculation of Risk Weighted As'!D76-'Calculation of Risk Weighte нац'!D76 -> 0 | E76: =+'Calculation of Risk Weighted As'!E76-'Calculation of Risk Weighte нац'!E76 -> 0 | G76: =+'Calculation of Risk Weighted As'!G76-'Calculation of Risk Weighte нац'!G76 -> 0 | I76: =+'Calculation of Risk Weighted As'!I76-'Calculation of Risk Weighte нац'!I76 -> 0 | K76: =+'Calculation of Risk Weighted As'!K76-'Calculation of Risk Weighte нац'!K76 -> 0 | L76: =SUM(D73:K76) -> 2081146247 | M76: =+[7]Commitments!$E$10 -> 2081146247 | N76: =+L76-M76 -> 0
A77: 5 | B77: Форвард шартномалар, спот, своплар, опционлар ва шунга ўхшаш мажбуриятлар
A78: a | B78: Фоиз ставкалари бўйича шартномалар
A79: а1 | B79: Бир йил муддатгача | C79: 0.005 | D79: =+'Calculation of Risk Weighted As'!D79-'Calculation of Risk Weighte нац'!D79 -> 0 | E79: =+'Calculation of Risk Weighted As'!E79-'Calculation of Risk Weighte нац'!E79 -> 0 | G79: =+'Calculation of Risk Weighted As'!G79-'Calculation of Risk Weighte нац'!G79 -> 0 | I79: =+'Calculation of Risk Weighted As'!I79-'Calculation of Risk Weighte нац'!I79 -> 0
A80: а2 | B80: Бир йилдан икки йил муддатгача | C80: 0.01 | D80: =+'Calculation of Risk Weighted As'!D80-'Calculation of Risk Weighte нац'!D80 -> 0 | E80: =+'Calculation of Risk Weighted As'!E80-'Calculation of Risk Weighte нац'!E80 -> 0 | G80: =+'Calculation of Risk Weighted As'!G80-'Calculation of Risk Weighte нац'!G80 -> 0 | I80: =+'Calculation of Risk Weighted As'!I80-'Calculation of Risk Weighte нац'!I80 -> 0
A81: а3 | B81: Икки йилдан уч йил муддатгача | C81: 0.02 | D81: =+'Calculation of Risk Weighted As'!D81-'Calculation of Risk Weighte нац'!D81 -> 0 | E81: =+'Calculation of Risk Weighted As'!E81-'Calculation of Risk Weighte нац'!E81 -> 0 | G81: =+'Calculation of Risk Weighted As'!G81-'Calculation of Risk Weighte нац'!G81 -> 0 | I81: =+'Calculation of Risk Weighted As'!I81-'Calculation of Risk Weighte нац'!I81 -> 0
A82: б | B82: Валюта шартномалари ва олтин
A83: б1 | B83: Бир йилгача бўлган муддатда қайтариш | C83: 0.02 | D83: =+'Calculation of Risk Weighted As'!D83-'Calculation of Risk Weighte нац'!D83 -> 329472240 | E83: =+'Calculation of Risk Weighted As'!E83-'Calculation of Risk Weighte нац'!E83 -> 0 | G83: =+'Calculation of Risk Weighted As'!G83-'Calculation of Risk Weighte нац'!G83 -> 0 | I83: =+'Calculation of Risk Weighted As'!I83-'Calculation of Risk Weighte нац'!I83 -> 0
A84: б2 | B84: Бир йилдан икки йилгача бўлган муддатда қайтариш | C84: 0.05 | D84: =+'Calculation of Risk Weighted As'!D84-'Calculation of Risk Weighte нац'!D84 -> 0 | E84: =+'Calculation of Risk Weighted As'!E84-'Calculation of Risk Weighte нац'!E84 -> 0 | G84: =+'Calculation of Risk Weighted As'!G84-'Calculation of Risk Weighte нац'!G84 -> 0 | I84: =+'Calculation of Risk Weighted As'!I84-'Calculation of Risk Weighte нац'!I84 -> 0
A85: б3 | B85: Икки йилдан уч йилгача бўлган муддатда қайтариш | C85: 0.08 | D85: =+'Calculation of Risk Weighted As'!D85-'Calculation of Risk Weighte нац'!D85 -> 0 | E85: =+'Calculation of Risk Weighted As'!E85-'Calculation of Risk Weighte нац'!E85 -> 0 | G85: =+'Calculation of Risk Weighted As'!G85-'Calculation of Risk Weighte нац'!G85 -> 0 | I85: =+'Calculation of Risk Weighted As'!I85-'Calculation of Risk Weighte нац'!I85 -> 0
A86: 6 | B86: Балансдан ташқари активларнинг умумий миқдори | D86: =SUM(D68:D85) -> 1924145164 | E86: =SUM(E68:E85) -> 0 | F86: =SUM(F68:F85) -> 0 | G86: =SUM(G68:G85) -> 0 | H86: =SUM(H68:H85) -> 0 | I86: =SUM(I68:I85) -> 3886424082 | J86: =SUM(J68:J85) -> 0 | K86: =SUM(K68:K85) -> 44981244
A87: 7 | B87: Таваккалчилик қиймати | D87: =+(D68*$C$68*$D$3)+(D69*$C$69*$D$3)+(D70*$C$70*$D$3)+(D71*$C$71*$D$3)+(D73*$C$73*$D$3)+(D74*$C$74*$D$3)+(D75*$C$75*$D$3)+(D76*$C$76*$D$3)+(D79*$C$79*$D$3)+(D80*$C$80*$D$3)+(D81*$C$81*$D$3)+(D83*$C$83*$D$3)+(D84*$C$84*$D$3)+(D85*$C$85*$D$3) -> 0 | E87: =+(E68*$C$68*$E$3)+(E69*$C$69*$E$3)+(E70*$C$70*$E$3)+(E71*$C$71*$E$3)+(E73*$C$73*$E$3)+(E74*$C$74*$E$3)+(E75*$C$75*$E$3)+(E76*$C$76*$E$3)+(E79*$C$79*$E$3)+(E80*$C$80*$E$3)+(E81*$C$81*$E$3)+(E83*$C$83*$E$3)+(E84*$C$84*$E$3)+(E85*$C$85*$E$3) -> 0 | F87: =+(F68*$C$68*$F$3)+(F69*$C$69*$F$3)+(F70*$C$70*$F$3)+(F71*$C$71*$F$3)+(F73*$C$73*$F$3)+(F74*$C$74*$F$3)+(F75*$C$75*$F$3)+(F76*$C$76*$F$3)+(F79*$C$79*$F$3)+(F80*$C$80*$F$3)+(F81*$C$81*$F$3)+(F83*$C$83*$F$3)+(F84*$C$84*$F$3)+(F85*$C$85*$F$3) -> 0 | G87: =+(G68*$C$68*$G$3)+(G69*$C$69*$G$3)+(G70*$C$70*$G$3)+(G71*$C$71*$G$3)+(G73*$C$73*$G$3)+(G74*$C$74*$G$3)+(G75*$C$75*$G$3)+(G76*$C$76*$G$3)+(G79*$C$79*$G$3)+(G80*$C$80*$G$3)+(G81*$C$81*$G$3)+(G83*$C$83*$G$3)+(G84*$C$84*$G$3)+(G85*$C$85*$G$3) -> 0 | H87: =+(H68*$C$68*$G$3)+(H69*$C$69*$G$3)+(H70*$C$70*$G$3)+(H71*$C$71*$G$3)+(H73*$C$73*$G$3)+(H74*$C$74*$G$3)+(H75*$C$75*$G$3)+(H76*$C$76*$G$3)+(H79*$C$79*$G$3)+(H80*$C$80*$G$3)+(H81*$C$81*$G$3)+(H83*$C$83*$G$3)+(H84*$C$84*$G$3)+(H85*$C$85*$G$3) -> 0 | I87: =+(I68*$C$68*$I$3)+(I69*$C$69*$I$3)+(I70*$C$70*$I$3)+(I71*$C$71*$I$3)+(I73*$C$73*$I$3)+(I74*$C$74*$I$3)+(I75*$C$75*$I$3)+(I76*$C$76*$I$3)+(I79*$C$79*$I$3)+(I80*$C$80*$I$3)+(I81*$C$81*$I$3)+(I83*$C$83*$I$3)+(I84*$C$84*$I$3)+(I85*$C$85*$I$3) -> 2.4789427e+09 | J87: =+(J68*$C$68*$J$3)+(J69*$C$69*$J$3)+(J70*$C$70*$J$3)+(J71*$C$71*$J$3)+(J73*$C$73*$J$3)+(J74*$C$74*$J$3)+(J75*$C$75*$J$3)+(J76*$C$76*$J$3)+(J79*$C$79*$J$3)+(J80*$C$80*$J$3)+(J81*$C$81*$J$3)+(J83*$C$83*$J$3)+(J84*$C$84*$J$3)+(J85*$C$85*$J$3) -> 0 | K87: =+(K68*$C$68*$K$3)+(K69*$C$69*$K$3)+(K70*$C$70*$K$3)+(K71*$C$71*$K$3)+(K73*$C$73*$K$3)+(K74*$C$74*$K$3)+(K75*$C$75*$K$3)+(K76*$C$76*$K$3)+(K79*$C$79*$K$3)+(K80*$C$80*$K$3)+(K81*$C$81*$K$3)+(K83*$C$83*$K$3)+(K84*$C$84*$K$3)+(K85*$C$85*$K$3) -> 89962488
A88: 8 | B88: Жами балансдан ташқари активларнинг таваккалчиликка тортилган қиймати | K88: =SUM(D87:K87) -> 2.5689052e+09
A89: 9 | B89: Жами активларнинг таваккалчиликка тортилган қиймати | K89: =SUM(K88+K63) -> 4.241616e+10
B91: Бошқарув Раис имзоси:
B93: Бош бухгалтер имзоси:

Sheet Calculation of Risk
A1: ОПЕРАЦИОН ВА БОЗОР ТАВАККАЛЧИЛИКЛАРИ ҲИСОБ-КИТОБИ | C1: 6а-жадвал
B2: =IF(C3>0," "&TEXT(C3,"гггг"),"Число,Месяц,Год") -> 2024
B3: =+'Bank Capital Calc'!B3 -> "Ўзсаноатқурилишбанк" АТБ | C3: =+'Bank Capital Calc'!C3 -> 45653
A4: № | B4: Кўрсаткичлар номи | C4: минг сўмда
A5: 1. | B5: =+""&(D$6-3)&" йилдаги банкнинг ялпи даромади" -> 2021 йилдаги банкнинг ялпи даромади | C5: =+C6+C8-C7-C9 -> 3.798188e+09
A6: а. | B6: фоизли даромад | C6: 4.4842051e+09 | D6: =+B2 -> 2024 | E6: 13
A7: б. | B7: фоизли харажат | C7: 2.4173253e+09
A8: в. | B8: фоизсиз даромад | C8: 2.1643236e+09
A9: г. | B9: фоизсиз харажат | C9: 4.3301541e+08
A10: 2. | B10: =+""&(D$6-2)&" йилдаги банкнинг ялпи даромади" -> 2022 йилдаги банкнинг ялпи даромади | C10: =+C11+C13-C12-C14 -> 4529526362
A11: а. | B11: фоизли даромад | C11: 5385229821
A12: б. | B12: фоизли харажат | C12: 2789987110
A13: в. | B13: фоизсиз даромад | C13: 2895770101
A14: г. | B14: фоизсиз харажат | C14: 961486450
A15: 3. | B15: =+""&(D$6-1)&" йилдаги банкнинг ялпи даромади" -> 2023 йилдаги банкнинг ялпи даромади | C15: =+C16+C18-C17-C19 -> 4969541068
A16: а. | B16: фоизли даромад | C16: 7179862148
A17: б. | B17: фоизли харажат | C17: 4197900134
A18: в. | B18: фоизсиз даромад | C18: 3891738908
A19: г. | B19: фоизсиз харажат | C19: 1904159854
A20: 4. | B20: Банкнинг ўртача ялпи даромади (оҳирги уч йил давомида) | C20: =(C5+C10+C15)/3 -> 4.4324185e+09
A21: 5. | B21: Операцион таваккалчиликлар қиймати | C21: =+(100/C28)*C20*15% -> 5.114329e+09
A23: 6. | B23: Валюта позицияси ҳисобварақлари | C23: -1053244637 | E23: сўм қисми
A24: 7. | B24: Кўзда тутилмаган ҳолатлар бўйича талаблар | C24: 329472240 | D24: 92503, 92705, 92716, 92717, 92728, 92732 | E24: чет эл валютасидаги қолдиқларининг эквиваленти
A25: 8. | B25: Кўзда тутилмаган ҳолатлар бўйича мажбуриятлар | C25: 0 | D25: 92501, 92701, 92709, 92710, 92724, 92736 | E25: чет эл валютасидаги қолдиқларининг эквиваленти
A26: 9. | B26: Очиқ валюта позицияси, жами | C26: =ABS(C23+(C24-C25)) -> 723772397 | D26: =+C26*0.1 -> 72377240
A27: 10. | B27: Бозор таваккалчилиги суммаси | C27: =+(100/C28)*(C26*10%) -> 5.56748e+08
A28: 11. | B28: Капитал монандлигига бўлган амалдаги минимал талаб | C28: =VLOOKUP($D$6,$D$6:$E$6,2,0) -> 13
B30: Бошқарув Раис имзоси:
B32: Бош бухгалтер имзоси:
