Workbook
Name jop: #REF!
Name kol: #REF!
Name OLE_LINK19: Balance!$D$33
Name RISKTOTASS: SUM('[1]Calculation of Risk Weighted As'!$C$38:$F$38)
Name TwentyLargestData: #REF!
Name Е: #REF!

Sheet Balance
A1: СТРУКТУРА БАЛАНСА БАНКА | E1: Таблица-1 | F1: 1133
B2: =IF(C3>0," "&TEXT(C3,"д ММММ, гггг"),"Число,Месяц,Год") -> 30 Декабрь, 2019
B3: АКБ "Микрокредитбанк" | C3: 43829 | E3: тыс. сум
A4: № | B4: АКТИВЫ | C4: Итого | D4: в национальной валюте | E4: в иностранной валюте (в экв. в сумах)
A5: 1 | B5: Кассовая наличность и другие платежные документы | C5: =+D5+E5 -> 173211577 | D5: =+'Bank Assets Analysis'!T7 -> 69805132 | E5: =+'Bank Assets Analysis'!U7 -> 103406445 | L5: =+C5-D5-E5 -> 0
A6: 2 | B6: К получению из ЦБРУ | C6: =+D6+E6 -> 140577780 | D6: =+'Bank Assets Analysis'!T8+'Bank Assets Analysis'!T9 -> 119493320 | E6: =+'Bank Assets Analysis'!U8+'Bank Assets Analysis'!U9 -> 21084460 | L6: =+C6-D6-E6 -> 0
A7: 3 | B7: К получению из других банков, чистые | C7: =+'Bank Assets Analysis'!S10 -> 453538332 | D7: =+'Bank Assets Analysis'!T10 -> 266889175 | E7: =+'Bank Assets Analysis'!U10 -> 186649157 | L7: =+C7-D7-E7 -> 0
A8: 3.1. | B8: К получению из других банков, брутто | C8: =+D8+E8 -> 453538332 | D8: 266889175 | E8: 186649157 | L8: =+C8-D8-E8 -> 0
A9: 3.2. | B9: Минус: Резерв возможных убытков | C9: =+D9+E9 -> 0 | L9: =+C9-D9-E9 -> 0
A10: 4 | B10: Счета купли и продажи, чистые | C10: =+C11-C12 -> 119576827 | D10: =+'Investment Securities'!C28 -> 119576827 | E10: =+'Investment Securities'!D28 -> 0 | L10: =+C10-D10-E10 -> 0
A11: 4.1. | B11: Ценные бумаги для купли продажи, брутто | C11: =+D11+E11 -> 119576827 | D11: =+'Investment Securities'!C26 -> 119576827 | E11: =+'Investment Securities'!D26 -> 0 | L11: =+C11-D11-E11 -> 0
A12: 4.2. | B12: Минус: Резерв возможных убытков | C12: =+D12+E12 -> 0 | D12: =+'Investment Securities'!C27 -> 0 | E12: =+'Investment Securities'!D27 -> 0 | L12: =+C12-D12-E12 -> 0
A13: 5 | B13: Драгоценные металлы, монеты, камни, чистые | C13: =+C14-C15 -> 175 | D13: =+'Investment Securities'!C39 -> 175 | E13: =+'Investment Securities'!D39 -> 0 | L13: =+C13-D13-E13 -> 0
A14: 5.1. | B14: Драгоценные металлы, монеты, камни, брутто | C14: =+D14+E14 -> 175 | D14: =+'Investment Securities'!C37 -> 175 | E14: =+'Investment Securities'!D37 -> 0 | L14: =+C14-D14-E14 -> 0
A15: 5.2. | B15: Минус: Резерв возможных убытков | C15: =+D15+E15 -> 0 | D15: =+'Investment Securities'!C38 -> 0 | E15: =+'Investment Securities'!D38 -> 0 | L15: =+C15-D15-E15 -> 0
A16: 6 | B16: Инвестиции, чистые | C16: =+'Investment Securities'!B15 -> 6670220 | D16: =+'Investment Securities'!C15 -> 6670220 | E16: =+'Investment Securities'!D15 -> 0 | L16: =+C16-D16-E16 -> 0
A17: 6.1. | B17: Инвестиции, брутто | C17: =+D17+E17 -> 6941924 | D17: =+'Investment Securities'!C13 -> 6941924 | E17: =+'Investment Securities'!D13 -> 0 | L17: =+C17-D17-E17 -> 0
A18: 6.2. | B18: Минус: Резерв возможных убытков | C18: =+D18+E18 -> 271704 | D18: =+'Investment Securities'!C14 -> 271704 | E18: =+'Investment Securities'!D14 -> 0 | L18: =+C18-D18-E18 -> 0
A19: 7 | B19: Ценные бумаги купленные по соглашению c обратным выкупом, чистые | C19: =+'Bank Assets Analysis'!S28 -> 0 | D19: =+'Bank Assets Analysis'!T28 -> 0 | E19: =+'Bank Assets Analysis'!U28 -> 0 | L19: =+C19-D19-E19 -> 0
A20: 7.1. | B20: Ценные бумаги, купленные по соглашению с обратным выкупом, брутто | C20: =+D20+E20 -> 0 | D20: 0 | E20: 0 | L20: =+C20-D20-E20 -> 0
A21: 7.2. | B21: Резерв возможных убытков | C21: =+D21+E21 -> 0 | D21: 0 | E21: 0 | L21: =+C21-D21-E21 -> 0
A22: 8 | B22: Кредиты и лизинговые операции, чистые | C22: =+'Bank Assets Analysis'!S24+'Bank Assets Analysis'!S25+'Bank Assets Analysis'!S26 -> 4652448980 | D22: =+'Bank Assets Analysis'!T24+'Bank Assets Analysis'!T25+'Bank Assets Analysis'!T26 -> 3092790433 | E22: =+'Bank Assets Analysis'!U24+'Bank Assets Analysis'!U25+'Bank Assets Analysis'!U26 -> 1559658547 | L22: =+C22-D22-E22 -> 0
A23: 8.1. | B23: Кредиты и лизинговые операции, брутто | C23: =+D23+E23 -> 4772374677 | D23: 3194072351 | E23: 1578302326 | L23: =+C23-D23-E23 -> 0
A24: 8.2. | B24: Минус: Резерв возможных убытков | C24: =+'Charge-offs and Recoveries'!C25 -> 119925697 | D24: 101281918 | E24: 18643779 | F24: =+'Asset Classification'!Y50 -> 119925697 | L24: =+C24-D24-E24 -> 0
A25: 9 | B25: Купленные векселя, чистые | C25: =+'Bank Assets Analysis'!S20 -> 0 | D25: =+'Bank Assets Analysis'!T20 -> 0 | E25: =+'Bank Assets Analysis'!U20 -> 0 | L25: =+C25-D25-E25 -> 0
A26: 9.1. | B26: Купленные векселя, брутто | C26: =+D26+E26 -> 0 | D26: 0 | E26: 0 | L26: =+C26-D26-E26 -> 0
A27: 9.2. | B27: Минус: Резерв возможных убытков | C27: =+D27+E27 -> 0 | D27: 0 | E27: 0 | L27: =+C27-D27-E27 -> 0
A28: 10 | B28: Обязательства клиентов по финансовым инструментам, чистые | C28: =+D28+E28 -> 0 | D28: =+'Bank Assets Analysis'!T21+'Bank Assets Analysis'!T22 -> 0 | E28: =+'Bank Assets Analysis'!U21+'Bank Assets Analysis'!U22 -> 0 | L28: =+C28-D28-E28 -> 0
A29: 10.1. | B29: Обязательства клиентов по финансовым инструментам, брутто | C29: =+D29+E29 -> 0 | D29: 0 | E29: 0 | L29: =+C29-D29-E29 -> 0
A30: 10.2. | B30: Минус: Резерв возможных убытков | C30: =+D30+E30 -> 0 | L30: =+C30-D30-E30 -> 0
A31: 11 | B31: Основные средства, чистые | C31: =+'Bank Assets Analysis'!S31 -> 149099836 | D31: =+'Bank Assets Analysis'!T31 -> 149099836 | E31: =+'Bank Assets Analysis'!U31 -> 0 | L31: =+C31-D31-E31 -> 0
A32: 12 | B32: Начисленные процентные и беспроцентные доходы всего, чистые | C32: =+C33+C34-C35 -> 35355520 | D32: =+D33+D34-D35 -> 27389456 | E32: =+E33+E34-E35 -> 7966064 | L32: =+C32-D32-E32 -> 0
A33: 12.1. | B33: Начисленные проценты к получению, брутто | C33: =+'Bank Assets Analysis'!S36 -> 35343476 | D33: =+'Bank Assets Analysis'!T36 -> 27377412 | E33: =+'Bank Assets Analysis'!U36 -> 7966064 | L33: =+C33-D33-E33 -> 0
A34: 12.2. | B34: Начисленные беспроцентные доходы к получению, брутто | C34: =+D34+E34 -> 12044 | D34: 12044 | E34: 0 | L34: =+C34-D34-E34 -> 0
A35: 12.2.1. | B35: Минус: Резерв возможных убытков | C35: =+D35+E35 -> 0 | D35: 0 | E35: 0 | L35: =+C35-D35-E35 -> 0
A36: 13 | B36: Другое собственное имущество банка, чистые | C36: =+'Bank Assets Analysis'!S32 -> 0 | D36: =+'Bank Assets Analysis'!T32 -> 0 | E36: =+'Bank Assets Analysis'!U32 -> 0 | L36: =+C36-D36-E36 -> 0
A37: 13.1. | B37: Другие собственное имущество, взысканное по кредитам и лизингу, брутто | C37: =+D37+E37 -> 0 | L37: =+C37-D37-E37 -> 0
A38: 13.2. | B38: Другое собственное имущество банка, брутто | C38: =+D38+E38 -> 0 | L38: =+C38-D38-E38 -> 0
A39: 13.3. | B39: Минус:Накопленный износ и резервы на возможные убытки | C39: =+D39+E39 -> 0 | D39: 0 | L39: =+C39-D39-E39 -> 0
A40: 14 | B40: Другие активы, чистые | C40: =+C41-C42+C43 -> 159793158 | D40: =+D41-D42+D43 -> 87417391 | E40: =+E41-E42+E43 -> 72375767 | L40: =+C40-D40-E40 -> 0
A41: 14.1. | B41: Другие активы, брутто | C41: =+D41+E41 -> 164581413 | D41: 22080772 | E41: 142500641 | L41: =+C41-D41-E41 -> 0
A42: 14.2. | B42: Минус: Резерв возможных убытков | C42: =+D42+E42 -> 4788255 | D42: 4745103 | E42: 43152 | L42: =+C42-D42-E42 -> 0
A43: 14.3. | B43: Купля-продажа валюты и валютные позиции | C43: =+D43+E43 -> 0 | D43: 70081722 | E43: -70081722 | L43: =+C43-D43-E43 -> 0
A44: 15. | B44: Итого активов | C44: =+D44+E44 -> 5890272405 | D44: =+D5+D6+D7+D10+D13+D16+D19+D22+D25+D28+D31+D32+D36+D40 -> 3939131965 | E44: =+E5+E6+E7+E10+E13+E16+E19+E22+E25+E28+E31+E32+E36+E40 -> 1951140440 | F44: =+'Bank Assets Analysis'!S38 -> 5890272405 | G44: =+'Bank Assets Analysis'!T38 -> 3939131965 | H44: =+'Bank Assets Analysis'!U38 -> 1951140440 | L44: =+C44-D44-E44 -> 0
B46: ОБЯЗАТЕЛЬСТВА И СОБСТВЕННЫЙ КАПИТАЛ
B48: ОБЯЗАТЕЛЬСТВА
A49: 16. | B49: Депозиты до востребования | C49: =+'Deposits by Client'!C11 -> 411919754 | D49: =+'Bank Liabilities Analysis'!T16+'Bank Liabilities Analysis'!T8 -> 376542342 | E49: =+'Bank Liabilities Analysis'!U16+'Bank Liabilities Analysis'!U8 -> 35377412 | L49: =+C49-D49-E49 -> 0
A50: 17. | B50: Срочные депозиты | C50: =+'Deposits by Client'!C20 -> 980518852 | D50: =+'Bank Liabilities Analysis'!T13 -> 720172719 | E50: =+'Bank Liabilities Analysis'!U13 -> 260346133 | L50: =+C50-D50-E50 -> 0
A51: 18. | B51: К оплате в ЦБРУ | C51: =+'Bank Liabilities Analysis'!S23 -> 0 | D51: =+'Bank Liabilities Analysis'!T23 -> 0 | E51: =+'Bank Liabilities Analysis'!U23 -> 0 | L51: =+C51-D51-E51 -> 0
A52: 19. | B52: К оплате в другие банки | C52: =+'Bank Liabilities Analysis'!S24 -> 1255060883 | D52: =+'Bank Liabilities Analysis'!T24 -> 344256789 | E52: =+'Bank Liabilities Analysis'!U24 -> 910804094 | L52: =+C52-D52-E52 -> 0
A53: 20. | B53: Проданные по сделкам РЕПО ценные бумаги | C53: =+'Bank Liabilities Analysis'!S33 -> 0 | D53: =+'Bank Liabilities Analysis'!T33 -> 0 | E53: =+'Bank Liabilities Analysis'!U33 -> 0 | L53: =+C53-D53-E53 -> 0
A54: 21. | B54: Кредиты и лизинговые операции к оплате | C54: =+D54+E54 -> 1288900066 | D54: 818676330 | E54: 470223736 | L54: =+C54-D54-E54 -> 0
A55: 22. | B55: Выпущенные банком ценные бумаги | C55: =+D55+E55 -> 0 | D55: 0 | E55: 0 | L55: =+C55-D55-E55 -> 0
A56: 23. | B56: Субординированные долговые обязательства | C56: =+D56+E56 -> 0 | D56: 0 | E56: 0 | L56: =+C56-D56-E56 -> 0
A57: 24. | B57: Начисленные проценты к оплате | C57: =+'Bank Liabilities Analysis'!S36 -> 17489975 | D57: =+'Bank Liabilities Analysis'!T36 -> 10224338 | E57: =+'Bank Liabilities Analysis'!U36 -> 7265637 | L57: =+C57-D57-E57 -> 0
A58: 25. | B58: Начисленные налоги к оплате | C58: =+D58+E58 -> 6455266 | D58: 6455266 | E58: 0 | L58: =+C58-D58-E58 -> 0
A59: 26. | B59: Клиринговые трансакции | C59: =+'Bank Liabilities Analysis'!S35 -> 1615392 | D59: =+'Bank Liabilities Analysis'!T35 -> 1448014 | E59: =+'Bank Liabilities Analysis'!U35 -> 167378 | L59: =+C59-D59-E59 -> 0
A60: 27. | B60: Другие обязательства | C60: =+D60+E60 -> 303206742 | D60: 36250692 | E60: 266956050 | L60: =+C60-D60-E60 -> 0
A61: 28. | B61: Итого обязательств | C61: =+D61+E61 -> 4265166930 | D61: =SUM(D49:D60) -> 2314026490 | E61: =SUM(E49:E60) -> 1951140440 | F61: =+'Bank Liabilities Analysis'!S38 -> 4265166930 | G61: =+'Bank Liabilities Analysis'!T38 -> 2314026490 | H61: =+'Bank Liabilities Analysis'!U38 -> 1951140440 | L61: =+C61-D61-E61 -> 0
L62: =+C62-D62-E62 -> 0
B63: СОБСТВЕННЫЙ КАПИТАЛ | L63: =+C63-D63-E63 -> 0
L64: =+C64-D64-E64 -> 0
A65: 29. | B65: Уставный капитал | L65: =+C65-D65-E65 -> 0
A66: 29.1. | B66: Акции - Обыкновенные | C66: =+'Bank Capital Calc'!C7 -> 1641584276 | D66: 1641584276 | E66: 0 | L66: =+C66-D66-E66 -> 0
A67: 29.2. | B67: Акции - Привилегированные | C67: =+'Bank Capital Calc'!C25 -> 144180 | D67: 144180 | L67: =+C67-D67-E67 -> 0
A68: 30. | B68: Добавленный капитал | C68: =+'Bank Capital Calc'!C10+'Bank Capital Calc'!C28 -> 0 | D68: 0 | L68: =+C68-D68-E68 -> 0
A69: 31. | B69: Резервный капитал. | L69: =+C69-D69-E69 -> 0
A70: 31.1. | B70: Резервный фонд общего назначения | C70: =+D70+E70 -> 48234365 | D70: 48234365 | E70: 0 | L70: =+C70-D70-E70 -> 0
A71: 31.2. | B71: Резервы созданные по стандартным активам | C71: =+'Asset Classification'!G71 -> 0 | E71: =+'Asset Classification'!H71 -> 0 | F71: =+'Asset Classification'!G71 -> 0 | H71: =+'Asset Classification'!H71 -> 0 | L71: =+C71-D71-E71 -> 0
A72: 31.3. | B72: Резерв на Девальвацию | C72: =+'Bank Capital Calc'!C17 -> 0 | L72: =+C72-D72-E72 -> 0
A73: 31.4. | B73: Другие резервы и фонды | C73: =+D73+E73 -> 6153526 | D73: 6153526 | L73: =+C73-D73-E73 -> 0
A74: 32. | B74: Нераспределенная прибыль | C74: =+D74+E74 -> -71010872 | D74: -71010872 | E74: 0 | L74: =+C74-D74-E74 -> 0
A75: 32.1. | B75: из них, чистая прибыль (убыток) текущего года | C75: =+D75+E75 -> 6838822 | D75: 6838822 | L75: =+C75-D75-E75 -> 0
A76: 33. | B76: Итого собственного капитала | C76: =SUM(C66:C74) -> 1625105475 | D76: =SUM(D66:D74) -> 1625105475 | E76: =SUM(E66:E74) -> 0 | F76: =+'Changes in Equity'!C14 -> 1625105475 | L76: =+C76-D76-E76 -> 0
A77: 34. | B77: Итого обязательств и собственного капитала | C77: =+D77+E77 -> 5890272405 | D77: =+D61+D76 -> 3939131965 | E77: =+E61+E76 -> 1951140440 | L77: =+C77-D77-E77 -> 0
B79: Подпись Председателя правления:
B81: Подпись Главного Бухгалтера:
C83: =+C44-C77 -> 0

Sheet Asset quality
A1: ИНФОРМАЦИЯ О КАЧЕСТВЕ АКТИВОВ, ОЦЕНИВАЕМЫХ В ЦЕЛЯХ СОЗДАНИЯ РЕЗЕРВА НА ВОЗМОЖНЫЕ ПОТЕРИ | R1: Таблица-2
B3: =+Balance!B3 -> АКБ "Микрокредитбанк" | P3: =+Balance!C3 -> 43829 | S3: =+Balance!E3 -> тыс. сум
A4: № | B4: Состав активов* | C4: Остаток | D4: Категория качества | I4: Просроченная задолженность (брутто) | N4: Резерв на возможные потери
I5: итого | J5: до 30 дней | K5: от 31 до 90 дней | L5: от 91 до 180 дней | M5: свыше 180 дней | N5: фактически сформированный
N6: итого | O6: по категориям качества
D7: I | E7: II | F7: III | G7: IV | H7: V | O7: I | P7: II | Q7: III | R7: IV | S7: V
A8: А | B8: Б | C8: В | D8: Г | E8: Д | F8: Е | G8: Ж | H8: З | I8: И | J8: К | K8: Л | L8: М | M8: Н | N8: О | O8: П | P8: Р | Q8: С | R8: Т | S8: У
B9: ВСЕГО АКТИВОВ | C9: =SUM(C10:C60) -> 5890272405 | D9: =SUM(D10:D60) -> 5245683982 | E9: =SUM(E10:E60) -> 741964846 | F9: =SUM(F10:F60) -> 9977568 | G9: =SUM(G10:G60) -> 3530535 | H9: =SUM(H10:H60) -> 14101127 | I9: =SUM(I10:I60) -> 35636673 | J9: =SUM(J10:J60) -> 9434194 | ... S9: =SUM(S10:S60) -> 10600586
A10: 1 | B10: Кассовая наличность и другие платежные документы | C10: =SUM(D10:H10)-N10+O10 -> 173211577 | D10: 173211577 | I10: =SUM(J10:M10) -> 0 | N10: =SUM(O10:S10) -> 0 | T10: 10100
A11: 2 | B11: К получению из ЦБРУ | C11: =SUM(D11:H11)-N11+O11 -> 140577780 | D11: 140577780 | I11: =SUM(J11:M11) -> 0 | N11: =SUM(O11:S11) -> 0 | T11: 10300
A12: 3 | B12: К получению из других банков | C12: =SUM(D12:H12)-N12+O12 -> 453538332 | D12: 453538332 | I12: =SUM(J12:M12) -> 0 | N12: =SUM(O12:S12) -> 0 | T12: 10500
A13: 4 | B13: Ценные бумаги для купли и продажи | C13: =SUM(D13:H13)-N13+O13 -> 119576827 | D13: 119576827 | I13: =SUM(J13:M13) -> 0 | N13: =SUM(O13:S13) -> 0 | T13: 10700
A14: 5 | B14: Инвестиции в ценные бумаги, имеющиеся в наличии для продажи | C14: =SUM(D14:H14)-N14+O14 -> 0 | I14: =SUM(J14:M14) -> 0 | N14: =SUM(O14:S14) -> 0 | T14: 10800
A15: 6 | B15: Драгоценные металлы, камни и монеты для купли и продажи | C15: =SUM(D15:H15)-N15+O15 -> 175 | D15: 175 | I15: =SUM(J15:M15) -> 0 | N15: =SUM(O15:S15) -> 0 | T15: 10900
A16: 7 | B16: Купленные дебиторские задолженности - Факторинг | C16: =SUM(D16:H16)-N16+O16 -> 6311020 | D16: 6311020 | E16: 0 | F16: 0 | G16: 0 | H16: 0 | I16: =SUM(J16:M16) -> 279848 | J16: 0 | K16: 279848 | L16: 0 | M16: 0 | N16: =SUM(O16:S16) -> 0 | O16: 0 | P16: 0 | Q16: 0 | R16: 0 | S16: 0 | T16: 11100
A17: 8 | B17: Купленные векселя | C17: =SUM(D17:H17)-N17+O17 -> 0 | I17: =SUM(J17:M17) -> 0 | N17: =SUM(O17:S17) -> 0 | T17: 11300
A18: 9 | B18: Обязательства клиентов по траттам под аккредитив и/или трастовые документы | C18: =SUM(D18:H18)-N18+O18 -> 0 | I18: =SUM(J18:M18) -> 0 | N18: =SUM(O18:S18) -> 0 | T18: 11500
A19: 10 | B19: Обязательства лиентов по непогашенным акцептам банка | C19: =SUM(D19:H19)-N19+O19 -> 0 | I19: =SUM(J19:M19) -> 0 | N19: =SUM(O19:S19) -> 0 | T19: 11700
A20: 11 | B20: Купленные по сделкам РЕПО ценные бумаги | C20: =SUM(D20:H20)-N20+O20 -> 0 | I20: =SUM(J20:M20) -> 0 | N20: =SUM(O20:S20) -> 0 | T20: 11800
A21: 12 | B21: Краткосрочные кредиты, предоставленные ЦБРУ | C21: =SUM(D21:H21)-N21+O21 -> 0 | I21: =SUM(J21:M21) -> 0 | N21: =SUM(O21:S21) -> 0 | T21: 11900
A22: 13 | B22: Краткосрочные кредиты, предоставленные другим банкам | C22: =SUM(D22:H22)-N22+O22 -> 0 | I22: =SUM(J22:M22) -> 0 | N22: =SUM(O22:S22) -> 0 | T22: 12100
A23: 14 | B23: Краткосрочные кредиты, предоставленные правительству | C23: =SUM(D23:H23)-N23+O23 -> 0 | I23: =SUM(J23:M23) -> 0 | N23: =SUM(O23:S23) -> 0 | T23: 12300
A24: 15 | B24: Краткосрочные кредиты, предоставленные бюджетным организациям | C24: =SUM(D24:H24)-N24+O24 -> 0 | I24: =SUM(J24:M24) -> 0 | N24: =SUM(O24:S24) -> 0 | T24: 12400
A25: 16 | B25: Краткосрочные кредиты, предоставленные физическим лицам | C25: =SUM(D25:H25)-N25+O25 -> 81825947 | D25: 80249045 | E25: 1523268 | F25: 109598 | G25: 24327 | H25: 0 | I25: =SUM(J25:M25) -> 290686 | J25: 173539 | K25: 91690 | L25: 20347 | M25: 5110 | N25: =SUM(O25:S25) -> 80291 | O25: 0 | P25: 74471 | Q25: 5820 | R25: 0 | S25: 0 | T25: 12500
A26: 17 | B26: Краткосрочные кредиты, предоставленные индивидуальным предпринимателям | C26: =SUM(D26:H26)-N26+O26 -> 22125242 | D26: 20767187 | E26: 1132465 | F26: 384651 | G26: 4892 | H26: 0 | I26: =SUM(J26:M26) -> 370054 | J26: 113112 | K26: 160846 | L26: 93854 | M26: 2242 | N26: =SUM(O26:S26) -> 163953 | O26: 0 | P26: 62226 | Q26: 101727 | R26: 0 | S26: 0 | T26: 12600
A27: 18 | B27: Краткосрочные кредиты, предоставленные государственным предприятиям, организациям и учреждениям | C27: =SUM(D27:H27)-N27+O27 -> 4087343 | D27: 2328615 | E27: 2153839 | F27: 0 | G27: 5040 | H27: 0 | I27: =SUM(J27:M27) -> 0 | J27: 0 | K27: 0 | L27: 0 | M27: 0 | N27: =SUM(O27:S27) -> 400151 | O27: 0 | P27: 400151 | Q27: 0 | R27: 0 | S27: 0 | T27: 12700
A28: 19 | B28: Краткосрочные кредиты, предоставленные при содействии Государственного фонда поддержки развития предпринимательской деятельности | C28: =SUM(D28:H28)-N28+O28 -> 0 | I28: =SUM(J28:M28) -> 0 | N28: =SUM(O28:S28) -> 0 | T28: 12800
A29: 20 | B29: Краткосрочные кредиты, предоставленные предприятиям с участием иностранного капитала | C29: =SUM(D29:H29)-N29+O29 -> 28920287 | D29: 13333 | E29: 30315361 | F29: 0 | G29: 46684 | H29: 0 | I29: =SUM(J29:M29) -> 237330 | J29: 237330 | K29: 0 | L29: 0 | M29: 0 | N29: =SUM(O29:S29) -> 1455091 | O29: 0 | P29: 1455091 | Q29: 0 | R29: 0 | S29: 0 | T29: 12900
A30: 21 | B30: Краткосрочные кредиты, предоставленные негосударственным некоммерческим организациям | C30: =SUM(D30:H30)-N30+O30 -> 492867 | D30: 207415 | E30: 285452 | F30: 0 | G30: 0 | H30: 0 | I30: =SUM(J30:M30) -> 0 | J30: 0 | K30: 0 | L30: 0 | M30: 0 | N30: =SUM(O30:S30) -> 0 | O30: 0 | P30: 0 | Q30: 0 | R30: 0 | S30: 0 | T30: 13000
A31: 22 | B31: Краткосрочные кредиты, предоставленные частным предприятиям, хозяйственным товариществам и обществам | C31: =SUM(D31:H31)-N31+O31 -> 135706442 | D31: 118406210 | E31: 17108437 | F31: 0 | G31: 1547179 | H31: 0 | I31: =SUM(J31:M31) -> 1253341 | J31: 735495 | K31: 395749 | L31: 122097 | M31: 0 | N31: =SUM(O31:S31) -> 1355384 | O31: 0 | P31: 1355384 | Q31: 0 | R31: 0 | S31: 0 | T31: 13100
A32: 23 | B32: Краткосрочные кредиты, предоставленные небанковским финансовым институтам | C32: =SUM(D32:H32)-N32+O32 -> 10228 | D32: 10228 | I32: =SUM(J32:M32) -> 0 | N32: =SUM(O32:S32) -> 0 | T32: 13200
A33: 24 | B33: Краткосрочные кредиты, предоставленные для производства сельскохозяйственной продукции, закупаемой для государственных нужд | C33: =SUM(D33:H33)-N33+O33 -> 0 | I33: =SUM(J33:M33) -> 0 | N33: =SUM(O33:S33) -> 0 | T33: 13300
A34: 25 | B34: Долгосрочные кредиты, предоставленные для производства сельскохозяйственной продукции, закупаемой для государственных нужд | C34: =SUM(D34:H34)-N34+O34 -> 0 | I34: =SUM(J34:M34) -> 0 | N34: =SUM(O34:S34) -> 0 | T34: 14300
A35: 26 | B35: Долгосрочные кредиты, предоставленные при содействии Государственного фонда поддержки развития предпринимательской деятельности | C35: =SUM(D35:H35)-N35+O35 -> 2362100 | D35: 1996666 | E35: 413333 | F35: 0 | G35: 0 | H35: 0 | I35: =SUM(J35:M35) -> 21252 | J35: 16667 | K35: 4585 | L35: 0 | M35: 0 | N35: =SUM(O35:S35) -> 47899 | O35: 0 | P35: 47899 | Q35: 0 | R35: 0 | S35: 0 | T35: 14400
A36: 27 | B36: Долгосрочные кредиты, предоставленные другим банкам | C36: =SUM(D36:H36)-N36+O36 -> 0 | I36: =SUM(J36:M36) -> 0 | N36: =SUM(O36:S36) -> 0 | T36: 14500
A37: 28 | B37: Долгосрочные кредиты, предоставленные правительству | C37: =SUM(D37:H37)-N37+O37 -> 0 | I37: =SUM(J37:M37) -> 0 | N37: =SUM(O37:S37) -> 0 | T37: 14700
A38: 29 | B38: Долгосрочные кредиты, предоставленные бюджетным организациям | C38: =SUM(D38:H38)-N38+O38 -> 0 | I38: =SUM(J38:M38) -> 0 | N38: =SUM(O38:S38) -> 0 | T38: 14800
A39: 30 | B39: Долгосрочные кредиты, предоставленные физическим лицам | C39: =SUM(D39:H39)-N39+O39 -> 1374647662 | D39: 1360175424 | E39: 12442314 | F39: 4226282 | G39: 183301 | H39: 0 | I39: =SUM(J39:M39) -> 1921749 | J39: 660432 | K39: 580241 | L39: 401746 | M39: 279330 | N39: =SUM(O39:S39) -> 2379659 | P39: 1598673 | Q39: 627772 | R39: 153214 | S39: 0 | T39: 14900
A40: 31 | B40: Долгосрочные кредиты, предоставленные индивидуальным предпринимателям | C40: =SUM(D40:H40)-N40+O40 -> 127710513 | D40: 125749499 | E40: 2052405 | F40: 221484 | G40: 197968 | H40: 0 | I40: =SUM(J40:M40) -> 837202 | J40: 308051 | K40: 265750 | L40: 156359 | M40: 107042 | N40: =SUM(O40:S40) -> 510843 | O40: 0 | P40: 339850 | Q40: 62970 | R40: 108023 | S40: 0 | T40: 15000
A41: 32 | B41: Долгосрочные кредиты, предоставленные государственным предприятиям, организациям и учреждениям | C41: =SUM(D41:H41)-N41+O41 -> 90333574 | D41: 18109752 | E41: 76644921 | F41: 3534667 | G41: 579444 | H41: 0 | I41: =SUM(J41:M41) -> 243778 | J41: 40203 | K41: 65177 | L41: 95341 | M41: 43057 | N41: =SUM(O41:S41) -> 8535210 | O41: 0 | P41: 7024810 | Q41: 1210400 | R41: 300000 | S41: 0 | T41: 15100
A42: 33 | B42: Долгосрочные кредиты, предоставленные негосударственным некоммерческим организациям | C42: =SUM(D42:H42)-N42+O42 -> 37899886 | D42: 32190404 | E42: 5681414 | F42: 1096328 | G42: 102314 | H42: 0 | I42: =SUM(J42:M42) -> 395551 | J42: 59512 | K42: 108650 | L42: 96342 | M42: 131047 | N42: =SUM(O42:S42) -> 1170574 | O42: 0 | P42: 729570 | Q42: 341004 | R42: 100000 | S42: 0 | T42: 15200
A43: 34 | B43: Долгосрочные кредиты, предоставленные предприятиям с участием иностранного капитала | C43: =SUM(D43:H43)-N43+O43 -> 123715897 | D43: 119164340 | E43: 5380525 | F43: 0 | G43: 443556 | H43: 0 | I43: =SUM(J43:M43) -> 1329867 | J43: 386684 | K43: 673333 | L43: 269850 | M43: 0 | N43: =SUM(O43:S43) -> 1272524 | O43: 0 | P43: 418353 | Q43: 0 | R43: 854171 | S43: 0 | T43: 15300
A44: 35 | B44: Долгосрочные кредиты, предоставленные небанковским финансовым институтам | C44: =SUM(D44:H44)-N44+O44 -> 0 | I44: =SUM(J44:M44) -> 0 | N44: =SUM(O44:S44) -> 0 | O44: 0 | T44: 15400
A45: 36 | B45: Долгосрочные кредиты, предоставленные частным предприятиям, хозяйственным товариществам и обществам | C45: =SUM(D45:H45)-N45+O45 -> 2603384716 | D45: 2113605856 | E45: 586348885 | F45: 0 | G45: 0 | H45: 0 | I45: =SUM(J45:M45) -> 18207096 | J45: 4568793 | K45: 6877585 | L45: 4754619 | M45: 2006099 | N45: =SUM(O45:S45) -> 96570025 | O45: 0 | P45: 96570025 | Q45: 0 | R45: 0 | S45: 0 | T45: 15500
A46: 37 | B46: Лизинг (Финансовая аренда) | C46: =SUM(D46:H46)-N46+O46 -> 4354759 | D46: 3545827 | E46: 452007 | F46: 404558 | G46: 395830 | H46: 0 | I46: =SUM(J46:M46) -> 134754 | J46: 10689 | K46: 58544 | L46: 37445 | M46: 28076 | N46: =SUM(O46:S46) -> 443463 | O46: 0 | P46: 48244 | Q46: 144173 | R46: 251046 | S46: 0 | T46: 15600
A47: 38 | B47: Кредиты и лизинг, находящиеся в процессе судебного разбирательства | C47: =SUM(D47:H47)-N47+O47 -> 8560497 | D47: 0 | E47: 0 | F47: 0 | G47: 0 | H47: 14101127 | I47: =SUM(J47:M47) -> 0 | J47: 0 | K47: 0 | L47: 0 | M47: 0 | N47: =SUM(O47:S47) -> 5540630 | O47: 0 | P47: 0 | Q47: 0 | R47: 0 | S47: 5540630 | T47: 15700
A48: 39 | B48: Инвестиции в зависимые хозяйственные общества, совместные предприятия и дочерние хозяйственные общества | C48: =SUM(D48:H48)-N48+O48 -> 70220 | D48: 341924 | E48: 0 | F48: 0 | G48: 0 | H48: 0 | I48: =SUM(J48:M48) -> 0 | J48: 0 | K48: 0 | L48: 0 | M48: 0 | N48: =SUM(O48:S48) -> 271704 | O48: 0 | P48: 0 | Q48: 0 | R48: 0 | S48: 271704 | T48: 15800
A49: 40 | B49: Инвестиции в долговые ценные бумаги, удерживаемые до погашения | C49: =SUM(D49:H49)-N49+O49 -> 6600000 | D49: 6600000 | E49: 0 | F49: 0 | G49: 0 | H49: 0 | I49: =SUM(J49:M49) -> 0 | J49: 0 | K49: 0 | L49: 0 | M49: 0 | N49: =SUM(O49:S49) -> 0 | O49: 0 | P49: 0 | Q49: 0 | R49: 0 | S49: 0 | T49: 15900
A50: 41 | B50: Начисленные проценты к получению | C50: =SUM(D50:H50)-N50+O50 -> 35343476 | D50: 35343476 | E50: 0 | F50: 0 | G50: 0 | H50: 0 | I50: =SUM(J50:M50) -> 10114165 | J50: 2123687 | K50: 4429815 | L50: 2478121 | M50: 1082542 | N50: =SUM(O50:S50) -> 0 | O50: 0 | P50: 0 | Q50: 0 | R50: 0 | S50: 0 | T50: 16300
A51: 42 | B51: Начисленные беспроцентные доходы к получению | C51: =SUM(D51:H51)-N51+O51 -> 12043 | D51: 12043 | E51: 0 | F51: 0 | G51: 0 | H51: 0 | I51: =SUM(J51:M51) -> 0 | J51: 0 | K51: 0 | L51: 0 | M51: 0 | N51: =SUM(O51:S51) -> 0 | O51: 0 | P51: 0 | Q51: 0 | R51: 0 | S51: 0 | T51: 16400
A52: 43 | B52: Основные средства | C52: =SUM(D52:H52)-N52+O52 -> 147419920 | D52: 147419920 | E52: 0 | F52: 0 | G52: 0 | H52: 0 | I52: =SUM(J52:M52) -> 0 | J52: 0 | K52: 0 | L52: 0 | M52: 0 | N52: =SUM(O52:S52) -> 0 | O52: 0 | P52: 0 | Q52: 0 | R52: 0 | S52: 0 | T52: 16500
A53: 44 | B53: Нематериальные активы | C53: =SUM(D53:H53)-N53+O53 -> 1679916 | D53: 1679916 | E53: 0 | F53: 0 | G53: 0 | H53: 0 | I53: =SUM(J53:M53) -> 0 | J53: 0 | K53: 0 | L53: 0 | M53: 0 | N53: =SUM(O53:S53) -> 0 | O53: 0 | P53: 0 | Q53: 0 | R53: 0 | S53: 0 | T53: 16600
A54: 45 | B54: Другое собственное имущество банка | C54: =SUM(D54:H54)-N54+O54 -> 0 | D54: 0 | E54: 0 | F54: 0 | G54: 0 | H54: 0 | I54: =SUM(J54:M54) -> 0 | J54: 0 | K54: 0 | L54: 0 | M54: 0 | N54: =SUM(O54:S54) -> 0 | O54: 0 | P54: 0 | Q54: 0 | R54: 0 | S54: 0 | T54: 16700
A55: 46 | B55: Отсроченная дебиторская задолженность | C55: =SUM(D55:H55)-N55+O55 -> 1803739 | D55: 5409517 | E55: 30220 | F55: 0 | G55: 0 | H55: 0 | I55: =SUM(J55:M55) -> 0 | J55: 0 | K55: 0 | L55: 0 | M55: 0 | N55: =SUM(O55:S55) -> 3635998 | O55: 0 | P55: 0 | Q55: 0 | R55: 0 | S55: 3635998 | T55: 16800
A56: 47 | B56: Нереализованная прибыль при ревальвации производных инструментов | C56: =SUM(D56:H56)-N56+O56 -> 0 | D56: 0 | E56: 0 | F56: 0 | G56: 0 | H56: 0 | I56: =SUM(J56:M56) -> 0 | J56: 0 | K56: 0 | L56: 0 | M56: 0 | N56: =SUM(O56:S56) -> 0 | O56: 0 | P56: 0 | Q56: 0 | R56: 0 | S56: 0 | T56: 16900
... A60: 51 | B60: Другие активы | C60: =SUM(D60:H60)-N60+O60 -> 152544109 | D60: 153696363 | E60: 0 | F60: 0 | G60: 0 | H60: 0 | I60: =SUM(J60:M60) -> 0 | J60: 0 | K60: 0 | L60: 0 | M60: 0 | N60: =SUM(O60:S60) -> 1152254 | O60: 0 | P60: 0 | Q60: 0 | R60: 0 | S60: 1152254 | T60: 19900
B62: ЗАБАЛАНСОВЫЕ СТАТЬИ | C62: =SUM(D62:H62) -> 125869722 | D62: =SUM(D63:D64) -> 125869722 | E62: =SUM(E63:E64) -> 0 | F62: =SUM(F63:F64) -> 0 | G62: =SUM(G63:G64) -> 0 | H62: =SUM(H63:H64) -> 0 | I62: =SUM(J62:M62) -> 0 | J62: =SUM(J63:J64) -> 0 | K62: =SUM(K63:K64) -> 0 | L62: =SUM(L63:L64) -> 0 | M62: =SUM(M63:M64) -> 0 | N62: =SUM(N63:N64) -> 0 | O62: =SUM(O63:O64) -> 0 | P62: =SUM(P63:P64) -> 0 | Q62: =SUM(Q63:Q64) -> 0 | ... S62: =SUM(S63:S64) -> 0
A63: 1 | B63: Аккредитивы | C63: =SUM(D63:H63)-N63+O63 -> 11705135 | D63: 11705135 | I63: =SUM(J63:M63) -> 0 | N63: =SUM(O63:S63) -> 0 | T63: 90908-90958
A64: 2 | B64: Гарантии и поручетельства | C64: =SUM(D64:H64)-N64+O64 -> 114164587 | D64: 114164587 | I64: =SUM(J64:M64) -> 0 | N64: =SUM(O64:S64) -> 0 | T64: 90993
B67: Подпись Председателя правления:
B69: Подпись Главного Бухгалтера:
B71: Состав активов банка формируется в соответсвии с Планом счетов
C72: =+Balance!C44 -> 5890272405

Sheet Income 
B1: ОТЧЕТ О ФИНАНСОВЫХ РЕЗУЛЬТАТАХ | D1: Таблица-3
B3: =Balance!B3 -> АКБ "Микрокредитбанк" | C3: =+'Asset quality'!P3 -> 43829 | E3: в тыс. сум
A4: № | B4: Категории | C4: Итого | D4: в национальной валюте | E4: в иностранной валюте (в экв. в сумах)
A5: 1. | B5: 1. ПРОЦЕНТНЫЕ ДОХОДЫ
A6: a. | B6: Процентные доходы по счетам в ЦБРУ | C6: =+D6+E6 -> 81594 | D6: 81594
A7: б. | B7: Процентные доходы по счетам в других банках | C7: =+D7+E7 -> 12489567 | D7: 12489567
A8: в. | B8: Процентные доходы по купленным векселям | C8: =+D8+E8 -> 0 | D8: 0
A9: г. | B9: Процентные доходы по инвестициям | C9: =+D9+E9 -> 792723 | D9: 792723
A10: д. | B10: Процентные доходы по счетам купли-продажи ценных бумаг | C10: =+D10+E10 -> 9722584 | D10: 9722584
A11: е. | B11: Процентные доходы по обязательствам клиентов | C11: =+D11+E11 -> 0 | D11: 0
A12: ж. | B12: Процентные доходы по обяз-вам клиентов по непогашенным акцептам этого банка | C12: =+D12+E12 -> 0 | D12: 0
A13: з. | B13: Процент, Дисконт (Скидки) и взносы по кредитным и лизинговым операциям | C13: =+D13+E13 -> 509814535 | D13: 509814535
A14: и. | B14: Процентные доходы по соглашениям о покупке ценных бумаг с обратным выкупом | C14: =+D14+E14 -> 0 | D14: 0
A15: к. | B15: Другие процентные доходы | C15: =+D15+E15 -> 188576046 | D15: 188576046
A16: л. | B16: Итого процентных доходов | C16: =SUM(C6:C15) -> 721477049 | D16: =SUM(D6:D15) -> 721477049 | E16: =SUM(E6:E15) -> 0 | G16: =+'Analysis of Interest'!C42 -> 721477049
A18: 2. | B18: ПРОЦЕНТНЫЕ РАСХОДЫ
A19: а. | B19: Процентные расходы по депозитам до востребования | C19: =+D19+E19 -> 1370451 | D19: 1370451
A20: б. | B20: Процентные расходы по срочным депозитам | C20: =+D20+E20 -> 125270257 | D20: 125270257
A21: в. | B21: Процентные расходы по счетам к оплате в ЦБРУ | C21: =+D21+E21 -> 0
A22: г. | B22: Процентные расходы по счетам к оплате в другие банки | C22: =+D22+E22 -> 52377347 | D22: 52377347
A23: д. | B23: Итого процентных расходов по депозитам | C23: =SUM(C19:C22) -> 179018055 | D23: =SUM(D19:D22) -> 179018055 | E23: =SUM(E19:E22) -> 0
A24: е. | B24: Процентные расходы по кредитам к оплате | C24: =+D24+E24 -> 36723237 | D24: 36723237
A25: ж. | B25: Процентные расходы по соглашениям о продаже ц/б с последующим выкупом | C25: =+D25+E25 -> 0
A26: з. | B26: Другие процентные расходы | C26: =+D26+E26 -> 187555672 | D26: 187555672
A27: и. | B27: Итого процентных расходов по займам | C27: =SUM(C24:C26) -> 224278909 | D27: =SUM(D24:D26) -> 224278909 | E27: =SUM(E24:E26) -> 0
A28: л. | B28: Итого процентных расходов | C28: =C27+C23 -> 403296964 | D28: =D27+D23 -> 403296964 | E28: =E27+E23 -> 0 | G28: =+'Analysis of Interest'!C72 -> 403296964
A30: 3. | B30: ЧИСТЫЕ ПРОЦЕНТНЫЕ ДОХОДЫ ДО ОЦЕНКИ ВОЗМОЖНЫХ УБЫТКОВ ПО АКТИВАМ | C30: =C16-C28 -> 318180085 | D30: =D16-D28 -> 318180085 | E30: =E16-E28 -> 0
A31: а. | B31: Минус: Оценка возможных убытков по кредитам и лизингу | C31: =+D31+E31 -> 139622948 | D31: 139622948
A32: б. | B32: Минус: Оценка возможных убытков по в ценным бумагам | C32: =+D32+E32 -> 0 | D32: 0
A33: в. | B33: Минус: Оценка возможных убытков по инвестициям | C33: =+D33+E33 -> 271704 | D33: 271704
A34: г. | B34: Минус: Оценка возможных убытков по другим активам | C34: =+D34+E34 -> 4727042 | D34: 4727042
A35: д. | B35: Чистые процентные доходы после оценки возможных убытков по кредитам и лизингу | C35: =C30-C31-C32-C33-C34 -> 173558391 | D35: =D30-D31-D32-D33-D34 -> 173558391 | E35: =E30-E31-E32-E33-E34 -> 0
A37: 4. | B37: БЕСПРОЦЕНТНЫЕ ДОХОДЫ
A38: а. | B38: Доходы от комиссий и платы за услуги | C38: =+D38+E38 -> 77887497 | D38: 77887497
A39: б. | B39: Прибыль в иностранной валюте | C39: =+D39+E39 -> 40924909 | D39: 40924909
A40: в. | B40: Прибыль от коммерческих операций | C40: =+D40+E40 -> 21699 | D40: 21699
A41: г. | B41: Прибыль и дивиденды от инвестиций | C41: =+D41+E41 -> 23246 | D41: 23246
A42: д. | B42: Другие беспроцентные доходы | C42: =+D42+E42 -> 97933027 | D42: 97933027
A43: е. | B43: Итого беспроцентных доходов | C43: =SUM(C38:C42) -> 216790378 | D43: =SUM(D38:D42) -> 216790378 | E43: =SUM(E38:E42) -> 0
A45: 5. | B45: БЕСПРОЦЕНТНЫЕ РАСХОДЫ
A46: а. | B46: Комиссионные расходы и расходы за услуги | C46: =+D46+E46 -> 25072126 | D46: 25072126
A47: б. | B47: Убытки в иностранной валюте | C47: =+D47+E47 -> 66056180 | D47: 66056180
A48: в. | B48: Убытки по счетам купли-продажи | C48: =+D48+E48 -> 0
A49: г. | B49: Убытки от инвестиций | C49: =+D49+E49 -> 0
A50: д. | B50: Другие беспроцентные расходы | C50: =+D50+E50 -> 1412453 | D50: 1412453
A51: е. | B51: Итого беспроцентных расходов | C51: =SUM(C46:C50) -> 92540759 | D51: =SUM(D46:D50) -> 92540759 | E51: =SUM(E46:E50) -> 0
A53: 6. | B53: ЧИСТЫЙ ДОХОД ДО ОПЕРАЦИОННЫХ РАСХОДОВ | C53: =C35+C43-C51 -> 297808010 | D53: =D35+D43-D51 -> 297808010 | E53: =E35+E43-E51 -> 0
A55: 7. | B55: ОПЕРАЦИОННЫЕ РАСХОДЫ
A56: а. | B56: Заработная плата и другие расходы на сотрудников | C56: =+D56+E56 -> 198100660 | D56: 198100660
A57: а1) | B57: из них, выплаты основному руководящему персоналу | C57: =+D57+E57 -> 0 | D57: 0
A58: б. | B58: Аренда и содержание | C58: =+D58+E58 -> 32455060 | D58: 32455060
A59: в. | B59: Командировочные и транспортные расходы | C59: =+D59+E59 -> 5294616 | D59: 5294616
A60: г. | B60: Административные расходы | C60: =+D60+E60 -> 8647268 | D60: 8647268
A61: д. | B61: Репрезентация и благотворительность | C61: =+D61+E61 -> 3492509 | D61: 3492509
A62: е. | B62: Расходы на износ | C62: =+D62+E62 -> 20436225 | D62: 20436225
A63: ж. | B63: Страхование | C63: =+D63+E63 -> 8862516 | D63: 8862516
A64: з. | B64: Налоги | C64: =+D64+E64 -> 2302338 | D64: 2302338
A65: и. | B65: Штрафы и пеня | C65: =+D65+E65 -> 0 | D65: 0
A66: к. | B66: Другие операционные расходы | C66: =+D66+E66 -> 8247191 | D66: 8247191
A67: л. | B67: Итого операционных расходов | C67: =SUM(C56:C66)-C57 -> 287838383 | D67: =SUM(D56:D66)-D57 -> 287838383
A69: 8. | B69: ЧИСТАЯ ПРИБЫЛЬ ДО УПЛАТЫ НАЛОГОВ И ДРУГИХ ПОПРАВОК | C69: =C53-C67 -> 9969627 | D69: =D53-D67 -> 9969627 | E69: =+E53-(C67-D67) -> 0
A70: а. | B70: Оценка налога на прибыль | C70: =+D70 -> 3130805 | D70: 3130805
A72: 9. | B72: ДОХОД ДО ВВЕДЕНИЯ ПОПРАВОК | C72: =C69-C70 -> 6838822 | D72: =D69-D70 -> 6838822 | E72: =E69-E70 -> 0
A73: а. | B73: Непредвиденные доходы или убытки, чистые | C73: =+D73+E73 -> 0
A74: б. | B74: Другие поправки к прибыли, чистые | C74: =+D74+E74 -> 0
A76: 10. | B76: ЧИСТАЯ ПРИБЫЛЬ (УБЫТКИ) | C76: =C72+C73+C74 -> 6838822 | D76: =D72+D73+D74 -> 6838822 | E76: =E72+E73+E74 -> 0
B78: Подпись Председателя правления:
B80: Подпись Главного Бухгалтера:

Sheet Analysis of Interest
B1: АНАЛИЗ ПРОЦЕНТНЫХ ДОХОДОВ И РАСХОДОВ | C1: Таблица-4
B3: =Balance!B3 -> АКБ "Микрокредитбанк" | C3: =+Balance!C3 -> 43829
A4: № | B4: Категория | C4: в тыс. сум
A5: 1 . | B5: ПРОЦЕНТНЫЕ ДОХОДЫ ПО КРЕДИТНЫМ И ЛИЗИНГОВЫМ ОПЕРАЦИЯМ
A6: a. | B6: Кредиты и лизинговые операции ЦБРУ
A7: б. | B7: Кредиты и лизинговые операции другим банкам | C7: 31454
A8: в. | B8: Кредиты и лизинговые операции Правительству
A9: г. | B9: Кредиты и лизинговые операции физическим лицам | C9: 254188323
A10: д. | B10: Кредиты и лизинговые операции государственным предприятиям | C10: 8243902
A11: е. | B11: Кредиты и лизинговые операции совместным и иностранным предприятиям | C11: 26345385
A12: ж. | B12: Кредиты и лизинговые операции частным товариществам и корпорациям | C12: 218415663
A13: з. | B13: Другие кредиты и лизинговые операции | C13: 2589808
A14: и. | B14: ИТОГО ПРОЦЕНТНЫХ ДОХОДОВ ПО КРЕДИТНЫМ И ЛИЗИНГОВЫМ ОПЕРАЦИЯМ | C14: =SUM(C6:C13) -> 509814535
A16: 2. | B16: ПРОЦЕНТНЫЕ ДОХОДЫ ПО КОРРЕСПОНДЕНТСКИМ СЧЕТАМ
A17: a. | B17: К получению из ЦБРУ | C17: 81594
A18: б. | B18: К получению из других банков | C18: 12489567
B19: ИТОГО ПРОЦЕНТНЫХ ДОХОДОВ ПО КОРРЕСПОНДЕНТСКИМ СЧЕТАМ | C19: =SUM(C17:C18) -> 12571161
A21: 3. | B21: ПРОЦЕНТНЫЕ ДОХОДЫ ПО СЧЕТАМ КУПЛИ-ПРОДАЖИ Ц/Б
A22: a. | B22: Государственные казначейские ценные бумаги | C22: 9722584
A23: б. | B23: Облигации и ценные бумаги ЦБРУ | C23: 0
A24: в. | B24: Ценные бумаги государственных корпораций | C24: 0
A25: г. | B25: Еврооблигации | C25: 0
A26: д. | B26: Частные ценные бумаги | C26: 0
A27: е. | B27: Другие ценные бумаги | C27: 0
A28: ж. | B28: ИТОГО ПРОЦЕНТНЫХ ДОХОДОВ ПО СЧЕТАМ КУПЛИ-ПРОДАЖИ Ц/Б | C28: =SUM(C22:C27) -> 9722584
A30: 4. | B30: ПРОЦЕНТНЫЕ ДОХОДЫ ПО ИНВЕСТИЦИЯМ
A31: a. | B31: Государственные облигации | C31: 0
A32: б. | B32: Облигации и ценные бумаги ЦБРУ | C32: 0
A33: в. | B33: Частные облигации | C33: 0
A34: г. | B34: Еврооблигации | C34: 0
A35: д. | B35: Другие ценные бумаги | C35: 792723
A36: е. | B36: ИТОГО ПРОЦЕНТНЫХ ДОХОДОВ ПО ИНВЕСТИЦИЯМ | C36: =SUM(C31:C35) -> 792723
A38: 5. | B38: ДРУГИЕ ПРОЦЕНТНЫЕ ДОХОДЫ
A39: a. | B39: Процентные доходы по соглашениям о покупке ц/б c обратным выкупом | C39: 0
A40: б. | B40: Другие процентные доходы | C40: 188576046
A42: 6. | B42: ИТОГО ПРОЦЕНТНЫХ ДОХОДОВ | C42: =C14+C19+C28+C36+C39+C40 -> 721477049
A44: 7. | B44: ПРОЦЕНТНЫЕ РАСХОДЫ ПО ДЕПОЗИТАМ
A45: A. | B45: Депозиты до востребования
A46: a. | B46: Правительство | C46: 1364336
A47: б. | B47: Физические лица | C47: 6115
A48: в. | B48: Государственные предприятия | C48: 0
A49: г. | B49: Совместные и иностранные предприятия | C49: 0
A50: д. | B50: Частные товарищества и корпорации | C50: 0
A51: е. | B51: Другие депозиты | C51: 0
A52: ж. | B52: Итого процентных расходов по депозитам до востребования | C52: =SUM(C46:C51) -> 1370451
A54: Б. | B54: Срочные депозиты
A55: a. | B55: Правительство | C55: 64964982
A56: б. | B56: Физические лица | C56: 26849088
A57: в. | B57: Государственные предприятия | C57: 12011951
A58: г. | B58: Совместные и иностранные предприятия | C58: 244451
A59: д. | B59: Частные товарищества и корпорации | C59: 1461546
A60: е. | B60: Другие депозиты | C60: 19738238
A61: ж. | B61: Итого процентных расходов по срочным депозитам | C61: =SUM(C55:C60) -> 125270256
A63: В. | B63: ИТОГО ПРОЦЕНТНЫХ РАСХОДОВ ПО ДЕПОЗИТАМ | C63: =C52+C61 -> 126640707
A65: 8. | B65: ПРОЦЕНТНЫЕ РАСХОДЫ ПО ДРУГИМ ОБЯЗАТЕЛЬСТВАМ
A66: а. | B66: Процентные расходы по непогашенным акцептам | C66: 0
A67: б. | B67: Процентные расходы по кредитам к оплате | C67: 36723237
A68: в. | B68: Процентные расходы по соглашениям о продаже ц/б с последующим выкупом | C68: 0
A69: г. | B69: Другие процентные расходы | C69: 239933020
A70: д. | B70: ИТОГО ПРОЦЕНТНЫХ РАСХОДОВ ПО ДРУГИМ ОБЯЗАТЕЛЬСТВАМ | C70: =SUM(C66:C69) -> 276656257
A72: 9. | B72: ИТОГО ПРОЦЕНТНЫХ РАСХОДОВ | C72: =C63+C70 -> 403296964
B74: Подпись Председателя правления:
B76: Подпись Главного Бухгалтера:

Sheet Bank Capital Calc
A1: РАСЧЕТ РЕГУЛЯТИВНОГО КАПИТАЛА БАНКА | C1: Таблица-5
B3: =Balance!B3 -> АКБ "Микрокредитбанк" | C3: =+Balance!C3 -> 43829
A4: № | B4: Характеристики | C4: Итого капитала
A5: I. | B5: КАПИТАЛ УРОВНЯ 1
A6: 1 | B6: ОСНОВНОЙ КАПИТАЛ УРОВНЯ 1
A7: 1.1. | B7: Обыкновенные Акции, чистые | C7: =+C8+C9 -> 1641584276
A8: a | B8: Полностью оплаченные обыкновенные акции | C8: 1641584276
A9: б | B9: Минус: Обратно Выкупленные обыкновенные акции
A10: 1.2. | B10: Добавленный капитал - Обыкновенные | C10: 0
A11: 1.3. | B11: Нераспределенная прибыль (убыток), в том числе капитальные резервы | C11: =+C12+C13-C14-C15 -> -28839355
A12: а | B12: Капитальные резервы | C12: 49010340
A13: б | B13: Нераспределенная прибыль | C13: 0
A14: в | B14: Убыток за предыдущие периоды | C14: 77849695
A15: г | B15: Убыток за текущий год | C15: 0
A16: 1.4. | B16: Интерес меньшинства в консолидированных дочерних компаниях (согласно МБС) | C16: 0
A17: 1.5. | B17: Резерв на девальвацию | C17: 0
B18: Итого основного капитала уровня I до вычетов | C18: =+C7+C10+C11+C16+C17 -> 1612744921
A19: 1.6. | B19: Вычеты из суммы основного капитала уровня I | C19: =C21+C22 -> 6941923
A20: а | B20: Нематериальные активы | C20: 1679916
A21: б | B21: Все инвестиции в капитал неконсолидированных хозяйствующих субъектов, в том числе в долговые обязательства, которые образуют капитал хозяйствующих субъектов | C21: 6941923
A22: в | B22: Инвестиции в капитал других банков | C22: 0
A23: I | B23: ВСЕГО СКОРРЕКТИРОВАННЫЙ ОСНОВНОЙ КАПИТАЛ УРОВНЯ I | C23: =+C18-C19 -> 1605802998
A24: 2 | B24: ДОБАВЛЕННЫЙ КАПИТАЛ УРОВНЯ 1
A25: 2.1. | B25: Некумулятивные бессрочные привилегированные акции | C25: =+C26+C27 -> 144180
A26: а | B26: Полностью оплаченные привилегированные акции | C26: 144180
A27: б | B27: Минус: Обратно Выкупленные привилегированные акции | C27: 0
A28: 2.2. | B28: Добавленный капитал - Привилегированные | C28: 0
A29: 2.3. | B29: Интерес меньшинства в консолидированных дочерних компаниях | C29: 0
A30: 2.4. | B30: Доля участия дочерних предприятий (выпущенные дочерними предприятиями и находящиеся во владении третьих лиц инструменты, приравненные к капиталу) | C30: 0
A31: II | B31: ВСЕГО ДОБАВЛЕННЫЙ КАПИТАЛ УРОВНЯ I | C31: =+C25+C28+C29+C30 -> 144180
A32: III | B32: ВСЕГО СКОРРЕКТИРОВАННЫЙ КАПИТАЛ УРОВНЯ I | C32: =+C23+C31 -> 1605947178
B33: КАПИТАЛ УРОВНЯ II
A34: 3.1. | B34: Прибыль за текущий год | C34: 6838822
A35: 3.2. | B35: Резервы, создаваемые на стандартные кредиты (активы), в размере не более 1.25% от общей суммы активов, взвешенных с учетом риска | C35: =IF(Balance!C71<(C43*1.25%),Balance!C71,(C43*1.25%)) -> 0
A36: 3.3. | B36: Излишки оценочной стоимости прироста над первоначальной стоимостью | C36: 2419898
A37: 3.4. | B37: Другие инструменты капитала (не более 1/3 части капитала 1 уровня после вычетов) | C37: 0
A38: 3.5. | B38: Субординированный долг | C38: 0
A39: 3.6. | B39: Вычеты превышения Капитала Уровня II над Капиталом Уровня I | C39: =IF(C40<(C32/3),0,(C40-C32/3)*-1) -> 0
B40: Итого капитала Уровня II | C40: =SUM(C34:C38) -> 9258720
A41: IV | B41: СКОРРЕКТИРОВАННЫЙ КАПИТАЛ УРОВНЯ II | C41: =+C39+C40 -> 9258720
A42: V | B42: ВСЕГО РЕГУЛЯТИВНЫЙ КАПИТАЛ | C42: =+C32+C39+C40 -> 1615205898
A43: VI | B43: ОБЩАЯ СУММА АКТИВОВ ВЗВЕШЕННЫХ С УЧЕТОМ РИСКА | C43: =+C44+C45+C46 -> 6.8074885e+09
A44: а | B44: Сумма балансовых и забалансовых активов, взвешенных с учетом риска | C44: =+'Calculation of Risk Weighted As'!J78 -> 6.483866e+09
A45: б | B45: Операционный риск | C45: =+'Calculation of Risk'!C21 -> 269713520
A46: в | B46: Рыночный риск | C46: =+'Calculation of Risk'!C27 -> 53909018 | E46: =+'Calculation of Risk'!G11 -> 10
A47: VII | B47: КОЭФФИЦИЕНТ ОСНОВНОГО КАПИТАЛА УРОВНЯ I (I/VI) | C47: =+C23/C43 -> 0.23588773
A48: VIII | B48: КОЭФФИЦИЕНТ КАПИТАЛА УРОВНЯ I (III/VI) | C48: =+C32/C43 -> 0.23590891
A49: IX | B49: КОЭФФИЦИЕНТ ОБЩЕЙ СУММЫ КАПИТАЛА, ОСНОВАННОГО НА РИСКЕ (V/VI) | C49: =+C42/C43 -> 0.23726899
A50: X | B50: Активы для расчета левеража | C50: =SUM(C51:C53)-C54 -> 6739896681
A51: а | B51: Общие активы | C51: =+Balance!C44 -> 5890272405
A52: б | B52: Забалансовые инструменты | C52: =SUM('Calculation of Risk Weighted As'!F58:I66) -> 856566199 | D52: =+'Calculation of Risk Weighted As'!J78 -> 6.483866e+09
A53: в | B53: Деривативные (производные) инструменты | C53: =SUM('Calculation of Risk Weighted As'!J69:J75) -> 0
A54: г | B54: Минус: Строка 1.6. Итого вычетов из суммы основного капитала Уровня 1 | C54: =+C19 -> 6941923
A55: XI | B55: Коэффициент левеража | C55: =+C32/C50 -> 0.23827475
B57: Подпись Председателя правления:
B59: Подпись Главного Бухгалтера:

Sheet Bank Capital Calc (2)
A1: РАСЧЕТ РЕГУЛЯТИВНОГО КАПИТАЛА БАНКА | C1: Таблица-5
B3: =Balance!B3 -> АКБ "Микрокредитбанк" | C3: =+Balance!C3 -> 43829
A4: № | B4: Характеристики | C4: Итого капитала
A5: I. | B5: КАПИТАЛ УРОВНЯ 1
A6: 1 | B6: ОСНОВНОЙ КАПИТАЛ УРОВНЯ 1
A7: 1.1. | B7: Обыкновенные Акции, чистые | C7: Формула
A8: a | B8: Полностью оплаченные обыкновенные акции
A9: б | B9: Минус: Обратно Выкупленные обыкновенные акции
A10: 1.2. | B10: Добавленный капитал - Обыкновенные | C10: 0
A11: 1.3. | B11: Нераспределенная прибыль (убыток), в том числе капитальные резервы | C11: Формула
A12: а | B12: Капитальные резервы
A13: б | B13: Нераспределенная прибыль
A14: в | B14: Убыток за предыдущие периоды
A15: г | B15: Убыток за текущий год
A16: 1.4. | B16: Интерес меньшинства в консолидированных дочерних компаниях (согласно МБС)
A17: 1.5. | B17: Резерв на девальвацию
B18: Итого основного капитала уровня I до вычетов | C18: Формула
A19: 1.6. | B19: Вычеты из суммы основного капитала уровня I | C19: Формула
A20: а | B20: Нематериальные активы
A21: б | B21: Все инвестиции в капитал неконсолидированных хозяйствующих субъектов, в том числе в долговые обязательства, которые образуют капитал хозяйствующих субъектов
A22: в | B22: Инвестиции в капитал других банков
A23: I | B23: ВСЕГО СКОРРЕКТИРОВАННЫЙ ОСНОВНОЙ КАПИТАЛ УРОВНЯ I | C23: Формула
A24: 2 | B24: ДОБАВЛЕННЫЙ КАПИТАЛ УРОВНЯ 1
A25: 2.1. | B25: Некумулятивные бессрочные привилегированные акции | C25: =+C26+C27 -> 0
A26: а | B26: Полностью оплаченные привилегированные акции
A27: б | B27: Минус: Обратно Выкупленные привилегированные акции
A28: 2.2. | B28: Добавленный капитал - Привилегированные | C28: 0
A29: 2.3. | B29: Интерес меньшинства в консолидированных дочерних компаниях | C29: 0
A30: 2.4. | B30: Доля участия дочерних предприятий (выпущенные дочерними предприятиями и находящиеся во владении третьих лиц инструменты, приравненные к капиталу) | C30: 0
A31: II | B31: ВСЕГО ДОБАВЛЕННЫЙ КАПИТАЛ УРОВНЯ I | C31: =+C25+C28+C29+C30 -> 0
A32: III | B32: ВСЕГО СКОРРЕКТИРОВАННЫЙ КАПИТАЛ УРОВНЯ I | C32: Формула
B33: КАПИТАЛ УРОВНЯ II
A34: 3.1. | B34: Прибыль за текущий год
A35: 3.2. | B35: Резервы, создаваемые на стандартные кредиты (активы), в размере не более 1.25% от общей суммы активов, взвешенных с учетом риска | C35: =IF(Balance!C71<(C43*1.25%),Balance!C71,(C43*1.25%)) -> 0
A36: 3.3. | B36: Излишки оценочной стоимости прироста над первоначальной стоимостью
A37: 3.4. | B37: Другие инструменты капитала (не более 1/3 части капитала 1 уровня после вычетов)
A38: 3.5. | B38: Субординированный долг
A39: 3.6. | B39: Вычеты превышения Капитала Уровня II над Капиталом Уровня I | C39: Формула
B40: Итого капитала Уровня II | C40: =SUM(C34:C38) -> 0
A41: IV | B41: СКОРРЕКТИРОВАННЫЙ КАПИТАЛ УРОВНЯ II | C41: Формула
A42: V | B42: ВСЕГО РЕГУЛЯТИВНЫЙ КАПИТАЛ | C42: Формула
A43: VI | B43: ОБЩАЯ СУММА АКТИВОВ ВЗВЕШЕННЫХ С УЧЕТОМ РИСКА | C43: =+C44+C45+C46 -> 6.8074885e+09
A44: а | B44: Сумма балансовых и забалансовых активов, взвешенных с учетом риска | C44: =+'Calculation of Risk Weighted As'!J78 -> 6.483866e+09
A45: б | B45: Операционный риск | C45: =+'Calculation of Risk'!C21 -> 269713520
A46: в | B46: Рыночный риск | C46: =+'Calculation of Risk'!C27 -> 53909018 | E46: =+'Calculation of Risk'!G11 -> 10
A47: VII | B47: КОЭФФИЦИЕНТ ОСНОВНОГО КАПИТАЛА УРОВНЯ I (I/VI) | C47: Формула
A48: VIII | B48: КОЭФФИЦИЕНТ КАПИТАЛА УРОВНЯ I (III/VI) | C48: Формула
A49: IX | B49: КОЭФФИЦИЕНТ ОБЩЕЙ СУММЫ КАПИТАЛА, ОСНОВАННОГО НА РИСКЕ (V/VI) | C49: Формула
A50: X | B50: Активы для расчета левеража | C50: Формула
A51: а | B51: Общие активы | C51: =+Balance!C44 -> 5890272405
A52: б | B52: Забалансовые инструменты | C52: =SUM('Calculation of Risk Weighted As'!F58:I66) -> 856566199 | D52: =+'Calculation of Risk Weighted As'!J78 -> 6.483866e+09
A53: в | B53: Деривативные (производные) инструменты | C53: =SUM('Calculation of Risk Weighted As'!J69:J75) -> 0
A54: г | B54: Минус: Строка 1.6. Итого вычетов из суммы основного капитала Уровня 1 | C54: =+C19 -> Формула
A55: XI | B55: Коэффициент левеража | C55: Формула
B57: Подпись Председателя правления:
B59: Подпись Главного Бухгалтера:

Sheet Calculation of Risk Weighted As
A1: РАСЧЕТ АКТИВОВ ВЗВЕШЕННЫХ С УЧЕТОМ РИСКА | I1: Таблица-6
B3: =Balance!B3 -> АКБ "Микрокредитбанк" | G3: =+Balance!C3 -> 43829 | J3: =+Balance!E3 -> тыс. сум
A4: № | B4: Характеристики | C4: 0 | D4: 0.2 | E4: 0.3 | F4: 0.5 | G4: 1 | H4: 1.5 | I4: 2 | J4: 3
C5: Риск | D5: Риск | E5: Риск | F5: Риск | G5: Риск | H5: Риск | I5: Риск | J5: Риск
B6: (A) | C6: (Б) | D6: (В) | E6: (Г) | F6: (Д) | G6: (Е) | H6: (Ж) | I6: (З) | J6: (И)
B7: Балансовые Активы
A8: 1. | B8: Касса (наличность и монеты) и Драгоценные металлы | C8: 159937550
A9: 2. | B9: Денежная наличность и другие платежные документы в пути | D9: 13274201
A10: 3. | B10: Корреспондентские и резервные счета в ЦБРУ | C10: =+Balance!D6 -> 119493320 | D10: =+Balance!E6 -> 21084460
A11: 4. | B11: Корр. счета, кредиты и другие требования к банкам | G11: 309855 | H11: 453228477
A12: 5. | B12: Рыночные ценные бумаги, чистые
A13: а) | B13: Ценные бумаги, выпущенные Правительством Республики Узбекистан и ЦБРУ | C13: 109174000
A14: б) | B14: Ценные бумаги, выпущенные правительствами и центральными банками стран, с низким уровня риска, а также другие требования к центральным банкам и правительствам этих стран
A15: в) | B15: Ценные бумаги, выпущенные банками стран, с низким уровнем риска
A16: г) | B16: Другие ценные бумаги | G16: 10402827
A17: 6. | B17: Кредиты и другие активы или их части, обеспеченные наличными деньгами, хранящимися на отдельном блокированном депозитном счете.
A18: 7. | B18: Все требования банка, деноминированные в местную валюту стран не входящих в группу стран с низким уровнем риска, к Центральным банкам и центральным правительствам этих стран
A19: 8. | B19: Активы, обеспеченные ценными бумагами выпущенными банками зарегистрированными в странах с низким уровнем риска
A20: 9. | B20: Требования банка к международным финансовым организациям, а также активы, гарантированные этими организациями
A21: 10. | B21: Активы или их части, обеспеченные залогом в виде ценных бумаг, оцененных по текущей рыночной стоимости и эмитированных международными финансовыми институтами
A22: 11. | B22: Кредиты и лизинги, чистые
A23: а) | B23: прямые требования к Правительству и Центральному банку Республики Узбекистан | C23: 0 | D23: 0
A24: б) | B24: Гарантированные кредиты международными кредитными организациями | C24: 0
A25: в) | B25: Активы или их части, обеспеченные ценными бумагами, которые оцененные по текущей рыночной стоимости и выпущенными или гарантированными Правительством Республики Узбекистан, Центральным банком Республики Узбекистан или Правительствами стран с низким уровнем риска. | D25: 0
A26: г) | B26: Кредиты на недвижимость обеспеченные приобретаемым или строящимся домом (квартирой) | F26: 66552554
A27: д) | B27: Реструктуризированные кредиты и кредиты в статусе "ненаращивания" | G27: 129827087
A28: е) | B28: Кредиты, по которым банк не имеет приоритетного права на залог | G28: 0
A29: ж) | B29: Пересмотренные или пролонгированные кредиты и лизинги более одного раза | H29: 0
A30: з) | B30: Кредиты, выданные населению для приобретения автомобилей | G30: 2152157 | H30: 91403487 | I30: 56603467 | J30: 16031679
A31: и) | B31: Кредиты, выданные юридическим лицам на покупку автомобиля | J31: 65055525
A32: к) | B32: Микрозаймы (все нецелевые кредиты) | G32: 4227795 | H32: 43981306 | I32: 32208912 | J32: 138898
A33: л) | B33: Все другие кредиты (кроме лизинга) | G33: 4105828351
A34: 12. | B34: Кредиты и лизинги в судебном разбирательстве, чистые | H34: 8560497 | K34: =+'Bank Assets Analysis'!S26 -> 8560497
A35: 13. | B35: Просроченные кредиты и лизинги, чистые | H35: 25522506 | K35: =+'Bank Assets Analysis'!C25+'Bank Assets Analysis'!C24 -> 25522506
A36: 14. | B36: Финансовый лизинг, чистые | G36: 4354759
A37: 15. | B37: Основные средств и другое собственное имущество банка
A38: а | B38: Основные средства, используемые в банковской деятельности (минус амортизация) | G38: 147419920
A39: б | B39: Другое банковское собственное имущество | G39: 0
A40: в | B40: Недвижимое имущество принятое на баланс банка в целях полного или частичного погащения задолженности | H40: 0
A41: г | B41: Недвижимое имущество банка, которым банк не пользуется более двух лет | H41: 0
A42: 16. | B42: Инвестиции в капитал неконсолидированных банковских и небанковских финансовых дочерних компаний и всех нефинансовых предприятий | C42: 0
A43: 17. | B43: Все другие инвестиции, чистые | G43: 6670221
A44: 18. | B44: Нематериальные активы, включая гудвилл | C44: =+'Bank Capital Calc'!C20 -> 1679916
A45: 19. | B45: Другие активы в судебном разбирательстве и не взысканные в установленном порядке | H45: 349952
A46: 20. | B46: Другие активы, чистые | G46: 194798726 | K46: =+Balance!C44 -> 5890272405
A47: 21. | B47: Общая сумма балансовых активов согласно Инструкции | C47: =SUM(C8:C46) -> 390284786 | D47: =SUM(D8:D46) -> 34358661 | E47: =SUM(E8:E46) -> 0 | F47: =SUM(F8:F46) -> 66552554 | G47: =SUM(G8:G46) -> 4605991698 | H47: =SUM(H8:H46) -> 623046225 | I47: =SUM(I8:I46) -> 88812379 | J47: =SUM(J8:J46) -> 81226102 | K47: =SUM(C47:J47) -> 5890272405 | L47: =+Balance!C44 -> 5890272405 | M47: =+K47-L47 -> 0
A48: 22. | B48: Общая сумма балансовых рисковых активов, по группам риска | D48: =D47*D4 -> 6871732.2 | E48: =E47*E4 -> 0 | F48: =F47*F4 -> 33276277 | G48: =G47*G4 -> 4605991698 | H48: =H47*H4 -> 9.3456934e+08 | I48: =I47*I4 -> 177624758 | J48: =J47*J4 -> 243678306
A49: 23. | B49: Общая сумма балансовых рисковых активов | J49: =SUM(D48:J48) -> 6.0020121e+09
A52: № | B52: Характеристики | D52: Фактор пересчета кредита | F52: 0 | G52: 0.2 | H52: 0.5 | I52: 1 | J52: Значение риска
F53: Риск | G53: Риск | H53: Риск | I53: Риск
B55: (A) | D55: (Б) | F55: (В) | G55: (Г) | H55: (Д) | I55: (Е) | J55: (Ж)
A56: Забалансовые Активы
A57: 1 | B57: Обязательства по выдаче кредита
A58: a | B58: Более одного года | D58: 0.5 | I58: 730696477 | J58: =(G58*0.1)+(H58*0.25)+(I58*0.5) -> 3.6534824e+08
A59: б | B59: Год и менее | D59: 0.2 | J59: =(G59*0.04)+(H59*0.1)+(I59*0.2) -> 0
A60: 2 | B60: Обязательства по приобретению ценных бумаг и других активов (включая активы, проданные в соответствии с соглашениями о выкупе) | D60: 1 | J60: =(G60*0.2)+(H60*0.5)+(I60*1) -> 0
A61: 3 | B61: Гарантии и поручительства | D61: 1 | I61: 114164587 | J61: =(G61*0.2)+(H61*0.5)+(I61*1) -> 114164587
A62: 4 | B62: Аккредитивы
A63: a | B63: Прямые кредитные заменители | D63: 1 | J63: =(G63*0.2)+(H63*0.5)+(I63*1) -> 0
A64: б | B64: Связанные со сделками | D64: 0.5 | J64: =(G64*0.1)+(H64*0.25)+(I64*0.5) -> 0
A65: в | B65: Связанные с торговлей (краткосрочные, самоликвидирующиеся, обеспеченные) | D65: 0.2 | I65: 11705135 | J65: =(G65*0.04)+(H65*0.1)+(I65*0.2) -> 2341027
A66: г | B66: Другие аккредитивы | D66: 1 | J66: =(G66*0.2)+(H66*0.5)+(I66*1) -> 0
A67: 5 | B67: Форврдные котракты, свопы, опционы и подобные обязательства
A68: a | B68: Контракты по процентной ставке
A69: а1 | B69: Со оставшимся сроком погашения до одного года | D69: 0.005 | J69: =(G69*0.001)+(H69*0.0025)+(I69*0.005) -> 0
A70: а2 | B70: Со оставшимся сроком погашения от одного года до двух лет | D70: 0.01 | J70: =(G70*0.002)+(H70*0.005)+(I70*0.01) -> 0
A71: а3 | B71: Со оставшимся сроком погашения от двух до трех лет | D71: 0.02 | J71: =(G71*0.004)+(H71*0.01)+(I71*0.02) -> 0
A72: б | B72: Валютные котракты и золото
A73: б1 | B73: С первоначальным сроком погашения до одного года | D73: 0.02 | J73: =(G73*0.004)+(H73*0.01)+(I73*0.02) -> 0
A74: б2 | B74: С первоначальным сроком погашения от одного года до двух лет | D74: 0.05 | J74: =(G74*0.01)+(H74*0.025)+(I74*0.05) -> 0
A75: б3 | B75: С первоначальным сроком погашения от двух до трех лет | D75: 0.08 | J75: =(G75*0.016)+(H75*0.04)+(I75*0.08) -> 0
A76: 6 | B76: Общая сумма забалансовых активов | F76: =SUM(F58:F75) -> 0 | G76: =SUM(G58:G75) -> 0 | H76: =SUM(H58:H75) -> 0 | I76: =SUM(I58:I75) -> 856566199 | K76: =+F76+G76+H76+I76 -> 856566199 | L76: =+Commitments!C4+Commitments!C7+Commitments!C10+Commitments!C19+Commitments!C20+Commitments!C21+Commitments!C22 -> 856566199 | M76: =+K76-L76 -> 0
A77: 7 | B77: Общая сумма забалансовых активов, взвешенных с учетом риска | J77: =SUM(J58:J75) -> 4.8185385e+08
A78: 8 | B78: Общая сумма активов, взвешенных с учетом риска | J78: =SUM(J77+J49) -> 6.483866e+09 | K78: =+J78*0.15 -> 9.7257989e+08
B80: Подпись Председателя правления:
B82: Подпись Главного Бухгалтера:

Sheet Calculation of Risk Weighte нац
A1: РАСЧЕТ АКТИВОВ ВЗВЕШЕННЫХ С УЧЕТОМ РИСКА В НАЦИОНАЛЬНОЙ ВАЛЮТЕ | I1: Таблица-6.1
B3: =Balance!B3 -> АКБ "Микрокредитбанк" | G3: =+Balance!C3 -> 43829 | J3: =+Balance!E3 -> тыс. сум
A4: № | B4: Характеристики | C4: 0 | D4: 0.2 | E4: 0.3 | F4: 0.5 | G4: 1 | H4: 1.5 | I4: 2 | J4: 3
C5: Риск | D5: Риск | E5: Риск | F5: Риск | G5: Риск | H5: Риск | I5: Риск | J5: Риск
B6: (A) | C6: (Б) | D6: (В) | E6: (Г) | F6: (Д) | G6: (Е) | H6: (Ж) | I6: (З) | J6: (И)
B7: Балансовые Активы
A8: 1. | B8: Касса (наличность и монеты) и Драгоценные металлы | C8: 60859707
A9: 2. | B9: Денежная наличность и другие платежные документы в пути | D9: 8945599
A10: 3. | B10: Корреспондентские и резервные счета в ЦБРУ | C10: =+Balance!D6 -> 119493320
A11: 4. | B11: Корр. счета, кредиты и другие требования к банкам | H11: 266889175
A12: 5. | B12: Рыночные ценные бумаги, чистые
A13: а) | B13: Ценные бумаги, выпущенные Правительством Республики Узбекистан и ЦБРУ | C13: 109174000
A14: б) | B14: Ценные бумаги, выпущенные правительствами и центральными банками стран, с низким уровня риска, а также другие требования к центральным банкам и правительствам этих стран
A15: в) | B15: Ценные бумаги, выпущенные банками стран, с низким уровнем риска
A16: г) | B16: Другие ценные бумаги | G16: 10402827
A17: 6. | B17: Кредиты и другие активы или их части, обеспеченные наличными деньгами, хранящимися на отдельном блокированном депозитном счете.
A18: 7. | B18: Все требования банка, деноминированные в местную валюту стран не входящих в группу стран с низким уровнем риска, к Центральным банкам и центральным правительствам этих стран
A19: 8. | B19: Активы, обеспеченные ценными бумагами выпущенными банками зарегистрированными в странах с низким уровнем риска
A20: 9. | B20: Требования банка к международным финансовым организациям, а также активы, гарантированные этими организациями
A21: 10. | B21: Активы или их части, обеспеченные залогом в виде ценных бумаг, оцененных по текущей рыночной стоимости и эмитированных международными финансовыми институтами
A22: 11. | B22: Кредиты и лизинги, чистые
A23: а) | B23: прямые требования к Правительству и Центральному банку Республики Узбекистан | C23: 0 | D23: 0
A24: б) | B24: Гарантированные кредиты международными кредитными организациями | C24: 0
A25: в) | B25: Активы или их части, обеспеченные ценными бумагами, которые оцененные по текущей рыночной стоимости и выпущенными или гарантированными Правительством Республики Узбекистан, Центральным банком Республики Узбекистан или Правительствами стран с низким уровнем риска. | D25: 0
A26: г) | B26: Кредиты на недвижимость обеспеченные приобретаемым или строящимся домом (квартирой) | F26: 66552554
A27: д) | B27: Реструктуризированные кредиты и кредиты в статусе "ненаращивания" | G27: 129827087
A28: е) | B28: Кредиты, по которым банк не имеет приоритетного права на залог
A29: ж) | B29: Пересмотренные или пролонгированные кредиты и лизинги более одного раза | H29: 0
A30: з) | B30: Кредиты, выданные населению для приобретения автомобилей | G30: 2152157 | H30: 91403487 | I30: 56603467 | J30: 16031679
A31: и) | B31: Кредиты, выданные юридическим лицам на покупку автомобиля | J31: 65055525
A32: к) | B32: Микрозаймы (все нецелевые кредиты) | G32: 4227795 | H32: 43981306 | I32: 32208912 | J32: 138898
A33: л) | B33: Все другие кредиты (кроме лизинга) | G33: 2550363615
A34: 12. | B34: Кредиты и лизинги в судебном разбирательстве, чистые | H34: 8560497 | K34: =+'Bank Assets Analysis (нац)'!K25 -> 8560497
A35: 13. | B35: Просроченные кредиты и лизинги, чистые | H35: 23225577 | K35: =+'Bank Assets Analysis (нац)'!C23+'Bank Assets Analysis (нац)'!C24 -> 23225577
A36: 14. | B36: Финансовый лизинг, чистые | G36: 2107924
A37: 15. | B37: Основные средств и другое собственное имущество банка
A38: а | B38: Основные средства, используемые в банковской деятельности (минус амортизация) | G38: 147419920
A39: б | B39: Другое банковское собственное имущество | G39: 0
A40: в | B40: Недвижимое имущество принятое на баланс банка в целях полного или частичного погащения задолженности | H40: 0
A41: г | B41: Недвижимое имущество банка, которым банк не пользуется более двух лет | H41: 0
A42: 16. | B42: Инвестиции в капитал неконсолидированных банковских и небанковских финансовых дочерних компаний и всех нефинансовых предприятий
A43: 17. | B43: Все другие инвестиции, чистые | G43: 6670221
A44: 18. | B44: Нематериальные активы, включая гудвилл | C44: 1679916
A45: 19. | B45: Другие активы в судебном разбирательстве и не взысканные в установленном порядке | H45: 349952
A46: 20. | B46: Другие активы, чистые | G46: 114806848 | K46: =+Balance!C44 -> 5890272405
A47: 21. | B47: Общая сумма балансовых активов согласно Инструкции | C47: =SUM(C8:C46) -> 291206943 | D47: =SUM(D8:D46) -> 8945599 | E47: =SUM(E8:E46) -> 0 | F47: =SUM(F8:F46) -> 66552554 | G47: =SUM(G8:G46) -> 2967978394 | H47: =SUM(H8:H46) -> 434409994 | I47: =SUM(I8:I46) -> 88812379 | J47: =SUM(J8:J46) -> 81226102 | K47: =SUM(C47:J47) -> 3939131965 | L47: =+Balance!D44 -> 3939131965 | M47: =+K47-L47 -> 0
A48: 22. | B48: Общая сумма балансовых рисковых активов, по группам риска | D48: =D47*D4 -> 1789119.8 | E48: =E47*E4 -> 0 | F48: =F47*F4 -> 33276277 | G48: =G47*G4 -> 2967978394 | H48: =H47*H4 -> 651614991 | I48: =I47*I4 -> 177624758 | J48: =J47*J4 -> 243678306
A49: 23. | B49: Общая сумма балансовых рисковых активов | J49: =SUM(D48:J48) -> 4.0759618e+09
A52: № | B52: Характеристики | D52: Фактор пересчета кредита | F52: 0 | G52: 0.2 | H52: 0.5 | I52: 1 | J52: Значение риска
F53: Риск | G53: Риск | H53: Риск | I53: Риск
B55: (A) | D55: (Б) | F55: (В) | G55: (Г) | H55: (Д) | I55: (Е) | J55: (Ж)
A56: Забалансовые Активы
A57: 1 | B57: Обязательства по выдаче кредита
A58: a | B58: Более одного года | D58: 0.5 | I58: 202970378 | J58: =(G58*0.1)+(H58*0.25)+(I58*0.5) -> 101485189
A59: б | B59: Год и менее | D59: 0.2 | J59: =(G59*0.04)+(H59*0.1)+(I59*0.2) -> 0
A60: 2 | B60: Обязательства по приобретению ценных бумаг и других активов (включая активы, проданные в соответствии с соглашениями о выкупе) | D60: 1 | J60: =(G60*0.2)+(H60*0.5)+(I60*1) -> 0
A61: 3 | B61: Гарантии и поручительства | D61: 1 | I61: 1364025 | J61: =(G61*0.2)+(H61*0.5)+(I61*1) -> 1364025
A62: 4 | B62: Аккредитивы
A63: a | B63: Прямые кредитные заменители | D63: 1 | J63: =(G63*0.2)+(H63*0.5)+(I63*1) -> 0
A64: б | B64: Связанные со сделками | D64: 0.5 | J64: =(G64*0.1)+(H64*0.25)+(I64*0.5) -> 0
A65: в | B65: Связанные с торговлей (краткосрочные, самоликвидирующиеся, обеспеченные) | D65: 0.2 | J65: =(G65*0.04)+(H65*0.1)+(I65*0.2) -> 0
A66: г | B66: Другие аккредитивы | D66: 1 | J66: =(G66*0.2)+(H66*0.5)+(I66*1) -> 0
A67: 5 | B67: Форврдные котракты, свопы, опционы и подобные обязательства
A68: a | B68: Контракты по процентной ставке
A69: а1 | B69: Со оставшимся сроком погашения до одного года | D69: 0.005 | J69: =(G69*0.001)+(H69*0.0025)+(I69*0.005) -> 0
A70: а2 | B70: Со оставшимся сроком погашения от одного года до двух лет | D70: 0.01 | J70: =(G70*0.002)+(H70*0.005)+(I70*0.01) -> 0
A71: а3 | B71: Со оставшимся сроком погашения от двух до трех лет | D71: 0.02 | J71: =(G71*0.004)+(H71*0.01)+(I71*0.02) -> 0
A72: б | B72: Валютные котракты и золото
A73: б1 | B73: С первоначальным сроком погашения до одного года | D73: 0.02 | J73: =(G73*0.004)+(H73*0.01)+(I73*0.02) -> 0
A74: б2 | B74: С первоначальным сроком погашения от одного года до двух лет | D74: 0.05 | J74: =(G74*0.01)+(H74*0.025)+(I74*0.05) -> 0
A75: б3 | B75: С первоначальным сроком погашения от двух до трех лет | D75: 0.08 | J75: =(G75*0.016)+(H75*0.04)+(I75*0.08) -> 0
A76: 6 | B76: Общая сумма забалансовых активов | F76: =SUM(F58:F75) -> 0 | G76: =SUM(G58:G75) -> 0 | H76: =SUM(H58:H75) -> 0 | I76: =SUM(I58:I75) -> 204334403 | K76: =+F76+G76+H76+I76 -> 204334403 | L76: =+Commitments!C4+Commitments!C7+Commitments!C10+Commitments!C19+Commitments!C20+Commitments!C21+Commitments!C22 -> 856566199 | M76: =+K76-L76 -> -652231796
A77: 7 | B77: Общая сумма забалансовых активов, взвешенных с учетом риска | J77: =SUM(J58:J75) -> 102849214
A78: 8 | B78: Общая сумма активов, взвешенных с учетом риска | J78: =SUM(J77+J49) -> 4.1788111e+09 | K78: =+J78*0.15 -> 6.2682166e+08
B80: Подпись Председателя правления:
B82: Подпись Главного Бухгалтера:

Sheet Calculation of Risk Weighte ин
A1: РАСЧЕТ АКТИВОВ ВЗВЕШЕННЫХ С УЧЕТОМ РИСКА В ИНОСТРАННОЙ ВАЛЮТЕ | I1: Таблица-6.2
B3: =Balance!B3 -> АКБ "Микрокредитбанк" | G3: =+Balance!C3 -> 43829 | J3: =+Balance!E3 -> тыс. сум
A4: № | B4: Характеристики | C4: 0 | D4: 0.2 | E4: 0.3 | F4: 0.5 | G4: 1 | H4: 1.5 | I4: 2 | J4: 3
C5: Риск | D5: Риск | E5: Риск | F5: Риск | G5: Риск | H5: Риск | I5: Риск | J5: Риск
B6: (A) | C6: (Б) | D6: (В) | E6: (Г) | F6: (Д) | G6: (Е) | H6: (Ж) | I6: (З) | J6: (И)
B7: Балансовые Активы
A8: 1. | B8: Касса (наличность и монеты) и Драгоценные металлы | C8: =+'Calculation of Risk Weighted As'!C8-'Calculation of Risk Weighte нац'!C8 -> 99077843
A9: 2. | B9: Денежная наличность и другие платежные документы в пути | D9: =+'Calculation of Risk Weighted As'!D9-'Calculation of Risk Weighte нац'!D9 -> 4328602
A10: 3. | B10: Корреспондентские и резервные счета в ЦБРУ | D10: =+Balance!E6 -> 21084460
A11: 4. | B11: Корр. счета, кредиты и другие требования к банкам | D11: =+'Calculation of Risk Weighted As'!D11-'Calculation of Risk Weighte нац'!D11 -> 0 | E11: =+'Calculation of Risk Weighted As'!E11-'Calculation of Risk Weighte нац'!E11 -> 0 | F11: =+'Calculation of Risk Weighted As'!F11-'Calculation of Risk Weighte нац'!F11 -> 0 | G11: =+'Calculation of Risk Weighted As'!G11-'Calculation of Risk Weighte нац'!G11 -> 309855 | H11: =+'Calculation of Risk Weighted As'!H11-'Calculation of Risk Weighte нац'!H11 -> 186339302
A12: 5. | B12: Рыночные ценные бумаги, чистые
A13: а) | B13: Ценные бумаги, выпущенные Правительством Республики Узбекистан и ЦБРУ | C13: =+'Calculation of Risk Weighted As'!C13-'Calculation of Risk Weighte нац'!C13 -> 0
A14: б) | B14: Ценные бумаги, выпущенные правительствами и центральными банками стран, с низким уровня риска, а также другие требования к центральным банкам и правительствам этих стран | C14: =+'Calculation of Risk Weighted As'!C14-'Calculation of Risk Weighte нац'!C14 -> 0
A15: в) | B15: Ценные бумаги, выпущенные банками стран, с низким уровнем риска | D15: =+'Calculation of Risk Weighted As'!D15-'Calculation of Risk Weighte нац'!D15 -> 0 | F15: =+'Calculation of Risk Weighted As'!F15-'Calculation of Risk Weighte нац'!F15 -> 0
A16: г) | B16: Другие ценные бумаги | C16: =+'Calculation of Risk Weighted As'!C16-'Calculation of Risk Weighte нац'!C16 -> 0 | G16: =+'Calculation of Risk Weighted As'!G16-'Calculation of Risk Weighte нац'!G16 -> 0
A17: 6. | B17: Кредиты и другие активы или их части, обеспеченные наличными деньгами, хранящимися на отдельном блокированном депозитном счете. | C17: =+'Calculation of Risk Weighted As'!C17-'Calculation of Risk Weighte нац'!C17 -> 0
A18: 7. | B18: Все требования банка, деноминированные в местную валюту стран не входящих в группу стран с низким уровнем риска, к Центральным банкам и центральным правительствам этих стран | D18: =+'Calculation of Risk Weighted As'!D18-'Calculation of Risk Weighte нац'!D18 -> 0
A19: 8. | B19: Активы, обеспеченные ценными бумагами выпущенными банками зарегистрированными в странах с низким уровнем риска | D19: =+'Calculation of Risk Weighted As'!D19-'Calculation of Risk Weighte нац'!D19 -> 0 | F19: =+'Calculation of Risk Weighted As'!F19-'Calculation of Risk Weighte нац'!F19 -> 0
A20: 9. | B20: Требования банка к международным финансовым организациям, а также активы, гарантированные этими организациями | C20: =+'Calculation of Risk Weighted As'!C20-'Calculation of Risk Weighte нац'!C20 -> 0
A21: 10. | B21: Активы или их части, обеспеченные залогом в виде ценных бумаг, оцененных по текущей рыночной стоимости и эмитированных международными финансовыми институтами | D21: =+'Calculation of Risk Weighted As'!D21-'Calculation of Risk Weighte нац'!D21 -> 0
A22: 11. | B22: Кредиты и лизинги, чистые
A23: а) | B23: прямые требования к Правительству и Центральному банку Республики Узбекистан | C23: =+'Calculation of Risk Weighted As'!C23-'Calculation of Risk Weighte нац'!C23 -> 0 | D23: =+'Calculation of Risk Weighted As'!D23-'Calculation of Risk Weighte нац'!D23 -> 0
A24: б) | B24: Гарантированные кредиты международными кредитными организациями | C24: =+'Calculation of Risk Weighted As'!C24-'Calculation of Risk Weighte нац'!C24 -> 0
A25: в) | B25: Активы или их части, обеспеченные ценными бумагами, которые оцененные по текущей рыночной стоимости и выпущенными или гарантированными Правительством Республики Узбекистан, Центральным банком Республики Узбекистан или Правительствами стран с низким уровнем риска. | D25: =+'Calculation of Risk Weighted As'!D25-'Calculation of Risk Weighte нац'!D25 -> 0
A26: г) | B26: Кредиты на недвижимость обеспеченные приобретаемым или строящимся домом (квартирой) | F26: =+'Calculation of Risk Weighted As'!F26-'Calculation of Risk Weighte нац'!F26 -> 0
A27: д) | B27: Реструктуризированные кредиты и кредиты в статусе "ненаращивания" | G27: =+'Calculation of Risk Weighted As'!G27-'Calculation of Risk Weighte нац'!G27 -> 0
A28: е) | B28: Кредиты, по которым банк не имеет приоритетного права на залог | G28: =+'Calculation of Risk Weighted As'!G28-'Calculation of Risk Weighte нац'!G28 -> 0
A29: ж) | B29: Пересмотренные или пролонгированные кредиты и лизинги более одного раза | H29: =+'Calculation of Risk Weighted As'!H29-'Calculation of Risk Weighte нац'!H29 -> 0
A30: з) | B30: Кредиты, выданные населению для приобретения автомобилей | G30: =+'Calculation of Risk Weighted As'!G30-'Calculation of Risk Weighte нац'!G30 -> 0 | H30: =+'Calculation of Risk Weighted As'!H30-'Calculation of Risk Weighte нац'!H30 -> 0 | I30: =+'Calculation of Risk Weighted As'!I30-'Calculation of Risk Weighte нац'!I30 -> 0 | J30: =+'Calculation of Risk Weighted As'!J30-'Calculation of Risk Weighte нац'!J30 -> 0
A31: и) | B31: Кредиты, выданные юридическим лицам на покупку автомобиля | J31: =+'Calculation of Risk Weighted As'!J31-'Calculation of Risk Weighte нац'!J31 -> 0
A32: к) | B32: Микрозаймы (все нецелевые кредиты) | G32: =+'Calculation of Risk Weighted As'!G32-'Calculation of Risk Weighte нац'!G32 -> 0 | H32: =+'Calculation of Risk Weighted As'!H32-'Calculation of Risk Weighte нац'!H32 -> 0 | I32: =+'Calculation of Risk Weighted As'!I32-'Calculation of Risk Weighte нац'!I32 -> 0 | J32: =+'Calculation of Risk Weighted As'!J32-'Calculation of Risk Weighte нац'!J32 -> 0
A33: л) | B33: Все другие кредиты (кроме лизинга) | G33: =+'Calculation of Risk Weighted As'!G33-'Calculation of Risk Weighte нац'!G33 -> 1555464736
A34: 12. | B34: Кредиты и лизинги в судебном разбирательстве, чистые | H34: =+'Calculation of Risk Weighted As'!H34-'Calculation of Risk Weighte нац'!H34 -> 0 | K34: =+'Bank Assets Analysis'!U26 -> 0
A35: 13. | B35: Просроченные кредиты и лизинги, чистые | H35: =+'Calculation of Risk Weighted As'!H35-'Calculation of Risk Weighte нац'!H35 -> 2296929 | K35: =+'Bank Assets Analysis'!D24+'Bank Assets Analysis'!D25 -> 2296929
A36: 14. | B36: Финансовый лизинг, чистые | G36: =+'Calculation of Risk Weighted As'!G36-'Calculation of Risk Weighte нац'!G36 -> 2246835
A37: 15. | B37: Основные средств и другое собственное имущество банка
A38: а | B38: Основные средства, используемые в банковской деятельности (минус амортизация) | G38: =+'Calculation of Risk Weighted As'!G38-'Calculation of Risk Weighte нац'!G38 -> 0
A39: б | B39: Другое банковское собственное имущество | G39: =+'Calculation of Risk Weighted As'!G39-'Calculation of Risk Weighte нац'!G39 -> 0
A40: в | B40: Недвижимое имущество принятое на баланс банка в целях полного или частичного погащения задолженности | H40: =+'Calculation of Risk Weighted As'!H40-'Calculation of Risk Weighte нац'!H40 -> 0
A41: г | B41: Недвижимое имущество банка, которым банк не пользуется более двух лет | H41: =+'Calculation of Risk Weighted As'!H41-'Calculation of Risk Weighte нац'!H41 -> 0
A42: 16. | B42: Инвестиции в капитал неконсолидированных банковских и небанковских финансовых дочерних компаний и всех нефинансовых предприятий | C42: =+'Calculation of Risk Weighted As'!C42-'Calculation of Risk Weighte нац'!C42 -> 0
A43: 17. | B43: Все другие инвестиции, чистые | G43: =+'Calculation of Risk Weighted As'!G43-'Calculation of Risk Weighte нац'!G43 -> 0
A44: 18. | B44: Нематериальные активы, включая гудвилл | C44: =+'Calculation of Risk Weighted As'!C44-'Calculation of Risk Weighte нац'!C44 -> 0
A45: 19. | B45: Другие активы в судебном разбирательстве и не взысканные в установленном порядке | H45: =+'Calculation of Risk Weighted As'!H45-'Calculation of Risk Weighte нац'!H45 -> 0
A46: 20. | B46: Другие активы, чистые | C46: =+'Calculation of Risk Weighted As'!C46-'Calculation of Risk Weighte нац'!C46 -> 0 | G46: =+'Calculation of Risk Weighted As'!G46-'Calculation of Risk Weighte нац'!G46 -> 79991878 | K46: =+Balance!C44 -> 5890272405
A47: 21. | B47: Общая сумма балансовых активов согласно Инструкции | C47: =SUM(C8:C46) -> 99077843 | D47: =SUM(D8:D46) -> 25413062 | E47: =SUM(E8:E46) -> 0 | F47: =SUM(F8:F46) -> 0 | G47: =SUM(G8:G46) -> 1638013304 | H47: =SUM(H8:H46) -> 188636231 | I47: =SUM(I8:I46) -> 0 | J47: =SUM(J8:J46) -> 0 | K47: =SUM(C47:J47) -> 1951140440 | L47: =+Balance!E44 -> 1951140440 | M47: =+K47-L47 -> 0
A48: 22. | B48: Общая сумма балансовых рисковых активов, по группам риска | D48: =D47*D4 -> 5082612.4 | E48: =E47*E4 -> 0 | F48: =F47*F4 -> 0 | G48: =G47*G4 -> 1638013304 | H48: =H47*H4 -> 2.8295435e+08 | I48: =I47*I4 -> 0 | J48: =J47*J4 -> 0
A49: 23. | B49: Общая сумма балансовых рисковых активов | J49: =SUM(D48:J48) -> 1.9260503e+09
A52: № | B52: Характеристики | D52: Фактор пересчета кредита | F52: 0 | G52: 0.2 | H52: 0.5 | I52: 1 | J52: Значение риска
F53: Риск | G53: Риск | H53: Риск | I53: Риск
B55: (A) | D55: (Б) | F55: (В) | G55: (Г) | H55: (Д) | I55: (Е) | J55: (Ж)
A56: Забалансовые Активы
A57: 1 | B57: Обязательства по выдаче кредита
A58: a | B58: Более одного года | D58: 0.5 | F58: =+'Calculation of Risk Weighted As'!F58-'Calculation of Risk Weighte нац'!F58 -> 0 | G58: =+'Calculation of Risk Weighted As'!G58-'Calculation of Risk Weighte нац'!G58 -> 0 | H58: =+'Calculation of Risk Weighted As'!H58-'Calculation of Risk Weighte нац'!H58 -> 0 | I58: =+'Calculation of Risk Weighted As'!I58-'Calculation of Risk Weighte нац'!I58 -> 527726099 | J58: =(G58*0.1)+(H58*0.25)+(I58*0.5) -> 2.6386305e+08
A59: б | B59: Год и менее | D59: 0.2 | F59: =+'Calculation of Risk Weighted As'!F59-'Calculation of Risk Weighte нац'!F59 -> 0 | G59: =+'Calculation of Risk Weighted As'!G59-'Calculation of Risk Weighte нац'!G59 -> 0 | H59: =+'Calculation of Risk Weighted As'!H59-'Calculation of Risk Weighte нац'!H59 -> 0 | I59: =+'Calculation of Risk Weighted As'!I59-'Calculation of Risk Weighte нац'!I59 -> 0 | J59: =(G59*0.04)+(H59*0.1)+(I59*0.2) -> 0
A60: 2 | B60: Обязательства по приобретению ценных бумаг и других активов (включая активы, проданные в соответствии с соглашениями о выкупе) | D60: 1 | F60: =+'Calculation of Risk Weighted As'!F60-'Calculation of Risk Weighte нац'!F60 -> 0 | G60: =+'Calculation of Risk Weighted As'!G60-'Calculation of Risk Weighte нац'!G60 -> 0 | H60: =+'Calculation of Risk Weighted As'!H60-'Calculation of Risk Weighte нац'!H60 -> 0 | I60: =+'Calculation of Risk Weighted As'!I60-'Calculation of Risk Weighte нац'!I60 -> 0 | J60: =(G60*0.2)+(H60*0.5)+(I60*1) -> 0
A61: 3 | B61: Гарантии и поручительства | D61: 1 | F61: =+'Calculation of Risk Weighted As'!F61-'Calculation of Risk Weighte нац'!F61 -> 0 | I61: =+'Calculation of Risk Weighted As'!I61-'Calculation of Risk Weighte нац'!I61 -> 112800562 | J61: =(G61*0.2)+(H61*0.5)+(I61*1) -> 112800562
A62: 4 | B62: Аккредитивы
A63: a | B63: Прямые кредитные заменители | D63: 1 | F63: =+'Calculation of Risk Weighted As'!F63-'Calculation of Risk Weighte нац'!F63 -> 0 | G63: =+'Calculation of Risk Weighted As'!G63-'Calculation of Risk Weighte нац'!G63 -> 0 | H63: =+'Calculation of Risk Weighted As'!H63-'Calculation of Risk Weighte нац'!H63 -> 0 | I63: =+'Calculation of Risk Weighted As'!I63-'Calculation of Risk Weighte нац'!I63 -> 0 | J63: =(G63*0.2)+(H63*0.5)+(I63*1) -> 0
A64: б | B64: Связанные со сделками | D64: 0.5 | F64: =+'Calculation of Risk Weighted As'!F64-'Calculation of Risk Weighte нац'!F64 -> 0 | G64: =+'Calculation of Risk Weighted As'!G64-'Calculation of Risk Weighte нац'!G64 -> 0 | H64: =+'Calculation of Risk Weighted As'!H64-'Calculation of Risk Weighte нац'!H64 -> 0 | I64: =+'Calculation of Risk Weighted As'!I64-'Calculation of Risk Weighte нац'!I64 -> 0 | J64: =(G64*0.1)+(H64*0.25)+(I64*0.5) -> 0
A65: в | B65: Связанные с торговлей (краткосрочные, самоликвидирующиеся, обеспеченные) | D65: 0.2 | F65: =+'Calculation of Risk Weighted As'!F65-'Calculation of Risk Weighte нац'!F65 -> 0 | G65: =+'Calculation of Risk Weighted As'!G65-'Calculation of Risk Weighte нац'!G65 -> 0 | H65: =+'Calculation of Risk Weighted As'!H65-'Calculation of Risk Weighte нац'!H65 -> 0 | I65: =+'Calculation of Risk Weighted As'!I65-'Calculation of Risk Weighte нац'!I65 -> 11705135 | J65: =(G65*0.04)+(H65*0.1)+(I65*0.2) -> 2341027
A66: г | B66: Другие аккредитивы | D66: 1 | F66: =+'Calculation of Risk Weighted As'!F66-'Calculation of Risk Weighte нац'!F66 -> 0 | I66: =+'Calculation of Risk Weighted As'!I66-'Calculation of Risk Weighte нац'!I66 -> 0 | J66: =(G66*0.2)+(H66*0.5)+(I66*1) -> 0
A67: 5 | B67: Форврдные котракты, свопы, опционы и подобные обязательства
A68: a | B68: Контракты по процентной ставке
A69: а1 | B69: Со оставшимся сроком погашения до одного года | D69: 0.005 | F69: =+'Calculation of Risk Weighted As'!F69-'Calculation of Risk Weighte нац'!F69 -> 0 | G69: =+'Calculation of Risk Weighted As'!G69-'Calculation of Risk Weighte нац'!G69 -> 0 | H69: =+'Calculation of Risk Weighted As'!H69-'Calculation of Risk Weighte нац'!H69 -> 0 | I69: =+'Calculation of Risk Weighted As'!I69-'Calculation of Risk Weighte нац'!I69 -> 0 | J69: =(G69*0.001)+(H69*0.0025)+(I69*0.005) -> 0
A70: а2 | B70: Со оставшимся сроком погашения от одного года до двух лет | D70: 0.01 | F70: =+'Calculation of Risk Weighted As'!F70-'Calculation of Risk Weighte нац'!F70 -> 0 | G70: =+'Calculation of Risk Weighted As'!G70-'Calculation of Risk Weighte нац'!G70 -> 0 | H70: =+'Calculation of Risk Weighted As'!H70-'Calculation of Risk Weighte нац'!H70 -> 0 | I70: =+'Calculation of Risk Weighted As'!I70-'Calculation of Risk Weighte нац'!I70 -> 0 | J70: =(G70*0.002)+(H70*0.005)+(I70*0.01) -> 0
A71: а3 | B71: Со оставшимся сроком погашения от двух до трех лет | D71: 0.02 | F71: =+'Calculation of Risk Weighted As'!F71-'Calculation of Risk Weighte нац'!F71 -> 0 | G71: =+'Calculation of Risk Weighted As'!G71-'Calculation of Risk Weighte нац'!G71 -> 0 | H71: =+'Calculation of Risk Weighted As'!H71-'Calculation of Risk Weighte нац'!H71 -> 0 | I71: =+'Calculation of Risk Weighted As'!I71-'Calculation of Risk Weighte нац'!I71 -> 0 | J71: =(G71*0.004)+(H71*0.01)+(I71*0.02) -> 0
A72: б | B72: Валютные котракты и золото
A73: б1 | B73: С первоначальным сроком погашения до одного года | D73: 0.02 | F73: =+'Calculation of Risk Weighted As'!F73-'Calculation of Risk Weighte нац'!F73 -> 0 | G73: =+'Calculation of Risk Weighted As'!G73-'Calculation of Risk Weighte нац'!G73 -> 0 | H73: =+'Calculation of Risk Weighted As'!H73-'Calculation of Risk Weighte нац'!H73 -> 0 | I73: =+'Calculation of Risk Weighted As'!I73-'Calculation of Risk Weighte нац'!I73 -> 0 | J73: =(G73*0.004)+(H73*0.01)+(I73*0.02) -> 0
A74: б2 | B74: С первоначальным сроком погашения от одного года до двух лет | D74: 0.05 | F74: =+'Calculation of Risk Weighted As'!F74-'Calculation of Risk Weighte нац'!F74 -> 0 | G74: =+'Calculation of Risk Weighted As'!G74-'Calculation of Risk Weighte нац'!G74 -> 0 | H74: =+'Calculation of Risk Weighted As'!H74-'Calculation of Risk Weighte нац'!H74 -> 0 | I74: =+'Calculation of Risk Weighted As'!I74-'Calculation of Risk Weighte нац'!I74 -> 0 | J74: =(G74*0.01)+(H74*0.025)+(I74*0.05) -> 0
A75: б3 | B75: С первоначальным сроком погашения от двух до трех лет | D75: 0.08 | F75: =+'Calculation of Risk Weighted As'!F75-'Calculation of Risk Weighte нац'!F75 -> 0 | G75: =+'Calculation of Risk Weighted As'!G75-'Calculation of Risk Weighte нац'!G75 -> 0 | H75: =+'Calculation of Risk Weighted As'!H75-'Calculation of Risk Weighte нац'!H75 -> 0 | I75: =+'Calculation of Risk Weighted As'!I75-'Calculation of Risk Weighte нац'!I75 -> 0 | J75: =(G75*0.016)+(H75*0.04)+(I75*0.08) -> 0
A76: 6 | B76: Общая сумма забалансовых активов | F76: =SUM(F58:F75) -> 0 | G76: =SUM(G58:G75) -> 0 | H76: =SUM(H58:H75) -> 0 | I76: =SUM(I58:I75) -> 652231796 | K76: =+F76+G76+H76+I76 -> 652231796 | L76: =+Commitments!C4+Commitments!C7+Commitments!C10+Commitments!C19+Commitments!C20+Commitments!C21+Commitments!C22 -> 856566199 | M76: =+K76-L76 -> -204334403
A77: 7 | B77: Общая сумма забалансовых активов, взвешенных с учетом риска | J77: =SUM(J58:J75) -> 3.7900464e+08
A78: 8 | B78: Общая сумма активов, взвешенных с учетом риска | J78: =SUM(J77+J49) -> 2.3050549e+09 | K78: =+J78*0.15 -> 3.4575824e+08
B80: Подпись Председателя правления:
B82: Подпись Главного Бухгалтера:

Sheet Calculation of Risk
A1: РАСЧЕТ ПО ОПЕРАЦИОННЫМ И РЫНОЧНЫМ РИСКАМ | I1: Достаточность капитала - К1 | J1: Коэффициент достаточности капитала I уровня K2 | K1: Доля основного капитала I уровня к регулятивному капиталу | L1: Коэффициент нормы покрытия ликвидности | M1: Норма чистого стабильного финансирования (НЧСФ)
C2: Таблица-6А | H2: 2015 | I2: 10 | J2: 7.5 | K2: 6 | L2: 80
B3: =+Balance!B3 -> АКБ "Микрокредитбанк" | C3: =+Balance!C3 -> 43829 | H3: 2016 | I3: 11.5 | J3: 8.5 | K3: 7 | L3: 80
A4: № | B4: Наименование показателя | C4: в тыс. сум | H4: 2017 | I4: 12.5 | J4: 9.5 | K4: 7.5 | L4: 90
A5: 1. | B5: =+"Валовый доход банка за "&(E$9-3)&" год" -> Валовый доход банка за 2016 год | C5: =+C6+C8-C7-C9 -> 151405362 | H5: 2018 | I5: 12.5 | J5: 9.5 | K5: 7.5 | L5: 100 | M5: 100
A6: а. | B6: процентные доходы | C6: 204104096 | H6: 2019 | I6: 13 | J6: 10 | K6: 8 | L6: 100 | M6: 100
A7: б. | B7: процентные расходы | C7: 126300057 | E7: =RIGHT(Balance!B2,4) -> 2019
A8: в. | B8: беспроцентные доходы | C8: 94287758 | G8: =VLOOKUP(E9,H2:M6,2,0) -> 13
A9: г. | B9: беспроцентные расходы | C9: 20686435 | E9: =IF(E7>H6,H6,E7) -> 2019
A10: 2. | B10: =+"Валовый доход банка за "&(E$9-2)&" год" -> Валовый доход банка за 2017 год | C10: =+C11+C13-C12-C14 -> 215368224 | G10: =VLOOKUP($E$9,$H$2:$M$6,4,0) -> 8
A11: а. | B11: процентные доходы | C11: 222901466 | G11: =VLOOKUP($E$9,$H$2:$J$6,3,0) -> 10
A12: б. | B12: процентные расходы | C12: 146139315 | G12: =VLOOKUP($E$9,H2:M6,5,0) -> 100
A13: в. | B13: беспроцентные доходы | C13: 164180943 | G13: =VLOOKUP(E9,H2:M6,6,0) -> 100
A14: г. | B14: беспроцентные расходы | C14: 25574870
A15: 3. | B15: =+"Валовый доход банка за "&(E$9-1)&" год" -> Валовый доход банка за 2018 год | C15: =+C16+C18-C17-C19 -> 334481566
A16: а. | B16: процентные доходы | C16: 446360945
A17: б. | B17: процентные расходы | C17: 228795878
A18: в. | B18: беспроцентные доходы | C18: 158773389
A19: г. | B19: беспроцентные расходы | C19: 41856890
A20: 4. | B20: Средний валовый доход банка (за последние три года) | C20: =(C5+C10+C15)/3 -> 2.3375172e+08
A21: 5. | B21: Сумма операционных рисков | C21: =+(100/C28)*C20*15% -> 269713520
A23: 6. | B23: Счета валютной позиции (счет 17101 (сумавая часть)) | C23: 70081723
A24: 7. | B24: Продажа на условиях Своп и Форвард (счет 92709, 92732) | C24: 0
A25: 8. | B25: Покупка на условиях Своп и Форвард (счет 92716, 92736) | C25: 0
A26: 9. | B26: Открытая валютная позиция, всего | C26: =ABS(C23+(C24-C25)) -> 70081723 | D26: =+C26*0.1 -> 7008172.3
A27: 10. | B27: Сумма рыночных рисков | C27: =+(100/C28)*(C26*10%) -> 53909018
A28: 11. | B28: Действуюший минимальное требование к достаточности капитала | C28: =VLOOKUP($E$9,$H$2:$I$6,2,0) -> 13
A30: Подпись Председателя правления:
A32: Подпись Главного Бухгалтера:

Sheet Changes in Equity
B1: ИЗМЕНЕНИЯ В СОБСТВЕННОМ КАПИТАЛЕ | C1: Таблица-7
B3: =Balance!B3 -> АКБ "Микрокредитбанк" | C3: =+Balance!C3 -> 43829
A4: № | B4: Категория | C4: в тыс. сум
A5: 1. | B5: Итого собственного капитала первоначально определенного за прошлый год | C5: 665013964
A6: 2. | B6: Исправления в собственном капитале не показанные в отчете за прошлый год, чистые
A7: 3. | B7: Исправленный баланс на конец прошлого календарного года (сумма строк 1 и 2) | C7: =SUM(C5:C6) -> 665013964
A8: 4. | B8: Чистый прибыль (убыток) по состоянию на дату от начала года | C8: =+'Income '!C76 -> 6838822 | I8: =+Balance!C75 -> 6838822
A9: 5. | B9: Продажа, Обмен, Приобретение или выкуп акций, за текущий год (чистая выручка) | C9: 947543197
A10: 6. | B10: Изменения в оценочной стоимости прироста над первонач. стоимостью, за текущий год (чистые) | C10: 5377552
A11: 7. | B11: МИНУС: Денежные дивиденды объявленные по привилегированным акциям | C11: 0
A12: 8. | B12: МИНУС: Денежные дивиденды объявленные по обыкновенным акциям | C12: 0
A13: 9. | B13: Другие статьи влияющие на собственный капитал за текущий год (чистые) | C13: 331940
A14: 10. | B14: Итого собственного капитала на конец текущего периода (сумма строк с 3 по 10) | C14: =C7+SUM(C8:C10)-SUM(C11:C12)+C13 -> 1625105475 | D14: =+Balance!C76 -> 1625105475 | I14: =+Balance!C76 -> 1625105475
B16: Подпись Председателя правления:
B18: Подпись Главного Бухгалтера:

Sheet Loans Receivable
A1: КРЕДИТЫ И ЛИЗИНГИ К ПОЛУЧЕНИЮ ПО ОТРАСЛЯМ ЭКОНОМИКИ, ТИПАМ КЛИЕНТОВ И ПО ТИПУ ОБЕСПЕЧЕНИЯ | W1: Таблица-8
B3: =Balance!B3 -> АКБ "Микрокредитбанк" | T3: =+Balance!C3 -> 43829 | X3: =+Balance!E3 -> тыс. сум
A4: № | B4: Отрасль экономики | C4: Сумма кредита | D4: в национальной валюте | F4: в иностранной валюте (в экв. в сумах) | H4: из них | J4: из них
D5: Сумма | E5: средне-взвешенные процентные ставки | F5: Сумма | G5: средне-взвешенные процентные ставки | H5: Начисляемые кредиты | I5: Кредиты переведённые в статус ненаращивания процентов | J5: Депозиты | K5: Гарантированные Правительством Республики Узбекистан | L5: из них | M5: Транспортные средства | N5: Инвентарь | O5: Недвижимость | P5: из них | R5: Оборудование | S5: Векселя (облигации) | T5: Акции | U5: Гарантия третьей стороны | V5: Поручительства третьей стороны | W5: Страховой полис | X5: Необеспеченные | Y5: Другое обеспечение
L6: Гарантированные Правительством Республики Узбекистан в иностранной валюте (экв.сум) | P6: жилая недвижимость | Q6: коммерческая недвижимость
A7: Код | B7: (А) | C7: (Б) | D7: (Б1) | E7: (Б2) | F7: (Б3) | G7: (Б4) | H7: (В) | I7: (Г) | J7: (Д) | K7: (Е) | L7: (Е1) | M7: (Ж) | N7: (З) | O7: (И) | P7: (И1) | Q7: (И2) | R7: (К) | S7: (Л) | T7: (М) | U7: (Н) | V7: (О) | W7: (П) | X7: (Р) | Y7: (С)
B8: Промышленность
A9: 10 | B9: Физические лица | C9: =SUM(J9:Y9)-L9-P9-Q9 -> 100645482 | D9: 100645482 | E9: 0.077441266 | H9: 100645482 | J9: 0 | K9: 0 | L9: 0 | M9: 91464 | N9: 0 | O9: =+P9+Q9 -> 58001 | P9: 0 | Q9: 58001 | R9: 0 | S9: 0 | T9: 0 | U9: 0 | V9: 18608939 | W9: 81887078 | X9: 0 | Y9: 0
A10: =A9+10 -> 20 | B10: Государственные предприятия | C10: =SUM(J10:Y10)-L10-P10-Q10 -> 1060521 | D10: 1060521 | E10: 0.18592445 | H10: 1060521 | I10: 0 | J10: 0 | K10: 0 | L10: 0 | M10: 10000 | N10: 0 | O10: =+P10+Q10 -> 1050521 | P10: 0 | Q10: 1050521 | R10: 0 | S10: 0 | T10: 0 | U10: 0 | V10: 0 | W10: 0 | X10: 0 | Y10: 0
A11: =A10+10 -> 30 | B11: Совместные и иностранные предприятия | C11: =SUM(J11:Y11)-L11-P11-Q11 -> 81185906 | D11: 46882998 | E11: 0.21228218 | F11: 34302908 | G11: 0.11938421 | H11: 81185906 | I11: 0 | J11: 0 | K11: 0 | L11: 0 | M11: 443463 | N11: 0 | O11: =+P11+Q11 -> 50898620 | P11: 0 | Q11: 50898620 | R11: 0 | S11: 0 | T11: 0 | U11: 0 | V11: 0 | W11: 29606493 | X11: 0 | Y11: 237330
A12: =A11+10 -> 40 | B12: Частные товарищества и корпорации | C12: =SUM(J12:Y12)-L12-P12-Q12 -> 1044810736 | D12: 301931344 | E12: 0.12828057 | F12: 742879392 | G12: 0.10057936 | H12: 1039069231 | I12: 5741505 | J12: 0 | K12: 0 | L12: 0 | M12: 72364171 | N12: 0 | O12: =+P12+Q12 -> 667211899 | P12: 0 | Q12: 667211899 | R12: 5921945 | S12: 0 | T12: 0 | U12: 0 | V12: 34968502 | W12: 263835401 | X12: 0 | Y12: 508818
A13: =A12+10 -> 50 | B13: Правительство | C13: =SUM(J13:Y13)-L13-P13-Q13 -> 0 | O13: =+P13+Q13 -> 0
A14: =A13+10 -> 60 | B14: Прочие | C14: =SUM(J14:Y14)-L14-P14-Q14 -> 0 | O14: =+P14+Q14 -> 0
A15: =A14+10 -> 70 | B15: Итого по промышленности | C15: =SUM(J15:Y15)-L15-P15-Q15 -> 1227702645 | D15: =SUM(D9:D14) -> 450520345 | E15: =IFERROR(((D9*E9)/D15)+((D10*E10)/D15)+((D11*E11)/D15)+((D12*E12)/D15)+((D13*E13)/D15)+((D14*E14)/D15),0) -> 0.1258004 | F15: =SUM(F9:F14) -> 777182300 | G15: =IFERROR(((F9*G9)/F15)+((F10*G10)/F15)+((F11*G11)/F15)+((F12*G12)/F15)+((F13*G13)/F15)+((F14*G14)/F15),0) -> 0.10140936 | H15: =SUM(H9:H14) -> 1221961140 | I15: =SUM(I9:I14) -> 5741505 | J15: =SUM(J9:J14) -> 0 | K15: =SUM(K9:K14) -> 0 | L15: =SUM(L9:L14) -> 0 | M15: =SUM(M9:M14) -> 72909098 | N15: =SUM(N9:N14) -> 0 | O15: =SUM(O9:O14) -> 719219041 | ... Y15: =SUM(Y9:Y14) -> 746148
B16: Сельское хозяйство
A17: =A15+10 -> 80 | B17: Физические лица | C17: =SUM(J17:Y17)-L17-P17-Q17 -> 584765854 | D17: 584765854 | E17: 0.077723513 | H17: 584765854 | J17: 0 | K17: 0 | L17: 0 | M17: 1760837 | N17: 0 | O17: =+P17+Q17 -> 421378 | P17: 0 | Q17: 421378 | R17: 0 | S17: 0 | T17: 0 | U17: 0 | V17: 139930320 | W17: 442576277 | X17: 0 | Y17: 77042
A18: =A17+10 -> 90 | B18: Государственные предприятия | C18: =SUM(J18:Y18)-L18-P18-Q18 -> 71121613 | D18: 71121613 | E18: 0.066449218 | H18: 71121613 | J18: 0 | K18: 0 | L18: 0 | M18: 0 | N18: 0 | O18: =+P18+Q18 -> 2330000 | P18: 0 | Q18: 2330000 | R18: 0 | S18: 0 | T18: 0 | U18: 0 | V18: 68791613 | W18: 0 | X18: 0 | Y18: 0
A19: =A18+10 -> 100 | B19: Совместные и иностранные предприятия | C19: =SUM(J19:Y19)-L19-P19-Q19 -> 26499946 | D19: 26499946 | E19: 0.21056598 | H19: 26499946 | J19: 0 | K19: 0 | L19: 0 | M19: 0 | N19: 0 | O19: =+P19+Q19 -> 26499946 | P19: 0 | Q19: 26499946 | R19: 0 | S19: 0 | T19: 0 | U19: 0 | V19: 0 | W19: 0 | X19: 0 | Y19: 0
A20: =A19+10 -> 110 | B20: Частные товарищества и корпорации | C20: =SUM(J20:Y20)-L20-P20-Q20 -> 310022747 | D20: 215495555 | E20: 0.16510115 | F20: 94527192 | G20: 0.08852717 | H20: 301272419 | I20: 8750328 | J20: 0 | K20: 0 | L20: 0 | M20: 25591161 | N20: 0 | O20: =+P20+Q20 -> 209382778 | P20: 0 | Q20: 209382778 | R20: 4193068 | S20: 0 | T20: 0 | U20: 0 | V20: 10879376 | W20: 59976364 | X20: 0 | Y20: 0
A21: =A20+10 -> 120 | B21: Фермерское хозяйство | C21: =SUM(J21:Y21)-L21-P21-Q21 -> 60729562 | D21: 42011514 | E21: 0.17209202 | F21: 18718048 | G21: 0.054379883 | H21: 59150502 | I21: 1579060 | J21: 322400 | K21: 0 | L21: 0 | M21: 15614270 | N21: 0 | O21: =+P21+Q21 -> 43105805 | P21: 0 | Q21: 43105805 | R21: 40735 | S21: 0 | T21: 0 | U21: 0 | V21: 1053454 | W21: 592898 | X21: 0 | Y21: 0
A22: =A21+10 -> 130 | B22: Правительство | C22: =SUM(J22:Y22)-L22-P22-Q22 -> 0 | O22: =+P22+Q22 -> 0
A23: =A22+10 -> 140 | B23: Прочие | C23: =SUM(J23:Y23)-L23-P23-Q23 -> 0 | O23: =+P23+Q23 -> 0
A24: =A23+10 -> 150 | B24: Итого по сельскому хозяйству | C24: =SUM(J24:Y24)-L24-P24-Q24 -> 1053139722 | D24: =SUM(D17:D23) -> 939894482 | E24: =IFERROR(((D17*E17)/D24)+((D18*E18)/D24)+((D19*E19)/D24)+((D20*E20)/D24)+((D21*E21)/D24)+((D22*E22)/D24)+((D23*E23)/D24),0) -> 0.10486755 | F24: =SUM(F17:F23) -> 113245240 | G24: =IFERROR(((F17*G17)/F24)+((F18*G18)/F24)+((F19*G19)/F24)+((F20*G20)/F24)+((F21*G21)/F24)+((F22*G22)/F24)+((F23*G23)/F24),0) -> 0.082883043 | H24: =SUM(H17:H23) -> 1042810334 | I24: =SUM(I17:I23) -> 10329388 | J24: =SUM(J17:J23) -> 322400 | K24: =SUM(K17:K23) -> 0 | L24: =SUM(L17:L23) -> 0 | M24: =SUM(M17:M23) -> 42966268 | N24: =SUM(N17:N23) -> 0 | O24: =SUM(O17:O23) -> 281739907 | ... Y24: =SUM(Y17:Y23) -> 77042
B25: Транспорт и коммуникации
A26: =A24+10 -> 160 | B26: Физические лица | C26: =SUM(J26:Y26)-L26-P26-Q26 -> 169885131 | D26: 169885131 | E26: 0.27803906 | H26: 169885131 | J26: 0 | K26: 0 | L26: 0 | M26: 166183224 | N26: 0 | O26: =+P26+Q26 -> 0 | P26: 0 | Q26: 0 | R26: 0 | S26: 0 | T26: 0 | U26: 0 | V26: 7952 | W26: 3693955 | X26: 0 | Y26: 0
A27: =A26+10 -> 170 | B27: Государственные предприятия | C27: =SUM(J27:Y27)-L27-P27-Q27 -> 928138 | D27: 928138 | E27: 0.23207596 | H27: 928138 | J27: 0 | K27: 0 | L27: 0 | M27: 661138 | N27: 0 | O27: =+P27+Q27 -> 267000 | P27: 0 | Q27: 267000 | R27: 0 | S27: 0 | T27: 0 | U27: 0 | V27: 0 | W27: 0 | X27: 0 | Y27: 0
A28: =A27+10 -> 180 | B28: Совместные и иностранные предприятия | C28: =SUM(J28:Y28)-L28-P28-Q28 -> 47581850 | F28: 47581850 | G28: 0.09 | H28: 47581850 | J28: 0 | K28: 0 | L28: 0 | M28: 0 | N28: 0 | O28: =+P28+Q28 -> 47581850 | P28: 0 | Q28: 47581850 | R28: 0 | S28: 0 | T28: 0 | U28: 0 | V28: 0 | W28: 0 | X28: 0 | Y28: 0
A29: =A28+10 -> 190 | B29: Частные товарищества и корпорации | C29: =SUM(J29:Y29)-L29-P29-Q29 -> 237862697 | D29: 161511964 | E29: 0.23810183 | F29: 76350733 | G29: 0.11976033 | H29: 228920662 | I29: 8942035 | J29: 1625936 | K29: 0 | L29: 0 | M29: 116093385 | N29: 0 | O29: =+P29+Q29 -> 116013320 | P29: 0 | Q29: 116013320 | R29: 0 | S29: 0 | T29: 0 | U29: 0 | V29: 1372122 | W29: 2757934 | X29: 0 | Y29: 0
A30: =A29+10 -> 200 | B30: Правительство | C30: =SUM(J30:Y30)-L30-P30-Q30 -> 0 | O30: =+P30+Q30 -> 0
A31: =A30+10 -> 210 | B31: Прочие | C31: =SUM(J31:Y31)-L31-P31-Q31 -> 0 | O31: =+P31+Q31 -> 0
A32: =A31+10 -> 220 | B32: Итого по транспорту и коммуникациям | C32: =SUM(J32:Y32)-L32-P32-Q32 -> 456257816 | D32: =SUM(D26:D31) -> 332325233 | E32: =IFERROR(((D26*E26)/D32)+((D27*E27)/D32)+((D28*E28)/D32)+((D29*E29)/D32)+((D30*E30)/D32)+((D31*E31)/D32),0) -> 0.25850097 | F32: =SUM(F26:F31) -> 123932583 | G32: =IFERROR(((F26*G26)/F32)+((F27*G27)/F32)+((F28*G28)/F32)+((F29*G29)/F32)+((F30*G30)/F32)+((F31*G31)/F32),0) -> 0.10833434 | H32: =SUM(H26:H31) -> 447315781 | I32: =SUM(I26:I31) -> 8942035 | J32: =SUM(J26:J31) -> 1625936 | K32: =SUM(K26:K31) -> 0 | L32: =SUM(L26:L31) -> 0 | M32: =SUM(M26:M31) -> 282937747 | N32: =SUM(N26:N31) -> 0 | O32: =SUM(O26:O31) -> 163862170 | ... Y32: =SUM(Y26:Y31) -> 0
B33: Строительство
A34: =A32+10 -> 230 | B34: Физические лица | C34: =SUM(J34:Y34)-L34-P34-Q34 -> 0 | O34: =+P34+Q34 -> 0
A35: =A34+10 -> 240 | B35: Государственные предприятия | C35: =SUM(J35:Y35)-L35-P35-Q35 -> 1049953 | D35: 1049953 | E35: 0.28 | H35: 1049953 | J35: 0 | K35: 0 | L35: 0 | M35: 0 | N35: 0 | O35: =+P35+Q35 -> 350000 | P35: 0 | Q35: 350000 | R35: 0 | S35: 0 | T35: 0 | U35: 0 | V35: 699953 | W35: 0 | X35: 0 | Y35: 0
A36: =A35+10 -> 250 | B36: Совместные и иностранные предприятия | C36: =SUM(J36:Y36)-L36-P36-Q36 -> 490239 | D36: 490239 | E36: 0.24 | H36: 490239 | J36: 0 | K36: 0 | L36: 0 | M36: 0 | N36: 0 | O36: =+P36+Q36 -> 490239 | P36: 0 | Q36: 490239 | R36: 0 | S36: 0 | T36: 0 | U36: 0 | V36: 0 | W36: 0 | X36: 0 | Y36: 0
A37: =A36+10 -> 260 | B37: Частные товарищества и корпорации | C37: =SUM(J37:Y37)-L37-P37-Q37 -> 276471671 | D37: 276471671 | E37: 0.13227021 | H37: 233094178 | I37: 43377493 | J37: 0 | K37: 0 | L37: 0 | M37: 3947713 | N37: 0 | O37: =+P37+Q37 -> 259600031 | P37: 0 | Q37: 259600031 | R37: 1547619 | S37: 0 | T37: 0 | U37: 0 | V37: 7963862 | W37: 3412446 | X37: 0 | Y37: 0
A38: =A37+10 -> 270 | B38: Правительство | C38: =SUM(J38:Y38)-L38-P38-Q38 -> 0 | O38: =+P38+Q38 -> 0
A39: =A38+10 -> 280 | B39: Прочие | C39: =SUM(J39:Y39)-L39-P39-Q39 -> 0 | O39: =+P39+Q39 -> 0
A40: =A39+10 -> 290 | B40: Итого по строительству | C40: =SUM(J40:Y40)-L40-P40-Q40 -> 278011863 | D40: =SUM(D34:D39) -> 278011863 | E40: =IFERROR(((D34*E34)/D40)+((D35*E35)/D40)+((D36*E36)/D40)+((D37*E37)/D40)+((D38*E38)/D40)+((D39*E39)/D40),0) -> 0.1330181 | F40: =SUM(F34:F39) -> 0 | G40: =IFERROR(((F34*G34)/F40)+((F35*G35)/F40)+((F36*G36)/F40)+((F37*G37)/F40)+((F38*G38)/F40)+((F39*G39)/F40),0) -> 0 | H40: =SUM(H34:H39) -> 234634370 | I40: =SUM(I34:I39) -> 43377493 | J40: =SUM(J34:J39) -> 0 | K40: =SUM(K34:K39) -> 0 | L40: =SUM(L34:L39) -> 0 | M40: =SUM(M34:M39) -> 3947713 | N40: =SUM(N34:N39) -> 0 | O40: =SUM(O34:O39) -> 260440270 | ... Y40: =SUM(Y34:Y39) -> 0
B41: Торговля и общественное питание
A42: =A40+10 -> 300 | B42: Физические лица | C42: =SUM(J42:Y42)-L42-P42-Q42 -> 0 | O42: =+P42+Q42 -> 0
A43: =A42+10 -> 310 | B43: Государственные предприятия | C43: =SUM(J43:Y43)-L43-P43-Q43 -> 19571931 | D43: 19571931 | E43: 0.16346228 | H43: 19571931 | J43: 0 | K43: 0 | L43: 0 | M43: 116665 | N43: 0 | O43: =+P43+Q43 -> 9555266 | P43: 0 | Q43: 9555266 | R43: 9900000 | S43: 0 | T43: 0 | U43: 0 | V43: 0 | W43: 0 | X43: 0 | Y43: 0
A44: =A43+10 -> 320 | B44: Совместные и иностранные предприятия | C44: =SUM(J44:Y44)-L44-P44-Q44 -> 0 | J44: 0 | K44: 0 | L44: 0 | M44: 0 | N44: 0 | O44: =+P44+Q44 -> 0 | P44: 0 | Q44: 0 | R44: 0 | S44: 0 | T44: 0 | U44: 0 | V44: 0 | W44: 0 | X44: 0 | Y44: 0
A45: =A44+10 -> 330 | B45: Частные товарищества и корпорации | C45: =SUM(J45:Y45)-L45-P45-Q45 -> 414998050 | D45: 258460758 | E45: 0.23345217 | F45: 156537292 | G45: 0.10510108 | H45: 405173615 | I45: 9824435 | J45: 251000 | K45: 0 | L45: 0 | M45: 37231617 | N45: 0 | O45: =+P45+Q45 -> 172073738 | P45: 0 | Q45: 172073738 | R45: 0 | S45: 0 | T45: 0 | U45: 0 | V45: 15407700 | W45: 189712485 | X45: 0 | Y45: 321510
A46: =A45+10 -> 340 | B46: Правительство | C46: =SUM(J46:Y46)-L46-P46-Q46 -> 0 | O46: =+P46+Q46 -> 0
A47: =A46+10 -> 350 | B47: Прочие | C47: =SUM(J47:Y47)-L47-P47-Q47 -> 0 | O47: =+P47+Q47 -> 0
A48: =A47+10 -> 360 | B48: Итого по торговле и общественному питанию | C48: =SUM(J48:Y48)-L48-P48-Q48 -> 434569981 | D48: =SUM(D42:D47) -> 278032689 | E48: =IFERROR(((D42*E42)/D48)+((D43*E43)/D48)+((D44*E44)/D48)+((D45*E45)/D48)+((D46*E46)/D48)+((D47*E47)/D48),0) -> 0.22852527 | F48: =SUM(F42:F47) -> 156537292 | G48: =IFERROR(((F42*G42)/F48)+((F43*G43)/F48)+((F44*G44)/F48)+((F45*G45)/F48)+((F46*G46)/F48)+((F47*G47)/F48),0) -> 0.10510108 | H48: =SUM(H42:H47) -> 424745546 | I48: =SUM(I42:I47) -> 9824435 | J48: =SUM(J42:J47) -> 251000 | K48: =SUM(K42:K47) -> 0 | L48: =SUM(L42:L47) -> 0 | M48: =SUM(M42:M47) -> 37348282 | N48: =SUM(N42:N47) -> 0 | O48: =SUM(O42:O47) -> 181629004 | ... Y48: =SUM(Y42:Y47) -> 321510
B49: Материально-техническое снабжение и сбыт
A50: =A48+10 -> 370 | B50: Физические лица | C50: =SUM(J50:Y50)-L50-P50-Q50 -> 6334221 | D50: 6334221 | E50: 0.078824376 | H50: 6334221 | J50: 0 | K50: 0 | L50: 0 | M50: 0 | N50: 0 | O50: =+P50+Q50 -> 8999 | P50: 0 | Q50: 8999 | R50: 0 | S50: 0 | T50: 0 | U50: 0 | V50: 1607847 | W50: 4717375 | X50: 0 | Y50: 0
A51: =A50+10 -> 380 | B51: Государственные предприятия | C51: =SUM(J51:Y51)-L51-P51-Q51 -> 189159 | D51: 189159 | E51: 0.24 | H51: 189159 | J51: 0 | K51: 0 | L51: 0 | M51: 0 | N51: 0 | O51: =+P51+Q51 -> 189159 | P51: 0 | Q51: 189159 | R51: 0 | S51: 0 | T51: 0 | U51: 0 | V51: 0 | W51: 0 | X51: 0 | Y51: 0
A52: =A51+10 -> 390 | B52: Совместные и иностранные предприятия | C52: =SUM(J52:Y52)-L52-P52-Q52 -> 0 | J52: 0 | K52: 0 | L52: 0 | M52: 0 | N52: 0 | O52: =+P52+Q52 -> 0 | P52: 0 | Q52: 0 | R52: 0 | S52: 0 | T52: 0 | U52: 0 | V52: 0 | W52: 0 | X52: 0 | Y52: 0
A53: =A52+10 -> 400 | B53: Частные товарищества и корпорации | C53: =SUM(J53:Y53)-L53-P53-Q53 -> 599368724 | D53: 196593529 | E53: 0.17370448 | F53: 402775195 | G53: 0.10262048 | H53: 599368724 | J53: 0 | K53: 0 | L53: 0 | M53: 27411502 | N53: 0 | O53: =+P53+Q53 -> 273902853 | P53: 0 | Q53: 273902853 | R53: 0 | S53: 0 | T53: 0 | U53: 0 | V53: 16082037 | W53: 281971618 | X53: 0 | Y53: 714
A54: =A53+10 -> 410 | B54: Правительство | C54: =SUM(J54:Y54)-L54-P54-Q54 -> 0 | J54: 0 | K54: 0 | L54: 0 | M54: 0 | N54: 0 | O54: =+P54+Q54 -> 0 | P54: 0 | Q54: 0 | R54: 0 | S54: 0 | T54: 0 | U54: 0 | V54: 0 | W54: 0 | X54: 0 | Y54: 0
A55: =A54+10 -> 420 | B55: Прочие | C55: =SUM(J55:Y55)-L55-P55-Q55 -> 199980 | D55: 199980 | E55: 0.28 | H55: 199980 | J55: 0 | K55: 0 | L55: 0 | M55: 0 | N55: 0 | O55: =+P55+Q55 -> 199980 | P55: 0 | Q55: 199980 | R55: 0 | S55: 0 | T55: 0 | U55: 0 | V55: 0 | W55: 0 | X55: 0 | Y55: 0
A56: =A55+10 -> 430 | B56: Итого по материально-техническому снабжению и сбыту | C56: =SUM(J56:Y56)-L56-P56-Q56 -> 606092084 | D56: =SUM(D50:D55) -> 203316889 | E56: =IFERROR(((D50*E50)/D56)+((D51*E51)/D56)+((D52*E52)/D56)+((D53*E53)/D56)+((D54*E54)/D56)+((D55*E55)/D56),0) -> 0.17091477 | F56: =SUM(F50:F55) -> 402775195 | G56: =IFERROR(((F50*G50)/F56)+((F51*G51)/F56)+((F52*G52)/F56)+((F53*G53)/F56)+((F54*G54)/F56)+((F55*G55)/F56),0) -> 0.10262048 | H56: =SUM(H50:H55) -> 606092084 | I56: =SUM(I50:I55) -> 0 | J56: =SUM(J50:J55) -> 0 | K56: =SUM(K50:K55) -> 0 | L56: =SUM(L50:L55) -> 0 | M56: =SUM(M50:M55) -> 27411502 | N56: =SUM(N50:N55) -> 0 | O56: =SUM(O50:O55) -> 274300991 | ... Y56: =SUM(Y50:Y55) -> 714
B57: Жилищно-коммунальные услуги
A58: =A56+10 -> 440 | B58: Физические лица | C58: =SUM(J58:Y58)-L58-P58-Q58 -> 0 | O58: =+P58+Q58 -> 0
A59: =A58+10 -> 450 | B59: Государственные предприятия | C59: =SUM(J59:Y59)-L59-P59-Q59 -> 9883333 | D59: 9883333 | E59: 0.1331271 | H59: 8657198 | I59: 1226135 | J59: 0 | K59: 0 | L59: 0 | M59: 0 | N59: 0 | O59: =+P59+Q59 -> 0 | P59: 0 | Q59: 0 | R59: 0 | S59: 0 | T59: 0 | U59: 0 | V59: 2103310 | W59: 7780023 | X59: 0 | Y59: 0
A60: =A59+10 -> 460 | B60: Совместные и иностранные предприятия | C60: =SUM(J60:Y60)-L60-P60-Q60 -> 0 | J60: 0 | K60: 0 | L60: 0 | M60: 0 | N60: 0 | O60: =+P60+Q60 -> 0 | P60: 0 | Q60: 0 | R60: 0 | S60: 0 | T60: 0 | U60: 0 | V60: 0 | W60: 0 | X60: 0 | Y60: 0
A61: =A60+10 -> 470 | B61: Частные товарищества и корпорации | C61: =SUM(J61:Y61)-L61-P61-Q61 -> 50932526 | D61: 50932526 | E61: 0.13834122 | H61: 30910960 | I61: 20021566 | J61: 0 | K61: 0 | L61: 0 | M61: 0 | N61: 0 | O61: =+P61+Q61 -> 0 | P61: 0 | Q61: 0 | R61: 0 | S61: 0 | T61: 0 | U61: 0 | V61: 13586629 | W61: 37345897 | X61: 0 | Y61: 0
A62: =A61+10 -> 480 | B62: Правительство | C62: =SUM(J62:Y62)-L62-P62-Q62 -> 0 | J62: 0 | K62: 0 | L62: 0 | M62: 0 | N62: 0 | O62: =+P62+Q62 -> 0 | P62: 0 | Q62: 0 | R62: 0 | S62: 0 | T62: 0 | U62: 0 | V62: 0 | W62: 0 | X62: 0 | Y62: 0
A63: 485 | B63: Негосударственные некоммерческие организации | C63: =SUM(J63:Y63)-L63-P63-Q63 -> 40062247 | D63: 40062247 | E63: 0.14081935 | H63: 12577788 | I63: 27484459 | J63: 0 | K63: 0 | L63: 0 | M63: 350662 | N63: 0 | O63: =+P63+Q63 -> 0 | P63: 0 | Q63: 0 | R63: 0 | S63: 0 | T63: 0 | U63: 0 | V63: 10514893 | W63: 29196692 | X63: 0 | Y63: 0
A64: =A62+10 -> 490 | B64: Прочие | C64: =SUM(J64:Y64)-L64-P64-Q64 -> 0 | O64: =+P64+Q64 -> 0
A65: =A64+10 -> 500 | B65: Итого по жилищно-коммунальным услугам | C65: =SUM(J65:Y65)-L65-P65-Q65 -> 100878106 | D65: =SUM(D58:D64) -> 100878106 | E65: =IFERROR(((D58*E58)/D65)+((D59*E59)/D65)+((D60*E60)/D65)+((D61*E61)/D65)+((D62*E62)/D65)+((D63*E63)/D65)+((D64*E64)/D65),0) -> 0.13881453 | F65: =SUM(F58:F64) -> 0 | G65: =IFERROR(((F58*G58)/F65)+((F59*G59)/F65)+((F60*G60)/F65)+((F61*G61)/F65)+((F62*G62)/F65)+((F63*G63)/F65)+((F64*G64)/F65),0) -> 0 | H65: =SUM(H58:H64) -> 52145946 | I65: =SUM(I58:I64) -> 48732160 | J65: =SUM(J58:J64) -> 0 | K65: =SUM(K58:K64) -> 0 | L65: =SUM(L58:L64) -> 0 | M65: =SUM(M58:M64) -> 350662 | N65: =SUM(N58:N64) -> 0 | O65: =SUM(O58:O64) -> 0 | ... Y65: =SUM(Y58:Y64) -> 0
B66: Другие отрасли
A67: =A65+10 -> 510 | B67: Физические лица | C67: =SUM(J67:Y67)-L67-P67-Q67 -> 598592536 | D67: 598592536 | E67: 0.23896246 | H67: 596248680 | I67: 2343856 | J67: 83036 | K67: 0 | L67: 0 | M67: 3652386 | N67: 0 | O67: =+P67+Q67 -> 172885346 | P67: 172381016 | Q67: 504330 | R67: 0 | S67: 0 | T67: 0 | U67: 0 | V67: 407688089 | W67: 14247185 | X67: 0 | Y67: 36494
A68: =A67+10 -> 520 | B68: Государственные предприятия | C68: =SUM(J68:Y68)-L68-P68-Q68 -> 5666000 | D68: 5666000 | E68: 0.11420226 | H68: 5666000 | J68: 0 | K68: 0 | L68: 0 | M68: 6240 | N68: 0 | O68: =+P68+Q68 -> 0 | P68: 0 | Q68: 0 | R68: 0 | S68: 0 | T68: 0 | U68: 0 | V68: 0 | W68: 0 | X68: 0 | Y68: 5659760
A69: =A68+10 -> 530 | B69: Совместные и иностранные предприятия | C69: =SUM(J69:Y69)-L69-P69-Q69 -> 0 | J69: 0 | K69: 0 | L69: 0 | M69: 0 | N69: 0 | O69: =+P69+Q69 -> 0 | P69: 0 | Q69: 0 | R69: 0 | S69: 0 | T69: 0 | U69: 0 | V69: 0 | W69: 0 | X69: 0 | Y69: 0
A70: =A69+10 -> 540 | B70: Частные товарищества и корпорации | C70: =SUM(J70:Y70)-L70-P70-Q70 -> 10504833 | D70: 5875121 | E70: 0.18644922 | F70: 4629712 | G70: 0.09 | H70: 10437763 | I70: 67070 | J70: 0 | K70: 0 | L70: 0 | M70: 2262940 | N70: 0 | O70: =+P70+Q70 -> 4882483 | P70: 0 | Q70: 4882483 | R70: 29188 | S70: 0 | T70: 0 | U70: 0 | V70: 1080700 | W70: 777532 | X70: 0 | Y70: 1471990
A71: =A70+10 -> 550 | B71: Центральный банк | C71: =SUM(J71:Y71)-L71-P71-Q71 -> 0 | J71: 0 | K71: 0 | L71: 0 | M71: 0 | N71: 0 | O71: =+P71+Q71 -> 0 | P71: 0 | Q71: 0 | R71: 0 | S71: 0 | T71: 0 | U71: 0 | V71: 0 | W71: 0 | X71: 0 | Y71: 0
A72: =A71+10 -> 560 | B72: Другие банки | C72: =SUM(J72:Y72)-L72-P72-Q72 -> 0 | J72: 0 | K72: 0 | L72: 0 | M72: 0 | N72: 0 | O72: =+P72+Q72 -> 0 | P72: 0 | Q72: 0 | R72: 0 | S72: 0 | T72: 0 | U72: 0 | V72: 0 | W72: 0 | X72: 0 | Y72: 0
A73: =A72+10 -> 570 | B73: Правительство | C73: =SUM(J73:Y73)-L73-P73-Q73 -> 0 | J73: 0 | K73: 0 | L73: 0 | M73: 0 | N73: 0 | O73: =+P73+Q73 -> 0 | P73: 0 | Q73: 0 | R73: 0 | S73: 0 | T73: 0 | U73: 0 | V73: 0 | W73: 0 | X73: 0 | Y73: 0
A74: =A73+10 -> 580 | B74: Небанковские финансовые институты | C74: =SUM(J74:Y74)-L74-P74-Q74 -> 0 | J74: 0 | K74: 0 | L74: 0 | M74: 0 | N74: 0 | O74: =+P74+Q74 -> 0 | P74: 0 | Q74: 0 | R74: 0 | S74: 0 | T74: 0 | U74: 0 | V74: 0 | W74: 0 | X74: 0 | Y74: 0
A75: =A74+10 -> 590 | B75: Негосударственные некоммерческие организации | C75: =SUM(J75:Y75)-L75-P75-Q75 -> 959091 | D75: 959091 | E75: 0.18257883 | H75: 489946 | I75: 469145 | J75: 0 | K75: 0 | L75: 0 | M75: 10569 | N75: 0 | O75: =+P75+Q75 -> 754682 | P75: 0 | Q75: 754682 | R75: 0 | S75: 0 | T75: 0 | U75: 0 | V75: 88365 | W75: 97014 | X75: 0 | Y75: 8461
A76: =A75+10 -> 600 | B76: Бюджетные организации | C76: =SUM(J76:Y76)-L76-P76-Q76 -> 0 | O76: =+P76+Q76 -> 0
A77: =A76+10 -> 610 | B77: Прочие | C77: =SUM(J77:Y77)-L77-P77-Q77 -> 0 | O77: =+P77+Q77 -> 0
A78: =A77+10 -> 620 | B78: Итого по другим отраслям | C78: =SUM(J78:Y78)-L78-P78-Q78 -> 615722460 | D78: =SUM(D67:D77) -> 611092748 | E78: =IFERROR(((D67*E67)/D78)+((D68*E68)/D78)+((D69*E69)/D78)+((D70*E70)/D78)+((D71*E71)/D78)+((D72*E72)/D78)+((D73*E73)/D78)+((D74*E74)/D78)+((D75*E75)/D78)+((D76*E76)/D78)+((D77*E77)/D78),0) -> 0.23721233 | F78: =SUM(F67:F77) -> 4629712 | G78: =IFERROR(((F67*G67)/F78)+((F68*G68)/F78)+((F69*G69)/F78)+((F70*G70)/F78)+((F71*G71)/F78)+((F72*G72)/F78)+((F73*G73)/F78)+((F74*G74)/F78)+((F75*G75)/F78)+((F76*G76)/F78)+((F77*G77)/F78),0) -> 0.09 | H78: =SUM(H67:H77) -> 612842389 | I78: =SUM(I67:I77) -> 2880071 | J78: =SUM(J67:J77) -> 83036 | K78: =SUM(K67:K77) -> 0 | L78: =SUM(L67:L77) -> 0 | M78: =SUM(M67:M77) -> 5932135 | N78: =SUM(N67:N77) -> 0 | O78: =SUM(O67:O77) -> 178522511 | ... Y78: =SUM(Y67:Y77) -> 7176705
B79: Кредитные и лизинговые операции
A80: =A78+10 -> 630 | B80: Физические лица | C80: =SUM(J80:Y80)-L80-P80-Q80 -> 1460223224 | D80: =D9+D17+D26+D34+D42+D50+D58+D67 -> 1460223224 | E80: =IFERROR(((D9*E9)/D80)+((D17*E17)/D80)+((D26*E26)/D80)+((D34*E34)/D80)+((D42*E42)/D80)+((D50*E50)/D80)+((D58*E58)/D80)+((D67*E67)/D80),0) -> 0.16711096 | F80: =F9+F17+F26+F34+F42+F50+F58+F67 -> 0 | G80: =IFERROR(((F9*G9)/F80)+((F17*G17)/F80)+((F26*G26)/F80)+((F34*G34)/F80)+((F42*G42)/F80)+((F50*G50)/F80)+((F58*G58)/F80)+((F67*G67)/F80),0) -> 0 | H80: =H9+H17+H26+H34+H42+H50+H58+H67 -> 1457879368 | I80: =I9+I17+I26+I34+I42+I50+I58+I67 -> 2343856 | J80: =J9+J17+J26+J34+J42+J50+J58+J67 -> 83036 | K80: =K9+K17+K26+K34+K42+K50+K58+K67 -> 0 | L80: =L9+L17+L26+L34+L42+L50+L58+L67 -> 0 | M80: =M9+M17+M26+M34+M42+M50+M58+M67 -> 171687911 | N80: =N9+N17+N26+N34+N42+N50+N58+N67 -> 0 | O80: =O9+O17+O26+O34+O42+O50+O58+O67 -> 173373724 | ... Y80: =Y9+Y17+Y26+Y34+Y42+Y50+Y58+Y67 -> 113536
A81: =A80+10 -> 640 | B81: Государственные предприятия | C81: =SUM(J81:Y81)-L81-P81-Q81 -> 109470648 | D81: =D10+D18+D27+D35+D43+D51+D59+D68 -> 109470648 | E81: =IFERROR(((D10*E10)/D81)+((D18*E18)/D81)+((D27*E27)/D81)+((D35*E35)/D81)+((D43*E43)/D81)+((D51*E51)/D81)+((D59*E59)/D81)+((D68*E68)/D81),0) -> 0.097195167 | F81: =F10+F18+F27+F35+F43+F51+F59+F68 -> 0 | G81: =IFERROR(((F10*G10)/F81)+((F18*G18)/F81)+((F27*G27)/F81)+((F35*G35)/F81)+((F43*G43)/F81)+((F51*G51)/F81)+((F59*G59)/F81)+((F68*G68)/F81),0) -> 0 | H81: =H10+H18+H27+H35+H43+H51+H59+H68 -> 108244513 | I81: =I10+I18+I27+I35+I43+I51+I59+I68 -> 1226135 | J81: =J10+J18+J27+J35+J43+J51+J59+J68 -> 0 | K81: =K10+K18+K27+K35+K43+K51+K59+K68 -> 0 | L81: =L10+L18+L27+L35+L43+L51+L59+L68 -> 0 | M81: =M10+M18+M27+M35+M43+M51+M59+M68 -> 794043 | N81: =N10+N18+N27+N35+N43+N51+N59+N68 -> 0 | O81: =O10+O18+O27+O35+O43+O51+O59+O68 -> 13741946 | ... Y81: =Y10+Y18+Y27+Y35+Y43+Y51+Y59+Y68 -> 5659760
A82: =A81+10 -> 650 | B82: Совместные и иностранные предприятия | C82: =SUM(J82:Y82)-L82-P82-Q82 -> 155757941 | D82: =D11+D19+D28+D36+D44+D52+D60+D69 -> 73873183 | E82: =IFERROR(((D11*E11)/D82)+((D19*E19)/D82)+((D28*E28)/D82)+((D36*E36)/D82)+((D44*E44)/D82)+((D52*E52)/D82)+((D60*E60)/D82)+((D69*E69)/D82),0) -> 0.21185048 | F82: =F11+F19+F28+F36+F44+F52+F60+F69 -> 81884758 | G82: =IFERROR(((F11*G11)/F82)+((F19*G19)/F82)+((F28*G28)/F82)+((F36*G36)/F82)+((F44*G44)/F82)+((F52*G52)/F82)+((F60*G60)/F82)+((F69*G69)/F82),0) -> 0.10230954 | H82: =H11+H19+H28+H36+H44+H52+H60+H69 -> 155757941 | I82: =I11+I19+I28+I36+I44+I52+I60+I69 -> 0 | J82: =J11+J19+J28+J36+J44+J52+J60+J69 -> 0 | K82: =K11+K19+K28+K36+K44+K52+K60+K69 -> 0 | L82: =L11+L19+L28+L36+L44+L52+L60+L69 -> 0 | M82: =M11+M19+M28+M36+M44+M52+M60+M69 -> 443463 | N82: =N11+N19+N28+N36+N44+N52+N60+N69 -> 0 | O82: =O11+O19+O28+O36+O44+O52+O60+O69 -> 125470655 | ... Y82: =Y11+Y19+Y28+Y36+Y44+Y52+Y60+Y69 -> 237330
A83: =A82+10 -> 660 | B83: Частные товарищества и корпорации | C83: =SUM(J83:Y83)-L83-P83-Q83 -> 2944971984 | D83: =D12+D20+D29+D37+D45+D53+D61+D70 -> 1467272468 | E83: =IFERROR(((D12*E12)/D83)+((D20*E20)/D83)+((D29*E29)/D83)+((D37*E37)/D83)+((D45*E45)/D83)+((D53*E53)/D83)+((D61*E61)/D83)+((D70*E70)/D83),0) -> 0.17172313 | F83: =F12+F20+F29+F37+F45+F53+F61+F70 -> 1477699516 | G83: =IFERROR(((F12*G12)/F83)+((F20*G20)/F83)+((F29*G29)/F83)+((F37*G37)/F83)+((F45*G45)/F83)+((F53*G53)/F83)+((F61*G61)/F83)+((F70*G70)/F83),0) -> 0.10180165 | H83: =H12+H20+H29+H37+H45+H53+H61+H70 -> 2848247552 | I83: =I12+I20+I29+I37+I45+I53+I61+I70 -> 96724432 | J83: =J12+J20+J29+J37+J45+J53+J61+J70 -> 1876936 | K83: =K12+K20+K29+K37+K45+K53+K61+K70 -> 0 | L83: =L12+L20+L29+L37+L45+L53+L61+L70 -> 0 | M83: =M12+M20+M29+M37+M45+M53+M61+M70 -> 284902489 | N83: =N12+N20+N29+N37+N45+N53+N61+N70 -> 0 | O83: =O12+O20+O29+O37+O45+O53+O61+O70 -> 1703067102 | ... Y83: =Y12+Y20+Y29+Y37+Y45+Y53+Y61+Y70 -> 2303032
A84: =A83+10 -> 670 | B84: Фермерское хозяйство | C84: =SUM(J84:Y84)-L84-P84-Q84 -> 60729562 | D84: =D21 -> 42011514 | E84: =IFERROR(E21,0) -> 0.17209202 | F84: =F21 -> 18718048 | G84: =IFERROR(G21,0) -> 0.054379883 | H84: =H21 -> 59150502 | I84: =I21 -> 1579060 | J84: =J21 -> 322400 | K84: =K21 -> 0 | L84: =L21 -> 0 | M84: =M21 -> 15614270 | N84: =N21 -> 0 | O84: =O21 -> 43105805 | ... Y84: =Y21 -> 0
A85: =A84+10 -> 680 | B85: Другие банки | C85: =SUM(J85:Y85)-L85-P85-Q85 -> 0 | D85: =D72 -> 0 | E85: =E72 -> 0 | F85: =F72 -> 0 | G85: =G72 -> 0 | H85: =H72 -> 0 | I85: =I72 -> 0 | J85: =J72 -> 0 | K85: =K72 -> 0 | ... Y85: =Y72 -> 0
A86: =A85+10 -> 690 | B86: Центральный банк | C86: =SUM(J86:Y86)-L86-P86-Q86 -> 0 | D86: =D71 -> 0 | E86: =E71 -> 0 | F86: =F71 -> 0 | G86: =G71 -> 0 | H86: =H71 -> 0 | I86: =I71 -> 0 | J86: =J71 -> 0 | K86: =K71 -> 0 | ... Y86: =Y71 -> 0
A87: =A86+10 -> 700 | B87: Правительство | C87: =SUM(J87:Y87)-L87-P87-Q87 -> 0 | D87: =D13+D22+D30+D38+D46+D54+D62+D73 -> 0 | E87: =IFERROR(((D13*E13)/D87)+((D22*E22)/D87)+((D30*E30)/D87)+((D38*E38)/D87)+((D46*E46)/D87)+((D54*E54)/D87)+((D62*E62)/D87)+((D73*E73)/D87),0) -> 0 | F87: =F13+F22+F30+F38+F46+F54+F62+F73 -> 0 | G87: =IFERROR(((F13*G13)/F87)+((F22*G22)/F87)+((F30*G30)/F87)+((F38*G38)/F87)+((F46*G46)/F87)+((F54*G54)/F87)+((F62*G62)/F87)+((F73*G73)/F87),0) -> 0 | H87: =H13+H22+H30+H38+H46+H54+H62+H73 -> 0 | I87: =I13+I22+I30+I38+I46+I54+I62+I73 -> 0 | J87: =J13+J22+J30+J38+J46+J54+J62+J73 -> 0 | K87: =K13+K22+K30+K38+K46+K54+K62+K73 -> 0 | L87: =L13+L22+L30+L38+L46+L54+L62+L73 -> 0 | M87: =M13+M22+M30+M38+M46+M54+M62+M73 -> 0 | N87: =N13+N22+N30+N38+N46+N54+N62+N73 -> 0 | O87: =O13+O22+O30+O38+O46+O54+O62+O73 -> 0 | ... Y87: =Y13+Y22+Y30+Y38+Y46+Y54+Y62+Y73 -> 0
A88: =A87+10 -> 710 | B88: Небанковские финансовые институты | C88: =SUM(J88:Y88)-L88-P88-Q88 -> 0 | D88: =D74 -> 0 | E88: =E74 -> 0 | F88: =F74 -> 0 | G88: =G74 -> 0 | H88: =H74 -> 0 | I88: =I74 -> 0 | J88: =J74 -> 0 | K88: =K74 -> 0 | ... Y88: =Y74 -> 0
A89: =A88+10 -> 720 | B89: Негосударственные некоммерческие организации | C89: =SUM(J89:Y89)-L89-P89-Q89 -> 41021338 | D89: =+D63+D75 -> 41021338 | E89: =IFERROR(((D75*E75)/D78)+((D63*E63)/D65),0) -> 0.056210872 | F89: =+F63+F75 -> 0 | G89: =IFERROR(((F75*G75)/F78)+((F63*G63)/F65),0) -> 0 | H89: =+H63+H75 -> 13067734 | I89: =+I63+I75 -> 27953604 | J89: =+J63+J75 -> 0 | K89: =+K63+K75 -> 0 | L89: =+L63+L75 -> 0 | M89: =+M63+M75 -> 361231 | N89: =+N63+N75 -> 0 | O89: =+O63+O75 -> 754682 | ... Y89: =+Y63+Y75 -> 8461
A90: =A89+10 -> 730 | B90: Бюджетные организации | C90: =SUM(J90:Y90)-L90-P90-Q90 -> 0 | D90: =D76 -> 0 | E90: =E76 -> 0 | F90: =F76 -> 0 | G90: =G76 -> 0 | H90: =H76 -> 0 | I90: =I76 -> 0 | J90: =J76 -> 0 | K90: =K76 -> 0 | ... Y90: =Y76 -> 0
A91: =A90+10 -> 740 | B91: Прочие | C91: =SUM(J91:Y91)-L91-P91-Q91 -> 199980 | D91: =D14+D23+D31+D39+D47+D55+D64+D77 -> 199980 | E91: =IFERROR(((D14*E14)/D91)+((D23*E23)/D91)+((D31*E31)/D91)+((D39*E39)/D91)+((D47*E47)/D91)+((D55*E55)/D91)+((D64*E64)/D91)+((D77*E77)/D91),0) -> 0.28 | F91: =F14+F23+F31+F39+F47+F55+F64+F77 -> 0 | G91: =IFERROR(((F14*G14)/F91)+((F23*G23)/F91)+((F31*G31)/F91)+((F39*G39)/F91)+((F47*G47)/F91)+((F55*G55)/F91)+((F64*G64)/F91)+((F77*G77)/F91),0) -> 0 | H91: =H14+H23+H31+H39+H47+H55+H64+H77 -> 199980 | I91: =I14+I23+I31+I39+I47+I55+I64+I77 -> 0 | J91: =J14+J23+J31+J39+J47+J55+J64+J77 -> 0 | K91: =K14+K23+K31+K39+K47+K55+K64+K77 -> 0 | L91: =L14+L23+L31+L39+L47+L55+L64+L77 -> 0 | M91: =M14+M23+M31+M39+M47+M55+M64+M77 -> 0 | N91: =N14+N23+N31+N39+N47+N55+N64+N77 -> 0 | O91: =O14+O23+O31+O39+O47+O55+O64+O77 -> 199980 | ... Y91: =Y14+Y23+Y31+Y39+Y47+Y55+Y64+Y77 -> 0
A92: =A91+10 -> 750 | B92: Итого кредита и лизинга | C92: =SUM(J92:Y92)-L92-P92-Q92 -> 4772374677 | D92: =SUM(D80:D91) -> 3194072355 | E92: =IFERROR(((D80*E80)/D92)+((D81*E81)/D92)+((D82*E82)/D92)+((D83*E83)/D92)+((D84*E84)/D92)+((D85*E85)/D92)+((D86*E86)/D92)+((D87*E87)/D92)+((D88*E88)/D92)+((D89*E89)/D92)+((D90*E90)/D92)+((D91*E91)/D92),0) -> 0.16651649 | F92: =SUM(F80:F91) -> 1578302322 | G92: =IFERROR(((F80*G80)/F92)+((F81*G81)/F92)+((F82*G82)/F92)+((F83*G83)/F92)+((F84*G84)/F92)+((F85*G85)/F92)+((F86*G86)/F92)+((F87*G87)/F92)+((F88*G88)/F92)+((F89*G89)/F92)+((F90*G90)/F92)+((F91*G91)/F92),0) -> 0.10126559 | H92: =SUM(H80:H91) -> 4642547590 | I92: =SUM(I80:I91) -> 129827087 | J92: =SUM(J80:J91) -> 2282372 | K92: =SUM(K80:K91) -> 0 | L92: =SUM(L80:L91) -> 0 | M92: =SUM(M80:M91) -> 473803407 | N92: =SUM(N80:N91) -> 0 | O92: =SUM(O80:O91) -> 2059713894 | ... Y92: =SUM(Y80:Y91) -> 8322119
B95: Подпись Председателя правления:
B97: Подпись Главного Бухгалтера:
C99: =+Balance!C23 -> 4772374677
C102: =+Balance!C23 -> 4772374677

Sheet Aging Analysis
A1: АНАЛИЗ ПРОСРОЧЕННЫХ КРЕДИТОВ И ФИНАНСОВОГО ЛИЗИНГА К ПОЛУЧЕНИЮ | X1: Таблица-9
B3: =Balance!B3 -> АКБ "Микрокредитбанк" | T3: =+Balance!C3 -> 43829 | X3: =+Balance!E3 -> тыс. сум
A4: № | B4: Характеристики | C4: Всего задолжность по кредитам | D4: % | E4: Реструктуризированные кредиты | F4: % | G4: В ходе судебного разбирательства | H4: % | I4: Просроченная задолжность | K4: % | L4: в том числе, анализ временной задолженности
L5: 1-30 дней | N5: 31-60 дней | P5: 61-90 дней | R5: 91-180 дней | T5: 181-365 дней | V5: 366-730 дней | X5: Свыше 2 лет
I6: основной долг | J6: процент | L6: основной долг | M6: процент | N6: основной долг | O6: процент | P6: основной долг | Q6: процент | R6: основной долг | S6: процент | T6: основной долг | U6: процент | V6: основной долг | W6: процент | X6: основной долг | Y6: процент
B7: (А) | C7: (Б) | D7: (В) | E7: (Г) | F7: (Д) | G7: (Е) | H7: (Ж) | I7: (З) | J7: (З1) | K7: (И) | L7: (К) | M7: (К1) | N7: (Л) | O7: (Л1) | P7: (М) | Q7: (М1) | R7: (Н) | S7: (Н1) | T7: (О) | U7: (О1) | V7: (П) | W7: (П1) | X7: (Р) | Y7: (Р1)
B8: По типу клиента
A9: 1 | B9: Центральный банк | C9: =+'Loans Receivable'!C86 -> 0 | D9: =IF(C$22=0,"",C9/C$22) -> 0 | E9: 0 | F9: =IF(E$22=0,"",E9/E$22) | G9: 0 | H9: =IF($G$22=0,"",G9/$G$22) -> 0 | I9: =+L9+N9+P9+R9+T9+V9+X9 -> 0 | J9: =+M9+O9+T9+S9+U9+W9+Y9 -> 0 | K9: =IF($Z$22=0,"",Z9/$Z$22) -> 0 | L9: 0 | M9: 0 | N9: 0 | O9: 0 | P9: 0 | Q9: 0 | R9: 0 | S9: 0 | T9: 0 | U9: 0 | V9: 0 | W9: 0 | X9: 0 | Y9: 0 | Z9: =+I9+J9 -> 0
A10: 2 | B10: Другие банки | C10: =+'Loans Receivable'!C85 -> 0 | D10: =IF(C$22=0,"",C10/C$22) -> 0 | E10: 0 | F10: =IF(E$22=0,"",E10/E$22) | G10: 0 | H10: =IF($G$22=0,"",G10/$G$22) -> 0 | I10: =+L10+N10+P10+R10+T10+V10+X10 -> 0 | J10: =+M10+O10+Q10+S10+U10+W10+Y10 -> 0 | K10: =IF($Z$22=0,"",Z10/$Z$22) -> 0 | L10: 0 | M10: 0 | N10: 0 | O10: 0 | P10: 0 | Q10: 0 | R10: 0 | S10: 0 | T10: 0 | U10: 0 | V10: 0 | W10: 0 | X10: 0 | Y10: 0 | Z10: =+I10+J10 -> 0
A11: 3 | B11: Правительство | C11: =+'Loans Receivable'!C87 -> 0 | D11: =IF(C$22=0,"",C11/C$22) -> 0 | E11: 0 | F11: =IF(E$22=0,"",E11/E$22) | G11: 0 | H11: =IF($G$22=0,"",G11/$G$22) -> 0 | I11: =+L11+N11+P11+R11+T11+V11+X11 -> 0 | J11: =+M11+O11+Q11+S11+U11+W11+Y11 -> 0 | K11: =IF($Z$22=0,"",Z11/$Z$22) -> 0 | L11: 0 | M11: 0 | N11: 0 | O11: 0 | P11: 0 | Q11: 0 | R11: 0 | S11: 0 | T11: 0 | U11: 0 | V11: 0 | W11: 0 | X11: 0 | Y11: 0 | Z11: =+I11+J11 -> 0
A12: 4 | B12: Физические лица | C12: =+'Loans Receivable'!C80 -> 1460223224 | D12: =IF(C$22=0,"",C12/C$22) -> 0.30597414 | E12: 0 | F12: =IF(E$22=0,"",E12/E$22) | G12: 4521 | H12: =IF($G$22=0,"",G12/$G$22) -> 0.00032061267 | I12: =+L12+N12+P12+R12+T12+V12+X12 -> 2212434 | J12: =+M12+O12+Q12+S12+U12+W12+Y12 -> 2285521 | K12: =IF($Z$22=0,"",Z12/$Z$22) -> 0.12621705 | L12: 833971 | M12: 617875 | N12: 419289 | O12: 486083 | P12: 252641 | Q12: 287877 | R12: 422093 | S12: 570246 | T12: 253339 | U12: 306487 | V12: 31101 | W12: 16953 | X12: 0 | Y12: 0 | Z12: =+I12+J12 -> 4497955
A13: 5 | B13: Государственные предприятия | C13: =+'Loans Receivable'!C81 -> 109470648 | D13: =IF(C$22=0,"",C13/C$22) -> 0.022938402 | E13: 0 | F13: =IF(E$22=0,"",E13/E$22) | G13: 0 | H13: =IF($G$22=0,"",G13/$G$22) -> 0 | I13: =+L13+N13+P13+R13+T13+V13+X13 -> 243778 | J13: =+M13+O13+Q13+S13+U13+W13+Y13 -> 211587 | K13: =IF($Z$22=0,"",Z13/$Z$22) -> 0.01277799 | L13: 40203 | M13: 39144 | N13: 33380 | O13: 26946 | P13: 31797 | Q13: 17357 | R13: 95341 | S13: 83449 | T13: 43057 | U13: 44691 | V13: 0 | W13: 0 | X13: 0 | Y13: 0 | Z13: =+I13+J13 -> 455365
A14: 6 | B14: Совместные и иностранные предприятия | C14: =+'Loans Receivable'!C82 -> 155757941 | D14: =IF(C$22=0,"",C14/C$22) -> 0.032637408 | E14: 0 | F14: =IF(E$22=0,"",E14/E$22) | G14: 0 | H14: =IF($G$22=0,"",G14/$G$22) -> 0 | I14: =+L14+N14+P14+R14+T14+V14+X14 -> 1567196 | J14: =+M14+O14+Q14+S14+U14+W14+Y14 -> 194183 | K14: =IF($Z$22=0,"",Z14/$Z$22) -> 0.049426029 | L14: 624013 | M14: 63542 | N14: 340000 | O14: 57336 | P14: 333333 | Q14: 73305 | R14: 269850 | S14: 0 | T14: 0 | U14: 0 | V14: 0 | W14: 0 | X14: 0 | Y14: 0 | Z14: =+I14+J14 -> 1761379
A15: 7 | B15: Частные товарищества и корпорации | C15: =+'Loans Receivable'!C83 -> 2944971984 | D15: =IF(C$22=0,"",C15/C$22) -> 0.61708734 | E15: 0 | F15: =IF(E$22=0,"",E15/E$22) | G15: 13835570 | H15: =IF($G$22=0,"",G15/$G$22) -> 0.98116768 | I15: =+L15+N15+P15+R15+T15+V15+X15 -> 18967753 | J15: =+M15+O15+Q15+S15+U15+W15+Y15 -> 6503698 | K15: =IF($Z$22=0,"",Z15/$Z$22) -> 0.714754 | L15: 5145347 | M15: 1229904 | N15: 4965861 | O15: 1150359 | P15: 2320736 | Q15: 1953830 | R15: 4675527 | S15: 1609456 | T15: 1743248 | U15: 530014 | V15: 117034 | W15: 30135 | X15: 0 | Y15: 0 | Z15: =+I15+J15 -> 25471451
A16: 8 | B16: Фермерское хозяйство | C16: =+'Loans Receivable'!C84 -> 60729562 | D16: =IF(C$22=0,"",C16/C$22) -> 0.012725229 | E16: 0 | F16: =IF(E$22=0,"",E16/E$22) | G16: 195035 | H16: =IF($G$22=0,"",G16/$G$22) -> 0.013831164 | I16: =+L16+N16+P16+R16+T16+V16+X16 -> 928533 | J16: =+M16+O16+Q16+S16+U16+W16+Y16 -> 389211 | K16: =IF($Z$22=0,"",Z16/$Z$22) -> 0.036977194 | L16: 165044 | M16: 81454 | N16: 223981 | O16: 79023 | P16: 126983 | Q16: 108736 | R16: 238633 | S16: 80673 | T16: 173041 | U16: 39325 | V16: 851 | W16: 0 | X16: 0 | Y16: 0 | Z16: =+I16+J16 -> 1317744
A17: 9 | B17: Небанковские финансовые институты | C17: =+'Loans Receivable'!C88 -> 0 | D17: =IF(C$22=0,"",C17/C$22) -> 0 | E17: 0 | F17: =IF(E$22=0,"",E17/E$22) | G17: 0 | H17: =IF($G$22=0,"",G17/$G$22) -> 0 | I17: =+L17+N17+P17+R17+T17+V17+X17 -> 0 | J17: =+M17+O17+Q17+S17+U17+W17+Y17 -> 0 | K17: =IF($Z$22=0,"",Z17/$Z$22) -> 0 | L17: 0 | M17: 0 | N17: 0 | O17: 0 | P17: 0 | Q17: 0 | R17: 0 | S17: 0 | T17: 0 | U17: 0 | V17: 0 | W17: 0 | X17: 0 | Y17: 0 | Z17: =+I17+J17 -> 0
A18: 10 | B18: Негосударственные некоммерческие организации | C18: =+'Loans Receivable'!C89 -> 41021338 | D18: =IF(C$22=0,"",C18/C$22) -> 0.008595582 | E18: 0 | F18: =IF(E$22=0,"",E18/E$22) | G18: 0 | H18: =IF($G$22=0,"",G18/$G$22) -> 0 | I18: =+L18+N18+P18+R18+T18+V18+X18 -> 395550 | J18: =+M18+O18+Q18+S18+U18+W18+Y18 -> 360966 | K18: =IF($Z$22=0,"",Z18/$Z$22) -> 0.021228584 | L18: 59512 | M18: 37795 | N18: 56090 | O18: 63926 | P18: 52559 | Q18: 57296 | R18: 96342 | S18: 103036 | T18: 111407 | U18: 98913 | V18: 19640 | W18: 0 | X18: 0 | Y18: 0 | Z18: =+I18+J18 -> 756516
A19: 11 | B19: Бюджетные организации | C19: =+'Loans Receivable'!C90 -> 0 | D19: =IF(C$22=0,"",C19/C$22) -> 0 | E19: 0 | F19: =IF(E$22=0,"",E19/E$22) | G19: 0 | H19: =IF($G$22=0,"",G19/$G$22) -> 0 | I19: =+L19+N19+P19+R19+T19+V19+X19 -> 0 | J19: =+M19+O19+Q19+S19+U19+W19+Y19 -> 0 | K19: =IF($Z$22=0,"",Z19/$Z$22) -> 0 | L19: 0 | M19: 0 | N19: 0 | O19: 0 | P19: 0 | Q19: 0 | R19: 0 | S19: 0 | T19: 0 | U19: 0 | V19: 0 | W19: 0 | X19: 0 | Y19: 0 | Z19: =+I19+J19 -> 0
A20: 12 | B20: Прочие | C20: =+'Loans Receivable'!C91 -> 199980 | D20: =IF(C$22=0,"",C20/C$22) -> 4.1903667e-05 | E20: 0 | F20: =IF(E$22=0,"",E20/E$22) | G20: 66001 | H20: =IF($G$22=0,"",G20/$G$22) -> 0.0046805479 | I20: =+L20+N20+P20+R20+T20+V20+X20 -> 1207257 | J20: =+M20+O20+Q20+S20+U20+W20+Y20 -> 169001 | K20: =IF($Z$22=0,"",Z20/$Z$22) -> 0.038619155 | L20: 421163 | M20: 53972 | N20: 261730 | O20: 41255 | P20: 164867 | Q20: 26488 | R20: 250213 | S20: 31262 | T20: 94595 | U20: 15778 | V20: 14689 | W20: 246 | X20: 0 | Y20: 0 | Z20: =+I20+J20 -> 1376258
Z21: =+I21+J21 -> 0
A22: 13 | B22: Итого кредита и лизинга | C22: =SUM(C9:C20) -> 4772374677 | D22: =IF(C$22=0,"",C22/C$22) -> 1 | E22: =SUM(E9:E20) -> 0 | F22: =IF(E$22=0,"",E22/E$22) | G22: =SUM(G9:G20) -> 14101127 | H22: =IF($G$22=0,"",G22/$G$22) -> 1 | I22: =SUM(I9:I20) -> 25522501 | J22: =SUM(J9:J20) -> 10114167 | K22: =IF($Z$22=0,"",Z22/$Z$22) -> 1 | L22: =SUM(L9:L20) -> 7289253 | M22: =SUM(M9:M20) -> 2123686 | N22: =SUM(N9:N20) -> 6300331 | O22: =SUM(O9:O20) -> 1904928 | P22: =SUM(P9:P20) -> 3282916 | Q22: =SUM(Q9:Q20) -> 2524889 | R22: =SUM(R9:R20) -> 6047999 | S22: =SUM(S9:S20) -> 2478122 | ... Y22: =SUM(Y9:Y20) -> 0 | Z22: =+I22+J22 -> 35636668
Z23: =+I23+J23 -> 0
B24: По сектору экономики | F24: =IF(E$22=0,"",E24/E$22) | Z24: =+I24+J24 -> 0
A25: 14 | B25: Промышленность | C25: =+'Loans Receivable'!C15 -> 1227702645 | D25: =IF(C$34=0,"",C25/C$34) -> 0.25725194 | E25: 0 | F25: =IF($E$34=0,"",E25/$E$34) | G25: 1533410 | H25: =IF($G$34=0,"",G25/$G$34) -> 0.10874379 | I25: =+L25+N25+P25+R25+T25+V25+X25 -> 7581240 | J25: =+M25+O25+Q25+S25+U25+W25+Y25 -> 1351885 | K25: =IF($Z$34=0,"",Z25/$Z$34) -> 0.25067229 | L25: 2303900 | M25: 291997 | N25: 1421991 | O25: 358068 | P25: 1167105 | Q25: 465939 | R25: 2352140 | S25: 182878 | T25: 310770 | U25: 52762 | V25: 25334 | W25: 241 | X25: 0 | Y25: 0 | Z25: =+I25+J25 -> 8933125
A26: 15 | B26: Сельское хозяйство | C26: =+'Loans Receivable'!C24 -> 1053139722 | D26: =IF(C$34=0,"",C26/C$34) -> 0.22067415 | E26: 0 | F26: =IF($E$34=0,"",E26/$E$34) | G26: 327911 | H26: =IF($G$34=0,"",G26/$G$34) -> 0.023254241 | I26: =+L26+N26+P26+R26+T26+V26+X26 -> 3443159 | J26: =+M26+O26+Q26+S26+U26+W26+Y26 -> 1609868 | K26: =IF($Z$34=0,"",Z26/$Z$34) -> 0.14179291 | L26: 924471 | M26: 272066 | N26: 771720 | O26: 224950 | P26: 526413 | Q26: 515942 | R26: 713308 | S26: 501395 | T26: 506396 | U26: 95515 | V26: 851 | W26: 0 | X26: 0 | Y26: 0 | Z26: =+I26+J26 -> 5053027
A27: 16 | B27: Транспорт и коммуникации | C27: =+'Loans Receivable'!C32 -> 456257816 | D27: =IF(C$34=0,"",C27/C$34) -> 0.095603939 | E27: 0 | F27: =IF($E$34=0,"",E27/$E$34) | G27: 143655 | H27: =IF($G$34=0,"",G27/$G$34) -> 0.010187484 | I27: =+L27+N27+P27+R27+T27+V27+X27 -> 1544539 | J27: =+M27+O27+Q27+S27+U27+W27+Y27 -> 178538 | K27: =IF($Z$34=0,"",Z27/$Z$34) -> 0.048351238 | L27: 590835 | M27: 64152 | N27: 539960 | O27: 39370 | P27: 127855 | Q27: 31718 | R27: 167870 | S27: 43298 | T27: 118019 | U27: 0 | V27: 0 | W27: 0 | X27: 0 | Y27: 0 | Z27: =+I27+J27 -> 1723077
A28: 17 | B28: Строительство | C28: =+'Loans Receivable'!C40 -> 278011863 | D28: =IF(C$34=0,"",C28/C$34) -> 0.058254408 | E28: 0 | F28: =IF($E$34=0,"",E28/$E$34) | G28: 7219621 | H28: =IF($G$34=0,"",G28/$G$34) -> 0.51198894 | I28: =+L28+N28+P28+R28+T28+V28+X28 -> 2435627 | J28: =+M28+O28+Q28+S28+U28+W28+Y28 -> 812994 | K28: =IF($Z$34=0,"",Z28/$Z$34) -> 0.091159505 | L28: 470940 | M28: 167671 | N28: 1631843 | O28: 152022 | P28: 133388 | Q28: 329706 | R28: 104069 | S28: 136612 | T28: 89178 | U28: 24252 | V28: 6209 | W28: 2731 | X28: 0 | Y28: 0 | Z28: =+I28+J28 -> 3248621
A29: 18 | B29: Торговля и общественное питание | C29: =+'Loans Receivable'!C48 -> 434569981 | D29: =IF(C$34=0,"",C29/C$34) -> 0.091059485 | E29: 0 | F29: =IF($E$34=0,"",E29/$E$34) | G29: 3353953 | H29: =IF($G$34=0,"",G29/$G$34) -> 0.23785 | I29: =+L29+N29+P29+R29+T29+V29+X29 -> 4607433 | J29: =+M29+O29+Q29+S29+U29+W29+Y29 -> 1416597 | K29: =IF($Z$34=0,"",Z29/$Z$34) -> 0.16904021 | L29: 1144406 | M29: 304383 | N29: 717843 | O29: 263771 | P29: 614693 | Q29: 520797 | R29: 1438666 | S29: 257375 | T29: 615674 | U29: 70271 | V29: 76151 | W29: 0 | X29: 0 | Y29: 0 | Z29: =+I29+J29 -> 6024030
A30: 19 | B30: Материально-техническое снабжение и сбыт | C30: =+'Loans Receivable'!C56 -> 606092084 | D30: =IF(C$34=0,"",C30/C$34) -> 0.1270001 | E30: 0 | F30: =IF($E$34=0,"",E30/$E$34) | G30: 0 | H30: =IF($G$34=0,"",G30/$G$34) -> 0 | I30: =+L30+N30+P30+R30+T30+V30+X30 -> 0 | J30: =+M30+O30+Q30+S30+U30+W30+Y30 -> 0 | K30: =IF($Z$34=0,"",Z30/$Z$34) -> 0 | L30: 0 | M30: 0 | N30: 0 | O30: 0 | P30: 0 | Q30: 0 | R30: 0 | S30: 0 | T30: 0 | U30: 0 | V30: 0 | W30: 0 | X30: 0 | Y30: 0 | Z30: =+I30+J30 -> 0
A31: 20 | B31: Жилищно-коммунальные услуги | C31: =+'Loans Receivable'!C65 -> 100878106 | D31: =IF(C$34=0,"",C31/C$34) -> 0.021137927 | E31: 0 | F31: =IF($E$34=0,"",E31/$E$34) | G31: 0 | H31: =IF($G$34=0,"",G31/$G$34) -> 0 | I31: =+L31+N31+P31+R31+T31+V31+X31 -> 130000 | J31: =+M31+O31+Q31+S31+U31+W31+Y31 -> 22001 | K31: =IF($Z$34=0,"",Z31/$Z$34) -> 0.0042652978 | L31: 71667 | M31: 8163 | N31: 58333 | O31: 7488 | P31: 0 | Q31: 6350 | R31: 0 | S31: 0 | T31: 0 | U31: 0 | V31: 0 | W31: 0 | X31: 0 | Y31: 0 | Z31: =+I31+J31 -> 152001
A32: 21 | B32: Другие сектора | C32: =+'Loans Receivable'!C78 -> 615722460 | D32: =IF(C$34=0,"",C32/C$34) -> 0.12901805 | E32: 0 | F32: =IF($E$34=0,"",E32/$E$34) | G32: 1522577 | H32: =IF($G$34=0,"",G32/$G$34) -> 0.10797555 | I32: =+L32+N32+P32+R32+T32+V32+X32 -> 5780503 | J32: =+M32+O32+Q32+S32+U32+W32+Y32 -> 4722284 | K32: =IF($Z$34=0,"",Z32/$Z$34) -> 0.29471855 | L32: 1783034 | M32: 1015254 | N32: 1158641 | O32: 859259 | P32: 713462 | Q32: 654437 | R32: 1271946 | S32: 1356564 | T32: 778650 | U32: 792408 | V32: 74770 | W32: 44362 | X32: 0 | Y32: 0 | Z32: =+I32+J32 -> 10502787
Z33: =+I33+J33 -> 0
A34: 22 | B34: Итого кредита и лизинга | C34: =SUM(C25:C32) -> 4772374677 | D34: =IF(C$34=0,"",C34/C$34) -> 1 | E34: =SUM(E25:E32) -> 0 | F34: =IF($E$34=0,"",E34/$E$34) | G34: =SUM(G25:G32) -> 14101127 | H34: =IF($G$34=0,"",G34/$G$34) -> 1 | I34: =SUM(I25:I32) -> 25522501 | J34: =SUM(J25:J32) -> 10114167 | K34: =IF($Z$34=0,"",Z34/$Z$34) -> 1 | L34: =SUM(L25:L32) -> 7289253 | M34: =SUM(M25:M32) -> 2123686 | N34: =SUM(N25:N32) -> 6300331 | O34: =SUM(O25:O32) -> 1904928 | P34: =SUM(P25:P32) -> 3282916 | Q34: =SUM(Q25:Q32) -> 2524889 | R34: =SUM(R25:R32) -> 6047999 | S34: =SUM(S25:S32) -> 2478122 | ... Y34: =SUM(Y25:Y32) -> 0 | Z34: =+I34+J34 -> 35636668
B37: Подпись Председателя правления:
B39: Подпись Главного Бухгалтера:

Sheet Asset Classification
A1: ОТЧЕТ О КЛАССИФИКАЦИИ АКТИВОВ ПО СТЕПЕНИ РИСКА | W1: Таблица-10
B2: =Balance!B3 -> АКБ "Микрокредитбанк" | U2: =+Balance!B2 -> 30 Декабрь, 2019 | Z2: =+Balance!E3 -> тыс. сум
A3: № | B3: Статьи баланса | C3: Общая сумма | D3: из них, в иностранной валюте (в экв. в сумах) | E3: Стандартные | F3: из них, в иностранной валюте (в экв. в сумах) | G3: Общие резервы (1%) | H3: из них, в иностранной валюте (в экв. в сумах) | I3: Субстандартные | J3: из них, в иностранной валюте (в экв. в сумах) | K3: Специальные резервы (мин 10%) | L3: из них, в иностранной валюте (в экв. в сумах) | M3: Неудовлетворительные | N3: из них, в иностранной валюте (в экв. в сумах) | O3: Специальные резервы (мин 25%) | P3: из них, в иностранной валюте (в экв. в сумах) | Q3: Сомнительные | R3: из них, в иностранной валюте (в экв. в сумах) | S3: Специальные резервы (мин 50%) | T3: из них, в иностранной валюте (в экв. в сумах) | U3: Безнадежные | V3: из них, в иностранной валюте (в экв. в сумах) | W3: Специальные резервы (100%) | X3: из них, в иностранной валюте (в экв. в сумах) | Y3: Совокупная сумма специальных резервов | Z3: из них, в иностранной валюте (в экв. в сумах)
A4: (А) | B4: (Б) | C4: (В) | D4: (В1) | E4: (Г) | F4: (Г1) | G4: (Д) | H4: (Д1) | I4: (Е) | J4: (Е1) | K4: (Ж) | L4: (Ж1) | M4: (З) | N4: (З1) | O4: (И) | P4: (И1) | Q4: (К) | R4: (К1) | S4: (Л) | T4: (Л1) | U4: (М) | V4: (М1) | W4: (Н) | X4: (Н1) | Y4: О=Ж+И+Л+Н | Z4: (О1)=(Ж1)+(И1)+(Л1)+(Н1)
B5: По типу клиента
A6: 1 | B6: Центральный банк | C6: =E6+I6+M6+Q6+U6 -> 0 | D6: =F6+J6+N6+R6+V6 -> 0 | Y6: =+W6+S6+O6+K6 -> 0 | Z6: =+X6+T6+P6+L6 -> 0 | AA6: =+'Aging Analysis'!C9 -> 0
B7: из них необеспеченные | C7: =E7+I7+M7+Q7+U7 -> 0 | D7: =F7+J7+N7+R7+V7 -> 0 | Y7: =+W7+S7+O7+K7 -> 0 | Z7: =+X7+T7+P7+L7 -> 0
A8: 2 | B8: Другие банки | C8: =E8+I8+M8+Q8+U8 -> 0 | D8: =F8+J8+N8+R8+V8 -> 0 | Y8: =+W8+S8+O8+K8 -> 0 | Z8: =+X8+T8+P8+L8 -> 0 | AA8: =+'Aging Analysis'!C10 -> 0
B9: из них необеспеченные | C9: =E9+I9+M9+Q9+U9 -> 0 | D9: =F9+J9+N9+R9+V9 -> 0 | Y9: =+W9+S9+O9+K9 -> 0 | Z9: =+X9+T9+P9+L9 -> 0
A10: 3 | B10: Правительство | C10: =E10+I10+M10+Q10+U10 -> 0 | D10: =F10+J10+N10+R10+V10 -> 0 | Y10: =+W10+S10+O10+K10 -> 0 | Z10: =+X10+T10+P10+L10 -> 0 | AA10: =+'Aging Analysis'!C11 -> 0
B11: из них необеспеченные | C11: =E11+I11+M11+Q11+U11 -> 0 | D11: =F11+J11+N11+R11+V11 -> 0 | Y11: =+W11+S11+O11+K11 -> 0 | Z11: =+X11+T11+P11+L11 -> 0
A12: 4 | B12: Физические лица | C12: =E12+I12+M12+Q12+U12 -> 1460223224 | D12: =F12+J12+N12+R12+V12 -> 0 | E12: 1440604883 | I12: 19180910 | K12: 3629425 | M12: 402692 | O12: 100563 | Q12: 30218 | S12: 15105 | U12: 4521 | W12: 2540 | Y12: =+W12+S12+O12+K12 -> 3747633 | Z12: =+X12+T12+P12+L12 -> 0 | AA12: =+'Aging Analysis'!C12 -> 1460223224
B13: из них необеспеченные | C13: =E13+I13+M13+Q13+U13 -> 0 | D13: =F13+J13+N13+R13+V13 -> 0 | Y13: =+W13+S13+O13+K13 -> 0 | Z13: =+X13+T13+P13+L13 -> 0
A14: 5 | B14: Государственные предприятия | C14: =E14+I14+M14+Q14+U14 -> 109470648 | D14: =F14+J14+N14+R14+V14 -> 0 | E14: 23119073 | I14: 85951575 | K14: 9735361 | Q14: 400000 | S14: 200000 | Y14: =+W14+S14+O14+K14 -> 9935361 | Z14: =+X14+T14+P14+L14 -> 0 | AA14: =+'Aging Analysis'!C13 -> 109470648
B15: из них необеспеченные | C15: =E15+I15+M15+Q15+U15 -> 0 | D15: =F15+J15+N15+R15+V15 -> 0 | Y15: =+W15+S15+O15+K15 -> 0 | Z15: =+X15+T15+P15+L15 -> 0
A16: 6 | B16: Совместные и иностранные предприятия | C16: =E16+I16+M16+Q16+U16 -> 155757941 | D16: =F16+J16+N16+R16+V16 -> 81884758 | E16: 118773503 | F16: 48327077 | I16: 36984438 | J16: 33557681 | K16: 3121757 | L16: 2373405 | Y16: =+W16+S16+O16+K16 -> 3121757 | Z16: =+X16+T16+P16+L16 -> 2373405 | AA16: =+'Aging Analysis'!C14 -> 155757941
B17: из них необеспеченные | C17: =E17+I17+M17+Q17+U17 -> 0 | D17: =F17+J17+N17+R17+V17 -> 0 | Y17: =+W17+S17+O17+K17 -> 0 | Z17: =+X17+T17+P17+L17 -> 0
A18: 7 | B18: Частные товарищества и корпорации | C18: =E18+I18+M18+Q18+U18 -> 2944971984 | D18: =F18+J18+N18+R18+V18 -> 1477699520 | E18: 2346481896 | F18: 1263319757 | I18: 572977252 | J18: 214379763 | K18: 87716718 | L18: 14948352 | M18: 8488339 | O18: 2121668 | Q18: 3100317 | S18: 1551349 | U18: 13924180 | W18: 5497232 | Y18: =+W18+S18+O18+K18 -> 96886967 | Z18: =+X18+T18+P18+L18 -> 14948352 | AA18: =+'Aging Analysis'!C15 -> 2944971984
B19: из них необеспеченные | C19: =E19+I19+M19+Q19+U19 -> 0 | D19: =F19+J19+N19+R19+V19 -> 0 | Y19: =+W19+S19+O19+K19 -> 0 | Z19: =+X19+T19+P19+L19 -> 0
A20: 8 | B20: Фермерское хозяйство | C20: =E20+I20+M20+Q20+U20 -> 60729562 | D20: =F20+J20+N20+R20+V20 -> 18718047 | E20: 41203175 | F20: 8655771 | I20: 18551385 | J20: 9601693 | K20: 3107916 | L20: 1206875 | M20: 802576 | N20: 460583 | O20: 200644 | P20: 115146 | U20: 172426 | W20: 40858 | Y20: =+W20+S20+O20+K20 -> 3349418 | Z20: =+X20+T20+P20+L20 -> 1322021 | AA20: =+'Aging Analysis'!C16 -> 60729562
B21: из них необеспеченные | C21: =E21+I21+M21+Q21+U21 -> 0 | D21: =F21+J21+N21+R21+V21 -> 0 | Y21: =+W21+S21+O21+K21 -> 0 | Z21: =+X21+T21+P21+L21 -> 0
A22: 9 | B22: Небанковские финансовые институты | C22: =E22+I22+M22+Q22+U22 -> 0 | D22: =F22+J22+N22+R22+V22 -> 0 | Y22: =+W22+S22+O22+K22 -> 0 | Z22: =+X22+T22+P22+L22 -> 0 | AA22: =+'Aging Analysis'!C17 -> 0
B23: из них необеспеченные | C23: =E23+I23+M23+Q23+U23 -> 0 | D23: =F23+J23+N23+R23+V23 -> 0 | Y23: =+W23+S23+O23+K23 -> 0 | Z23: =+X23+T23+P23+L23 -> 0
A24: 10 | B24: Негосударственные некоммерческие организации | C24: =E24+I24+M24+Q24+U24 -> 41021338 | D24: =F24+J24+N24+R24+V24 -> 0 | E24: 32448311 | I24: 8289066 | K24: 2813570 | M24: 283961 | O24: 70991 | Y24: =+W24+S24+O24+K24 -> 2884561 | Z24: =+X24+T24+P24+L24 -> 0 | AA24: =+'Aging Analysis'!C18 -> 41021338
B25: из них необеспеченные | C25: =E25+I25+M25+Q25+U25 -> 0 | D25: =F25+J25+N25+R25+V25 -> 0 | Y25: =+W25+S25+O25+K25 -> 0 | Z25: =+X25+T25+P25+L25 -> 0
A26: 11 | B26: Бюджетные организации | C26: =E26+I26+M26+Q26+U26 -> 0 | D26: =F26+J26+N26+R26+V26 -> 0 | Y26: =+W26+S26+O26+K26 -> 0 | Z26: =+X26+T26+P26+L26 -> 0 | AA26: =+'Aging Analysis'!C19 -> 0
B27: из них необеспеченные | C27: =E27+I27+M27+Q27+U27 -> 0 | D27: =F27+J27+N27+R27+V27 -> 0 | Y27: =+W27+S27+O27+K27 -> 0 | Z27: =+X27+T27+P27+L27 -> 0
A28: 12 | B28: Прочие | C28: =E28+I28+M28+Q28+U28 -> 199980 | D28: =F28+J28+N28+R28+V28 -> 0 | E28: 199980 | Y28: =+W28+S28+O28+K28 -> 0 | Z28: =+X28+T28+P28+L28 -> 0 | AA28: =+'Aging Analysis'!C20 -> 199980
B29: из них необеспеченные | C29: =E29+I29+M29+Q29+U29 -> 0 | D29: =F29+J29+N29+R29+V29 -> 0 | Y29: =+W29+S29+O29+K29 -> 0 | Z29: =+X29+T29+P29+L29 -> 0 | AA29: =+'Aging Analysis'!C21 -> 0
A30: 13 | B30: Итого кредита и лизинга | C30: =+C6+C8+C10+C12+C14+C16+C18+C20+C22+C24+C26+C28 -> 4772374677 | D30: =+D6+D8+D10+D12+D14+D16+D18+D20+D22+D24+D26+D28 -> 1578302325 | E30: =+E6+E8+E10+E12+E14+E16+E18+E20+E22+E24+E26+E28 -> 4002830821 | F30: =+F6+F8+F10+F12+F14+F16+F18+F20+F22+F24+F26+F28 -> 1320302605 | G30: =+G6+G8+G10+G12+G14+G16+G18+G20+G22+G24+G26+G28 -> 0 | H30: =+H6+H8+H10+H12+H14+H16+H18+H20+H22+H24+H26+H28 -> 0 | I30: =+I6+I8+I10+I12+I14+I16+I18+I20+I22+I24+I26+I28 -> 741934626 | J30: =+J6+J8+J10+J12+J14+J16+J18+J20+J22+J24+J26+J28 -> 257539137 | ... Z30: =+Z6+Z8+Z10+Z12+Z14+Z16+Z18+Z20+Z22+Z24+Z26+Z28 -> 18643778 | AA30: =+'Aging Analysis'!C22 -> 4772374677
B31: из них необеспеченные | C31: =+C7+C9+C11+C13+C15+C17+C19+C21+C23+C25+C27+C29 -> 0 | D31: =+D7+D9+D11+D13+D15+D17+D19+D21+D23+D25+D27+D29 -> 0 | E31: =+E7+E9+E11+E13+E15+E17+E19+E21+E23+E25+E27+E29 -> 0 | F31: =+F7+F9+F11+F13+F15+F17+F19+F21+F23+F25+F27+F29 -> 0 | G31: =+G7+G9+G11+G13+G15+G17+G19+G21+G23+G25+G27+G29 -> 0 | H31: =+H7+H9+H11+H13+H15+H17+H19+H21+H23+H25+H27+H29 -> 0 | I31: =+I7+I9+I11+I13+I15+I17+I19+I21+I23+I25+I27+I29 -> 0 | J31: =+J7+J9+J11+J13+J15+J17+J19+J21+J23+J25+J27+J29 -> 0 | ... Z31: =+Z7+Z9+Z11+Z13+Z15+Z17+Z19+Z21+Z23+Z25+Z27+Z29 -> 0 | AA31: =+'Aging Analysis'!C23 -> 0
B32: По сектору экономики | AA32: =+'Aging Analysis'!C24 -> 0
A34: 14 | B34: Промышленность | C34: =E34+I34+M34+Q34+U34 -> 1227702645 | D34: =F34+J34+N34+R34+V34 -> 777182302 | E34: 960279021 | F34: 581718225 | I34: 263767265 | J34: 195464077 | K34: 24385207 | L34: 11159071 | M34: 1961532 | O34: 490387 | Q34: 410470 | S34: 205232 | U34: 1284357 | W34: 10332 | Y34: =+W34+S34+O34+K34 -> 25091158 | Z34: =+X34+T34+P34+L34 -> 11159071 | AA34: =+'Aging Analysis'!C25 -> 1227702645 | CH34: ='Aging Analysis'!C25 -> 1227702645
B35: из них необеспеченные | C35: =E35+I35+M35+Q35+U35 -> 0 | D35: =F35+J35+N35+R35+V35 -> 0 | Y35: =+W35+S35+O35+K35 -> 0 | Z35: =+X35+T35+P35+L35 -> 0
A36: 15 | B36: Сельское хозяйство | C36: =E36+I36+M36+Q36+U36 -> 1053139722 | D36: =F36+J36+N36+R36+V36 -> 113245239 | E36: 919543910 | F36: 97153487 | I36: 131030375 | J36: 15631169 | K36: 23640083 | L36: 1824901 | M36: 1513250 | N36: 460583 | O36: 378244 | P36: 115146 | Q36: 814632 | S36: 408508 | U36: 237555 | W36: 81398 | Y36: =+W36+S36+O36+K36 -> 24508233 | Z36: =+X36+T36+P36+L36 -> 1940047 | AA36: =+'Aging Analysis'!C26 -> 1053139722 | CH36: ='Aging Analysis'!C26 -> 1053139722
B37: из них необеспеченные | C37: =E37+I37+M37+Q37+U37 -> 0 | D37: =F37+J37+N37+R37+V37 -> 0 | Y37: =+W37+S37+O37+K37 -> 0 | Z37: =+X37+T37+P37+L37 -> 0
A38: 16 | B38: Транспорт и коммуникации | C38: =E38+I38+M38+Q38+U38 -> 456257816 | D38: =F38+J38+N38+R38+V38 -> 123932583 | E38: 398749953 | F38: 107198293 | I38: 55899494 | J38: 16734290 | K38: 12288933 | L38: 1419499 | M38: 1132424 | O38: 283106 | U38: 475945 | W38: 448568 | Y38: =+W38+S38+O38+K38 -> 13020607 | Z38: =+X38+T38+P38+L38 -> 1419499 | AA38: =+'Aging Analysis'!C27 -> 456257816 | CH38: ='Aging Analysis'!C27 -> 456257816
B39: из них необеспеченные | C39: =E39+I39+M39+Q39+U39 -> 0 | D39: =F39+J39+N39+R39+V39 -> 0 | Y39: =+W39+S39+O39+K39 -> 0 | Z39: =+X39+T39+P39+L39 -> 0
A40: 17 | B40: Строительство | C40: =E40+I40+M40+Q40+U40 -> 278011863 | D40: =F40+J40+N40+R40+V40 -> 0 | E40: 159764320 | I40: 114401332 | K40: 11742961 | U40: 3846211 | W40: 577257 | Y40: =+W40+S40+O40+K40 -> 12320218 | Z40: =+X40+T40+P40+L40 -> 0 | AA40: =+'Aging Analysis'!C28 -> 278011863 | CH40: ='Aging Analysis'!C28 -> 278011863
B41: из них необеспеченные | C41: =E41+I41+M41+Q41+U41 -> 0 | D41: =F41+J41+N41+R41+V41 -> 0 | Y41: =+W41+S41+O41+K41 -> 0 | Z41: =+X41+T41+P41+L41 -> 0
A42: 18 | B42: Торговля и общественное питание | C42: =E42+I42+M42+Q42+U42 -> 434569981 | D42: =F42+J42+N42+R42+V42 -> 156537292 | E42: 372609817 | F42: 156537292 | I42: 54262075 | K42: 13721089 | M42: 2115014 | O42: 528754 | Q42: 550000 | S42: 275000 | U42: 5033075 | W42: 1223075 | Y42: =+W42+S42+O42+K42 -> 15747918 | Z42: =+X42+T42+P42+L42 -> 0 | AA42: =+'Aging Analysis'!C29 -> 434569981 | CH42: ='Aging Analysis'!C29 -> 434569981
B43: из них необеспеченные | C43: =E43+I43+M43+Q43+U43 -> 0 | D43: =F43+J43+N43+R43+V43 -> 0 | Y43: =+W43+S43+O43+K43 -> 0 | Z43: =+X43+T43+P43+L43 -> 0
A44: 19 | B44: Материально-техническое снабжение и сбыт | C44: =E44+I44+M44+Q44+U44 -> 606092084 | D44: =F44+J44+N44+R44+V44 -> 402775195 | E44: 520009340 | F44: 373065594 | I44: 78703760 | J44: 29709601 | K44: 13367757 | L44: 4125161 | M44: 2400000 | O44: 600000 | Q44: 1755000 | S44: 877498 | U44: 3223984 | W44: 3200000 | Y44: =+W44+S44+O44+K44 -> 18045255 | Z44: =+X44+T44+P44+L44 -> 4125161 | AA44: =+'Aging Analysis'!C30 -> 606092084 | CH44: ='Aging Analysis'!C30 -> 606092084
B45: из них необеспеченные | C45: =E45+I45+M45+Q45+U45 -> 0 | D45: =F45+J45+N45+R45+V45 -> 0 | Y45: =+W45+S45+O45+K45 -> 0 | Z45: =+X45+T45+P45+L45 -> 0
A46: 20 | B46: Жилищно-коммунальные услуги | C46: =E46+I46+M46+Q46+U46 -> 100878106 | D46: =F46+J46+N46+R46+V46 -> 0 | E46: 74469220 | I46: 25895462 | K46: 6613543 | M46: 513424 | O46: 127922 | Y46: =+W46+S46+O46+K46 -> 6741465 | Z46: =+X46+T46+P46+L46 -> 0 | AA46: =+'Aging Analysis'!C31 -> 100878106 | CH46: ='Aging Analysis'!C31 -> 100878106
B47: из них необеспеченные | C47: =E47+I47+M47+Q47+U47 -> 0 | D47: =F47+J47+N47+R47+V47 -> 0 | Y47: =+W47+S47+O47+K47 -> 0 | Z47: =+X47+T47+P47+L47 -> 0
A48: 21 | B48: Другие сектора | C48: =E48+I48+M48+Q48+U48 -> 615722460 | D48: =F48+J48+N48+R48+V48 -> 4629714 | E48: 597405240 | F48: 4629714 | I48: 17974863 | K48: 4365174 | M48: 341924 | O48: 85453 | Q48: 433 | S48: 216 | Y48: =+W48+S48+O48+K48 -> 4450843 | Z48: =+X48+T48+P48+L48 -> 0 | AA48: =+'Aging Analysis'!C32 -> 615722460 | CH48: ='Aging Analysis'!C32 -> 615722460
B49: из них необеспеченные | C49: =E49+I49+M49+Q49+U49 -> 0 | D49: =F49+J49+N49+R49+V49 -> 0 | Y49: =+W49+S49+O49+K49 -> 0 | Z49: =+X49+T49+P49+L49 -> 0 | AA49: =+'Aging Analysis'!C33 -> 0
A50: 22 | B50: Итого кредита и лизинга | C50: =+C34+C36+C38+C40+C42+C44+C46+C48 -> 4772374677 | D50: =+D34+D36+D38+D40+D42+D44+D46+D48 -> 1578302325 | E50: =+E34+E36+E38+E40+E42+E44+E46+E48 -> 4002830821 | F50: =+F34+F36+F38+F40+F42+F44+F46+F48 -> 1320302605 | G50: =+G34+G36+G38+G40+G42+G44+G46+G48 -> 0 | H50: =+H34+H36+H38+H40+H42+H44+H46+H48 -> 0 | I50: =+I34+I36+I38+I40+I42+I44+I46+I48 -> 741934626 | J50: =+J34+J36+J38+J40+J42+J44+J46+J48 -> 257539137 | ... Z50: =+Z34+Z36+Z38+Z40+Z42+Z44+Z46+Z48 -> 18643778 | AA50: =+'Aging Analysis'!C34 -> 4772374677 | CH50: ='Aging Analysis'!C34 -> 4772374677
B51: из них необеспеченные | C51: =+C35+C37+C39+C41+C43+C45+C47+C49 -> 0 | D51: =+D35+D37+D39+D41+D43+D45+D47+D49 -> 0 | E51: =+E35+E37+E39+E41+E43+E45+E47+E49 -> 0 | F51: =+F35+F37+F39+F41+F43+F45+F47+F49 -> 0 | G51: =+G35+G37+G39+G41+G43+G45+G47+G49 -> 0 | H51: =+H35+H37+H39+H41+H43+H45+H47+H49 -> 0 | I51: =+I35+I37+I39+I41+I43+I45+I47+I49 -> 0 | J51: =+J35+J37+J39+J41+J43+J45+J47+J49 -> 0 | ... Z51: =+Z35+Z37+Z39+Z41+Z43+Z45+Z47+Z49 -> 0
B52: По регионам | AA52: =+'[2]Aging Analysis'!C42 -> 0
A54: 23 | B54: Республика Каракалпакстан | C54: =E54+I54+M54+Q54+U54 -> 252434523 | D54: =F54+J54+N54+R54+V54 -> 9199713 | E54: 195830774 | F54: 0 | I54: 55073193 | J54: 8739130 | K54: 11968259 | L54: 1967891 | M54: 1524613 | N54: 460583 | O54: 381154 | P54: 115146 | Q54: 0 | S54: 0 | U54: 5943 | W54: 5943 | Y54: =+W54+S54+O54+K54 -> 12355356 | Z54: =+X54+T54+P54+L54 -> 2083037 | AA54: =+'[2]Aging Analysis'!C43 -> 0 | CH54: ='[2]Aging Analysis'!C43 -> 0
A55: 24 | B55: Андижанская область | C55: =E55+I55+M55+Q55+U55 -> 164558784 | D55: =F55+J55+N55+R55+V55 -> 18164858 | E55: 160554040 | F55: 18164858 | I55: 3664303 | J55: 0 | K55: 614656 | L55: 0 | M55: 32541 | N55: 0 | O55: 8105 | P55: 0 | Q55: 0 | S55: 0 | U55: 307900 | W55: 2541 | Y55: =+W55+S55+O55+K55 -> 625302 | Z55: =+X55+T55+P55+L55 -> 0
A56: 25 | B56: Бухарская область | C56: =E56+I56+M56+Q56+U56 -> 234866139 | D56: =F56+J56+N56+R56+V56 -> 20878676 | E56: 203584850 | F56: 13949476 | I56: 31136646 | J56: 6929200 | K56: 2630666 | L56: 639919 | M56: 0 | N56: 0 | O56: 0 | P56: 0 | Q56: 11049 | S56: 5520 | U56: 133594 | W56: 0 | Y56: =+W56+S56+O56+K56 -> 2636186 | Z56: =+X56+T56+P56+L56 -> 639919 | AA56: =+'[2]Aging Analysis'!C44 -> 0 | CH56: ='[2]Aging Analysis'!C44 -> 0
A57: 26 | B57: Джизакская область | C57: =E57+I57+M57+Q57+U57 -> 224943112 | D57: =F57+J57+N57+R57+V57 -> 36813673 | E57: 179862021 | F57: 31202613 | I57: 44928590 | J57: 5611060 | K57: 4392134 | L57: 743078 | M57: 1665 | N57: 0 | O57: 416 | P57: 0 | Q57: 18736 | S57: 9369 | U57: 132100 | W57: 132100 | Y57: =+W57+S57+O57+K57 -> 4534019 | Z57: =+X57+T57+P57+L57 -> 743078
A58: 27 | B58: Кашкадарьинская область | C58: =E58+I58+M58+Q58+U58 -> 462044449 | D58: =F58+J58+N58+R58+V58 -> 108007006 | E58: 373873311 | F58: 69583268 | I58: 75888197 | J58: 38423738 | K58: 11268090 | L58: 1157873 | M58: 2400000 | N58: 0 | O58: 600000 | P58: 0 | Q58: 1150769 | S58: 575216 | U58: 8732172 | W58: 5015918 | Y58: =+W58+S58+O58+K58 -> 17459224 | Z58: =+X58+T58+P58+L58 -> 1157873 | AA58: =+'[2]Aging Analysis'!C45 -> 0 | CH58: ='[2]Aging Analysis'!C45 -> 0
A59: 28 | B59: Навоийская область | C59: =E59+I59+M59+Q59+U59 -> 170340853 | D59: =F59+J59+N59+R59+V59 -> 9141768 | E59: 143577410 | F59: 8323046 | I59: 26763443 | J59: 818722 | K59: 2558724 | L59: 74918 | M59: 0 | N59: 0 | O59: 0 | P59: 0 | Q59: 0 | S59: 0 | U59: 0 | W59: 0 | Y59: =+W59+S59+O59+K59 -> 2558724 | Z59: =+X59+T59+P59+L59 -> 74918
A60: 29 | B60: Наманганская область | C60: =E60+I60+M60+Q60+U60 -> 264951765 | D60: =F60+J60+N60+R60+V60 -> 21757314 | E60: 217618310 | F60: 6097071 | I60: 46761967 | J60: 15660243 | K60: 7656231 | L60: 1673172 | M60: 417289 | N60: 0 | O60: 103893 | P60: 0 | Q60: 421 | S60: 211 | U60: 153778 | W60: 15378 | Y60: =+W60+S60+O60+K60 -> 7775713 | Z60: =+X60+T60+P60+L60 -> 1673172 | AA60: =+'[2]Aging Analysis'!C46 -> 0 | CH60: ='[2]Aging Analysis'!C46 -> 0
A61: 30 | B61: Самаркандская область | C61: =E61+I61+M61+Q61+U61 -> 374628458 | D61: =F61+J61+N61+R61+V61 -> 17353533 | E61: 279920386 | F61: 9848295 | I61: 91744199 | J61: 7505238 | K61: 10674672 | L61: 600706 | M61: 26556 | N61: 0 | O61: 6646 | P61: 0 | Q61: 0 | S61: 0 | U61: 2937317 | W61: 294 | Y61: =+W61+S61+O61+K61 -> 10681612 | Z61: =+X61+T61+P61+L61 -> 600706
A62: 31 | B62: Сурхандарьинская область | C62: =E62+I62+M62+Q62+U62 -> 588033245 | D62: =F62+J62+N62+R62+V62 -> 258375827 | E62: 413038048 | F62: 131550560 | I62: 173687160 | J62: 126825267 | K62: 21744396 | L62: 7489864 | M62: 708037 | N62: 0 | O62: 177027 | P62: 0 | Q62: 600000 | S62: 300000 | U62: 0 | W62: 0 | Y62: =+W62+S62+O62+K62 -> 22221423 | Z62: =+X62+T62+P62+L62 -> 7489864 | AA62: =+'[2]Aging Analysis'!C47 -> 0 | CH62: ='[2]Aging Analysis'!C47 -> 0
A63: 32 | B63: Сырдарьинская область | C63: =E63+I63+M63+Q63+U63 -> 227548296 | D63: =F63+J63+N63+R63+V63 -> 104919025 | E63: 181463372 | F63: 74539621 | I63: 46081759 | J63: 30379404 | K63: 11526808 | L63: 2302680 | M63: 3165 | N63: 0 | O63: 795 | P63: 0 | Q63: 0 | S63: 0 | U63: 0 | W63: 0 | Y63: =+W63+S63+O63+K63 -> 11527603 | Z63: =+X63+T63+P63+L63 -> 2302680
A64: 33 | B64: Ташкентская область | C64: =E64+I64+M64+Q64+U64 -> 337780737 | D64: =F64+J64+N64+R64+V64 -> 122676571 | E64: 301090999 | F64: 113340608 | I64: 31777764 | J64: 9335963 | K64: 5910181 | L64: 1342141 | M64: 2605364 | N64: 0 | O64: 651342 | P64: 0 | Q64: 955000 | S64: 477499 | U64: 1351610 | W64: 21742 | Y64: =+W64+S64+O64+K64 -> 7060764 | Z64: =+X64+T64+P64+L64 -> 1342141 | AA64: =+'[2]Aging Analysis'!C48 -> 0 | CH64: ='[2]Aging Analysis'!C48 -> 0
A65: 34 | B65: Ферганская область | C65: =E65+I65+M65+Q65+U65 -> 169002895 | D65: =F65+J65+N65+R65+V65 -> 17214062 | E65: 144704753 | F65: 17214062 | I65: 22219382 | J65: 0 | K65: 4921287 | L65: 0 | M65: 1484200 | N65: 0 | O65: 370952 | P65: 0 | Q65: 594560 | S65: 298640 | U65: 0 | W65: 0 | Y65: =+W65+S65+O65+K65 -> 5590879 | Z65: =+X65+T65+P65+L65 -> 0
A66: 35 | B66: Хорезмская область | C66: =E66+I66+M66+Q66+U66 -> 189615721 | D66: =F66+J66+N66+R66+V66 -> 23849646 | E66: 173904067 | F66: 21619840 | I66: 14707271 | J66: 2229806 | K66: 4571185 | L66: 222981 | M66: 774138 | N66: 0 | O66: 193536 | P66: 0 | Q66: 200000 | S66: 99999 | U66: 30245 | W66: 30246 | Y66: =+W66+S66+O66+K66 -> 4894966 | Z66: =+X66+T66+P66+L66 -> 222981 | AA66: =+'[2]Aging Analysis'!C49 -> 0 | CH66: ='[2]Aging Analysis'!C49 -> 0
A67: 36 | B67: г. Ташкент | C67: =E67+I67+M67+Q67+U67 -> 1111625700 | D67: =F67+J67+N67+R67+V67 -> 809950653 | E67: 1033808480 | F67: 804869287 | I67: 77500752 | J67: 5081366 | K67: 9687458 | L67: 313409 | M67: 0 | N67: 0 | O67: 0 | P67: 0 | Q67: 0 | S67: 0 | U67: 316468 | W67: 316468 | Y67: =+W67+S67+O67+K67 -> 10003926 | Z67: =+X67+T67+P67+L67 -> 313409
A68: 37 | B68: Итого кредита и лизинга | C68: =SUM(C54:C67) -> 4772374677 | D68: =SUM(D54:D67) -> 1578302325 | E68: =SUM(E54:E67) -> 4002830821 | F68: =SUM(F54:F67) -> 1320302605 | G68: =SUM(G54:G67) -> 0 | H68: =SUM(H54:H67) -> 0 | I68: =SUM(I54:I67) -> 741934626 | J68: =SUM(J54:J67) -> 257539137 | ... Z68: =SUM(Z54:Z67) -> 18643778 | AA68: =+'[2]Aging Analysis'!C51 -> 0 | CH68: ='[2]Aging Analysis'!C51 -> 0
A69: 38 | B69: Другие классифицированные активы | C69: =E69+I69+M69+Q69+U69 -> 159478025 | D69: =F69+J69+N69+R69+V69 -> 142500641 | E69: 154418067 | F69: 142457488 | U69: 5059958 | V69: 43153 | W69: 5059956 | X69: 43153 | Y69: =+W69+S69+O69+K69 -> 5059956 | Z69: =+X69+T69+P69+L69 -> 43153
B70: из них необеспеченные | C70: =E70+I70+M70+Q70+U70 -> 0 | D70: =F70+J70+N70+R70+V70 -> 0 | Y70: =+W70+S70+O70+K70 -> 0 | Z70: =+X70+T70+P70+L70 -> 0
A71: 39 | B71: Всего классифицированных активов | C71: =+C50+C69 -> 4931852702 | D71: =+D50+D69 -> 1720802966 | E71: =+E50+E69 -> 4157248888 | F71: =+F50+F69 -> 1462760093 | G71: =+G50+G69 -> 0 | H71: =+H50+H69 -> 0 | I71: =+I50+I69 -> 741934626 | J71: =+J50+J69 -> 257539137 | ... Z71: =+Z50+Z69 -> 18686931
B74: Подпись Председателя правления:
B76: Подпись Главного Бухгалтера:
E77: =SUM('Asset quality'!D21:D47)+'Asset quality'!D16 -> 4002830821 | G77: =SUM('Asset quality'!O21:O47)+'Asset quality'!O16 -> 0 | I77: =SUM('Asset quality'!E21:E47)+'Asset quality'!E16 -> 741934626 | K77: =SUM('Asset quality'!P21:P47)+'Asset quality'!P16 -> 110124747 | M77: =SUM('Asset quality'!F21:F47) -> 9977568 | O77: =SUM('Asset quality'!Q21:Q47) -> 2493866 | Q77: =SUM('Asset quality'!G21:G47) -> 3530535 | S77: =SUM('Asset quality'!R21:R47) -> 1766454 | U77: =SUM('Asset quality'!H21:H47) -> 14101127 | W77: =SUM('Asset quality'!S21:S47)+'Asset quality'!S16 -> 5540630 | Y77: =+W77+S77+O77+K77 -> 119925697
G78: =+'Asset quality'!O9+'Asset quality'!O62 -> 0 | K78: =+'Asset quality'!P9+'Asset quality'!P62 -> 110124747 | O78: =+'Asset quality'!Q9+'Asset quality'!Q62 -> 2493866 | S78: =+'Asset quality'!R9+'Asset quality'!R62 -> 1766454 | W78: =+'Asset quality'!S9+'Asset quality'!S62 -> 10600586 | Y78: =+W78+S78+O78+K78 -> 124985653
E79: =+E77-E50 -> 0 | G79: =+G77-G50 -> 0 | I79: =+I77-I50 -> 0 | K79: =+K77-K50 -> 0 | M79: =+M77-M50 -> 0 | O79: =+O77-O50 -> 0 | Q79: =+Q77-Q50 -> 0 | S79: =+S77-S50 -> 0 | U79: =+U77-U50 -> 0 | W79: =+W77-W50 -> 0 | Y79: =+Y77-Y50 -> 0
G80: =+G78-G71 -> 0 | K80: =+K78-K71 -> 0 | O80: =+O78-O71 -> 0 | S80: =+S78-S71 -> 0 | W80: =+W78-W71 -> 0 | Y80: =+Y78-Y71 -> 0
AA85: =+Balance!C24 -> 119925697

Sheet Loans to Affiliated P.
A1: ОТЧЕТ О СДЕЛКАХ, ЗАКЛЮЧЕННЫХ СО СВЯЗАННЫМИ ЛИЦАМИ | R1: Таблица-11
B3: =Balance!B3 -> АКБ "Микрокредитбанк" | M3: =+Balance!C3 -> 43829 | R3: =+Balance!E3 -> тыс. сум
A4: № | B4: Наименования клиента | C4: ИНН | D4: Вид деятельности | E4: Код валюты | F4: Номер группы | G4: Текущая задолженность | H4: из них | M4: Пересмотрения | N4: Обеспечения | P4: Классификация | Q4: Резерв | R4: Источник кредита
H5: Кредиты и лизинги | I5: Инвестиции | J5: Аккредитивы | K5: Гарантии | L5: другие активы* | N5: Вид залога | O5: Сумма залога
B6: А | C6: Б | D6: В | E6: Г | F6: Д | G6: Е | H6: Е1 | I6: Е2 | J6: Е3 | K6: Е4 | L6: Е5 | M6: Ж | N6: З | O6: И | P6: К | Q6: Л | R6: М
A7: 1 | B7: Исматуллоев Акрам Акмалович | C7: AA5013105 | D7: Физические лица | E7: 000 | F7: 1 | G7: 252717.46 | H7: 252717.46 | P7: 1 | Q7: 0 | R7: 11-Собственные
A8: =A7+1 -> 2 | B8: Гуччиев Илхом Турсункулович | C8: CT1907643 | D8: Физические лица | E8: 000 | F8: 2 | G8: 61638.619 | H8: 61638.619 | P8: 1 | Q8: 0 | R8: 11-Собственные | S8: 1000
A9: =A8+1 -> 3 | B9: Пулатова Муниса Тоировна | C9: AA1343647 | D9: Физические лица | E9: 000 | F9: 3 | G9: 51185.211 | H9: 51185.211 | P9: 1 | Q9: 0 | R9: 11-Собственные
A10: =A9+1 -> 4 | B10: Умаров Сарвар Салахиддинович | C10: AB5528260 | D10: Физические лица | E10: 000 | F10: 4 | G10: 48668.24 | H10: 48668.24 | P10: 1 | Q10: 0 | R10: 11-Собственные
A11: =A10+1 -> 5 | B11: Ахмаджонов Абдулазиз Абдусатторович | C11: AA1266275 | D11: Физические лица | E11: 000 | F11: 5 | G11: 31012.128 | H11: 31012.128 | P11: 1 | Q11: 0 | R11: 11-Собственные
A12: =A11+1 -> 6 | B12: Тогаев Даврон Дусмамат уғли | C12: CT1881274 | D12: Физические лица | E12: 000 | F12: 6 | G12: 34527.646 | H12: 34527.646 | P12: 1 | Q12: 0 | R12: 11-Собственные
A13: =A12+1 -> 7 | B13: Саматов Юнус Уралович | C13: CS0384112 | D13: Физические лица | E13: 000 | F13: 7 | G13: 20939.249 | H13: 20939.249 | P13: 1 | Q13: 0 | R13: 11-Собственные
A14: =A13+1 -> 8 | B14: Каримкулов Хикматулло | C14: BG0108618 | D14: Физические лица | E14: 000 | F14: 8 | G14: 18178.647 | H14: 18178.647 | P14: 1 | Q14: 0 | R14: 11-Собственные
A15: =A14+1 -> 9 | B15: Саксонов Азизбек Нурбобоевич | C15: CE2612031 | D15: Физические лица | E15: 000 | F15: 9 | G15: 14826.673 | H15: 14826.673 | P15: 1 | Q15: 0 | R15: 11-Собственные
A16: =A15+1 -> 10 | B16: Бабаджанов Шухрат Адилбекович | C16: AA1901433 | D16: Физические лица | E16: 000 | F16: 10 | G16: 10416.13 | H16: 10416.13 | P16: 1 | Q16: 0 | R16: 11-Собственные
A17: =A16+1 -> 11 | B17: Бегматов Бобур Яхшиевич | C17: CN2398457 | D17: Физические лица | E17: 000 | F17: 11 | G17: 13914 | H17: 13914 | P17: 3 | Q17: 0 | R17: 11-Собственные
A18: =A17+1 -> 12 | B18: Муминов Юсуп Машарипович | C18: CE2162465 | D18: Физические лица | E18: 000 | F18: 12 | G18: 9952.7389 | H18: 9952.7389 | P18: 1 | Q18: 0 | R18: 11-Собственные
A19: =A18+1 -> 13 | B19: Жалолов Бегзод Кодиркулович | C19: CT2349128 | D19: Физические лица | E19: 000 | F19: 13 | G19: 9100 | H19: 9100 | P19: 2 | Q19: 0 | R19: 11-Собственные
A20: =A19+1 -> 14 | B20: Мирзанов Толиб Исломович | C20: CT0670437 | D20: Физические лица | E20: 000 | F20: 14 | G20: 7636.368 | H20: 7636.368 | P20: 1 | Q20: 0 | R20: 11-Собственные
... A37: =A36+1 -> 31 | B37: Кушназаров Акбар Нарханович | C37: AA1814951 | D37: Физические лица | E37: 000 | F37: 32 | G37: 30811.316 | H37: 30811.316 | P37: 1 | Q37: 0 | R37: 11-Собственные
A38: =A37+1 -> 32 | B38: Все остальные физические лица (197 человек) | D38: Физические лица | G38: 389169 | H38: 389169
A39: ИТОГО АКТИВОВ ПО СВЯЗАННЫМ ЛИЦАМ | G39: =SUM(G7:G38) -> 1143633.5 | H39: =SUM(H7:H38) -> 1143633.5 | I39: =SUM(I7:I38) -> 0 | J39: =SUM(J7:J38) -> 0 | K39: =SUM(K7:K38) -> 0 | L39: =SUM(L7:L38) -> 0 | O39: =SUM(O7:O38) -> 0
A40: САМЫЙ КРУПНЫЙ АКТИВ, ВЫДАННЫЙ БАНКОМ ОДНОМУ ИНСАЙДЕРУ | G40: =MAX(G7:G38) -> 389169 | H40: =MAX(H7:H38) -> 389169 | I40: =MAX(I7:I38) -> 0 | J40: =MAX(J7:J38) -> 0 | K40: =MAX(K7:K38) -> 0 | L40: =MAX(L7:L38) -> 0 | O40: =MAX(O7:O38) -> 0
B43: Подпись Председателя правления:
B45: Подпись Главного Бухгалтера:
B47: *Примечание: -например беспроцентные доходы, ценные бумаги, овердрафт, средства в других банках, имущество проданное в рассрочку и т.д.

Sheet  Largest risk
A1: ОТЧЕТ О КРУПНЫХ РИСКАХ | R1: Таблица-12
B3: =Balance!B3 -> АКБ "Микрокредитбанк" | M3: =+Balance!C3 -> 43829 | N3: =+Balance!C3 -> 43829 | R3: =+Balance!E3 -> тыс. сум
A4: № | B4: Наименования клиента | C4: ИНН | D4: Вид деятельности | E4: Код валюты | F4: Номер группы | G4: Текущая задолженность | H4: из них | M4: Пересмотрения | N4: Обеспечения | P4: Классификация | Q4: Резерв | R4: Источник кредита
H5: Кредиты и лизинги | I5: Инвестиции | J5: Аккредитивы | K5: Гарантии | L5: другие активы* | N5: Вид залога | O5: Сумма залога
B6: А | C6: Б | D6: В | E6: Г | F6: Д | G6: Е | H6: Е1 | I6: Е2 | J6: Е3 | K6: Е4 | L6: Е5 | M6: Ж | N6: З | O6: И | P6: К | Q6: Л | R6: М
A7: 1 | B7: ООО "SESAME" | C7: 306892604 | D7: нефт | E7: 840 | F7: 1 | G7: =SUM(H7:L7) -> 280732915 | H7: 280732915 | P7: 1 | Q7: 0 | R7: 11-Собственные | T7: 0
A8: 2 | B8: ИП ООО "EPSILON DEVELOPMENT COMPANY" | C8: 305922787 | D8: нефт | E8: 840 | F8: 2 | G8: =SUM(H8:L8) -> 400825035 | H8: 400825035 | P8: 1 | Q8: 0 | R8: 11-Собственные
A9: 3 | G9: =SUM(H9:L9) -> 0
A10: 4 | G10: =SUM(H10:L10) -> 0
A11: 5 | G11: =SUM(H11:L11) -> 0
A12: 6 | G12: =SUM(H12:L12) -> 0
A13: 7 | G13: =SUM(H13:L13) -> 0
A14: 8 | G14: =SUM(H14:L14) -> 0
A15: 9 | G15: =SUM(H15:L15) -> 0
A16: 10 | G16: =SUM(H16:L16) -> 0
A17: 11 | G17: =SUM(H17:L17) -> 0
A18: 12 | G18: =SUM(H18:L18) -> 0
A19: 13 | G19: =SUM(H19:L19) -> 0
A20: 14 | G20: =SUM(H20:L20) -> 0
... A66: 60 | G66: =SUM(H66:L66) -> 0
B67: ИТОГО КРУПНЫХ АКТИВОВ | G67: =SUM(G7:G66) -> 681557950 | H67: =SUM(H7:H66) -> 681557950 | I67: =SUM(I7:I66) -> 0 | J67: =SUM(J7:J66) -> 0 | K67: =SUM(K7:K66) -> 0 | L67: =SUM(L7:L66) -> 0 | O67: =SUM(O7:O66) -> 0
B68: САМЫЙ КРУПНЫЙ АКТИВ, ВЫДАННЫЙ БАНКОМ | G68: =MAX(G7:G66) -> 400825035 | H68: =MAX(H7:H66) -> 400825035 | I68: =MAX(I7:I66) -> 0 | J68: =MAX(J7:J66) -> 0 | K68: =MAX(K7:K66) -> 0 | L68: =MAX(L7:L66) -> 0 | O68: =MAX(O7:O66) -> 0
B71: Подпись Председателя правления:
B73: Подпись Главного Бухгалтера:
B76: *Примечание: -например беспроцентные доходы, ценные бумаги, овердрафт, средства в других банках, имущество проданное в рассрочку и т.д.

Sheet Charge-offs and Recoveries
A1: ОТЧЕТ О CПИСАННЫХ И ВОЗВРАЩЕННЫХ ПЛАТЕЖАХ ИЗ РЕЗЕРВА ВОЗМОЖНЫХ ПОТЕРЬ ПО КРЕДИТАМ И ЛИЗИНГУ | E1: Таблица-13
A3: Часть 1 Списания и возврат | B3: =Balance!B3 -> АКБ "Микрокредитбанк" | E3: =+Balance!B2 -> 30 Декабрь, 2019
A4: Отрасль экономики | B4: Списание - А | D4: Возврат - Б
B5: Всего | C5: в иностранной валюте | D5: Всего | E5: в иностранной валюте
A6: А | B6: Б | C6: В | D6: Г | E6: Д
A7: 1. Промышленность | B7: 1816473 | C7: 0 | D7: 516697 | E7: 0
A8: 2. Сельское хозяйство | B8: 5366960 | C8: 0 | D8: 4396131 | E8: 0
A9: 3. Транспорт и коммуникации | B9: 65065 | C9: 0 | D9: 210170 | E9: 0
A10: 4. Строительство | B10: 850135 | C10: 0 | D10: 888585 | E10: 0
A11: 5. Торговля и общественное питание | B11: 2597913 | C11: 0 | D11: 2760536 | E11: 0
A12: 6. Материально-техническое снабжение и сбыт | B12: 0 | C12: 0 | D12: 0 | E12: 0
A13: 7. Жилищно-коммунальные услуги | B13: 0 | C13: 0 | D13: 0 | E13: 0
A14: 8. Другие сектора | B14: 1502376 | C14: 0 | D14: 1466409 | E14: 0
A15: 9. Итого | B15: =SUM(B7:B14) -> 12198922 | C15: =SUM(C7:C14) -> 0 | D15: =SUM(D7:D14) -> 10238528 | E15: =SUM(E7:E14) -> 0
A18: Часть 2
A19: Изменения в резерве возможных убытков по кредитам и лизингу
A20: 1. Остаток на начало текущего года | C20: 63498748
A21: 2. Плюс: Возвращенные платежи | C21: =D15 -> 10238528
A22: 3. Минус: Списанные кредиты и лизинги | B22: 0 | C22: =B15 -> 12198922
A23: 4. Отчисления в резерв по состоянию на дату от начала года | C23: =+'Income '!C31 -> 139622948
A24: 5. Поправки | C24: -81235605 | H24: =+'Income '!C31 -> 139622948
A25: 6. Текущий баланс | C25: =SUM(C20:C21)-C22+SUM(C23:C24) -> 119925697 | F25: =+'Asset Classification'!Y50 -> 119925697 | H25: ='Asset Classification'!Y50 -> 119925697
A28: Подпись Председателя правления:
A30: Подпись Главного Бухгалтера:

Sheet Deposits by Client
A1: ОТЧЕТ О ДЕПОЗИТАХ ПО ТИПАМ КЛИЕНТОВ | D1: Таблица-14
B2: =+Balance!B3 -> АКБ "Микрокредитбанк" | C2: =+Balance!B2 -> 30 Декабрь, 2019 | D2: в тыс. сум
A3: № | B3: Категории | C3: Итого | D3: из них, в иностранной валюте (в экв. в сумах)
A4: 1. | B4: Депозиты до востребования
A5: а. | B5: Правительство | C5: 880965 | D5: 179548
A6: б. | B6: Физические лица | C6: 138847610 | D6: 7672786
A7: в. | B7: Государственные предприятия | C7: 24695061 | D7: 767726
A8: г. | B8: Совместные и иностранные предприятия | C8: 3741553 | D8: 190152
A9: д. | B9: Частные товарищества и корпорации | C9: 144253948 | D9: 4935177
A10: е. | B10: Другие депозиты до востребования | C10: 99500617 | D10: 21632023
A11: ж. | B11: Итого депозитов до востребования | C11: =SUM(C5:C10) -> 411919754 | D11: =SUM(D5:D10) -> 35377412 | E11: =+'Bank Liabilities Analysis'!S16+'Bank Liabilities Analysis'!S8 -> 411919754 | F11: =+'Bank Liabilities Analysis'!T16+'Bank Liabilities Analysis'!T8 -> 376542342 | G11: =+'Bank Liabilities Analysis'!U16+'Bank Liabilities Analysis'!U8 -> 35377412
A13: 2. | B13: Срочные депозиты
A14: а. | B14: Правительство | C14: 411007192 | D14: 142745550
A15: б. | B15: Физические лица | C15: 211599363 | D15: 4862025
A16: в. | B16: Государственные предприятия | C16: 182330832 | D16: 100902897
A17: г. | B17: Совместные и иностранные предприятия | C17: 5275000 | D17: 0
A18: д. | B18: Частные товарищества и корпорации | C18: 35398407 | D18: 0
A19: е. | B19: Другие cрочные депозиты | C19: 134908058 | D19: 11835661
A20: ж. | B20: Итого срочных депозитов | C20: =SUM(C14:C19) -> 980518852 | D20: =SUM(D14:D19) -> 260346133 | E20: =+'Bank Liabilities Analysis'!S13 -> 980518852 | F20: =+'Bank Liabilities Analysis'!T13 -> 720172719 | G20: =+'Bank Liabilities Analysis'!U13 -> 260346133
A22: 3. | B22: Итого депозитов | C22: =+C11+C20 -> 1392438606 | D22: =+D11+D20 -> 295723545 | E22: =+'Bank Liabilities Analysis'!S22 -> 1392438606 | F22: =+'Bank Liabilities Analysis'!T22 -> 1096715061 | G22: =+'Bank Liabilities Analysis'!U22 -> 295723545
B25: Подпись Председателя правления:
B27: Подпись Главного Бухгалтера:

Sheet Investment Securities
A1: ОТЧЕТ ОБ ИНВЕСТИЦИЯХ В ЦЕННЫЕ БУМАГИ И СЧЕТА КУПЛИ-ПРОДАЖИ АКТИВОВ | E1: Таблица-15
A2: =Balance!B3 -> АКБ "Микрокредитбанк" | C2: =+Balance!B2 -> 30 Декабрь, 2019 | E2: =+Balance!E3 -> тыс. сум
A3: Часть 1 - Инвестиции в ценные бумаги | B3: Балансовая стоимость | C3: Балансовая стоимость | E3: Рыночная стоимость
C4: в национальной валюте | D4: в иностранной валюте (в экв. в сумах)
A6: 1. Инвестиции в государственные облигации | B6: =+C6+D6 -> 0
A7: 2. Инвестиции в ценные бумаги и облигации ЦБРУ | B7: =+C7+D7 -> 0
A8: 3. Инвестиции в частные облигации | B8: =+C8+D8 -> 0
A9: 4. Инвестиции в еврооблигации | B9: =+C9+D9 -> 0
A10: 5. Инвестиции в акции гос предприятий | B10: =+C10+D10 -> 0 | C10: 0 | D10: 0 | E10: 341924
A11: 6. Инвестиции в акции частных предприятий | B11: =+C11+D11 -> 70220 | C11: 70220
A12: 7. Инвестиции в другие ценные бумаги | B12: =+C12+D12 -> 6871704 | C12: =6600000+271704 -> 6871704 | D12: 0 | E12: 6600000
A13: 8. Итого инвестиций | B13: =+C13+D13 -> 6941924 | C13: =SUM(C6:C12) -> 6941924 | D13: =SUM(D6:D12) -> 0 | E13: =SUM(E6:E12) -> 6941924
A14: 9. Минус: Резерв возможных убытков | B14: =+C14+D14 -> 271704 | C14: 271704
A15: 10. Чистая балансовая стоимость инвестиций | B15: =+C15+D15 -> 6670220 | C15: =C13-C14 -> 6670220 | D15: =D13-D14 -> 0 | F15: =+'Bank Assets Analysis'!S27 -> 6670220 | G15: =+'Bank Assets Analysis'!T27 -> 6670220 | H15: =+'Bank Assets Analysis'!U27 -> 0
A17: Часть 2 - Счета купли-продажи ценных бумаг | B17: Балансовая стоимость | C17: в национальной валюте | D17: в иностранной валюте (в экв. в сумах) | E17: Рыночная стоимость | F17: =+Balance!C16 -> 6670220 | G17: =+Balance!D16 -> 6670220 | H17: =+Balance!E16 -> 0
A19: 1. Государственные казначейские векселя | B19: =+C19+D19 -> 0 | C19: 0
A20: 2. Государственные облигации | B20: =+C20+D20 -> 119576827 | C20: 119576827 | D20: 0 | E20: 119576827
A21: 3. Ценные бумаги и облигации ЦБРУ | B21: =+C21+D21 -> 0
A22: 4. Ценные бумаги гос корпораций | B22: =+C22+D22 -> 0
A23: 5. Еврооблигации | B23: =+C23+D23 -> 0
A24: 6. Частные ценные бумаги | B24: =+C24+D24 -> 0
A25: 7. Другие ценные бумаги | B25: =+C25+D25 -> 0
A26: 8. Итого по счетам купли-продажи ценных бумаг | B26: =+C26+D26 -> 119576827 | C26: =SUM(C19:C25) -> 119576827 | D26: =SUM(D19:D25) -> 0 | E26: =SUM(E19:E25) -> 119576827
A27: 9. Минус: Резерв возможных убытков | B27: =+C27+D27 -> 0
A28: 10. Чистая балансовая стоимость по счетам купли-продажи ц/б | B28: =+C28+D28 -> 119576827 | C28: =C26-C27 -> 119576827 | D28: =D26-D27 -> 0
A32: Часть 3 - Счета купли и продажи драгоценных металлов | B32: Первоначальная стоимость | C32: в национальной валюте | D32: в иностранной валюте (в экв. в сумах) | E32: Рыночная стоимость
A34: 1. Драгоценные металлы | B34: =+C34+D34 -> 0 | C34: 0
A35: 2. Драгоценные камни | B35: =+C35+D35 -> 0 | C35: 0
A36: 3. Драгоценные монеты | B36: =+C36+D36 -> 175 | C36: 175 | E36: 174.702
A37: 4. Итого драгоценных металлов | B37: =+C37+D37 -> 175 | C37: =SUM(C34:C36) -> 175 | D37: =SUM(D34:D36) -> 0 | E37: =SUM(E34:E36) -> 174.702
A38: 5. Минус: Резерв возможных убытков | B38: =+C38+D38 -> 0
A39: 6. Чистая балансовая стоимость по счетам купли и продажи д/м | B39: =+C39+D39 -> 175 | C39: =C37-C38 -> 175 | D39: =D37-D38 -> 0
A41: Примечание:
A42: Итого ценных бумаг заложенных для общественных депозитов
A43: Портфель инвестиций в ценные бумаги
A44: Увеличение (Снижение) стоимости | B44: =E13-B13 -> 0
A45: Счета купли-продажи ценных бумаг
A46: Увеличение (Снижение) стоимости | B46: =E26-B26 -> 0
A47: Счета купли-продажи драгоценных предметов
A48: Увеличение (Снижение) стоимости | B48: =E37-B37 -> -0.298
A51: Подпись Председателя правления:
A53: Подпись Главного Бухгалтера:

Sheet Liquidity Analysis
B1: АНАЛИЗ ЛИКВИДНОСТИ | E1: Таблица-16
B2: =Balance!B3 -> АКБ "Микрокредитбанк" | C2: =+Balance!B2 -> 30 Декабрь, 2019 | E2: в тыс. сум
A3: № | B3: Часть 1. Ликвидные активы | C3: Сумма | D3: Нацвалюта | E3: Инвалюта
A5: 1. | B5: Касса (наличность и монеты) и Драгоценные металлы | C5: =+'Bank Assets Analysis'!S7+'Investment Securities'!B39 -> 173211752 | D5: =+'Bank Assets Analysis'!T7+'Investment Securities'!C39 -> 69805307 | E5: =+'Bank Assets Analysis'!U7+'Investment Securities'!D39 -> 103406445
A6: 2. | B6: К получению из ЦБРУ | C6: =+'Bank Assets Analysis'!S8+'Bank Assets Analysis'!S9 -> 140577780 | D6: =+'Bank Assets Analysis'!T8+'Bank Assets Analysis'!T9 -> 119493320 | E6: =+'Bank Assets Analysis'!U8+'Bank Assets Analysis'!U9 -> 21084460
A7: 3. | B7: К получению из других банков | C7: ='Bank Assets Analysis'!C11+'Bank Assets Analysis'!C13+'Bank Assets Analysis'!C14+'Bank Assets Analysis'!E14+'Bank Assets Analysis'!G14 -> 187559446 | D7: =+C7-E7 -> 1165678 | E7: ='Bank Assets Analysis'!D11+'Bank Assets Analysis'!D13+'Bank Assets Analysis'!D14+'Bank Assets Analysis'!F14+'Bank Assets Analysis'!H14 -> 186393768
A8: 3.1. | B8: К получению из других банков - Депозиты (чистые) | C8: =IF(F8>0,F8,0) -> 0 | D8: =IF(G8>0,G8,0) -> 0 | E8: =IF(H8>0,H8,0) -> 0 | F8: =(('Bank Assets Analysis'!E11+'Bank Assets Analysis'!G11+'Bank Assets Analysis'!C12+'Bank Assets Analysis'!E12+'Bank Assets Analysis'!G12)-'Bank Liabilities Analysis'!C25-'Bank Liabilities Analysis'!E25-'Bank Liabilities Analysis'!G25) -> -338682024 | G8: =+('Bank Assets Analysis'!E11-'Bank Assets Analysis'!F11+'Bank Assets Analysis'!G11-'Bank Assets Analysis'!H11+'Bank Assets Analysis'!C12-'Bank Assets Analysis'!D12+'Bank Assets Analysis'!E12-'Bank Assets Analysis'!F12+'Bank Assets Analysis'!G12-'Bank Assets Analysis'!H12)-('Bank Liabilities Analysis'!C25-'Bank Liabilities Analysis'!D25+'Bank Liabilities Analysis'!E25-'Bank Liabilities Analysis'!F25+'Bank Liabilities Analysis'!G25-'Bank Liabilities Analysis'!H25) -> -39826503 | H8: =(('Bank Assets Analysis'!F11+'Bank Assets Analysis'!H11+'Bank Assets Analysis'!D12+'Bank Assets Analysis'!F12+'Bank Assets Analysis'!H12)-'Bank Liabilities Analysis'!D25-'Bank Liabilities Analysis'!F25-'Bank Liabilities Analysis'!H25) -> -298855521
A9: 4. | B9: Ценные бумаги, выпущенные Правительством Республики Узбекистан и ЦБРУ (векселя, облигации и другие долговые ценные бумаги) | C9: 109174000 | D9: 109174000
A10: 5. | B10: Ценные бумаги, выпущенные странами с низким уровня риска | C10: 0 | D10: 0
A11: 6. | B11: Другие легко реализуемые ценные бумаги | C11: 10402827 | D11: 10402827
A12: 7. | B12: Итого ликвидных активов | C12: =SUM(C5:C11) -> 620925805 | D12: =SUM(D5:D11) -> 310041132 | E12: =SUM(E5:E11) -> 310884673
A13: 8. | B13: Плюс: Кредиты и лизинги со сроком погашения 30 дней или менее | C13: =+'Bank Assets Analysis'!C23+'Bank Assets Analysis'!C24+'Bank Assets Analysis'!C25+'Bank Assets Analysis'!C26+'Bank Assets Analysis'!E23+'Bank Assets Analysis'!E24+'Bank Assets Analysis'!E25+'Bank Assets Analysis'!E26+'Bank Assets Analysis'!G23+'Bank Assets Analysis'!G24+'Bank Assets Analysis'!G25+'Bank Assets Analysis'!G26 -> 141749847 | D13: =+C13-E13 -> 136259201 | E13: =+'Bank Assets Analysis'!D23+'Bank Assets Analysis'!D24+'Bank Assets Analysis'!D25+'Bank Assets Analysis'!D26+'Bank Assets Analysis'!F23+'Bank Assets Analysis'!F24+'Bank Assets Analysis'!F25+'Bank Assets Analysis'!F26+'Bank Assets Analysis'!H23+'Bank Assets Analysis'!H24+'Bank Assets Analysis'!H25+'Bank Assets Analysis'!H26 -> 5490646
A14: 9. | B14: Минус: Просроченные, неблагоприятно классифицированные, неначисляемые, пролонгированные, или реструктуризированные кредиты и лизинги, включенные в строку 8. | C14: =+'Bank Assets Analysis'!C25+'Bank Assets Analysis'!C26 -> 34083003 | D14: =+C14-E14 -> 31786074 | E14: =+'Bank Assets Analysis'!D25 -> 2296929
A15: 10. | B15: Текущие Активы | C15: =SUM(C12:C13)-C14 -> 728592649 | D15: =SUM(D12:D13)-D14 -> 414514259 | E15: =SUM(E12:E13)-E14 -> 314078390
B17: Часть 2. Коэфициенты наличности и ликвидности | C17: в процентах
A19: 2.1. | B19: Коэффициент наличности
A20: 2.1.1. | B20: Итого кассы разделить на
B21: среднее активов за текущий квартал | C21: =IF(C36=0,0,(C5/C36)) -> 0.033719481 | D21: =IF(D36=0,0,(D5/D36)) -> 0.020280167 | E21: =IF(E36=0,0,(E5/E36)) -> 0.061014051
A22: 2.2. | B22: Коэффициент ликвидности
A23: 2.2.1. | B23: Итого ликвидных активов разделить на
B24: среднее активов за текущий квартал | C24: =IF(C36=0,0,(C12/C36)) -> 0.12087688 | D24: =IF(D36=0,0,(D12/D36)) -> 0.090074614 | E24: =IF(E36=0,0,(E12/E36)) -> 0.18343473
A25: 2.3. | B25: Непостоянные обязательства/ среднее активов за текущий квартал
A26: 2.4. | B26: Ликвидные активы/ Непостоянные обязательства
A27: 2.5. | B27: Кредиты (чистые)/ Депозиты | C27: =IF('Deposits by Client'!E22=0,"",Balance!C22/'Deposits by Client'!E22) -> 3.3412238 | D27: =IF('Deposits by Client'!F22=0,"",Balance!D22/'Deposits by Client'!F22) -> 2.8200492 | E27: =IF('Deposits by Client'!G22=0,"",Balance!E22/'Deposits by Client'!G22) -> 5.2740425
A28: 2.6. | B28: Заложенные ценные бумаги/ Общая сумма ценных бумаг
B30: Часть 3. Экономические нормативы - Ликвидность
A32: 3.1. | B32: Расчет коэффициента текущей ликвидности (Н4) | C32: =IFERROR(+C15/F32,0) -> 0.61193935 | D32: =IFERROR(+D15/G32,0) -> 0.71825082 | E32: =IFERROR(+E15/H32,0) -> 0.51193474 | F32: =+(('Bank Liabilities Analysis'!C38+'Bank Liabilities Analysis'!E38+'Bank Liabilities Analysis'!G38-'Bank Liabilities Analysis'!C25-'Bank Liabilities Analysis'!E25-'Bank Liabilities Analysis'!G25)-(IF(F8<0,F8,0))) -> 1190628854 | G32: =+(('Bank Liabilities Analysis (нац)'!C37+'Bank Liabilities Analysis (нац)'!D37+'Bank Liabilities Analysis (нац)'!E37--'Bank Liabilities Analysis (нац)'!C24-'Bank Liabilities Analysis (нац)'!D24-'Bank Liabilities Analysis (нац)'!E24)-(IF(G8<0,G8,0))) -> 577116305 | H32: =+(('Bank Liabilities Analysis'!D38+'Bank Liabilities Analysis'!F38+'Bank Liabilities Analysis'!H38-'Bank Liabilities Analysis'!D25-'Bank Liabilities Analysis'!F25-'Bank Liabilities Analysis'!H25)-(IF(H8<0,H8,0))) -> 613512549
B35: Примечание:
B36: Укажите среднедневную сумму активов за текущий период, рассчитанную компьютерной системой действующей в банке. | C36: 5.1368451e+09 | D36: 3.4420479e+09 | E36: 1694797250 | H36: ='Bank Assets Analysis'!S38*(100%-20%) -> 4712217924 | I36: ='Bank Assets Analysis'!S38*(100%+20%) -> 7068326886
B37: Часть 4. | H37: ='Bank Assets Analysis'!T38*(100%-20%) -> 3151305572 | I37: ='Bank Assets Analysis'!T38*(100%+20%) -> 4726958358
A38: 4.1. | B38: Коэффициент покрытия ликвидности | C38: =IFERROR((+C39/C40),0) -> 0.90549095 | D38: =IFERROR((+D39/D40),0) -> 1.191982 | E38: =IFERROR((+E39/E40),0) -> 0.74878077 | H38: ='Bank Assets Analysis'!U38*(100%-20%) -> 1560912352 | I38: ='Bank Assets Analysis'!U38*(100%+20%) -> 2341368528
A39: 4.1.1. | B39: Высоколиквидные активы | C39: =+'Bank Assets Analysis'!AB41 -> 547901904 | D39: =+'Bank Assets Analysis (нац)'!P40 -> 255026112 | E39: =+'Bank Assets Analysis'!AD41 -> 292875792
A40: 4.1.2. | B40: Чистый отток в последующие 30 дней | C40: =+'Bank Assets Analysis'!AB42 -> 6.0508822e+08 | D40: =+'Bank Assets Analysis (нац)'!P41 -> 2.1395131e+08 | E40: =+'Bank Assets Analysis'!AD42 -> 3.9113691e+08 | H40: =$H$36 -> 4712217924 | I40: =$I$36 -> 7068326886
A41: 4.2. | B41: Норма чистого стабильного финансирования | C41: =IFERROR((C42/C47),0) -> 1.0220018 | D41: =IFERROR((D42/D47),0) -> 1.2454718 | E41: =IFERROR((E42/E47),0) -> 0.64141029
A42: 4.3. | B42: Доступная сумма стабильного финансирования | C42: =SUM(C43:C46) -> 4.010103e+09 | D42: =SUM(D43:D46) -> 3.0790427e+09 | E42: =SUM(E43:E46) -> 9.310603e+08
A43: 4.3.1. | B43: Собственный капитал | C43: =Balance!C76 -> 1625105475 | D43: =Balance!D76 -> 1625105475 | E43: =Balance!E76 -> 0
A44: 4.3.2. | B44: Обязательства свыше 1 года | C44: ='Bank Liabilities Analysis'!O38+'Bank Liabilities Analysis'!Q38 -> 1579210609 | D44: =+'Bank Liabilities Analysis (нац)'!I37+'Bank Liabilities Analysis (нац)'!J37 -> 1085327517 | E44: ='Bank Liabilities Analysis'!P38+'Bank Liabilities Analysis'!R38 -> 493883092
A45: 4.3.3. | B45: 30% других бессрочных обязательств | C45: =+('Bank Liabilities Analysis'!C38)*0.3 -> 2.2763118e+08 | D45: =+('Bank Liabilities Analysis (нац)'!C37)*0.3 -> 1.3470124e+08 | E45: =+('Bank Liabilities Analysis'!D38)*0.3 -> 92929943
A46: 4.3.4. | B46: 30% других обязательств менее 1 года | C46: =+('Bank Liabilities Analysis'!E38+'Bank Liabilities Analysis'!G38+'Bank Liabilities Analysis'!I38+'Bank Liabilities Analysis'!K38+'Bank Liabilities Analysis'!M38)*0.3 -> 5.7815572e+08 | D46: =+('Bank Liabilities Analysis (нац)'!D37+'Bank Liabilities Analysis (нац)'!E37+'Bank Liabilities Analysis (нац)'!F37+'Bank Liabilities Analysis (нац)'!G37+'Bank Liabilities Analysis (нац)'!H37)*0.3 -> 2.3390846e+08 | E46: =+('Bank Liabilities Analysis'!F38+'Bank Liabilities Analysis'!H38+'Bank Liabilities Analysis'!J38+'Bank Liabilities Analysis'!L38+'Bank Liabilities Analysis'!N38)*0.3 -> 3.4424726e+08
A47: 4.4. | B47: Необходимая сумма стабильного финансирования | C47: =SUM(C48:C53) -> 3.9237728e+09 | D47: =SUM(D48:D53) -> 2472189762 | E47: =SUM(E48:E53) -> 1.451583e+09
A48: 4.4.1. | B48: Активы свыше 1 года | C48: =+'Bank Assets Analysis'!O38-'Bank Assets Analysis'!O31+'Bank Assets Analysis'!Q38-'Bank Assets Analysis'!Q31 -> 2966747269 | D48: =+C48-E48 -> 1767615654 | E48: =+'Bank Assets Analysis'!P38-'Bank Assets Analysis'!P34-'Bank Assets Analysis'!P31+'Bank Assets Analysis'!R38-'Bank Assets Analysis'!R34-'Bank Assets Analysis'!R31 -> 1199131615
A49: 4.4.2. | B49: Банковские помещения, мебель и оборудование, чистые | C49: =+'Bank Assets Analysis'!S31 -> 149099836 | D49: =+'Bank Assets Analysis'!T31 -> 149099836 | E49: =+'Bank Assets Analysis'!U31 -> 0
A50: 4.4.3. | B50: Кредиты и лизинги и авансы в процессе судебного разбирательства, чистые или не взысканные в установленном порядке | C50: =+'Bank Assets Analysis'!C23+'Bank Assets Analysis'!C24+'Bank Assets Analysis'!C25+'Bank Assets Analysis'!C26 -> 34083003 | D50: =+'Bank Assets Analysis (нац)'!C25+'Bank Assets Analysis (нац)'!C24+'Bank Assets Analysis (нац)'!C23+'Bank Assets Analysis (нац)'!C22 -> 31786074 | E50: =+'Bank Assets Analysis'!D23+'Bank Assets Analysis'!D24+'Bank Assets Analysis'!D25+'Bank Assets Analysis'!D26 -> 2296929
A51: 4.4.4. | B51: Активы в процессе судебного разбирательства или не взысканные в установленном порядке(не указанные в строке "4.4.3.)") | C51: =+'Calculation of Risk Weighted As'!H45 -> 349952 | D51: 349952 | E51: 0
A52: 4.4.5. | B52: 30% других активов менее 1 го года (за исключением бессрочных и со сроком менее 1 го года ликвидных активов) | C52: =(+'Bank Assets Analysis'!S38-'Bank Assets Analysis'!O38-'Bank Assets Analysis'!Q38-'Liquidity Analysis'!C12)*0.3 -> 6.4604985e+08 | D52: =('Bank Assets Analysis (нац)'!K37-'Bank Assets Analysis (нац)'!C33-'Bank Assets Analysis (нац)'!I37-'Bank Assets Analysis (нац)'!J37-'Liquidity Analysis'!D12+(IF('Bank Assets Analysis'!C34>0,'Bank Assets Analysis'!C34,0)))*0.3 -> 492688086 | E52: =(+'Bank Assets Analysis'!U38-'Bank Assets Analysis'!D34-'Bank Assets Analysis'!P38-'Bank Assets Analysis'!R38-'Liquidity Analysis'!E12+(IF('Bank Assets Analysis'!C34<0,'Bank Assets Analysis'!C34,0)))*0.3 -> 1.5336176e+08
A53: 4.4.6. | B53: 15% из забалансовых инструментов | C53: =+ROUND(SUM(Commitments!C4-Commitments!C5+Commitments!C7-Commitments!C8+Commitments!C10-'Bank Liabilities Analysis'!S19+Commitments!C18-Commitments!C23)*15%,0) -> 127442887 | D53: =+ROUND(SUM(Commitments!D4-Commitments!D5+Commitments!D7-Commitments!D8+Commitments!D10-'Bank Liabilities Analysis'!T19+Commitments!D18-Commitments!D23)*15%,0) -> 30650160 | E53: =+ROUND(SUM(Commitments!E4-Commitments!E5+Commitments!E7-Commitments!E8+Commitments!E10-'Bank Liabilities Analysis'!U19+Commitments!E18-Commitments!E23)*15%,0) -> 96792727
B56: Подпись Председателя правления:
B58: Подпись Главного Бухгалтера:

Sheet Bank Assets Analysis
A1: АНАЛИЗ АКТИВОВ БАНКА | X1: Таблица-17
B2: =Balance!B3 -> АКБ "Микрокредитбанк" | T2: =+Balance!B2 -> 30 Декабрь, 2019 | Z2: в тыс. сум
A3: № | B3: Характеристики | C3: Срок погашения (в днях) | S3: ВСЕГО | T3: из них | V3: Коэффициент | W3: Сумма активов | X3: Высоко-ликвидные активы | Y3: Сумма активов (в иностранной валюте) | Z3: Высоко-ликвидные активы (в иностранной валюте)
C4: Бессрочные | E4: От 1 до 7 дней | G4: От 8 до 30 дней | I4: От 31 до 90 дней | K4: От 91 до 180 дней | M4: От 181 до 365 дней | O4: От 366 до 730 дней | Q4: Свыше 2 лет
C5: Сумма | D5: в том числе, в иностранной валюте (в экв. в сумах) | E5: Сумма | F5: в том числе, в иностранной валюте (в экв. в сумах) | G5: Сумма | H5: в том числе, в иностранной валюте (в экв. в сумах) | I5: Сумма | J5: в том числе, в иностранной валюте (в экв. в сумах) | K5: Сумма | L5: в том числе, в иностранной валюте (в экв. в сумах) | M5: Сумма | N5: в том числе, в иностранной валюте (в экв. в сумах) | O5: Сумма | P5: в том числе, в иностранной валюте (в экв. в сумах) | Q5: Сумма | R5: в том числе, в иностранной валюте (в экв. в сумах) | T5: в национальной валюте | U5: в иностранной валюте (в экв. в сумах)
B6: АКТИВЫ
A7: 1. | B7: Наличность и другие кассовые документы | C7: 173211577 | D7: 103406445 | S7: =+C7+E7+G7+I7+K7+M7+O7+Q7 -> 173211577 | T7: =+S7-U7 -> 69805132 | U7: =+D7+F7+H7+J7+L7+N7+P7+R7 -> 103406445 | V7: 1 | W7: =+C7 -> 173211577 | X7: =+W7*V7 -> 173211577 | Y7: =+D7 -> 103406445 | Z7: =+Y7*V7 -> 103406445
A8: 2. | B8: К получению из ЦБРУ не учитывая сумму обязательных резервов банка(ФОР) | C8: 97131440 | D8: 0 | F8: 21084460 | S8: =+C8+E8+G8+I8+K8+M8+O8+Q8 -> 97131440 | T8: =+S8-U8 -> 76046980 | U8: =+D8+F8+H8+J8+L8+N8+P8+R8 -> 21084460 | V8: 1 | W8: =+C8+E8+G8 -> 97131440 | X8: =+W8*V8 -> 97131440 | Y8: =+D8+F8+H8 -> 21084460 | Z8: =+Y8*V8 -> 21084460
A9: 2.1 | B9: К получению из ЦБРУ (сумма обязательных резервов банка(ФОР)) | C9: 43446340 | H9: 0 | S9: =+C9+E9+G9+I9+K9+M9+O9+Q9 -> 43446340 | T9: =+S9-U9 -> 43446340 | U9: =+D9+F9+H9+J9+L9+N9+P9+R9 -> 0 | V9: 0 | W9: =+C9 -> 43446340 | X9: =+W9*V9 -> 0 | Y9: =+D9 -> 0 | Z9: =+Y9*V9 -> 0
A10: 3. | B10: К получению из других банков | C10: =SUM(C11:C14) -> 187988332 | D10: =SUM(D11:D14) -> 186649157 | E10: =SUM(E11:E14) -> 0 | F10: =SUM(F11:F14) -> 0 | G10: =SUM(G11:G14) -> 0 | H10: =SUM(H11:H14) -> 0 | I10: =SUM(I11:I14) -> 250000000 | J10: =SUM(J11:J14) -> 0 | ... R10: =SUM(R11:R14) -> 0 | S10: =+C10+E10+G10+I10+K10+M10+O10+Q10 -> 453538332 | T10: =+S10-U10 -> 266889175 | U10: =+D10+F10+H10+J10+L10+N10+P10+R10 -> 186649157 | X10: =+W10*V10 -> 0
A11: 3.1 | B11: К получению со счетов в банках стран с низким уровнем риска (ностро, депозиты), но размещенные не в качестве обеспечения | C11: 168384887 | D11: 168384887 | S11: =+C11+E11+G11+I11+K11+M11+O11+Q11 -> 168384887 | T11: =+S11-U11 -> 0 | U11: =+D11+F11+H11+J11+L11+N11+P11+R11 -> 168384887 | V11: 1 | W11: =+C11+E11+G11 -> 168384887 | X11: =+W11*V11 -> 168384887 | Y11: =+D11+F11+H11 -> 168384887 | Z11: =+Y11*V11 -> 168384887
A12: 3.2 | B12: К получению из других банков - депозиты | C12: 428886 | D12: 255389 | G12: 0 | I12: 250000000 | O12: 11250000 | Q12: 4300000 | S12: =+C12+E12+G12+I12+K12+M12+O12+Q12 -> 265978886 | T12: =+S12-U12 -> 265723497 | U12: =+D12+F12+H12+J12+L12+N12+P12+R12 -> 255389 | V12: 1 | W12: =+C12+E12+G12 -> 428886 | X12: =+W12*V12 -> 428886 | Y12: =+D12+F12+H12 -> 255389 | Z12: =+Y12*V12 -> 255389
A13: 3.3 | B13: К получению из других банков по расчетам пластиковых карт | C13: 1165678 | D13: 0 | S13: =+C13+E13+G13+I13+K13+M13+O13+Q13 -> 1165678 | T13: =+S13-U13 -> 1165678 | U13: =+D13+F13+H13+J13+L13+N13+P13+R13 -> 0 | V13: 0.5 | W13: =+C13+E13+G13 -> 1165678 | X13: =+W13*V13 -> 582839 | Y13: =+D13+F13+H13 -> 0 | Z13: =+Y13*V13 -> 0
A14: 3.4 | B14: Другие статьи | C14: 18008881 | D14: 18008881 | S14: =+C14+E14+G14+I14+K14+M14+O14+Q14 -> 18008881 | T14: =+S14-U14 -> 0 | U14: =+D14+F14+H14+J14+L14+N14+P14+R14 -> 18008881 | V14: 0.3 | W14: =+C14+E14+G14 -> 18008881 | X14: =+W14*V14 -> 5402664.3 | Y14: =+D14+F14+H14 -> 18008881 | Z14: =+Y14*V14 -> 5402664.3
A15: 4. | B15: Счета купли и продажи, чистые | C15: =+C16+C17+C18+C19 -> 10403002 | D15: =+D16+D17+D18+D19 -> 0 | E15: =+E16+E17+E18+E19 -> 0 | F15: =+F16+F17+F18+F19 -> 0 | G15: =+G16+G17+G18+G19 -> 0 | H15: =+H16+H17+H18+H19 -> 0 | I15: =+I16+I17+I18+I19 -> 22174000 | J15: =+J16+J17+J18+J19 -> 0 | ... R15: =+R16+R17+R18+R19 -> 0 | S15: =+C15+E15+G15+I15+K15+M15+O15+Q15 -> 119577002 | T15: =+S15-U15 -> 119577002 | U15: =+D15+F15+H15+J15+L15+N15+P15+R15 -> 0 | X15: =+W15*V15 -> 0 | Z15: =+Y15*V15 -> 0
A16: 4.1 | B16: Ценные бумаги, выпущенные Правительством Республики Узбекистан и ЦБРУ (векселя, облигации и другие долговые ценные бумаги) | I16: 22174000 | O16: 87000000 | S16: =+C16+E16+G16+I16+K16+M16+O16+Q16 -> 109174000 | T16: =+S16-U16 -> 109174000 | U16: =+D16+F16+H16+J16+L16+N16+P16+R16 -> 0 | V16: 1 | W16: =+C16+E16+G16+I16+K16+M16+O16+Q16 -> 109174000 | X16: =+W16*V16 -> 109174000 | Y16: =+D16+F16+H16+J16+L16+N16+P16+R16 -> 0 | Z16: =+Y16*V16 -> 0
A17: 4.2 | B17: Правительственные ценные бумаги стран с низкой степенью странового риска | S17: =+C17+E17+G17+I17+K17+M17+O17+Q17 -> 0 | T17: =+S17-U17 -> 0 | U17: =+D17+F17+H17+J17+L17+N17+P17+R17 -> 0 | V17: 1 | W17: =+C17+E17+G17 -> 0 | X17: =+W17*V17 -> 0 | Y17: =+D17+F17+H17 -> 0 | Z17: =+Y17*V17 -> 0
A18: 4.3 | B18: Ценные бумаги ведущих транснациональных компаний с низким уровнем странового риска | S18: =+C18+E18+G18+I18+K18+M18+O18+Q18 -> 0 | T18: =+S18-U18 -> 0 | U18: =+D18+F18+H18+J18+L18+N18+P18+R18 -> 0 | V18: 1 | W18: =+C18+E18+G18 -> 0 | X18: =+W18*V18 -> 0 | Y18: =+D18+F18+H18 -> 0 | Z18: =+Y18*V18 -> 0
A19: 4.4 | B19: Другие | C19: 10403002 | S19: =+C19+E19+G19+I19+K19+M19+O19+Q19 -> 10403002 | T19: =+S19-U19 -> 10403002 | U19: =+D19+F19+H19+J19+L19+N19+P19+R19 -> 0 | V19: 0 | W19: =+C19+E19+G19 -> 10403002 | X19: =+W19*V19 -> 0 | Y19: =+D19+F19+H19 -> 0 | Z19: =+Y19*V19 -> 0
A20: 5. | B20: Купленные векселя, чистые | S20: =+C20+E20+G20+I20+K20+M20+O20+Q20 -> 0 | T20: =+S20-U20 -> 0 | U20: =+D20+F20+H20+J20+L20+N20+P20+R20 -> 0 | V20: 0.3 | W20: =+C20+E20+G20 -> 0 | X20: =+W20*V20 -> 0 | Y20: =+D20+F20+H20 -> 0 | Z20: =+Y20*V20 -> 0
A21: 6. | B21: Обязательства клиентов по траттам под аккредитивы или трастовые документы | S21: =+C21+E21+G21+I21+K21+M21+O21+Q21 -> 0 | T21: =+S21-U21 -> 0 | U21: =+D21+F21+H21+J21+L21+N21+P21+R21 -> 0 | V21: 0.3 | W21: =+C21+E21+G21 -> 0 | X21: =+W21*V21 -> 0 | Y21: =+D21+F21+H21 -> 0 | Z21: =+Y21*V21 -> 0
A22: 7. | B22: Обязательства клиентов по непогашенным акцептам этого банка | S22: =+C22+E22+G22+I22+K22+M22+O22+Q22 -> 0 | T22: =+S22-U22 -> 0 | U22: =+D22+F22+H22+J22+L22+N22+P22+R22 -> 0 | V22: 0.3 | W22: =+C22+E22+G22 -> 0 | X22: =+W22*V22 -> 0 | Y22: =+D22+F22+H22 -> 0 | Z22: =+Y22*V22 -> 0
A23: 8. | B23: Кредиты и лизинги, предоставленные ЦБРУ, чистые | S23: =+C23+E23+G23+I23+K23+M23+O23+Q23 -> 0 | T23: =+S23-U23 -> 0 | U23: =+D23+F23+H23+J23+L23+N23+P23+R23 -> 0 | V23: 1 | W23: =+C23+E23+G23 -> 0 | X23: =+W23*V23 -> 0 | Y23: =+D23+F23+H23 -> 0 | Z23: =+Y23*V23 -> 0
A24: 9. | B24: Кредиты и лизинги, предоставленные другим банкам, чистые | S24: =+C24+E24+G24+I24+K24+M24+O24+Q24 -> 0 | T24: =+S24-U24 -> 0 | U24: =+D24+F24+H24+J24+L24+N24+P24+R24 -> 0 | V24: 0.5 | W24: =+C24+E24+G24 -> 0 | X24: =+W24*V24 -> 0 | Y24: =+D24+F24+H24 -> 0 | Z24: =+Y24*V24 -> 0
A25: 10 | B25: Кредиты и лизинги, предоставленные другим клиентам, чистые | C25: 25522506 | D25: 2296929 | E25: 49142260 | F25: 1105250 | G25: 58524584 | H25: 2088467 | I25: 299929961 | J25: 46988108 | K25: 467046178 | L25: 92296824 | M25: 879525725 | N25: 215751354 | O25: 1293596512 | P25: 435986816 | Q25: 1570600757 | R25: 763144799 | S25: =+C25+E25+G25+I25+K25+M25+O25+Q25 -> 4643888483 | T25: =+S25-U25 -> 3084229936 | U25: =+D25+F25+H25+J25+L25+N25+P25+R25 -> 1559658547 | V25: 0.3 | W25: =+C25+E25+G25 -> 133189350 | X25: =+W25*V25 -> 39956805 | Y25: =+D25+F25+H25 -> 5490646 | Z25: =+Y25*V25 -> 1647193.8
A26: 11 | B26: Кредиты и лизинги и авансы в процессе судебного разбирательства, чистые | C26: 8560497 | D26: 0 | S26: =+C26+E26+G26+I26+K26+M26+O26+Q26 -> 8560497 | T26: =+S26-U26 -> 8560497 | U26: =+D26+F26+H26+J26+L26+N26+P26+R26 -> 0 | V26: 0 | W26: =+C26+E26+G26 -> 8560497 | X26: =+W26*V26 -> 0 | Y26: =+D26+F26+H26 -> 0 | Z26: =+Y26*V26 -> 0
A27: 12. | B27: Инвестиции, чистые | C27: 70220 | D27: 0 | K27: 6600000 | S27: =+C27+E27+G27+I27+K27+M27+O27+Q27 -> 6670220 | T27: =+S27-U27 -> 6670220 | U27: =+D27+F27+H27+J27+L27+N27+P27+R27 -> 0 | V27: 0 | W27: =+C27+E27+G27 -> 70220 | X27: =+W27*V27 -> 0 | Y27: =+D27+F27+H27 -> 0 | Z27: =+Y27*V27 -> 0
A28: 13. | B28: Ценные бумаги купленные по соглашению с обратным выкупом | S28: =+C28+E28+G28+I28+K28+M28+O28+Q28 -> 0 | T28: =+S28-U28 -> 0 | U28: =+D28+F28+H28+J28+L28+N28+P28+R28 -> 0 | X28: =+W28*V28 -> 0 | Z28: =+Y28*V28 -> 0
A29: 13.1 | B29: Правительственные ценные бумаги купленные по соглашению с обратным выкупом (РЕПО) | S29: =+C29+E29+G29+I29+K29+M29+O29+Q29 -> 0 | T29: =+S29-U29 -> 0 | U29: =+D29+F29+H29+J29+L29+N29+P29+R29 -> 0 | V29: 0.3 | W29: =+C29+E29+G29 -> 0 | X29: =+W29*V29 -> 0 | Y29: =+D29+F29+H29 -> 0 | Z29: =+Y29*V29 -> 0
A30: 13,2 | B30: Другие ценные бумаги купленные по соглашению с обратным выкупом (РЕПО) | S30: =+C30+E30+G30+I30+K30+M30+O30+Q30 -> 0 | T30: =+S30-U30 -> 0 | U30: =+D30+F30+H30+J30+L30+N30+P30+R30 -> 0 | V30: 0 | W30: =+C30+E30+G30 -> 0 | X30: =+W30*V30 -> 0 | Y30: =+D30+F30+H30 -> 0 | Z30: =+Y30*V30 -> 0
A31: 14. | B31: Основные средства, чистые | Q31: 149099836 | R31: 0 | S31: =+C31+E31+G31+I31+K31+M31+O31+Q31 -> 149099836 | T31: =+S31-U31 -> 149099836 | U31: =+D31+F31+H31+J31+L31+N31+P31+R31 -> 0 | V31: 0 | W31: =+C31+E31+G31 -> 0 | X31: =+W31*V31 -> 0 | Y31: =+D31+F31+H31 -> 0 | Z31: =+Y31*V31 -> 0
A32: 15. | B32: Другое собственное имущество банка, чистые | S32: =+C32+E32+G32+I32+K32+M32+O32+Q32 -> 0 | T32: =+S32-U32 -> 0 | U32: =+D32+F32+H32+J32+L32+N32+P32+R32 -> 0 | V32: 0 | W32: =+C32+E32+G32 -> 0 | X32: =+W32*V32 -> 0 | Y32: =+D32+F32+H32 -> 0 | Z32: =+Y32*V32 -> 0
A33: 16. | B33: Нереализованная прибыль при ревальвации по сделкам "форвард" | S33: =+C33+E33+G33+I33+K33+M33+O33+Q33 -> 0 | T33: =+S33-U33 -> 0 | U33: =+D33+F33+H33+J33+L33+N33+P33+R33 -> 0 | V33: 0 | W33: =+C33+E33+G33 -> 0 | X33: =+W33*V33 -> 0 | Y33: =+D33+F33+H33 -> 0 | Z33: =+Y33*V33 -> 0
A34: 17. | B34: Счета купли-продажи валюты и валютные позиции | C34: 0 | D34: -70081723 | S34: =+C34+E34+G34+I34+K34+M34+O34+Q34 -> 0 | T34: =+S34-U34 -> 70081723 | U34: =+D34+F34+H34+J34+L34+N34+P34+R34 -> -70081723 | V34: 0 | W34: =+C34+E34+G34 -> 0 | X34: =+W34*V34 -> 0 | Y34: =+D34+F34+H34 -> -70081723 | Z34: =+Y34*V34 -> 0
A35: 18. | B35: Клиринговые счета | S35: =+C35+E35+G35+I35+K35+M35+O35+Q35 -> 0 | T35: =+S35-U35 -> 0 | U35: =+D35+F35+H35+J35+L35+N35+P35+R35 -> 0 | V35: 0 | W35: =+C35+E35+G35 -> 0 | X35: =+W35*V35 -> 0 | Y35: =+D35+F35+H35 -> 0 | Z35: =+Y35*V35 -> 0
A36: 19. | B36: Начисленные проценты | C36: 35343476 | D36: 7966064 | S36: =+C36+E36+G36+I36+K36+M36+O36+Q36 -> 35343476 | T36: =+S36-U36 -> 27377412 | U36: =+D36+F36+H36+J36+L36+N36+P36+R36 -> 7966064 | V36: 0.3 | W36: =+C36+E36+G36 -> 35343476 | X36: =+W36*V36 -> 10603043 | Y36: =+D36+F36+H36 -> 7966064 | Z36: =+Y36*V36 -> 2389819.2
A37: 20. | B37: Другие активы | C37: 159805202 | D37: 142457490 | S37: =+C37+E37+G37+I37+K37+M37+O37+Q37 -> 159805202 | T37: =+S37-U37 -> 17347712 | U37: =+D37+F37+H37+J37+L37+N37+P37+R37 -> 142457490 | V37: 0 | W37: =+C37+E37+G37 -> 159805202 | X37: =+W37*V37 -> 0 | Y37: =+D37+F37+H37 -> 142457490 | Z37: =+Y37*V37 -> 0
A38: 21. | B38: ИТОГО АКТИВОВ | C38: =SUM(C7:C37)-C10-C15-C28 -> 741482592 | D38: =SUM(D7:D37)-D10-D15-D28 -> 372694362 | E38: =SUM(E7:E37)-E10-E15-E28 -> 49142260 | F38: =SUM(F7:F37)-F10-F15-F28 -> 22189710 | G38: =SUM(G7:G37)-G10-G15-G28 -> 58524584 | H38: =SUM(H7:H37)-H10-H15-H28 -> 2088467 | I38: =SUM(I7:I37)-I10-I15-I28 -> 572103961 | J38: =SUM(J7:J37)-J10-J15-J28 -> 46988108 | ... R38: =SUM(R7:R37)-R10-R15-R28 -> 763144799 | S38: =+C38+E38+G38+I38+K38+M38+O38+Q38 -> 5890272405 | T38: =+S38-U38 -> 3939131965 | U38: =+D38+F38+H38+J38+L38+N38+P38+R38 -> 1951140440 | X38: =SUM(X7:X37)-X10-X28 -> 6.0487614e+08 | Z38: =SUM(Z7:Z37)-Z10-Z28 -> 3.0257086e+08 | AA38: =+Balance!C44 -> 5890272405 | AB38: =+Balance!D44 -> 3939131965 | AC38: =+Balance!E44 -> 1951140440
C39: =+C38-C26-C7-C8-C10-C15-C24 -> 264187744 | E39: =+E38-E26-E7-E8-E10-E15-E24 -> 49142260 | G39: =+G38-G26-G7-G8-G10-G15-G24 -> 58524584 | K39: =+K38-K26-K7-K8-K10-K15-K24 -> 473646178 | M39: =+M38-M26-M7-M8-M10-M15-M24 -> 879525725
AA40: Ликвидные активы | AB40: =+X38-AB41 -> 56974237 | AC40: Ликвидные активы | AD40: =+Z38-AD41 -> 9695066.3
B41: Подпись Председателя правления: | AA41: Высоко-ликвидные активы | AB41: =+X7+X8+X11+X16+X17+X18+X29 -> 547901904 | AC41: Высоко-ликвидные активы | AD41: =+Z7+Z8+Z11+Z16+Z17+Z18+Z29 -> 292875792
AA42: Чистый отток за 30 дней | AB42: =+AB44-AB45 -> 6.0508822e+08 | AC42: Чистый отток за 30 дней | AD42: =+AD44-AD45 -> 3.9113691e+08
B43: Подпись Главного Бухгалтера:
AA44: Отток | AB44: =+'Bank Liabilities Analysis'!X38 -> 6.6206245e+08 | AC44: Отток | AD44: =+'Bank Liabilities Analysis'!Z38 -> 4.0083197e+08
AA45: Приток по положению | AB45: =IF(AB40>(AB44*0.75),AB44*0.75,AB40) -> 56974237 | AC45: Приток по положению | AD45: =IF(AD40>(AD44*0.75),AD44*0.75,AD40) -> 9695066.3

Sheet Bank Assets Analysis (нац)
A1: АНАЛИЗ АКТИВОВ БАНКА В НАЦИОНАЛЬНОЙ ВАЛЮТЕ | L1: Таблица-17А
B2: =Balance!B3 -> АКБ "Микрокредитбанк" | J2: =+Balance!B2 -> 30 Декабрь, 2019 | N2: =+Balance!E3 -> тыс. сум
A3: № | B3: Характеристики | C3: Срок погашения (в днях) | K3: ВСЕГО | L3: Коэффициент | M3: Сумма активов | N3: Высоко-ликвидные активы
C4: Бессрочные | D4: От 1 до 7 дней | E4: От 8 до 30 дней | F4: От 31 до 90 дней | G4: От 91 до 180 дней | H4: От 181 до 365 дней | I4: От 366 до 730 дней | J4: Свыше 2 лет
B5: АКТИВЫ
A6: 1. | B6: Наличность и другие кассовые документы | C6: =+'Bank Assets Analysis'!C7-'Bank Assets Analysis'!D7 -> 69805132 | D6: =+'Bank Assets Analysis'!E7-'Bank Assets Analysis'!F7 -> 0 | E6: =+'Bank Assets Analysis'!G7-'Bank Assets Analysis'!H7 -> 0 | F6: =+'Bank Assets Analysis'!I7-'Bank Assets Analysis'!J7 -> 0 | G6: =+'Bank Assets Analysis'!K7-'Bank Assets Analysis'!L7 -> 0 | H6: =+'Bank Assets Analysis'!M7-'Bank Assets Analysis'!N7 -> 0 | I6: =+'Bank Assets Analysis'!O7-'Bank Assets Analysis'!P7 -> 0 | J6: =+'Bank Assets Analysis'!Q7-'Bank Assets Analysis'!R7 -> 0 | K6: =+C6+D6+E6+F6+G6+H6+I6+J6 -> 69805132 | L6: 1 | M6: =+C6 -> 69805132 | N6: =+M6*L6 -> 69805132
A7: 2. | B7: К получению из ЦБРУ не учитывая сумму обязательных резервов банка(ФОР) | C7: =+'Bank Assets Analysis'!C8-'Bank Assets Analysis'!D8 -> 97131440 | D7: =+'Bank Assets Analysis'!E8-'Bank Assets Analysis'!F8 -> -21084460 | E7: =+'Bank Assets Analysis'!G8-'Bank Assets Analysis'!H8 -> 0 | F7: =+'Bank Assets Analysis'!I8-'Bank Assets Analysis'!J8 -> 0 | G7: =+'Bank Assets Analysis'!K8-'Bank Assets Analysis'!L8 -> 0 | H7: =+'Bank Assets Analysis'!M8-'Bank Assets Analysis'!N8 -> 0 | I7: =+'Bank Assets Analysis'!O8-'Bank Assets Analysis'!P8 -> 0 | J7: =+'Bank Assets Analysis'!Q8-'Bank Assets Analysis'!R8 -> 0 | K7: =+C7+D7+E7+F7+G7+H7+I7+J7 -> 76046980 | L7: 1 | M7: =+C7+D7+E7 -> 76046980 | N7: =+M7*L7 -> 76046980
A8: 2.1 | B8: К получению из ЦБРУ (сумма обязательных резервов банка(ФОР)) | C8: =+'Bank Assets Analysis'!C9-'Bank Assets Analysis'!D9 -> 43446340 | D8: =+'Bank Assets Analysis'!E9-'Bank Assets Analysis'!F9 -> 0 | E8: =+'Bank Assets Analysis'!G9-'Bank Assets Analysis'!H9 -> 0 | F8: =+'Bank Assets Analysis'!I9-'Bank Assets Analysis'!J9 -> 0 | G8: =+'Bank Assets Analysis'!K9-'Bank Assets Analysis'!L9 -> 0 | H8: =+'Bank Assets Analysis'!M9-'Bank Assets Analysis'!N9 -> 0 | I8: =+'Bank Assets Analysis'!O9-'Bank Assets Analysis'!P9 -> 0 | J8: =+'Bank Assets Analysis'!Q9-'Bank Assets Analysis'!R9 -> 0 | K8: =+C8+D8+E8+F8+G8+H8+I8+J8 -> 43446340 | L8: 0 | M8: =+C8 -> 43446340 | N8: =+M8*L8 -> 0
A9: 3. | B9: К получению из других банков | C9: =SUM(C10:C13) -> 1339175 | D9: =SUM(D10:D13) -> 0 | E9: =SUM(E10:E13) -> 0 | F9: =SUM(F10:F13) -> 250000000 | G9: =SUM(G10:G13) -> 0 | H9: =SUM(H10:H13) -> 0 | I9: =SUM(I10:I13) -> 11250000 | J9: =SUM(J10:J13) -> 4300000 | K9: =+C9+D9+E9+F9+G9+H9+I9+J9 -> 266889175 | N9: =+M9*L9 -> 0
A10: 3.1 | B10: К получению со счетов в банках стран с низким уровнем риска (ностро, депозиты), но размещенные не в качестве обеспечения | C10: =+'Bank Assets Analysis'!C11-'Bank Assets Analysis'!D11 -> 0 | D10: =+'Bank Assets Analysis'!E11-'Bank Assets Analysis'!F11 -> 0 | E10: =+'Bank Assets Analysis'!G11-'Bank Assets Analysis'!H11 -> 0 | F10: =+'Bank Assets Analysis'!I11-'Bank Assets Analysis'!J11 -> 0 | G10: =+'Bank Assets Analysis'!K11-'Bank Assets Analysis'!L11 -> 0 | H10: =+'Bank Assets Analysis'!M11-'Bank Assets Analysis'!N11 -> 0 | I10: =+'Bank Assets Analysis'!O11-'Bank Assets Analysis'!P11 -> 0 | J10: =+'Bank Assets Analysis'!Q11-'Bank Assets Analysis'!R11 -> 0 | K10: =+C10+D10+E10+F10+G10+H10+I10+J10 -> 0 | L10: 1 | M10: =+C10+D10+E10 -> 0 | N10: =+M10*L10 -> 0
A11: 3.2 | B11: К получению из других банков - депозиты | C11: =+'Bank Assets Analysis'!C12-'Bank Assets Analysis'!D12 -> 173497 | D11: =+'Bank Assets Analysis'!E12-'Bank Assets Analysis'!F12 -> 0 | E11: =+'Bank Assets Analysis'!G12-'Bank Assets Analysis'!H12 -> 0 | F11: =+'Bank Assets Analysis'!I12-'Bank Assets Analysis'!J12 -> 250000000 | G11: =+'Bank Assets Analysis'!K12-'Bank Assets Analysis'!L12 -> 0 | H11: =+'Bank Assets Analysis'!M12-'Bank Assets Analysis'!N12 -> 0 | I11: =+'Bank Assets Analysis'!O12-'Bank Assets Analysis'!P12 -> 11250000 | J11: =+'Bank Assets Analysis'!Q12-'Bank Assets Analysis'!R12 -> 4300000 | K11: =+C11+D11+E11+F11+G11+H11+I11+J11 -> 265723497 | L11: 1 | M11: =+C11+D11+E11 -> 173497 | N11: =+M11*L11 -> 173497
A12: 3.3 | B12: К получению из других банков по расчетам пластиковых карт | C12: =+'Bank Assets Analysis'!C13-'Bank Assets Analysis'!D13 -> 1165678 | D12: =+'Bank Assets Analysis'!E13-'Bank Assets Analysis'!F13 -> 0 | E12: =+'Bank Assets Analysis'!G13-'Bank Assets Analysis'!H13 -> 0 | F12: =+'Bank Assets Analysis'!I13-'Bank Assets Analysis'!J13 -> 0 | G12: =+'Bank Assets Analysis'!K13-'Bank Assets Analysis'!L13 -> 0 | H12: =+'Bank Assets Analysis'!M13-'Bank Assets Analysis'!N13 -> 0 | I12: =+'Bank Assets Analysis'!O13-'Bank Assets Analysis'!P13 -> 0 | J12: =+'Bank Assets Analysis'!Q13-'Bank Assets Analysis'!R13 -> 0 | K12: =+C12+D12+E12+F12+G12+H12+I12+J12 -> 1165678 | L12: 0.5 | M12: =+C12+D12+E12 -> 1165678 | N12: =+M12*L12 -> 582839
A13: 3.4 | B13: Другие статьи | C13: =+'Bank Assets Analysis'!C14-'Bank Assets Analysis'!D14 -> 0 | D13: =+'Bank Assets Analysis'!E14-'Bank Assets Analysis'!F14 -> 0 | E13: =+'Bank Assets Analysis'!G14-'Bank Assets Analysis'!H14 -> 0 | F13: =+'Bank Assets Analysis'!I14-'Bank Assets Analysis'!J14 -> 0 | G13: =+'Bank Assets Analysis'!K14-'Bank Assets Analysis'!L14 -> 0 | H13: =+'Bank Assets Analysis'!M14-'Bank Assets Analysis'!N14 -> 0 | I13: =+'Bank Assets Analysis'!O14-'Bank Assets Analysis'!P14 -> 0 | J13: =+'Bank Assets Analysis'!Q14-'Bank Assets Analysis'!R14 -> 0 | K13: =+C13+D13+E13+F13+G13+H13+I13+J13 -> 0 | L13: 0.3 | M13: =+C13+D13+E13 -> 0 | N13: =+M13*L13 -> 0
A14: 4. | B14: Счета купли и продажи, чистые | C14: =+C15+C16+C17+C18 -> 10403002 | D14: =+D15+D16+D17+D18 -> 0 | E14: =+E15+E16+E17+E18 -> 0 | F14: =+F15+F16+F17+F18 -> 22174000 | G14: =+G15+G16+G17+G18 -> 0 | H14: =+H15+H16+H17+H18 -> 0 | I14: =+I15+I16+I17+I18 -> 87000000 | J14: =+J15+J16+J17+J18 -> 0 | K14: =+C14+D14+E14+F14+G14+H14+I14+J14 -> 119577002 | N14: =+M14*L14 -> 0
A15: 4.1 | B15: Ценные бумаги, выпущенные Правительством Республики Узбекистан и ЦБРУ (векселя, облигации и другие долговые ценные бумаги) | C15: =+'Bank Assets Analysis'!C16-'Bank Assets Analysis'!D16 -> 0 | D15: =+'Bank Assets Analysis'!E16-'Bank Assets Analysis'!F16 -> 0 | E15: =+'Bank Assets Analysis'!G16-'Bank Assets Analysis'!H16 -> 0 | F15: =+'Bank Assets Analysis'!I16-'Bank Assets Analysis'!J16 -> 22174000 | G15: =+'Bank Assets Analysis'!K16-'Bank Assets Analysis'!L16 -> 0 | H15: =+'Bank Assets Analysis'!M16-'Bank Assets Analysis'!N16 -> 0 | I15: =+'Bank Assets Analysis'!O16-'Bank Assets Analysis'!P16 -> 87000000 | J15: =+'Bank Assets Analysis'!Q16-'Bank Assets Analysis'!R16 -> 0 | K15: =+C15+D15+E15+F15+G15+H15+I15+J15 -> 109174000 | L15: 1 | M15: =+C15+D15+E15+F15+G15+H15+I15+J15 -> 109174000 | N15: =+M15*L15 -> 109174000
A16: 4.2 | B16: Правительственные ценные бумаги стран с низкой степенью странового риска | C16: =+'Bank Assets Analysis'!C17-'Bank Assets Analysis'!D17 -> 0 | D16: =+'Bank Assets Analysis'!E17-'Bank Assets Analysis'!F17 -> 0 | E16: =+'Bank Assets Analysis'!G17-'Bank Assets Analysis'!H17 -> 0 | F16: =+'Bank Assets Analysis'!I17-'Bank Assets Analysis'!J17 -> 0 | G16: =+'Bank Assets Analysis'!K17-'Bank Assets Analysis'!L17 -> 0 | H16: =+'Bank Assets Analysis'!M17-'Bank Assets Analysis'!N17 -> 0 | I16: =+'Bank Assets Analysis'!O17-'Bank Assets Analysis'!P17 -> 0 | J16: =+'Bank Assets Analysis'!Q17-'Bank Assets Analysis'!R17 -> 0 | K16: =+C16+D16+E16+F16+G16+H16+I16+J16 -> 0 | L16: 1 | M16: =+C16+D16+E16 -> 0 | N16: =+M16*L16 -> 0
A17: 4.3 | B17: Ценные бумаги ведущих транснациональных компаний с низким уровнем странового риска | C17: =+'Bank Assets Analysis'!C18-'Bank Assets Analysis'!D18 -> 0 | D17: =+'Bank Assets Analysis'!E18-'Bank Assets Analysis'!F18 -> 0 | E17: =+'Bank Assets Analysis'!G18-'Bank Assets Analysis'!H18 -> 0 | F17: =+'Bank Assets Analysis'!I18-'Bank Assets Analysis'!J18 -> 0 | G17: =+'Bank Assets Analysis'!K18-'Bank Assets Analysis'!L18 -> 0 | H17: =+'Bank Assets Analysis'!M18-'Bank Assets Analysis'!N18 -> 0 | I17: =+'Bank Assets Analysis'!O18-'Bank Assets Analysis'!P18 -> 0 | J17: =+'Bank Assets Analysis'!Q18-'Bank Assets Analysis'!R18 -> 0 | K17: =+C17+D17+E17+F17+G17+H17+I17+J17 -> 0 | L17: 1 | M17: =+C17+D17+E17 -> 0 | N17: =+M17*L17 -> 0
A18: 4.4 | B18: Другие | C18: =+'Bank Assets Analysis'!C19-'Bank Assets Analysis'!D19 -> 10403002 | D18: =+'Bank Assets Analysis'!E19-'Bank Assets Analysis'!F19 -> 0 | E18: =+'Bank Assets Analysis'!G19-'Bank Assets Analysis'!H19 -> 0 | F18: =+'Bank Assets Analysis'!I19-'Bank Assets Analysis'!J19 -> 0 | G18: =+'Bank Assets Analysis'!K19-'Bank Assets Analysis'!L19 -> 0 | H18: =+'Bank Assets Analysis'!M19-'Bank Assets Analysis'!N19 -> 0 | I18: =+'Bank Assets Analysis'!O19-'Bank Assets Analysis'!P19 -> 0 | J18: =+'Bank Assets Analysis'!Q19-'Bank Assets Analysis'!R19 -> 0 | K18: =+C18+D18+E18+F18+G18+H18+I18+J18 -> 10403002 | L18: 0 | M18: =+C18+D18+E18 -> 10403002 | N18: =+M18*L18 -> 0
A19: 5. | B19: Купленные векселя, чистые | C19: =+'Bank Assets Analysis'!C20-'Bank Assets Analysis'!D20 -> 0 | D19: =+'Bank Assets Analysis'!E20-'Bank Assets Analysis'!F20 -> 0 | E19: =+'Bank Assets Analysis'!G20-'Bank Assets Analysis'!H20 -> 0 | F19: =+'Bank Assets Analysis'!I20-'Bank Assets Analysis'!J20 -> 0 | G19: =+'Bank Assets Analysis'!K20-'Bank Assets Analysis'!L20 -> 0 | H19: =+'Bank Assets Analysis'!M20-'Bank Assets Analysis'!N20 -> 0 | I19: =+'Bank Assets Analysis'!O20-'Bank Assets Analysis'!P20 -> 0 | J19: =+'Bank Assets Analysis'!Q20-'Bank Assets Analysis'!R20 -> 0 | K19: =+C19+D19+E19+F19+G19+H19+I19+J19 -> 0 | L19: 0.3 | M19: =+C19+D19+E19 -> 0 | N19: =+M19*L19 -> 0
