Workbook
Name bal: [1]balance!$A:$IV
Name OLE_LINK19: Balance!$B$33

Sheet Balance
B1: Приложение №1 к Рекомендациям по заполнению отчетности коммерческих банков по банковскому надзору представляемых Центральному банку Республики Узбекистан
A2: БАЛАНСОВЫЙ ОТЧЕТ КОММЕРЧЕСКОГО БАНКА | B2: Таблица-1(Форма-0110BS)
A3: =IF(B4>0," "&TEXT(B4,"д ММММ, гггг"),"Число,Месяц,Год") -> 31 Декабрь, 2017 | B3: АКБ "Микрокредитбанк"
A4: =IF(B4>0,B4,"Число,Месяц,Год") -> 43100 | B4: 43100
A5: АКТИВЫ | B5: в тыс.сум
A7: 1. Кассовая наличность и другие платежные документы | C7: ='Bank Assets Analysis'!H9 -> 76954182
A8: 2. К получению из ЦБРУ | C8: ='Bank Assets Analysis'!H10+'Bank Assets Analysis'!H11 -> 213192148
A9: 3. К получению из других банков | C9: ='Bank Assets Analysis'!H12 -> 78542844
A10: 4. Счета купли и продажи
A11: а. Ценные бумаги | B11: ='Investment Securities'!B26 -> 349524
A12: б. Драгоценные металлы, монеты, камни | B12: ='Investment Securities'!B37 -> 175
A13: в. Минус: Резерв возможных убытков по счетам купли-продажи | B13: ='Investment Securities'!B27+'Investment Securities'!B38 -> 0
A14: г. Счета купли-продажи, чистые | C14: ='Bank Assets Analysis'!H16 -> 349699
A15: 5 а. Инвестиции | B15: ='Investment Securities'!B13 -> 2750000
A16: б. Минус: Резерв возможных убытков по инвестициям | B16: ='Investment Securities'!B14 -> 1
A17: в. Инвестиции, чистые | C17: ='Bank Assets Analysis'!H28 -> 2749999
A18: 6. Ценные бумаги купленные по соглашению c обратным выкупом | C18: ='Bank Assets Analysis'!H29 -> 0
A19: 7. Кредиты и лизинговые операции
A20: а. Брутто кредиты | B20: 1280369363
A21: б. Лизинговые операции, Брутто | B21: 5753150
A22: в. Минус: Резерв возможных убытков по кредитам и лизингу | B22: ='Charge-offs and Recoveries'!C26 -> 33716097 | E22: =+'Loan Classification'!N14 -> 33716097
A23: г. Кредиты и лизинговые операции, чистые | C23: =('Bank Assets Analysis'!H25+'Bank Assets Analysis'!H26+'Bank Assets Analysis'!H27) -> 1252406416
A24: 8 а. Купленные векселя
A25: б. Минус: Резерв возможных убытков по купленным векселям
A26: в. Купленные векселя, чистые | C26: ='Bank Assets Analysis'!H21 -> 0
A27: 9. Обязательства клиентов по финансовым инструментам | C27: ='Bank Assets Analysis'!H22 -> 0
A28: 10. Основные средства, чистые | C28: ='Bank Assets Analysis'!H32 -> 100870267
A29: 11. Начисленные проценты к получению | C29: ='Bank Assets Analysis'!H37 -> 7348132
A30: 12. Другое собственное имущество банка
A31: а. Инвестиции в недвижимость
A32: б. Другие активы, приобретенные при кредитных расчетах | B32: 3341276
A33: в. Минус:Резервы на возможные убытки по другому собственному имуществу банка | B33: 1728161
A34: г. Чистые, другое собственное имущество банка | C34: ='Bank Assets Analysis'!H33 -> 1613115
A35: 13. Другие активы | C35: 8966247
A36: 14. Итого активов | C36: =C7+C8+C9+C14+C17+C18+C23+C26+C27+C28+C29+C34+C35 -> 1742993049
A38: ОБЯЗАТЕЛЬСТВА И СОБСТВЕННЫЙ КАПИТАЛ
A40: ОБЯЗАТЕЛЬСТВА
A41: 15. Депозиты до востребования | C41: ='Deposits by Client'!B12 -> 357875870
A42: 16.Сберегательные депозиты | C42: ='Deposits by Client'!B21 -> 21367374
A43: 17. Срочные депозиты | C43: ='Deposits by Client'!B30 -> 642761240
A44: 18. К оплате в ЦБРУ | C44: ='Bank Liabilities Analysis'!H19 -> 0
A45: 19. К оплате в другие банки | C45: ='Bank Liabilities Analysis'!H20 -> 12150000
A46: 20. Ценные бумаги проданные по соглашению с последующим выкупом | C46: ='Bank Liabilities Analysis'!H24 -> 0
A47: 21. Кредиты и лизинговые операции к оплате | C47: 141068948
A48: 22. Субординированные долговые обязательства
A49: 23. Начисленные проценты к оплате | C49: ='Bank Liabilities Analysis'!H30 -> 2367927
A50: 24. Другие обязательства | C50: =+'Bank Liabilities Analysis'!H21+'Bank Liabilities Analysis'!H22+'Bank Liabilities Analysis'!H28+'Bank Liabilities Analysis'!H29+'Bank Liabilities Analysis'!H31+'Bank Liabilities Analysis'!H32 -> 19626824
A51: 25. Итого обязательств | C51: =SUM(C41:C50) -> 1197218183
A53: СОБСТВЕННЫЙ КАПИТАЛ
A54: 26. Уставный капитал
A55: а. Акции - Обыкновенные | C55: =+'Bank Capital Calc.'!E12 -> 592608108
A56: б.Акции - Привилегированные | C56: =+'Bank Capital Calc.'!E16 -> 144180
A57: 27. Добавленный капитал | C57: =+'Bank Capital Calc.'!E17 -> 0
A58: 28. Резервный капитал.
A59: а. Резервный фонд общего назначения | C59: 27245577
A60: а.1. Из них, резервы созданные по стандартным активам | C60: =+'Loan Classification'!E16 -> 0 | E60: =+'Loan Classification'!E14 -> 0
A61: б. Резерв на Девальвацию
A62: в. Другие резервы и фонды | C62: 1152899
A63: 29. Нераспределенная прибыль | C63: -75375898
A64: 30. Итого собственного капитала | C64: =SUM(C55:C63)-C60 -> 545774866
A65: 31. Итого обязательств и собственного капитала | C65: =+C51+C64 -> 1742993049
A67: Подпись Председателя правления:
A69: Подпись Главного Бухгалтера:

Sheet Income 
B1: Приложение №1 к Рекомендациям по заполнению отчетности коммерческих банков по банковскому надзору представляемых Центральному банку Республики Узбекистан
A2: ОТЧЕТ О ПРИБЫЛЯХ И УБЫТКАХ | B2: Таблица-2 (Форма-0204IS)
A3: =+Balance!A4 -> 43100 | B3: =Balance!B3 -> АКБ "Микрокредитбанк"
A4: Категории | B4: в тыс. сум
A5: 1. ПРОЦЕНТНЫЕ ДОХОДЫ
A6: a. Процентные доходы по счетам в ЦБРУ | B6: 62
A7: б. Процентные доходы по счетам в других банках | B7: 58525
A8: в. Процентные доходы по купленным векселям | B8: 0
A9: г. Процентные доходы по инвестициям | B9: 0
A10: д. Процентные доходы по счетам купли-продажи ценных бумаг | B10: 222750
A11: е. Процентные доходы по обязательствам клиентов | B11: 0
A12: ж. Процентные доходы по обяз-вам клиентов по непогашенным акцептам этого банка | B12: 0
A13: з. Процент, Дисконт (Скидки) и взносы по кредитным и лизинговым операциям | B13: 142882099
A14: и. Процентные доходы по соглашениям о покупке ценных бумаг с обратным выкупом | B14: 0
A15: к. Другие процентные доходы | B15: 79738030
A16: л. Итого процентных доходов | B16: =SUM(B6:B15) -> 222901466 | D16: =+'Analysis of Interest'!B42 -> 222901466
A18: 2. ПРОЦЕНТНЫЕ РАСХОДЫ
A19: а. Процентные расходы по депозитам до востребования | B19: 374026
A20: б. Процентные расходы по сберегательным депозитам | B20: 9509331
A21: в. Процентные расходы по срочным депозитам | B21: 58283006
A22: г. Процентные расходы по счетам к оплате в ЦБРУ | B22: 0
A23: д. Процентные расходы по счетам к оплате в другие банки | B23: 9974483
A24: е. Итого процентных расходов по депозитам | B24: =SUM(B19:B23) -> 78140846
A25: ж. Процентные расходы по кредитам к оплате | B25: 2088909
A26: з. Процентные расходы по соглашениям о продаже ц/б с последующим выкупом | B26: 0
A27: и. Другие процентные расходы | B27: 65909560
A28: к. Итого процентных расходов по займам | B28: =SUM(B25:B27) -> 67998469
A29: л. Итого процентных расходов | B29: =B28+B24 -> 146139315 | C29: =+'Analysis of Interest'!B81 -> 146139315
A31: 3. ЧИСТЫЕ ПРОЦЕНТНЫЕ ДОХОДЫ ДО ОЦЕНКИ ВОЗМОЖНЫХ УБЫТКОВ ПО КРЕДИТАМ И ЛИЗИНГУ | B31: =B16-B29 -> 76762151
A32: а. Минус: Оценка возможных убытков по кредитам и лизингу | B32: 86761235
A33: б. Чистые процентные доходы после оценки возможных убытков по кредитам и лизингу | B33: =B31-B32 -> -9999084
A35: 4. БЕСПРОЦЕНТНЫЕ ДОХОДЫ
A36: а. Доходы от комиссий и платы за услуги | B36: 75291341
A37: б. Прибыль в иностранной валюте | B37: 53897168
A38: в. Прибыль от коммерческих операций | B38: 0
A39: г. Прибыль и дивиденды от инвестиций | B39: 69286
A40: д. Другие беспроцентные доходы | B40: 34923148
A41: е. Итого беспроцентных доходов | B41: =SUM(B36:B40) -> 164180943
A43: 5. БЕСПРОЦЕНТНЫЕ РАСХОДЫ
A44: а. Комиссионные расходы и расходы за услуги | B44: 20979604
A45: б. Убытки в иностранной валюте | B45: 4286591
A46: в. Убытки по счетам купли-продажи | B46: 0
A47: г. Убытки от инвестиций | B47: 0
A48: д. Другие беспроцентные расходы | B48: 308675
A49: е. Итого беспроцентных расходов | B49: =SUM(B44:B48) -> 25574870
A51: 6. ЧИСТЫЙ ДОХОД ДО ОПЕРАЦИОННЫХ РАСХОДОВ | B51: =B33+B41-B49 -> 128606989
A53: 7. ОПЕРАЦИОННЫЕ РАСХОДЫ
A54: а. Заработная плата и другие расходы на сотрудников | B54: 118025538
A55: б. Аренда и содержание | B55: 21282435
A56: в. Командировочные и транспортные расходы | B56: 3152602
A57: г. Административные расходы | B57: 8171359
A58: д. Репрезентация и благотворительность | B58: 4838603
A59: е. Расходы на износ | B59: 10322100
A60: ж. Страхование, налоги и другие расходы | B60: 25742096
A61: з. Итого операционных расходов | B61: =SUM(B54:B60) -> 191534733
A63: 8. ОЦЕНКА НЕКРЕДИТНЫХ УБЫТКОВ | B63: 17346697
A65: 9. ЧИСТАЯ ПРИБЫЛЬ ДО УПЛАТЫ НАЛОГОВ И ДРУГИХ ПОПРАВОК | B65: =B51-B61-B63 -> -80274441
A66: а. Оценка налога на прибыль | B66: 7948902
A68: 10. ДОХОД ДО ВВЕДЕНИЯ ПОПРАВОК | B68: =B65-B66 -> -88223343
A69: а. Непредвиденные доходы или убытки, чистые
A70: б. Другие поправки к прибыли, чистые
A72: 11. ЧИСТАЯ ПРИБЫЛЬ (УБЫТКИ) | B72: =B68+B69+B70 -> -88223343
A74: Подпись Председателя правления:
A76: Подпись Главного Бухгалтера:

Sheet Analysis of Interest
B1: Приложение №1 к Рекомендациям по заполнению отчетности коммерческих банков по банковскому надзору представляемых Центральному банку Республики Узбекистан
A2: АНАЛИЗ ПРОЦЕНТНЫХ ДОХОДОВ И РАСХОДОВ | B2: Таблица-3 (Форма-0206IS)
A3: =+Balance!A4 -> 43100 | B3: =Balance!B3 -> АКБ "Микрокредитбанк"
A4: Категория | B4: в тыс. сум
A5: 1 . ПРОЦЕНТНЫЕ ДОХОДЫ ПО КРЕДИТНЫМ И ЛИЗИНГОВЫМ ОПЕРАЦИЯМ
A6: a. Кредиты и лизинговые операции ЦБРУ | B6: 0
A7: б. Кредиты и лизинговые операции другим банкам | B7: 27
A8: в. Кредиты и лизинговые операции Правительству | B8: 1355
A9: г. Кредиты и лизинговые операции физическим лицам | B9: 54031630
A10: д. Кредиты и лизинговые операции государственным предприятиям | B10: 9124556
A11: е. Кредиты и лизинговые операции совместным и иностранным предприятиям | B11: 294487
A12: ж. Кредиты и лизинговые операции частным товариществам и корпорациям | B12: 78087747
A13: з. Другие кредиты и лизинговые операции | B13: 1342297
A14: и. ИТОГО ПРОЦЕНТНЫХ ДОХОДОВ ПО КРЕДИТНЫМ И ЛИЗИНГОВЫМ ОПЕРАЦИЯМ | B14: =SUM(B6:B13) -> 142882099
A16: 2. ПРОЦЕНТНЫЕ ДОХОДЫ ПО КОРРЕСПОНДЕНТСКИМ СЧЕТАМ
A17: a. К получению из ЦБРУ | B17: 62
A18: б. К получению из других банков | B18: 58525
A19: в. ИТОГО ПРОЦЕНТНЫХ ДОХОДОВ ПО КОРРЕСПОНДЕНТСКИМ СЧЕТАМ | B19: =SUM(B17:B18) -> 58587
A21: 3. ПРОЦЕНТНЫЕ ДОХОДЫ ПО СЧЕТАМ КУПЛИ-ПРОДАЖИ Ц/Б
A22: a. Государственные казначейские ценные бумаги | B22: 0
A23: б. Облигации и ценные бумаги ЦБРУ | B23: 0
A24: в. Ценные бумаги государственных корпораций | B24: 0
A25: г. Еврооблигации | B25: 0
A26: д. Частные ценные бумаги | B26: 222750
A27: е. Другие ценные бумаги | B27: 0
A28: ж. ИТОГО ПРОЦЕНТНЫХ ДОХОДОВ ПО СЧЕТАМ КУПЛИ-ПРОДАЖИ Ц/Б | B28: =SUM(B22:B27) -> 222750
A30: 4. ПРОЦЕНТНЫЕ ДОХОДЫ ПО ИНВЕСТИЦИЯМ
A31: а. Государственные облигации | B31: 0
A32: б. Облигации и ценные бумаги ЦБРУ | B32: 0
A33: в. Частные облигации | B33: 0
A34: г. Еврооблигации | B34: 0
A35: д. Другие ценные бумаги | B35: 0
A36: е. ИТОГО ПРОЦЕНТНЫХ ДОХОДОВ ПО ИНВЕСТИЦИЯМ | B36: =SUM(B31:B35) -> 0
A38: 5. ДРУГИЕ ПРОЦЕНТНЫЕ ДОХОДЫ
A39: а. Процентные доходы по соглашениям о покупке ц/б c обратным выкупом | B39: 0
A40: б. Другие процентные доходы | B40: 79738030
A42: 6. ИТОГО ПРОЦЕНТНЫХ ДОХОДОВ | B42: =B14+B19+B28+B36+B39+B40 -> 222901466
A44: 7. ПРОЦЕНТНЫЕ РАСХОДЫ ПО ДЕПОЗИТАМ
A45: A. Депозиты до востребования
A46: а. Правительство | B46: 269131
A47: б. Физические лица | B47: 104789
A48: в. Государственные предприятия | B48: 0
A49: г. Совместные и иностранные предприятия | B49: 0
A50: д. Частные товарищества и корпорации | B50: 106
A51: е. Другие депозиты | B51: 0
A52: ж. Итого процентных расходов по депозитам до востребования | B52: =SUM(B46:B51) -> 374026
A54: Б. Сберегательные депозиты
A55: а. Правительство | B55: 294
A56: б. Физические лица | B56: 9502597
A57: в. Государственные предприятия | B57: 985
A58: г. Совместные и иностранные предприятия | B58: 0
A59: д. Частные товарищества и корпорации | B59: 2441
A60: е. Другие депозиты | B60: 3014
A61: ж. Итого процентных расходов по сберегательным депозитам | B61: =SUM(B55:B60) -> 9509331
A63: В. Срочные депозиты
A64: а. Правительство | B64: 33155971
A65: б. Физические лица | B65: 12396061
A66: в. Государственные предприятия | B66: 1981714
A67: г. Совместные и иностранные предприятия | B67: 3106589
A68: д. Частные товарищества и корпорации | B68: 922357
A69: е. Другие депозиты | B69: 6720314
A70: ж. Итого процентных расходов по срочным депозитам | B70: =SUM(B64:B69) -> 58283006
A72: Г. ИТОГО ПРОЦЕНТНЫХ РАСХОДОВ ПО ДЕПОЗИТАМ | B72: =B52+B61+B70 -> 68166363
A74: 8. ПРОЦЕНТНЫЕ РАСХОДЫ ПО ДРУГИМ ОБЯЗАТЕЛЬСТВАМ
A75: а. Процентные расходы по непогашенным акцептам | B75: 0
A76: б. Процентные расходы по кредитам к оплате | B76: 1904416
A77: в. Процентные расходы по соглашениям о продаже ц/б с последующим выкупом | B77: 0
A78: г. Другие процентные расходы | B78: 76068536
A79: д. ИТОГО ПРОЦЕНТНЫХ РАСХОДОВ ПО ДРУГИМ ОБЯЗАТЕЛЬСТВАМ | B79: =SUM(B75:B78) -> 77972952
A81: 9. ИТОГО ПРОЦЕНТНЫХ РАСХОДОВ | B81: =B72+B79 -> 146139315
A83: Подпись Председателя правления:
A85: Подпись Главного Бухгалтера:

Sheet Bank Capital Calc.
D1: Приложение №1 к Рекомендациям по заполнению отчетности коммерческих банков по банковскому надзору представляемых Центральному банку Республики Узбекистан
A2: РАСЧЕТ КАПИТАЛА БАНКА | E2: Таблица-4 (Форма-3004CAR)
A3: =+Balance!A4 -> 43100
D4: =Balance!B3 -> АКБ "Микрокредитбанк"
A5: No. | B5: Характеристики | C5: Капитал
C6: Основной | D6: Дополнительный | E6: Итого капитала
B7: (A) | C7: (Б) | D7: (В) | E7: (Г)
A8: I. | B8: КАПИТАЛ УРОВНЯ 1 (до вычетов)
A9: 1 | B9: Обыкновенные Акции
A10: a | B10: Полностью оплаченные обыкновенные акции | C10: 592608108
A11: б | B11: Минус: Обратно Выкупленные обыкновенные акции | C11: 0
A12: в | B12: Выпущенные, полностью оплаченные обыкновенные акции | E12: =+C10-C11 -> 592608108
A13: 2 | B13: Некумулятивные бессрочные привилегированные акции
A14: а | B14: Полностью оплаченные привилегированные акции | D14: 144180
A15: б | B15: Минус: Обратно Выкупленные привилегированные акции
A16: в | B16: Выпущенные, полностью оплаченные привилегированные акции | E16: =+D14-D15 -> 144180
A17: 3 | B17: Добавленный капитал | E17: =+C17+D17 -> 0
A18: 4 | B18: Нераспределенная прибыль
A19: а | B19: Капитальные резервы | C19: 28021551
A20: б | B20: Нераспределенная прибыль | C20: 12847445
A21: в | B21: Минус: Убыток за текущий год | C21: -88223343
A22: г | B22: Итого нераспределенная прибыль | E22: =+C19+C20+C21 -> -47354347
A23: 5 | B23: Интерес меньшинства в консолидированных дочерних компаниях (согласно МБС) | E23: =+C23 -> 0
A24: 6 | B24: Доля участия дочерних предприятий (выпущенные дочерними предприятиями и находящиеся во владении третьих лиц инструменты, приравненные к капиталу) | E24: =+D24 -> 0
A25: 7 | B25: Резерв на девальвацию | E25: =+C25 -> 0
A26: 8 | B26: Итого капитал уровня 1 до вычетов | C26: =SUM(C10:C25) -> 5.4525376e+08 | D26: =SUM(D10:D25) -> 144180 | E26: =SUM(C26+D26) -> 5.4539794e+08
A27: II | B27: ВЫЧЕТЫ ИЗ СУММЫ КАПИТАЛА УРОВНЯ I
A28: 1 | B28: Нематериальные активы | C28: 1980258 | E28: =-C28 -> -1980258
A29: 2 | B29: Все инвестиции в капитал неконсолидированных хозяйствующих субъектов, в том числе в долговые обязательства, которые образуют капитал хозяйствующих субъектов | C29: 3099523 | E29: =-C29 -> -3099523
A30: 3 | B30: Инвестиции в капитал других банков | E30: =-C30 -> 0
A31: 4 | B31: Итого вычетов из суммы капитала Уровня 1 | C31: =SUM(C28:C30) -> 5079781 | E31: =-C31 -> -5079781
A32: III | B32: СКОРРЕКТИРОВАННЫЙ КАПИТАЛ УРОВНЯ I | E32: =SUM(E12+E16+E17+E22+E23+E25+E31) -> 5.4031816e+08
A34: IV | B34: КАПИТАЛ УРОВНЯ II
A36: 1 | B36: Прибыль за текущий год (при подтверждении аудиторами - 100%, в противном случае 50% от суммы) | C36: 0 | E36: =+C36 -> 0
A37: 2 | B37: Резервы, создаваемые на стандартные кредиты (активы), в размере не более 1.25% от общей суммы активов, взвешенных с учетом риска | C37: 0 | E37: =+C37 -> 0
A38: 3 | B38: Субординированный долг | C38: 0 | E38: =+C38 -> 0
A39: 4 | B39: Излишки оценочной стоимости прироста над первоначальной стоимостью | C39: 169615.96 | E39: =+C39 -> 169615.96
A40: 5 | B40: Другие инструменты капитала, в том числе обязательства смешанного типа (не более 1/3 части капитала 1 уровня после вычетов) | C40: 0 | E40: =+C40 -> 0
A41: 6 | B41: Вычеты превышения Капитала Уровня II над Капиталом Уровня I | E41: =IF(C42<(E32/3),0,(C42-E32/3)*-1) -> 0
A42: 7 | B42: Итого капитала Уровня II | C42: =SUM(C36:C40) -> 169615.96 | E42: =+C42 -> 169615.96
A43: V | B43: СКОРРЕКТИРОВАННЫЙ КАПИТАЛ УРОВНЯ II | E43: =+C42+E41 -> 169615.96
A44: VI | B44: ИТОГО РЕГУЛЯТИВНЫЙ КАПИТАЛ | E44: =E32+C42+E41 -> 5.4048778e+08
A45: VII | B45: ОБЩАЯ СУММА АКТИВОВ, ВЗВЕШЕННЫХ С УЧЕТОМ РИСКА | E45: =E46+E47-(IF(E48<0,E48,0)) -> 1.8831785e+09
A46: 1 | B46: Сумма балансовых и забалансовых активов, взвешенных с учетом риска | E46: ='Calculation of Risk Weighted As'!H74 -> 1.7071404e+09
A47: 2 | B47: Операционный риск | E47: ='Calculation of Risk'!C19 -> 1.7603803e+08
A48: 3 | B48: Рыночный риск | E48: ='Calculation of Risk'!C25 -> 99201970
A49: VIII | B49: КОЭФФИЦИЕНТ КАПИТАЛА УРОВНЯ I (III/VII) | E49: =IF(E45=0,"",E32/E45) -> 0.28691819 | G49: =+'Calculation of Risk'!G10 -> 9.5
A50: IX | B50: КОЭФФИЦИЕНТ ОБЩЕЙ СУММЫ КАПИТАЛА, ОСНОВАННОГО НА РИСКЕ (VI/VII) | E50: =E44/E45 -> 0.28700826
A51: X | B51: Активы для расчета левеража | E51: =SUM(E52:E55) -> 2.2465929e+09
A52: 1 | B52: Общие активы | E52: =+Balance!C36 -> 1742993049
A53: 2 | B53: забалансовые инструменты | E53: =+'Calculation of Risk Weighted As'!G72 -> 505580123
A54: 3 | B54: деривативные (производные) инструменты
A55: 4 | B55: Минус: Нематериальные активы | E55: =+E28 -> -1980258
A56: XI | B56: Коэффициент левеража | E56: =E32/E51 -> 0.24050559
B58: Подпись Председателя правления:
B60: Подпись Главного Бухгалтера:

Sheet Calculation of Risk Weighted As
F1: Приложение №1 к Рекомендациям по заполнению отчетности коммерческих банков по банковскому надзору представляемых Центральному банку Республики Узбекистан
A2: РАСЧЕТ АКТИВОВ ВЗВЕШЕННЫХ С УЧЕТОМ РИСКА | G2: Таблица-5 (Форма-3006CAR)
B3: =+Balance!A4 -> 43100 | D3: =Balance!B3 -> АКБ "Микрокредитбанк"
A5: № | B5: Характеристики | C5: 0 | D5: 0.2 | E5: 0.5 | F5: 1 | G5: 1.5
C6: Риск | D6: Риск | E6: Риск | F6: Риск | G6: Риск
B7: (A) | C7: (Б) | D7: (В) | E7: (Г) | F7: (Д) | G7: (Е)
B8: Балансовые Активы
A9: 1. | B9: Касса (наличность и монеты) и Драгоценные металлы | C9: 75966635
A10: 2. | B10: Денежная наличность и другие платежные документы в пути | D10: 987722
A11: 3. | B11: Корреспондентские и резервные счета в ЦБРУ | C11: 213192148
A12: 4. | B12: Корр. счета, кредиты и другие требования к банкам и депозитарным институтам
A13: а | B13: требования к банкам стран с низким уровнем риска
A14: б | B14: требования к другим банкам | F14: 78542844
A15: 5. | B15: Рыночные ценные бумаги, чистые
A16: а) | B16: Ценные бумаги, выпущенные Правительством Республики Узбекистан и ЦБРУ | C16: 0
A17: б) | B17: Ценные бумаги, выпущенные правительствами и центральными банками стран, с низким уровня риска, а также другие требования к центральным банкам и правительствам этих стран | C17: 0
A18: в) | B18: Другие ценные бумаги | F18: 349524
A19: 6. | B19: Кредиты и другие активы или их части, обеспеченные наличными деньгами, хранящимися на отдельном блокированном депозитном счете. | C19: 0
A20: 7. | B20: Все требования банка, деноминированные в местную валюту стран не входящих в группу стран с низким уровнем риска, к Центральным банкам и центральным правительствам этих стран | D20: 0
A21: 8. | B21: Активы, обеспеченные ценными бумагами выпущенными банками зарегистрированными в странах с низким уровнем риска | D21: 0
A22: 9. | B22: Требования банка к международным кредитным организациям, а также активы, гарантированные этими организациями | D22: 0
A23: 10. | B23: Активы или их части, обеспеченные залогом в виде ценных бумаг, оцененных по текущей рыночной стоимости и эмитированных международными финансовыми институтами | D23: 0
A24: 11. | B24: Кредиты и лизинги, чистые
A25: а) | B25: прямые требования к Правительству и Центральному банку Республики Узбекистан | C25: 0
A26: б) | B26: Активы или их части, обеспеченные ценными бумагами, которые оцененные по текущей рыночной стоимости и выпущенными или гарантированными Правительством Республики Узбекистан, Центральным банком Республики Узбекистан или Правительствами стран с низким уровнем риска. | D26: 0
A27: в) | B27: Кредиты на недвижимость обеспеченные приобретаемым или строящимся домом (квартирой) | E27: 0
A28: г) | B28: Реструктуризированные кредиты и кредиты в статусе "ненаращивания" | F28: 0
A29: д) | B29: Кредиты, по которым банк не имеет приоритетного права на залог | F29: 0
A30: е) | B30: Пересмотренные или пролонгированные кредиты и лизинги более одного раза | G30: 0
A31: ж) | B31: все другие кредиты (кроме лизинга) | F31: 1236844076
A32: 12. | B32: Кредиты и лизинги в судебном разбирательстве, чистые
A33: 13. | B33: Просроченные кредиты и лизинги, чистые | G33: 10299194
A34: 14. | B34: Финансовый лизинг | F34: 5263146
A35: 15. | B35: Основные средств и другое собственное имущество банка
A36: а | B36: Основные средства, используемые в банковской деятельности (минус амортизация) | F36: 98890009
A37: б | B37: Недвижимое имущество принятое на баланс банка в целях полного или частичного погащения задолженности | G37: 1613115
A38: в | B38: Недвижимое имущество банка, которым банк не пользуется более двух лет | G38: 0
A39: 16. | B39: Инвестиции в капитал неконсолидированных банковских и небанковских финансовых дочерних компаний и всех нефинансовых предприятий
A40: 17. | B40: Все другие инвестиции, чистые | F40: 2749999
A41: 18. | B41: Нематериальные активы, включая гудвилл | C41: 1980258
A42: 19. | B42: Другие активы в судебном разбирательстве и не взысканные в установленном порядке | G42: 0
A43: 20. | B43: Другие активы, чистые | C43: 13259251 | F43: 3055128 | H43: =Balance!C36 -> 1742993049
A44: 21. | B44: Общая сумма балансовых активов согласно Инструкции | C44: =SUM(C9:C43) -> 304398292 | D44: =SUM(D9:D43) -> 987722 | E44: =SUM(E9:E43) -> 0 | F44: =SUM(F9:F43) -> 1425694726 | G44: =SUM(G9:G43) -> 11912309 | H44: =SUM(C44:G44) -> 1742993049
A45: 22. | B45: Общая сумма балансовых рисковых активов, по группам риска | D45: =D44*D5 -> 197544.4 | E45: =E44*E5 -> 0 | F45: =F44*F5 -> 1425694726 | G45: =G44*G5 -> 17868464
A46: 23. | B46: Общая сумма балансовых рисковых активов | G46: =SUM(D45:G45) -> 1.4437607e+09
A49: № | B49: Характеристики | C49: Фактор пересчета кредита | D49: 0 | E49: 0.2 | F49: 0.5 | G49: 1 | H49: Значение риска
D50: Риск | E50: Риск | F50: Риск | G50: Риск
B52: (A) | C52: (Б) | D52: (В) | E52: (Г) | F52: (Д) | G52: (Е) | H52: (Ж)
A53: Забалансовые Активы
A54: 1 | B54: Обязательства по выдаче кредита
A55: a | B55: Более одного года | C55: 0.5 | G55: 484400880 | H55: =(E55*0.1)+(F55*0.25)+(G55*0.5) -> 242200440
A56: б | B56: Год и менее | C56: 0.2 | H56: =(E56*0.04)+(F56*0.1)+(G56*0.2) -> 0
A57: 2 | B57: Обязательства по приобретению ценных бумаг и других активов (включая активы, проданные в соответствии с соглашениями о выкупе) | C57: 1 | H57: =(E57*0.2)+(F57*0.5)+(G57*1) -> 0
A58: 3 | B58: Гарантии и поручительства | C58: 1 | G58: 21179243 | H58: =(E58*0.2)+(F58*0.5)+(G58*1) -> 21179243
A59: 4 | B59: Аккредитивы
A60: a | B60: Прямые кредитные заменители | C60: 1 | H60: =(E60*0.2)+(F60*0.5)+(G60*1) -> 0
A61: б | B61: Связанные со сделками | C61: 0.5 | H61: =(E61*0.1)+(F61*0.25)+(G61*0.5) -> 0
A62: в | B62: Связанные с торговлей (краткосрочные, самоликвидирующиеся, обеспеченные) | C62: 0.2 | H62: =(E62*0.04)+(F62*0.1)+(G62*0.2) -> 0
A63: 5 | B63: Форврдные котракты, свопы, опционы и подобные обязательства
A64: a | B64: Контракты по процентной ставке
A65: а1 | B65: Со оставшимся сроком погашения до одного года | C65: 0.005 | H65: =(E65*0.001)+(F65*0.0025)+(G65*0.005) -> 0
A66: а2 | B66: Со оставшимся сроком погашения от одного года до двух лет | C66: 0.01 | H66: =(E66*0.002)+(F66*0.005)+(G66*0.01) -> 0
A67: а3 | B67: Со оставшимся сроком погашения от двух до трех лет | C67: 0.02 | H67: =(E67*0.004)+(F67*0.01)+(G67*0.02) -> 0
A68: б | B68: Валютные котракты и золото
A69: б1 | B69: С первоначальным сроком погашения до одного года | C69: 0.02 | G69: 0 | H69: =(E69*0.004)+(F69*0.01)+(G69*0.02) -> 0
A70: б2 | B70: С первоначальным сроком погашения от одного года до двух лет | C70: 0.05 | H70: =(E70*0.01)+(F70*0.025)+(G70*0.05) -> 0
A71: б3 | B71: С первоначальным сроком погашения от двух до трех лет | C71: 0.08 | H71: =(E71*0.016)+(F71*0.04)+(G71*0.08) -> 0
A72: 6 | B72: Общая сумма забалансовых активов | D72: =SUM(D55:D71) -> 0 | E72: =SUM(E55:E71) -> 0 | F72: =SUM(F55:F71) -> 0 | G72: =SUM(G55:G71) -> 505580123
A73: 7 | B73: Общая сумма забалансовых активов, взвешенных с учетом риска | H73: =SUM(H55:H71) -> 263379683
A74: 8 | B74: Общая сумма активов, взвешенных с учетом риска | H74: =SUM(H73+G46) -> 1.7071404e+09 | I74: =+H74*0.15 -> 2.5607106e+08
B76: Подпись Председателя правления:
B78: Подпись Главного Бухгалтера:

Sheet Calculation of Risk
C1: Приложение №1 к Рекомендациям по заполнению отчетности коммерческих банков по банковскому надзору представляемых Центральному банку Республики Узбекистан | I1: Достаточность капитала - К1 | J1: Коэффициент достаточности капитала I уровня K2 | K1: Доля основного капитала I уровня к регулятивному капиталу | L1: Коэффициент нормы покрытия ликвидности | M1: Норма чистого стабильного финансирования (НЧСФ)
A2: РАСЧЕТ ПО ОПЕРАЦИОННЫМ И РЫНОЧНЫМ РИСКАМ | H2: 2015 | I2: 10 | J2: 7.5 | K2: 6 | L2: 80
C3: Таблица-5А (Форма-3006CAR) | H3: 2016 | I3: 11.5 | J3: 8.5 | K3: 7 | L3: 80
B4: =+Balance!A4 -> 43100 | C4: =+Balance!B3 -> АКБ "Микрокредитбанк" | H4: 2017 | I4: 12.5 | J4: 9.5 | K4: 7.5 | L4: 90
A5: № | B5: Наименование показателя | C5: в тыс. сум | H5: 2018 | I5: 13.5 | J5: 10.5 | K5: 8.5 | L5: 100 | M5: 100
A6: 1. | B6: =+"Валовый доход банка за "&(E$9-3)&" год" -> Валовый доход банка за 2014 год | C6: =+C7-C8+C9 -> 117166860 | H6: 2019 | I6: 14.5 | J6: 11 | K6: 9.5 | L6: 100 | M6: 100
A7: а. | B7: процентные доходы | C7: 112378436
A8: б. | B8: процентные расходы | C8: 61062136 | E8: =RIGHT(Balance!A3,4) -> 2017 | G8: =VLOOKUP(E9,H2:M6,2,0) -> 12.5
A9: в. | B9: другие доходы | C9: 65850560 | E9: =IF(E8>H6,H6,E8) -> 2017
A10: 2. | B10: =+"Валовый доход банка за "&(E$9-2)&" год" -> Валовый доход банка за 2015 год | C10: =+C11-C12+C13 -> 150836429 | G10: =VLOOKUP($E$9,$H$2:$J$6,3,0) -> 9.5
A11: а. | B11: процентные доходы | C11: 154719438 | G11: =VLOOKUP($E$9,H2:M6,5,0) -> 90
A12: б. | B12: процентные расходы | C12: 96585301 | G12: =VLOOKUP(E9,H2:M6,6,0) -> 0
A13: в. | B13: другие доходы | C13: 92702292
A14: 3. | B14: =+"Валовый доход банка за "&(E$9-1)&" год" -> Валовый доход банка за 2016 год | C14: =+C15-C16+C17 -> 172091797
A15: а. | B15: процентные доходы | C15: 204104096
A16: б. | B16: процентные расходы | C16: 126300057
A17: в. | B17: другие доходы | C17: 94287758
A18: 4. | B18: Средний валовый доход банка (за последние три года) | C18: =(C6+C10+C14)/3 -> 146698362
A19: 5. | B19: Сумма операционных рисков | C19: =+(100/C26)*C18*15% -> 1.7603803e+08
A21: 6. | B21: Счета валютной позиции (счет 17101 (сумавая часть)) | C21: 124002463
A22: 7. | B22: Продажа на условиях Своп и Форвард (счет 92709, 92732) | C22: 0
A23: 8. | B23: Покупка на условиях Своп и Форвард (счет 92716, 92736) | C23: 0
A24: 9. | B24: Открытая валютная позиция, всего | C24: =C21+(C23-C22) -> 124002463 | D24: =+C24*0.1 -> 12400246
A25: 10. | B25: Сумма рыночных рисков | C25: =+(100/C26)*(C24*10%) -> 99201970
A26: 11. | B26: Действуюший минимальное требование к достаточности капитала | C26: =VLOOKUP($E$9,$H$2:$I$6,2,0) -> 12.5
A28: Подпись Председателя правления:
A30: Подпись Главного Бухгалтера:

Sheet Changes in Equity
B1: Приложение №1 к Рекомендациям по заполнению отчетности коммерческих банков по банковскому надзору представляемых Центральному банку Республики Узбекистан
A2: ИЗМЕНЕНИЯ В СОБСТВЕННОМ КАПИТАЛЕ | B2: Таблица-6 (Форма-3106CSA)
A3: =+Balance!A4 -> 43100 | B3: =Balance!B3 -> АКБ "Микрокредитбанк"
A4: Категория | B4: в тыс. сум
A5: 1. Итого собственного капитала первоначально определенного за прошлый год | B5: 282646747
A6: 2. Исправления в собственном капитале не показанные в отчете за прошлый год, чистые | B6: 0
A7: 3. Исправленный баланс на конец прошлого календарного года (сумма строк 1 и 2) | B7: =SUM(B5:B6) -> 282646747
A8: 4. Чистый прибыль (убыток) по состоянию на дату от начала года | B8: -88223343
A9: 5. Продажа, Обмен, Приобретение или выкуп акций, за текущий год (чистая выручка) | B9: 342586323
A10: 6. Изменения в оценочной стоимости прироста над первонач. стоимостью, за текущий год (чистые) | B10: -9709947
A11: 7. МИНУС: Денежные дивиденды объявленные по привилегированным акциям
A12: 8. МИНУС: Денежные дивиденды объявленные по обыкновенным акциям
A13: 9. Другие статьи влияющие на собственный капитал за текущий год (чистые) | B13: 18475086
A14: 10. Итого собственного капитала на конец текущего периода (сумма строк с 3 по 10) | B14: =B7+SUM(B8:B10)-SUM(B11:B12)+B13 -> 545774866
A16: Подпись Председателя правления:
A18: Подпись Главного Бухгалтера:

Sheet Recociliation 
B1: Приложение №1 к Рекомендациям по заполнению отчетности коммерческих банков по банковскому надзору представляемых Центральному банку Республики Узбекистан
A2: ВЫВЕРКА НЕРАСПРЕДЕЛЕННОЙ ПРИБЫЛИ | B2: Таблица-7 (Форма-0208IS)
A3: =+Balance!A4 -> 43100
A4: =Balance!B3 -> АКБ "Микрокредитбанк" | B4: в тыс. сум
A5: 1. Нераспределенная прибыль, указанная в отчете за предыдущий календарный год | B5: 40126023
A6: 2. Плюс или Минус: Предварит. корректировки не указанные в отчете к концу года
A7: 3. Равно: Откорректированная нераспределенная прибыль | B7: =B5+B6 -> 40126023
A8: 4. Плюс или Минус: Кумулятивная чистая прибыль (Убытки) в текущем году | B8: -88223343
A9: 5. Минус: Денежные дивиденды объявленные по обыкновенным акциям
A10: 6. Минус: Денежные дивиденды объявленные по привилегированным акциям
A11: 7. Минус: Дивиденды в виде акций объявленные по обыкновенным акциям
A12: 8. Минус: Дивиденды в виде акций объявленные по привилегированным акциям
A13: 9. Другие статьи, влияющие на нераспределенную прибыль,Чистые | B13: 18475086
A14: 10. Равно: Текущий Баланс, Нераспределенная прибыль | B14: =B7+B8-SUM(B9:B12)+B13 -> -29622234
A16: Подпись Председателя правления:
A18: Подпись Главного Бухгалтера:

Sheet Loans Receivable
Q1: Приложение №1 к Рекомендациям по заполнению отчетности коммерческих банков по банковскому надзору представляемых Центральному банку Республики Узбекистан
A2: Кредиты к получению по отраслям экономики, типам клиентов и по типу обеспечения | R2: Таблица-8 (Форма-1516LES)
B3: =+Balance!A4 -> 43100 | P3: =Balance!B3 -> АКБ "Микрокредитбанк"
B4: Отрасль экономики | C4: Сумма кредита | D4: из них | G4: из них
D5: Начисляемые кредиты | E5: Неначисляемые кредиты | F5: Средняя процентная ставка | G5: Депозиты | H5: Гарантированные Правительством Республики Узбекистан | I5: из них | J5: Транспортные средства | K5: Инвентарь | L5: Недвижимость | M5: Оборудование | N5: Векселя (облигации) | O5: Акции | P5: Гарантия третьей стороны | Q5: Поручительства третьей стороны | R5: Страховой полис | S5: Необеспеченные | T5: Другое обеспечение
I6: Гарантированные Правительством Республики Узбекистан в иностранной валюте (экв.сум)
A7: Код | B7: (А) | C7: (Б) | D7: (В) | E7: (Г) | F7: (Д) | G7: (Е) | H7: (Ж) | I7: (Ж1) | J7: (З) | K7: (И) | L7: (К) | M7: (Л) | N7: (М) | O7: (Н) | P7: (О) | Q7: (П) | R7: (Р) | S7: (С) | T7: (Т)
B8: Промышленность
A9: 10 | B9: Физические лица | C9: =SUM(G9:T9)-I9 -> 14276766 | D9: =+SUM(G9:T9) -> 14276766 | F9: 0.16 | J9: 4960453 | L9: 3609587 | P9: 5706726
A10: =A9+10 -> 20 | B10: Государственные предприятия | C10: =SUM(G10:T10)-I10 -> 55895043 | D10: =+SUM(G10:T10) -> 55895043 | F10: 0.16 | J10: 1728447 | L10: 3647876 | P10: 50518720
A11: =A10+10 -> 30 | B11: Совместные и иностранные предприятия | C11: =SUM(G11:T11)-I11 -> 6560620 | D11: =+SUM(G11:T11) -> 6560620 | F11: 0.16 | J11: 2045376 | L11: 4515244
A12: =A11+10 -> 40 | B12: Частные товарищества и корпорации | C12: =SUM(G12:T12)-I12 -> 139693563 | D12: =+SUM(G12:T12) -> 139693563 | F12: 0.14 | J12: 52584227 | L12: 74035305 | M12: 1796900 | P12: 6033776 | T12: 5243355
A13: =A12+10 -> 50 | B13: Правительство | C13: =SUM(G13:T13)-I13 -> 0 | D13: 0
A14: =A13+10 -> 60 | B14: Прочие | C14: =SUM(G14:T14)-I14 -> 0 | D14: 0
A15: =A14+10 -> 70 | B15: Итого по промышленности | C15: =SUM(G15:T15)-I15 -> 216425992 | D15: =SUM(D9:D14) -> 216425992 | E15: =SUM(E9:E14) -> 0 | F15: =IF(C15=0,"",(F9*(C9/C15))+(F10*(C10/C15))+(F11*(C11/C15))+(F12*(C12/C15))+(F13*(C13/C15))+(F14*(C14/C15))) -> 0.14709087 | G15: =SUM(G9:G14) -> 0 | H15: =SUM(H9:H14) -> 0 | I15: =SUM(I9:I14) -> 0 | J15: =SUM(J9:J14) -> 61318503 | K15: =SUM(K9:K14) -> 0 | L15: =SUM(L9:L14) -> 85808012 | M15: =SUM(M9:M14) -> 1796900 | N15: =SUM(N9:N14) -> 0 | ... T15: =SUM(T9:T14) -> 5243355
B16: Сельское хозяйство
A17: =A15+10 -> 80 | B17: Физические лица | C17: =SUM(G17:T17)-I17 -> 137890348 | D17: =+SUM(G17:T17) -> 137890348 | F17: 0.13 | J17: 9473254 | L17: 12901203 | P17: 110089436 | T17: 5426455
A18: =A17+10 -> 90 | B18: Государственные предприятия | C18: =SUM(G18:T18)-I18 -> 56823460 | D18: =+SUM(G18:T18) -> 56823460 | F18: 0.14 | J18: 22095034 | L18: 22460581 | P18: 12267845
A19: =A18+10 -> 100 | B19: Совместные и иностранные предприятия | C19: =SUM(G19:T19)-I19 -> 0 | D19: =+SUM(G19:T19) -> 0
A20: =A19+10 -> 110 | B20: Частные товарищества и корпорации | C20: =SUM(G20:T20)-I20 -> 105931280 | D20: =+SUM(G20:T20) -> 105931280 | F20: 0.14 | J20: 37468720 | L20: 58021690 | P20: 10440870 | T20: 0
A21: =A20+10 -> 120 | B21: Фермерское хозяйство | C21: =SUM(G21:T21)-I21 -> 0 | D21: =+SUM(G21:T21) -> 0
A22: =A21+10 -> 130 | B22: Правительство | C22: =SUM(G22:T22)-I22 -> 0 | D22: =+SUM(G22:T22) -> 0
A23: =A22+10 -> 140 | B23: Прочие | C23: =SUM(G23:T23)-I23 -> 0 | D23: =+SUM(G23:T23) -> 0
A24: =A23+10 -> 150 | B24: Итого по сельскому хозяйству | C24: =SUM(G24:T24)-I24 -> 300645088 | D24: =SUM(D17:D23) -> 300645088 | E24: =SUM(E17:E23) -> 0 | F24: =IF(C24=0,"",(F17*(C17/C24))+(F18*(C18/C24))+(F19*(C19/C24))+(F20*(C20/C24))+(F21*(C21/C24))+(F22*(C22/C24))+(F23*(C23/C24))) -> 0.13541352 | G24: =SUM(G17:G23) -> 0 | H24: =SUM(H17:H23) -> 0 | I24: =SUM(I17:I23) -> 0 | J24: =SUM(J17:J23) -> 69037008 | K24: =SUM(K17:K23) -> 0 | L24: =SUM(L17:L23) -> 93383474 | M24: =SUM(M17:M23) -> 0 | N24: =SUM(N17:N23) -> 0 | ... T24: =SUM(T17:T23) -> 5426455
B25: Транспорт и коммуникации
A26: =A24+10 -> 160 | B26: Физические лица | C26: =SUM(G26:T26)-I26 -> 25275397 | D26: =+SUM(G26:T26) -> 25275397 | F26: 0.14 | G26: 502345 | J26: 19303796 | L26: 4373750 | P26: 743361 | T26: 352145
A27: =A26+10 -> 170 | B27: Государственные предприятия | C27: =SUM(G27:T27)-I27 -> 6469866 | D27: =+SUM(G27:T27) -> 6469866 | F27: 0.16 | J27: 5959815 | L27: 510051
A28: =A27+10 -> 180 | B28: Совместные и иностранные предприятия | C28: =SUM(G28:T28)-I28 -> 0 | D28: =+SUM(G28:T28) -> 0
A29: =A28+10 -> 190 | B29: Частные товарищества и корпорации | C29: =SUM(G29:T29)-I29 -> 138791421 | D29: =+SUM(G29:T29) -> 138791421 | F29: 0.14 | G29: 2297231 | J29: 120331781 | L29: 16162409
A30: =A29+10 -> 200 | B30: Правительство | C30: =SUM(G30:T30)-I30 -> 0 | D30: =+SUM(G30:T30) -> 0
A31: =A30+10 -> 210 | B31: Прочие | C31: =SUM(G31:T31)-I31 -> 0 | D31: =+SUM(G31:T31) -> 0
A32: =A31+10 -> 220 | B32: Итого по транспорту и коммуникациям | C32: =SUM(G32:T32)-I32 -> 170536684 | D32: =SUM(D26:D31) -> 170536684 | E32: =SUM(E26:E31) -> 0 | F32: =IF(C32=0,"",(F26*(C26/C32))+(F27*(C27/C32))+(F28*(C28/C32))+(F29*(C29/C32))+(F30*(C30/C32))+(F31*(C31/C32))) -> 0.14075877 | G32: =SUM(G26:G31) -> 2799576 | H32: =SUM(H26:H31) -> 0 | I32: =SUM(I26:I31) -> 0 | J32: =SUM(J26:J31) -> 145595392 | K32: =SUM(K26:K31) -> 0 | L32: =SUM(L26:L31) -> 21046210 | M32: =SUM(M26:M31) -> 0 | N32: =SUM(N26:N31) -> 0 | ... T32: =SUM(T26:T31) -> 352145
B33: Строительство
A34: =A32+10 -> 230 | B34: Физические лица | C34: =SUM(G34:T34)-I34 -> 51518565 | D34: =+SUM(G34:T34) -> 51518565 | F34: 0.15 | J34: 8046631 | L34: 16814400 | P34: 26514988 | T34: 142546
A35: =A34+10 -> 240 | B35: Государственные предприятия | C35: =SUM(G35:T35)-I35 -> 6926416 | D35: =+SUM(G35:T35) -> 6926416 | F35: 0.14 | J35: 2957132 | L35: 3648123 | P35: 321161
A36: =A35+10 -> 250 | B36: Совместные и иностранные предприятия | C36: =SUM(G36:T36)-I36 -> 0 | D36: =+SUM(G36:T36) -> 0
A37: =A36+10 -> 260 | B37: Частные товарищества и корпорации | C37: =SUM(G37:T37)-I37 -> 120243894 | D37: =+SUM(G37:T37) -> 120243894 | F37: 0.14 | J37: 41263190 | L37: 70055647 | M37: 1264299 | P37: 5715489 | T37: 1945269
A38: =A37+10 -> 270 | B38: Правительство | C38: =SUM(G38:T38)-I38 -> 0 | D38: =+SUM(G38:T38) -> 0
A39: =A38+10 -> 280 | B39: Прочие | C39: =SUM(G39:T39)-I39 -> 0 | D39: =+SUM(G39:T39) -> 0
A40: =A39+10 -> 290 | B40: Итого по строительству | C40: =SUM(G40:T40)-I40 -> 178688875 | D40: =SUM(D34:D39) -> 178688875 | E40: =SUM(E34:E39) -> 0 | F40: =IF(C40=0,"",(F34*(C34/C40))+(F35*(C35/C40))+(F36*(C36/C40))+(F37*(C37/C40))+(F38*(C38/C40))+(F39*(C39/C40))) -> 0.14288314 | G40: =SUM(G34:G39) -> 0 | H40: =SUM(H34:H39) -> 0 | I40: =SUM(I34:I39) -> 0 | J40: =SUM(J34:J39) -> 52266953 | K40: =SUM(K34:K39) -> 0 | L40: =SUM(L34:L39) -> 90518170 | M40: =SUM(M34:M39) -> 1264299 | N40: =SUM(N34:N39) -> 0 | ... T40: =SUM(T34:T39) -> 2087815
B41: Торговля и общественное питание
A42: =A40+10 -> 300 | B42: Физические лица | C42: =SUM(G42:T42)-I42 -> 85164109 | D42: =+SUM(G42:T42) -> 85164109 | F42: 0.16 | J42: 24642013 | L42: 35660511 | P42: 24007477 | T42: 854108
A43: =A42+10 -> 310 | B43: Государственные предприятия | C43: =SUM(G43:T43)-I43 -> 11994969 | D43: =+SUM(G43:T43) -> 11994969 | F43: 0.15 | J43: 3967574 | L43: 6906074 | P43: 395199 | T43: 726122
A44: =A43+10 -> 320 | B44: Совместные и иностранные предприятия | C44: =SUM(G44:T44)-I44 -> 0 | D44: =+SUM(G44:T44) -> 0
A45: =A44+10 -> 330 | B45: Частные товарищества и корпорации | C45: =SUM(G45:T45)-I45 -> 43054871 | D45: =+SUM(G45:T45) -> 43054871 | F45: 0.16 | J45: 14946585 | L45: 26474322 | P45: 1203581 | T45: 430383
A46: =A45+10 -> 340 | B46: Правительство | C46: =SUM(G46:T46)-I46 -> 0 | D46: =+SUM(G46:T46) -> 0
A47: =A46+10 -> 350 | B47: Прочие | C47: =SUM(G47:T47)-I47 -> 0 | D47: =+SUM(G47:T47) -> 0
A48: =A47+10 -> 360 | B48: Итого по торговле и общественному питанию | C48: =SUM(G48:T48)-I48 -> 140213949 | D48: =SUM(D42:D47) -> 140213949 | E48: =SUM(E42:E47) -> 0 | F48: =IF(C48=0,"",(F42*(C42/C48))+(F43*(C43/C48))+(F44*(C44/C48))+(F45*(C45/C48))+(F46*(C46/C48))+(F47*(C47/C48))) -> 0.15914452 | G48: =SUM(G42:G47) -> 0 | H48: =SUM(H42:H47) -> 0 | I48: =SUM(I42:I47) -> 0 | J48: =SUM(J42:J47) -> 43556172 | K48: =SUM(K42:K47) -> 0 | L48: =SUM(L42:L47) -> 69040907 | M48: =SUM(M42:M47) -> 0 | N48: =SUM(N42:N47) -> 0 | ... T48: =SUM(T42:T47) -> 2010613
B49: Материально-техническое снабжение и сбыт
A50: =A48+10 -> 370 | B50: Физические лица | C50: =SUM(G50:T50)-I50 -> 65829139 | D50: =+SUM(G50:T50) -> 65829139 | F50: 0.16 | J50: 7068729 | L50: 15270285 | P50: 42219188 | T50: 1270937
A51: =A50+10 -> 380 | B51: Государственные предприятия | C51: =SUM(G51:T51)-I51 -> 2035329 | D51: =+SUM(G51:T51) -> 2035329 | F51: 0.14 | J51: 946750 | L51: 1088579
A52: =A51+10 -> 390 | B52: Совместные и иностранные предприятия | C52: =SUM(G52:T52)-I52 -> 1483421 | D52: =+SUM(G52:T52) -> 1483421 | F52: 0.16 | J52: 374457 | L52: 1108964
A53: =A52+10 -> 400 | B53: Частные товарищества и корпорации | C53: =SUM(G53:T53)-I53 -> 58287022 | D53: =+SUM(G53:T53) -> 58287022 | F53: 0.14 | J53: 21356226 | L53: 32048155 | M53: 3101200 | P53: 1131404 | T53: 650037
A54: =A53+10 -> 410 | B54: Правительство | C54: =SUM(G54:T54)-I54 -> 0 | D54: =+SUM(G54:T54) -> 0
A55: =A54+10 -> 420 | B55: Прочие | C55: =SUM(G55:T55)-I55 -> 0 | D55: =+SUM(G55:T55) -> 0
A56: =A55+10 -> 430 | B56: Итого по материально-техническому снабжению и сбыту | C56: =SUM(G56:T56)-I56 -> 127634911 | D56: =SUM(D50:D55) -> 127634911 | E56: =SUM(E50:E55) -> 0 | F56: =IF(C56=0,"",(F50*(C50/C56))+(F51*(C51/C56))+(F52*(C52/C56))+(F53*(C53/C56))+(F54*(C54/C56))+(F55*(C55/C56))) -> 0.15054767 | G56: =SUM(G50:G55) -> 0 | H56: =SUM(H50:H55) -> 0 | I56: =SUM(I50:I55) -> 0 | J56: =SUM(J50:J55) -> 29746162 | K56: =SUM(K50:K55) -> 0 | L56: =SUM(L50:L55) -> 49515983 | M56: =SUM(M50:M55) -> 3101200 | N56: =SUM(N50:N55) -> 0 | ... T56: =SUM(T50:T55) -> 1920974
B57: Жилищно-коммунальные услуги
A58: =A56+10 -> 440 | B58: Физические лица | C58: =SUM(G58:T58)-I58 -> 0 | D58: =+SUM(G58:T58) -> 0
A59: =A58+10 -> 450 | B59: Государственные предприятия | C59: =SUM(G59:T59)-I59 -> 0 | D59: =+SUM(G59:T59) -> 0
A60: =A59+10 -> 460 | B60: Совместные и иностранные предприятия | C60: =SUM(G60:T60)-I60 -> 0 | D60: =+SUM(G60:T60) -> 0
A61: =A60+10 -> 470 | B61: Частные товарищества и корпорации | C61: =SUM(G61:T61)-I61 -> 0 | D61: =+SUM(G61:T61) -> 0
A62: =A61+10 -> 480 | B62: Правительство | C62: =SUM(G62:T62)-I62 -> 0 | D62: =+SUM(G62:T62) -> 0
A63: =A62+10 -> 490 | B63: Прочие | C63: =SUM(G63:T63)-I63 -> 0 | D63: =+SUM(G63:T63) -> 0
A64: =A63+10 -> 500 | B64: Итого по жилищно-коммунальным услугам | C64: =SUM(G64:T64)-I64 -> 0 | D64: =SUM(D58:D63) -> 0 | E64: =SUM(E58:E63) -> 0 | F64: =IF(C64=0,"",(F58*(C58/C64))+(F59*(C59/C64))+(F60*(C60/C64))+(F61*(C61/C64))+(F62*(C62/C64))+(F63*(C63/C64))) | G64: =SUM(G58:G63) -> 0 | H64: =SUM(H58:H63) -> 0 | I64: =SUM(I58:I63) -> 0 | J64: =SUM(J58:J63) -> 0 | K64: =SUM(K58:K63) -> 0 | L64: =SUM(L58:L63) -> 0 | M64: =SUM(M58:M63) -> 0 | N64: =SUM(N58:N63) -> 0 | ... T64: =SUM(T58:T63) -> 0
B65: Другие отрасли
A66: =A64+10 -> 510 | B66: Физические лица | C66: =SUM(G66:T66)-I66 -> 88308872 | D66: =+SUM(G66:T66) -> 88308872 | F66: 0.16 | J66: 21946257 | L66: 31485013 | P66: 32453920 | T66: 2423682
A67: =A66+10 -> 520 | B67: Государственные предприятия | C67: =SUM(G67:T67)-I67 -> 1788535 | D67: =+SUM(G67:T67) -> 1788535 | T67: 1788535
A68: =A67+10 -> 530 | B68: Совместные и иностранные предприятия | C68: =SUM(G68:T68)-I68 -> 0 | D68: =+SUM(G68:T68) -> 0
A69: =A68+10 -> 540 | B69: Частные товарищества и корпорации | C69: =SUM(G69:T69)-I69 -> 61879609 | D69: =+SUM(G69:T69) -> 61879609 | F69: 0.15 | J69: 20869688 | L69: 33566210 | M69: 947432 | P69: 4231163 | T69: 2265116
A70: =A69+10 -> 550 | B70: Центральный банк | C70: =SUM(G70:T70)-I70 -> 0 | D70: =+SUM(G70:T70) -> 0
A71: =A70+10 -> 560 | B71: Другие банки | C71: =SUM(G71:T71)-I71 -> 0 | D71: =+SUM(G71:T71) -> 0
A72: =A71+10 -> 570 | B72: Правительство | C72: =SUM(G72:T72)-I72 -> 0 | D72: =+SUM(G72:T72) -> 0
A73: =A72+10 -> 580 | B73: Небанковские финансовые институты | C73: =SUM(G73:T73)-I73 -> 0 | D73: =+SUM(G73:T73) -> 0
A74: =A73+10 -> 590 | B74: Негосударственные некоммерческие организации | C74: =SUM(G74:T74)-I74 -> 0 | D74: =+SUM(G74:T74) -> 0
A75: =A74+10 -> 600 | B75: Бюджетные организации | C75: =SUM(G75:T75)-I75 -> 0 | D75: =+SUM(G75:T75) -> 0
A76: =A75+10 -> 610 | B76: Прочие | C76: =SUM(G76:T76)-I76 -> 0 | D76: =+SUM(G76:T76) -> 0
A77: =A76+10 -> 620 | B77: Итого по другим отраслям | C77: =SUM(G77:T77)-I77 -> 151977016 | D77: =SUM(D66:D76) -> 151977016 | E77: =SUM(E66:E76) -> 0 | F77: =IF(C77=0,"",(F66*(C66/C77))+(F67*(C67/C77))+(F68*(C68/C77))+(F69*(C69/C77))+(F70*(C70/C77))+(F71*(C71/C77))+(F72*(C72/C77))+(F73*(C73/C77))+(F74*(C74/C77))+(F75*(C75/C77))+(F76*(C76/C77))) -> 0.1540454 | G77: =SUM(G66:G76) -> 0 | H77: =SUM(H66:H76) -> 0 | I77: =SUM(I66:I76) -> 0 | J77: =SUM(J66:J76) -> 42815945 | K77: =SUM(K66:K76) -> 0 | L77: =SUM(L66:L76) -> 65051223 | M77: =SUM(M66:M76) -> 947432 | N77: =SUM(N66:N76) -> 0 | ... T77: =SUM(T66:T76) -> 6477333
B78: Кредитные и лизинговые операции
A79: =A77+10 -> 630 | B79: Физические лица | C79: =SUM(G79:T79)-I79 -> 468263196 | D79: =D9+D17+D26+D34+D42+D50+D58+D66 -> 468263196 | E79: =E9+E17+E26+E34+E42+E50+E58+E66 -> 0 | F79: =IF(C79=0,0,(F9*(C9/C79))+(F17*(C17/C79))+(F26*(C26/C79))+(F34*(C34/C79))+(F42*(C42/C79))+(F50*(C50/C79))+(F58*(C58/C79))+(F66*(C66/C79))) -> 0.1489861 | G79: =G9+G17+G26+G34+G42+G50+G58+G66 -> 502345 | H79: =H9+H17+H26+H34+H42+H50+H58+H66 -> 0 | I79: =I9+I17+I26+I34+I42+I50+I58+I66 -> 0 | J79: =J9+J17+J26+J34+J42+J50+J58+J66 -> 95441133 | K79: =K9+K17+K26+K34+K42+K50+K58+K66 -> 0 | L79: =L9+L17+L26+L34+L42+L50+L58+L66 -> 120114749 | M79: =M9+M17+M26+M34+M42+M50+M58+M66 -> 0 | N79: =N9+N17+N26+N34+N42+N50+N58+N66 -> 0 | ... T79: =T9+T17+T26+T34+T42+T50+T58+T66 -> 10469873
A80: =A79+10 -> 640 | B80: Государственные предприятия | C80: =SUM(G80:T80)-I80 -> 141933618 | D80: =D10+D18+D27+D35+D43+D51+D59+D67 -> 141933618 | E80: =E10+E18+E27+E35+E43+E51+E59+E67 -> 0 | F80: =IF(C80=0,0,(F10*(C10/C80))+(F18*(C18/C80))+(F27*(C27/C80))+(F35*(C35/C80))+(F43*(C43/C80))+(F51*(C51/C80))+(F59*(C59/C80))+(F67*(C67/C80))) -> 0.14786884 | G80: =G10+G18+G27+G35+G43+G51+G59+G67 -> 0 | H80: =H10+H18+H27+H35+H43+H51+H59+H67 -> 0 | I80: =I10+I18+I27+I35+I43+I51+I59+I67 -> 0 | J80: =J10+J18+J27+J35+J43+J51+J59+J67 -> 37654752 | K80: =K10+K18+K27+K35+K43+K51+K59+K67 -> 0 | L80: =L10+L18+L27+L35+L43+L51+L59+L67 -> 38261284 | M80: =M10+M18+M27+M35+M43+M51+M59+M67 -> 0 | N80: =N10+N18+N27+N35+N43+N51+N59+N67 -> 0 | ... T80: =T10+T18+T27+T35+T43+T51+T59+T67 -> 2514657
A81: =A80+10 -> 650 | B81: Совместные и иностранные предприятия | C81: =SUM(G81:T81)-I81 -> 8044041 | D81: =D11+D19+D28+D36+D44+D52+D60+D68 -> 8044041 | E81: =E11+E19+E28+E36+E44+E52+E60+E68 -> 0 | F81: =IF(C81=0,0,(F11*(C11/C81))+(F19*(C19/C81))+(F28*(C28/C81))+(F36*(C36/C81))+(F44*(C44/C81))+(F52*(C52/C81))+(F60*(C60/C81))+(F68*(C68/C81))) -> 0.16 | G81: =G11+G19+G28+G36+G44+G52+G60+G68 -> 0 | H81: =H11+H19+H28+H36+H44+H52+H60+H68 -> 0 | I81: =I11+I19+I28+I36+I44+I52+I60+I68 -> 0 | J81: =J11+J19+J28+J36+J44+J52+J60+J68 -> 2419833 | K81: =K11+K19+K28+K36+K44+K52+K60+K68 -> 0 | L81: =L11+L19+L28+L36+L44+L52+L60+L68 -> 5624208 | M81: =M11+M19+M28+M36+M44+M52+M60+M68 -> 0 | N81: =N11+N19+N28+N36+N44+N52+N60+N68 -> 0 | ... T81: =T11+T19+T28+T36+T44+T52+T60+T68 -> 0
A82: =A81+10 -> 660 | B82: Частные товарищества и корпорации | C82: =SUM(G82:T82)-I82 -> 667881660 | D82: =D12+D20+D29+D37+D45+D53+D61+D69 -> 667881660 | E82: =E12+E20+E29+E37+E45+E53+E61+E69 -> 0 | F82: =IF(C82=0,0,(F12*(C12/C82))+(F20*(C20/C82))+(F29*(C29/C82))+(F37*(C37/C82))+(F45*(C45/C82))+(F53*(C53/C82))+(F61*(C61/C82))+(F69*(C69/C82))) -> 0.1422158 | G82: =G12+G20+G29+G37+G45+G53+G61+G69 -> 2297231 | H82: =H12+H20+H29+H37+H45+H53+H61+H69 -> 0 | I82: =I12+I20+I29+I37+I45+I53+I61+I69 -> 0 | J82: =J12+J20+J29+J37+J45+J53+J61+J69 -> 308820417 | K82: =K12+K20+K29+K37+K45+K53+K61+K69 -> 0 | L82: =L12+L20+L29+L37+L45+L53+L61+L69 -> 310363738 | M82: =M12+M20+M29+M37+M45+M53+M61+M69 -> 7109831 | N82: =N12+N20+N29+N37+N45+N53+N61+N69 -> 0 | ... T82: =T12+T20+T29+T37+T45+T53+T61+T69 -> 10534160
A83: =A82+10 -> 670 | B83: Фермерское хозяйство | C83: =SUM(G83:T83)-I83 -> 0 | D83: =D21 -> 0 | E83: =E21 -> 0 | F83: =IF(C83=0,0,(F21*(C21/C83))) -> 0 | G83: =G21 -> 0 | H83: =H21 -> 0 | I83: =I21 -> 0 | J83: =J21 -> 0 | K83: =K21 -> 0 | L83: =L21 -> 0 | M83: =M21 -> 0 | N83: =N21 -> 0 | ... T83: =T21 -> 0
A84: =A83+10 -> 680 | B84: Другие банки | C84: =SUM(G84:T84)-I84 -> 0 | D84: =D71 -> 0 | E84: =E71 -> 0 | F84: =IF(F71=0,0,F71) -> 0 | G84: =G71 -> 0 | H84: =H71 -> 0 | I84: =I71 -> 0 | J84: =J71 -> 0 | K84: =K71 -> 0 | L84: =L71 -> 0 | M84: =M71 -> 0 | N84: =N71 -> 0 | ... T84: =T71 -> 0
A85: =A84+10 -> 690 | B85: Центральный банк | C85: =SUM(G85:T85)-I85 -> 0 | D85: =D70 -> 0 | E85: =E70 -> 0 | F85: =IF(F70=0,0,F70) -> 0 | G85: =G70 -> 0 | H85: =H70 -> 0 | I85: =I70 -> 0 | J85: =J70 -> 0 | K85: =K70 -> 0 | L85: =L70 -> 0 | M85: =M70 -> 0 | N85: =N70 -> 0 | ... T85: =T70 -> 0
A86: =A85+10 -> 700 | B86: Правительство | C86: =SUM(G86:T86)-I86 -> 0 | D86: =D13+D22+D30+D38+D46+D54+D62+D72 -> 0 | E86: =E13+E22+E30+E38+E46+E54+E62+E72 -> 0 | F86: =IF(F72=0,0,F72) -> 0 | G86: =G13+G22+G30+G38+G46+G54+G62+G72 -> 0 | H86: =H13+H22+H30+H38+H46+H54+H62+H72 -> 0 | I86: =I13+I22+I30+I38+I46+I54+I62+I72 -> 0 | J86: =J13+J22+J30+J38+J46+J54+J62+J72 -> 0 | K86: =K13+K22+K30+K38+K46+K54+K62+K72 -> 0 | L86: =L13+L22+L30+L38+L46+L54+L62+L72 -> 0 | M86: =M13+M22+M30+M38+M46+M54+M62+M72 -> 0 | N86: =N13+N22+N30+N38+N46+N54+N62+N72 -> 0 | ... T86: =T13+T22+T30+T38+T46+T54+T62+T72 -> 0
A87: =A86+10 -> 710 | B87: Небанковские финансовые институты | C87: =SUM(G87:T87)-I87 -> 0 | D87: =D73 -> 0 | E87: =E73 -> 0 | F87: =IF(F73=0,0,F73) -> 0 | G87: =G73 -> 0 | H87: =H73 -> 0 | I87: =I73 -> 0 | J87: =J73 -> 0 | K87: =K73 -> 0 | L87: =L73 -> 0 | M87: =M73 -> 0 | N87: =N73 -> 0 | ... T87: =T73 -> 0
A88: =A87+10 -> 720 | B88: Негосударственные некоммерческие организации | C88: =SUM(G88:T88)-I88 -> 0 | D88: =D74 -> 0 | E88: =E74 -> 0 | F88: =IF(F74=0,0,F74) -> 0 | G88: =G74 -> 0 | H88: =H74 -> 0 | I88: =I74 -> 0 | J88: =J74 -> 0 | K88: =K74 -> 0 | L88: =L74 -> 0 | M88: =M74 -> 0 | N88: =N74 -> 0 | ... T88: =T74 -> 0
A89: =A88+10 -> 730 | B89: Бюджетные организации | C89: =SUM(G89:T89)-I89 -> 0 | D89: =D75 -> 0 | E89: =E75 -> 0 | F89: =IF(F75=0,0,F75) -> 0 | G89: =G75 -> 0 | H89: =H75 -> 0 | I89: =I75 -> 0 | J89: =J75 -> 0 | K89: =K75 -> 0 | L89: =L75 -> 0 | M89: =M75 -> 0 | N89: =N75 -> 0 | ... T89: =T75 -> 0
A90: =A89+10 -> 740 | B90: Прочие | C90: =SUM(G90:T90)-I90 -> 0 | D90: =D14+D23+D31+D39+D47+D55+D63+D76 -> 0 | E90: =E14+E23+E31+E39+E47+E55+E63+E76 -> 0 | F90: =IF(C90=0,0,(F14*(C14/C90))+(F23*(C23/C90))+(F31*(C31/C90))+(F39*(C39/C90))+(F47*(C47/C90))+(F55*(C55/C90))+(F63*(C63/C90))+(F76*(C76/C90))) -> 0 | G90: =G14+G23+G31+G39+G47+G55+G63+G76 -> 0 | H90: =H14+H23+H31+H39+H47+H55+H63+H76 -> 0 | I90: =I14+I23+I31+I39+I47+I55+I63+I76 -> 0 | J90: =J14+J23+J31+J39+J47+J55+J63+J76 -> 0 | K90: =K14+K23+K31+K39+K47+K55+K63+K76 -> 0 | L90: =L14+L23+L31+L39+L47+L55+L63+L76 -> 0 | M90: =M14+M23+M31+M39+M47+M55+M63+M76 -> 0 | N90: =N14+N23+N31+N39+N47+N55+N63+N76 -> 0 | ... T90: =T14+T23+T31+T39+T47+T55+T63+T76 -> 0
A91: =A90+10 -> 750 | B91: Итого кредита и лизинга | C91: =SUM(G91:T91)-I91 -> 1286122515 | D91: =SUM(D79:D90) -> 1286122515 | E91: =SUM(E79:E90) -> 0 | F91: =IF(C91=0,0,(F79*(C79/C91))+(F80*(C80/C91))+(F81*(C81/C91))+(F82*(C82/C91))+(F83*(C83/C91))+(F84*(C84/C91))+(F85*(C85/C91))+(F86*(C86/C91))+(F87*(C87/C91))+(F88*(C88/C91))+(F89*(C89/C91)+(F90*(C90/C91)))) -> 0.14541588 | G91: =SUM(G79:G90) -> 2799576 | H91: =SUM(H79:H90) -> 0 | I91: =SUM(I79:I90) -> 0 | J91: =SUM(J79:J90) -> 444336135 | K91: =SUM(K79:K90) -> 0 | L91: =SUM(L79:L90) -> 474363979 | M91: =SUM(M79:M90) -> 7109831 | N91: =SUM(N79:N90) -> 0 | ... T91: =SUM(T79:T90) -> 23518690
B93: Подпись Председателя правления: | C93: =Balance!B20+Balance!B21 -> 1286122513
B95: Подпись Главного Бухгалтера:

Sheet Aging Analysis
O1: Приложение №1 к Рекомендациям по заполнению отчетности коммерческих банков по банковскому надзору представляемых Центральному банку Республики Узбекистан
A2: Анализ просроченных кредитов и финансового лизинга к получению | P2: Таблица-9 (Форма-1604LOA)
A3: =Balance!A4 -> 43100 | O3: =Balance!B3 -> АКБ "Микрокредитбанк"
A5: № | B5: Характеристики | C5: Всего задолжность по кредитам | D5: % | E5: Реструктуризированные кредиты | F5: % | G5: Просроченная задолжность | K5: Анализ временной задолженности
G6: Всего | H6: % | I6: из них | K6: 1-30 дней | L6: 31-60 дней | M6: 61-90 дней | N6: 91-180 дней | O6: 181-365 дней | P6: 366 дней-2лет | Q6: Свыше 2 лет
I7: Просроченная задолжность | J7: В ходе судебного разбирательства
B9: (А) | C9: (Б) | D9: (В) | E9: (Г) | F9: (Д) | G9: (Е) | H9: (Ж) | I9: (З) | J9: (И) | K9: (К) | L9: (Л) | M9: (М) | N9: (Н) | O9: (О) | P9: (П) | Q9: (Р)
B10: По типу клиента
A11: 1 | B11: Центральный банк | C11: ='Loans Receivable'!C85 -> 0 | D11: =IF(C$24=0,"",C11/C$24) -> 0 | F11: =IF(E$24=0,"",E11/E$24) | G11: =SUM(K11:Q11) -> 0 | H11: =IF($G$24=0,"",G11/$G$24) -> 0
A12: 2 | B12: Другие банки | C12: ='Loans Receivable'!C84 -> 0 | D12: =IF(C$24=0,"",C12/C$24) -> 0 | F12: =IF(E$24=0,"",E12/E$24) | G12: =SUM(K12:Q12) -> 0 | H12: =IF($G$24=0,"",G12/$G$24) -> 0
A13: 3 | B13: Правительство | C13: ='Loans Receivable'!C86 -> 0 | D13: =IF(C$24=0,"",C13/C$24) -> 0 | F13: =IF(E$24=0,"",E13/E$24) | G13: =SUM(K13:Q13) -> 0 | H13: =IF($G$24=0,"",G13/$G$24) -> 0
A14: 4 | B14: Физические лица | C14: ='Loans Receivable'!C79 -> 468263196 | D14: =IF(C$24=0,"",C14/C$24) -> 0.36408911 | F14: =IF(E$24=0,"",E14/E$24) | G14: =SUM(K14:Q14) -> 2323519 | H14: =IF($G$24=0,"",G14/$G$24) -> 0.22564214 | I14: 2323519 | K14: 2323519
A15: 5 | B15: Государственные предприятия | C15: ='Loans Receivable'!C80 -> 141933618 | D15: =IF(C$24=0,"",C15/C$24) -> 0.11035777 | F15: =IF(E$24=0,"",E15/E$24) | G15: =SUM(K15:Q15) -> 13511 | H15: =IF($G$24=0,"",G15/$G$24) -> 0.0013120835 | I15: 13511 | K15: 13511
A16: 6 | B16: Совместные и иностранные предприятия | C16: ='Loans Receivable'!C81 -> 8044041 | D16: =IF(C$24=0,"",C16/C$24) -> 0.0062544905 | F16: =IF(E$24=0,"",E16/E$24) | G16: =SUM(K16:Q16) -> 3884 | H16: =IF($G$24=0,"",G16/$G$24) -> 0.00037718395 | I16: 3884 | K16: 3884
A17: 7 | B17: Частные товарищества и корпорации | C17: ='Loans Receivable'!C82 -> 667881660 | D17: =IF(C$24=0,"",C17/C$24) -> 0.51929863 | F17: =IF(E$24=0,"",E17/E$24) | G17: =SUM(K17:Q17) -> 7695228 | H17: =IF($G$24=0,"",G17/$G$24) -> 0.74730084 | I17: 7695228 | K17: 7695228
A18: 8 | B18: Фермерское хозяйство | C18: ='Loans Receivable'!C83 -> 0 | D18: =IF(C$24=0,"",C18/C$24) -> 0 | F18: =IF(E$24=0,"",E18/E$24) | G18: =SUM(K18:Q18) -> 0 | H18: =IF($G$24=0,"",G18/$G$24) -> 0
A19: 9 | B19: Небанковские финансовые институты | C19: ='Loans Receivable'!C87 -> 0 | D19: =IF(C$24=0,"",C19/C$24) -> 0 | F19: =IF(E$24=0,"",E19/E$24) | G19: =SUM(K19:Q19) -> 0 | H19: =IF($G$24=0,"",G19/$G$24) -> 0
A20: 10 | B20: Негосударственные некоммерческие организации | C20: ='Loans Receivable'!C88 -> 0 | D20: =IF(C$24=0,"",C20/C$24) -> 0 | F20: =IF(E$24=0,"",E20/E$24) | G20: =SUM(K20:Q20) -> 261221 | H20: =IF($G$24=0,"",G20/$G$24) -> 0.025367757 | I20: 261221 | K20: 261221
A21: 11 | B21: Бюджетные организации | C21: ='Loans Receivable'!C89 -> 0 | D21: =IF(C$24=0,"",C21/C$24) -> 0 | F21: =IF(E$24=0,"",E21/E$24) | G21: =SUM(K21:Q21) -> 0 | H21: =IF($G$24=0,"",G21/$G$24) -> 0
A22: 12 | B22: Прочие | C22: ='Loans Receivable'!C90 -> 0 | D22: =IF(C$24=0,"",C22/C$24) -> 0 | F22: =IF(E$24=0,"",E22/E$24) | G22: =SUM(K22:Q22) -> 0 | H22: =IF($G$24=0,"",G22/$G$24) -> 0
A24: 13 | B24: Итого кредита и лизинга | C24: =SUM(C11:C22) -> 1286122515 | D24: =IF(C$24=0,"",C24/C$24) -> 1 | E24: =SUM(E11:E22) -> 0 | F24: =IF(E$24=0,"",E24/E$24) | G24: =SUM(G11:G22) -> 10297363 | H24: =IF($G$24=0,"",G24/$G$24) -> 1 | I24: =SUM(I11:I22) -> 10297363 | J24: =SUM(J11:J22) -> 0 | K24: =SUM(K11:K22) -> 10297363 | L24: =SUM(L11:L22) -> 0 | M24: =SUM(M11:M22) -> 0 | N24: =SUM(N11:N22) -> 0 | O24: =SUM(O11:O22) -> 0 | P24: =SUM(P11:P22) -> 0 | Q24: =SUM(Q11:Q22) -> 0
F25: =IF(E$24=0,"",E25/E$24)
B26: По сектору экономики | F26: =IF(E$24=0,"",E26/E$24)
A27: 14 | B27: Промышленность | C27: ='Loans Receivable'!C15 -> 216425992 | D27: =IF(C$36=0,"",C27/C$36) -> 0.1682779 | F27: =IF(E$24=0,"",E27/E$24) | G27: =SUM(K27:Q27) -> 0 | H27: =IF($G$36=0,"",G27/$G$36) -> 0
A28: 15 | B28: Сельское хозяйство | C28: ='Loans Receivable'!C24 -> 300645088 | D28: =IF(C$36=0,"",C28/C$36) -> 0.23376085 | F28: =IF(E$24=0,"",E28/E$24) | G28: =SUM(K28:Q28) -> 0 | H28: =IF($G$36=0,"",G28/$G$36) -> 0
A29: 16 | B29: Транспорт и коммуникации | C29: ='Loans Receivable'!C32 -> 170536684 | D29: =IF(C$36=0,"",C29/C$36) -> 0.13259754 | F29: =IF(E$24=0,"",E29/E$24) | G29: =SUM(K29:Q29) -> 0 | H29: =IF($G$36=0,"",G29/$G$36) -> 0
A30: 17 | B30: Строительство | C30: ='Loans Receivable'!C40 -> 178688875 | D30: =IF(C$36=0,"",C30/C$36) -> 0.13893612 | F30: =IF(E$24=0,"",E30/E$24) | G30: =SUM(K30:Q30) -> 0 | H30: =IF($G$36=0,"",G30/$G$36) -> 0
A31: 18 | B31: Торговля и общественное питание | C31: ='Loans Receivable'!C48 -> 140213949 | D31: =IF(C$36=0,"",C31/C$36) -> 0.10902068 | F31: =IF(E$24=0,"",E31/E$24) | G31: =SUM(K31:Q31) -> 0 | H31: =IF($G$36=0,"",G31/$G$36) -> 0
A32: 19 | B32: Материально-техническое снабжение и сбыт | C32: ='Loans Receivable'!C56 -> 127634911 | D32: =IF(C$36=0,"",C32/C$36) -> 0.099240088 | F32: =IF(E$24=0,"",E32/E$24) | G32: =SUM(K32:Q32) -> 0 | H32: =IF($G$36=0,"",G32/$G$36) -> 0
A33: 20 | B33: Жилищно-коммунальные услуги | C33: ='Loans Receivable'!C64 -> 0 | D33: =IF(C$36=0,"",C33/C$36) -> 0 | F33: =IF(E$24=0,"",E33/E$24) | G33: =SUM(K33:Q33) -> 0 | H33: =IF($G$36=0,"",G33/$G$36) -> 0
A34: 21 | B34: Другие сектора | C34: ='Loans Receivable'!C77 -> 151977016 | D34: =IF(C$36=0,"",C34/C$36) -> 0.11816683 | F34: =IF(E$24=0,"",E34/E$24) | G34: =SUM(K34:Q34) -> 10297363 | H34: =IF($G$36=0,"",G34/$G$36) -> 1 | I34: 10297363 | K34: 10297363
F35: =IF(E$24=0,"",E35/E$24)
A36: 22 | B36: Итого кредита и лизинга | C36: =SUM(C27:C34) -> 1286122515 | D36: =IF(C$36=0,"",C36/C$36) -> 1 | E36: =SUM(E27:E34) -> 0 | F36: =IF(E$24=0,"",E36/E$24) | G36: =SUM(G27:G34) -> 10297363 | H36: =IF($G$36=0,"",G36/$G$36) -> 1 | I36: =SUM(I27:I34) -> 10297363 | J36: =SUM(J27:J34) -> 0 | K36: =SUM(K27:K34) -> 10297363 | L36: =SUM(L27:L34) -> 0 | M36: =SUM(M27:M34) -> 0 | N36: =SUM(N27:N34) -> 0 | O36: =SUM(O27:O34) -> 0 | P36: =SUM(P27:P34) -> 0 | Q36: =SUM(Q27:Q34) -> 0
B38: Подпись Председателя правления:
B40: Подпись Главного Бухгалтера:

Sheet Loan Classification
L1: Приложение №1 к Рекомендациям по заполнению отчетности коммерческих банков по банковскому надзору представляемых Центральному банку Республики Узбекистан
A2: Отчет о классификации активов по степени риска | M2: Таблица-10 (Форма-1596LKA)
B3: =Balance!A4 -> 43100 | L3: =Balance!B3 -> АКБ "Микрокредитбанк"
A4: № | B4: Статьи баланса | C4: Общая сумма | D4: Стандартные | E4: Общие резервы (1%) | F4: Субстандартные | G4: Специальные резервы (мин 10%) | H4: Неудовлетворительные | I4: Специальные резервы (мин 25%) | J4: Сомнительные | K4: Специальные резервы (мин 50%) | L4: Безнадежные | M4: Специальные резервы (100%) | N4: Совокупная сумма специальных резервов
A5: А | B5: Б | C5: В | D5: Г | E5: Д | F5: Е | G5: Ж | H5: З | I5: И | J5: К | K5: Л | L5: М | M5: Н | N5: О=Ж+И+Л+Н
A6: 1 | B6: Промышленность | C6: =D6+F6+H6+J6+L6 -> 216425992 | D6: 182709895 | F6: 33716097 | G6: 3371610 | N6: =+M6+K6+I6+G6 -> 3371610 | BX6: ='Aging Analysis'!C27 -> 216425992
A7: 2 | B7: Сельское хозяйство | C7: =D7+F7+H7+J7+L7 -> 300645088 | D7: 233212894 | F7: 67432194 | G7: 6743219 | N7: =+M7+K7+I7+G7 -> 6743219 | BX7: ='Aging Analysis'!C28 -> 300645088
A8: 3 | B8: Транспорт и коммуникации | C8: =D8+F8+H8+J8+L8 -> 170536684 | D8: 119962539 | F8: 50574145 | G8: 5057415 | N8: =+M8+K8+I8+G8 -> 5057415 | BX8: ='Aging Analysis'!C29 -> 170536684
A9: 4 | B9: Строительство | C9: =D9+F9+H9+J9+L9 -> 178688875 | D9: 134857949 | F9: 43830926 | G9: 4383093 | N9: =+M9+K9+I9+G9 -> 4383093 | BX9: ='Aging Analysis'!C30 -> 178688875
A10: 5 | B10: Торговля и сфера общественных услуг | C10: =D10+F10+H10+J10+L10 -> 140213949 | D10: 79524975 | F10: 60688974 | G10: 6068897 | N10: =+M10+K10+I10+G10 -> 6068897 | BX10: ='Aging Analysis'!C31 -> 140213949
A11: 6 | B11: Материально-техническое снабжение и сбыт | C11: =D11+F11+H11+J11+L11 -> 127634911 | D11: 90547204 | F11: 37087707 | G11: 3708771 | N11: =+M11+K11+I11+G11 -> 3708771 | BX11: ='Aging Analysis'!C32 -> 127634911
A12: 7 | B12: Жилищно-коммунальные услуги | C12: =D12+F12+H12+J12+L12 -> 0 | D12: 0 | F12: 0 | N12: =+M12+K12+I12+G12 -> 0 | BX12: ='Aging Analysis'!C33 -> 0
A13: 8 | B13: Другие сектора | C13: =D13+F13+H13+J13+L13 -> 151977016 | D13: 108146090 | F13: 43830926 | G13: 4383092 | N13: =+M13+K13+I13+G13 -> 4383092 | BX13: ='Aging Analysis'!C34 -> 151977016
A14: 9 | B14: Итого кредита и лизинга | C14: =SUM(C6:C13) -> 1286122515 | D14: =SUM(D6:D13) -> 948961546 | E14: =SUM(E6:E13) -> 0 | F14: =SUM(F6:F13) -> 337160969 | G14: =SUM(G6:G13) -> 33716097 | H14: =SUM(H6:H13) -> 0 | I14: =SUM(I6:I13) -> 0 | J14: =SUM(J6:J13) -> 0 | ... M14: =SUM(M6:M13) -> 0 | N14: =+M14+K14+I14+G14 -> 33716097 | BX14: ='Aging Analysis'!C36 -> 1286122515
A15: 10 | B15: Другие классифицированные активы | C15: =D15+F15+H15+J15+L15 -> 0 | N15: =+M15+K15+I15+G15 -> 0
A16: 11 | B16: Всего классифицированных активов | C16: =SUM(C14:C15) -> 1286122515 | D16: =SUM(D14:D15) -> 948961546 | E16: =SUM(E14:E15) -> 0 | F16: =SUM(F14:F15) -> 337160969 | G16: =SUM(G14:G15) -> 33716097 | H16: =SUM(H14:H15) -> 0 | I16: =SUM(I14:I15) -> 0 | J16: =SUM(J14:J15) -> 0 | ... M16: =SUM(M14:M15) -> 0 | N16: =+M16+K16+I16+G16 -> 33716097
B18: Подпись Председателя правления:
B20: Подпись Главного Бухгалтера:

Sheet Loans to Affiliated P.
I1: Приложение №1 к Рекомендациям по заполнению отчетности коммерческих банков по банковскому надзору представляемых Центральному банку Республики Узбекистан
A2: Отчет о кредитах и лизинге, выданным связанным лицам | J2: Таблица-11 (Форма-1624LCO)
A3: =Balance!A4 -> 43100 | I3: =Balance!B3 -> АКБ "Микрокредитбанк"
A5: № | B5: Наименования клиента | C5: Номер группы | D5: Дата выдачи | E5: Дата погашения | F5: Основная сумма кредита | G5: Текущая кредитная задолженность | H5: Пересмотрения | I5: Цель кредита | J5: Тип залога | K5: Классификация | L5: Источник кредита
B6: А | C6: Б | D6: В | E6: Г | F6: Д | G6: Е | H6: Ж | I6: З | J6: И | K6: К | L6: Л
A7: 1 | B7: Хасанов М. | C7: 1 | D7: 39961 | E7: 45448 | F7: 55500 | G7: 28003 | I7: 60011-Кредиты, выданные населению на приобретение квартиры в многоквартирных домах | J7: 22-Недвижимость (ипотека) | K7: 1-Хороший | L7: собственный
A8: =A7+1 -> 2 | B8: Раджаметов М. | C8: 1 | D8: 40157 | E8: 43809 | F8: 50000 | G8: 17361 | I8: 60011-Кредиты, выданные населению на приобретение квартиры в многоквартирных домах | J8: 22-Недвижимость (ипотека) | K8: 1-Хороший | L8: собственный
A9: =A8+1 -> 3 | B9: Пулатова М. | C9: 1 | D9: 41533 | E9: 45160 | F9: 100000 | G9: 84337 | I9: 60011-Кредиты, выданные населению на приобретение квартиры в многоквартирных домах | J9: 22-Недвижимость (ипотека) | K9: 1-Хороший | L9: собственный
A10: =A9+1 -> 4 | B10: Якубова Н. | C10: 1 | D10: 40017 | E10: 45498 | F10: 37500 | G10: 20833 | I10: 60011-Кредиты, выданные населению на приобретение квартиры в многоквартирных домах | J10: 22-Недвижимость (ипотека) | K10: 1-Хороший | L10: собственный
A11: =A10+1 -> 5 | B11: Саксонов А. | C11: 1 | D11: 40540 | E11: 46019 | F11: 52500 | G11: 14900 | I11: 60011-Кредиты, выданные населению на приобретение квартиры в многоквартирных домах | J11: 22-Недвижимость (ипотека) | K11: 1-Хороший | L11: собственный
A12: =A11+1 -> 6 | B12: ISMATULLOYEV AKRAM AKMALOVICH | C12: 1 | D12: 42611 | E12: 48088 | F12: 260000 | G12: 260000 | I12: 60011-Кредиты, выданные населению на приобретение квартиры в многоквартирных домах | J12: 22-Недвижимость (ипотека) | K12: 1-Хороший | L12: собственный
A13: =A12+1 -> 7
A14: =A13+1 -> 8
A15: =A14+1 -> 9
A16: =A15+1 -> 10
A17: =A16+1 -> 11
A18: =A17+1 -> 12
A19: =A18+1 -> 13
A20: =A19+1 -> 14
A21: =A20+1 -> 15
A22: =A21+1 -> 16
A23: =A22+1 -> 17
A24: =A23+1 -> 18
... A36: =A35+1 -> 30
A37: =A36+1 -> 31 | B37: ИТОГО СУММА КРЕДИТОВ/ ЛИЗИНГА СВЯЗАННЫМ ЛИЦАМ | F37: =SUM(G7:G36) -> 425434
A38: =A37+1 -> 32 | B38: САМЫЙ КРУПНЫЙ КРЕДИТ/ ЛИЗИНГ ОДНОМУ ИНСАЙДЕРУ | F38: =MAX(G7:G36) -> 260000
B40: Подпись Председателя правления:
B42: Подпись Главного Бухгалтера:

Sheet Twenty Largest
I1: Приложение №1 к Рекомендациям по заполнению отчетности коммерческих банков по банковскому надзору представляемых Центральному банку Республики Узбекистан
A2: Кредиты и лизинги к получению - двадцать крупнейших заёмщиков | J2: Таблица-12 (Форма-1574LBB)
A3: =Balance!A4 -> 43100 | I3: =Balance!B3 -> АКБ "Микрокредитбанк"
A5: № | B5: Наименования клиента | C5: Номер группы | D5: Дата выдачи | E5: Дата погашения | F5: Основная сумма кредиты | G5: Текущая кредитная задолженность | H5: Пересмотрения | I5: Цель кредита | J5: Тип залога | K5: Классификация | L5: Источник кредита
B6: А | C6: Б | D6: В | E6: Г | F6: Д | G6: Е | H6: Ж | I6: З | J6: И | K6: К | L6: Л
A7: 1 | P7: 0
A8: 2
A9: 3
A10: 4
A11: 5
A12: 6
A13: 7
A14: 8
A15: 9
A16: 10
A17: 11
A18: 12
A19: 13
... A36: 30
A37: 31 | B37: ИТОГО КРУПНЫХ КРЕДИТОВ/ ЛИЗИНГА | F37: =SUM(G7:G36) -> 0
A38: 32 | B38: САМЫЙ КРУПНЫЙ КРЕДИТ/ ЛИЗИНГ, ВЫДАННЫЙ БАНКОМ | F38: =MAX(G7:G36) -> 0
B40: Подпись Председателя правления:
B42: Подпись Главного Бухгалтера:
M45: Классификация
M46: К

Sheet Charge-offs and Recoveries
D1: Приложение №1 к Рекомендациям по заполнению отчетности коммерческих банков по банковскому надзору представляемых Центральному банку Республики Узбекистан
A2: ОТЧЕТ О CПИСАННЫХ И ВОЗВРАЩЕННЫХ ПЛАТЕЖАХ ИЗ РЕЗЕРВА ВОЗМОЖНЫХ ПОТЕРЬ ПО КРЕДИТАМ И ЛИЗИНГУ | E2: Таблица-13 (Форма-1598LKA)
B3: =Balance!A4 -> 43100 | D3: =Balance!B3 -> АКБ "Микрокредитбанк"
A4: Часть 1 Списания и возврат
B5: Списание - А | D5: Возврат - Б
B6: Всего | C6: в иностранной валюте | D6: Всего | E6: в иностранной валюте
A7: А | B7: Б | C7: В | D7: Г | E7: Д
A8: 1. Промышленность | B8: 3916716 | D8: 695049
A9: 2. Сельское хозяйство | B9: 77336760 | D9: 5530423
A10: 3. Транспорт и коммуникации | B10: 6390713 | D10: 720777
A11: 4. Строительство | B11: 5882656 | D11: 1555242
A12: 5. Торговля и общественное питание | B12: 7868824 | D12: 1284975
A13: 6. Материально-техническое снабжение и сбыт | B13: 897061 | D13: 0
A14: 7. Жилищно-коммунальные услуги | B14: 0 | D14: 0
A15: 8. Другие сектора | B15: 11566269 | D15: 644772
A16: 9. Итого | B16: =SUM(B8:B15) -> 113858999 | C16: =SUM(C8:C15) -> 0 | D16: =SUM(D8:D15) -> 10431238 | E16: =SUM(E8:E15) -> 0
A19: Часть 2
A20: Изменения в резерве возможных убытков по кредитам и лизингу
A21: 1. Остаток на начало текущего года | C21: 1173488
A22: 2. Плюс: Возвращенные платежи | C22: =D16 -> 10431238
A23: 3. Минус: Списанные кредиты и лизинги | C23: =B16 -> 113858999
A24: 4. Отчисления в резерв по состоянию на дату от начала года | C24: 86761235
A25: 5. Поправки | C25: 49209135
A26: 6. Текущий баланс | C26: =SUM(C21:C22)-C23+SUM(C24:C25) -> 33716097 | D26: =Balance!B22 -> 33716097 | E26: ='Loan Classification'!N14 -> 33716097
A28: Подпись Председателя правления:
A30: Подпись Главного Бухгалтера:

Sheet Deposits by Client
B1: Приложение №1 к Рекомендациям по заполнению отчетности коммерческих банков по банковскому надзору представляемых Центральному банку Республики Узбекистан
A2: ОТЧЕТ О ДЕПОЗИТАХ ПО ТИПАМ КЛИЕНТОВ Таблица-14 (Форма-2106DMC)
A3: =Balance!A4 -> 43100 | B3: =Balance!B3 -> АКБ "Микрокредитбанк" | C3: в тыс. сум
A4: Категории | B4: Всего | C4: в том числе в иностранной валюте
A5: 1. Депозиты до востребования
A6: а. Правительство | B6: 4533100 | C6: 0
A7: б. Физические лица | B7: 89954541 | C7: 11187202
A8: в. Государственные предприятия | B8: 108650817 | C8: 222607
A9: г. Совместные и иностранные предприятия | B9: 5121972 | C9: 4340017
A10: д. Частные товарищества и корпорации | B10: 81567352 | C10: 1858764
A11: е. Другие депозиты до востребования | B11: 68048088 | C11: 18443567
A12: ж. Итого депозитов до востребования | B12: =SUM(B6:B11) -> 357875870 | C12: =SUM(C6:C11) -> 36052157
A14: 2. Сберегательные депозиты
A15: а. Правительство | B15: 0 | C15: 0
A16: б. Физические лица | B16: 17605402 | C16: 374396
A17: в. Государственные предприятия | B17: 0 | C17: 0
A18: г. Совместные и иностранные предприятия | B18: 0 | C18: 0
A19: д. Частные товарищества и корпорации | B19: 3711173 | C19: 0
A20: е. Другие сберегательные депозиты | B20: 50799 | C20: 0
A21: ж. Итого сберегательных депозитов | B21: =SUM(B15:B20) -> 21367374 | C21: =SUM(C15:C20) -> 374396
A23: 3. Срочные депозиты
A24: а. Правительство | B24: 319400000 | C24: 0
A25: б. Физические лица | B25: 112319624 | C25: 0
A26: в. Государственные предприятия | B26: 94295850 | C26: 81255850
A27: г. Совместные и иностранные предприятия | B27: 34975000 | C27: 0
A28: д. Частные товарищества и корпорации | B28: 8275372 | C28: 0
A29: е. Другие срочные депозиты | B29: 73495394 | C29: 0
A30: ж. Итого срочных депозитов | B30: =SUM(B24:B29) -> 642761240 | C30: =SUM(C24:C29) -> 81255850
A32: 4. Итого депозитов | B32: =B12+B21+B30 -> 1022004484 | C32: =C12+C21+C30 -> 117682403
A34: Примечание:
A35: Были ли случаи, что банк не смог выплатить вкладчику основную сумму вклада или же процент в течение квартала?
A37: Подпись Председателя правления:
A39: Подпись Главного Бухгалтера:

Sheet Investment Securities
B1: Приложение №1 к Рекомендациям по заполнению отчетности коммерческих банков по банковскому надзору представляемых Центральному банку Республики Узбекистан
A2: ОТЧЕТ ОБ ИНВЕСТИЦИЯХ В ЦЕННЫЕ БУМАГИ И СЧЕТА КУПЛИ-ПРОДАЖИ АКТИВОВ | C2: Таблица-15 (Форма-1726SEC )
A3: =+Balance!A4 -> 43100 | C3: =Balance!B3 -> АКБ "Микрокредитбанк"
A4: Часть 1 - Инвестиции в ценные бумаги | B4: Балансовая стоимость | C4: Рыночная стоимость
A6: 1. Инвестиции в государственные облигации | B6: 0
A7: 2. Инвестиции в ценные бумаги и облигации ЦБРУ | B7: 0
A8: 3. Инвестиции в частные облигации | B8: 0
A9: 4. Инвестиции в еврооблигации | B9: 0
A10: 5. Инвестиции в акции гос предприятий | B10: 0
A11: 6. Инвестиции в акции частных предприятий | B11: 0
A12: 7. Инвестиции в другие ценные бумаги | B12: 2750000
A13: 8. Итого инвестиций | B13: =SUM(B6:B12) -> 2750000 | C13: =SUM(C6:C12) -> 0
A14: 9. Минус: Резерв возможных убытков | B14: 1
A15: 10. Чистая балансовая стоимость инвестиций | B15: =B13-B14 -> 2749999
A17: Часть 2 - Счета купли-продажи ценных бумаг | B17: Балансовая стоимость | C17: Рыночная стоимость
A19: 1. Государственные казначейские векселя | B19: 0
A20: 2. Государственные облигации | B20: 0
A21: 3. Ценные бумаги и облигации ЦБРУ | B21: 0
A22: 4. Ценные бумаги гос корпораций | B22: 0
A23: 5. Еврооблигации | B23: 0
A24: 6. Частные ценные бумаги | B24: 349524
A25: 7. Другие ценные бумаги | B25: 0
A26: 8. Итого по счетам купли-продажи ценных бумаг | B26: =SUM(B19:B25) -> 349524 | C26: =SUM(C19:C25) -> 0
A27: 9. Минус: Резерв возможных убытков
A28: 10. Чистая балансовая стоимость по счетам купли-продажи ц/б | B28: =B26-B27 -> 349524
A32: Часть 3 - Счета купли и продажи драгоценных металлов | B32: Первоначальная стоимость | C32: Рыночная стоимость
A34: 1. Драгоценные металлы | B34: 0
A35: 2. Драгоценные камни | B35: 0
A36: 3. Драгоценные монеты | B36: 175
A37: 5. Итого драгоценных металлов | B37: =SUM(B34:B36) -> 175 | C37: =SUM(C34:C36) -> 0
A38: 6. Минус: Резерв возможных убытков | B38: 0
A39: 7. Чистая балансовая стоимость по счетам купли и продажи д/м | B39: =B37-B38 -> 175
A41: Примечание:
A42: Итого ценных бумаг заложенных для общественных депозитов
A43: Портфель инвестиций в ценные бумаги
A44: Увеличение (Снижение) стоимости | B44: =C13-B13 -> -2750000
A45: Счета купли-продажи ценных бумаг
A46: Увеличение (Снижение) стоимости | B46: =C26-B26 -> -349524
A47: Счета купли-продажи драгоценных предметов
A48: Увеличение (Снижение) стоимости | B48: =C37-B37 -> -175
A50: Подпись Председателя правления:
A52: Подпись Главного Бухгалтера:
A53: Formulas are for Original Cost only.

Sheet Liquidity Analysis
B1: Приложение №1 к Рекомендациям по заполнению отчетности коммерческих банков по банковскому надзору представляемых Центральному банку Республики Узбекистан
A2: АНАЛИЗ ЛИКВИДНОСТИ | B2: Таблица-16 (Форма-0022AAL)
A3: =Balance!A4 -> 43100 | B3: =Balance!B3 -> АКБ "Микрокредитбанк"
A4: Часть 1. Ликвидные активы | B4: в тыс. сум
A6: 1. Касса (наличность и монеты) и Драгоценные металлы | B6: 76954356
A7: 2. К получению из ЦБРУ | B7: 213192148
A8: 3. К получению из других банков | B8: 78170286
A9: 4. Ценные бумаги, выпущенные Правительством Республики Узбекистан и ЦБРУ (векселя, облигации и другие долговые ценные бумаги) | B9: 0
A10: 5. Ценные бумаги, выпущенные странами с низким уровня риска | B10: 0
A11: 6. Другие легко реализуемые ценные бумаги | B11: 0
A12: 7. Итого ликвидных активов | B12: =SUM(B6:B11) -> 368316790
A13: 8. Плюс: Кредиты и лизинги со сроком погашения 30 дней или менее | B13: 63112110
A14: 9. Минус: Просроченные, неблагоприятно классифицированные, неначисляемые, пролонгированные, или реструктуризированные кредиты и лизинги, включенные в строку 8. | B14: 10196060
A15: 10. Текущие Активы | B15: =SUM(B12:B13)-B14 -> 421232840
A17: Часть 2. Коэфициенты наличности и ликвидности | B17: в процентах
A19: 1. Коэффициент наличности
A20: а. Итого кассы разделить на
A21: среднее активов за текущий квартал | B21: =IF(B36=0,0,(B6/B36)) -> 0
A22: 2. Коэффициент ликвидности
A23: а. Итого ликвидных активов разделить на
A24: среднее активов за текущий квартал | B24: =IF(B36=0,0,(B7/B36)) -> 0
A25: 3. Непостоянные обязательства/ среднее активов за текущий квартал | B25: 0
A26: 4. Ликвидные активы/ Непостоянные обязательства | B26: 0
A27: 5. Кредиты (чистые)/ Депозиты | B27: =IF('Deposits by Client'!B32=0,"",Balance!C23/'Deposits by Client'!B32) -> 1.2254412
A28: 6 Заложенные ценные бумаги/ Общая сумма ценных бумаг
A30: Часть 3. Экономические нормативы - Ликвидность
A32: 1. Расчет коэффициента текущей ликвидности (Н4) | B32: =B15/('Bank Liabilities Analysis'!C33+'Bank Liabilities Analysis'!D33) -> 0.93350739
A35: Примечание:
A36: Укажите среднедневную сумму активов за текущий период, рассчитанную компьютерной системой действующей в банке.
A37: Часть 4.
A38: 1. Коэффициент покрытия ликвидности | B38: ='Bank Assets Analysis'!K41/'Bank Assets Analysis'!K42 -> 2.3779889
A39: а) Высоколиквидные активы | B39: =+'Bank Assets Analysis'!K41 -> 368659820
A40: б) Чистый отток в последующие 30 дней | B40: =+'Bank Assets Analysis'!K42 -> 1.5503009e+08
A41: 2. Норма чистого стабильного финансирования | B41: =+B42/B47 -> 1.0145831
A42: 3. Доступная сумма стабильного финансирования | B42: =SUM(B43:B46) -> 1.1029413e+09
A43: а) Регулятивный капитал | B43: =+'Bank Capital Calc.'!E44 -> 5.4048778e+08
A44: б) Обязательства свыше 1 года | B44: =+'Bank Liabilities Analysis'!G33 -> 290411542
A45: в) 30% других бессрочных обязательств | B45: =+('Bank Liabilities Analysis'!C33)*0.3 -> 1.1463425e+08
A46: г) 30% других обязательств менее 1 года | B46: =+('Bank Liabilities Analysis'!D33+'Bank Liabilities Analysis'!E33+'Bank Liabilities Analysis'!F33)*0.3 -> 1.5740774e+08
A47: 4. Необходимая сумма стабильного финансирования | B47: =SUM(B48:B53) -> 1087088150
A48: а) Активы свыше 1 года | B48: =+'Bank Assets Analysis'!G39-'Bank Assets Analysis'!G32 -> 824127683
A49: б) Банковские помещения, мебель и оборудование, чистые | B49: =+'Bank Assets Analysis'!H32 -> 100870267
A50: в) Кредиты и лизинги и авансы в процессе судебного разбирательства, чистые или не взысканные в установленном порядке | B50: =+'Bank Assets Analysis'!C27+'Bank Assets Analysis'!C26 -> 10196060
A51: г) Активы в процессе судебного разбирательства или не взысканные в установленном порядке(не указанные в строке "в)") | B51: 0
A52: д) 30% других активов менее 1 го года (за исключением бессрочных и со сроком менее 1 го года ликвидных активов) | B52: =+('Bank Assets Analysis'!D39+'Bank Assets Analysis'!E39+'Bank Assets Analysis'!F39-'Liquidity Analysis'!C12)*0.3 -> 151894140
A53: е) 15% из забалансовых обязательств
A55: Подпись Председателя правления:
A57: Подпись Главного Бухгалтера:

Sheet Bank Assets Analysis
I1: Приложение №1 к Рекомендациям по заполнению отчетности коммерческих банков по банковскому надзору представляемых Центральному банку Республики Узбекистан
A2: АНАЛИЗ АКТИВОВ БАНКА | I2: Таблица-17 (Форма-0024AAL)
A3: =Balance!A4 -> 43100 | I3: =Balance!B3 -> АКБ "Микрокредитбанк"
A5: № | B5: Характеристики | C5: Дата погашения (в днях) | H5: ВСЕГО | I5: Коэффициент | J5: Сумма активов | K5: Высоко-ликвидные активы
C6: Бессрочные | D6: от 1 до 30 | E6: от 31 до180 | F6: от 181до 365 | G6: Свыше 365
B7: (А) | C7: (Б) | D7: (В) | E7: (Г) | F7: (Д) | G7: (Е) | H7: (Ж) | I7: (З) | J7: (И) | K7: (К=З*И)
B8: АКТИВЫ
A9: 1. | B9: Наличность и другие кассовые документы | C9: 76954182 | H9: =SUM(C9:G9) -> 76954182 | I9: 1 | J9: =+C9 -> 76954182 | K9: =+J9*I9 -> 76954182
A10: 2. | B10: К получению из ЦБРУ не учитывая сумму "Резервов на покрытие возможных убытков" (без ДОР) | C10: 129692339 | D10: 83499809 | H10: =SUM(C10:G10) -> 213192148 | I10: 1 | J10: =+C10+D10 -> 213192148 | K10: =+J10*I10 -> 213192148
A11: 2.1 | B11: К получению из ЦБРУ (сумма созданных резервов на покрытие возможных убытков по активам банка (ДОР)) | H11: =SUM(C11:G11) -> 0 | I11: 0 | J11: =+C11 -> 0 | K11: =+J11*I11 -> 0
A12: 3. | B12: К получению из других банков | C12: =+C13+C14+C15 -> 78174640 | D12: =+D13+D14+D15 -> 368204 | E12: =+E13+E14+E15 -> 0 | F12: =+F13+F14+F15 -> 0 | G12: =+G13+G14+G15 -> 0 | H12: =SUM(C12:G12) -> 78542844 | K12: =+J12*I12 -> 0
A13: 3.1 | B13: К получению со счетов в банках стран с низким уровнем риска (ностро, депозиты), но размещенные не в качестве обеспечения | C13: 78145286 | D13: 368204 | H13: =SUM(C13:G13) -> 78513490 | I13: 1 | J13: =+H13 -> 78513490 | K13: =+J13*I13 -> 78513490
A14: 3.2 | B14: К получению из других банков по расчетам пластиковых карт | C14: 4354 | H14: =SUM(C14:G14) -> 4354 | I14: 0.5 | J14: =+H14 -> 4354 | K14: =+J14*I14 -> 2177
A15: 3.3 | B15: Другие статьи | C15: 25000 | H15: =SUM(C15:G15) -> 25000 | I15: 0 | J15: =+H15 -> 25000 | K15: =+J15*I15 -> 0
A16: 4. | B16: Счета купли и продажи, чистые | C16: =+C17+C18+C19+C20 -> 349699 | D16: =+D17+D18+D19+D20 -> 0 | E16: =+E17+E18+E19+E20 -> 0 | F16: =+F17+F18+F19+F20 -> 0 | G16: =+G17+G18+G19+G20 -> 0 | H16: =SUM(C16:G16) -> 349699 | K16: =+J16*I16 -> 0
A17: 4.1 | B17: Ценные бумаги, выпущенные Правительством Республики Узбекистан и ЦБРУ (векселя, облигации и другие долговые ценные бумаги) | H17: =SUM(C17:G17) -> 0 | I17: 1 | J17: =+C17+D17 -> 0 | K17: =+J17*I17 -> 0
A18: 4.2 | B18: Правительственные ценные бумаги стран с низкой степенью странового риска | H18: =SUM(C18:G18) -> 0 | I18: 1 | J18: =+C18+D18 -> 0 | K18: =+J18*I18 -> 0
A19: 4.3 | B19: Ценные бумаги ведущих транснациональных компаний с низким уровнем странового риска | H19: =SUM(C19:G19) -> 0 | I19: 1 | J19: =+C19+D19 -> 0 | K19: =+J19*I19 -> 0
A20: 4.4 | B20: Другие | C20: 349699 | H20: =SUM(C20:G20) -> 349699 | I20: 0 | J20: =+C20+D20 -> 349699 | K20: =+J20*I20 -> 0
A21: 5. | B21: Купленные векселя, чистые | H21: =SUM(C21:G21) -> 0 | I21: 0.3 | J21: =+C21+D21 -> 0 | K21: =+J21*I21 -> 0
A22: 6. | B22: Обязательства клиентов по траттам под аккредитивы или трастовые документы | H22: =SUM(C22:G22) -> 0 | I22: 0.3 | J22: =+C22+D22 -> 0 | K22: =+J22*I22 -> 0
A23: 7. | B23: Обязательства клиентов по непогашенным акцептам этого банка | H23: =SUM(C23:G23) -> 0 | I23: 0.3 | J23: =+C23+D23 -> 0 | K23: =+J23*I23 -> 0
A24: 8. | B24: Кредиты и лизинги, предоставленные ЦБРУ, чистые | H24: =SUM(C24:G24) -> 0 | I24: 1 | J24: =+C24+D24 -> 0 | K24: =+J24*I24 -> 0
A25: 9. | B25: Кредиты и лизинги, предоставленные другим банкам, чистые | H25: =SUM(C25:G25) -> 0 | I25: 0.5 | J25: =+D25 -> 0 | K25: =+J25*I25 -> 0
A26: 10 | B26: Кредиты и лизинги, предоставленные другим клиентам, чистые | C26: 10299194 | D26: 52916050 | E26: 90771118 | F26: 277145504 | G26: 821377684 | H26: =SUM(C26:G26) -> 1252509550 | I26: 0.3 | J26: =+D26 -> 52916050 | K26: =+J26*I26 -> 15874815
A27: 11 | B27: Кредиты и лизинги и авансы в процессе судебного разбирательства, чистые | C27: -103134 | H27: =SUM(C27:G27) -> -103134 | I27: 0 | J27: =+C27+D27 -> -103134 | K27: =+J27*I27 -> 0
A28: 12. | B28: Инвестиции, чистые | G28: 2749999 | H28: =SUM(C28:G28) -> 2749999 | I28: 0 | J28: =+C28+D28 -> 0 | K28: =+J28*I28 -> 0
A29: 13. | B29: Ценные бумаги купленные по соглашению с обратным выкупом | C29: =+C30+C31 -> 0 | D29: =+D30+D31 -> 0 | E29: =+E30+E31 -> 0 | F29: =+F30+F31 -> 0 | G29: =+G30+G31 -> 0 | H29: =SUM(C29:G29) -> 0 | K29: =+J29*I29 -> 0
A30: 13.1 | B30: Правительственные ценные бумаги купленные по соглашению с обратным выкупом (РЕПО) | H30: =SUM(C30:G30) -> 0 | I30: 0.3 | J30: =+C30+D30 -> 0 | K30: =+J30*I30 -> 0
A31: 13,2 | B31: Другие ценные бумаги купленные по соглашению с обратным выкупом (РЕПО) | H31: =SUM(C31:G31) -> 0 | I31: 0 | J31: =+C31+D31 -> 0 | K31: =+J31*I31 -> 0
A32: 14. | B32: Банковские помещения, мебель и оборудование, чистые | G32: 100870267 | H32: =SUM(C32:G32) -> 100870267 | I32: 0 | J32: =+C32+D32 -> 0 | K32: =+J32*I32 -> 0
A33: 15. | B33: Недвижимость и другое собственное имущество, чистые | D33: 1613115 | H33: =SUM(C33:G33) -> 1613115 | I33: 0 | J33: =+C33+D33 -> 1613115 | K33: =+J33*I33 -> 0
A34: 16. | B34: Нереализованная прибыль при ревальвации по сделкам "форвард" | H34: =SUM(C34:G34) -> 0 | I34: 0 | J34: =+C34+D34 -> 0 | K34: =+J34*I34 -> 0
A35: 17. | B35: Счета купли-продажи валюты и валютные позиции | H35: =SUM(C35:G35) -> 0 | I35: 0 | J35: =+C35+D35 -> 0 | K35: =+J35*I35 -> 0
A36: 18. | B36: Клиринговые счета | H36: =SUM(C36:G36) -> 0 | I36: 0 | J36: =+C36+D36 -> 0 | K36: =+J36*I36 -> 0
A37: 19. | B37: Начисленные проценты | C37: 7348132 | H37: =SUM(C37:G37) -> 7348132 | I37: 0.3 | J37: =+D37 -> 0 | K37: =+J37*I37 -> 0
A38: 20. | B38: Другие активы | C38: 8966247 | H38: =SUM(C38:G38) -> 8966247 | I38: 0 | J38: =+C38+D38 -> 8966247 | K38: =+J38*I38 -> 0
A39: 21. | B39: ИТОГО АКТИВОВ | C39: =SUM(C9:C38)-C12-C16-C29 -> 311681299 | D39: =SUM(D9:D38)-D12-D16-D29 -> 138397178 | E39: =SUM(E9:E38)-E12-E16-E29 -> 90771118 | F39: =SUM(F9:F38)-F12-F16-F29 -> 277145504 | G39: =SUM(G9:G38)-G12-G16-G29 -> 924997950 | H39: =SUM(H9:H38)-H12-H16-H29 -> 1742993049 | K39: =SUM(K9:K38)-K12-K29 -> 384536812
C40: =+C39-C27-C9-C10-C12-C16-C25 -> 26613573 | D40: =+D39-D27-D9-D10-D12-D16-D25 -> 54529165 | E40: =+E39-E27-E9-E10-E12-E16-E25 -> 90771118 | F40: =+F39-F27-F9-F10-F12-F16-F25 -> 277145504 | I40: Ликвидные активы | K40: =+K39-K41 -> 15876992
B41: * Примечание: Показать раздельно суммы | C41: =+C40+D40+E40+F40 -> 449059360 | D41: =+C41*0.3 -> 134717808 | I41: Активы с риском 0% | K41: =+K9+K10+K13+K17+K18 -> 368659820
I42: Чистый расход за 30 дней | K42: =+'Bank Liabilities Analysis'!K33-'Bank Assets Analysis'!K40 -> 1.5503009e+08
B44: Корреспондентского счета в ЦБРУ | C44: 129692339 | H44: =+C44 -> 129692339
B45: Счета Обязательного Резерва в ЦБРУ | C45: 83499809 | H45: =+C45 -> 83499809
B48: Подпись Председателя правления:
B50: Подпись Главного Бухгалтера:

Sheet Bank Liabilities Analysis
I1: Приложение №1 к Рекомендациям по заполнению отчетности коммерческих банков по банковскому надзору представляемых Центральному банку Республики Узбекистан
A2: АНАЛИЗ ОБЯЗАТЕЛЬСТВ БАНКА | I2: Таблица-18 (Форма-0026AAL)
A3: =Balance!A4:A4 -> 43100 | I3: =Balance!B3 -> АКБ "Микрокредитбанк"
A5: № | B5: Характеристики | D5: Срок погашения (в днях) | H5: ВСЕГО | I5: Коэффициент | J5: Сумма расхода за 30 дней | K5: Сумма чистого расхода за 30 дней
C6: Бессрочные | D6: от 1 до 30 | E6: от 31 до180 | F6: от 181до 365 | G6: Свыше 1 года
B7: (А) | C7: (Б) | D7: (В) | E7: (Г) | F7: (Д) | G7: (Е) | H7: (Ж) | I7: (З) | J7: (И) | K7: (К=З*И)
B8: ОБЯЗАТЕЛЬСТВА
A9: 1. | B9: ДЕПОЗИТЫ
A10: 1.1 | B10: Депозиты до востребования | C10: =SUM(C11:C15) -> 235562823 | D10: =SUM(D11:D15) -> 0 | E10: =SUM(E11:E15) -> 0 | F10: =SUM(F11:F15) -> 0 | G10: =SUM(G11:G15) -> 582695 | H10: =SUM(C10:G10) -> 236145518
A11: а) | B11: Вклады населения до востребования (гарантированные) | C11: 14481346 | H11: =SUM(C11:G11) -> 14481346 | I11: 0.1 | J11: =+C11+D11 -> 14481346 | K11: =+J11*I11 -> 1448134.6
A12: б) | B12: Вклады населения до востребования (не гарантированные) | H12: =SUM(C12:G12) -> 0 | I12: 0.15 | J12: =+C12+D12 -> 0 | K12: =+J12*I12 -> 0
A13: в) | B13: Вклады населения до востребования (под залогом по выданным кредитам) | G13: 582695 | H13: =SUM(C13:G13) -> 582695 | I13: 0 | J13: =+C13+D13 -> 0 | K13: =+J13*I13 -> 0
A14: г) | B14: Другие депозиты до востребования (под залогом по выданным кредитам) | H14: =SUM(C14:G14) -> 0 | I14: 0 | J14: =+C14+D14 -> 0 | K14: =+J14*I14 -> 0
A15: д) | B15: Другие депозиты до востребования | C15: 221081477 | H15: =SUM(C15:G15) -> 221081477 | I15: 0.3 | J15: =+C15+D15 -> 221081477 | K15: =+J15*I15 -> 66324443
A16: 1.2 | B16: Сберегательные депозиты | C16: 3987905 | D16: 1350620 | E16: 6458717 | F16: 6213678 | G16: 3356454 | H16: =SUM(C16:G16) -> 21367374 | I16: 1 | J16: =+C16+D16 -> 5338525 | K16: =+J16*I16 -> 5338525
A17: 1.3 | B17: Срочные депозиты | C17: 1126255 | D17: 65404045 | E17: 238905216 | F17: 174092279 | G17: 163233446 | H17: =SUM(C17:G17) -> 642761241 | I17: 1 | J17: =+C17+D17 -> 66530300 | K17: =+J17*I17 -> 66530300
A18: 1.4 | B18: Итого депозитов | C18: =SUM(C11:C17) -> 240676983 | D18: =SUM(D11:D17) -> 66754665 | E18: =SUM(E11:E17) -> 245363933 | F18: =SUM(F11:F17) -> 180305957 | G18: =SUM(G11:G17) -> 167172595 | H18: =SUM(C18:G18) -> 900274133 | K18: =+J18*I18 -> 0
A19: 2. | B19: К оплате в ЦБРУ | H19: =SUM(C19:G19) -> 0 | I19: 1 | J19: =+C19+D19 -> 0 | K19: =+J19*I19 -> 0
A20: 3. | B20: К оплате в другие банки | C20: 80000 | E20: 9900000 | F20: 0 | G20: 2170000 | H20: =SUM(C20:G20) -> 12150000 | I20: 1 | J20: =+C20+D20 -> 80000 | K20: =+J20*I20 -> 80000
A21: 4. | B21: Управленческие чеки | H21: =SUM(C21:G21) -> 0 | I21: 1 | J21: =+C21+D21 -> 0 | K21: =+J21*I21 -> 0
A22: 5. | B22: Непогашенные акцепты, выполненные банком или по поручению этого банка | H22: =SUM(C22:G22) -> 0 | I22: 1 | J22: =+C22+D22 -> 0 | K22: =+J22*I22 -> 0
A23: 6. | B23: Кредиты и лизинговые операции к оплате | F23: 20000000 | G23: 121068947 | H23: =SUM(C23:G23) -> 141068947 | I23: 1 | J23: =+C23+D23 -> 0 | K23: =+J23*I23 -> 0
A24: 7. | B24: Ценные бумаги проданные по соглашению с последующим выкупом | H24: =SUM(C24:G24) -> 0 | I24: 1 | J24: =+C24+D24 -> 0 | K24: =+J24*I24 -> 0
A25: 8. | B25: Другие депозиты клиентов | C25: 121730352 | H25: =SUM(C25:G25) -> 121730352 | J25: =+C25+D25 -> 121730352 | K25: =+J25*I25 -> 0
A26: 8.1 | B26: Средства на банковских пластиковых карточках | C26: 85414829 | H26: =SUM(C26:G26) -> 85414829 | I26: 0.1 | J26: =+C26+D26 -> 85414829 | K26: =+J26*I26 -> 8541482.9
A27: 8.2 | B27: Другие | C27: =+C25-C26 -> 36315523 | D27: =+D25-D26 -> 0 | E27: =+E25-E26 -> 0 | F27: =+F25-F26 -> 0 | G27: =+G25-G26 -> 0 | H27: =SUM(C27:G27) -> 36315523 | I27: 0.3 | J27: =+C27+D27 -> 36315523 | K27: =+J27*I27 -> 10894657
A28: 9. | B28: Нереализованная прибыль или убытки по форвардным сделкам и другим отсроченным кредитам | C28: 17518 | H28: =SUM(C28:G28) -> 17518 | I28: 1 | J28: =+C28+D28 -> 17518 | K28: =+J28*I28 -> 17518
A29: 10. | B29: Клиринговые счета - кредитовый остаток | C29: 4973286 | H29: =SUM(C29:G29) -> 4973286 | I29: 1 | J29: =+C29+D29 -> 4973286 | K29: =+J29*I29 -> 4973286
A30: 11. | B30: Начисленные проценты | D30: 2367927 | H30: =SUM(C30:G30) -> 2367927 | I30: 1 | J30: =+C30+D30 -> 2367927 | K30: =+J30*I30 -> 2367927
A31: 12. | B31: Условные обязательства | H31: =SUM(C31:G31) -> 0 | I31: 0.1 | J31: =+C31+D31 -> 0 | K31: =+J31*I31 -> 0
A32: 13. | B32: Другие обязательства | C32: 14636020 | H32: =SUM(C32:G32) -> 14636020 | I32: 0.3 | J32: =+C32+D32 -> 14636020 | K32: =+J32*I32 -> 4390806
A33: 14. | B33: ИТОГО ОБЯЗАТЕЛЬСТВ | C33: =SUM(C18:C32)-C25 -> 382114159 | D33: =SUM(D18:D32)-D25 -> 69122592 | E33: =SUM(E18:E32)-E25 -> 255263933 | F33: =SUM(F18:F32)-F25 -> 200305957 | G33: =SUM(G18:G32)-G25 -> 290411542 | H33: =SUM(H18:H32)-H25 -> 1197218183 | I33: отток | K33: =SUM(K11:K32) -> 1.7090708e+08
B35: Подпись Председателя правления:
B37: Подпись Главного Бухгалтера:

Sheet Commitments
B1: Приложение №1 к Рекомендациям по заполнению отчетности коммерческих банков по банковскому надзору представляемых Центральному банку Республики Узбекистан
A2: ОТЧЕТ О СЧЕТАХ ОБЯЗАТЕЛЬСТВ И НЕПРЕДВИДЕННЫХ ОБСТОЯТЕЛЬСТВ | B2: Таблица-19 (Форма-0126BS)
A3: =Balance!A4 -> 43100 | B3: =Balance!B3 -> АКБ "Микрокредитбанк"
A4: Категории | B4: в тыс. сум
A5: 1. Линии кредита и Обязательства
A6: а. Неиспользованные кредитные линии/Обязательства для финансирования кредита | B6: 484400880
A8: 2. Гарантии и аккредитивы
A9: а. Гарантии и финансовые аккредитивы "Стэнд-бай" | B9: 21179243
A10: б. Аккредитивы "Стэнд-бай" под исполнение | B10: 0
A11: в. Коммерческие аккредитивы (документарные) | B11: 0
A12: г. Итого гарантий и аккредитивов | B12: =SUM(B9:B11) -> 21179243
A14: 3. Другие статьи непредвиденных обстоятельств
A15: а. Условная стоимость процентного свопа | B15: 0
A16: б. Условная стоимость обменного свопа (Валютный своп) | B16: 0
A17: в. Фьючерсные, Форвардные и Опционные контракты | B17: 0
A18: г. Обязательства по покупке кредитов, ценных бумаг или других активов | B18: 0
A19: д. Другие счета непредвиденных обстоятельств | B19: 43380833
A20: е. Итого других статей непредвиденных обстоятельств | B20: =SUM(B15:B19) -> 43380833
A22: 4. Итого статей непредвиденных обстоятельств | B22: =B6+B12+B20 -> 548960956
A24: Подпись Председателя правления:
A26: Подпись Главного Бухгалтера:

Sheet Economic Normatives
I1: Приложение №1 к Рекомендациям по заполнению отчетности коммерческих банков по банковскому надзору представляемых Центральному банку Республики Узбекистан
A2: РАСЧЕТ ЭКОНОМИЧЕСКИХ НОРМАТИВОВ | I2: Таблица-20 (Форма-3006EN)
A3: =Balance!A4 -> 43100 | J3: =Balance!B3 -> АКБ "Микрокредитбанк"
A5: № | B5: Наименование экономического норматива | F5: Формула | I5: Фактическое значение | J5: Нормативное значение | K5: Отклонение
B6: A | F6: Б | I6: В | J6: Г | K6: Д
A7: 1 | B7: Показатели достаточности капитала
A8: 1.1 | B8: Коэффициент достаточности капитала | F8: Скорректированная общая капитала, основанного на риске | I8: ='Bank Capital Calc.'!E50 -> 0.28700826 | J8: Мин | K8: =IF(I8="",0-J9,(IF((I8-J9)>0,"",I8-J9)))
F9: Активы с учетом риска | J9: =+'Calculation of Risk'!C26/100 -> 0.125
A10: 1.2 | B10: Коэффициент достаточности Капитала Уровня 1 | F10: Капитал Уровня I | I10: ='Bank Capital Calc.'!E49 -> 0.28691819 | J10: Мин | K10: =IF(I10="",0-J11,(IF((I10-J11)>0,"",I10-J11)))
F11: Активы с учетом риска | J11: =+'Calculation of Risk'!G10/100 -> 0.095
A12: 1.3 | B12: Левераж | F12: Капитал Уровня I | I12: =+'Bank Capital Calc.'!E56 -> 0.24050559 | J12: Мин | K12: =IF(I12="",0-J13,(IF((I12-J13)>0,"",I12-J13)))
F13: Активы + забалансовые инструменты+ деривативные (производные) инструменты - Нематериальные активы | J13: 0.06
A14: 2 | B14: Показатель ликвидности
A15: 2.1 | B15: Коэффициент текущей ликвидности (Н4) | F15: Ликвидные активы и активы со сроком погашения до 30 дней | I15: ='Liquidity Analysis'!B32 -> 0.93350739 | J15: Мин | K15: =IF(I15="",0-J16,(IF((I15-J16)>0,"",I15-J16)))
F16: Обязательства до востребования и со сроком погашения до 30 дней | J16: 0.3
A17: 2.2 | B17: Коэффициент покрытия ликвидности | F17: Высоколиквидные активы | I17: =+'Liquidity Analysis'!B38 -> 2.3779889 | J17: Мин | K17: =IF(I17="",0-J18,(IF((I17-J18)>0,"",I17-J18)))
F18: Чистый отток в последующие 30 дней | J18: =+'Calculation of Risk'!G11/100 -> 0.9
A19: 2.3 | B19: Норма чистого стабильного финансирования | F19: Доступная сумма стабильного финансирования | I19: =+'Liquidity Analysis'!B41 -> 1.0145831 | J19: Мин | K19: =IF(I19="",0-J20,(IF((I19-J20)>0,"",I19-J20)))
F20: Необходимая сумма стабильного финансирования | J20: =+'Calculation of Risk'!G12/100 -> 0
A21: 3 | B21: Нормативы по операциям с заемщиками
A22: 3.1 | B22: Максимальный размер риска на одного заемщика или группу взаимосвязанных заемщиков,Обеспеченные кредиты | F22: Максимальная сумма кредита на одного заемщика, обеспеченные кредиты | I22: 0 | J22: Макс | K22: =IF(I22="","",IF(I22<0,"ОТР",IF((I22-J23)<0,"",I22-J23)))
F23: Капитал Уровня I | J23: 0.25
A24: 3.2 | B24: Максимальный размер риска на одного заемщика или группу взаимосвязанных заемщиков, Необеспеченные кредиты | F24: Максимальная сумма кредита на одного заемщика, необеспеченные кредиты | I24: 0 | J24: Макс | K24: =IF(I24<0,"ОТР",IF((I24-J25)<0,"",I24-J25))
F25: Капитал Уровня I | J25: 0.05
A26: 3.3 | B26: Максимальный размер риска для всех крупных кредитов | F26: Совокупная сумма крупных кредитов | I26: 0 | J26: Макс | K26: =IF(I26="","",IF(I26<0,"ОТР",IF((I26-J27)<0,"",I26-J27)))
F27: Капитал Уровня I | J27: 8
A28: 4 | B28: Нормативы по операциям с ценными бумагами
A29: 4.1 | B29: Максимальный размер инвестиций в ценные бумаги одного эмитента | F29: Инвестиции в негосударственные ценные бумаги одного эмитента | I29: =+Balance!B15/'Bank Capital Calc.'!E32 -> 0.0050895939 | J29: Макс | K29: =IF(I29<0,"ОТР",IF((I29-J30)<0,"",I29-J30))
F30: Капитал Уровня I | J30: 0.15
A31: 4.2 | B31: Максимальный общий размер инвестиций в ценные бумаги для купли- продажи | F31: Общий размер инвестиций в ценные бумаги для купли- продажи | I31: =IF('Bank Capital Calc.'!E32=0,"",'Investment Securities'!B26/'Bank Capital Calc.'!E32) -> 0.00064688553 | J31: Макс | K31: =IF(I31="","",IF(I31<0,"ОТР",IF((I31-J32)<0,"",I31-J32)))
F32: Капитал Уровня I | J32: 0.25
A33: 4.3 | B33: Максимальный общий размер инвестиций в уставной капитал и другие ценные бумаги всех эмитентов | F33: Общий размер инвестиций в уставной капитал и другие ценные бумаги всех эмитентов | I33: 0.006 | J33: Макс | K33: =IF(I33="","",IF(I33<0,"ОТР",IF((I33-J34)<0,"",I33-J34)))
F34: Капитал Уровня I | J34: 0.5
A35: 5 | B35: Нормативы показателей по операциям со связанными лицами (инсайдерами)
A36: 5.1 | B36: Сумма выданных кредитов одному инсайдеру или группе связанных лиц, Обеспеченные Кредиты/ Лизинг | F36: Самый крупный кредит одному инсайдеру, обеспеченный | I36: =IF('Bank Capital Calc.'!E32=0,"",'Loans to Affiliated P.'!F38/'Bank Capital Calc.'!E32) -> 0.00048119797 | J36: Макс | K36: =IF(I36="","",IF(I36<0,"ОТР",IF((I36-J37)<0,"",I36-J37)))
F37: Капитал Уровня I | J37: 0.25
A38: 5.2 | B38: Совокупная сумма кредитов предоставленых банком всем инсайдерам | F38: Совокупная сумма кредитов выданных инсайдерам | I38: =IF('Bank Capital Calc.'!E32=0,"",'Loans to Affiliated P.'!F37/'Bank Capital Calc.'!E32) -> 0.00078737683 | J38: Макс | K38: =IF(I38="","",IF(I38<0,"ОТР",IF((I38-J39)<0,"",I38-J39)))
F39: Капитал Уровня I | J39: 1
A40: 6 | B40: Нормативы по лизинговым услугам оказываемых банками
A41: 6.1 | B41: Максимальный размер риска лизинговых услуг оказываемых банками | F41: Общая сумма лизинговых услуг (за исключением авиализинга) | I41: 0.010647708 | J41: Макс | K41: =IF(I41="","",IF(I41<0,"ОТР",IF((I41-J42)<0,"",I41-J42)))
F42: Капитал Уровня I | J42: 0.25
A43: 7 | B43: Нормативы по банковским гарантиям
A44: 7.1 | B44: Сумма всех гарантий и средств, предоставленных коммерческими банками, уплаченных бенефициару и не покрытых принципалом | F44: Сумма всех предоставленных коммерческими банками гарантий | I44: 0.039197726 | J44: Макс | K44: =IF(I44="","",IF(I44<0,"ОТР",IF((I44-J45)<0,"",I44-J45)))
F45: Капитал Уровня I | J45: 0.25
D47: Подпись Председателя правления:
D49: Подпись Главного Бухгалтера:

Sheet Miscellaneous
B1: Приложение №1 к Рекомендациям по заполнению отчетности коммерческих банков по банковскому надзору представляемых Центральному банку Республики Узбекистан
A2: РАЗНАЯ ИНФОРМАЦИЯ | B2: Таблица-21 (Форма-9006ME)
A3: =Balance!A4 -> 43100 | B3: =Balance!B3 -> АКБ "Микрокредитбанк"
A5: 1. Назначал ли банк новых администраторов (начальников, директоров, членов
A6: аудиторского комитета) в течение месяца? | B6: н
A7: 2. Покупали ли физические или юридические лица или группы физических
A8: или юридических лиц новые или дополнительные акции, тем самым
A9: повлияв на долю владения собственностью учреждения на 5% и более? | B9: н
A10: 3. Приобретал ли банк долевое участие в каких-либо финансовых учреждениях
A11: или компаниях в течение месяца? | B11: н
A12: 4. Занимался ли банк новой финансовой деятельностью в течение месяца? | B12: н
A13: 5. Нарушались ли банком экономические нормативы в
A14: течение месяца? | B14: н
B15: Кол-во
A16: 6. Численность работников банка, включая административный, филиалы,
A17: и представительства банка. | B17: 3699
A18: 7. Общее количество отделений банка, включая административный, филиалы,
A19: и представительства банка. | B19: 86
A21: Подпись Председателя правления:
A23: Подпись Главного Бухгалтера:
