Workbook
Name jop: #REF!
Name kol: #REF!
Name RISKTOTASS: SUM('[6]Calculation of Risk Weighted As'!$C$38:$F$38)
Name RISKTOTASS: SUM('[7]Calculation of Risk Weighted As'!$C$41:$G$41)
Name TwentyLargestData: #REF!
Name Е: #REF!

Sheet Asset quality
A1: АКТИВЛАР ТАСНИФИ ВА УЛАР БЎЙИЧА ЯРАТИЛГАН ЭҲТИМОЛИЙ ЙЎҚОТИШЛАРНИ ҚОПЛАШ ЗАХИРАЛАРИ ТЎҒРИСИДА ҲИСОБОТ | S1: 2-жадвал | V1: №6
B3: "Ўзсаноатқурилишбанк" АТБ | Q3: 44925 | T3: минг. сўмда
A4: № | B4: Активлар таркиби* | C4: Қолдиқ | D4: Сифат тоифаси | I4: Муддати ўтган қарздорлик (брутто) | O4: Зарарларни қоплаш захираси
I5: Жами | J5: 30 кунгача | K5: 31дан 90 кунгача | L5: 91дан 180 кунгача | M5: 181 дан 365 кунгача | N5: 366 кун ва ундан ортиқ | O5: ҳақиқатдан яратилган захиралар
O6: Жами | P6: сифат тоифаси бўйича
D7: I | E7: II | F7: III | G7: IV | H7: V | P7: I | Q7: II | R7: III | S7: IV | T7: V
A8: А | B8: Б | C8: В | D8: Г | E8: Д | F8: Е | G8: Ж | H8: З | I8: И | J8: К | K8: Л | L8: М | M8: Н | N8: О | O8: П | P8: Р | Q8: С | R8: Т | S8: У | T8: Ф
B9: Жами активлар | C9: =SUM(C10:C58)+C60-C59 -> 64263771349 | D9: =SUM(D10:D58)-D59+D60 -> 60944572016 | E9: =SUM(E10:E58)-E59+E60 -> 2691462008 | F9: =SUM(F10:F58)-F59+F60 -> 507333345 | G9: =SUM(G10:G58)-G59+G60 -> 1000162337 | H9: =SUM(H10:H58)-H59+H60 -> 257499868 | I9: =SUM(I10:I60) -> 988593441 | J9: =SUM(J10:J60) -> 96264988 | K9: =SUM(K10:K60) -> 283830528 | L9: =SUM(L10:L60) -> 264621199 | M9: =SUM(M10:M60) -> 314624827 | N9: =SUM(N10:N60) -> 29251899 | O9: =SUM(O10:O60) -> 1659124432 | P9: =SUM(P10:P60) -> 521866207 | ... T9: =SUM(T10:T60) -> 222940564
A10: 1 | B10: Кассадаги нақд пул ва бошқа тўлов ҳужжатлари | C10: =SUM(D10:H10)-O10+P10 -> 1558319960 | D10: 1558319960 | E10: 0 | F10: 0 | G10: 0 | H10: 0 | I10: =SUM(J10:N10) -> 0 | O10: =SUM(P10:T10) -> 0 | P10: 0 | Q10: 0 | R10: 0 | S10: 0 | T10: 0 | U10: 10100
A11: 2 | B11: Банкнинг Марказий банкдаги маблағлар | C11: =SUM(D11:H11)-O11+P11 -> 1510578445 | D11: 1510578445 | E11: 0 | F11: 0 | G11: 0 | H11: 0 | I11: =SUM(J11:N11) -> 0 | O11: =SUM(P11:T11) -> 0 | P11: 0 | Q11: 0 | R11: 0 | S11: 0 | T11: 0 | U11: 10300
A12: 3 | B12: Бошқа банклар ва молиявий ташкилотлардан олиниши лозим бўлган маблағлар | C12: =SUM(D12:H12)-O12+P12 -> 6508984468 | D12: 6508984468 | E12: 0 | F12: 0 | G12: 0 | H12: 33976380 | I12: =SUM(J12:N12) -> 0 | O12: =SUM(P12:T12) -> 99066225 | P12: 65089845 | Q12: 0 | R12: 0 | S12: 0 | T12: 33976380 | U12: 10500
A13: 4 | B13: Фойда ёки зарар орқали ҳаққоний қийматда баҳоланадиган қимматли қоғозлар | C13: =SUM(D13:H13)-O13+P13 -> 2655203447 | D13: 2655203447 | E13: 0 | F13: 0 | G13: 0 | H13: 0 | I13: =SUM(J13:N13) -> 0 | O13: =SUM(P13:T13) -> 0 | P13: 0 | Q13: 0 | R13: 0 | S13: 0 | T13: 0 | U13: 10700
A14: 5 | B14: Бошқа умумлашган даромад орқали ҳаққоний қийматда баҳоланадиган қимматли қоғозларга қилинган инвестициялар | C14: =SUM(D14:H14)-O14+P14 -> 0 | D14: 0 | E14: 0 | F14: 0 | G14: 0 | H14: 0 | I14: =SUM(J14:N14) -> 0 | O14: =SUM(P14:T14) -> 0 | P14: 0 | Q14: 0 | R14: 0 | S14: 0 | T14: 0 | U14: 10800
A15: 6 | B15: Олди-сотдига мўлжалланган қимматбаҳо металлар, тошлар ва тангалар | C15: =SUM(D15:H15)-O15+P15 -> 875 | D15: 875 | E15: 0 | F15: 0 | G15: 0 | H15: 0 | I15: =SUM(J15:N15) -> 0 | O15: =SUM(P15:T15) -> 9 | P15: 9 | Q15: 0 | R15: 0 | S15: 0 | T15: 0 | U15: 10900
A16: 7 | B16: Сотиб олинган дебиторлик қарзлари — Факторинг | C16: =SUM(D16:H16)-O16+P16 -> 283941159 | D16: 283941159 | E16: 0 | F16: 0 | G16: 0 | H16: 0 | I16: =SUM(J16:N16) -> 0 | O16: =SUM(P16:T16) -> 2839412 | P16: 2839412 | Q16: 0 | R16: 0 | S16: 0 | T16: 0 | U16: 11100
A17: 8 | B17: Мижозларнинг аккредитив ва/ёки траст ҳужжатлари билан кафолатланган тратталари бўйича мажбуриятлари | C17: =SUM(D17:H17)-O17+P17 -> 47694399 | D17: 47694399 | E17: 0 | F17: 0 | G17: 0 | H17: 0 | I17: =SUM(J17:N17) -> 0 | O17: =SUM(P17:T17) -> 476944 | P17: 476944 | Q17: 0 | R17: 0 | S17: 0 | T17: 0 | U17: 11500
A18: 9 | B18: Банкнинг тўланмаган акцептлари бўйича мижозларнинг мажбуриятлари | C18: =SUM(D18:H18)-O18+P18 -> 0 | D18: 0 | E18: 0 | F18: 0 | G18: 0 | H18: 0 | I18: =SUM(J18:N18) -> 0 | O18: =SUM(P18:T18) -> 0 | P18: 0 | Q18: 0 | R18: 0 | S18: 0 | T18: 0 | U18: 11700
A19: 10 | B19: РЕПО битимлари бўйича сотиб олинган қимматли қоғозлар | C19: =SUM(D19:H19)-O19+P19 -> 0 | D19: 0 | E19: 0 | F19: 0 | G19: 0 | H19: 0 | I19: =SUM(J19:N19) -> 0 | O19: =SUM(P19:T19) -> 0 | P19: 0 | Q19: 0 | R19: 0 | S19: 0 | T19: 0 | U19: 11800
A20: 11 | B20: Марказий банкка берилган қисқа муддатли кредитлар | C20: =SUM(D20:H20)-O20+P20 -> 0 | D20: 0 | E20: 0 | F20: 0 | G20: 0 | H20: 0 | I20: =SUM(J20:N20) -> 0 | O20: =SUM(P20:T20) -> 0 | P20: 0 | Q20: 0 | R20: 0 | S20: 0 | T20: 0 | U20: 11900
A21: 12 | B21: Бошқа банкларга берилган қисқа муддатли кредитлар | C21: =SUM(D21:H21)-O21+P21 -> 0 | D21: 0 | E21: 0 | F21: 0 | G21: 0 | H21: 0 | I21: =SUM(J21:N21) -> 0 | O21: =SUM(P21:T21) -> 0 | P21: 0 | Q21: 0 | R21: 0 | S21: 0 | T21: 0 | U21: 12100
A22: 13 | B22: Ҳукуматга берилган қисқа муддатли кредитлар | C22: =SUM(D22:H22)-O22+P22 -> 0 | D22: 0 | E22: 0 | F22: 0 | G22: 0 | H22: 0 | I22: =SUM(J22:N22) -> 0 | O22: =SUM(P22:T22) -> 0 | P22: 0 | Q22: 0 | R22: 0 | S22: 0 | T22: 0 | U22: 12300
A23: 14 | B23: Бюджет ташкилотларига берилган қисқа муддатли кредитлар | C23: =SUM(D23:H23)-O23+P23 -> 0 | D23: 0 | E23: 0 | F23: 0 | G23: 0 | H23: 0 | I23: =SUM(J23:N23) -> 0 | O23: =SUM(P23:T23) -> 0 | P23: 0 | Q23: 0 | R23: 0 | S23: 0 | T23: 0 | U23: 12400
A24: 15 | B24: Жисмоний шахсларга берилган қисқа муддатли кредитлар | C24: =SUM(D24:H24)-O24+P24 -> 192018693 | D24: 190619423 | E24: 824220 | F24: 492025 | G24: 571217 | H24: 23941 | I24: =SUM(J24:N24) -> 1330970 | J24: 184668 | K24: 261812 | L24: 365976 | M24: 494755 | N24: 23759 | O24: =SUM(P24:T24) -> 2418327 | P24: 1906194 | Q24: 80437 | R24: 122147 | S24: 285608 | T24: 23941 | U24: 12500
A25: 16 | B25: Якка тартибдаги тадбиркорларга берилган қисқа муддатли кредитлар | C25: =SUM(D25:H25)-O25+P25 -> 46132525 | D25: 45113153 | E25: 1132636 | F25: 0 | G25: 0 | H25: 0 | I25: =SUM(J25:N25) -> 124747 | J25: 116565 | K25: 8182 | L25: 0 | M25: 0 | N25: 0 | O25: =SUM(P25:T25) -> 564396 | P25: 451132 | Q25: 113264 | R25: 0 | S25: 0 | T25: 0 | U25: 12600
A26: 17 | B26: Давлат корхоналари, ташкилотлари ва муассасаларига берилган қисқа муддатли кредитлар | C26: =SUM(D26:H26)-O26+P26 -> 2644342581 | D26: 2627395347 | E26: 18830260 | F26: 0 | G26: 0 | H26: 0 | I26: =SUM(J26:N26) -> 1754549 | J26: 0 | K26: 1754549 | L26: 0 | M26: 0 | N26: 0 | O26: =SUM(P26:T26) -> 28156979 | P26: 26273953 | Q26: 1883026 | R26: 0 | S26: 0 | T26: 0 | U26: 12700
A27: 18 | B27: Тадбиркорлик фаолиятини қўллаб-қувватлаш давлат жамғармаси кўмагида берилган қисқа муддатли кредитлар | C27: =SUM(D27:H27)-O27+P27 -> 154873173 | D27: 107408832 | E27: 24050379 | F27: 12924812 | G27: 26417752 | H27: 335987 | I27: =SUM(J27:N27) -> 48886846 | J27: 762434 | K27: 14684729 | L27: 14954366 | M27: 18149330 | N27: 335987 | O27: =SUM(P27:T27) -> 17338677 | P27: 1074088 | Q27: -511477 | R27: 3231203 | S27: 13208876 | T27: 335987 | U27: 12800
A28: 19 | B28: Чет эл капитали иштирокидаги корхоналарга берилган қисқа муддатли кредитлар | C28: =SUM(D28:H28)-O28+P28 -> 2071605949 | D28: 2067731539 | E28: 0 | F28: 0 | G28: 7748821 | H28: 0 | I28: =SUM(J28:N28) -> 7748821 | J28: 0 | K28: 0 | L28: 0 | M28: 7748821 | N28: 0 | O28: =SUM(P28:T28) -> 24551726 | P28: 20677315 | Q28: 0 | R28: 0 | S28: 3874411 | T28: 0 | U28: 12900
A29: 20 | B29: Нодавлат нотижорат ташкилотларига берилган қисқа муддатли кредитлар | C29: =SUM(D29:H29)-O29+P29 -> 888692 | D29: 888692 | E29: 0 | F29: 0 | G29: 0 | H29: 0 | I29: =SUM(J29:N29) -> 0 | J29: 0 | K29: 0 | L29: 0 | M29: 0 | N29: 0 | O29: =SUM(P29:T29) -> 8887 | P29: 8887 | Q29: 0 | R29: 0 | S29: 0 | T29: 0 | U29: 13000
A30: 21 | B30: Хусусий корхоналар, хўжалик ширкатлари ва жамиятларга берилган қисқа муддатли кредитлар | C30: =SUM(D30:H30)-O30+P30 -> 2389804204 | D30: 2167565789 | E30: 179961956 | F30: 56340014 | G30: 43128739 | H30: 3118638 | I30: =SUM(J30:N30) -> 114308313 | J30: 8172378 | K30: 14726247 | L30: 61560581 | M30: 28751052 | N30: 1098055 | O30: =SUM(P30:T30) -> 81986590 | P30: 21675658 | Q30: 19961421 | R30: 15666503 | S30: 21564370 | T30: 3118638 | U30: 13100
A31: 22 | B31: Банк бўлмаган молиявий муассасаларга берилган қисқа муддатли кредитлар | C31: =SUM(D31:H31)-O31+P31 -> 3441000 | D31: 3441000 | E31: 0 | F31: 0 | G31: 0 | H31: 0 | I31: =SUM(J31:N31) -> 0 | J31: 0 | K31: 0 | L31: 0 | M31: 0 | N31: 0 | O31: =SUM(P31:T31) -> 34410 | P31: 34410 | Q31: 0 | R31: 0 | S31: 0 | T31: 0 | U31: 13200
A32: 23 | B32: Давлат эҳтиёжлари учун харид қилинадиган қишлоқ хўжалиги маҳсулотларини етиштириш учун берилган қисқа муддатли кредитлар | C32: =SUM(D32:H32)-O32+P32 -> 0 | D32: 0 | E32: 0 | F32: 0 | G32: 0 | H32: 0 | I32: =SUM(J32:N32) -> 0 | J32: 0 | K32: 0 | L32: 0 | M32: 0 | N32: 0 | O32: =SUM(P32:T32) -> 0 | P32: 0 | Q32: 0 | R32: 0 | S32: 0 | T32: 0 | U32: 13300
A33: 24 | B33: Давлат эҳтиёжлари учун харид қилинадиган қишлоқ хўжалиги маҳсулотларини етиштириш учун берилган узоқ муддатли кредитлар | C33: =SUM(D33:H33)-O33+P33 -> 1652275495 | D33: 1652275495 | E33: 0 | F33: 0 | G33: 0 | H33: 0 | I33: =SUM(J33:N33) -> 2104992 | J33: 2104992 | K33: 0 | L33: 0 | M33: 0 | N33: 0 | O33: =SUM(P33:T33) -> 16522755 | P33: 16522755 | Q33: 0 | R33: 0 | S33: 0 | T33: 0 | U33: 14300
A34: 25 | B34: Тадбиркорлик фаолиятини қўллаб-қувватлаш давлат жамғармаси кўмагида берилган узоқ муддатли кредитлар | C34: =SUM(D34:H34)-O34+P34 -> 3482004636 | D34: 2691959341 | E34: 632888609 | F34: 154748726 | G34: 195717001 | H34: 39238546 | I34: =SUM(J34:N34) -> 130907677 | J34: 22955573 | K34: 30860755 | L34: 20959439 | M34: 44440642 | N34: 11691268 | O34: =SUM(P34:T34) -> 259467180 | P34: 26919593 | Q34: 57829778 | R34: 37620763 | S34: 97858500 | T34: 39238546 | U34: 14400
A35: 26 | B35: Бошқа банкларга берилган узоқ муддатли кредитлар | C35: =SUM(D35:H35)-O35+P35 -> 0 | D35: 0 | E35: 0 | F35: 0 | G35: 0 | H35: 0 | I35: =SUM(J35:N35) -> 0 | J35: 0 | K35: 0 | L35: 0 | M35: 0 | N35: 0 | O35: =SUM(P35:T35) -> 0 | P35: 0 | Q35: 0 | R35: 0 | S35: 0 | T35: 0 | U35: 14500
... A44: 35 | B44: Хусусий корхоналар, хўжалик ширкатлари ва жамиятларга берилган узоқ муддатли кредитлар | C44: =SUM(D44:H44)-O44+P44 -> 12071110691 | D44: 10879925723 | E44: 1107278492 | F44: 122981634 | G44: 201183364 | H44: 7654167 | I44: =SUM(J44:N44) -> 161508676 | J44: 9367918 | K44: 63342905 | L44: 33308775 | M44: 55343245 | N44: 145833 | O44: =SUM(P44:T44) -> 356711946 | P44: 108799257 | Q44: 108859695 | R44: 30811112 | S44: 100587715 | T44: 7654167 | U44: 15500
A45: 36 | B45: Лизинг (молиявий ижара) | C45: =SUM(D45:H45)-O45+P45 -> 335566010 | D45: 335566010 | E45: 0 | F45: 0 | G45: 0 | H45: 0 | I45: =SUM(J45:N45) -> 0 | O45: =SUM(P45:T45) -> 3355660 | P45: 3355660 | Q45: 0 | R45: 0 | S45: 0 | T45: 0 | U45: 15600
A46: 37 | B46: Суд ёки ижро иши юритиш жараёнидаги кредитлар ва лизинг | C46: =SUM(D46:H46)-O46+P46 -> 71465006 | D46: 0 | E46: 0 | F46: 63874260 | G46: 60205586 | H46: 32313429 | I46: =SUM(J46:N46) -> 0 | O46: =SUM(P46:T46) -> 84928269 | P46: 0 | Q46: 8301596 | R46: 14217481 | S46: 30095766 | T46: 32313426 | U46: 15700
A47: 38 | B47: Қарам хўжалик жамиятларига, биргаликдаги корхоналарга ва шўъба хўжалик жамиятларига қилинган инвестициялар | C47: =SUM(D47:H47)-O47+P47 -> 233090515 | D47: 227467057 | E47: 0 | F47: 7499992 | G47: 0 | H47: 3205644 | I47: =SUM(J47:N47) -> 0 | O47: =SUM(P47:T47) -> 7356849 | P47: 2274671 | Q47: 0 | R47: 1876534 | S47: 0 | T47: 3205644 | U47: 15800
A48: 39 | B48: Амортизацияланган қиймати бўйича баҳоланадиган қарз қимматли қоғозларга қилинган инвестициялар | C48: =SUM(D48:H48)-O48+P48 -> 5805445 | D48: 5805445 | E48: 0 | F48: 0 | G48: 0 | H48: 0 | I48: =SUM(J48:N48) -> 0 | O48: =SUM(P48:T48) -> 58054 | P48: 58054 | Q48: 0 | R48: 0 | S48: 0 | T48: 0 | U48: 15900
A49: 40 | B49: Олиниши лозим бўлган ҳисобланган фоизлар | C49: =SUM(D49:H49)-O49+P49 -> 1805164470 | D49: 1581537458 | E49: 121751748 | F49: 54841935 | G49: 156571796 | H49: 18261861 | I49: =SUM(J49:N49) -> 494296721 | J49: ='Aging Analysis'!L22 -> 48132494 | K49: ='Aging Analysis'!N22+'Aging Analysis'!P22 -> 141915264 | L49: ='Aging Analysis'!R22 -> 132310600 | M49: ='Aging Analysis'!T22 -> 157312413 | N49: ='Aging Analysis'!V22+'Aging Analysis'!X22 -> 14625950 | O49: =SUM(P49:T49) -> 143615659 | P49: 15815331 | Q49: 127800328 | R49: 0 | S49: 0 | T49: 0 | U49: 16300
A50: 41 | B50: Олиниши лозим бўлган ҳисобланган фоизсиз даромадлар | C50: =SUM(D50:H50)-O50+P50 -> 14867045 | D50: 12584437 | E50: 1723089 | F50: 177311 | G50: 2253444 | H50: 2240385 | I50: =SUM(J50:N50) -> 0 | O50: =SUM(P50:T50) -> 4237465 | P50: 125844 | Q50: 113136 | R50: 80977 | S50: 1677123 | T50: 2240385 | U50: 16400
A51: 42 | B51: Асосий воситалар | C51: =SUM(D51:H51)-O51+P51 -> 1973852967 | D51: 1973852967 | E51: 0 | F51: 0 | G51: 0 | H51: 0 | I51: =SUM(J51:N51) -> 0 | O51: =SUM(P51:T51) -> 0 | P51: 0 | Q51: 0 | R51: 0 | S51: 0 | T51: 0 | U51: 16500
A52: 43 | B52: Номоддий активлар | C52: =SUM(D52:H52)-O52+P52 -> 74978867 | D52: 74978867 | E52: 0 | F52: 0 | G52: 0 | H52: 0 | I52: =SUM(J52:N52) -> 0 | O52: =SUM(P52:T52) -> 0 | P52: 0 | Q52: 0 | R52: 0 | S52: 0 | T52: 0 | U52: 16600
A53: 44 | B53: Банкнинг бошқа хусусий мулклари | C53: =SUM(D53:H53)-O53+P53 -> 235154635 | D53: 215019847 | E53: 3020841 | F53: 36494 | G53: 4711168 | H53: 98485544 | I53: =SUM(J53:N53) -> 0 | O53: =SUM(P53:T53) -> 86164462 | P53: 45203 | Q53: 945979 | R53: 31932 | S53: 2095979 | T53: 83045369 | U53: 16700
A54: 45 | B54: Муддати узайтирилган дебитор қарздорлик | C54: =SUM(D54:H54)-O54+P54 -> 339298588 | D54: 326644941 | E54: 0 | F54: 7832177 | G54: 6027764 | H54: 0 | I54: =SUM(J54:N54) -> 0 | O54: =SUM(P54:T54) -> 1310070 | P54: 103776 | Q54: 103776 | R54: 0 | S54: 1102518 | T54: 0 | U54: 16800
A55: 46 | B55: Ҳосилавий инструментларнинг ревальвацияси натижасида ўзлаштирилмаган фойда | C55: =SUM(D55:H55)-O55+P55 -> 0 | D55: 0 | E55: 0 | F55: 0 | G55: 0 | H55: 0 | I55: =SUM(J55:N55) -> 0 | O55: =SUM(P55:T55) -> 0 | P55: 0 | Q55: 0 | R55: 0 | S55: 0 | T55: 0 | U55: 16900
A56: 47 | B56: Валюталар савдоси ва валюта позициялари | C56: =SUM(D56:H56)-O56+P56 -> 0 | D56: 0 | E56: 0 | F56: 0 | G56: 0 | H56: 0 | I56: =SUM(J56:N56) -> 0 | O56: =SUM(P56:T56) -> 0 | P56: 0 | Q56: 0 | R56: 0 | S56: 0 | T56: 0 | U56: 17100
A57: 48 | B57: Транзит ҳисобварақлари | C57: =SUM(D57:H57)-O57+P57 -> 0 | D57: 0 | E57: 0 | F57: 0 | G57: 0 | H57: 0 | I57: =SUM(J57:N57) -> 0 | O57: =SUM(P57:T57) -> 0 | P57: 0 | Q57: 0 | R57: 0 | S57: 0 | T57: 0 | U57: 17300
A58: 49 | B58: Мижозларнинг банк карталаридан ҳисобдан чиқарилиши лозим бўлган маблағлар бўйича транзит ҳисобварақлари | C58: =SUM(D58:H58)-O58+P58 -> 72774486 | D58: 72774486 | E58: 0 | F58: 0 | G58: 0 | H58: 0 | I58: =SUM(J58:N58) -> 0 | O58: =SUM(P58:T58) -> 727745 | P58: 727745 | Q58: 0 | R58: 0 | S58: 0 | T58: 0 | U58: 17400
A59: 50 | B59: Стандарт активлар бўйича яратилган захирлар | C59: =SUM(D59:H59)-O59 -> 521866207 | D59: 521866207 | E59: 0 | F59: 0 | G59: 0 | H59: 0 | I59: =SUM(J59:N59) -> 0 | O59: =SUM(P59:T59) -> 0 | P59: 0 | Q59: 0 | R59: 0 | S59: 0 | T59: 0 | U59: 17700
A60: 51 | B60: Бошқа активлар | C60: =SUM(D60:H60)-O60+P60 -> 542796803 | D60: 534693376 | E60: 8065678 | F60: 156226 | G60: 155357 | H60: 9875592 | I60: =SUM(J60:N60) -> 0 | O60: =SUM(P60:T60) -> 32608239 | P60: 22458813 | Q60: 135039 | R60: 39356 | S60: 99439 | T60: 9875592 | U60: 19900
B62: БАЛАНСДАН ТАШҚАРИ МОДДАЛАР | C62: =SUM(C63:C65) -> 3920720148 | D62: =SUM(D63:D65) -> 3695720549 | E62: =SUM(E63:E65) -> 221884934 | F62: =SUM(F63:F65) -> 80000 | G62: =SUM(G63:G65) -> 3034665 | H62: =SUM(H63:H65) -> 0 | I62: =SUM(J62:N62) -> 0 | J62: =SUM(J63:J65) -> 0 | K62: =SUM(K63:K65) -> 0 | L62: =SUM(L63:L65) -> 0 | M62: =SUM(M63:M65) -> 0 | N62: =SUM(N63:N65) -> 0 | O62: =SUM(O63:O65) -> 27671391 | P62: =SUM(P63:P65) -> 24500000 | Q62: =SUM(Q63:Q65) -> 2860881 | ... T62: =SUM(T63:T65) -> 0
A63: 1 | B63: Аккредитивлар | C63: =SUM(D63:H63) -> 1491721327 | D63: 1317365127 | E63: 174356200 | F63: 0 | G63: 0 | H63: 0 | I63: =SUM(J63:N63) -> 0 | O63: =SUM(P63:T63) -> 3557087 | P63: 2634730 | Q63: 922357 | R63: 0 | S63: 0 | T63: 0 | U63: 90908-90958
A64: 2 | B64: Кафолат ва кафилликлар | C64: =SUM(D64:H64) -> 1933384881 | D64: 1886666052 | E64: 46718829 | F64: 0 | G64: 0 | H64: 0 | I64: =SUM(J64:N64) -> 0 | O64: =SUM(P64:T64) -> 20524690 | P64: 18866661 | Q64: 1658029 | R64: 0 | S64: 0 | T64: 0 | U64: 90993
A65: 3 | B65: Банкнинг кредит ва лизинг бериш бўйича мажбуриятлари | C65: =SUM(D65:H65) -> 495613940 | D65: 491689370 | E65: 809905 | F65: 80000 | G65: 3034665 | H65: 0 | I65: =SUM(J65:N65) -> 0 | O65: =SUM(P65:T65) -> 3589614 | P65: 2998609 | Q65: 280495 | R65: 1500 | S65: 309010 | T65: 0 | U65: 91809
B67: Бошқарув Раис имзоси:
B69: Бош бухгалтер имзоси:
C73: =+[8]Balance!$C$47 -> 64263771349

Sheet Income 
A1: МОЛИЯВИЙ НАТИЖАЛАР ТЎҒРИСИДА ҲИСОБОТ | E1: 3-жадвал
B3: =+'Asset quality'!B3 -> "Ўзсаноатқурилишбанк" АТБ | D3: =+'Asset quality'!Q3 -> 44925 | E3: =+'Asset quality'!T3 -> минг. сўмда
A4: № | B4: Кўрсаткичлар | C4: Жами | D4: миллий валютада | E4: хорижий валютада (экв. сўмда)
A5: 1. | B5: ФОИЗЛИ ДАРОМАДЛАР
A6: a. | B6: Марказий банкдаги ҳисобварақлар бўйича фоизли даромадлар | C6: =+D6+E6 -> 35844465 | D6: 35844465 | E6: 0
A7: б. | B7: Бошқа банклардаги ҳисобварақлар бўйича фоизли даромадлар | C7: =+D7+E7 -> 268881890 | D7: 62413635 | E7: 206468255
A8: в. | B8: Амортизацияланган қиймати бўйича баҳоланадиган қарз қимматли қоғозларга қилинган инвестициялар бўйича фоизли даромадлар | C8: =+D8+E8 -> 1289908 | D8: 1289908 | E8: 0
A9: г. | B9: Қимматли қоғозлар ва уларга қилинган инвестициялар бўйича фоизли даромадлар | C9: =+D9+E9 -> 269037836 | D9: 267075910 | E9: 1961926
A10: д. | B10: Мижозларнинг мажбуриятлари бўйича ҳисобланган фоизлар | C10: =+D10+E10 -> 0 | D10: 0 | E10: 0
A11: е. | B11: Банкнинг тўланмаган акцептлари юзасидан мижозлар мажбуриятлари бўйича фоизли даромадлар | C11: =+D11+E11 -> 0 | D11: 0 | E11: 0
A12: ж. | B12: Кредит ва лизинг операциялари бўйича фоизлар, дисконтлар (чегирмалар) ва бадаллар | C12: =+D12+E12 -> 4591911242 | D12: 2769776100 | E12: 1822135142
A13: з. | B13: Қимматли қоғозлар билан амалга оширилган РЕПО битимлари бўйича фоизли даромадлар | C13: =+D13+E13 -> 0 | D13: 0 | E13: 0
A14: и. | B14: Бошқа фоизли даромадлар | C14: =+D14+E14 -> 218264480 | D14: 95915323 | E14: 122349157
A15: к. | B15: Жами фоизли даромадлар | C15: =SUM(C6:C14) -> 5385229821 | D15: =SUM(D6:D14) -> 3232315341 | E15: =SUM(E6:E14) -> 2152914480 | G15: =+'Analysis of Interest'!C42 -> 5385229821
A17: 2. | B17: ФОИЗЛИ ХAРAЖAТЛAР
A18: а. | B18: Талаб қилиб олингунча сақланадиган депозитлар бўйича фоизли харажатлар | C18: =+D18+E18 -> 6423638 | D18: 5582656 | E18: 840982
A19: б. | B19: Муддатли депозитлар бўйича фоизли харажатлар | C19: =+D19+E19 -> 783151094 | D19: 611953664 | E19: 171197430
A20: в. | B20: Марказий банкнинг ҳисобварақлари бўйича фоизли харажатлар | C20: =+D20+E20 -> 0 | D20: 0 | E20: 0
A21: г. | B21: Бошқа банкларнинг ҳисобварақлари бўйича фоизли харажатлар | C21: =+D21+E21 -> 114525305 | D21: 76606694 | E21: 37918611
A22: д. | B22: Жами депозитлар бўйича фоизли харажатлар | C22: =SUM(C18:C21) -> 904100037 | D22: =SUM(D18:D21) -> 694143014 | E22: =SUM(E18:E21) -> 209957023
A23: е. | B23: Кредитлар бўйича фоизли харажатлар | C23: =+D23+E23 -> 1446893800 | D23: 676650337 | E23: 770243463
A24: ж. | B24: Қимматли қоғозлар билан амалга оширилган РЕПО битимлари бўйича фоизли харажатлар | C24: =+D24+E24 -> 1443836 | D24: 1443836 | E24: 0
A25: з. | B25: Бошқа фоизли харажатлар | C25: =+D25+E25 -> 437549437 | D25: 111482420 | E25: 326067017
A26: и. | B26: Жами кредит ва бошқа қарздорликлар бўйича фоизли харажатлар | C26: =SUM(C23:C25) -> 1885887073 | D26: =SUM(D23:D25) -> 789576593 | E26: =SUM(E23:E25) -> 1096310480
A27: к. | B27: Жами фоизли харажатлар | C27: =C26+C22 -> 2789987110 | D27: =D26+D22 -> 1483719607 | E27: =E26+E22 -> 1306267503 | G27: =+'Analysis of Interest'!C72 -> 2789987110
A29: 3. | B29: Активлар бўйича эҳтимолий йўқотишларга қарши яратилган захираларни баҳолашдан олдинги соф даромад | C29: =C15-C27 -> 2595242711 | D29: =D15-D27 -> 1748595734 | E29: =E15-E27 -> 846646977
A30: а. | B30: Минус: Кредит ва лизинглар бўйича кўрилиши мумкин бўлган зарарларни баҳолаш | C30: =+D30+E30 -> 2008948377 | D30: 425674834 | E30: 1583273543
A31: б. | B31: Минус: Қимматли қоғозлар бўйича кўрилиши мумкин бўлган зарарларни баҳолаш | C31: =+D31+E31 -> 0 | D31: 0 | E31: 0
A32: в. | B32: Минус: Инвестициялар бўйича кўрилиши мумкин бўлган зарарларни баҳолаш | C32: =+D32+E32 -> 1874998 | D32: 1581228 | E32: 293770
A33: г. | B33: Минус: Бошқа активлар бўйича кўрилиши мумкин бўлган зарарларни баҳолаш | C33: =+D33+E33 -> 456006888 | D33: 252820973 | E33: 203185915
A34: д. | B34: Активлар бўйича эҳтимолий зарарларни баҳолашдан кейинги соф даромад | C34: =C29-C30-C31-C32-C33 -> 128412448 | D34: =D29-D30-D31-D32-D33 -> 1068518699 | E34: =E29-E30-E31-E32-E33 -> -940106251
A36: 4. | B36: ФОИЗСИЗ ДАРОМАДЛАР
A37: а. | B37: Кўрсатилган хизматлар ва воситачилик учун олинган даромадлар | C37: =+D37+E37 -> 474409860 | D37: 363862280 | E37: 110547580
A38: б. | B38: Хорижий валюталардаги фойда | C38: =+D38+E38 -> 1042504795 | D38: 189142622 | E38: 853362173
A39: в. | B39: Тижорат операцияларидан олинган фойда | C39: =+D39+E39 -> 0 | D39: 0 | E39: 0
A40: г. | B40: Инвестициядан олинган фойда ва дивидендлар | C40: =+D40+E40 -> 23609691 | D40: 23325363 | E40: 284328
A41: д. | B41: Бошқа фоизсиз даромадлар | C41: =+D41+E41 -> 1355245755 | D41: 567412819 | E41: 787832936
B42: шундан
A43: д1. | B43: Активлар бўйича эҳтимолий йўқотишларга қарши яратилган захираларни қайтарилиши | C43: =+D43+E43 -> 1287422060 | D43: 519119171 | E43: 768302889
A44: д2. | B44: Ҳисобдан чиқарилган кредитлар қайтарилиши билан боғлиқ даромадлар | C44: =+D44+E44 -> 0 | D44: 0 | E44: 0
A45: е. | B45: Жами фоизсиз даромадлар | C45: =SUM(C37:C41) -> 2895770101 | D45: =SUM(D37:D41) -> 1143743084 | E45: =SUM(E37:E41) -> 1752027017
A47: 5. | B47: ФОИЗСИЗ ХАРАЖАТЛАР
A48: а. | B48: Воситачилик ва кўрсатилган хизматлар учун харажатлар | C48: =+D48+E48 -> 207700975 | D48: 122713120 | E48: 84987855
A49: б. | B49: Хорижий валютада кўрилган зарарлар | C49: =+D49+E49 -> 699232326 | D49: 4740798 | E49: 694491528
A50: в. | B50: Тижорат операцияларидан кўрилган зарарлар | C50: =+D50+E50 -> 0 | D50: 0 | E50: 0
A51: г. | B51: Инвестициядан кўрилган зарарлар | C51: =+D51+E51 -> 0 | D51: 0 | E51: 0
A52: д. | B52: Бошқа фоизсиз харажатлар | C52: =+D52+E52 -> 54553149 | D52: 51103109 | E52: 3450040
A53: е. | B53: Жами фоизсиз харажатлар | C53: =SUM(C48:C52) -> 961486450 | D53: =SUM(D48:D52) -> 178557027 | E53: =SUM(E48:E52) -> 782929423
A55: 6. | B55: ОПЕРАЦИОН ХАРАЖАТЛАРДАН ОЛДИНГИ СОФ ДАРОМАД | C55: =C34+C45-C53 -> 2062696099 | D55: =D34+D45-D53 -> 2033704756 | E55: =E34+E45-E53 -> 28991343
A57: 7. | B57: ОПЕРАЦИОН ХАРАЖАТЛАР
A58: а. | B58: Банк хизматчиларига иш ҳақи ва бошқа харажатлар | C58: 811430648 | D58: 811430648
A59: а1) | B59: шундан, раҳбар ходимларга тўловлар | C59: 34945643 | D59: 34945643
A60: б. | B60: Ижара ва таъминот харажатлари | C60: 84194959 | D60: 84194959
A61: в. | B61: Хизмат сафари ва транспорт харажатлари | C61: 13119982 | D61: 13119982
A62: г. | B62: Маъмурий харажатлар | C62: 38506004 | D62: 38506004
A63: д. | B63: Репрезентация ва хайрия | C63: 115193184 | D63: 115193184
A64: е. | B64: Эскириш харажатлари | C64: 88348887 | D64: 88348887
A65: ж. | B65: Суғурта харажатлари | C65: 1606911 | D65: 1606911
A66: з. | B66: Солиқлар (фойда солиғидан ташқари) ва лицензиялар | C66: 50626401 | D66: 50626401
A67: и. | B67: Жарима ва пенялар | C67: 883001 | D67: 883001
A68: к. | B68: Бошқа операцион харажатлар | C68: 37021253 | D68: 37021253
A69: л. | B69: Жами операцион харажатлар | C69: =SUM(C58:C68)-C59 -> 1240931230 | D69: =SUM(D58:D68)-D59 -> 1240931230
A71: 8. | B71: Солиқ тўлангунга қадар соф фойда ва бошқа тузатишлар | C71: =C55-C69 -> 821764869 | D71: =D55-D69 -> 792773526 | E71: =+E55-(C69-D69) -> 28991343
A72: а. | B72: Фойда солиғини баҳолаш | C72: =+D72+E72 -> 232827820 | D72: 232827820
A74: 9. | B74: ТУЗАТИШЛАР КИРИТИЛГУНГА ҚАДАР ДАРОМАД | C74: =C71-C72 -> 588937049 | D74: =D71-D72 -> 559945706 | E74: =E71-E72 -> 28991343
A75: а. | B75: Кўзда тутилмаган даромад ёки зарарлар, соф | C75: =+D75+E75 -> 0 | D75: 0 | E75: 0
A76: б. | B76: Фойда бўйича тузатишлар, соф | C76: =+D76+E76 -> 0 | D76: 0 | E76: 0
A78: 10. | B78: СОФ ФОЙДА (ЗАРАР) | C78: =C74+C75+C76 -> 588937049 | D78: =D74+D75+D76 -> 559945706 | E78: =E74+E75+E76 -> 28991343
B80: Бошқарув Раис имзоси:
B82: Бош бухгалтер имзоси:

Sheet Analysis of Interest
B1: ФОИЗЛИ ДАРОМАД ВА ХАРАЖАТЛАР ТАҲЛИЛИ | C1: 4-жадвал
B3: =+'Asset quality'!B3 -> "Ўзсаноатқурилишбанк" АТБ | C3: =+'Asset quality'!Q3 -> 44925
A4: № | B4: Кўрсаткичлар | C4: =+'Asset quality'!T3 -> минг. сўмда
A5: 1. | B5: КРЕДИТ ВА ЛИЗИНГ ОПЕРАЦИЯЛАРИ БЎЙИЧА ФОИЗЛИ ДАРОМАДЛАР
A6: a. | B6: Марказий банкка берилган қисқа муддатли кредитлар | C6: 0
A7: б. | B7: Бошқа банкларга берилган кредитлар | C7: 0
A8: в. | B8: Ҳукуматга берилган кредитлар | C8: 4173
A9: г. | B9: Жисмоний шахсларга берилган кредит ва лизинглар | C9: 670526003
A10: д. | B10: Давлат корхоналарига берилган кредит ва лизинглар | C10: 901937445
A11: е. | B11: Қўшма ва чет эл капитали иштирокидаги корхоналарга берилган кредит ва лизинглар | C11: 695588564
A12: ж. | B12: Хусусий корхоналар, хўжалик ширкатлари ва жамиятларга берилган кредит ва лизинглар | C12: 2274341091
A13: з. | B13: Бошқа кредит ва лизинглар | C13: 49513966
A14: и. | B14: Жами кредит ва лизинг операциялари бўйича фоизли даромад | C14: =SUM(C6:C13) -> 4591911242
A16: 2. | B16: ВАКИЛЛИК ҲИСОБВАРАҚЛАРИ БЎЙИЧА ФОИЗЛИ ДАРОМАДЛАР
A17: a. | B17: Марказий банкдаги ҳисобварақлар бўйича фоизли даромадлар | C17: 35844465
A18: б. | B18: Бошқа банклардаги ҳисобварақлар бўйича фоизли даромадлар | C18: 268881890
B19: Жами вакиллик ҳисобварағи бўйича фоизли даромадлар | C19: =SUM(C17:C18) -> 304726355
A21: 3. | B21: ҚИММАТЛИ ҚОҒОЗЛАР ВА УЛАРГА ҚИЛИНГАН ИНВЕСТИЦИЯЛАР БЎЙИЧА ФОИЗЛИ ДАРОМАДЛАР
A22: a. | B22: Давлат қимматли қоғозлари | C22: 102223104
A23: б. | B23: Марказий банкнинг облигациялари ва бошқа қимматли қоғозлари | C23: 166814732
A24: в. | B24: Давлат корхоналарининг қарз қимматли қоғозлари бўйича фоизли даромадлар | C24: 0
A25: г. | B25: Еврооблигациялар бўйича фоизли даромадлар | C25: 0
A26: д. | B26: Хусусий корхоналарнинг қимматли қоғозлари | C26: 0
A27: е. | B27: Бошқа қимматли қоғозлар | C27: 0
A28: ж. | B28: Жами олди-сотди қимматли қоғозлар бўйича фоизли даромадлар | C28: =SUM(C22:C27) -> 269037836
A30: 4. | B30: ИНВЕСТИЦИЯЛАР БЎЙИЧА ФОИЗЛИ ДАРОМАДЛАР
A31: a. | B31: Давлат қимматли қоғозлари | C31: 0
A32: б. | B32: Марказий банкнинг облигациялари ва бошқа қарз қимматли қоғозларига қилинган инвестициялар бўйича фоизли даромадлар | C32: 0
A33: в. | B33: Корхоналарнинг қарз қимматли қоғозларига қилинган инвестициялар бўйича фоизли даромадлар | C33: 1289908
A34: г. | B34: Еврооблигациялар | C34: 0
A35: д. | B35: Бошқа қимматли қоғозлар | C35: 0
A36: е. | B36: Жами инвестициялар бўйича фоизли даромадлар | C36: =SUM(C31:C35) -> 1289908
A38: 5. | B38: БОШҚА ФОИЗЛИ ДАРОМАДЛАР
A39: a. | B39: Қимматли қоғозлар билан амалга оширилган репо битимлари бўйича фоизли даромадлар | C39: 0
A40: б. | B40: Бошқа фоизли даромадлар | C40: 218264480
A42: 6. | B42: ЖАМИ ФОИЗЛИ ДАРОМАДЛАР | C42: =C14+C19+C28+C36+C39+C40 -> 5385229821
A44: 7. | B44: ДЕПОЗИТЛАР БЎЙИЧА ФОИЗЛИ ХАРАЖАТЛАР
A45: A. | B45: Талаб қилиб олингунча сақланадиган депозитлар
A46: a. | B46: Ҳукумат | C46: 4254521
A47: б. | B47: Жисмоний шахслар | C47: 0
A48: в. | B48: Давлат корхоналари | C48: 2169117
A49: г. | B49: Қўшма ва чет эл капитали иштирокидаги корхоналар | C49: 0
A50: д. | B50: Хусусий корхоналар | C50: 0
A51: е. | B51: Бошқа депозитлар | C51: 0
A52: ж. | B52: Жами талаб қилиб олингунча сақланадиган депозитлар бўйича фоизли харажатлар | C52: =SUM(C46:C51) -> 6423638
A54: Б. | B54: Муддатли депозитлар
A55: a. | B55: Ҳукумат | C55: 281418038
A56: б. | B56: Жисмоний шахслар | C56: 415224021
A57: в. | B57: Давлат корхоналари | C57: 7101747
A58: г. | B58: Қўшма ва чет эл капитали иштирокидаги корхоналар | C58: 59032611
A59: д. | B59: Хусусий корхоналар | C59: 8258724
A60: е. | B60: Бошқа депозитлар | C60: 12115953
A61: ж. | B61: Жами муддатли депозитлар бўйича фоизли харажатлар | C61: =SUM(C55:C60) -> 783151094
A63: В. | B63: ЖАМИ ДЕПОЗИТЛАР БЎЙИЧА ФОИЗЛИ ХАРАЖАТЛАР | C63: =C52+C61 -> 789574732
A65: 8. | B65: БОШҚА МАЖБУРИЯТЛАР БЎЙИЧА ФОИЗЛИ ХАРАЖАТЛАР
A66: а. | B66: Банкнинг тўланмаган акцептлари бўйича фоизли харажатлари | C66: 0
A67: б. | B67: Кредитлар бўйича фоизли харажатлар | C67: 1446893800
A68: в. | B68: Қимматли қоғозлар билан амалга оширилган РЕПО битимлари бўйича фоизли харажатлар | C68: 1443836
A69: г. | B69: Бошқа фоизли харажатлар | C69: 552074742
A70: д. | B70: Жами бошқa мажбуриятлар бўйича фоизли хaрaжaтлaр | C70: =SUM(C66:C69) -> 2000412378
A72: 9. | B72: ЖАМИ ФОИЗЛИ ХAРAЖAТЛAР | C72: =C63+C70 -> 2789987110
B74: Бошқарув Раис имзоси:
B76: Бош бухгалтер имзоси:

Sheet Changes in Equity
A1: ХУСУСИЙ КАПИТАЛДАГИ ЎЗГАРИШЛАР | C1: 7-жадвал
B3: =+'Asset quality'!B3 -> "Ўзсаноатқурилишбанк" АТБ | C3: =+'Asset quality'!Q3 -> 44925
A4: № | B4: Кўрсаткичлар | C4: =+'Asset quality'!T3 -> минг. сўмда
A5: 1. | B5: Ўтган йил учун дастлабки ҳисобланган умумий капитал | C5: 7700913106
A6: 2. | B6: Хусусий капиталдаги ўтган йил учун ҳисоботларда кўрсатилмаган тузатишлар, (соф) | C6: 0
A7: 3. | B7: Ўтган календар йили якуни бўйича балансдаги тузатишлар (3=1-2 ) | C7: =SUM(C5:C6) -> 7700913106
A8: 4. | B8: Йил бошидан соф фойда (зарар) | C8: =+'Income '!C78 -> 588937049 | D8: =+[8]Balance!$C$77 -> 588937049 | E8: =+C8-D8 -> 0
A9: 5. | B9: Жорий йилда сотиш, айирбошлаш, сотиб олиш ёки қайтиб сотиб олиш (соф кирим)
A10: 6. | B10: Жорий йил учун бошланғич қийматига нисбатан баҳолаш қийматининг ошган суммаси | C10: -1001834
A11: 7. | B11: МИНУС: Имтиёзли акциялар бўйича эълон қилинган пул дивидендлари | C11: 1616900
A12: 8. | B12: МИНУС: Оддий акциялар бўйича эълон қилинган пуллик дивидендлар
A13: 9. | B13: Жорий йилнинг соф хусусий капиталига таъсир этувчи бошқа моддалар | C13: -459110228
A14: 10. | B14: Жорий давр якуни бўйича жами хусусий капитал | C14: =C7+SUM(C8:C10)-SUM(C11:C12)+C13 -> 7828121193 | D14: =+[8]Balance!$C$78 -> 7828121193 | E14: =+C14-D14 -> 0
B16: Бошқарув Раис имзоси:
B18: Бош бухгалтер имзоси:

Sheet Loans Receivable
A1: ИҚТИСОДИЁТ ТАРМОҚЛАРИ, МИЖОЗЛАР ТУРЛАРИ, ВА ТАЪМИНОТ ТУРЛАРИ БЎЙИЧА АЖРАТИЛГАН КРЕДИТЛАР ВА ЛИЗИНГЛАР ҲИСОБОТИ | W1: 8-жадвал
B3: =+'Asset quality'!B3 -> "Ўзсаноатқурилишбанк" АТБ | T3: =+'Asset quality'!Q3 -> 44925 | X3: =+'Asset quality'!T3 -> минг. сўмда
A4: № | B4: Иқтисодиёт тармоқлари бўйича | C4: Кредит суммаси | D4: шундан | F4: шундан муаммоли кредитлар | J4: шундан
D5: миллий валютада | E5: хорижий валютада (экв. сўмда) | F5: NPL | G5: шундан | J5: Депозитлар | K5: Ўзбекистон Республикаси Ҳукумати тамонидан кафолатланган кредитлар | L5: шундан | M5: Транспорт воситалари | N5: Инвентарлар | O5: Кўчмас мулк | P5: шундан | R5: Асбоб ускуналар | S5: Векселлар (облигациялар) | T5: Акциялар | U5: Учинчи шахс кафолати | V5: Учинчи шахс кафиллиги | W5: Суғурта полиси | X5: Таъминотсиз | Y5: Бошқа кафолатлар
G6: Қониқарсиз | H6: Шубҳали | I6: Умидсиз | L6: Ўзбекистон Республикаси Ҳукумати томонидан кафолатланган хорижий валютадаги (эквивалент сўмда) кредитлар | P6: турар жой (хонадон) | Q6: тижорат кўчмас мулки
A7: Код | B7: (А) | C7: (Б) | D7: (Б1) | E7: (Б3) | F7: (В) | G7: (В1) | H7: (В2) | I7: (В3) | J7: (Г) | K7: (Д) | L7: (Д1) | M7: (Е) | N7: (Ж) | O7: (З) | P7: (З1) | Q7: (З2) | R7: (И) | S7: (К) | T7: (Л) | U7: (М) | V7: (Н) | W7: (О) | X7: (П) | Y7: (Р)
B8: Саноат
A9: 10 | B9: Давлат корхоналари | C9: =SUM(J9:Y9)-L9-P9-Q9 -> 9559065439 | D9: 2992378874 | E9: 6566686565 | F9: =+G9+H9+I9 -> 0 | G9: 0 | H9: 0 | I9: 0 | J9: 0 | K9: 5110248432 | L9: 4404306552 | M9: 2579996 | N9: 104883818 | O9: =+P9+Q9 -> 55561125 | P9: 0 | Q9: 55561125 | R9: 661917992 | S9: 0 | T9: 135469078 | U9: 0 | V9: 1914735664 | W9: 4024826 | X9: 991196 | Y9: 1568653312
A10: =A9+10 -> 20 | B10: Қўшма ва чет эл капитали иштирокидаги корхоналар | C10: =SUM(J10:Y10)-L10-P10-Q10 -> 6958698729 | D10: 621062088 | E10: 6337636641 | F10: =+G10+H10+I10 -> 344600281 | G10: 46812333 | H10: 288718899 | I10: 9069049 | J10: 561273 | K10: 0 | L10: 0 | M10: 9913428 | N10: 184799033 | O10: =+P10+Q10 -> 1490965564 | P10: 4855793 | Q10: 1486109771 | R10: 2388920405 | S10: 0 | T10: 0 | U10: 0 | V10: 849084580 | W10: 738362324 | X10: 0 | Y10: 1296092122
A11: =A10+10 -> 30 | B11: Хусусий корхоналар | C11: =SUM(J11:Y11)-L11-P11-Q11 -> 9455672521 | D11: 1907106967 | E11: 7548565554 | F11: =+G11+H11+I11 -> 429545142 | G11: 136589558 | H11: 270073650 | I11: 22881934 | J11: 36176 | K11: 0 | L11: 0 | M11: 66396915 | N11: 27988346 | O11: =+P11+Q11 -> 2599824005 | P11: 27105904 | Q11: 2572718101 | R11: 1118503607 | S11: 0 | T11: 0 | U11: 0 | V11: 4862465700 | W11: 556796471 | X11: 0 | Y11: 223661301
A12: =A11+10 -> 40 | B12: Ҳукумат | C12: =SUM(J12:Y12)-L12-P12-Q12 -> 0 | D12: 0 | E12: 0 | F12: =+G12+H12+I12 -> 0 | G12: 0 | H12: 0 | I12: 0 | J12: 0 | K12: 0 | L12: 0 | M12: 0 | N12: 0 | O12: =+P12+Q12 -> 0 | P12: 0 | Q12: 0 | R12: 0 | S12: 0 | T12: 0 | U12: 0 | V12: 0 | W12: 0 | X12: 0 | Y12: 0
A13: =A12+10 -> 50 | B13: Бошқалар | C13: =SUM(J13:Y13)-L13-P13-Q13 -> 0 | D13: 0 | E13: 0 | F13: =+G13+H13+I13 -> 0 | G13: 0 | H13: 0 | I13: 0 | J13: 0 | K13: 0 | L13: 0 | M13: 0 | N13: 0 | O13: =+P13+Q13 -> 0 | P13: 0 | Q13: 0 | R13: 0 | S13: 0 | T13: 0 | U13: 0 | V13: 0 | W13: 0 | X13: 0 | Y13: 0
A14: =A13+10 -> 60 | B14: Жами | C14: =SUM(J14:Y14)-L14-P14-Q14 -> 25973436689 | D14: =SUM(D9:D13) -> 5520547929 | E14: =SUM(E9:E13) -> 20452888760 | F14: =+G14+H14+I14 -> 774145423 | G14: =SUM(G9:G13) -> 183401891 | H14: =SUM(H9:H13) -> 558792549 | I14: =SUM(I9:I13) -> 31950983 | J14: =SUM(J9:J13) -> 597449 | K14: =SUM(K9:K13) -> 5110248432 | L14: =SUM(L9:L13) -> 4404306552 | M14: =SUM(M9:M13) -> 78890339 | N14: =SUM(N9:N13) -> 317671197 | ... Y14: =SUM(Y9:Y13) -> 3088406735
B15: Қишлоқ хўжалиги
A16: 70 | B16: Давлат корхоналари | C16: =SUM(J16:Y16)-L16-P16-Q16 -> 0 | D16: 0 | E16: 0 | F16: =+G16+H16+I16 -> 0 | G16: 0 | H16: 0 | I16: 0 | J16: 0 | K16: 0 | L16: 0 | M16: 0 | N16: 0 | O16: =+P16+Q16 -> 0 | P16: 0 | Q16: 0 | R16: 0 | S16: 0 | T16: 0 | U16: 0 | V16: 0 | W16: 0 | X16: 0 | Y16: 0
A17: =A16+10 -> 80 | B17: Қўшма ва чет эл капитали иштирокидаги корхоналар | C17: =SUM(J17:Y17)-L17-P17-Q17 -> 838902053 | D17: 402022799 | E17: 436879254 | F17: =+G17+H17+I17 -> 32971304 | G17: 19024038 | H17: 13947266 | I17: 0 | J17: 0 | K17: 0 | L17: 0 | M17: 14478125 | N17: 0 | O17: =+P17+Q17 -> 358052465 | P17: 2478414 | Q17: 355574051 | R17: 144725800 | S17: 0 | T17: 0 | U17: 0 | V17: 92397841 | W17: 229247822 | X17: 0 | Y17: 0
A18: =A17+10 -> 90 | B18: Хусусий корхоналар | C18: =SUM(J18:Y18)-L18-P18-Q18 -> 3470971636 | D18: 1885540800 | E18: 1585430836 | F18: =+G18+H18+I18 -> 70014262 | G18: 10087312 | H18: 49837815 | I18: 10089135 | J18: 250000 | K18: 0 | L18: 0 | M18: 39177304 | N18: 0 | O18: =+P18+Q18 -> 705114499 | P18: 25260544 | Q18: 679853955 | R18: 248869958 | S18: 0 | T18: 0 | U18: 0 | V18: 1687360502 | W18: 787230913 | X18: 0 | Y18: 2968460
A19: =A18+10 -> 100 | B19: Фермер хўжалиги | C19: =SUM(J19:Y19)-L19-P19-Q19 -> 171788067 | D19: 69222758 | E19: 102565309 | F19: =+G19+H19+I19 -> 37243840 | G19: 9188880 | H19: 16591663 | I19: 11463297 | J19: 0 | K19: 0 | L19: 0 | M19: 3948793 | N19: 0 | O19: =+P19+Q19 -> 67131807 | P19: 1760740 | Q19: 65371067 | R19: 23770438 | S19: 0 | T19: 0 | U19: 0 | V19: 74042509 | W19: 2894520 | X19: 0 | Y19: 0
A20: =A19+10 -> 110 | B20: Ҳукумат | C20: =SUM(J20:Y20)-L20-P20-Q20 -> 0 | D20: 0 | E20: 0 | F20: =+G20+H20+I20 -> 0 | G20: 0 | H20: 0 | I20: 0 | J20: 0 | K20: 0 | L20: 0 | M20: 0 | N20: 0 | O20: =+P20+Q20 -> 0 | P20: 0 | Q20: 0 | R20: 0 | S20: 0 | T20: 0 | U20: 0 | V20: 0 | W20: 0 | X20: 0 | Y20: 0
A21: =A20+10 -> 120 | B21: Бошқалар | C21: =SUM(J21:Y21)-L21-P21-Q21 -> 0 | D21: 0 | E21: 0 | F21: =+G21+H21+I21 -> 0 | G21: 0 | H21: 0 | I21: 0 | J21: 0 | K21: 0 | L21: 0 | M21: 0 | N21: 0 | O21: =+P21+Q21 -> 0 | P21: 0 | Q21: 0 | R21: 0 | S21: 0 | T21: 0 | U21: 0 | V21: 0 | W21: 0 | X21: 0 | Y21: 0
A22: =A21+10 -> 130 | B22: Жами | C22: =SUM(J22:Y22)-L22-P22-Q22 -> 4481661756 | D22: =SUM(D16:D21) -> 2356786357 | E22: =SUM(E16:E21) -> 2124875399 | F22: =+G22+H22+I22 -> 140229406 | G22: =SUM(G17:G21) -> 38300230 | H22: =SUM(H17:H21) -> 80376744 | I22: =SUM(I17:I21) -> 21552432 | J22: =SUM(J16:J21) -> 250000 | K22: =SUM(K16:K21) -> 0 | L22: =SUM(L16:L21) -> 0 | M22: =SUM(M16:M21) -> 57604222 | N22: =SUM(N16:N21) -> 0 | O22: =SUM(O16:O21) -> 1130298771 | P22: =SUM(P16:P21) -> 29499698 | Q22: =SUM(Q16:Q21) -> 1100799073 | ... Y22: =SUM(Y16:Y21) -> 2968460
B23: Транспорт ва коммуникация
A24: 140 | B24: Давлат корхоналари | C24: =SUM(J24:Y24)-L24-P24-Q24 -> 2946182415 | D24: 4183369 | E24: 2941999046 | F24: =+G24+H24+I24 -> 0 | G24: 0 | H24: 0 | I24: 0 | J24: 958841375 | K24: 1514601374 | L24: 1514601374 | M24: 0 | N24: 0 | O24: =+P24+Q24 -> 281000 | P24: 0 | Q24: 281000 | R24: 40179434 | S24: 0 | T24: 0 | U24: 0 | V24: 432279232 | W24: 0 | X24: 0 | Y24: 0
A25: =A24+10 -> 150 | B25: Қўшма ва чет эл капитали иштирокидаги корхоналар | C25: =SUM(J25:Y25)-L25-P25-Q25 -> 0 | D25: 0 | E25: 0 | F25: =+G25+H25+I25 -> 0 | G25: 0 | H25: 0 | I25: 0 | J25: 0 | K25: 0 | L25: 0 | M25: 0 | N25: 0 | O25: =+P25+Q25 -> 0 | P25: 0 | Q25: 0 | R25: 0 | S25: 0 | T25: 0 | U25: 0 | V25: 0 | W25: 0 | X25: 0 | Y25: 0
A26: =A25+10 -> 160 | B26: Хусусий корхоналар | C26: =SUM(J26:Y26)-L26-P26-Q26 -> 559117995 | D26: 150846747 | E26: 408271248 | F26: =+G26+H26+I26 -> 31632641 | G26: 8383679 | H26: 13866148 | I26: 9382814 | J26: 0 | K26: 0 | L26: 0 | M26: 48382688 | N26: 0 | O26: =+P26+Q26 -> 281442114 | P26: 2296906 | Q26: 279145208 | R26: 33280781 | S26: 0 | T26: 0 | U26: 0 | V26: 165058278 | W26: 30954134 | X26: 0 | Y26: 0
A27: =A26+10 -> 170 | B27: Ҳукумат | C27: =SUM(J27:Y27)-L27-P27-Q27 -> 0 | D27: 0 | E27: 0 | F27: =+G27+H27+I27 -> 0 | G27: 0 | H27: 0 | I27: 0 | J27: 0 | K27: 0 | L27: 0 | M27: 0 | N27: 0 | O27: =+P27+Q27 -> 0 | P27: 0 | Q27: 0 | R27: 0 | S27: 0 | T27: 0 | U27: 0 | V27: 0 | W27: 0 | X27: 0 | Y27: 0
A28: =A27+10 -> 180 | B28: Бошқалар | C28: =SUM(J28:Y28)-L28-P28-Q28 -> 0 | D28: 0 | E28: 0 | F28: =+G28+H28+I28 -> 0 | G28: 0 | H28: 0 | I28: 0 | J28: 0 | K28: 0 | L28: 0 | M28: 0 | N28: 0 | O28: =+P28+Q28 -> 0 | P28: 0 | Q28: 0 | R28: 0 | S28: 0 | T28: 0 | U28: 0 | V28: 0 | W28: 0 | X28: 0 | Y28: 0
A29: =A28+10 -> 190 | B29: Жами | C29: =SUM(J29:Y29)-L29-P29-Q29 -> 3505300410 | D29: =SUM(D24:D28) -> 155030116 | E29: =SUM(E24:E28) -> 3350270294 | F29: =+G29+H29+I29 -> 31632641 | G29: =SUM(G24:G28) -> 8383679 | H29: =SUM(H24:H28) -> 13866148 | I29: =SUM(I24:I28) -> 9382814 | J29: =SUM(J24:J28) -> 958841375 | K29: =SUM(K24:K28) -> 1514601374 | L29: =SUM(L24:L28) -> 1514601374 | M29: =SUM(M24:M28) -> 48382688 | N29: =SUM(N24:N28) -> 0 | ... Y29: =SUM(Y24:Y28) -> 0
B30: Қурилиш соҳаси
A31: 200 | B31: Давлат корхоналари | C31: =SUM(J31:Y31)-L31-P31-Q31 -> 0 | D31: 0 | E31: 0 | F31: =+G31+H31+I31 -> 0 | G31: 0 | H31: 0 | I31: 0 | J31: 0 | K31: 0 | L31: 0 | M31: 0 | N31: 0 | O31: =+P31+Q31 -> 0 | P31: 0 | Q31: 0 | R31: 0 | S31: 0 | T31: 0 | U31: 0 | V31: 0 | W31: 0 | X31: 0 | Y31: 0
A32: =A31+10 -> 210 | B32: Қўшма ва чет эл капитали иштирокидаги корхоналар | C32: =SUM(J32:Y32)-L32-P32-Q32 -> 50217990 | D32: 51106 | E32: 50166884 | F32: =+G32+H32+I32 -> 0 | G32: 0 | H32: 0 | I32: 0 | J32: 0 | K32: 0 | L32: 0 | M32: 2325361 | N32: 0 | O32: =+P32+Q32 -> 32449763 | P32: 0 | Q32: 32449763 | R32: 3415018 | S32: 0 | T32: 0 | U32: 0 | V32: 11786898 | W32: 240950 | X32: 0 | Y32: 0
A33: =A32+10 -> 220 | B33: Хусусий корхоналар | C33: =SUM(J33:Y33)-L33-P33-Q33 -> 1261005857 | D33: 518177848 | E33: 742828009 | F33: =+G33+H33+I33 -> 106874131 | G33: 3404956 | H33: 100045006 | I33: 3424169 | J33: 111077 | K33: 0 | L33: 0 | M33: 32040088 | N33: 172080 | O33: =+P33+Q33 -> 383012929 | P33: 20142780 | Q33: 362870149 | R33: 31732933 | S33: 0 | T33: 0 | U33: 0 | V33: 732626027 | W33: 74348968 | X33: 0 | Y33: 6961755
A34: =A33+10 -> 230 | B34: Ҳукумат | C34: =SUM(J34:Y34)-L34-P34-Q34 -> 0 | D34: 0 | E34: 0 | F34: =+G34+H34+I34 -> 0 | G34: 0 | H34: 0 | I34: 0 | J34: 0 | K34: 0 | L34: 0 | M34: 0 | N34: 0 | O34: =+P34+Q34 -> 0 | P34: 0 | Q34: 0 | R34: 0 | S34: 0 | T34: 0 | U34: 0 | V34: 0 | W34: 0 | X34: 0 | Y34: 0
A35: =A34+10 -> 240 | B35: Бошқалар | C35: =SUM(J35:Y35)-L35-P35-Q35 -> 0 | D35: 0 | E35: 0 | F35: =+G35+H35+I35 -> 0 | G35: 0 | H35: 0 | I35: 0 | J35: 0 | K35: 0 | L35: 0 | M35: 0 | N35: 0 | O35: =+P35+Q35 -> 0 | P35: 0 | Q35: 0 | R35: 0 | S35: 0 | T35: 0 | U35: 0 | V35: 0 | W35: 0 | X35: 0 | Y35: 0
A36: =A35+10 -> 250 | B36: Жами | C36: =SUM(J36:Y36)-L36-P36-Q36 -> 1311223847 | D36: =SUM(D31:D35) -> 518228954 | E36: =SUM(E31:E35) -> 792994893 | F36: =+G36+H36+I36 -> 106874131 | G36: =SUM(G31:G35) -> 3404956 | H36: =SUM(H31:H35) -> 100045006 | I36: =SUM(I31:I35) -> 3424169 | J36: =SUM(J31:J35) -> 111077 | K36: =SUM(K31:K35) -> 0 | L36: =SUM(L31:L35) -> 0 | M36: =SUM(M31:M35) -> 34365449 | N36: =SUM(N31:N35) -> 172080 | ... Y36: =SUM(Y31:Y35) -> 6961755
B37: Савдо ва умумий хизмат
A38: 260 | B38: Давлат корхоналари | C38: =SUM(J38:Y38)-L38-P38-Q38 -> 400000 | D38: 400000 | E38: 0 | F38: =+G38+H38+I38 -> 0 | G38: 0 | H38: 0 | I38: 0 | J38: 0 | K38: 0 | L38: 0 | M38: 0 | N38: 0 | O38: =+P38+Q38 -> 400000 | P38: 0 | Q38: 400000 | R38: 0 | S38: 0 | T38: 0 | U38: 0 | V38: 0 | W38: 0 | X38: 0 | Y38: 0
A39: =A38+10 -> 270 | B39: Қўшма ва чет эл капитали иштирокидаги корхоналар | C39: =SUM(J39:Y39)-L39-P39-Q39 -> 232072283 | D39: 3666673 | E39: 228405610 | F39: =+G39+H39+I39 -> 176151 | G39: 176151 | H39: 0 | I39: 0 | J39: 0 | K39: 0 | L39: 0 | M39: 2677448 | N39: 0 | O39: =+P39+Q39 -> 111780563 | P39: 0 | Q39: 111780563 | R39: 10625758 | S39: 0 | T39: 0 | U39: 0 | V39: 73169728 | W39: 33818786 | X39: 0 | Y39: 0
A40: =A39+10 -> 280 | B40: Хусусий корхоналар | C40: =SUM(J40:Y40)-L40-P40-Q40 -> 2656484827 | D40: 818723732 | E40: 1837761095 | F40: =+G40+H40+I40 -> 155857839 | G40: 112833422 | H40: 33775945 | I40: 9248472 | J40: 150000 | K40: 0 | L40: 0 | M40: 49897108 | N40: 138064027 | O40: =+P40+Q40 -> 1086573961 | P40: 14170538 | Q40: 1072403423 | R40: 132269678 | S40: 0 | T40: 0 | U40: 0 | V40: 894155650 | W40: 355368844 | X40: 0 | Y40: 5559
A41: =A40+10 -> 290 | B41: Ҳукумат | C41: =SUM(J41:Y41)-L41-P41-Q41 -> 0 | D41: 0 | E41: 0 | F41: =+G41+H41+I41 -> 0 | G41: 0 | H41: 0 | I41: 0 | J41: 0 | K41: 0 | L41: 0 | M41: 0 | N41: 0 | O41: =+P41+Q41 -> 0 | P41: 0 | Q41: 0 | R41: 0 | S41: 0 | T41: 0 | U41: 0 | V41: 0 | W41: 0 | X41: 0 | Y41: 0
A42: =A41+10 -> 300 | B42: Бошқалар | C42: =SUM(J42:Y42)-L42-P42-Q42 -> 0 | D42: 0 | E42: 0 | F42: =+G42+H42+I42 -> 0 | G42: 0 | H42: 0 | I42: 0 | J42: 0 | K42: 0 | L42: 0 | M42: 0 | N42: 0 | O42: =+P42+Q42 -> 0 | P42: 0 | Q42: 0 | R42: 0 | S42: 0 | T42: 0 | U42: 0 | V42: 0 | W42: 0 | X42: 0 | Y42: 0
A43: =A42+10 -> 310 | B43: Жами | C43: =SUM(J43:Y43)-L43-P43-Q43 -> 2888957110 | D43: =SUM(D38:D42) -> 822790405 | E43: =SUM(E38:E42) -> 2066166705 | F43: =+G43+H43+I43 -> 156033990 | G43: =SUM(G38:G42) -> 113009573 | H43: =SUM(H38:H42) -> 33775945 | I43: =SUM(I38:I42) -> 9248472 | J43: =SUM(J38:J42) -> 150000 | K43: =SUM(K38:K42) -> 0 | L43: =SUM(L38:L42) -> 0 | M43: =SUM(M38:M42) -> 52574556 | N43: =SUM(N38:N42) -> 138064027 | ... Y43: =SUM(Y38:Y42) -> 5559
B44: Моддий ва техник таъминотни ривожлантириш
A45: 320 | B45: Давлат корхоналари | C45: =SUM(J45:Y45)-L45-P45-Q45 -> 1216229604 | D45: 1216229604 | E45: 0 | F45: =+G45+H45+I45 -> 0 | G45: 0 | H45: 0 | I45: 0 | J45: 0 | K45: 0 | L45: 0 | M45: 0 | N45: 0 | O45: =+P45+Q45 -> 0 | P45: 0 | Q45: 0 | R45: 3468333 | S45: 0 | T45: 0 | U45: 0 | V45: 36118127 | W45: 0 | X45: 283941159 | Y45: 892701985
A46: =A45+10 -> 330 | B46: Қўшма ва чет эл капитали иштирокидаги корхоналар | C46: =SUM(J46:Y46)-L46-P46-Q46 -> 0 | D46: 0 | E46: 0 | F46: =+G46+H46+I46 -> 0 | G46: 0 | H46: 0 | I46: 0 | J46: 0 | K46: 0 | L46: 0 | M46: 0 | N46: 0 | O46: =+P46+Q46 -> 0 | P46: 0 | Q46: 0 | R46: 0 | S46: 0 | T46: 0 | U46: 0 | V46: 0 | W46: 0 | X46: 0 | Y46: 0
A47: =A46+10 -> 340 | B47: Хусусий корхоналар | C47: =SUM(J47:Y47)-L47-P47-Q47 -> 110338547 | D47: 85328005 | E47: 25010542 | F47: =+G47+H47+I47 -> 9105859 | G47: 9105859 | H47: 0 | I47: 0 | J47: 0 | K47: 0 | L47: 0 | M47: 3437759 | N47: 0 | O47: =+P47+Q47 -> 34341233 | P47: 1079468 | Q47: 33261765 | R47: 8473749 | S47: 0 | T47: 0 | U47: 0 | V47: 35538580 | W47: 28547226 | X47: 0 | Y47: 0
A48: =A47+10 -> 350 | B48: Ҳукумат | C48: =SUM(J48:Y48)-L48-P48-Q48 -> 0 | D48: 0 | E48: 0 | F48: =+G48+H48+I48 -> 0 | G48: 0 | H48: 0 | I48: 0 | J48: 0 | K48: 0 | L48: 0 | M48: 0 | N48: 0 | O48: =+P48+Q48 -> 0 | P48: 0 | Q48: 0 | R48: 0 | S48: 0 | T48: 0 | U48: 0 | V48: 0 | W48: 0 | X48: 0 | Y48: 0
A49: =A48+10 -> 360 | B49: Бошқалар | C49: =SUM(J49:Y49)-L49-P49-Q49 -> 0 | D49: 0 | E49: 0 | F49: =+G49+H49+I49 -> 0 | G49: 0 | H49: 0 | I49: 0 | J49: 0 | K49: 0 | L49: 0 | M49: 0 | N49: 0 | O49: =+P49+Q49 -> 0 | P49: 0 | Q49: 0 | R49: 0 | S49: 0 | T49: 0 | U49: 0 | V49: 0 | W49: 0 | X49: 0 | Y49: 0
A50: =A49+10 -> 370 | B50: Жами | C50: =SUM(J50:Y50)-L50-P50-Q50 -> 1326568151 | D50: =SUM(D45:D49) -> 1301557609 | E50: =SUM(E45:E49) -> 25010542 | F50: =+G50+H50+I50 -> 9105859 | G50: =SUM(G45:G49) -> 9105859 | H50: =SUM(H45:H49) -> 0 | I50: =SUM(I45:I49) -> 0 | J50: =SUM(J45:J49) -> 0 | K50: =SUM(K45:K49) -> 0 | L50: =SUM(L45:L49) -> 0 | M50: =SUM(M45:M49) -> 3437759 | N50: =SUM(N45:N49) -> 0 | ... Y50: =SUM(Y45:Y49) -> 892701985
B51: Уй-жой коммунал хизмати
A52: 380 | B52: Давлат корхоналари | C52: =SUM(J52:Y52)-L52-P52-Q52 -> 0 | D52: 0 | E52: 0 | F52: =+G52+H52+I52 -> 0 | G52: 0 | H52: 0 | I52: 0 | J52: 0 | K52: 0 | L52: 0 | M52: 0 | N52: 0 | O52: =+P52+Q52 -> 0 | P52: 0 | Q52: 0 | R52: 0 | S52: 0 | T52: 0 | U52: 0 | V52: 0 | W52: 0 | X52: 0 | Y52: 0
A53: =A52+10 -> 390 | B53: Қўшма ва чет эл капитали иштирокидаги корхоналар | C53: =SUM(J53:Y53)-L53-P53-Q53 -> 0 | D53: 0 | E53: 0 | F53: =+G53+H53+I53 -> 0 | G53: 0 | H53: 0 | I53: 0 | J53: 0 | K53: 0 | L53: 0 | M53: 0 | N53: 0 | O53: =+P53+Q53 -> 0 | P53: 0 | Q53: 0 | R53: 0 | S53: 0 | T53: 0 | U53: 0 | V53: 0 | W53: 0 | X53: 0 | Y53: 0
A54: =A53+10 -> 400 | B54: Хусусий корхоналар | C54: =SUM(J54:Y54)-L54-P54-Q54 -> 0 | D54: 0 | E54: 0 | F54: =+G54+H54+I54 -> 0 | G54: 0 | H54: 0 | I54: 0 | J54: 0 | K54: 0 | L54: 0 | M54: 0 | N54: 0 | O54: =+P54+Q54 -> 0 | P54: 0 | Q54: 0 | R54: 0 | S54: 0 | T54: 0 | U54: 0 | V54: 0 | W54: 0 | X54: 0 | Y54: 0
A55: =A54+10 -> 410 | B55: Ҳукумат | C55: =SUM(J55:Y55)-L55-P55-Q55 -> 0 | D55: 0 | E55: 0 | F55: =+G55+H55+I55 -> 0 | G55: 0 | H55: 0 | I55: 0 | J55: 0 | K55: 0 | L55: 0 | M55: 0 | N55: 0 | O55: =+P55+Q55 -> 0 | P55: 0 | Q55: 0 | R55: 0 | S55: 0 | T55: 0 | U55: 0 | V55: 0 | W55: 0 | X55: 0 | Y55: 0
A56: 485 | B56: Нодавлат нотижорат ташкилотлар | C56: =SUM(J56:Y56)-L56-P56-Q56 -> 10242602 | D56: 10242602 | E56: 0 | F56: =+G56+H56+I56 -> 6118961 | G56: 1041035 | H56: 1884435 | I56: 3193491 | J56: 0 | K56: 0 | L56: 0 | M56: 0 | N56: 0 | O56: =+P56+Q56 -> 0 | P56: 0 | Q56: 0 | R56: 0 | S56: 0 | T56: 0 | U56: 0 | V56: 4855226 | W56: 5387376 | X56: 0 | Y56: 0
A57: =A55+10 -> 420 | B57: Бошқалар | C57: =SUM(J57:Y57)-L57-P57-Q57 -> 0 | D57: 0 | E57: 0 | F57: =+G57+H57+I57 -> 0 | G57: 0 | H57: 0 | I57: 0 | J57: 0 | K57: 0 | L57: 0 | M57: 0 | N57: 0 | O57: =+P57+Q57 -> 0 | P57: 0 | Q57: 0 | R57: 0 | S57: 0 | T57: 0 | U57: 0 | V57: 0 | W57: 0 | X57: 0 | Y57: 0
A58: =A57+10 -> 430 | B58: Жами | C58: =SUM(J58:Y58)-L58-P58-Q58 -> 10242602 | D58: =SUM(D52:D57) -> 10242602 | E58: =SUM(E52:E57) -> 0 | F58: =+G58+H58+I58 -> 6118961 | G58: =SUM(G53:G57) -> 1041035 | H58: =SUM(H53:H57) -> 1884435 | I58: =SUM(I53:I57) -> 3193491 | J58: =SUM(J52:J57) -> 0 | K58: =SUM(K52:K57) -> 0 | L58: =SUM(L52:L57) -> 0 | M58: =SUM(M52:M57) -> 0 | N58: =SUM(N52:N57) -> 0 | O58: =SUM(O52:O57) -> 0 | P58: =SUM(P52:P57) -> 0 | Q58: =SUM(Q52:Q57) -> 0 | ... Y58: =SUM(Y52:Y57) -> 0
B59: Бошқа соҳалар
A60: 440 | B60: Давлат корхоналари | C60: =SUM(J60:Y60)-L60-P60-Q60 -> 371292768 | D60: 303940008 | E60: 67352760 | F60: =+G60+H60+I60 -> 0 | G60: 0 | H60: 0 | I60: 0 | J60: 0 | K60: 186764141 | L60: 0 | M60: 44888589 | N60: 0 | O60: =+P60+Q60 -> 74372260 | P60: 0 | Q60: 74372260 | R60: 0 | S60: 0 | T60: 0 | U60: 0 | V60: 61567272 | W60: 3700506 | X60: 0 | Y60: 0
A61: =A60+10 -> 450 | B61: Қўшма ва чет эл капитали иштирокидаги корхоналар | C61: =SUM(J61:Y61)-L61-P61-Q61 -> 1000399446 | D61: 112434647 | E61: 887964799 | F61: =+G61+H61+I61 -> 0 | G61: 0 | H61: 0 | I61: 0 | J61: 0 | K61: 0 | L61: 0 | M61: 49272825 | N61: 0 | O61: =+P61+Q61 -> 621359008 | P61: 879781 | Q61: 620479227 | R61: 79218572 | S61: 0 | T61: 0 | U61: 0 | V61: 180121277 | W61: 70427764 | X61: 0 | Y61: 0
A62: =A61+10 -> 460 | B62: Хусусий корхоналар | C62: =SUM(J62:Y62)-L62-P62-Q62 -> 1741375646 | D62: 680757154 | E62: 1060618492 | F62: =+G62+H62+I62 -> 84207389 | G62: 55124153 | H62: 23289729 | I62: 5793507 | J62: 0 | K62: 0 | L62: 0 | M62: 40576522 | N62: 0 | O62: =+P62+Q62 -> 517277509 | P62: 22369046 | Q62: 494908463 | R62: 118968811 | S62: 0 | T62: 0 | U62: 381944 | V62: 927182069 | W62: 134771393 | X62: 2203856 | Y62: 13542
A63: =A62+10 -> 470 | B63: Марказий банк | C63: =SUM(J63:Y63)-L63-P63-Q63 -> 0 | D63: 0 | E63: 0 | F63: =+G63+H63+I63 -> 0 | G63: 0 | H63: 0 | I63: 0 | J63: 0 | K63: 0 | L63: 0 | M63: 0 | N63: 0 | O63: =+P63+Q63 -> 0 | P63: 0 | Q63: 0 | R63: 0 | S63: 0 | T63: 0 | U63: 0 | V63: 0 | W63: 0 | X63: 0 | Y63: 0
A64: =A63+10 -> 480 | B64: Бошқа банклар | C64: =SUM(J64:Y64)-L64-P64-Q64 -> 0 | D64: 0 | E64: 0 | F64: =+G64+H64+I64 -> 0 | G64: 0 | H64: 0 | I64: 0 | J64: 0 | K64: 0 | L64: 0 | M64: 0 | N64: 0 | O64: =+P64+Q64 -> 0 | P64: 0 | Q64: 0 | R64: 0 | S64: 0 | T64: 0 | U64: 0 | V64: 0 | W64: 0 | X64: 0 | Y64: 0
A65: =A64+10 -> 490 | B65: Ҳукумат | C65: =SUM(J65:Y65)-L65-P65-Q65 -> 0 | D65: 0 | E65: 0 | F65: =+G65+H65+I65 -> 0 | G65: 0 | H65: 0 | I65: 0 | J65: 0 | K65: 0 | L65: 0 | M65: 0 | N65: 0 | O65: =+P65+Q65 -> 0 | P65: 0 | Q65: 0 | R65: 0 | S65: 0 | T65: 0 | U65: 0 | V65: 0 | W65: 0 | X65: 0 | Y65: 0
A66: =A65+10 -> 500 | B66: Банк бўлмаган молиявий муассасалар | C66: =SUM(J66:Y66)-L66-P66-Q66 -> 2059286 | D66: 2059286 | E66: 0 | F66: =+G66+H66+I66 -> 0 | G66: 0 | H66: 0 | I66: 0 | J66: 0 | K66: 0 | L66: 0 | M66: 228995 | N66: 0 | O66: =+P66+Q66 -> 1500000 | P66: 0 | Q66: 1500000 | R66: 0 | S66: 0 | T66: 0 | U66: 0 | V66: 0 | W66: 330291 | X66: 0 | Y66: 0
A67: =A66+10 -> 510 | B67: Нодавлат нотижорат ташкилотлар | C67: =SUM(J67:Y67)-L67-P67-Q67 -> 0 | D67: 0 | E67: 0 | F67: =+G67+H67+I67 -> 0 | G67: 0 | H67: 0 | I67: 0 | J67: 0 | K67: 0 | L67: 0 | M67: 0 | N67: 0 | O67: =+P67+Q67 -> 0 | P67: 0 | Q67: 0 | R67: 0 | S67: 0 | T67: 0 | U67: 0 | V67: 0 | W67: 0 | X67: 0 | Y67: 0
A68: =A67+10 -> 520 | B68: Бюджет ташкилотлари | C68: =SUM(J68:Y68)-L68-P68-Q68 -> 0 | D68: 0 | E68: 0 | F68: =+G68+H68+I68 -> 0 | G68: 0 | H68: 0 | I68: 0 | J68: 0 | K68: 0 | L68: 0 | M68: 0 | N68: 0 | O68: =+P68+Q68 -> 0 | P68: 0 | Q68: 0 | R68: 0 | S68: 0 | T68: 0 | U68: 0 | V68: 0 | W68: 0 | X68: 0 | Y68: 0
A69: =A68+10 -> 530 | B69: Бошқалар | C69: =SUM(J69:Y69)-L69-P69-Q69 -> 0 | D69: 0 | E69: 0 | F69: =+G69+H69+I69 -> 0 | G69: 0 | H69: 0 | I69: 0 | J69: 0 | K69: 0 | L69: 0 | M69: 0 | N69: 0 | O69: =+P69+Q69 -> 0 | P69: 0 | Q69: 0 | R69: 0 | S69: 0 | T69: 0 | U69: 0 | V69: 0 | W69: 0 | X69: 0 | Y69: 0
A70: =A69+10 -> 540 | B70: Жами | C70: =SUM(J70:Y70)-L70-P70-Q70 -> 3115127146 | D70: =SUM(D60:D69) -> 1099191095 | E70: =SUM(E60:E69) -> 2015936051 | F70: =+G70+H70+I70 -> 84207389 | G70: =SUM(G60:G69) -> 55124153 | H70: =SUM(H60:H69) -> 23289729 | I70: =SUM(I60:I69) -> 5793507 | J70: =SUM(J60:J69) -> 0 | K70: =SUM(K60:K69) -> 186764141 | L70: =SUM(L60:L69) -> 0 | M70: =SUM(M60:M69) -> 134966931 | N70: =SUM(N60:N69) -> 0 | ... Y70: =SUM(Y60:Y69) -> 13542
A71: 550 | B71: Жами жисмоний шахслар | C71: =SUM(J71:Y71)-L71-P71-Q71 -> 5463367169 | D71: 5463367169 | E71: 0 | F71: =+G71+H71+I71 -> 50338680 | G71: 25017834 | H71: 18412252 | I71: 6908594 | J71: 0 | K71: 63556 | L71: 0 | M71: 173176262 | N71: 0 | O71: =+P71+Q71 -> 3156481451 | P71: 3154985645 | Q71: 1495806 | R71: 0 | S71: 0 | T71: 0 | U71: 164730 | V71: 1351507963 | W71: 779861704 | X71: 1051960 | Y71: 1059543
B72: Кредит ва лизинг операциялари
A73: =A71+10 -> 560 | B73: Жисмоний шахслар | C73: =SUM(J73:Y73)-L73-P73-Q73 -> 5463367169 | D73: =+D71 -> 5463367169 | E73: =+E71 -> 0 | F73: =+F71 -> 50338680 | G73: =+G71 -> 25017834 | H73: =+H71 -> 18412252 | I73: =+I71 -> 6908594 | J73: =+J71 -> 0 | K73: =+K71 -> 63556 | ... Y73: =+Y71 -> 1059543
A74: =A73+10 -> 570 | B74: Давлат корхоналари | C74: =SUM(J74:Y74)-L74-P74-Q74 -> 14093170226 | D74: =D9+D16+D24+D31+D38+D45+D52+D60 -> 4517131855 | E74: =E9+E16+E24+E31+E38+E45+E52+E60 -> 9576038371 | F74: =F9+F16+F24+F31+F38+F45+F52+F60 -> 0 | G74: =G9+G16+G24+G31+G38+G45+G52+G60 -> 0 | H74: =H9+H16+H24+H31+H38+H45+H52+H60 -> 0 | I74: =I9+I16+I24+I31+I38+I45+I52+I60 -> 0 | J74: =J9+J16+J24+J31+J38+J45+J52+J60 -> 958841375 | K74: =K9+K16+K24+K31+K38+K45+K52+K60 -> 6811613947 | ... Y74: =Y9+Y16+Y24+Y31+Y38+Y45+Y52+Y60 -> 2461355297
A75: =A74+10 -> 580 | B75: Қўшма ва чет эл капитали иштирокидаги корхоналар | C75: =SUM(J75:Y75)-L75-P75-Q75 -> 9080290501 | D75: =D10+D17+D25+D32+D39+D46+D53+D61 -> 1139237313 | E75: =E10+E17+E25+E32+E39+E46+E53+E61 -> 7941053188 | F75: =F10+F17+F25+F32+F39+F46+F53+F61 -> 377747736 | G75: =G10+G17+G25+G32+G39+G46+G53+G61 -> 66012522 | H75: =H10+H17+H25+H32+H39+H46+H53+H61 -> 302666165 | I75: =I10+I17+I25+I32+I39+I46+I53+I61 -> 9069049 | J75: =J10+J17+J25+J32+J39+J46+J53+J61 -> 561273 | K75: =K10+K17+K25+K32+K39+K46+K53+K61 -> 0 | ... Y75: =Y10+Y17+Y25+Y32+Y39+Y46+Y53+Y61 -> 1296092122
A76: =A75+10 -> 590 | B76: Хусусий корхоналар | C76: =SUM(J76:Y76)-L76-P76-Q76 -> 19254967029 | D76: =D11+D18+D26+D33+D40+D47+D54+D62 -> 6046481253 | E76: =E11+E18+E26+E33+E40+E47+E54+E62 -> 13208485776 | F76: =F11+F18+F26+F33+F40+F47+F54+F62 -> 887237263 | G76: =G11+G18+G26+G33+G40+G47+G54+G62 -> 335528939 | H76: =H11+H18+H26+H33+H40+H47+H54+H62 -> 490888293 | I76: =I11+I18+I26+I33+I40+I47+I54+I62 -> 60820031 | J76: =J11+J18+J26+J33+J40+J47+J54+J62 -> 547253 | K76: =K11+K18+K26+K33+K40+K47+K54+K62 -> 0 | ... Y76: =Y11+Y18+Y26+Y33+Y40+Y47+Y54+Y62 -> 233610617
A77: =A76+10 -> 600 | B77: Фермер хўжалиги | C77: =SUM(J77:Y77)-L77-P77-Q77 -> 171788067 | D77: =D19 -> 69222758 | E77: =E19 -> 102565309 | F77: =F19 -> 37243840 | G77: =G19 -> 9188880 | H77: =H19 -> 16591663 | I77: =I19 -> 11463297 | J77: =J19 -> 0 | K77: =K19 -> 0 | ... Y77: =Y19 -> 0
A78: =A77+10 -> 610 | B78: Бошқа банклар | C78: =SUM(J78:Y78)-L78-P78-Q78 -> 0 | D78: =D64 -> 0 | E78: =E64 -> 0 | F78: =F64 -> 0 | G78: =G64 -> 0 | H78: =H64 -> 0 | I78: =I64 -> 0 | J78: =J64 -> 0 | K78: =K64 -> 0 | ... Y78: =Y64 -> 0
A79: =A78+10 -> 620 | B79: Марказий банк | C79: =SUM(J79:Y79)-L79-P79-Q79 -> 0 | D79: =D63 -> 0 | E79: =E63 -> 0 | F79: =F63 -> 0 | G79: =G63 -> 0 | H79: =H63 -> 0 | I79: =I63 -> 0 | J79: =J63 -> 0 | K79: =K63 -> 0 | ... Y79: =Y63 -> 0
A80: =A79+10 -> 630 | B80: Ҳукумат | C80: =SUM(J80:Y80)-L80-P80-Q80 -> 0 | D80: =D12+D20+D27+D34+D41+D48+D55+D65 -> 0 | E80: =E12+E20+E27+E34+E41+E48+E55+E65 -> 0 | F80: =F12+F20+F27+F34+F41+F48+F55+F65 -> 0 | G80: =G12+G20+G27+G34+G41+G48+G55+G65 -> 0 | H80: =H12+H20+H27+H34+H41+H48+H55+H65 -> 0 | I80: =I12+I20+I27+I34+I41+I48+I55+I65 -> 0 | J80: =J12+J20+J27+J34+J41+J48+J55+J65 -> 0 | K80: =K12+K20+K27+K34+K41+K48+K55+K65 -> 0 | ... Y80: =Y12+Y20+Y27+Y34+Y41+Y48+Y55+Y65 -> 0
A81: =A80+10 -> 640 | B81: Банк бўлмаган молиявий муассасалар | C81: =SUM(J81:Y81)-L81-P81-Q81 -> 2059286 | D81: =D66 -> 2059286 | E81: =E66 -> 0 | F81: =F66 -> 0 | G81: =G66 -> 0 | H81: =H66 -> 0 | I81: =I66 -> 0 | J81: =J66 -> 0 | K81: =K66 -> 0 | ... Y81: =Y66 -> 0
A82: =A81+10 -> 650 | B82: Нодавлат нотижорат ташкилотлар | C82: =SUM(J82:Y82)-L82-P82-Q82 -> 10242602 | D82: =+D56+D67 -> 10242602 | E82: =+E56+E67 -> 0 | F82: =+F56+F67 -> 6118961 | G82: =+G56+G67 -> 1041035 | H82: =+H56+H67 -> 1884435 | I82: =+I56+I67 -> 3193491 | J82: =+J56+J67 -> 0 | K82: =+K56+K67 -> 0 | ... Y82: =+Y56+Y67 -> 0
A83: =A82+10 -> 660 | B83: Бюджет ташкилотлари | C83: =SUM(J83:Y83)-L83-P83-Q83 -> 0 | D83: =D68 -> 0 | E83: =E68 -> 0 | F83: =F68 -> 0 | G83: =G68 -> 0 | H83: =H68 -> 0 | I83: =I68 -> 0 | J83: =J68 -> 0 | K83: =K68 -> 0 | ... Y83: =Y68 -> 0
A84: =A83+10 -> 670 | B84: Бошқалар | C84: =SUM(J84:Y84)-L84-P84-Q84 -> 0 | D84: =D13+D21+D28+D35+D42+D49+D57+D69 -> 0 | E84: =E13+E21+E28+E35+E42+E49+E57+E69 -> 0 | F84: =F13+F21+F28+F35+F42+F49+F57+F69 -> 0 | G84: =G13+G21+G28+G35+G42+G49+G57+G69 -> 0 | H84: =H13+H21+H28+H35+H42+H49+H57+H69 -> 0 | I84: =I13+I21+I28+I35+I42+I49+I57+I69 -> 0 | J84: =J13+J21+J28+J35+J42+J49+J57+J69 -> 0 | K84: =K13+K21+K28+K35+K42+K49+K57+K69 -> 0 | ... Y84: =Y13+Y21+Y28+Y35+Y42+Y49+Y57+Y69 -> 0
A85: =A84+10 -> 680 | B85: Жами кредит ва лизинг суммаси | C85: =SUM(J85:Y85)-L85-P85-Q85 -> 48075884880 | D85: =SUM(D73:D84) -> 17247742236 | E85: =SUM(E73:E84) -> 30828142644 | F85: =SUM(F73:F84) -> 1358686480 | G85: =SUM(G73:G84) -> 436789210 | H85: =SUM(H73:H84) -> 830442808 | I85: =SUM(I73:I84) -> 91454462 | J85: =SUM(J73:J84) -> 959949901 | K85: =SUM(K73:K84) -> 6811677503 | ... Y85: =SUM(Y73:Y84) -> 3992117579
B87: Бошқарув Раис имзоси:
B89: Бош бухгалтер имзоси:
C92: =+[8]Balance!C25 -> 48075884880 | D92: =+[8]Balance!D25 -> 17247742236 | E92: =+[8]Balance!E25 -> 30828142644 | F92: =+'Asset Classification'!M31+'Asset Classification'!Q31+'Asset Classification'!U31 -> 1358686480 | G92: =+'Asset Classification'!M31 -> 436789210 | H92: =+'Asset Classification'!Q31 -> 830442808 | I92: =+'Asset Classification'!U31 -> 91454462 | J92: =+'[9]Calculation of Risk Weighted As'!$C$24+'[9]Calculation of Risk Weighted As'!$D$24 -> 959949901
C93: =+C85-C92 -> 0 | D93: =+D85-D92 -> 0 | E93: =+E85-E92 -> 0 | F93: =+F85-F92 -> 0 | G93: =+G85-G92 -> 0 | H93: =+H85-H92 -> 0 | I93: =+I85-I92 -> 0 | J93: =+J85-J92 -> 0

Sheet Aging Analysis
A1: ОЛИНИШИ ЛОЗИМ БЎЛГАН МУДДАТИ ЎТГАН КРЕДИТ ВА МОЛИЯВИЙ ЛИЗИНГ ТАҲЛИЛИ | X1: 9-жадвал
B3: =+'Asset quality'!B3 -> "Ўзсаноатқурилишбанк" АТБ | T3: =+'Asset quality'!Q3 -> 44925 | X3: =+'Asset quality'!T3 -> минг. сўмда
A4: № | B4: Кўрсаткичлар | C4: Жами кредит суммаси | D4: % | E4: Шартлари қайта кўрилган кредит ва лизинглар | F4: % | G4: Суд жараёнидаги қарздорликлар | H4: % | I4: Муддати ўтган | K4: % | L4: шу жумладан, кечиктирилган муддати бўйича
L5: 1-30 кун | N5: 31-60 кун | P5: 61-90 кун | R5: 91-180 кун | T5: 181-365 кун | V5: 366-730 кун | X5: 2 йилдан ортиқ
I6: асосий қарздорлик | J6: фоиз тўловлари | L6: асосий қарздорлик | M6: фоиз тўловлари | N6: асосий қарздорлик | O6: фоиз тўловлари | P6: асосий қарздорлик | Q6: фоиз тўловлари | R6: асосий қарздорлик | S6: фоиз тўловлари | T6: асосий қарздорлик | U6: фоиз тўловлари | V6: асосий қарздорлик | W6: фоиз тўловлари | X6: асосий қарздорлик | Y6: фоиз тўловлари
B7: (А) | C7: (Б) | D7: (В) | E7: (Г) | F7: (Д) | G7: (Е) | H7: (Ж) | I7: (З) | J7: (З1) | K7: (И) | L7: (К) | M7: (К1) | N7: (Л) | O7: (Л1) | P7: (М) | Q7: (М1) | R7: (Н) | S7: (Н1) | T7: (О) | U7: (О1) | V7: (П) | W7: (П1) | X7: (Р) | Y7: (Р1)
B8: Мижозлар тури бўйича
A9: 1 | B9: Марказий банк | C9: =+'Loans Receivable'!C79 -> 0 | D9: =IF(C$22=0,"",C9/C$22) -> 0 | F9: =IF(E$22=0,"",E9/E$22) -> 0 | H9: =IF($G$22=0,"",G9/$G$22) -> 0 | I9: =+L9+N9+P9+R9+T9+V9+X9 -> 0 | J9: =+M9+O9+T9+S9+U9+W9+Y9 -> 0 | K9: =IF($Z$22=0,"",Z9/$Z$22) -> 0 | Z9: =+I9+J9 -> 0
A10: 2 | B10: Бошқа банклар | C10: =+'Loans Receivable'!C78 -> 0 | D10: =IF(C$22=0,"",C10/C$22) -> 0 | F10: =IF(E$22=0,"",E10/E$22) -> 0 | H10: =IF($G$22=0,"",G10/$G$22) -> 0 | I10: =+L10+N10+P10+R10+T10+V10+X10 -> 0 | J10: =+M10+O10+Q10+S10+U10+W10+Y10 -> 0 | K10: =IF($Z$22=0,"",Z10/$Z$22) -> 0 | Z10: =+I10+J10 -> 0
A11: 3 | B11: Ҳукумат | C11: =+'Loans Receivable'!C80 -> 0 | D11: =IF(C$22=0,"",C11/C$22) -> 0 | F11: =IF(E$22=0,"",E11/E$22) -> 0 | H11: =IF($G$22=0,"",G11/$G$22) -> 0 | I11: =+L11+N11+P11+R11+T11+V11+X11 -> 0 | J11: =+M11+O11+Q11+S11+U11+W11+Y11 -> 0 | K11: =IF($Z$22=0,"",Z11/$Z$22) -> 0 | Z11: =+I11+J11 -> 0
A12: 4 | B12: Жисмоний шахслар | C12: =+'Loans Receivable'!C73 -> 5463367169 | D12: =IF(C$22=0,"",C12/C$22) -> 0.11364049 | E12: 9541830 | F12: =IF(E$22=0,"",E12/E$22) -> 0.028943972 | G12: 1711326 | H12: =IF($G$22=0,"",G12/$G$22) -> 0.010942453 | I12: =+L12+N12+P12+R12+T12+V12+X12 -> 7346228 | J12: =+M12+O12+Q12+S12+U12+W12+Y12 -> 4378892 | K12: =IF($Z$22=0,"",Z12/$Z$22) -> 0.016912068 | L12: 1074616 | M12: 2473682 | N12: 813701 | O12: 336955 | P12: 674122 | Q12: 270739 | R12: 1466502 | S12: 348343 | T12: 2583601 | U12: 724568 | V12: 733686 | W12: 224605 | X12: 0 | Y12: 0 | Z12: =+I12+J12 -> 11725120
A13: 5 | B13: Давлат корхоналари | C13: =+'Loans Receivable'!C74 -> 14093170226 | D13: =IF(C$22=0,"",C13/C$22) -> 0.29314427 | E13: 9742376 | F13: =IF(E$22=0,"",E13/E$22) -> 0.029552304 | G13: 0 | H13: =IF($G$22=0,"",G13/$G$22) -> 0 | I13: =+L13+N13+P13+R13+T13+V13+X13 -> 3481735 | J13: =+M13+O13+Q13+S13+U13+W13+Y13 -> 820795 | K13: =IF($Z$22=0,"",Z13/$Z$22) -> 0.0062058794 | L13: 393852 | M13: 446437 | N13: 2666667 | O13: 374358 | P13: 421216 | Q13: 0 | R13: 0 | S13: 0 | T13: 0 | U13: 0 | V13: 0 | W13: 0 | X13: 0 | Y13: 0 | Z13: =+I13+J13 -> 4302530
A14: 6 | B14: Қўшма ва чет эл капитали иштирокидаги корхоналар | C14: =+'Loans Receivable'!C75 -> 9080290501 | D14: =IF(C$22=0,"",C14/C$22) -> 0.18887412 | E14: 9669020 | F14: =IF(E$22=0,"",E14/E$22) -> 0.029329787 | G14: 5188589 | H14: =IF($G$22=0,"",G14/$G$22) -> 0.033176548 | I14: =+L14+N14+P14+R14+T14+V14+X14 -> 47188479 | J14: =+M14+O14+Q14+S14+U14+W14+Y14 -> 54022771 | K14: =IF($Z$22=0,"",Z14/$Z$22) -> 0.14598499 | L14: 3369687 | M14: 51164011 | N14: 3246003 | O14: 258667 | P14: 11680881 | Q14: 0 | R14: 13826655 | S14: 273229 | T14: 15065253 | U14: 2326864 | V14: 0 | W14: 0 | X14: 0 | Y14: 0 | Z14: =+I14+J14 -> 101211250
A15: 7 | B15: Хусусий корхоналар | C15: =+'Loans Receivable'!C76 -> 19254967029 | D15: =IF(C$22=0,"",C15/C$22) -> 0.40051196 | E15: 296813214 | F15: =IF(E$22=0,"",E15/E$22) -> 0.90034651 | G15: 147248642 | H15: =IF($G$22=0,"",G15/$G$22) -> 0.94152797 | I15: =+L15+N15+P15+R15+T15+V15+X15 -> 424144654 | J15: =+M15+O15+Q15+S15+U15+W15+Y15 -> 133005898 | K15: =IF($Z$22=0,"",Z15/$Z$22) -> 0.80362232 | L15: 43241798 | M15: 47119344 | N15: 35396391 | O15: 17670132 | P15: 86198154 | Q15: 8131320 | R15: 116819260 | S15: 22582178 | T15: 133241936 | U15: 36579419 | V15: 9247115 | W15: 923505 | X15: 0 | Y15: 0 | Z15: =+I15+J15 -> 557150552
A16: 8 | B16: Фермер хўжаликлари | C16: =+'Loans Receivable'!C77 -> 171788067 | D16: =IF(C$22=0,"",C16/C$22) -> 0.003573269 | E16: 3660807 | F16: =IF(E$22=0,"",E16/E$22) -> 0.011104609 | G16: 2244718 | H16: =IF($G$22=0,"",G16/$G$22) -> 0.014353034 | I16: =+L16+N16+P16+R16+T16+V16+X16 -> 11246932 | J16: =+M16+O16+Q16+S16+U16+W16+Y16 -> 5744647 | K16: =IF($Z$22=0,"",Z16/$Z$22) -> 0.024508299 | L16: 52541 | M16: 2276772 | N16: 561273 | O16: 969267 | P16: 218906 | Q16: 23478 | R16: 152097 | S16: 136477 | T16: 6225901 | U16: 806374 | V16: 4036214 | W16: 1532279 | X16: 0 | Y16: 0 | Z16: =+I16+J16 -> 16991579
A17: 9 | B17: Нобанк молиявий институтлар | C17: =+'Loans Receivable'!C81 -> 2059286 | D17: =IF(C$22=0,"",C17/C$22) -> 4.2834074e-05 | E17: 0 | F17: =IF(E$22=0,"",E17/E$22) -> 0 | G17: 0 | H17: =IF($G$22=0,"",G17/$G$22) -> 0 | I17: =+L17+N17+P17+R17+T17+V17+X17 -> 0 | J17: =+M17+O17+Q17+S17+U17+W17+Y17 -> 0 | K17: =IF($Z$22=0,"",Z17/$Z$22) -> 0 | L17: 0 | M17: 0 | N17: 0 | O17: 0 | P17: 0 | Q17: 0 | R17: 0 | S17: 0 | T17: 0 | U17: 0 | V17: 0 | W17: 0 | X17: 0 | Y17: 0 | Z17: =+I17+J17 -> 0
A18: 10 | B18: Нодавлат нотижорат ташкилотлар | C18: =+'Loans Receivable'!C82 -> 10242602 | D18: =IF(C$22=0,"",C18/C$22) -> 0.00021305072 | E18: 238287 | F18: =IF(E$22=0,"",E18/E$22) -> 0.00072281441 | G18: 0 | H18: =IF($G$22=0,"",G18/$G$22) -> 0 | I18: =+L18+N18+P18+R18+T18+V18+X18 -> 888693 | J18: =+M18+O18+Q18+S18+U18+W18+Y18 -> 1029274 | K18: =IF($Z$22=0,"",Z18/$Z$22) -> 0.0027664356 | L18: 0 | M18: 346988 | N18: 20791 | O18: 10927 | P18: 17159 | Q18: 10029 | R18: 46086 | S18: 89136 | T18: 195722 | U18: 143457 | V18: 182126 | W18: 94110 | X18: 426809 | Y18: 334627 | Z18: =+I18+J18 -> 1917967
A19: 11 | B19: Бюджет ташкилотлари | C19: =+'Loans Receivable'!C83 -> 0 | D19: =IF(C$22=0,"",C19/C$22) -> 0 | E19: 0 | F19: =IF(E$22=0,"",E19/E$22) -> 0 | G19: 0 | H19: =IF($G$22=0,"",G19/$G$22) -> 0 | I19: =+L19+N19+P19+R19+T19+V19+X19 -> 0 | J19: =+M19+O19+Q19+S19+U19+W19+Y19 -> 0 | K19: =IF($Z$22=0,"",Z19/$Z$22) -> 0 | L19: 0 | M19: 0 | N19: 0 | O19: 0 | P19: 0 | Q19: 0 | R19: 0 | S19: 0 | T19: 0 | U19: 0 | V19: 0 | W19: 0 | X19: 0 | Y19: 0 | Z19: =+I19+J19 -> 0
A20: 12 | B20: Бошқалар | C20: =+'Loans Receivable'!C84 -> 0 | D20: =IF(C$22=0,"",C20/C$22) -> 0 | E20: 0 | F20: =IF(E$22=0,"",E20/E$22) -> 0 | G20: 0 | H20: =IF($G$22=0,"",G20/$G$22) -> 0 | I20: =+L20+N20+P20+R20+T20+V20+X20 -> 0 | J20: =+M20+O20+Q20+S20+U20+W20+Y20 -> 0 | K20: =IF($Z$22=0,"",Z20/$Z$22) -> 0 | L20: 0 | M20: 0 | N20: 0 | O20: 0 | P20: 0 | Q20: 0 | R20: 0 | S20: 0 | T20: 0 | U20: 0 | V20: 0 | W20: 0 | X20: 0 | Y20: 0 | Z20: =+I20+J20 -> 0
Z21: =+I21+J21 -> 0
A22: 13 | B22: Жами кредит ва лизинг суммаси | C22: =SUM(C9:C20) -> 48075884880 | D22: =IF(C$22=0,"",C22/C$22) -> 1 | E22: =SUM(E9:E20) -> 329665534 | F22: =IF(E$22=0,"",E22/E$22) -> 1 | G22: =SUM(G9:G20) -> 156393275 | H22: =IF($G$22=0,"",G22/$G$22) -> 1 | I22: =SUM(I9:I20) -> 494296721 | J22: =SUM(J9:J20) -> 199002277 | K22: =IF($Z$22=0,"",Z22/$Z$22) -> 1 | L22: =SUM(L9:L20) -> 48132494 | M22: =SUM(M9:M20) -> 103827234 | N22: =SUM(N9:N20) -> 42704826 | O22: =SUM(O9:O20) -> 19620306 | P22: =SUM(P9:P20) -> 99210438 | Q22: =SUM(Q9:Q20) -> 8435566 | R22: =SUM(R9:R20) -> 132310600 | S22: =SUM(S9:S20) -> 23429363 | ... Y22: =SUM(Y9:Y20) -> 334627 | Z22: =+I22+J22 -> 693298998
Z23: =+I23+J23 -> 0
B24: Иқтисодиёт соҳалари бўйича | Z24: =+I24+J24 -> 0
A25: 14 | B25: Саноат | C25: =+'Loans Receivable'!C14 -> 25973436689 | D25: =IF(C$35=0,"",C25/C$35) -> 0.54025915 | E25: 150027294 | F25: =IF($E$35=0,"",E25/$E$35) -> 0.45508941 | G25: 91038174 | H25: =IF($G$35=0,"",G25/$G$35) -> 0.58211054 | I25: =+L25+N25+P25+R25+T25+V25+X25 -> 223468386 | J25: =+M25+O25+Q25+S25+U25+W25+Y25 -> 106525185 | K25: =IF($Z$35=0,"",Z25/$Z$35) -> 0.47597584 | L25: 18792123 | M25: 64950098 | N25: 25030864 | O25: 14806158 | P25: 40121655 | Q25: 2324621 | R25: 55627970 | S25: 2629302 | T25: 83749941 | U25: 21762591 | V25: 145833 | W25: 52415 | X25: 0 | Y25: 0 | Z25: =+I25+J25 -> 329993571
A26: 15 | B26: Қишлоқ хўжалиги | C26: =+'Loans Receivable'!C22 -> 4481661756 | D26: =IF(C$35=0,"",C26/C$35) -> 0.093220578 | E26: 90115429 | F26: =IF($E$35=0,"",E26/$E$35) -> 0.27335411 | G26: 14074906 | H26: =IF($G$35=0,"",G26/$G$35) -> 0.089996875 | I26: =+L26+N26+P26+R26+T26+V26+X26 -> 70212702 | J26: =+M26+O26+Q26+S26+U26+W26+Y26 -> 27065280 | K26: =IF($Z$35=0,"",Z26/$Z$35) -> 0.14031173 | L26: 8877669 | M26: 15758057 | N26: 3461787 | O26: 1811421 | P26: 19402635 | Q26: 461247 | R26: 9347300 | S26: 1300830 | T26: 23177876 | U26: 5931353 | V26: 5945435 | W26: 1802372 | X26: 0 | Y26: 0 | Z26: =+I26+J26 -> 97277982
A27: 16 | B27: Транспорт ва коммуникация | C27: =+'Loans Receivable'!C29 -> 3505300410 | D27: =IF(C$35=0,"",C27/C$35) -> 0.072911823 | E27: 4744500 | F27: =IF($E$35=0,"",E27/$E$35) -> 0.014391859 | G27: 9278723 | H27: =IF($G$35=0,"",G27/$G$35) -> 0.059329424 | I27: =+L27+N27+P27+R27+T27+V27+X27 -> 25773249 | J27: =+M27+O27+Q27+S27+U27+W27+Y27 -> 3989332 | K27: =IF($Z$35=0,"",Z27/$Z$35) -> 0.042928925 | L27: 1398426 | M27: 1282817 | N27: 512649 | O27: 193017 | P27: 6734519 | Q27: 98139 | R27: 168882 | S27: 29066 | T27: 11572222 | U27: 2201867 | V27: 5386551 | W27: 184426 | X27: 0 | Y27: 0 | Z27: =+I27+J27 -> 29762581
A28: 17 | B28: Қурилиш соҳаси | C28: =+'Loans Receivable'!C36 -> 1311223847 | D28: =IF(C$35=0,"",C28/C$35) -> 0.027274045 | E28: 8739643 | F28: =IF($E$35=0,"",E28/$E$35) -> 0.026510636 | G28: 19101309 | H28: =IF($G$35=0,"",G28/$G$35) -> 0.12213638 | I28: =+L28+N28+P28+R28+T28+V28+X28 -> 49667336 | J28: =+M28+O28+Q28+S28+U28+W28+Y28 -> 18979950 | K28: =IF($Z$35=0,"",Z28/$Z$35) -> 0.099015412 | L28: 5152208 | M28: 3265904 | N28: 1075051 | O28: 164607 | P28: 1502729 | Q28: 4673 | R28: 25848379 | S28: 11138412 | T28: 15731466 | U28: 4296336 | V28: 357503 | W28: 110018 | X28: 0 | Y28: 0 | Z28: =+I28+J28 -> 68647286
A29: 18 | B29: Савдо ва умумий овқатланиш | C29: =+'Loans Receivable'!C43 -> 2888957110 | D29: =IF(C$35=0,"",C29/C$35) -> 0.060091606 | E29: 56289986 | F29: =IF($E$35=0,"",E29/$E$35) -> 0.17074877 | G29: 13674645 | H29: =IF($G$35=0,"",G29/$G$35) -> 0.087437551 | I29: =+L29+N29+P29+R29+T29+V29+X29 -> 97251982 | J29: =+M29+O29+Q29+S29+U29+W29+Y29 -> 22632924 | K29: =IF($Z$35=0,"",Z29/$Z$35) -> 0.17291949 | L29: 6625092 | M29: 8117954 | N29: 10706096 | O29: 1689674 | P29: 29003647 | Q29: 4801942 | R29: 38386796 | S29: 7554300 | T29: 12192585 | U29: 430060 | V29: 337766 | W29: 38994 | X29: 0 | Y29: 0 | Z29: =+I29+J29 -> 119884906
A30: 19 | B30: Моддий ва техник таъминотни ривожлантириш | C30: =+'Loans Receivable'!C50 -> 1326568151 | D30: =IF(C$35=0,"",C30/C$35) -> 0.027593213 | E30: 0 | F30: =IF($E$35=0,"",E30/$E$35) -> 0 | G30: 4490184 | H30: =IF($G$35=0,"",G30/$G$35) -> 0.028710851 | I30: =+L30+N30+P30+R30+T30+V30+X30 -> 988575 | J30: =+M30+O30+Q30+S30+U30+W30+Y30 -> 741033 | K30: =IF($Z$35=0,"",Z30/$Z$35) -> 0.0024947505 | L30: 917073 | M30: 730013 | N30: 21502 | O30: 1760 | P30: 50000 | Q30: 9260 | R30: 0 | S30: 0 | T30: 0 | U30: 0 | V30: 0 | W30: 0 | X30: 0 | Y30: 0 | Z30: =+I30+J30 -> 1729608
A31: 20 | B31: Уй-жой коммунал хизмати | C31: =+'Loans Receivable'!C58 -> 10242602 | D31: =IF(C$35=0,"",C31/C$35) -> 0.00021305072 | E31: 238287 | F31: =IF($E$35=0,"",E31/$E$35) -> 0.00072281441 | G31: 0 | H31: =IF($G$35=0,"",G31/$G$35) -> 0 | I31: =+L31+N31+P31+R31+T31+V31+X31 -> 888693 | J31: =+M31+O31+Q31+S31+U31+W31+Y31 -> 1029274 | K31: =IF($Z$35=0,"",Z31/$Z$35) -> 0.0027664356 | L31: 0 | M31: 346988 | N31: 20791 | O31: 10927 | P31: 17159 | Q31: 10029 | R31: 46086 | S31: 89136 | T31: 195722 | U31: 143457 | V31: 182126 | W31: 94110 | X31: 426809 | Y31: 334627 | Z31: =+I31+J31 -> 1917967
A32: 21 | B32: Бошқа соҳалар | C32: =+'Loans Receivable'!C70 -> 3115127146 | D32: =IF(C$35=0,"",C32/C$35) -> 0.064796044 | E32: 9968565 | F32: =IF($E$35=0,"",E32/$E$35) -> 0.03023842 | G32: 3024008 | H32: =IF($G$35=0,"",G32/$G$35) -> 0.019335921 | I32: =+L32+N32+P32+R32+T32+V32+X32 -> 18699570 | J32: =+M32+O32+Q32+S32+U32+W32+Y32 -> 13660407 | K32: =IF($Z$35=0,"",Z32/$Z$35) -> 0.046675355 | L32: 5295287 | M32: 6901721 | N32: 1062385 | O32: 605787 | P32: 1703972 | Q32: 454916 | R32: 1418685 | S32: 339974 | T32: 8109000 | U32: 5090450 | V32: 1110241 | W32: 267559 | X32: 0 | Y32: 0 | Z32: =+I32+J32 -> 32359977
A33: 22 | B33: Жисмоний шахслар | C33: =+'Loans Receivable'!C71 -> 5463367169 | D33: =IF(C$35=0,"",C33/C$35) -> 0.11364049 | E33: 9541830 | F33: =IF($E$35=0,"",E33/$E$35) -> 0.028943972 | G33: 1711326 | H33: =IF($G$35=0,"",G33/$G$35) -> 0.010942453 | I33: =+L33+N33+P33+R33+T33+V33+X33 -> 7346228 | J33: =+M33+O33+Q33+S33+U33+W33+Y33 -> 4378892 | K33: =IF($Z$35=0,"",Z33/$Z$35) -> 0.016912068 | L33: 1074616 | M33: 2473682 | N33: 813701 | O33: 336955 | P33: 674122 | Q33: 270739 | R33: 1466502 | S33: 348343 | T33: 2583601 | U33: 724568 | V33: 733686 | W33: 224605 | X33: 0 | Y33: 0 | Z33: =+I33+J33 -> 11725120
Z34: =+I34+J34 -> 0
A35: 23 | B35: Жами кредит ва лизинг суммаси | C35: =SUM(C25:C33) -> 48075884880 | D35: =IF(C$35=0,"",C35/C$35) -> 1 | E35: =SUM(E25:E33) -> 329665534 | F35: =IF($E$35=0,"",E35/$E$35) -> 1 | G35: =SUM(G25:G33) -> 156393275 | H35: =IF($G$35=0,"",G35/$G$35) -> 1 | I35: =SUM(I25:I33) -> 494296721 | J35: =SUM(J25:J33) -> 199002277 | K35: =IF($Z$35=0,"",Z35/$Z$35) -> 1 | L35: =SUM(L25:L33) -> 48132494 | M35: =SUM(M25:M33) -> 103827234 | N35: =SUM(N25:N33) -> 42704826 | O35: =SUM(O25:O33) -> 19620306 | P35: =SUM(P25:P33) -> 99210438 | Q35: =SUM(Q25:Q33) -> 8435566 | R35: =SUM(R25:R33) -> 132310600 | S35: =SUM(S25:S33) -> 23429363 | ... Y35: =SUM(Y25:Y33) -> 334627 | Z35: =+I35+J35 -> 693298998
B37: Бошқарув Раис имзоси:
B39: Бош бухгалтер имзоси:
G42: =+'[8]Bank Assets Analysis'!$S$31 -> 71465006

Sheet Asset Classification
A1: АКТИВЛАР СИФАТИ БЎЙИЧА ТАСНИФЛАНИШИ ТЎҒРИСИДА ҲИСОБОТ | Z1: 10-жадвал
B3: =+'Asset quality'!B3 -> "Ўзсаноатқурилишбанк" АТБ | U3: =+'Asset quality'!Q3 -> 44925 | AB3: =+'Asset quality'!T3 -> минг. сўмда
A4: № | B4: Кўрсаткичлар | C4: Жами суммаси | D4: шундан, хорижий валютада (экв. сўмда) | E4: Стандарт | F4: шундан, хорижий валютада (экв. сўмда) | G4: Стандарт активлар бўйича яратилган захиралар (1%) | H4: шундан, хорижий валютада (экв. сўмда) | I4: Субстандарт | J4: шундан, хорижий валютада (экв. сўмда) | K4: Махсус захиралар (мин 10%) | L4: шундан, хорижий валютада (экв. сўмда) | M4: Қониқарсиз | N4: шундан, хорижий валютада (экв. сўмда) | O4: Махсус захиралар (мин 25%) | P4: шундан, хорижий валютада (экв. сўмда) | Q4: Шубҳали | R4: шундан, хорижий валютада (экв. сўмда) | S4: Махсус захиралар (мин 50%) | T4: шундан, хорижий валютада (экв. сўмда) | U4: Умидсиз | V4: шундан, хорижий валютада (экв. сўмда) | W4: Махсус захиралар (мин 100%) | X4: шундан, хорижий валютада (экв. сўмда) | Y4: Жами махсус захиралар суммаси | Z4: шундан, хорижий валютада (экв. сўмда) | AA4: ҳисобот ойида балансдан ташқари ҳисобдан чиқарилган кредитлар | AB4: ҳисобот ойида балансдан ташқари қайтган кредитлар суммаси
A5: (А) | B5: (Б) | C5: (В) | D5: (В1) | E5: (Г) | F5: (Г1) | G5: (Д) | H5: (Д1) | I5: (Е) | J5: (Е1) | K5: (Ж) | L5: (Ж1) | M5: (З) | N5: (З1) | O5: (И) | P5: (И1) | Q5: (К) | R5: (К1) | S5: (Л) | T5: (Л1) | U5: (М) | V5: (М1) | W5: (Н) | X5: (Н1) | Y5: О=Ж+И+Л+Н | Z5: (О1)=(Ж1)+(И1)+(Л1)+(Н1) | AA5: П | AB5: Р
B6: Мижозлар тури бўйича
A7: 1 | B7: Марказий банк | C7: =E7+I7+M7+Q7+U7 -> 0 | D7: =F7+J7+N7+R7+V7 -> 0 | Y7: =+W7+S7+O7+K7 -> 0 | Z7: =+X7+T7+P7+L7 -> 0 | AC7: =+'Aging Analysis'!C9 -> 0
B8: шундан, таъминланмаган қисми | C8: =E8+I8+M8+Q8+U8 -> 0 | D8: =F8+J8+N8+R8+V8 -> 0 | Y8: =+W8+S8+O8+K8 -> 0 | Z8: =+X8+T8+P8+L8 -> 0
A9: 2 | B9: Бошқа банклар | C9: =E9+I9+M9+Q9+U9 -> 0 | D9: =F9+J9+N9+R9+V9 -> 0 | Y9: =+W9+S9+O9+K9 -> 0 | Z9: =+X9+T9+P9+L9 -> 0 | AC9: =+'Aging Analysis'!C10 -> 0
B10: шундан, таъминланмаган қисми | C10: =E10+I10+M10+Q10+U10 -> 0 | D10: =F10+J10+N10+R10+V10 -> 0 | Y10: =+W10+S10+O10+K10 -> 0 | Z10: =+X10+T10+P10+L10 -> 0
A11: 3 | B11: Ҳукумат | C11: =E11+I11+M11+Q11+U11 -> 0 | D11: =F11+J11+N11+R11+V11 -> 0 | Y11: =+W11+S11+O11+K11 -> 0 | Z11: =+X11+T11+P11+L11 -> 0 | AC11: =+'Aging Analysis'!C11 -> 0
B12: шундан, таъминланмаган қисми | C12: =E12+I12+M12+Q12+U12 -> 0 | D12: =F12+J12+N12+R12+V12 -> 0 | Y12: =+W12+S12+O12+K12 -> 0 | Z12: =+X12+T12+P12+L12 -> 0
A13: 4 | B13: Жисмоний шахслар | C13: =E13+I13+M13+Q13+U13 -> 5463367169 | D13: =F13+J13+N13+R13+V13 -> 0 | E13: 5326427523 | F13: 0 | G13: 53264275 | H13: 0 | I13: 86600966 | J13: 0 | K13: 8592799 | L13: 0 | M13: 25017834 | N13: 0 | O13: 6063606 | P13: 0 | Q13: 18412252 | R13: 0 | S13: 8853606 | T13: 0 | U13: 6908594 | V13: 0 | W13: 6238672 | X13: 0 | Y13: =+W13+S13+O13+K13 -> 29748683 | Z13: =+X13+T13+P13+L13 -> 0 | AA13: 0 | AB13: 16092828 | AC13: =+'Aging Analysis'!C12 -> 5463367169
B14: шундан, таъминланмаган қисми | C14: =E14+I14+M14+Q14+U14 -> 0 | D14: =F14+J14+N14+R14+V14 -> 0 | E14: 0 | F14: 0 | G14: 0 | H14: 0 | I14: 0 | J14: 0 | K14: 0 | L14: 0 | M14: 0 | N14: 0 | O14: 0 | P14: 0 | Q14: 0 | R14: 0 | S14: 0 | T14: 0 | U14: 0 | V14: 0 | W14: 0 | X14: 0 | Y14: =+W14+S14+O14+K14 -> 0 | Z14: =+X14+T14+P14+L14 -> 0
A15: 5 | B15: Давлат корхоналари | C15: =E15+I15+M15+Q15+U15 -> 14093170226 | D15: =F15+J15+N15+R15+V15 -> 9576038371 | E15: 13717203032 | F15: 9508685611 | G15: 110259025 | H15: 0 | I15: 375967194 | J15: 67352760 | K15: 37596719 | L15: 6735276 | M15: 0 | N15: 0 | O15: 0 | P15: 0 | Q15: 0 | R15: 0 | S15: 0 | T15: 0 | U15: 0 | V15: 0 | W15: 0 | X15: 0 | Y15: =+W15+S15+O15+K15 -> 37596719 | Z15: =+X15+T15+P15+L15 -> 6735276 | AA15: 0 | AB15: 0 | AC15: =+'Aging Analysis'!C13 -> 14093170226
B16: шундан, таъминланмаган қисми | C16: =E16+I16+M16+Q16+U16 -> 0 | D16: =F16+J16+N16+R16+V16 -> 0 | E16: 0 | F16: 0 | G16: 0 | H16: 0 | I16: 0 | J16: 0 | K16: 0 | L16: 0 | M16: 0 | N16: 0 | O16: 0 | P16: 0 | Q16: 0 | R16: 0 | S16: 0 | T16: 0 | U16: 0 | V16: 0 | W16: 0 | X16: 0 | Y16: =+W16+S16+O16+K16 -> 0 | Z16: =+X16+T16+P16+L16 -> 0
A17: 6 | B17: Қўшма ва чет эл капитали иштирокидаги корхоналар | C17: =E17+I17+M17+Q17+U17 -> 9080290501 | D17: =F17+J17+N17+R17+V17 -> 7941053189 | E17: 8484483815 | F17: 7364846691 | G17: 84844838 | H17: 0 | I17: 218058951 | J17: 217658951 | K17: 21805895 | L17: 21765895 | M17: 66012521 | N17: 46812333 | O17: 16503130 | P17: 11703083 | Q17: 302666165 | R17: 302666165 | S17: 151333083 | T17: 151333083 | U17: 9069049 | V17: 9069049 | W17: 9069049 | X17: 9069049 | Y17: =+W17+S17+O17+K17 -> 198711157 | Z17: =+X17+T17+P17+L17 -> 193871110 | AA17: 0 | AB17: 0 | AC17: =+'Aging Analysis'!C14 -> 9080290501
B18: шундан, таъминланмаган қисми | C18: =E18+I18+M18+Q18+U18 -> 0 | D18: =F18+J18+N18+R18+V18 -> 0 | E18: 0 | F18: 0 | G18: 0 | H18: 0 | I18: 0 | J18: 0 | K18: 0 | L18: 0 | M18: 0 | N18: 0 | O18: 0 | P18: 0 | Q18: 0 | R18: 0 | S18: 0 | T18: 0 | U18: 0 | V18: 0 | W18: 0 | X18: 0 | Y18: =+W18+S18+O18+K18 -> 0 | Z18: =+X18+T18+P18+L18 -> 0
A19: 7 | B19: Хусусий корхоналар | C19: =E19+I19+M19+Q19+U19 -> 19254967029 | D19: =F19+J19+N19+R19+V19 -> 13208485774 | E19: 16537850982 | F19: 11383471585 | G19: 165378510 | H19: 0 | I19: 1829878783 | J19: 1356486852 | K19: 182987879 | L19: 135648686 | M19: 335528940 | N19: 181918056 | O19: 82728319 | P19: 44413096 | Q19: 490888293 | R19: 252257337 | S19: 245440179 | T19: 126128669 | U19: 60820031 | V19: 34351944 | W19: 60820030 | X19: 34351944 | Y19: =+W19+S19+O19+K19 -> 571976407 | Z19: =+X19+T19+P19+L19 -> 340542395 | AA19: 926786525 | AB19: 46859020 | AC19: =+'Aging Analysis'!C15 -> 19254967029
B20: шундан, таъминланмаган қисми | C20: =E20+I20+M20+Q20+U20 -> 0 | D20: =F20+J20+N20+R20+V20 -> 0 | E20: 0 | F20: 0 | G20: 0 | H20: 0 | I20: 0 | J20: 0 | K20: 0 | L20: 0 | M20: 0 | N20: 0 | O20: 0 | P20: 0 | Q20: 0 | R20: 0 | S20: 0 | T20: 0 | U20: 0 | V20: 0 | W20: 0 | X20: 0 | Y20: =+W20+S20+O20+K20 -> 0 | Z20: =+X20+T20+P20+L20 -> 0
A21: 8 | B21: Фермер хўжалиги | C21: =E21+I21+M21+Q21+U21 -> 171788067 | D21: =F21+J21+N21+R21+V21 -> 102565310 | E21: 89223633 | F21: 50848569 | G21: 892236 | H21: 0 | I21: 45320594 | J21: 43464476 | K21: 4532059 | L21: 4346448 | M21: 9188880 | N21: 0 | O21: 2297220 | P21: 0 | Q21: 16591663 | R21: 8252265 | S21: 8295831 | T21: 4126132 | U21: 11463297 | V21: 0 | W21: 11463297 | X21: 0 | Y21: =+W21+S21+O21+K21 -> 26588407 | Z21: =+X21+T21+P21+L21 -> 8472580 | AA21: 0 | AB21: 5719014 | AC21: =+'Aging Analysis'!C16 -> 171788067
B22: шундан, таъминланмаган қисми | C22: =E22+I22+M22+Q22+U22 -> 0 | D22: =F22+J22+N22+R22+V22 -> 0 | E22: 0 | F22: 0 | G22: 0 | H22: 0 | I22: 0 | J22: 0 | K22: 0 | L22: 0 | M22: 0 | N22: 0 | O22: 0 | P22: 0 | Q22: 0 | R22: 0 | S22: 0 | T22: 0 | U22: 0 | V22: 0 | W22: 0 | X22: 0 | Y22: =+W22+S22+O22+K22 -> 0 | Z22: =+X22+T22+P22+L22 -> 0
A23: 9 | B23: Нобанк молиявий институтлар | C23: =E23+I23+M23+Q23+U23 -> 2059286 | D23: =F23+J23+N23+R23+V23 -> 0 | E23: 2059286 | F23: 0 | G23: 20593 | H23: 0 | I23: 0 | J23: 0 | K23: 0 | L23: 0 | M23: 0 | N23: 0 | O23: 0 | P23: 0 | Q23: 0 | R23: 0 | S23: 0 | T23: 0 | U23: 0 | V23: 0 | W23: 0 | X23: 0 | Y23: =+W23+S23+O23+K23 -> 0 | Z23: =+X23+T23+P23+L23 -> 0 | AA23: 0 | AB23: 0 | AC23: =+'Aging Analysis'!C17 -> 2059286
B24: шундан, таъминланмаган қисми | C24: =E24+I24+M24+Q24+U24 -> 0 | D24: =F24+J24+N24+R24+V24 -> 0 | E24: 0 | F24: 0 | G24: 0 | H24: 0 | I24: 0 | J24: 0 | K24: 0 | L24: 0 | M24: 0 | N24: 0 | O24: 0 | P24: 0 | Q24: 0 | R24: 0 | S24: 0 | T24: 0 | U24: 0 | V24: 0 | W24: 0 | X24: 0 | Y24: =+W24+S24+O24+K24 -> 0 | Z24: =+X24+T24+P24+L24 -> 0
A25: 10 | B25: Нодавлат нотижорат ташкилотлар | C25: =E25+I25+M25+Q25+U25 -> 10242602 | D25: =F25+J25+N25+R25+V25 -> 0 | E25: 3049477 | F25: 0 | G25: 30495 | H25: 0 | I25: 1074164 | J25: 0 | K25: 107416 | L25: 0 | M25: 1041035 | N25: 0 | O25: 195258 | P25: 0 | Q25: 1884435 | R25: 0 | S25: 882546 | T25: 0 | U25: 3193491 | V25: 0 | W25: 3006146 | X25: 0 | Y25: =+W25+S25+O25+K25 -> 4191366 | Z25: =+X25+T25+P25+L25 -> 0 | AA25: 0 | AB25: 1288476 | AC25: =+'Aging Analysis'!C18 -> 10242602
B26: шундан, таъминланмаган қисми | C26: =E26+I26+M26+Q26+U26 -> 0 | D26: =F26+J26+N26+R26+V26 -> 0 | Y26: =+W26+S26+O26+K26 -> 0 | Z26: =+X26+T26+P26+L26 -> 0
A27: 11 | B27: Бюджет ташкилотлари | C27: =E27+I27+M27+Q27+U27 -> 0 | D27: =F27+J27+N27+R27+V27 -> 0 | Y27: =+W27+S27+O27+K27 -> 0 | Z27: =+X27+T27+P27+L27 -> 0 | AA27: 0 | AB27: 0 | AC27: =+'Aging Analysis'!C19 -> 0
B28: шундан, таъминланмаган қисми | C28: =E28+I28+M28+Q28+U28 -> 0 | D28: =F28+J28+N28+R28+V28 -> 0 | Y28: =+W28+S28+O28+K28 -> 0 | Z28: =+X28+T28+P28+L28 -> 0
A29: 12 | B29: Бошқалар | C29: =E29+I29+M29+Q29+U29 -> 0 | D29: =F29+J29+N29+R29+V29 -> 0 | Y29: =+W29+S29+O29+K29 -> 0 | Z29: =+X29+T29+P29+L29 -> 0 | AA29: 0 | AB29: 386400 | AC29: =+'Aging Analysis'!C20 -> 0
B30: шундан, таъминланмаган қисми | C30: =E30+I30+M30+Q30+U30 -> 0 | D30: =F30+J30+N30+R30+V30 -> 0 | Y30: =+W30+S30+O30+K30 -> 0 | Z30: =+X30+T30+P30+L30 -> 0
A31: 13 | B31: Жами кредит ва лизинг суммаси | C31: =+C7+C9+C11+C13+C15+C17+C19+C21+C23+C25+C27+C29 -> 48075884880 | D31: =+D7+D9+D11+D13+D15+D17+D19+D21+D23+D25+D27+D29 -> 30828142644 | E31: =+E7+E9+E11+E13+E15+E17+E19+E21+E23+E25+E27+E29 -> 44160297748 | F31: =+F7+F9+F11+F13+F15+F17+F19+F21+F23+F25+F27+F29 -> 28307852456 | G31: =+G7+G9+G11+G13+G15+G17+G19+G21+G23+G25+G27+G29 -> 414689972 | H31: =+H7+H9+H11+H13+H15+H17+H19+H21+H23+H25+H27+H29 -> 0 | I31: =+I7+I9+I11+I13+I15+I17+I19+I21+I23+I25+I27+I29 -> 2556900652 | J31: =+J7+J9+J11+J13+J15+J17+J19+J21+J23+J25+J27+J29 -> 1684963039 | ... AB31: =+AB7+AB9+AB11+AB13+AB15+AB17+AB19+AB21+AB23+AB25+AB27+AB29 -> 70345738 | AC31: =+'Loans Receivable'!C85 -> 48075884880
B32: шундан, таъминланмаган қисми | C32: =+C8+C10+C12+C14+C16+C18+C20+C22+C24+C26+C28+C30 -> 0 | D32: =+D8+D10+D12+D14+D16+D18+D20+D22+D24+D26+D28+D30 -> 0 | E32: =+E8+E10+E12+E14+E16+E18+E20+E22+E24+E26+E28+E30 -> 0 | F32: =+F8+F10+F12+F14+F16+F18+F20+F22+F24+F26+F28+F30 -> 0 | G32: =+G8+G10+G12+G14+G16+G18+G20+G22+G24+G26+G28+G30 -> 0 | H32: =+H8+H10+H12+H14+H16+H18+H20+H22+H24+H26+H28+H30 -> 0 | I32: =+I8+I10+I12+I14+I16+I18+I20+I22+I24+I26+I28+I30 -> 0 | J32: =+J8+J10+J12+J14+J16+J18+J20+J22+J24+J26+J28+J30 -> 0 | ... Z32: =+Z8+Z10+Z12+Z14+Z16+Z18+Z20+Z22+Z24+Z26+Z28+Z30 -> 0
B33: Иқтисодиёт соҳалари бўйича
A35: 14 | B35: Саноат | C35: =E35+I35+M35+Q35+U35 -> 25973436689 | D35: =F35+J35+N35+R35+V35 -> 20452888759 | E35: 23956057531 | F35: 18751236268 | G35: 212647570 | H35: 0 | I35: 1243233736 | J35: 1012742617 | K35: 124323374 | L35: 101274262 | M35: 183401890 | N35: 163938428 | O35: 45850473 | P35: 40984608 | Q35: 558792549 | R35: 497220482 | S35: 279392307 | T35: 248610241 | U35: 31950983 | V35: 27750964 | W35: 31950983 | X35: 27750964 | Y35: =+W35+S35+O35+K35 -> 481517137 | Z35: =+X35+T35+P35+L35 -> 418620075 | AA35: 926786525 | AB35: 171235 | AC35: =+'Aging Analysis'!C25 -> 25973436689
B36: шундан, таъминланмаган қисми | C36: =E36+I36+M36+Q36+U36 -> 0 | D36: =F36+J36+N36+R36+V36 -> 0 | E36: 0 | F36: 0 | G36: 0 | H36: 0 | I36: 0 | J36: 0 | K36: 0 | L36: 0 | M36: 0 | N36: 0 | O36: 0 | P36: 0 | Q36: 0 | R36: 0 | S36: 0 | T36: 0 | U36: 0 | V36: 0 | W36: 0 | X36: 0 | Y36: =+W36+S36+O36+K36 -> 0 | Z36: =+X36+T36+P36+L36 -> 0
A37: 15 | B37: Қишлоқ хўжалиги | C37: =E37+I37+M37+Q37+U37 -> 4481661756 | D37: =F37+J37+N37+R37+V37 -> 2124875399 | E37: 3903598762 | F37: 1717697080 | G37: 39035988 | H37: 0 | I37: 437833588 | J37: 373231039 | K37: 43783359 | L37: 37323104 | M37: 38300230 | N37: 1622384 | O37: 9575058 | P37: 405596 | Q37: 80376744 | R37: 32324896 | S37: 40188372 | T37: 16162448 | U37: 21552432 | V37: 0 | W37: 21552432 | X37: 0 | Y37: =+W37+S37+O37+K37 -> 115099221 | Z37: =+X37+T37+P37+L37 -> 53891148 | AA37: 0 | AB37: 43302779 | AC37: =+'Aging Analysis'!C26 -> 4481661756
B38: шундан, таъминланмаган қисми | C38: =E38+I38+M38+Q38+U38 -> 0 | D38: =F38+J38+N38+R38+V38 -> 0 | E38: 0 | F38: 0 | G38: 0 | H38: 0 | I38: 0 | J38: 0 | K38: 0 | L38: 0 | M38: 0 | N38: 0 | O38: 0 | P38: 0 | Q38: 0 | R38: 0 | S38: 0 | T38: 0 | U38: 0 | V38: 0 | W38: 0 | X38: 0 | Y38: =+W38+S38+O38+K38 -> 0 | Z38: =+X38+T38+P38+L38 -> 0
A39: 16 | B39: Транспорт ва коммуникация | C39: =E39+I39+M39+Q39+U39 -> 3505300410 | D39: =F39+J39+N39+R39+V39 -> 3350270294 | E39: 3388441418 | F39: 3274590974 | G39: 33884414 | H39: 0 | I39: 85226351 | J39: 60007783 | K39: 8522635 | L39: 6000778 | M39: 8383679 | N39: 5124797 | O39: 2095920 | P39: 1281199 | Q39: 13866148 | R39: 1163926 | S39: 6933074 | T39: 581963 | U39: 9382814 | V39: 9382814 | W39: 9382814 | X39: 9382814 | Y39: =+W39+S39+O39+K39 -> 26934443 | Z39: =+X39+T39+P39+L39 -> 17246754 | AA39: 0 | AB39: 741143 | AC39: =+'Aging Analysis'!C27 -> 3505300410
B40: шундан, таъминланмаган қисми | C40: =E40+I40+M40+Q40+U40 -> 0 | D40: =F40+J40+N40+R40+V40 -> 0 | E40: 0 | F40: 0 | G40: 0 | H40: 0 | I40: 0 | J40: 0 | K40: 0 | L40: 0 | M40: 0 | N40: 0 | O40: 0 | P40: 0 | Q40: 0 | R40: 0 | S40: 0 | T40: 0 | U40: 0 | V40: 0 | W40: 0 | X40: 0 | Y40: =+W40+S40+O40+K40 -> 0 | Z40: =+X40+T40+P40+L40 -> 0
A41: 17 | B41: Қурилиш соҳаси | C41: =E41+I41+M41+Q41+U41 -> 1311223847 | D41: =F41+J41+N41+R41+V41 -> 792994893 | E41: 1150663799 | F41: 759231946 | G41: 11506638 | H41: 0 | I41: 53685917 | J41: 27589522 | K41: 5368592 | L41: 2758952 | M41: 3404956 | N41: 281898 | O41: 851239 | P41: 70474 | Q41: 100045006 | R41: 5891527 | S41: 50022503 | T41: 2945763 | U41: 3424169 | V41: 0 | W41: 3424169 | X41: 0 | Y41: =+W41+S41+O41+K41 -> 59666503 | Z41: =+X41+T41+P41+L41 -> 5775189 | AA41: 0 | AB41: 1615558 | AC41: =+'Aging Analysis'!C28 -> 1311223847
B42: шундан, таъминланмаган қисми | C42: =E42+I42+M42+Q42+U42 -> 0 | D42: =F42+J42+N42+R42+V42 -> 0 | E42: 0 | F42: 0 | G42: 0 | H42: 0 | I42: 0 | J42: 0 | K42: 0 | L42: 0 | M42: 0 | N42: 0 | O42: 0 | P42: 0 | Q42: 0 | R42: 0 | S42: 0 | T42: 0 | U42: 0 | V42: 0 | W42: 0 | X42: 0 | Y42: =+W42+S42+O42+K42 -> 0 | Z42: =+X42+T42+P42+L42 -> 0
A43: 18 | B43: Савдо ва умумий хизмат | C43: =E43+I43+M43+Q43+U43 -> 2888957110 | D43: =F43+J43+N43+R43+V43 -> 2066166704 | E43: 2538581387 | F43: 1875127540 | G43: 25385814 | H43: 0 | I43: 194341734 | J43: 124588010 | K43: 19434173 | L43: 12458801 | M43: 113009572 | N43: 39407159 | O43: 28252393 | P43: 9851790 | Q43: 33775945 | R43: 20756780 | S43: 16887972 | T43: 10378390 | U43: 9248472 | V43: 6287215 | W43: 9248472 | X43: 6287215 | Y43: =+W43+S43+O43+K43 -> 73823010 | Z43: =+X43+T43+P43+L43 -> 38976196 | AA43: 0 | AB43: 3044109 | AC43: =+'Aging Analysis'!C29 -> 2888957110
B44: шундан, таъминланмаган қисми | C44: =E44+I44+M44+Q44+U44 -> 0 | D44: =F44+J44+N44+R44+V44 -> 0 | E44: 0 | F44: 0 | G44: 0 | H44: 0 | I44: 0 | J44: 0 | K44: 0 | L44: 0 | M44: 0 | N44: 0 | O44: 0 | P44: 0 | Q44: 0 | R44: 0 | S44: 0 | T44: 0 | U44: 0 | V44: 0 | W44: 0 | X44: 0 | Y44: =+W44+S44+O44+K44 -> 0 | Z44: =+X44+T44+P44+L44 -> 0
A45: 19 | B45: Моддий ва техник таъминотни ривожлантириш | C45: =E45+I45+M45+Q45+U45 -> 1326568151 | D45: =F45+J45+N45+R45+V45 -> 25010543 | E45: 1310552678 | F45: 16254684 | G45: 13105527 | H45: 0 | I45: 6909614 | J45: 0 | K45: 690961 | L45: 0 | M45: 9105859 | N45: 8755859 | O45: 1122546 | P45: 1122546 | Q45: 0 | R45: 0 | S45: 0 | T45: 0 | U45: 0 | V45: 0 | W45: 0 | X45: 0 | Y45: =+W45+S45+O45+K45 -> 1813507 | Z45: =+X45+T45+P45+L45 -> 1122546 | AA45: 0 | AB45: 40572 | AC45: =+'Aging Analysis'!C30 -> 1326568151
B46: шундан, таъминланмаган қисми | C46: =E46+I46+M46+Q46+U46 -> 0 | D46: =F46+J46+N46+R46+V46 -> 0 | E46: 0 | F46: 0 | G46: 0 | H46: 0 | I46: 0 | J46: 0 | K46: 0 | L46: 0 | M46: 0 | N46: 0 | O46: 0 | P46: 0 | Q46: 0 | R46: 0 | S46: 0 | T46: 0 | U46: 0 | V46: 0 | W46: 0 | X46: 0 | Y46: =+W46+S46+O46+K46 -> 0 | Z46: =+X46+T46+P46+L46 -> 0
A47: 20 | B47: Уй-жой коммунал хизмати | C47: =E47+I47+M47+Q47+U47 -> 10242602 | D47: =F47+J47+N47+R47+V47 -> 0 | E47: 3049477 | F47: 0 | G47: 30495 | H47: 0 | I47: 1074164 | J47: 0 | K47: 107416 | L47: 0 | M47: 1041035 | N47: 0 | O47: 195258 | P47: 0 | Q47: 1884435 | R47: 0 | S47: 882546 | T47: 0 | U47: 3193491 | V47: 0 | W47: 3006146 | X47: 0 | Y47: =+W47+S47+O47+K47 -> 4191366 | Z47: =+X47+T47+P47+L47 -> 0 | AA47: 0 | AB47: 1288476 | AC47: =+'Aging Analysis'!C31 -> 10242602
B48: шундан, таъминланмаган қисми | C48: =E48+I48+M48+Q48+U48 -> 0 | D48: =F48+J48+N48+R48+V48 -> 0 | E48: 0 | F48: 0 | G48: 0 | H48: 0 | I48: 0 | J48: 0 | K48: 0 | L48: 0 | M48: 0 | N48: 0 | O48: 0 | P48: 0 | Q48: 0 | R48: 0 | S48: 0 | T48: 0 | U48: 0 | V48: 0 | W48: 0 | X48: 0 | Y48: =+W48+S48+O48+K48 -> 0 | Z48: =+X48+T48+P48+L48 -> 0
A49: 21 | B49: Бошқа соҳалар | C49: =E49+I49+M49+Q49+U49 -> 3115127146 | D49: =F49+J49+N49+R49+V49 -> 2015936052 | E49: 2582925173 | F49: 1913713964 | G49: 25829251 | H49: 0 | I49: 447994582 | J49: 86804068 | K49: 44799458 | L49: 8680408 | M49: 55124155 | N49: 9599864 | O49: 13781040 | P49: 2399966 | Q49: 23289729 | R49: 5818156 | S49: 11644865 | T49: 2909079 | U49: 5793507 | V49: 0 | W49: 5793506 | X49: 0 | Y49: =+W49+S49+O49+K49 -> 76018869 | Z49: =+X49+T49+P49+L49 -> 13989453 | AA49: 0 | AB49: 4049038 | AC49: =+'Aging Analysis'!C32 -> 3115127146
B50: шундан, таъминланмаган қисми | C50: =E50+I50+M50+Q50+U50 -> 0 | D50: =F50+J50+N50+R50+V50 -> 0 | E50: 0 | F50: 0 | G50: 0 | H50: 0 | I50: 0 | J50: 0 | K50: 0 | L50: 0 | M50: 0 | N50: 0 | O50: 0 | P50: 0 | Q50: 0 | R50: 0 | S50: 0 | T50: 0 | U50: 0 | V50: 0 | W50: 0 | X50: 0 | Y50: =+W50+S50+O50+K50 -> 0 | Z50: =+X50+T50+P50+L50 -> 0
A51: 22 | B51: Жисмоний шахслар | C51: =E51+I51+M51+Q51+U51 -> 5463367169 | D51: =F51+J51+N51+R51+V51 -> 0 | E51: 5326427523 | F51: 0 | G51: 53264275 | H51: 0 | I51: 86600966 | J51: 0 | K51: 8592799 | L51: 0 | M51: 25017834 | N51: 0 | O51: 6063606 | P51: 0 | Q51: 18412252 | R51: 0 | S51: 8853606 | T51: 0 | U51: 6908594 | V51: 0 | W51: 6238672 | X51: 0 | Y51: =+W51+S51+O51+K51 -> 29748683 | Z51: =+X51+T51+P51+L51 -> 0 | AA51: 0 | AB51: 16092828 | AC51: =+'Aging Analysis'!C33 -> 5463367169
B52: шундан, таъминланмаган қисми | C52: =E52+I52+M52+Q52+U52 -> 0 | D52: =F52+J52+N52+R52+V52 -> 0 | Y52: =+W52+S52+O52+K52 -> 0 | Z52: =+X52+T52+P52+L52 -> 0
A53: 23 | B53: Жами кредит ва лизинг суммаси | C53: =+C35+C37+C39+C41+C43+C45+C47+C49+C51 -> 48075884880 | D53: =+D35+D37+D39+D41+D43+D45+D47+D49+D51 -> 30828142644 | E53: =+E35+E37+E39+E41+E43+E45+E47+E49+E51 -> 44160297748 | F53: =+F35+F37+F39+F41+F43+F45+F47+F49+F51 -> 28307852456 | G53: =+G35+G37+G39+G41+G43+G45+G47+G49+G51 -> 414689972 | H53: =+H35+H37+H39+H41+H43+H45+H47+H49+H51 -> 0 | I53: =+I35+I37+I39+I41+I43+I45+I47+I49+I51 -> 2556900652 | J53: =+J35+J37+J39+J41+J43+J45+J47+J49+J51 -> 1684963039 | ... AB53: =+AB35+AB37+AB39+AB41+AB43+AB45+AB47+AB49+AB51 -> 70345738 | AC53: =+'Aging Analysis'!C35 -> 48075884880
B54: шундан, таъминланмаган қисми | C54: =E54+I54+M54+Q54+U54 -> 0 | D54: =+D36+D38+D40+D42+D44+D46+D48+D50+D52 -> 0 | E54: 0 | F54: 0 | G54: =+G36+G38+G40+G42+G44+G46+G48+G50+G52 -> 0 | H54: =+H36+H38+H40+H42+H44+H46+H48+H50+H52 -> 0 | I54: =+I36+I38+I40+I42+I44+I46+I48+I50+I52 -> 0 | J54: =+J36+J38+J40+J42+J44+J46+J48+J50+J52 -> 0 | K54: =+K36+K38+K40+K42+K44+K46+K48+K50+K52 -> 0 | L54: =+L36+L38+L40+L42+L44+L46+L48+L50+L52 -> 0 | M54: =+M36+M38+M40+M42+M44+M46+M48+M50+M52 -> 0 | N54: =+N36+N38+N40+N42+N44+N46+N48+N50+N52 -> 0 | ... AB54: =+AB36+AB38+AB40+AB42+AB44+AB46+AB48+AB50+AB52 -> 0
B55: Ҳудудлар қирқимида
A57: 24 | B57: Қорақалпоғистон Республикаси | C57: =E57+I57+M57+Q57+U57 -> 1609455410 | D57: =F57+J57+N57+R57+V57 -> 762257731 | E57: 1563148657 | F57: 746646348 | G57: 11072659 | H57: 0 | I57: 32482518 | J57: 14447457 | K57: 3244039 | L57: 1444746 | M57: 6808733 | N57: 0 | O57: 1702183 | P57: 0 | Q57: 6960712 | R57: 1163926 | S57: 3425026 | T57: 581963 | U57: 54790 | V57: 0 | W57: 54790 | X57: 0 | Y57: =+W57+S57+O57+K57 -> 8426038 | Z57: =+X57+T57+P57+L57 -> 2026709 | AA57: 0 | AB57: 39604505
A58: 25 | B58: Андижон вилояти | C58: =E58+I58+M58+Q58+U58 -> 1164312118 | D58: =F58+J58+N58+R58+V58 -> 721413632 | E58: 945578117 | F58: 555045506 | G58: 10254993 | H58: 0 | I58: 185854595 | J58: 154267901 | K58: 18568920 | L58: 15426790 | M58: 14531742 | N58: 9174922 | O58: 3624680 | P58: 2293731 | Q58: 6710429 | R58: 2925303 | S58: 3354940 | T58: 1462651 | U58: 11637235 | V58: 0 | W58: 11637235 | X58: 0 | Y58: =+W58+S58+O58+K58 -> 37185775 | Z58: =+X58+T58+P58+L58 -> 19183172 | AA58: 0 | AB58: 2355090
A59: 26 | B59: Бухоро вилояти | C59: =E59+I59+M59+Q59+U59 -> 1681535519 | D59: =F59+J59+N59+R59+V59 -> 1147783044 | E59: 1322950032 | F59: 901942901 | G59: 11745891 | H59: 0 | I59: 248858552 | J59: 172270296 | K59: 24885855 | L59: 17227030 | M59: 33081958 | N59: 28198628 | O59: 7102970 | P59: 5983238 | Q59: 60460173 | R59: 33967822 | S59: 30230086 | T59: 16983911 | U59: 16184804 | V59: 11403397 | W59: 16184804 | X59: 11403397 | Y59: =+W59+S59+O59+K59 -> 78403715 | Z59: =+X59+T59+P59+L59 -> 51597576 | AA59: 0 | AB59: 1989864
A60: 27 | B60: Жиззах вилояти | C60: =E60+I60+M60+Q60+U60 -> 1143106711 | D60: =F60+J60+N60+R60+V60 -> 779723418 | E60: 1116767407 | F60: 765428208 | G60: 10609211 | H60: 0 | I60: 15988883 | J60: 12769174 | K60: 1598751 | L60: 1276917 | M60: 5895379 | N60: 0 | O60: 1471630 | P60: 0 | Q60: 4336384 | R60: 1526036 | S60: 2168192 | T60: 763018 | U60: 118658 | V60: 0 | W60: 118658 | X60: 0 | Y60: =+W60+S60+O60+K60 -> 5357231 | Z60: =+X60+T60+P60+L60 -> 2039935 | AA60: 0 | AB60: 4204861
A61: 28 | B61: Қашқадарё вилояти | C61: =E61+I61+M61+Q61+U61 -> 1213232734 | D61: =F61+J61+N61+R61+V61 -> 249604507 | E61: 1080232255 | F61: 176970426 | G61: 14498781 | H61: 0 | I61: 122540249 | J61: 71990097 | K61: 12254025 | L61: 7199010 | M61: 7708222 | N61: 281898 | O61: 1905013 | P61: 70474 | Q61: 1777504 | R61: 362086 | S61: 780970 | T61: 181043 | U61: 974504 | V61: 0 | W61: 974504 | X61: 0 | Y61: =+W61+S61+O61+K61 -> 15914512 | Z61: =+X61+T61+P61+L61 -> 7450527 | AA61: 0 | AB61: 1761094
A62: 29 | B62: Навоий вилояти | C62: =E62+I62+M62+Q62+U62 -> 1300102322 | D62: =F62+J62+N62+R62+V62 -> 759172492 | E62: 1249883007 | F62: 750682363 | G62: 11790777 | H62: 0 | I62: 28063230 | J62: 6990083 | K62: 2806323 | L62: 699008 | M62: 19825663 | N62: 0 | O62: 4900131 | P62: 0 | Q62: 2141270 | R62: 1500046 | S62: 1070635 | T62: 750023 | U62: 189152 | V62: 0 | W62: 189152 | X62: 0 | Y62: =+W62+S62+O62+K62 -> 8966241 | Z62: =+X62+T62+P62+L62 -> 1449031 | AA62: 0 | AB62: 664480
A63: 30 | B63: Наманган вилояти | C63: =E63+I63+M63+Q63+U63 -> 662112229 | D63: =F63+J63+N63+R63+V63 -> 395478229 | E63: 400127582 | F63: 208736685 | G63: 4925718 | H63: 0 | I63: 229672343 | J63: 186447889 | K63: 22967234 | L63: 18644789 | M63: 1169582 | N63: 293655 | O63: 292395 | P63: 73414 | Q63: 25900607 | R63: 0 | S63: 12950304 | T63: 0 | U63: 5242115 | V63: 0 | W63: 5242115 | X63: 0 | Y63: =+W63+S63+O63+K63 -> 41452048 | Z63: =+X63+T63+P63+L63 -> 18718203 | AA63: 0 | AB63: 226507
A64: 31 | B64: Самарқанд вилояти | C64: =E64+I64+M64+Q64+U64 -> 1780027645 | D64: =F64+J64+N64+R64+V64 -> 1127987565 | E64: 1661081207 | F64: 1041005359 | G64: 12742160 | H64: 0 | I64: 103243447 | J64: 74124766 | K64: 10323469 | L64: 7412477 | M64: 2557424 | N64: 522812 | O64: 639356 | P64: 130703 | Q64: 4058476 | R64: 3265579 | S64: 2029238 | T64: 1632790 | U64: 9087091 | V64: 9069049 | W64: 9087091 | X64: 9069049 | Y64: =+W64+S64+O64+K64 -> 22079154 | Z64: =+X64+T64+P64+L64 -> 18245019 | AA64: 0 | AB64: 194839
A65: 32 | B65: Сурхондарё вилояти | C65: =E65+I65+M65+Q65+U65 -> 989325279 | D65: =F65+J65+N65+R65+V65 -> 344966652 | E65: 675112858 | F65: 96369727 | G65: 5848868 | H65: 0 | I65: 271661212 | J65: 226572660 | K65: 27165784 | L65: 22657266 | M65: 10756940 | N65: 8438205 | O65: 2689235 | P65: 2109551 | Q65: 24533068 | R65: 10218422 | S65: 12266534 | T65: 5109211 | U65: 7261201 | V65: 3367638 | W65: 7261199 | X65: 3367638 | Y65: =+W65+S65+O65+K65 -> 49382752 | Z65: =+X65+T65+P65+L65 -> 33243666 | AA65: 0 | AB65: 3486824
A66: 33 | B66: Сирдарё вилояти | C66: =E66+I66+M66+Q66+U66 -> 2106753229 | D66: =F66+J66+N66+R66+V66 -> 1377515551 | E66: 1788617469 | F66: 1142013251 | G66: 18700461 | H66: 0 | I66: 249212833 | J66: 191796389 | K66: 24921283 | L66: 19179639 | M66: 40908120 | N66: 24440931 | O66: 10227030 | P66: 6110233 | Q66: 25755025 | R66: 19264980 | S66: 12877513 | T66: 9632490 | U66: 2259782 | V66: 0 | W66: 2259782 | X66: 0 | Y66: =+W66+S66+O66+K66 -> 50285608 | Z66: =+X66+T66+P66+L66 -> 34922362 | AA66: 0 | AB66: 1800060
A67: 34 | B67: Тошкент шаҳар | C67: =E67+I67+M67+Q67+U67 -> 27440382717 | D67: =F67+J67+N67+R67+V67 -> 19050773520 | E67: 25950594298 | F67: 18171857227 | G67: 259258661 | H67: 0 | I67: 854580370 | J67: 456927377 | K67: 85413106 | L67: 45692738 | M67: 226059285 | N67: 106887764 | O67: 56430546 | P67: 26721941 | Q67: 384421176 | R67: 298936490 | S67: 191961782 | T67: 149468245 | U67: 24727588 | V67: 16164662 | W67: 23870322 | X67: 16164662 | Y67: =+W67+S67+O67+K67 -> 357675756 | Z67: =+X67+T67+P67+L67 -> 238047586 | AA67: 926786525 | AB67: 4864549
A68: 35 | B68: Тошкент вилояти | C68: =E68+I68+M68+Q68+U68 -> 3391807355 | D68: =F68+J68+N68+R68+V68 -> 1838243439 | E68: 3186466009 | F68: 1672749889 | G68: 23872359 | H68: 0 | I68: 48848166 | J68: 23872219 | K68: 4884810 | L68: 2387222 | M68: 22722517 | N68: 21970307 | O68: 5612282 | P68: 5492577 | Q68: 133410771 | R68: 119651024 | S68: 66701418 | T68: 59825512 | U68: 359892 | V68: 0 | W68: 359892 | X68: 0 | Y68: =+W68+S68+O68+K68 -> 77558402 | Z68: =+X68+T68+P68+L68 -> 67705311 | AA68: 0 | AB68: 1767420
... A70: 37 | B70: Хоразм вилояти | C70: =E70+I70+M70+Q70+U70 -> 1066881707 | D70: =F70+J70+N70+R70+V70 -> 654697368 | E70: 866257871 | F70: 584606274 | G70: 7014727 | H70: 0 | I70: 98500248 | J70: 42295748 | K70: 9849767 | L70: 4229575 | M70: 14959441 | N70: 2995731 | O70: 3739860 | P70: 748933 | Q70: 77026468 | R70: 23900621 | S70: 38513234 | T70: 11950311 | U70: 10137679 | V70: 898994 | W70: 10137679 | X70: 898994 | Y70: =+W70+S70+O70+K70 -> 62240540 | Z70: =+X70+T70+P70+L70 -> 17827813 | AA70: 0 | AB70: 6659996
A71: 38 | B71: Жами кредит ва лизинг суммаси | C71: =SUM(C57:C70) -> 48075884880 | D71: =SUM(D57:D70) -> 30828142644 | E71: =SUM(E57:E70) -> 44160297748 | F71: =SUM(F57:F70) -> 28307852456 | G71: =SUM(G57:G70) -> 414689972 | H71: =SUM(H57:H70) -> 0 | I71: =SUM(I57:I70) -> 2556900652 | J71: =SUM(J57:J70) -> 1684963039 | ... AB71: =SUM(AB57:AB70) -> 70345738 | AC71: =+'Loans Receivable'!C85 -> 48075884880
A72: 39 | B72: Бошқа таснифланган активлар | C72: =E72+I72+M72+Q72+U72 -> 10074076340 | D72: =F72+J72+N72+R72+V72 -> 0 | E72: ='Asset quality'!D12+'Asset quality'!D17+'Asset quality'!D47+'Asset quality'!D48+'Asset quality'!D49+'Asset quality'!D50+'Asset quality'!D53+'Asset quality'!D54+'Asset quality'!D58+'Asset quality'!D60 -> 9533205914 | G72: ='Asset quality'!P12+'Asset quality'!P17+'Asset quality'!P47+'Asset quality'!P48+'Asset quality'!P49+'Asset quality'!P50+'Asset quality'!P53+'Asset quality'!P54+'Asset quality'!P58+'Asset quality'!P60+'Asset quality'!P62+9 -> 131676235 | I72: ='Asset quality'!E12+'Asset quality'!E17+'Asset quality'!E47+'Asset quality'!E48+'Asset quality'!E49+'Asset quality'!E50+'Asset quality'!E53+'Asset quality'!E54+'Asset quality'!E58+'Asset quality'!E60 -> 134561356 | K72: ='Asset quality'!Q12+'Asset quality'!Q17+'Asset quality'!Q47+'Asset quality'!Q48+'Asset quality'!Q49+'Asset quality'!Q50+'Asset quality'!Q53+'Asset quality'!Q54+'Asset quality'!Q58+'Asset quality'!Q60+'Asset quality'!Q62 -> 131959139 | M72: ='Asset quality'!F12+'Asset quality'!F17+'Asset quality'!F47+'Asset quality'!F48+'Asset quality'!F49+'Asset quality'!F50+'Asset quality'!F53+'Asset quality'!F54+'Asset quality'!F58+'Asset quality'!F60 -> 70544135 | O72: ='Asset quality'!R12+'Asset quality'!R17+'Asset quality'!R47+'Asset quality'!R48+'Asset quality'!R49+'Asset quality'!R50+'Asset quality'!R53+'Asset quality'!R54+'Asset quality'!R58+'Asset quality'!R60+'Asset quality'!R62 -> 2030299 | Q72: ='Asset quality'!G12+'Asset quality'!G17+'Asset quality'!G47+'Asset quality'!G48+'Asset quality'!G49+'Asset quality'!G50+'Asset quality'!G53+'Asset quality'!G54+'Asset quality'!G58+'Asset quality'!G60 -> 169719529 | S72: ='Asset quality'!S12+'Asset quality'!S17+'Asset quality'!S47+'Asset quality'!S48+'Asset quality'!S49+'Asset quality'!S50+'Asset quality'!S53+'Asset quality'!S54+'Asset quality'!S58+'Asset quality'!S60+'Asset quality'!S62 -> 5284069 | U72: ='Asset quality'!H12+'Asset quality'!H17+'Asset quality'!H47+'Asset quality'!H48+'Asset quality'!H49+'Asset quality'!H50+'Asset quality'!H53+'Asset quality'!H54+'Asset quality'!H58+'Asset quality'!H60 -> 166045406 | W72: ='Asset quality'!T12+'Asset quality'!T17+'Asset quality'!T47+'Asset quality'!T48+'Asset quality'!T49+'Asset quality'!T50+'Asset quality'!T53+'Asset quality'!T54+'Asset quality'!T58+'Asset quality'!T60+'Asset quality'!T62 -> 132343370 | Y72: =+W72+S72+O72+K72 -> 271616877 | Z72: =+X72+T72+P72+L72 -> 0
B73: шундан, таъминланмаган қисми | C73: =E73+I73+M73+Q73+U73 -> 0 | D73: =F73+J73+N73+R73+V73 -> 0 | Y73: =+W73+S73+O73+K73 -> 0 | Z73: =+X73+T73+P73+L73 -> 0
A74: 40 | B74: Жами таснифланган активлар суммаси | C74: =+C53+C72 -> 58149961220 | D74: =+D53+D72 -> 30828142644 | E74: =+E53+E72 -> 53693503662 | F74: =+F53+F72 -> 28307852456 | G74: =+G53+G72 -> 546366207 | H74: =+H53+H72 -> 0 | I74: =+I53+I72 -> 2691462008 | J74: =+J53+J72 -> 1684963039 | ... AB74: =+AB53+AB72 -> 70345738
B76: Бошқарув Раис имзоси:
B78: Бош бухгалтер имзоси:
E80: =SUM('Asset quality'!D20:D46)+'Asset quality'!D16 -> 44160297748 | G80: =SUM('Asset quality'!P20:P46)+'Asset quality'!P16 -> 414689972 | I80: =SUM('Asset quality'!E20:E46)+'Asset quality'!E16 -> 2556900652 | K80: =SUM('Asset quality'!Q20:Q46)+'Asset quality'!Q16 -> 255622767 | M80: =SUM('Asset quality'!F20:F46)+'Asset quality'!F16 -> 436789210 | O80: =SUM('Asset quality'!R20:R46)+'Asset quality'!R16 -> 107787533 | Q80: =SUM('Asset quality'!G20:G46)+'Asset quality'!G16 -> 830442808 | S80: =SUM('Asset quality'!S20:S46)+'Asset quality'!S16 -> 414805245 | U80: =SUM('Asset quality'!H20:H46)+'Asset quality'!H16 -> 91454462 | W80: =SUM('Asset quality'!T20:T46)+'Asset quality'!T16 -> 90597194 | Y80: =+W80+S80+O80+K80 -> 868812739
G81: =+'Asset quality'!P9+'Asset quality'!P62 -> 546366207 | K81: =+'Asset quality'!Q9+'Asset quality'!Q62 -> 387581906 | O81: =+'Asset quality'!R9+'Asset quality'!R62 -> 109817832 | S81: =+'Asset quality'!S9+'Asset quality'!S62 -> 420089314 | W81: =+'Asset quality'!T9+'Asset quality'!T62 -> 222940564 | Y81: =+W81+S81+O81+K81 -> 1140429616
E82: =+E80-E53 -> 0 | G82: =+G80-G53 -> 0 | I82: =+I80-I53 -> 0 | K82: =+K80-K53 -> 0 | M82: =+M80-M53 -> 0 | O82: =+O80-O53 -> 0 | Q82: =+Q80-Q53 -> 0 | S82: =+S80-S53 -> 0 | U82: =+U80-U53 -> 0 | W82: =+W80-W53 -> 0 | Y82: =+Y80-Y53 -> 0
G83: =+G81-G74 -> 0 | K83: =+K81-K74 -> 0 | O83: =+O81-O74 -> 0 | S83: =+S81-S74 -> 0 | W83: =+W81-W74 -> 0 | Y83: =+Y81-Y74 -> 0

Sheet Asset Provisioning
A1: АКТИВЛАР ВА УЛАРНИНГ ТАСНИФИ БЎЙИЧА ШАКЛЛАНТИРИЛГАН ЗАХИРАЛАР | AT1: 10 А-жадвал
B3: =+'Asset quality'!B3 -> "Ўзсаноатқурилишбанк" АТБ | AH3: =+'Asset quality'!Q3 -> 44925 | AU3: =+'Asset quality'!T3 -> минг. сўмда
A4: № | B4: Кўрсаткичлар | C4: Жами суммаси | D4: шундан, хорижий валютада (экв. сўмда) | E4: Стандарт | F4: шундан, хорижий валютада (экв. сўмда) | G4: Стандарт активлар бўйича яратилган захиралар (мин 1%) | J4: Субстандарт | K4: шундан, хорижий валютада (экв. сўмда) | L4: Субстандарт активлар бўйича яратилган захиралар (мин 10%) | O4: шундан, хорижий валютада (экв. сўмда) | R4: Қониқарсиз | S4: шундан, хорижий валютада (экв. сўмда) | T4: Қониқарсиз активлар бўйича яратилган захиралар (мин 25%) | W4: шундан, хорижий валютада (экв. сўмда) | Z4: Шубҳали | AA4: шундан, хорижий валютада (экв. сўмда) | AB4: Шубҳали активлар бўйича яратилган захиралар (мин 50%) | AE4: шундан, хорижий валютада (экв. сўмда) | AH4: Умидсиз | AI4: шундан, хорижий валютада (экв. сўмда) | AJ4: Умидсиз активлар бўйича яратилган захиралар (мин 100%) | AM4: шундан, хорижий валютада (экв. сўмда) | AP4: Жами махсус захиралар суммаси | AS4: шундан, хорижий валютада (экв. сўмда)
G5: Ҳақиқатдан яратилган заҳира | H5: Яратилиши лозим бўлган заҳира | I5: Фарқи | L5: Ҳақиқатдан яратилган заҳира | M5: Яратилиши лозим бўлган заҳира | N5: Фарқи | O5: Ҳақиқатдан яратилган заҳира | P5: Яратилиши лозим бўлган заҳира | Q5: Фарқи | T5: Ҳақиқатдан яратилган заҳира | U5: Яратилиши лозим бўлган заҳира | V5: Фарқи | W5: Ҳақиқатдан яратилган заҳира | X5: Яратилиши лозим бўлган заҳира | Y5: Фарқи | AB5: Ҳақиқатдан яратилган заҳира | AC5: Яратилиши лозим бўлган заҳира | AD5: Фарқи | AE5: Ҳақиқатдан яратилган заҳира | AF5: Яратилиши лозим бўлган заҳира | AG5: Фарқи | AJ5: Ҳақиқатдан яратилган заҳира | AK5: Яратилиши лозим бўлган заҳира | AL5: Фарқи | AM5: Ҳақиқатдан яратилган заҳира | AN5: Яратилиши лозим бўлган заҳира | AO5: Фарқи | AP5: Ҳақиқатдан яратилган заҳира | AQ5: Яратилиши лозим бўлган заҳира | AR5: Фарқи | AS5: Ҳақиқатдан яратилган заҳира | AT5: Яратилиши лозим бўлган заҳира | AU5: Фарқи
B6: Мижозлар тури бўйича
A7: 1 | B7: Марказий банк | C7: =+'Asset Classification'!C7 -> 0 | D7: =+'Asset Classification'!D7 -> 0 | E7: =+'Asset Classification'!E7 -> 0 | F7: =+'Asset Classification'!F7 -> 0 | G7: =+'Asset Classification'!G7 -> 0 | H7: =+E7*1% -> 0 | I7: =+G7-H7 -> 0 | J7: =+'Asset Classification'!I7 -> 0 | K7: =+'Asset Classification'!J7 -> 0 | L7: =+'Asset Classification'!K7 -> 0 | M7: =+J7*10% -> 0 | N7: =+L7-M7 -> 0 | O7: =+'Asset Classification'!L7 -> 0 | P7: =+K7*10% -> 0 | Q7: =+O7-P7 -> 0 | R7: =+'Asset Classification'!M7 -> 0 | S7: =+'Asset Classification'!N7 -> 0 | T7: =+'Asset Classification'!O7 -> 0 | U7: =+R7*25% -> 0 | V7: =+T7-U7 -> 0 | W7: =+'Asset Classification'!P7 -> 0 | X7: =+S7*25% -> 0 | Y7: =+W7-X7 -> 0 | Z7: =+'Asset Classification'!Q7 -> 0 | AA7: =+'Asset Classification'!R7 -> 0 | AB7: =+'Asset Classification'!S7 -> 0 | AC7: =+Z7*50% -> 0 | AD7: =+AB7-AC7 -> 0 | AE7: =+'Asset Classification'!T7 -> 0 | AF7: =+AA7*50% -> 0 | AG7: =+AE7-AF7 -> 0 | AH7: =+'Asset Classification'!U7 -> 0 | AI7: =+'Asset Classification'!V7 -> 0 | AJ7: =+'Asset Classification'!W7 -> 0 | AK7: =+AH7*100% -> 0 | AL7: =+AJ7-AK7 -> 0 | AM7: =+'Asset Classification'!X7 -> 0 | AN7: =+AI7*100% -> 0 | AO7: =+AM7-AN7 -> 0 | AP7: =+L7+T7+AB7+AJ7 -> 0 | AQ7: =+M7+U7+AC7+AK7 -> 0 | AR7: =+AP7-AQ7 -> 0 | AS7: =+O7+W7+AE7+AM7 -> 0 | AT7: =+P7+X7+AF7+AN7 -> 0 | AU7: =+AS7-AT7 -> 0 | AV7: =+'Aging Analysis'!C9 -> 0
B8: шундан, таъминланмаган қисми | C8: =+'Asset Classification'!C8 -> 0 | D8: =+'Asset Classification'!D8 -> 0 | E8: =+'Asset Classification'!E8 -> 0 | F8: =+'Asset Classification'!F8 -> 0 | G8: =+'Asset Classification'!G8 -> 0 | H8: =+E8*1% -> 0 | I8: =+G8-H8 -> 0 | J8: =+'Asset Classification'!I8 -> 0 | K8: =+'Asset Classification'!J8 -> 0 | L8: =+'Asset Classification'!K8 -> 0 | M8: =+J8*10% -> 0 | N8: =+L8-M8 -> 0 | O8: =+'Asset Classification'!L8 -> 0 | P8: =+K8*10% -> 0 | Q8: =+O8-P8 -> 0 | R8: =+'Asset Classification'!M8 -> 0 | S8: =+'Asset Classification'!N8 -> 0 | T8: =+'Asset Classification'!O8 -> 0 | U8: =+R8*25% -> 0 | V8: =+T8-U8 -> 0 | W8: =+'Asset Classification'!P8 -> 0 | X8: =+S8*25% -> 0 | Y8: =+W8-X8 -> 0 | Z8: =+'Asset Classification'!Q8 -> 0 | AA8: =+'Asset Classification'!R8 -> 0 | AB8: =+'Asset Classification'!S8 -> 0 | AC8: =+Z8*50% -> 0 | AD8: =+AB8-AC8 -> 0 | AE8: =+'Asset Classification'!T8 -> 0 | AF8: =+AA8*50% -> 0 | AG8: =+AE8-AF8 -> 0 | AH8: =+'Asset Classification'!U8 -> 0 | AI8: =+'Asset Classification'!V8 -> 0 | AJ8: =+'Asset Classification'!W8 -> 0 | AK8: =+AH8*100% -> 0 | AL8: =+AJ8-AK8 -> 0 | AM8: =+'Asset Classification'!X8 -> 0 | AN8: =+AI8*100% -> 0 | AO8: =+AM8-AN8 -> 0 | AP8: =+L8+T8+AB8+AJ8 -> 0 | AQ8: =+M8+U8+AC8+AK8 -> 0 | AR8: =+AP8-AQ8 -> 0 | AS8: =+O8+W8+AE8+AM8 -> 0 | AT8: =+P8+X8+AF8+AN8 -> 0 | AU8: =+AS8-AT8 -> 0
A9: 2 | B9: Бошқа банклар | C9: =+'Asset Classification'!C9 -> 0 | D9: =+'Asset Classification'!D9 -> 0 | E9: =+'Asset Classification'!E9 -> 0 | F9: =+'Asset Classification'!F9 -> 0 | G9: =+'Asset Classification'!G9 -> 0 | H9: =+E9*1% -> 0 | I9: =+G9-H9 -> 0 | J9: =+'Asset Classification'!I9 -> 0 | K9: =+'Asset Classification'!J9 -> 0 | L9: =+'Asset Classification'!K9 -> 0 | M9: =+J9*10% -> 0 | N9: =+L9-M9 -> 0 | O9: =+'Asset Classification'!L9 -> 0 | P9: =+K9*10% -> 0 | Q9: =+O9-P9 -> 0 | R9: =+'Asset Classification'!M9 -> 0 | S9: =+'Asset Classification'!N9 -> 0 | T9: =+'Asset Classification'!O9 -> 0 | U9: =+R9*25% -> 0 | V9: =+T9-U9 -> 0 | W9: =+'Asset Classification'!P9 -> 0 | X9: =+S9*25% -> 0 | Y9: =+W9-X9 -> 0 | Z9: =+'Asset Classification'!Q9 -> 0 | AA9: =+'Asset Classification'!R9 -> 0 | AB9: =+'Asset Classification'!S9 -> 0 | AC9: =+Z9*50% -> 0 | AD9: =+AB9-AC9 -> 0 | AE9: =+'Asset Classification'!T9 -> 0 | AF9: =+AA9*50% -> 0 | AG9: =+AE9-AF9 -> 0 | AH9: =+'Asset Classification'!U9 -> 0 | AI9: =+'Asset Classification'!V9 -> 0 | AJ9: =+'Asset Classification'!W9 -> 0 | AK9: =+AH9*100% -> 0 | AL9: =+AJ9-AK9 -> 0 | AM9: =+'Asset Classification'!X9 -> 0 | AN9: =+AI9*100% -> 0 | AO9: =+AM9-AN9 -> 0 | AP9: =+L9+T9+AB9+AJ9 -> 0 | AQ9: =+M9+U9+AC9+AK9 -> 0 | AR9: =+AP9-AQ9 -> 0 | AS9: =+O9+W9+AE9+AM9 -> 0 | AT9: =+P9+X9+AF9+AN9 -> 0 | AU9: =+AS9-AT9 -> 0 | AV9: =+'Aging Analysis'!C10 -> 0
B10: шундан, таъминланмаган қисми | C10: =+'Asset Classification'!C10 -> 0 | D10: =+'Asset Classification'!D10 -> 0 | E10: =+'Asset Classification'!E10 -> 0 | F10: =+'Asset Classification'!F10 -> 0 | G10: =+'Asset Classification'!G10 -> 0 | H10: =+E10*1% -> 0 | I10: =+G10-H10 -> 0 | J10: =+'Asset Classification'!I10 -> 0 | K10: =+'Asset Classification'!J10 -> 0 | L10: =+'Asset Classification'!K10 -> 0 | M10: =+J10*10% -> 0 | N10: =+L10-M10 -> 0 | O10: =+'Asset Classification'!L10 -> 0 | P10: =+K10*10% -> 0 | Q10: =+O10-P10 -> 0 | R10: =+'Asset Classification'!M10 -> 0 | S10: =+'Asset Classification'!N10 -> 0 | T10: =+'Asset Classification'!O10 -> 0 | U10: =+R10*25% -> 0 | V10: =+T10-U10 -> 0 | W10: =+'Asset Classification'!P10 -> 0 | X10: =+S10*25% -> 0 | Y10: =+W10-X10 -> 0 | Z10: =+'Asset Classification'!Q10 -> 0 | AA10: =+'Asset Classification'!R10 -> 0 | AB10: =+'Asset Classification'!S10 -> 0 | AC10: =+Z10*50% -> 0 | AD10: =+AB10-AC10 -> 0 | AE10: =+'Asset Classification'!T10 -> 0 | AF10: =+AA10*50% -> 0 | AG10: =+AE10-AF10 -> 0 | AH10: =+'Asset Classification'!U10 -> 0 | AI10: =+'Asset Classification'!V10 -> 0 | AJ10: =+'Asset Classification'!W10 -> 0 | AK10: =+AH10*100% -> 0 | AL10: =+AJ10-AK10 -> 0 | AM10: =+'Asset Classification'!X10 -> 0 | AN10: =+AI10*100% -> 0 | AO10: =+AM10-AN10 -> 0 | AP10: =+L10+T10+AB10+AJ10 -> 0 | AQ10: =+M10+U10+AC10+AK10 -> 0 | AR10: =+AP10-AQ10 -> 0 | AS10: =+O10+W10+AE10+AM10 -> 0 | AT10: =+P10+X10+AF10+AN10 -> 0 | AU10: =+AS10-AT10 -> 0
A11: 3 | B11: Ҳукумат | C11: =+'Asset Classification'!C11 -> 0 | D11: =+'Asset Classification'!D11 -> 0 | E11: =+'Asset Classification'!E11 -> 0 | F11: =+'Asset Classification'!F11 -> 0 | G11: =+'Asset Classification'!G11 -> 0 | H11: =+E11*1% -> 0 | I11: =+G11-H11 -> 0 | J11: =+'Asset Classification'!I11 -> 0 | K11: =+'Asset Classification'!J11 -> 0 | L11: =+'Asset Classification'!K11 -> 0 | M11: =+J11*10% -> 0 | N11: =+L11-M11 -> 0 | O11: =+'Asset Classification'!L11 -> 0 | P11: =+K11*10% -> 0 | Q11: =+O11-P11 -> 0 | R11: =+'Asset Classification'!M11 -> 0 | S11: =+'Asset Classification'!N11 -> 0 | T11: =+'Asset Classification'!O11 -> 0 | U11: =+R11*25% -> 0 | V11: =+T11-U11 -> 0 | W11: =+'Asset Classification'!P11 -> 0 | X11: =+S11*25% -> 0 | Y11: =+W11-X11 -> 0 | Z11: =+'Asset Classification'!Q11 -> 0 | AA11: =+'Asset Classification'!R11 -> 0 | AB11: =+'Asset Classification'!S11 -> 0 | AC11: =+Z11*50% -> 0 | AD11: =+AB11-AC11 -> 0 | AE11: =+'Asset Classification'!T11 -> 0 | AF11: =+AA11*50% -> 0 | AG11: =+AE11-AF11 -> 0 | AH11: =+'Asset Classification'!U11 -> 0 | AI11: =+'Asset Classification'!V11 -> 0 | AJ11: =+'Asset Classification'!W11 -> 0 | AK11: =+AH11*100% -> 0 | AL11: =+AJ11-AK11 -> 0 | AM11: =+'Asset Classification'!X11 -> 0 | AN11: =+AI11*100% -> 0 | AO11: =+AM11-AN11 -> 0 | AP11: =+L11+T11+AB11+AJ11 -> 0 | AQ11: =+M11+U11+AC11+AK11 -> 0 | AR11: =+AP11-AQ11 -> 0 | AS11: =+O11+W11+AE11+AM11 -> 0 | AT11: =+P11+X11+AF11+AN11 -> 0 | AU11: =+AS11-AT11 -> 0 | AV11: =+'Aging Analysis'!C11 -> 0
B12: шундан, таъминланмаган қисми | C12: =+'Asset Classification'!C12 -> 0 | D12: =+'Asset Classification'!D12 -> 0 | E12: =+'Asset Classification'!E12 -> 0 | F12: =+'Asset Classification'!F12 -> 0 | G12: =+'Asset Classification'!G12 -> 0 | H12: =+E12*1% -> 0 | I12: =+G12-H12 -> 0 | J12: =+'Asset Classification'!I12 -> 0 | K12: =+'Asset Classification'!J12 -> 0 | L12: =+'Asset Classification'!K12 -> 0 | M12: =+J12*10% -> 0 | N12: =+L12-M12 -> 0 | O12: =+'Asset Classification'!L12 -> 0 | P12: =+K12*10% -> 0 | Q12: =+O12-P12 -> 0 | R12: =+'Asset Classification'!M12 -> 0 | S12: =+'Asset Classification'!N12 -> 0 | T12: =+'Asset Classification'!O12 -> 0 | U12: =+R12*25% -> 0 | V12: =+T12-U12 -> 0 | W12: =+'Asset Classification'!P12 -> 0 | X12: =+S12*25% -> 0 | Y12: =+W12-X12 -> 0 | Z12: =+'Asset Classification'!Q12 -> 0 | AA12: =+'Asset Classification'!R12 -> 0 | AB12: =+'Asset Classification'!S12 -> 0 | AC12: =+Z12*50% -> 0 | AD12: =+AB12-AC12 -> 0 | AE12: =+'Asset Classification'!T12 -> 0 | AF12: =+AA12*50% -> 0 | AG12: =+AE12-AF12 -> 0 | AH12: =+'Asset Classification'!U12 -> 0 | AI12: =+'Asset Classification'!V12 -> 0 | AJ12: =+'Asset Classification'!W12 -> 0 | AK12: =+AH12*100% -> 0 | AL12: =+AJ12-AK12 -> 0 | AM12: =+'Asset Classification'!X12 -> 0 | AN12: =+AI12*100% -> 0 | AO12: =+AM12-AN12 -> 0 | AP12: =+L12+T12+AB12+AJ12 -> 0 | AQ12: =+M12+U12+AC12+AK12 -> 0 | AR12: =+AP12-AQ12 -> 0 | AS12: =+O12+W12+AE12+AM12 -> 0 | AT12: =+P12+X12+AF12+AN12 -> 0 | AU12: =+AS12-AT12 -> 0
A13: 4 | B13: Жисмоний шахслар | C13: =+'Asset Classification'!C13 -> 5463367169 | D13: =+'Asset Classification'!D13 -> 0 | E13: =+'Asset Classification'!E13 -> 5326427523 | F13: =+'Asset Classification'!F13 -> 0 | G13: =+'Asset Classification'!G13 -> 53264275 | H13: =+E13*1% -> 53264275 | I13: =+G13-H13 -> -0.23 | J13: =+'Asset Classification'!I13 -> 86600966 | K13: =+'Asset Classification'!J13 -> 0 | L13: =+'Asset Classification'!K13 -> 8592799 | M13: =+J13*10% -> 8660096.6 | N13: =+L13-M13 -> -67297.6 | O13: =+'Asset Classification'!L13 -> 0 | P13: =+K13*10% -> 0 | Q13: =+O13-P13 -> 0 | R13: =+'Asset Classification'!M13 -> 25017834 | S13: =+'Asset Classification'!N13 -> 0 | T13: =+'Asset Classification'!O13 -> 6063606 | U13: =+R13*25% -> 6254458.5 | V13: =+T13-U13 -> -190852.5 | W13: =+'Asset Classification'!P13 -> 0 | X13: =+S13*25% -> 0 | Y13: =+W13-X13 -> 0 | Z13: =+'Asset Classification'!Q13 -> 18412252 | AA13: =+'Asset Classification'!R13 -> 0 | AB13: =+'Asset Classification'!S13 -> 8853606 | AC13: =+Z13*50% -> 9206126 | AD13: =+AB13-AC13 -> -352520 | AE13: =+'Asset Classification'!T13 -> 0 | AF13: =+AA13*50% -> 0 | AG13: =+AE13-AF13 -> 0 | AH13: =+'Asset Classification'!U13 -> 6908594 | AI13: =+'Asset Classification'!V13 -> 0 | AJ13: =+'Asset Classification'!W13 -> 6238672 | AK13: =+AH13*100% -> 6908594 | AL13: =+AJ13-AK13 -> -669922 | AM13: =+'Asset Classification'!X13 -> 0 | AN13: =+AI13*100% -> 0 | AO13: =+AM13-AN13 -> 0 | AP13: =+L13+T13+AB13+AJ13 -> 29748683 | AQ13: =+M13+U13+AC13+AK13 -> 31029275 | AR13: =+AP13-AQ13 -> -1280592.1 | AS13: =+O13+W13+AE13+AM13 -> 0 | AT13: =+P13+X13+AF13+AN13 -> 0 | AU13: =+AS13-AT13 -> 0 | AV13: =+'Aging Analysis'!C12 -> 5463367169
B14: шундан, таъминланмаган қисми | C14: =+'Asset Classification'!C14 -> 0 | D14: =+'Asset Classification'!D14 -> 0 | E14: =+'Asset Classification'!E14 -> 0 | F14: =+'Asset Classification'!F14 -> 0 | G14: =+'Asset Classification'!G14 -> 0 | H14: =+E14*1% -> 0 | I14: =+G14-H14 -> 0 | J14: =+'Asset Classification'!I14 -> 0 | K14: =+'Asset Classification'!J14 -> 0 | L14: =+'Asset Classification'!K14 -> 0 | M14: =+J14*10% -> 0 | N14: =+L14-M14 -> 0 | O14: =+'Asset Classification'!L14 -> 0 | P14: =+K14*10% -> 0 | Q14: =+O14-P14 -> 0 | R14: =+'Asset Classification'!M14 -> 0 | S14: =+'Asset Classification'!N14 -> 0 | T14: =+'Asset Classification'!O14 -> 0 | U14: =+R14*25% -> 0 | V14: =+T14-U14 -> 0 | W14: =+'Asset Classification'!P14 -> 0 | X14: =+S14*25% -> 0 | Y14: =+W14-X14 -> 0 | Z14: =+'Asset Classification'!Q14 -> 0 | AA14: =+'Asset Classification'!R14 -> 0 | AB14: =+'Asset Classification'!S14 -> 0 | AC14: =+Z14*50% -> 0 | AD14: =+AB14-AC14 -> 0 | AE14: =+'Asset Classification'!T14 -> 0 | AF14: =+AA14*50% -> 0 | AG14: =+AE14-AF14 -> 0 | AH14: =+'Asset Classification'!U14 -> 0 | AI14: =+'Asset Classification'!V14 -> 0 | AJ14: =+'Asset Classification'!W14 -> 0 | AK14: =+AH14*100% -> 0 | AL14: =+AJ14-AK14 -> 0 | AM14: =+'Asset Classification'!X14 -> 0 | AN14: =+AI14*100% -> 0 | AO14: =+AM14-AN14 -> 0 | AP14: =+L14+T14+AB14+AJ14 -> 0 | AQ14: =+M14+U14+AC14+AK14 -> 0 | AR14: =+AP14-AQ14 -> 0 | AS14: =+O14+W14+AE14+AM14 -> 0 | AT14: =+P14+X14+AF14+AN14 -> 0 | AU14: =+AS14-AT14 -> 0
A15: 5 | B15: Давлат корхоналари | C15: =+'Asset Classification'!C15 -> 14093170226 | D15: =+'Asset Classification'!D15 -> 9576038371 | E15: =+'Asset Classification'!E15 -> 13717203032 | F15: =+'Asset Classification'!F15 -> 9508685611 | G15: =+'Asset Classification'!G15 -> 110259025 | H15: =+E15*1% -> 1.3717203e+08 | I15: =+G15-H15 -> -26913005 | J15: =+'Asset Classification'!I15 -> 375967194 | K15: =+'Asset Classification'!J15 -> 67352760 | L15: =+'Asset Classification'!K15 -> 37596719 | M15: =+J15*10% -> 37596719 | N15: =+L15-M15 -> -0.4 | O15: =+'Asset Classification'!L15 -> 6735276 | P15: =+K15*10% -> 6735276 | Q15: =+O15-P15 -> 0 | R15: =+'Asset Classification'!M15 -> 0 | S15: =+'Asset Classification'!N15 -> 0 | T15: =+'Asset Classification'!O15 -> 0 | U15: =+R15*25% -> 0 | V15: =+T15-U15 -> 0 | W15: =+'Asset Classification'!P15 -> 0 | X15: =+S15*25% -> 0 | Y15: =+W15-X15 -> 0 | Z15: =+'Asset Classification'!Q15 -> 0 | AA15: =+'Asset Classification'!R15 -> 0 | AB15: =+'Asset Classification'!S15 -> 0 | AC15: =+Z15*50% -> 0 | AD15: =+AB15-AC15 -> 0 | AE15: =+'Asset Classification'!T15 -> 0 | AF15: =+AA15*50% -> 0 | AG15: =+AE15-AF15 -> 0 | AH15: =+'Asset Classification'!U15 -> 0 | AI15: =+'Asset Classification'!V15 -> 0 | AJ15: =+'Asset Classification'!W15 -> 0 | AK15: =+AH15*100% -> 0 | AL15: =+AJ15-AK15 -> 0 | AM15: =+'Asset Classification'!X15 -> 0 | AN15: =+AI15*100% -> 0 | AO15: =+AM15-AN15 -> 0 | AP15: =+L15+T15+AB15+AJ15 -> 37596719 | AQ15: =+M15+U15+AC15+AK15 -> 37596719 | AR15: =+AP15-AQ15 -> -0.4 | AS15: =+O15+W15+AE15+AM15 -> 6735276 | AT15: =+P15+X15+AF15+AN15 -> 6735276 | AU15: =+AS15-AT15 -> 0 | AV15: =+'Aging Analysis'!C13 -> 14093170226
B16: шундан, таъминланмаган қисми | C16: =+'Asset Classification'!C16 -> 0 | D16: =+'Asset Classification'!D16 -> 0 | E16: =+'Asset Classification'!E16 -> 0 | F16: =+'Asset Classification'!F16 -> 0 | G16: =+'Asset Classification'!G16 -> 0 | H16: =+E16*1% -> 0 | I16: =+G16-H16 -> 0 | J16: =+'Asset Classification'!I16 -> 0 | K16: =+'Asset Classification'!J16 -> 0 | L16: =+'Asset Classification'!K16 -> 0 | M16: =+J16*10% -> 0 | N16: =+L16-M16 -> 0 | O16: =+'Asset Classification'!L16 -> 0 | P16: =+K16*10% -> 0 | Q16: =+O16-P16 -> 0 | R16: =+'Asset Classification'!M16 -> 0 | S16: =+'Asset Classification'!N16 -> 0 | T16: =+'Asset Classification'!O16 -> 0 | U16: =+R16*25% -> 0 | V16: =+T16-U16 -> 0 | W16: =+'Asset Classification'!P16 -> 0 | X16: =+S16*25% -> 0 | Y16: =+W16-X16 -> 0 | Z16: =+'Asset Classification'!Q16 -> 0 | AA16: =+'Asset Classification'!R16 -> 0 | AB16: =+'Asset Classification'!S16 -> 0 | AC16: =+Z16*50% -> 0 | AD16: =+AB16-AC16 -> 0 | AE16: =+'Asset Classification'!T16 -> 0 | AF16: =+AA16*50% -> 0 | AG16: =+AE16-AF16 -> 0 | AH16: =+'Asset Classification'!U16 -> 0 | AI16: =+'Asset Classification'!V16 -> 0 | AJ16: =+'Asset Classification'!W16 -> 0 | AK16: =+AH16*100% -> 0 | AL16: =+AJ16-AK16 -> 0 | AM16: =+'Asset Classification'!X16 -> 0 | AN16: =+AI16*100% -> 0 | AO16: =+AM16-AN16 -> 0 | AP16: =+L16+T16+AB16+AJ16 -> 0 | AQ16: =+M16+U16+AC16+AK16 -> 0 | AR16: =+AP16-AQ16 -> 0 | AS16: =+O16+W16+AE16+AM16 -> 0 | AT16: =+P16+X16+AF16+AN16 -> 0 | AU16: =+AS16-AT16 -> 0
A17: 6 | B17: Қўшма ва чет эл капитали иштирокидаги корхоналар | C17: =+'Asset Classification'!C17 -> 9080290501 | D17: =+'Asset Classification'!D17 -> 7941053189 | E17: =+'Asset Classification'!E17 -> 8484483815 | F17: =+'Asset Classification'!F17 -> 7364846691 | G17: =+'Asset Classification'!G17 -> 84844838 | H17: =+E17*1% -> 84844838 | I17: =+G17-H17 -> -0.15000001 | J17: =+'Asset Classification'!I17 -> 218058951 | K17: =+'Asset Classification'!J17 -> 217658951 | L17: =+'Asset Classification'!K17 -> 21805895 | M17: =+J17*10% -> 21805895 | N17: =+L17-M17 -> -0.1 | O17: =+'Asset Classification'!L17 -> 21765895 | P17: =+K17*10% -> 21765895 | Q17: =+O17-P17 -> -0.1 | R17: =+'Asset Classification'!M17 -> 66012521 | S17: =+'Asset Classification'!N17 -> 46812333 | T17: =+'Asset Classification'!O17 -> 16503130 | U17: =+R17*25% -> 16503130 | V17: =+T17-U17 -> -0.25 | W17: =+'Asset Classification'!P17 -> 11703083 | X17: =+S17*25% -> 11703083 | Y17: =+W17-X17 -> -0.25 | Z17: =+'Asset Classification'!Q17 -> 302666165 | AA17: =+'Asset Classification'!R17 -> 302666165 | AB17: =+'Asset Classification'!S17 -> 151333083 | AC17: =+Z17*50% -> 1.5133308e+08 | AD17: =+AB17-AC17 -> 0.5 | AE17: =+'Asset Classification'!T17 -> 151333083 | AF17: =+AA17*50% -> 1.5133308e+08 | AG17: =+AE17-AF17 -> 0.5 | AH17: =+'Asset Classification'!U17 -> 9069049 | AI17: =+'Asset Classification'!V17 -> 9069049 | AJ17: =+'Asset Classification'!W17 -> 9069049 | AK17: =+AH17*100% -> 9069049 | AL17: =+AJ17-AK17 -> 0 | AM17: =+'Asset Classification'!X17 -> 9069049 | AN17: =+AI17*100% -> 9069049 | AO17: =+AM17-AN17 -> 0 | AP17: =+L17+T17+AB17+AJ17 -> 198711157 | AQ17: =+M17+U17+AC17+AK17 -> 1.9871116e+08 | AR17: =+AP17-AQ17 -> 0.15000001 | AS17: =+O17+W17+AE17+AM17 -> 193871110 | AT17: =+P17+X17+AF17+AN17 -> 1.9387111e+08 | AU17: =+AS17-AT17 -> 0.15000001 | AV17: =+'Aging Analysis'!C14 -> 9080290501
B18: шундан, таъминланмаган қисми | C18: =+'Asset Classification'!C18 -> 0 | D18: =+'Asset Classification'!D18 -> 0 | E18: =+'Asset Classification'!E18 -> 0 | F18: =+'Asset Classification'!F18 -> 0 | G18: =+'Asset Classification'!G18 -> 0 | H18: =+E18*1% -> 0 | I18: =+G18-H18 -> 0 | J18: =+'Asset Classification'!I18 -> 0 | K18: =+'Asset Classification'!J18 -> 0 | L18: =+'Asset Classification'!K18 -> 0 | M18: =+J18*10% -> 0 | N18: =+L18-M18 -> 0 | O18: =+'Asset Classification'!L18 -> 0 | P18: =+K18*10% -> 0 | Q18: =+O18-P18 -> 0 | R18: =+'Asset Classification'!M18 -> 0 | S18: =+'Asset Classification'!N18 -> 0 | T18: =+'Asset Classification'!O18 -> 0 | U18: =+R18*25% -> 0 | V18: =+T18-U18 -> 0 | W18: =+'Asset Classification'!P18 -> 0 | X18: =+S18*25% -> 0 | Y18: =+W18-X18 -> 0 | Z18: =+'Asset Classification'!Q18 -> 0 | AA18: =+'Asset Classification'!R18 -> 0 | AB18: =+'Asset Classification'!S18 -> 0 | AC18: =+Z18*50% -> 0 | AD18: =+AB18-AC18 -> 0 | AE18: =+'Asset Classification'!T18 -> 0 | AF18: =+AA18*50% -> 0 | AG18: =+AE18-AF18 -> 0 | AH18: =+'Asset Classification'!U18 -> 0 | AI18: =+'Asset Classification'!V18 -> 0 | AJ18: =+'Asset Classification'!W18 -> 0 | AK18: =+AH18*100% -> 0 | AL18: =+AJ18-AK18 -> 0 | AM18: =+'Asset Classification'!X18 -> 0 | AN18: =+AI18*100% -> 0 | AO18: =+AM18-AN18 -> 0 | AP18: =+L18+T18+AB18+AJ18 -> 0 | AQ18: =+M18+U18+AC18+AK18 -> 0 | AR18: =+AP18-AQ18 -> 0 | AS18: =+O18+W18+AE18+AM18 -> 0 | AT18: =+P18+X18+AF18+AN18 -> 0 | AU18: =+AS18-AT18 -> 0
A19: 7 | B19: Хусусий корхоналар | C19: =+'Asset Classification'!C19 -> 19254967029 | D19: =+'Asset Classification'!D19 -> 13208485774 | E19: =+'Asset Classification'!E19 -> 16537850982 | F19: =+'Asset Classification'!F19 -> 11383471585 | G19: =+'Asset Classification'!G19 -> 165378510 | H19: =+E19*1% -> 1.6537851e+08 | I19: =+G19-H19 -> 0.18000001 | J19: =+'Asset Classification'!I19 -> 1829878783 | K19: =+'Asset Classification'!J19 -> 1356486852 | L19: =+'Asset Classification'!K19 -> 182987879 | M19: =+J19*10% -> 1.8298788e+08 | N19: =+L19-M19 -> 0.69999999 | O19: =+'Asset Classification'!L19 -> 135648686 | P19: =+K19*10% -> 1.3564869e+08 | Q19: =+O19-P19 -> 0.79999998 | R19: =+'Asset Classification'!M19 -> 335528940 | S19: =+'Asset Classification'!N19 -> 181918056 | T19: =+'Asset Classification'!O19 -> 82728319 | U19: =+R19*25% -> 83882235 | V19: =+T19-U19 -> -1153916 | W19: =+'Asset Classification'!P19 -> 44413096 | X19: =+S19*25% -> 45479514 | Y19: =+W19-X19 -> -1066418 | Z19: =+'Asset Classification'!Q19 -> 490888293 | AA19: =+'Asset Classification'!R19 -> 252257337 | AB19: =+'Asset Classification'!S19 -> 245440179 | AC19: =+Z19*50% -> 2.4544415e+08 | AD19: =+AB19-AC19 -> -3967.5 | AE19: =+'Asset Classification'!T19 -> 126128669 | AF19: =+AA19*50% -> 1.2612867e+08 | AG19: =+AE19-AF19 -> 0.5 | AH19: =+'Asset Classification'!U19 -> 60820031 | AI19: =+'Asset Classification'!V19 -> 34351944 | AJ19: =+'Asset Classification'!W19 -> 60820030 | AK19: =+AH19*100% -> 60820031 | AL19: =+AJ19-AK19 -> -1 | AM19: =+'Asset Classification'!X19 -> 34351944 | AN19: =+AI19*100% -> 34351944 | AO19: =+AM19-AN19 -> 0 | AP19: =+L19+T19+AB19+AJ19 -> 571976407 | AQ19: =+M19+U19+AC19+AK19 -> 5.7313429e+08 | AR19: =+AP19-AQ19 -> -1157883.8 | AS19: =+O19+W19+AE19+AM19 -> 340542395 | AT19: =+P19+X19+AF19+AN19 -> 3.4160881e+08 | AU19: =+AS19-AT19 -> -1066416.7 | AV19: =+'Aging Analysis'!C15 -> 19254967029
B20: шундан, таъминланмаган қисми | C20: =+'Asset Classification'!C20 -> 0 | D20: =+'Asset Classification'!D20 -> 0 | E20: =+'Asset Classification'!E20 -> 0 | F20: =+'Asset Classification'!F20 -> 0 | G20: =+'Asset Classification'!G20 -> 0 | H20: =+E20*1% -> 0 | I20: =+G20-H20 -> 0 | J20: =+'Asset Classification'!I20 -> 0 | K20: =+'Asset Classification'!J20 -> 0 | L20: =+'Asset Classification'!K20 -> 0 | M20: =+J20*10% -> 0 | N20: =+L20-M20 -> 0 | O20: =+'Asset Classification'!L20 -> 0 | P20: =+K20*10% -> 0 | Q20: =+O20-P20 -> 0 | R20: =+'Asset Classification'!M20 -> 0 | S20: =+'Asset Classification'!N20 -> 0 | T20: =+'Asset Classification'!O20 -> 0 | U20: =+R20*25% -> 0 | V20: =+T20-U20 -> 0 | W20: =+'Asset Classification'!P20 -> 0 | X20: =+S20*25% -> 0 | Y20: =+W20-X20 -> 0 | Z20: =+'Asset Classification'!Q20 -> 0 | AA20: =+'Asset Classification'!R20 -> 0 | AB20: =+'Asset Classification'!S20 -> 0 | AC20: =+Z20*50% -> 0 | AD20: =+AB20-AC20 -> 0 | AE20: =+'Asset Classification'!T20 -> 0 | AF20: =+AA20*50% -> 0 | AG20: =+AE20-AF20 -> 0 | AH20: =+'Asset Classification'!U20 -> 0 | AI20: =+'Asset Classification'!V20 -> 0 | AJ20: =+'Asset Classification'!W20 -> 0 | AK20: =+AH20*100% -> 0 | AL20: =+AJ20-AK20 -> 0 | AM20: =+'Asset Classification'!X20 -> 0 | AN20: =+AI20*100% -> 0 | AO20: =+AM20-AN20 -> 0 | AP20: =+L20+T20+AB20+AJ20 -> 0 | AQ20: =+M20+U20+AC20+AK20 -> 0 | AR20: =+AP20-AQ20 -> 0 | AS20: =+O20+W20+AE20+AM20 -> 0 | AT20: =+P20+X20+AF20+AN20 -> 0 | AU20: =+AS20-AT20 -> 0
A21: 8 | B21: Фермер хўжалиги | C21: =+'Asset Classification'!C21 -> 171788067 | D21: =+'Asset Classification'!D21 -> 102565310 | E21: =+'Asset Classification'!E21 -> 89223633 | F21: =+'Asset Classification'!F21 -> 50848569 | G21: =+'Asset Classification'!G21 -> 892236 | H21: =+E21*1% -> 892236.33 | I21: =+G21-H21 -> -0.33 | J21: =+'Asset Classification'!I21 -> 45320594 | K21: =+'Asset Classification'!J21 -> 43464476 | L21: =+'Asset Classification'!K21 -> 4532059 | M21: =+J21*10% -> 4532059.4 | N21: =+L21-M21 -> -0.4 | O21: =+'Asset Classification'!L21 -> 4346448 | P21: =+K21*10% -> 4346447.6 | Q21: =+O21-P21 -> 0.4 | R21: =+'Asset Classification'!M21 -> 9188880 | S21: =+'Asset Classification'!N21 -> 0 | T21: =+'Asset Classification'!O21 -> 2297220 | U21: =+R21*25% -> 2297220 | V21: =+T21-U21 -> 0 | W21: =+'Asset Classification'!P21 -> 0 | X21: =+S21*25% -> 0 | Y21: =+W21-X21 -> 0 | Z21: =+'Asset Classification'!Q21 -> 16591663 | AA21: =+'Asset Classification'!R21 -> 8252265 | AB21: =+'Asset Classification'!S21 -> 8295831 | AC21: =+Z21*50% -> 8295831.5 | AD21: =+AB21-AC21 -> -0.5 | AE21: =+'Asset Classification'!T21 -> 4126132 | AF21: =+AA21*50% -> 4126132.5 | AG21: =+AE21-AF21 -> -0.5 | AH21: =+'Asset Classification'!U21 -> 11463297 | AI21: =+'Asset Classification'!V21 -> 0 | AJ21: =+'Asset Classification'!W21 -> 11463297 | AK21: =+AH21*100% -> 11463297 | AL21: =+AJ21-AK21 -> 0 | AM21: =+'Asset Classification'!X21 -> 0 | AN21: =+AI21*100% -> 0 | AO21: =+AM21-AN21 -> 0 | AP21: =+L21+T21+AB21+AJ21 -> 26588407 | AQ21: =+M21+U21+AC21+AK21 -> 26588408 | AR21: =+AP21-AQ21 -> -0.9 | AS21: =+O21+W21+AE21+AM21 -> 8472580 | AT21: =+P21+X21+AF21+AN21 -> 8472580.1 | AU21: =+AS21-AT21 -> -0.1 | AV21: =+'Aging Analysis'!C16 -> 171788067
B22: шундан, таъминланмаган қисми | C22: =+'Asset Classification'!C22 -> 0 | D22: =+'Asset Classification'!D22 -> 0 | E22: =+'Asset Classification'!E22 -> 0 | F22: =+'Asset Classification'!F22 -> 0 | G22: =+'Asset Classification'!G22 -> 0 | H22: =+E22*1% -> 0 | I22: =+G22-H22 -> 0 | J22: =+'Asset Classification'!I22 -> 0 | K22: =+'Asset Classification'!J22 -> 0 | L22: =+'Asset Classification'!K22 -> 0 | M22: =+J22*10% -> 0 | N22: =+L22-M22 -> 0 | O22: =+'Asset Classification'!L22 -> 0 | P22: =+K22*10% -> 0 | Q22: =+O22-P22 -> 0 | R22: =+'Asset Classification'!M22 -> 0 | S22: =+'Asset Classification'!N22 -> 0 | T22: =+'Asset Classification'!O22 -> 0 | U22: =+R22*25% -> 0 | V22: =+T22-U22 -> 0 | W22: =+'Asset Classification'!P22 -> 0 | X22: =+S22*25% -> 0 | Y22: =+W22-X22 -> 0 | Z22: =+'Asset Classification'!Q22 -> 0 | AA22: =+'Asset Classification'!R22 -> 0 | AB22: =+'Asset Classification'!S22 -> 0 | AC22: =+Z22*50% -> 0 | AD22: =+AB22-AC22 -> 0 | AE22: =+'Asset Classification'!T22 -> 0 | AF22: =+AA22*50% -> 0 | AG22: =+AE22-AF22 -> 0 | AH22: =+'Asset Classification'!U22 -> 0 | AI22: =+'Asset Classification'!V22 -> 0 | AJ22: =+'Asset Classification'!W22 -> 0 | AK22: =+AH22*100% -> 0 | AL22: =+AJ22-AK22 -> 0 | AM22: =+'Asset Classification'!X22 -> 0 | AN22: =+AI22*100% -> 0 | AO22: =+AM22-AN22 -> 0 | AP22: =+L22+T22+AB22+AJ22 -> 0 | AQ22: =+M22+U22+AC22+AK22 -> 0 | AR22: =+AP22-AQ22 -> 0 | AS22: =+O22+W22+AE22+AM22 -> 0 | AT22: =+P22+X22+AF22+AN22 -> 0 | AU22: =+AS22-AT22 -> 0
A23: 9 | B23: Нобанк молиявий институтлар | C23: =+'Asset Classification'!C23 -> 2059286 | D23: =+'Asset Classification'!D23 -> 0 | E23: =+'Asset Classification'!E23 -> 2059286 | F23: =+'Asset Classification'!F23 -> 0 | G23: =+'Asset Classification'!G23 -> 20593 | H23: =+E23*1% -> 20592.86 | I23: =+G23-H23 -> 0.14 | J23: =+'Asset Classification'!I23 -> 0 | K23: =+'Asset Classification'!J23 -> 0 | L23: =+'Asset Classification'!K23 -> 0 | M23: =+J23*10% -> 0 | N23: =+L23-M23 -> 0 | O23: =+'Asset Classification'!L23 -> 0 | P23: =+K23*10% -> 0 | Q23: =+O23-P23 -> 0 | R23: =+'Asset Classification'!M23 -> 0 | S23: =+'Asset Classification'!N23 -> 0 | T23: =+'Asset Classification'!O23 -> 0 | U23: =+R23*25% -> 0 | V23: =+T23-U23 -> 0 | W23: =+'Asset Classification'!P23 -> 0 | X23: =+S23*25% -> 0 | Y23: =+W23-X23 -> 0 | Z23: =+'Asset Classification'!Q23 -> 0 | AA23: =+'Asset Classification'!R23 -> 0 | AB23: =+'Asset Classification'!S23 -> 0 | AC23: =+Z23*50% -> 0 | AD23: =+AB23-AC23 -> 0 | AE23: =+'Asset Classification'!T23 -> 0 | AF23: =+AA23*50% -> 0 | AG23: =+AE23-AF23 -> 0 | AH23: =+'Asset Classification'!U23 -> 0 | AI23: =+'Asset Classification'!V23 -> 0 | AJ23: =+'Asset Classification'!W23 -> 0 | AK23: =+AH23*100% -> 0 | AL23: =+AJ23-AK23 -> 0 | AM23: =+'Asset Classification'!X23 -> 0 | AN23: =+AI23*100% -> 0 | AO23: =+AM23-AN23 -> 0 | AP23: =+L23+T23+AB23+AJ23 -> 0 | AQ23: =+M23+U23+AC23+AK23 -> 0 | AR23: =+AP23-AQ23 -> 0 | AS23: =+O23+W23+AE23+AM23 -> 0 | AT23: =+P23+X23+AF23+AN23 -> 0 | AU23: =+AS23-AT23 -> 0 | AV23: =+'Aging Analysis'!C17 -> 2059286
B24: шундан, таъминланмаган қисми | C24: =+'Asset Classification'!C24 -> 0 | D24: =+'Asset Classification'!D24 -> 0 | E24: =+'Asset Classification'!E24 -> 0 | F24: =+'Asset Classification'!F24 -> 0 | G24: =+'Asset Classification'!G24 -> 0 | H24: =+E24*1% -> 0 | I24: =+G24-H24 -> 0 | J24: =+'Asset Classification'!I24 -> 0 | K24: =+'Asset Classification'!J24 -> 0 | L24: =+'Asset Classification'!K24 -> 0 | M24: =+J24*10% -> 0 | N24: =+L24-M24 -> 0 | O24: =+'Asset Classification'!L24 -> 0 | P24: =+K24*10% -> 0 | Q24: =+O24-P24 -> 0 | R24: =+'Asset Classification'!M24 -> 0 | S24: =+'Asset Classification'!N24 -> 0 | T24: =+'Asset Classification'!O24 -> 0 | U24: =+R24*25% -> 0 | V24: =+T24-U24 -> 0 | W24: =+'Asset Classification'!P24 -> 0 | X24: =+S24*25% -> 0 | Y24: =+W24-X24 -> 0 | Z24: =+'Asset Classification'!Q24 -> 0 | AA24: =+'Asset Classification'!R24 -> 0 | AB24: =+'Asset Classification'!S24 -> 0 | AC24: =+Z24*50% -> 0 | AD24: =+AB24-AC24 -> 0 | AE24: =+'Asset Classification'!T24 -> 0 | AF24: =+AA24*50% -> 0 | AG24: =+AE24-AF24 -> 0 | AH24: =+'Asset Classification'!U24 -> 0 | AI24: =+'Asset Classification'!V24 -> 0 | AJ24: =+'Asset Classification'!W24 -> 0 | AK24: =+AH24*100% -> 0 | AL24: =+AJ24-AK24 -> 0 | AM24: =+'Asset Classification'!X24 -> 0 | AN24: =+AI24*100% -> 0 | AO24: =+AM24-AN24 -> 0 | AP24: =+L24+T24+AB24+AJ24 -> 0 | AQ24: =+M24+U24+AC24+AK24 -> 0 | AR24: =+AP24-AQ24 -> 0 | AS24: =+O24+W24+AE24+AM24 -> 0 | AT24: =+P24+X24+AF24+AN24 -> 0 | AU24: =+AS24-AT24 -> 0
A25: 10 | B25: Нодавлат нотижорат ташкилотлар | C25: =+'Asset Classification'!C25 -> 10242602 | D25: =+'Asset Classification'!D25 -> 0 | E25: =+'Asset Classification'!E25 -> 3049477 | F25: =+'Asset Classification'!F25 -> 0 | G25: =+'Asset Classification'!G25 -> 30495 | H25: =+E25*1% -> 30494.77 | I25: =+G25-H25 -> 0.23 | J25: =+'Asset Classification'!I25 -> 1074164 | K25: =+'Asset Classification'!J25 -> 0 | L25: =+'Asset Classification'!K25 -> 107416 | M25: =+J25*10% -> 107416.4 | N25: =+L25-M25 -> -0.4 | O25: =+'Asset Classification'!L25 -> 0 | P25: =+K25*10% -> 0 | Q25: =+O25-P25 -> 0 | R25: =+'Asset Classification'!M25 -> 1041035 | S25: =+'Asset Classification'!N25 -> 0 | T25: =+'Asset Classification'!O25 -> 195258 | U25: =+R25*25% -> 260258.75 | V25: =+T25-U25 -> -65000.75 | W25: =+'Asset Classification'!P25 -> 0 | X25: =+S25*25% -> 0 | Y25: =+W25-X25 -> 0 | Z25: =+'Asset Classification'!Q25 -> 1884435 | AA25: =+'Asset Classification'!R25 -> 0 | AB25: =+'Asset Classification'!S25 -> 882546 | AC25: =+Z25*50% -> 942217.5 | AD25: =+AB25-AC25 -> -59671.5 | AE25: =+'Asset Classification'!T25 -> 0 | AF25: =+AA25*50% -> 0 | AG25: =+AE25-AF25 -> 0 | AH25: =+'Asset Classification'!U25 -> 3193491 | AI25: =+'Asset Classification'!V25 -> 0 | AJ25: =+'Asset Classification'!W25 -> 3006146 | AK25: =+AH25*100% -> 3193491 | AL25: =+AJ25-AK25 -> -187345 | AM25: =+'Asset Classification'!X25 -> 0 | AN25: =+AI25*100% -> 0 | AO25: =+AM25-AN25 -> 0 | AP25: =+L25+T25+AB25+AJ25 -> 4191366 | AQ25: =+M25+U25+AC25+AK25 -> 4503383.7 | AR25: =+AP25-AQ25 -> -312017.65 | AS25: =+O25+W25+AE25+AM25 -> 0 | AT25: =+P25+X25+AF25+AN25 -> 0 | AU25: =+AS25-AT25 -> 0 | AV25: =+'Aging Analysis'!C18 -> 10242602
B26: шундан, таъминланмаган қисми | C26: =+'Asset Classification'!C26 -> 0 | D26: =+'Asset Classification'!D26 -> 0 | E26: =+'Asset Classification'!E26 -> 0 | F26: =+'Asset Classification'!F26 -> 0 | G26: =+'Asset Classification'!G26 -> 0 | H26: =+E26*1% -> 0 | I26: =+G26-H26 -> 0 | J26: =+'Asset Classification'!I26 -> 0 | K26: =+'Asset Classification'!J26 -> 0 | L26: =+'Asset Classification'!K26 -> 0 | M26: =+J26*10% -> 0 | N26: =+L26-M26 -> 0 | O26: =+'Asset Classification'!L26 -> 0 | P26: =+K26*10% -> 0 | Q26: =+O26-P26 -> 0 | R26: =+'Asset Classification'!M26 -> 0 | S26: =+'Asset Classification'!N26 -> 0 | T26: =+'Asset Classification'!O26 -> 0 | U26: =+R26*25% -> 0 | V26: =+T26-U26 -> 0 | W26: =+'Asset Classification'!P26 -> 0 | X26: =+S26*25% -> 0 | Y26: =+W26-X26 -> 0 | Z26: =+'Asset Classification'!Q26 -> 0 | AA26: =+'Asset Classification'!R26 -> 0 | AB26: =+'Asset Classification'!S26 -> 0 | AC26: =+Z26*50% -> 0 | AD26: =+AB26-AC26 -> 0 | AE26: =+'Asset Classification'!T26 -> 0 | AF26: =+AA26*50% -> 0 | AG26: =+AE26-AF26 -> 0 | AH26: =+'Asset Classification'!U26 -> 0 | AI26: =+'Asset Classification'!V26 -> 0 | AJ26: =+'Asset Classification'!W26 -> 0 | AK26: =+AH26*100% -> 0 | AL26: =+AJ26-AK26 -> 0 | AM26: =+'Asset Classification'!X26 -> 0 | AN26: =+AI26*100% -> 0 | AO26: =+AM26-AN26 -> 0 | AP26: =+L26+T26+AB26+AJ26 -> 0 | AQ26: =+M26+U26+AC26+AK26 -> 0 | AR26: =+AP26-AQ26 -> 0 | AS26: =+O26+W26+AE26+AM26 -> 0 | AT26: =+P26+X26+AF26+AN26 -> 0 | AU26: =+AS26-AT26 -> 0
A27: 11 | B27: Бюджет ташкилотлари | C27: =+'Asset Classification'!C27 -> 0 | D27: =+'Asset Classification'!D27 -> 0 | E27: =+'Asset Classification'!E27 -> 0 | F27: =+'Asset Classification'!F27 -> 0 | G27: =+'Asset Classification'!G27 -> 0 | H27: =+E27*1% -> 0 | I27: =+G27-H27 -> 0 | J27: =+'Asset Classification'!I27 -> 0 | K27: =+'Asset Classification'!J27 -> 0 | L27: =+'Asset Classification'!K27 -> 0 | M27: =+J27*10% -> 0 | N27: =+L27-M27 -> 0 | O27: =+'Asset Classification'!L27 -> 0 | P27: =+K27*10% -> 0 | Q27: =+O27-P27 -> 0 | R27: =+'Asset Classification'!M27 -> 0 | S27: =+'Asset Classification'!N27 -> 0 | T27: =+'Asset Classification'!O27 -> 0 | U27: =+R27*25% -> 0 | V27: =+T27-U27 -> 0 | W27: =+'Asset Classification'!P27 -> 0 | X27: =+S27*25% -> 0 | Y27: =+W27-X27 -> 0 | Z27: =+'Asset Classification'!Q27 -> 0 | AA27: =+'Asset Classification'!R27 -> 0 | AB27: =+'Asset Classification'!S27 -> 0 | AC27: =+Z27*50% -> 0 | AD27: =+AB27-AC27 -> 0 | AE27: =+'Asset Classification'!T27 -> 0 | AF27: =+AA27*50% -> 0 | AG27: =+AE27-AF27 -> 0 | AH27: =+'Asset Classification'!U27 -> 0 | AI27: =+'Asset Classification'!V27 -> 0 | AJ27: =+'Asset Classification'!W27 -> 0 | AK27: =+AH27*100% -> 0 | AL27: =+AJ27-AK27 -> 0 | AM27: =+'Asset Classification'!X27 -> 0 | AN27: =+AI27*100% -> 0 | AO27: =+AM27-AN27 -> 0 | AP27: =+L27+T27+AB27+AJ27 -> 0 | AQ27: =+M27+U27+AC27+AK27 -> 0 | AR27: =+AP27-AQ27 -> 0 | AS27: =+O27+W27+AE27+AM27 -> 0 | AT27: =+P27+X27+AF27+AN27 -> 0 | AU27: =+AS27-AT27 -> 0 | AV27: =+'Aging Analysis'!C19 -> 0
B28: шундан, таъминланмаган қисми | C28: =+'Asset Classification'!C28 -> 0 | D28: =+'Asset Classification'!D28 -> 0 | E28: =+'Asset Classification'!E28 -> 0 | F28: =+'Asset Classification'!F28 -> 0 | G28: =+'Asset Classification'!G28 -> 0 | H28: =+E28*1% -> 0 | I28: =+G28-H28 -> 0 | J28: =+'Asset Classification'!I28 -> 0 | K28: =+'Asset Classification'!J28 -> 0 | L28: =+'Asset Classification'!K28 -> 0 | M28: =+J28*10% -> 0 | N28: =+L28-M28 -> 0 | O28: =+'Asset Classification'!L28 -> 0 | P28: =+K28*10% -> 0 | Q28: =+O28-P28 -> 0 | R28: =+'Asset Classification'!M28 -> 0 | S28: =+'Asset Classification'!N28 -> 0 | T28: =+'Asset Classification'!O28 -> 0 | U28: =+R28*25% -> 0 | V28: =+T28-U28 -> 0 | W28: =+'Asset Classification'!P28 -> 0 | X28: =+S28*25% -> 0 | Y28: =+W28-X28 -> 0 | Z28: =+'Asset Classification'!Q28 -> 0 | AA28: =+'Asset Classification'!R28 -> 0 | AB28: =+'Asset Classification'!S28 -> 0 | AC28: =+Z28*50% -> 0 | AD28: =+AB28-AC28 -> 0 | AE28: =+'Asset Classification'!T28 -> 0 | AF28: =+AA28*50% -> 0 | AG28: =+AE28-AF28 -> 0 | AH28: =+'Asset Classification'!U28 -> 0 | AI28: =+'Asset Classification'!V28 -> 0 | AJ28: =+'Asset Classification'!W28 -> 0 | AK28: =+AH28*100% -> 0 | AL28: =+AJ28-AK28 -> 0 | AM28: =+'Asset Classification'!X28 -> 0 | AN28: =+AI28*100% -> 0 | AO28: =+AM28-AN28 -> 0 | AP28: =+L28+T28+AB28+AJ28 -> 0 | AQ28: =+M28+U28+AC28+AK28 -> 0 | AR28: =+AP28-AQ28 -> 0 | AS28: =+O28+W28+AE28+AM28 -> 0 | AT28: =+P28+X28+AF28+AN28 -> 0 | AU28: =+AS28-AT28 -> 0
A29: 12 | B29: Бошқалар | C29: =+'Asset Classification'!C29 -> 0 | D29: =+'Asset Classification'!D29 -> 0 | E29: =+'Asset Classification'!E29 -> 0 | F29: =+'Asset Classification'!F29 -> 0 | G29: =+'Asset Classification'!G29 -> 0 | H29: =+E29*1% -> 0 | I29: =+G29-H29 -> 0 | J29: =+'Asset Classification'!I29 -> 0 | K29: =+'Asset Classification'!J29 -> 0 | L29: =+'Asset Classification'!K29 -> 0 | M29: =+J29*10% -> 0 | N29: =+L29-M29 -> 0 | O29: =+'Asset Classification'!L29 -> 0 | P29: =+K29*10% -> 0 | Q29: =+O29-P29 -> 0 | R29: =+'Asset Classification'!M29 -> 0 | S29: =+'Asset Classification'!N29 -> 0 | T29: =+'Asset Classification'!O29 -> 0 | U29: =+R29*25% -> 0 | V29: =+T29-U29 -> 0 | W29: =+'Asset Classification'!P29 -> 0 | X29: =+S29*25% -> 0 | Y29: =+W29-X29 -> 0 | Z29: =+'Asset Classification'!Q29 -> 0 | AA29: =+'Asset Classification'!R29 -> 0 | AB29: =+'Asset Classification'!S29 -> 0 | AC29: =+Z29*50% -> 0 | AD29: =+AB29-AC29 -> 0 | AE29: =+'Asset Classification'!T29 -> 0 | AF29: =+AA29*50% -> 0 | AG29: =+AE29-AF29 -> 0 | AH29: =+'Asset Classification'!U29 -> 0 | AI29: =+'Asset Classification'!V29 -> 0 | AJ29: =+'Asset Classification'!W29 -> 0 | AK29: =+AH29*100% -> 0 | AL29: =+AJ29-AK29 -> 0 | AM29: =+'Asset Classification'!X29 -> 0 | AN29: =+AI29*100% -> 0 | AO29: =+AM29-AN29 -> 0 | AP29: =+L29+T29+AB29+AJ29 -> 0 | AQ29: =+M29+U29+AC29+AK29 -> 0 | AR29: =+AP29-AQ29 -> 0 | AS29: =+O29+W29+AE29+AM29 -> 0 | AT29: =+P29+X29+AF29+AN29 -> 0 | AU29: =+AS29-AT29 -> 0 | AV29: =+'Aging Analysis'!C20 -> 0
B30: шундан, таъминланмаган қисми | C30: =+'Asset Classification'!C30 -> 0 | D30: =+'Asset Classification'!D30 -> 0 | E30: =+'Asset Classification'!E30 -> 0 | F30: =+'Asset Classification'!F30 -> 0 | G30: =+'Asset Classification'!G30 -> 0 | H30: =+E30*1% -> 0 | I30: =+G30-H30 -> 0 | J30: =+'Asset Classification'!I30 -> 0 | K30: =+'Asset Classification'!J30 -> 0 | L30: =+'Asset Classification'!K30 -> 0 | M30: =+J30*10% -> 0 | N30: =+L30-M30 -> 0 | O30: =+'Asset Classification'!L30 -> 0 | P30: =+K30*10% -> 0 | Q30: =+O30-P30 -> 0 | R30: =+'Asset Classification'!M30 -> 0 | S30: =+'Asset Classification'!N30 -> 0 | T30: =+'Asset Classification'!O30 -> 0 | U30: =+R30*25% -> 0 | V30: =+T30-U30 -> 0 | W30: =+'Asset Classification'!P30 -> 0 | X30: =+S30*25% -> 0 | Y30: =+W30-X30 -> 0 | Z30: =+'Asset Classification'!Q30 -> 0 | AA30: =+'Asset Classification'!R30 -> 0 | AB30: =+'Asset Classification'!S30 -> 0 | AC30: =+Z30*50% -> 0 | AD30: =+AB30-AC30 -> 0 | AE30: =+'Asset Classification'!T30 -> 0 | AF30: =+AA30*50% -> 0 | AG30: =+AE30-AF30 -> 0 | AH30: =+'Asset Classification'!U30 -> 0 | AI30: =+'Asset Classification'!V30 -> 0 | AJ30: =+'Asset Classification'!W30 -> 0 | AK30: =+AH30*100% -> 0 | AL30: =+AJ30-AK30 -> 0 | AM30: =+'Asset Classification'!X30 -> 0 | AN30: =+AI30*100% -> 0 | AO30: =+AM30-AN30 -> 0 | AP30: =+L30+T30+AB30+AJ30 -> 0 | AQ30: =+M30+U30+AC30+AK30 -> 0 | AR30: =+AP30-AQ30 -> 0 | AS30: =+O30+W30+AE30+AM30 -> 0 | AT30: =+P30+X30+AF30+AN30 -> 0 | AU30: =+AS30-AT30 -> 0
A31: 13 | B31: Жами кредит ва лизинг суммаси | C31: =+'Asset Classification'!C31 -> 48075884880 | D31: =+'Asset Classification'!D31 -> 30828142644 | E31: =+'Asset Classification'!E31 -> 44160297748 | F31: =+'Asset Classification'!F31 -> 28307852456 | G31: =+'Asset Classification'!G31 -> 414689972 | H31: =+H7+H9+H11+H13+H15+H17+H19+H21+H23+H25+H27+H29 -> 4.4160298e+08 | I31: =+I7+I9+I11+I13+I15+I17+I19+I21+I23+I25+I27+I29 -> -26913005 | J31: =+'Asset Classification'!I31 -> 2556900652 | K31: =+'Asset Classification'!J31 -> 1684963039 | L31: =+'Asset Classification'!K31 -> 255622767 | M31: =+M7+M9+M11+M13+M15+M17+M19+M21+M23+M25+M27+M29 -> 2.5569007e+08 | N31: =+N7+N9+N11+N13+N15+N17+N19+N21+N23+N25+N27+N29 -> -67298.2 | O31: =+'Asset Classification'!L31 -> 168496305 | P31: =+P7+P9+P11+P13+P15+P17+P19+P21+P23+P25+P27+P29 -> 1.684963e+08 | Q31: =+Q7+Q9+Q11+Q13+Q15+Q17+Q19+Q21+Q23+Q25+Q27+Q29 -> 1.1 | R31: =+'Asset Classification'!M31 -> 436789210 | S31: =+'Asset Classification'!N31 -> 228730389 | T31: =+'Asset Classification'!O31 -> 107787533 | U31: =+U7+U9+U11+U13+U15+U17+U19+U21+U23+U25+U27+U29 -> 1.091973e+08 | V31: =+V7+V9+V11+V13+V15+V17+V19+V21+V23+V25+V27+V29 -> -1409769.5 | W31: =+'Asset Classification'!P31 -> 56116179 | X31: =+X7+X9+X11+X13+X15+X17+X19+X21+X23+X25+X27+X29 -> 57182597 | Y31: =+Y7+Y9+Y11+Y13+Y15+Y17+Y19+Y21+Y23+Y25+Y27+Y29 -> -1066418.2 | Z31: =+'Asset Classification'!Q31 -> 830442808 | AA31: =+'Asset Classification'!R31 -> 563175767 | AB31: =+'Asset Classification'!S31 -> 414805245 | AC31: =+AC7+AC9+AC11+AC13+AC15+AC17+AC19+AC21+AC23+AC25+AC27+AC29 -> 415221404 | AD31: =+AD7+AD9+AD11+AD13+AD15+AD17+AD19+AD21+AD23+AD25+AD27+AD29 -> -416159 | AE31: =+'Asset Classification'!T31 -> 281587884 | AF31: =+AF7+AF9+AF11+AF13+AF15+AF17+AF19+AF21+AF23+AF25+AF27+AF29 -> 2.8158788e+08 | AG31: =+AG7+AG9+AG11+AG13+AG15+AG17+AG19+AG21+AG23+AG25+AG27+AG29 -> 0.5 | AH31: =+'Asset Classification'!U31 -> 91454462 | AI31: =+'Asset Classification'!V31 -> 43420993 | AJ31: =+'Asset Classification'!W31 -> 90597194 | AK31: =+AK7+AK9+AK11+AK13+AK15+AK17+AK19+AK21+AK23+AK25+AK27+AK29 -> 91454462 | AL31: =+AL7+AL9+AL11+AL13+AL15+AL17+AL19+AL21+AL23+AL25+AL27+AL29 -> -857268 | AM31: =+'Asset Classification'!X31 -> 43420993 | AN31: =+AN7+AN9+AN11+AN13+AN15+AN17+AN19+AN21+AN23+AN25+AN27+AN29 -> 43420993 | AO31: =+AO7+AO9+AO11+AO13+AO15+AO17+AO19+AO21+AO23+AO25+AO27+AO29 -> 0 | AP31: =+AP7+AP9+AP11+AP13+AP15+AP17+AP19+AP21+AP23+AP25+AP27+AP29 -> 868812739 | AQ31: =+AQ7+AQ9+AQ11+AQ13+AQ15+AQ17+AQ19+AQ21+AQ23+AQ25+AQ27+AQ29 -> 8.7156323e+08 | AR31: =+AR7+AR9+AR11+AR13+AR15+AR17+AR19+AR21+AR23+AR25+AR27+AR29 -> -2750494.7 | AS31: =+AS7+AS9+AS11+AS13+AS15+AS17+AS19+AS21+AS23+AS25+AS27+AS29 -> 549621361 | AT31: =+AT7+AT9+AT11+AT13+AT15+AT17+AT19+AT21+AT23+AT25+AT27+AT29 -> 5.5068778e+08 | AU31: =+AU7+AU9+AU11+AU13+AU15+AU17+AU19+AU21+AU23+AU25+AU27+AU29 -> -1066416.7 | AV31: =+'Loans Receivable'!C85 -> 48075884880
B32: шундан, таъминланмаган қисми | C32: =+'Asset Classification'!C32 -> 0 | D32: =+'Asset Classification'!D32 -> 0 | E32: =+'Asset Classification'!E32 -> 0 | F32: =+'Asset Classification'!F32 -> 0 | G32: =+'Asset Classification'!G32 -> 0 | H32: =+E32*1% -> 0 | I32: =+G32-H32 -> 0 | J32: =+'Asset Classification'!I32 -> 0 | K32: =+'Asset Classification'!J32 -> 0 | L32: =+'Asset Classification'!K32 -> 0 | M32: =+J32*10% -> 0 | N32: =+L32-M32 -> 0 | O32: =+'Asset Classification'!L32 -> 0 | P32: =+K32*10% -> 0 | Q32: =+O32-P32 -> 0 | R32: =+'Asset Classification'!M32 -> 0 | S32: =+'Asset Classification'!N32 -> 0 | T32: =+'Asset Classification'!O32 -> 0 | U32: =+R32*25% -> 0 | V32: =+T32-U32 -> 0 | W32: =+'Asset Classification'!P32 -> 0 | X32: =+S32*25% -> 0 | Y32: =+W32-X32 -> 0 | Z32: =+'Asset Classification'!Q32 -> 0 | AA32: =+'Asset Classification'!R32 -> 0 | AB32: =+'Asset Classification'!S32 -> 0 | AC32: =+Z32*50% -> 0 | AD32: =+AB32-AC32 -> 0 | AE32: =+'Asset Classification'!T32 -> 0 | AF32: =+AA32*50% -> 0 | AG32: =+AE32-AF32 -> 0 | AH32: =+'Asset Classification'!U32 -> 0 | AI32: =+'Asset Classification'!V32 -> 0 | AJ32: =+'Asset Classification'!W32 -> 0 | AK32: =+AH32*100% -> 0 | AL32: =+AJ32-AK32 -> 0 | AM32: =+'Asset Classification'!X32 -> 0 | AN32: =+AI32*100% -> 0 | AO32: =+AM32-AN32 -> 0 | AP32: =+L32+T32+AB32+AJ32 -> 0 | AQ32: =+M32+U32+AC32+AK32 -> 0 | AR32: =+AP32-AQ32 -> 0 | AS32: =+O32+W32+AE32+AM32 -> 0 | AT32: =+P32+X32+AF32+AN32 -> 0 | AU32: =+AS32-AT32 -> 0
B33: Иқтисодиёт соҳалари бўйича
A35: 14 | B35: Саноат | C35: =+'Asset Classification'!C35 -> 25973436689 | D35: =+'Asset Classification'!D35 -> 20452888759 | E35: =+'Asset Classification'!E35 -> 23956057531 | F35: =+'Asset Classification'!F35 -> 18751236268 | G35: =+'Asset Classification'!G35 -> 212647570 | H35: =+E35*1% -> 2.3956058e+08 | I35: =+G35-H35 -> -26913005 | J35: =+'Asset Classification'!I35 -> 1243233736 | K35: =+'Asset Classification'!J35 -> 1012742617 | L35: =+'Asset Classification'!K35 -> 124323374 | M35: =+J35*10% -> 1.2432337e+08 | N35: =+L35-M35 -> 0.39999999 | O35: =+'Asset Classification'!L35 -> 101274262 | P35: =+K35*10% -> 1.0127426e+08 | Q35: =+O35-P35 -> 0.3 | R35: =+'Asset Classification'!M35 -> 183401890 | S35: =+'Asset Classification'!N35 -> 163938428 | T35: =+'Asset Classification'!O35 -> 45850473 | U35: =+R35*25% -> 45850472 | V35: =+T35-U35 -> 0.5 | W35: =+'Asset Classification'!P35 -> 40984608 | X35: =+S35*25% -> 40984607 | Y35: =+W35-X35 -> 1 | Z35: =+'Asset Classification'!Q35 -> 558792549 | AA35: =+'Asset Classification'!R35 -> 497220482 | AB35: =+'Asset Classification'!S35 -> 279392307 | AC35: =+Z35*50% -> 2.7939627e+08 | AD35: =+AB35-AC35 -> -3967.5 | AE35: =+'Asset Classification'!T35 -> 248610241 | AF35: =+AA35*50% -> 248610241 | AG35: =+AE35-AF35 -> 0 | AH35: =+'Asset Classification'!U35 -> 31950983 | AI35: =+'Asset Classification'!V35 -> 27750964 | AJ35: =+'Asset Classification'!W35 -> 31950983 | AK35: =+AH35*100% -> 31950983 | AL35: =+AJ35-AK35 -> 0 | AM35: =+'Asset Classification'!X35 -> 27750964 | AN35: =+AI35*100% -> 27750964 | AO35: =+AM35-AN35 -> 0 | AP35: =+L35+T35+AB35+AJ35 -> 481517137 | AQ35: =+M35+U35+AC35+AK35 -> 4.815211e+08 | AR35: =+AP35-AQ35 -> -3966.6 | AS35: =+O35+W35+AE35+AM35 -> 418620075 | AT35: =+P35+X35+AF35+AN35 -> 4.1862007e+08 | AU35: =+AS35-AT35 -> 1.3 | AV35: =+'Aging Analysis'!C25 -> 25973436689
B36: шундан, таъминланмаган қисми | C36: =+'Asset Classification'!C36 -> 0 | D36: =+'Asset Classification'!D36 -> 0 | E36: =+'Asset Classification'!E36 -> 0 | F36: =+'Asset Classification'!F36 -> 0 | G36: =+'Asset Classification'!G36 -> 0 | H36: =+E36*1% -> 0 | I36: =+G36-H36 -> 0 | J36: =+'Asset Classification'!I36 -> 0 | K36: =+'Asset Classification'!J36 -> 0 | L36: =+'Asset Classification'!K36 -> 0 | M36: =+J36*10% -> 0 | N36: =+L36-M36 -> 0 | O36: =+'Asset Classification'!L36 -> 0 | P36: =+K36*10% -> 0 | Q36: =+O36-P36 -> 0 | R36: =+'Asset Classification'!M36 -> 0 | S36: =+'Asset Classification'!N36 -> 0 | T36: =+'Asset Classification'!O36 -> 0 | U36: =+R36*25% -> 0 | V36: =+T36-U36 -> 0 | W36: =+'Asset Classification'!P36 -> 0 | X36: =+S36*25% -> 0 | Y36: =+W36-X36 -> 0 | Z36: =+'Asset Classification'!Q36 -> 0 | AA36: =+'Asset Classification'!R36 -> 0 | AB36: =+'Asset Classification'!S36 -> 0 | AC36: =+Z36*50% -> 0 | AD36: =+AB36-AC36 -> 0 | AE36: =+'Asset Classification'!T36 -> 0 | AF36: =+AA36*50% -> 0 | AG36: =+AE36-AF36 -> 0 | AH36: =+'Asset Classification'!U36 -> 0 | AI36: =+'Asset Classification'!V36 -> 0 | AJ36: =+'Asset Classification'!W36 -> 0 | AK36: =+AH36*100% -> 0 | AL36: =+AJ36-AK36 -> 0 | AM36: =+'Asset Classification'!X36 -> 0 | AN36: =+AI36*100% -> 0 | AO36: =+AM36-AN36 -> 0 | AP36: =+L36+T36+AB36+AJ36 -> 0 | AQ36: =+M36+U36+AC36+AK36 -> 0 | AR36: =+AP36-AQ36 -> 0 | AS36: =+O36+W36+AE36+AM36 -> 0 | AT36: =+P36+X36+AF36+AN36 -> 0 | AU36: =+AS36-AT36 -> 0
A37: 15 | B37: Қишлоқ хўжалиги | C37: =+'Asset Classification'!C37 -> 4481661756 | D37: =+'Asset Classification'!D37 -> 2124875399 | E37: =+'Asset Classification'!E37 -> 3903598762 | F37: =+'Asset Classification'!F37 -> 1717697080 | G37: =+'Asset Classification'!G37 -> 39035988 | H37: =+E37*1% -> 39035988 | I37: =+G37-H37 -> 0.38 | J37: =+'Asset Classification'!I37 -> 437833588 | K37: =+'Asset Classification'!J37 -> 373231039 | L37: =+'Asset Classification'!K37 -> 43783359 | M37: =+J37*10% -> 43783359 | N37: =+L37-M37 -> 0.2 | O37: =+'Asset Classification'!L37 -> 37323104 | P37: =+K37*10% -> 37323104 | Q37: =+O37-P37 -> 0.1 | R37: =+'Asset Classification'!M37 -> 38300230 | S37: =+'Asset Classification'!N37 -> 1622384 | T37: =+'Asset Classification'!O37 -> 9575058 | U37: =+R37*25% -> 9575057.5 | V37: =+T37-U37 -> 0.5 | W37: =+'Asset Classification'!P37 -> 405596 | X37: =+S37*25% -> 405596 | Y37: =+W37-X37 -> 0 | Z37: =+'Asset Classification'!Q37 -> 80376744 | AA37: =+'Asset Classification'!R37 -> 32324896 | AB37: =+'Asset Classification'!S37 -> 40188372 | AC37: =+Z37*50% -> 40188372 | AD37: =+AB37-AC37 -> 0 | AE37: =+'Asset Classification'!T37 -> 16162448 | AF37: =+AA37*50% -> 16162448 | AG37: =+AE37-AF37 -> 0 | AH37: =+'Asset Classification'!U37 -> 21552432 | AI37: =+'Asset Classification'!V37 -> 0 | AJ37: =+'Asset Classification'!W37 -> 21552432 | AK37: =+AH37*100% -> 21552432 | AL37: =+AJ37-AK37 -> 0 | AM37: =+'Asset Classification'!X37 -> 0 | AN37: =+AI37*100% -> 0 | AO37: =+AM37-AN37 -> 0 | AP37: =+L37+T37+AB37+AJ37 -> 115099221 | AQ37: =+M37+U37+AC37+AK37 -> 1.1509922e+08 | AR37: =+AP37-AQ37 -> 0.69999999 | AS37: =+O37+W37+AE37+AM37 -> 53891148 | AT37: =+P37+X37+AF37+AN37 -> 53891148 | AU37: =+AS37-AT37 -> 0.1 | AV37: =+'Aging Analysis'!C26 -> 4481661756
B38: шундан, таъминланмаган қисми | C38: =+'Asset Classification'!C38 -> 0 | D38: =+'Asset Classification'!D38 -> 0 | E38: =+'Asset Classification'!E38 -> 0 | F38: =+'Asset Classification'!F38 -> 0 | G38: =+'Asset Classification'!G38 -> 0 | H38: =+E38*1% -> 0 | I38: =+G38-H38 -> 0 | J38: =+'Asset Classification'!I38 -> 0 | K38: =+'Asset Classification'!J38 -> 0 | L38: =+'Asset Classification'!K38 -> 0 | M38: =+J38*10% -> 0 | N38: =+L38-M38 -> 0 | O38: =+'Asset Classification'!L38 -> 0 | P38: =+K38*10% -> 0 | Q38: =+O38-P38 -> 0 | R38: =+'Asset Classification'!M38 -> 0 | S38: =+'Asset Classification'!N38 -> 0 | T38: =+'Asset Classification'!O38 -> 0 | U38: =+R38*25% -> 0 | V38: =+T38-U38 -> 0 | W38: =+'Asset Classification'!P38 -> 0 | X38: =+S38*25% -> 0 | Y38: =+W38-X38 -> 0 | Z38: =+'Asset Classification'!Q38 -> 0 | AA38: =+'Asset Classification'!R38 -> 0 | AB38: =+'Asset Classification'!S38 -> 0 | AC38: =+Z38*50% -> 0 | AD38: =+AB38-AC38 -> 0 | AE38: =+'Asset Classification'!T38 -> 0 | AF38: =+AA38*50% -> 0 | AG38: =+AE38-AF38 -> 0 | AH38: =+'Asset Classification'!U38 -> 0 | AI38: =+'Asset Classification'!V38 -> 0 | AJ38: =+'Asset Classification'!W38 -> 0 | AK38: =+AH38*100% -> 0 | AL38: =+AJ38-AK38 -> 0 | AM38: =+'Asset Classification'!X38 -> 0 | AN38: =+AI38*100% -> 0 | AO38: =+AM38-AN38 -> 0 | AP38: =+L38+T38+AB38+AJ38 -> 0 | AQ38: =+M38+U38+AC38+AK38 -> 0 | AR38: =+AP38-AQ38 -> 0 | AS38: =+O38+W38+AE38+AM38 -> 0 | AT38: =+P38+X38+AF38+AN38 -> 0 | AU38: =+AS38-AT38 -> 0
A39: 16 | B39: Транспорт ва коммуникация | C39: =+'Asset Classification'!C39 -> 3505300410 | D39: =+'Asset Classification'!D39 -> 3350270294 | E39: =+'Asset Classification'!E39 -> 3388441418 | F39: =+'Asset Classification'!F39 -> 3274590974 | G39: =+'Asset Classification'!G39 -> 33884414 | H39: =+E39*1% -> 33884414 | I39: =+G39-H39 -> -0.18 | J39: =+'Asset Classification'!I39 -> 85226351 | K39: =+'Asset Classification'!J39 -> 60007783 | L39: =+'Asset Classification'!K39 -> 8522635 | M39: =+J39*10% -> 8522635.1 | N39: =+L39-M39 -> -0.1 | O39: =+'Asset Classification'!L39 -> 6000778 | P39: =+K39*10% -> 6000778.3 | Q39: =+O39-P39 -> -0.3 | R39: =+'Asset Classification'!M39 -> 8383679 | S39: =+'Asset Classification'!N39 -> 5124797 | T39: =+'Asset Classification'!O39 -> 2095920 | U39: =+R39*25% -> 2095919.8 | V39: =+T39-U39 -> 0.25 | W39: =+'Asset Classification'!P39 -> 1281199 | X39: =+S39*25% -> 1281199.2 | Y39: =+W39-X39 -> -0.25 | Z39: =+'Asset Classification'!Q39 -> 13866148 | AA39: =+'Asset Classification'!R39 -> 1163926 | AB39: =+'Asset Classification'!S39 -> 6933074 | AC39: =+Z39*50% -> 6933074 | AD39: =+AB39-AC39 -> 0 | AE39: =+'Asset Classification'!T39 -> 581963 | AF39: =+AA39*50% -> 581963 | AG39: =+AE39-AF39 -> 0 | AH39: =+'Asset Classification'!U39 -> 9382814 | AI39: =+'Asset Classification'!V39 -> 9382814 | AJ39: =+'Asset Classification'!W39 -> 9382814 | AK39: =+AH39*100% -> 9382814 | AL39: =+AJ39-AK39 -> 0 | AM39: =+'Asset Classification'!X39 -> 9382814 | AN39: =+AI39*100% -> 9382814 | AO39: =+AM39-AN39 -> 0 | AP39: =+L39+T39+AB39+AJ39 -> 26934443 | AQ39: =+M39+U39+AC39+AK39 -> 26934443 | AR39: =+AP39-AQ39 -> 0.15 | AS39: =+O39+W39+AE39+AM39 -> 17246754 | AT39: =+P39+X39+AF39+AN39 -> 17246755 | AU39: =+AS39-AT39 -> -0.55 | AV39: =+'Aging Analysis'!C27 -> 3505300410
B40: шундан, таъминланмаган қисми | C40: =+'Asset Classification'!C40 -> 0 | D40: =+'Asset Classification'!D40 -> 0 | E40: =+'Asset Classification'!E40 -> 0 | F40: =+'Asset Classification'!F40 -> 0 | G40: =+'Asset Classification'!G40 -> 0 | H40: =+E40*1% -> 0 | I40: =+G40-H40 -> 0 | J40: =+'Asset Classification'!I40 -> 0 | K40: =+'Asset Classification'!J40 -> 0 | L40: =+'Asset Classification'!K40 -> 0 | M40: =+J40*10% -> 0 | N40: =+L40-M40 -> 0 | O40: =+'Asset Classification'!L40 -> 0 | P40: =+K40*10% -> 0 | Q40: =+O40-P40 -> 0 | R40: =+'Asset Classification'!M40 -> 0 | S40: =+'Asset Classification'!N40 -> 0 | T40: =+'Asset Classification'!O40 -> 0 | U40: =+R40*25% -> 0 | V40: =+T40-U40 -> 0 | W40: =+'Asset Classification'!P40 -> 0 | X40: =+S40*25% -> 0 | Y40: =+W40-X40 -> 0 | Z40: =+'Asset Classification'!Q40 -> 0 | AA40: =+'Asset Classification'!R40 -> 0 | AB40: =+'Asset Classification'!S40 -> 0 | AC40: =+Z40*50% -> 0 | AD40: =+AB40-AC40 -> 0 | AE40: =+'Asset Classification'!T40 -> 0 | AF40: =+AA40*50% -> 0 | AG40: =+AE40-AF40 -> 0 | AH40: =+'Asset Classification'!U40 -> 0 | AI40: =+'Asset Classification'!V40 -> 0 | AJ40: =+'Asset Classification'!W40 -> 0 | AK40: =+AH40*100% -> 0 | AL40: =+AJ40-AK40 -> 0 | AM40: =+'Asset Classification'!X40 -> 0 | AN40: =+AI40*100% -> 0 | AO40: =+AM40-AN40 -> 0 | AP40: =+L40+T40+AB40+AJ40 -> 0 | AQ40: =+M40+U40+AC40+AK40 -> 0 | AR40: =+AP40-AQ40 -> 0 | AS40: =+O40+W40+AE40+AM40 -> 0 | AT40: =+P40+X40+AF40+AN40 -> 0 | AU40: =+AS40-AT40 -> 0
A41: 17 | B41: Қурилиш соҳаси | C41: =+'Asset Classification'!C41 -> 1311223847 | D41: =+'Asset Classification'!D41 -> 792994893 | E41: =+'Asset Classification'!E41 -> 1150663799 | F41: =+'Asset Classification'!F41 -> 759231946 | G41: =+'Asset Classification'!G41 -> 11506638 | H41: =+E41*1% -> 11506638 | I41: =+G41-H41 -> 0.0099999998 | J41: =+'Asset Classification'!I41 -> 53685917 | K41: =+'Asset Classification'!J41 -> 27589522 | L41: =+'Asset Classification'!K41 -> 5368592 | M41: =+J41*10% -> 5368591.7 | N41: =+L41-M41 -> 0.3 | O41: =+'Asset Classification'!L41 -> 2758952 | P41: =+K41*10% -> 2758952.2 | Q41: =+O41-P41 -> -0.2 | R41: =+'Asset Classification'!M41 -> 3404956 | S41: =+'Asset Classification'!N41 -> 281898 | T41: =+'Asset Classification'!O41 -> 851239 | U41: =+R41*25% -> 851239 | V41: =+T41-U41 -> 0 | W41: =+'Asset Classification'!P41 -> 70474 | X41: =+S41*25% -> 70474.5 | Y41: =+W41-X41 -> -0.5 | Z41: =+'Asset Classification'!Q41 -> 100045006 | AA41: =+'Asset Classification'!R41 -> 5891527 | AB41: =+'Asset Classification'!S41 -> 50022503 | AC41: =+Z41*50% -> 50022503 | AD41: =+AB41-AC41 -> 0 | AE41: =+'Asset Classification'!T41 -> 2945763 | AF41: =+AA41*50% -> 2945763.5 | AG41: =+AE41-AF41 -> -0.5 | AH41: =+'Asset Classification'!U41 -> 3424169 | AI41: =+'Asset Classification'!V41 -> 0 | AJ41: =+'Asset Classification'!W41 -> 3424169 | AK41: =+AH41*100% -> 3424169 | AL41: =+AJ41-AK41 -> 0 | AM41: =+'Asset Classification'!X41 -> 0 | AN41: =+AI41*100% -> 0 | AO41: =+AM41-AN41 -> 0 | AP41: =+L41+T41+AB41+AJ41 -> 59666503 | AQ41: =+M41+U41+AC41+AK41 -> 59666503 | AR41: =+AP41-AQ41 -> 0.3 | AS41: =+O41+W41+AE41+AM41 -> 5775189 | AT41: =+P41+X41+AF41+AN41 -> 5775190.2 | AU41: =+AS41-AT41 -> -1.2 | AV41: =+'Aging Analysis'!C28 -> 1311223847
B42: шундан, таъминланмаган қисми | C42: =+'Asset Classification'!C42 -> 0 | D42: =+'Asset Classification'!D42 -> 0 | E42: =+'Asset Classification'!E42 -> 0 | F42: =+'Asset Classification'!F42 -> 0 | G42: =+'Asset Classification'!G42 -> 0 | H42: =+E42*1% -> 0 | I42: =+G42-H42 -> 0 | J42: =+'Asset Classification'!I42 -> 0 | K42: =+'Asset Classification'!J42 -> 0 | L42: =+'Asset Classification'!K42 -> 0 | M42: =+J42*10% -> 0 | N42: =+L42-M42 -> 0 | O42: =+'Asset Classification'!L42 -> 0 | P42: =+K42*10% -> 0 | Q42: =+O42-P42 -> 0 | R42: =+'Asset Classification'!M42 -> 0 | S42: =+'Asset Classification'!N42 -> 0 | T42: =+'Asset Classification'!O42 -> 0 | U42: =+R42*25% -> 0 | V42: =+T42-U42 -> 0 | W42: =+'Asset Classification'!P42 -> 0 | X42: =+S42*25% -> 0 | Y42: =+W42-X42 -> 0 | Z42: =+'Asset Classification'!Q42 -> 0 | AA42: =+'Asset Classification'!R42 -> 0 | AB42: =+'Asset Classification'!S42 -> 0 | AC42: =+Z42*50% -> 0 | AD42: =+AB42-AC42 -> 0 | AE42: =+'Asset Classification'!T42 -> 0 | AF42: =+AA42*50% -> 0 | AG42: =+AE42-AF42 -> 0 | AH42: =+'Asset Classification'!U42 -> 0 | AI42: =+'Asset Classification'!V42 -> 0 | AJ42: =+'Asset Classification'!W42 -> 0 | AK42: =+AH42*100% -> 0 | AL42: =+AJ42-AK42 -> 0 | AM42: =+'Asset Classification'!X42 -> 0 | AN42: =+AI42*100% -> 0 | AO42: =+AM42-AN42 -> 0 | AP42: =+L42+T42+AB42+AJ42 -> 0 | AQ42: =+M42+U42+AC42+AK42 -> 0 | AR42: =+AP42-AQ42 -> 0 | AS42: =+O42+W42+AE42+AM42 -> 0 | AT42: =+P42+X42+AF42+AN42 -> 0 | AU42: =+AS42-AT42 -> 0
A43: 18 | B43: Савдо ва умумий хизмат | C43: =+'Asset Classification'!C43 -> 2888957110 | D43: =+'Asset Classification'!D43 -> 2066166704 | E43: =+'Asset Classification'!E43 -> 2538581387 | F43: =+'Asset Classification'!F43 -> 1875127540 | G43: =+'Asset Classification'!G43 -> 25385814 | H43: =+E43*1% -> 25385814 | I43: =+G43-H43 -> 0.13 | J43: =+'Asset Classification'!I43 -> 194341734 | K43: =+'Asset Classification'!J43 -> 124588010 | L43: =+'Asset Classification'!K43 -> 19434173 | M43: =+J43*10% -> 19434173 | N43: =+L43-M43 -> -0.4 | O43: =+'Asset Classification'!L43 -> 12458801 | P43: =+K43*10% -> 12458801 | Q43: =+O43-P43 -> 0 | R43: =+'Asset Classification'!M43 -> 113009572 | S43: =+'Asset Classification'!N43 -> 39407159 | T43: =+'Asset Classification'!O43 -> 28252393 | U43: =+R43*25% -> 28252393 | V43: =+T43-U43 -> 0 | W43: =+'Asset Classification'!P43 -> 9851790 | X43: =+S43*25% -> 9851789.8 | Y43: =+W43-X43 -> 0.25 | Z43: =+'Asset Classification'!Q43 -> 33775945 | AA43: =+'Asset Classification'!R43 -> 20756780 | AB43: =+'Asset Classification'!S43 -> 16887972 | AC43: =+Z43*50% -> 16887972 | AD43: =+AB43-AC43 -> -0.5 | AE43: =+'Asset Classification'!T43 -> 10378390 | AF43: =+AA43*50% -> 10378390 | AG43: =+AE43-AF43 -> 0 | AH43: =+'Asset Classification'!U43 -> 9248472 | AI43: =+'Asset Classification'!V43 -> 6287215 | AJ43: =+'Asset Classification'!W43 -> 9248472 | AK43: =+AH43*100% -> 9248472 | AL43: =+AJ43-AK43 -> 0 | AM43: =+'Asset Classification'!X43 -> 6287215 | AN43: =+AI43*100% -> 6287215 | AO43: =+AM43-AN43 -> 0 | AP43: =+L43+T43+AB43+AJ43 -> 73823010 | AQ43: =+M43+U43+AC43+AK43 -> 73823011 | AR43: =+AP43-AQ43 -> -0.90000001 | AS43: =+O43+W43+AE43+AM43 -> 38976196 | AT43: =+P43+X43+AF43+AN43 -> 38976196 | AU43: =+AS43-AT43 -> 0.25 | AV43: =+'Aging Analysis'!C29 -> 2888957110
B44: шундан, таъминланмаган қисми | C44: =+'Asset Classification'!C44 -> 0 | D44: =+'Asset Classification'!D44 -> 0 | E44: =+'Asset Classification'!E44 -> 0 | F44: =+'Asset Classification'!F44 -> 0 | G44: =+'Asset Classification'!G44 -> 0 | H44: =+E44*1% -> 0 | I44: =+G44-H44 -> 0 | J44: =+'Asset Classification'!I44 -> 0 | K44: =+'Asset Classification'!J44 -> 0 | L44: =+'Asset Classification'!K44 -> 0 | M44: =+J44*10% -> 0 | N44: =+L44-M44 -> 0 | O44: =+'Asset Classification'!L44 -> 0 | P44: =+K44*10% -> 0 | Q44: =+O44-P44 -> 0 | R44: =+'Asset Classification'!M44 -> 0 | S44: =+'Asset Classification'!N44 -> 0 | T44: =+'Asset Classification'!O44 -> 0 | U44: =+R44*25% -> 0 | V44: =+T44-U44 -> 0 | W44: =+'Asset Classification'!P44 -> 0 | X44: =+S44*25% -> 0 | Y44: =+W44-X44 -> 0 | Z44: =+'Asset Classification'!Q44 -> 0 | AA44: =+'Asset Classification'!R44 -> 0 | AB44: =+'Asset Classification'!S44 -> 0 | AC44: =+Z44*50% -> 0 | AD44: =+AB44-AC44 -> 0 | AE44: =+'Asset Classification'!T44 -> 0 | AF44: =+AA44*50% -> 0 | AG44: =+AE44-AF44 -> 0 | AH44: =+'Asset Classification'!U44 -> 0 | AI44: =+'Asset Classification'!V44 -> 0 | AJ44: =+'Asset Classification'!W44 -> 0 | AK44: =+AH44*100% -> 0 | AL44: =+AJ44-AK44 -> 0 | AM44: =+'Asset Classification'!X44 -> 0 | AN44: =+AI44*100% -> 0 | AO44: =+AM44-AN44 -> 0 | AP44: =+L44+T44+AB44+AJ44 -> 0 | AQ44: =+M44+U44+AC44+AK44 -> 0 | AR44: =+AP44-AQ44 -> 0 | AS44: =+O44+W44+AE44+AM44 -> 0 | AT44: =+P44+X44+AF44+AN44 -> 0 | AU44: =+AS44-AT44 -> 0
A45: 19 | B45: Моддий ва техник таъминотни ривожлантириш | C45: =+'Asset Classification'!C45 -> 1326568151 | D45: =+'Asset Classification'!D45 -> 25010543 | E45: =+'Asset Classification'!E45 -> 1310552678 | F45: =+'Asset Classification'!F45 -> 16254684 | G45: =+'Asset Classification'!G45 -> 13105527 | H45: =+E45*1% -> 13105527 | I45: =+G45-H45 -> 0.22 | J45: =+'Asset Classification'!I45 -> 6909614 | K45: =+'Asset Classification'!J45 -> 0 | L45: =+'Asset Classification'!K45 -> 690961 | M45: =+J45*10% -> 690961.4 | N45: =+L45-M45 -> -0.4 | O45: =+'Asset Classification'!L45 -> 0 | P45: =+K45*10% -> 0 | Q45: =+O45-P45 -> 0 | R45: =+'Asset Classification'!M45 -> 9105859 | S45: =+'Asset Classification'!N45 -> 8755859 | T45: =+'Asset Classification'!O45 -> 1122546 | U45: =+R45*25% -> 2276464.8 | V45: =+T45-U45 -> -1153918.8 | W45: =+'Asset Classification'!P45 -> 1122546 | X45: =+S45*25% -> 2188964.8 | Y45: =+W45-X45 -> -1066418.8 | Z45: =+'Asset Classification'!Q45 -> 0 | AA45: =+'Asset Classification'!R45 -> 0 | AB45: =+'Asset Classification'!S45 -> 0 | AC45: =+Z45*50% -> 0 | AD45: =+AB45-AC45 -> 0 | AE45: =+'Asset Classification'!T45 -> 0 | AF45: =+AA45*50% -> 0 | AG45: =+AE45-AF45 -> 0 | AH45: =+'Asset Classification'!U45 -> 0 | AI45: =+'Asset Classification'!V45 -> 0 | AJ45: =+'Asset Classification'!W45 -> 0 | AK45: =+AH45*100% -> 0 | AL45: =+AJ45-AK45 -> 0 | AM45: =+'Asset Classification'!X45 -> 0 | AN45: =+AI45*100% -> 0 | AO45: =+AM45-AN45 -> 0 | AP45: =+L45+T45+AB45+AJ45 -> 1813507 | AQ45: =+M45+U45+AC45+AK45 -> 2967426.1 | AR45: =+AP45-AQ45 -> -1153919.1 | AS45: =+O45+W45+AE45+AM45 -> 1122546 | AT45: =+P45+X45+AF45+AN45 -> 2188964.8 | AU45: =+AS45-AT45 -> -1066418.8 | AV45: =+'Aging Analysis'!C30 -> 1326568151
B46: шундан, таъминланмаган қисми | C46: =+'Asset Classification'!C46 -> 0 | D46: =+'Asset Classification'!D46 -> 0 | E46: =+'Asset Classification'!E46 -> 0 | F46: =+'Asset Classification'!F46 -> 0 | G46: =+'Asset Classification'!G46 -> 0 | H46: =+E46*1% -> 0 | I46: =+G46-H46 -> 0 | J46: =+'Asset Classification'!I46 -> 0 | K46: =+'Asset Classification'!J46 -> 0 | L46: =+'Asset Classification'!K46 -> 0 | M46: =+J46*10% -> 0 | N46: =+L46-M46 -> 0 | O46: =+'Asset Classification'!L46 -> 0 | P46: =+K46*10% -> 0 | Q46: =+O46-P46 -> 0 | R46: =+'Asset Classification'!M46 -> 0 | S46: =+'Asset Classification'!N46 -> 0 | T46: =+'Asset Classification'!O46 -> 0 | U46: =+R46*25% -> 0 | V46: =+T46-U46 -> 0 | W46: =+'Asset Classification'!P46 -> 0 | X46: =+S46*25% -> 0 | Y46: =+W46-X46 -> 0 | Z46: =+'Asset Classification'!Q46 -> 0 | AA46: =+'Asset Classification'!R46 -> 0 | AB46: =+'Asset Classification'!S46 -> 0 | AC46: =+Z46*50% -> 0 | AD46: =+AB46-AC46 -> 0 | AE46: =+'Asset Classification'!T46 -> 0 | AF46: =+AA46*50% -> 0 | AG46: =+AE46-AF46 -> 0 | AH46: =+'Asset Classification'!U46 -> 0 | AI46: =+'Asset Classification'!V46 -> 0 | AJ46: =+'Asset Classification'!W46 -> 0 | AK46: =+AH46*100% -> 0 | AL46: =+AJ46-AK46 -> 0 | AM46: =+'Asset Classification'!X46 -> 0 | AN46: =+AI46*100% -> 0 | AO46: =+AM46-AN46 -> 0 | AP46: =+L46+T46+AB46+AJ46 -> 0 | AQ46: =+M46+U46+AC46+AK46 -> 0 | AR46: =+AP46-AQ46 -> 0 | AS46: =+O46+W46+AE46+AM46 -> 0 | AT46: =+P46+X46+AF46+AN46 -> 0 | AU46: =+AS46-AT46 -> 0
A47: 20 | B47: Уй-жой коммунал хизмати | C47: =+'Asset Classification'!C47 -> 10242602 | D47: =+'Asset Classification'!D47 -> 0 | E47: =+'Asset Classification'!E47 -> 3049477 | F47: =+'Asset Classification'!F47 -> 0 | G47: =+'Asset Classification'!G47 -> 30495 | H47: =+E47*1% -> 30494.77 | I47: =+G47-H47 -> 0.23 | J47: =+'Asset Classification'!I47 -> 1074164 | K47: =+'Asset Classification'!J47 -> 0 | L47: =+'Asset Classification'!K47 -> 107416 | M47: =+J47*10% -> 107416.4 | N47: =+L47-M47 -> -0.4 | O47: =+'Asset Classification'!L47 -> 0 | P47: =+K47*10% -> 0 | Q47: =+O47-P47 -> 0 | R47: =+'Asset Classification'!M47 -> 1041035 | S47: =+'Asset Classification'!N47 -> 0 | T47: =+'Asset Classification'!O47 -> 195258 | U47: =+R47*25% -> 260258.75 | V47: =+T47-U47 -> -65000.75 | W47: =+'Asset Classification'!P47 -> 0 | X47: =+S47*25% -> 0 | Y47: =+W47-X47 -> 0 | Z47: =+'Asset Classification'!Q47 -> 1884435 | AA47: =+'Asset Classification'!R47 -> 0 | AB47: =+'Asset Classification'!S47 -> 882546 | AC47: =+Z47*50% -> 942217.5 | AD47: =+AB47-AC47 -> -59671.5 | AE47: =+'Asset Classification'!T47 -> 0 | AF47: =+AA47*50% -> 0 | AG47: =+AE47-AF47 -> 0 | AH47: =+'Asset Classification'!U47 -> 3193491 | AI47: =+'Asset Classification'!V47 -> 0 | AJ47: =+'Asset Classification'!W47 -> 3006146 | AK47: =+AH47*100% -> 3193491 | AL47: =+AJ47-AK47 -> -187345 | AM47: =+'Asset Classification'!X47 -> 0 | AN47: =+AI47*100% -> 0 | AO47: =+AM47-AN47 -> 0 | AP47: =+L47+T47+AB47+AJ47 -> 4191366 | AQ47: =+M47+U47+AC47+AK47 -> 4503383.7 | AR47: =+AP47-AQ47 -> -312017.65 | AS47: =+O47+W47+AE47+AM47 -> 0 | AT47: =+P47+X47+AF47+AN47 -> 0 | AU47: =+AS47-AT47 -> 0 | AV47: =+'Aging Analysis'!C31 -> 10242602
B48: шундан, таъминланмаган қисми | C48: =+'Asset Classification'!C48 -> 0 | D48: =+'Asset Classification'!D48 -> 0 | E48: =+'Asset Classification'!E48 -> 0 | F48: =+'Asset Classification'!F48 -> 0 | G48: =+'Asset Classification'!G48 -> 0 | H48: =+E48*1% -> 0 | I48: =+G48-H48 -> 0 | J48: =+'Asset Classification'!I48 -> 0 | K48: =+'Asset Classification'!J48 -> 0 | L48: =+'Asset Classification'!K48 -> 0 | M48: =+J48*10% -> 0 | N48: =+L48-M48 -> 0 | O48: =+'Asset Classification'!L48 -> 0 | P48: =+K48*10% -> 0 | Q48: =+O48-P48 -> 0 | R48: =+'Asset Classification'!M48 -> 0 | S48: =+'Asset Classification'!N48 -> 0 | T48: =+'Asset Classification'!O48 -> 0 | U48: =+R48*25% -> 0 | V48: =+T48-U48 -> 0 | W48: =+'Asset Classification'!P48 -> 0 | X48: =+S48*25% -> 0 | Y48: =+W48-X48 -> 0 | Z48: =+'Asset Classification'!Q48 -> 0 | AA48: =+'Asset Classification'!R48 -> 0 | AB48: =+'Asset Classification'!S48 -> 0 | AC48: =+Z48*50% -> 0 | AD48: =+AB48-AC48 -> 0 | AE48: =+'Asset Classification'!T48 -> 0 | AF48: =+AA48*50% -> 0 | AG48: =+AE48-AF48 -> 0 | AH48: =+'Asset Classification'!U48 -> 0 | AI48: =+'Asset Classification'!V48 -> 0 | AJ48: =+'Asset Classification'!W48 -> 0 | AK48: =+AH48*100% -> 0 | AL48: =+AJ48-AK48 -> 0 | AM48: =+'Asset Classification'!X48 -> 0 | AN48: =+AI48*100% -> 0 | AO48: =+AM48-AN48 -> 0 | AP48: =+L48+T48+AB48+AJ48 -> 0 | AQ48: =+M48+U48+AC48+AK48 -> 0 | AR48: =+AP48-AQ48 -> 0 | AS48: =+O48+W48+AE48+AM48 -> 0 | AT48: =+P48+X48+AF48+AN48 -> 0 | AU48: =+AS48-AT48 -> 0
A49: 21 | B49: Бошқа соҳалар | C49: =+'Asset Classification'!C49 -> 3115127146 | D49: =+'Asset Classification'!D49 -> 2015936052 | E49: =+'Asset Classification'!E49 -> 2582925173 | F49: =+'Asset Classification'!F49 -> 1913713964 | G49: =+'Asset Classification'!G49 -> 25829251 | H49: =+E49*1% -> 25829252 | I49: =+G49-H49 -> -0.73 | J49: =+'Asset Classification'!I49 -> 447994582 | K49: =+'Asset Classification'!J49 -> 86804068 | L49: =+'Asset Classification'!K49 -> 44799458 | M49: =+J49*10% -> 44799458 | N49: =+L49-M49 -> -0.2 | O49: =+'Asset Classification'!L49 -> 8680408 | P49: =+K49*10% -> 8680406.8 | Q49: =+O49-P49 -> 1.2 | R49: =+'Asset Classification'!M49 -> 55124155 | S49: =+'Asset Classification'!N49 -> 9599864 | T49: =+'Asset Classification'!O49 -> 13781040 | U49: =+R49*25% -> 13781039 | V49: =+T49-U49 -> 1.25 | W49: =+'Asset Classification'!P49 -> 2399966 | X49: =+S49*25% -> 2399966 | Y49: =+W49-X49 -> 0 | Z49: =+'Asset Classification'!Q49 -> 23289729 | AA49: =+'Asset Classification'!R49 -> 5818156 | AB49: =+'Asset Classification'!S49 -> 11644865 | AC49: =+Z49*50% -> 11644864 | AD49: =+AB49-AC49 -> 0.5 | AE49: =+'Asset Classification'!T49 -> 2909079 | AF49: =+AA49*50% -> 2909078 | AG49: =+AE49-AF49 -> 1 | AH49: =+'Asset Classification'!U49 -> 5793507 | AI49: =+'Asset Classification'!V49 -> 0 | AJ49: =+'Asset Classification'!W49 -> 5793506 | AK49: =+AH49*100% -> 5793507 | AL49: =+AJ49-AK49 -> -1 | AM49: =+'Asset Classification'!X49 -> 0 | AN49: =+AI49*100% -> 0 | AO49: =+AM49-AN49 -> 0 | AP49: =+L49+T49+AB49+AJ49 -> 76018869 | AQ49: =+M49+U49+AC49+AK49 -> 76018868 | AR49: =+AP49-AQ49 -> 0.55 | AS49: =+O49+W49+AE49+AM49 -> 13989453 | AT49: =+P49+X49+AF49+AN49 -> 13989451 | AU49: =+AS49-AT49 -> 2.2 | AV49: =+'Aging Analysis'!C32 -> 3115127146
B50: шундан, таъминланмаган қисми | C50: =+'Asset Classification'!C50 -> 0 | D50: =+'Asset Classification'!D50 -> 0 | E50: =+'Asset Classification'!E50 -> 0 | F50: =+'Asset Classification'!F50 -> 0 | G50: =+'Asset Classification'!G50 -> 0 | H50: =+E50*1% -> 0 | I50: =+G50-H50 -> 0 | J50: =+'Asset Classification'!I50 -> 0 | K50: =+'Asset Classification'!J50 -> 0 | L50: =+'Asset Classification'!K50 -> 0 | M50: =+J50*10% -> 0 | N50: =+L50-M50 -> 0 | O50: =+'Asset Classification'!L50 -> 0 | P50: =+K50*10% -> 0 | Q50: =+O50-P50 -> 0 | R50: =+'Asset Classification'!M50 -> 0 | S50: =+'Asset Classification'!N50 -> 0 | T50: =+'Asset Classification'!O50 -> 0 | U50: =+R50*25% -> 0 | V50: =+T50-U50 -> 0 | W50: =+'Asset Classification'!P50 -> 0 | X50: =+S50*25% -> 0 | Y50: =+W50-X50 -> 0 | Z50: =+'Asset Classification'!Q50 -> 0 | AA50: =+'Asset Classification'!R50 -> 0 | AB50: =+'Asset Classification'!S50 -> 0 | AC50: =+Z50*50% -> 0 | AD50: =+AB50-AC50 -> 0 | AE50: =+'Asset Classification'!T50 -> 0 | AF50: =+AA50*50% -> 0 | AG50: =+AE50-AF50 -> 0 | AH50: =+'Asset Classification'!U50 -> 0 | AI50: =+'Asset Classification'!V50 -> 0 | AJ50: =+'Asset Classification'!W50 -> 0 | AK50: =+AH50*100% -> 0 | AL50: =+AJ50-AK50 -> 0 | AM50: =+'Asset Classification'!X50 -> 0 | AN50: =+AI50*100% -> 0 | AO50: =+AM50-AN50 -> 0 | AP50: =+L50+T50+AB50+AJ50 -> 0 | AQ50: =+M50+U50+AC50+AK50 -> 0 | AR50: =+AP50-AQ50 -> 0 | AS50: =+O50+W50+AE50+AM50 -> 0 | AT50: =+P50+X50+AF50+AN50 -> 0 | AU50: =+AS50-AT50 -> 0
A51: 22 | B51: Жисмоний шахслар | C51: =+'Asset Classification'!C51 -> 5463367169 | D51: =+'Asset Classification'!D51 -> 0 | E51: =+'Asset Classification'!E51 -> 5326427523 | F51: =+'Asset Classification'!F51 -> 0 | G51: =+'Asset Classification'!G51 -> 53264275 | H51: =+E51*1% -> 53264275 | I51: =+G51-H51 -> -0.23 | J51: =+'Asset Classification'!I51 -> 86600966 | K51: =+'Asset Classification'!J51 -> 0 | L51: =+'Asset Classification'!K51 -> 8592799 | M51: =+J51*10% -> 8660096.6 | N51: =+L51-M51 -> -67297.6 | O51: =+'Asset Classification'!L51 -> 0 | P51: =+K51*10% -> 0 | Q51: =+O51-P51 -> 0 | R51: =+'Asset Classification'!M51 -> 25017834 | S51: =+'Asset Classification'!N51 -> 0 | T51: =+'Asset Classification'!O51 -> 6063606 | U51: =+R51*25% -> 6254458.5 | V51: =+T51-U51 -> -190852.5 | W51: =+'Asset Classification'!P51 -> 0 | X51: =+S51*25% -> 0 | Y51: =+W51-X51 -> 0 | Z51: =+'Asset Classification'!Q51 -> 18412252 | AA51: =+'Asset Classification'!R51 -> 0 | AB51: =+'Asset Classification'!S51 -> 8853606 | AC51: =+Z51*50% -> 9206126 | AD51: =+AB51-AC51 -> -352520 | AE51: =+'Asset Classification'!T51 -> 0 | AF51: =+AA51*50% -> 0 | AG51: =+AE51-AF51 -> 0 | AH51: =+'Asset Classification'!U51 -> 6908594 | AI51: =+'Asset Classification'!V51 -> 0 | AJ51: =+'Asset Classification'!W51 -> 6238672 | AK51: =+AH51*100% -> 6908594 | AL51: =+AJ51-AK51 -> -669922 | AM51: =+'Asset Classification'!X51 -> 0 | AN51: =+AI51*100% -> 0 | AO51: =+AM51-AN51 -> 0 | AP51: =+L51+T51+AB51+AJ51 -> 29748683 | AQ51: =+M51+U51+AC51+AK51 -> 31029275 | AR51: =+AP51-AQ51 -> -1280592.1 | AS51: =+O51+W51+AE51+AM51 -> 0 | AT51: =+P51+X51+AF51+AN51 -> 0 | AU51: =+AS51-AT51 -> 0 | AV51: =+'Aging Analysis'!C33 -> 5463367169
B52: шундан, таъминланмаган қисми | C52: =+'Asset Classification'!C52 -> 0 | D52: =+'Asset Classification'!D52 -> 0 | E52: =+'Asset Classification'!E52 -> 0 | F52: =+'Asset Classification'!F52 -> 0 | G52: =+'Asset Classification'!G52 -> 0 | H52: =+E52*1% -> 0 | I52: =+G52-H52 -> 0 | J52: =+'Asset Classification'!I52 -> 0 | K52: =+'Asset Classification'!J52 -> 0 | L52: =+'Asset Classification'!K52 -> 0 | M52: =+J52*10% -> 0 | N52: =+L52-M52 -> 0 | O52: =+'Asset Classification'!L52 -> 0 | P52: =+K52*10% -> 0 | Q52: =+O52-P52 -> 0 | R52: =+'Asset Classification'!M52 -> 0 | S52: =+'Asset Classification'!N52 -> 0 | T52: =+'Asset Classification'!O52 -> 0 | U52: =+R52*25% -> 0 | V52: =+T52-U52 -> 0 | W52: =+'Asset Classification'!P52 -> 0 | X52: =+S52*25% -> 0 | Y52: =+W52-X52 -> 0 | Z52: =+'Asset Classification'!Q52 -> 0 | AA52: =+'Asset Classification'!R52 -> 0 | AB52: =+'Asset Classification'!S52 -> 0 | AC52: =+Z52*50% -> 0 | AD52: =+AB52-AC52 -> 0 | AE52: =+'Asset Classification'!T52 -> 0 | AF52: =+AA52*50% -> 0 | AG52: =+AE52-AF52 -> 0 | AH52: =+'Asset Classification'!U52 -> 0 | AI52: =+'Asset Classification'!V52 -> 0 | AJ52: =+'Asset Classification'!W52 -> 0 | AK52: =+AH52*100% -> 0 | AL52: =+AJ52-AK52 -> 0 | AM52: =+'Asset Classification'!X52 -> 0 | AN52: =+AI52*100% -> 0 | AO52: =+AM52-AN52 -> 0 | AP52: =+L52+T52+AB52+AJ52 -> 0 | AQ52: =+M52+U52+AC52+AK52 -> 0 | AR52: =+AP52-AQ52 -> 0 | AS52: =+O52+W52+AE52+AM52 -> 0 | AT52: =+P52+X52+AF52+AN52 -> 0 | AU52: =+AS52-AT52 -> 0
A53: 23 | B53: Жами кредит ва лизинг суммаси | C53: =+'Asset Classification'!C53 -> 48075884880 | D53: =+'Asset Classification'!D53 -> 30828142644 | E53: =+'Asset Classification'!E53 -> 44160297748 | F53: =+'Asset Classification'!F53 -> 28307852456 | G53: =+'Asset Classification'!G53 -> 414689972 | H53: =+H35+H37+H39+H41+H43+H45+H47+H49+H51 -> 4.4160298e+08 | I53: =+I35+I37+I39+I41+I43+I45+I47+I49+I51 -> -26913005 | J53: =+'Asset Classification'!I53 -> 2556900652 | K53: =+'Asset Classification'!J53 -> 1684963039 | L53: =+'Asset Classification'!K53 -> 255622767 | M53: =+M35+M37+M39+M41+M43+M45+M47+M49+M51 -> 2.5569007e+08 | N53: =+N35+N37+N39+N41+N43+N45+N47+N49+N51 -> -67298.2 | O53: =+'Asset Classification'!L53 -> 168496305 | P53: =+P35+P37+P39+P41+P43+P45+P47+P49+P51 -> 1.684963e+08 | Q53: =+Q35+Q37+Q39+Q41+Q43+Q45+Q47+Q49+Q51 -> 1.1 | R53: =+'Asset Classification'!M53 -> 436789210 | S53: =+'Asset Classification'!N53 -> 228730389 | T53: =+'Asset Classification'!O53 -> 107787533 | U53: =+U35+U37+U39+U41+U43+U45+U47+U49+U51 -> 1.091973e+08 | V53: =+V35+V37+V39+V41+V43+V45+V47+V49+V51 -> -1409769.5 | W53: =+'Asset Classification'!P53 -> 56116179 | X53: =+X35+X37+X39+X41+X43+X45+X47+X49+X51 -> 57182597 | Y53: =+Y35+Y37+Y39+Y41+Y43+Y45+Y47+Y49+Y51 -> -1066418.2 | Z53: =+'Asset Classification'!Q53 -> 830442808 | AA53: =+'Asset Classification'!R53 -> 563175767 | AB53: =+'Asset Classification'!S53 -> 414805245 | AC53: =+AC35+AC37+AC39+AC41+AC43+AC45+AC47+AC49+AC51 -> 415221404 | AD53: =+AD35+AD37+AD39+AD41+AD43+AD45+AD47+AD49+AD51 -> -416159 | AE53: =+'Asset Classification'!T53 -> 281587884 | AF53: =+AF35+AF37+AF39+AF41+AF43+AF45+AF47+AF49+AF51 -> 2.8158788e+08 | AG53: =+AG35+AG37+AG39+AG41+AG43+AG45+AG47+AG49+AG51 -> 0.5 | AH53: =+'Asset Classification'!U53 -> 91454462 | AI53: =+'Asset Classification'!V53 -> 43420993 | AJ53: =+'Asset Classification'!W53 -> 90597194 | AK53: =+AK35+AK37+AK39+AK41+AK43+AK45+AK47+AK49+AK51 -> 91454462 | AL53: =+AL35+AL37+AL39+AL41+AL43+AL45+AL47+AL49+AL51 -> -857268 | AM53: =+'Asset Classification'!X53 -> 43420993 | AN53: =+AN35+AN37+AN39+AN41+AN43+AN45+AN47+AN49+AN51 -> 43420993 | AO53: =+AO35+AO37+AO39+AO41+AO43+AO45+AO47+AO49+AO51 -> 0 | AP53: =+AP35+AP37+AP39+AP41+AP43+AP45+AP47+AP49+AP51 -> 868812739 | AQ53: =+AQ35+AQ37+AQ39+AQ41+AQ43+AQ45+AQ47+AQ49+AQ51 -> 8.7156323e+08 | AR53: =+AR35+AR37+AR39+AR41+AR43+AR45+AR47+AR49+AR51 -> -2750494.7 | AS53: =+AS35+AS37+AS39+AS41+AS43+AS45+AS47+AS49+AS51 -> 549621361 | AT53: =+AT35+AT37+AT39+AT41+AT43+AT45+AT47+AT49+AT51 -> 5.5068778e+08 | AU53: =+AU35+AU37+AU39+AU41+AU43+AU45+AU47+AU49+AU51 -> -1066416.6 | AV53: =+'Aging Analysis'!C35 -> 48075884880
B54: шундан, таъминланмаган қисми | C54: =+'Asset Classification'!C54 -> 0 | D54: =+'Asset Classification'!D54 -> 0 | E54: =+'Asset Classification'!E54 -> 0 | F54: =+'Asset Classification'!F54 -> 0 | G54: =+'Asset Classification'!G54 -> 0 | H54: =+E54*1% -> 0 | I54: =+G54-H54 -> 0 | J54: =+'Asset Classification'!I54 -> 0 | K54: =+'Asset Classification'!J54 -> 0 | L54: =+'Asset Classification'!K54 -> 0 | M54: =+J54*10% -> 0 | N54: =+L54-M54 -> 0 | O54: =+'Asset Classification'!L54 -> 0 | P54: =+K54*10% -> 0 | Q54: =+O54-P54 -> 0 | R54: =+'Asset Classification'!M54 -> 0 | S54: =+'Asset Classification'!N54 -> 0 | T54: =+'Asset Classification'!O54 -> 0 | U54: =+R54*25% -> 0 | V54: =+T54-U54 -> 0 | W54: =+'Asset Classification'!P54 -> 0 | X54: =+S54*25% -> 0 | Y54: =+W54-X54 -> 0 | Z54: =+'Asset Classification'!Q54 -> 0 | AA54: =+'Asset Classification'!R54 -> 0 | AB54: =+'Asset Classification'!S54 -> 0 | AC54: =+Z54*50% -> 0 | AD54: =+AB54-AC54 -> 0 | AE54: =+'Asset Classification'!T54 -> 0 | AF54: =+AA54*50% -> 0 | AG54: =+AE54-AF54 -> 0 | AH54: =+'Asset Classification'!U54 -> 0 | AI54: =+'Asset Classification'!V54 -> 0 | AJ54: =+'Asset Classification'!W54 -> 0 | AK54: =+AH54*100% -> 0 | AL54: =+AJ54-AK54 -> 0 | AM54: =+'Asset Classification'!X54 -> 0 | AN54: =+AI54*100% -> 0 | AO54: =+AM54-AN54 -> 0 | AP54: =+L54+T54+AB54+AJ54 -> 0 | AQ54: =+M54+U54+AC54+AK54 -> 0 | AR54: =+AP54-AQ54 -> 0 | AS54: =+O54+W54+AE54+AM54 -> 0 | AT54: =+P54+X54+AF54+AN54 -> 0 | AU54: =+AS54-AT54 -> 0
B55: Ҳудудлар қирқимида
A57: 24 | B57: Қорақалпоғистон Республикаси | C57: =+'Asset Classification'!C57 -> 1609455410 | D57: =+'Asset Classification'!D57 -> 762257731 | E57: =+'Asset Classification'!E57 -> 1563148657 | F57: =+'Asset Classification'!F57 -> 746646348 | G57: =+'Asset Classification'!G57 -> 11072659 | H57: =+E57*1% -> 15631487 | I57: =+G57-H57 -> -4558827.6 | J57: =+'Asset Classification'!I57 -> 32482518 | K57: =+'Asset Classification'!J57 -> 14447457 | L57: =+'Asset Classification'!K57 -> 3244039 | M57: =+J57*10% -> 3248251.8 | N57: =+L57-M57 -> -4212.8 | O57: =+'Asset Classification'!L57 -> 1444746 | P57: =+K57*10% -> 1444745.7 | Q57: =+O57-P57 -> 0.3 | R57: =+'Asset Classification'!M57 -> 6808733 | S57: =+'Asset Classification'!N57 -> 0 | T57: =+'Asset Classification'!O57 -> 1702183 | U57: =+R57*25% -> 1702183.2 | V57: =+T57-U57 -> -0.25 | W57: =+'Asset Classification'!P57 -> 0 | X57: =+S57*25% -> 0 | Y57: =+W57-X57 -> 0 | Z57: =+'Asset Classification'!Q57 -> 6960712 | AA57: =+'Asset Classification'!R57 -> 1163926 | AB57: =+'Asset Classification'!S57 -> 3425026 | AC57: =+Z57*50% -> 3480356 | AD57: =+AB57-AC57 -> -55330 | AE57: =+'Asset Classification'!T57 -> 581963 | AF57: =+AA57*50% -> 581963 | AG57: =+AE57-AF57 -> 0 | AH57: =+'Asset Classification'!U57 -> 54790 | AI57: =+'Asset Classification'!V57 -> 0 | AJ57: =+'Asset Classification'!W57 -> 54790 | AK57: =+AH57*100% -> 54790 | AL57: =+AJ57-AK57 -> 0 | AM57: =+'Asset Classification'!X57 -> 0 | AN57: =+AI57*100% -> 0 | AO57: =+AM57-AN57 -> 0 | AP57: =+L57+T57+AB57+AJ57 -> 8426038 | AQ57: =+M57+U57+AC57+AK57 -> 8485581.1 | AR57: =+AP57-AQ57 -> -59543.05 | AS57: =+O57+W57+AE57+AM57 -> 2026709 | AT57: =+P57+X57+AF57+AN57 -> 2026708.7 | AU57: =+AS57-AT57 -> 0.3
A58: 25 | B58: Андижон вилояти | C58: =+'Asset Classification'!C58 -> 1164312118 | D58: =+'Asset Classification'!D58 -> 721413632 | E58: =+'Asset Classification'!E58 -> 945578117 | F58: =+'Asset Classification'!F58 -> 555045506 | G58: =+'Asset Classification'!G58 -> 10254993 | H58: =+E58*1% -> 9455781.2 | I58: =+G58-H58 -> 799211.83 | J58: =+'Asset Classification'!I58 -> 185854595 | K58: =+'Asset Classification'!J58 -> 154267901 | L58: =+'Asset Classification'!K58 -> 18568920 | M58: =+J58*10% -> 18585460 | N58: =+L58-M58 -> -16539.5 | O58: =+'Asset Classification'!L58 -> 15426790 | P58: =+K58*10% -> 15426790 | Q58: =+O58-P58 -> -0.1 | R58: =+'Asset Classification'!M58 -> 14531742 | S58: =+'Asset Classification'!N58 -> 9174922 | T58: =+'Asset Classification'!O58 -> 3624680 | U58: =+R58*25% -> 3632935.5 | V58: =+T58-U58 -> -8255.5 | W58: =+'Asset Classification'!P58 -> 2293731 | X58: =+S58*25% -> 2293730.5 | Y58: =+W58-X58 -> 0.5 | Z58: =+'Asset Classification'!Q58 -> 6710429 | AA58: =+'Asset Classification'!R58 -> 2925303 | AB58: =+'Asset Classification'!S58 -> 3354940 | AC58: =+Z58*50% -> 3355214.5 | AD58: =+AB58-AC58 -> -274.5 | AE58: =+'Asset Classification'!T58 -> 1462651 | AF58: =+AA58*50% -> 1462651.5 | AG58: =+AE58-AF58 -> -0.5 | AH58: =+'Asset Classification'!U58 -> 11637235 | AI58: =+'Asset Classification'!V58 -> 0 | AJ58: =+'Asset Classification'!W58 -> 11637235 | AK58: =+AH58*100% -> 11637235 | AL58: =+AJ58-AK58 -> 0 | AM58: =+'Asset Classification'!X58 -> 0 | AN58: =+AI58*100% -> 0 | AO58: =+AM58-AN58 -> 0 | AP58: =+L58+T58+AB58+AJ58 -> 37185775 | AQ58: =+M58+U58+AC58+AK58 -> 37210844 | AR58: =+AP58-AQ58 -> -25069.5 | AS58: =+O58+W58+AE58+AM58 -> 19183172 | AT58: =+P58+X58+AF58+AN58 -> 19183172 | AU58: =+AS58-AT58 -> -0.1
A59: 26 | B59: Бухоро вилояти | C59: =+'Asset Classification'!C59 -> 1681535519 | D59: =+'Asset Classification'!D59 -> 1147783044 | E59: =+'Asset Classification'!E59 -> 1322950032 | F59: =+'Asset Classification'!F59 -> 901942901 | G59: =+'Asset Classification'!G59 -> 11745891 | H59: =+E59*1% -> 13229500 | I59: =+G59-H59 -> -1483609.3 | J59: =+'Asset Classification'!I59 -> 248858552 | K59: =+'Asset Classification'!J59 -> 172270296 | L59: =+'Asset Classification'!K59 -> 24885855 | M59: =+J59*10% -> 24885855 | N59: =+L59-M59 -> -0.2 | O59: =+'Asset Classification'!L59 -> 17227030 | P59: =+K59*10% -> 17227030 | Q59: =+O59-P59 -> 0.4 | R59: =+'Asset Classification'!M59 -> 33081958 | S59: =+'Asset Classification'!N59 -> 28198628 | T59: =+'Asset Classification'!O59 -> 7102970 | U59: =+R59*25% -> 8270489.5 | V59: =+T59-U59 -> -1167519.5 | W59: =+'Asset Classification'!P59 -> 5983238 | X59: =+S59*25% -> 7049657 | Y59: =+W59-X59 -> -1066419 | Z59: =+'Asset Classification'!Q59 -> 60460173 | AA59: =+'Asset Classification'!R59 -> 33967822 | AB59: =+'Asset Classification'!S59 -> 30230086 | AC59: =+Z59*50% -> 30230086 | AD59: =+AB59-AC59 -> -0.5 | AE59: =+'Asset Classification'!T59 -> 16983911 | AF59: =+AA59*50% -> 16983911 | AG59: =+AE59-AF59 -> 0 | AH59: =+'Asset Classification'!U59 -> 16184804 | AI59: =+'Asset Classification'!V59 -> 11403397 | AJ59: =+'Asset Classification'!W59 -> 16184804 | AK59: =+AH59*100% -> 16184804 | AL59: =+AJ59-AK59 -> 0 | AM59: =+'Asset Classification'!X59 -> 11403397 | AN59: =+AI59*100% -> 11403397 | AO59: =+AM59-AN59 -> 0 | AP59: =+L59+T59+AB59+AJ59 -> 78403715 | AQ59: =+M59+U59+AC59+AK59 -> 79571235 | AR59: =+AP59-AQ59 -> -1167520.2 | AS59: =+O59+W59+AE59+AM59 -> 51597576 | AT59: =+P59+X59+AF59+AN59 -> 52663995 | AU59: =+AS59-AT59 -> -1066418.6
A60: 27 | B60: Жиззах вилояти | C60: =+'Asset Classification'!C60 -> 1143106711 | D60: =+'Asset Classification'!D60 -> 779723418 | E60: =+'Asset Classification'!E60 -> 1116767407 | F60: =+'Asset Classification'!F60 -> 765428208 | G60: =+'Asset Classification'!G60 -> 10609211 | H60: =+E60*1% -> 11167674 | I60: =+G60-H60 -> -558463.07 | J60: =+'Asset Classification'!I60 -> 15988883 | K60: =+'Asset Classification'!J60 -> 12769174 | L60: =+'Asset Classification'!K60 -> 1598751 | M60: =+J60*10% -> 1598888.3 | N60: =+L60-M60 -> -137.3 | O60: =+'Asset Classification'!L60 -> 1276917 | P60: =+K60*10% -> 1276917.4 | Q60: =+O60-P60 -> -0.4 | R60: =+'Asset Classification'!M60 -> 5895379 | S60: =+'Asset Classification'!N60 -> 0 | T60: =+'Asset Classification'!O60 -> 1471630 | U60: =+R60*25% -> 1473844.8 | V60: =+T60-U60 -> -2214.75 | W60: =+'Asset Classification'!P60 -> 0 | X60: =+S60*25% -> 0 | Y60: =+W60-X60 -> 0 | Z60: =+'Asset Classification'!Q60 -> 4336384 | AA60: =+'Asset Classification'!R60 -> 1526036 | AB60: =+'Asset Classification'!S60 -> 2168192 | AC60: =+Z60*50% -> 2168192 | AD60: =+AB60-AC60 -> 0 | AE60: =+'Asset Classification'!T60 -> 763018 | AF60: =+AA60*50% -> 763018 | AG60: =+AE60-AF60 -> 0 | AH60: =+'Asset Classification'!U60 -> 118658 | AI60: =+'Asset Classification'!V60 -> 0 | AJ60: =+'Asset Classification'!W60 -> 118658 | AK60: =+AH60*100% -> 118658 | AL60: =+AJ60-AK60 -> 0 | AM60: =+'Asset Classification'!X60 -> 0 | AN60: =+AI60*100% -> 0 | AO60: =+AM60-AN60 -> 0 | AP60: =+L60+T60+AB60+AJ60 -> 5357231 | AQ60: =+M60+U60+AC60+AK60 -> 5359583 | AR60: =+AP60-AQ60 -> -2352.05 | AS60: =+O60+W60+AE60+AM60 -> 2039935 | AT60: =+P60+X60+AF60+AN60 -> 2039935.4 | AU60: =+AS60-AT60 -> -0.4
A61: 28 | B61: Қашқадарё вилояти | C61: =+'Asset Classification'!C61 -> 1213232734 | D61: =+'Asset Classification'!D61 -> 249604507 | E61: =+'Asset Classification'!E61 -> 1080232255 | F61: =+'Asset Classification'!F61 -> 176970426 | G61: =+'Asset Classification'!G61 -> 14498781 | H61: =+E61*1% -> 10802323 | I61: =+G61-H61 -> 3696458.4 | J61: =+'Asset Classification'!I61 -> 122540249 | K61: =+'Asset Classification'!J61 -> 71990097 | L61: =+'Asset Classification'!K61 -> 12254025 | M61: =+J61*10% -> 12254025 | N61: =+L61-M61 -> 0.1 | O61: =+'Asset Classification'!L61 -> 7199010 | P61: =+K61*10% -> 7199009.7 | Q61: =+O61-P61 -> 0.3 | R61: =+'Asset Classification'!M61 -> 7708222 | S61: =+'Asset Classification'!N61 -> 281898 | T61: =+'Asset Classification'!O61 -> 1905013 | U61: =+R61*25% -> 1927055.5 | V61: =+T61-U61 -> -22042.5 | W61: =+'Asset Classification'!P61 -> 70474 | X61: =+S61*25% -> 70474.5 | Y61: =+W61-X61 -> -0.5 | Z61: =+'Asset Classification'!Q61 -> 1777504 | AA61: =+'Asset Classification'!R61 -> 362086 | AB61: =+'Asset Classification'!S61 -> 780970 | AC61: =+Z61*50% -> 888752 | AD61: =+AB61-AC61 -> -107782 | AE61: =+'Asset Classification'!T61 -> 181043 | AF61: =+AA61*50% -> 181043 | AG61: =+AE61-AF61 -> 0 | AH61: =+'Asset Classification'!U61 -> 974504 | AI61: =+'Asset Classification'!V61 -> 0 | AJ61: =+'Asset Classification'!W61 -> 974504 | AK61: =+AH61*100% -> 974504 | AL61: =+AJ61-AK61 -> 0 | AM61: =+'Asset Classification'!X61 -> 0 | AN61: =+AI61*100% -> 0 | AO61: =+AM61-AN61 -> 0 | AP61: =+L61+T61+AB61+AJ61 -> 15914512 | AQ61: =+M61+U61+AC61+AK61 -> 16044336 | AR61: =+AP61-AQ61 -> -129824.4 | AS61: =+O61+W61+AE61+AM61 -> 7450527 | AT61: =+P61+X61+AF61+AN61 -> 7450527.2 | AU61: =+AS61-AT61 -> -0.2
A62: 29 | B62: Навоий вилояти | C62: =+'Asset Classification'!C62 -> 1300102322 | D62: =+'Asset Classification'!D62 -> 759172492 | E62: =+'Asset Classification'!E62 -> 1249883007 | F62: =+'Asset Classification'!F62 -> 750682363 | G62: =+'Asset Classification'!G62 -> 11790777 | H62: =+E62*1% -> 12498830 | I62: =+G62-H62 -> -708053.07 | J62: =+'Asset Classification'!I62 -> 28063230 | K62: =+'Asset Classification'!J62 -> 6990083 | L62: =+'Asset Classification'!K62 -> 2806323 | M62: =+J62*10% -> 2806323 | N62: =+L62-M62 -> 0 | O62: =+'Asset Classification'!L62 -> 699008 | P62: =+K62*10% -> 699008.3 | Q62: =+O62-P62 -> -0.3 | R62: =+'Asset Classification'!M62 -> 19825663 | S62: =+'Asset Classification'!N62 -> 0 | T62: =+'Asset Classification'!O62 -> 4900131 | U62: =+R62*25% -> 4956415.8 | V62: =+T62-U62 -> -56284.75 | W62: =+'Asset Classification'!P62 -> 0 | X62: =+S62*25% -> 0 | Y62: =+W62-X62 -> 0 | Z62: =+'Asset Classification'!Q62 -> 2141270 | AA62: =+'Asset Classification'!R62 -> 1500046 | AB62: =+'Asset Classification'!S62 -> 1070635 | AC62: =+Z62*50% -> 1070635 | AD62: =+AB62-AC62 -> 0 | AE62: =+'Asset Classification'!T62 -> 750023 | AF62: =+AA62*50% -> 750023 | AG62: =+AE62-AF62 -> 0 | AH62: =+'Asset Classification'!U62 -> 189152 | AI62: =+'Asset Classification'!V62 -> 0 | AJ62: =+'Asset Classification'!W62 -> 189152 | AK62: =+AH62*100% -> 189152 | AL62: =+AJ62-AK62 -> 0 | AM62: =+'Asset Classification'!X62 -> 0 | AN62: =+AI62*100% -> 0 | AO62: =+AM62-AN62 -> 0 | AP62: =+L62+T62+AB62+AJ62 -> 8966241 | AQ62: =+M62+U62+AC62+AK62 -> 9022525.8 | AR62: =+AP62-AQ62 -> -56284.75 | AS62: =+O62+W62+AE62+AM62 -> 1449031 | AT62: =+P62+X62+AF62+AN62 -> 1449031.3 | AU62: =+AS62-AT62 -> -0.3
A63: 30 | B63: Наманган вилояти | C63: =+'Asset Classification'!C63 -> 662112229 | D63: =+'Asset Classification'!D63 -> 395478229 | E63: =+'Asset Classification'!E63 -> 400127582 | F63: =+'Asset Classification'!F63 -> 208736685 | G63: =+'Asset Classification'!G63 -> 4925718 | H63: =+E63*1% -> 4001275.8 | I63: =+G63-H63 -> 924442.18 | J63: =+'Asset Classification'!I63 -> 229672343 | K63: =+'Asset Classification'!J63 -> 186447889 | L63: =+'Asset Classification'!K63 -> 22967234 | M63: =+J63*10% -> 22967234 | N63: =+L63-M63 -> -0.3 | O63: =+'Asset Classification'!L63 -> 18644789 | P63: =+K63*10% -> 18644789 | Q63: =+O63-P63 -> 0.099999998 | R63: =+'Asset Classification'!M63 -> 1169582 | S63: =+'Asset Classification'!N63 -> 293655 | T63: =+'Asset Classification'!O63 -> 292395 | U63: =+R63*25% -> 292395.5 | V63: =+T63-U63 -> -0.5 | W63: =+'Asset Classification'!P63 -> 73414 | X63: =+S63*25% -> 73413.75 | Y63: =+W63-X63 -> 0.25 | Z63: =+'Asset Classification'!Q63 -> 25900607 | AA63: =+'Asset Classification'!R63 -> 0 | AB63: =+'Asset Classification'!S63 -> 12950304 | AC63: =+Z63*50% -> 12950304 | AD63: =+AB63-AC63 -> 0.5 | AE63: =+'Asset Classification'!T63 -> 0 | AF63: =+AA63*50% -> 0 | AG63: =+AE63-AF63 -> 0 | AH63: =+'Asset Classification'!U63 -> 5242115 | AI63: =+'Asset Classification'!V63 -> 0 | AJ63: =+'Asset Classification'!W63 -> 5242115 | AK63: =+AH63*100% -> 5242115 | AL63: =+AJ63-AK63 -> 0 | AM63: =+'Asset Classification'!X63 -> 0 | AN63: =+AI63*100% -> 0 | AO63: =+AM63-AN63 -> 0 | AP63: =+L63+T63+AB63+AJ63 -> 41452048 | AQ63: =+M63+U63+AC63+AK63 -> 41452048 | AR63: =+AP63-AQ63 -> -0.3 | AS63: =+O63+W63+AE63+AM63 -> 18718203 | AT63: =+P63+X63+AF63+AN63 -> 18718203 | AU63: =+AS63-AT63 -> 0.35
A64: 31 | B64: Самарқанд вилояти | C64: =+'Asset Classification'!C64 -> 1780027645 | D64: =+'Asset Classification'!D64 -> 1127987565 | E64: =+'Asset Classification'!E64 -> 1661081207 | F64: =+'Asset Classification'!F64 -> 1041005359 | G64: =+'Asset Classification'!G64 -> 12742160 | H64: =+E64*1% -> 16610812 | I64: =+G64-H64 -> -3868652.1 | J64: =+'Asset Classification'!I64 -> 103243447 | K64: =+'Asset Classification'!J64 -> 74124766 | L64: =+'Asset Classification'!K64 -> 10323469 | M64: =+J64*10% -> 10324345 | N64: =+L64-M64 -> -875.7 | O64: =+'Asset Classification'!L64 -> 7412477 | P64: =+K64*10% -> 7412476.6 | Q64: =+O64-P64 -> 0.4 | R64: =+'Asset Classification'!M64 -> 2557424 | S64: =+'Asset Classification'!N64 -> 522812 | T64: =+'Asset Classification'!O64 -> 639356 | U64: =+R64*25% -> 639356 | V64: =+T64-U64 -> 0 | W64: =+'Asset Classification'!P64 -> 130703 | X64: =+S64*25% -> 130703 | Y64: =+W64-X64 -> 0 | Z64: =+'Asset Classification'!Q64 -> 4058476 | AA64: =+'Asset Classification'!R64 -> 3265579 | AB64: =+'Asset Classification'!S64 -> 2029238 | AC64: =+Z64*50% -> 2029238 | AD64: =+AB64-AC64 -> 0 | AE64: =+'Asset Classification'!T64 -> 1632790 | AF64: =+AA64*50% -> 1632789.5 | AG64: =+AE64-AF64 -> 0.5 | AH64: =+'Asset Classification'!U64 -> 9087091 | AI64: =+'Asset Classification'!V64 -> 9069049 | AJ64: =+'Asset Classification'!W64 -> 9087091 | AK64: =+AH64*100% -> 9087091 | AL64: =+AJ64-AK64 -> 0 | AM64: =+'Asset Classification'!X64 -> 9069049 | AN64: =+AI64*100% -> 9069049 | AO64: =+AM64-AN64 -> 0 | AP64: =+L64+T64+AB64+AJ64 -> 22079154 | AQ64: =+M64+U64+AC64+AK64 -> 22080030 | AR64: =+AP64-AQ64 -> -875.7 | AS64: =+O64+W64+AE64+AM64 -> 18245019 | AT64: =+P64+X64+AF64+AN64 -> 18245018 | AU64: =+AS64-AT64 -> 0.9
A65: 32 | B65: Сурхондарё вилояти | C65: =+'Asset Classification'!C65 -> 989325279 | D65: =+'Asset Classification'!D65 -> 344966652 | E65: =+'Asset Classification'!E65 -> 675112858 | F65: =+'Asset Classification'!F65 -> 96369727 | G65: =+'Asset Classification'!G65 -> 5848868 | H65: =+E65*1% -> 6751128.6 | I65: =+G65-H65 -> -902260.58 | J65: =+'Asset Classification'!I65 -> 271661212 | K65: =+'Asset Classification'!J65 -> 226572660 | L65: =+'Asset Classification'!K65 -> 27165784 | M65: =+J65*10% -> 27166121 | N65: =+L65-M65 -> -337.2 | O65: =+'Asset Classification'!L65 -> 22657266 | P65: =+K65*10% -> 22657266 | Q65: =+O65-P65 -> 0 | R65: =+'Asset Classification'!M65 -> 10756940 | S65: =+'Asset Classification'!N65 -> 8438205 | T65: =+'Asset Classification'!O65 -> 2689235 | U65: =+R65*25% -> 2689235 | V65: =+T65-U65 -> 0 | W65: =+'Asset Classification'!P65 -> 2109551 | X65: =+S65*25% -> 2109551.2 | Y65: =+W65-X65 -> -0.25 | Z65: =+'Asset Classification'!Q65 -> 24533068 | AA65: =+'Asset Classification'!R65 -> 10218422 | AB65: =+'Asset Classification'!S65 -> 12266534 | AC65: =+Z65*50% -> 12266534 | AD65: =+AB65-AC65 -> 0 | AE65: =+'Asset Classification'!T65 -> 5109211 | AF65: =+AA65*50% -> 5109211 | AG65: =+AE65-AF65 -> 0 | AH65: =+'Asset Classification'!U65 -> 7261201 | AI65: =+'Asset Classification'!V65 -> 3367638 | AJ65: =+'Asset Classification'!W65 -> 7261199 | AK65: =+AH65*100% -> 7261201 | AL65: =+AJ65-AK65 -> -2 | AM65: =+'Asset Classification'!X65 -> 3367638 | AN65: =+AI65*100% -> 3367638 | AO65: =+AM65-AN65 -> 0 | AP65: =+L65+T65+AB65+AJ65 -> 49382752 | AQ65: =+M65+U65+AC65+AK65 -> 49383091 | AR65: =+AP65-AQ65 -> -339.2 | AS65: =+O65+W65+AE65+AM65 -> 33243666 | AT65: =+P65+X65+AF65+AN65 -> 33243666 | AU65: =+AS65-AT65 -> -0.25
A66: 33 | B66: Сирдарё вилояти | C66: =+'Asset Classification'!C66 -> 2106753229 | D66: =+'Asset Classification'!D66 -> 1377515551 | E66: =+'Asset Classification'!E66 -> 1788617469 | F66: =+'Asset Classification'!F66 -> 1142013251 | G66: =+'Asset Classification'!G66 -> 18700461 | H66: =+E66*1% -> 17886175 | I66: =+G66-H66 -> 814286.31 | J66: =+'Asset Classification'!I66 -> 249212833 | K66: =+'Asset Classification'!J66 -> 191796389 | L66: =+'Asset Classification'!K66 -> 24921283 | M66: =+J66*10% -> 24921283 | N66: =+L66-M66 -> -0.3 | O66: =+'Asset Classification'!L66 -> 19179639 | P66: =+K66*10% -> 19179639 | Q66: =+O66-P66 -> 0.099999998 | R66: =+'Asset Classification'!M66 -> 40908120 | S66: =+'Asset Classification'!N66 -> 24440931 | T66: =+'Asset Classification'!O66 -> 10227030 | U66: =+R66*25% -> 10227030 | V66: =+T66-U66 -> 0 | W66: =+'Asset Classification'!P66 -> 6110233 | X66: =+S66*25% -> 6110232.8 | Y66: =+W66-X66 -> 0.25 | Z66: =+'Asset Classification'!Q66 -> 25755025 | AA66: =+'Asset Classification'!R66 -> 19264980 | AB66: =+'Asset Classification'!S66 -> 12877513 | AC66: =+Z66*50% -> 12877512 | AD66: =+AB66-AC66 -> 0.5 | AE66: =+'Asset Classification'!T66 -> 9632490 | AF66: =+AA66*50% -> 9632490 | AG66: =+AE66-AF66 -> 0 | AH66: =+'Asset Classification'!U66 -> 2259782 | AI66: =+'Asset Classification'!V66 -> 0 | AJ66: =+'Asset Classification'!W66 -> 2259782 | AK66: =+AH66*100% -> 2259782 | AL66: =+AJ66-AK66 -> 0 | AM66: =+'Asset Classification'!X66 -> 0 | AN66: =+AI66*100% -> 0 | AO66: =+AM66-AN66 -> 0 | AP66: =+L66+T66+AB66+AJ66 -> 50285608 | AQ66: =+M66+U66+AC66+AK66 -> 50285608 | AR66: =+AP66-AQ66 -> 0.2 | AS66: =+O66+W66+AE66+AM66 -> 34922362 | AT66: =+P66+X66+AF66+AN66 -> 34922362 | AU66: =+AS66-AT66 -> 0.34999999
