Workbook
Name jop: #REF!
Name kol: #REF!
Name RISKTOTASS: SUM('[6]Calculation of Risk Weighted As'!$C$38:$F$38)
Name RISKTOTASS: SUM('[7]Calculation of Risk Weighted As'!$C$41:$G$41)
Name TwentyLargestData: #REF!
Name Е: #REF!

Sheet Asset quality
A1: ИНФОРМАЦИЯ О КАЧЕСТВЕ АКТИВОВ, ОЦЕНИВАЕМЫХ В ЦЕЛЯХ СОЗДАНИЯ РЕЗЕРВА НА ВОЗМОЖНЫЕ ПОТЕРИ | R1: Таблица-2 | U1: №3
B3: АК "Алокабанк" | P3: 44196 | S3: тыс. сум
A4: № | B4: Состав активов* | C4: Остаток | D4: Категория качества | I4: Просроченная задолженность (брутто) | N4: Резерв на возможные потери
I5: итого | J5: до 30 дней | K5: от 31 до 90 дней | L5: от 91 до 180 дней | M5: свыше 180 дней | N5: фактически сформированный
N6: итого | O6: по категориям качества
D7: I | E7: II | F7: III | G7: IV | H7: V | O7: I | P7: II | Q7: III | R7: IV | S7: V
A8: А | B8: Б | C8: В | D8: Г | E8: Д | F8: Е | G8: Ж | H8: З | I8: И | J8: К | K8: Л | L8: М | M8: Н | N8: О | O8: П | P8: Р | Q8: С | R8: Т | S8: У
B9: ВСЕГО АКТИВОВ | C9: =SUM(C10:C60) -> 8108166331 | D9: =SUM(D10:D60) -> 8018633034 | E9: =SUM(E10:E60) -> 92173584 | F9: =SUM(F10:F60) -> 3580002 | G9: =SUM(G10:G60) -> 1568386 | H9: =SUM(H10:H60) -> 2291299 | I9: =SUM(I10:I60) -> 47490418 | J9: =SUM(J10:J60) -> 12969480 | ... S9: =SUM(S10:S60) -> 1518185
A10: 1 | B10: Кассовая наличность и другие платежные документы | C10: =SUM(D10:H10)-N10+O10 -> 252071807 | D10: 252071807 | I10: =SUM(J10:M10) -> 0 | N10: =SUM(O10:S10) -> 0 | T10: 10100
A11: 2 | B11: К получению из ЦБРУ | C11: =SUM(D11:H11)-N11+O11 -> 376855943 | D11: 376855943 | I11: =SUM(J11:M11) -> 0 | N11: =SUM(O11:S11) -> 0 | T11: 10300
A12: 3 | B12: К получению из других банков | C12: =SUM(D12:H12)-N12+O12 -> 445250157 | D12: 445250157 | I12: =SUM(J12:M12) -> 0 | N12: =SUM(O12:S12) -> 0 | T12: 10500
A13: 4 | B13: Ценные бумаги для купли и продажи | C13: =SUM(D13:H13)-N13+O13 -> 370787088 | D13: 370787088 | I13: =SUM(J13:M13) -> 0 | N13: =SUM(O13:S13) -> 0 | T13: 10700
A14: 5 | B14: Инвестиции в ценные бумаги, имеющиеся в наличии для продажи | C14: =SUM(D14:H14)-N14+O14 -> 0 | D14: 0 | I14: =SUM(J14:M14) -> 0 | N14: =SUM(O14:S14) -> 0 | T14: 10800
A15: 6 | B15: Драгоценные металлы, камни и монеты для купли и продажи | C15: =SUM(D15:H15)-N15+O15 -> 251 | D15: 251 | I15: =SUM(J15:M15) -> 0 | N15: =SUM(O15:S15) -> 0 | T15: 10900
A16: 7 | B16: Купленные дебиторские задолженности - Факторинг | C16: =SUM(D16:H16)-N16+O16 -> 0 | D16: 0 | I16: =SUM(J16:M16) -> 0 | N16: =SUM(O16:S16) -> 0 | T16: 11100
A17: 8 | B17: Купленные векселя | C17: =SUM(D17:H17)-N17+O17 -> 0 | D17: 0 | I17: =SUM(J17:M17) -> 0 | N17: =SUM(O17:S17) -> 0 | T17: 11300
A18: 9 | B18: Обязательства клиентов по траттам под аккредитив и/или трастовые документы | C18: =SUM(D18:H18)-N18+O18 -> 8617398 | D18: 8617398 | I18: =SUM(J18:M18) -> 0 | N18: =SUM(O18:S18) -> 0 | T18: 11500
A19: 10 | B19: Обязательства лиентов по непогашенным акцептам банка | C19: =SUM(D19:H19)-N19+O19 -> 0 | D19: 0 | I19: =SUM(J19:M19) -> 0 | N19: =SUM(O19:S19) -> 0 | T19: 11700
A20: 11 | B20: Купленные по сделкам РЕПО ценные бумаги | C20: =SUM(D20:H20)-N20+O20 -> 0 | D20: 0 | I20: =SUM(J20:M20) -> 0 | N20: =SUM(O20:S20) -> 0 | T20: 11800
A21: 12 | B21: Краткосрочные кредиты, предоставленные ЦБРУ | C21: =SUM(D21:H21)-N21+O21 -> 0 | D21: 0 | I21: =SUM(J21:M21) -> 0 | N21: =SUM(O21:S21) -> 0 | T21: 11900
... A24: 15 | B24: Краткосрочные кредиты, предоставленные бюджетным организациям | C24: =SUM(D24:H24)-N24+O24 -> 0 | D24: 0 | I24: =SUM(J24:M24) -> 0 | N24: =SUM(O24:S24) -> 0 | T24: 12400
A25: 16 | B25: Краткосрочные кредиты, предоставленные физическим лицам | C25: =SUM(D25:H25)-N25+O25 -> 148162141 | D25: 148154877 | E25: 14950 | F25: 1698 | G25: 21462 | H25: 71351 | I25: =SUM(J25:M25) -> 795643 | J25: 481223 | K25: 186380 | L25: 31478 | M25: 96562 | N25: =SUM(O25:S25) -> 1722693 | O25: 1620496 | P25: 9385 | Q25: 0 | R25: 21462 | S25: 71350 | T25: 12500
A26: 17 | B26: Краткосрочные кредиты, предоставленные индивидуальным предпринимателям | C26: =SUM(D26:H26)-N26+O26 -> 11443778 | D26: 11443778 | I26: =SUM(J26:M26) -> 0 | J26: 0 | K26: 0 | L26: 0 | M26: 0 | N26: =SUM(O26:S26) -> 125170 | O26: 125170 | T26: 12600
A27: 18 | B27: Краткосрочные кредиты, предоставленные государственным предприятиям, организациям и учреждениям | C27: =SUM(D27:H27)-N27+O27 -> 52510405 | D27: 52510405 | I27: =SUM(J27:M27) -> 0 | J27: 0 | K27: 0 | L27: 0 | M27: 0 | N27: =SUM(O27:S27) -> 574351 | O27: 574351 | T27: 12700
A28: 19 | B28: Краткосрочные кредиты, предоставленные при содействии Государственного фонда поддержки развития предпринимательской деятельности | C28: =SUM(D28:H28)-N28+O28 -> 0 | I28: =SUM(J28:M28) -> 0 | J28: 0 | K28: 0 | L28: 0 | M28: 0 | N28: =SUM(O28:S28) -> 0 | O28: 0 | T28: 12800
A29: 20 | B29: Краткосрочные кредиты, предоставленные предприятиям с участием иностранного капитала | C29: =SUM(D29:H29)-N29+O29 -> 22000000 | D29: 22000000 | I29: =SUM(J29:M29) -> 0 | J29: 0 | K29: 0 | L29: 0 | M29: 0 | N29: =SUM(O29:S29) -> 240633 | O29: 240633 | T29: 12900
A30: 21 | B30: Краткосрочные кредиты, предоставленные негосударственным некоммерческим организациям | C30: =SUM(D30:H30)-N30+O30 -> 0 | I30: =SUM(J30:M30) -> 0 | J30: 0 | K30: 0 | L30: 0 | M30: 0 | N30: =SUM(O30:S30) -> 0 | O30: 0 | T30: 13000
A31: 22 | B31: Краткосрочные кредиты, предоставленные частным предприятиям, хозяйственным товариществам и обществам | C31: =SUM(D31:H31)-N31+O31 -> 378174633 | D31: 374390579 | E31: 4101289 | F31: 23090 | G31: 0 | H31: 0 | I31: =SUM(J31:M31) -> 6115073 | J31: 890406 | K31: 890674 | L31: 209614 | M31: 4124379 | N31: =SUM(O31:S31) -> 4435352 | O31: 4095027 | P31: 317235 | Q31: 23090 | R31: 0 | S31: 0 | T31: 13100
A32: 23 | B32: Краткосрочные кредиты, предоставленные небанковским финансовым институтам | C32: =SUM(D32:H32)-N32+O32 -> 0 | I32: =SUM(J32:M32) -> 0 | J32: 0 | K32: 0 | L32: 0 | M32: 0 | N32: =SUM(O32:S32) -> 0 | O32: 0 | T32: 13200
A33: 24 | B33: Краткосрочные кредиты, предоставленные для производства сельскохозяйственной продукции, закупаемой для государственных нужд | C33: =SUM(D33:H33)-N33+O33 -> 0 | I33: =SUM(J33:M33) -> 0 | J33: 0 | K33: 0 | L33: 0 | M33: 0 | N33: =SUM(O33:S33) -> 0 | O33: 0 | T33: 13300
A34: 25 | B34: Долгосрочные кредиты, предоставленные для производства сельскохозяйственной продукции, закупаемой для государственных нужд | C34: =SUM(D34:H34)-N34+O34 -> 0 | I34: =SUM(J34:M34) -> 0 | J34: 0 | K34: 0 | L34: 0 | M34: 0 | N34: =SUM(O34:S34) -> 0 | O34: 0 | T34: 14300
A35: 26 | B35: Долгосрочные кредиты, предоставленные при содействии Государственного фонда поддержки развития предпринимательской деятельности | C35: =SUM(D35:H35)-N35+O35 -> 7526408 | D35: 7526408 | I35: =SUM(J35:M35) -> 105380 | J35: 62917 | K35: 42463 | L35: 0 | M35: 0 | N35: =SUM(O35:S35) -> 82323 | O35: 82323 | T35: 14400
A36: 27 | B36: Долгосрочные кредиты, предоставленные другим банкам | C36: =SUM(D36:H36)-N36+O36 -> 0 | I36: =SUM(J36:M36) -> 0 | J36: 0 | K36: 0 | L36: 0 | M36: 0 | N36: =SUM(O36:S36) -> 0 | O36: 0 | T36: 14500
A37: 28 | B37: Долгосрочные кредиты, предоставленные правительству | C37: =SUM(D37:H37)-N37+O37 -> 0 | I37: =SUM(J37:M37) -> 0 | J37: 0 | K37: 0 | L37: 0 | M37: 0 | N37: =SUM(O37:S37) -> 0 | O37: 0 | T37: 14700
A38: 29 | B38: Долгосрочные кредиты, предоставленные бюджетным организациям | C38: =SUM(D38:H38)-N38+O38 -> 0 | I38: =SUM(J38:M38) -> 0 | J38: 0 | K38: 0 | L38: 0 | M38: 0 | N38: =SUM(O38:S38) -> 0 | O38: 0 | T38: 14800
A39: 30 | B39: Долгосрочные кредиты, предоставленные физическим лицам | C39: =SUM(D39:H39)-N39+O39 -> 871890514 | D39: 865817982 | E39: 3416846 | F39: 2192229 | G39: 1436376 | H39: 1272415 | I39: =SUM(J39:M39) -> 8184822 | J39: 2667312 | K39: 2919449 | L39: 1332803 | M39: 1265258 | N39: =SUM(O39:S39) -> 11715520 | O39: 9470186 | P39: 727279 | Q39: 470636 | R39: 548116 | S39: 499303 | T39: 14900
A40: 31 | B40: Долгосрочные кредиты, предоставленные индивидуальным предпринимателям | C40: =SUM(D40:H40)-N40+O40 -> 57899605 | D40: 56248350 | E40: 1809771 | F40: 13621 | G40: 0 | H40: 0 | I40: =SUM(J40:M40) -> 614521 | J40: 186583 | K40: 299277 | L40: 122193 | M40: 6468 | N40: =SUM(O40:S40) -> 787373 | O40: 615236 | P40: 168732 | Q40: 3405 | R40: 0 | S40: 0 | T40: 15000
A41: 32 | B41: Долгосрочные кредиты, предоставленные государственным предприятиям, организациям и учреждениям | C41: =SUM(D41:H41)-N41+O41 -> 706562920 | D41: 706562920 | I41: =SUM(J41:M41) -> 0 | J41: 0 | K41: 0 | L41: 0 | M41: 0 | N41: =SUM(O41:S41) -> 7728278 | O41: 7728278 | T41: 15100
A42: 33 | B42: Долгосрочные кредиты, предоставленные негосударственным некоммерческим организациям | C42: =SUM(D42:H42)-N42+O42 -> 14958733 | D42: 10276403 | E42: 5372687 | F42: 0 | I42: =SUM(J42:M42) -> 812510 | J42: 15911 | K42: 83209 | L42: 544318 | M42: 169072 | N42: =SUM(O42:S42) -> 802759 | O42: 112402 | P42: 690357 | Q42: 0 | R42: 0 | S42: 0 | T42: 15200
A43: 34 | B43: Долгосрочные кредиты, предоставленные предприятиям с участием иностранного капитала | C43: =SUM(D43:H43)-N43+O43 -> 431029828 | D43: 409200375 | E43: 22072253 | F43: 0 | I43: =SUM(J43:M43) -> 76626 | J43: 15335 | K43: 30670 | L43: 30621 | M43: 0 | N43: =SUM(O43:S43) -> 4718572 | O43: 4475772 | P43: 242800 | Q43: 0 | R43: 0 | S43: 0 | T43: 15300
A44: 35 | B44: Долгосрочные кредиты, предоставленные небанковским финансовым институтам | C44: =SUM(D44:H44)-N44+O44 -> 1424539 | D44: 1424539 | I44: =SUM(J44:M44) -> 0 | N44: =SUM(O44:S44) -> 15581 | O44: 15581 | T44: 15400
A45: 36 | B45: Долгосрочные кредиты, предоставленные частным предприятиям, хозяйственным товариществам и обществам | C45: =SUM(D45:H45)-N45+O45 -> 2992636623 | D45: 2941185489 | E45: 55385788 | F45: 1349364 | G45: 0 | H45: 0 | I45: =SUM(J45:M45) -> 30785843 | J45: 8649793 | K45: 7376985 | L45: 6482932 | M45: 8276133 | N45: =SUM(O45:S45) -> 37454259 | O45: 32170241 | P45: 4734018 | Q45: 550000 | R45: 0 | S45: 0 | T45: 15500
A46: 37 | B46: Лизинг (Финансовая аренда) | C46: =SUM(D46:H46)-N46+O46 -> 639526 | D46: 639526 | E46: 0 | F46: 0 | G46: 0 | H46: 0 | I46: =SUM(J46:M46) -> 0 | J46: 0 | K46: 0 | L46: 0 | M46: 0 | N46: =SUM(O46:S46) -> 6995 | O46: 6995 | T46: 15600
A47: 38 | B47: Кредиты и лизинг, находящиеся в процессе судебного разбирательства | C47: =SUM(D47:H47)-N47+O47 -> 0 | I47: =SUM(J47:M47) -> 0 | N47: =SUM(O47:S47) -> 0 | T47: 15700
A48: 39 | B48: Инвестиции в зависимые хозяйственные общества, совместные предприятия и дочерние хозяйственные общества | C48: =SUM(D48:H48)-N48+O48 -> 41111168 | D48: 41055894 | G48: 110548 | I48: =SUM(J48:M48) -> 0 | N48: =SUM(O48:S48) -> 55274 | R48: 55274 | T48: 15800
A49: 40 | B49: Инвестиции в долговые ценные бумаги, удерживаемые до погашения | C49: =SUM(D49:H49)-N49+O49 -> 0 | D49: 0 | I49: =SUM(J49:M49) -> 0 | N49: =SUM(O49:S49) -> 0 | T49: 15900
A50: 41 | B50: Начисленные проценты к получению | C50: =SUM(D50:H50)-N50+O50 -> 126411305 | D50: 126411305 | I50: =SUM(J50:M50) -> 0 | N50: =SUM(O50:S50) -> 0 | T50: 16300
A51: 42 | B51: Начисленные беспроцентные доходы к получению | C51: =SUM(D51:H51)-N51+O51 -> 6532398 | D51: 6532398 | I51: =SUM(J51:M51) -> 0 | N51: =SUM(O51:S51) -> 0 | T51: 16400
A52: 43 | B52: Основные средства | C52: =SUM(D52:H52)-N52+O52 -> 427989486 | D52: 427989486 | I52: =SUM(J52:M52) -> 0 | N52: =SUM(O52:S52) -> 0 | T52: 16500
A53: 44 | B53: Нематериальные активы | C53: =SUM(D53:H53)-N53+O53 -> 34313760 | D53: 34313760 | I53: =SUM(J53:M53) -> 0 | N53: =SUM(O53:S53) -> 0 | T53: 16600
A54: 45 | B54: Другое собственное имущество банка | C54: =SUM(D54:H54)-N54+O54 -> 33496865 | D54: 33496865 | H54: 201348 | I54: =SUM(J54:M54) -> 0 | N54: =SUM(O54:S54) -> 201348 | S54: 201348 | T54: 16700
A55: 46 | B55: Отсроченная дебиторская задолженность | C55: =SUM(D55:H55)-N55+O55 -> 0 | D55: 0 | I55: =SUM(J55:M55) -> 0 | N55: =SUM(O55:S55) -> 0 | T55: 16800
A56: 47 | B56: Нереализованная прибыль при ревальвации производных инструментов | C56: =SUM(D56:H56)-N56+O56 -> 1749067 | D56: 1749067 | I56: =SUM(J56:M56) -> 0 | N56: =SUM(O56:S56) -> 0 | T56: 16900
A57: 48 | B57: Купля-продажа валюты и валютные позиции | C57: =SUM(D57:H57)-N57+O57 -> 0 | D57: 0 | I57: =SUM(J57:M57) -> 0 | N57: =SUM(O57:S57) -> 0 | T57: 17100
A58: 49 | B58: Транзитные счета | C58: =SUM(D58:H58)-N58+O58 -> 0 | D58: 0 | I58: =SUM(J58:M58) -> 0 | N58: =SUM(O58:S58) -> 0 | T58: 17300
A59: 50 | B59: Транзитные счета по средствам к списанию с пластиковых карт клиентов | C59: =SUM(D59:H59)-N59+O59 -> 21125572 | D59: 21125572 | I59: =SUM(J59:M59) -> 0 | N59: =SUM(O59:S59) -> 0 | T59: 17400
A60: 51 | B60: Другие активы | C60: =SUM(D60:H60)-N60+O60 -> 264994413 | D60: 264994412 | H60: 746185 | I60: =SUM(J60:M60) -> 0 | N60: =SUM(O60:S60) -> 746184 | S60: 746184 | T60: 19900
B62: ЗАБАЛАНСОВЫЕ СТАТЬИ | C62: =SUM(D62:H62) -> 525621390 | D62: =SUM(D63:D64) -> 525621390 | E62: =SUM(E63:E64) -> 0 | F62: =SUM(F63:F64) -> 0 | G62: =SUM(G63:G64) -> 0 | H62: =SUM(H63:H64) -> 0 | I62: =SUM(J62:M62) -> 0 | J62: =SUM(J63:J64) -> 0 | K62: =SUM(K63:K64) -> 0 | L62: =SUM(L63:L64) -> 0 | M62: =SUM(M63:M64) -> 0 | N62: =SUM(N63:N64) -> 0 | O62: =SUM(O63:O64) -> 0 | P62: =SUM(P63:P64) -> 0 | Q62: =SUM(Q63:Q64) -> 0 | ... S62: =SUM(S63:S64) -> 0
A63: 1 | B63: Аккредитивы | C63: =SUM(D63:H63)-N63+O63 -> 231843131 | D63: 231843131 | I63: =SUM(J63:M63) -> 0 | N63: =SUM(O63:S63) -> 0 | T63: 90908-90958
A64: 2 | B64: Гарантии и поручетельства | C64: =SUM(D64:H64)-N64+O64 -> 293778259 | D64: 293778259 | I64: =SUM(J64:M64) -> 0 | N64: =SUM(O64:S64) -> 0 | T64: 90993
B67: Подпись Председателя правления:
B69: Подпись Главного Бухгалтера:
B71: Состав активов банка формируется в соответсвии с Планом счетов
C72: =+[8]Balance!$C$45 -> 8108166331

Sheet Income 
B1: ОТЧЕТ О ФИНАНСОВЫХ РЕЗУЛЬТАТАХ | D1: Таблица-3
B3: =+'Asset quality'!B3 -> АК "Алокабанк" | C3: =+'Asset quality'!P3 -> 44196 | E3: в тыс. сум
A4: № | B4: Категории | C4: Итого | D4: в национальной валюте | E4: в иностранной валюте (в экв. в сумах)
A5: 1. | B5: 1. ПРОЦЕНТНЫЕ ДОХОДЫ
A6: a. | B6: Процентные доходы по счетам в ЦБРУ | C6: =+D6+E6 -> 2418508 | D6: 2418508 | E6: 0
A7: б. | B7: Процентные доходы по счетам в других банках | C7: =+D7+E7 -> 19392899 | D7: 12283332 | E7: 7109567
A8: в. | B8: Процентные доходы по купленным векселям | C8: =+D8+E8 -> 0 | D8: 0 | E8: 0
A9: г. | B9: Процентные доходы по инвестициям | C9: =+D9+E9 -> 0 | D9: 0 | E9: 0
A10: д. | B10: Процентные доходы по счетам купли-продажи ценных бумаг | C10: =+D10+E10 -> 27019780 | D10: 27019780 | E10: 0
A11: е. | B11: Процентные доходы по обязательствам клиентов | C11: =+D11+E11 -> 0 | D11: 0 | E11: 0
A12: ж. | B12: Процентные доходы по обяз-вам клиентов по непогашенным акцептам этого банка | C12: =+D12+E12 -> 14390522 | D12: 6017575 | E12: 8372947
A13: з. | B13: Процент, Дисконт (Скидки) и взносы по кредитным и лизинговым операциям | C13: =+D13+E13 -> 809668910 | D13: 668826621 | E13: 140842289
A14: и. | B14: Процентные доходы по соглашениям о покупке ценных бумаг с обратным выкупом | C14: =+D14+E14 -> 0 | D14: 0 | E14: 0
A15: к. | B15: Другие процентные доходы | C15: =+D15+E15 -> 312983639 | D15: 245717672 | E15: 67265967
A16: л. | B16: Итого процентных доходов | C16: =SUM(C6:C15) -> 1185874258 | D16: =SUM(D6:D15) -> 962283488 | E16: =SUM(E6:E15) -> 223590770 | G16: =+'Analysis of Interest'!C42 -> 1185874258
A18: 2. | B18: ПРОЦЕНТНЫЕ РАСХОДЫ
A19: а. | B19: Процентные расходы по депозитам до востребования | C19: =+D19+E19 -> 2744263 | D19: 2568266 | E19: 175997
A20: б. | B20: Процентные расходы по срочным депозитам | C20: =+D20+E20 -> 405792705 | D20: 361158722 | E20: 44633983
A21: в. | B21: Процентные расходы по счетам к оплате в ЦБРУ | C21: =+D21+E21 -> 0 | D21: 0 | E21: 0
A22: г. | B22: Процентные расходы по счетам к оплате в другие банки | C22: =+D22+E22 -> 55867688 | D22: 35681600 | E22: 20186088
A23: д. | B23: Итого процентных расходов по депозитам | C23: =SUM(C19:C22) -> 464404656 | D23: =SUM(D19:D22) -> 399408588 | E23: =SUM(E19:E22) -> 64996068
A24: е. | B24: Процентные расходы по кредитам к оплате | C24: =+D24+E24 -> 25140419 | D24: 5905209 | E24: 19235210
A25: ж. | B25: Процентные расходы по соглашениям о продаже ц/б с последующим выкупом | C25: =+D25+E25 -> 9175036 | D25: 9175036 | E25: 0
A26: з. | B26: Другие процентные расходы | C26: =+D26+E26 -> 320618142 | D26: 250227780 | E26: 70390362
A27: и. | B27: Итого процентных расходов по займам | C27: =SUM(C24:C26) -> 354933597 | D27: =SUM(D24:D26) -> 265308025 | E27: =SUM(E24:E26) -> 89625572
A28: л. | B28: Итого процентных расходов | C28: =C27+C23 -> 819338253 | D28: =D27+D23 -> 664716613 | E28: =E27+E23 -> 154621640 | G28: =+'Analysis of Interest'!C72 -> 819338253
A30: 3. | B30: ЧИСТЫЕ ПРОЦЕНТНЫЕ ДОХОДЫ ДО ОЦЕНКИ ВОЗМОЖНЫХ УБЫТКОВ ПО АКТИВАМ | C30: =C16-C28 -> 366536005 | D30: =D16-D28 -> 297566875 | E30: =E16-E28 -> 68969130
A31: а. | B31: Минус: Оценка возможных убытков по кредитам и лизингу | C31: =+D31+E31 -> 12410997 | D31: 12056751 | E31: 354246
A32: б. | B32: Минус: Оценка возможных убытков по в ценным бумагам | C32: =+D32+E32 -> 0 | D32: 0 | E32: 0
A33: в. | B33: Минус: Оценка возможных убытков по инвестициям | C33: =+D33+E33 -> 0 | D33: 0 | E33: 0
A34: г. | B34: Минус: Оценка возможных убытков по другим активам | C34: =+D34+E34 -> 1375976 | D34: 1375976 | E34: 0
A35: д. | B35: Чистые процентные доходы после оценки возможных убытков по кредитам и лизингу | C35: =C30-C31-C32-C33-C34 -> 352749032 | D35: =D30-D31-D32-D33-D34 -> 284134148 | E35: =E30-E31-E32-E33-E34 -> 68614884
A37: 4. | B37: БЕСПРОЦЕНТНЫЕ ДОХОДЫ
A38: а. | B38: Доходы от комиссий и платы за услуги | C38: =+D38+E38 -> 193159885 | D38: 185807323 | E38: 7352562
A39: б. | B39: Прибыль в иностранной валюте | C39: =+D39+E39 -> 69811238 | D39: 6140505 | E39: 63670733
A40: в. | B40: Прибыль от коммерческих операций | C40: =+D40+E40 -> 0 | D40: 0 | E40: 0
A41: г. | B41: Прибыль и дивиденды от инвестиций | C41: =+D41+E41 -> 3427132 | D41: 3427132 | E41: 0
A42: д. | B42: Другие беспроцентные доходы | C42: =+D42+E42 -> 28083485 | D42: 23997307 | E42: 4086178
A43: е. | B43: Итого беспроцентных доходов | C43: =SUM(C38:C42) -> 294481740 | D43: =SUM(D38:D42) -> 219372267 | E43: =SUM(E38:E42) -> 75109473
A45: 5. | B45: БЕСПРОЦЕНТНЫЕ РАСХОДЫ
A46: а. | B46: Комиссионные расходы и расходы за услуги | C46: =+D46+E46 -> 96701899 | D46: 94182515 | E46: 2519384
A47: б. | B47: Убытки в иностранной валюте | C47: =+D47+E47 -> 71056726 | D47: 10123936 | E47: 60932790
A48: в. | B48: Убытки по счетам купли-продажи | C48: =+D48+E48 -> 2212040 | D48: 2212040 | E48: 0
A49: г. | B49: Убытки от инвестиций | C49: =+D49+E49 -> 0 | D49: 0 | E49: 0
A50: д. | B50: Другие беспроцентные расходы | C50: =+D50+E50 -> 84060 | D50: 84060 | E50: 0
A51: е. | B51: Итого беспроцентных расходов | C51: =SUM(C46:C50) -> 170054725 | D51: =SUM(D46:D50) -> 106602551 | E51: =SUM(E46:E50) -> 63452174
A53: 6. | B53: ЧИСТЫЙ ДОХОД ДО ОПЕРАЦИОННЫХ РАСХОДОВ | C53: =C35+C43-C51 -> 477176047 | D53: =D35+D43-D51 -> 396903864 | E53: =E35+E43-E51 -> 80272183
A55: 7. | B55: ОПЕРАЦИОННЫЕ РАСХОДЫ
A56: а. | B56: Заработная плата и другие расходы на сотрудников | C56: 176293103 | D56: 176293103
A57: а1) | B57: из них, выплаты основному руководящему персоналу | C57: 16304105 | D57: 16304105
A58: б. | B58: Аренда и содержание | C58: 20481774 | D58: 20481774
A59: в. | B59: Командировочные и транспортные расходы | C59: 2052434 | D59: 2052434
A60: г. | B60: Административные расходы | C60: 14616303 | D60: 14616303
A61: д. | B61: Репрезентация и благотворительность | C61: 23795977 | D61: 23795977
A62: е. | B62: Расходы на износ | C62: 20612652 | D62: 20612652
A63: ж. | B63: Страхование | C63: 453988 | D63: 453988
A64: з. | B64: Налоги | C64: 3013199 | D64: 3013199
A65: и. | B65: Штрафы и пеня | C65: 527076 | D65: 527076
A66: к. | B66: Другие операционные расходы | C66: 2646419 | D66: 2646419
A67: л. | B67: Итого операционных расходов | C67: =SUM(C56:C66)-C57 -> 264492925 | D67: =SUM(D56:D66)-D57 -> 264492925
A69: 8. | B69: ЧИСТАЯ ПРИБЫЛЬ ДО УПЛАТЫ НАЛОГОВ И ДРУГИХ ПОПРАВОК | C69: =C53-C67 -> 212683122 | D69: =D53-D67 -> 132410939 | E69: =+E53-(C67-D67) -> 80272183
A70: а. | B70: Оценка налога на прибыль | C70: =+D70 -> 42683122 | D70: 42683122
A72: 9. | B72: ДОХОД ДО ВВЕДЕНИЯ ПОПРАВОК | C72: =C69-C70 -> 170000000 | D72: =D69-D70 -> 89727817 | E72: =E69-E70 -> 80272183
A73: а. | B73: Непредвиденные доходы или убытки, чистые | C73: =+D73+E73 -> 0 | D73: 0 | E73: 0
A74: б. | B74: Другие поправки к прибыли, чистые | C74: =+D74+E74 -> 0 | D74: 0 | E74: 0
A76: 10. | B76: ЧИСТАЯ ПРИБЫЛЬ (УБЫТКИ) | C76: =C72+C73+C74 -> 170000000 | D76: =D72+D73+D74 -> 89727817 | E76: =E72+E73+E74 -> 80272183
B78: Подпись Председателя правления:
B80: Подпись Главного Бухгалтера:

Sheet Analysis of Interest
B1: АНАЛИЗ ПРОЦЕНТНЫХ ДОХОДОВ И РАСХОДОВ | C1: Таблица-4
B3: =+'Asset quality'!B3 -> АК "Алокабанк" | C3: =+'Asset quality'!P3 -> 44196
A4: № | B4: Категория | C4: в тыс. сум
A5: 1 . | B5: ПРОЦЕНТНЫЕ ДОХОДЫ ПО КРЕДИТНЫМ И ЛИЗИНГОВЫМ ОПЕРАЦИЯМ
A6: a. | B6: Кредиты и лизинговые операции ЦБРУ | C6: 0
A7: б. | B7: Кредиты и лизинговые операции другим банкам | C7: 0
A8: в. | B8: Кредиты и лизинговые операции Правительству | C8: 0
A9: г. | B9: Кредиты и лизинговые операции физическим лицам | C9: 198040984
A10: д. | B10: Кредиты и лизинговые операции государственным предприятиям | C10: 75953823
A11: е. | B11: Кредиты и лизинговые операции совместным и иностранным предприятиям | C11: 70472407
A12: ж. | B12: Кредиты и лизинговые операции частным товариществам и корпорациям | C12: 445373824
A13: з. | B13: Другие кредиты и лизинговые операции | C13: 19827873
A14: и. | B14: ИТОГО ПРОЦЕНТНЫХ ДОХОДОВ ПО КРЕДИТНЫМ И ЛИЗИНГОВЫМ ОПЕРАЦИЯМ | C14: =SUM(C6:C13) -> 809668911
A16: 2. | B16: ПРОЦЕНТНЫЕ ДОХОДЫ ПО КОРРЕСПОНДЕНТСКИМ СЧЕТАМ
A17: a. | B17: К получению из ЦБРУ | C17: 2418508
A18: б. | B18: К получению из других банков | C18: 19392899
B19: ИТОГО ПРОЦЕНТНЫХ ДОХОДОВ ПО КОРРЕСПОНДЕНТСКИМ СЧЕТАМ | C19: =SUM(C17:C18) -> 21811407
A21: 3. | B21: ПРОЦЕНТНЫЕ ДОХОДЫ ПО СЧЕТАМ КУПЛИ-ПРОДАЖИ Ц/Б
A22: a. | B22: Государственные казначейские ценные бумаги | C22: 9710959
A23: б. | B23: Облигации и ценные бумаги ЦБРУ | C23: 17308821
A24: в. | B24: Ценные бумаги государственных корпораций | C24: 0
A25: г. | B25: Еврооблигации | C25: 0
A26: д. | B26: Частные ценные бумаги | C26: 0
A27: е. | B27: Другие ценные бумаги | C27: 0
A28: ж. | B28: ИТОГО ПРОЦЕНТНЫХ ДОХОДОВ ПО СЧЕТАМ КУПЛИ-ПРОДАЖИ Ц/Б | C28: =SUM(C22:C27) -> 27019780
A30: 4. | B30: ПРОЦЕНТНЫЕ ДОХОДЫ ПО ИНВЕСТИЦИЯМ
A31: a. | B31: Государственные облигации | C31: 0
A32: б. | B32: Облигации и ценные бумаги ЦБРУ | C32: 0
A33: в. | B33: Частные облигации | C33: 0
A34: г. | B34: Еврооблигации | C34: 0
A35: д. | B35: Другие ценные бумаги | C35: 0
A36: е. | B36: ИТОГО ПРОЦЕНТНЫХ ДОХОДОВ ПО ИНВЕСТИЦИЯМ | C36: =SUM(C31:C35) -> 0
A38: 5. | B38: ДРУГИЕ ПРОЦЕНТНЫЕ ДОХОДЫ
A39: a. | B39: Процентные доходы по соглашениям о покупке ц/б c обратным выкупом | C39: 0
A40: б. | B40: Другие процентные доходы | C40: 327374160
A42: 6. | B42: ИТОГО ПРОЦЕНТНЫХ ДОХОДОВ | C42: =C14+C19+C28+C36+C39+C40 -> 1185874258
A44: 7. | B44: ПРОЦЕНТНЫЕ РАСХОДЫ ПО ДЕПОЗИТАМ
A45: A. | B45: Депозиты до востребования
A46: a. | B46: Правительство | C46: 1302247
A47: б. | B47: Физические лица | C47: 4748
A48: в. | B48: Государственные предприятия | C48: 978499
A49: г. | B49: Совместные и иностранные предприятия | C49: 185152
A50: д. | B50: Частные товарищества и корпорации | C50: 214311
A51: е. | B51: Другие депозиты | C51: 59304
A52: ж. | B52: Итого процентных расходов по депозитам до востребования | C52: =SUM(C46:C51) -> 2744261
A54: Б. | B54: Срочные депозиты
A55: a. | B55: Правительство | C55: 158396207
A56: б. | B56: Физические лица | C56: 40367657
A57: в. | B57: Государственные предприятия | C57: 38537386
A58: г. | B58: Совместные и иностранные предприятия | C58: 3294301
A59: д. | B59: Частные товарищества и корпорации | C59: 110613834
A60: е. | B60: Другие депозиты | C60: 54583319
A61: ж. | B61: Итого процентных расходов по срочным депозитам | C61: =SUM(C55:C60) -> 405792704
A63: В. | B63: ИТОГО ПРОЦЕНТНЫХ РАСХОДОВ ПО ДЕПОЗИТАМ | C63: =C52+C61 -> 408536965
A65: 8. | B65: ПРОЦЕНТНЫЕ РАСХОДЫ ПО ДРУГИМ ОБЯЗАТЕЛЬСТВАМ
A66: а. | B66: Процентные расходы по непогашенным акцептам | C66: 4472296
A67: б. | B67: Процентные расходы по кредитам к оплате | C67: 25140419
A68: в. | B68: Процентные расходы по соглашениям о продаже ц/б с последующим выкупом | C68: 9175036
A69: г. | B69: Другие процентные расходы | C69: 372013537
A70: д. | B70: ИТОГО ПРОЦЕНТНЫХ РАСХОДОВ ПО ДРУГИМ ОБЯЗАТЕЛЬСТВАМ | C70: =SUM(C66:C69) -> 410801288
A72: 9. | B72: ИТОГО ПРОЦЕНТНЫХ РАСХОДОВ | C72: =C63+C70 -> 819338253
B74: Подпись Председателя правления:
B76: Подпись Главного Бухгалтера:

Sheet Changes in Equity
B1: ИЗМЕНЕНИЯ В СОБСТВЕННОМ КАПИТАЛЕ | C1: Таблица-7
B3: =+'Asset quality'!B3 -> АК "Алокабанк" | C3: =+'Asset quality'!P3 -> 44196
A4: № | B4: Категория | C4: в тыс. сум
A5: 1. | B5: Итого собственного капитала первоначально определенного за прошлый год | C5: 1396370695
A6: 2. | B6: Исправления в собственном капитале не показанные в отчете за прошлый год, чистые | C6: -132057
A7: 3. | B7: Исправленный баланс на конец прошлого календарного года (сумма строк 1 и 2) | C7: =SUM(C5:C6) -> 1396238638
A8: 4. | B8: Чистый прибыль (убыток) по состоянию на дату от начала года | C8: =+'Income '!C76 -> 170000000 | D8: =+[8]Balance!$C$76 -> 170000000
A9: 5. | B9: Продажа, Обмен, Приобретение или выкуп акций, за текущий год (чистая выручка) | C9: 0
A10: 6. | B10: Изменения в оценочной стоимости прироста над первонач. стоимостью, за текущий год (чистые) | C10: 3793523
A11: 7. | B11: МИНУС: Денежные дивиденды объявленные по привилегированным акциям | C11: 0
A12: 8. | B12: МИНУС: Денежные дивиденды объявленные по обыкновенным акциям | C12: 0
A13: 9. | B13: Другие статьи влияющие на собственный капитал за текущий год (чистые) | C13: -1502349
A14: 10. | B14: Итого собственного капитала на конец текущего периода (сумма строк с 3 по 10) | C14: =C7+SUM(C8:C10)-SUM(C11:C12)+C13 -> 1568529812 | D14: =+[8]Balance!$C$77 -> 1568529812
B16: Подпись Председателя правления:
B18: Подпись Главного Бухгалтера:

Sheet Loans Receivable
A1: КРЕДИТЫ И ЛИЗИНГИ К ПОЛУЧЕНИЮ ПО ОТРАСЛЯМ ЭКОНОМИКИ, ТИПАМ КЛИЕНТОВ И ПО ТИПУ ОБЕСПЕЧЕНИЯ | W1: Таблица-8
B3: =+'Asset quality'!B3 -> АК "Алокабанк" | T3: =+'Asset quality'!P3 -> 44196 | X3: тыс. сум
A4: № | B4: Отрасль экономики | C4: Сумма кредита | D4: в национальной валюте | F4: в иностранной валюте (в экв. в сумах) | H4: из них | J4: из них
D5: Сумма | E5: средне-взвешенные процентные ставки | F5: Сумма | G5: средне-взвешенные процентные ставки | H5: Начисляемые кредиты | I5: Кредиты переведённые в статус ненаращивания процентов | J5: Депозиты | K5: Гарантированные Правительством Республики Узбекистан | L5: из них | M5: Транспортные средства | N5: Инвентарь | O5: Недвижимость | P5: из них | R5: Оборудование | S5: Векселя (облигации) | T5: Акции | U5: Гарантия третьей стороны | V5: Поручительства третьей стороны | W5: Страховой полис | X5: Необеспеченные | Y5: Другое обеспечение
L6: Гарантированные Правительством Республики Узбекистан в иностранной валюте (экв.сум) | P6: жилая недвижимость | Q6: коммерческая недвижимость
A7: Код | B7: (А) | C7: (Б) | D7: (Б1) | E7: (Б2) | F7: (Б3) | G7: (Б4) | H7: (В) | I7: (Г) | J7: (Д) | K7: (Е) | L7: (Е1) | M7: (Ж) | N7: (З) | O7: (И) | P7: (И1) | Q7: (И2) | R7: (К) | S7: (Л) | T7: (М) | U7: (Н) | V7: (О) | W7: (П) | X7: (Р) | Y7: (С)
B8: Промышленность
A9: 10 | B9: Физические лица | C9: =SUM(J9:Y9)-L9-P9-Q9 -> 0 | O9: =+P9+Q9 -> 0
A10: =A9+10 -> 20 | B10: Государственные предприятия | C10: =SUM(J10:Y10)-L10-P10-Q10 -> 61193904 | D10: 61193904 | E10: 0.19267973 | H10: 61193904 | I10: 0 | J10: 0 | K10: 0 | M10: 14126062 | O10: =+P10+Q10 -> 36362525 | Q10: 36362525 | R10: 0 | S10: 0 | T10: 0 | U10: 0 | V10: 10705317 | W10: 0 | X10: 0 | Y10: 0
A11: =A10+10 -> 30 | B11: Совместные и иностранные предприятия | C11: =SUM(J11:Y11)-L11-P11-Q11 -> 220704413 | D11: 180690724 | E11: 0.18963013 | F11: 40013689 | G11: 0.08847224 | H11: 220704413 | I11: 0 | J11: 0 | K11: 0 | M11: 659597 | O11: =+P11+Q11 -> 208326179 | Q11: 208326179 | R11: 9953669 | S11: 0 | T11: 0 | U11: 0 | V11: 1535202 | W11: 229766 | X11: 0 | Y11: 0
A12: =A11+10 -> 40 | B12: Частные товарищества и корпорации | C12: =SUM(J12:Y12)-L12-P12-Q12 -> 679011714 | D12: 273162529 | E12: 0.19607391 | F12: 405849185 | G12: 0.07348888 | H12: 678842521 | I12: 169193 | J12: 30300 | K12: 0 | M12: 44263230 | O12: =+P12+Q12 -> 440006984 | Q12: 440006984 | R12: 185753199 | S12: 0 | T12: 0 | U12: 0 | V12: 8654567 | W12: 275107 | X12: 0 | Y12: 28327
A13: =A12+10 -> 50 | B13: Правительство | C13: =SUM(J13:Y13)-L13-P13-Q13 -> 0 | O13: =+P13+Q13 -> 0
A14: =A13+10 -> 60 | B14: Прочие | C14: =SUM(J14:Y14)-L14-P14-Q14 -> 4438396 | D14: 4438396 | E14: 0.21729926 | H14: 4438396 | M14: 2184879 | O14: =+P14+Q14 -> 2205476 | Q14: 2205476 | R14: 0 | S14: 0 | T14: 0 | U14: 0 | V14: 22627 | W14: 25414 | X14: 0 | Y14: 0
A15: =A14+10 -> 70 | B15: Итого по промышленности | C15: =SUM(J15:Y15)-L15-P15-Q15 -> 965348427 | D15: =SUM(D9:D14) -> 519485553 | E15: =IFERROR(((D9*E9)/D15)+((D10*E10)/D15)+((D11*E11)/D15)+((D12*E12)/D15)+((D13*E13)/D15)+((D14*E14)/D15),0) -> 0.19361411 | F15: =SUM(F9:F14) -> 445862874 | G15: =IFERROR(((F9*G9)/F15)+((F10*G10)/F15)+((F11*G11)/F15)+((F12*G12)/F15)+((F13*G13)/F15)+((F14*G14)/F15),0) -> 0.074833552 | H15: =SUM(H9:H14) -> 965179234 | I15: =SUM(I9:I14) -> 169193 | J15: =SUM(J9:J14) -> 30300 | K15: =SUM(K9:K14) -> 0 | L15: =SUM(L9:L14) -> 0 | M15: =SUM(M9:M14) -> 61233768 | N15: =SUM(N9:N14) -> 0 | O15: =SUM(O9:O14) -> 686901164 | ... Y15: =SUM(Y9:Y14) -> 28327
B16: Сельское хозяйство
A17: =A15+10 -> 80 | B17: Физические лица | C17: =SUM(J17:Y17)-L17-P17-Q17 -> 0 | O17: =+P17+Q17 -> 0
A18: =A17+10 -> 90 | B18: Государственные предприятия | C18: =SUM(J18:Y18)-L18-P18-Q18 -> 0 | O18: =+P18+Q18 -> 0
A19: =A18+10 -> 100 | B19: Совместные и иностранные предприятия | C19: =SUM(J19:Y19)-L19-P19-Q19 -> 0 | O19: =+P19+Q19 -> 0
A20: =A19+10 -> 110 | B20: Частные товарищества и корпорации | C20: =SUM(J20:Y20)-L20-P20-Q20 -> 111388171 | D20: 57688485 | E20: 0.19018186 | F20: 53699686 | G20: 0.093366011 | H20: 111353891 | I20: 34280 | M20: 34580459 | N20: 0 | O20: =+P20+Q20 -> 56037268 | Q20: 56037268 | R20: 14985280 | S20: 0 | T20: 0 | U20: 0 | V20: 5675708 | W20: 109456 | X20: 0 | Y20: 0
A21: =A20+10 -> 120 | B21: Фермерское хозяйство | C21: =SUM(J21:Y21)-L21-P21-Q21 -> 0 | O21: =+P21+Q21 -> 0
A22: =A21+10 -> 130 | B22: Правительство | C22: =SUM(J22:Y22)-L22-P22-Q22 -> 0 | O22: =+P22+Q22 -> 0
A23: =A22+10 -> 140 | B23: Прочие | C23: =SUM(J23:Y23)-L23-P23-Q23 -> 2194100 | D23: 2194100 | E23: 0.18993801 | H23: 2194100 | O23: =+P23+Q23 -> 1838080 | Q23: 1838080 | S23: 0 | T23: 0 | U23: 0 | V23: 149227 | W23: 201136 | X23: 0 | Y23: 5657
A24: =A23+10 -> 150 | B24: Итого по сельскому хозяйству | C24: =SUM(J24:Y24)-L24-P24-Q24 -> 113582271 | D24: =SUM(D17:D23) -> 59882585 | E24: =IFERROR(((D17*E17)/D24)+((D18*E18)/D24)+((D19*E19)/D24)+((D20*E20)/D24)+((D21*E21)/D24)+((D22*E22)/D24)+((D23*E23)/D24),0) -> 0.19017293 | F24: =SUM(F17:F23) -> 53699686 | G24: =IFERROR(((F17*G17)/F24)+((F18*G18)/F24)+((F19*G19)/F24)+((F20*G20)/F24)+((F21*G21)/F24)+((F22*G22)/F24)+((F23*G23)/F24),0) -> 0.093366011 | H24: =SUM(H17:H23) -> 113547991 | I24: =SUM(I17:I23) -> 34280 | J24: =SUM(J17:J23) -> 0 | K24: =SUM(K17:K23) -> 0 | L24: =SUM(L17:L23) -> 0 | M24: =SUM(M17:M23) -> 34580459 | N24: =SUM(N17:N23) -> 0 | O24: =SUM(O17:O23) -> 57875348 | ... Y24: =SUM(Y17:Y23) -> 5657
B25: Транспорт и коммуникации
A26: =A24+10 -> 160 | B26: Физические лица | C26: =SUM(J26:Y26)-L26-P26-Q26 -> 0 | O26: =+P26+Q26 -> 0
A27: =A26+10 -> 170 | B27: Государственные предприятия | C27: =SUM(J27:Y27)-L27-P27-Q27 -> 363140450 | D27: 363140450 | E27: 0.12184635 | H27: 363140450 | J27: 216263967 | K27: 0 | M27: 7032 | N27: 0 | O27: =+P27+Q27 -> 133604201 | Q27: 133604201 | R27: 0 | S27: 0 | T27: 0 | U27: 0 | V27: 33600 | W27: 13231650 | X27: 0 | Y27: 0
A28: =A27+10 -> 180 | B28: Совместные и иностранные предприятия | C28: =SUM(J28:Y28)-L28-P28-Q28 -> 99981592 | D28: 99981592 | E28: 0.15 | H28: 99981592 | J28: 0 | K28: 0 | M28: 0 | N28: 0 | O28: =+P28+Q28 -> 99981592 | Q28: 99981592 | R28: 0 | S28: 0 | T28: 0 | U28: 0 | V28: 0 | W28: 0 | X28: 0 | Y28: 0
A29: =A28+10 -> 190 | B29: Частные товарищества и корпорации | C29: =SUM(J29:Y29)-L29-P29-Q29 -> 65589004 | D29: 54445535 | E29: 0.20415534 | F29: 11143469 | G29: 0.094929392 | H29: 65589004 | J29: 45114 | K29: 0 | M29: 39854264 | N29: 0 | O29: =+P29+Q29 -> 25107788 | Q29: 25107788 | R29: 241698 | S29: 0 | T29: 0 | U29: 0 | V29: 251059 | W29: 89081 | X29: 0 | Y29: 0
A30: =A29+10 -> 200 | B30: Правительство | C30: =SUM(J30:Y30)-L30-P30-Q30 -> 0 | O30: =+P30+Q30 -> 0
A31: =A30+10 -> 210 | B31: Прочие | C31: =SUM(J31:Y31)-L31-P31-Q31 -> 14611472 | D31: 14611472 | E31: 0.21427128 | H31: 14611472 | J31: 30430 | K31: 0 | M31: 13837573 | N31: 0 | O31: =+P31+Q31 -> 655997 | Q31: 655997 | R31: 0 | S31: 0 | T31: 0 | U31: 0 | V31: 5796 | W31: 81676 | X31: 0 | Y31: 0
A32: =A31+10 -> 220 | B32: Итого по транспорту и коммуникациям | C32: =SUM(J32:Y32)-L32-P32-Q32 -> 543322518 | D32: =SUM(D26:D31) -> 532179049 | E32: =IFERROR(((D26*E26)/D32)+((D27*E27)/D32)+((D28*E28)/D32)+((D29*E29)/D32)+((D30*E30)/D32)+((D31*E31)/D32),0) -> 0.13809402 | F32: =SUM(F26:F31) -> 11143469 | G32: =IFERROR(((F26*G26)/F32)+((F27*G27)/F32)+((F28*G28)/F32)+((F29*G29)/F32)+((F30*G30)/F32)+((F31*G31)/F32),0) -> 0.094929392 | H32: =SUM(H26:H31) -> 543322518 | I32: =SUM(I26:I31) -> 0 | J32: =SUM(J26:J31) -> 216339511 | K32: =SUM(K26:K31) -> 0 | L32: =SUM(L26:L31) -> 0 | M32: =SUM(M26:M31) -> 53698869 | N32: =SUM(N26:N31) -> 0 | O32: =SUM(O26:O31) -> 259349578 | ... Y32: =SUM(Y26:Y31) -> 0
B33: Строительство
A34: =A32+10 -> 230 | B34: Физические лица | C34: =SUM(J34:Y34)-L34-P34-Q34 -> 0 | O34: =+P34+Q34 -> 0
A35: =A34+10 -> 240 | B35: Государственные предприятия | C35: =SUM(J35:Y35)-L35-P35-Q35 -> 245351 | D35: 245351 | E35: 0.23807764 | H35: 245351 | J35: 0 | K35: 0 | M35: 243716 | N35: 0 | O35: =+P35+Q35 -> 0 | Q35: 0 | R35: 0 | S35: 0 | T35: 0 | U35: 0 | V35: 0 | W35: 1635 | X35: 0 | Y35: 0
A36: =A35+10 -> 250 | B36: Совместные и иностранные предприятия | C36: =SUM(J36:Y36)-L36-P36-Q36 -> 0 | H36: 0 | J36: 0 | K36: 0 | M36: 0 | N36: 0 | O36: =+P36+Q36 -> 0 | Q36: 0 | R36: 0 | S36: 0 | T36: 0 | U36: 0 | V36: 0 | W36: 0 | X36: 0 | Y36: 0
A37: =A36+10 -> 260 | B37: Частные товарищества и корпорации | C37: =SUM(J37:Y37)-L37-P37-Q37 -> 283095278 | D37: 162329475 | E37: 0.20526708 | F37: 120765803 | G37: 0.079655054 | H37: 283095278 | J37: 305412 | K37: 0 | M37: 43361438 | N37: 0 | O37: =+P37+Q37 -> 196853232 | Q37: 196853232 | R37: 40230902 | S37: 0 | T37: 0 | U37: 0 | V37: 2183563 | W37: 160731 | X37: 0 | Y37: 0
A38: =A37+10 -> 270 | B38: Правительство | C38: =SUM(J38:Y38)-L38-P38-Q38 -> 0 | O38: =+P38+Q38 -> 0
A39: =A38+10 -> 280 | B39: Прочие | C39: =SUM(J39:Y39)-L39-P39-Q39 -> 0 | O39: =+P39+Q39 -> 0
A40: =A39+10 -> 290 | B40: Итого по строительству | C40: =SUM(J40:Y40)-L40-P40-Q40 -> 283340629 | D40: =SUM(D34:D39) -> 162574826 | E40: =IFERROR(((D34*E34)/D40)+((D35*E35)/D40)+((D36*E36)/D40)+((D37*E37)/D40)+((D38*E38)/D40)+((D39*E39)/D40),0) -> 0.2053166 | F40: =SUM(F34:F39) -> 120765803 | G40: =IFERROR(((F34*G34)/F40)+((F35*G35)/F40)+((F36*G36)/F40)+((F37*G37)/F40)+((F38*G38)/F40)+((F39*G39)/F40),0) -> 0.079655054 | H40: =SUM(H34:H39) -> 283340629 | I40: =SUM(I34:I39) -> 0 | J40: =SUM(J34:J39) -> 305412 | K40: =SUM(K34:K39) -> 0 | L40: =SUM(L34:L39) -> 0 | M40: =SUM(M34:M39) -> 43605154 | N40: =SUM(N34:N39) -> 0 | O40: =SUM(O34:O39) -> 196853232 | ... Y40: =SUM(Y34:Y39) -> 0
B41: Торговля и общественное питание
A42: =A40+10 -> 300 | B42: Физические лица | C42: =SUM(J42:Y42)-L42-P42-Q42 -> 0 | O42: =+P42+Q42 -> 0
A43: =A42+10 -> 310 | B43: Государственные предприятия | C43: =SUM(J43:Y43)-L43-P43-Q43 -> 0 | O43: =+P43+Q43 -> 0
A44: =A43+10 -> 320 | B44: Совместные и иностранные предприятия | C44: =SUM(J44:Y44)-L44-P44-Q44 -> 0 | O44: =+P44+Q44 -> 0
A45: =A44+10 -> 330 | B45: Частные товарищества и корпорации | C45: =SUM(J45:Y45)-L45-P45-Q45 -> 138956640 | D45: 119458478 | E45: 0.2057157 | F45: 19498162 | G45: 0.097125217 | H45: 138956640 | I45: 0 | J45: 330191 | M45: 15512878 | N45: 0 | O45: =+P45+Q45 -> 110854591 | Q45: 110854591 | R45: 10048781 | S45: 0 | T45: 0 | U45: 0 | V45: 2099976 | W45: 101594 | X45: 0 | Y45: 8629
A46: =A45+10 -> 340 | B46: Правительство | C46: =SUM(J46:Y46)-L46-P46-Q46 -> 0 | H46: 0 | J46: 0 | K46: 0 | M46: 0 | N46: 0 | O46: =+P46+Q46 -> 0 | Q46: 0 | R46: 0 | S46: 0 | T46: 0 | U46: 0 | V46: 0 | W46: 0 | X46: 0 | Y46: 0
A47: =A46+10 -> 350 | B47: Прочие | C47: =SUM(J47:Y47)-L47-P47-Q47 -> 12963628 | D47: 12963628 | E47: 0.21301924 | F47: 0 | H47: 12963628 | J47: 69439 | K47: 0 | M47: 7056083 | N47: 0 | O47: =+P47+Q47 -> 5754484 | Q47: 5754484 | R47: 5063 | S47: 0 | T47: 0 | U47: 0 | V47: 21700 | W47: 56859 | X47: 0 | Y47: 0
A48: =A47+10 -> 360 | B48: Итого по торговле и общественному питанию | C48: =SUM(J48:Y48)-L48-P48-Q48 -> 151920268 | D48: =SUM(D42:D47) -> 132422106 | E48: =IFERROR(((D42*E42)/D48)+((D43*E43)/D48)+((D44*E44)/D48)+((D45*E45)/D48)+((D46*E46)/D48)+((D47*E47)/D48),0) -> 0.20643069 | F48: =SUM(F42:F47) -> 19498162 | G48: =IFERROR(((F42*G42)/F48)+((F43*G43)/F48)+((F44*G44)/F48)+((F45*G45)/F48)+((F46*G46)/F48)+((F47*G47)/F48),0) -> 0.097125217 | H48: =SUM(H42:H47) -> 151920268 | I48: =SUM(I42:I47) -> 0 | J48: =SUM(J42:J47) -> 399630 | K48: =SUM(K42:K47) -> 0 | L48: =SUM(L42:L47) -> 0 | M48: =SUM(M42:M47) -> 22568961 | N48: =SUM(N42:N47) -> 0 | O48: =SUM(O42:O47) -> 116609075 | ... Y48: =SUM(Y42:Y47) -> 8629
B49: Материально-техническое снабжение и сбыт
A50: =A48+10 -> 370 | B50: Физические лица | C50: =SUM(J50:Y50)-L50-P50-Q50 -> 0 | O50: =+P50+Q50 -> 0
A51: =A50+10 -> 380 | B51: Государственные предприятия | C51: =SUM(J51:Y51)-L51-P51-Q51 -> 12225981 | D51: 12225981 | E51: 0.23926523 | H51: 12225981 | M51: 12131742 | N51: 0 | O51: =+P51+Q51 -> 0 | Q51: 0 | R51: 0 | S51: 0 | T51: 0 | U51: 0 | V51: 0 | W51: 94239 | X51: 0 | Y51: 0
A52: =A51+10 -> 390 | B52: Совместные и иностранные предприятия | C52: =SUM(J52:Y52)-L52-P52-Q52 -> 0 | M52: 0 | N52: 0 | O52: =+P52+Q52 -> 0 | Q52: 0 | R52: 0 | S52: 0 | T52: 0 | U52: 0 | V52: 0 | W52: 0 | X52: 0 | Y52: 0
A53: =A52+10 -> 400 | B53: Частные товарищества и корпорации | C53: =SUM(J53:Y53)-L53-P53-Q53 -> 64716721 | D53: 64716721 | E53: 0.17578657 | H53: 64716721 | M53: 37749979 | N53: 0 | O53: =+P53+Q53 -> 26271364 | Q53: 26271364 | R53: 152124 | S53: 0 | T53: 0 | U53: 0 | V53: 0 | W53: 543254 | X53: 0 | Y53: 0
A54: =A53+10 -> 410 | B54: Правительство | C54: =SUM(J54:Y54)-L54-P54-Q54 -> 0 | O54: =+P54+Q54 -> 0
A55: =A54+10 -> 420 | B55: Прочие | C55: =SUM(J55:Y55)-L55-P55-Q55 -> 0 | O55: =+P55+Q55 -> 0
A56: =A55+10 -> 430 | B56: Итого по материально-техническому снабжению и сбыту | C56: =SUM(J56:Y56)-L56-P56-Q56 -> 76942702 | D56: =SUM(D50:D55) -> 76942702 | E56: =IFERROR(((D50*E50)/D56)+((D51*E51)/D56)+((D52*E52)/D56)+((D53*E53)/D56)+((D54*E54)/D56)+((D55*E55)/D56),0) -> 0.18587315 | F56: =SUM(F50:F55) -> 0 | G56: =IFERROR(((F50*G50)/F56)+((F51*G51)/F56)+((F52*G52)/F56)+((F53*G53)/F56)+((F54*G54)/F56)+((F55*G55)/F56),0) -> 0 | H56: =SUM(H50:H55) -> 76942702 | I56: =SUM(I50:I55) -> 0 | J56: =SUM(J50:J55) -> 0 | K56: =SUM(K50:K55) -> 0 | L56: =SUM(L50:L55) -> 0 | M56: =SUM(M50:M55) -> 49881721 | N56: =SUM(N50:N55) -> 0 | O56: =SUM(O50:O55) -> 26271364 | ... Y56: =SUM(Y50:Y55) -> 0
B57: Жилищно-коммунальные услуги
A58: =A56+10 -> 440 | B58: Физические лица | C58: =SUM(J58:Y58)-L58-P58-Q58 -> 0 | O58: =+P58+Q58 -> 0
A59: =A58+10 -> 450 | B59: Государственные предприятия | C59: =SUM(J59:Y59)-L59-P59-Q59 -> 0 | O59: =+P59+Q59 -> 0
A60: =A59+10 -> 460 | B60: Совместные и иностранные предприятия | C60: =SUM(J60:Y60)-L60-P60-Q60 -> 0 | O60: =+P60+Q60 -> 0
A61: =A60+10 -> 470 | B61: Частные товарищества и корпорации | C61: =SUM(J61:Y61)-L61-P61-Q61 -> 8977191 | D61: 8977191 | E61: 0.18582246 | H61: 8977191 | J61: 35280 | K61: 0 | M61: 966938 | N61: 0 | O61: =+P61+Q61 -> 6063448 | Q61: 6063448 | R61: 0 | S61: 0 | T61: 0 | U61: 0 | V61: 20417 | W61: 1891108 | X61: 0 | Y61: 0
A62: =A61+10 -> 480 | B62: Правительство | C62: =SUM(J62:Y62)-L62-P62-Q62 -> 0 | H62: 0 | J62: 0 | K62: 0 | M62: 0 | N62: 0 | O62: =+P62+Q62 -> 0 | Q62: 0 | R62: 0 | S62: 0 | T62: 0 | U62: 0 | V62: 0 | W62: 0 | X62: 0 | Y62: 0
A63: 485 | B63: Негосударственные некоммерческие организации | C63: =SUM(J63:Y63)-L63-P63-Q63 -> 12433813 | D63: 12433813 | E63: 0.12478983 | H63: 12433813 | J63: 0 | K63: 0 | M63: 384155 | N63: 0 | O63: =+P63+Q63 -> 0 | Q63: 0 | R63: 0 | S63: 0 | T63: 0 | U63: 0 | V63: 860712 | W63: 9814300 | X63: 0 | Y63: 1374646
A64: =A62+10 -> 490 | B64: Прочие | C64: =SUM(J64:Y64)-L64-P64-Q64 -> 0 | O64: =+P64+Q64 -> 0
A65: =A64+10 -> 500 | B65: Итого по жилищно-коммунальным услугам | C65: =SUM(J65:Y65)-L65-P65-Q65 -> 21411004 | D65: =SUM(D58:D64) -> 21411004 | E65: =IFERROR(((D58*E58)/D65)+((D59*E59)/D65)+((D60*E60)/D65)+((D61*E61)/D65)+((D62*E62)/D65)+((D63*E63)/D65)+((D64*E64)/D65),0) -> 0.15037955 | F65: =SUM(F58:F64) -> 0 | G65: =IFERROR(((F58*G58)/F65)+((F59*G59)/F65)+((F60*G60)/F65)+((F61*G61)/F65)+((F62*G62)/F65)+((F63*G63)/F65)+((F64*G64)/F65),0) -> 0 | H65: =SUM(H58:H64) -> 21411004 | I65: =SUM(I58:I64) -> 0 | J65: =SUM(J58:J64) -> 35280 | K65: =SUM(K58:K64) -> 0 | L65: =SUM(L58:L64) -> 0 | M65: =SUM(M58:M64) -> 1351093 | N65: =SUM(N58:N64) -> 0 | O65: =SUM(O58:O64) -> 6063448 | ... Y65: =SUM(Y58:Y64) -> 1374646
B66: Другие отрасли
A67: =A65+10 -> 510 | B67: Физические лица | C67: =SUM(J67:Y67)-L67-P67-Q67 -> 1022400185 | D67: 1022400185 | E67: 0.19719004 | F67: 0 | G67: 0 | H67: 1018793154 | I67: 3607031 | J67: 193441807 | K67: 0 | M67: 144465513 | N67: 0 | O67: =+P67+Q67 -> 371161921 | Q67: 371161921 | R67: 10617 | S67: 0 | T67: 0 | U67: 690 | V67: 222143940 | W67: 85150479 | X67: 6020690 | Y67: 4528
A68: =A67+10 -> 520 | B68: Государственные предприятия | C68: =SUM(J68:Y68)-L68-P68-Q68 -> 322267639 | D68: 7960039 | E68: 0.21969337 | F68: 314307600 | G68: 0.0606 | H68: 322267639 | I68: 0 | J68: 0 | K68: 0 | M68: 1165049 | N68: 0 | O68: =+P68+Q68 -> 6784990 | Q68: 6784990 | R68: 0 | S68: 0 | T68: 0 | U68: 0 | V68: 10000 | W68: 314307600 | X68: 0 | Y68: 0
A69: =A68+10 -> 530 | B69: Совместные и иностранные предприятия | C69: =SUM(J69:Y69)-L69-P69-Q69 -> 134881623 | D69: 2703094 | E69: 0.18 | F69: 132178529 | G69: 0.088143705 | H69: 134881623 | I69: 0 | J69: 0 | K69: 0 | M69: 326027 | N69: 0 | O69: =+P69+Q69 -> 57874522 | Q69: 57874522 | R69: 75398481 | S69: 0 | T69: 0 | U69: 0 | V69: 1274943 | W69: 0 | X69: 0 | Y69: 7650
A70: =A69+10 -> 540 | B70: Частные товарищества и корпорации | C70: =SUM(J70:Y70)-L70-P70-Q70 -> 2030621814 | D70: 1208591601 | E70: 0.18412005 | F70: 822030213 | G70: 0.084236649 | H70: 2025282802 | I70: 5339012 | J70: 34833878 | K70: 0 | M70: 418325953 | N70: 399690 | O70: =+P70+Q70 -> 1151627687 | Q70: 1151627687 | R70: 292369018 | S70: 0 | T70: 0 | U70: 0 | V70: 92430565 | W70: 40336215 | X70: 0 | Y70: 298808
A71: =A70+10 -> 550 | B71: Центральный банк | C71: =SUM(J71:Y71)-L71-P71-Q71 -> 0 | H71: 0 | I71: 0 | J71: 0 | K71: 0 | M71: 0 | N71: 0 | O71: =+P71+Q71 -> 0 | Q71: 0 | R71: 0 | S71: 0 | T71: 0 | U71: 0 | V71: 0 | W71: 0 | X71: 0 | Y71: 0
A72: =A71+10 -> 560 | B72: Другие банки | C72: =SUM(J72:Y72)-L72-P72-Q72 -> 0 | H72: 0 | I72: 0 | J72: 0 | K72: 0 | M72: 0 | N72: 0 | O72: =+P72+Q72 -> 0 | Q72: 0 | R72: 0 | S72: 0 | T72: 0 | U72: 0 | V72: 0 | W72: 0 | X72: 0 | Y72: 0
A73: =A72+10 -> 570 | B73: Правительство | C73: =SUM(J73:Y73)-L73-P73-Q73 -> 0 | H73: 0 | I73: 0 | J73: 0 | K73: 0 | M73: 0 | N73: 0 | O73: =+P73+Q73 -> 0 | Q73: 0 | R73: 0 | S73: 0 | T73: 0 | U73: 0 | V73: 0 | W73: 0 | X73: 0 | Y73: 0
A74: =A73+10 -> 580 | B74: Небанковские финансовые институты | C74: =SUM(J74:Y74)-L74-P74-Q74 -> 1424539 | D74: 1424539 | E74: 0.2 | H74: 1424539 | I74: 0 | J74: 0 | K74: 0 | M74: 1373134 | N74: 0 | O74: =+P74+Q74 -> 0 | Q74: 0 | R74: 40240 | S74: 0 | T74: 0 | U74: 0 | V74: 0 | W74: 11165 | X74: 0 | Y74: 0
A75: =A74+10 -> 590 | B75: Негосударственные некоммерческие организации | C75: =SUM(J75:Y75)-L75-P75-Q75 -> 3215278 | D75: 3215278 | E75: 0.17904162 | H75: 3215278 | I75: 0 | J75: 0 | K75: 0 | M75: 838551 | N75: 0 | O75: =+P75+Q75 -> 0 | Q75: 0 | R75: 0 | S75: 0 | T75: 0 | U75: 0 | V75: 161405 | W75: 968147 | X75: 0 | Y75: 1247175
A76: =A75+10 -> 600 | B76: Бюджетные организации | C76: =SUM(J76:Y76)-L76-P76-Q76 -> 0 | H76: 0 | I76: 0 | J76: 0 | K76: 0 | M76: 0 | N76: 0 | O76: =+P76+Q76 -> 0 | Q76: 0 | R76: 0 | S76: 0 | T76: 0 | U76: 0 | V76: 0 | W76: 0 | X76: 0 | Y76: 0
A77: =A76+10 -> 610 | B77: Прочие | C77: =SUM(J77:Y77)-L77-P77-Q77 -> 35257924 | D77: 35257924 | E77: 0.2058441 | H77: 35257924 | I77: 0 | J77: 380351 | K77: 0 | M77: 12436845 | N77: 0 | O77: =+P77+Q77 -> 19010005 | Q77: 19010005 | R77: 76006 | S77: 0 | T77: 0 | U77: 0 | V77: 3076267 | W77: 249509 | X77: 0 | Y77: 28941
A78: =A77+10 -> 620 | B78: Итого по другим отраслям | C78: =SUM(J78:Y78)-L78-P78-Q78 -> 3550069002 | D78: =SUM(D67:D77) -> 2281552660 | E78: =IFERROR(((D67*E67)/D78)+((D68*E68)/D78)+((D69*E69)/D78)+((D70*E70)/D78)+((D71*E71)/D78)+((D72*E72)/D78)+((D73*E73)/D78)+((D74*E74)/D78)+((D75*E75)/D78)+((D76*E76)/D78)+((D77*E77)/D78),0) -> 0.19043462 | F78: =SUM(F67:F77) -> 1268516342 | G78: =IFERROR(((F67*G67)/F78)+((F68*G68)/F78)+((F69*G69)/F78)+((F70*G70)/F78)+((F71*G71)/F78)+((F72*G72)/F78)+((F73*G73)/F78)+((F74*G74)/F78)+((F75*G75)/F78)+((F76*G76)/F78)+((F77*G77)/F78),0) -> 0.078787173 | H78: =SUM(H67:H77) -> 3541122959 | I78: =SUM(I67:I77) -> 8946043 | J78: =SUM(J67:J77) -> 228656036 | K78: =SUM(K67:K77) -> 0 | L78: =SUM(L67:L77) -> 0 | M78: =SUM(M67:M77) -> 578931072 | N78: =SUM(N67:N77) -> 399690 | O78: =SUM(O67:O77) -> 1606459125 | ... Y78: =SUM(Y67:Y77) -> 1587102
B79: Кредитные и лизинговые операции
A80: =A78+10 -> 630 | B80: Физические лица | C80: =SUM(J80:Y80)-L80-P80-Q80 -> 1022400185 | D80: =D9+D17+D26+D34+D42+D50+D58+D67 -> 1022400185 | E80: =IFERROR(((D9*E9)/D80)+((D17*E17)/D80)+((D26*E26)/D80)+((D34*E34)/D80)+((D42*E42)/D80)+((D50*E50)/D80)+((D58*E58)/D80)+((D67*E67)/D80),0) -> 0.19719004 | F80: =F9+F17+F26+F34+F42+F50+F58+F67 -> 0 | G80: =IFERROR(((F9*G9)/F80)+((F17*G17)/F80)+((F26*G26)/F80)+((F34*G34)/F80)+((F42*G42)/F80)+((F50*G50)/F80)+((F58*G58)/F80)+((F67*G67)/F80),0) -> 0 | H80: =H9+H17+H26+H34+H42+H50+H58+H67 -> 1018793154 | I80: =I9+I17+I26+I34+I42+I50+I58+I67 -> 3607031 | J80: =J9+J17+J26+J34+J42+J50+J58+J67 -> 193441807 | K80: =K9+K17+K26+K34+K42+K50+K58+K67 -> 0 | L80: =L9+L17+L26+L34+L42+L50+L58+L67 -> 0 | M80: =M9+M17+M26+M34+M42+M50+M58+M67 -> 144465513 | N80: =N9+N17+N26+N34+N42+N50+N58+N67 -> 0 | O80: =O9+O17+O26+O34+O42+O50+O58+O67 -> 371161921 | ... Y80: =Y9+Y17+Y26+Y34+Y42+Y50+Y58+Y67 -> 4528
A81: =A80+10 -> 640 | B81: Государственные предприятия | C81: =SUM(J81:Y81)-L81-P81-Q81 -> 759073325 | D81: =D10+D18+D27+D35+D43+D51+D59+D68 -> 444765725 | E81: =IFERROR(((D10*E10)/D81)+((D18*E18)/D81)+((D27*E27)/D81)+((D35*E35)/D81)+((D43*E43)/D81)+((D51*E51)/D81)+((D59*E59)/D81)+((D68*E68)/D81),0) -> 0.13663507 | F81: =F10+F18+F27+F35+F43+F51+F59+F68 -> 314307600 | G81: =IFERROR(((F10*G10)/F81)+((F18*G18)/F81)+((F27*G27)/F81)+((F35*G35)/F81)+((F43*G43)/F81)+((F51*G51)/F81)+((F59*G59)/F81)+((F68*G68)/F81),0) -> 0.0606 | H81: =H10+H18+H27+H35+H43+H51+H59+H68 -> 759073325 | I81: =I10+I18+I27+I35+I43+I51+I59+I68 -> 0 | J81: =J10+J18+J27+J35+J43+J51+J59+J68 -> 216263967 | K81: =K10+K18+K27+K35+K43+K51+K59+K68 -> 0 | L81: =L10+L18+L27+L35+L43+L51+L59+L68 -> 0 | M81: =M10+M18+M27+M35+M43+M51+M59+M68 -> 27673601 | N81: =N10+N18+N27+N35+N43+N51+N59+N68 -> 0 | O81: =O10+O18+O27+O35+O43+O51+O59+O68 -> 176751716 | ... Y81: =Y10+Y18+Y27+Y35+Y43+Y51+Y59+Y68 -> 0
A82: =A81+10 -> 650 | B82: Совместные и иностранные предприятия | C82: =SUM(J82:Y82)-L82-P82-Q82 -> 455567628 | D82: =D11+D19+D28+D36+D44+D52+D60+D69 -> 283375410 | E82: =IFERROR(((D11*E11)/D82)+((D19*E19)/D82)+((D28*E28)/D82)+((D36*E36)/D82)+((D44*E44)/D82)+((D52*E52)/D82)+((D60*E60)/D82)+((D69*E69)/D82),0) -> 0.17555581 | F82: =F11+F19+F28+F36+F44+F52+F60+F69 -> 172192218 | G82: =IFERROR(((F11*G11)/F82)+((F19*G19)/F82)+((F28*G28)/F82)+((F36*G36)/F82)+((F44*G44)/F82)+((F52*G52)/F82)+((F60*G60)/F82)+((F69*G69)/F82),0) -> 0.08822005 | H82: =H11+H19+H28+H36+H44+H52+H60+H69 -> 455567628 | I82: =I11+I19+I28+I36+I44+I52+I60+I69 -> 0 | J82: =J11+J19+J28+J36+J44+J52+J60+J69 -> 0 | K82: =K11+K19+K28+K36+K44+K52+K60+K69 -> 0 | L82: =L11+L19+L28+L36+L44+L52+L60+L69 -> 0 | M82: =M11+M19+M28+M36+M44+M52+M60+M69 -> 985624 | N82: =N11+N19+N28+N36+N44+N52+N60+N69 -> 0 | O82: =O11+O19+O28+O36+O44+O52+O60+O69 -> 366182293 | ... Y82: =Y11+Y19+Y28+Y36+Y44+Y52+Y60+Y69 -> 7650
A83: =A82+10 -> 660 | B83: Частные товарищества и корпорации | C83: =SUM(J83:Y83)-L83-P83-Q83 -> 3382356533 | D83: =D12+D20+D29+D37+D45+D53+D61+D70 -> 1949370015 | E83: =IFERROR(((D12*E12)/D83)+((D20*E20)/D83)+((D29*E29)/D83)+((D37*E37)/D83)+((D45*E45)/D83)+((D53*E53)/D83)+((D61*E61)/D83)+((D70*E70)/D83),0) -> 0.18934964 | F83: =F12+F20+F29+F37+F45+F53+F61+F70 -> 1432986518 | G83: =IFERROR(((F12*G12)/F83)+((F20*G20)/F83)+((F29*G29)/F83)+((F37*G37)/F83)+((F45*G45)/F83)+((F53*G53)/F83)+((F61*G61)/F83)+((F70*G70)/F83),0) -> 0.081407194 | H83: =H12+H20+H29+H37+H45+H53+H61+H70 -> 3376814048 | I83: =I12+I20+I29+I37+I45+I53+I61+I70 -> 5542485 | J83: =J12+J20+J29+J37+J45+J53+J61+J70 -> 35580175 | K83: =K12+K20+K29+K37+K45+K53+K61+K70 -> 0 | L83: =L12+L20+L29+L37+L45+L53+L61+L70 -> 0 | M83: =M12+M20+M29+M37+M45+M53+M61+M70 -> 634615139 | N83: =N12+N20+N29+N37+N45+N53+N61+N70 -> 399690 | O83: =O12+O20+O29+O37+O45+O53+O61+O70 -> 2012822362 | ... Y83: =Y12+Y20+Y29+Y37+Y45+Y53+Y61+Y70 -> 335764
A84: =A83+10 -> 670 | B84: Фермерское хозяйство | C84: =SUM(J84:Y84)-L84-P84-Q84 -> 0 | D84: =D21 -> 0 | E84: =IFERROR(E21,0) -> 0 | F84: =F21 -> 0 | G84: =IFERROR(G21,0) -> 0 | H84: =H21 -> 0 | I84: =I21 -> 0 | J84: =J21 -> 0 | K84: =K21 -> 0 | L84: =L21 -> 0 | M84: =M21 -> 0 | N84: =N21 -> 0 | O84: =O21 -> 0 | ... Y84: =Y21 -> 0
A85: =A84+10 -> 680 | B85: Другие банки | C85: =SUM(J85:Y85)-L85-P85-Q85 -> 0 | D85: =D72 -> 0 | E85: =E72 -> 0 | F85: =F72 -> 0 | G85: =G72 -> 0 | H85: =H72 -> 0 | I85: =I72 -> 0 | J85: =J72 -> 0 | K85: =K72 -> 0 | ... Y85: =Y72 -> 0
A86: =A85+10 -> 690 | B86: Центральный банк | C86: =SUM(J86:Y86)-L86-P86-Q86 -> 0 | D86: =D71 -> 0 | E86: =E71 -> 0 | F86: =F71 -> 0 | G86: =G71 -> 0 | H86: =H71 -> 0 | I86: =I71 -> 0 | J86: =J71 -> 0 | K86: =K71 -> 0 | ... Y86: =Y71 -> 0
A87: =A86+10 -> 700 | B87: Правительство | C87: =SUM(J87:Y87)-L87-P87-Q87 -> 0 | D87: =D13+D22+D30+D38+D46+D54+D62+D73 -> 0 | E87: =IFERROR(((D13*E13)/D87)+((D22*E22)/D87)+((D30*E30)/D87)+((D38*E38)/D87)+((D46*E46)/D87)+((D54*E54)/D87)+((D62*E62)/D87)+((D73*E73)/D87),0) -> 0 | F87: =F13+F22+F30+F38+F46+F54+F62+F73 -> 0 | G87: =IFERROR(((F13*G13)/F87)+((F22*G22)/F87)+((F30*G30)/F87)+((F38*G38)/F87)+((F46*G46)/F87)+((F54*G54)/F87)+((F62*G62)/F87)+((F73*G73)/F87),0) -> 0 | H87: =H13+H22+H30+H38+H46+H54+H62+H73 -> 0 | I87: =I13+I22+I30+I38+I46+I54+I62+I73 -> 0 | J87: =J13+J22+J30+J38+J46+J54+J62+J73 -> 0 | K87: =K13+K22+K30+K38+K46+K54+K62+K73 -> 0 | L87: =L13+L22+L30+L38+L46+L54+L62+L73 -> 0 | M87: =M13+M22+M30+M38+M46+M54+M62+M73 -> 0 | N87: =N13+N22+N30+N38+N46+N54+N62+N73 -> 0 | O87: =O13+O22+O30+O38+O46+O54+O62+O73 -> 0 | ... Y87: =Y13+Y22+Y30+Y38+Y46+Y54+Y62+Y73 -> 0
A88: =A87+10 -> 710 | B88: Небанковские финансовые институты | C88: =SUM(J88:Y88)-L88-P88-Q88 -> 1424539 | D88: =D74 -> 1424539 | E88: =E74 -> 0.2 | F88: =F74 -> 0 | G88: =G74 -> 0 | H88: =H74 -> 1424539 | I88: =I74 -> 0 | J88: =J74 -> 0 | K88: =K74 -> 0 | ... Y88: =Y74 -> 0
A89: =A88+10 -> 720 | B89: Негосударственные некоммерческие организации | C89: =SUM(J89:Y89)-L89-P89-Q89 -> 15649091 | D89: =+D63+D75 -> 15649091 | E89: =IFERROR(((D75*E75)/D78)+((D63*E63)/D65),0) -> 0.072720353 | F89: =+F63+F75 -> 0 | G89: =IFERROR(((F75*G75)/F78)+((F63*G63)/F65),0) -> 0 | H89: =+H63+H75 -> 15649091 | I89: =+I63+I75 -> 0 | J89: =+J63+J75 -> 0 | K89: =+K63+K75 -> 0 | L89: =+L63+L75 -> 0 | M89: =+M63+M75 -> 1222706 | N89: =+N63+N75 -> 0 | O89: =+O63+O75 -> 0 | ... Y89: =+Y63+Y75 -> 2621821
A90: =A89+10 -> 730 | B90: Бюджетные организации | C90: =SUM(J90:Y90)-L90-P90-Q90 -> 0 | D90: =D76 -> 0 | E90: =E76 -> 0 | F90: =F76 -> 0 | G90: =G76 -> 0 | H90: =H76 -> 0 | I90: =I76 -> 0 | J90: =J76 -> 0 | K90: =K76 -> 0 | ... Y90: =Y76 -> 0
A91: =A90+10 -> 740 | B91: Прочие | C91: =SUM(J91:Y91)-L91-P91-Q91 -> 69465520 | D91: =D14+D23+D31+D39+D47+D55+D64+D77 -> 69465520 | E91: =IFERROR(((D14*E14)/D91)+((D23*E23)/D91)+((D31*E31)/D91)+((D39*E39)/D91)+((D47*E47)/D91)+((D55*E55)/D91)+((D64*E64)/D91)+((D77*E77)/D91),0) -> 0.20918521 | F91: =F14+F23+F31+F39+F47+F55+F64+F77 -> 0 | G91: =IFERROR(((F14*G14)/F91)+((F23*G23)/F91)+((F31*G31)/F91)+((F39*G39)/F91)+((F47*G47)/F91)+((F55*G55)/F91)+((F64*G64)/F91)+((F77*G77)/F91),0) -> 0 | H91: =H14+H23+H31+H39+H47+H55+H64+H77 -> 69465520 | I91: =I14+I23+I31+I39+I47+I55+I64+I77 -> 0 | J91: =J14+J23+J31+J39+J47+J55+J64+J77 -> 480220 | K91: =K14+K23+K31+K39+K47+K55+K64+K77 -> 0 | L91: =L14+L23+L31+L39+L47+L55+L64+L77 -> 0 | M91: =M14+M23+M31+M39+M47+M55+M64+M77 -> 35515380 | N91: =N14+N23+N31+N39+N47+N55+N64+N77 -> 0 | O91: =O14+O23+O31+O39+O47+O55+O64+O77 -> 29464042 | ... Y91: =Y14+Y23+Y31+Y39+Y47+Y55+Y64+Y77 -> 34598
A92: =A91+10 -> 750 | B92: Итого кредита и лизинга | C92: =SUM(J92:Y92)-L92-P92-Q92 -> 5705936821 | D92: =SUM(D80:D91) -> 3786450485 | E92: =IFERROR(((D80*E80)/D92)+((D81*E81)/D92)+((D82*E82)/D92)+((D83*E83)/D92)+((D84*E84)/D92)+((D85*E85)/D92)+((D86*E86)/D92)+((D87*E87)/D92)+((D88*E88)/D92)+((D89*E89)/D92)+((D90*E90)/D92)+((D91*E91)/D92),0) -> 0.18412826 | F92: =SUM(F80:F91) -> 1919486336 | G92: =IFERROR(((F80*G80)/F92)+((F81*G81)/F92)+((F82*G82)/F92)+((F83*G83)/F92)+((F84*G84)/F92)+((F85*G85)/F92)+((F86*G86)/F92)+((F87*G87)/F92)+((F88*G88)/F92)+((F89*G89)/F92)+((F90*G90)/F92)+((F91*G91)/F92),0) -> 0.078611269 | H92: =SUM(H80:H91) -> 5696787305 | I92: =SUM(I80:I91) -> 9149516 | J92: =SUM(J80:J91) -> 445766169 | K92: =SUM(K80:K91) -> 0 | L92: =SUM(L80:L91) -> 0 | M92: =SUM(M80:M91) -> 845851097 | N92: =SUM(N80:N91) -> 399690 | O92: =SUM(O80:O91) -> 2956382334 | ... Y92: =SUM(Y80:Y91) -> 3004361
B95: Подпись Председателя правления:
B97: Подпись Главного Бухгалтера:
C99: =+[8]Balance!$C$24 -> 5705936821
C100: =+C92-C99 -> 0

Sheet Aging Analysis
A1: АНАЛИЗ ПРОСРОЧЕННЫХ КРЕДИТОВ И ФИНАНСОВОГО ЛИЗИНГА К ПОЛУЧЕНИЮ | X1: Таблица-9
B3: =+'Asset quality'!B3 -> АК "Алокабанк" | T3: =+'Asset quality'!P3 -> 44196 | X3: тыс. сум
A4: № | B4: Характеристики | C4: Всего задолжность по кредитам | D4: % | E4: Реструктуризированные кредиты | F4: % | G4: В ходе судебного разбирательства | H4: % | I4: Просроченная задолжность | K4: % | L4: в том числе, анализ временной задолженности
L5: 1-30 дней | N5: 31-60 дней | P5: 61-90 дней | R5: 91-180 дней | T5: 181-365 дней | V5: 366-730 дней | X5: Свыше 2 лет
I6: основной долг | J6: процент | L6: основной долг | M6: процент | N6: основной долг | O6: процент | P6: основной долг | Q6: процент | R6: основной долг | S6: процент | T6: основной долг | U6: процент | V6: основной долг | W6: процент | X6: основной долг | Y6: процент
B7: (А) | C7: (Б) | D7: (В) | E7: (Г) | F7: (Д) | G7: (Е) | H7: (Ж) | I7: (З) | J7: (З1) | K7: (И) | L7: (К) | M7: (К1) | N7: (Л) | O7: (Л1) | P7: (М) | Q7: (М1) | R7: (Н) | S7: (Н1) | T7: (О) | U7: (О1) | V7: (П) | W7: (П1) | X7: (Р) | Y7: (Р1)
B8: По типу клиента
A9: 1 | B9: Центральный банк | C9: =+'Loans Receivable'!C86 -> 0 | D9: =IF(C$22=0,"",C9/C$22) -> 0 | E9: 0 | F9: =IF(E$22=0,"",E9/E$22) -> 0 | H9: =IF($G$22=0,"",G9/$G$22) | I9: =+L9+N9+P9+R9+T9+V9+X9 -> 0 | J9: =+M9+O9+T9+S9+U9+W9+Y9 -> 0 | K9: =IF($Z$22=0,"",Z9/$Z$22) -> 0 | L9: 0 | M9: 0 | N9: 0 | O9: 0 | P9: 0 | Q9: 0 | R9: 0 | S9: 0 | T9: 0 | U9: 0 | V9: 0 | W9: 0 | X9: 0 | Y9: 0 | Z9: =+I9+J9 -> 0
A10: 2 | B10: Другие банки | C10: =+'Loans Receivable'!C85 -> 0 | D10: =IF(C$22=0,"",C10/C$22) -> 0 | E10: 0 | F10: =IF(E$22=0,"",E10/E$22) -> 0 | H10: =IF($G$22=0,"",G10/$G$22) | I10: =+L10+N10+P10+R10+T10+V10+X10 -> 0 | J10: =+M10+O10+Q10+S10+U10+W10+Y10 -> 0 | K10: =IF($Z$22=0,"",Z10/$Z$22) -> 0 | L10: 0 | M10: 0 | N10: 0 | O10: 0 | P10: 0 | Q10: 0 | R10: 0 | S10: 0 | T10: 0 | U10: 0 | V10: 0 | W10: 0 | X10: 0 | Y10: 0 | Z10: =+I10+J10 -> 0
A11: 3 | B11: Правительство | C11: =+'Loans Receivable'!C87 -> 0 | D11: =IF(C$22=0,"",C11/C$22) -> 0 | E11: 0 | F11: =IF(E$22=0,"",E11/E$22) -> 0 | H11: =IF($G$22=0,"",G11/$G$22) | I11: =+L11+N11+P11+R11+T11+V11+X11 -> 0 | J11: =+M11+O11+Q11+S11+U11+W11+Y11 -> 0 | K11: =IF($Z$22=0,"",Z11/$Z$22) -> 0 | L11: 0 | M11: 0 | N11: 0 | O11: 0 | P11: 0 | Q11: 0 | R11: 0 | S11: 0 | T11: 0 | U11: 0 | V11: 0 | W11: 0 | X11: 0 | Y11: 0 | Z11: =+I11+J11 -> 0
A12: 4 | B12: Физические лица | C12: =+'Loans Receivable'!C80 -> 1022400185 | D12: =IF(C$22=0,"",C12/C$22) -> 0.17918183 | E12: 0 | F12: =IF(E$22=0,"",E12/E$22) -> 0 | H12: =IF($G$22=0,"",G12/$G$22) | I12: =+L12+N12+P12+R12+T12+V12+X12 -> 8980464 | J12: =+M12+O12+Q12+S12+U12+W12+Y12 -> 5030869 | K12: =IF($Z$22=0,"",Z12/$Z$22) -> 0.18356932 | L12: 3148535 | M12: 269608 | N12: 1846505 | O12: 725614 | P12: 1259323 | Q12: 527453 | R12: 1364281 | S12: 2357840 | T12: 993057 | U12: 552850 | V12: 362648 | W12: 499973 | X12: 6115 | Y12: 97531 | Z12: =+I12+J12 -> 14011333
A13: 5 | B13: Государственные предприятия | C13: =+'Loans Receivable'!C81 -> 759073325 | D13: =IF(C$22=0,"",C13/C$22) -> 0.1330322 | E13: 13497500 | F13: =IF(E$22=0,"",E13/E$22) -> 0.1404912 | G13: 0 | H13: =IF($G$22=0,"",G13/$G$22) | I13: =+L13+N13+P13+R13+T13+V13+X13 -> 0 | J13: =+M13+O13+Q13+S13+U13+W13+Y13 -> 0 | K13: =IF($Z$22=0,"",Z13/$Z$22) -> 0 | L13: 0 | M13: 0 | N13: 0 | O13: 0 | P13: 0 | Q13: 0 | R13: 0 | S13: 0 | T13: 0 | U13: 0 | V13: 0 | W13: 0 | X13: 0 | Y13: 0 | Z13: =+I13+J13 -> 0
A14: 6 | B14: Совместные и иностранные предприятия | C14: =+'Loans Receivable'!C82 -> 455567628 | D14: =IF(C$22=0,"",C14/C$22) -> 0.079840987 | E14: 0 | F14: =IF(E$22=0,"",E14/E$22) -> 0 | G14: 0 | H14: =IF($G$22=0,"",G14/$G$22) | I14: =+L14+N14+P14+R14+T14+V14+X14 -> 76626 | J14: =+M14+O14+Q14+S14+U14+W14+Y14 -> 2002978 | K14: =IF($Z$22=0,"",Z14/$Z$22) -> 0.027245908 | L14: 15335 | M14: 0 | N14: 15335 | O14: 0 | P14: 15335 | Q14: 7430 | R14: 30621 | S14: 0 | T14: 0 | U14: 0 | V14: 0 | W14: 1995548 | X14: 0 | Y14: 0 | Z14: =+I14+J14 -> 2079604
A15: 7 | B15: Частные товарищества и корпорации | C15: =+'Loans Receivable'!C83 -> 3382356533 | D15: =IF(C$22=0,"",C15/C$22) -> 0.59277848 | E15: 82576130 | F15: =IF(E$22=0,"",E15/E$22) -> 0.8595088 | G15: 0 | H15: =IF($G$22=0,"",G15/$G$22) | I15: =+L15+N15+P15+R15+T15+V15+X15 -> 36289881 | J15: =+M15+O15+Q15+S15+U15+W15+Y15 -> 20610204 | K15: =IF($Z$22=0,"",Z15/$Z$22) -> 0.74547581 | L15: 9532164 | M15: 275289 | N15: 5390049 | O15: 341431 | P15: 2798748 | Q15: 385506 | R15: 6692546 | S15: 13468555 | T15: 5267022 | U15: 5833421 | V15: 6609352 | W15: 289163 | X15: 0 | Y15: 16839 | Z15: =+I15+J15 -> 56900085
A16: 8 | B16: Фермерское хозяйство | C16: =+'Loans Receivable'!C84 -> 0 | D16: =IF(C$22=0,"",C16/C$22) -> 0 | E16: 0 | F16: =IF(E$22=0,"",E16/E$22) -> 0 | H16: =IF($G$22=0,"",G16/$G$22) | I16: =+L16+N16+P16+R16+T16+V16+X16 -> 0 | J16: =+M16+O16+Q16+S16+U16+W16+Y16 -> 0 | K16: =IF($Z$22=0,"",Z16/$Z$22) -> 0 | Z16: =+I16+J16 -> 0
A17: 9 | B17: Небанковские финансовые институты | C17: =+'Loans Receivable'!C88 -> 1424539 | D17: =IF(C$22=0,"",C17/C$22) -> 0.00024965909 | E17: 0 | F17: =IF(E$22=0,"",E17/E$22) -> 0 | H17: =IF($G$22=0,"",G17/$G$22) | I17: =+L17+N17+P17+R17+T17+V17+X17 -> 0 | J17: =+M17+O17+Q17+S17+U17+W17+Y17 -> 0 | K17: =IF($Z$22=0,"",Z17/$Z$22) -> 0 | L17: 0 | M17: 0 | N17: 0 | O17: 0 | P17: 0 | Q17: 0 | R17: 0 | S17: 0 | T17: 0 | U17: 0 | V17: 0 | W17: 0 | X17: 0 | Y17: 0 | Z17: =+I17+J17 -> 0
A18: 10 | B18: Негосударственные некоммерческие организации | C18: =+'Loans Receivable'!C89 -> 15649091 | D18: =IF(C$22=0,"",C18/C$22) -> 0.002742598 | E18: 0 | F18: =IF(E$22=0,"",E18/E$22) -> 0 | H18: =IF($G$22=0,"",G18/$G$22) | I18: =+L18+N18+P18+R18+T18+V18+X18 -> 812510 | J18: =+M18+O18+Q18+S18+U18+W18+Y18 -> 1108916 | K18: =IF($Z$22=0,"",Z18/$Z$22) -> 0.025173541 | L18: 15911 | M18: 328 | N18: 14607 | O18: 6423 | P18: 68602 | Q18: 723 | R18: 544318 | S18: 23988 | T18: 61164 | U18: 304236 | V18: 107908 | W18: 755165 | X18: 0 | Y18: 18053 | Z18: =+I18+J18 -> 1921426
A19: 11 | B19: Бюджетные организации | C19: =+'Loans Receivable'!C90 -> 0 | D19: =IF(C$22=0,"",C19/C$22) -> 0 | E19: 0 | F19: =IF(E$22=0,"",E19/E$22) -> 0 | H19: =IF($G$22=0,"",G19/$G$22) | I19: =+L19+N19+P19+R19+T19+V19+X19 -> 0 | J19: =+M19+O19+Q19+S19+U19+W19+Y19 -> 0 | K19: =IF($Z$22=0,"",Z19/$Z$22) -> 0 | Z19: =+I19+J19 -> 0
A20: 12 | B20: Прочие | C20: =+'Loans Receivable'!C91 -> 69465520 | D20: =IF(C$22=0,"",C20/C$22) -> 0.012174253 | E20: 0 | F20: =IF(E$22=0,"",E20/E$22) -> 0 | H20: =IF($G$22=0,"",G20/$G$22) | I20: =+L20+N20+P20+R20+T20+V20+X20 -> 1330936 | J20: =+M20+O20+Q20+S20+U20+W20+Y20 -> 83821 | K20: =IF($Z$22=0,"",Z20/$Z$22) -> 0.018535423 | L20: 257534 | M20: 3142 | N20: 230587 | O20: 5533 | P20: 190016 | Q20: 9441 | R20: 122193 | S20: 42018 | T20: 161640 | U20: 14802 | V20: 368966 | W20: 8885 | X20: 0 | Y20: 0 | Z20: =+I20+J20 -> 1414757
Z21: =+I21+J21 -> 0
A22: 13 | B22: Итого кредита и лизинга | C22: =SUM(C9:C20) -> 5705936821 | D22: =IF(C$22=0,"",C22/C$22) -> 1 | E22: =SUM(E9:E20) -> 96073630 | F22: =IF(E$22=0,"",E22/E$22) -> 1 | G22: =SUM(G9:G20) -> 0 | H22: =IF($G$22=0,"",G22/$G$22) | I22: =SUM(I9:I20) -> 47490417 | J22: =SUM(J9:J20) -> 28836788 | K22: =IF($Z$22=0,"",Z22/$Z$22) -> 1 | L22: =SUM(L9:L20) -> 12969479 | M22: =SUM(M9:M20) -> 548367 | N22: =SUM(N9:N20) -> 7497083 | O22: =SUM(O9:O20) -> 1079001 | P22: =SUM(P9:P20) -> 4332024 | Q22: =SUM(Q9:Q20) -> 930553 | R22: =SUM(R9:R20) -> 8753959 | S22: =SUM(S9:S20) -> 15892401 | ... Y22: =SUM(Y9:Y20) -> 132423 | Z22: =+I22+J22 -> 76327205
Z23: =+I23+J23 -> 0
B24: По сектору экономики | F24: =IF(E$22=0,"",E24/E$22) -> 0 | Z24: =+I24+J24 -> 0
A25: 14 | B25: Промышленность | C25: =+'Loans Receivable'!C15 -> 965348427 | D25: =IF(C$34=0,"",C25/C$34) -> 0.16918316 | E25: 16357500 | F25: =IF($E$34=0,"",E25/$E$34) -> 0.17026004 | G25: 0 | H25: =IF($G$34=0,"",G25/$G$34) | I25: =+L25+N25+P25+R25+T25+V25+X25 -> 2909434 | J25: =+M25+O25+Q25+S25+U25+W25+Y25 -> 2507999 | K25: =IF($Z$34=0,"",Z25/$Z$34) -> 0.070976436 | L25: 1122196 | M25: 9292 | N25: 677815 | O25: 3243 | P25: 530896 | Q25: 336752 | R25: 154333 | S25: 154279 | T25: 399883 | U25: 0 | V25: 24311 | W25: 2004433 | X25: 0 | Y25: 0 | Z25: =+I25+J25 -> 5417433
A26: 15 | B26: Сельское хозяйство | C26: =+'Loans Receivable'!C24 -> 113582271 | D26: =IF(C$34=0,"",C26/C$34) -> 0.019905981 | E26: 0 | F26: =IF($E$34=0,"",E26/$E$34) -> 0 | G26: 0 | H26: =IF($G$34=0,"",G26/$G$34) | I26: =+L26+N26+P26+R26+T26+V26+X26 -> 4135476 | J26: =+M26+O26+Q26+S26+U26+W26+Y26 -> 792109 | K26: =IF($Z$34=0,"",Z26/$Z$34) -> 0.064558698 | L26: 510497 | M26: 16673 | N26: 228559 | O26: 9671 | P26: 8059 | Q26: 4526 | R26: 28898 | S26: 0 | T26: 2987447 | U26: 758695 | V26: 372016 | W26: 2544 | X26: 0 | Y26: 0 | Z26: =+I26+J26 -> 4927585
A27: 16 | B27: Транспорт и коммуникации | C27: =+'Loans Receivable'!C32 -> 543322518 | D27: =IF(C$34=0,"",C27/C$34) -> 0.095220563 | E27: 0 | F27: =IF($E$34=0,"",E27/$E$34) -> 0 | G27: 0 | H27: =IF($G$34=0,"",G27/$G$34) | I27: =+L27+N27+P27+R27+T27+V27+X27 -> 291329 | J27: =+M27+O27+Q27+S27+U27+W27+Y27 -> 801011 | K27: =IF($Z$34=0,"",Z27/$Z$34) -> 0.01431128 | L27: 110500 | M27: 10003 | N27: 110500 | O27: 13636 | P27: 26877 | Q27: 0 | R27: 43452 | S27: 0 | T27: 0 | U27: 777372 | V27: 0 | W27: 0 | X27: 0 | Y27: 0 | Z27: =+I27+J27 -> 1092340
A28: 17 | B28: Строительство | C28: =+'Loans Receivable'!C40 -> 283340629 | D28: =IF(C$34=0,"",C28/C$34) -> 0.049657162 | E28: 0 | F28: =IF($E$34=0,"",E28/$E$34) -> 0 | G28: 0 | H28: =IF($G$34=0,"",G28/$G$34) | I28: =+L28+N28+P28+R28+T28+V28+X28 -> 5470550 | J28: =+M28+O28+Q28+S28+U28+W28+Y28 -> 30577 | K28: =IF($Z$34=0,"",Z28/$Z$34) -> 0.072072952 | L28: 1231802 | M28: 0 | N28: 750019 | O28: 7634 | P28: 36356 | Q28: 0 | R28: 3452373 | S28: 22943 | T28: 0 | U28: 0 | V28: 0 | W28: 0 | X28: 0 | Y28: 0 | Z28: =+I28+J28 -> 5501127
A29: 18 | B29: Торговля и общественное питание | C29: =+'Loans Receivable'!C48 -> 151920268 | D29: =IF(C$34=0,"",C29/C$34) -> 0.026624947 | E29: 0 | F29: =IF($E$34=0,"",E29/$E$34) -> 0 | G29: 0 | H29: =IF($G$34=0,"",G29/$G$34) | I29: =+L29+N29+P29+R29+T29+V29+X29 -> 4205498 | J29: =+M29+O29+Q29+S29+U29+W29+Y29 -> 71638 | K29: =IF($Z$34=0,"",Z29/$Z$34) -> 0.056036848 | L29: 1179420 | M29: 31123 | N29: 677935 | O29: 1692 | P29: 610767 | Q29: 22690 | R29: 1727676 | S29: 16133 | T29: 9700 | U29: 0 | V29: 0 | W29: 0 | X29: 0 | Y29: 0 | Z29: =+I29+J29 -> 4277136
A30: 19 | B30: Материально-техническое снабжение и сбыт | C30: =+'Loans Receivable'!C56 -> 76942702 | D30: =IF(C$34=0,"",C30/C$34) -> 0.013484675 | E30: 0 | F30: =IF($E$34=0,"",E30/$E$34) -> 0 | G30: 0 | H30: =IF($G$34=0,"",G30/$G$34) | I30: =+L30+N30+P30+R30+T30+V30+X30 -> 0 | J30: =+M30+O30+Q30+S30+U30+W30+Y30 -> 0 | K30: =IF($Z$34=0,"",Z30/$Z$34) -> 0 | L30: 0 | M30: 0 | N30: 0 | O30: 0 | P30: 0 | Q30: 0 | R30: 0 | S30: 0 | T30: 0 | U30: 0 | V30: 0 | W30: 0 | X30: 0 | Y30: 0 | Z30: =+I30+J30 -> 0
A31: 20 | B31: Жилищно-коммунальные услуги | C31: =+'Loans Receivable'!C65 -> 21411004 | D31: =IF(C$34=0,"",C31/C$34) -> 0.0037524082 | E31: 0 | F31: =IF($E$34=0,"",E31/$E$34) -> 0 | G31: 0 | H31: =IF($G$34=0,"",G31/$G$34) | I31: =+L31+N31+P31+R31+T31+V31+X31 -> 687308 | J31: =+M31+O31+Q31+S31+U31+W31+Y31 -> 1042908 | K31: =IF($Z$34=0,"",Z31/$Z$34) -> 0.022668405 | L31: 15911 | M31: 328 | N31: 14607 | O31: 25029 | P31: 62065 | Q31: 723 | R31: 504699 | S31: 23988 | T31: 28472 | U31: 161423 | V31: 61554 | W31: 796525 | X31: 0 | Y31: 34892 | Z31: =+I31+J31 -> 1730216
A32: 21 | B32: Другие сектора | C32: =+'Loans Receivable'!C78 -> 3550069002 | D32: =IF(C$34=0,"",C32/C$34) -> 0.6221711 | E32: 79716130 | F32: =IF($E$34=0,"",E32/$E$34) -> 0.82973996 | G32: 0 | H32: =IF($G$34=0,"",G32/$G$34) | I32: =+L32+N32+P32+R32+T32+V32+X32 -> 29790822 | J32: =+M32+O32+Q32+S32+U32+W32+Y32 -> 23590546 | K32: =IF($Z$34=0,"",Z32/$Z$34) -> 0.69937538 | L32: 8799153 | M32: 480948 | N32: 5037648 | O32: 1018096 | P32: 3057004 | Q32: 565862 | R32: 2842528 | S32: 15675058 | T32: 3057381 | U32: 5007819 | V32: 6990993 | W32: 745232 | X32: 6115 | Y32: 97531 | Z32: =+I32+J32 -> 53381368
Z33: =+I33+J33 -> 0
A34: 22 | B34: Итого кредита и лизинга | C34: =SUM(C25:C32) -> 5705936821 | D34: =IF(C$34=0,"",C34/C$34) -> 1 | E34: =SUM(E25:E32) -> 96073630 | F34: =IF($E$34=0,"",E34/$E$34) -> 1 | G34: =SUM(G25:G32) -> 0 | H34: =IF($G$34=0,"",G34/$G$34) | I34: =SUM(I25:I32) -> 47490417 | J34: =SUM(J25:J32) -> 28836788 | K34: =IF($Z$34=0,"",Z34/$Z$34) -> 1 | L34: =SUM(L25:L32) -> 12969479 | M34: =SUM(M25:M32) -> 548367 | N34: =SUM(N25:N32) -> 7497083 | O34: =SUM(O25:O32) -> 1079001 | P34: =SUM(P25:P32) -> 4332024 | Q34: =SUM(Q25:Q32) -> 930553 | R34: =SUM(R25:R32) -> 8753959 | S34: =SUM(S25:S32) -> 15892401 | ... Y34: =SUM(Y25:Y32) -> 132423 | Z34: =+I34+J34 -> 76327205
B37: Подпись Председателя правления:
B39: Подпись Главного Бухгалтера:

Sheet Asset Classification
A1: ОТЧЕТ О КЛАССИФИКАЦИИ АКТИВОВ ПО СТЕПЕНИ РИСКА | W1: Таблица-10
B2: =+'Asset quality'!B3 -> АК "Алокабанк" | U2: =+'Asset quality'!P3 -> 44196 | Z2: тыс. сум
A3: № | B3: Статьи баланса | C3: Общая сумма | D3: из них, в иностранной валюте (в экв. в сумах) | E3: Стандартные | F3: из них, в иностранной валюте (в экв. в сумах) | G3: Общие резервы (1%) | H3: из них, в иностранной валюте (в экв. в сумах) | I3: Субстандартные | J3: из них, в иностранной валюте (в экв. в сумах) | K3: Специальные резервы (мин 10%) | L3: из них, в иностранной валюте (в экв. в сумах) | M3: Неудовлетворительные | N3: из них, в иностранной валюте (в экв. в сумах) | O3: Специальные резервы (мин 25%) | P3: из них, в иностранной валюте (в экв. в сумах) | Q3: Сомнительные | R3: из них, в иностранной валюте (в экв. в сумах) | S3: Специальные резервы (мин 50%) | T3: из них, в иностранной валюте (в экв. в сумах) | U3: Безнадежные | V3: из них, в иностранной валюте (в экв. в сумах) | W3: Специальные резервы (100%) | X3: из них, в иностранной валюте (в экв. в сумах) | Y3: Совокупная сумма специальных резервов | Z3: из них, в иностранной валюте (в экв. в сумах)
A4: (А) | B4: (Б) | C4: (В) | D4: (В1) | E4: (Г) | F4: (Г1) | G4: (Д) | H4: (Д1) | I4: (Е) | J4: (Е1) | K4: (Ж) | L4: (Ж1) | M4: (З) | N4: (З1) | O4: (И) | P4: (И1) | Q4: (К) | R4: (К1) | S4: (Л) | T4: (Л1) | U4: (М) | V4: (М1) | W4: (Н) | X4: (Н1) | Y4: О=Ж+И+Л+Н | Z4: (О1)=(Ж1)+(И1)+(Л1)+(Н1)
B5: По типу клиента
A6: 1 | B6: Центральный банк | C6: =E6+I6+M6+Q6+U6 -> 0 | D6: =F6+J6+N6+R6+V6 -> 0 | Y6: =+W6+S6+O6+K6 -> 0 | Z6: =+X6+T6+P6+L6 -> 0 | AA6: =+'Aging Analysis'!C9 -> 0
B7: из них необеспеченные | C7: =E7+I7+M7+Q7+U7 -> 0 | D7: =F7+J7+N7+R7+V7 -> 0 | Y7: =+W7+S7+O7+K7 -> 0 | Z7: =+X7+T7+P7+L7 -> 0
A8: 2 | B8: Другие банки | C8: =E8+I8+M8+Q8+U8 -> 0 | D8: =F8+J8+N8+R8+V8 -> 0 | Y8: =+W8+S8+O8+K8 -> 0 | Z8: =+X8+T8+P8+L8 -> 0 | AA8: =+'Aging Analysis'!C10 -> 0
B9: из них необеспеченные | C9: =E9+I9+M9+Q9+U9 -> 0 | D9: =F9+J9+N9+R9+V9 -> 0 | Y9: =+W9+S9+O9+K9 -> 0 | Z9: =+X9+T9+P9+L9 -> 0
A10: 3 | B10: Правительство | C10: =E10+I10+M10+Q10+U10 -> 0 | D10: =F10+J10+N10+R10+V10 -> 0 | Y10: =+W10+S10+O10+K10 -> 0 | Z10: =+X10+T10+P10+L10 -> 0 | AA10: =+'Aging Analysis'!C11 -> 0
B11: из них необеспеченные | C11: =E11+I11+M11+Q11+U11 -> 0 | D11: =F11+J11+N11+R11+V11 -> 0 | Y11: =+W11+S11+O11+K11 -> 0 | Z11: =+X11+T11+P11+L11 -> 0
A12: 4 | B12: Физические лица | C12: =E12+I12+M12+Q12+U12 -> 1022400185 | D12: =F12+J12+N12+R12+V12 -> 0 | E12: 1013972858 | G12: 11090682 | I12: 3431795 | K12: 736664 | M12: 2193928 | O12: 470636 | Q12: 1457838 | S12: 569578 | U12: 1343766 | W12: 570653 | Y12: =+W12+S12+O12+K12 -> 2347531 | Z12: =+X12+T12+P12+L12 -> 0 | AA12: =+'Aging Analysis'!C12 -> 1022400185
B13: из них необеспеченные | C13: =E13+I13+M13+Q13+U13 -> 0 | D13: =F13+J13+N13+R13+V13 -> 0 | G13: 0 | Y13: =+W13+S13+O13+K13 -> 0 | Z13: =+X13+T13+P13+L13 -> 0
A14: 5 | B14: Государственные предприятия | C14: =E14+I14+M14+Q14+U14 -> 759073325 | D14: =F14+J14+N14+R14+V14 -> 314307600 | E14: 759073325 | F14: 314307600 | G14: 8302629 | I14: 0 | M14: 0 | Y14: =+W14+S14+O14+K14 -> 0 | Z14: =+X14+T14+P14+L14 -> 0 | AA14: =+'Aging Analysis'!C13 -> 759073325
B15: из них необеспеченные | C15: =E15+I15+M15+Q15+U15 -> 0 | D15: =F15+J15+N15+R15+V15 -> 0 | G15: 0 | Y15: =+W15+S15+O15+K15 -> 0 | Z15: =+X15+T15+P15+L15 -> 0
A16: 6 | B16: Совместные и иностранные предприятия | C16: =E16+I16+M16+Q16+U16 -> 455567628 | D16: =F16+J16+N16+R16+V16 -> 172192219 | E16: 433495375 | F16: 150365274 | G16: 4741507 | I16: 22072253 | J16: 21826945 | K16: 242801 | L16: 218269 | M16: 0 | Y16: =+W16+S16+O16+K16 -> 242801 | Z16: =+X16+T16+P16+L16 -> 218269 | AA16: =+'Aging Analysis'!C14 -> 455567628
B17: из них необеспеченные | C17: =E17+I17+M17+Q17+U17 -> 0 | D17: =F17+J17+N17+R17+V17 -> 0 | G17: 0 | Y17: =+W17+S17+O17+K17 -> 0 | Z17: =+X17+T17+P17+L17 -> 0
A18: 7 | B18: Частные товарищества и корпорации | C18: =E18+I18+M18+Q18+U18 -> 3382356533 | D18: =F18+J18+N18+R18+V18 -> 1432986517 | E18: 3321497002 | F18: 1425634870 | G18: 36330031 | H18: 238850 | I18: 59487078 | J18: 7328557 | K18: 5051251 | L18: 528058 | M18: 1372453 | N18: 23090 | O18: 573090 | P18: 23090 | Y18: =+W18+S18+O18+K18 -> 5624341 | Z18: =+X18+T18+P18+L18 -> 551148 | AA18: =+'Aging Analysis'!C15 -> 3382356533
B19: из них необеспеченные | C19: =E19+I19+M19+Q19+U19 -> 0 | D19: =F19+J19+N19+R19+V19 -> 0 | G19: 0 | Y19: =+W19+S19+O19+K19 -> 0 | Z19: =+X19+T19+P19+L19 -> 0
A20: 8 | B20: Фермерское хозяйство | C20: =E20+I20+M20+Q20+U20 -> 0 | D20: =F20+J20+N20+R20+V20 -> 0 | G20: 0 | Y20: =+W20+S20+O20+K20 -> 0 | Z20: =+X20+T20+P20+L20 -> 0 | AA20: =+'Aging Analysis'!C16 -> 0
B21: из них необеспеченные | C21: =E21+I21+M21+Q21+U21 -> 0 | D21: =F21+J21+N21+R21+V21 -> 0 | G21: 0 | Y21: =+W21+S21+O21+K21 -> 0 | Z21: =+X21+T21+P21+L21 -> 0
A22: 9 | B22: Небанковские финансовые институты | C22: =E22+I22+M22+Q22+U22 -> 1424539 | D22: =F22+J22+N22+R22+V22 -> 0 | E22: 1424539 | G22: 15581 | I22: 0 | M22: 0 | Y22: =+W22+S22+O22+K22 -> 0 | Z22: =+X22+T22+P22+L22 -> 0 | AA22: =+'Aging Analysis'!C17 -> 1424539
B23: из них необеспеченные | C23: =E23+I23+M23+Q23+U23 -> 0 | D23: =F23+J23+N23+R23+V23 -> 0 | G23: 0 | Y23: =+W23+S23+O23+K23 -> 0 | Z23: =+X23+T23+P23+L23 -> 0
A24: 10 | B24: Негосударственные некоммерческие организации | C24: =E24+I24+M24+Q24+U24 -> 15649091 | D24: =F24+J24+N24+R24+V24 -> 0 | E24: 10276404 | G24: 112402 | I24: 5372687 | K24: 690357 | M24: 0 | Y24: =+W24+S24+O24+K24 -> 690357 | Z24: =+X24+T24+P24+L24 -> 0 | AA24: =+'Aging Analysis'!C18 -> 15649091
B25: из них необеспеченные | C25: =E25+I25+M25+Q25+U25 -> 0 | D25: =F25+J25+N25+R25+V25 -> 0 | G25: 0 | Y25: =+W25+S25+O25+K25 -> 0 | Z25: =+X25+T25+P25+L25 -> 0
A26: 11 | B26: Бюджетные организации | C26: =E26+I26+M26+Q26+U26 -> 0 | D26: =F26+J26+N26+R26+V26 -> 0 | G26: 0 | Y26: =+W26+S26+O26+K26 -> 0 | Z26: =+X26+T26+P26+L26 -> 0 | AA26: =+'Aging Analysis'!C19 -> 0
B27: из них необеспеченные | C27: =E27+I27+M27+Q27+U27 -> 0 | D27: =F27+J27+N27+R27+V27 -> 0 | G27: 0 | Y27: =+W27+S27+O27+K27 -> 0 | Z27: =+X27+T27+P27+L27 -> 0
A28: 12 | B28: Прочие | C28: =E28+I28+M28+Q28+U28 -> 69465520 | D28: =F28+J28+N28+R28+V28 -> 0 | E28: 67642128 | G28: 739859 | I28: 1809771 | K28: 168733 | M28: 13621 | O28: 3405 | Y28: =+W28+S28+O28+K28 -> 172138 | Z28: =+X28+T28+P28+L28 -> 0 | AA28: =+'Aging Analysis'!C20 -> 69465520
B29: из них необеспеченные | C29: =E29+I29+M29+Q29+U29 -> 0 | D29: =F29+J29+N29+R29+V29 -> 0 | E29: 0 | F29: 0 | G29: 0 | H29: 0 | I29: 0 | J29: 0 | K29: 0 | L29: 0 | M29: 0 | N29: 0 | O29: 0 | P29: 0 | Q29: 0 | R29: 0 | S29: 0 | T29: 0 | U29: 0 | V29: 0 | W29: 0 | X29: 0 | Y29: =+W29+S29+O29+K29 -> 0 | Z29: =+X29+T29+P29+L29 -> 0
A30: 13 | B30: Итого кредита и лизинга | C30: =+C6+C8+C10+C12+C14+C16+C18+C20+C22+C24+C26+C28 -> 5705936821 | D30: =+D6+D8+D10+D12+D14+D16+D18+D20+D22+D24+D26+D28 -> 1919486336 | E30: =+E6+E8+E10+E12+E14+E16+E18+E20+E22+E24+E26+E28 -> 5607381631 | F30: =+F6+F8+F10+F12+F14+F16+F18+F20+F22+F24+F26+F28 -> 1890307744 | G30: =+G6+G8+G10+G12+G14+G16+G18+G20+G22+G24+G26+G28 -> 61332691 | H30: =+H6+H8+H10+H12+H14+H16+H18+H20+H22+H24+H26+H28 -> 238850 | I30: =+I6+I8+I10+I12+I14+I16+I18+I20+I22+I24+I26+I28 -> 92173584 | J30: =+J6+J8+J10+J12+J14+J16+J18+J20+J22+J24+J26+J28 -> 29155502 | ... Z30: =+Z6+Z8+Z10+Z12+Z14+Z16+Z18+Z20+Z22+Z24+Z26+Z28 -> 769417
B31: из них необеспеченные | C31: =+C7+C9+C11+C13+C15+C17+C19+C21+C23+C25+C27+C29 -> 0 | D31: =+D7+D9+D11+D13+D15+D17+D19+D21+D23+D25+D27+D29 -> 0 | E31: =+E7+E9+E11+E13+E15+E17+E19+E21+E23+E25+E27+E29 -> 0 | F31: =+F7+F9+F11+F13+F15+F17+F19+F21+F23+F25+F27+F29 -> 0 | G31: =+G7+G9+G11+G13+G15+G17+G19+G21+G23+G25+G27+G29 -> 0 | H31: =+H7+H9+H11+H13+H15+H17+H19+H21+H23+H25+H27+H29 -> 0 | I31: =+I7+I9+I11+I13+I15+I17+I19+I21+I23+I25+I27+I29 -> 0 | J31: =+J7+J9+J11+J13+J15+J17+J19+J21+J23+J25+J27+J29 -> 0 | ... Z31: =+Z7+Z9+Z11+Z13+Z15+Z17+Z19+Z21+Z23+Z25+Z27+Z29 -> 0
B32: По сектору экономики
A34: 14 | B34: Промышленность | C34: =E34+I34+M34+Q34+U34 -> 965348427 | D34: =F34+J34+N34+R34+V34 -> 445862874 | E34: 937080574 | F34: 423578214 | G34: 10249645 | I34: 28267853 | J34: 22284660 | K34: 833239 | L34: 264041 | M34: 0 | Y34: =+W34+S34+O34+K34 -> 833239 | Z34: =+X34+T34+P34+L34 -> 264041 | AA34: =+'Aging Analysis'!C25 -> 965348427
B35: из них необеспеченные | C35: =E35+I35+M35+Q35+U35 -> 0 | D35: =F35+J35+N35+R35+V35 -> 0 | G35: 0 | Y35: =+W35+S35+O35+K35 -> 0 | Z35: =+X35+T35+P35+L35 -> 0
A36: 15 | B36: Сельское хозяйство | C36: =E36+I36+M36+Q36+U36 -> 113582271 | D36: =F36+J36+N36+R36+V36 -> 53699686 | E36: 88912886 | F36: 53699686 | G36: 972516 | I36: 23355764 | K36: 1555587 | M36: 1313621 | O36: 553405 | Y36: =+W36+S36+O36+K36 -> 2108992 | Z36: =+X36+T36+P36+L36 -> 0 | AA36: =+'Aging Analysis'!C26 -> 113582271
B37: из них необеспеченные | C37: =E37+I37+M37+Q37+U37 -> 0 | D37: =F37+J37+N37+R37+V37 -> 0 | G37: 0 | Y37: =+W37+S37+O37+K37 -> 0 | Z37: =+X37+T37+P37+L37 -> 0
A38: 16 | B38: Транспорт и коммуникации | C38: =E38+I38+M38+Q38+U38 -> 543322518 | D38: =F38+J38+N38+R38+V38 -> 11143469 | E38: 543118761 | F38: 11143469 | G38: 5940551 | I38: 203757 | K38: 14747 | M38: 0 | Y38: =+W38+S38+O38+K38 -> 14747 | Z38: =+X38+T38+P38+L38 -> 0 | AA38: =+'Aging Analysis'!C27 -> 543322518
B39: из них необеспеченные | C39: =E39+I39+M39+Q39+U39 -> 0 | D39: =F39+J39+N39+R39+V39 -> 0 | G39: 0 | Y39: =+W39+S39+O39+K39 -> 0 | Z39: =+X39+T39+P39+L39 -> 0
A40: 17 | B40: Строительство | C40: =E40+I40+M40+Q40+U40 -> 283340629 | D40: =F40+J40+N40+R40+V40 -> 120765803 | E40: 282819684 | F40: 120765803 | G40: 3093439 | I40: 520945 | K40: 233213 | M40: 0 | Y40: =+W40+S40+O40+K40 -> 233213 | Z40: =+X40+T40+P40+L40 -> 0 | AA40: =+'Aging Analysis'!C28 -> 283340629
B41: из них необеспеченные | C41: =E41+I41+M41+Q41+U41 -> 0 | D41: =F41+J41+N41+R41+V41 -> 0 | G41: 0 | Y41: =+W41+S41+O41+K41 -> 0 | Z41: =+X41+T41+P41+L41 -> 0
A42: 18 | B42: Торговля и общественное питание | C42: =E42+I42+M42+Q42+U42 -> 151920268 | D42: =F42+J42+N42+R42+V42 -> 19498162 | E42: 143904887 | F42: 19498162 | G42: 1574010 | I42: 8015381 | K42: 179623 | M42: 0 | Y42: =+W42+S42+O42+K42 -> 179623 | Z42: =+X42+T42+P42+L42 -> 0 | AA42: =+'Aging Analysis'!C29 -> 151920268
B43: из них необеспеченные | C43: =E43+I43+M43+Q43+U43 -> 0 | D43: =F43+J43+N43+R43+V43 -> 0 | G43: 0 | Y43: =+W43+S43+O43+K43 -> 0 | Z43: =+X43+T43+P43+L43 -> 0
A44: 19 | B44: Материально-техническое снабжение и сбыт | C44: =E44+I44+M44+Q44+U44 -> 76942702 | D44: =F44+J44+N44+R44+V44 -> 0 | E44: 76942702 | G44: 841587 | I44: 0 | K44: 0 | M44: 0 | Y44: =+W44+S44+O44+K44 -> 0 | Z44: =+X44+T44+P44+L44 -> 0 | AA44: =+'Aging Analysis'!C30 -> 76942702
B45: из них необеспеченные | C45: =E45+I45+M45+Q45+U45 -> 0 | D45: =F45+J45+N45+R45+V45 -> 0 | G45: 0 | Y45: =+W45+S45+O45+K45 -> 0 | Z45: =+X45+T45+P45+L45 -> 0
A46: 20 | B46: Жилищно-коммунальные услуги | C46: =E46+I46+M46+Q46+U46 -> 21411004 | D46: =F46+J46+N46+R46+V46 -> 0 | E46: 15963389 | G46: 174605 | I46: 5447615 | K46: 694592 | M46: 0 | Y46: =+W46+S46+O46+K46 -> 694592 | Z46: =+X46+T46+P46+L46 -> 0 | AA46: =+'Aging Analysis'!C31 -> 21411004
B47: из них необеспеченные | C47: =E47+I47+M47+Q47+U47 -> 0 | D47: =F47+J47+N47+R47+V47 -> 0 | G47: 0 | Y47: =+W47+S47+O47+K47 -> 0 | Z47: =+X47+T47+P47+L47 -> 0
A48: 21 | B48: Другие сектора | C48: =E48+I48+M48+Q48+U48 -> 3550069002 | D48: =F48+J48+N48+R48+V48 -> 1268516342 | E48: 3518638748 | F48: 1261622410 | G48: 38486338 | H48: 238850 | I48: 26362269 | J48: 6870842 | K48: 3378805 | L48: 482286 | M48: 2266381 | N48: 23090 | O48: 493726 | P48: 23090 | Q48: 1457838 | S48: 569578 | U48: 1343766 | W48: 570653 | Y48: =+W48+S48+O48+K48 -> 5012762 | Z48: =+X48+T48+P48+L48 -> 505376 | AA48: =+'Aging Analysis'!C32 -> 3550069002
B49: из них необеспеченные | C49: =E49+I49+M49+Q49+U49 -> 0 | D49: =F49+J49+N49+R49+V49 -> 0 | E49: 0 | F49: 0 | G49: 0 | H49: 0 | I49: 0 | J49: 0 | K49: 0 | L49: 0 | M49: 0 | N49: 0 | O49: 0 | P49: 0 | Q49: 0 | R49: 0 | S49: 0 | T49: 0 | U49: 0 | V49: 0 | W49: 0 | X49: 0 | Y49: =+W49+S49+O49+K49 -> 0 | Z49: =+X49+T49+P49+L49 -> 0
A50: 22 | B50: Итого кредита и лизинга | C50: =+C34+C36+C38+C40+C42+C44+C46+C48 -> 5705936821 | D50: =+D34+D36+D38+D40+D42+D44+D46+D48 -> 1919486336 | E50: =+E34+E36+E38+E40+E42+E44+E46+E48 -> 5607381631 | F50: =+F34+F36+F38+F40+F42+F44+F46+F48 -> 1890307744 | G50: =+G34+G36+G38+G40+G42+G44+G46+G48 -> 61332691 | H50: =+H34+H36+H38+H40+H42+H44+H46+H48 -> 238850 | I50: =+I34+I36+I38+I40+I42+I44+I46+I48 -> 92173584 | J50: =+J34+J36+J38+J40+J42+J44+J46+J48 -> 29155502 | ... Z50: =+Z34+Z36+Z38+Z40+Z42+Z44+Z46+Z48 -> 769417
B51: из них необеспеченные | C51: =+C35+C37+C39+C41+C43+C45+C47+C49 -> 0 | D51: =+D35+D37+D39+D41+D43+D45+D47+D49 -> 0 | E51: =+E35+E37+E39+E41+E43+E45+E47+E49 -> 0 | F51: =+F35+F37+F39+F41+F43+F45+F47+F49 -> 0 | G51: =+G35+G37+G39+G41+G43+G45+G47+G49 -> 0 | H51: =+H35+H37+H39+H41+H43+H45+H47+H49 -> 0 | I51: =+I35+I37+I39+I41+I43+I45+I47+I49 -> 0 | J51: =+J35+J37+J39+J41+J43+J45+J47+J49 -> 0 | ... Z51: =+Z35+Z37+Z39+Z41+Z43+Z45+Z47+Z49 -> 0
B52: По регионам
A54: 23 | B54: Республика Каракалпакстан | C54: =E54+I54+M54+Q54+U54 -> 181876078 | D54: =F54+J54+N54+R54+V54 -> 22001532 | E54: 180110705 | F54: 22001532 | G54: 1970041 | H54: 0 | I54: 1169121 | J54: 0 | K54: 280149 | L54: 0 | M54: 121920 | N54: 0 | O54: 1273 | P54: 0 | Q54: 132317 | R54: 0 | S54: 34048 | T54: 0 | U54: 342015 | V54: 0 | W54: 34293 | Y54: =+W54+S54+O54+K54 -> 349763 | Z54: =+X54+T54+P54+L54 -> 0
A55: 24 | B55: Андижанская область | C55: =E55+I55+M55+Q55+U55 -> 0 | D55: =F55+J55+N55+R55+V55 -> 0 | E55: 0 | F55: 0 | G55: 0 | H55: 0 | I55: 0 | J55: 0 | K55: 0 | L55: 0 | M55: 0 | N55: 0 | O55: 0 | P55: 0 | Q55: 0 | R55: 0 | S55: 0 | T55: 0 | U55: 0 | V55: 0 | W55: 0 | Y55: =+W55+S55+O55+K55 -> 0 | Z55: =+X55+T55+P55+L55 -> 0
A56: 25 | B56: Бухарская область | C56: =E56+I56+M56+Q56+U56 -> 308836551 | D56: =F56+J56+N56+R56+V56 -> 141387670 | E56: 303688547 | F56: 138555423 | G56: 3321729 | H56: 0 | I56: 5145038 | J56: 2832247 | K56: 394660 | L56: 283225 | M56: 0 | N56: 0 | O56: 0 | P56: 0 | Q56: 0 | R56: 0 | S56: 0 | T56: 0 | U56: 2966 | V56: 0 | W56: 0 | Y56: =+W56+S56+O56+K56 -> 394660 | Z56: =+X56+T56+P56+L56 -> 283225
A57: 26 | B57: Джизакская область | C57: =E57+I57+M57+Q57+U57 -> 334326136 | D57: =F57+J57+N57+R57+V57 -> 106484275 | E57: 332383517 | F57: 106484275 | G57: 3635593 | H57: 0 | I57: 1885803 | J57: 0 | K57: 301375 | L57: 0 | M57: 0 | N57: 0 | O57: 0 | P57: 0 | Q57: 56816 | R57: 0 | S57: 28408 | T57: 0 | U57: 0 | V57: 0 | W57: 0 | Y57: =+W57+S57+O57+K57 -> 329783 | Z57: =+X57+T57+P57+L57 -> 0
A58: 27 | B58: Кашкадарьинская область | C58: =E58+I58+M58+Q58+U58 -> 204740327 | D58: =F58+J58+N58+R58+V58 -> 12395269 | E58: 201949662 | F58: 12395269 | G58: 2208914 | H58: 0 | I58: 2433501 | J58: 0 | K58: 312757 | L58: 0 | M58: 32636 | N58: 0 | O58: 2124 | P58: 0 | Q58: 0 | R58: 0 | S58: 0 | T58: 0 | U58: 324528 | V58: 0 | W58: 160390 | Y58: =+W58+S58+O58+K58 -> 475271 | Z58: =+X58+T58+P58+L58 -> 0
A59: 28 | B59: Навоийская область | C59: =E59+I59+M59+Q59+U59 -> 539858298 | D59: =F59+J59+N59+R59+V59 -> 351166440 | E59: 537663241 | F59: 351166440 | G59: 5880932 | H59: 0 | I59: 2164060 | J59: 0 | K59: 230626 | L59: 0 | M59: 0 | N59: 0 | O59: 0 | P59: 0 | Q59: 8888 | R59: 0 | S59: 3513 | T59: 0 | U59: 22109 | V59: 0 | W59: 11054 | Y59: =+W59+S59+O59+K59 -> 245193 | Z59: =+X59+T59+P59+L59 -> 0
A60: 29 | B60: Наманганская область | C60: =E60+I60+M60+Q60+U60 -> 182794766 | D60: =F60+J60+N60+R60+V60 -> 77671476 | E60: 180111128 | F60: 77213760 | G60: 1970046 | H60: 0 | I60: 1140165 | J60: 457716 | K60: 127006 | L60: 45772 | M60: 1452495 | N60: 0 | O60: 576621 | P60: 0 | Q60: 29826 | R60: 0 | S60: 12816 | T60: 0 | U60: 61152 | V60: 0 | W60: 32980 | Y60: =+W60+S60+O60+K60 -> 749423 | Z60: =+X60+T60+P60+L60 -> 45772
A61: 30 | B61: Самаркандская область | C61: =E61+I61+M61+Q61+U61 -> 499862577 | D61: =F61+J61+N61+R61+V61 -> 253829339 | E61: 496170806 | F61: 253829339 | G61: 5427090 | H61: 238850 | I61: 3301149 | J61: 0 | K61: 908543 | L61: 0 | M61: 132030 | N61: 0 | O61: 13910 | P61: 0 | Q61: 249789 | R61: 0 | S61: 63610 | T61: 0 | U61: 8803 | V61: 0 | W61: 0 | Y61: =+W61+S61+O61+K61 -> 986063 | Z61: =+X61+T61+P61+L61 -> 0
A62: 31 | B62: Сурхандарьинская область | C62: =E62+I62+M62+Q62+U62 -> 367713765 | D62: =F62+J62+N62+R62+V62 -> 58902503 | E62: 361815425 | F62: 58902503 | G62: 3957518 | H62: 0 | I62: 4668921 | J62: 0 | K62: 675526 | L62: 0 | M62: 752740 | N62: 0 | O62: 325588 | P62: 0 | Q62: 404834 | R62: 0 | S62: 190472 | T62: 0 | U62: 71845 | V62: 0 | W62: 44249 | Y62: =+W62+S62+O62+K62 -> 1235835 | Z62: =+X62+T62+P62+L62 -> 0
A63: 32 | B63: Сырдарьинская область | C63: =E63+I63+M63+Q63+U63 -> 0 | D63: =F63+J63+N63+R63+V63 -> 0 | E63: 0 | F63: 0 | G63: 0 | H63: 0 | I63: 0 | J63: 0 | K63: 0 | L63: 0 | M63: 0 | N63: 0 | O63: 0 | P63: 0 | Q63: 0 | R63: 0 | S63: 0 | T63: 0 | U63: 0 | V63: 0 | W63: 0 | Y63: =+W63+S63+O63+K63 -> 0 | Z63: =+X63+T63+P63+L63 -> 0
A64: 33 | B64: г. Ташкент | C64: =E64+I64+M64+Q64+U64 -> 2213996208 | D64: =F64+J64+N64+R64+V64 -> 552249441 | E64: 2165230405 | F64: 548210846 | G64: 23683173 | H64: 0 | I64: 47070668 | J64: 4038595 | K64: 3094965 | L64: 199061 | M64: 679309 | N64: 0 | O64: 92194 | P64: 0 | Q64: 541355 | R64: 0 | S64: 223013 | T64: 0 | U64: 474471 | V64: 0 | W64: 271121 | Y64: =+W64+S64+O64+K64 -> 3681293 | Z64: =+X64+T64+P64+L64 -> 199061
A65: 34 | B65: Ташкентская область | C65: =E65+I65+M65+Q65+U65 -> 0 | D65: =F65+J65+N65+R65+V65 -> 0 | E65: 0 | F65: 0 | G65: 0 | H65: 0 | I65: 0 | J65: 0 | K65: 0 | L65: 0 | M65: 0 | N65: 0 | O65: 0 | P65: 0 | Q65: 0 | R65: 0 | S65: 0 | T65: 0 | U65: 0 | V65: 0 | W65: 0 | Y65: =+W65+S65+O65+K65 -> 0 | Z65: =+X65+T65+P65+L65 -> 0
... A67: 36 | B67: Хорезмская область | C67: =E67+I67+M67+Q67+U67 -> 238789072 | D67: =F67+J67+N67+R67+V67 -> 97141616 | E67: 238434978 | F67: 97118526 | G67: 2607442 | H67: 0 | I67: 209584 | J67: 0 | K67: 182388 | L67: 0 | M67: 76797 | N67: 23090 | O67: 35421 | P67: 23090 | Q67: 34013 | R67: 0 | S67: 13698 | T67: 0 | U67: 33700 | V67: 0 | W67: 15477 | Y67: =+W67+S67+O67+K67 -> 246984 | Z67: =+X67+T67+P67+L67 -> 23090
A68: 37 | B68: Итого кредита и лизинга | C68: =SUM(C54:C67) -> 5705936821 | D68: =SUM(D54:D67) -> 1919486336 | E68: =SUM(E54:E67) -> 5607381631 | F68: =SUM(F54:F67) -> 1890307744 | G68: =SUM(G54:G67) -> 61332691 | H68: =SUM(H54:H67) -> 238850 | I68: =SUM(I54:I67) -> 92173584 | J68: =SUM(J54:J67) -> 29155502 | ... Z68: =SUM(Z54:Z67) -> 769417
A69: 38 | B69: Другие классифицированные активы | C69: =E69+I69+M69+Q69+U69 -> 8109113864 | D69: =F69+J69+N69+R69+V69 -> 0 | E69: 8108166331 | P69: 110548 | S69: 55274 | U69: 947533 | W69: =1947533-1000001 -> 947532 | Y69: =+W69+S69+O69+K69 -> 1002806 | Z69: =+X69+T69+P69+L69 -> 110548
B70: из них необеспеченные | C70: =E70+I70+M70+Q70+U70 -> 0 | D70: =F70+J70+N70+R70+V70 -> 0 | Y70: =+W70+S70+O70+K70 -> 0 | Z70: =+X70+T70+P70+L70 -> 0
A71: 39 | B71: Всего классифицированных активов | C71: =+C50+C69 -> 13815050685 | D71: =+D50+D69 -> 1919486336 | E71: =+E50+E69 -> 13715547962 | F71: =+F50+F69 -> 1890307744 | G71: =+G50+G69 -> 61332691 | H71: =+H50+H69 -> 238850 | I71: =+I50+I69 -> 92173584 | J71: =+J50+J69 -> 29155502 | ... Z71: =+Z50+Z69 -> 879965
B74: Подпись Председателя правления:
B76: Подпись Главного Бухгалтера:
E77: =SUM('Asset quality'!D21:D47)+'Asset quality'!D16 -> 5607381631 | G77: =SUM('Asset quality'!O21:O47)+'Asset quality'!O16 -> 61332691 | I77: =SUM('Asset quality'!E21:E47)+'Asset quality'!E16 -> 92173584 | K77: =SUM('Asset quality'!P21:P47)+'Asset quality'!P16 -> 6889806 | M77: =SUM('Asset quality'!F21:F47) -> 3580002 | O77: =SUM('Asset quality'!Q21:Q47)+'Asset quality'!Q16 -> 1047131 | Q77: =SUM('Asset quality'!G21:G47) -> 1457838 | S77: =SUM('Asset quality'!R21:R47)+'Asset quality'!R16 -> 569578 | U77: =SUM('Asset quality'!H21:H47) -> 1343766 | W77: =SUM('Asset quality'!S21:S47)+'Asset quality'!S16 -> 570653 | Y77: =+W77+S77+O77+K77 -> 9077168
G78: =+'Asset quality'!O9+'Asset quality'!O62 -> 61332691 | K78: =+'Asset quality'!P9+'Asset quality'!P62 -> 6889806 | O78: =+'Asset quality'!Q9+'Asset quality'!Q62 -> 1047131 | S78: =+'Asset quality'!R9+'Asset quality'!R62 -> 624852 | W78: =+'Asset quality'!S9+'Asset quality'!S62 -> 1518185 | Y78: =+W78+S78+O78+K78 -> 10079974
E79: =+E77-E50 -> 0 | G79: =+G77-G50 -> 0 | I79: =+I77-I50 -> 0 | K79: =+K77-K50 -> 0 | M79: =+M77-M50 -> 0 | O79: =+O77-O50 -> 0 | Q79: =+Q77-Q50 -> 0 | S79: =+S77-S50 -> 0 | U79: =+U77-U50 -> 0 | W79: =+W77-W50 -> 0 | Y79: =+Y77-Y50 -> 0
G80: =+G78-G71 -> 0 | K80: =+K78-K71 -> 0 | O80: =+O78-O71 -> 0 | S80: =+S78-S71 -> 0 | W80: =+W78-W71 -> 0 | Y80: =+Y78-Y71 -> 0

Sheet Loans to Affiliated P.
A1: ОТЧЕТ О СДЕЛКАХ, ЗАКЛЮЧЕННЫХ СО СВЯЗАННЫМИ ЛИЦАМИ | S1: Таблица-11
B3: =+'Asset quality'!B3 -> АК "Алокабанк" | N3: =+'Asset quality'!P3 -> 44196 | S3: тыс. сум
A4: № | B4: Наименования клиента | C4: ИНН | D4: Вид деятельности | E4: Код валюты | F4: Номер группы | G4: Текущая задолженность | H4: из них | N4: Пересмотрения | O4: Обеспечения | Q4: Классификация | R4: Резерв | S4: Источник кредита
H5: Кредиты и лизинги | I5: Инвестиции | J5: Аккредитивы | K5: Гарантии | L5: Межбанковские кредиты и депозиты | M5: другие активы* | O5: Вид залога | P5: Сумма залога
B6: А | C6: Б | D6: В | E6: Г | F6: Д | G6: Е | H6: Е1 | I6: Е2 | J6: Е3 | K6: Е4 | L6: Е5 | M6: Е6 | N6: Ж | O6: З | P6: И | Q6: К | R6: Л | S6: М
A7: 1 | B7: "Тошкент Чинни Заводи" МЧЖ | C7: 305646742 | D7: 23490 | E7: 860 | F7: 1 | G7: =SUM(H7:M7) -> 116803254 | H7: 94628083 | M7: 22175171 | Q7: 1
A8: =A7+1 -> 2 | B8: "Алока Актив" МЧЖ | C8: 305186248 | D8: 96190 | E8: 860 | F8: 1 | G8: =SUM(H8:M8) -> 33000000 | I8: 33000000 | Q8: 1
A9: 3 | B9: "Алокализинг" МЧЖ | C9: 305675865 | D9: 64990 | E9: 860 | F9: 2 | G9: =SUM(H9:M9) -> 22310000 | H9: 21100000 | I9: 1210000 | Q9: 1
A10: 4 | B10: "Уздижитал ТВ" МЧЖ | C10: 207027936 | D10: 52300 | E10: 860 | F10: 3 | G10: =SUM(H10:M10) -> 1136155.4 | I10: 1136155.4 | Q10: 1
A11: 5 | B11: "Пеймент Агригайшн Системс" МЧЖ | C11: 305148809 | D11: 58290 | E11: 860 | F11: 4 | G11: =SUM(H11:M11) -> 375000 | I11: 375000 | Q11: 1
A12: 6 | B12: "Оила даврасида газетаси тахририяти" МЧЖ | C12: 207151206 | D12: 87100 | E12: 860 | F12: 5 | G12: =SUM(H12:M12) -> 110548.84 | I12: 110548.84 | Q12: 4 | R12: 55274.42
A13: 7 | B13: АО СК "Алском" | C13: 201941144 | D13: 65120 | E13: 860 | F13: 6 | G13: =SUM(H13:M13) -> 2607352 | I13: 2607352 | Q13: 1
A14: 8 | B14: "Ўзбектелеком" АЖ | C14: 203366731 | D14: 61100 | E14: 860 | F14: 7 | G14: =SUM(H14:M14) -> 455250911 | H14: 349753188 | K14: 104769200 | M14: 728523 | P14: 216400000 | Q14: 1
A15: 9 | B15: "Нано Лизинг Компанияси" МЧЖ | C15: 207137166 | D15: 64910 | E15: 860 | F15: 8 | G15: =SUM(H15:M15) -> 76940143 | H15: 76940143 | Q15: 1
A16: 10 | B16: "IT-INVEST" МЧЖ | C16: 305059128 | D16: 62020 | E16: 860 | F16: 8 | G16: =SUM(H16:M16) -> 3666667 | H16: 3666667 | Q16: 1
A17: 11 | B17: Маматов Улугбек Фуркат угли | C17: 545091429 | D17: 99950 | E17: 860 | F17: 9 | G17: =SUM(H17:M17) -> 987784 | H17: 987784 | P17: 0
A18: 12 | B18: Ибрагимов Азизбек Кэлдибек ўғли | C18: 506643954 | D18: 99950 | E18: 860 | F18: 10 | G18: =SUM(H18:M18) -> 786602 | H18: 786602 | P18: 0
A19: 13 | B19: Халавов Фаррух Истамович | C19: 540576855 | D19: 99950 | E19: 860 | F19: 11 | G19: =SUM(H19:M19) -> 661406 | H19: 661406 | P19: 0
A20: 14 | B20: Ганиев Шерали Алижон угли | C20: 510888885 | D20: 99950 | E20: 860 | F20: 12 | G20: =SUM(H20:M20) -> 623431 | H20: 623431 | P20: 0
A21: 15 | B21: Абдурашидова Нигора Ибрагимовна | C21: 487802528 | D21: 99950 | E21: 860 | F21: 13 | G21: =SUM(H21:M21) -> 535724 | H21: 535724 | P21: 0
A22: 16 | B22: Ходжаниязов Уткир Юсупович | C22: 498628800 | D22: 99950 | E22: 860 | F22: 14 | G22: =SUM(H22:M22) -> 528805 | H22: 528805 | P22: 0
A23: 17 | B23: Хакбердиев Зафар Алишер угли | C23: 508642376 | D23: 99950 | E23: 860 | F23: 15 | G23: =SUM(H23:M23) -> 489574 | H23: 489574 | P23: 20648
A24: 18 | B24: Жумаев Ҳафиз Ҳусенович | C24: 486784282 | D24: 99950 | E24: 860 | F24: 16 | G24: =SUM(H24:M24) -> 487605 | H24: 487605 | P24: 0
A25: 19 | B25: Гуломова Инобат Анваровна | D25: 99950 | E25: 860 | F25: 17 | G25: =SUM(H25:M25) -> 478509 | H25: 478509 | P25: 0
A26: 20 | B26: Пўлатова Ҳилола Ғайрат қизи | C26: 497547744 | D26: 99950 | E26: 860 | F26: 18 | G26: =SUM(H26:M26) -> 476933 | H26: 476933 | P26: 0
A27: 21 | B27: Хасанов Назиржон Набижанович | C27: 496418880 | D27: 99950 | E27: 860 | F27: 19 | G27: =SUM(H27:M27) -> 455866 | H27: 455866 | P27: 0
A28: 22 | B28: Набижонов Муҳаммадносир нодир ўғли | C28: 514610438 | D28: 99950 | E28: 860 | F28: 20 | G28: =SUM(H28:M28) -> 442994 | H28: 442994 | P28: 0
A29: 23 | B29: Аслонов Низомжон Аслонович | C29: 514658789 | D29: 99950 | E29: 860 | F29: 21 | G29: =SUM(H29:M29) -> 433085 | H29: 433085 | P29: 0
A30: 24 | B30: Ботиров Бекзод Косимович | C30: 495549767 | D30: 99950 | E30: 860 | F30: 22 | G30: =SUM(H30:M30) -> 428523 | H30: 428523 | P30: 1
A31: 25 | B31: Абдуллаев Учкун Аширович | C31: 487873266 | D31: 99950 | E31: 860 | F31: 23 | G31: =SUM(H31:M31) -> 412499 | H31: 412499 | P31: 0
A32: 26 | B32: Полвонов Асроржон Абдулхаевич | C32: 509499854 | D32: 99950 | E32: 860 | F32: 24 | G32: =SUM(H32:M32) -> 407274 | H32: 407274 | P32: 0
A33: 27 | B33: Усмонов Шухрат Собиржонович | C33: 501360789 | D33: 99950 | E33: 860 | F33: 25 | G33: =SUM(H33:M33) -> 397087 | H33: 397087 | P33: 0
A34: 28 | B34: Расулов Абдурахмон Муратович | C34: 460627292 | D34: 99950 | E34: 860 | F34: 26 | G34: =SUM(H34:M34) -> 386296 | H34: 386296 | P34: 0
A35: 29 | B35: Ахтамов Шароф Ахтам ўғли | C35: 524032978 | D35: 99950 | E35: 860 | F35: 27 | G35: =SUM(H35:M35) -> 366262 | H35: 366262 | P35: 0
A36: 30 | B36: Мирзаев Мақсуд Баходирович | D36: 99950 | E36: 860 | F36: 28 | G36: =SUM(H36:M36) -> 355231 | H36: 355231 | P36: 0
A37: 31 | B37: Файзиев Сирожиддин Собир ўғли | C37: 511420770 | D37: 99950 | E37: 860 | F37: 29 | G37: =SUM(H37:M37) -> 353560 | H37: 353560 | P37: 0
A38: 32 | B38: Худойбердиев Кахрамон Абдуназарович | C38: 496259336 | D38: 99950 | E38: 860 | F38: 30 | G38: =SUM(H38:M38) -> 352676 | H38: 352676 | P38: 0
A39: 33 | B39: Гайбуллоев Сухроб Одил ўғли | C39: 501987649 | D39: 99950 | E39: 860 | F39: 31 | G39: =SUM(H39:M39) -> 351553 | H39: 351553 | P39: 10770
A40: 34 | B40: Қадомов Махмудбек Баходир ўғли | C40: 538664452 | D40: 99950 | E40: 860 | F40: 32 | G40: =SUM(H40:M40) -> 350422 | H40: 350422 | P40: 0
A41: 35 | B41: Раҳматов Аҳад Комил ўғли | C41: 500261635 | D41: 99950 | E41: 860 | F41: 33 | G41: =SUM(H41:M41) -> 349265 | H41: 349265 | P41: 0
A42: 36 | B42: Умурбаев Азиз Махсадбекович | C42: 498620804 | D42: 99950 | E42: 860 | F42: 34 | G42: =SUM(H42:M42) -> 348123 | H42: 348123 | P42: 24814
A43: 37 | B43: Халавов Фируз Истамович | C43: 499601185 | D43: 99950 | E43: 860 | F43: 35 | G43: =SUM(H43:M43) -> 347672 | H43: 347672 | P43: 0
A44: 38 | B44: Раззакова Дилором Шараф кизи | C44: 517275235 | D44: 99950 | E44: 860 | F44: 36 | G44: =SUM(H44:M44) -> 336951 | H44: 336951 | P44: 0
A45: 39 | B45: Утамова Шоира Абдуразаковна | C45: 532588471 | D45: 99950 | E45: 860 | F45: 37 | G45: =SUM(H45:M45) -> 332698 | H45: 332698 | P45: 0
A46: 40 | B46: Рустамов Сарвар Сувонкулович | C46: 499355491 | D46: 99950 | E46: 860 | F46: 38 | G46: =SUM(H46:M46) -> 330520 | H46: 330520 | P46: 93
A47: 41 | B47: Гуломов Шарофиддин Шарифжон ўғли | C47: 515556883 | D47: 99950 | E47: 860 | F47: 39 | G47: =SUM(H47:M47) -> 328297 | H47: 328297 | P47: 0
A48: 42 | B48: Кахаров Элдиёр Холмуродович | C48: 473452774 | D48: 99950 | E48: 860 | F48: 40 | G48: =SUM(H48:M48) -> 312365 | H48: 312365 | P48: 0
A49: 43 | B49: Рахимназаров Йулдош Бозорович | D49: 99950 | E49: 860 | F49: 41 | G49: =SUM(H49:M49) -> 305126 | H49: 305126 | P49: 0
A50: 44 | B50: Тошпулатов Бекзод | C50: 499849485 | D50: 99950 | E50: 860 | F50: 42 | G50: =SUM(H50:M50) -> 304388 | H50: 304388 | P50: 0
A51: 45 | B51: Саидов Эгамжон Шахриёр ўғли | C51: 499944186 | D51: 99950 | E51: 860 | F51: 43 | G51: =SUM(H51:M51) -> 303094 | H51: 303094 | P51: 0
A52: 46 | B52: Файзиев Сардор Собирович | D52: 99950 | E52: 860 | F52: 44 | G52: =SUM(H52:M52) -> 300553 | H52: 300553 | P52: 0
A53: 47 | B53: Адилов Абдужалол Халматович | C53: 454843114 | D53: 99950 | E53: 860 | F53: 45 | G53: =SUM(H53:M53) -> 300258 | H53: 300258 | P53: 0
A54: 48 | B54: Жураева Гавхар Нуритдинова | C54: 507554580 | D54: 99950 | E54: 860 | F54: 46 | G54: =SUM(H54:M54) -> 297783 | H54: 297783 | P54: 0
A55: 49 | B55: Axmedova Moxira Shogdorovna | C55: 490485109 | D55: 99950 | E55: 860 | F55: 47 | G55: =SUM(H55:M55) -> 296652 | H55: 296652 | P55: 0
A56: 50 | B56: Каримов Сирожиддин Уролович | C56: 496128672 | D56: 99950 | E56: 860 | F56: 48 | G56: =SUM(H56:M56) -> 295119 | H56: 295119 | P56: 0
A57: 51 | B57: Муратбаева Халима Аллабай қизи | D57: 99950 | E57: 860 | F57: 49 | G57: =SUM(H57:M57) -> 293981 | H57: 293981 | P57: 0
A58: 52 | B58: Холиқов Зохид Рашидович | C58: 513199657 | D58: 99950 | E58: 860 | F58: 50 | G58: =SUM(H58:M58) -> 293172 | H58: 293172 | P58: 0
A59: 53 | B59: Маткаримов Санжар Юлдош ўғли | C59: 523640490 | D59: 99950 | E59: 860 | F59: 51 | G59: =SUM(H59:M59) -> 290067 | H59: 290067 | P59: 0
A60: 54 | B60: Mallayev Elyor Ibroximovich | C60: 493989601 | D60: 99950 | E60: 860 | F60: 52 | G60: =SUM(H60:M60) -> 283633 | H60: 283633 | P60: 0
A61: 55 | B61: Мусаев Илхомжон Рустам ўғли | C61: 517681744 | D61: 99950 | E61: 860 | F61: 53 | G61: =SUM(H61:M61) -> 271650 | H61: 271650 | P61: 0
A62: 56 | B62: Авазов Баҳодир Бахтиёрович | C62: 494549830 | D62: 99950 | E62: 860 | F62: 54 | G62: =SUM(H62:M62) -> 270995 | H62: 270995 | P62: 0
A63: 57 | B63: Ибрахимов Ибрахимжон Отаназарович | C63: 495392918 | D63: 99950 | E63: 860 | F63: 55 | G63: =SUM(H63:M63) -> 255315 | H63: 255315 | P63: 0
A64: 58 | B64: Умаркулова Зиёда XXX | C64: 489072043 | D64: 99950 | E64: 860 | F64: 56 | G64: =SUM(H64:M64) -> 253690 | H64: 253690 | P64: 0
A65: 59 | B65: Тураев Шавкат Абдузоирович | C65: 496318340 | D65: 99950 | E65: 860 | F65: 57 | G65: =SUM(H65:M65) -> 253650 | H65: 253650 | P65: 0
A66: 60 | B66: Буранова Мунаввар Омановна | D66: 99950 | E66: 860 | F66: 58 | G66: =SUM(H66:M66) -> 247226 | H66: 247226 | P66: 0
A67: 61 | B67: Холов Хуршиджон Худойбердиевич | C67: 513726894 | D67: 99950 | E67: 860 | F67: 59 | G67: =SUM(H67:M67) -> 246294 | H67: 246294 | P67: 0
A68: 62 | B68: Прочие (1 250 физ. лиц) | D68: 99950 | E68: 860 | F68: 60 | G68: =SUM(H68:M68) -> 34546465 | H68: 34546465 | P68: 1018765
A69: ИТОГО АКТИВОВ ПО СВЯЗАННЫМ ЛИЦАМ | G69: =SUM(G7:G68) -> 7.6634473e+08 | H69: =SUM(H7:H68) -> 600232784 | I69: =SUM(I7:I68) -> 38439056 | J69: =SUM(J7:J68) -> 0 | K69: =SUM(K7:K68) -> 104769200 | L69: =SUM(L7:L68) -> 0 | M69: =SUM(M7:M68) -> 22903694 | P69: =SUM(P7:P68) -> 217475091
A70: САМЫЙ КРУПНЫЙ АКТИВ, ВЫДАННЫЙ БАНКОМ ОДНОМУ ИНСАЙДЕРУ | G70: =MAX(G7:G68) -> 455250911 | H70: =MAX(H7:H68) -> 349753188 | I70: =MAX(I7:I68) -> 33000000 | J70: =MAX(J7:J68) -> 0 | K70: =MAX(K7:K68) -> 104769200 | L70: =MAX(L7:L68) -> 0 | M70: =MAX(M7:M68) -> 22175171 | P70: =MAX(P7:P68) -> 216400000
B73: Подпись Председателя Правления:
B75: Подпись Главного Бухгалтера:

Sheet  Largest risk
A1: ОТЧЕТ О КРУПНЫХ РИСКАХ | S1: Таблица-12
B3: =+'Asset quality'!B3 -> АК "Алокабанк" | N3: =+'Asset quality'!P3 -> 44196 | O3: =+#REF! -> #REF! | S3: тыс. сум
A4: № | B4: Наименования клиента | C4: ИНН | D4: Вид деятельности | E4: Код валюты | F4: Номер группы | G4: Текущая задолженность | H4: из них | N4: Пересмотрения | O4: Обеспечения | Q4: Классификация | R4: Резерв | S4: Источник кредита
H5: Кредиты и лизинги | I5: Инвестиции | J5: Аккредитивы | K5: Гарантии | L5: Межбанковские кредиты и депозиты | M5: другие активы* | O5: Вид залога | P5: Сумма залога
B6: А | C6: Б | D6: В | E6: Г | F6: Д | G6: Е | H6: Е1 | I6: Е2 | J6: Е3 | K6: Е4 | L6: Е5 | M6: Е6 | N6: Ж | O6: З | P6: И | Q6: К | R6: Л | S6: М
A7: 1 | B7: АК "Ўзбектелеком" | C7: 203366731 | D7: 52300 | E7: 860 | F7: 1 | G7: =SUM(H7:M7) -> 455250911 | H7: 349753188 | K7: 104769200 | M7: 728523 | O7: 2 | P7: 216400000 | Q7: 4 | U7: 0
A8: 2 | B8: Навоийский горно-метал. ком. | C8: 201204514 | D8: 12411 | E8: 840 | F8: 2 | G8: =SUM(H8:M8) -> 314307600 | H8: 314307600 | Q8: 1
A9: 3 | B9: "Универсал Мобайл Системс" МЧЖ | C9: 303020732 | D9: 52300 | E9: 860 | F9: 3 | G9: =SUM(H9:M9) -> 100241592 | H9: 99981592 | M9: 260000 | Q9: 1
A10: 4 | B10: ХЁАТ "Ориент Финанс банк" | C10: 207086151 | D10: 96120 | E10: 840 | F10: 4 | G10: =SUM(H10:M10) -> 157153800 | L10: 157153800 | Q10: 1
A11: 5 | G11: =SUM(H11:M11) -> 0
A12: 6 | G12: =SUM(H12:M12) -> 0
A13: 7 | G13: =SUM(H13:M13) -> 0
A14: 8 | G14: =SUM(H14:M14) -> 0
A15: 9 | G15: =SUM(H15:M15) -> 0
A16: 10 | G16: =SUM(H16:M16) -> 0
A17: 11 | G17: =SUM(H17:M17) -> 0
A18: 12 | G18: =SUM(H18:M18) -> 0
A19: 13 | G19: =SUM(H19:M19) -> 0
A20: 14 | G20: =SUM(H20:M20) -> 0
A21: 15 | G21: =SUM(H21:M21) -> 0
A22: 16 | G22: =SUM(H22:M22) -> 0
... A66: 60 | G66: =SUM(H66:M66) -> 0
B67: ИТОГО КРУПНЫХ АКТИВОВ | G67: =SUM(G7:G66) -> 1026953903 | H67: =SUM(H7:H66) -> 764042380 | I67: =SUM(I7:I66) -> 0 | J67: =SUM(J7:J66) -> 0 | K67: =SUM(K7:K66) -> 104769200 | L67: =SUM(L7:L66) -> 157153800 | M67: =SUM(M7:M66) -> 988523 | P67: =SUM(P7:P66) -> 216400000
B68: САМЫЙ КРУПНЫЙ АКТИВ, ВЫДАННЫЙ БАНКОМ | G68: =MAX(G7:G66) -> 455250911 | H68: =MAX(H7:H66) -> 349753188 | I68: =MAX(I7:I66) -> 0 | J68: =MAX(J7:J66) -> 0 | K68: =MAX(K7:K66) -> 104769200 | L68: =MAX(L7:L66) -> 157153800 | M68: =MAX(M7:M66) -> 728523 | P68: =MAX(P7:P66) -> 216400000
B71: Подпись Председателя правления:
B73: Подпись Главного Бухгалтера:

Sheet Charge-offs and Recoveries
A1: ОТЧЕТ О CПИСАННЫХ И ВОЗВРАЩЕННЫХ ПЛАТЕЖАХ ИЗ РЕЗЕРВА ВОЗМОЖНЫХ ПОТЕРЬ ПО КРЕДИТАМ И ЛИЗИНГУ | E1: Таблица-13
A3: Часть 1 Списания и возврат | B3: =+'Asset quality'!B3 -> АК "Алокабанк" | E3: =+'Asset quality'!P3 -> 44196
A4: Отрасль экономики | B4: Списание - А | D4: Возврат - Б
B5: Всего | C5: в иностранной валюте | D5: Всего | E5: в иностранной валюте
A6: А | B6: Б | C6: В | D6: Г | E6: Д
A7: 1. Промышленность | B7: 478318 | C7: 0 | D7: 0 | E7: 0
A8: 2. Сельское хозяйство | B8: 0 | C8: 0 | D8: 5408 | E8: 0
A9: 3. Транспорт и коммуникации | B9: 0 | C9: 0 | D9: 0 | E9: 0
A10: 4. Строительство | B10: 0 | C10: 0 | D10: 0 | E10: 0
A11: 5. Торговля и общественное питание | B11: 0 | C11: 0 | D11: 995325 | E11: 0
A12: 6. Материально-техническое снабжение и сбыт | B12: 0 | C12: 0 | D12: 0 | E12: 0
A13: 7. Жилищно-коммунальные услуги | B13: 181207 | C13: 0 | D13: 0 | E13: 0
A14: 8. Другие сектора | B14: 3424292 | C14: 0 | D14: 40235 | E14: 0
A15: 9. Итого | B15: =SUM(B7:B14) -> 4083817 | C15: =SUM(C7:C14) -> 0 | D15: =SUM(D7:D14) -> 1040968 | E15: =SUM(E7:E14) -> 0
A18: Часть 2
A19: Изменения в резерве возможных убытков по кредитам и лизингу
A20: 1. Остаток на начало текущего года | C20: 8904825
A21: 2. Плюс: Возвращенные платежи | C21: =D15 -> 1040968
A22: 3. Минус: Списанные кредиты и лизинги | B22: 0 | C22: =B15 -> 4083817
A23: 4. Отчисления в резерв по состоянию на дату от начала года | C23: 12410997
A24: 5. Поправки | C24: -9195805
A25: 6. Текущий баланс | C25: =SUM(C20:C21)-C22+SUM(C23:C24) -> 9077168 | F25: =+'Asset Classification'!Y50 -> 9077168
A28: Подпись Председателя правления:
A30: Подпись Главного Бухгалтера:

Sheet loans_av rate
A1: ДАННЫЕ О СРЕДНЕВЗВЕШЕННЫХ ПРОЦЕНТНЫХ СТАВКАХ ПО КРЕДИТАМ | H1: Таблица-20
B3: =+'Asset quality'!B3 -> АК "Алокабанк" | F3: =+'Asset quality'!P3 -> 44196 | H3: тыс. сум
A4: № | B4: Виды кредитования | C4: всего | E4: в том числе
E5: в национальный валюте | G5: в иностранной валюте
C6: остаток всего | D6: средневзвешенные процентные ставки | E6: остаток всего | F6: средневзвешенные процентные ставки | G6: остаток всего | H6: средневзвешенные процентные ставки
B7: А | C7: Б | D7: В | E7: Г | F7: Д | G7: Е | H7: Ж
A8: 1 | B8: Физические лица (льготные кредиты) | C8: =SUM(C10:C14) -> 202869977 | D8: =IFERROR(((C10*D10)/C8)+((C11*D11)/C8)+((C12*D12)/C8)+((C13*D13)/C8)+((C14*D14)/C8),0) -> 0.10960682 | E8: =SUM(E10:E14) -> 202869977 | F8: =IFERROR(((E10*F10)/E8)+((E11*F11)/E8)+((E12*F12)/E8)+((E13*F13)/E8)+((E14*F14)/E8),0) -> 0.10960682 | G8: =SUM(G10:G14) -> 0 | H8: =IFERROR(((G10*H10)/G8)+((G11*H11)/G8)+((G12*H12)/G8)+((G13*H13)/G8)+((G14*H14)/G8),0) -> 0 | J8: =+C8+C16+C24+C33 -> 5705936821 | K8: =+E8+E16+E24+E33 -> 3786450485 | L8: =+G8+G16+G24+G33 -> 1919486336
B9: в том числе | J9: =+'loans type'!C8 -> 5705936821 | K9: =+'loans type'!E8 -> 3786450485 | L9: =+'loans type'!G8 -> 1919486336
A10: 1.1. | B10: ипотечный кредит | C10: =+E10+G10 -> 124357836 | D10: 0.13414024 | E10: 124357836 | F10: 0.13414024 | G10: 0 | H10: 0 | J10: =+J8-J9 -> 0 | K10: =+K8-K9 -> 0 | L10: =+L8-L9 -> 0
A11: 1.2. | B11: автокредит | C11: =+E11+G11 -> 294435 | D11: 0.14269329 | E11: 294435 | F11: 0.14269329 | G11: 0 | H11: 0
A12: 1.3. | B12: микрозайм (все нецелевые кредиты) | C12: =+E12+G12 -> 57322 | D12: 0.14416116 | E12: 57322 | F12: 0.14416116 | G12: 0 | H12: 0
A13: 1.4. | B13: потребительские кредиты | C13: =+E13+G13 -> 17238816 | D13: 0.0026067431 | E13: 17238816 | F13: 0.0026067431 | G13: 0 | H13: 0
A14: 1.5. | B14: другие кредиты физическим лицам | C14: =+E14+G14 -> 60921568 | D14: 0.08961242 | E14: 60921568 | F14: 0.08961242 | G14: 0 | H14: 0
A16: 2 | B16: Физические лица (коммерческие кредиты) | C16: =SUM(C18:C22) -> 819530208 | D16: =IFERROR(((C18*D18)/C16)+((C19*D19)/C16)+((C20*D20)/C16)+((C21*D21)/C16)+((C22*D22)/C16),0) -> 0.21887059 | E16: =SUM(E18:E22) -> 819530208 | F16: =IFERROR(((E18*F18)/E16)+((E19*F19)/E16)+((E20*F20)/E16)+((E21*F21)/E16)+((E22*F22)/E16),0) -> 0.21887059 | G16: =SUM(G18:G22) -> 0 | H16: =IFERROR(((G18*H18)/G16)+((G19*H19)/G16)+((G20*H20)/G16)+((G21*H21)/G16)+((G22*H22)/G16),0) -> 0
B17: в том числе
A18: 2.1. | B18: ипотечный кредит | C18: =+E18+G18 -> 248824226 | D18: 0.18635999 | E18: 248824226 | F18: 0.18635999 | G18: 0 | H18: 0
A19: 2.2. | B19: автокредит | C19: =+E19+G19 -> 336936414 | D19: 0.22095799 | E19: 336936414 | F19: 0.22095799 | G19: 0 | H19: 0
A20: 2.3. | B20: микрозайм (все нецелевые кредиты) | C20: =+E20+G20 -> 171704122 | D20: 0.24536909 | E20: 171704122 | F20: 0.24536909 | G20: 0 | H20: 0
A21: 2.4. | B21: потребительские кредиты | C21: =+E21+G21 -> 60017660 | D21: 0.26690586 | E21: 60017660 | F21: 0.26690586 | G21: 0 | H21: 0
A22: 2.5. | B22: другие кредиты физическим лицам | C22: =+E22+G22 -> 2047786 | D22: 0.19603488 | E22: 2047786 | F22: 0.19603488 | G22: 0 | H22: 0
A24: 3 | B24: Юридические лица (льготные кредиты) | C24: =SUM(C26:C31) -> 965096577 | D24: =IFERROR(((C26*D26)/C24)+((C27*D27)/C24)+((C28*D28)/C24)+((C29*D29)/C24)+((C30*D30)/C24)+((C31*D31)/C24),0) -> 0.092275833 | E24: =SUM(E26:E31) -> 665781293 | F24: =IFERROR(((E26*F26)/E24)+((E27*F27)/E24)+((E28*F28)/E24)+((E29*F29)/E24)+((E30*F30)/E24)+((E31*F31)/E24),0) -> 0.11120043 | G24: =SUM(G26:G31) -> 299315284 | H24: =IFERROR(((G26*H26)/G24)+((G27*H27)/G24)+((G28*H28)/G24)+((G29*H29)/G24)+((G30*H30)/G24)+((G31*H31)/G24),0) -> 0.050180943
B25: в том числе
A26: 3.1. | B26: микрокредит | C26: =+E26+G26 -> 29729185 | D26: =(E26*F26+G26*H26)/(E26+G26) -> 0.096802166 | E26: 29729185 | F26: 0.096802166 | G26: 0 | H26: 0
A27: 3.2. | B27: синдицированные кредит | C27: =+E27+G27 -> 0 | D27: 0 | E27: 0 | F27: 0 | G27: 0 | H27: 0
A28: 3.3. | B28: лизинг | C28: =+E28+G28 -> 639526 | D28: =(E28*F28+G28*H28)/(E28+G28) -> 0.10999004 | E28: 639526 | F28: 0.10999004 | G28: 0 | H28: 0
A29: 3.4. | B29: факторинг | C29: =+E29+G29 -> 0 | D29: 0 | E29: 0 | F29: 0 | G29: 0 | H29: 0
A30: 3.5. | B30: межбанковский кредит | C30: =+E30+G30 -> 0 | D30: 0 | E30: 0 | F30: 0 | G30: 0 | H30: 0
A31: 3.6. | B31: другие кредиты юридическим лицам | C31: =+E31+G31 -> 934727866 | D31: =(E31*F31+G31*H31)/(E31+G31) -> 0.092119752 | E31: 635412582 | F31: 0.1118753 | G31: 299315284 | H31: 0.050180943
A33: 4 | B33: Юридические лица (коммерческие кредиты) | C33: =SUM(C35:C40) -> 3718440059 | D33: =IFERROR(((C35*D35)/C33)+((C36*D39)/C33)+((C37*D37)/C33)+((C38*D38)/C33)+((C39*#REF!)/C33)+((C40*D40)/C33),0) -> 0 | E33: =SUM(E35:E40) -> 2098269007 | F33: =IFERROR(((E35*F35)/E33)+((E36*F36)/E33)+((E37*F37)/E33)+((E38*F38)/E33)+((E39*F39)/E33)+((E40*F40)/E33),0) -> 0.20137566 | G33: =SUM(G35:G40) -> 1620171052 | H33: =IFERROR(((G35*H35)/G33)+((G36*H36)/G33)+((G37*H37)/G33)+((G38*H38)/G33)+((G39*H39)/G33)+((G40*H40)/G33),0) -> 0.083863574
B34: в том числе
A35: 4.1. | B35: микрокредит | C35: =+E35+G35 -> 139806869 | D35: =(E35*F35+G35*H35)/(E35+G35) -> 0.21700161 | E35: 137923210 | F35: 0.21857771 | G35: 1883659 | H35: 0.10159778
A36: 4.2. | B36: синдицированные кредит | C36: =+E36+G36 -> 0 | D36: 0 | E36: 0 | F36: 0 | G36: 0 | H36: 0
A37: 4.3. | B37: лизинг | C37: =+E37+G37 -> 0 | D37: 0 | E37: 0 | F37: 0 | G37: 0 | H37: 0
A38: 4.4. | B38: факторинг | C38: =+E38+G38 -> 0 | D38: 0 | E38: 0 | F38: 0 | G38: 0 | H38: 0
A39: 4.5. | B39: межбанковский кредит | C39: =+E39+G39 -> 0 | D39: 0 | E39: 0 | F39: 0 | G39: 0 | H39: 0
A40: 4.6. | B40: другие кредиты юридическим лицам | C40: =+E40+G40 -> 3578633190 | D40: =(E40*F40+G40*H40)/(E40+G40) -> 0.14756341 | E40: 1960345797 | F40: 0.20016538 | G40: 1618287393 | H40: 0.083842931
B43: Подпись Председателя правления:
B45: Подпись Главного Бухгалтера:
B47: Всего | C47: =+C8+C16+C24+C33 -> 5705936821 | E47: =+E8+E16+E24+E33 -> 3786450485 | G47: =+G8+G16+G24+G33 -> 1919486336
C48: =+C50+C54 -> 5705936821 | E48: =+E9+E17+E25+E34 -> 0 | G48: =+G50+G54 -> 1919486336
B50: Физлица | C50: =+'Asset Classification'!C12 -> 1022400185 | G50: =+'Asset Classification'!D12 -> 0
C51: =C8+C16 -> 1022400185 | G51: =G8+G16 -> 0
C52: =+C50-C51 -> 0 | G52: =+G50-G51 -> 0
B54: Юрзлица | C54: =+'Asset Classification'!C30-'Asset Classification'!C12 -> 4683536636 | G54: =+'Asset Classification'!D30-'Asset Classification'!D12 -> 1919486336
C55: =C24+C33 -> 4683536636 | G55: =G24+G33 -> 1919486336
C56: =+C54-C55 -> 0 | G56: =+G54-G55 -> 0

Sheet loans type
Z1: Таблица-20 А
A2: Информация о структуре кредитного портфеля
B3: =+'Asset quality'!B3 -> АК "Алокабанк" | V3: =+'Asset quality'!P3 -> 44196 | Z3: тыс. сум
A4: № | B4: Виды кредитования | C4: всего | I4: Сроки | N4: Категория качества | S4: Резерв на возможные потери | Y4: Списанные на внебаланс | Z4: Реструктуризи-рованные кредиты
I5: до 1 года | J5: От 1 до 5 лет | K5: От 5 до 10 лет | L5: От 10 до 15 лет | M5: Свыше 15 лет | S5: итого | T5: по категориям качества
C6: Остаток | D6: средневзвешенные % ставки | E6: в нацвалюте | F6: средневзвешенные % ставки | G6: в инвалюте | H6: средневзвешенные % ставки | N6: I | O6: II | P6: III | Q6: IV | R6: V | T6: I | U6: II | V6: III | W6: IV | X6: V | AB6: I | AC6: II | AD6: III | AE6: IV | AF6: V
B7: А | C7: Б | D7: В | E7: Г | F7: Д | G7: Е | H7: Ж | I7: З | J7: И | K7: К | L7: Л | M7: М | N7: Н | O7: О | P7: П | Q7: Р | R7: С | S7: Т | T7: У | U7: Ф | V7: Х | W7: Ц | X7: Ч | Y7: Ш | Z7: Щ
B8: ВСЕГО | C8: =+C9+C25 -> 5705936821 | D8: =IFERROR(((C9*D9)/C8)+((C25*D25)/C8),0) -> 0.041162238 | E8: =+E9+E25 -> 3786450485 | F8: =IFERROR(((E9*F9)/E8)+((E25*F25)/E8),0) -> 0.18440155 | G8: =+G9+G25 -> 1919486336 | H8: =IFERROR(((G9*H9)/G8)+((G25*H25)/G8),0) -> 0.078611269 | I8: =+I9+I25 -> 607080505 | J8: =+J9+J25 -> 2690424936 | K8: =+K9+K25 -> 2135130269 | L8: =+L9+L25 -> 195641003 | M8: =+M9+M25 -> 77660108 | N8: =+N9+N25 -> 5607381631 | O8: =+O9+O25 -> 92173584 | P8: =+P9+P25 -> 3580002 | ... Z8: =+Z9+Z25 -> 103020262 | AA8: =+'Loans Receivable'!C92 -> 5705936821 | AB8: =+'Asset Classification'!G30 -> 61332691 | AC8: =+'Asset Classification'!K30 -> 6889806 | AD8: =+'Asset Classification'!O50 -> 1047131 | AE8: =+'Asset Classification'!S50 -> 569578 | AF8: =+'Asset Classification'!W50 -> 570653
A9: I | B9: Физические лица | C9: =+C11+C16+C21+C22+C24 -> 1022400185 | D9: =IFERROR(((C11*D11)/C9)+((C16*D16)/C9)+((C21*D21)/C9)+((C22*D22)/C9)+((C24*D24)/C9),0) -> 0.19723486 | E9: =+E11+E16+E21+E22+E24 -> 1022400185 | F9: =IFERROR(((E11*F11)/E9)+((E16*F16)/E9)+((E21*F21)/E9)+((E22*F22)/E9)+((E24*F24)/E9),0) -> 0.19723486 | G9: =+G11+G16+G21+G22+G24 -> 0 | H9: =IFERROR(((G11*H11)/G9)+((G16*H16)/G9)+((G21*H21)/G9)+((G22*H22)/G9)+((G24*H24)/G9),0) -> 0 | I9: =+I11+I16+I21+I22+I24 -> 148332396 | J9: =+J11+J16+J21+J22+J24 -> 500964992 | K9: =+K11+K16+K21+K22+K24 -> 180313608 | L9: =+L11+L16+L21+L22+L24 -> 142536048 | M9: =+M11+M16+M21+M22+M24 -> 50253141 | N9: =+N11+N16+N21+N22+N24 -> 1013972859 | O9: =+O11+O16+O21+O22+O24 -> 3431795 | P9: =+P11+P16+P21+P22+P24 -> 2193927 | ... Z9: =+Z11+Z16+Z21+Z22+Z24 -> 0 | AA9: =+'Loans Receivable'!C80 -> 1022400185 | AB9: =+'Asset Classification'!E30 -> 5607381631 | AC9: =+'Asset Classification'!I30 -> 92173584 | AD9: =+'Asset Classification'!M30 -> 3580002 | AE9: =+'Asset Classification'!Q30 -> 1457838 | AF9: =+'Asset Classification'!U30 -> 1343766
B10: в том числе | AB10: =+N8-AB9 -> 0 | AC10: =+O8-AC9 -> 0 | AD10: =+P8-AD9 -> 0 | AE10: =+Q8-AE9 -> 0 | AF10: =+R8-AF9 -> 0
A11: 1 | B11: Ипотечные кредиты (льготные) в том числе: | C11: =SUM(C12:C15) -> 124357836 | D11: =IFERROR(((C12*D12)/C11)+((C13*D13)/C11)+((C14*D14)/C11)+((C15*D15)/C11),0) -> 0.13414024 | E11: =SUM(E12:E15) -> 124357836 | F11: =IFERROR(((E12*F12)/E11)+((E13*F13)/E11)+((E14*F14)/E11)+((E15*F15)/E11),0) -> 0.13414024 | G11: =SUM(G12:G15) -> 0 | H11: =IFERROR(((G12*H12)/G11)+((G13*H13)/G11)+((G14*H14)/G11)+((G15*H15)/G11),0) -> 0 | I11: =SUM(I12:I15) -> 0 | J11: =SUM(J12:J15) -> 0 | K11: =SUM(K12:K15) -> 12968275 | L11: =SUM(L12:L15) -> 82544210 | M11: =SUM(M12:M15) -> 28845351 | N11: =SUM(N12:N15) -> 123601727 | O11: =SUM(O12:O15) -> 525395 | P11: =SUM(P12:P15) -> 230714 | ... Z11: =SUM(Z12:Z15) -> 0 | AA11: =+'loans_av rate'!C10 -> 124357836 | AB11: =+'loans_av rate'!E10 -> 124357836 | AC11: =+'loans_av rate'!G10 -> 0
A12: 1.1. | B12: на приобретение недвижимого имущества | C12: =+E12+G12 -> 123210582 | D12: 0.13428878 | E12: 123210582 | F12: 0.13428878 | G12: 0 | H12: 0 | I12: 0 | J12: 0 | K12: 12611963 | L12: 81980924 | M12: 28617695 | N12: 122454473 | O12: 525395 | P12: 230714 | Q12: 0 | R12: 0 | S12: =SUM(T12:X12) -> 1399849 | T12: 1324381 | U12: 19275 | V12: 56193 | W12: 0 | X12: 0
A13: 1.2. | B13: на ремонт недвижимого имущества | C13: =+E13+G13 -> 0 | D13: 0 | E13: 0 | F13: 0 | G13: 0 | H13: 0 | I13: 0 | J13: 0 | K13: 0 | L13: 0 | M13: 0 | N13: 0 | O13: 0 | P13: 0 | Q13: 0 | R13: 0 | S13: =SUM(T13:X13) -> 0 | T13: 0 | U13: 0 | V13: 0 | W13: 0 | X13: 0 | Y13: 0 | Z13: 0
A14: 1.3. | B14: на реконструкцию недвижимого имущества | C14: =+E14+G14 -> 540997 | D14: 0.12834675 | E14: 540997 | F14: 0.12834675 | G14: 0 | H14: 0 | I14: 0 | J14: 0 | K14: 335886 | L14: 103776 | M14: 101335 | N14: 540997 | O14: 0 | P14: 0 | Q14: 0 | R14: 0 | S14: =SUM(T14:X14) -> 5815 | T14: 5815 | U14: 0 | V14: 0 | W14: 0 | X14: 0 | Y14: 0 | Z14: 0
A15: 1.4. | B15: на строительство недвижимого имущества | C15: =+E15+G15 -> 606257 | D15: 0.10912118 | E15: 606257 | F15: 0.10912118 | G15: 0 | H15: 0 | I15: 0 | J15: 0 | K15: 20426 | L15: 459510 | M15: 126321 | N15: 606257 | O15: 0 | P15: 0 | Q15: 0 | R15: 0 | S15: =SUM(T15:X15) -> 6517 | T15: 6517 | U15: 0 | V15: 0 | W15: 0 | X15: 0 | Y15: 0 | Z15: 0
A16: 2 | B16: Ипотечные кредиты (коммерческие) в том числе: | C16: =SUM(C17:C20) -> 248824226 | D16: =IFERROR(((C17*D17)/C16)+((C18*D18)/C16)+((C19*D19)/C16)+((C20*D20)/C16),0) -> 0.18635999 | E16: =SUM(E17:E20) -> 248824226 | F16: =IFERROR(((E17*F17)/E16)+((E18*F18)/E16)+((E19*F19)/E16)+((E20*F20)/E16),0) -> 0.18635999 | G16: =SUM(G17:G20) -> 0 | H16: =IFERROR(((G17*H17)/G16)+((G18*H18)/G16)+((G19*H19)/G16)+((G20*H20)/G16),0) -> 0 | I16: =SUM(I17:I20) -> 0 | J16: =SUM(J17:J20) -> 2634957 | K16: =SUM(K17:K20) -> 165869407 | L16: =SUM(L17:L20) -> 58912072 | M16: =SUM(M17:M20) -> 21407790 | N16: =SUM(N17:N20) -> 247439432 | O16: =SUM(O17:O20) -> 950460 | P16: =SUM(P17:P20) -> 34879 | ... Z16: =SUM(Z17:Z20) -> 0 | AA16: =+'loans_av rate'!C18 -> 248824226 | AB16: =+'loans_av rate'!E18 -> 248824226 | AC16: =+'loans_av rate'!G18 -> 0
A17: 2.1. | B17: на приобретение недвижимого имущества | C17: =+E17+G17 -> 248102877 | D17: 0.18631315 | E17: 248102877 | F17: 0.18631315 | G17: 0 | H17: 0 | I17: 0 | J17: 2634957 | K17: 165225683 | L17: 58834447 | M17: 21407790 | N17: 246718083 | O17: 950460 | P17: 34879 | Q17: 127763 | R17: 271692 | S17: =SUM(T17:X17) -> 2825138 | T17: 2666839 | U17: 141132 | V17: 0 | W17: 17167 | X17: 0 | Y17: 0 | Z17: 0
A18: 2.2. | B18: на ремонт недвижимого имущества | C18: =+E18+G18 -> 0 | D18: 0 | E18: 0 | F18: 0 | G18: 0 | H18: 0 | I18: 0 | J18: 0 | K18: 0 | L18: 0 | M18: 0 | N18: 0 | O18: 0 | P18: 0 | Q18: 0 | R18: 0 | S18: =SUM(T18:X18) -> 0 | T18: 0 | U18: 0 | V18: 0 | W18: 0 | X18: 0 | Y18: 0 | Z18: 0
A19: 2.3. | B19: на реконструкцию недвижимого имущества | C19: =+E19+G19 -> 468015 | D19: 0.19972215 | E19: 468015 | F19: 0.19972215 | G19: 0 | H19: 0 | I19: 0 | J19: 0 | K19: 390390 | L19: 77625 | M19: 0 | N19: 468015 | O19: 0 | P19: 0 | Q19: 0 | R19: 0 | S19: =SUM(T19:X19) -> 5031 | T19: 5031 | U19: 0 | V19: 0 | W19: 0 | X19: 0 | Y19: 0 | Z19: 0
A20: 2.4. | B20: на строительство недвижимого имущества | C20: =+E20+G20 -> 253334 | D20: 0.20754869 | E20: 253334 | F20: 0.20754869 | G20: 0 | H20: 0 | I20: 0 | J20: 0 | K20: 253334 | L20: 0 | M20: 0 | N20: 253334 | O20: 0 | P20: 0 | Q20: 0 | R20: 0 | S20: =SUM(T20:X20) -> 2723 | T20: 2723 | U20: 0 | V20: 0 | W20: 0 | X20: 0 | Y20: 0 | Z20: 0
A21: 3 | B21: микрозайм (все нецелевые кредиты) | C21: =+E21+G21 -> 171761444 | D21: 0.24534354 | E21: 171761444 | F21: 0.24534354 | G21: 0 | H21: 0 | I21: 127792764 | J21: 43917032 | K21: 51648 | L21: 0 | M21: 0 | N21: 171435947 | O21: 97364 | P21: 9052 | Q21: 115563 | R21: 103518 | S21: =SUM(T21:X21) -> 2012524 | T21: 1842991 | U21: 31601 | V21: 1062 | W21: 63215 | X21: 73655 | Y21: 0 | Z21: 0 | AA21: =+'loans_av rate'!C12+'loans_av rate'!C20 -> 171761444 | AB21: =+'loans_av rate'!E12+'loans_av rate'!E20 -> 171761444 | AC21: =+'loans_av rate'!G12+'loans_av rate'!G20 -> 0
A22: 4 | B22: потребительские кредиты | C22: =+E22+G22 -> 414487325 | D22: 0.21847425 | E22: 414487325 | F22: 0.21847425 | G22: 0 | H22: 0 | I22: 20171299 | J22: 394069366 | K22: 246660 | L22: 0 | M22: 0 | N22: 411035185 | O22: 1180183 | P22: 1026002 | Q22: 603549 | R22: 642406 | S22: =SUM(T22:X22) -> 5294825 | T22: 4455294 | U22: 279071 | V22: 59591 | W22: 239628 | X22: 261241 | Y22: 41559.149 | Z22: 0 | AA22: =+'loans_av rate'!C11+'loans_av rate'!C13+'loans_av rate'!C19+'loans_av rate'!C21 -> 414487325 | AB22: =+'loans_av rate'!E11+'loans_av rate'!E13+'loans_av rate'!E19+'loans_av rate'!E21 -> 414487325
A23: 4.1. | B23: из них на приобретения автомобиля | C23: =+E23+G23 -> 337230849 | D23: 0.22088965 | E23: 337230849 | F23: 0.22088965 | G23: 0 | H23: 0 | I23: 1920439 | J23: 335310410 | K23: 0 | L23: 0 | M23: 0 | N23: 334591316 | O23: 1042009 | P23: 985000 | Q23: 242446 | R23: 370078 | S23: =SUM(T23:X23) -> 4067631 | T23: 3624870 | U23: 177239 | V23: 50131 | W23: 67942 | X23: 147449 | Y23: 41559.149 | Z23: 0 | AA23: =+'loans_av rate'!C11+'loans_av rate'!C19 -> 337230849 | AB23: =+'loans_av rate'!E11+'loans_av rate'!E19 -> 337230849 | AC23: =+'loans_av rate'!G11+'loans_av rate'!G19 -> 0
A24: 5 | B24: другие кредиты физическим лицам | C24: =+E24+G24 -> 62969354 | D24: 0.093780893 | E24: 62969354 | F24: 0.093780893 | G24: 0 | H24: 0 | I24: 368333 | J24: 60343637 | K24: 1177618 | L24: 1079766 | M24: 0 | N24: 60460568 | O24: 678393 | P24: 893280 | Q24: 610963 | R24: 326150 | S24: =SUM(T24:X24) -> 1885792 | T24: 781091 | U24: 265586 | V24: 353790 | W24: 249568 | X24: 235757 | Y24: 159954.6 | Z24: 0 | AA24: =+'loans_av rate'!C14+'loans_av rate'!C22 -> 62969354 | AB24: =+'loans_av rate'!E14+'loans_av rate'!E22 -> 62969354
A25: II | B25: Юридические лица | C25: =+C26 -> 4683536636 | D25: =IFERROR(((C27*D27)/C25)+((C28*D28)/C25)+((C29*D29)/C25)+((C30*D30)/C25)+((C31*D31)/C25)+((C32*D32)/C25),0) -> 0.0070921116 | E25: =+E26 -> 2764050300 | F25: =IFERROR(((E27*F27)/E25)+((E28*F28)/E25)+((E29*F29)/E25)+((E30*F30)/E25)+((E31*F31)/E25)+((E32*F32)/E25),0) -> 0.17965461 | G25: =+G26 -> 1919486336 | H25: =IFERROR(((G27*H27)/G25)+((G28*H28)/G25)+((G29*H29)/G25)+((G30*H30)/G25)+((G31*H31)/G25)+((G32*H32)/G25),0) -> 0.078611269 | I25: =+I26 -> 458748109 | J25: =+J26 -> 2189459944 | K25: =+K26 -> 1954816661 | L25: =+L26 -> 53104955 | M25: =+M26 -> 27406967 | N25: =+N26 -> 4593408772 | O25: =+O26 -> 88741789 | P25: =+P26 -> 1386075 | ... Z25: =+Z26 -> 103020262 | AA25: =+'loans_av rate'!C24+'loans_av rate'!C33 -> 4683536636 | AB25: =+'loans_av rate'!E24+'loans_av rate'!E33 -> 2764050300 | AC25: =+'loans_av rate'!G24+'loans_av rate'!G33 -> 1919486336
B26: в том числе по видам кредитования | C26: =SUM(C27:C32) -> 4683536636 | D26: =IFERROR(((C28*D28)/C26)+((C29*D29)/C26)+((C30*D30)/C26)+((C31*D31)/C26)+((C32*D32)/C26),0) -> 0 | E26: =SUM(E27:E32) -> 2764050300 | F26: =IFERROR(((E28*F28)/E26)+((E29*F29)/E26)+((E30*F30)/E26)+((E31*F31)/E26)+((E32*F32)/E26),0) -> 0.16770664 | G26: =SUM(G27:G32) -> 1919486336 | H26: =IFERROR(((G28*H28)/G26)+((G29*H29)/G26)+((G30*H30)/G26)+((G31*H31)/G26)+((G32*H32)/G26),0) -> 0.078511568 | I26: =SUM(I27:I32) -> 458748109 | J26: =SUM(J27:J32) -> 2189459944 | K26: =SUM(K27:K32) -> 1954816661 | L26: =SUM(L27:L32) -> 53104955 | M26: =SUM(M27:M32) -> 27406967 | N26: =SUM(N27:N32) -> 4593408772 | O26: =SUM(O27:O32) -> 88741789 | P26: =SUM(P27:P32) -> 1386075 | ... Z26: =SUM(Z27:Z32) -> 103020262
A27: 1 | B27: микрокредит | C27: =+E27+G27 -> 169536054 | D27: =(E27*F27+G27*H27)/(E27+G27) -> 0.1959239 | E27: 167652395 | F27: 0.1969837 | G27: 1883659 | H27: 0.10159778 | I27: 32209080 | J27: 120289712 | K27: 11561212 | L27: 5476050 | M27: 0 | N27: 162990006 | O27: 6459973 | P27: 86075 | S27: =SUM(T27:X27) -> 2781372 | T27: 1822330 | U27: 932547 | V27: 26495 | AA27: =+'loans_av rate'!C26+'loans_av rate'!C35 -> 169536054 | AB27: =+'loans_av rate'!E26+'loans_av rate'!E35 -> 167652395 | AC27: =+'loans_av rate'!G26+'loans_av rate'!G35 -> 1883659
A28: 2 | B28: синдицированные кредит | C28: =+E28+G28 -> 0 | S28: =SUM(T28:X28) -> 0 | T28: 0 | AA28: =+'loans_av rate'!C27+'loans_av rate'!C36 -> 0 | AB28: =+'loans_av rate'!E27+'loans_av rate'!E36 -> 0 | AC28: =+'loans_av rate'!G27+'loans_av rate'!G36 -> 0
A29: 3 | B29: лизинг | C29: =+E29+G29 -> 639526 | E29: 639526 | F29: 0.10999004 | G29: 0 | I29: 0 | J29: 0 | K29: 639526 | L29: 0 | M29: 0 | N29: 639526 | O29: 0 | P29: 0 | S29: =SUM(T29:X29) -> 6874 | T29: 6874 | AA29: =+'loans_av rate'!C28+'loans_av rate'!C37 -> 639526 | AB29: =+'loans_av rate'!E28+'loans_av rate'!E37 -> 639526 | AC29: =+'loans_av rate'!G28+'loans_av rate'!G37 -> 0
A30: 4 | B30: факторинг | C30: =+E30+G30 -> 0 | S30: =SUM(T30:X30) -> 0 | T30: 0 | AA30: =+'loans_av rate'!C29+'loans_av rate'!C38 -> 0 | AB30: =+'loans_av rate'!E29+'loans_av rate'!E38 -> 0 | AC30: =+'loans_av rate'!G29+'loans_av rate'!G38 -> 0
A31: 5 | B31: межбанковский кредит | C31: =+E31+G31 -> 0 | S31: =SUM(T31:X31) -> 0 | T31: 0 | AA31: =+'loans_av rate'!C30+'loans_av rate'!C39 -> 0 | AB31: =+'loans_av rate'!E30+'loans_av rate'!E39 -> 0 | AC31: =+'loans_av rate'!G30+'loans_av rate'!G39 -> 0
A32: 6 | B32: другие виды кредитования | C32: =+E32+G32 -> 4513361056 | E32: 2595758379 | F32: 0.17855254 | G32: 1917602677 | H32: 0.07858869 | I32: 426539029 | J32: 2069170232 | K32: 1942615923 | L32: 47628905 | M32: 27406967 | N32: 4429779240 | O32: 82281816 | P32: 1300000 | S32: =SUM(T32:X32) -> 54183399 | T32: 48412805 | U32: 5220594 | V32: 550000 | Y32: 743185 | Z32: 103020262 | AA32: =+'loans_av rate'!C31+'loans_av rate'!C40 -> 4513361056 | AB32: =+'loans_av rate'!E31+'loans_av rate'!E40 -> 2595758379 | AC32: =+'loans_av rate'!G31+'loans_av rate'!G40 -> 1917602677
B33: в том числе по цели кредитования | C33: =SUM(C34:C39) -> 4683536636 | D33: =IFERROR(((C35*D35)/C33)+((C36*D36)/C33)+((C37*D37)/C33)+((C38*D38)/C33)+((C39*D39)/C33),0) -> 0 | E33: =SUM(E34:E39) -> 2764050300 | F33: =IFERROR(((E35*F35)/E33)+((E36*F36)/E33)+((E37*F37)/E33)+((E38*F38)/E33)+((E39*F39)/E33),0) -> 0.17615119 | G33: =SUM(G34:G39) -> 1919486336 | H33: =IFERROR(((G35*H35)/G33)+((G36*H36)/G33)+((G37*H37)/G33)+((G38*H38)/G33)+((G39*H39)/G33),0) -> 0.078611269 | I33: =SUM(I34:I39) -> 458748109 | J33: =SUM(J34:J39) -> 2189459944 | K33: =SUM(K34:K39) -> 1954816661 | L33: =SUM(L34:L39) -> 53104955 | M33: =SUM(M34:M39) -> 27406967 | N33: =SUM(N34:N39) -> 4593408772 | O33: =SUM(O34:O39) -> 88741789 | P33: =SUM(P34:P39) -> 1386075 | ... Z33: =SUM(Z34:Z39) -> 103020262
A34: 1 | B34: кредиты, выданные на формирование стартового капитала | C34: =+E34+G34 -> 48869627 | E34: 48869627 | F34: 0.19813747 | I34: 24531160 | J34: 21767171 | K34: 2571296 | L34: 0 | M34: 0 | N34: 48869627 | S34: =SUM(T34:X34) -> 4113234 | T34: 525302 | U34: 3587932 | V34: 0
A35: 2 | B35: кредиты на пополнение оборотных средств | C35: =+E35+G35 -> 488796205 | E35: 379492543 | F35: 0.21339654 | G35: 109303662 | H35: 0.078137265 | I35: 329549486 | J35: 158657171 | K35: 234428 | L35: 355120 | M35: 0 | N35: 484111674 | O35: 4647820 | P35: 36711 | S35: =SUM(T35:X35) -> 5755944 | T35: 5254090 | U35: 475359 | V35: 26495 | Z35: 16280000
A36: 3 | B36: кредиты, выданные на приобретение, модернизацию или приватизацию основных средств | C36: =+E36+G36 -> 2593489119 | E36: 1590469514 | F36: 0.17829747 | G36: 1003019605 | H36: 0.086639174 | I36: 58436093 | J36: 1332320442 | K36: 1181712546 | L36: 16518093 | M36: 4501945 | N36: 2530456738 | O36: 62983017 | P36: 49364 | S36: =SUM(T36:X36) -> 27877519 | T36: 27877519 | Z36: 80880262
A37: 4 | B37: кредиты, выданные на покрытие затрат, связанных с импортом и экспортом продукции | C37: =+E37+G37 -> 0 | S37: =SUM(T37:X37) -> 0 | T37: 0
A38: 5 | B38: кредиты, выданные по отдельным решениям правительства | C38: =+E38+G38 -> 0 | S38: =SUM(T38:X38) -> 0 | T38: 0
A39: 6 | B39: другие цели кредитования | C39: =+E39+G39 -> 1552381685 | E39: 745218616 | F39: 0.16415543 | G39: 807163069 | H39: 0.068699598 | I39: 46231370 | J39: 676715160 | K39: 770298391 | L39: 36231742 | M39: 22905022 | N39: 1529970733 | O39: 21110952 | P39: 1300000 | S39: =SUM(T39:X39) -> 19224948 | T39: 16585098 | U39: 2089850 | V39: 550000 | Y39: 743185 | Z39: 5860000
B41: Подпись Председателя правления:
B43: Подпись Главного Бухгалтера:

Sheet Bank Capital Calc (2)
A1: РАСЧЕТ РЕГУЛЯТИВНОГО КАПИТАЛА БАНКА | C1: Таблица-5
B3: =#REF! -> #REF! | C3: =+#REF! -> #REF!
A4: № | B4: Характеристики | C4: Итого капитала
A5: I. | B5: КАПИТАЛ УРОВНЯ 1
A6: 1 | B6: ОСНОВНОЙ КАПИТАЛ УРОВНЯ 1
A7: 1.1. | B7: Обыкновенные Акции, чистые | C7: Формула
A8: a | B8: Полностью оплаченные обыкновенные акции
A9: б | B9: Минус: Обратно Выкупленные обыкновенные акции
A10: 1.2. | B10: Добавленный капитал - Обыкновенные | C10: 0
A11: 1.3. | B11: Нераспределенная прибыль (убыток), в том числе капитальные резервы | C11: Формула
A12: а | B12: Капитальные резервы
A13: б | B13: Нераспределенная прибыль
A14: в | B14: Убыток за предыдущие периоды
A15: г | B15: Убыток за текущий год
A16: 1.4. | B16: Интерес меньшинства в консолидированных дочерних компаниях (согласно МБС)
A17: 1.5. | B17: Резерв на девальвацию
B18: Итого основного капитала уровня I до вычетов | C18: Формула
A19: 1.6. | B19: Вычеты из суммы основного капитала уровня I | C19: Формула
A20: а | B20: Нематериальные активы
A21: б | B21: Все инвестиции в капитал неконсолидированных хозяйствующих субъектов, в том числе в долговые обязательства, которые образуют капитал хозяйствующих субъектов
A22: в | B22: Инвестиции в капитал других банков
A23: I | B23: ВСЕГО СКОРРЕКТИРОВАННЫЙ ОСНОВНОЙ КАПИТАЛ УРОВНЯ I | C23: Формула
A24: 2 | B24: ДОБАВЛЕННЫЙ КАПИТАЛ УРОВНЯ 1
A25: 2.1. | B25: Некумулятивные бессрочные привилегированные акции | C25: =+C26+C27 -> 0
A26: а | B26: Полностью оплаченные привилегированные акции
A27: б | B27: Минус: Обратно Выкупленные привилегированные акции
A28: 2.2. | B28: Добавленный капитал - Привилегированные | C28: 0
A29: 2.3. | B29: Интерес меньшинства в консолидированных дочерних компаниях | C29: 0
A30: 2.4. | B30: Доля участия дочерних предприятий (выпущенные дочерними предприятиями и находящиеся во владении третьих лиц инструменты, приравненные к капиталу) | C30: 0
A31: II | B31: ВСЕГО ДОБАВЛЕННЫЙ КАПИТАЛ УРОВНЯ I | C31: =+C25+C28+C29+C30 -> 0
A32: III | B32: ВСЕГО СКОРРЕКТИРОВАННЫЙ КАПИТАЛ УРОВНЯ I | C32: Формула
B33: КАПИТАЛ УРОВНЯ II
A34: 3.1. | B34: Прибыль за текущий год
A35: 3.2. | B35: Резервы, создаваемые на стандартные кредиты (активы), в размере не более 1.25% от общей суммы активов, взвешенных с учетом риска | C35: =IF(#REF!<(C43*1.25%),#REF!,(C43*1.25%)) -> #REF!
A36: 3.3. | B36: Излишки оценочной стоимости прироста над первоначальной стоимостью
A37: 3.4. | B37: Другие инструменты капитала (не более 1/3 части капитала 1 уровня после вычетов)
A38: 3.5. | B38: Субординированный долг
A39: 3.6. | B39: Вычеты превышения Капитала Уровня II над Капиталом Уровня I | C39: Формула
B40: Итого капитала Уровня II | C40: =SUM(C34:C38) -> #REF!
A41: IV | B41: СКОРРЕКТИРОВАННЫЙ КАПИТАЛ УРОВНЯ II | C41: Формула
A42: V | B42: ВСЕГО РЕГУЛЯТИВНЫЙ КАПИТАЛ | C42: Формула
A43: VI | B43: ОБЩАЯ СУММА АКТИВОВ ВЗВЕШЕННЫХ С УЧЕТОМ РИСКА | C43: =+C44+C45+C46 -> #REF!
A44: а | B44: Сумма балансовых и забалансовых активов, взвешенных с учетом риска | C44: =+#REF! -> #REF!
A45: б | B45: Операционный риск | C45: =+#REF! -> #REF!
A46: в | B46: Рыночный риск | C46: =+#REF! -> #REF! | E46: =+#REF! -> #REF!
A47: VII | B47: КОЭФФИЦИЕНТ ОСНОВНОГО КАПИТАЛА УРОВНЯ I (I/VI) | C47: Формула
A48: VIII | B48: КОЭФФИЦИЕНТ КАПИТАЛА УРОВНЯ I (III/VI) | C48: Формула
A49: IX | B49: КОЭФФИЦИЕНТ ОБЩЕЙ СУММЫ КАПИТАЛА, ОСНОВАННОГО НА РИСКЕ (V/VI) | C49: Формула
A50: X | B50: Активы для расчета левеража | C50: Формула
A51: а | B51: Общие активы | C51: =+#REF! -> #REF!
A52: б | B52: Забалансовые инструменты | C52: =SUM(#REF!) -> #REF! | D52: =+#REF! -> #REF!
A53: в | B53: Деривативные (производные) инструменты | C53: =SUM(#REF!) -> #REF!
A54: г | B54: Минус: Строка 1.6. Итого вычетов из суммы основного капитала Уровня 1 | C54: =+C19 -> Формула
A55: XI | B55: Коэффициент левеража | C55: Формула
B57: Подпись Председателя правления:
B59: Подпись Главного Бухгалтера:

Sheet Deposits_av rate
A1: ДАННЫЕ О СРЕДНЕВЗВЕШЕННЫХ ПРОЦЕНТНЫХ СТАВКАХ ПО ПРИВЛЕЧЕННЫМ ДЕПОЗИТАМ БАНКОВ | N1: Таблица-21
B2: =+'Asset quality'!B3 -> АК "Алокабанк" | K2: =+'loans_av rate'!F3 -> 44196 | N2: тыс. сум
A3: № | B3: Сроки, погашения средств | C3: Вклады (депозиты) физических лиц | I3: Вклады (депозиты) юридических лиц
C4: общая сумма (тыс. сум) | D4: средневзвешенные процентные ставки | E4: в том числе | I4: общая сумма (тыс. сум) | J4: средневзвешенные процентные ставки | K4: в том числе
E5: в национальный валюте | G5: в иностранной валюте | K5: в национальный валюте | M5: в иностранной валюте
E6: остаток всего | F6: средневзвешенные процентные ставки | G6: остаток всего | H6: средневзвешенные процентные ставки | K6: остаток всего | L6: средневзвешенные процентные ставки | M6: остаток всего | N6: средневзвешенные процентные ставки
B7: А | C7: Б | D7: В | E7: Г | F7: Д | G7: Е | H7: Ж | I7: З | J7: И | K7: К | L7: Л | M7: М | N7: Н
A8: 1 | B8: Бессрочные | C8: =+E8+G8 -> 315114291 | D8: 0 | E8: 252596722 | F8: 0 | G8: 62517569 | H8: 0 | I8: =+K8+M8 -> 1185726857 | J8: 2.3173559e-05 | K8: 931894470 | L8: 2.9509779e-05 | M8: 253832387 | N8: 0 | P8: =+'[8]Bank Liabilities Analysis'!$C$22 -> 1500841148 | Q8: =+P8-C8-I8 -> 0
A9: 2 | B9: От 1 до 7 дней | C9: =+E9+G9 -> 866553 | D9: 0.1863 | E9: 866553 | F9: 0.1863 | G9: 0 | H9: 0 | I9: =+K9+M9 -> 111000000 | J9: 0.1755 | K9: 111000000 | L9: 0.1755 | M9: 0 | N9: 0 | P9: =+'[8]Bank Liabilities Analysis'!$E$22 -> 111866553 | Q9: =+P9-C9-I9 -> 0
A10: 3 | B10: От 8 до 30 дней | C10: =+E10+G10 -> 6963385 | D10: 0.1863 | E10: 6963385 | F10: 0.1863 | G10: 0 | H10: 0 | I10: =+K10+M10 -> 35646593 | J10: 0.1688 | K10: 35200000 | L10: 0.1688 | M10: 446593 | N10: 0 | P10: =+'[8]Bank Liabilities Analysis'!$G$22 -> 42609978 | Q10: =+P10-C10-I10 -> 0
A11: 4 | B11: От 31 до 90 дней | C11: =+E11+G11 -> 22820177 | D11: 0.2 | E11: 22820177 | F11: 0.2 | G11: 0 | H11: 0 | I11: =+K11+M11 -> 378155975 | J11: 0.172 | K11: 377632129 | L11: 0.172 | M11: 523846 | N11: 0 | P11: =+'[8]Bank Liabilities Analysis'!$I$22 -> 400976152 | Q11: =+P11-C11-I11 -> 0
A12: 5 | B12: От 91 до 180 дней | C12: =+E12+G12 -> 30139732 | D12: 0.196 | E12: 30139732 | F12: 0.196 | G12: 0 | H12: 0 | I12: =+K12+M12 -> 287469740 | J12: 0.132 | K12: 287469740 | L12: 0.132 | M12: 0 | N12: 0 | P12: =+'[8]Bank Liabilities Analysis'!$K$22 -> 317609472 | Q12: =+P12-C12-I12 -> 0
A13: 6 | B13: От 181 до 365 дней | C13: =+E13+G13 -> 52890906 | D13: 0.17405627 | E13: 51379401 | F13: 0.178 | G13: 1511505 | H13: 0.04 | I13: =+K13+M13 -> 364429448 | J13: 0.17193065 | K13: 355419297 | L13: 0.1749 | M13: 9010151 | N13: 0.0548 | P13: =+'[8]Bank Liabilities Analysis'!$M$22 -> 417320354 | Q13: =+P13-C13-I13 -> 0
A14: 7 | B14: От 366 до 730 дней | C14: =+E14+G14 -> 136654184 | D14: 0.17938881 | E14: 125480113 | F14: 0.191 | G14: 11174071 | H14: 0.049 | I14: =+K14+M14 -> 269814551 | J14: 0.12358799 | K14: 170283811 | L14: 0.1749 | M14: 99530740 | N14: 0.0358 | P14: =+'[8]Bank Liabilities Analysis'!$O$22 -> 406468735 | Q14: =+P14-C14-I14 -> 0
A15: 8 | B15: Свыше 2 лет | C15: =+E15+G15 -> 27427585 | D15: 0.16206254 | E15: 22272498 | F15: 0.188 | G15: 5155087 | H15: 0.05 | I15: =+K15+M15 -> 1698968399 | J15: 0.054873792 | K15: 430979211 | L15: 0.1207 | M15: 1267989188 | N15: 0.0325 | P15: =+'[8]Bank Liabilities Analysis'!$Q$22 -> 1726395984 | Q15: =+P15-C15-I15 -> 0
A16: 9 | B16: Итого (сумма строк 1, 2, 3, 4, 5, 6, 7, 8 ) | C16: =SUM(C8:C15) -> 592876813 | D16: =IFERROR(((C8*D8)/C16)+((C9*D9)/C16)+((C10*D10)/C16)+((C11*D11)/C16)+((C12*D12)/C16)+((C13*D13)/C16)+((C14*D14)/C16)+((C15*D15)/C16),0) -> 0.084495375 | E16: =SUM(E8:E15) -> 512518581 | F16: =IFERROR(((E8*F8)/E16)+((E9*F9)/E16)+((E10*F10)/E16)+((E11*F11)/E16)+((E12*F12)/E16)+((E13*F13)/E16)+((E14*F14)/E16)+((E15*F15)/E16),0) -> 0.096054283 | G16: =SUM(G8:G15) -> 80358232 | H16: =IFERROR(((G8*H8)/G16)+((G9*H9)/G16)+((G10*H10)/G16)+((G11*H11)/G16)+((G12*H12)/G16)+((G13*H13)/G16)+((G14*H14)/G16)+((G15*H15)/G16),0) -> 0.010773557 | I16: =SUM(I8:I15) -> 4331211563 | J16: =IFERROR(((I8*J8)/I16)+((I9*J9)/I16)+((I10*J10)/I16)+((I11*J11)/I16)+((I12*J12)/I16)+((I13*J13)/I16)+((I14*J14)/I16)+((I15*J15)/I16),0) -> 0.073361742 | K16: =SUM(K8:K15) -> 2699878658 | L16: =IFERROR(((K8*L8)/K16)+((K9*L9)/K16)+((K10*L10)/K16)+((K11*L11)/K16)+((K12*L12)/K16)+((K13*L13)/K16)+((K14*L14)/K16)+((K15*L15)/K16),0) -> 0.10086126 | M16: =SUM(M8:M15) -> 1631332905 | N16: =IFERROR(((M8*N8)/M16)+((M9*N9)/M16)+((M10*N10)/M16)+((M11*N11)/M16)+((M12*N12)/M16)+((M13*N13)/M16)+((M14*N14)/M16)+((M15*N15)/M16),0) -> 0.027748233 | P16: =+'[8]Bank Liabilities Analysis'!$S$22 -> 4924088376 | Q16: =+P16-C16-I16 -> 0
B19: Подпись Председателя правления:
B21: Подпись Главного Бухгалтера:
B24: Физлица | C24: =+'[8]Deposits by Client'!$C$6+'[8]Deposits by Client'!$C$15 -> 592876813 | G24: =+'[8]Deposits by Client'!$D$6+'[8]Deposits by Client'!$D$15 -> 80358232
C25: =+C16 -> 592876813 | G25: =+G16 -> 80358232
C26: =+C24-C25 -> 0 | G26: =+G24-G25 -> 0
B27: Юрзлица | I27: =+'[8]Deposits by Client'!$C$22-'[8]Deposits by Client'!$C$6-'[8]Deposits by Client'!$C$15 -> 4331211563 | M27: =+'[8]Deposits by Client'!$D$22-'[8]Deposits by Client'!$D$6-'[8]Deposits by Client'!$D$15 -> 1631332905
I28: =+I16 -> 4331211563 | M28: =+M16 -> 1631332905
I29: =+I27-I28 -> 0 | M29: =+M27-M28 -> 0

Sheet Economic Normatives
A1: РАСЧЕТ ПРУДЕНЦИАЛЬНЫХ НОРМАТИВОВ | I1: Таблица-22
B2: =+'Asset quality'!B3 -> АК "Алокабанк" | I2: =+'Asset quality'!P3 -> 44196
A4: № | B4: Наименование экономического норматива | F4: Формула | I4: Фактическое значение | J4: Нормативное значение | K4: Отклонение
B5: A | F5: Б | I5: В | J5: Г | K5: Д
A6: 1 | B6: Показатели достаточности капитала
A7: 1.1 | B7: Коэффициент достаточности капитала | F7: Скорректированная общая капитала, основанного на риске | I7: =+'[9]Bank Capital Calc'!$C$50 -> 0.19025174 | J7: Мин | K7: =IF(I7="",0-J8,(IF((I7-J8)>0,"",I7-J8)))
F8: Активы с учетом риска | J8: 0.13
A9: 1.2 | B9: Коэффициент достаточности Капитала Уровня 1 | F9: Капитал Уровня I | I9: =+'[9]Bank Capital Calc'!$C$49 -> 0.16049009 | J9: Мин | K9: =IF(I9="",0-J10,(IF((I9-J10)>0,"",I9-J10)))
F10: Активы с учетом риска | J10: 0.1
A11: 1.3 | B11: Коэффициент достаточности основного Капитала Уровня 1 | F11: Основной капитал Уровня I | I11: =+'[9]Bank Capital Calc'!$C$48 -> 0.16020854 | J11: Мин | K11: =IF(I11="",0-J12,(IF((I11-J12)>0,"",I11-J12)))
F12: Активы с учетом риска | J12: 0.08
A13: 1.4 | B13: Левераж | F13: Капитал Уровня I | I13: =+'[9]Bank Capital Calc'!$C$56 -> 0.14427315 | J13: Мин | K13: =IF(I13="",0-J14,(IF((I13-J14)>0,"",I13-J14)))
F14: Активы + забалансовые инструменты+ деривативные (производные) инструменты - вычеты из суммы основного капитала уровня I | J14: 0.06
A15: 2 | B15: Показатели ликвидности
A16: 2.1 | B16: Коэффициент покрытия ликвидности | E16: Всего | F16: Высоколиквидные активы | I16: =IFERROR((+'[8]Liquidity Analysis'!$C$21),0) -> 1.9137692 | J16: Мин | K16: =IF(I16="",0-$J$18,(IF((I16-$J$18)>0,"",I16-$J$18)))
E17: в национальной валюте | I17: =IFERROR((+'[8]Liquidity Analysis'!$D$21),0) -> 1.4845926 | K17: =IF(I17="",0-$J$18,(IF((I17-$J$18)>0,"",I17-$J$18)))
E18: в иностранной валюте | F18: Чистый отток в последующие 30 дней | I18: =IFERROR((+'[8]Liquidity Analysis'!$E$21),0) -> 3.2242828 | J18: 1 | K18: =IF(I18="",0-$J$18,(IF((I18-$J$18)>0,"",I18-$J$18)))
A19: 2.2 | B19: Норма чистого стабильного финансирования | E19: Всего | F19: Доступная сумма стабильного финансирования | I19: =IFERROR((+'[8]Liquidity Analysis'!$C$31),0) -> 1.1363895 | J19: Мин | K19: =IF(I19="",0-$J$21,(IF((I19-$J$21)>0,"",I19-$J$21)))
E20: в национальной валюте | I20: =IFERROR((+'[8]Liquidity Analysis'!$D$31),0) -> 1.0846295 | K20: =IF(I20="",0-$J$21,(IF((I20-$J$21)>0,"",I20-$J$21)))
E21: в иностранной валюте | F21: Необходимая сумма стабильного финансирования | I21: =IFERROR((+'[8]Liquidity Analysis'!$E$31),0) -> 1.2266078 | J21: 1 | K21: =IF(I21="",0-$J$21,(IF((I21-$J$21)>0,"",I21-$J$21)))
A22: 3 | B22: Нормативы по операциям с заемщиками
A23: 3.1 | B23: Максимальный размер риска на одного заемщика или группу взаимосвязанных заемщиков, Обеспеченные активами | F23: Максимальный размер риска на одного заемщика или группу взаимосвязанных заемщиков,Обеспеченные активами | I23: =IFERROR(((+' Largest risk'!G8)/+'[9]Bank Capital Calc'!$C$33),0) -> 0.24904624 | J23: Макс | K23: =IF(I23="","",IF(I23<0,"ОТР",IF((I23-J24)<0,"",I23-J24)))
F24: Капитал Уровня I | J24: 0.25
A25: 3.2 | B25: Максимальный размер риска на один банк или группу взаимосвязанных заемщиков банков по межбанковским кредитам и депозитам | F25: Максимальный размер риска на один банк или группу взаимосвязанных заемщиков банков по межбанковским кредитам и депозитам | I25: =IFERROR((' Largest risk'!L10/+'[9]Bank Capital Calc'!$C$33),0) -> 0.12452312 | J25: Макс | K25: =IF(I25<0,"ОТР",IF((I25-J26)<0,"",I25-J26))
F26: Капитал Уровня I | J26: 0.25
A27: 3.3 | B27: Максимальный размер риска на одного заемщика или группу взаимосвязанных заемщиков, Необеспеченные активы | F27: Максимальный размер риска на одного заемщика или группу взаимосвязанных заемщиков, Необеспеченные активы | I27: =IFERROR(((0)/+'[9]Bank Capital Calc'!$C$33),0) -> 0 | J27: Макс | K27: =IF(I27<0,"ОТР",IF((I27-J28)<0,"",I27-J28))
F28: Капитал Уровня I | J28: 0.05
A29: 3.4 | B29: Максимальный размер риска для всех крупных активов | F29: Совокупная сумма крупных активов | I29: =IFERROR((+' Largest risk'!G67/+'[9]Bank Capital Calc'!$C$33),0) -> 0.81372199 | J29: Макс | K29: =IF(I29="","",IF(I29<0,"ОТР",IF((I29-J30)<0,"",I29-J30)))
F30: Капитал Уровня I | J30: 8
A31: 4 | B31: Нормативы по операциям с ценными бумагами
A32: 4.1 | B32: Максимальный размер инвестиций в ценные бумаги одного эмитента | F32: Инвестиции в негосударственные ценные бумаги одного эмитента | I32: =IFERROR((33000000/+'[9]Bank Capital Calc'!$C$33),0) -> 0.026148034 | J32: Макс | K32: =IF(I32<0,"ОТР",IF((I32-J33)<0,"",I32-J33))
F33: Капитал Уровня I | J33: 0.15
A34: 4.2 | B34: Максимальный общий размер инвестиций в ценные бумаги для купли- продажи | F34: Общий размер инвестиций в ценные бумаги для купли- продажи | I34: =IFERROR((+('[8]Investment Securities'!$B$22+'[8]Investment Securities'!$B$23+'[8]Investment Securities'!$B$24+'[8]Investment Securities'!$B$25-'[8]Investment Securities'!$B$28)/+'[9]Bank Capital Calc'!$C$33),0) -> 0 | J34: Макс | K34: =IF(I34="","",IF(I34<0,"ОТР",IF((I34-J35)<0,"",I34-J35)))
F35: Капитал Уровня I | J35: 0.25
A36: 4.3 | B36: Максимальный общий размер инвестиций в уставной капитал и другие ценные бумаги всех эмитентов | F36: Общий размер инвестиций в уставной капитал и другие ценные бумаги всех эмитентов | I36: =IFERROR((+(+'[8]Investment Securities'!$B$15-'[8]Investment Securities'!$B$6-'[8]Investment Securities'!$B$7+'[8]Investment Securities'!$B$22+'[8]Investment Securities'!$B$23+'[8]Investment Securities'!$B$24+'[8]Investment Securities'!$B$25-'[8]Investment Securities'!$B$28)/+'[9]Bank Capital Calc'!$C$33),0) -> 0.032575037 | J36: Макс | K36: =IF(I36="","",IF(I36<0,"ОТР",IF((I36-J37)<0,"",I36-J37)))
F37: Капитал Уровня I | J37: 0.5
A38: 5 | B38: Нормативы показателей по операциям со связанными лицами (инсайдерами)
A39: 5.1 | B39: Сумма выданным активам одному инсайдеру или группе связанных лиц, Обеспеченные активы | F39: Сумма выданным активам одному инсайдеру или группе связанных лиц, Обеспеченный активом | I39: =IFERROR(((+'Loans to Affiliated P.'!G7+'Loans to Affiliated P.'!G8)/+'[9]Bank Capital Calc'!$C$33),0) -> 0.11869881 | J39: Макс | K39: =IF(I39="","",IF(I39<0,"ОТР",IF((I39-J40)<0,"",I39-J40)))
F40: Капитал Уровня I | J40: 0.25
A41: 5.2 | B41: Совокупная сумма активов предоставленых банком всем инсайдерам | F41: Совокупная сумма активов выданных инсайдерам | I41: =IFERROR((+'Loans to Affiliated P.'!G69/+'[9]Bank Capital Calc'!$C$33),0) -> 0.6072245 | J41: Макс | K41: =IF(I41="","",IF(I41<0,"ОТР",IF((I41-J42)<0,"",I41-J42)))
F42: Капитал Уровня I | J42: 1
A43: 6 | B43: Нормативный показатель по инвестициям банка в недвижимость
A44: 6.1 | B44: Совокупная сумма всех инвестиций банка в недвижимость | F44: Сумма всех инвестиций банка в недвижимость | I44: =IFERROR(((346491330)/+'[9]Bank Capital Calc'!$C$33),0) -> 0.27454749 | J44: Макс | K44: =IF(I44="","",IF(I44<0,"ОТР",IF((I44-J45)<0,"",I44-J45)))
F45: Капитал Уровня I | J45: 1
D47: Подпись Председателя правления:
D49: Подпись Главного Бухгалтера:

Sheet Miscellaneous
B1: РАЗНАЯ ИНФОРМАЦИЯ | C1: Таблица-23
B2: =+'Asset quality'!B3 -> АК "Алокабанк" | C2: тыс. сум
A3: 1. | B3: Численность работников банка, включая административный, филиалы, и представительства банка.
A4: а | B4: Численность работников банка по штатному расписанию | C4: 1352
A5: б | B5: Фактическая численность работников банка | C5: 1328
A6: 2. | B6: Общее количество отделений банка, включая административный, филиалы, и представительства банка. | C6: =+C8+C9+C10+C11 -> 226
B7: из них,
A8: а | B8: Количество филиалов | C8: 14
A9: б | B9: Количество мини банков | C9: 0
A10: в | B10: Количество розничных касс вне банка (филиалы) | C10: 136
A11: г | B11: Количество центров банковских услуг | C11: 76
A12: 3. | B12: Клиенская база банка | C12: =C14+C15+C16 -> 761205
B13: из них,
A14: а | B14: Физические лица | C14: 732507
A15: б | B15: Индивидуальные предприниматели | C15: 11226
A16: в | B16: Юридические лица | C16: =C18+C19+C20+C21+C22 -> 17472
B17: в том числе имеющие основной счет в банке
A18: - | B18: Государственные предприятия | C18: 289
A19: - | B19: Частные товарищества и корпорации | C19: 14377
A20: - | B20: Фермерское хозяйство | C20: 2109
A21: - | B21: Правительство | C21: 19
A22: - | B22: Прочие | C22: 678
A23: 4. | B23: Рейтинг банка
A24: а | B24: Названия рейтинговой компании | C24: Moody's
A25: б | B25: Оценка рейтинга банка | C25: B1/NP, B2/NP, Stable
B28: Подпись Председателя правления:
B30: Подпись Главного Бухгалтера:

Sheet ПФУ
A1: Показатели финансовой устойчивости
A2: =+'Asset quality'!B3 -> АК "Алокабанк" | B2: тыс. сум | C2: Месяц
A3: Основные показатели | B3: =+'Asset quality'!P3 -> 44196 | K3: Месяц | L3: Актив | M3: Капитал | O3: Всего активы (средний за период) | P3: Совокупный капитал (средний за период)
A4: Регулятивный капитал к активам взвешанных с учетом риска | B4: =IFERROR((B5/B6),0) -> 0.19387485 | J4: 1 января | K4: 1 | L4: 7341732732 | M4: 1396370695
A5: Всего Регулятивный капитал | B5: =+'[10]Bank Capital Calc'!$C$43 -> 1423921361 | J5: 1 февраль | K5: 2 | L5: 7120715993 | M5: 1421110100 | N5: 1 | O5: =+(L4+L5)/2 -> 7.2312244e+09 | P5: =+(M4+M5)/2 -> 1.4087404e+09
A6: Активы взвешанные с учетом риска | B6: =+'[10]Bank Capital Calc'!$C$44 -> 7.3445389e+09 | J6: 1 март | K6: 3 | L6: 7136809831 | M6: 1439417017 | N6: 2 | O6: =+(L4+L5+L6)/3 -> 7199752852 | P6: =+(M4+M5+M6)/3 -> 1.4189659e+09
A7: Регулятивный капитал 1 - уровня к Активам взвешанных с учетом риска | B7: =IFERROR((B8/B9),0) -> 0.17953184 | J7: 1 апрель | K7: 4 | L7: 7256386817 | M7: 1447376099 | N7: 3 | O7: =+(L4+L7)/2 -> 7.2990598e+09 | P7: =+(M4+M7)/2 -> 1421873397
A8: Регулятивный капитал 1- уровня | B8: =+'[10]Bank Capital Calc'!$C$33 -> 1318578624 | J8: 1 май | K8: 5 | L8: 7463956451 | M8: 1451780246 | N8: 4 | O8: =+(+L4+L5+L6+L7+L8)/5 -> 7.2639204e+09 | P8: =+(+M4+M5+M6+M7+M8)/5 -> 1.4312108e+09
A9: Активы взвешанные с учетом риска | B9: =+'[10]Bank Capital Calc'!$C$44 -> 7.3445389e+09 | J9: 1 июнь | K9: 6 | L9: 7455535974 | M9: 1447558325 | N9: 5 | O9: =+(+L4+L5+L6+L7+L8+L9)/6 -> 7.2958563e+09 | P9: =+(+M4+M5+M6+M7+M8+M9)/6 -> 1.4339354e+09
A10: Недействующие ссуды за вычетом резервов/общий объем капитала | B10: =IFERROR((B11/B12),0) -> 0.002673997 | J10: 1 июль | K10: 7 | L10: 7525975866 | M10: 1460947503 | N10: 6 | O10: =+(L4+L7+L10)/3 -> 7.3746985e+09 | P10: =+(M4+M7+M10)/3 -> 1434898099
A11: Недействующие ссуды за вычетом резервов | B11: =+('Asset Classification'!M50-'Asset Classification'!O50+'Asset Classification'!Q50-'Asset Classification'!S50+'Asset Classification'!U50-'Asset Classification'!W50) -> 4194244 | J11: 1 август | K11: 8 | L11: 7798467447 | M11: 1465925407 | N11: 7 | O11: =(L4+L5+L6+L7+L8+L9+L10+L11)/8 -> 7.3874476e+09 | P11: =(M4+M5+M6+M7+M8+M9+M10+M11)/8 -> 1441310674
A12: Совокупный капитал на конец периода | B12: =+B35 -> 1568529812 | J12: 1 сентябрь | K12: 9 | L12: 7897871930 | M12: 1482330874 | N12: 8 | O12: =(L4+L5+L6+L7+L8+L9+L10+L11+L12)/9 -> 7444161449 | P12: =(M4+M5+M6+M7+M8+M9+M10+M11+M12)/9 -> 1445868474
A13: Недействующие ссуды/общая сумма ссуд | B13: =IFERROR((B14/B15),0) -> 0.0011184151 | J13: 1 октябрь | K13: 10 | L13: 8056867400 | M13: 1499005420 | N13: 9 | O13: =+(L4+L7+L10+L13)/4 -> 7.5452407e+09 | P13: =+(M4+M7+M10+M13)/4 -> 1.4509249e+09
A14: Недействующие ссуды | B14: =+('Asset Classification'!M50+'Asset Classification'!Q50+'Asset Classification'!U50) -> 6381606 | J14: 1 ноябрь | K14: 11 | L14: 8168827942 | M14: 1531843962 | N14: 10 | O14: =(+L4+L5+L6+L7+L8+L9+L10+L11+L12+L13+L14)/11 -> 7.5657408e+09 | P14: =(+M4+M5+M6+M7+M8+M9+M10+M11+M12+M13+M14)/11 -> 1.4585151e+09
A15: Общая сумма ссуд | B15: =+'Loans Receivable'!C92 -> 5705936821 | J15: 1 декабрь | K15: 12 | L15: 8343264184 | M15: 1547647721 | N15: 11 | O15: =(+L4+L5+L6+L7+L8+L9+L10+L11+L12+L13+L14+L15)/12 -> 7.6305344e+09 | P15: =(+M4+M5+M6+M7+M8+M9+M10+M11+M12+M13+M14+M15)/12 -> 1.4659428e+09
A16: Рентабельность активов | B16: =IFERROR((B17/B18),0) -> 0.027773304 | J16: 1 январь | K16: 13 | L16: 8108166331 | M16: 1568529812 | N16: 12 | O16: =+(L4+L7+L10+L13+L16)/5 -> 7.6578258e+09 | P16: =+(M4+M7+M10+M13+M16)/5 -> 1.4744459e+09
A17: Чистая прибыль до уплаты налогов | B17: =(+'Income '!C69)/MONTH(B3)*12 -> 212683122
A18: Всего активы (средний за период) | B18: =VLOOKUP(MONTH(B3),$N$4:$P$16,2,0) -> 7.6578258e+09
A19: Рентабельность капитала | B19: =IFERROR((B20/B21),0) -> 0.11529755
A20: Чистая прибыль | B20: =(+'Income '!C76)/MONTH(B3)*12 -> 170000000
A21: Совокупный капитал (средний за период) | B21: =VLOOKUP(MONTH(B3),$N$4:$P$16,3,0) -> 1.4744459e+09
A22: Процентная маржа/валовой доход | B22: =IFERROR((B23/B24),0) -> 0.55450252
A23: Процентная маржа | B23: =+'Income '!C30 -> 366536005
A24: Валовой доход | B24: =+B27 -> 661017745
A25: Непроцентные расходы/валовой доход | B25: =IFERROR((B26/B27),0) -> 0.65739181
A26: Непроцентные расходы | B26: =+'Income '!C51+'Income '!C67 -> 434547650
A27: Валовой доход | B27: =+'Income '!C30+'Income '!C43 -> 661017745
A28: Ликвидные активы/всего активы | B28: =IFERROR((B29/B30),0) -> 0.14877927
A29: Ликвидные активы | B29: =+B32 -> 1206327062
A30: Всего активы | B30: =+B36 -> 8108166331
A31: Ликвидные активы/краткосрочные обязательства | B31: =IFERROR((B29/B33),0) -> 0.33608082
A32: Ликвидные активы | B32: =+B54 -> 1206327062
A33: Краткосрочные обязательства | B33: =+('[8]Bank Liabilities Analysis'!$C$39+'[8]Bank Liabilities Analysis'!$E$39+'[8]Bank Liabilities Analysis'!$G$39+'[8]Bank Liabilities Analysis'!$I$39+'[8]Bank Liabilities Analysis'!$K$39+'[8]Bank Liabilities Analysis'!$M$39) -> 3589395683
A34: Совокупный капитал на конец периода/Всего активы | B34: =IFERROR((B35/B36),0) -> 0.19345062
A35: Совокупный капитал на конец периода | B35: =+[8]Balance!$C$77 -> 1568529812
A36: Всего активы | B36: =+[8]Balance!$C$45 -> 8108166331
A37: Чистая открытая валютная позиция /Совокупный капитал на конец периода | B37: =IFERROR((B38/B39),0) -> 0.03048718
A38: Чистая открытая валютная позиция | B38: =+'[10]Calculation of Risk'!$C$26 -> 47820050
A39: Совокупный капитал на конец периода | B39: =+B35 -> 1568529812
A42: Подпись Председателя правления:
A44: Подпись Главного Бухгалтера:
A46: Ликвидные активы | B46: Сумма | C46: Нацвалюта | D46: Инвалюта
A47: Наличные денежные средства и Драгоценные металлы | B47: =+'[8]Liquidity Analysis'!$C$57 -> 252072058 | C47: =+'[8]Liquidity Analysis'!$D$57 -> 61937102 | D47: =+'[8]Liquidity Analysis'!$E$57 -> 190134956 | E47: 1.
A48: К получению из ЦБРУ | B48: =+'[8]Liquidity Analysis'!$C$58 -> 376855943 | C48: =+'[8]Liquidity Analysis'!$D$58 -> 282195518 | D48: =+'[8]Liquidity Analysis'!$E$58 -> 94660425 | E48: 2.
A49: К получению из других банков | B49: =+'[8]Liquidity Analysis'!$C$59 -> 203594061 | C49: =+'[8]Liquidity Analysis'!$D$59 -> 714881 | D49: =+'[8]Liquidity Analysis'!$E$59 -> 202879180 | E49: 3.
A50: К получению из других банков - Депозиты (чистые) | B50: =+'[8]Liquidity Analysis'!$C$60 -> 0 | C50: =+'[8]Liquidity Analysis'!$D$60 -> 0 | D50: =+'[8]Liquidity Analysis'!$E$60 -> 0 | E50: 3.1. | F50: =+'[8]Liquidity Analysis'!$F$60 -> -93040756 | G50: =+'[8]Liquidity Analysis'!$G$60 -> -30179236 | H50: =+'[8]Liquidity Analysis'!$H$60 -> -62861520
A51: Ценные бумаги, выпущенные Правительством Республики Узбекистан и ЦБРУ (векселя, облигации и другие долговые ценные бумаги) | B51: =+'[8]Liquidity Analysis'!$C$61 -> 373805000 | C51: =+'[8]Liquidity Analysis'!$D$61 -> 373805000 | D51: =+'[8]Liquidity Analysis'!$E$61 -> 0 | E51: 4.
A52: Ценные бумаги, выпущенные странами с низким уровня риска | B52: =+'[8]Liquidity Analysis'!$C$62 -> 0 | C52: =+'[8]Liquidity Analysis'!$D$62 -> 0 | D52: =+'[8]Liquidity Analysis'!$E$62 -> 0 | E52: 5.
A53: Другие легко реализуемые ценные бумаги | B53: =+'[8]Liquidity Analysis'!$C$63 -> 0 | C53: =+'[8]Liquidity Analysis'!$D$63 -> 0 | D53: =+'[8]Liquidity Analysis'!$E$63 -> 0 | E53: 6.
A54: Итого ликвидных активов | B54: =+'[8]Liquidity Analysis'!$C$64 -> 1206327062 | C54: =+'[8]Liquidity Analysis'!$D$64 -> 718652501 | D54: =+'[8]Liquidity Analysis'!$E$64 -> 487674561 | E54: 7.
