Workbook
Name jop: #REF!
Name kol: #REF!
Name OLE_LINK19: Balance!$D$32
Name TwentyLargestData: #REF!
Name Е: #REF!

Sheet Balance
A1: БАНК БАЛАНСИ ТАРКИБИ | E1: 1-жадвал | G1: №1
B2: =IF(D3>0," "&TEXT(D3,"д ММММ, гггг"),"Число,Месяц,Год") -> 29 Декабрь, 2023
B3: "Ўзсаноатқурилишбанк" АТБ | D3: 45289 | E3: минг сўмда
A4: № | B4: АКТИВЛАР | C4: Жами | D4: Миллий валютада | E4: Хорижий валютада (сўм экв.)
A5: 1 | B5: Кассадаги нақд пул ва бошқа тўлов ҳужжатлари | C5: =+D5+E5 -> 1565389581 | D5: =+'Bank Assets Analysis'!T6 -> 494142662 | E5: =+'Bank Assets Analysis'!U6 -> 1071246919 | J5: =+C5-D5-E5 -> 0
A6: 2 | B6: Банкнинг Марказий банкдаги маблағлари | C6: =+D6+E6 -> 2526034447 | D6: =+'Bank Assets Analysis'!T7+'Bank Assets Analysis'!T8 -> 817118237 | E6: =+'Bank Assets Analysis'!U7+'Bank Assets Analysis'!U8 -> 1708916210 | J6: =+C6-D6-E6 -> 0
A7: 3 | B7: Бошқа банклар ва молиявий ташкилотлардан олиниши лозим бўлган маблағлар, соф | C7: =+'Bank Assets Analysis'!S9 -> 5562959410 | D7: =+'Bank Assets Analysis'!T9 -> 596977053 | E7: =+'Bank Assets Analysis'!U9 -> 4965982357 | J7: =+C7-D7-E7 -> 0
A8: 3.1 | B8: Бошқа банклар ва молиявий ташкилотлардан олиниши лозим бўлган маблағлар, брутто | C8: =+D8+E8 -> 5600216777 | D8: 597218110 | E8: 5002998667 | J8: =+C8-D8-E8 -> 0
A9: 3.2 | B9: Минус: Кўрилиши мумкин бўлган зарарларни қоплаш захираси | C9: =+D9+E9 -> 37257367 | D9: 241057 | E9: 37016310 | J9: =+C9-D9-E9 -> 0
A10: 4 | B10: Қимматли қоғозлар ва уларга қилинган инвестициялар, соф | C10: =+D10+E10 -> 2043306103 | D10: =+'Investment Securities'!C29 -> 1920633909 | E10: =+'Investment Securities'!D29 -> 122672194 | J10: =+C10-D10-E10 -> 0
A11: 4.1 | B11: Қимматли қоғозлар ва уларга қилинган инвестициялар, брутто | C11: =+D11+E11 -> 2056792700 | D11: =+'Investment Securities'!C26 -> 1933405000 | E11: =+'Investment Securities'!D26 -> 123387700 | J11: =+C11-D11-E11 -> 0
A12: 4.2 | B12: Қимматли қоғозлар бўйича харажатлар, дисконт, мукофот ва уларнинг ҳаққоний қийматининг ўзгариши | C12: =+D12+E12 -> -13486597 | D12: =+'Investment Securities'!C27 -> -12771091 | E12: =+'Investment Securities'!D27 -> -715506 | J12: =+C12-D12-E12 -> 0
A13: 4.3 | B13: Минус: Кўрилиши мумкин бўлган зарарларни қоплаш захираси | C13: =+D13+E13 -> 0 | D13: =+'Investment Securities'!C28 -> 0 | E13: =+'Investment Securities'!D28 -> 0 | J13: =+C13-D13-E13 -> 0
A14: 5 | B14: Қимматбаҳо металлар, тошлар ва тангалар, соф | C14: =+C15-C16 -> 875 | D14: =+'Investment Securities'!C39 -> 875 | E14: =+'Investment Securities'!D39 -> 0 | J14: =+C14-D14-E14 -> 0
A15: 5.1 | B15: Қимматбаҳо металлар, тошлар ва тангалар, брутто | C15: =+D15+E15 -> 875 | D15: =+'Investment Securities'!C37 -> 875 | E15: =+'Investment Securities'!D37 -> 0 | J15: =+C15-D15-E15 -> 0
A16: 5.2 | B16: Минус: Кўрилиши мумкин бўлган зарарларни қоплаш захираси | C16: =+D16+E16 -> 0 | D16: =+'Investment Securities'!C38 -> 0 | E16: =+'Investment Securities'!D38 -> 0 | J16: =+C16-D16-E16 -> 0
A17: 6 | B17: Инвестициялар, соф | C17: =+'Investment Securities'!B15 -> 406437547 | D17: =+'Investment Securities'!C15 -> 403272949 | E17: =+'Investment Securities'!D15 -> 3164598 | J17: =+C17-D17-E17 -> 0
A18: 6.1 | B18: Инвестициялар, брутто | C18: =+D18+E18 -> 413393187 | D18: =+'Investment Securities'!C12 -> 410228589 | E18: =+'Investment Securities'!D12 -> 3164598 | J18: =+C18-D18-E18 -> 0
A19: 6.2 | B19: Инвестициялар бўйича харажатлар, дисконт ва мукофот | C19: =+D19+E19 -> 0 | D19: =+'Investment Securities'!C13 -> 0 | E19: =+'Investment Securities'!D13 -> 0 | J19: =+C19-D19-E19 -> 0
A20: 6.3 | B20: Минус: Кўрилиши мумкин бўлган зарарларни қоплаш захираси | C20: =+D20+E20 -> 6955640 | D20: =+'Investment Securities'!C14 -> 6955640 | E20: =+'Investment Securities'!D14 -> 0 | J20: =+C20-D20-E20 -> 0
A21: 7 | B21: РЕПО битимлари бўйича сотиб олинган қимматли қоғозлар, соф | C21: =+'Bank Assets Analysis'!S33 -> 0 | D21: =+'Bank Assets Analysis'!T33 -> 0 | E21: =+'Bank Assets Analysis'!U33 -> 0 | J21: =+C21-D21-E21 -> 0
A22: 7.1 | B22: РЕПО битимлари бўйича сотиб олинган қимматли қоғозлар, брутто | C22: =+D22+E22 -> 0 | D22: 0 | E22: 0 | J22: =+C22-D22-E22 -> 0
A23: 7.2 | B23: Минус: Кўрилиши мумкин бўлган зарарларни қоплаш захираси | C23: =+D23+E23 -> 0 | D23: 0 | E23: 0 | J23: =+C23-D23-E23 -> 0
A24: 8 | B24: Кредит ва лизинг операциялари, соф | C24: =+'Bank Assets Analysis'!S28+'Bank Assets Analysis'!S29+'Bank Assets Analysis'!S31 -> 55975575345 | D24: =+'Bank Assets Analysis'!T28+'Bank Assets Analysis'!T29+'Bank Assets Analysis'!T31 -> 18735480179 | E24: =+'Bank Assets Analysis'!U28+'Bank Assets Analysis'!U29+'Bank Assets Analysis'!U31 -> 37240095166 | J24: =+C24-D24-E24 -> 0
A25: 8.1 | B25: Кредит ва лизинг операциялари, брутто | C25: =+D25+E25 -> 57124403912 | D25: 19111443266 | E25: 38012960646 | J25: =+C25-D25-E25 -> 0
A26: 8.2 | B26: Минус: Кўрилиши мумкин бўлган зарарларни қоплаш захираси | C26: =+D26+E26 -> 1148828567 | D26: 375963087 | E26: 772865480 | J26: =+C26-D26-E26 -> 0
A27: 9 | B27: Молиявий инструментлар бўйича мижозларнинг мажбуриятлари, соф | C27: =+'Bank Assets Analysis'!S25+'Bank Assets Analysis'!S26 -> 81572337 | D27: =+'Bank Assets Analysis'!T25+'Bank Assets Analysis'!T26 -> 0 | E27: =+'Bank Assets Analysis'!U25+'Bank Assets Analysis'!U26 -> 81572337 | J27: =+C27-D27-E27 -> 0
A28: 9.1 | B28: Молиявий инструментлар бўйича мижозларнинг мажбуриятлари, брутто | C28: =+D28+E28 -> 110235813 | D28: 0 | E28: 110235813 | J28: =+C28-D28-E28 -> 0
A29: 9.2 | B29: Минус: Кўрилиши мумкин бўлган зарарларни қоплаш захираси | C29: =+D29+E29 -> 28663476 | D29: 0 | E29: 28663476 | J29: =+C29-D29-E29 -> 0
A30: 10 | B30: Асосий воситалар, соф | C30: =+'Bank Assets Analysis'!S36 -> 3125231142 | D30: =+'Bank Assets Analysis'!T36 -> 3125231142 | E30: =+'Bank Assets Analysis'!U36 -> 0 | J30: =+C30-D30-E30 -> 0
A31: 11 | B31: Жами ҳисобланган фоизли ва фоизсиз даромадлар, соф | C31: =+C32+C33-C34 -> 2753931292 | D31: =+D32+D33-D34 -> 1003545484 | E31: =+E32+E33-E34 -> 1750385808 | J31: =+C31-D31-E31 -> 0
A32: 11.1 | B32: Ҳисобланган фоизли даромадлар, брутто | C32: =+D32+E32 -> 2908221192 | D32: 1078665407 | E32: 1829555785 | J32: =+C32-D32-E32 -> 0
A33: 11.2 | B33: Ҳисобланган фоизсиз даромадлар, брутто | C33: =+D33+E33 -> 21602471 | D33: 9272876 | E33: 12329595 | J33: =+C33-D33-E33 -> 0
A34: 11.2.1 | B34: Минус: Кўрилиши мумкин бўлган зарарларни қоплаш захираси | C34: =+D34+E34 -> 175892371 | D34: 84392799 | E34: 91499572 | J34: =+C34-D34-E34 -> 0
A35: 12 | B35: Банкнинг бошқа хусусий мулклари, соф | C35: =+'Bank Assets Analysis'!S37 -> 70914978 | D35: =+'Bank Assets Analysis'!T37 -> 70914978 | E35: =+'Bank Assets Analysis'!U37 -> 0 | J35: =+C35-D35-E35 -> 0
A36: 12.1 | B36: Кредит ва лизинг бўйича гаров ҳисобидан ундирилган бошқа мулклар, брутто | C36: =+D36+E36 -> 236581413 | D36: 236581413 | E36: 0 | J36: =+C36-D36-E36 -> 0
A37: 12.2 | B37: Банкнинг бошқа хусусий мулклари, брутто | C37: =+D37+E37 -> 23620471 | D37: 23620471 | E37: 0 | J37: =+C37-D37-E37 -> 0
A38: 12.3 | B38: Минус: Йиғилган эскириш суммаси ва кўрилиши мумкин бўлган зарарларни қоплаш захираси | C38: =+D38+E38 -> 189286906 | D38: 189286906 | E38: 0 | J38: =+C38-D38-E38 -> 0
A39: 13 | B39: Стандарт деб таснифланган активлар бўйича яратилган захиралар | C39: =+D39+E39 -> 615172207 | D39: =+D40+D41+D42 -> 615172207 | E39: =+E40+E41+E42 -> 0 | J39: =+C39-D39-E39 -> 0
A40: 13.1 | B40: Стандарт деб таснифланган кредитлар, лизинг ва факторинг бўйича захира | C40: =+D40+E40 -> 504953973 | D40: 504953973 | E40: 0 | J40: =+C40-D40-E40 -> 0
A41: 13.2 | B41: Стандарт деб таснифланган бошқа активлар бўйича захира | C41: =+D41+E41 -> 88013008 | D41: 88013008 | E41: 0 | J41: =+C41-D41-E41 -> 0
A42: 13.3 | B42: Стандарт деб таснифланган активлар бўйича фоизлар ва воситачилик ҳақларига оид захира | C42: =+D42+E42 -> 22205226 | D42: 22205226 | E42: 0 | J42: =+C42-D42-E42 -> 0
A43: 14 | B43: Бошқа активлар, соф | C43: =+C44-C45+C46 -> 1138242348 | D43: =+D44-D45+D46 -> 994146946 | E43: =+E44-E45+E46 -> 144095402 | J43: =+C43-D43-E43 -> 0
A44: 14.1 | B44: Бошқа активлар, брутто | C44: =+D44+E44 -> 1161663188 | D44: 1017290474 | E44: 144372714 | J44: =+C44-D44-E44 -> 0
A45: 14.2 | B45: Минус: Кўрилиши мумкин бўлган зарарларни қоплаш захираси | C45: =+D45+E45 -> 23420840 | D45: 23143528 | E45: 277312 | J45: =+C45-D45-E45 -> 0
A46: 14.3 | B46: Валюталар савдоси ва валюта позициялари | C46: 0 | J46: =+C46-D46-E46 -> 0
A47: 15 | B47: Жами активлар | C47: =+D47+E47 -> 74634423198 | D47: =+D5+D6+D7+D10+D14+D17+D21+D24+D27+D30+D31+D35-D39+D43 -> 27546292207 | E47: =+E5+E6+E7+E10+E14+E17+E21+E24+E27+E30+E31+E35-E39+E43 -> 47088130991 | F47: =+'Bank Assets Analysis'!S44 -> 74634423198 | G47: =+'Bank Assets Analysis'!T44 -> 27546292207 | H47: =+'Bank Assets Analysis'!U44 -> 47088130991 | J47: =+C47-D47-E47 -> 0
B49: МАЖБУРИЯТЛАР
A50: 16 | B50: Талаб қилиб олингунча сақланадиган депозитлар | C50: =+'Deposits by Client'!C11 -> 5825503526 | D50: =+'Bank Liabilities Analysis'!T15+'Bank Liabilities Analysis'!T7 -> 3554942463 | E50: =+'Bank Liabilities Analysis'!U15+'Bank Liabilities Analysis'!U7 -> 2270561063 | J50: =+C50-D50-E50 -> 0
A51: 17 | B51: Муддатли депозитлар | C51: =+'Deposits by Client'!C20 -> 7973087622 | D51: =+'Bank Liabilities Analysis'!T12 -> 5354638519 | E51: =+'Bank Liabilities Analysis'!U12 -> 2618449103 | J51: =+C51-D51-E51 -> 0
A52: 18 | B52: Марказий банкка тўланиши лозим бўлган маблағлар | C52: =+'Bank Liabilities Analysis'!S21 -> 1074053 | D52: =+'Bank Liabilities Analysis'!T21 -> 1074053 | E52: =+'Bank Liabilities Analysis'!U21 -> 0 | J52: =+C52-D52-E52 -> 0
A53: 19 | B53: Бошқа банклар ва молиявий ташкилотларнинг ҳисобварақлари | C53: =+'Bank Liabilities Analysis'!S23 -> 6093050942 | D53: =+'Bank Liabilities Analysis'!T23 -> 1573440667 | E53: =+'Bank Liabilities Analysis'!U23 -> 4519610275 | J53: =+C53-D53-E53 -> 0
A54: 20 | B54: РЕПО битимлари бўйича сотилган қимматли қоғозлар | C54: =+'Bank Liabilities Analysis'!S33 -> 816807035 | D54: =+'Bank Liabilities Analysis'!T33 -> 816807035 | E54: =+'Bank Liabilities Analysis'!U33 -> 0 | J54: =+C54-D54-E54 -> 0
A55: 21 | B55: Кредит ва лизинг операциялари бўйича мажбуриятлар | C55: =+D55+E55 -> 36468927735 | D55: 5523902926 | E55: 30945024809 | J55: =+C55-D55-E55 -> 0
A56: 22 | B56: Банк томонидан чиқарилган қимматли қоғозлар | C56: =+D56+E56 -> 4928243152 | D56: 0 | E56: 4928243152 | J56: =+C56-D56-E56 -> 0
A57: 23 | B57: Субординар қарз | C57: =+D57+E57 -> 2209944719 | D57: 1506867106 | E57: 703077613 | J57: =+C57-D57-E57 -> 0
A58: 24 | B58: Тўланиши лозим бўлган ҳисобланган фоизлар | C58: =+'Bank Liabilities Analysis'!S38 -> 893129828 | D58: =+'Bank Liabilities Analysis'!T38 -> 187398264 | E58: =+'Bank Liabilities Analysis'!U38 -> 705731564 | J58: =+C58-D58-E58 -> 0
A59: 25 | B59: Ҳисобланган солиқлар бўйича мажбуриятлар | C59: =+D59+E59 -> 28539623 | D59: 28539623 | E59: 0 | J59: =+C59-D59-E59 -> 0
A60: 26 | B60: Клиринг транзакциялари | C60: =+'Bank Liabilities Analysis'!S37 -> 2215477 | D60: =+'Bank Liabilities Analysis'!T37 -> 2214968 | E60: =+'Bank Liabilities Analysis'!U37 -> 509 | J60: =+C60-D60-E60 -> 0
A61: 27 | B61: Стандарт деб таснифланган балансдан ташқари моддаларга яратилган захиралар | C61: =+D61+E61 -> 14950000 | D61: 14950000 | E61: 0 | J61: =+C61-D61-E61 -> 0
A62: 28 | B62: Бошқа мажбуриятлар | C62: =+D62+E62 -> 650589334 | D62: 204895426 | E62: 445693908 | J62: =+C62-D62-E62 -> 0
A63: 29 | B63: Жами мажбуриятлар | C63: =+D63+E63 -> 65906063046 | D63: =SUM(D50:D62) -> 18769671050 | E63: =SUM(E50:E62) -> 47136391996 | F63: =+'Bank Liabilities Analysis'!S40 -> 65906063046 | G63: =+'Bank Liabilities Analysis'!T40 -> 18769671050 | H63: =+'Bank Liabilities Analysis'!U40 -> 47136391996 | J63: =+C63-D63-E63 -> 0
B65: ХУСУСИЙ КАПИТАЛ
A67: 30 | B67: Устав капитали | C67: =+C68+C69 -> 4628941928 | D67: =+D68+D69 -> 4628941928 | E67: =+E68+E69 -> 0 | J67: =+C67-D67-E67 -> 0
A68: 30.1 | B68: Aкциялар – оддий | C68: =+D68+E68 -> 4621911928 | D68: 4621911928 | E68: 0 | J68: =+C68-D68-E68 -> 0
A69: 30.2 | B69: Aкциялар – имтиёзли | C69: =+D69+E69 -> 7030000 | D69: 7030000 | E69: 0 | J69: =+C69-D69-E69 -> 0
A70: 31 | B70: Қўшилган капитал | C70: =+D70+E70 -> 696121 | D70: 696121 | E70: 0 | J70: =+C70-D70-E70 -> 0
A71: 32 | B71: Захира капитали | C71: =+C72+C73+C74 -> 1717703829 | D71: =+D72+D73+D74 -> 1717703829 | E71: =+E72+E73+E74 -> 0 | J71: =+C71-D71-E71 -> 0
A72: 32.1 | B72: Умумий захира фонди | C72: =+D72+E72 -> 1703796223 | D72: 1703796223 | E72: 0 | J72: =+C72-D72-E72 -> 0
A73: 32.2 | B73: Девальвация учун захира | C73: =+D73+E73 -> 0 | D73: 0 | E73: 0 | J73: =+C73-D73-E73 -> 0
A74: 32.3 | B74: Бошқа захира фондлари | C74: =+D74+E74 -> 13907606 | D74: 13907606 | E74: 0 | J74: =+C74-D74-E74 -> 0
A75: 33 | B75: Тақсимланмаган фойда | C75: =+D75+E75 -> 2381018274 | D75: 2381018274 | E75: 0 | J75: =+C75-D75-E75 -> 0
A76: 33.1 | B76: шундан, жорий йил соф фойдаси (зарари) | C76: =+D76+E76 -> 911684119 | D76: 911684119 | E76: 0 | J76: =+C76-D76-E76 -> 0
A77: 34 | B77: Жами хусусий капитал | C77: =+C67+C70+C71+C75 -> 8728360152 | D77: =+D67+D70+D71+D75 -> 8728360152 | E77: =+E67+E70+E71+E75 -> 0 | J77: =+C77-D77-E77 -> 0
A78: 35 | B78: Жами мажбуриятлар ва хусусий капитал | C78: =+D78+E78 -> 74634423198 | D78: =+D63+D77 -> 27498031202 | E78: =+E63+E77 -> 47136391996 | J78: =+C78-D78-E78 -> 0
B80: Бошқарув Раис имзоси:
B82: Бош бухгалтер имзоси:
C86: =+C47-C78 -> 0

Sheet Bank Capital Calc (2)
A1: РАСЧЕТ РЕГУЛЯТИВНОГО КАПИТАЛА БАНКА | C1: Таблица-5
B3: =Balance!B3 -> "Ўзсаноатқурилишбанк" АТБ | C3: =+Balance!D3 -> 45289
A4: № | B4: Характеристики | C4: Итого капитала
A5: I. | B5: КАПИТАЛ УРОВНЯ 1
A6: 1 | B6: ОСНОВНОЙ КАПИТАЛ УРОВНЯ 1
A7: 1.1. | B7: Обыкновенные Акции, чистые | C7: Формула
A8: a | B8: Полностью оплаченные обыкновенные акции
A9: б | B9: Минус: Обратно Выкупленные обыкновенные акции
A10: 1.2. | B10: Добавленный капитал - Обыкновенные | C10: 0
A11: 1.3. | B11: Нераспределенная прибыль (убыток), в том числе капитальные резервы | C11: Формула
A12: а | B12: Капитальные резервы
A13: б | B13: Нераспределенная прибыль
A14: в | B14: Убыток за предыдущие периоды
A15: г | B15: Убыток за текущий год
A16: 1.4. | B16: Интерес меньшинства в консолидированных дочерних компаниях (согласно МБС)
A17: 1.5. | B17: Резерв на девальвацию
B18: Итого основного капитала уровня I до вычетов | C18: Формула
A19: 1.6. | B19: Вычеты из суммы основного капитала уровня I | C19: Формула
A20: а | B20: Нематериальные активы
A21: б | B21: Все инвестиции в капитал неконсолидированных хозяйствующих субъектов, в том числе в долговые обязательства, которые образуют капитал хозяйствующих субъектов
A22: в | B22: Инвестиции в капитал других банков
A23: I | B23: ВСЕГО СКОРРЕКТИРОВАННЫЙ ОСНОВНОЙ КАПИТАЛ УРОВНЯ I | C23: Формула
A24: 2 | B24: ДОБАВЛЕННЫЙ КАПИТАЛ УРОВНЯ 1
A25: 2.1. | B25: Некумулятивные бессрочные привилегированные акции | C25: =+C26+C27 -> 0
A26: а | B26: Полностью оплаченные привилегированные акции
A27: б | B27: Минус: Обратно Выкупленные привилегированные акции
A28: 2.2. | B28: Добавленный капитал - Привилегированные | C28: 0
A29: 2.3. | B29: Интерес меньшинства в консолидированных дочерних компаниях | C29: 0
A30: 2.4. | B30: Доля участия дочерних предприятий (выпущенные дочерними предприятиями и находящиеся во владении третьих лиц инструменты, приравненные к капиталу) | C30: 0
A31: II | B31: ВСЕГО ДОБАВЛЕННЫЙ КАПИТАЛ УРОВНЯ I | C31: =+C25+C28+C29+C30 -> 0
A32: III | B32: ВСЕГО СКОРРЕКТИРОВАННЫЙ КАПИТАЛ УРОВНЯ I | C32: Формула
B33: КАПИТАЛ УРОВНЯ II
A34: 3.1. | B34: Прибыль за текущий год
A35: 3.2. | B35: Резервы, создаваемые на стандартные кредиты (активы), в размере не более 1.25% от общей суммы активов, взвешенных с учетом риска | C35: =IF(Balance!#REF!<(C43*1.25%),Balance!#REF!,(C43*1.25%)) -> #REF!
A36: 3.3. | B36: Излишки оценочной стоимости прироста над первоначальной стоимостью
A37: 3.4. | B37: Другие инструменты капитала (не более 1/3 части капитала 1 уровня после вычетов)
A38: 3.5. | B38: Субординированный долг
A39: 3.6. | B39: Вычеты превышения Капитала Уровня II над Капиталом Уровня I | C39: Формула
B40: Итого капитала Уровня II | C40: =SUM(C34:C38) -> #REF!
A41: IV | B41: СКОРРЕКТИРОВАННЫЙ КАПИТАЛ УРОВНЯ II | C41: Формула
A42: V | B42: ВСЕГО РЕГУЛЯТИВНЫЙ КАПИТАЛ | C42: Формула
A43: VI | B43: ОБЩАЯ СУММА АКТИВОВ ВЗВЕШЕННЫХ С УЧЕТОМ РИСКА | C43: =+C44+C45+C46 -> #REF!
A44: а | B44: Сумма балансовых и забалансовых активов, взвешенных с учетом риска | C44: =+#REF! -> #REF!
A45: б | B45: Операционный риск | C45: =+#REF! -> #REF!
A46: в | B46: Рыночный риск | C46: =+#REF! -> #REF! | E46: =+#REF! -> #REF!
A47: VII | B47: КОЭФФИЦИЕНТ ОСНОВНОГО КАПИТАЛА УРОВНЯ I (I/VI) | C47: Формула
A48: VIII | B48: КОЭФФИЦИЕНТ КАПИТАЛА УРОВНЯ I (III/VI) | C48: Формула
A49: IX | B49: КОЭФФИЦИЕНТ ОБЩЕЙ СУММЫ КАПИТАЛА, ОСНОВАННОГО НА РИСКЕ (V/VI) | C49: Формула
A50: X | B50: Активы для расчета левеража | C50: Формула
A51: а | B51: Общие активы | C51: =+Balance!C47 -> 74634423198
A52: б | B52: Забалансовые инструменты | C52: =SUM(#REF!) -> #REF! | D52: =+#REF! -> #REF!
A53: в | B53: Деривативные (производные) инструменты | C53: =SUM(#REF!) -> #REF!
A54: г | B54: Минус: Строка 1.6. Итого вычетов из суммы основного капитала Уровня 1 | C54: =+C19 -> Формула
A55: XI | B55: Коэффициент левеража | C55: Формула
B57: Подпись Председателя правления:
B59: Подпись Главного Бухгалтера:

Sheet Liquidity Analysis
A1: ЛИКВИДЛИЛИК ТАҲЛИЛИ | E1: 16-жадвал
B2: =Balance!B3 -> "Ўзсаноатқурилишбанк" АТБ | D2: =+Balance!D3 -> 45289 | E2: минг сўмда
A3: № | B3: Ликвид активлар | C3: Жами | D3: Миллий валютада | E3: Хорижий валютада
B4: 1-қисм. Юқори ликвидли активлар | C4: фоизда
A5: 1.1 | B5: Кассадаги нақд пул ва бошқа тўлов ҳужжатлари | C5: =+'Bank Assets Analysis'!S6 -> 1565389581 | D5: =+'Bank Assets Analysis'!T6 -> 494142662 | E5: =+'Bank Assets Analysis'!U6 -> 1071246919
A6: 1.2 | B6: Банкнинг Марказий банкдаги маблағлар (мажбурий захираларсиз) | C6: =+'Bank Assets Analysis'!S7 -> 2352337755 | D6: =+'Bank Assets Analysis'!T7 -> 643421545 | E6: =+'Bank Assets Analysis'!U7 -> 1708916210
A7: 1.3 | B7: Ҳукумат ва Марказий банки томонидан чиқарилган қимматли қоғозлар | C7: =+'Bank Assets Analysis'!S19 -> 2033306103 | D7: =+'Bank Assets Analysis'!T19 -> 1910633909 | E7: =+'Bank Assets Analysis'!U19 -> 122672194
A8: 1.4 | B8: Инвестиция даражасидан паст бўлмаган рейтингга эга хорижий банкларда ва кредит рейтингига эга маҳаллий банкларда очилган вакиллик ҳисобварақларидаги маблағлар | C8: =+E8 -> 2934924132 | E8: =+'Bank Assets Analysis'!D10+'Bank Assets Analysis'!D11 -> 2934924132
A9: 1.5 | B9: Инвестиция даражасидан паст бўлмаган рейтингга эга бўлган мамлакатлардаги банкларда чет-эл валютасида овернайт шарти асосида жойлаштирилган депозитлар | C9: =+E9 -> 0 | E9: =+'Bank Assets Analysis'!F13 -> 0
A10: 1.6 | B10: ХВФ, Жаҳон банки гуруҳи, ҲМТ, ОТБ, Осиё инвестиция ва инфратузилма банки, ЕТTБ, Европа инвестиция банки, Европа инвестиция жамғармаси, Ислом тараққиёт банки ва Европа иттифоқи тараққиёт банки томонидан чиқарилган қимматли қоғозлар | C10: =+'Bank Assets Analysis'!S21 -> 0 | D10: =+'Bank Assets Analysis'!T21 -> 0 | E10: =+'Bank Assets Analysis'!U21 -> 0
A11: 1.7 | B11: Хатарлилик даражаси паст бўлган мамлакатлар ҳукуматиларининг қимматли қоғозлари | C11: =+'Bank Assets Analysis'!S20 -> 0 | D11: =+'Bank Assets Analysis'!T20 -> 0 | E11: =+'Bank Assets Analysis'!U20 -> 0
A12: 1.8 | B12: Қайтариб олинмайдиган кредит линиялари (ўзлаштирилмаган қисми) | C12: =+D12 -> 0 | D12: 0 | G12: Мазкур қатор ЎзР. Марказий банки билан тегишли кредит шартнома тузилганда тўлдириши керак. Ҳисобот даврига банкнинг нетто активларининг 2 % акс эттирилади.
A13: 1.9 | B13: Ипотекани қайта молиялаштириш ташкилотлари қимматли қоғозлари | C13: =+'Bank Assets Analysis'!S23 -> 10000000 | D13: =+'Bank Assets Analysis'!T23 -> 10000000 | E13: =+'Bank Assets Analysis'!U23 -> 0
A14: 1.10 | B14: РЕПО битимлари бўйича сотиб олинган юқори ликвидли қимматли қоғозлар | C14: =+'Bank Assets Analysis'!S34 -> 0 | D14: =+'Bank Assets Analysis'!T34 -> 0 | E14: =+'Bank Assets Analysis'!U34 -> 0
A15: 1.11 | B15: Гаровга қўйилган юқори ликвидли активлар | C15: =+'Bank Assets Analysis'!S18+'Bank Assets Analysis'!S43 -> 816807035 | D15: =+'Bank Assets Analysis'!T18+'Bank Assets Analysis'!T43 -> 816807035 | E15: =+'Bank Assets Analysis'!U18+'Bank Assets Analysis'!U43 -> 0
A16: 1.12 | B16: Жами юқори ликвидли активлар | C16: =SUM(C5:C14)-'Bank Liabilities Analysis'!S22-'Bank Liabilities Analysis'!T25-C15 -> 8078076483 | D16: =SUM(D5:D14)-'Bank Liabilities Analysis'!T22-'Bank Liabilities Analysis'!T25-D15 -> 2240317028 | E16: =SUM(E5:E14)-'Bank Liabilities Analysis'!U22-E15 -> 5837759455
B17: 2-қисм. Иқтисодий меъёрлар - Ликвидлилик
A18: 2.1 | B18: Юқори ликвидли активларнинг жами активларга нисбати | C18: =IFERROR((+C19/C20),0) -> 0.10943291 | D18: =IFERROR((+D19/D20),0) -> 0.083814447 | E18: =IFERROR((+E19/E20),0) -> 0.12397518
A19: 2.1.1 | B19: Юқори ликвидли активлар | C19: =+C16 -> 8078076483 | D19: =+D16 -> 2240317028 | E19: =+E16 -> 5837759455
A20: 2.1.2 | B20: Жами активлар (РЕПО битимлари айрилган ҳолда) | C20: =Balance!C47-'Bank Liabilities Analysis'!S34 -> 73817616163 | D20: =Balance!D47-'Bank Liabilities Analysis'!T34 -> 26729485172 | E20: =Balance!E47-'Bank Liabilities Analysis'!U34 -> 47088130991
A21: 2.2 | B21: Юқори ликвидли активларнинг қисқа муддатли мажбуриятларга нисбати | C21: =IFERROR((+C22/C23),0) -> 0.24125414 | D21: =IFERROR((+D22/D23),0) -> 0.19271715 | E21: =IFERROR((+E22/E23),0) -> 0.26706699
A22: 2.2.1 | B22: Юқори ликвидли активлар | C22: =+C16 -> 8078076483 | D22: =+D16 -> 2240317028 | E22: =+E16 -> 5837759455
A23: 2.2.2 | B23: Қисқа муддатли мажбуриятлар (РЕПО битимлари айрилган ҳолда) | C23: =+'Bank Liabilities Analysis'!C40+'Bank Liabilities Analysis'!E40+'Bank Liabilities Analysis'!G40+'Bank Liabilities Analysis'!I40+'Bank Liabilities Analysis'!K40+'Bank Liabilities Analysis'!M40-'Bank Liabilities Analysis'!C34-'Bank Liabilities Analysis'!E34-'Bank Liabilities Analysis'!G34-'Bank Liabilities Analysis'!I34-'Bank Liabilities Analysis'!K34-'Bank Liabilities Analysis'!M34 -> 33483680021 | D23: =+C23-E23 -> 11624896826 | E23: =+'Bank Liabilities Analysis'!D40+'Bank Liabilities Analysis'!F40+'Bank Liabilities Analysis'!H40+'Bank Liabilities Analysis'!J40+'Bank Liabilities Analysis'!L40+'Bank Liabilities Analysis'!N40-'Bank Liabilities Analysis'!D34-'Bank Liabilities Analysis'!F34-'Bank Liabilities Analysis'!H34-'Bank Liabilities Analysis'!J34-'Bank Liabilities Analysis'!L34-'Bank Liabilities Analysis'!N34 -> 21858783195
A24: 2.3 | B24: Ликвидлиликни қоплаш меъёри коэффициенти | C24: =IFERROR((+C25/C26),0) -> 1.7727614 | D24: =IFERROR((+D25/D26),0) -> 1.1596058 | E24: =IFERROR((+E25/E26),0) -> 2.2240679
A25: 2.3.1 | B25: Юқори ликвидли активлар | C25: =+C16 -> 8078076483 | D25: =+D16 -> 2240317028 | E25: =+E16 -> 5837759455
A26: 2.3.2 | B26: Кейинги 30 кун ичида соф чиқим | C26: =+'Bank Assets Analysis'!X62 -> 4.5567761e+09 | D26: =+'Bank Assets Analysis (нац)'!P58 -> 1.9319643e+09 | E26: =+'Bank Assets Analysis'!Z62 -> 2.6248118e+09
B27: 30 кунлик чиқим суммаси | C27: =+'Bank Assets Analysis'!X64 -> 7.6789545e+09 | D27: =+'Bank Assets Analysis (нац)'!P60 -> 3550751739 | E27: =+'Bank Assets Analysis'!Z64 -> 4.1282028e+09
B28: 30 кунлик кирим суммаси | C28: =+'Bank Assets Analysis'!X67 -> 3122178489 | D28: =+'Bank Assets Analysis (нац)'!P62 -> 1.6187874e+09 | E28: =+'Bank Assets Analysis'!Z67 -> 1.5033911e+09
A29: 2.4 | B29: Соф барқарор молиялаштириш меъёри | C29: =IFERROR((C30/C35),0) -> 1.0417986 | D29: =IFERROR((D30/D35),0) -> 1.0332124 | E29: =IFERROR((E30/E35),0) -> 1.0484544
A30: 2.5 | B30: Барқарор молиялаштиришнинг мавжуд суммаси | C30: =SUM(C31:C34) -> 5.0624082e+10 | D30: =SUM(D31:D34) -> 1.8788838e+10 | E30: =SUM(E31:E34) -> 3.1835244e+10
A31: 2.5.1 | B31: Хусусий капитал | C31: =Balance!C77 -> 8728360152 | D31: =Balance!D77 -> 8728360152 | E31: =Balance!E77 -> 0
A32: 2.5.2 | B32: Бир йилдан ортиқ муддатли мажбуриятлар | C32: ='Bank Liabilities Analysis'!O40+'Bank Liabilities Analysis'!Q40 -> 31605575990 | D32: =+'Bank Liabilities Analysis (нац)'!I41+'Bank Liabilities Analysis (нац)'!J41 -> 6327967189 | E32: ='Bank Liabilities Analysis'!P40+'Bank Liabilities Analysis'!R40 -> 25277608801
A33: 2.5.3 | B33: Бошқа муддатсиз мажбуриятларнинг 30 фоизи | C33: =+('Bank Liabilities Analysis'!C40)*0.3 -> 1.7660087e+09 | D33: =+('Bank Liabilities Analysis (нац)'!C41)*0.3 -> 1.1635219e+09 | E33: =+('Bank Liabilities Analysis'!D40)*0.3 -> 6.0248681e+08
A34: 2.5.4 | B34: Бир йилдан кам муддатли жами мажбуриятларнинг 30 фоизи | C34: =+('Bank Liabilities Analysis'!E40+'Bank Liabilities Analysis'!G40+'Bank Liabilities Analysis'!I40+'Bank Liabilities Analysis'!K40+'Bank Liabilities Analysis'!M40)*0.3 -> 8524137417 | D34: =+('Bank Liabilities Analysis (нац)'!D41+'Bank Liabilities Analysis (нац)'!E41+'Bank Liabilities Analysis (нац)'!F41+'Bank Liabilities Analysis (нац)'!G41+'Bank Liabilities Analysis (нац)'!H41)*0.3 -> 2.5689893e+09 | E34: =+('Bank Liabilities Analysis'!F40+'Bank Liabilities Analysis'!H40+'Bank Liabilities Analysis'!J40+'Bank Liabilities Analysis'!L40+'Bank Liabilities Analysis'!N40)*0.3 -> 5.9551481e+09
A35: 2.6 | B35: Барқарор молиялаштиришнинг зарур суммаси | C35: =SUM(C36:C41) -> 4.8592964e+10 | D35: =SUM(D36:D41) -> 1.8184876e+10 | E35: =SUM(E36:E41) -> 3.0363975e+10
A36: 2.6.1 | B36: Бир йилдан ортиқ муддатли активлар | C36: =+'Bank Assets Analysis'!O44-'Bank Assets Analysis'!O36+'Bank Assets Analysis'!Q44-'Bank Assets Analysis'!Q36 -> 36406725309 | D36: =+C36-E36 -> 11780272584 | E36: =+'Bank Assets Analysis'!P44-'Bank Assets Analysis'!P39-'Bank Assets Analysis'!P36+'Bank Assets Analysis'!R44-'Bank Assets Analysis'!R39-'Bank Assets Analysis'!R36 -> 24626452725
A37: 2.6.2 | B37: Банкнинг бошқа хусусий мулклари, соф | C37: =+'Bank Assets Analysis'!S36 -> 3125231142 | D37: =+'Bank Assets Analysis'!T36 -> 3125231142 | E37: =+'Bank Assets Analysis'!U36 -> 0
A38: 2.6.3 | B38: Суд жараёнида бўлган ёки белгиланган тартибда ундирилмаган кредит ва лизинглар, соф | C38: =+'Bank Assets Analysis'!C27+'Bank Assets Analysis'!C28+'Bank Assets Analysis'!C29+'Bank Assets Analysis'!C31 -> 813353525 | D38: =+'Bank Assets Analysis (нац)'!C27+'Bank Assets Analysis (нац)'!C28+'Bank Assets Analysis (нац)'!C29+'Bank Assets Analysis (нац)'!C31 -> 387345005 | E38: =+'Bank Assets Analysis'!D27+'Bank Assets Analysis'!D28+'Bank Assets Analysis'!D29+'Bank Assets Analysis'!D31 -> 426008520
A39: 2.6.4 | B39: Суд жараёнида бўлган ёки белгиланган тартибда ундирилмаган активлар, соф (2.6.3-қаторда кўрсатилмаган қисми) | C39: =+D39+E39 -> 0 | D39: 0 | E39: 0
A40: 2.6.5 | B40: Қайтариш муддати 1 йилдан кам бўлган бошқа активлар суммасининг 30 фоизи (қайтариш муддати 1 йилдан кам бўлган ёки муддатсиз ликвидли активлар бундан мустасно) | C40: =(+'Bank Assets Analysis'!S44-'Bank Assets Analysis'!O44-'Bank Assets Analysis'!Q44-'Liquidity Analysis'!C58)*0.3 -> 7.7971299e+09 | D40: =('Bank Assets Analysis (нац)'!K44-'Bank Assets Analysis (нац)'!I44-'Bank Assets Analysis (нац)'!J44-'Liquidity Analysis'!D58)*0.3 -> 2.8110512e+09 | E40: =('Bank Assets Analysis'!U44-'Bank Assets Analysis'!P44-'Bank Assets Analysis'!R44-'Liquidity Analysis'!E58)*0.3 -> 4.9419661e+09
A41: 2.6.6 | B41: Балансдан ташқари активларнинг 15 фоизи | C41: =+ROUND(SUM(Commitments!C4-Commitments!C5+Commitments!C7-Commitments!C8+Commitments!C10-'Bank Liabilities Analysis'!S18)*15%,0) -> 450523719 | D41: =+ROUND(SUM(Commitments!D4-Commitments!D5+Commitments!D7-Commitments!D8+Commitments!D10-'Bank Liabilities Analysis'!T18)*15%,0) -> 80975733 | E41: =+ROUND(SUM(Commitments!E4-Commitments!E5+Commitments!E7-Commitments!E8+Commitments!E10-'Bank Liabilities Analysis'!U18)*15%,0) -> 369547986
B43: Бошқарув Раис имзоси:
B45: Бош бухгалтер имзоси:
A50: № | B50: Ликвидли активлар | C50: Жами | D50: Миллий валютада | E50: Хорижий валютада
A51: 1. | B51: Кассадаги нақд пул ва бошқа тўлов ҳужжатлари ва қимматбаҳо металлар | C51: =+'Bank Assets Analysis'!S6+'Investment Securities'!B39 -> 1565390456 | D51: =+'Bank Assets Analysis'!T6+'Investment Securities'!C39 -> 494143537 | E51: =+'Bank Assets Analysis'!U6+'Investment Securities'!D39 -> 1071246919
A52: 2. | B52: Банкнинг Марказий банкдаги маблағлар | C52: =+'Bank Assets Analysis'!S7+'Bank Assets Analysis'!S8 -> 2526034447 | D52: =+'Bank Assets Analysis'!T7+'Bank Assets Analysis'!T8 -> 817118237 | E52: =+'Bank Assets Analysis'!U7+'Bank Assets Analysis'!U8 -> 1708916210
A53: 3. | B53: Бошқа банклар ва молиявий ташкилотлардан олиниши лозим бўлган маблағлар | C53: ='Bank Assets Analysis'!C10+'Bank Assets Analysis'!C11+'Bank Assets Analysis'!C12+'Bank Assets Analysis'!C15+'Bank Assets Analysis'!C16+'Bank Assets Analysis'!E16+'Bank Assets Analysis'!G16 -> 2973816111 | D53: =+C53-E53 -> 35951070 | E53: ='Bank Assets Analysis'!D10+'Bank Assets Analysis'!D11+'Bank Assets Analysis'!D15+'Bank Assets Analysis'!D16+'Bank Assets Analysis'!F16+'Bank Assets Analysis'!H16 -> 2937865041
A54: 3.1. | B54: Бошқа банклар ва молиявий ташкилотлардан олиниши лозим бўлган маблағлар - соф депозитлар | C54: =IF(F54>0,F54,0) -> 0 | D54: =IF(G54>0,G54,0) -> 0 | E54: =IF(H54>0,H54,0) -> 147041964 | F54: =(('Bank Assets Analysis'!E10+'Bank Assets Analysis'!E12+'Bank Assets Analysis'!G10+'Bank Assets Analysis'!C14+'Bank Assets Analysis'!E14+'Bank Assets Analysis'!G14)-'Bank Liabilities Analysis'!C26-'Bank Liabilities Analysis'!E26-'Bank Liabilities Analysis'!G26) -> -535480260 | G54: =+('Bank Assets Analysis'!E10-'Bank Assets Analysis'!F10+'Bank Assets Analysis'!G10-'Bank Assets Analysis'!H10+'Bank Assets Analysis'!E12-'Bank Assets Analysis'!F12+'Bank Assets Analysis'!C14-'Bank Assets Analysis'!D14+'Bank Assets Analysis'!E14-'Bank Assets Analysis'!F14+'Bank Assets Analysis'!G14-'Bank Assets Analysis'!H14)-('Bank Liabilities Analysis'!C26-'Bank Liabilities Analysis'!D26+'Bank Liabilities Analysis'!E26-'Bank Liabilities Analysis'!F26+'Bank Liabilities Analysis'!G26-'Bank Liabilities Analysis'!H26) -> -682522224 | H54: =(('Bank Assets Analysis'!F10+'Bank Assets Analysis'!F12+'Bank Assets Analysis'!H10+'Bank Assets Analysis'!D14+'Bank Assets Analysis'!F14+'Bank Assets Analysis'!H14)-'Bank Liabilities Analysis'!D26-'Bank Liabilities Analysis'!F26-'Bank Liabilities Analysis'!H26) -> 147041964
A55: 4. | B55: Ўзбекистон Республикаси Ҳукумати ва Марказий банк тамонидан чиқарилган қимматли қоғозлар (векселлар, облигациялар ва бошқа қимматли қоғозлар) | C55: =+'Investment Securities'!B5+'Investment Securities'!B6+'Investment Securities'!B19+'Investment Securities'!B20+'Investment Securities'!B21 -> 2046792700 | D55: =+'Investment Securities'!C5+'Investment Securities'!C6+'Investment Securities'!C19+'Investment Securities'!C20+'Investment Securities'!C21 -> 1923405000 | E55: =+'Investment Securities'!D5+'Investment Securities'!D6+'Investment Securities'!D19+'Investment Securities'!D20+'Investment Securities'!D21 -> 123387700
A56: 5. | B56: Таваккалчилик даражаси паст бўлган мамлакатлар томонидан чиқарилган қимматли қоғозлар
A57: 6. | B57: Бошқа осон сотиладиган қимматли қоғозлар
A58: 7. | B58: Жами ликвид активлар | C58: =SUM(C51:C57) -> 9112033714 | D58: =SUM(D51:D57) -> 3270617844 | E58: =SUM(E51:E57) -> 5988457834

Sheet Bank Assets Analysis
A1: БАНК АКТИВЛАРИ ТАҲЛИЛИ | X1: 17-жадвал
B2: =Balance!B3 -> "Ўзсаноатқурилишбанк" АТБ | X2: =+Balance!D3 -> 45289 | Z2: минг сўмда
A3: № | B3: Кўрсаткичлар | C3: Сўндириш муддати (кунларда) | S3: Жами | T3: шундан, | V3: Ликвидлиликни қоплаш меёри ҳисоб китоби
C4: Муддатсиз | E4: 1 дан 7 гача | G4: 8 дан 30 гача | I4: 31 дан 90 гача | K4: 91 дан 180 гача | M4: 181 дан 365 гача | O4: 366 дан 730 гача | Q4: 2 йилдан ортиқ
C5: Сумма | D5: шундан, хорижий валютада (сўм экв.) | E5: Сумма | F5: шундан, хорижий валютада (сўм экв.) | G5: Сумма | H5: шундан, хорижий валютада (сўм экв.) | I5: Сумма | J5: шундан, хорижий валютада (сўм экв.) | K5: Сумма | L5: шундан, хорижий валютада (сўм экв.) | M5: Сумма | N5: шундан, хорижий валютада (сўм экв.) | O5: Сумма | P5: шундан, хорижий валютада (сўм экв.) | Q5: Сумма | R5: шундан, хорижий валютада (сўм экв.) | T5: миллий валютада | U5: хорижий валютада (сўм экв.) | V5: Коэффициент | W5: Активлар | X5: Юқори ликвидли активлар/кирим | Y5: Активлар (хорижий валютада) | Z5: Юқори ликвидли активлар/кирим (хорижий валютада)
A6: 1 | B6: Кассадаги нақд пул ва бошқа тўлов ҳужжатлари | C6: 1565389581 | D6: 1071246919 | S6: =+C6+E6+G6+I6+K6+M6+O6+Q6 -> 1565389581 | T6: =+S6-U6 -> 494142662 | U6: =+D6+F6+H6+J6+L6+N6+P6+R6 -> 1071246919 | V6: 1 | W6: =+S6 -> 1565389581 | X6: =+W6*V6 -> 1565389581 | Y6: =+U6 -> 1071246919 | Z6: =+Y6*V6 -> 1071246919
A7: 2 | B7: Банкнинг Марказий банкдаги маблағлари (мажбурий захирасиз) | C7: 2352337755 | D7: 1708916210 | S7: =+C7+E7+G7+I7+K7+M7+O7+Q7 -> 2352337755 | T7: =+S7-U7 -> 643421545 | U7: =+D7+F7+H7+J7+L7+N7+P7+R7 -> 1708916210 | V7: 1 | W7: =S7 -> 2352337755 | X7: =+W7*V7 -> 2352337755 | Y7: =+U7 -> 1708916210 | Z7: =+Y7*V7 -> 1708916210
A8: 2.1 | B8: Банкнинг Марказий банкдаги мажбурий захира ҳисобварағидаги маблағлар | C8: 173696692 | D8: 0 | S8: =+C8+E8+G8+I8+K8+M8+O8+Q8 -> 173696692 | T8: =+S8-U8 -> 173696692 | U8: =+D8+F8+H8+J8+L8+N8+P8+R8 -> 0 | V8: 0
A9: 3 | B9: Бошқа банклар ва молиявий ташкилотлардан олиниши лозим бўлган маблағлар | C9: =SUM(C10:C16)-C13 -> 2973866111 | D9: =SUM(D10:D16)-D13 -> 2937865041 | E9: =SUM(E10:E16)-E13 -> 0 | F9: =SUM(F10:F16)-F13 -> 0 | G9: =SUM(G10:G16)-G13 -> 806705760 | H9: =SUM(H10:H16)-H13 -> 806705760 | I9: =SUM(I10:I16)-I13 -> 479340299 | J9: =SUM(J10:J16)-J13 -> 436101370 | ... R9: =SUM(R10:R16)-R13 -> 256027997 | S9: =+C9+E9+G9+I9+K9+M9+O9+Q9 -> 5562959410 | T9: =+S9-U9 -> 596977053 | U9: =+D9+F9+H9+J9+L9+N9+P9+R9 -> 4965982357
A10: 3.1 | B10: Таваккалчилик даражаси паст банклардаги вакиллик ҳисобварақлари (ностро) | C10: =2934939326-C11-C16 -> 2649976049 | D10: =2934939326-D11-D16 -> 2649976049 | S10: =+C10+E10+G10+I10+K10+M10+O10+Q10 -> 2649976049 | T10: =+S10-U10 -> 0 | U10: =+D10+F10+H10+J10+L10+N10+P10+R10 -> 2649976049 | V10: 1 | W10: =+C10 -> 2649976049 | X10: =+W10*V10 -> 2649976049 | Y10: =+D10 -> 2649976049 | Z10: =+Y10*V10 -> 2649976049
A11: 3.2 | B11: Маҳаллий банклардаги вакиллик ҳисобварақлари (ностро) | C11: 284948083 | D11: 284948083 | S11: =+C11 -> 284948083 | T11: =+S11-U11 -> 0 | U11: =+D11 -> 284948083 | V11: 1 | W11: =+C11 -> 284948083 | X11: =+W11*V11 -> 284948083 | Y11: =+D11 -> 284948083 | Z11: =+Y11*V11 -> 284948083
A12: 3.3 | B12: Овернайт шарти билан жойлаштирилган депозитлар | E12: 0 | F12: 0 | S12: =+E12 -> 0 | T12: =+S12-U12 -> 0 | U12: =+F12 -> 0 | V12: 1 | W12: =+E12-E13 -> 0 | X12: =+W12*V12 -> 0 | Y12: =+F12-F13 -> 0 | Z12: =+Y12*V12 -> 0
A13: 3.3.1. | B13: шундан, инвестицион даражадан паст бўлмаган рейтингга эга банкларга овернайт шарти билан жойлаштирилган хорижий валютадаги депозитлар | E13: 0 | F13: 0 | S13: =+E13 -> 0 | T13: =+S13-U13 -> 0 | U13: =+F13 -> 0 | V13: 1 | W13: =+F13 -> 0 | X13: =+W13*V13 -> 0 | Y13: =+F13 -> 0 | Z13: =+Y13*V13 -> 0
A14: 3.4 | B14: Банкнинг бошқа банклар/молиявий ташкилотлардаги ҳисобварақлари | C14: 50000 | D14: 0 | E14: 0 | F14: 0 | G14: 806705760 | H14: 806705760 | I14: 479340299 | J14: 436101370 | K14: 209081737 | L14: 169985735 | M14: 252942180 | N14: 185081550 | O14: 315534641 | P14: 174214904 | Q14: 525488682 | R14: 256027997 | S14: =+C14+E14+G14+I14+K14+M14+O14+Q14 -> 2589143299 | T14: =+S14-U14 -> 561025983 | U14: =+D14+F14+H14+J14+L14+N14+P14+R14 -> 2028117316 | V14: 1 | W14: =+C14+E14+G14+E10+G10+E11+G11 -> 806755760 | X14: =+W14*V14 -> 806755760 | Y14: =+D14+F14+H14+F10+H10+F11+H11 -> 806705760 | Z14: =+Y14*V14 -> 806705760
A15: 3.5 | B15: Пластик карталардан амалга оширилган тўловлар бўйича бошқа банклардан олиниши лозим бўлган маблағлар | C15: 38876785 | D15: 2925715 | S15: =+C15+E15+G15+I15+K15+M15+O15+Q15 -> 38876785 | T15: =+S15-U15 -> 35951070 | U15: =+D15+F15+H15+J15+L15+N15+P15+R15 -> 2925715 | V15: 1 | W15: =+C15+E15+G15 -> 38876785 | X15: =+W15*V15 -> 38876785 | Y15: =+D15+F15+H15 -> 2925715 | Z15: =+Y15*V15 -> 2925715
A16: 3.6 | B16: Бошқа моддалар | C16: 15194 | D16: 15194 | S16: =+C16+E16+G16+I16+K16+M16+O16+Q16 -> 15194 | T16: =+S16-U16 -> 0 | U16: =+D16+F16+H16+J16+L16+N16+P16+R16 -> 15194 | V16: 1 | W16: =+C16+E16+G16 -> 15194 | X16: =+W16*V16 -> 15194 | Y16: =+D16+F16+H16 -> 15194 | Z16: =+Y16*V16 -> 15194
A17: 4 | B17: Қимматли қоғозлар ва уларга қилинган инвестициялар, соф | C17: =SUM(C19:C24) -> 875 | D17: =SUM(D19:D24) -> 0 | E17: =SUM(E19:E24) -> 0 | F17: =SUM(F19:F24) -> 0 | G17: =SUM(G19:G24) -> 0 | H17: =SUM(H19:H24) -> 0 | I17: =SUM(I19:I24) -> 142672194 | J17: =SUM(J19:J24) -> 122672194 | ... R17: =SUM(R19:R24) -> 0 | S17: =+C17+E17+G17+I17+K17+M17+O17+Q17 -> 2043306978 | T17: =+S17-U17 -> 1920634784 | U17: =+D17+F17+H17+J17+L17+N17+P17+R17 -> 122672194
A18: 4a | B18: шу жумладан, таъминот остидаги юқори ликвидли қимматли қоғозлар | C18: =+'Bank Liabilities Analysis'!C34 -> 0 | D18: =+'Bank Liabilities Analysis'!D34 -> 0 | E18: =+'Bank Liabilities Analysis'!E34 -> 816807035 | F18: =+'Bank Liabilities Analysis'!F34 -> 0 | G18: =+'Bank Liabilities Analysis'!G34 -> 0 | H18: =+'Bank Liabilities Analysis'!H34 -> 0 | I18: =+'Bank Liabilities Analysis'!I34 -> 0 | J18: =+'Bank Liabilities Analysis'!J34 -> 0 | ... R18: =+'Bank Liabilities Analysis'!R34 -> 0 | S18: =+C18+E18+G18+I18+K18+M18+O18+Q18 -> 816807035 | T18: =+S18-U18 -> 816807035 | U18: =+D18+F18+H18+J18+L18+N18+P18+R18 -> 0 | V18: 1 | W18: =+C18+E18+G18 -> 816807035 | X18: =+W18*V18 -> 816807035 | Y18: =+D18+F18+H18 -> 0 | Z18: =+Y18*V18 -> 0
A19: 4.1 | B19: Ўзбекистон Республикаси Ҳукумати ва Марказий банк томонидан чиқарилган қимматли қоғозлар (векселлар, облигациялар ва бошқа қарз қимматли қоғозлар) | C19: 0 | D19: 0 | E19: 0 | F19: 0 | G19: 0 | H19: 0 | I19: 142672194 | J19: 122672194 | K19: 961548830 | L19: 0 | M19: 696557516 | N19: 0 | O19: 197102323 | P19: 0 | Q19: 35425240 | R19: 0 | S19: =+C19+E19+G19+I19+K19+M19+O19+Q19 -> 2033306103 | T19: =+S19-U19 -> 1910633909 | U19: =+D19+F19+H19+J19+L19+N19+P19+R19 -> 122672194 | V19: 1 | W19: =+S19 -> 2033306103 | X19: =+W19*V19 -> 2033306103 | Y19: =+U19 -> 122672194 | Z19: =+Y19*V19 -> 122672194
A20: 4.2 | B20: Таваккалчилик даражаси паст бўлган мамлакатларнинг қимматли қоғозлари | S20: =+C20+E20+G20+I20+K20+M20+O20+Q20 -> 0 | T20: =+S20-U20 -> 0 | U20: =+D20+F20+H20+J20+L20+N20+P20+R20 -> 0 | V20: 1 | W20: =+S20 -> 0 | X20: =+W20*V20 -> 0 | Y20: =+U20 -> 0 | Z20: =+Y20*V20 -> 0
A21: 4.3 | B21: ХВФ, Жаҳон банки гуруҳи, Осиё тараққиёт банки, Осиё инфраструктура инвестиция банки, ЕТТБ, Европа инвестиция банки, Европа инвестиция жамғармаси, Ислом тараққиёт банки ва Европа Кенгашининг тараққиёт банки томонидан чиқарилган қимматли қоғозлар | S21: =+C21+E21+G21+I21+K21+M21+O21+Q21 -> 0 | T21: =+S21-U21 -> 0 | U21: =+D21+F21+H21+J21+L21+N21+P21+R21 -> 0 | V21: 1 | W21: =+S21 -> 0 | X21: =+W21*V21 -> 0 | Y21: =+U21 -> 0 | Z21: =+Y21*V21 -> 0
A22: 4.4 | B22: Таваккалчилик даражаси паст бўлган мамлакатларнинг етакчи компаниялари қимматли қоғозлари | S22: =+C22+E22+G22+I22+K22+M22+O22+Q22 -> 0 | T22: =+S22-U22 -> 0 | U22: =+D22+F22+H22+J22+L22+N22+P22+R22 -> 0 | V22: 1 | W22: =+S22 -> 0 | X22: =+W22*V22 -> 0 | Y22: =+U22 -> 0 | Z22: =+Y22*V22 -> 0
A23: 4.5 | B23: Ипотекани қайта молиялаштириш ташкилотлари қимматли қоғозлари | Q23: 10000000 | R23: 0 | S23: =+C23+E23+G23+I23+K23+M23+O23+Q23 -> 10000000 | T23: =+S23-U23 -> 10000000 | U23: =+D23+F23+H23+J23+L23+N23+P23+R23 -> 0 | V23: 1 | W23: =+S23 -> 10000000 | X23: =+W23*V23 -> 10000000 | Y23: =+U23 -> 0 | Z23: =+Y23*V23 -> 0
A24: 4.6 | B24: Бошқалар | C24: 875 | D24: 0 | S24: =+C24+E24+G24+I24+K24+M24+O24+Q24 -> 875 | T24: =+S24-U24 -> 875 | U24: =+D24+F24+H24+J24+L24+N24+P24+R24 -> 0 | V24: 1 | W24: =+C24+E24+G24 -> 875 | X24: =+W24*V24 -> 875 | Y24: =+D24+F24+H24 -> 0 | Z24: =+Y24*V24 -> 0
A25: 5 | B25: Мижозларнинг аккредитив ва траст ҳужжатлари билан кафолатланган тратталари бўйича мажбуриятлари, соф | C25: 81572337 | D25: 81572337 | S25: =+C25+E25+G25+I25+K25+M25+O25+Q25 -> 81572337 | T25: =+S25-U25 -> 0 | U25: =+D25+F25+H25+J25+L25+N25+P25+R25 -> 81572337 | V25: 0.5 | W25: =+E25+G25 -> 0 | X25: =+W25*V25 -> 0 | Y25: =+F25+H25 -> 0 | Z25: =+Y25*V25 -> 0
A26: 6 | B26: Мижозларнинг банк олдидаги тўланмаган акцептлари бўйича мажбуриятлари, соф | S26: =+C26+E26+G26+I26+K26+M26+O26+Q26 -> 0 | T26: =+S26-U26 -> 0 | U26: =+D26+F26+H26+J26+L26+N26+P26+R26 -> 0 | V26: 0.5 | W26: =+E26+G26 -> 0 | X26: =+W26*V26 -> 0 | Y26: =+F26+H26 -> 0 | Z26: =+Y26*V26 -> 0
A27: 7 | B27: Марказий банкка берилган кредит ва лизинглар, соф | S27: =+C27+E27+G27+I27+K27+M27+O27+Q27 -> 0 | T27: =+S27-U27 -> 0 | U27: =+D27+F27+H27+J27+L27+N27+P27+R27 -> 0 | V27: 1 | W27: =+C27+E27+G27 -> 0 | X27: =+W27*V27 -> 0 | Y27: =+D27+F27+H27 -> 0 | Z27: =+Y27*V27 -> 0
A28: 8 | B28: Бошқа банкларга берилган кредит ва лизинглар, соф | S28: =+C28+E28+G28+I28+K28+M28+O28+Q28 -> 0 | T28: =+S28-U28 -> 0 | U28: =+D28+F28+H28+J28+L28+N28+P28+R28 -> 0 | V28: 0.5 | W28: =+E28+G28 -> 0 | X28: =+W28*V28 -> 0 | Y28: =+F28+H28 -> 0 | Z28: =+Y28*V28 -> 0
A29: 9 | B29: Мижозларга берилган кредит ва лизинглар, соф | C29: 729978490 | D29: 363804584 | E29: 588414426 | F29: 297804274 | G29: 1834027756 | H29: 817045961 | I29: 3526309483 | J29: 2129700124 | K29: 4572795107 | L29: 3125146392 | M29: 9925859830 | N29: 6576356844 | O29: 8710158511 | P29: 6145020272 | Q29: 26004656707 | R29: 17723012779 | S29: =+C29+E29+G29+I29+K29+M29+O29+Q29 -> 55892200310 | T29: =+S29-U29 -> 18714309080 | U29: =+D29+F29+H29+J29+L29+N29+P29+R29 -> 37177891230 | V29: 0.5 | W29: =+E29+G29 -> 2422442182 | X29: =+W29*V29 -> 1211221091 | Y29: =+F29+H29 -> 1114850235 | Z29: =+Y29*V29 -> 5.5742512e+08
A30: 9.1 | B30: шу жумладан, жисмоний шахсларга берилган кредит ва лизинглар | C30: 3555869 | D30: 0 | E30: 60906069 | F30: 0 | G30: 27865818 | H30: 0 | I30: 195740632 | J30: 0 | K30: 295764899 | L30: 0 | M30: 570767523 | N30: 0 | O30: 1037718485 | P30: 0 | Q30: 5591631789 | R30: 0 | S30: =+C30+E30+G30+I30+K30+M30+O30+Q30 -> 7783951084 | T30: =+S30-U30 -> 7783951084 | U30: =+D30+F30+H30+J30+L30+N30+P30+R30 -> 0 | V30: 0 | W30: =+E30+G30 -> 88771887 | X30: =+W30*V30 -> 0 | Y30: =+F30+H30 -> 0 | Z30: =+Y30*V30 -> 0
A31: 10 | B31: Суд ёки ижро иши юритиш жараёнидаги кредитлар ва лизинг, соф | C31: 83375035 | D31: 62203936 | S31: =+C31+E31+G31+I31+K31+M31+O31+Q31 -> 83375035 | T31: =+S31-U31 -> 21171099 | U31: =+D31+F31+H31+J31+L31+N31+P31+R31 -> 62203936 | V31: 0 | W31: =+E31+G31 -> 0 | X31: =+W31*V31 -> 0 | Y31: =+F31+H31 -> 0 | Z31: =+Y31*V31 -> 0
A32: 11 | B32: Инвестициялар, соф | C32: 406437548 | D32: 3164598 | S32: =+C32+E32+G32+I32+K32+M32+O32+Q32 -> 406437548 | T32: =+S32-U32 -> 403272950 | U32: =+D32+F32+H32+J32+L32+N32+P32+R32 -> 3164598 | V32: 0 | W32: =+E32+G32 -> 0 | X32: =+W32*V32 -> 0 | Y32: =+F32+H32 -> 0 | Z32: =+Y32*V32 -> 0
A33: 12 | B33: РЕПО битимлари бўйича сотиб олинган қимматли қоғозлар | C33: =+C34+C35 -> 0 | D33: =+D34+D35 -> 0 | E33: =+E34+E35 -> 0 | F33: =+F34+F35 -> 0 | G33: =+G34+G35 -> 0 | H33: =+H34+H35 -> 0 | I33: =+I34+I35 -> 0 | J33: =+J34+J35 -> 0 | ... Q33: =+Q34+Q35 -> 0 | S33: =+C33+E33+G33+I33+K33+M33+O33+Q33 -> 0 | T33: =+S33-U33 -> 0 | U33: =+D33+F33+H33+J33+L33+N33+P33+R33 -> 0 | V33: 0 | W33: =+E33+G33 -> 0 | X33: =+W33*V33 -> 0 | Y33: =+F33+H33 -> 0 | Z33: =+Y33*V33 -> 0
A34: 12.1 | B34: РЕПО битимлари бўйича сотиб олинган юқори ликвидли қимматли қоғозлар | S34: =+C34+E34+G34+I34+K34+M34+O34+Q34 -> 0 | T34: =+S34-U34 -> 0 | U34: =+D34+F34+H34+J34+L34+N34+P34+R34 -> 0 | V34: 1 | W34: =+S34 -> 0 | X34: =+W34*V34 -> 0 | Y34: =+U34 -> 0 | Z34: =+Y34*V34 -> 0
A35: 12.2 | B35: РЕПО битимлари бўйича сотиб олинган бошқа қимматли қоғозлар | S35: =+C35+E35+G35+I35+K35+M35+O35+Q35 -> 0 | T35: =+S35-U35 -> 0 | U35: =+D35+F35+H35+J35+L35+N35+P35+R35 -> 0 | V35: 0
A36: 13 | B36: Aсосий воситалар, соф | Q36: 3125231142 | R36: 0 | S36: =+C36+E36+G36+I36+K36+M36+O36+Q36 -> 3125231142 | T36: =+S36-U36 -> 3125231142 | U36: =+D36+F36+H36+J36+L36+N36+P36+R36 -> 0 | V36: 0
A37: 14 | B37: Банкнинг бошқа хусусий мулклари, соф | C37: 70914978 | D37: 0 | S37: =+C37+E37+G37+I37+K37+M37+O37+Q37 -> 70914978 | T37: =+S37-U37 -> 70914978 | U37: =+D37+F37+H37+J37+L37+N37+P37+R37 -> 0 | V37: 0
A38: 15 | B38: Ҳосилавий инструментларнинг ревальвацияси натижасида ўзлаштирилмаган фойда | S38: =+C38+E38+G38+I38+K38+M38+O38+Q38 -> 0 | T38: =+S38-U38 -> 0 | U38: =+D38+F38+H38+J38+L38+N38+P38+R38 -> 0 | V38: 0
A39: 16 | B39: Валюта савдоси ва валюта позициялари | S39: =+C39+E39+G39+I39+K39+M39+O39+Q39 -> 0 | T39: =+S39-U39 -> 0 | U39: =+D39+F39+H39+J39+L39+N39+P39+R39 -> 0 | V39: 0
A40: 17 | B40: Транзит ҳисобварақлари | S40: =+C40+E40+G40+I40+K40+M40+O40+Q40 -> 0 | T40: =+S40-U40 -> 0 | U40: =+D40+F40+H40+J40+L40+N40+P40+R40 -> 0 | V40: 0
A41: 18 | B41: Олиниши лозим бўлган ҳисобланган фоизлар | C41: 330177627 | D41: 201828438 | E41: 168957815 | F41: 66910691 | G41: 328047433 | H41: 205727847 | I41: 370299734 | J41: 244993456 | K41: 442349303 | L41: 345165185 | M41: 486829988 | N41: 346223671 | O41: 471992634 | P41: 263750779 | Q41: 136366571 | R41: 64425994 | S41: =+C41+E41+G41+I41+K41+M41+O41+Q41 -> 2735021105 | T41: =+S41-U41 -> 995995044 | U41: =+D41+F41+H41+J41+L41+N41+P41+R41 -> 1739026061 | V41: 0.5 | W41: =+E41+G41 -> 497005248 | X41: =+W41*V41 -> 248502624 | Y41: =+F41+H41 -> 272638538 | Z41: =+Y41*V41 -> 136319269
A42: 19 | B42: Бошқа активлар | C42: 523070138 | D42: 144095400 | G42: 18910189 | H42: 11359749 | S42: =+C42+E42+G42+I42+K42+M42+O42+Q42 -> 541980327 | T42: =+S42-U42 -> 386525178 | U42: =+D42+F42+H42+J42+L42+N42+P42+R42 -> 155455149 | V42: 0
A43: 20 | B43: Гаровга қўйилган юқори ликвидли активлар, 4a бундан мустасно | S43: =+C43+E43+G43+I43+K43+M43+O43+Q43 -> 0 | T43: =+S43-U43 -> 0 | U43: =+D43+F43+H43+J43+L43+N43+P43+R43 -> 0 | V43: 1 | W43: =+C43+E43+G43 -> 0 | X43: =+W43*V43 -> 0 | Y43: =+D43+F43+H43 -> 0 | Z43: =+Y43*V43 -> 0
A44: 21 | B44: ЖAМИ АКТИВЛАР | C44: =SUM(C6:C42)-C9-C13-C17-C18-C30-C33 -> 9290817167 | D44: =SUM(D6:D42)-D9-D13-D17-D18-D30-D33 -> 6574697463 | E44: =SUM(E6:E42)-E9-E13-E17-E18-E30-E33 -> 757372241 | F44: =SUM(F6:F42)-F9-F13-F17-F18-F30-F33 -> 364714965 | G44: =SUM(G6:G42)-G9-G13-G17-G18-G30-G33 -> 2987691138 | H44: =SUM(H6:H42)-H9-H13-H17-H18-H30-H33 -> 1840839317 | I44: =SUM(I6:I42)-I9-I13-I17-I18-I30-I33 -> 4518621710 | J44: =SUM(J6:J42)-J9-J13-J17-J18-J30-J33 -> 2933467144 | ... R44: =SUM(R6:R42)-R9-R13-R17-R18-R30-R33 -> 18043466770 | S44: =+C44+E44+G44+I44+K44+M44+O44+Q44 -> 74634423198 | T44: =+S44-U44 -> 27546292207 | U44: =+D44+F44+H44+J44+L44+N44+P44+R44 -> 47088130991 | X44: =+X12+X14+X15+X16+X18+X25+X26+X27+X28+X29+X41+X43 -> 3122178489 | Z44: =+Z12+Z14+Z15+Z16+Z18+Z25+Z26+Z27+Z28+Z29+Z41+Z43 -> 1.5033911e+09 | AA44: =+Balance!C47 -> 74634423198 | AB44: =+Balance!D47 -> 27546292207 | AC44: =+Balance!E47 -> 47088130991
B45: Балансдан ташқари мажбуриятлар | AA45: =+AA44-S44 -> 0 | AB45: =+AB44-T44 -> 0 | AC45: =+AC44-U44 -> 0
A46: 1 | B46: Банкнинг кредит ва лизинг бериш бўйича мажбуриятлари (91809) | C46: 171438 | D46: 0 | E46: 3534103 | F46: 0 | G46: 74770521 | H46: 5712851 | I46: 55142644 | J46: 6875935 | K46: 21040272 | L46: 611075 | M46: 75312401 | N46: 31464684 | O46: 38193188 | P46: 14847663 | Q46: 600978624 | R46: 278263010 | S46: =+C46+E46+G46+I46+K46+M46+O46+Q46 -> 869143191 | T46: =+S46-U46 -> 531367973 | U46: =+D46+F46+H46+J46+L46+N46+P46+R46 -> 337775218 | AA46: =+Commitments!C4 -> 869143191 | AB46: =+Commitments!D4 -> 531367973 | AC46: =+Commitments!E4 -> 337775218 | AD46: =+AA46-S46 -> 0 | AE46: =+AB46-T46 -> 0 | AF46: =+AC46-U46 -> 0
B47: шундан, ХМИ, Молия вазирлиги, фондлар ва бошқа ташкилотларнинг депозитлари билан таъминланган | S47: =+C47+E47+G47+I47+K47+M47+O47+Q47 -> 0 | T47: =+S47-U47 -> 0 | U47: =+D47+F47+H47+J47+L47+N47+P47+R47 -> 0 | AA47: =+Commitments!C5 -> 0 | AB47: =+Commitments!D5 -> 0 | AC47: =+Commitments!E5 -> 0
A48: 2 | B48: Кафолат ва кафилликлар (90993) | C48: 0 | D48: 0 | E48: 5727307 | F48: 5727307 | G48: 7812565 | H48: 7812565 | I48: 56090499 | J48: 50726936 | K48: 378286622 | L48: 374286622 | M48: 46203284 | N48: 46203284 | O48: 43358607 | P48: 43358607 | Q48: 920224136 | R48: 920224136 | S48: =+C48+E48+G48+I48+K48+M48+O48+Q48 -> 1457703020 | T48: =+S48-U48 -> 9363563 | U48: =+D48+F48+H48+J48+L48+N48+P48+R48 -> 1448339457 | AA48: =+Commitments!C7 -> 1457703020 | AB48: =+Commitments!D7 -> 9363563 | AC48: =+Commitments!E7 -> 1448339457 | AD48: =+AA48-S48 -> 0 | AE48: =+AB48-T48 -> 0 | AF48: =+AC48-U48 -> 0
B49: - шундан, алоҳида блокланган ҳисобварақлардаги депозитлар билан таъминланган кафолат ва кафилликлар | I49: 34693113 | J49: 34329550 | K49: 25206913 | L49: 25206913 | O49: 1974203 | P49: 1974203 | Q49: 124468577 | R49: 124468577 | S49: =+C49+E49+G49+I49+K49+M49+O49+Q49 -> 186342806 | T49: =+S49-U49 -> 363563 | U49: =+D49+F49+H49+J49+L49+N49+P49+R49 -> 185979243 | AA49: =+Commitments!C8 -> 186342806 | AB49: =+Commitments!D8 -> 363563 | AC49: =+Commitments!E8 -> 185979243
A50: 3 | B50: Аккредитивлар (90908-90958) | C50: 0 | D50: 0 | E50: 0 | F50: 0 | G50: 110222852 | H50: 110222852 | I50: 1003248325 | J50: 1003248325 | K50: 418842812 | L50: 418842812 | M50: 258314981 | N50: 258314981 | O50: 239375099 | P50: 239375099 | Q50: 0 | R50: 0 | S50: =+C50+E50+G50+I50+K50+M50+O50+Q50 -> 2030004069 | T50: =+S50-U50 -> 0 | U50: =+D50+F50+H50+J50+L50+N50+P50+R50 -> 2030004069 | AA50: =+Commitments!C10 -> 2030004069 | AB50: =+Commitments!D10 -> 0 | AC50: =+Commitments!E10 -> 2030004069 | AD50: =+AA50-S50 -> 0 | AE50: =+AB50-T50 -> 0 | AF50: =+AC50-U50 -> 0
B51: - шундан, 22602 баланс ҳисобварағида депозит билан таъминланганлар кўрсатилади | C51: 0 | D51: 0 | E51: 0 | F51: 0 | G51: 110222850 | H51: 110222850 | I51: 139730522 | J51: 139730522 | K51: 418842812 | L51: 418842812 | M51: 258314981 | N51: 258314981 | O51: 239375099 | P51: 239375099 | Q51: 0 | R51: 0 | S51: =+C51+E51+G51+I51+K51+M51+O51+Q51 -> 1166486264 | T51: =+S51-U51 -> 0 | U51: =+D51+F51+H51+J51+L51+N51+P51+R51 -> 1166486264
B53: Бошқарув Раис имзоси:
B55: Бош бухгалтер имзоси:
W57: По новым расчетам
W58: =+Balance!C47 -> 74634423198 | X58: =+Balance!D47 -> 27546292207 | Y58: =+Balance!E47 -> 47088130991
W59: Всего | Y59: Ин вал
W60: Приток | X60: =+X44 -> 3122178489 | Y60: Приток | Z60: =+Z44 -> 1.5033911e+09
W61: Высоко-ликвидные активы | X61: =+X6+X7+X10+X11+X13+X19+X20+X21+X22+X23+X34-X43-X18 -> 8079150536 | Y61: Высоко-ликвидные активы | Z61: =+Z6+Z7+Z10+Z11+Z13+Z19+Z20+Z21+Z22+Z23+Z34-Z43-Z18 -> 5837759455
W62: Чистый отток за 30 дней | X62: =+X64-X67 -> 4.5567761e+09 | Y62: Чистый отток за 30 дней | Z62: =+Z64-Z67 -> 2.6248118e+09
W64: Всего отток | X64: =+'Bank Liabilities Analysis'!W40+'Liquidity Analysis'!C41 -> 7.6789545e+09 | Y64: Отток | Z64: =+'Bank Liabilities Analysis'!X40+'Liquidity Analysis'!E41 -> 4.1282028e+09
W65: в том числе отток по внебалансу | X65: =+'Liquidity Analysis'!C41 -> 450523719 | Y65: в том числе отток по внебалансу | Z65: =+'Liquidity Analysis'!E41 -> 369547986
W67: Приток по положению | X67: =IF(X60>(X64*0.75),X64*0.75,X60) -> 3122178489 | Y67: Приток по положению | Z67: =IF(Z60>(Z64*0.75),Z64*0.75,Z60) -> 1.5033911e+09

Sheet Bank Assets Analysis (нац)
A2: МИЛЛИЙ ВАЛЮТАДАГИ БАНК АКТИВЛАРИ ТАҲЛИЛИ | L2: 17 А-жадвал
B3: =Balance!B3 -> "Ўзсаноатқурилишбанк" АТБ | K3: =+Balance!D3 -> 45289 | N3: =+Balance!E3 -> минг сўмда
A4: № | B4: Кўрсаткичлар | C4: Сўндириш муддати (кунларда) | K4: Жами | L4: Ликвидлиликни қоплаш меёри ҳисоб китоби
C5: Муддатсиз | D5: 1 дан 7 гача | E5: 8 дан 30 гача | F5: 31 дан 90 гача | G5: 91 дан 180 гача | H5: 181 дан 365 гача | I5: 366 дан 730 гача | J5: 2 йилдан ортиқ | L5: Коэффициент | M5: Активлар | N5: Юқори ликвидли активлар/кирим
A6: 1 | B6: Кассадаги нақд пул ва бошқа тўлов ҳужжатлари | C6: =+'Bank Assets Analysis'!C6-'Bank Assets Analysis'!D6 -> 494142662 | D6: =+'Bank Assets Analysis'!E6-'Bank Assets Analysis'!F6 -> 0 | E6: =+'Bank Assets Analysis'!G6-'Bank Assets Analysis'!H6 -> 0 | F6: =+'Bank Assets Analysis'!I6-'Bank Assets Analysis'!J6 -> 0 | G6: =+'Bank Assets Analysis'!K6-'Bank Assets Analysis'!L6 -> 0 | H6: =+'Bank Assets Analysis'!M6-'Bank Assets Analysis'!N6 -> 0 | I6: =+'Bank Assets Analysis'!O6-'Bank Assets Analysis'!P6 -> 0 | J6: =+'Bank Assets Analysis'!Q6-'Bank Assets Analysis'!R6 -> 0 | K6: =+C6+D6+E6+F6+G6+H6+I6+J6 -> 494142662 | L6: 1 | M6: =+K6 -> 494142662 | N6: =+M6*L6 -> 494142662
A7: 2 | B7: Банкнинг Марказий банкдаги маблағлари (мажбурий захирасиз) | C7: =+'Bank Assets Analysis'!C7-'Bank Assets Analysis'!D7 -> 643421545 | D7: =+'Bank Assets Analysis'!E7-'Bank Assets Analysis'!F7 -> 0 | E7: =+'Bank Assets Analysis'!G7-'Bank Assets Analysis'!H7 -> 0 | F7: =+'Bank Assets Analysis'!I7-'Bank Assets Analysis'!J7 -> 0 | G7: =+'Bank Assets Analysis'!K7-'Bank Assets Analysis'!L7 -> 0 | H7: =+'Bank Assets Analysis'!M7-'Bank Assets Analysis'!N7 -> 0 | I7: =+'Bank Assets Analysis'!O7-'Bank Assets Analysis'!P7 -> 0 | J7: =+'Bank Assets Analysis'!Q7-'Bank Assets Analysis'!R7 -> 0 | K7: =+C7+D7+E7+F7+G7+H7+I7+J7 -> 643421545 | L7: 1 | M7: =+K7 -> 643421545 | N7: =+M7*L7 -> 643421545
A8: 2.1 | B8: Банкнинг Марказий банкдаги мажбурий захира ҳисобварағидаги маблағлар | C8: =+'Bank Assets Analysis'!C8-'Bank Assets Analysis'!D8 -> 173696692 | D8: =+'Bank Assets Analysis'!E8-'Bank Assets Analysis'!F8 -> 0 | E8: =+'Bank Assets Analysis'!G8-'Bank Assets Analysis'!H8 -> 0 | F8: =+'Bank Assets Analysis'!I8-'Bank Assets Analysis'!J8 -> 0 | G8: =+'Bank Assets Analysis'!K8-'Bank Assets Analysis'!L8 -> 0 | H8: =+'Bank Assets Analysis'!M8-'Bank Assets Analysis'!N8 -> 0 | I8: =+'Bank Assets Analysis'!O8-'Bank Assets Analysis'!P8 -> 0 | J8: =+'Bank Assets Analysis'!Q8-'Bank Assets Analysis'!R8 -> 0 | K8: =+C8+D8+E8+F8+G8+H8+I8+J8 -> 173696692 | L8: 0 | N8: =+M8*L8 -> 0
A9: 3 | B9: Бошқа банклар ва молиявий ташкилотлардан олиниши лозим бўлган маблағлар | C9: =SUM(C10:C16)-C13 -> 36001070 | D9: =SUM(D10:D16)-D13 -> 0 | E9: =SUM(E10:E16)-E13 -> 0 | F9: =SUM(F10:F16)-F13 -> 43238929 | G9: =SUM(G10:G16)-G13 -> 39096002 | H9: =SUM(H10:H16)-H13 -> 67860630 | I9: =SUM(I10:I16)-I13 -> 141319737 | J9: =SUM(J10:J16)-J13 -> 269460685 | K9: =+C9+D9+E9+F9+G9+H9+I9+J9 -> 596977053 | N9: =+M9*L9 -> 0
A10: 3.1 | B10: Таваккалчилик даражаси паст банклардаги вакиллик ҳисобварақлари (ностро) | C10: =+'Bank Assets Analysis'!C10-'Bank Assets Analysis'!D10 -> 0 | D10: =+'Bank Assets Analysis'!E10-'Bank Assets Analysis'!F10 -> 0 | E10: =+'Bank Assets Analysis'!G10-'Bank Assets Analysis'!H10 -> 0 | F10: =+'Bank Assets Analysis'!I10-'Bank Assets Analysis'!J10 -> 0 | G10: =+'Bank Assets Analysis'!K10-'Bank Assets Analysis'!L10 -> 0 | H10: =+'Bank Assets Analysis'!M10-'Bank Assets Analysis'!N10 -> 0 | I10: =+'Bank Assets Analysis'!O10-'Bank Assets Analysis'!P10 -> 0 | J10: =+'Bank Assets Analysis'!Q10-'Bank Assets Analysis'!R10 -> 0 | K10: =+C10+D10+E10+F10+G10+H10+I10+J10 -> 0 | L10: 1 | M10: =+C10 -> 0 | N10: =+M10*L10 -> 0
A11: 3.2 | B11: Маҳаллий банклардаги вакиллик ҳисобварақлари (ностро) | C11: =+'Bank Assets Analysis'!C11-'Bank Assets Analysis'!D11 -> 0 | D11: =+'Bank Assets Analysis'!E11-'Bank Assets Analysis'!F11 -> 0 | E11: =+'Bank Assets Analysis'!G11-'Bank Assets Analysis'!H11 -> 0 | F11: =+'Bank Assets Analysis'!I11-'Bank Assets Analysis'!J11 -> 0 | G11: =+'Bank Assets Analysis'!K11-'Bank Assets Analysis'!L11 -> 0 | H11: =+'Bank Assets Analysis'!M11-'Bank Assets Analysis'!N11 -> 0 | I11: =+'Bank Assets Analysis'!O11-'Bank Assets Analysis'!P11 -> 0 | J11: =+'Bank Assets Analysis'!Q11-'Bank Assets Analysis'!R11 -> 0 | K11: =+C11+D11+E11+F11+G11+H11+I11+J11 -> 0 | L11: 1 | M11: =+C11 -> 0 | N11: =+M11*L11 -> 0
A12: 3.3 | B12: Овернайт шарти билан жойлаштирилган депозитлар | C12: =+'Bank Assets Analysis'!C12-'Bank Assets Analysis'!D12 -> 0 | D12: =+'Bank Assets Analysis'!E12-'Bank Assets Analysis'!F12 -> 0 | E12: =+'Bank Assets Analysis'!G12-'Bank Assets Analysis'!H12 -> 0 | F12: =+'Bank Assets Analysis'!I12-'Bank Assets Analysis'!J12 -> 0 | G12: =+'Bank Assets Analysis'!K12-'Bank Assets Analysis'!L12 -> 0 | H12: =+'Bank Assets Analysis'!M12-'Bank Assets Analysis'!N12 -> 0 | I12: =+'Bank Assets Analysis'!O12-'Bank Assets Analysis'!P12 -> 0 | J12: =+'Bank Assets Analysis'!Q12-'Bank Assets Analysis'!R12 -> 0 | K12: =+C12+D12+E12+F12+G12+H12+I12+J12 -> 0 | L12: 1 | M12: =+D12-D13 -> 0 | N12: =+M12*L12 -> 0
A13: 3.3.1. | B13: шундан, инвестицион даражадан паст бўлмаган рейтингга эга банкларга овернайт шарти билан жойлаштирилган хорижий валютадаги депозитлар | C13: =+'Bank Assets Analysis'!C13-'Bank Assets Analysis'!D13 -> 0 | D13: =+'Bank Assets Analysis'!E13-'Bank Assets Analysis'!F13 -> 0 | E13: =+'Bank Assets Analysis'!G13-'Bank Assets Analysis'!H13 -> 0 | F13: =+'Bank Assets Analysis'!I13-'Bank Assets Analysis'!J13 -> 0 | G13: =+'Bank Assets Analysis'!K13-'Bank Assets Analysis'!L13 -> 0 | H13: =+'Bank Assets Analysis'!M13-'Bank Assets Analysis'!N13 -> 0 | I13: =+'Bank Assets Analysis'!O13-'Bank Assets Analysis'!P13 -> 0 | J13: =+'Bank Assets Analysis'!Q13-'Bank Assets Analysis'!R13 -> 0 | K13: =+C13+D13+E13+F13+G13+H13+I13+J13 -> 0 | L13: 1 | M13: =+D13 -> 0 | N13: =+M13*L13 -> 0
A14: 3.4 | B14: Банкнинг бошқа банклар/молиявий ташкилотлардаги ҳисобварақлари | C14: =+'Bank Assets Analysis'!C14-'Bank Assets Analysis'!D14 -> 50000 | D14: =+'Bank Assets Analysis'!E14-'Bank Assets Analysis'!F14 -> 0 | E14: =+'Bank Assets Analysis'!G14-'Bank Assets Analysis'!H14 -> 0 | F14: =+'Bank Assets Analysis'!I14-'Bank Assets Analysis'!J14 -> 43238929 | G14: =+'Bank Assets Analysis'!K14-'Bank Assets Analysis'!L14 -> 39096002 | H14: =+'Bank Assets Analysis'!M14-'Bank Assets Analysis'!N14 -> 67860630 | I14: =+'Bank Assets Analysis'!O14-'Bank Assets Analysis'!P14 -> 141319737 | J14: =+'Bank Assets Analysis'!Q14-'Bank Assets Analysis'!R14 -> 269460685 | K14: =+C14+D14+E14+F14+G14+H14+I14+J14 -> 561025983 | L14: 1 | M14: =+C14+D14+E14+D10+D11 -> 50000 | N14: =+M14*L14 -> 50000
A15: 3.5 | B15: Пластик карталардан амалга оширилган тўловлар бўйича бошқа банклардан олиниши лозим бўлган маблағлар | C15: =+'Bank Assets Analysis'!C15-'Bank Assets Analysis'!D15 -> 35951070 | D15: =+'Bank Assets Analysis'!E15-'Bank Assets Analysis'!F15 -> 0 | E15: =+'Bank Assets Analysis'!G15-'Bank Assets Analysis'!H15 -> 0 | F15: =+'Bank Assets Analysis'!I15-'Bank Assets Analysis'!J15 -> 0 | G15: =+'Bank Assets Analysis'!K15-'Bank Assets Analysis'!L15 -> 0 | H15: =+'Bank Assets Analysis'!M15-'Bank Assets Analysis'!N15 -> 0 | I15: =+'Bank Assets Analysis'!O15-'Bank Assets Analysis'!P15 -> 0 | J15: =+'Bank Assets Analysis'!Q15-'Bank Assets Analysis'!R15 -> 0 | K15: =+C15+D15+E15+F15+G15+H15+I15+J15 -> 35951070 | L15: 1 | M15: =+C15+D15+E15 -> 35951070 | N15: =+M15*L15 -> 35951070
A16: 3.6 | B16: Бошқа моддалар | C16: =+'Bank Assets Analysis'!C16-'Bank Assets Analysis'!D16 -> 0 | D16: =+'Bank Assets Analysis'!E16-'Bank Assets Analysis'!F16 -> 0 | E16: =+'Bank Assets Analysis'!G16-'Bank Assets Analysis'!H16 -> 0 | F16: =+'Bank Assets Analysis'!I16-'Bank Assets Analysis'!J16 -> 0 | G16: =+'Bank Assets Analysis'!K16-'Bank Assets Analysis'!L16 -> 0 | H16: =+'Bank Assets Analysis'!M16-'Bank Assets Analysis'!N16 -> 0 | I16: =+'Bank Assets Analysis'!O16-'Bank Assets Analysis'!P16 -> 0 | J16: =+'Bank Assets Analysis'!Q16-'Bank Assets Analysis'!R16 -> 0 | K16: =+C16+D16+E16+F16+G16+H16+I16+J16 -> 0 | L16: 1 | M16: =+C16+D16+E16 -> 0 | N16: =+M16*L16 -> 0
A17: 4 | B17: Қимматли қоғозлар ва уларга қилинган инвестициялар, соф | C17: =+'Bank Assets Analysis'!C17-'Bank Assets Analysis'!D17 -> 875 | D17: =+'Bank Assets Analysis'!E17-'Bank Assets Analysis'!F17 -> 0 | E17: =+'Bank Assets Analysis'!G17-'Bank Assets Analysis'!H17 -> 0 | F17: =+'Bank Assets Analysis'!I17-'Bank Assets Analysis'!J17 -> 20000000 | G17: =+'Bank Assets Analysis'!K17-'Bank Assets Analysis'!L17 -> 961548830 | H17: =+'Bank Assets Analysis'!M17-'Bank Assets Analysis'!N17 -> 696557516 | I17: =+'Bank Assets Analysis'!O17-'Bank Assets Analysis'!P17 -> 197102323 | J17: =+'Bank Assets Analysis'!Q17-'Bank Assets Analysis'!R17 -> 45425240 | K17: =+C17+D17+E17+F17+G17+H17+I17+J17 -> 1920634784 | N17: =+M17*L17 -> 0
A18: 4a | B18: шу жумладан, таъминот остидаги юқори ликвидли қимматли қоғозлар | C18: =+'Bank Assets Analysis'!C18-'Bank Assets Analysis'!D18 -> 0 | D18: =+'Bank Assets Analysis'!E18-'Bank Assets Analysis'!F18 -> 816807035 | E18: =+'Bank Assets Analysis'!G18-'Bank Assets Analysis'!H18 -> 0 | F18: =+'Bank Assets Analysis'!I18-'Bank Assets Analysis'!J18 -> 0 | G18: =+'Bank Assets Analysis'!K18-'Bank Assets Analysis'!L18 -> 0 | H18: =+'Bank Assets Analysis'!M18-'Bank Assets Analysis'!N18 -> 0 | I18: =+'Bank Assets Analysis'!O18-'Bank Assets Analysis'!P18 -> 0 | J18: =+'Bank Assets Analysis'!Q18-'Bank Assets Analysis'!R18 -> 0 | K18: =+C18+D18+E18+F18+G18+H18+I18+J18 -> 816807035 | L18: 1 | M18: =SUM(C18:E18) -> 816807035 | N18: =+M18*L18 -> 816807035
A19: 4.1 | B19: Ўзбекистон Республикаси Ҳукумати ва Марказий банк томонидан чиқарилган қимматли қоғозлар (векселлар, облигациялар ва бошқа қарз қимматли қоғозлар) | C19: =+'Bank Assets Analysis'!C19-'Bank Assets Analysis'!D19 -> 0 | D19: =+'Bank Assets Analysis'!E19-'Bank Assets Analysis'!F19 -> 0 | E19: =+'Bank Assets Analysis'!G19-'Bank Assets Analysis'!H19 -> 0 | F19: =+'Bank Assets Analysis'!I19-'Bank Assets Analysis'!J19 -> 20000000 | G19: =+'Bank Assets Analysis'!K19-'Bank Assets Analysis'!L19 -> 961548830 | H19: =+'Bank Assets Analysis'!M19-'Bank Assets Analysis'!N19 -> 696557516 | I19: =+'Bank Assets Analysis'!O19-'Bank Assets Analysis'!P19 -> 197102323 | J19: =+'Bank Assets Analysis'!Q19-'Bank Assets Analysis'!R19 -> 35425240 | K19: =+C19+D19+E19+F19+G19+H19+I19+J19 -> 1910633909 | L19: 1 | M19: =+K19 -> 1910633909 | N19: =+M19*L19 -> 1910633909
A20: 4.2 | B20: Таваккалчилик даражаси паст бўлган мамлакатларнинг қимматли қоғозлари | C20: =+'Bank Assets Analysis'!C20-'Bank Assets Analysis'!D20 -> 0 | D20: =+'Bank Assets Analysis'!E20-'Bank Assets Analysis'!F20 -> 0 | E20: =+'Bank Assets Analysis'!G20-'Bank Assets Analysis'!H20 -> 0 | F20: =+'Bank Assets Analysis'!I20-'Bank Assets Analysis'!J20 -> 0 | G20: =+'Bank Assets Analysis'!K20-'Bank Assets Analysis'!L20 -> 0 | H20: =+'Bank Assets Analysis'!M20-'Bank Assets Analysis'!N20 -> 0 | I20: =+'Bank Assets Analysis'!O20-'Bank Assets Analysis'!P20 -> 0 | J20: =+'Bank Assets Analysis'!Q20-'Bank Assets Analysis'!R20 -> 0 | K20: =+C20+D20+E20+F20+G20+H20+I20+J20 -> 0 | L20: 1 | M20: =+K20 -> 0 | N20: =+M20*L20 -> 0
A21: 4.3 | B21: ХВФ, Жаҳон банки гуруҳи, Осиё тараққиёт банки, Осиё инфраструктура инвестиция банки, ЕТТБ, Европа инвестиция банки, Европа инвестиция жамғармаси, Ислом тараққиёт банки ва Европа Кенгашининг тараққиёт банки томонидан чиқарилган қимматли қоғозлар | C21: =+'Bank Assets Analysis'!C21-'Bank Assets Analysis'!D21 -> 0 | D21: =+'Bank Assets Analysis'!E21-'Bank Assets Analysis'!F21 -> 0 | E21: =+'Bank Assets Analysis'!G21-'Bank Assets Analysis'!H21 -> 0 | F21: =+'Bank Assets Analysis'!I21-'Bank Assets Analysis'!J21 -> 0 | G21: =+'Bank Assets Analysis'!K21-'Bank Assets Analysis'!L21 -> 0 | H21: =+'Bank Assets Analysis'!M21-'Bank Assets Analysis'!N21 -> 0 | I21: =+'Bank Assets Analysis'!O21-'Bank Assets Analysis'!P21 -> 0 | J21: =+'Bank Assets Analysis'!Q21-'Bank Assets Analysis'!R21 -> 0 | K21: =+C21+D21+E21+F21+G21+H21+I21+J21 -> 0 | L21: 1 | M21: =+K21 -> 0 | N21: =+M21*L21 -> 0
A22: 4.4 | B22: Таваккалчилик даражаси паст бўлган мамлакатларнинг етакчи компаниялари қимматли қоғозлари | C22: =+'Bank Assets Analysis'!C22-'Bank Assets Analysis'!D22 -> 0 | D22: =+'Bank Assets Analysis'!E22-'Bank Assets Analysis'!F22 -> 0 | E22: =+'Bank Assets Analysis'!G22-'Bank Assets Analysis'!H22 -> 0 | F22: =+'Bank Assets Analysis'!I22-'Bank Assets Analysis'!J22 -> 0 | G22: =+'Bank Assets Analysis'!K22-'Bank Assets Analysis'!L22 -> 0 | H22: =+'Bank Assets Analysis'!M22-'Bank Assets Analysis'!N22 -> 0 | I22: =+'Bank Assets Analysis'!O22-'Bank Assets Analysis'!P22 -> 0 | J22: =+'Bank Assets Analysis'!Q22-'Bank Assets Analysis'!R22 -> 0 | K22: =+C22+D22+E22+F22+G22+H22+I22+J22 -> 0 | L22: 1 | M22: =+D22+E22 -> 0 | N22: =+M22*L22 -> 0
A23: 4.5 | B23: Ипотекани қайта молиялаштириш ташкилотлари қимматли қоғозлари | C23: =+'Bank Assets Analysis'!C23-'Bank Assets Analysis'!D23 -> 0 | D23: =+'Bank Assets Analysis'!E23-'Bank Assets Analysis'!F23 -> 0 | E23: =+'Bank Assets Analysis'!G23-'Bank Assets Analysis'!H23 -> 0 | F23: =+'Bank Assets Analysis'!I23-'Bank Assets Analysis'!J23 -> 0 | G23: =+'Bank Assets Analysis'!K23-'Bank Assets Analysis'!L23 -> 0 | H23: =+'Bank Assets Analysis'!M23-'Bank Assets Analysis'!N23 -> 0 | I23: =+'Bank Assets Analysis'!O23-'Bank Assets Analysis'!P23 -> 0 | J23: =+'Bank Assets Analysis'!Q23-'Bank Assets Analysis'!R23 -> 10000000 | K23: =+C23+D23+E23+F23+G23+H23+I23+J23 -> 10000000 | L23: 1 | M23: =+D23+E23 -> 0 | N23: =+M23*L23 -> 0
A24: 4.6 | B24: Бошқалар | C24: =+'Bank Assets Analysis'!C24-'Bank Assets Analysis'!D24 -> 875 | D24: =+'Bank Assets Analysis'!E24-'Bank Assets Analysis'!F24 -> 0 | E24: =+'Bank Assets Analysis'!G24-'Bank Assets Analysis'!H24 -> 0 | F24: =+'Bank Assets Analysis'!I24-'Bank Assets Analysis'!J24 -> 0 | G24: =+'Bank Assets Analysis'!K24-'Bank Assets Analysis'!L24 -> 0 | H24: =+'Bank Assets Analysis'!M24-'Bank Assets Analysis'!N24 -> 0 | I24: =+'Bank Assets Analysis'!O24-'Bank Assets Analysis'!P24 -> 0 | J24: =+'Bank Assets Analysis'!Q24-'Bank Assets Analysis'!R24 -> 0 | K24: =+C24+D24+E24+F24+G24+H24+I24+J24 -> 875 | L24: 1 | M24: =+C24+D24+E24 -> 875 | N24: =+M24*L24 -> 875
A25: 5 | B25: Мижозларнинг аккредитив ва траст ҳужжатлари билан кафолатланган тратталари бўйича мажбуриятлари, соф | C25: =+'Bank Assets Analysis'!C25-'Bank Assets Analysis'!D25 -> 0 | D25: =+'Bank Assets Analysis'!E25-'Bank Assets Analysis'!F25 -> 0 | E25: =+'Bank Assets Analysis'!G25-'Bank Assets Analysis'!H25 -> 0 | F25: =+'Bank Assets Analysis'!I25-'Bank Assets Analysis'!J25 -> 0 | G25: =+'Bank Assets Analysis'!K25-'Bank Assets Analysis'!L25 -> 0 | H25: =+'Bank Assets Analysis'!M25-'Bank Assets Analysis'!N25 -> 0 | I25: =+'Bank Assets Analysis'!O25-'Bank Assets Analysis'!P25 -> 0 | J25: =+'Bank Assets Analysis'!Q25-'Bank Assets Analysis'!R25 -> 0 | K25: =+C25+D25+E25+F25+G25+H25+I25+J25 -> 0 | L25: 0.5 | M25: =+D25+E25 -> 0 | N25: =+M25*L25 -> 0
A26: 6 | B26: Мижозларнинг банк олдидаги тўланмаган акцептлари бўйича мажбуриятлари, соф | C26: =+'Bank Assets Analysis'!C26-'Bank Assets Analysis'!D26 -> 0 | D26: =+'Bank Assets Analysis'!E26-'Bank Assets Analysis'!F26 -> 0 | E26: =+'Bank Assets Analysis'!G26-'Bank Assets Analysis'!H26 -> 0 | F26: =+'Bank Assets Analysis'!I26-'Bank Assets Analysis'!J26 -> 0 | G26: =+'Bank Assets Analysis'!K26-'Bank Assets Analysis'!L26 -> 0 | H26: =+'Bank Assets Analysis'!M26-'Bank Assets Analysis'!N26 -> 0 | I26: =+'Bank Assets Analysis'!O26-'Bank Assets Analysis'!P26 -> 0 | J26: =+'Bank Assets Analysis'!Q26-'Bank Assets Analysis'!R26 -> 0 | K26: =+C26+D26+E26+F26+G26+H26+I26+J26 -> 0 | L26: 0.5 | M26: =+D26+E26 -> 0 | N26: =+M26*L26 -> 0
A27: 7 | B27: Марказий банкка берилган кредит ва лизинглар, соф | C27: =+'Bank Assets Analysis'!C27-'Bank Assets Analysis'!D27 -> 0 | D27: =+'Bank Assets Analysis'!E27-'Bank Assets Analysis'!F27 -> 0 | E27: =+'Bank Assets Analysis'!G27-'Bank Assets Analysis'!H27 -> 0 | F27: =+'Bank Assets Analysis'!I27-'Bank Assets Analysis'!J27 -> 0 | G27: =+'Bank Assets Analysis'!K27-'Bank Assets Analysis'!L27 -> 0 | H27: =+'Bank Assets Analysis'!M27-'Bank Assets Analysis'!N27 -> 0 | I27: =+'Bank Assets Analysis'!O27-'Bank Assets Analysis'!P27 -> 0 | J27: =+'Bank Assets Analysis'!Q27-'Bank Assets Analysis'!R27 -> 0 | K27: =+C27+D27+E27+F27+G27+H27+I27+J27 -> 0 | L27: 1 | M27: =C27+D27+E27 -> 0 | N27: =+M27*L27 -> 0
A28: 8 | B28: Бошқа банкларга берилган кредит ва лизинглар, соф | C28: =+'Bank Assets Analysis'!C28-'Bank Assets Analysis'!D28 -> 0 | D28: =+'Bank Assets Analysis'!E28-'Bank Assets Analysis'!F28 -> 0 | E28: =+'Bank Assets Analysis'!G28-'Bank Assets Analysis'!H28 -> 0 | F28: =+'Bank Assets Analysis'!I28-'Bank Assets Analysis'!J28 -> 0 | G28: =+'Bank Assets Analysis'!K28-'Bank Assets Analysis'!L28 -> 0 | H28: =+'Bank Assets Analysis'!M28-'Bank Assets Analysis'!N28 -> 0 | I28: =+'Bank Assets Analysis'!O28-'Bank Assets Analysis'!P28 -> 0 | J28: =+'Bank Assets Analysis'!Q28-'Bank Assets Analysis'!R28 -> 0 | K28: =+C28+D28+E28+F28+G28+H28+I28+J28 -> 0 | L28: 0.5 | M28: =+D28+E28 -> 0 | N28: =+M28*L28 -> 0
A29: 9 | B29: Мижозларга берилган кредит ва лизинглар, соф | C29: =+'Bank Assets Analysis'!C29-'Bank Assets Analysis'!D29 -> 366173906 | D29: =+'Bank Assets Analysis'!E29-'Bank Assets Analysis'!F29 -> 290610152 | E29: =+'Bank Assets Analysis'!G29-'Bank Assets Analysis'!H29 -> 1016981795 | F29: =+'Bank Assets Analysis'!I29-'Bank Assets Analysis'!J29 -> 1396609359 | G29: =+'Bank Assets Analysis'!K29-'Bank Assets Analysis'!L29 -> 1447648715 | H29: =+'Bank Assets Analysis'!M29-'Bank Assets Analysis'!N29 -> 3349502986 | I29: =+'Bank Assets Analysis'!O29-'Bank Assets Analysis'!P29 -> 2565138239 | J29: =+'Bank Assets Analysis'!Q29-'Bank Assets Analysis'!R29 -> 8281643928 | K29: =+C29+D29+E29+F29+G29+H29+I29+J29 -> 18714309080 | L29: 0.5 | M29: =+D29+E29 -> 1307591947 | N29: =+M29*L29 -> 6.5379597e+08
A30: 9.1 | B30: шу жумладан, жисмоний шахсларга берилган кредит ва лизинглар | C30: =+'Bank Assets Analysis'!C30-'Bank Assets Analysis'!D30 -> 3555869 | D30: =+'Bank Assets Analysis'!E30-'Bank Assets Analysis'!F30 -> 60906069 | E30: =+'Bank Assets Analysis'!G30-'Bank Assets Analysis'!H30 -> 27865818 | F30: =+'Bank Assets Analysis'!I30-'Bank Assets Analysis'!J30 -> 195740632 | G30: =+'Bank Assets Analysis'!K30-'Bank Assets Analysis'!L30 -> 295764899 | H30: =+'Bank Assets Analysis'!M30-'Bank Assets Analysis'!N30 -> 570767523 | I30: =+'Bank Assets Analysis'!O30-'Bank Assets Analysis'!P30 -> 1037718485 | J30: =+'Bank Assets Analysis'!Q30-'Bank Assets Analysis'!R30 -> 5591631789 | K30: =+C30+D30+E30+F30+G30+H30+I30+J30 -> 7783951084 | L30: 0 | M30: =+D30+E30 -> 88771887 | N30: =+M30*L30 -> 0
A31: 10 | B31: Суд ёки ижро иши юритиш жараёнидаги кредитлар ва лизинг, соф | C31: =+'Bank Assets Analysis'!C31-'Bank Assets Analysis'!D31 -> 21171099 | D31: =+'Bank Assets Analysis'!E31-'Bank Assets Analysis'!F31 -> 0 | E31: =+'Bank Assets Analysis'!G31-'Bank Assets Analysis'!H31 -> 0 | F31: =+'Bank Assets Analysis'!I31-'Bank Assets Analysis'!J31 -> 0 | G31: =+'Bank Assets Analysis'!K31-'Bank Assets Analysis'!L31 -> 0 | H31: =+'Bank Assets Analysis'!M31-'Bank Assets Analysis'!N31 -> 0 | I31: =+'Bank Assets Analysis'!O31-'Bank Assets Analysis'!P31 -> 0 | J31: =+'Bank Assets Analysis'!Q31-'Bank Assets Analysis'!R31 -> 0 | K31: =+C31+D31+E31+F31+G31+H31+I31+J31 -> 21171099 | L31: 0 | M31: =+D31+E31 -> 0 | N31: =+M31*L31 -> 0
A32: 11 | B32: Инвестициялар, соф | C32: =+'Bank Assets Analysis'!C32-'Bank Assets Analysis'!D32 -> 403272950 | D32: =+'Bank Assets Analysis'!E32-'Bank Assets Analysis'!F32 -> 0 | E32: =+'Bank Assets Analysis'!G32-'Bank Assets Analysis'!H32 -> 0 | F32: =+'Bank Assets Analysis'!I32-'Bank Assets Analysis'!J32 -> 0 | G32: =+'Bank Assets Analysis'!K32-'Bank Assets Analysis'!L32 -> 0 | H32: =+'Bank Assets Analysis'!M32-'Bank Assets Analysis'!N32 -> 0 | I32: =+'Bank Assets Analysis'!O32-'Bank Assets Analysis'!P32 -> 0 | J32: =+'Bank Assets Analysis'!Q32-'Bank Assets Analysis'!R32 -> 0 | K32: =+C32+D32+E32+F32+G32+H32+I32+J32 -> 403272950 | L32: 0 | M32: =+D32+E32 -> 0 | N32: =+M32*L32 -> 0
A33: 12 | B33: РЕПО битимлари бўйича сотиб олинган қимматли қоғозлар | C33: =+C34+C35 -> 0 | D33: =+D34+D35 -> 0 | E33: =+E34+E35 -> 0 | F33: =+F34+F35 -> 0 | G33: =+G34+G35 -> 0 | H33: =+H34+H35 -> 0 | I33: =+I34+I35 -> 0 | J33: =+J34+J35 -> 0 | K33: =+C33+D33+E33+F33+G33+H33+I33+J33 -> 0 | L33: 0 | M33: =+D33+E33 -> 0 | N33: =+M33*L33 -> 0
A34: 12.1 | B34: РЕПО битимлари бўйича сотиб олинган юқори ликвидли қимматли қоғозлар | C34: =+'Bank Assets Analysis'!C34-'Bank Assets Analysis'!D34 -> 0 | D34: =+'Bank Assets Analysis'!E34-'Bank Assets Analysis'!F34 -> 0 | E34: =+'Bank Assets Analysis'!G34-'Bank Assets Analysis'!H34 -> 0 | F34: =+'Bank Assets Analysis'!I34-'Bank Assets Analysis'!J34 -> 0 | G34: =+'Bank Assets Analysis'!K34-'Bank Assets Analysis'!L34 -> 0 | H34: =+'Bank Assets Analysis'!M34-'Bank Assets Analysis'!N34 -> 0 | I34: =+'Bank Assets Analysis'!O34-'Bank Assets Analysis'!P34 -> 0 | J34: =+'Bank Assets Analysis'!Q34-'Bank Assets Analysis'!R34 -> 0 | K34: =+C34+D34+E34+F34+G34+H34+I34+J34 -> 0 | L34: 1 | M34: =+K34 -> 0 | N34: =+M34*L34 -> 0
A35: 12.2 | B35: РЕПО битимлари бўйича сотиб олинган бошқа қимматли қоғозлар | C35: =+'Bank Assets Analysis'!C35-'Bank Assets Analysis'!D35 -> 0 | D35: =+'Bank Assets Analysis'!E35-'Bank Assets Analysis'!F35 -> 0 | E35: =+'Bank Assets Analysis'!G35-'Bank Assets Analysis'!H35 -> 0 | F35: =+'Bank Assets Analysis'!I35-'Bank Assets Analysis'!J35 -> 0 | G35: =+'Bank Assets Analysis'!K35-'Bank Assets Analysis'!L35 -> 0 | H35: =+'Bank Assets Analysis'!M35-'Bank Assets Analysis'!N35 -> 0 | I35: =+'Bank Assets Analysis'!O35-'Bank Assets Analysis'!P35 -> 0 | J35: =+'Bank Assets Analysis'!Q35-'Bank Assets Analysis'!R35 -> 0 | K35: =+C35+D35+E35+F35+G35+H35+I35+J35 -> 0 | L35: 0 | N35: =+M35*L35 -> 0
A36: 13 | B36: Aсосий воситалар, соф | C36: =+'Bank Assets Analysis'!C36-'Bank Assets Analysis'!D36 -> 0 | D36: =+'Bank Assets Analysis'!E36-'Bank Assets Analysis'!F36 -> 0 | E36: =+'Bank Assets Analysis'!G36-'Bank Assets Analysis'!H36 -> 0 | F36: =+'Bank Assets Analysis'!I36-'Bank Assets Analysis'!J36 -> 0 | G36: =+'Bank Assets Analysis'!K36-'Bank Assets Analysis'!L36 -> 0 | H36: =+'Bank Assets Analysis'!M36-'Bank Assets Analysis'!N36 -> 0 | I36: =+'Bank Assets Analysis'!O36-'Bank Assets Analysis'!P36 -> 0 | J36: =+'Bank Assets Analysis'!Q36-'Bank Assets Analysis'!R36 -> 3125231142 | K36: =+C36+D36+E36+F36+G36+H36+I36+J36 -> 3125231142 | L36: 0 | N36: =+M36*L36 -> 0
A37: 14 | B37: Банкнинг бошқа хусусий мулклари, соф | C37: =+'Bank Assets Analysis'!C37-'Bank Assets Analysis'!D37 -> 70914978 | D37: =+'Bank Assets Analysis'!E37-'Bank Assets Analysis'!F37 -> 0 | E37: =+'Bank Assets Analysis'!G37-'Bank Assets Analysis'!H37 -> 0 | F37: =+'Bank Assets Analysis'!I37-'Bank Assets Analysis'!J37 -> 0 | G37: =+'Bank Assets Analysis'!K37-'Bank Assets Analysis'!L37 -> 0 | H37: =+'Bank Assets Analysis'!M37-'Bank Assets Analysis'!N37 -> 0 | I37: =+'Bank Assets Analysis'!O37-'Bank Assets Analysis'!P37 -> 0 | J37: =+'Bank Assets Analysis'!Q37-'Bank Assets Analysis'!R37 -> 0 | K37: =+C37+D37+E37+F37+G37+H37+I37+J37 -> 70914978 | L37: 0 | N37: =+M37*L37 -> 0
A38: 15 | B38: Ҳосилавий инструментларнинг ревальвацияси натижасида ўзлаштирилмаган фойда | C38: =+'Bank Assets Analysis'!C38-'Bank Assets Analysis'!D38 -> 0 | D38: =+'Bank Assets Analysis'!E38-'Bank Assets Analysis'!F38 -> 0 | E38: =+'Bank Assets Analysis'!G38-'Bank Assets Analysis'!H38 -> 0 | F38: =+'Bank Assets Analysis'!I38-'Bank Assets Analysis'!J38 -> 0 | G38: =+'Bank Assets Analysis'!K38-'Bank Assets Analysis'!L38 -> 0 | H38: =+'Bank Assets Analysis'!M38-'Bank Assets Analysis'!N38 -> 0 | I38: =+'Bank Assets Analysis'!O38-'Bank Assets Analysis'!P38 -> 0 | J38: =+'Bank Assets Analysis'!Q38-'Bank Assets Analysis'!R38 -> 0 | K38: =+C38+D38+E38+F38+G38+H38+I38+J38 -> 0 | L38: 0 | N38: =+M38*L38 -> 0
A39: 16 | B39: Валюта савдоси ва валюта позициялари | K39: =+C39+D39+E39+F39+G39+H39+I39+J39 -> 0 | L39: 0 | N39: =+M39*L39 -> 0
A40: 17 | B40: Транзит ҳисобварақлари | C40: =+'Bank Assets Analysis'!C40-'Bank Assets Analysis'!D40 -> 0 | D40: =+'Bank Assets Analysis'!E40-'Bank Assets Analysis'!F40 -> 0 | E40: =+'Bank Assets Analysis'!G40-'Bank Assets Analysis'!H40 -> 0 | F40: =+'Bank Assets Analysis'!I40-'Bank Assets Analysis'!J40 -> 0 | G40: =+'Bank Assets Analysis'!K40-'Bank Assets Analysis'!L40 -> 0 | H40: =+'Bank Assets Analysis'!M40-'Bank Assets Analysis'!N40 -> 0 | I40: =+'Bank Assets Analysis'!O40-'Bank Assets Analysis'!P40 -> 0 | J40: =+'Bank Assets Analysis'!Q40-'Bank Assets Analysis'!R40 -> 0 | K40: =+C40+D40+E40+F40+G40+H40+I40+J40 -> 0 | L40: 0 | N40: =+M40*L40 -> 0
A41: 18 | B41: Олиниши лозим бўлган ҳисобланган фоизлар | C41: =+'Bank Assets Analysis'!C41-'Bank Assets Analysis'!D41 -> 128349189 | D41: =+'Bank Assets Analysis'!E41-'Bank Assets Analysis'!F41 -> 102047124 | E41: =+'Bank Assets Analysis'!G41-'Bank Assets Analysis'!H41 -> 122319586 | F41: =+'Bank Assets Analysis'!I41-'Bank Assets Analysis'!J41 -> 125306278 | G41: =+'Bank Assets Analysis'!K41-'Bank Assets Analysis'!L41 -> 97184118 | H41: =+'Bank Assets Analysis'!M41-'Bank Assets Analysis'!N41 -> 140606317 | I41: =+'Bank Assets Analysis'!O41-'Bank Assets Analysis'!P41 -> 208241855 | J41: =+'Bank Assets Analysis'!Q41-'Bank Assets Analysis'!R41 -> 71940577 | K41: =+C41+D41+E41+F41+G41+H41+I41+J41 -> 995995044 | L41: 0.5 | M41: =+D41+E41 -> 224366710 | N41: =+M41*L41 -> 112183355
A42: 19 | B42: Бошқа активлар | C42: =+'Bank Assets Analysis'!C42-'Bank Assets Analysis'!D42 -> 378974738 | D42: =+'Bank Assets Analysis'!E42-'Bank Assets Analysis'!F42 -> 0 | E42: =+'Bank Assets Analysis'!G42-'Bank Assets Analysis'!H42 -> 7550440 | F42: =+'Bank Assets Analysis'!I42-'Bank Assets Analysis'!J42 -> 0 | G42: =+'Bank Assets Analysis'!K42-'Bank Assets Analysis'!L42 -> 0 | H42: =+'Bank Assets Analysis'!M42-'Bank Assets Analysis'!N42 -> 0 | I42: =+'Bank Assets Analysis'!O42-'Bank Assets Analysis'!P42 -> 0 | J42: =+'Bank Assets Analysis'!Q42-'Bank Assets Analysis'!R42 -> 0 | K42: =+C42+D42+E42+F42+G42+H42+I42+J42 -> 386525178 | L42: 0 | N42: =+M42*L42 -> 0
A43: 20 | B43: Гаровга қўйилган юқори ликвидли активлар, 4.1.1. бундан мустасно | C43: =+'Bank Assets Analysis'!C43-'Bank Assets Analysis'!D43 -> 0 | D43: =+'Bank Assets Analysis'!E43-'Bank Assets Analysis'!F43 -> 0 | E43: =+'Bank Assets Analysis'!G43-'Bank Assets Analysis'!H43 -> 0 | F43: =+'Bank Assets Analysis'!I43-'Bank Assets Analysis'!J43 -> 0 | G43: =+'Bank Assets Analysis'!K43-'Bank Assets Analysis'!L43 -> 0 | H43: =+'Bank Assets Analysis'!M43-'Bank Assets Analysis'!N43 -> 0 | I43: =+'Bank Assets Analysis'!O43-'Bank Assets Analysis'!P43 -> 0 | J43: =+'Bank Assets Analysis'!Q43-'Bank Assets Analysis'!R43 -> 0 | K43: =+C43+D43+E43+F43+G43+H43+I43+J43 -> 0 | L43: 1 | M43: =+C43+D43+E43 -> 0 | N43: =+M43*L43 -> 0
A44: 21 | B44: ЖAМИ АКТИВЛАР | C44: =SUM(C6:C42)-C9-C13-C17-C18-C30-C33 -> 2716119704 | D44: =SUM(D6:D42)-D9-D13-D17-D18-D30-D33 -> 392657276 | E44: =SUM(E6:E42)-E9-E13-E17-E18-E30-E33 -> 1146851821 | F44: =SUM(F6:F42)-F9-F13-F17-F18-F30-F33 -> 1585154566 | G44: =SUM(G6:G42)-G9-G13-G17-G18-G30-G33 -> 2545477665 | H44: =SUM(H6:H42)-H9-H13-H17-H18-H30-H33 -> 4254527449 | I44: =SUM(I6:I42)-I9-I13-I17-I18-I30-I33 -> 3111802154 | J44: =SUM(J6:J42)-J9-J13-J17-J18-J30-J33 -> 11793701572 | K44: =SUM(C44:J44) -> 27546292207 | M44: =SUM(M6:M42)-M9-M33 -> 5521737640 | N44: =+N12+N13+N14+N15+N16+N18+N25+N26+N27+N28+N29+N41+N43 -> 1.6187874e+09 | O44: =+Balance!D47 -> 27546292207 | P44: =+K44-O44 -> 0 | R44: =+O44 -> 27546292207 | S44: =+K44-R44 -> 0
B45: Балансдан ташқари мажбуриятлар
A46: 1 | B46: Банкнинг кредит ва лизинг бериш бўйича мажбуриятлари (91809) | C46: =+'Bank Assets Analysis'!C46-'Bank Assets Analysis'!D46 -> 171438 | D46: =+'Bank Assets Analysis'!E46-'Bank Assets Analysis'!F46 -> 3534103 | E46: =+'Bank Assets Analysis'!G46-'Bank Assets Analysis'!H46 -> 69057670 | F46: =+'Bank Assets Analysis'!I46-'Bank Assets Analysis'!J46 -> 48266709 | G46: =+'Bank Assets Analysis'!K46-'Bank Assets Analysis'!L46 -> 20429197 | H46: =+'Bank Assets Analysis'!M46-'Bank Assets Analysis'!N46 -> 43847717 | I46: =+'Bank Assets Analysis'!O46-'Bank Assets Analysis'!P46 -> 23345525 | J46: =+'Bank Assets Analysis'!Q46-'Bank Assets Analysis'!R46 -> 322715614 | K46: =+C46+D46+E46+F46+G46+H46+I46+J46 -> 531367973
B47: шундан, ХМИ, Молия вазирлиги, фондлар ва бошқа ташкилотларнинг депозитлари билан таъминланган | C47: =+'Bank Assets Analysis'!C47-'Bank Assets Analysis'!D47 -> 0 | D47: =+'Bank Assets Analysis'!E47-'Bank Assets Analysis'!F47 -> 0 | E47: =+'Bank Assets Analysis'!G47-'Bank Assets Analysis'!H47 -> 0 | F47: =+'Bank Assets Analysis'!I47-'Bank Assets Analysis'!J47 -> 0 | G47: =+'Bank Assets Analysis'!K47-'Bank Assets Analysis'!L47 -> 0 | H47: =+'Bank Assets Analysis'!M47-'Bank Assets Analysis'!N47 -> 0 | I47: =+'Bank Assets Analysis'!O47-'Bank Assets Analysis'!P47 -> 0 | J47: =+'Bank Assets Analysis'!Q47-'Bank Assets Analysis'!R47 -> 0 | K47: =+C47+D47+E47+F47+G47+H47+I47+J47 -> 0
A48: 2 | B48: Кафолат ва кафилликлар (90993) | C48: =+'Bank Assets Analysis'!C48-'Bank Assets Analysis'!D48 -> 0 | D48: =+'Bank Assets Analysis'!E48-'Bank Assets Analysis'!F48 -> 0 | E48: =+'Bank Assets Analysis'!G48-'Bank Assets Analysis'!H48 -> 0 | F48: =+'Bank Assets Analysis'!I48-'Bank Assets Analysis'!J48 -> 5363563 | G48: =+'Bank Assets Analysis'!K48-'Bank Assets Analysis'!L48 -> 4000000 | H48: =+'Bank Assets Analysis'!M48-'Bank Assets Analysis'!N48 -> 0 | I48: =+'Bank Assets Analysis'!O48-'Bank Assets Analysis'!P48 -> 0 | J48: =+'Bank Assets Analysis'!Q48-'Bank Assets Analysis'!R48 -> 0 | K48: =+C48+D48+E48+F48+G48+H48+I48+J48 -> 9363563
B49: - шундан, алоҳида блокланган ҳисобварақлардаги депозитлар билан таъминланган кафолат ва кафилликлар | C49: =+'Bank Assets Analysis'!C49-'Bank Assets Analysis'!D49 -> 0 | D49: =+'Bank Assets Analysis'!E49-'Bank Assets Analysis'!F49 -> 0 | E49: =+'Bank Assets Analysis'!G49-'Bank Assets Analysis'!H49 -> 0 | F49: =+'Bank Assets Analysis'!I49-'Bank Assets Analysis'!J49 -> 363563 | G49: =+'Bank Assets Analysis'!K49-'Bank Assets Analysis'!L49 -> 0 | H49: =+'Bank Assets Analysis'!M49-'Bank Assets Analysis'!N49 -> 0 | I49: =+'Bank Assets Analysis'!O49-'Bank Assets Analysis'!P49 -> 0 | J49: =+'Bank Assets Analysis'!Q49-'Bank Assets Analysis'!R49 -> 0 | K49: =+C49+D49+E49+F49+G49+H49+I49+J49 -> 363563
A50: 3 | B50: Аккредитивлар (90908-90958) | C50: =+'Bank Assets Analysis'!C50-'Bank Assets Analysis'!D50 -> 0 | D50: =+'Bank Assets Analysis'!E50-'Bank Assets Analysis'!F50 -> 0 | E50: =+'Bank Assets Analysis'!G50-'Bank Assets Analysis'!H50 -> 0 | F50: =+'Bank Assets Analysis'!I50-'Bank Assets Analysis'!J50 -> 0 | G50: =+'Bank Assets Analysis'!K50-'Bank Assets Analysis'!L50 -> 0 | H50: =+'Bank Assets Analysis'!M50-'Bank Assets Analysis'!N50 -> 0 | I50: =+'Bank Assets Analysis'!O50-'Bank Assets Analysis'!P50 -> 0 | J50: =+'Bank Assets Analysis'!Q50-'Bank Assets Analysis'!R50 -> 0 | K50: =+C50+D50+E50+F50+G50+H50+I50+J50 -> 0
B51: - шундан, 22602 баланс ҳисобварағида депозит билан таъминланганлар кўрсатилади | C51: =+'Bank Assets Analysis'!C51-'Bank Assets Analysis'!D51 -> 0 | D51: =+'Bank Assets Analysis'!E51-'Bank Assets Analysis'!F51 -> 0 | E51: =+'Bank Assets Analysis'!G51-'Bank Assets Analysis'!H51 -> 0 | F51: =+'Bank Assets Analysis'!I51-'Bank Assets Analysis'!J51 -> 0 | G51: =+'Bank Assets Analysis'!K51-'Bank Assets Analysis'!L51 -> 0 | H51: =+'Bank Assets Analysis'!M51-'Bank Assets Analysis'!N51 -> 0 | I51: =+'Bank Assets Analysis'!O51-'Bank Assets Analysis'!P51 -> 0 | J51: =+'Bank Assets Analysis'!Q51-'Bank Assets Analysis'!R51 -> 0 | K51: =+C51+D51+E51+F51+G51+H51+I51+J51 -> 0
B53: Бошқарув Раис имзоси:
B55: Бош бухгалтер имзоси:
O56: Ликвидные активы | P56: =+N44 -> 1.6187874e+09
O57: Высоко-ликвидные активы | P57: =+N6+N7+N10+N11+N19+N20+N21+N22+N23+N34-N43-N18 -> 2231391081
O58: Чистый отток за 30 дней | P58: =+P60-P62 -> 1.9319643e+09
O60: всего отток | P60: ='Bank Liabilities Analysis (нац)'!M41+P61 -> 3550751739
O61: в том числе отток по внебалансу | P61: =+'Liquidity Analysis'!D41 -> 80975733
O62: Приток по положению | P62: =IF(P56>(P60*0.75),P60*0.75,P56) -> 1.6187874e+09

Sheet Bank Liabilities Analysis
A1: БАНК МАЖБУРИЯТЛАРИ ТАҲЛИЛИ | W1: 18-жадвал
B2: =Balance!B3 -> "Ўзсаноатқурилишбанк" АТБ | V2: =+Balance!D3 -> 45289 | X2: минг сўмда
A3: № | B3: Кўрсаткичлар | C3: Сўндириш муддати (кунларда) | S3: Жами | T3: шундан, | V3: Ликвидлиликни қоплаш меёри ҳисоб китоби
C4: Муддатсиз | E4: 1 дан 7 гача | G4: 8 дан 30 гача | I4: 31 дан 90 гача | K4: 91 дан 180 гача | M4: 181 дан 365 гача | O4: 366 дан 730 гача | Q4: 2 йилдан ортиқ
C5: Сумма | D5: шундан, хорижий валютада (сўм экв.) | E5: Сумма | F5: шундан, хорижий валютада (сўм экв.) | G5: Сумма | H5: шундан, хорижий валютада (сўм экв.) | I5: Сумма | J5: шундан, хорижий валютада (сўм экв.) | K5: Сумма | L5: шундан, хорижий валютада (сўм экв.) | M5: Сумма | N5: шундан, хорижий валютада (сўм экв.) | O5: Сумма | P5: шундан, хорижий валютада (сўм экв.) | Q5: Сумма | R5: шундан, хорижий валютада (сўм экв.) | T5: миллий валютада | U5: хорижий валютада (сўм экв.) | V5: Коэффициент | W5: 30 кунлик чиқим суммаси | X5: 30 кунлик чиқим суммаси (хорижий валютада)
A6: 1. | B6: ДЕПОЗИТЛАР
A7: 1.1 | B7: Талаб қилиб олингунча депозитлар | C7: =SUM(C8:C11) -> 2722791137 | D7: =SUM(D8:D11) -> 859139365 | E7: =SUM(E8:E11) -> 0 | F7: =SUM(F8:F11) -> 0 | G7: =SUM(G8:G11) -> 0 | H7: =SUM(H8:H11) -> 0 | I7: =SUM(I8:I11) -> 0 | J7: =SUM(J8:J11) -> 0 | ... R7: =SUM(R8:R11) -> 0 | S7: =+C7+E7+G7+I7+K7+M7+O7+Q7 -> 2722791137 | T7: =+S7-U7 -> 1863651772 | U7: =+D7+F7+H7+J7+L7+N7+P7+R7 -> 859139365
A8: 1.1.1 | B8: Aҳолининг талаб қилиб олингунча омонатлари | C8: 181810063 | D8: 124306460 | S8: =+C8+E8+G8+I8+K8+M8+O8+Q8 -> 181810063 | T8: =+S8-U8 -> 57503603 | U8: =+D8+F8+H8+J8+L8+N8+P8+R8 -> 124306460
A9: 1.1.2 | B9: Кредит таъминоти сифатида жалб этилган aҳоли омонатлари | S9: =+C9+E9+G9+I9+K9+M9+O9+Q9 -> 0 | T9: =+S9-U9 -> 0 | U9: =+D9+F9+H9+J9+L9+N9+P9+R9 -> 0
A10: 1.1.3 | B10: Кредит таъминоти сифатида жалб этилган бошқа депозитлар | S10: =+C10+E10+G10+I10+K10+M10+O10+Q10 -> 0 | T10: =+S10-U10 -> 0 | U10: =+D10+F10+H10+J10+L10+N10+P10+R10 -> 0
A11: 1.1.4 | B11: Талаб қилиб олингунча бошқа депозитлар | C11: 2540981074 | D11: 734832905 | S11: =+C11+E11+G11+I11+K11+M11+O11+Q11 -> 2540981074 | T11: =+S11-U11 -> 1806148169 | U11: =+D11+F11+H11+J11+L11+N11+P11+R11 -> 734832905
A12: 1.2 | B12: Муддатли депозитлар | C12: =200000+C13+C14 -> 32310530 | D12: =0+D13+D14 -> 58666 | E12: =41129+1780001+E13+E14 -> 53385736 | F12: =41129+F13+F14 -> 14321636 | G12: =165733939+G13+G14 -> 335537837 | H12: =71467643+H13+H14 -> 97578144 | I12: =229164220+I13+I14 -> 888164380 | J12: =110114175+J13+J14 -> 196843902 | K12: =701684443+K13+K14 -> 1150956467 | L12: =91138642+L13+L14 -> 202031117 | M12: =517061146+M13+M14 -> 1705054735 | N12: =248123789+N13+N14 -> 266132422 | O12: =1231533006+16100000+O13+O14 -> 1660568440 | P12: =1004525430+P13+P14 -> 1004525430 | Q12: =2143017462+Q13+Q14 -> 2147109497 | R12: =836957786+R13+R14 -> 836957786 | S12: =+C12+E12+G12+I12+K12+M12+O12+Q12 -> 7973087622 | T12: =+S12-U12 -> 5354638519 | U12: =+D12+F12+H12+J12+L12+N12+P12+R12 -> 2618449103
A13: 1.2.1 | B13: Аҳоли омонатлари | C13: 32110530 | D13: 58666 | E13: 51564606 | F13: 14280507 | G13: 169803898 | H13: 26110501 | I13: 659000160 | J13: 86729727 | K13: 449272024 | L13: 110892475 | M13: 1187993589 | N13: 18008633 | O13: 412935434 | P13: 0 | Q13: 4092035 | R13: 0 | S13: =+C13+E13+G13+I13+K13+M13+O13+Q13 -> 2966772276 | T13: =+S13-U13 -> 2710691767 | U13: =+D13+F13+H13+J13+L13+N13+P13+R13 -> 256080509
A14: 1.2.2 | B14: Чиқарилган депозит сертификатлари | S14: =+C14+E14+G14+I14+K14+M14+O14+Q14 -> 0 | T14: =+S14-U14 -> 0 | U14: =+D14+F14+H14+J14+L14+N14+P14+R14 -> 0
A15: 1.3 | B15: Мижозларнинг бошқа депозитлари | C15: =SUM(C16:C19) -> 1935696373 | D15: =SUM(D16:D19) -> 244935434 | E15: =SUM(E16:E19) -> 0 | F15: =SUM(F16:F19) -> 0 | G15: =SUM(G16:G19) -> 110222850 | H15: =SUM(H16:H19) -> 110222850 | I15: =SUM(I16:I19) -> 140260274 | J15: =SUM(J16:J19) -> 139730522 | ... R15: =SUM(R16:R19) -> 0 | S15: =+C15+E15+G15+I15+K15+M15+O15+Q15 -> 3102712389 | T15: =+S15-U15 -> 1691290691 | U15: =+D15+F15+H15+J15+L15+N15+P15+R15 -> 1411421698
A16: 1.3.1 | B16: Жисмоний шахсларнинг банк пластик карталаридаги маблағлари | C16: 1291535177 | D16: 162945903 | S16: =+C16+E16+G16+I16+K16+M16+O16+Q16 -> 1291535177 | T16: =+S16-U16 -> 1128589274 | U16: =+D16+F16+H16+J16+L16+N16+P16+R16 -> 162945903
A17: 1.3.2 | B17: Бошқа мижозларнинг банк пластик карталаридаги маблағлари | C17: 16528585 | D17: 0 | S17: =+C17+E17+G17+I17+K17+M17+O17+Q17 -> 16528585 | T17: =+S17-U17 -> 16528585 | U17: =+D17+F17+H17+J17+L17+N17+P17+R17 -> 0
A18: 1.3.3 | B18: Мижозларнинг аккредитив бўйича депозитлари | C18: 0 | D18: 0 | E18: 0 | F18: 0 | G18: 110222850 | H18: 110222850 | I18: =139730522+529752 -> 140260274 | J18: 139730522 | K18: 418842812 | L18: 418842812 | M18: 258314981 | N18: 258314981 | O18: 239375099 | P18: 239375099 | Q18: 0 | R18: 0 | S18: =+C18+E18+G18+I18+K18+M18+O18+Q18 -> 1167016016 | T18: =+S18-U18 -> 529752 | U18: =+D18+F18+H18+J18+L18+N18+P18+R18 -> 1166486264
A19: 1.3.4 | B19: Бошқалар | C19: 627632611 | D19: 81989531 | S19: =+C19+E19+G19+I19+K19+M19+O19+Q19 -> 627632611 | T19: =+S19-U19 -> 545643080 | U19: =+D19+F19+H19+J19+L19+N19+P19+R19 -> 81989531
A20: 1.4 | B20: Жами депозитлар | C20: =+C7+C12+C15 -> 4690798040 | D20: =+D7+D12+D15 -> 1104133465 | E20: =+E7+E12+E15 -> 53385736 | F20: =+F7+F12+F15 -> 14321636 | G20: =+G7+G12+G15 -> 445760687 | H20: =+H7+H12+H15 -> 207800994 | I20: =+I7+I12+I15 -> 1028424654 | J20: =+J7+J12+J15 -> 336574424 | ... R20: =+R7+R12+R15 -> 836957786 | S20: =+C20+E20+G20+I20+K20+M20+O20+Q20 -> 13798591148 | T20: =+S20-U20 -> 8909580982 | U20: =+D20+F20+H20+J20+L20+N20+P20+R20 -> 4889010166 | V20: 0.15 | W20: =+X20+'Bank Liabilities Analysis (нац)'!M21 -> 1.8130039e+09 | X20: =(U20-(J44+L44+N44+P44+R44))*V20 -> 4.7656677e+08 | Y20: =+'Deposits by Client'!C22 -> 13798591148 | Z20: =+Y20-AA20 -> 8909580982 | AA20: =+'Deposits by Client'!D22 -> 4889010166
A21: 2. | B21: Марказий банкка тўланиши лозим бўлган маблағлар | C21: =C22 -> 1074053 | D21: 0 | S21: =+C21+E21+G21+I21+K21+M21+O21+Q21 -> 1074053 | T21: =+S21-U21 -> 1074053 | U21: =+D21+F21+H21+J21+L21+N21+P21+R21 -> 0 | V21: 1 | W21: =(C21+E21+G21-C22-E22-G22)*V21 -> 0 | X21: =(D21+F21+H21-D22-F22-H22)*V21 -> 0 | Y21: =+S20-Y20 -> 0 | Z21: =+T20-Z20 -> 0 | AA21: =+U20-AA20 -> 0
A22: 2.1. | B22: шу жумладан, Марказий банкка тўланиши лозим бўлган маблағлар -Тезкор тўловлар ҳамда клиринг тизимлари | C22: 1074053 | D22: 0 | S22: =+C22+E22+G22+I22+K22+M22+O22+Q22 -> 1074053 | T22: =+S22-U22 -> 1074053 | U22: =+D22+F22+H22+J22+L22+N22+P22+R22 -> 0
A23: 3. | B23: Бошқа банклар ва молиявий ташкилотларга тўланиши лозим бўлган маблағлар | C23: =SUM(C24:C28)-C25 -> 497095880 | D23: =SUM(D24:D28)-D25 -> 458461140 | E23: =SUM(E24:E28)-E25 -> 274636400 | F23: =SUM(F24:F28)-F25 -> 274636400 | G23: =SUM(G24:G28)-G25 -> 1057907551 | H23: =SUM(H24:H28)-H25 -> 382287100 | I23: =SUM(I24:I28)-I25 -> 3572927419 | J23: =SUM(J24:J28)-J25 -> 3130907870 | ... R23: =SUM(R24:R28)-R25 -> 0 | S23: =+C23+E23+G23+I23+K23+M23+O23+Q23 -> 6093050942 | T23: =+S23-U23 -> 1573440667 | U23: =+D23+F23+H23+J23+L23+N23+P23+R23 -> 4519610275
A24: 3.1 | B24: Бошқа банкларнинг вакиллик ҳисобварақларига тўланиши лозим бўлган маблағлар | C24: 457416473 | D24: 454725055 | S24: =+C24 -> 457416473 | T24: =+S24-U24 -> 2691418 | U24: =+D24 -> 454725055 | V24: 1 | W24: =X24+'Bank Liabilities Analysis (нац)'!M25 -> 276512575 | X24: =(U24-U25)*V24 -> 273821157
A25: 3.1.1 | B25: шу жумладан, махаллий банкларнинг вакиллик ҳисобварақларига тўланиши лозим бўлган маблағлар | C25: 180903898 | D25: 180903898 | S25: =+C25 -> 180903898 | T25: =+S25-U25 -> 0 | U25: =+D25 -> 180903898 | V25: 1 | W25: =(U25*V25) -> 180903898 | X25: =(U25*V25) -> 180903898
A26: 3.2 | B26: Бошқа банкларнинг ҳисобварақлари - Депозитлар | C26: 9692069 | D26: 2740296 | E26: 274636400 | F26: 274636400 | G26: 1057907551 | H26: 382287100 | I26: 3572927419 | J26: 3130907870 | K26: 244545210 | L26: 0 | M26: 110875781 | N26: 66629358 | O26: 284402609 | P26: 206688407 | Q26: 50660092 | R26: 0 | S26: =+C26+E26+G26+I26+K26+M26+O26+Q26 -> 5605647131 | T26: =+S26-U26 -> 1541757700 | U26: =+D26+F26+H26+J26+L26+N26+P26+R26 -> 4063889431 | V26: 1 | W26: =(C26+E26+G26)*V26 -> 1342236020 | X26: =(D26+F26+H26)*V26 -> 659663796
A27: 3.3 | B27: Банк карталаридан амалга оширилган тўловлар бўйича банкларга тўланиши лозим бўлган маблағлар | C27: 29987338 | D27: 995789 | S27: =+C27+E27+G27+I27+K27+M27+O27+Q27 -> 29987338 | T27: =+S27-U27 -> 28991549 | U27: =+D27+F27+H27+J27+L27+N27+P27+R27 -> 995789 | V27: 1 | W27: =(C27+E27+G27)*V27 -> 29987338 | X27: =(D27+F27+H27)*V27 -> 995789
A28: 3.4 | B28: Бошқа моддалар | C28: 0 | D28: 0 | S28: =+C28+E28+G28+I28+K28+M28+O28+Q28 -> 0 | T28: =+S28-U28 -> 0 | U28: =+D28+F28+H28+J28+L28+N28+P28+R28 -> 0 | V28: 1 | W28: =(C28+E28+G28)*V28 -> 0 | X28: =(D28+F28+H28)*V28 -> 0
A29: 4. | B29: Банкнинг тўланмаган акцептлари | C29: 0 | D29: 0 | S29: =+C29+E29+G29+I29+K29+M29+O29+Q29 -> 0 | T29: =+S29-U29 -> 0 | U29: =+D29+F29+H29+J29+L29+N29+P29+R29 -> 0 | V29: 1 | W29: =(C29+E29+G29)*V29 -> 0 | X29: =(D29+F29+H29)*V29 -> 0
A30: 5. | B30: Олинган кредит ва лизинглар (молиявий ижара) бўйича мажбуриятлар | C30: 1325111 | D30: 0 | E30: 29155066 | F30: 22358015 | G30: 783028394 | H30: 779802118 | I30: 1118023740 | J30: 933878353 | K30: 3344058361 | L30: 2319183254 | M30: 7393665029 | N30: 5836695603 | O30: 5812004746 | P30: 4663934211 | Q30: 17987667288 | R30: 16389173255 | S30: =+C30+E30+G30+I30+K30+M30+O30+Q30 -> 36468927735 | T30: =+S30-U30 -> 5523902926 | U30: =+D30+F30+H30+J30+L30+N30+P30+R30 -> 30945024809 | V30: 0.05 | W30: =X30+'Bank Liabilities Analysis (нац)'!M31 -> 1.7949535e+09 | X30: =(U30-(J49+L49+N49+P49+R49))*V30 -> 1.5187583e+09
A31: 6. | B31: Банк томонидан чиқарилган қимматли қоғозлар | C31: 0 | D31: 0 | E31: 0 | F31: 0 | G31: 0 | H31: 0 | I31: 0 | J31: 0 | K31: 0 | L31: 0 | M31: 3694366152 | N31: 3694366152 | O31: 0 | P31: 0 | Q31: 1233877000 | R31: 1233877000 | S31: =+C31+E31+G31+I31+K31+M31+O31+Q31 -> 4928243152 | T31: =+S31-U31 -> 0 | U31: =+D31+F31+H31+J31+L31+N31+P31+R31 -> 4928243152 | V31: 1 | W31: =(C31+E31+G31)*V31 -> 0 | X31: =(D31+F31+H31)*V31 -> 0
A32: 7. | B32: Субординар қарз мажбуриятлари | C32: 0 | D32: 0 | E32: 0 | F32: 0 | G32: 1994167 | H32: 0 | I32: 2431833 | J32: 0 | K32: 4426000 | L32: 0 | M32: 11181500 | N32: 0 | O32: 27022000 | P32: 0 | Q32: 2162889219 | R32: 703077613 | S32: =+C32+E32+G32+I32+K32+M32+O32+Q32 -> 2209944719 | T32: =+S32-U32 -> 1506867106 | U32: =+D32+F32+H32+J32+L32+N32+P32+R32 -> 703077613 | V32: 1 | W32: =(C32+E32+G32)*V32 -> 1994167 | X32: =(D32+F32+H32)*V32 -> 0
A33: 8. | B33: РЕПО битимлари бўйича сотилган қимматли қоғозлар | C33: =+C34+C35 -> 0 | D33: =+D34+D35 -> 0 | E33: =+E34+E35 -> 816807035 | F33: =+F34+F35 -> 0 | G33: =+G34+G35 -> 0 | H33: =+H34+H35 -> 0 | I33: =+I34+I35 -> 0 | J33: =+J34+J35 -> 0 | ... R33: =+R34+R35 -> 0 | S33: =+C33+E33+G33+I33+K33+M33+O33+Q33 -> 816807035 | T33: =+S33-U33 -> 816807035 | U33: =+D33+F33+H33+J33+L33+N33+P33+R33 -> 0
A34: 8.1 | B34: РЕПО битимлари бўйича сотилган юқори ликвидли қимматли қоғозлар | E34: 816807035 | F34: 0 | S34: =+C34+E34+G34+I34+K34+M34+O34+Q34 -> 816807035 | T34: =+S34-U34 -> 816807035 | U34: =+D34+F34+H34+J34+L34+N34+P34+R34 -> 0 | V34: 1 | W34: =(C34+E34+G34)*V34 -> 816807035 | X34: =(D34+F34+H34)*V34 -> 0
A35: 8.2 | B35: РЕПО битимлари бўйича сотилган бошқа қимматли қоғозлар | S35: =+C35+E35+G35+I35+K35+M35+O35+Q35 -> 0 | T35: =+S35-U35 -> 0 | U35: =+D35+F35+H35+J35+L35+N35+P35+R35 -> 0 | V35: 1 | W35: =(C35+E35+G35)*V35 -> 0 | X35: =(D35+F35+H35)*V35 -> 0
A36: 9. | B36: Ҳосилавий инструментлар бўйича ревальвация натижасида амалга ошмаган зарарлар ва бошқа муддати узайтирилган даромадлар | C36: 25174062 | D36: 91337 | S36: =+C36+E36+G36+I36+K36+M36+O36+Q36 -> 25174062 | T36: =+S36-U36 -> 25082725 | U36: =+D36+F36+H36+J36+L36+N36+P36+R36 -> 91337 | V36: 1 | W36: =(S36)*V36 -> 25174062 | X36: =(U36)*V36 -> 91337
A37: 10. | B37: Клиринг транзакциялари | C37: 2215477 | D37: 509 | S37: =+C37+E37+G37+I37+K37+M37+O37+Q37 -> 2215477 | T37: =+S37-U37 -> 2214968 | U37: =+D37+F37+H37+J37+L37+N37+P37+R37 -> 509 | V37: 1 | W37: =(S37)*V37 -> 2215477 | X37: =(U37)*V37 -> 509
A38: 11. | B38: Тўланиши лозим бўлган ҳисобланган фоизлар | C38: 108148 | D38: 351 | E38: 0 | F38: 0 | G38: 166678346 | H38: 113400775 | I38: 0 | J38: 0 | K38: 726343334 | L38: 592330438 | M38: 0 | N38: 0 | O38: 0 | P38: 0 | Q38: 0 | R38: 0 | S38: =+C38+E38+G38+I38+K38+M38+O38+Q38 -> 893129828 | T38: =+S38-U38 -> 187398264 | U38: =+D38+F38+H38+J38+L38+N38+P38+R38 -> 705731564 | W38: =C38+E38+G38+((I38+K38+M38+O38+Q38)*15%) -> 2.7573799e+08 | X38: =D38+F38+H38+((J38+L38+N38+P38+R38)*15%) -> 2.0225069e+08
A39: 12. | B39: Бошқа мажбуриятлар | C39: 668904895 | D39: 445602571 | S39: =+C39+E39+G39+I39+K39+M39+O39+Q39 -> 668904895 | T39: =+S39-U39 -> 223302324 | U39: =+D39+F39+H39+J39+L39+N39+P39+R39 -> 445602571 | V39: 1 | W39: =(C39+E39+G39)*V39 -> 668904895 | X39: =(D39+F39+H39)*V39 -> 445602571
A40: 13 | B40: ЖАМИ МАЖБУРИЯТЛАР | C40: =+C20+C29+C30+C31+C32+C33+C36+C37+C38+C39+C21+C23 -> 5886695666 | D40: =+D20+D29+D30+D31+D32+D33+D36+D37+D38+D39+D21+D23 -> 2008289373 | E40: =+E20+E29+E30+E31+E32+E33+E36+E37+E38+E39+E21+E23 -> 1173984237 | F40: =+F20+F29+F30+F31+F32+F33+F36+F37+F38+F39+F21+F23 -> 311316051 | G40: =+G20+G29+G30+G31+G32+G33+G36+G37+G38+G39+G21+G23 -> 2455369145 | H40: =+H20+H29+H30+H31+H32+H33+H36+H37+H38+H39+H21+H23 -> 1483290987 | I40: =+I20+I29+I30+I31+I32+I33+I36+I37+I38+I39+I21+I23 -> 5721807646 | J40: =+J20+J29+J30+J31+J32+J33+J36+J37+J38+J39+J21+J23 -> 4401360647 | ... U40: =+U20+U29+U30+U31+U32+U33+U36+U37+U38+U39+U21+U23 -> 47136391996 | V40: отток | W40: =SUM(W8:W39) -> 7.2284308e+09 | X40: =SUM(X8:X39) -> 3.7586548e+09 | Y40: =+Balance!C63 -> 65906063046 | Z40: =+Balance!D63 -> 18769671050 | AA40: =+Balance!E63 -> 47136391996
B41: шундан, | S41: =+C41+E41+G41+I41+K41+M41+O41+Q41 -> 0 | T41: =+S41-U41 -> 0 | U41: =+D41+F41+H41+J41+L41+N41+P41+R41 -> 0 | Y41: =+S40-Y40 -> 0 | Z41: =+T40-Z40 -> 0 | AA41: =+U40-AA40 -> 0
B42: Ўзбекистон Республикаси Молия вазирлиги маблағлари, шундан | C42: =+C43+C44 -> 0 | D42: =+D43+D44 -> 0 | E42: =+E43+E44 -> 51738176 | F42: =+F43+F44 -> 49693546 | G42: =+G43+G44 -> 45290672 | H42: =+H43+H44 -> 35752218 | I42: =+I43+I44 -> 295884812 | J42: =+J43+J44 -> 142575519 | ... R42: =+R43+R44 -> 1079421189 | S42: =+C42+E42+G42+I42+K42+M42+O42+Q42 -> 4951750451 | T42: =+S42-U42 -> 2429511709 | U42: =+D42+F42+H42+J42+L42+N42+P42+R42 -> 2522238742
B43: Кредит ва лизинглар | C43: 0 | D43: 0 | E43: 21667975 | F43: 20326650 | G43: 9100245 | H43: 6385322 | I43: 103458951 | J43: 83841727 | K43: 145165813 | L43: 106955758 | M43: 125616742 | N43: 69055135 | O43: 184505514 | P43: 81284361 | Q43: 813523270 | R43: 383757598 | S43: =+C43+E43+G43+I43+K43+M43+O43+Q43 -> 1403038510 | T43: =+S43-U43 -> 651431959 | U43: =+D43+F43+H43+J43+L43+N43+P43+R43 -> 751606551
B44: Депозит маблағлар | C44: 0 | D44: 0 | E44: 30070201 | F44: 29366896 | G44: 36190427 | H44: 29366896 | I44: 192425861 | J44: 58733792 | K44: 255584198 | L44: 88100687 | M44: 646165414 | N44: 546364475 | O44: 396629944 | P44: 323035854 | Q44: 1991645896 | R44: 695663591 | S44: =+C44+E44+G44+I44+K44+M44+O44+Q44 -> 3548711941 | T44: =+S44-U44 -> 1778079750 | U44: =+D44+F44+H44+J44+L44+N44+P44+R44 -> 1770632191 | Y44: 20202,20204,20602
B45: Бюджетдан ташқари фондларнинг маблағлари, шундан | C45: =+C46+C47 -> 1325111 | D45: =+D46+D47 -> 0 | E45: =+E46+E47 -> 13017 | F45: =+F46+F47 -> 0 | G45: =+G46+G47 -> 160721 | H45: =+H46+H47 -> 0 | I45: =+I46+I47 -> 782896 | J45: =+J46+J47 -> 0 | ... R45: =+R46+R47 -> 0 | S45: =+C45+E45+G45+I45+K45+M45+O45+Q45 -> 8148415 | T45: =+S45-U45 -> 8148415 | U45: =+D45+F45+H45+J45+L45+N45+P45+R45 -> 0
B46: Кредит ва лизинглар | C46: 1325111 | D46: 0 | E46: 13017 | F46: 0 | G46: 160721 | H46: 0 | I46: 782896 | J46: 0 | K46: 2877166 | L46: 0 | M46: 375762 | N46: 0 | O46: 751524 | P46: 0 | Q46: 1862218 | R46: 0 | S46: =+C46+E46+G46+I46+K46+M46+O46+Q46 -> 8148415 | T46: =+S46-U46 -> 8148415 | U46: =+D46+F46+H46+J46+L46+N46+P46+R46 -> 0
B47: Депозит маблағлар | S47: =+C47+E47+G47+I47+K47+M47+O47+Q47 -> 0 | T47: =+S47-U47 -> 0 | U47: =+D47+F47+H47+J47+L47+N47+P47+R47 -> 0
B48: Ўзбекистон тикланиш ва тараққиёт фонди (ФРРУ), шундан | C48: =+C49+C50 -> 0 | D48: =+D49+D50 -> 0 | E48: =+E49+E50 -> 0 | F48: =+F49+F50 -> 0 | G48: =+G49+G50 -> 35200621 | H48: =+H49+H50 -> 35200621 | I48: =+I49+I50 -> 36347377 | J48: =+J49+J50 -> 19545256 | ... R48: =+R49+R50 -> 386075753 | S48: =+C48+E48+G48+I48+K48+M48+O48+Q48 -> 1389498535 | T48: =+S48-U48 -> 784439274 | U48: =+D48+F48+H48+J48+L48+N48+P48+R48 -> 605059261
B49: Кредит ва лизинглар | C49: 0 | D49: 0 | E49: 0 | F49: 0 | G49: 35200621 | H49: 35200621 | I49: 36347377 | J49: 19545256 | K49: 52776825 | L49: 0 | M49: 130130380 | N49: 54745877 | O49: 256530866 | P49: 109491754 | Q49: 878512466 | R49: 386075753 | S49: =+C49+E49+G49+I49+K49+M49+O49+Q49 -> 1389498535 | T49: =+S49-U49 -> 784439274 | U49: =+D49+F49+H49+J49+L49+N49+P49+R49 -> 605059261
B50: Депозит маблағлар | S50: =+C50+E50+G50+I50+K50+M50+O50+Q50 -> 0 | T50: =+S50-U50 -> 0 | U50: =+D50+F50+H50+J50+L50+N50+P50+R50 -> 0
B51: Хорижий банклар, шундан | C51: =+C52+C53 -> 0 | D51: =+D52+D53 -> 0 | E51: =+E52+E53 -> 2031365 | F51: =+F52+F53 -> 2031365 | G51: =+G52+G53 -> 738216175 | H51: =+H52+H53 -> 738216175 | I51: =+I52+I53 -> 788947997 | J51: =+J52+J53 -> 788947997 | ... R51: =+R52+R53 -> 9487003522 | S51: =+C51+E51+G51+I51+K51+M51+O51+Q51 -> 20914638743 | T51: =+S51-U51 -> 229294221 | U51: =+D51+F51+H51+J51+L51+N51+P51+R51 -> 20685344522
B52: Кредит ва лизинглар | C52: 0 | D52: 0 | E52: 2031365 | F52: 2031365 | G52: 738216175 | H52: 738216175 | I52: 788947997 | J52: 788947997 | K52: 2176482569 | L52: 2161000212 | M52: 5012647777 | N52: 4936216370 | O52: 2709309338 | P52: 2571928881 | Q52: 9487003522 | R52: 9487003522 | S52: =+C52+E52+G52+I52+K52+M52+O52+Q52 -> 20914638743 | T52: =+S52-U52 -> 229294221 | U52: =+D52+F52+H52+J52+L52+N52+P52+R52 -> 20685344522
B53: Депозит маблағлар | S53: =+C53+E53+G53+I53+K53+M53+O53+Q53 -> 0 | T53: =+S53-U53 -> 0 | U53: =+D53+F53+H53+J53+L53+N53+P53+R53 -> 0
B54: Бошқа халқаро молия ташкилотлари маблағлари, шундан, | C54: =+C55+C56 -> 0 | D54: =+D55+D56 -> 0 | E54: =+E55+E56 -> 0 | F54: =+F55+F56 -> 0 | G54: =+G55+G56 -> 0 | H54: =+H55+H56 -> 0 | I54: =+I55+I56 -> 41676136 | J54: =+J55+J56 -> 41543372 | ... R54: =+R55+R56 -> 6132336383 | S54: =+C54+E54+G54+I54+K54+M54+O54+Q54 -> 10985493764 | T54: =+S54-U54 -> 2082479289 | U54: =+D54+F54+H54+J54+L54+N54+P54+R54 -> 8903014475
B55: Кредит ва лизинглар | C55: 0 | D55: 0 | E55: 0 | F55: 0 | G55: 0 | H55: 0 | I55: 41676136 | J55: 41543372 | K55: 678510949 | L55: 51227285 | M55: 913535215 | N55: 776678221 | O55: 2591571520 | P55: 1901229214 | Q55: 6760199944 | R55: 6132336383 | S55: =+C55+E55+G55+I55+K55+M55+O55+Q55 -> 10985493764 | T55: =+S55-U55 -> 2082479289 | U55: =+D55+F55+H55+J55+L55+N55+P55+R55 -> 8903014475
B56: Депозит маблағлар | S56: =+C56+E56+G56+I56+K56+M56+O56+Q56 -> 0 | T56: =+S56-U56 -> 0 | U56: =+D56+F56+H56+J56+L56+N56+P56+R56 -> 0
B58: Бошқарув Раис имзоси:
B60: Бош бухгалтер имзоси:

Sheet Bank Liabilities Analysis (нац)
A2: МИЛЛИЙ ВАЛЮТАДА БАНК МАЖБУРИЯТЛАРИ ТАҲЛИЛИ | L2: 18 А-жадвал
B3: =Balance!B3 -> "Ўзсаноатқурилишбанк" АТБ | K3: =+Balance!D3 -> 45289 | M3: =+Balance!E3 -> минг сўмда
A4: № | B4: Кўрсаткичлар | C4: Сўндириш муддати (кунларда) | K4: Жами | L4: Ликвидлиликни қоплаш меёри ҳисоб китоби
C5: Муддатсиз | D5: 1 дан 7 гача | E5: 8 дан 30 гача | F5: 31 дан 90 гача | G5: 91 дан 180 гача | H5: 181 дан 365 гача | I5: 366 дан 730 гача | J5: 2 йилдан ортиқ
L6: Коэффициент | M6: 30 кунлик чиқим суммаси
A7: 1. | B7: ДЕПОЗИТЛАР
A8: 1.1 | B8: Талаб қилиб олингунча депозитлар | C8: =SUM(C9:C12) -> 1863651772 | D8: =SUM(D9:D12) -> 0 | E8: =SUM(E9:E12) -> 0 | F8: =SUM(F9:F12) -> 0 | G8: =SUM(G9:G12) -> 0 | H8: =SUM(H9:H12) -> 0 | I8: =SUM(I9:I12) -> 0 | J8: =SUM(J9:J12) -> 0 | K8: =+C8+D8+E8+F8+G8+H8+I8+J8 -> 1863651772
A9: 1.1.1 | B9: Aҳолининг талаб қилиб олингунча омонатлари | C9: =+'Bank Liabilities Analysis'!C8-'Bank Liabilities Analysis'!D8 -> 57503603 | D9: =+'Bank Liabilities Analysis'!E8-'Bank Liabilities Analysis'!F8 -> 0 | E9: =+'Bank Liabilities Analysis'!G8-'Bank Liabilities Analysis'!H8 -> 0 | F9: =+'Bank Liabilities Analysis'!I8-'Bank Liabilities Analysis'!J8 -> 0 | G9: =+'Bank Liabilities Analysis'!K8-'Bank Liabilities Analysis'!L8 -> 0 | H9: =+'Bank Liabilities Analysis'!M8-'Bank Liabilities Analysis'!N8 -> 0 | I9: =+'Bank Liabilities Analysis'!O8-'Bank Liabilities Analysis'!P8 -> 0 | J9: =+'Bank Liabilities Analysis'!Q8-'Bank Liabilities Analysis'!R8 -> 0 | K9: =+C9+D9+E9+F9+G9+H9+I9+J9 -> 57503603
A10: 1.1.2 | B10: Кредит таъминоти сифатида жалб этилган aҳоли омонатлари | C10: =+'Bank Liabilities Analysis'!C9-'Bank Liabilities Analysis'!D9 -> 0 | D10: =+'Bank Liabilities Analysis'!E9-'Bank Liabilities Analysis'!F9 -> 0 | E10: =+'Bank Liabilities Analysis'!G9-'Bank Liabilities Analysis'!H9 -> 0 | F10: =+'Bank Liabilities Analysis'!I9-'Bank Liabilities Analysis'!J9 -> 0 | G10: =+'Bank Liabilities Analysis'!K9-'Bank Liabilities Analysis'!L9 -> 0 | H10: =+'Bank Liabilities Analysis'!M9-'Bank Liabilities Analysis'!N9 -> 0 | I10: =+'Bank Liabilities Analysis'!O9-'Bank Liabilities Analysis'!P9 -> 0 | J10: =+'Bank Liabilities Analysis'!Q9-'Bank Liabilities Analysis'!R9 -> 0 | K10: =+C10+D10+E10+F10+G10+H10+I10+J10 -> 0
A11: 1.1.3 | B11: Кредит таъминоти сифатида жалб этилган бошқа депозитлар | C11: =+'Bank Liabilities Analysis'!C10-'Bank Liabilities Analysis'!D10 -> 0 | D11: =+'Bank Liabilities Analysis'!E10-'Bank Liabilities Analysis'!F10 -> 0 | E11: =+'Bank Liabilities Analysis'!G10-'Bank Liabilities Analysis'!H10 -> 0 | F11: =+'Bank Liabilities Analysis'!I10-'Bank Liabilities Analysis'!J10 -> 0 | G11: =+'Bank Liabilities Analysis'!K10-'Bank Liabilities Analysis'!L10 -> 0 | H11: =+'Bank Liabilities Analysis'!M10-'Bank Liabilities Analysis'!N10 -> 0 | I11: =+'Bank Liabilities Analysis'!O10-'Bank Liabilities Analysis'!P10 -> 0 | J11: =+'Bank Liabilities Analysis'!Q10-'Bank Liabilities Analysis'!R10 -> 0 | K11: =+C11+D11+E11+F11+G11+H11+I11+J11 -> 0
A12: 1.1.4 | B12: Талаб қилиб олингунча бошқа депозитлар | C12: =+'Bank Liabilities Analysis'!C11-'Bank Liabilities Analysis'!D11 -> 1806148169 | D12: =+'Bank Liabilities Analysis'!E11-'Bank Liabilities Analysis'!F11 -> 0 | E12: =+'Bank Liabilities Analysis'!G11-'Bank Liabilities Analysis'!H11 -> 0 | F12: =+'Bank Liabilities Analysis'!I11-'Bank Liabilities Analysis'!J11 -> 0 | G12: =+'Bank Liabilities Analysis'!K11-'Bank Liabilities Analysis'!L11 -> 0 | H12: =+'Bank Liabilities Analysis'!M11-'Bank Liabilities Analysis'!N11 -> 0 | I12: =+'Bank Liabilities Analysis'!O11-'Bank Liabilities Analysis'!P11 -> 0 | J12: =+'Bank Liabilities Analysis'!Q11-'Bank Liabilities Analysis'!R11 -> 0 | K12: =+C12+D12+E12+F12+G12+H12+I12+J12 -> 1806148169
A13: 1.2 | B13: Муддатли депозитлар | C13: =+'Bank Liabilities Analysis'!C12-'Bank Liabilities Analysis'!D12 -> 32251864 | D13: =+'Bank Liabilities Analysis'!E12-'Bank Liabilities Analysis'!F12 -> 39064100 | E13: =+'Bank Liabilities Analysis'!G12-'Bank Liabilities Analysis'!H12 -> 237959693 | F13: =+'Bank Liabilities Analysis'!I12-'Bank Liabilities Analysis'!J12 -> 691320478 | G13: =+'Bank Liabilities Analysis'!K12-'Bank Liabilities Analysis'!L12 -> 948925350 | H13: =+'Bank Liabilities Analysis'!M12-'Bank Liabilities Analysis'!N12 -> 1438922313 | I13: =+'Bank Liabilities Analysis'!O12-'Bank Liabilities Analysis'!P12 -> 656043010 | J13: =+'Bank Liabilities Analysis'!Q12-'Bank Liabilities Analysis'!R12 -> 1310151711 | K13: =+C13+D13+E13+F13+G13+H13+I13+J13 -> 5354638519
A14: 1.2.1 | B14: Аҳоли омонатлари | C14: =+'Bank Liabilities Analysis'!C13-'Bank Liabilities Analysis'!D13 -> 32051864 | D14: =+'Bank Liabilities Analysis'!E13-'Bank Liabilities Analysis'!F13 -> 37284099 | E14: =+'Bank Liabilities Analysis'!G13-'Bank Liabilities Analysis'!H13 -> 143693397 | F14: =+'Bank Liabilities Analysis'!I13-'Bank Liabilities Analysis'!J13 -> 572270433 | G14: =+'Bank Liabilities Analysis'!K13-'Bank Liabilities Analysis'!L13 -> 338379549 | H14: =+'Bank Liabilities Analysis'!M13-'Bank Liabilities Analysis'!N13 -> 1169984956 | I14: =+'Bank Liabilities Analysis'!O13-'Bank Liabilities Analysis'!P13 -> 412935434 | J14: =+'Bank Liabilities Analysis'!Q13-'Bank Liabilities Analysis'!R13 -> 4092035 | K14: =+C14+D14+E14+F14+G14+H14+I14+J14 -> 2710691767
A15: 1.2.2 | B15: Чиқарилган депозит сертификатлари | C15: =+'Bank Liabilities Analysis'!C14-'Bank Liabilities Analysis'!D14 -> 0 | D15: =+'Bank Liabilities Analysis'!E14-'Bank Liabilities Analysis'!F14 -> 0 | E15: =+'Bank Liabilities Analysis'!G14-'Bank Liabilities Analysis'!H14 -> 0 | F15: =+'Bank Liabilities Analysis'!I14-'Bank Liabilities Analysis'!J14 -> 0 | G15: =+'Bank Liabilities Analysis'!K14-'Bank Liabilities Analysis'!L14 -> 0 | H15: =+'Bank Liabilities Analysis'!M14-'Bank Liabilities Analysis'!N14 -> 0 | I15: =+'Bank Liabilities Analysis'!O14-'Bank Liabilities Analysis'!P14 -> 0 | J15: =+'Bank Liabilities Analysis'!Q14-'Bank Liabilities Analysis'!R14 -> 0 | K15: =+C15+D15+E15+F15+G15+H15+I15+J15 -> 0
A16: 1.3 | B16: Мижозларнинг бошқа депозитлари | C16: =SUM(C17:C20) -> 1690760939 | D16: =SUM(D17:D20) -> 0 | E16: =SUM(E17:E20) -> 0 | F16: =SUM(F17:F20) -> 529752 | G16: =SUM(G17:G20) -> 0 | H16: =SUM(H17:H20) -> 0 | I16: =SUM(I17:I20) -> 0 | J16: =SUM(J17:J20) -> 0 | K16: =+C16+D16+E16+F16+G16+H16+I16+J16 -> 1691290691
A17: 1.3.1 | B17: Жисмоний шахсларнинг банк пластик карталаридаги маблағлари | C17: =+'Bank Liabilities Analysis'!C16-'Bank Liabilities Analysis'!D16 -> 1128589274 | D17: =+'Bank Liabilities Analysis'!E16-'Bank Liabilities Analysis'!F16 -> 0 | E17: =+'Bank Liabilities Analysis'!G16-'Bank Liabilities Analysis'!H16 -> 0 | F17: =+'Bank Liabilities Analysis'!I16-'Bank Liabilities Analysis'!J16 -> 0 | G17: =+'Bank Liabilities Analysis'!K16-'Bank Liabilities Analysis'!L16 -> 0 | H17: =+'Bank Liabilities Analysis'!M16-'Bank Liabilities Analysis'!N16 -> 0 | I17: =+'Bank Liabilities Analysis'!O16-'Bank Liabilities Analysis'!P16 -> 0 | J17: =+'Bank Liabilities Analysis'!Q16-'Bank Liabilities Analysis'!R16 -> 0 | K17: =+C17+D17+E17+F17+G17+H17+I17+J17 -> 1128589274
A18: 1.3.2 | B18: Бошқа мижозларнинг банк пластик карталаридаги маблағлари | C18: =+'Bank Liabilities Analysis'!C17-'Bank Liabilities Analysis'!D17 -> 16528585 | D18: =+'Bank Liabilities Analysis'!E17-'Bank Liabilities Analysis'!F17 -> 0 | E18: =+'Bank Liabilities Analysis'!G17-'Bank Liabilities Analysis'!H17 -> 0 | F18: =+'Bank Liabilities Analysis'!I17-'Bank Liabilities Analysis'!J17 -> 0 | G18: =+'Bank Liabilities Analysis'!K17-'Bank Liabilities Analysis'!L17 -> 0 | H18: =+'Bank Liabilities Analysis'!M17-'Bank Liabilities Analysis'!N17 -> 0 | I18: =+'Bank Liabilities Analysis'!O17-'Bank Liabilities Analysis'!P17 -> 0 | J18: =+'Bank Liabilities Analysis'!Q17-'Bank Liabilities Analysis'!R17 -> 0 | K18: =+C18+D18+E18+F18+G18+H18+I18+J18 -> 16528585
A19: 1.3.3 | B19: Мижозларнинг аккредитив бўйича депозитлари | C19: =+'Bank Liabilities Analysis'!C18-'Bank Liabilities Analysis'!D18 -> 0 | D19: =+'Bank Liabilities Analysis'!E18-'Bank Liabilities Analysis'!F18 -> 0 | E19: =+'Bank Liabilities Analysis'!G18-'Bank Liabilities Analysis'!H18 -> 0 | F19: =+'Bank Liabilities Analysis'!I18-'Bank Liabilities Analysis'!J18 -> 529752 | G19: =+'Bank Liabilities Analysis'!K18-'Bank Liabilities Analysis'!L18 -> 0 | H19: =+'Bank Liabilities Analysis'!M18-'Bank Liabilities Analysis'!N18 -> 0 | I19: =+'Bank Liabilities Analysis'!O18-'Bank Liabilities Analysis'!P18 -> 0 | J19: =+'Bank Liabilities Analysis'!Q18-'Bank Liabilities Analysis'!R18 -> 0 | K19: =+C19+D19+E19+F19+G19+H19+I19+J19 -> 529752
A20: 1.3.4 | B20: Бошқалар | C20: =+'Bank Liabilities Analysis'!C19-'Bank Liabilities Analysis'!D19 -> 545643080 | D20: =+'Bank Liabilities Analysis'!E19-'Bank Liabilities Analysis'!F19 -> 0 | E20: =+'Bank Liabilities Analysis'!G19-'Bank Liabilities Analysis'!H19 -> 0 | F20: =+'Bank Liabilities Analysis'!I19-'Bank Liabilities Analysis'!J19 -> 0 | G20: =+'Bank Liabilities Analysis'!K19-'Bank Liabilities Analysis'!L19 -> 0 | H20: =+'Bank Liabilities Analysis'!M19-'Bank Liabilities Analysis'!N19 -> 0 | I20: =+'Bank Liabilities Analysis'!O19-'Bank Liabilities Analysis'!P19 -> 0 | J20: =+'Bank Liabilities Analysis'!Q19-'Bank Liabilities Analysis'!R19 -> 0 | K20: =+C20+D20+E20+F20+G20+H20+I20+J20 -> 545643080
A21: 1.4 | B21: Жами депозитлар | C21: =+C8+C13+C16 -> 3586664575 | D21: =+D8+D13+D16 -> 39064100 | E21: =+E8+E13+E16 -> 237959693 | F21: =+F8+F13+F16 -> 691850230 | G21: =+G8+G13+G16 -> 948925350 | H21: =+H8+H13+H16 -> 1438922313 | I21: =+I8+I13+I16 -> 656043010 | J21: =+J8+J13+J16 -> 1310151711 | K21: =+C21+D21+E21+F21+G21+H21+I21+J21 -> 8909580982 | L21: 0.15 | M21: =+K21*L21 -> 1.3364371e+09
A22: 2. | B22: Марказий банкка тўланиши лозим бўлган маблағлар | C22: =+'Bank Liabilities Analysis'!C21-'Bank Liabilities Analysis'!D21 -> 1074053 | D22: =+'Bank Liabilities Analysis'!E21-'Bank Liabilities Analysis'!F21 -> 0 | E22: =+'Bank Liabilities Analysis'!G21-'Bank Liabilities Analysis'!H21 -> 0 | F22: =+'Bank Liabilities Analysis'!I21-'Bank Liabilities Analysis'!J21 -> 0 | G22: =+'Bank Liabilities Analysis'!K21-'Bank Liabilities Analysis'!L21 -> 0 | H22: =+'Bank Liabilities Analysis'!M21-'Bank Liabilities Analysis'!N21 -> 0 | I22: =+'Bank Liabilities Analysis'!O21-'Bank Liabilities Analysis'!P21 -> 0 | J22: =+'Bank Liabilities Analysis'!Q21-'Bank Liabilities Analysis'!R21 -> 0 | K22: =+C22+D22+E22+F22+G22+H22+I22+J22 -> 1074053 | L22: 1 | M22: =(C22+D22+E22-C23-D23-E23)*L22 -> 0
A23: 2.1. | B23: шу жумладан, Марказий банкка тўланиши лозим бўлган маблағлар -Тезкор тўловлар ҳамда клиринг тизими | C23: =+'Bank Liabilities Analysis'!C22-'Bank Liabilities Analysis'!D22 -> 1074053 | D23: =+'Bank Liabilities Analysis'!E22-'Bank Liabilities Analysis'!F22 -> 0 | E23: =+'Bank Liabilities Analysis'!G22-'Bank Liabilities Analysis'!H22 -> 0 | F23: =+'Bank Liabilities Analysis'!I22-'Bank Liabilities Analysis'!J22 -> 0 | G23: =+'Bank Liabilities Analysis'!K22-'Bank Liabilities Analysis'!L22 -> 0 | H23: =+'Bank Liabilities Analysis'!M22-'Bank Liabilities Analysis'!N22 -> 0 | I23: =+'Bank Liabilities Analysis'!O22-'Bank Liabilities Analysis'!P22 -> 0 | J23: =+'Bank Liabilities Analysis'!Q22-'Bank Liabilities Analysis'!R22 -> 0 | K23: =+C23+D23+E23+F23+G23+H23+I23+J23 -> 1074053
A24: 3. | B24: Бошқа банклар ва молиявий ташкилотларга тўланиши лозим бўлган маблағлар | C24: =SUM(C25:C29)-C26 -> 38634740 | D24: =SUM(D25:D29)-D26 -> 0 | E24: =SUM(E25:E29)-E26 -> 675620451 | F24: =SUM(F25:F29)-F26 -> 442019549 | G24: =SUM(G25:G29)-G26 -> 244545210 | H24: =SUM(H25:H29)-H26 -> 44246423 | I24: =SUM(I25:I29)-I26 -> 77714202 | J24: =SUM(J25:J29)-J26 -> 50660092 | K24: =+C24+D24+E24+F24+G24+H24+I24+J24 -> 1573440667
A25: 3.1 | B25: Бошқа банкларнинг вакиллик ҳисобварақларига тўланиши лозим бўлган маблағлар | C25: =+'Bank Liabilities Analysis'!C24-'Bank Liabilities Analysis'!D24 -> 2691418 | D25: =+'Bank Liabilities Analysis'!E24-'Bank Liabilities Analysis'!F24 -> 0 | E25: =+'Bank Liabilities Analysis'!G24-'Bank Liabilities Analysis'!H24 -> 0 | F25: =+'Bank Liabilities Analysis'!I24-'Bank Liabilities Analysis'!J24 -> 0 | G25: =+'Bank Liabilities Analysis'!K24-'Bank Liabilities Analysis'!L24 -> 0 | H25: =+'Bank Liabilities Analysis'!M24-'Bank Liabilities Analysis'!N24 -> 0 | I25: =+'Bank Liabilities Analysis'!O24-'Bank Liabilities Analysis'!P24 -> 0 | J25: =+'Bank Liabilities Analysis'!Q24-'Bank Liabilities Analysis'!R24 -> 0 | K25: =+C25+D25+E25+F25+G25+H25+I25+J25 -> 2691418 | L25: 1 | M25: =C25*L25 -> 2691418
A26: 3.1.1 | B26: шу жумладан, махаллий банкларнинг вакиллик ҳисобварақларига тўланиши лозим бўлган маблағлар | C26: =+'Bank Liabilities Analysis'!C25-'Bank Liabilities Analysis'!D25 -> 0 | D26: =+'Bank Liabilities Analysis'!E25-'Bank Liabilities Analysis'!F25 -> 0 | E26: =+'Bank Liabilities Analysis'!G25-'Bank Liabilities Analysis'!H25 -> 0 | F26: =+'Bank Liabilities Analysis'!I25-'Bank Liabilities Analysis'!J25 -> 0 | G26: =+'Bank Liabilities Analysis'!K25-'Bank Liabilities Analysis'!L25 -> 0 | H26: =+'Bank Liabilities Analysis'!M25-'Bank Liabilities Analysis'!N25 -> 0 | I26: =+'Bank Liabilities Analysis'!O25-'Bank Liabilities Analysis'!P25 -> 0 | J26: =+'Bank Liabilities Analysis'!Q25-'Bank Liabilities Analysis'!R25 -> 0 | K26: =+C26+D26+E26+F26+G26+H26+I26+J26 -> 0
A27: 3.2 | B27: Бошқа банкларнинг ҳисобварақлари - Депозитлар | C27: =+'Bank Liabilities Analysis'!C26-'Bank Liabilities Analysis'!D26 -> 6951773 | D27: =+'Bank Liabilities Analysis'!E26-'Bank Liabilities Analysis'!F26 -> 0 | E27: =+'Bank Liabilities Analysis'!G26-'Bank Liabilities Analysis'!H26 -> 675620451 | F27: =+'Bank Liabilities Analysis'!I26-'Bank Liabilities Analysis'!J26 -> 442019549 | G27: =+'Bank Liabilities Analysis'!K26-'Bank Liabilities Analysis'!L26 -> 244545210 | H27: =+'Bank Liabilities Analysis'!M26-'Bank Liabilities Analysis'!N26 -> 44246423 | I27: =+'Bank Liabilities Analysis'!O26-'Bank Liabilities Analysis'!P26 -> 77714202 | J27: =+'Bank Liabilities Analysis'!Q26-'Bank Liabilities Analysis'!R26 -> 50660092 | K27: =+C27+D27+E27+F27+G27+H27+I27+J27 -> 1541757700 | L27: 1 | M27: =(C27+D27+E27)*L27 -> 682572224
A28: 3.3 | B28: Банк карталаридан амалга оширилган тўловлар бўйича банкларга тўланиши лозим бўлган маблағлар | C28: =+'Bank Liabilities Analysis'!C27-'Bank Liabilities Analysis'!D27 -> 28991549 | D28: =+'Bank Liabilities Analysis'!E27-'Bank Liabilities Analysis'!F27 -> 0 | E28: =+'Bank Liabilities Analysis'!G27-'Bank Liabilities Analysis'!H27 -> 0 | F28: =+'Bank Liabilities Analysis'!I27-'Bank Liabilities Analysis'!J27 -> 0 | G28: =+'Bank Liabilities Analysis'!K27-'Bank Liabilities Analysis'!L27 -> 0 | H28: =+'Bank Liabilities Analysis'!M27-'Bank Liabilities Analysis'!N27 -> 0 | I28: =+'Bank Liabilities Analysis'!O27-'Bank Liabilities Analysis'!P27 -> 0 | J28: =+'Bank Liabilities Analysis'!Q27-'Bank Liabilities Analysis'!R27 -> 0 | K28: =+C28+D28+E28+F28+G28+H28+I28+J28 -> 28991549 | L28: 1 | M28: =(C28+D28+E28)*L28 -> 28991549
A29: 3.4 | B29: Бошқа моддалар | C29: =+'Bank Liabilities Analysis'!C28-'Bank Liabilities Analysis'!D28 -> 0 | D29: =+'Bank Liabilities Analysis'!E28-'Bank Liabilities Analysis'!F28 -> 0 | E29: =+'Bank Liabilities Analysis'!G28-'Bank Liabilities Analysis'!H28 -> 0 | F29: =+'Bank Liabilities Analysis'!I28-'Bank Liabilities Analysis'!J28 -> 0 | G29: =+'Bank Liabilities Analysis'!K28-'Bank Liabilities Analysis'!L28 -> 0 | H29: =+'Bank Liabilities Analysis'!M28-'Bank Liabilities Analysis'!N28 -> 0 | I29: =+'Bank Liabilities Analysis'!O28-'Bank Liabilities Analysis'!P28 -> 0 | J29: =+'Bank Liabilities Analysis'!Q28-'Bank Liabilities Analysis'!R28 -> 0 | K29: =+C29+D29+E29+F29+G29+H29+I29+J29 -> 0 | L29: 1 | M29: =(C29+D29+E29)*L29 -> 0
A30: 4. | B30: Банкнинг тўланмаган акцептлари | C30: =+'Bank Liabilities Analysis'!C29-'Bank Liabilities Analysis'!D29 -> 0 | D30: =+'Bank Liabilities Analysis'!E29-'Bank Liabilities Analysis'!F29 -> 0 | E30: =+'Bank Liabilities Analysis'!G29-'Bank Liabilities Analysis'!H29 -> 0 | F30: =+'Bank Liabilities Analysis'!I29-'Bank Liabilities Analysis'!J29 -> 0 | G30: =+'Bank Liabilities Analysis'!K29-'Bank Liabilities Analysis'!L29 -> 0 | H30: =+'Bank Liabilities Analysis'!M29-'Bank Liabilities Analysis'!N29 -> 0 | I30: =+'Bank Liabilities Analysis'!O29-'Bank Liabilities Analysis'!P29 -> 0 | J30: =+'Bank Liabilities Analysis'!Q29-'Bank Liabilities Analysis'!R29 -> 0 | K30: =+C30+D30+E30+F30+G30+H30+I30+J30 -> 0 | L30: 1 | M30: =(C30+D30+E30)*L30 -> 0
A31: 5. | B31: Олинган кредит ва лизинглар (молиявий ижара) бўйича мажбуриятлар | C31: =+'Bank Liabilities Analysis'!C30-'Bank Liabilities Analysis'!D30 -> 1325111 | D31: =+'Bank Liabilities Analysis'!E30-'Bank Liabilities Analysis'!F30 -> 6797051 | E31: =+'Bank Liabilities Analysis'!G30-'Bank Liabilities Analysis'!H30 -> 3226276 | F31: =+'Bank Liabilities Analysis'!I30-'Bank Liabilities Analysis'!J30 -> 184145387 | G31: =+'Bank Liabilities Analysis'!K30-'Bank Liabilities Analysis'!L30 -> 1024875107 | H31: =+'Bank Liabilities Analysis'!M30-'Bank Liabilities Analysis'!N30 -> 1556969426 | I31: =+'Bank Liabilities Analysis'!O30-'Bank Liabilities Analysis'!P30 -> 1148070535 | J31: =+'Bank Liabilities Analysis'!Q30-'Bank Liabilities Analysis'!R30 -> 1598494033 | K31: =+C31+D31+E31+F31+G31+H31+I31+J31 -> 5523902926 | L31: 0.05 | M31: =+K31*L31 -> 2.7619515e+08
A32: 6. | B32: Банк томонидан чиқарилган қимматли қоғозлар | C32: =+'Bank Liabilities Analysis'!C31-'Bank Liabilities Analysis'!D31 -> 0 | D32: =+'Bank Liabilities Analysis'!E31-'Bank Liabilities Analysis'!F31 -> 0 | E32: =+'Bank Liabilities Analysis'!G31-'Bank Liabilities Analysis'!H31 -> 0 | F32: =+'Bank Liabilities Analysis'!I31-'Bank Liabilities Analysis'!J31 -> 0 | G32: =+'Bank Liabilities Analysis'!K31-'Bank Liabilities Analysis'!L31 -> 0 | H32: =+'Bank Liabilities Analysis'!M31-'Bank Liabilities Analysis'!N31 -> 0 | I32: =+'Bank Liabilities Analysis'!O31-'Bank Liabilities Analysis'!P31 -> 0 | J32: =+'Bank Liabilities Analysis'!Q31-'Bank Liabilities Analysis'!R31 -> 0 | K32: =+C32+D32+E32+F32+G32+H32+I32+J32 -> 0 | L32: 1 | M32: =(C32+D32+E32)*L32 -> 0
A33: 7. | B33: Субординар қарз мажбуриятлари | C33: =+'Bank Liabilities Analysis'!C32-'Bank Liabilities Analysis'!D32 -> 0 | D33: =+'Bank Liabilities Analysis'!E32-'Bank Liabilities Analysis'!F32 -> 0 | E33: =+'Bank Liabilities Analysis'!G32-'Bank Liabilities Analysis'!H32 -> 1994167 | F33: =+'Bank Liabilities Analysis'!I32-'Bank Liabilities Analysis'!J32 -> 2431833 | G33: =+'Bank Liabilities Analysis'!K32-'Bank Liabilities Analysis'!L32 -> 4426000 | H33: =+'Bank Liabilities Analysis'!M32-'Bank Liabilities Analysis'!N32 -> 11181500 | I33: =+'Bank Liabilities Analysis'!O32-'Bank Liabilities Analysis'!P32 -> 27022000 | J33: =+'Bank Liabilities Analysis'!Q32-'Bank Liabilities Analysis'!R32 -> 1459811606 | K33: =+C33+D33+E33+F33+G33+H33+I33+J33 -> 1506867106 | L33: 1 | M33: =(C33+D33+E33)*L33 -> 1994167
A34: 8. | B34: РЕПО битимлари бўйича сотилган қимматли қоғозлар | C34: =+'Bank Liabilities Analysis'!C33-'Bank Liabilities Analysis'!D33 -> 0 | D34: =+'Bank Liabilities Analysis'!E33-'Bank Liabilities Analysis'!F33 -> 816807035 | E34: =+'Bank Liabilities Analysis'!G33-'Bank Liabilities Analysis'!H33 -> 0 | F34: =+'Bank Liabilities Analysis'!I33-'Bank Liabilities Analysis'!J33 -> 0 | G34: =+'Bank Liabilities Analysis'!K33-'Bank Liabilities Analysis'!L33 -> 0 | H34: =+'Bank Liabilities Analysis'!M33-'Bank Liabilities Analysis'!N33 -> 0 | I34: =+'Bank Liabilities Analysis'!O33-'Bank Liabilities Analysis'!P33 -> 0 | J34: =+'Bank Liabilities Analysis'!Q33-'Bank Liabilities Analysis'!R33 -> 0 | K34: =+C34+D34+E34+F34+G34+H34+I34+J34 -> 816807035
A35: 8.1 | B35: РЕПО битимлари бўйича сотилган юқори ликвидли қимматли қоғозлар | C35: =+'Bank Liabilities Analysis'!C34-'Bank Liabilities Analysis'!D34 -> 0 | D35: =+'Bank Liabilities Analysis'!E34-'Bank Liabilities Analysis'!F34 -> 816807035 | E35: =+'Bank Liabilities Analysis'!G34-'Bank Liabilities Analysis'!H34 -> 0 | F35: =+'Bank Liabilities Analysis'!I34-'Bank Liabilities Analysis'!J34 -> 0 | G35: =+'Bank Liabilities Analysis'!K34-'Bank Liabilities Analysis'!L34 -> 0 | H35: =+'Bank Liabilities Analysis'!M34-'Bank Liabilities Analysis'!N34 -> 0 | I35: =+'Bank Liabilities Analysis'!O34-'Bank Liabilities Analysis'!P34 -> 0 | J35: =+'Bank Liabilities Analysis'!Q34-'Bank Liabilities Analysis'!R34 -> 0 | K35: =+C35+D35+E35+F35+G35+H35+I35+J35 -> 816807035 | L35: 1 | M35: =(C35+D35+E35)*L35 -> 816807035
A36: 8.2 | B36: РЕПО битимлари бўйича сотилган бошқа қимматли қоғозлар | C36: =+'Bank Liabilities Analysis'!C35-'Bank Liabilities Analysis'!D35 -> 0 | D36: =+'Bank Liabilities Analysis'!E35-'Bank Liabilities Analysis'!F35 -> 0 | E36: =+'Bank Liabilities Analysis'!G35-'Bank Liabilities Analysis'!H35 -> 0 | F36: =+'Bank Liabilities Analysis'!I35-'Bank Liabilities Analysis'!J35 -> 0 | G36: =+'Bank Liabilities Analysis'!K35-'Bank Liabilities Analysis'!L35 -> 0 | H36: =+'Bank Liabilities Analysis'!M35-'Bank Liabilities Analysis'!N35 -> 0 | I36: =+'Bank Liabilities Analysis'!O35-'Bank Liabilities Analysis'!P35 -> 0 | J36: =+'Bank Liabilities Analysis'!Q35-'Bank Liabilities Analysis'!R35 -> 0 | K36: =+C36+D36+E36+F36+G36+H36+I36+J36 -> 0 | L36: 1 | M36: =(C36+D36+E36)*L36 -> 0
A37: 9. | B37: Ҳосилавий инструментлар бўйича ревальвация натижасида амалга ошмаган зарарлар ва бошқа муддати узайтирилган даромадлар | C37: =+'Bank Liabilities Analysis'!C36-'Bank Liabilities Analysis'!D36 -> 25082725 | D37: =+'Bank Liabilities Analysis'!E36-'Bank Liabilities Analysis'!F36 -> 0 | E37: =+'Bank Liabilities Analysis'!G36-'Bank Liabilities Analysis'!H36 -> 0 | F37: =+'Bank Liabilities Analysis'!I36-'Bank Liabilities Analysis'!J36 -> 0 | G37: =+'Bank Liabilities Analysis'!K36-'Bank Liabilities Analysis'!L36 -> 0 | H37: =+'Bank Liabilities Analysis'!M36-'Bank Liabilities Analysis'!N36 -> 0 | I37: =+'Bank Liabilities Analysis'!O36-'Bank Liabilities Analysis'!P36 -> 0 | J37: =+'Bank Liabilities Analysis'!Q36-'Bank Liabilities Analysis'!R36 -> 0 | K37: =+C37+D37+E37+F37+G37+H37+I37+J37 -> 25082725 | L37: 1 | M37: =+K37*L37 -> 25082725
A38: 10. | B38: Клиринг транзакциялари | C38: =+'Bank Liabilities Analysis'!C37-'Bank Liabilities Analysis'!D37 -> 2214968 | D38: =+'Bank Liabilities Analysis'!E37-'Bank Liabilities Analysis'!F37 -> 0 | E38: =+'Bank Liabilities Analysis'!G37-'Bank Liabilities Analysis'!H37 -> 0 | F38: =+'Bank Liabilities Analysis'!I37-'Bank Liabilities Analysis'!J37 -> 0 | G38: =+'Bank Liabilities Analysis'!K37-'Bank Liabilities Analysis'!L37 -> 0 | H38: =+'Bank Liabilities Analysis'!M37-'Bank Liabilities Analysis'!N37 -> 0 | I38: =+'Bank Liabilities Analysis'!O37-'Bank Liabilities Analysis'!P37 -> 0 | J38: =+'Bank Liabilities Analysis'!Q37-'Bank Liabilities Analysis'!R37 -> 0 | K38: =+C38+D38+E38+F38+G38+H38+I38+J38 -> 2214968 | L38: 1 | M38: =+K38*L38 -> 2214968
A39: 11. | B39: Тўланиши лозим бўлган ҳисобланган фоизлар | C39: =+'Bank Liabilities Analysis'!C38-'Bank Liabilities Analysis'!D38 -> 107797 | D39: =+'Bank Liabilities Analysis'!E38-'Bank Liabilities Analysis'!F38 -> 0 | E39: =+'Bank Liabilities Analysis'!G38-'Bank Liabilities Analysis'!H38 -> 53277571 | F39: =+'Bank Liabilities Analysis'!I38-'Bank Liabilities Analysis'!J38 -> 0 | G39: =+'Bank Liabilities Analysis'!K38-'Bank Liabilities Analysis'!L38 -> 134012896 | H39: =+'Bank Liabilities Analysis'!M38-'Bank Liabilities Analysis'!N38 -> 0 | I39: =+'Bank Liabilities Analysis'!O38-'Bank Liabilities Analysis'!P38 -> 0 | J39: =+'Bank Liabilities Analysis'!Q38-'Bank Liabilities Analysis'!R38 -> 0 | K39: =+C39+D39+E39+F39+G39+H39+I39+J39 -> 187398264 | M39: =C39+D39+E39+((F39+G39+H39+I39+J39)*15%) -> 73487302
A40: 12. | B40: Бошқа мажбуриятлар | C40: =+'Bank Liabilities Analysis'!C39-'Bank Liabilities Analysis'!D39 -> 223302324 | D40: =+'Bank Liabilities Analysis'!E39-'Bank Liabilities Analysis'!F39 -> 0 | E40: =+'Bank Liabilities Analysis'!G39-'Bank Liabilities Analysis'!H39 -> 0 | F40: =+'Bank Liabilities Analysis'!I39-'Bank Liabilities Analysis'!J39 -> 0 | G40: =+'Bank Liabilities Analysis'!K39-'Bank Liabilities Analysis'!L39 -> 0 | H40: =+'Bank Liabilities Analysis'!M39-'Bank Liabilities Analysis'!N39 -> 0 | I40: =+'Bank Liabilities Analysis'!O39-'Bank Liabilities Analysis'!P39 -> 0 | J40: =+'Bank Liabilities Analysis'!Q39-'Bank Liabilities Analysis'!R39 -> 0 | K40: =+C40+D40+E40+F40+G40+H40+I40+J40 -> 223302324 | L40: 1 | M40: =(C40+D40+E40)*L40 -> 223302324
A41: 13 | B41: ЖАМИ МАЖБУРИЯТЛАР | C41: =+C21+C30+C31+C32+C33+C34+C37+C38+C39+C40+C22+C24 -> 3878406293 | D41: =+D21+D30+D31+D32+D33+D34+D37+D38+D39+D40+D22+D24 -> 862668186 | E41: =+E21+E30+E31+E32+E33+E34+E37+E38+E39+E40+E22+E24 -> 972078158 | F41: =+F21+F30+F31+F32+F33+F34+F37+F38+F39+F40+F22+F24 -> 1320446999 | G41: =+G21+G30+G31+G32+G33+G34+G37+G38+G39+G40+G22+G24 -> 2356784563 | H41: =+H21+H30+H31+H32+H33+H34+H37+H38+H39+H40+H22+H24 -> 3051319662 | I41: =+I21+I30+I31+I32+I33+I34+I37+I38+I39+I40+I22+I24 -> 1908849747 | J41: =+J21+J30+J31+J32+J33+J34+J37+J38+J39+J40+J22+J24 -> 4419117442 | K41: =+K21+K30+K31+K32+K33+K34+K37+K38+K39+K40+K22+K24 -> 18769671050 | L41: отток | M41: =SUM(M8:M40) -> 3469776006 | N41: =+Balance!D63 -> 18769671050
B42: шундан, | K42: =+C42+D42+E42+F42+G42+H42+I42+J42 -> 0 | N42: =+Balance!C64 -> 0
B43: Ўзбекистон Республикаси Молия вазирлиги маблағлари, шундан | C43: =+C44+C45 -> 0 | D43: =+D44+D45 -> 2044630 | E43: =+E44+E45 -> 9538454 | F43: =+F44+F45 -> 153309293 | G43: =+G44+G45 -> 205693566 | H43: =+H44+H45 -> 156362546 | I43: =+I44+I45 -> 176815243 | J43: =+J44+J45 -> 1725747977 | K43: =+C43+D43+E43+F43+G43+H43+I43+J43 -> 2429511709
B44: Кредит ва лизинглар | C44: =+'Bank Liabilities Analysis'!C43-'Bank Liabilities Analysis'!D43 -> 0 | D44: =+'Bank Liabilities Analysis'!E43-'Bank Liabilities Analysis'!F43 -> 1341325 | E44: =+'Bank Liabilities Analysis'!G43-'Bank Liabilities Analysis'!H43 -> 2714923 | F44: =+'Bank Liabilities Analysis'!I43-'Bank Liabilities Analysis'!J43 -> 19617224 | G44: =+'Bank Liabilities Analysis'!K43-'Bank Liabilities Analysis'!L43 -> 38210055 | H44: =+'Bank Liabilities Analysis'!M43-'Bank Liabilities Analysis'!N43 -> 56561607 | I44: =+'Bank Liabilities Analysis'!O43-'Bank Liabilities Analysis'!P43 -> 103221153 | J44: =+'Bank Liabilities Analysis'!Q43-'Bank Liabilities Analysis'!R43 -> 429765672 | K44: =+C44+D44+E44+F44+G44+H44+I44+J44 -> 651431959
B45: Депозит маблағлар | C45: =+'Bank Liabilities Analysis'!C44-'Bank Liabilities Analysis'!D44 -> 0 | D45: =+'Bank Liabilities Analysis'!E44-'Bank Liabilities Analysis'!F44 -> 703305 | E45: =+'Bank Liabilities Analysis'!G44-'Bank Liabilities Analysis'!H44 -> 6823531 | F45: =+'Bank Liabilities Analysis'!I44-'Bank Liabilities Analysis'!J44 -> 133692069 | G45: =+'Bank Liabilities Analysis'!K44-'Bank Liabilities Analysis'!L44 -> 167483511 | H45: =+'Bank Liabilities Analysis'!M44-'Bank Liabilities Analysis'!N44 -> 99800939 | I45: =+'Bank Liabilities Analysis'!O44-'Bank Liabilities Analysis'!P44 -> 73594090 | J45: =+'Bank Liabilities Analysis'!Q44-'Bank Liabilities Analysis'!R44 -> 1295982305 | K45: =+C45+D45+E45+F45+G45+H45+I45+J45 -> 1778079750
B46: Бюджетдан ташқари фондларнинг маблағлари, шундан | C46: =+C47+C48 -> 1325111 | D46: =+D47+D48 -> 13017 | E46: =+E47+E48 -> 160721 | F46: =+F47+F48 -> 782896 | G46: =+G47+G48 -> 2877166 | H46: =+H47+H48 -> 375762 | I46: =+I47+I48 -> 751524 | J46: =+J47+J48 -> 1862218 | K46: =+C46+D46+E46+F46+G46+H46+I46+J46 -> 8148415
B47: Кредит ва лизинглар | C47: =+'Bank Liabilities Analysis'!C46-'Bank Liabilities Analysis'!D46 -> 1325111 | D47: =+'Bank Liabilities Analysis'!E46-'Bank Liabilities Analysis'!F46 -> 13017 | E47: =+'Bank Liabilities Analysis'!G46-'Bank Liabilities Analysis'!H46 -> 160721 | F47: =+'Bank Liabilities Analysis'!I46-'Bank Liabilities Analysis'!J46 -> 782896 | G47: =+'Bank Liabilities Analysis'!K46-'Bank Liabilities Analysis'!L46 -> 2877166 | H47: =+'Bank Liabilities Analysis'!M46-'Bank Liabilities Analysis'!N46 -> 375762 | I47: =+'Bank Liabilities Analysis'!O46-'Bank Liabilities Analysis'!P46 -> 751524 | J47: =+'Bank Liabilities Analysis'!Q46-'Bank Liabilities Analysis'!R46 -> 1862218 | K47: =+C47+D47+E47+F47+G47+H47+I47+J47 -> 8148415
B48: Депозит маблағлар | C48: =+'Bank Liabilities Analysis'!C47-'Bank Liabilities Analysis'!D47 -> 0 | D48: =+'Bank Liabilities Analysis'!E47-'Bank Liabilities Analysis'!F47 -> 0 | E48: =+'Bank Liabilities Analysis'!G47-'Bank Liabilities Analysis'!H47 -> 0 | F48: =+'Bank Liabilities Analysis'!I47-'Bank Liabilities Analysis'!J47 -> 0 | G48: =+'Bank Liabilities Analysis'!K47-'Bank Liabilities Analysis'!L47 -> 0 | H48: =+'Bank Liabilities Analysis'!M47-'Bank Liabilities Analysis'!N47 -> 0 | I48: =+'Bank Liabilities Analysis'!O47-'Bank Liabilities Analysis'!P47 -> 0 | J48: =+'Bank Liabilities Analysis'!Q47-'Bank Liabilities Analysis'!R47 -> 0 | K48: =+C48+D48+E48+F48+G48+H48+I48+J48 -> 0
B49: Ўзбекистон тикланиш ва тараққиёт фонди (ФРРУ), шундан | C49: =+C50+C51 -> 0 | D49: =+D50+D51 -> 0 | E49: =+E50+E51 -> 0 | F49: =+F50+F51 -> 16802121 | G49: =+G50+G51 -> 52776825 | H49: =+H50+H51 -> 75384503 | I49: =+I50+I51 -> 147039112 | J49: =+J50+J51 -> 492436713 | K49: =+C49+D49+E49+F49+G49+H49+I49+J49 -> 784439274
B50: Кредит ва лизинглар | C50: =+'Bank Liabilities Analysis'!C49-'Bank Liabilities Analysis'!D49 -> 0 | D50: =+'Bank Liabilities Analysis'!E49-'Bank Liabilities Analysis'!F49 -> 0 | E50: =+'Bank Liabilities Analysis'!G49-'Bank Liabilities Analysis'!H49 -> 0 | F50: =+'Bank Liabilities Analysis'!I49-'Bank Liabilities Analysis'!J49 -> 16802121 | G50: =+'Bank Liabilities Analysis'!K49-'Bank Liabilities Analysis'!L49 -> 52776825 | H50: =+'Bank Liabilities Analysis'!M49-'Bank Liabilities Analysis'!N49 -> 75384503 | I50: =+'Bank Liabilities Analysis'!O49-'Bank Liabilities Analysis'!P49 -> 147039112 | J50: =+'Bank Liabilities Analysis'!Q49-'Bank Liabilities Analysis'!R49 -> 492436713 | K50: =+C50+D50+E50+F50+G50+H50+I50+J50 -> 784439274
B51: Депозит маблағлар | C51: =+'Bank Liabilities Analysis'!C50-'Bank Liabilities Analysis'!D50 -> 0 | D51: =+'Bank Liabilities Analysis'!E50-'Bank Liabilities Analysis'!F50 -> 0 | E51: =+'Bank Liabilities Analysis'!G50-'Bank Liabilities Analysis'!H50 -> 0 | F51: =+'Bank Liabilities Analysis'!I50-'Bank Liabilities Analysis'!J50 -> 0 | G51: =+'Bank Liabilities Analysis'!K50-'Bank Liabilities Analysis'!L50 -> 0 | H51: =+'Bank Liabilities Analysis'!M50-'Bank Liabilities Analysis'!N50 -> 0 | I51: =+'Bank Liabilities Analysis'!O50-'Bank Liabilities Analysis'!P50 -> 0 | J51: =+'Bank Liabilities Analysis'!Q50-'Bank Liabilities Analysis'!R50 -> 0 | K51: =+C51+D51+E51+F51+G51+H51+I51+J51 -> 0
B52: Хорижий банклар, шундан | C52: =+C53+C54 -> 0 | D52: =+D53+D54 -> 0 | E52: =+E53+E54 -> 0 | F52: =+F53+F54 -> 0 | G52: =+G53+G54 -> 15482357 | H52: =+H53+H54 -> 76431407 | I52: =+I53+I54 -> 137380457 | J52: =+J53+J54 -> 0 | K52: =+C52+D52+E52+F52+G52+H52+I52+J52 -> 229294221
B53: Кредит ва лизинглар | C53: =+'Bank Liabilities Analysis'!C52-'Bank Liabilities Analysis'!D52 -> 0 | D53: =+'Bank Liabilities Analysis'!E52-'Bank Liabilities Analysis'!F52 -> 0 | E53: =+'Bank Liabilities Analysis'!G52-'Bank Liabilities Analysis'!H52 -> 0 | F53: =+'Bank Liabilities Analysis'!I52-'Bank Liabilities Analysis'!J52 -> 0 | G53: =+'Bank Liabilities Analysis'!K52-'Bank Liabilities Analysis'!L52 -> 15482357 | H53: =+'Bank Liabilities Analysis'!M52-'Bank Liabilities Analysis'!N52 -> 76431407 | I53: =+'Bank Liabilities Analysis'!O52-'Bank Liabilities Analysis'!P52 -> 137380457 | J53: =+'Bank Liabilities Analysis'!Q52-'Bank Liabilities Analysis'!R52 -> 0 | K53: =+C53+D53+E53+F53+G53+H53+I53+J53 -> 229294221
B54: Депозит маблағлар | C54: =+'Bank Liabilities Analysis'!C53-'Bank Liabilities Analysis'!D53 -> 0 | D54: =+'Bank Liabilities Analysis'!E53-'Bank Liabilities Analysis'!F53 -> 0 | E54: =+'Bank Liabilities Analysis'!G53-'Bank Liabilities Analysis'!H53 -> 0 | F54: =+'Bank Liabilities Analysis'!I53-'Bank Liabilities Analysis'!J53 -> 0 | G54: =+'Bank Liabilities Analysis'!K53-'Bank Liabilities Analysis'!L53 -> 0 | H54: =+'Bank Liabilities Analysis'!M53-'Bank Liabilities Analysis'!N53 -> 0 | I54: =+'Bank Liabilities Analysis'!O53-'Bank Liabilities Analysis'!P53 -> 0 | J54: =+'Bank Liabilities Analysis'!Q53-'Bank Liabilities Analysis'!R53 -> 0 | K54: =+C54+D54+E54+F54+G54+H54+I54+J54 -> 0
B55: Бошқа халқаро молия ташкилотлари маблағлари, шундан, | C55: =+C56+C57 -> 0 | D55: =+D56+D57 -> 0 | E55: =+E56+E57 -> 0 | F55: =+F56+F57 -> 132764 | G55: =+G56+G57 -> 627283664 | H55: =+H56+H57 -> 136856994 | I55: =+I56+I57 -> 690342306 | J55: =+J56+J57 -> 627863561 | K55: =+C55+D55+E55+F55+G55+H55+I55+J55 -> 2082479289
B56: Кредит ва лизинглар | C56: =+'Bank Liabilities Analysis'!C55-'Bank Liabilities Analysis'!D55 -> 0 | D56: =+'Bank Liabilities Analysis'!E55-'Bank Liabilities Analysis'!F55 -> 0 | E56: =+'Bank Liabilities Analysis'!G55-'Bank Liabilities Analysis'!H55 -> 0 | F56: =+'Bank Liabilities Analysis'!I55-'Bank Liabilities Analysis'!J55 -> 132764 | G56: =+'Bank Liabilities Analysis'!K55-'Bank Liabilities Analysis'!L55 -> 627283664 | H56: =+'Bank Liabilities Analysis'!M55-'Bank Liabilities Analysis'!N55 -> 136856994 | I56: =+'Bank Liabilities Analysis'!O55-'Bank Liabilities Analysis'!P55 -> 690342306 | J56: =+'Bank Liabilities Analysis'!Q55-'Bank Liabilities Analysis'!R55 -> 627863561 | K56: =+C56+D56+E56+F56+G56+H56+I56+J56 -> 2082479289
B57: Депозит маблағлар | C57: =+'Bank Liabilities Analysis'!C56-'Bank Liabilities Analysis'!D56 -> 0 | D57: =+'Bank Liabilities Analysis'!E56-'Bank Liabilities Analysis'!F56 -> 0 | E57: =+'Bank Liabilities Analysis'!G56-'Bank Liabilities Analysis'!H56 -> 0 | F57: =+'Bank Liabilities Analysis'!I56-'Bank Liabilities Analysis'!J56 -> 0 | G57: =+'Bank Liabilities Analysis'!K56-'Bank Liabilities Analysis'!L56 -> 0 | H57: =+'Bank Liabilities Analysis'!M56-'Bank Liabilities Analysis'!N56 -> 0 | I57: =+'Bank Liabilities Analysis'!O56-'Bank Liabilities Analysis'!P56 -> 0 | J57: =+'Bank Liabilities Analysis'!Q56-'Bank Liabilities Analysis'!R56 -> 0 | K57: =+C57+D57+E57+F57+G57+H57+I57+J57 -> 0
B59: Бошқарув Раис имзоси:
B61: Бош бухгалтер имзоси:

Sheet Commitments
A1: БАЛАНСДАН ТАШҚАРИ ҲИСОБВАРАҚЛАР ТЎҒРИСИДА ҲИСОБОТ | E1: 19-жадвал
B2: =Balance!B3 -> "Ўзсаноатқурилишбанк" АТБ | C2: =+Balance!D3 -> 45289 | E2: =+Balance!E3 -> минг сўмда
A3: № | B3: Кўрсаткичлар | C3: Жами | D3: миллий валютада | E3: хорижий валютада (сўм экв.)
A4: 1. | B4: Банкнинг кредит ва лизинг бериш бўйича мажбуриятлари | C4: =+D4+E4 -> 869143191 | D4: 531367973 | E4: 337775218 | F4: =+'Bank Assets Analysis'!S46 -> 869143191 | G4: =+'Bank Assets Analysis'!T46 -> 531367973 | H4: =+'Bank Assets Analysis'!U46 -> 337775218
A5: 1.1. | B5: шу жумладан, кредит линиялар маблағлари ҳисобидан (махсус шартлар билан) | C5: =+D5+E5 -> 0 | F5: =+'Bank Assets Analysis'!S47 -> 0 | G5: =+'Bank Assets Analysis'!T47 -> 0 | H5: =+'Bank Assets Analysis'!U47 -> 0
A7: 2. | B7: Кафолат ва кафилликлар | C7: =+D7+E7 -> 1457703020 | D7: 9363563 | E7: 1448339457 | F7: =+'Bank Assets Analysis'!S48 -> 1457703020 | G7: =+'Bank Assets Analysis'!T48 -> 9363563 | H7: =+'Bank Assets Analysis'!U48 -> 1448339457
A8: 2.1. | B8: шу жумладан депозитлар билан таъминланган | C8: =+D8+E8 -> 186342806 | D8: 363563 | E8: 185979243 | F8: =+'Bank Assets Analysis'!S49 -> 186342806 | G8: =+'Bank Assets Analysis'!T49 -> 363563 | H8: =+'Bank Assets Analysis'!U49 -> 185979243
A10: 3. | B10: Жами аккредитивлар | C10: =+D10+E10 -> 2030004069 | D10: =SUM(D11:D14) -> 0 | E10: =SUM(E11:E14) -> 2030004069
A11: 3.1. | B11: Тўловчи томонидан банкда очилган қопланган аккредитив | C11: =+D11+E11 -> 1166486266 | D11: 0 | E11: 1166486266
A12: 3.2. | B12: Тақдим этувчига тратталарни тўлаган ҳолдаги импорт билан боғлиқ тўланмаган аккредитивлар | C12: =+D12+E12 -> 863517803 | D12: 0 | E12: 863517803
A13: 3.3. | B13: Муддатли тратталарга қарши қўйилган, импорт билан боғлиқ тўланмаган аккредитивлар | C13: =+D13+E13 -> 0 | D13: 0 | E13: 0
A14: 3.4. | B14: Бошқа аккредитивлар | C14: =+D14+E14 -> 0 | D14: 0 | E14: 0
A16: 4. | B16: Факторинг, инкассо ва савдони молиялаштириш | C16: =+D16+E16 -> 1120734837 | D16: 1120734837 | E16: 0
A18: 5. | B18: Жами бошқа барча балансдан ташқари ҳисобварақлар | C18: =+D18+E18 -> 6499741397 | D18: =SUM(D19:D24) -> 1443536137 | E18: =SUM(E19:E24) -> 5056205260
A19: 5.1. | B19: Чет эл валюталари билан спот операциялари | C19: =+D19+E19 -> 246775400 | D19: 0 | E19: 246775400
A20: 5.2. | B20: Фоиз свопларининг шартли қиймати | C20: =+D20+E20 -> 0 | D20: 0 | E20: 0
A21: 5.3. | B21: Aйирбошлаш свопининг шартли қиймати (Валюта свопи) | C21: =+D21+E21 -> 36770760 | D21: 18262605 | E21: 18508155
A22: 5.4. | B22: Фьючерс, форвард ва опцион шартномалари | C22: =+D22+E22 -> 0 | D22: 0 | E22: 0
A23: 5.5. | B23: Кредитлар, қимматли қоғозлар ва бошқа активларни сотиб олиш бўйича мажбуриятлар | C23: =+D23+E23 -> 1070685717 | D23: 1070685717 | E23: 0
A24: 5.6. | B24: Бошқа балансдан ташқари ҳисобварақлар | C24: =+D24+E24 -> 5145509520 | D24: 354587815 | E24: 4790921705
A26: 6. | B26: Жами балансдан ташқари ҳисобварақлар | C26: =+C4+C7+C10+C16+C18 -> 11977326514 | D26: =+D4+D7+D10+D16+D18 -> 3105002510 | E26: =+E4+E7+E10+E16+E18 -> 8872324004
B28: Бошқарув Раис имзоси:
B30: Бош бухгалтер имзоси:

Sheet Deposits by Client
A1: МИЖОЗЛАР ТУРЛАРИГА КЎРА ДЕПОЗИТЛАР | D1: 14-жадвал
B2: =+Balance!B3 -> "Ўзсаноатқурилишбанк" АТБ | C2: =+Balance!D3 -> 45289 | D2: минг сўмда
A3: № | B3: Кўрсаткичлар | C3: Жами | D3: шундан, хорижий валютада (сўм экв.)
A4: 1. | B4: Талаб қилиб олингунча сақланадиган ва бошқа депозитлар
A5: а. | B5: Ҳукумат | C5: 66234614 | D5: 443486
A6: б. | B6: Жисмоний шахслар | C6: 1473345241 | D6: 287252364
A7: в. | B7: Давлат корхоналари | C7: 576393658 | D7: 324415661
A8: г. | B8: Чет эл капитали иштирокидаги корхоналар | C8: 439793150 | D8: 148181145
A9: д. | B9: Хусусий корхоналар | C9: 1307280161 | D9: 195277801
A10: е. | B10: Бошқа талаб қилиб олингунча депозитлар | C10: 1962456702 | D10: 1314990606
A11: ж. | B11: Жами талаб қилиб олингунча сақланадиган ва бошқа депозитлар | C11: =SUM(C5:C10) -> 5825503526 | D11: =SUM(D5:D10) -> 2270561063 | E11: =+'Bank Liabilities Analysis'!S15+'Bank Liabilities Analysis'!S7 -> 5825503526 | F11: =+'Bank Liabilities Analysis'!T15+'Bank Liabilities Analysis'!T7 -> 3554942463 | G11: =+'Bank Liabilities Analysis'!U15+'Bank Liabilities Analysis'!U7 -> 2270561063
A13: 2. | B13: Муддатли депозитлар | E13: =+C11-E11 -> 0 | G13: =+D11-G11 -> 0
A14: а. | B14: Ҳукумат | C14: 3856711941 | D14: 1770632191
A15: б. | B15: Жисмоний шахслар | C15: 2966772276 | D15: 256080509
A16: в. | B16: Давлат корхоналари | C16: 503649426 | D16: 186162426
A17: г. | B17: Чет эл капитали иштирокидаги корхоналар | C17: 441242989 | D17: 335242988
A18: д. | B18: Хусусий корхоналар | C18: 198575990 | D18: 70330989
A19: е. | B19: Бошқа муддатли депозитлар | C19: 6135000 | D19: 0
A20: ж. | B20: Жами муддатли депозитлар | C20: =SUM(C14:C19) -> 7973087622 | D20: =SUM(D14:D19) -> 2618449103 | E20: =+'Bank Liabilities Analysis'!S12 -> 7973087622 | F20: =+'Bank Liabilities Analysis'!T12 -> 5354638519 | G20: =+'Bank Liabilities Analysis'!U12 -> 2618449103
E21: =+C20-E20 -> 0 | G21: =+D20-G20 -> 0
A22: 3. | B22: Жами депозитлар | C22: =+C11+C20 -> 13798591148 | D22: =+D11+D20 -> 4889010166 | E22: =+'Bank Liabilities Analysis'!S20 -> 13798591148 | F22: =+'Bank Liabilities Analysis'!T20 -> 8909580982 | G22: =+'Bank Liabilities Analysis'!U20 -> 4889010166
E23: =+C22-E22 -> 0 | G23: =+D22-G22 -> 0
B24: Бошқарув Раис имзоси:
B26: Бош бухгалтер имзоси:

Sheet Investment Securities
A1: ҚИММАТЛИ ҚОҒОЗЛАР ВА УЛАРГА ҚИЛИНГАН ИНВЕСТИЦИЯЛАР ТЎҒРИСИДА ҲИСОБОТ | E1: 15-жадвал
A2: =Balance!B3 -> "Ўзсаноатқурилишбанк" АТБ | C2: =+Balance!D3 -> 45289 | E2: =+Balance!E3 -> минг сўмда
A3: Қисм 1 – Қарам хўжалик жамиятларига қилинган ҳамда амортизацияланган қиймати бўйича баҳоланадиган қарз қимматли қоғозларига қилинган инвестициялар | B3: Баланс қиймати | C3: шундан, | E3: Бозор қиймати
C4: миллий валютада | D4: хорижий валютада (сўм экв.)
A5: 1. Давлат қимматли қоғозлари | B5: =+C5+D5 -> 0 | C5: 0 | D5: 0 | E5: 0
A6: 2. Марказий банкнинг облигация ва бошқа қарз қимматли қоғозлари | B6: =+C6+D6 -> 0 | C6: 0 | D6: 0 | E6: 0
A7: 3. Корхоналарнинг қарз қимматли қоғозлари | B7: =+C7+D7 -> 0 | C7: 0 | D7: 0 | E7: 0
A8: 4. Еврооблигациялар | B8: =+C8+D8 -> 0 | C8: 0 | D8: 0 | E8: 0
A9: 5. Давлат улушига эга корхоналар акцияларига инвестициялар | B9: =+C9+D9 -> 19348501 | C9: 19348501 | D9: 0 | E9: 19348501
A10: 6. Хусусий корхоналар акцияларига инвестициялар | B10: =+C10+D10 -> 390839042 | C10: 387674444 | D10: 3164598 | E10: 390839042
A11: 7. Бошқа қимматли қоғозларга инвестициялар | B11: =+C11+D11 -> 3205644 | C11: 3205644 | D11: 0 | E11: 3205644
A12: 8. Жами инвестициялар | B12: =+C12+D12 -> 413393187 | C12: =SUM(C5:C11) -> 410228589 | D12: =SUM(D5:D11) -> 3164598 | E12: =SUM(E5:E11) -> 413393187
A13: 9. Инвестициялар бўйича харажатлар, дисконт ва мукофот | B13: =+C13+D13 -> 0 | C13: 0 | D13: 0 | E13: 0
A14: 10. Минус: Эҳтимолий йўқотишларга қарши захиралар | B14: =+C14+D14 -> 6955640 | C14: 6955640 | D14: 0
A15: 11. Инвестицияларнинг соф баланс қиймати | B15: =+C15+D15 -> 406437547 | C15: =C12+C13-C14 -> 403272949 | D15: =D12+D13-D14 -> 3164598
A17: Қисм – 2. Қимматли қоғозлар ва уларга қилинган инвестициялар | B17: Баланс қиймати | C17: шундан, | E17: Бозор қиймати
C18: миллий валютада | D18: хорижий валютада (сўм экв.)
A19: 1. Давлат хазина векселлари | B19: =+C19+D19 -> 0 | C19: 0 | D19: 0 | E19: =+C19 -> 0
A20: 2. Давлат облигациялари | B20: =+C20+D20 -> 2046792700 | C20: 1923405000 | D20: 123387700 | E20: 2046792700
A21: 3. Марказий банкнинг облигациялари ва бошқа қарз қимматли қоғозлари | B21: =+C21+D21 -> 0 | C21: 0 | D21: 0 | E21: =+C21 -> 0
A22: 4. Давлат улушига эга корхоналар қимматли қоғозлари | B22: =+C22+D22 -> 10000000 | C22: 10000000 | D22: 0 | E22: 10000000
A23: 5. Еврооблигациялар | B23: =+C23+D23 -> 0 | C23: 0 | D23: 0 | E23: =+C23 -> 0
A24: 6. Корхоналар қимматли қоғозлари | B24: =+C24+D24 -> 0 | C24: 0 | D24: 0 | E24: =+C24 -> 0
A25: 7. Бошқа қимматли қоғозлар | B25: =+C25+D25 -> 0 | C25: 0 | D25: 0 | E25: =+C25 -> 0
A26: 8. Жами қимматли қоғозлар ва уларга қилинган инвестициялар | B26: =+C26+D26 -> 2056792700 | C26: =SUM(C19:C25) -> 1933405000 | D26: =SUM(D19:D25) -> 123387700 | E26: =SUM(E19:E25) -> 2056792700
A27: 9. Қимматли қоғозлар бўйича харажатлар, дисконт, мукофот ва уларнинг ҳаққоний қийматининг ўзгариши | B27: =+C27+D27 -> -13486597 | C27: -12771091 | D27: -715506 | E27: -13486597
A28: 10. Минус: Эҳтимолий йўқотишларга қарши захиралар | B28: =+C28+D28 -> 0 | C28: 0 | D28: 0
A29: 11. Қимматли қоғозлар ва уларга қилинган инвестициялар, соф баланс қиймати | B29: =+C29+D29 -> 2043306103 | C29: =+C26+C27-C28 -> 1920633909 | D29: =+D26+D27-D28 -> 122672194
A31: Қисм – 3. Олди-сотдига мўлжалланган қимматбаҳо металлар, тошлар ва тангалар | B31: Баланс қиймати | C31: шундан, | E31: Бозор қиймати
C32: миллий валютада | D32: хорижий валютада (сўм экв.)
A34: 1. Қимматбаҳо металлар | B34: =+C34+D34 -> 0 | C34: 0 | D34: 0 | E34: 0
A35: 2. Қимматбаҳо тошлар | B35: =+C35+D35 -> 0 | C35: 0 | D35: 0 | E35: 0
A36: 3. Қимматбаҳо тангалар | B36: =+C36+D36 -> 875 | C36: 875 | D36: 0 | E36: 875
A37: 4. Қимматбаҳо металлар, тошлар ва тангалар жами | B37: =+C37+D37 -> 875 | C37: =SUM(C34:C36) -> 875 | D37: =SUM(D34:D36) -> 0 | E37: =SUM(E34:E36) -> 875
A38: 5. Минус: Эҳтимолий йўқотишларга қарши захиралар | B38: =+C38+D38 -> 0 | C38: 0 | D38: 0
A39: 6. Олди-сотдига мўлжалланган қимматбаҳо металлар, тошлар ва тангаларнинг соф баланс қиймати | B39: =+C39+D39 -> 875 | C39: =C37-C38 -> 875 | D39: =D37-D38 -> 0
A41: Бошқарув Раис имзоси:
A43: Бош бухгалтер имзоси:
