Workbook
Name jop: #REF!
Name kol: #REF!
Name RISKTOTASS: SUM('[6]Calculation of Risk Weighted As'!$C$38:$F$38)
Name RISKTOTASS: SUM('[7]Calculation of Risk Weighted As'!$C$41:$G$41)
Name TwentyLargestData: #REF!
Name Е: #REF!

Sheet Asset quality
A1: АКТИВЛАР ТАСНИФИ ВА УЛАР БЎЙИЧА ЯРАТИЛГАН ЭҲТИМОЛИЙ ЙЎҚОТИШЛАРНИ ҚОПЛАШ ЗАХИРАЛАРИ ТЎҒРИСИДА ҲИСОБОТ | S1: 2-жадвал | V1: №1
B3: "Ўзсаноатқурилишибанк" АТБ | Q3: 45289 | T3: минг. сўмда
A4: № | B4: Активлар таркиби* | C4: Қолдиқ | D4: Сифат тоифаси | I4: Муддати ўтган қарздорлик (брутто) | O4: Зарарларни қоплаш захираси
I5: Жами | J5: 30 кунгача | K5: 31дан 90 кунгача | L5: 91дан 180 кунгача | M5: 181 дан 365 кунгача | N5: 366 кун ва ундан ортиқ | O5: ҳақиқатдан яратилган захиралар
O6: Жами | P6: сифат тоифаси бўйича
D7: I | E7: II | F7: III | G7: IV | H7: V | P7: I | Q7: II | R7: III | S7: IV | T7: V
A8: А | B8: Б | C8: В | D8: Г | E8: Д | F8: Е | G8: Ж | H8: З | I8: И | J8: К | K8: Л | L8: М | M8: Н | N8: О | O8: П | P8: Р | Q8: С | R8: Т | S8: У | T8: Ф
B9: Жами активлар | C9: =SUM(C10:C58)+C60-C59 -> 74634423198 | D9: =SUM(D10:D58)-D59+D60 -> 67214176078 | E9: =SUM(E10:E58)-E59+E60 -> 7113099068 | F9: =SUM(F10:F58)-F59+F60 -> 597604434 | G9: =SUM(G10:G58)-G59+G60 -> 922834968 | H9: =SUM(H10:H58)-H59+H60 -> 397013815 | I9: =SUM(I10:I60) -> 1409911974 | J9: =SUM(J10:J60) -> 581272080 | K9: =SUM(K10:K60) -> 370487760 | L9: =SUM(L10:L60) -> 163070980 | M9: =SUM(M10:M60) -> 275815334 | N9: =SUM(N10:N60) -> 19265820 | O9: =SUM(O10:O60) -> 2225477374 | P9: =SUM(P10:P60) -> 615172209 | ... T9: =SUM(T10:T60) -> 304276405
A10: 1 | B10: Кассадаги нақд пул ва бошқа тўлов ҳужжатлари | C10: =SUM(D10:H10)-O10+P10 -> 1565389581 | D10: 1565389581 | E10: 0 | F10: 0 | G10: 0 | H10: 0 | I10: =SUM(J10:N10) -> 0 | O10: =SUM(P10:T10) -> 0 | P10: 0 | Q10: 0 | R10: 0 | S10: 0 | T10: 0 | U10: 10100
A11: 2 | B11: Банкнинг Марказий банкдаги маблағлар | C11: =SUM(D11:H11)-O11+P11 -> 2526034447 | D11: 2526034447 | E11: 0 | F11: 0 | G11: 0 | H11: 0 | I11: =SUM(J11:N11) -> 0 | O11: =SUM(P11:T11) -> 0 | P11: 0 | Q11: 0 | R11: 0 | S11: 0 | T11: 0 | U11: 10300
A12: 3 | B12: Бошқа банклар ва молиявий ташкилотлардан олиниши лозим бўлган маблағлар | C12: =SUM(D12:H12)-O12+P12 -> 5562959410 | D12: 5562959410 | E12: 0 | F12: 0 | G12: 0 | H12: 37257367 | I12: =SUM(J12:N12) -> 0 | O12: =SUM(P12:T12) -> 92886961 | P12: 55629594 | Q12: 0 | R12: 0 | S12: 0 | T12: 37257367 | U12: 10500
A13: 4 | B13: Фойда ёки зарар орқали ҳаққоний қийматда баҳоланадиган қимматли қоғозлар | C13: =SUM(D13:H13)-O13+P13 -> 2033306103 | D13: 2033306103 | E13: 0 | F13: 0 | G13: 0 | H13: 0 | I13: =SUM(J13:N13) -> 0 | O13: =SUM(P13:T13) -> 0 | P13: 0 | Q13: 0 | R13: 0 | S13: 0 | T13: 0 | U13: 10700
A14: 5 | B14: Бошқа умумлашган даромад орқали ҳаққоний қийматда баҳоланадиган қимматли қоғозларга қилинган инвестициялар | C14: =SUM(D14:H14)-O14+P14 -> 10000000 | D14: 10000000 | E14: 0 | F14: 0 | G14: 0 | H14: 0 | I14: =SUM(J14:N14) -> 0 | O14: =SUM(P14:T14) -> 0 | P14: 0 | Q14: 0 | R14: 0 | S14: 0 | T14: 0 | U14: 10800
A15: 6 | B15: Олди-сотдига мўлжалланган қимматбаҳо металлар, тошлар ва тангалар | C15: =SUM(D15:H15)-O15+P15 -> 875 | D15: 875 | E15: 0 | F15: 0 | G15: 0 | H15: 0 | I15: =SUM(J15:N15) -> 0 | O15: =SUM(P15:T15) -> 9 | P15: 9 | Q15: 0 | R15: 0 | S15: 0 | T15: 0 | U15: 10900
A16: 7 | B16: Сотиб олинган дебиторлик қарзлари — Факторинг | C16: =SUM(D16:H16)-O16+P16 -> 98000001 | D16: 98000001 | E16: 0 | F16: 0 | G16: 0 | H16: 0 | I16: =SUM(J16:N16) -> 0 | O16: =SUM(P16:T16) -> 980000 | P16: 980000 | Q16: 0 | R16: 0 | S16: 0 | T16: 0 | U16: 11100
A17: 8 | B17: Мижозларнинг аккредитив ва/ёки траст ҳужжатлари билан кафолатланган тратталари бўйича мажбуриятлари | C17: =SUM(D17:H17)-O17+P17 -> 81572337 | D17: 0 | E17: 0 | F17: 0 | G17: 0 | H17: 110235813 | I17: =SUM(J17:N17) -> 0 | O17: =SUM(P17:T17) -> 28663476 | P17: 0 | Q17: 0 | R17: 0 | S17: 0 | T17: 28663476 | U17: 11500
A18: 9 | B18: Банкнинг тўланмаган акцептлари бўйича мижозларнинг мажбуриятлари | C18: =SUM(D18:H18)-O18+P18 -> 0 | D18: 0 | E18: 0 | F18: 0 | G18: 0 | H18: 0 | I18: =SUM(J18:N18) -> 0 | O18: =SUM(P18:T18) -> 0 | P18: 0 | Q18: 0 | R18: 0 | S18: 0 | T18: 0 | U18: 11700
A19: 10 | B19: РЕПО битимлари бўйича сотиб олинган қимматли қоғозлар | C19: =SUM(D19:H19)-O19+P19 -> 0 | D19: 0 | E19: 0 | F19: 0 | G19: 0 | H19: 0 | I19: =SUM(J19:N19) -> 0 | O19: =SUM(P19:T19) -> 0 | P19: 0 | Q19: 0 | R19: 0 | S19: 0 | T19: 0 | U19: 11800
A20: 11 | B20: Марказий банкка берилган қисқа муддатли кредитлар | C20: =SUM(D20:H20)-O20+P20 -> 0 | D20: 0 | E20: 0 | F20: 0 | G20: 0 | H20: 0 | I20: =SUM(J20:N20) -> 0 | O20: =SUM(P20:T20) -> 0 | P20: 0 | Q20: 0 | R20: 0 | S20: 0 | T20: 0 | U20: 11900
A21: 12 | B21: Бошқа банкларга берилган қисқа муддатли кредитлар | C21: =SUM(D21:H21)-O21+P21 -> 0 | D21: 0 | E21: 0 | F21: 0 | G21: 0 | H21: 0 | I21: =SUM(J21:N21) -> 0 | O21: =SUM(P21:T21) -> 0 | P21: 0 | Q21: 0 | R21: 0 | S21: 0 | T21: 0 | U21: 12100
A22: 13 | B22: Ҳукуматга берилган қисқа муддатли кредитлар | C22: =SUM(D22:H22)-O22+P22 -> 0 | D22: 0 | E22: 0 | F22: 0 | G22: 0 | H22: 0 | I22: =SUM(J22:N22) -> 0 | O22: =SUM(P22:T22) -> 0 | P22: 0 | Q22: 0 | R22: 0 | S22: 0 | T22: 0 | U22: 12300
A23: 14 | B23: Бюджет ташкилотларига берилган қисқа муддатли кредитлар | C23: =SUM(D23:H23)-O23+P23 -> 0 | D23: 0 | E23: 0 | F23: 0 | G23: 0 | H23: 0 | I23: =SUM(J23:N23) -> 0 | O23: =SUM(P23:T23) -> 0 | P23: 0 | Q23: 0 | R23: 0 | S23: 0 | T23: 0 | U23: 12400
A24: 15 | B24: Жисмоний шахсларга берилган қисқа муддатли кредитлар | C24: =SUM(D24:H24)-O24+P24 -> 148925943 | D24: 147739621 | E24: 948395 | F24: 311797 | G24: 197836 | H24: 0 | I24: =SUM(J24:N24) -> 976239 | J24: 326455 | K24: 328035 | L24: 235604 | M24: 86145 | N24: 0 | O24: =SUM(P24:T24) -> 1749102 | P24: 1477396 | Q24: 94839 | R24: 77949 | S24: 98918 | T24: 0 | U24: 12500
A25: 16 | B25: Якка тартибдаги тадбиркорларга берилган қисқа муддатли кредитлар | C25: =SUM(D25:H25)-O25+P25 -> 20304028 | D25: 16905572 | E25: 1640587 | F25: 1094056 | G25: 2354312 | H25: 0 | I25: =SUM(J25:N25) -> 4796166 | J25: 653717 | K25: 999727 | L25: 788410 | M25: 2354312 | N25: 0 | O25: =SUM(P25:T25) -> 1859555 | P25: 169056 | Q25: 239828 | R25: 273514 | S25: 1177157 | T25: 0 | U25: 12600
A26: 17 | B26: Давлат корхоналари, ташкилотлари ва муассасаларига берилган қисқа муддатли кредитлар | C26: =SUM(D26:H26)-O26+P26 -> 3986468558 | D26: 3982421725 | E26: 4496481 | F26: 0 | G26: 0 | H26: 0 | I26: =SUM(J26:N26) -> 78885468 | J26: 78885468 | K26: 0 | L26: 0 | M26: 0 | N26: 0 | O26: =SUM(P26:T26) -> 40273865 | P26: 39824217 | Q26: 449648 | R26: 0 | S26: 0 | T26: 0 | U26: 12700
A27: 18 | B27: Тадбиркорлик фаолиятини қўллаб-қувватлаш давлат жамғармаси кўмагида берилган қисқа муддатли кредитлар | C27: =SUM(D27:H27)-O27+P27 -> 149038227 | D27: 137248835 | E27: 7526650 | F27: 0 | G27: 10030814 | H27: 0 | I27: =SUM(J27:N27) -> 10030814 | J27: 0 | K27: 0 | L27: 10030814 | M27: 0 | N27: 0 | O27: =SUM(P27:T27) -> 7140560 | P27: 1372488 | Q27: 3446107 | R27: 0 | S27: 1321965 | T27: 1000000 | U27: 12800
A28: 19 | B28: Чет эл капитали иштирокидаги корхоналарга берилган қисқа муддатли кредитлар | C28: =SUM(D28:H28)-O28+P28 -> 2217667706 | D28: 2213334426 | E28: 2603856 | F28: 810756 | G28: 2763487 | H28: 0 | I28: =SUM(J28:N28) -> 6384711 | J28: 1666667 | K28: 1399356 | L28: 555201 | M28: 2763487 | N28: 0 | O28: =SUM(P28:T28) -> 23978163 | P28: 22133344 | Q28: 260386 | R28: 202689 | S28: 1381744 | T28: 0 | U28: 12900
A29: 20 | B29: Нодавлат нотижорат ташкилотларига берилган қисқа муддатли кредитлар | C29: =SUM(D29:H29)-O29+P29 -> 13281 | D29: 13281 | E29: 0 | F29: 0 | G29: 0 | H29: 0 | I29: =SUM(J29:N29) -> 0 | J29: 0 | K29: 0 | L29: 0 | M29: 0 | N29: 0 | O29: =SUM(P29:T29) -> 133 | P29: 133 | Q29: 0 | R29: 0 | S29: 0 | T29: 0 | U29: 13000
A30: 21 | B30: Хусусий корхоналар, хўжалик ширкатлари ва жамиятларга берилган қисқа муддатли кредитлар | C30: =SUM(D30:H30)-O30+P30 -> 4935705825 | D30: 4619358133 | E30: 271591493 | F30: 48922451 | G30: 84946828 | H30: 350000 | I30: =SUM(J30:N30) -> 175785316 | J30: 23386912 | K30: 23683229 | L30: 43418347 | M30: 84946828 | N30: 350000 | O30: =SUM(P30:T30) -> 135656661 | P30: 46193581 | Q30: 30305809 | R30: 10835797 | S30: 47971474 | T30: 350000 | U30: 13100
A31: 22 | B31: Банк бўлмаган молиявий муассасаларга берилган қисқа муддатли кредитлар | C31: =SUM(D31:H31)-O31+P31 -> 118872 | D31: 118872 | E31: 0 | F31: 0 | G31: 0 | H31: 0 | I31: =SUM(J31:N31) -> 0 | J31: 0 | K31: 0 | L31: 0 | M31: 0 | N31: 0 | O31: =SUM(P31:T31) -> 1189 | P31: 1189 | Q31: 0 | R31: 0 | S31: 0 | T31: 0 | U31: 13200
A32: 23 | B32: Давлат эҳтиёжлари учун харид қилинадиган қишлоқ хўжалиги маҳсулотларини етиштириш учун берилган қисқа муддатли кредитлар | C32: =SUM(D32:H32)-O32+P32 -> 95979403 | D32: 95979403 | E32: 0 | F32: 0 | G32: 0 | H32: 0 | I32: =SUM(J32:N32) -> 0 | J32: 0 | K32: 0 | L32: 0 | M32: 0 | N32: 0 | O32: =SUM(P32:T32) -> 959794 | P32: 959794 | Q32: 0 | R32: 0 | S32: 0 | T32: 0 | U32: 13300
A33: 24 | B33: Давлат эҳтиёжлари учун харид қилинадиган қишлоқ хўжалиги маҳсулотларини етиштириш учун берилган узоқ муддатли кредитлар | C33: =SUM(D33:H33)-O33+P33 -> 1649230335 | D33: 775268383 | E33: 857553659 | F33: 80406648 | G33: 0 | H33: 0 | I33: =SUM(J33:N33) -> 224002222 | J33: 37479137 | K33: 186523085 | L33: 0 | M33: 0 | N33: 0 | O33: =SUM(P33:T33) -> 71751039 | P33: 7752684 | Q33: 43896693 | R33: 20101662 | S33: 0 | T33: 0 | U33: 14300
A34: 25 | B34: Тадбиркорлик фаолиятини қўллаб-қувватлаш давлат жамғармаси кўмагида берилган узоқ муддатли кредитлар | C34: =SUM(D34:H34)-O34+P34 -> 2855036998 | D34: 2045555885 | E34: 572712398 | F34: 147830825 | G34: 344420946 | H34: 16339332 | I34: =SUM(J34:N34) -> 190499105 | J34: 23239708 | K34: 43385102 | L34: 23052318 | M34: 94176217 | N34: 6645760 | O34: =SUM(P34:T34) -> 292277947 | P34: 20455559 | Q34: 46314877 | R34: 36957706 | S34: 172210473 | T34: 16339332 | U34: 14400
A35: 26 | B35: Бошқа банкларга берилган узоқ муддатли кредитлар | C35: =SUM(D35:H35)-O35+P35 -> 0 | D35: 0 | E35: 0 | F35: 0 | G35: 0 | H35: 0 | I35: =SUM(J35:N35) -> 0 | J35: 0 | K35: 0 | L35: 0 | M35: 0 | N35: 0 | O35: =SUM(P35:T35) -> 0 | P35: 0 | Q35: 0 | R35: 0 | S35: 0 | T35: 0 | U35: 14500
... A44: 35 | B44: Хусусий корхоналар, хўжалик ширкатлари ва жамиятларга берилган узоқ муддатли кредитлар | C44: =SUM(D44:H44)-O44+P44 -> 15090322433 | D44: 12646944183 | E44: 2525588929 | F44: 187367280 | G44: 135482702 | H44: 10550000 | I44: =SUM(J44:N44) -> 157068960 | J44: 33790306 | K44: 31195159 | L44: 52427466 | M44: 33656029 | N44: 6000000 | O44: =SUM(P44:T44) -> 542080103 | P44: 126469442 | Q44: 283030583 | R44: 48236636 | S44: 65936734 | T44: 18406708 | U44: 15500
A45: 36 | B45: Лизинг (молиявий ижара) | C45: =SUM(D45:H45)-O45+P45 -> 401306653 | D45: 401306653 | E45: 0 | F45: 0 | G45: 0 | H45: 0 | I45: =SUM(J45:N45) -> 0 | O45: =SUM(P45:T45) -> 4013067 | P45: 4013067 | Q45: 0 | R45: 0 | S45: 0 | T45: 0 | U45: 15600
A46: 37 | B46: Суд ёки ижро иши юритиш жараёнидаги кредитлар ва лизинг | C46: =SUM(D46:H46)-O46+P46 -> 83375035 | D46: 0 | E46: 0 | F46: 12579961 | G46: 145307500 | H46: 0 | I46: =SUM(J46:N46) -> 0 | O46: =SUM(P46:T46) -> 74512426 | P46: 0 | Q46: 7570393 | R46: 3144991 | S46: 72653750 | T46: -8856708 | U46: 15700
A47: 38 | B47: Қарам хўжалик жамиятларига, биргаликдаги корхоналарга ва шўъба хўжалик жамиятларига қилинган инвестициялар | C47: =SUM(D47:H47)-O47+P47 -> 406437548 | D47: 402687552 | E47: 0 | F47: 0 | G47: 7499992 | H47: 3205644 | I47: =SUM(J47:N47) -> 0 | O47: =SUM(P47:T47) -> 10982516 | P47: 4026876 | Q47: 0 | R47: 0 | S47: 3749996 | T47: 3205644 | U47: 15800
A48: 39 | B48: Амортизацияланган қиймати бўйича баҳоланадиган қарз қимматли қоғозларга қилинган инвестициялар | C48: =SUM(D48:H48)-O48+P48 -> 0 | D48: 0 | E48: 0 | F48: 0 | G48: 0 | H48: 0 | I48: =SUM(J48:N48) -> 0 | O48: =SUM(P48:T48) -> 0 | P48: 0 | Q48: 0 | R48: 0 | S48: 0 | T48: 0 | U48: 15900
A49: 40 | B49: Олиниши лозим бўлган ҳисобланган фоизлар | C49: =SUM(D49:H49)-O49+P49 -> 2735021105 | D49: 1929213128 | E49: 779730245 | F49: 66596339 | G49: 123673175 | H49: 9008305 | I49: =SUM(J49:N49) -> 418757540 | J49: ='Aging Analysis'!M22 -> 287015394 | K49: ='Aging Analysis'!O22+'Aging Analysis'!Q22 -> 41476817 | L49: ='Aging Analysis'!S22 -> 28533994 | M49: ='Aging Analysis'!U22 -> 55461275 | N49: ='Aging Analysis'!W22+'Aging Analysis'!Y22 -> 6270060 | O49: =SUM(P49:T49) -> 192492218 | P49: 19292131 | Q49: 173200087 | R49: 0 | S49: 0 | T49: 0 | U49: 16300
A50: 41 | B50: Олиниши лозим бўлган ҳисобланган фоизсиз даромадлар | C50: =SUM(D50:H50)-O50+P50 -> 18910189 | D50: 15409969 | E50: 3455855 | F50: 212095 | G50: 1320059 | H50: 1204494 | I50: =SUM(J50:N50) -> 0 | O50: =SUM(P50:T50) -> 2846383 | P50: 154100 | Q50: 398299 | R50: 60764 | S50: 1028726 | T50: 1204494 | U50: 16400
A51: 42 | B51: Асосий воситалар | C51: =SUM(D51:H51)-O51+P51 -> 3099257205 | D51: 3099257205 | E51: 0 | F51: 0 | G51: 0 | H51: 0 | I51: =SUM(J51:N51) -> 0 | O51: =SUM(P51:T51) -> 0 | P51: 0 | Q51: 0 | R51: 0 | S51: 0 | T51: 0 | U51: 16500
A52: 43 | B52: Номоддий активлар | C52: =SUM(D52:H52)-O52+P52 -> 25973937 | D52: 25973937 | E52: 0 | F52: 0 | G52: 0 | H52: 0 | I52: =SUM(J52:N52) -> 0 | O52: =SUM(P52:T52) -> 0 | P52: 0 | Q52: 0 | R52: 0 | S52: 0 | T52: 0 | U52: 16600
A53: 44 | B53: Банкнинг бошқа хусусий мулклари | C53: =SUM(D53:H53)-O53+P53 -> 70914978 | D53: 67185189 | E53: 2492552 | F53: 175298 | G53: 2193814 | H53: 188155031 | I53: =SUM(J53:N53) -> 0 | O53: =SUM(P53:T53) -> 189958758 | P53: 671852 | Q53: 2137500 | R53: 0 | S53: 0 | T53: 187149406 | U53: 16700
A54: 45 | B54: Муддати узайтирилган дебитор қарздорлик | C54: =SUM(D54:H54)-O54+P54 -> 442418991 | D54: 354071871 | E54: 30933776 | F54: 20978855 | G54: 35283346 | H54: 19750000 | I54: =SUM(J54:N54) -> 0 | O54: =SUM(P54:T54) -> 22139576 | P54: 3540719 | Q54: 0 | R54: 0 | S54: 0 | T54: 18598857 | U54: 16800
A55: 46 | B55: Ҳосилавий инструментларнинг ревальвацияси натижасида ўзлаштирилмаган фойда | C55: =SUM(D55:H55)-O55+P55 -> 0 | D55: 0 | E55: 0 | F55: 0 | G55: 0 | H55: 0 | I55: =SUM(J55:N55) -> 0 | O55: =SUM(P55:T55) -> 0 | P55: 0 | Q55: 0 | R55: 0 | S55: 0 | T55: 0 | U55: 16900
A56: 47 | B56: Валюталар савдоси ва валюта позициялари | C56: =SUM(D56:H56)-O56+P56 -> 0 | D56: 0 | E56: 0 | F56: 0 | G56: 0 | H56: 0 | I56: =SUM(J56:N56) -> 0 | O56: =SUM(P56:T56) -> 0 | P56: 0 | Q56: 0 | R56: 0 | S56: 0 | T56: 0 | U56: 17100
A57: 48 | B57: Транзит ҳисобварақлари | C57: =SUM(D57:H57)-O57+P57 -> 0 | D57: 0 | E57: 0 | F57: 0 | G57: 0 | H57: 0 | I57: =SUM(J57:N57) -> 0 | O57: =SUM(P57:T57) -> 0 | P57: 0 | Q57: 0 | R57: 0 | S57: 0 | T57: 0 | U57: 17300
A58: 49 | B58: Мижозларнинг банк карталаридан ҳисобдан чиқарилиши лозим бўлган маблағлар бўйича транзит ҳисобварақлари | C58: =SUM(D58:H58)-O58+P58 -> 62878271 | D58: 62878271 | E58: 0 | F58: 0 | G58: 0 | H58: 0 | I58: =SUM(J58:N58) -> 0 | O58: =SUM(P58:T58) -> 628783 | P58: 628783 | Q58: 0 | R58: 0 | S58: 0 | T58: 0 | U58: 17400
A59: 50 | B59: Стандарт активлар бўйича яратилган захирлар | C59: =SUM(D59:H59)-O59 -> 615172207 | D59: 615172207 | E59: 0 | F59: 0 | G59: 0 | H59: 0 | I59: =SUM(J59:N59) -> 0 | O59: =SUM(P59:T59) -> 0 | P59: 0 | Q59: 0 | R59: 0 | S59: 0 | T59: 0 | U59: 17700
A60: 51 | B60: Бошқа активлар | C60: =SUM(D60:H60)-O60+P60 -> 632945083 | D60: 626229486 | E60: 4009918 | F60: 3637360 | G60: 2932472 | H60: 957829 | I60: =SUM(J60:N60) -> 0 | O60: =SUM(P60:T60) -> 31096154 | P60: 26274172 | Q60: 18670 | R60: 1226375 | S60: 2619108 | T60: 957829 | U60: 19900
B62: БАЛАНСДАН ТАШҚАРИ МОДДАЛАР | C62: =SUM(C63:C65) -> 4356850281 | D62: =SUM(D63:D65) -> 4079775059 | E62: =SUM(E63:E65) -> 71638495 | F62: =SUM(F63:F65) -> 382210 | G62: =SUM(G63:G65) -> 1280618 | H62: =SUM(H63:H65) -> 203773899 | I62: =SUM(J62:N62) -> 0 | J62: =SUM(J63:J65) -> 0 | K62: =SUM(K63:K65) -> 0 | L62: =SUM(L63:L65) -> 0 | M62: =SUM(M63:M65) -> 0 | N62: =SUM(N63:N65) -> 0 | O62: =SUM(O63:O65) -> 16308193 | P62: =SUM(P63:P65) -> 16095591 | Q62: =SUM(Q63:Q65) -> 212329 | ... T62: =SUM(T63:T65) -> 0
A63: 1 | B63: Аккредитивлар | C63: =SUM(D63:H63) -> 2030004069 | D63: 2023747655 | E63: 6256414 | F63: 0 | G63: 0 | H63: 0 | I63: =SUM(J63:N63) -> 0 | O63: =SUM(P63:T63) -> 1379064 | P63: 1379064 | Q63: 0 | R63: 0 | S63: 0 | T63: 0 | U63: 90908-90958
A64: 2 | B64: Кафолат ва кафилликлар | C64: =SUM(D64:H64) -> 1457703020 | D64: 1219331041 | E64: 34598080 | F64: 0 | G64: 0 | H64: 203773899 | I64: =SUM(J64:N64) -> 0 | O64: =SUM(P64:T64) -> 11626206 | P64: =10480615+1145591 -> 11626206 | Q64: 0 | R64: 0 | S64: 0 | T64: 0 | U64: 90993
A65: 3 | B65: Банкнинг кредит ва лизинг бериш бўйича мажбуриятлари | C65: =SUM(D65:H65) -> 869143192 | D65: 836696363 | E65: 30784001 | F65: 382210 | G65: 1280618 | H65: 0 | I65: =SUM(J65:N65) -> 0 | O65: =SUM(P65:T65) -> 3302923 | P65: 3090321 | Q65: 212329 | R65: 272 | S65: 1 | T65: 0 | U65: 91809
B67: Бошқарув Раис имзоси:
B69: Бош бухгалтер имзоси:
C73: =+[8]Balance!$C$47 -> 74634423198 | D73: =+'loans type'!N8 -> 49548751261 | E73: =+'loans type'!O8 -> 6292476722 | F73: =+'loans type'!P8 -> 506004487 | G73: =+'loans type'!Q8 -> 749932110 | H73: =+'loans type'!R8 -> 27239332 | P73: =+'loans type'!T8 -> 504953973 | Q73: =+'loans type'!U8 -> 620122045 | R73: =+'loans type'!V8 -> 126501133 | S73: =+'loans type'!W8 -> 374966057 | T73: =+'loans type'!X8 -> 27239332
D74: =+D16+D20+D21+D22+D23+D24+D25+D26+D27+D28+D29+D30+D31+D32+D33+D34+D35+D36+D37+D38+D39+D40+D41+D42+D43+D44+D45+D46 -> 49548751261 | E74: =+E16+E19+E20+E21+E22+E23+E24+E25+E26+E27+E28+E29+E30+E31+E32+E33+E34+E35+E36+E37+E38+E39+E40+E41+E42+E43+E44+E45+E46 -> 6292476722 | F74: =+F16+F19+F20+F21+F22+F23+F24+F25+F26+F27+F28+F29+F30+F31+F32+F33+F34+F35+F36+F37+F38+F39+F40+F41+F42+F43+F44+F45+F46 -> 506004487 | G74: =+G16+G19+G20+G21+G22+G23+G24+G25+G26+G27+G28+G29+G30+G31+G32+G33+G34+G35+G36+G37+G38+G39+G40+G41+G42+G43+G44+G45+G46 -> 749932110 | H74: =+H16+H19+H20+H21+H22+H23+H24+H25+H26+H27+H28+H29+H30+H31+H32+H33+H34+H35+H36+H37+H38+H39+H40+H41+H42+H43+H44+H45+H46 -> 27239332 | P74: =+P16+P19+P20+P21+P22+P23+P24+P25+P26+P27+P28+P29+P30+P31+P32+P33+P34+P35+P36+P37+P38+P39+P40+P41+P42+P43+P44+P45+P46 -> 504953973 | Q74: =+Q16+Q19+Q20+Q21+Q22+Q23+Q24+Q25+Q26+Q27+Q28+Q29+Q30+Q31+Q32+Q33+Q34+Q35+Q36+Q37+Q38+Q39+Q40+Q41+Q42+Q43+Q44+Q45+Q46 -> 620122045 | R74: =+R16+R19+R20+R21+R22+R23+R24+R25+R26+R27+R28+R29+R30+R31+R32+R33+R34+R35+R36+R37+R38+R39+R40+R41+R42+R43+R44+R45+R46 -> 126501133 | S74: =+S16+S19+S20+S21+S22+S23+S24+S25+S26+S27+S28+S29+S30+S31+S32+S33+S34+S35+S36+S37+S38+S39+S40+S41+S42+S43+S44+S45+S46 -> 374966057 | T74: =+T16+T19+T20+T21+T22+T23+T24+T25+T26+T27+T28+T29+T30+T31+T32+T33+T34+T35+T36+T37+T38+T39+T40+T41+T42+T43+T44+T45+T46 -> 27239332
D75: =+D73-D74 -> 0 | E75: =+E73-E74 -> 0 | F75: =+F73-F74 -> 0 | G75: =+G73-G74 -> 0 | H75: =+H73-H74 -> 0 | P75: =+P73-P74 -> 0 | Q75: =+Q73-Q74 -> 0 | R75: =+R73-R74 -> 0 | S75: =+S73-S74 -> 0 | T75: =+T73-T74 -> 0

Sheet Income 
A1: МОЛИЯВИЙ НАТИЖАЛАР ТЎҒРИСИДА ҲИСОБОТ | E1: 3-жадвал
B3: =+'Asset quality'!B3 -> "Ўзсаноатқурилишибанк" АТБ | D3: =+'Asset quality'!Q3 -> 45289 | E3: =+'Asset quality'!T3 -> минг. сўмда
A4: № | B4: Кўрсаткичлар | C4: Жами | D4: миллий валютада | E4: хорижий валютада (экв. сўмда)
A5: 1. | B5: ФОИЗЛИ ДАРОМАДЛАР
A6: a. | B6: Марказий банкдаги ҳисобварақлар бўйича фоизли даромадлар | C6: =+D6+E6 -> 13993151 | D6: 13993151 | E6: 0 | G6: =+'Analysis of Interest'!C17 -> 13993151
A7: б. | B7: Бошқа банклардаги ҳисобварақлар бўйича фоизли даромадлар | C7: =+D7+E7 -> 472306870 | D7: 55384248 | E7: 416922622 | G7: =+'Analysis of Interest'!C18 -> 472306870
A8: в. | B8: Амортизацияланган қиймати бўйича баҳоланадиган қарз қимматли қоғозларга қилинган инвестициялар бўйича фоизли даромадлар | C8: =+D8+E8 -> 626507 | D8: 626507 | E8: 0
A9: г. | B9: Қимматли қоғозлар ва уларга қилинган инвестициялар бўйича фоизли даромадлар | C9: =+D9+E9 -> 398059254 | D9: 387708461 | E9: 10350793 | G9: =+'Analysis of Interest'!C28 -> 398059254
A10: д. | B10: Мижозларнинг мажбуриятлари бўйича ҳисобланган фоизлар | C10: =+D10+E10 -> 0 | D10: 0 | E10: 0
A11: е. | B11: Банкнинг тўланмаган акцептлари юзасидан мижозлар мажбуриятлари бўйича фоизли даромадлар | C11: =+D11+E11 -> 0 | D11: 0 | E11: 0
A12: ж. | B12: Кредит ва лизинг операциялари бўйича фоизлар, дисконтлар (чегирмалар) ва бадаллар | C12: =+D12+E12 -> 6278755813 | D12: 3433027405 | E12: 2845728408 | G12: =+'Analysis of Interest'!C14 -> 6278755813
A13: з. | B13: Қимматли қоғозлар билан амалга оширилган РЕПО битимлари бўйича фоизли даромадлар | C13: =+D13+E13 -> 2784649 | D13: 2784649 | E13: 0 | G13: =+'Analysis of Interest'!C39 -> 2784649
A14: и. | B14: Бошқа фоизли даромадлар | C14: =+D14+E14 -> 13335904 | D14: 13335904 | E14: 0 | G14: =+'Analysis of Interest'!C40 -> 13335904
A15: к. | B15: Жами фоизли даромадлар | C15: =SUM(C6:C14) -> 7179862148 | D15: =SUM(D6:D14) -> 3906860325 | E15: =SUM(E6:E14) -> 3273001823 | G15: =+'Analysis of Interest'!C42 -> 7179862148
A17: 2. | B17: ФОИЗЛИ ХAРAЖAТЛAР
A18: а. | B18: Талаб қилиб олингунча сақланадиган депозитлар бўйича фоизли харажатлар | C18: =+D18+E18 -> 15186418 | D18: 12113448 | E18: 3072970 | G18: =+'Analysis of Interest'!C52 -> 15186418
A19: б. | B19: Муддатли депозитлар бўйича фоизли харажатлар | C19: =+D19+E19 -> 1125844088 | D19: 994421587 | E19: 131422501 | G19: =+'Analysis of Interest'!C61 -> 1125844088
A20: в. | B20: Марказий банкнинг ҳисобварақлари бўйича фоизли харажатлар | C20: =+D20+E20 -> 0 | D20: 0 | E20: 0
A21: г. | B21: Бошқа банкларнинг ҳисобварақлари бўйича фоизли харажатлар | C21: =+D21+E21 -> 562077232 | D21: 319166644 | E21: 242910588
A22: д. | B22: Жами депозитлар бўйича фоизли харажатлар | C22: =SUM(C18:C21) -> 1703107738 | D22: =SUM(D18:D21) -> 1325701679 | E22: =SUM(E18:E21) -> 377406059
A23: е. | B23: Кредитлар бўйича фоизли харажатлар | C23: =+D23+E23 -> 2153234424 | D23: 564507134 | E23: 1588727290 | G23: =+'Analysis of Interest'!C67 -> 2153234424
A24: ж. | B24: Қимматли қоғозлар билан амалга оширилган РЕПО битимлари бўйича фоизли харажатлар | C24: =+D24+E24 -> 24948798 | D24: 24948798 | E24: 0 | G24: =+'Analysis of Interest'!C68 -> 24948798
A25: з. | B25: Бошқа фоизли харажатлар | C25: =+D25+E25 -> 316609174 | D25: 35242946 | E25: 281366228
A26: и. | B26: Жами кредит ва бошқа қарздорликлар бўйича фоизли харажатлар | C26: =SUM(C23:C25) -> 2494792396 | D26: =SUM(D23:D25) -> 624698878 | E26: =SUM(E23:E25) -> 1870093518
A27: к. | B27: Жами фоизли харажатлар | C27: =C26+C22 -> 4197900134 | D27: =D26+D22 -> 1950400557 | E27: =E26+E22 -> 2247499577 | G27: =+'Analysis of Interest'!C72 -> 4197900134
A29: 3. | B29: Активлар бўйича эҳтимолий йўқотишларга қарши яратилган захираларни баҳолашдан олдинги соф даромад | C29: =C15-C27 -> 2981962014 | D29: =D15-D27 -> 1956459768 | E29: =E15-E27 -> 1025502246
A30: а. | B30: Минус: Кредит ва лизинглар бўйича кўрилиши мумкин бўлган зарарларни баҳолаш | C30: =+D30+E30 -> 1676463088 | D30: 683983511 | E30: 992479577
A31: б. | B31: Минус: Қимматли қоғозлар бўйича кўрилиши мумкин бўлган зарарларни баҳолаш | C31: =+D31+E31 -> 0 | D31: 0 | E31: 0
A32: в. | B32: Минус: Инвестициялар бўйича кўрилиши мумкин бўлган зарарларни баҳолаш | C32: =+D32+E32 -> 1874998 | D32: 1874998 | E32: 0
A33: г. | B33: Минус: Бошқа активлар бўйича кўрилиши мумкин бўлган зарарларни баҳолаш | C33: =+D33+E33 -> 593274940 | D33: 400638979 | E33: 192635961
A34: д. | B34: Активлар бўйича эҳтимолий зарарларни баҳолашдан кейинги соф даромад | C34: =C29-C30-C31-C32-C33 -> 710348988 | D34: =D29-D30-D31-D32-D33 -> 869962280 | E34: =E29-E30-E31-E32-E33 -> -159613292
A36: 4. | B36: ФОИЗСИЗ ДАРОМАДЛАР
A37: а. | B37: Кўрсатилган хизматлар ва воситачилик учун олинган даромадлар | C37: =+D37+E37 -> 531777445 | D37: 441030394 | E37: 90747051
A38: б. | B38: Хорижий валюталардаги фойда | C38: =+D38+E38 -> 2075380431 | D38: 267053605 | E38: 1808326826
A39: в. | B39: Тижорат операцияларидан олинган фойда | C39: =+D39+E39 -> 0 | D39: 0 | E39: 0
A40: г. | B40: Инвестициядан олинган фойда ва дивидендлар | C40: =+D40+E40 -> 22179591 | D40: 21922751 | E40: 256840
A41: д. | B41: Активлар бўйича эҳтимолий йўқотишларга қарши яратилган захираларни қайтарилиши | C41: =+D41+E41 -> 115507327 | D41: 102698261 | E41: 12809066
A42: е. | B42: Ҳисобдан чиқарилган кредитлар қайтарилиши билан боғлиқ даромадлар | C42: =+D42+E42 -> 932350041 | D42: 280356779 | E42: 651993262
A43: ж. | B43: Бошқа фоизсиз даромадлар | C43: =+D43+E43 -> 214544073 | D43: 190803609 | E43: 23740464
A44: е. | B44: Жами фоизсиз даромадлар | C44: =SUM(C37:C43) -> 3891738908 | D44: =SUM(D37:D43) -> 1303865399 | E44: =SUM(E37:E43) -> 2587873509
A46: 5. | B46: ФОИЗСИЗ ХАРАЖАТЛАР
A47: а. | B47: Воситачилик ва кўрсатилган хизматлар учун харажатлар | C47: =+D47+E47 -> 254386568 | D47: 166602752 | E47: 87783816
A48: б. | B48: Хорижий валютада кўрилган зарарлар | C48: =+D48+E48 -> 1643886335 | D48: 42897 | E48: 1643843438
A49: в. | B49: Тижорат операцияларидан кўрилган зарарлар | C49: =+D49+E49 -> 0 | D49: 0 | E49: 0
A50: г. | B50: Инвестициядан кўрилган зарарлар | C50: =+D50+E50 -> 0 | D50: 0 | E50: 0
A51: д. | B51: Бошқа фоизсиз харажатлар | C51: =+D51+E51 -> 5886951 | D51: 5075059 | E51: 811892
A52: е. | B52: Жами фоизсиз харажатлар | C52: =SUM(C47:C51) -> 1904159854 | D52: =SUM(D47:D51) -> 171720708 | E52: =SUM(E47:E51) -> 1732439146
A54: 6. | B54: ОПЕРАЦИОН ХАРАЖАТЛАРДАН ОЛДИНГИ СОФ ДАРОМАД | C54: =C34+C44-C52 -> 2697928042 | D54: =D34+D44-D52 -> 2002106971 | E54: =E34+E44-E52 -> 695821071
A56: 7. | B56: ОПЕРАЦИОН ХАРАЖАТЛАР
A57: а. | B57: Банк хизматчиларига иш ҳақи ва бошқа харажатлар | C57: 1026816770 | D57: 1026816770
A58: а1) | B58: шундан, раҳбар ходимларга тўловлар | C58: 40136079 | D58: 40136079
A59: б. | B59: Ижара ва таъминот харажатлари | C59: 110709526 | D59: 110709526
A60: в. | B60: Хизмат сафари ва транспорт харажатлари | C60: 17989555 | D60: 17989555
A61: г. | B61: Маъмурий харажатлар | C61: 42883035 | D61: 42883035
A62: д. | B62: Репрезентация ва хайрия | C62: 118510637 | D62: 118510637
A63: е. | B63: Эскириш харажатлари | C63: 106150024 | D63: 106150024
A64: ж. | B64: Суғурта харажатлари | C64: 1963365 | D64: 1963365
A65: з. | B65: Солиқлар (фойда солиғидан ташқари) ва лицензиялар | C65: 102182136 | D65: 102182136
A66: и. | B66: Жарима ва пенялар | C66: 1177805 | D66: 1177805
A67: к. | B67: Бошқа операцион харажатлар | C67: 38103484 | D67: 38103484
A68: л. | B68: Жами операцион харажатлар | C68: =SUM(C57:C67)-C58 -> 1566486337 | D68: =SUM(D57:D67)-D58 -> 1566486337
A70: 8. | B70: Солиқ тўлангунга қадар соф фойда ва бошқа тузатишлар | C70: =C54-C68 -> 1131441705 | D70: =D54-D68 -> 435620634 | E70: =+E54-(C68-D68) -> 695821071
A71: а. | B71: Фойда солиғини баҳолаш | C71: =+D71+E71 -> 219757586 | D71: 219757586 | E71: 0
A73: 9. | B73: ТУЗАТИШЛАР КИРИТИЛГУНГА ҚАДАР ДАРОМАД | C73: =C70-C71 -> 911684119 | D73: =D70-D71 -> 215863048 | E73: =E70-E71 -> 695821071
A74: а. | B74: Кўзда тутилмаган даромад ёки зарарлар, соф | C74: =+D74+E74 -> 0 | D74: 0 | E74: 0
A75: б. | B75: Фойда бўйича тузатишлар, соф | C75: =+D75+E75 -> 0 | D75: 0 | E75: 0
A77: 10. | B77: СОФ ФОЙДА (ЗАРАР) | C77: =C73+C74+C75 -> 911684119 | D77: =D73+D74+D75 -> 215863048 | E77: =E73+E74+E75 -> 695821071
B79: Бошқарув Раис имзоси:
B81: Бош бухгалтер имзоси:

Sheet Analysis of Interest
B1: ФОИЗЛИ ДАРОМАД ВА ХАРАЖАТЛАР ТАҲЛИЛИ | C1: 4-жадвал
B3: =+'Asset quality'!B3 -> "Ўзсаноатқурилишибанк" АТБ | C3: =+'Asset quality'!Q3 -> 45289
A4: № | B4: Кўрсаткичлар | C4: =+'Asset quality'!T3 -> минг. сўмда
A5: 1. | B5: КРЕДИТ ВА ЛИЗИНГ ОПЕРАЦИЯЛАРИ БЎЙИЧА ФОИЗЛИ ДАРОМАДЛАР
A6: a. | B6: Марказий банкка берилган қисқа муддатли кредитлар | C6: 0
A7: б. | B7: Бошқа банкларга берилган кредитлар | C7: 0
A8: в. | B8: Ҳукуматга берилган кредитлар | C8: 16027206
A9: г. | B9: Жисмоний шахсларга берилган кредит ва лизинглар | C9: 1249916675
A10: д. | B10: Давлат корхоналарига берилган кредит ва лизинглар | C10: 1161079360
A11: е. | B11: Қўшма ва чет эл капитали иштирокидаги корхоналарга берилган кредит ва лизинглар | C11: 1166410537
A12: ж. | B12: Хусусий корхоналар, хўжалик ширкатлари ва жамиятларга берилган кредит ва лизинглар | C12: 2570519222
A13: з. | B13: Бошқа кредит ва лизинглар | C13: 114802813
A14: и. | B14: Жами кредит ва лизинг операциялари бўйича фоизли даромад | C14: =SUM(C6:C13) -> 6278755813 | E14: =+'Income '!C12 -> 6278755813
A16: 2. | B16: ВАКИЛЛИК ҲИСОБВАРАҚЛАРИ БЎЙИЧА ФОИЗЛИ ДАРОМАДЛАР
A17: a. | B17: Марказий банкдаги ҳисобварақлар бўйича фоизли даромадлар | C17: 13993151 | E17: =+'Income '!C6 -> 13993151
A18: б. | B18: Бошқа банклардаги ҳисобварақлар бўйича фоизли даромадлар | C18: 472306870 | E18: =+'Income '!C7 -> 472306870
B19: Жами вакиллик ҳисобварағи бўйича фоизли даромадлар | C19: =SUM(C17:C18) -> 486300021
A21: 3. | B21: ҚИММАТЛИ ҚОҒОЗЛАР ВА УЛАРГА ҚИЛИНГАН ИНВЕСТИЦИЯЛАР БЎЙИЧА ФОИЗЛИ ДАРОМАДЛАР
A22: a. | B22: Давлат қимматли қоғозлари | C22: 360316265
A23: б. | B23: Марказий банкнинг облигациялари ва бошқа қимматли қоғозлари | C23: 37508742
A24: в. | B24: Давлат корхоналарининг қарз қимматли қоғозлари бўйича фоизли даромадлар | C24: 234247
A25: г. | B25: Еврооблигациялар бўйича фоизли даромадлар | C25: 0
A26: д. | B26: Хусусий корхоналарнинг қимматли қоғозлари | C26: 0
A27: е. | B27: Бошқа қимматли қоғозлар | C27: 0
A28: ж. | B28: Жами олди-сотди қимматли қоғозлар бўйича фоизли даромадлар | C28: =SUM(C22:C27) -> 398059254 | E28: =+'Income '!C9 -> 398059254
A30: 4. | B30: ИНВЕСТИЦИЯЛАР БЎЙИЧА ФОИЗЛИ ДАРОМАДЛАР
A31: a. | B31: Давлат қимматли қоғозлари | C31: 0
A32: б. | B32: Марказий банкнинг облигациялари ва бошқа қарз қимматли қоғозларига қилинган инвестициялар бўйича фоизли даромадлар | C32: 0
A33: в. | B33: Корхоналарнинг қарз қимматли қоғозларига қилинган инвестициялар бўйича фоизли даромадлар | C33: 626507
A34: г. | B34: Еврооблигациялар | C34: 0
A35: д. | B35: Бошқа қимматли қоғозлар | C35: 0
A36: е. | B36: Жами инвестициялар бўйича фоизли даромадлар | C36: =SUM(C31:C35) -> 626507
A38: 5. | B38: БОШҚА ФОИЗЛИ ДАРОМАДЛАР
A39: a. | B39: Қимматли қоғозлар билан амалга оширилган репо битимлари бўйича фоизли даромадлар | C39: 2784649
A40: б. | B40: Бошқа фоизли даромадлар | C40: 13335904 | E40: =+'Income '!C14 -> 13335904
A42: 6. | B42: ЖАМИ ФОИЗЛИ ДАРОМАДЛАР | C42: =C14+C19+C28+C36+C39+C40 -> 7179862148 | E42: =+'Income '!C15 -> 7179862148
A44: 7. | B44: ДЕПОЗИТЛАР БЎЙИЧА ФОИЗЛИ ХАРАЖАТЛАР
A45: A. | B45: Талаб қилиб олингунча сақланадиган депозитлар
A46: a. | B46: Ҳукумат | C46: 7516492
A47: б. | B47: Жисмоний шахслар | C47: 1
A48: в. | B48: Давлат корхоналари | C48: 7264881
A49: г. | B49: Қўшма ва чет эл капитали иштирокидаги корхоналар | C49: 405044
A50: д. | B50: Хусусий корхоналар | C50: 0
A51: е. | B51: Бошқа депозитлар | C51: 0
A52: ж. | B52: Жами талаб қилиб олингунча сақланадиган депозитлар бўйича фоизли харажатлар | C52: =SUM(C46:C51) -> 15186418 | E52: =+'Income '!C18 -> 15186418
A54: Б. | B54: Муддатли депозитлар
A55: a. | B55: Ҳукумат | C55: 377707695
A56: б. | B56: Жисмоний шахслар | C56: 643574845
A57: в. | B57: Давлат корхоналари | C57: 18399104
A58: г. | B58: Қўшма ва чет эл капитали иштирокидаги корхоналар | C58: 65390485
A59: д. | B59: Хусусий корхоналар | C59: 14799201
A60: е. | B60: Бошқа депозитлар | C60: 5972758
A61: ж. | B61: Жами муддатли депозитлар бўйича фоизли харажатлар | C61: =SUM(C55:C60) -> 1125844088 | E61: =+'Income '!C19 -> 1125844088
A63: В. | B63: ЖАМИ ДЕПОЗИТЛАР БЎЙИЧА ФОИЗЛИ ХАРАЖАТЛАР | C63: =C52+C61 -> 1141030506
A65: 8. | B65: БОШҚА МАЖБУРИЯТЛАР БЎЙИЧА ФОИЗЛИ ХАРАЖАТЛАР
A66: а. | B66: Банкнинг тўланмаган акцептлари бўйича фоизли харажатлари | C66: 0
A67: б. | B67: Кредитлар бўйича фоизли харажатлар | C67: 2153234424 | E67: =+'Income '!C23 -> 2153234424
A68: в. | B68: Қимматли қоғозлар билан амалга оширилган РЕПО битимлари бўйича фоизли харажатлар | C68: 24948798 | E68: =+'Income '!C24 -> 24948798
A69: г. | B69: Бошқа фоизли харажатлар | C69: 878686406 | E69: =+'Income '!C25+'Income '!C21 -> 878686406
A70: д. | B70: Жами бошқa мажбуриятлар бўйича фоизли хaрaжaтлaр | C70: =SUM(C66:C69) -> 3056869628
A72: 9. | B72: ЖАМИ ФОИЗЛИ ХAРAЖAТЛAР | C72: =C63+C70 -> 4197900134 | E72: =+'Income '!C27 -> 4197900134
B74: Бошқарув Раис имзоси:
B76: Бош бухгалтер имзоси:

Sheet Changes in Equity
A1: ХУСУСИЙ КАПИТАЛДАГИ ЎЗГАРИШЛАР | C1: 7-жадвал
B3: =+'Asset quality'!B3 -> "Ўзсаноатқурилишибанк" АТБ | C3: =+'Asset quality'!Q3 -> 45289
A4: № | B4: Кўрсаткичлар | C4: =+'Asset quality'!T3 -> минг. сўмда
A5: 1. | B5: Ўтган йил учун дастлабки ҳисобланган умумий капитал | C5: 7828121193
A6: 2. | B6: Хусусий капиталдаги ўтган йил учун ҳисоботларда кўрсатилмаган тузатишлар, (соф) | C6: 0
A7: 3. | B7: Ўтган календар йили якуни бўйича балансдаги тузатишлар (3=1-2 ) | C7: =SUM(C5:C6) -> 7828121193
A8: 4. | B8: Йил бошидан соф фойда (зарар) | C8: =+'Income '!C77 -> 911684119 | D8: =+[8]Balance!$C$76 -> 911684119 | E8: =+C8-D8 -> 0
A9: 5. | B9: Жорий йилда сотиш, айирбошлаш, сотиб олиш ёки қайтиб сотиб олиш (соф кирим) | C9: -5571976
A10: 6. | B10: Жорий йил учун бошланғич қийматига нисбатан баҳолаш қийматининг ошган суммаси | C10: -1425151
A11: 7. | B11: МИНУС: Имтиёзли акциялар бўйича эълон қилинган пул дивидендлари | C11: 1616900
A12: 8. | B12: МИНУС: Оддий акциялар бўйича эълон қилинган пуллик дивидендлар
A13: 9. | B13: Жорий йилнинг соф хусусий капиталига таъсир этувчи бошқа моддалар | C13: -2831133
A14: 10. | B14: Жорий давр якуни бўйича жами хусусий капитал | C14: =C7+SUM(C8:C10)-SUM(C11:C12)+C13 -> 8728360152 | D14: =+[8]Balance!$C$77 -> 8728360152 | E14: =+C14-D14 -> 0
B16: Бошқарув Раис имзоси:
B18: Бош бухгалтер имзоси:

Sheet Loans Receivable
A1: ИҚТИСОДИЁТ ТАРМОҚЛАРИ, МИЖОЗЛАР ТУРЛАРИ, ВА ТАЪМИНОТ ТУРЛАРИ БЎЙИЧА АЖРАТИЛГАН КРЕДИТЛАР ВА ЛИЗИНГЛАР ҲИСОБОТИ | W1: 8-жадвал
B3: =+'Asset quality'!B3 -> "Ўзсаноатқурилишибанк" АТБ | T3: =+'Asset quality'!Q3 -> 45289 | X3: =+'Asset quality'!T3 -> минг. сўмда
A4: № | B4: Иқтисодиёт тармоқлари бўйича | C4: Кредит суммаси | D4: шундан | F4: шундан муаммоли кредитлар | J4: шундан
D5: миллий валютада | E5: хорижий валютада (экв. сўмда) | F5: NPL | G5: шундан | J5: Депозитлар | K5: Ўзбекистон Республикаси Ҳукумати тамонидан кафолатланган кредитлар | L5: шундан | M5: Транспорт воситалари | N5: Инвентарлар | O5: Кўчмас мулк | P5: шундан | R5: Асбоб ускуналар | S5: Векселлар (облигациялар) | T5: Акциялар | U5: Учинчи шахс кафолати | V5: Учинчи шахс кафиллиги | W5: Суғурта полиси | X5: Таъминотсиз | Y5: Бошқа кафолатлар
G6: Қониқарсиз | H6: Шубҳали | I6: Умидсиз | L6: Ўзбекистон Республикаси Ҳукумати томонидан кафолатланган хорижий валютадаги (эквивалент сўмда) кредитлар | P6: турар жой (хонадон) | Q6: тижорат кўчмас мулки
A7: Код | B7: (А) | C7: (Б) | D7: (Б1) | E7: (Б3) | F7: (В) | G7: (В1) | H7: (В2) | I7: (В3) | J7: (Г) | K7: (Д) | L7: (Д1) | M7: (Е) | N7: (Ж) | O7: (З) | P7: (З1) | Q7: (З2) | R7: (И) | S7: (К) | T7: (Л) | U7: (М) | V7: (Н) | W7: (О) | X7: (П) | Y7: (Р)
B8: Саноат
A9: 10 | B9: Давлат корхоналари | C9: =SUM(J9:Y9)-L9-P9-Q9 -> 9043576442 | D9: 2394277397 | E9: 6649299045 | F9: =+G9+H9+I9 -> 0 | G9: 0 | H9: 0 | I9: 0 | J9: 0 | K9: 4785668881 | L9: 4245386620 | M9: 0 | N9: 377148300 | O9: =+P9+Q9 -> 347845253 | P9: 0 | Q9: 347845253 | R9: 561819579 | S9: 0 | T9: 127632450 | U9: 0 | V9: 1470039773 | W9: 0 | X9: 0 | Y9: 1373422206
A10: =A9+10 -> 20 | B10: Қўшма ва чет эл капитали иштирокидаги корхоналар | C10: =SUM(J10:Y10)-L10-P10-Q10 -> 8066997417 | D10: 435809228 | E10: 7631188189 | F10: =+G10+H10+I10 -> 56216040 | G10: 0 | H10: 46247548 | I10: 9968492 | J10: 1233877 | K10: 0 | L10: 0 | M10: 4844791 | N10: 145131391 | O10: =+P10+Q10 -> 2029463925 | P10: 0 | Q10: 2029463925 | R10: 2661030818 | S10: 0 | T10: 0 | U10: 0 | V10: 1790251356 | W10: 340906107 | X10: 0 | Y10: 1094135152
A11: =A10+10 -> 30 | B11: Хусусий корхоналар | C11: =SUM(J11:Y11)-L11-P11-Q11 -> 12801927212 | D11: 1933287232 | E11: 10868639980 | F11: =+G11+H11+I11 -> 444638825 | G11: 201641115 | H11: 242997710 | I11: 0 | J11: 85489626 | K11: 0 | L11: 0 | M11: 56954934 | N11: 569706122 | O11: =+P11+Q11 -> 3447741382 | P11: 82069057 | Q11: 3365672325 | R11: 2303737768 | S11: 0 | T11: 0 | U11: 0 | V11: 4270803877 | W11: 1376344550 | X11: 0 | Y11: 691148953
A12: =A11+10 -> 40 | B12: Ҳукумат | C12: =SUM(J12:Y12)-L12-P12-Q12 -> 0 | D12: 0 | E12: 0 | F12: =+G12+H12+I12 -> 0 | G12: 0 | H12: 0 | I12: 0 | J12: 0 | K12: 0 | L12: 0 | M12: 0 | N12: 0 | O12: =+P12+Q12 -> 0 | P12: 0 | Q12: 0 | R12: 0 | S12: 0 | T12: 0 | U12: 0 | V12: 0 | W12: 0 | X12: 0 | Y12: 0
A13: =A12+10 -> 50 | B13: Бошқалар | C13: =SUM(J13:Y13)-L13-P13-Q13 -> 0 | D13: 0 | E13: 0 | F13: =+G13+H13+I13 -> 0 | G13: 0 | H13: 0 | I13: 0 | J13: 0 | K13: 0 | L13: 0 | M13: 0 | N13: 0 | O13: =+P13+Q13 -> 0 | P13: 0 | Q13: 0 | R13: 0 | S13: 0 | T13: 0 | U13: 0 | V13: 0 | W13: 0 | X13: 0 | Y13: 0
A14: =A13+10 -> 60 | B14: Жами | C14: =SUM(J14:Y14)-L14-P14-Q14 -> 29912501071 | D14: =SUM(D9:D13) -> 4763373857 | E14: =SUM(E9:E13) -> 25149127214 | F14: =+G14+H14+I14 -> 500854865 | G14: =SUM(G9:G13) -> 201641115 | H14: =SUM(H9:H13) -> 289245258 | I14: =SUM(I9:I13) -> 9968492 | J14: =SUM(J9:J13) -> 86723503 | K14: =SUM(K9:K13) -> 4785668881 | L14: =SUM(L9:L13) -> 4245386620 | M14: =SUM(M9:M13) -> 61799725 | N14: =SUM(N9:N13) -> 1091985813 | ... Y14: =SUM(Y9:Y13) -> 3158706311
B15: Қишлоқ хўжалиги
A16: 70 | B16: Давлат корхоналари | C16: =SUM(J16:Y16)-L16-P16-Q16 -> 0 | D16: 0 | E16: 0 | F16: =+G16+H16+I16 -> 0 | G16: 0 | H16: 0 | I16: 0 | J16: 0 | K16: 0 | L16: 0 | M16: 0 | N16: 0 | O16: =+P16+Q16 -> 0 | P16: 0 | Q16: 0 | R16: 0 | S16: 0 | T16: 0 | U16: 0 | V16: 0 | W16: 0 | X16: 0 | Y16: 0
A17: =A16+10 -> 80 | B17: Қўшма ва чет эл капитали иштирокидаги корхоналар | C17: =SUM(J17:Y17)-L17-P17-Q17 -> 789288690 | D17: 330794749 | E17: 458493941 | F17: =+G17+H17+I17 -> 0 | G17: 0 | H17: 0 | I17: 0 | J17: 41195460 | K17: 0 | L17: 0 | M17: 9015628 | N17: 0 | O17: =+P17+Q17 -> 327185990 | P17: 1556788 | Q17: 325629202 | R17: 121218327 | S17: 0 | T17: 0 | U17: 0 | V17: 25611990 | W17: 265061295 | X17: 0 | Y17: 0
A18: =A17+10 -> 90 | B18: Хусусий корхоналар | C18: =SUM(J18:Y18)-L18-P18-Q18 -> 4015699054 | D18: 2001495554 | E18: 2014203500 | F18: =+G18+H18+I18 -> 260746305 | G18: 107673112 | H18: 153073193 | I18: 0 | J18: 416758 | K18: 0 | L18: 0 | M18: 31454007 | N18: 13003626 | O18: =+P18+Q18 -> 865245645 | P18: 21357688 | Q18: 843887957 | R18: 426787534 | S18: 0 | T18: 0 | U18: 0 | V18: 1489794285 | W18: 1182472123 | X18: 0 | Y18: 6525076
A19: =A18+10 -> 100 | B19: Фермер хўжалиги | C19: =SUM(J19:Y19)-L19-P19-Q19 -> 121348475 | D19: 28204799 | E19: 93143676 | F19: =+G19+H19+I19 -> 16944233 | G19: 1534407 | H19: 15409826 | I19: 0 | J19: 0 | K19: 0 | L19: 0 | M19: 2236327 | N19: 0 | O19: =+P19+Q19 -> 46516068 | P19: 1588577 | Q19: 44927491 | R19: 17209353 | S19: 0 | T19: 0 | U19: 0 | V19: 51389821 | W19: 3996906 | X19: 0 | Y19: 0
A20: =A19+10 -> 110 | B20: Ҳукумат | C20: =SUM(J20:Y20)-L20-P20-Q20 -> 0 | D20: 0 | E20: 0 | F20: =+G20+H20+I20 -> 0 | G20: 0 | H20: 0 | I20: 0 | J20: 0 | K20: 0 | L20: 0 | M20: 0 | N20: 0 | O20: =+P20+Q20 -> 0 | P20: 0 | Q20: 0 | R20: 0 | S20: 0 | T20: 0 | U20: 0 | V20: 0 | W20: 0 | X20: 0 | Y20: 0
A21: =A20+10 -> 120 | B21: Бошқалар | C21: =SUM(J21:Y21)-L21-P21-Q21 -> 0 | D21: 0 | E21: 0 | F21: =+G21+H21+I21 -> 0 | G21: 0 | H21: 0 | I21: 0 | J21: 0 | K21: 0 | L21: 0 | M21: 0 | N21: 0 | O21: =+P21+Q21 -> 0 | P21: 0 | Q21: 0 | R21: 0 | S21: 0 | T21: 0 | U21: 0 | V21: 0 | W21: 0 | X21: 0 | Y21: 0
A22: =A21+10 -> 130 | B22: Жами | C22: =SUM(J22:Y22)-L22-P22-Q22 -> 4926336219 | D22: =SUM(D16:D21) -> 2360495102 | E22: =SUM(E16:E21) -> 2565841117 | F22: =+G22+H22+I22 -> 277690538 | G22: =SUM(G17:G21) -> 109207519 | H22: =SUM(H17:H21) -> 168483019 | I22: =SUM(I17:I21) -> 0 | J22: =SUM(J16:J21) -> 41612218 | K22: =SUM(K16:K21) -> 0 | L22: =SUM(L16:L21) -> 0 | M22: =SUM(M16:M21) -> 42705962 | N22: =SUM(N16:N21) -> 13003626 | O22: =SUM(O16:O21) -> 1238947703 | P22: =SUM(P16:P21) -> 24503053 | Q22: =SUM(Q16:Q21) -> 1214444650 | ... Y22: =SUM(Y16:Y21) -> 6525076
B23: Транспорт ва коммуникация
A24: 140 | B24: Давлат корхоналари | C24: =SUM(J24:Y24)-L24-P24-Q24 -> 3130908071 | D24: 0 | E24: 3130908071 | F24: =+G24+H24+I24 -> 0 | G24: 0 | H24: 0 | I24: 0 | J24: 881006874 | K24: 1583896166 | L24: 1583896166 | M24: 0 | N24: 0 | O24: =+P24+Q24 -> 0 | P24: 0 | Q24: 0 | R24: 17710248 | S24: 0 | T24: 0 | U24: 0 | V24: 528380933 | W24: 0 | X24: 0 | Y24: 119913850
A25: =A24+10 -> 150 | B25: Қўшма ва чет эл капитали иштирокидаги корхоналар | C25: =SUM(J25:Y25)-L25-P25-Q25 -> 0 | D25: 0 | E25: 0 | F25: =+G25+H25+I25 -> 0 | G25: 0 | H25: 0 | I25: 0 | J25: 0 | K25: 0 | L25: 0 | M25: 0 | N25: 0 | O25: =+P25+Q25 -> 0 | P25: 0 | Q25: 0 | R25: 0 | S25: 0 | T25: 0 | U25: 0 | V25: 0 | W25: 0 | X25: 0 | Y25: 0
A26: =A25+10 -> 160 | B26: Хусусий корхоналар | C26: =SUM(J26:Y26)-L26-P26-Q26 -> 837205251 | D26: 120515494 | E26: 716689757 | F26: =+G26+H26+I26 -> 68756122 | G26: 63274014 | H26: 3800001 | I26: 1682107 | J26: 430163 | K26: 0 | L26: 0 | M26: 54758747 | N26: 0 | O26: =+P26+Q26 -> 358447299 | P26: 2884083 | Q26: 355563216 | R26: 33472246 | S26: 0 | T26: 0 | U26: 0 | V26: 180730754 | W26: 209100650 | X26: 0 | Y26: 265392
A27: =A26+10 -> 170 | B27: Ҳукумат | C27: =SUM(J27:Y27)-L27-P27-Q27 -> 0 | D27: 0 | E27: 0 | F27: =+G27+H27+I27 -> 0 | G27: 0 | H27: 0 | I27: 0 | J27: 0 | K27: 0 | L27: 0 | M27: 0 | N27: 0 | O27: =+P27+Q27 -> 0 | P27: 0 | Q27: 0 | R27: 0 | S27: 0 | T27: 0 | U27: 0 | V27: 0 | W27: 0 | X27: 0 | Y27: 0
A28: =A27+10 -> 180 | B28: Бошқалар | C28: =SUM(J28:Y28)-L28-P28-Q28 -> 0 | D28: 0 | E28: 0 | F28: =+G28+H28+I28 -> 0 | G28: 0 | H28: 0 | I28: 0 | J28: 0 | K28: 0 | L28: 0 | M28: 0 | N28: 0 | O28: =+P28+Q28 -> 0 | P28: 0 | Q28: 0 | R28: 0 | S28: 0 | T28: 0 | U28: 0 | V28: 0 | W28: 0 | X28: 0 | Y28: 0
A29: =A28+10 -> 190 | B29: Жами | C29: =SUM(J29:Y29)-L29-P29-Q29 -> 3968113322 | D29: =SUM(D24:D28) -> 120515494 | E29: =SUM(E24:E28) -> 3847597828 | F29: =+G29+H29+I29 -> 68756122 | G29: =SUM(G24:G28) -> 63274014 | H29: =SUM(H24:H28) -> 3800001 | I29: =SUM(I24:I28) -> 1682107 | J29: =SUM(J24:J28) -> 881437037 | K29: =SUM(K24:K28) -> 1583896166 | L29: =SUM(L24:L28) -> 1583896166 | M29: =SUM(M24:M28) -> 54758747 | N29: =SUM(N24:N28) -> 0 | ... Y29: =SUM(Y24:Y28) -> 120179242
B30: Қурилиш соҳаси
A31: 200 | B31: Давлат корхоналари | C31: =SUM(J31:Y31)-L31-P31-Q31 -> 0 | D31: 0 | E31: 0 | F31: =+G31+H31+I31 -> 0 | G31: 0 | H31: 0 | I31: 0 | J31: 0 | K31: 0 | L31: 0 | M31: 0 | N31: 0 | O31: =+P31+Q31 -> 0 | P31: 0 | Q31: 0 | R31: 0 | S31: 0 | T31: 0 | U31: 0 | V31: 0 | W31: 0 | X31: 0 | Y31: 0
A32: =A31+10 -> 210 | B32: Қўшма ва чет эл капитали иштирокидаги корхоналар | C32: =SUM(J32:Y32)-L32-P32-Q32 -> 2516725 | D32: 1170701 | E32: 1346024 | F32: =+G32+H32+I32 -> 810756 | G32: 810756 | H32: 0 | I32: 0 | J32: 0 | K32: 0 | L32: 0 | M32: 139645 | N32: 0 | O32: =+P32+Q32 -> 919363 | P32: 0 | Q32: 919363 | R32: 0 | S32: 0 | T32: 0 | U32: 0 | V32: 1126054 | W32: 331663 | X32: 0 | Y32: 0
A33: =A32+10 -> 220 | B33: Хусусий корхоналар | C33: =SUM(J33:Y33)-L33-P33-Q33 -> 1309241651 | D33: 368458372 | E33: 940783279 | F33: =+G33+H33+I33 -> 93917041 | G33: 42107696 | H33: 51809345 | I33: 0 | J33: 93641 | K33: 0 | L33: 0 | M33: 26385606 | N33: 76350 | O33: =+P33+Q33 -> 440026532 | P33: 6729521 | Q33: 433297011 | R33: 35361268 | S33: 0 | T33: 0 | U33: 0 | V33: 680260077 | W33: 126847315 | X33: 0 | Y33: 190862
A34: =A33+10 -> 230 | B34: Ҳукумат | C34: =SUM(J34:Y34)-L34-P34-Q34 -> 0 | D34: 0 | E34: 0 | F34: =+G34+H34+I34 -> 0 | G34: 0 | H34: 0 | I34: 0 | J34: 0 | K34: 0 | L34: 0 | M34: 0 | N34: 0 | O34: =+P34+Q34 -> 0 | P34: 0 | Q34: 0 | R34: 0 | S34: 0 | T34: 0 | U34: 0 | V34: 0 | W34: 0 | X34: 0 | Y34: 0
A35: =A34+10 -> 240 | B35: Бошқалар | C35: =SUM(J35:Y35)-L35-P35-Q35 -> 0 | D35: 0 | E35: 0 | F35: =+G35+H35+I35 -> 0 | G35: 0 | H35: 0 | I35: 0 | J35: 0 | K35: 0 | L35: 0 | M35: 0 | N35: 0 | O35: =+P35+Q35 -> 0 | P35: 0 | Q35: 0 | R35: 0 | S35: 0 | T35: 0 | U35: 0 | V35: 0 | W35: 0 | X35: 0 | Y35: 0
A36: =A35+10 -> 250 | B36: Жами | C36: =SUM(J36:Y36)-L36-P36-Q36 -> 1311758376 | D36: =SUM(D31:D35) -> 369629073 | E36: =SUM(E31:E35) -> 942129303 | F36: =+G36+H36+I36 -> 94727797 | G36: =SUM(G31:G35) -> 42918452 | H36: =SUM(H31:H35) -> 51809345 | I36: =SUM(I31:I35) -> 0 | J36: =SUM(J31:J35) -> 93641 | K36: =SUM(K31:K35) -> 0 | L36: =SUM(L31:L35) -> 0 | M36: =SUM(M31:M35) -> 26525251 | N36: =SUM(N31:N35) -> 76350 | ... Y36: =SUM(Y31:Y35) -> 190862
B37: Савдо ва умумий хизмат
A38: 260 | B38: Давлат корхоналари | C38: =SUM(J38:Y38)-L38-P38-Q38 -> 0 | D38: 0 | E38: 0 | F38: =+G38+H38+I38 -> 0 | G38: 0 | H38: 0 | I38: 0 | J38: 0 | K38: 0 | L38: 0 | M38: 0 | N38: 0 | O38: =+P38+Q38 -> 0 | P38: 0 | Q38: 0 | R38: 0 | S38: 0 | T38: 0 | U38: 0 | V38: 0 | W38: 0 | X38: 0 | Y38: 0
A39: =A38+10 -> 270 | B39: Қўшма ва чет эл капитали иштирокидаги корхоналар | C39: =SUM(J39:Y39)-L39-P39-Q39 -> 210505732 | D39: 2886030 | E39: 207619702 | F39: =+G39+H39+I39 -> 0 | G39: 0 | H39: 0 | I39: 0 | J39: 0 | K39: 0 | L39: 0 | M39: 5533725 | N39: 0 | O39: =+P39+Q39 -> 46329299 | P39: 0 | Q39: 46329299 | R39: 12183800 | S39: 0 | T39: 0 | U39: 0 | V39: 140778051 | W39: 5680857 | X39: 0 | Y39: 0
A40: =A39+10 -> 280 | B40: Хусусий корхоналар | C40: =SUM(J40:Y40)-L40-P40-Q40 -> 3255933640 | D40: 707116615 | E40: 2548817025 | F40: =+G40+H40+I40 -> 264987535 | G40: 60676560 | H40: 193760975 | I40: 10550000 | J40: 281355 | K40: 0 | L40: 0 | M40: 63006710 | N40: 98572342 | O40: =+P40+Q40 -> 1259278840 | P40: 7623843 | Q40: 1251654997 | R40: 80183014 | S40: 0 | T40: 0 | U40: 0 | V40: 685150388 | W40: 1067567991 | X40: 0 | Y40: 1893000
A41: =A40+10 -> 290 | B41: Ҳукумат | C41: =SUM(J41:Y41)-L41-P41-Q41 -> 0 | D41: =+E41+F41 -> 0 | E41: =+F41+G41 -> 0 | F41: =+G41+H41+I41 -> 0 | G41: =+H41+I41 -> 0 | H41: =+I41+J41 -> 0 | I41: =+J41+K41 -> 0 | J41: =+K41+L41 -> 0 | K41: =+L41+M41 -> 0 | L41: =+M41+N41 -> 0 | M41: =+N41+O41 -> 0 | N41: =+O41+P41 -> 0 | O41: =+P41+Q41 -> 0 | P41: 0 | Q41: 0 | R41: 0 | S41: 0 | T41: 0 | U41: 0 | V41: 0 | W41: 0 | X41: 0 | Y41: 0
A42: =A41+10 -> 300 | B42: Бошқалар | C42: =SUM(J42:Y42)-L42-P42-Q42 -> 0 | D42: =+E42+F42 -> 0 | E42: =+F42+G42 -> 0 | F42: =+G42+H42+I42 -> 0 | G42: =+H42+I42 -> 0 | H42: =+I42+J42 -> 0 | I42: =+J42+K42 -> 0 | J42: =+K42+L42 -> 0 | K42: =+L42+M42 -> 0 | L42: =+M42+N42 -> 0 | M42: =+N42+O42 -> 0 | N42: =+O42+P42 -> 0 | O42: =+P42+Q42 -> 0 | P42: 0 | Q42: 0 | R42: 0 | S42: 0 | T42: 0 | U42: 0 | V42: 0 | W42: 0 | X42: 0 | Y42: 0
A43: =A42+10 -> 310 | B43: Жами | C43: =SUM(J43:Y43)-L43-P43-Q43 -> 3466439372 | D43: =SUM(D38:D42) -> 710002645 | E43: =SUM(E38:E42) -> 2756436727 | F43: =+G43+H43+I43 -> 264987535 | G43: =SUM(G38:G42) -> 60676560 | H43: =SUM(H38:H42) -> 193760975 | I43: =SUM(I38:I42) -> 10550000 | J43: =SUM(J38:J42) -> 281355 | K43: =SUM(K38:K42) -> 0 | L43: =SUM(L38:L42) -> 0 | M43: =SUM(M38:M42) -> 68540435 | N43: =SUM(N38:N42) -> 98572342 | ... Y43: =SUM(Y38:Y42) -> 1893000
B44: Моддий ва техник таъминотни ривожлантириш
A45: 320 | B45: Давлат корхоналари | C45: =SUM(J45:Y45)-L45-P45-Q45 -> 1556420375 | D45: 1435427852 | E45: 120992523 | F45: =+G45+H45+I45 -> 0 | G45: 0 | H45: 0 | I45: 0 | J45: 0 | K45: 0 | L45: 0 | M45: 0 | N45: 0 | O45: =+P45+Q45 -> 0 | P45: 0 | Q45: 0 | R45: 0 | S45: 0 | T45: 0 | U45: 0 | V45: 41540404 | W45: 0 | X45: 0 | Y45: 1514879971
A46: =A45+10 -> 330 | B46: Қўшма ва чет эл капитали иштирокидаги корхоналар | C46: =SUM(J46:Y46)-L46-P46-Q46 -> 8609646 | D46: 0 | E46: 8609646 | F46: =+G46+H46+I46 -> 0 | G46: 0 | H46: 0 | I46: 0 | J46: 0 | K46: 0 | L46: 0 | M46: 0 | N46: 0 | O46: =+P46+Q46 -> 3736133 | P46: 0 | Q46: 3736133 | R46: 4873513 | S46: 0 | T46: 0 | U46: 0 | V46: 0 | W46: 0 | X46: 0 | Y46: 0
A47: =A46+10 -> 340 | B47: Хусусий корхоналар | C47: =SUM(J47:Y47)-L47-P47-Q47 -> 592746241 | D47: 422140890 | E47: 170605351 | F47: =+G47+H47+I47 -> 5316686 | G47: 246815 | H47: 31138 | I47: 5038733 | J47: 0 | K47: 0 | L47: 0 | M47: 22115782 | N47: 0 | O47: =+P47+Q47 -> 246095042 | P47: 1140892 | Q47: 244954150 | R47: 6052989 | S47: 0 | T47: 0 | U47: 0 | V47: 294037765 | W47: 24444663 | X47: 0 | Y47: 0
A48: =A47+10 -> 350 | B48: Ҳукумат | C48: =SUM(J48:Y48)-L48-P48-Q48 -> 0 | D48: 0 | E48: 0 | F48: =+G48+H48+I48 -> 0 | G48: 0 | H48: 0 | I48: 0 | J48: 0 | K48: 0 | L48: 0 | M48: 0 | N48: 0 | O48: =+P48+Q48 -> 0 | P48: 0 | Q48: 0 | R48: 0 | S48: 0 | T48: 0 | U48: 0 | V48: 0 | W48: 0 | X48: 0 | Y48: 0
A49: =A48+10 -> 360 | B49: Бошқалар | C49: =SUM(J49:Y49)-L49-P49-Q49 -> 0 | D49: 0 | E49: 0 | F49: =+G49+H49+I49 -> 0 | G49: 0 | H49: 0 | I49: 0 | J49: 0 | K49: 0 | L49: 0 | M49: 0 | N49: 0 | O49: =+P49+Q49 -> 0 | P49: 0 | Q49: 0 | R49: 0 | S49: 0 | T49: 0 | U49: 0 | V49: 0 | W49: 0 | X49: 0 | Y49: 0
A50: =A49+10 -> 370 | B50: Жами | C50: =SUM(J50:Y50)-L50-P50-Q50 -> 2157776262 | D50: =SUM(D45:D49) -> 1857568742 | E50: =SUM(E45:E49) -> 300207520 | F50: =+G50+H50+I50 -> 5316686 | G50: =SUM(G45:G49) -> 246815 | H50: =SUM(H45:H49) -> 31138 | I50: =SUM(I45:I49) -> 5038733 | J50: =SUM(J45:J49) -> 0 | K50: =SUM(K45:K49) -> 0 | L50: =SUM(L45:L49) -> 0 | M50: =SUM(M45:M49) -> 22115782 | N50: =SUM(N45:N49) -> 0 | ... Y50: =SUM(Y45:Y49) -> 1514879971
B51: Уй-жой коммунал хизмати
A52: 380 | B52: Давлат корхоналари | C52: =SUM(J52:Y52)-L52-P52-Q52 -> 0 | D52: 0 | E52: 0 | F52: =+G52+H52+I52 -> 0 | G52: 0 | H52: 0 | I52: 0 | J52: 0 | K52: 0 | L52: 0 | M52: 0 | N52: 0 | O52: =+P52+Q52 -> 0 | P52: 0 | Q52: 0 | R52: 0 | S52: 0 | T52: 0 | U52: 0 | V52: 0 | W52: 0 | X52: 0 | Y52: 0
A53: =A52+10 -> 390 | B53: Қўшма ва чет эл капитали иштирокидаги корхоналар | C53: =SUM(J53:Y53)-L53-P53-Q53 -> 0 | D53: 0 | E53: 0 | F53: =+G53+H53+I53 -> 0 | G53: 0 | H53: 0 | I53: 0 | J53: 0 | K53: 0 | L53: 0 | M53: 0 | N53: 0 | O53: =+P53+Q53 -> 0 | P53: 0 | Q53: 0 | R53: 0 | S53: 0 | T53: 0 | U53: 0 | V53: 0 | W53: 0 | X53: 0 | Y53: 0
A54: =A53+10 -> 400 | B54: Хусусий корхоналар | C54: =SUM(J54:Y54)-L54-P54-Q54 -> 0 | D54: 0 | E54: 0 | F54: =+G54+H54+I54 -> 0 | G54: 0 | H54: 0 | I54: 0 | J54: 0 | K54: 0 | L54: 0 | M54: 0 | N54: 0 | O54: =+P54+Q54 -> 0 | P54: 0 | Q54: 0 | R54: 0 | S54: 0 | T54: 0 | U54: 0 | V54: 0 | W54: 0 | X54: 0 | Y54: 0
A55: =A54+10 -> 410 | B55: Ҳукумат | C55: =SUM(J55:Y55)-L55-P55-Q55 -> 0 | D55: 0 | E55: 0 | F55: =+G55+H55+I55 -> 0 | G55: 0 | H55: 0 | I55: 0 | J55: 0 | K55: 0 | L55: 0 | M55: 0 | N55: 0 | O55: =+P55+Q55 -> 0 | P55: 0 | Q55: 0 | R55: 0 | S55: 0 | T55: 0 | U55: 0 | V55: 0 | W55: 0 | X55: 0 | Y55: 0
A56: 485 | B56: Нодавлат нотижорат ташкилотлар | C56: =SUM(J56:Y56)-L56-P56-Q56 -> 1605566 | D56: 1605566 | E56: 0 | F56: =+G56+H56+I56 -> 138125 | G56: 138125 | H56: 0 | I56: 0 | J56: 0 | K56: 0 | L56: 0 | M56: 0 | N56: 0 | O56: =+P56+Q56 -> 0 | P56: 0 | Q56: 0 | R56: 0 | S56: 0 | T56: 0 | U56: 0 | V56: 1003838 | W56: 571728 | X56: 0 | Y56: 30000
A57: =A55+10 -> 420 | B57: Бошқалар | C57: =SUM(J57:Y57)-L57-P57-Q57 -> 0 | D57: 0 | E57: 0 | F57: =+G57+H57+I57 -> 0 | G57: 0 | H57: 0 | I57: 0 | J57: 0 | K57: 0 | L57: 0 | M57: 0 | N57: 0 | O57: =+P57+Q57 -> 0 | P57: 0 | Q57: 0 | R57: 0 | S57: 0 | T57: 0 | U57: 0 | V57: 0 | W57: 0 | X57: 0 | Y57: 0
A58: =A57+10 -> 430 | B58: Жами | C58: =SUM(J58:Y58)-L58-P58-Q58 -> 1605566 | D58: =SUM(D52:D57) -> 1605566 | E58: =SUM(E52:E57) -> 0 | F58: =+G58+H58+I58 -> 138125 | G58: =SUM(G53:G57) -> 138125 | H58: =SUM(H53:H57) -> 0 | I58: =SUM(I53:I57) -> 0 | J58: =SUM(J52:J57) -> 0 | K58: =SUM(K52:K57) -> 0 | L58: =SUM(L52:L57) -> 0 | M58: =SUM(M52:M57) -> 0 | N58: =SUM(N52:N57) -> 0 | O58: =SUM(O52:O57) -> 0 | P58: =SUM(P52:P57) -> 0 | Q58: =SUM(Q52:Q57) -> 0 | ... Y58: =SUM(Y52:Y57) -> 30000
B59: Бошқа соҳалар
A60: 440 | B60: Давлат корхоналари | C60: =SUM(J60:Y60)-L60-P60-Q60 -> 371830246 | D60: 371830246 | E60: 0 | F60: =+G60+H60+I60 -> 0 | G60: 0 | H60: 0 | I60: 0 | J60: 0 | K60: 121000801 | L60: 0 | M60: 28758609 | N60: 0 | O60: =+P60+Q60 -> 175478979 | P60: 0 | Q60: 175478979 | R60: 0 | S60: 0 | T60: 0 | U60: 0 | V60: 41940806 | W60: 4651051 | X60: 0 | Y60: 0
A61: =A60+10 -> 450 | B61: Қўшма ва чет эл капитали иштирокидаги корхоналар | C61: =SUM(J61:Y61)-L61-P61-Q61 -> 1218707466 | D61: 126831270 | E61: 1091876196 | F61: =+G61+H61+I61 -> 0 | G61: 0 | H61: 0 | I61: 0 | J61: 0 | K61: 0 | L61: 0 | M61: 46295763 | N61: 0 | O61: =+P61+Q61 -> 964259005 | P61: 0 | Q61: 964259005 | R61: 25735139 | S61: 0 | T61: 0 | U61: 0 | V61: 182417559 | W61: 0 | X61: 0 | Y61: 0
A62: =A61+10 -> 460 | B62: Хусусий корхоналар | C62: =SUM(J62:Y62)-L62-P62-Q62 -> 1971896497 | D62: 612151756 | E62: 1359744741 | F62: =+G62+H62+I62 -> 29263619 | G62: 8839572 | H62: 20424047 | I62: 0 | J62: 50000000 | K62: 0 | L62: 0 | M62: 26306417 | N62: 0 | O62: =+P62+Q62 -> 724133918 | P62: 25141676 | Q62: 698992242 | R62: 95238190 | S62: 0 | T62: 0 | U62: 285418 | V62: 976703346 | W62: 93187430 | X62: 0 | Y62: 6041778
A63: =A62+10 -> 470 | B63: Марказий банк | C63: =SUM(J63:Y63)-L63-P63-Q63 -> 0 | D63: 0 | E63: 0 | F63: =+G63+H63+I63 -> 0 | G63: 0 | H63: 0 | I63: 0 | J63: 0 | K63: 0 | L63: 0 | M63: 0 | N63: 0 | O63: =+P63+Q63 -> 0 | P63: 0 | Q63: 0 | R63: 0 | S63: 0 | T63: 0 | U63: 0 | V63: 0 | W63: 0 | X63: 0 | Y63: 0
A64: =A63+10 -> 480 | B64: Бошқа банклар | C64: =SUM(J64:Y64)-L64-P64-Q64 -> 0 | D64: 0 | E64: 0 | F64: =+G64+H64+I64 -> 0 | G64: 0 | H64: 0 | I64: 0 | J64: 0 | K64: 0 | L64: 0 | M64: 0 | N64: 0 | O64: =+P64+Q64 -> 0 | P64: 0 | Q64: 0 | R64: 0 | S64: 0 | T64: 0 | U64: 0 | V64: 0 | W64: 0 | X64: 0 | Y64: 0
A65: =A64+10 -> 490 | B65: Ҳукумат | C65: =SUM(J65:Y65)-L65-P65-Q65 -> 0 | D65: 0 | E65: 0 | F65: =+G65+H65+I65 -> 0 | G65: 0 | H65: 0 | I65: 0 | J65: 0 | K65: 0 | L65: 0 | M65: 0 | N65: 0 | O65: =+P65+Q65 -> 0 | P65: 0 | Q65: 0 | R65: 0 | S65: 0 | T65: 0 | U65: 0 | V65: 0 | W65: 0 | X65: 0 | Y65: 0
A66: =A65+10 -> 500 | B66: Банк бўлмаган молиявий муассасалар | C66: =SUM(J66:Y66)-L66-P66-Q66 -> 2946729 | D66: 2946729 | E66: 0 | F66: =+G66+H66+I66 -> 446729 | G66: 0 | H66: 446729 | I66: 0 | J66: 0 | K66: 0 | L66: 0 | M66: 446729 | N66: 0 | O66: =+P66+Q66 -> 2500000 | P66: 0 | Q66: 2500000 | R66: 0 | S66: 0 | T66: 0 | U66: 0 | V66: 0 | W66: 0 | X66: 0 | Y66: 0
A67: =A66+10 -> 510 | B67: Нодавлат нотижорат ташкилотлар | C67: =SUM(J67:Y67)-L67-P67-Q67 -> 0 | D67: 0 | E67: 0 | F67: =+G67+H67+I67 -> 0 | G67: 0 | H67: 0 | I67: 0 | J67: 0 | K67: 0 | L67: 0 | M67: 0 | N67: 0 | O67: =+P67+Q67 -> 0 | P67: 0 | Q67: 0 | R67: 0 | S67: 0 | T67: 0 | U67: 0 | V67: 0 | W67: 0 | X67: 0 | Y67: 0
A68: =A67+10 -> 520 | B68: Бюджет ташкилотлари | C68: =SUM(J68:Y68)-L68-P68-Q68 -> 0 | D68: 0 | E68: 0 | F68: =+G68+H68+I68 -> 0 | G68: 0 | H68: 0 | I68: 0 | J68: 0 | K68: 0 | L68: 0 | M68: 0 | N68: 0 | O68: =+P68+Q68 -> 0 | P68: 0 | Q68: 0 | R68: 0 | S68: 0 | T68: 0 | U68: 0 | V68: 0 | W68: 0 | X68: 0 | Y68: 0
A69: =A68+10 -> 530 | B69: Бошқалар | C69: =SUM(J69:Y69)-L69-P69-Q69 -> 0 | D69: 0 | E69: 0 | F69: =+G69+H69+I69 -> 0 | G69: 0 | H69: 0 | I69: 0 | J69: 0 | K69: 0 | L69: 0 | M69: 0 | N69: 0 | O69: =+P69+Q69 -> 0 | P69: 0 | Q69: 0 | R69: 0 | S69: 0 | T69: 0 | U69: 0 | V69: 0 | W69: 0 | X69: 0 | Y69: 0
A70: =A69+10 -> 540 | B70: Жами | C70: =SUM(J70:Y70)-L70-P70-Q70 -> 3565380938 | D70: =SUM(D60:D69) -> 1113760001 | E70: =SUM(E60:E69) -> 2451620937 | F70: =+G70+H70+I70 -> 29710348 | G70: =SUM(G60:G69) -> 8839572 | H70: =SUM(H60:H69) -> 20870776 | I70: =SUM(I60:I69) -> 0 | J70: =SUM(J60:J69) -> 50000000 | K70: =SUM(K60:K69) -> 121000801 | L70: =SUM(L60:L69) -> 0 | M70: =SUM(M60:M69) -> 101807518 | N70: =SUM(N60:N69) -> 0 | ... Y70: =SUM(Y60:Y69) -> 6041778
A71: 550 | B71: Жами жисмоний шахслар | C71: =SUM(J71:Y71)-L71-P71-Q71 -> 7814492786 | D71: 7814492786 | E71: 0 | F71: =+G71+H71+I71 -> 40993913 | G71: 19062315 | H71: 21931598 | I71: 0 | J71: 0 | K71: 0 | L71: 0 | M71: 438097917 | N71: 0 | O71: =+P71+Q71 -> 4705786266 | P71: 4703336166 | Q71: 2450100 | R71: 0 | S71: 0 | T71: 0 | U71: 154457 | V71: 1717574217 | W71: 945825798 | X71: 4031829 | Y71: 3022302
B72: Кредит ва лизинг операциялари
A73: =A71+10 -> 560 | B73: Жисмоний шахслар | C73: =SUM(J73:Y73)-L73-P73-Q73 -> 7814492786 | D73: =+D71 -> 7814492786 | E73: =+E71 -> 0 | F73: =+F71 -> 40993913 | G73: =+G71 -> 19062315 | H73: =+H71 -> 21931598 | I73: =+I71 -> 0 | J73: =+J71 -> 0 | K73: =+K71 -> 0 | ... Y73: =+Y71 -> 3022302
A74: =A73+10 -> 570 | B74: Давлат корхоналари | C74: =SUM(J74:Y74)-L74-P74-Q74 -> 14102735134 | D74: =D9+D16+D24+D31+D38+D45+D52+D60 -> 4201535495 | E74: =E9+E16+E24+E31+E38+E45+E52+E60 -> 9901199639 | F74: =F9+F16+F24+F31+F38+F45+F52+F60 -> 0 | G74: =G9+G16+G24+G31+G38+G45+G52+G60 -> 0 | H74: =H9+H16+H24+H31+H38+H45+H52+H60 -> 0 | I74: =I9+I16+I24+I31+I38+I45+I52+I60 -> 0 | J74: =J9+J16+J24+J31+J38+J45+J52+J60 -> 881006874 | K74: =K9+K16+K24+K31+K38+K45+K52+K60 -> 6490565848 | ... Y74: =Y9+Y16+Y24+Y31+Y38+Y45+Y52+Y60 -> 3008216027
A75: =A74+10 -> 580 | B75: Қўшма ва чет эл капитали иштирокидаги корхоналар | C75: =SUM(J75:Y75)-L75-P75-Q75 -> 10296625676 | D75: =D10+D17+D25+D32+D39+D46+D53+D61 -> 897491978 | E75: =E10+E17+E25+E32+E39+E46+E53+E61 -> 9399133698 | F75: =F10+F17+F25+F32+F39+F46+F53+F61 -> 57026796 | G75: =G10+G17+G25+G32+G39+G46+G53+G61 -> 810756 | H75: =H10+H17+H25+H32+H39+H46+H53+H61 -> 46247548 | I75: =I10+I17+I25+I32+I39+I46+I53+I61 -> 9968492 | J75: =J10+J17+J25+J32+J39+J46+J53+J61 -> 42429337 | K75: =K10+K17+K25+K32+K39+K46+K53+K61 -> 0 | ... Y75: =Y10+Y17+Y25+Y32+Y39+Y46+Y53+Y61 -> 1094135152
A76: =A75+10 -> 590 | B76: Хусусий корхоналар | C76: =SUM(J76:Y76)-L76-P76-Q76 -> 24784649546 | D76: =D11+D18+D26+D33+D40+D47+D54+D62 -> 6165165913 | E76: =E11+E18+E26+E33+E40+E47+E54+E62 -> 18619483633 | F76: =F11+F18+F26+F33+F40+F47+F54+F62 -> 1167626133 | G76: =G11+G18+G26+G33+G40+G47+G54+G62 -> 484458884 | H76: =H11+H18+H26+H33+H40+H47+H54+H62 -> 665896409 | I76: =I11+I18+I26+I33+I40+I47+I54+I62 -> 17270840 | J76: =J11+J18+J26+J33+J40+J47+J54+J62 -> 136711543 | K76: =K11+K18+K26+K33+K40+K47+K54+K62 -> 0 | ... Y76: =Y11+Y18+Y26+Y33+Y40+Y47+Y54+Y62 -> 706065061
A77: =A76+10 -> 600 | B77: Фермер хўжалиги | C77: =SUM(J77:Y77)-L77-P77-Q77 -> 121348475 | D77: =D19 -> 28204799 | E77: =E19 -> 93143676 | F77: =F19 -> 16944233 | G77: =G19 -> 1534407 | H77: =H19 -> 15409826 | I77: =I19 -> 0 | J77: =J19 -> 0 | K77: =K19 -> 0 | ... Y77: =Y19 -> 0
A78: =A77+10 -> 610 | B78: Бошқа банклар | C78: =SUM(J78:Y78)-L78-P78-Q78 -> 0 | D78: =D64 -> 0 | E78: =E64 -> 0 | F78: =F64 -> 0 | G78: =G64 -> 0 | H78: =H64 -> 0 | I78: =I64 -> 0 | J78: =J64 -> 0 | K78: =K64 -> 0 | ... Y78: =Y64 -> 0
A79: =A78+10 -> 620 | B79: Марказий банк | C79: =SUM(J79:Y79)-L79-P79-Q79 -> 0 | D79: =D63 -> 0 | E79: =E63 -> 0 | F79: =F63 -> 0 | G79: =G63 -> 0 | H79: =H63 -> 0 | I79: =I63 -> 0 | J79: =J63 -> 0 | K79: =K63 -> 0 | ... Y79: =Y63 -> 0
A80: =A79+10 -> 630 | B80: Ҳукумат | C80: =SUM(J80:Y80)-L80-P80-Q80 -> 0 | D80: =D12+D20+D27+D34+D41+D48+D55+D65 -> 0 | E80: =E12+E20+E27+E34+E41+E48+E55+E65 -> 0 | F80: =F12+F20+F27+F34+F41+F48+F55+F65 -> 0 | G80: =G12+G20+G27+G34+G41+G48+G55+G65 -> 0 | H80: =H12+H20+H27+H34+H41+H48+H55+H65 -> 0 | I80: =I12+I20+I27+I34+I41+I48+I55+I65 -> 0 | J80: =J12+J20+J27+J34+J41+J48+J55+J65 -> 0 | K80: =K12+K20+K27+K34+K41+K48+K55+K65 -> 0 | ... Y80: =Y12+Y20+Y27+Y34+Y41+Y48+Y55+Y65 -> 0
A81: =A80+10 -> 640 | B81: Банк бўлмаган молиявий муассасалар | C81: =SUM(J81:Y81)-L81-P81-Q81 -> 2946729 | D81: =D66 -> 2946729 | E81: =E66 -> 0 | F81: =F66 -> 446729 | G81: =G66 -> 0 | H81: =H66 -> 446729 | I81: =I66 -> 0 | J81: =J66 -> 0 | K81: =K66 -> 0 | ... Y81: =Y66 -> 0
A82: =A81+10 -> 650 | B82: Нодавлат нотижорат ташкилотлар | C82: =SUM(J82:Y82)-L82-P82-Q82 -> 1605566 | D82: =+D56+D67 -> 1605566 | E82: =+E56+E67 -> 0 | F82: =+F56+F67 -> 138125 | G82: =+G56+G67 -> 138125 | H82: =+H56+H67 -> 0 | I82: =+I56+I67 -> 0 | J82: =+J56+J67 -> 0 | K82: =+K56+K67 -> 0 | ... Y82: =+Y56+Y67 -> 30000
A83: =A82+10 -> 660 | B83: Бюджет ташкилотлари | C83: =SUM(J83:Y83)-L83-P83-Q83 -> 0 | D83: =D68 -> 0 | E83: =E68 -> 0 | F83: =F68 -> 0 | G83: =G68 -> 0 | H83: =H68 -> 0 | I83: =I68 -> 0 | J83: =J68 -> 0 | K83: =K68 -> 0 | ... Y83: =Y68 -> 0
A84: =A83+10 -> 670 | B84: Бошқалар | C84: =SUM(J84:Y84)-L84-P84-Q84 -> 0 | D84: =D13+D21+D28+D35+D42+D49+D57+D69 -> 0 | E84: =E13+E21+E28+E35+E42+E49+E57+E69 -> 0 | F84: =F13+F21+F28+F35+F42+F49+F57+F69 -> 0 | G84: =G13+G21+G28+G35+G42+G49+G57+G69 -> 0 | H84: =H13+H21+H28+H35+H42+H49+H57+H69 -> 0 | I84: =I13+I21+I28+I35+I42+I49+I57+I69 -> 0 | J84: =J13+J21+J28+J35+J42+J49+J57+J69 -> 0 | K84: =K13+K21+K28+K35+K42+K49+K57+K69 -> 0 | ... Y84: =Y13+Y21+Y28+Y35+Y42+Y49+Y57+Y69 -> 0
A85: =A84+10 -> 680 | B85: Жами кредит ва лизинг суммаси | C85: =SUM(J85:Y85)-L85-P85-Q85 -> 57124403912 | D85: =SUM(D73:D84) -> 19111443266 | E85: =SUM(E73:E84) -> 38012960646 | F85: =SUM(F73:F84) -> 1283175929 | G85: =SUM(G73:G84) -> 506004487 | H85: =SUM(H73:H84) -> 749932110 | I85: =SUM(I73:I84) -> 27239332 | J85: =SUM(J73:J84) -> 1060147754 | K85: =SUM(K73:K84) -> 6490565848 | ... Y85: =SUM(Y73:Y84) -> 4811468542
B87: Бошқарув Раис имзоси:
B89: Бош бухгалтер имзоси:
C92: =+[8]Balance!C25 -> 57124403912 | D92: =+[8]Balance!D25 -> 19111443266 | E92: =+[8]Balance!E25 -> 38012960646 | F92: =+'Asset Classification'!M31+'Asset Classification'!Q31+'Asset Classification'!U31 -> 1283175929 | G92: =+'Asset Classification'!M31 -> 506004487 | H92: =+'Asset Classification'!Q31 -> 749932110 | I92: =+'Asset Classification'!U31 -> 27239332
C93: =+C85-C92 -> 0 | D93: =+D85-D92 -> 0 | E93: =+E85-E92 -> 0 | F93: =+F85-F92 -> 0 | G93: =+G85-G92 -> 0 | H93: =+H85-H92 -> 0 | I93: =+I85-I92 -> 0

Sheet Aging Analysis
A1: ОЛИНИШИ ЛОЗИМ БЎЛГАН МУДДАТИ ЎТГАН КРЕДИТ ВА МОЛИЯВИЙ ЛИЗИНГ ТАҲЛИЛИ | X1: 9-жадвал
B3: =+'Asset quality'!B3 -> "Ўзсаноатқурилишибанк" АТБ | T3: =+'Asset quality'!Q3 -> 45289 | X3: =+'Asset quality'!T3 -> минг. сўмда
A4: № | B4: Кўрсаткичлар | C4: Жами кредит суммаси | D4: % | E4: Шартлари қайта кўрилган кредит ва лизинглар | F4: % | G4: Суд жараёнидаги қарздорликлар | H4: % | I4: Муддати ўтган | K4: % | L4: шу жумладан, кечиктирилган муддати бўйича
L5: 1-30 кун | N5: 31-60 кун | P5: 61-90 кун | R5: 91-180 кун | T5: 181-365 кун | V5: 366-730 кун | X5: 2 йилдан ортиқ
I6: асосий қарздорлик | J6: фоиз тўловлари | L6: асосий қарздорлик | M6: фоиз тўловлари | N6: асосий қарздорлик | O6: фоиз тўловлари | P6: асосий қарздорлик | Q6: фоиз тўловлари | R6: асосий қарздорлик | S6: фоиз тўловлари | T6: асосий қарздорлик | U6: фоиз тўловлари | V6: асосий қарздорлик | W6: фоиз тўловлари | X6: асосий қарздорлик | Y6: фоиз тўловлари
B7: (А) | C7: (Б) | D7: (В) | E7: (Г) | F7: (Д) | G7: (Е) | H7: (Ж) | I7: (З) | J7: (З1) | K7: (И) | L7: (К) | M7: (К1) | N7: (Л) | O7: (Л1) | P7: (М) | Q7: (М1) | R7: (Н) | S7: (Н1) | T7: (О) | U7: (О1) | V7: (П) | W7: (П1) | X7: (Р) | Y7: (Р1)
B8: Мижозлар тури бўйича
A9: 1 | B9: Марказий банк | C9: =+'Loans Receivable'!C79 -> 0 | D9: =IF(C$22=0,"",C9/C$22) -> 0 | F9: =IF(E$22=0,"",E9/E$22) -> 0 | H9: =IF($G$22=0,"",G9/$G$22) -> 0 | I9: =+L9+N9+P9+R9+T9+V9+X9 -> 0 | J9: =+M9+O9+T9+S9+U9+W9+Y9 -> 0 | K9: =IF($Z$22=0,"",Z9/$Z$22) -> 0 | Z9: =+I9+J9 -> 0 | AA9: =+C9-Z9 -> 0
A10: 2 | B10: Бошқа банклар | C10: =+'Loans Receivable'!C78 -> 0 | D10: =IF(C$22=0,"",C10/C$22) -> 0 | F10: =IF(E$22=0,"",E10/E$22) -> 0 | H10: =IF($G$22=0,"",G10/$G$22) -> 0 | I10: =+L10+N10+P10+R10+T10+V10+X10 -> 0 | J10: =+M10+O10+Q10+S10+U10+W10+Y10 -> 0 | K10: =IF($Z$22=0,"",Z10/$Z$22) -> 0 | Z10: =+I10+J10 -> 0
A11: 3 | B11: Ҳукумат | C11: =+'Loans Receivable'!C80 -> 0 | D11: =IF(C$22=0,"",C11/C$22) -> 0 | F11: =IF(E$22=0,"",E11/E$22) -> 0 | H11: =IF($G$22=0,"",G11/$G$22) -> 0 | I11: =+L11+N11+P11+R11+T11+V11+X11 -> 0 | J11: =+M11+O11+Q11+S11+U11+W11+Y11 -> 0 | K11: =IF($Z$22=0,"",Z11/$Z$22) -> 0 | Z11: =+I11+J11 -> 0
A12: 4 | B12: Жисмоний шахслар | C12: =+'Loans Receivable'!C73 -> 7814492786 | D12: =IF(C$22=0,"",C12/C$22) -> 0.1367978 | E12: 11346858 | F12: =IF(E$22=0,"",E12/E$22) -> 0.19429271 | G12: 43859 | H12: =IF($G$22=0,"",G12/$G$22) -> 0.00027778647 | I12: =+L12+N12+P12+R12+T12+V12+X12 -> 7856662 | J12: =+M12+O12+Q12+S12+U12+W12+Y12 -> 7474846 | K12: =IF($Z$22=0,"",Z12/$Z$22) -> 0.010874089 | L12: 1748340 | M12: 2291587 | N12: 1245341 | O12: 705234 | P12: 1251712 | Q12: 939523 | R12: 1276984 | S12: 767116 | T12: 2334285 | U12: 2771386 | V12: 0 | W12: 0 | X12: 0 | Y12: 0 | Z12: =+I12+J12 -> 15331508
A13: 5 | B13: Давлат корхоналари | C13: =+'Loans Receivable'!C74 -> 14102735134 | D13: =IF(C$22=0,"",C13/C$22) -> 0.24687759 | E13: 4496481 | F13: =IF(E$22=0,"",E13/E$22) -> 0.076993428 | G13: 0 | H13: =IF($G$22=0,"",G13/$G$22) -> 0 | I13: =+L13+N13+P13+R13+T13+V13+X13 -> 98319866 | J13: =+M13+O13+Q13+S13+U13+W13+Y13 -> 2441554 | K13: =IF($Z$22=0,"",Z13/$Z$22) -> 0.071466462 | L13: 98319866 | M13: 2441554 | N13: 0 | O13: 0 | P13: 0 | Q13: 0 | R13: 0 | S13: 0 | T13: 0 | U13: 0 | V13: 0 | W13: 0 | X13: 0 | Y13: 0 | Z13: =+I13+J13 -> 100761420
A14: 6 | B14: Қўшма ва чет эл капитали иштирокидаги корхоналар | C14: =+'Loans Receivable'!C75 -> 10296625676 | D14: =IF(C$22=0,"",C14/C$22) -> 0.18024916 | E14: 0 | F14: =IF(E$22=0,"",E14/E$22) -> 0 | G14: 0 | H14: =IF($G$22=0,"",G14/$G$22) -> 0 | I14: =+L14+N14+P14+R14+T14+V14+X14 -> 150059657 | J14: =+M14+O14+Q14+S14+U14+W14+Y14 -> 127290347 | K14: =IF($Z$22=0,"",Z14/$Z$22) -> 0.19671441 | L14: 78208666 | M14: 114030712 | N14: 14354547 | O14: 1555895 | P14: 30138339 | Q14: 6264672 | R14: 555201 | S14: 131412 | T14: 20157144 | U14: 2379726 | V14: 6645760 | W14: 2927930 | X14: 0 | Y14: 0 | Z14: =+I14+J14 -> 277350004
A15: 7 | B15: Хусусий корхоналар | C15: =+'Loans Receivable'!C76 -> 24784649546 | D15: =IF(C$22=0,"",C15/C$22) -> 0.43387148 | E15: 40892838 | F15: =IF(E$22=0,"",E15/E$22) -> 0.70020973 | G15: 157843603 | H15: =IF($G$22=0,"",G15/$G$22) -> 0.99972221 | I15: =+L15+N15+P15+R15+T15+V15+X15 -> 728560050 | J15: =+M15+O15+Q15+S15+U15+W15+Y15 -> 277799568 | K15: =IF($Z$22=0,"",Z15/$Z$22) -> 0.71377479 | L15: 113971397 | M15: 165987458 | N15: 177054680 | O15: 18045871 | P15: 104436616 | Q15: 13699389 | R15: 132240698 | S15: 27403948 | T15: 194506659 | U15: 49320772 | V15: 6350000 | W15: 3342130 | X15: 0 | Y15: 0 | Z15: =+I15+J15 -> 1006359618
A16: 8 | B16: Фермер хўжаликлари | C16: =+'Loans Receivable'!C77 -> 121348475 | D16: =IF(C$22=0,"",C16/C$22) -> 0.0021242843 | E16: 1664665 | F16: =IF(E$22=0,"",E16/E$22) -> 0.028504127 | G16: 0 | H16: =IF($G$22=0,"",G16/$G$22) -> 0 | I16: =+L16+N16+P16+R16+T16+V16+X16 -> 6226046 | J16: =+M16+O16+Q16+S16+U16+W16+Y16 -> 3683202 | K16: =IF($Z$22=0,"",Z16/$Z$22) -> 0.0070282742 | L16: 2008417 | M16: 2263948 | N16: 122615 | O16: 97805 | P16: 407093 | Q16: 168428 | R16: 412079 | S16: 215537 | T16: 3275842 | U16: 937484 | V16: 0 | W16: 0 | X16: 0 | Y16: 0 | Z16: =+I16+J16 -> 9909248
A17: 9 | B17: Нобанк молиявий институтлар | C17: =+'Loans Receivable'!C81 -> 2946729 | D17: =IF(C$22=0,"",C17/C$22) -> 5.1584416e-05 | E17: 0 | F17: =IF(E$22=0,"",E17/E$22) -> 0 | G17: 0 | H17: =IF($G$22=0,"",G17/$G$22) -> 0 | I17: =+L17+N17+P17+R17+T17+V17+X17 -> 118872 | J17: =+M17+O17+Q17+S17+U17+W17+Y17 -> 62346 | K17: =IF($Z$22=0,"",Z17/$Z$22) -> 0.00012853143 | L17: 0 | M17: 0 | N17: 0 | O17: 0 | P17: 0 | Q17: 0 | R17: 38743 | S17: 10439 | T17: 80129 | U17: 51907 | V17: 0 | W17: 0 | X17: 0 | Y17: 0 | Z17: =+I17+J17 -> 181218
A18: 10 | B18: Нодавлат нотижорат ташкилотлар | C18: =+'Loans Receivable'!C82 -> 1605566 | D18: =IF(C$22=0,"",C18/C$22) -> 2.8106481e-05 | E18: 0 | F18: =IF(E$22=0,"",E18/E$22) -> 0 | G18: 0 | H18: =IF($G$22=0,"",G18/$G$22) -> 0 | I18: =+L18+N18+P18+R18+T18+V18+X18 -> 13281 | J18: =+M18+O18+Q18+S18+U18+W18+Y18 -> 5677 | K18: =IF($Z$22=0,"",Z18/$Z$22) -> 1.344623e-05 | L18: 0 | M18: 135 | N18: 0 | O18: 0 | P18: 0 | Q18: 0 | R18: 13281 | S18: 5542 | T18: 0 | U18: 0 | V18: 0 | W18: 0 | X18: 0 | Y18: 0 | Z18: =+I18+J18 -> 18958
A19: 11 | B19: Бюджет ташкилотлари | C19: =+'Loans Receivable'!C83 -> 0 | D19: =IF(C$22=0,"",C19/C$22) -> 0 | E19: 0 | F19: =IF(E$22=0,"",E19/E$22) -> 0 | G19: 0 | H19: =IF($G$22=0,"",G19/$G$22) -> 0 | I19: =+L19+N19+P19+R19+T19+V19+X19 -> 0 | J19: =+M19+O19+Q19+S19+U19+W19+Y19 -> 0 | K19: =IF($Z$22=0,"",Z19/$Z$22) -> 0 | L19: 0 | M19: 0 | N19: 0 | O19: 0 | P19: 0 | Q19: 0 | R19: 0 | S19: 0 | T19: 0 | U19: 0 | V19: 0 | W19: 0 | X19: 0 | Y19: 0 | Z19: =+I19+J19 -> 0
A20: 12 | B20: Бошқалар | C20: =+'Loans Receivable'!C84 -> 0 | D20: =IF(C$22=0,"",C20/C$22) -> 0 | E20: 0 | F20: =IF(E$22=0,"",E20/E$22) -> 0 | G20: 0 | H20: =IF($G$22=0,"",G20/$G$22) -> 0 | I20: =+L20+N20+P20+R20+T20+V20+X20 -> 0 | J20: =+M20+O20+Q20+S20+U20+W20+Y20 -> 0 | K20: =IF($Z$22=0,"",Z20/$Z$22) -> 0 | L20: 0 | M20: 0 | N20: 0 | O20: 0 | P20: 0 | Q20: 0 | R20: 0 | S20: 0 | T20: 0 | U20: 0 | V20: 0 | W20: 0 | X20: 0 | Y20: 0 | Z20: =+I20+J20 -> 0
Z21: =+I21+J21 -> 0
A22: 13 | B22: Жами кредит ва лизинг суммаси | C22: =SUM(C9:C20) -> 57124403912 | D22: =IF(C$22=0,"",C22/C$22) -> 1 | E22: =SUM(E9:E20) -> 58400842 | F22: =IF(E$22=0,"",E22/E$22) -> 1 | G22: =SUM(G9:G20) -> 157887462 | H22: =IF($G$22=0,"",G22/$G$22) -> 1 | I22: =SUM(I9:I20) -> 991154434 | J22: =SUM(J9:J20) -> 418757540 | K22: =IF($Z$22=0,"",Z22/$Z$22) -> 1 | L22: =SUM(L9:L20) -> 294256686 | M22: =SUM(M9:M20) -> 287015394 | N22: =SUM(N9:N20) -> 192777183 | O22: =SUM(O9:O20) -> 20404805 | P22: =SUM(P9:P20) -> 136233760 | Q22: =SUM(Q9:Q20) -> 21072012 | R22: =SUM(R9:R20) -> 134536986 | S22: =SUM(S9:S20) -> 28533994 | ... Y22: =SUM(Y9:Y20) -> 0 | Z22: =+I22+J22 -> 1409911974
Z23: =+I23+J23 -> 0
B24: Иқтисодиёт соҳалари бўйича | Z24: =+I24+J24 -> 0
A25: 14 | B25: Саноат | C25: =+'Loans Receivable'!C14 -> 29912501071 | D25: =IF(C$35=0,"",C25/C$35) -> 0.52363787 | E25: 34378217 | F25: =IF($E$35=0,"",E25/$E$35) -> 0.58865961 | G25: 71852496 | H25: =IF($G$35=0,"",G25/$G$35) -> 0.45508678 | I25: =+L25+N25+P25+R25+T25+V25+X25 -> 416894845 | J25: =+M25+O25+Q25+S25+U25+W25+Y25 -> 220635459 | K25: =IF($Z$35=0,"",Z25/$Z$35) -> 0.45217738 | L25: 175273503 | M25: 170354551 | N25: 44261683 | O25: 6392554 | P25: 43153635 | Q25: 9499748 | R25: 71246613 | S25: 18117890 | T25: 76313651 | U25: 13342786 | V25: 6645760 | W25: 2927930 | X25: 0 | Y25: 0 | Z25: =+I25+J25 -> 637530304
A26: 15 | B26: Қишлоқ хўжалиги | C26: =+'Loans Receivable'!C22 -> 4926336219 | D26: =IF(C$35=0,"",C26/C$35) -> 0.086238733 | E26: 2415555 | F26: =IF($E$35=0,"",E26/$E$35) -> 0.041361647 | G26: 0 | H26: =IF($G$35=0,"",G26/$G$35) -> 0 | I26: =+L26+N26+P26+R26+T26+V26+X26 -> 293400607 | J26: =+M26+O26+Q26+S26+U26+W26+Y26 -> 64935267 | K26: =IF($Z$35=0,"",Z26/$Z$35) -> 0.25415478 | L26: 44832372 | M26: 33117186 | N26: 130600236 | O26: 11175199 | P26: 76132630 | Q26: 7675934 | R26: 15063040 | S26: 2232360 | T26: 26772329 | U26: 10734588 | V26: 0 | W26: 0 | X26: 0 | Y26: 0 | Z26: =+I26+J26 -> 358335874
A27: 16 | B27: Транспорт ва коммуникация | C27: =+'Loans Receivable'!C29 -> 3968113322 | D27: =IF(C$35=0,"",C27/C$35) -> 0.069464415 | E27: 899161 | F27: =IF($E$35=0,"",E27/$E$35) -> 0.01539637 | G27: 1 | H27: =IF($G$35=0,"",G27/$G$35) -> 6.3336251e-09 | I27: =+L27+N27+P27+R27+T27+V27+X27 -> 21275638 | J27: =+M27+O27+Q27+S27+U27+W27+Y27 -> 8346740 | K27: =IF($Z$35=0,"",Z27/$Z$35) -> 0.02101009 | L27: 504602 | M27: 4274245 | N27: 2567655 | O27: 97835 | P27: 278902 | Q27: 671682 | R27: 16934495 | S27: 2387538 | T27: 989984 | U27: 915440 | V27: 0 | W27: 0 | X27: 0 | Y27: 0 | Z27: =+I27+J27 -> 29622378
A28: 17 | B28: Қурилиш соҳаси | C28: =+'Loans Receivable'!C36 -> 1311758376 | D28: =IF(C$35=0,"",C28/C$35) -> 0.022963187 | E28: 493875 | F28: =IF($E$35=0,"",E28/$E$35) -> 0.0084566418 | G28: 11510424 | H28: =IF($G$35=0,"",G28/$G$35) -> 0.072902711 | I28: =+L28+N28+P28+R28+T28+V28+X28 -> 29147301 | J28: =+M28+O28+Q28+S28+U28+W28+Y28 -> 21660317 | K28: =IF($Z$35=0,"",Z28/$Z$35) -> 0.036036021 | L28: 3745843 | M28: 13941755 | N28: 664873 | O28: 432698 | P28: 2607789 | Q28: 861982 | R28: 2169141 | S28: 688812 | T28: 19959655 | U28: 5735070 | V28: 0 | W28: 0 | X28: 0 | Y28: 0 | Z28: =+I28+J28 -> 50807618
A29: 18 | B29: Савдо ва умумий овқатланиш | C29: =+'Loans Receivable'!C43 -> 3466439372 | D29: =IF(C$35=0,"",C29/C$35) -> 0.060682285 | E29: 8827176 | F29: =IF($E$35=0,"",E29/$E$35) -> 0.15114809 | G29: 72906866 | H29: =IF($G$35=0,"",G29/$G$35) -> 0.46176476 | I29: =+L29+N29+P29+R29+T29+V29+X29 -> 144642842 | J29: =+M29+O29+Q29+S29+U29+W29+Y29 -> 54210292 | K29: =IF($Z$35=0,"",Z29/$Z$35) -> 0.1410394 | L29: 6544435 | M29: 25602761 | N29: 9349182 | O29: 1090876 | P29: 11089066 | Q29: 830953 | R29: 25026725 | S29: 3600842 | T29: 86633434 | U29: 19935714 | V29: 6000000 | W29: 3149146 | X29: 0 | Y29: 0 | Z29: =+I29+J29 -> 198853134
A30: 19 | B30: Моддий ва техник таъминотни ривожлантириш | C30: =+'Loans Receivable'!C50 -> 2157776262 | D30: =IF(C$35=0,"",C30/C$35) -> 0.037773283 | E30: 0 | F30: =IF($E$35=0,"",E30/$E$35) -> 0 | G30: 0 | H30: =IF($G$35=0,"",G30/$G$35) -> 0 | I30: =+L30+N30+P30+R30+T30+V30+X30 -> 51801776 | J30: =+M30+O30+Q30+S30+U30+W30+Y30 -> 1363411 | K30: =IF($Z$35=0,"",Z30/$Z$35) -> 0.03770816 | L30: 50100000 | M30: 918440 | N30: 447990 | O30: 134319 | P30: 625833 | Q30: 116716 | R30: 246815 | S30: 515 | T30: 31138 | U30: 437 | V30: 350000 | W30: 192984 | X30: 0 | Y30: 0 | Z30: =+I30+J30 -> 53165187
A31: 20 | B31: Уй-жой коммунал хизмати | C31: =+'Loans Receivable'!C58 -> 1605566 | D31: =IF(C$35=0,"",C31/C$35) -> 2.8106481e-05 | E31: 0 | F31: =IF($E$35=0,"",E31/$E$35) -> 0 | G31: 0 | H31: =IF($G$35=0,"",G31/$G$35) -> 0 | I31: =+L31+N31+P31+R31+T31+V31+X31 -> 13281 | J31: =+M31+O31+Q31+S31+U31+W31+Y31 -> 5677 | K31: =IF($Z$35=0,"",Z31/$Z$35) -> 1.344623e-05 | L31: 0 | M31: 135 | N31: 0 | O31: 0 | P31: 0 | Q31: 0 | R31: 13281 | S31: 5542 | T31: 0 | U31: 0 | V31: 0 | W31: 0 | X31: 0 | Y31: 0 | Z31: =+I31+J31 -> 18958
A32: 21 | B32: Бошқа соҳалар | C32: =+'Loans Receivable'!C70 -> 3565380938 | D32: =IF(C$35=0,"",C32/C$35) -> 0.062414322 | E32: 40000 | F32: =IF($E$35=0,"",E32/$E$35) -> 0.00068492163 | G32: 1573816 | H32: =IF($G$35=0,"",G32/$G$35) -> 0.0099679606 | I32: =+L32+N32+P32+R32+T32+V32+X32 -> 26121482 | J32: =+M32+O32+Q32+S32+U32+W32+Y32 -> 40125531 | K32: =IF($Z$35=0,"",Z32/$Z$35) -> 0.046986631 | L32: 11507591 | M32: 36514734 | N32: 3640223 | O32: 376090 | P32: 1094193 | Q32: 475474 | R32: 2559892 | S32: 733379 | T32: 7319583 | U32: 2025854 | V32: 0 | W32: 0 | X32: 0 | Y32: 0 | Z32: =+I32+J32 -> 66247013
A33: 22 | B33: Жисмоний шахслар | C33: =+'Loans Receivable'!C71 -> 7814492786 | D33: =IF(C$35=0,"",C33/C$35) -> 0.1367978 | E33: 11346858 | F33: =IF($E$35=0,"",E33/$E$35) -> 0.19429271 | G33: 43859 | H33: =IF($G$35=0,"",G33/$G$35) -> 0.00027778647 | I33: =+L33+N33+P33+R33+T33+V33+X33 -> 7856662 | J33: =+M33+O33+Q33+S33+U33+W33+Y33 -> 7474846 | K33: =IF($Z$35=0,"",Z33/$Z$35) -> 0.010874089 | L33: 1748340 | M33: 2291587 | N33: 1245341 | O33: 705234 | P33: 1251712 | Q33: 939523 | R33: 1276984 | S33: 767116 | T33: 2334285 | U33: 2771386 | V33: 0 | W33: 0 | X33: 0 | Y33: 0 | Z33: =+I33+J33 -> 15331508
Z34: =+I34+J34 -> 0
A35: 23 | B35: Жами кредит ва лизинг суммаси | C35: =SUM(C25:C33) -> 57124403912 | D35: =IF(C$35=0,"",C35/C$35) -> 1 | E35: =SUM(E25:E33) -> 58400842 | F35: =IF($E$35=0,"",E35/$E$35) -> 1 | G35: =SUM(G25:G33) -> 157887462 | H35: =IF($G$35=0,"",G35/$G$35) -> 1 | I35: =SUM(I25:I33) -> 991154434 | J35: =SUM(J25:J33) -> 418757540 | K35: =IF($Z$35=0,"",Z35/$Z$35) -> 1 | L35: =SUM(L25:L33) -> 294256686 | M35: =SUM(M25:M33) -> 287015394 | N35: =SUM(N25:N33) -> 192777183 | O35: =SUM(O25:O33) -> 20404805 | P35: =SUM(P25:P33) -> 136233760 | Q35: =SUM(Q25:Q33) -> 21072012 | R35: =SUM(R25:R33) -> 134536986 | S35: =SUM(S25:S33) -> 28533994 | ... Y35: =SUM(Y25:Y33) -> 0 | Z35: =+I35+J35 -> 1409911974
B37: Бошқарув Раис имзоси:
B39: Бош бухгалтер имзоси:
G42: =+'[8]Bank Assets Analysis'!$S$31 -> 83375035

Sheet Asset Classification
A1: АКТИВЛАР СИФАТИ БЎЙИЧА ТАСНИФЛАНИШИ ТЎҒРИСИДА ҲИСОБОТ | Z1: 10-жадвал
B3: =+'Asset quality'!B3 -> "Ўзсаноатқурилишибанк" АТБ | U3: =+'Asset quality'!Q3 -> 45289 | AB3: =+'Asset quality'!T3 -> минг. сўмда
A4: № | B4: Кўрсаткичлар | C4: Жами суммаси | D4: шундан, хорижий валютада (экв. сўмда) | E4: Стандарт | F4: шундан, хорижий валютада (экв. сўмда) | G4: Стандарт активлар бўйича яратилган захиралар (1%) | H4: шундан, хорижий валютада (экв. сўмда) | I4: Субстандарт | J4: шундан, хорижий валютада (экв. сўмда) | K4: Махсус захиралар (мин 10%) | L4: шундан, хорижий валютада (экв. сўмда) | M4: Қониқарсиз | N4: шундан, хорижий валютада (экв. сўмда) | O4: Махсус захиралар (мин 25%) | P4: шундан, хорижий валютада (экв. сўмда) | Q4: Шубҳали | R4: шундан, хорижий валютада (экв. сўмда) | S4: Махсус захиралар (мин 50%) | T4: шундан, хорижий валютада (экв. сўмда) | U4: Умидсиз | V4: шундан, хорижий валютада (экв. сўмда) | W4: Махсус захиралар (мин 100%) | X4: шундан, хорижий валютада (экв. сўмда) | Y4: Жами махсус захиралар суммаси | Z4: шундан, хорижий валютада (экв. сўмда) | AA4: ҳисобот ойида балансдан ташқари ҳисобдан чиқарилган кредитлар | AB4: ҳисобот ойида балансдан ташқари қайтган кредитлар суммаси
A5: (А) | B5: (Б) | C5: (В) | D5: (В1) | E5: (Г) | F5: (Г1) | G5: (Д) | H5: (Д1) | I5: (Е) | J5: (Е1) | K5: (Ж) | L5: (Ж1) | M5: (З) | N5: (З1) | O5: (И) | P5: (И1) | Q5: (К) | R5: (К1) | S5: (Л) | T5: (Л1) | U5: (М) | V5: (М1) | W5: (Н) | X5: (Н1) | Y5: О=Ж+И+Л+Н | Z5: (О1)=(Ж1)+(И1)+(Л1)+(Н1) | AA5: П | AB5: Р
B6: Мижозлар тури бўйича
A7: 1 | B7: Марказий банк | C7: =E7+I7+M7+Q7+U7 -> 0 | D7: =F7+J7+N7+R7+V7 -> 0 | Y7: =+W7+S7+O7+K7 -> 0 | Z7: =+X7+T7+P7+L7 -> 0 | AC7: =+'Aging Analysis'!C9 -> 0 | AD7: =+C7-AC7 -> 0
B8: шундан, таъминланмаган қисми | C8: =E8+I8+M8+Q8+U8 -> 0 | D8: =F8+J8+N8+R8+V8 -> 0 | Y8: =+W8+S8+O8+K8 -> 0 | Z8: =+X8+T8+P8+L8 -> 0
A9: 2 | B9: Бошқа банклар | C9: =E9+I9+M9+Q9+U9 -> 0 | D9: =F9+J9+N9+R9+V9 -> 0 | Y9: =+W9+S9+O9+K9 -> 0 | Z9: =+X9+T9+P9+L9 -> 0 | AC9: =+'Aging Analysis'!C10 -> 0 | AD9: =+C9-AC9 -> 0
B10: шундан, таъминланмаган қисми | C10: =E10+I10+M10+Q10+U10 -> 0 | D10: =F10+J10+N10+R10+V10 -> 0 | Y10: =+W10+S10+O10+K10 -> 0 | Z10: =+X10+T10+P10+L10 -> 0
A11: 3 | B11: Ҳукумат | C11: =E11+I11+M11+Q11+U11 -> 0 | D11: =F11+J11+N11+R11+V11 -> 0 | Y11: =+W11+S11+O11+K11 -> 0 | Z11: =+X11+T11+P11+L11 -> 0 | AC11: =+'Aging Analysis'!C11 -> 0 | AD11: =+C11-AC11 -> 0
B12: шундан, таъминланмаган қисми | C12: =E12+I12+M12+Q12+U12 -> 0 | D12: =F12+J12+N12+R12+V12 -> 0 | Y12: =+W12+S12+O12+K12 -> 0 | Z12: =+X12+T12+P12+L12 -> 0
A13: 4 | B13: Жисмоний шахслар | C13: =E13+I13+M13+Q13+U13 -> 7814492786 | D13: =F13+J13+N13+R13+V13 -> 0 | E13: 7625652230 | F13: 0 | G13: 76256522 | H13: 0 | I13: 147846643 | J13: 0 | K13: 14782772 | L13: 0 | M13: 19062315 | N13: 0 | O13: 4765590 | P13: 0 | Q13: 21931598 | R13: 0 | S13: 10965799 | T13: 0 | U13: 0 | V13: 0 | W13: 0 | X13: 0 | Y13: =+W13+S13+O13+K13 -> 30514161 | Z13: =+X13+T13+P13+L13 -> 0 | AA13: 1722561 | AB13: 1562025 | AC13: =+'Aging Analysis'!C12 -> 7814492786 | AD13: =+C13-AC13 -> 0
B14: шундан, таъминланмаган қисми | C14: =E14+I14+M14+Q14+U14 -> 0 | D14: =F14+J14+N14+R14+V14 -> 0 | E14: 0 | F14: 0 | G14: 0 | H14: 0 | I14: 0 | J14: 0 | K14: 0 | L14: 0 | M14: 0 | N14: 0 | O14: 0 | P14: 0 | Q14: 0 | R14: 0 | S14: 0 | T14: 0 | U14: 0 | V14: 0 | W14: 0 | X14: 0 | Y14: =+W14+S14+O14+K14 -> 0 | Z14: =+X14+T14+P14+L14 -> 0
A15: 5 | B15: Давлат корхоналари | C15: =E15+I15+M15+Q15+U15 -> 14102735134 | D15: =F15+J15+N15+R15+V15 -> 9901199639 | E15: 14098238653 | F15: 9901199639 | G15: 150448847 | H15: 0 | I15: 4496481 | J15: 0 | K15: 449648 | L15: 0 | M15: 0 | N15: 0 | O15: 0 | P15: 0 | Q15: 0 | R15: 0 | S15: 0 | T15: 0 | U15: 0 | V15: 0 | W15: 0 | X15: 0 | Y15: =+W15+S15+O15+K15 -> 449648 | Z15: =+X15+T15+P15+L15 -> 0 | AA15: 13166667 | AB15: 0 | AC15: =+'Aging Analysis'!C13 -> 14102735134 | AD15: =+C15-AC15 -> 0
B16: шундан, таъминланмаган қисми | C16: =E16+I16+M16+Q16+U16 -> 0 | D16: =F16+J16+N16+R16+V16 -> 0 | E16: 0 | F16: 0 | G16: 0 | H16: 0 | I16: 0 | J16: 0 | K16: 0 | L16: 0 | M16: 0 | N16: 0 | O16: 0 | P16: 0 | Q16: 0 | R16: 0 | S16: 0 | T16: 0 | U16: 0 | V16: 0 | W16: 0 | X16: 0 | Y16: =+W16+S16+O16+K16 -> 0 | Z16: =+X16+T16+P16+L16 -> 0
A17: 6 | B17: Қўшма ва чет эл капитали иштирокидаги корхоналар | C17: =E17+I17+M17+Q17+U17 -> 10296625676 | D17: =F17+J17+N17+R17+V17 -> 9399133697 | E17: 7302774414 | F17: 6846681407 | G17: 73027744 | H17: 0 | I17: 2936824466 | J17: 2498999738 | K17: 293682447 | L17: 249899974 | M17: 810756 | N17: 0 | O17: 202689 | P17: 0 | Q17: 46247548 | R17: 43484060 | S17: 23123774 | T17: 21742030 | U17: 9968492 | V17: 9968492 | W17: 9968492 | X17: 9968492 | Y17: =+W17+S17+O17+K17 -> 326977402 | Z17: =+X17+T17+P17+L17 -> 281610496 | AA17: 0 | AB17: 0 | AC17: =+'Aging Analysis'!C14 -> 10296625676 | AD17: =+C17-AC17 -> 0
B18: шундан, таъминланмаган қисми | C18: =E18+I18+M18+Q18+U18 -> 0 | D18: =F18+J18+N18+R18+V18 -> 0 | E18: 0 | F18: 0 | G18: 0 | H18: 0 | I18: 0 | J18: 0 | K18: 0 | L18: 0 | M18: 0 | N18: 0 | O18: 0 | P18: 0 | Q18: 0 | R18: 0 | S18: 0 | T18: 0 | U18: 0 | V18: 0 | W18: 0 | X18: 0 | Y18: =+W18+S18+O18+K18 -> 0 | Z18: =+X18+T18+P18+L18 -> 0
A19: 7 | B19: Хусусий корхоналар | C19: =E19+I19+M19+Q19+U19 -> 24784649546 | D19: =F19+J19+N19+R19+V19 -> 18619483630 | E19: 20465632095 | F19: 16120791382 | G19: 204656322 | H19: 0 | I19: 3151391318 | J19: 1742099388 | K19: 306015397 | L19: 164856170 | M19: 484458884 | N19: 263138435 | O19: 121114721 | P19: 65784610 | Q19: 665896409 | R19: 488765692 | S19: 332948207 | T19: 244382848 | U19: 17270840 | V19: 4688733 | W19: 17270840 | X19: 4688733 | Y19: =+W19+S19+O19+K19 -> 777349165 | Z19: =+X19+T19+P19+L19 -> 479712361 | AA19: 276036951 | AB19: 14399898 | AC19: =+'Aging Analysis'!C15 -> 24784649546 | AD19: =+C19-AC19 -> 0
B20: шундан, таъминланмаган қисми | C20: =E20+I20+M20+Q20+U20 -> 0 | D20: =F20+J20+N20+R20+V20 -> 0 | E20: 0 | F20: 0 | G20: 0 | H20: 0 | I20: 0 | J20: 0 | K20: 0 | L20: 0 | M20: 0 | N20: 0 | O20: 0 | P20: 0 | Q20: 0 | R20: 0 | S20: 0 | T20: 0 | U20: 0 | V20: 0 | W20: 0 | X20: 0 | Y20: =+W20+S20+O20+K20 -> 0 | Z20: =+X20+T20+P20+L20 -> 0
A21: 8 | B21: Фермер хўжалиги | C21: =E21+I21+M21+Q21+U21 -> 121348475 | D21: =F21+J21+N21+R21+V21 -> 93143676 | E21: 52486428 | F21: 31214867 | G21: 524864 | H21: 0 | I21: 51917814 | J21: 48554449 | K21: 5191781 | L21: 4855445 | M21: 1534407 | N21: 0 | O21: 383602 | P21: 0 | Q21: 15409826 | R21: 13374360 | S21: 7704913 | T21: 6687180 | U21: 0 | V21: 0 | W21: 0 | X21: 0 | Y21: =+W21+S21+O21+K21 -> 13280296 | Z21: =+X21+T21+P21+L21 -> 11542625 | AA21: 2025920 | AB21: 647389 | AC21: =+'Aging Analysis'!C16 -> 121348475 | AD21: =+C21-AC21 -> 0
B22: шундан, таъминланмаган қисми | C22: =E22+I22+M22+Q22+U22 -> 0 | D22: =F22+J22+N22+R22+V22 -> 0 | E22: 0 | F22: 0 | G22: 0 | H22: 0 | I22: 0 | J22: 0 | K22: 0 | L22: 0 | M22: 0 | N22: 0 | O22: 0 | P22: 0 | Q22: 0 | R22: 0 | S22: 0 | T22: 0 | U22: 0 | V22: 0 | W22: 0 | X22: 0 | Y22: =+W22+S22+O22+K22 -> 0 | Z22: =+X22+T22+P22+L22 -> 0
A23: 9 | B23: Нобанк молиявий институтлар | C23: =E23+I23+M23+Q23+U23 -> 2946729 | D23: =F23+J23+N23+R23+V23 -> 0 | E23: 2500000 | F23: 0 | G23: 25000 | H23: 0 | I23: 0 | J23: 0 | K23: 0 | L23: 0 | M23: 0 | N23: 0 | O23: 0 | P23: 0 | Q23: 446729 | R23: 0 | S23: 223364 | T23: 0 | U23: 0 | V23: 0 | W23: 0 | X23: 0 | Y23: =+W23+S23+O23+K23 -> 223364 | Z23: =+X23+T23+P23+L23 -> 0 | AA23: 0 | AB23: 0 | AC23: =+'Aging Analysis'!C17 -> 2946729 | AD23: =+C23-AC23 -> 0
B24: шундан, таъминланмаган қисми | C24: =E24+I24+M24+Q24+U24 -> 0 | D24: =F24+J24+N24+R24+V24 -> 0 | E24: 0 | F24: 0 | G24: 0 | H24: 0 | I24: 0 | J24: 0 | K24: 0 | L24: 0 | M24: 0 | N24: 0 | O24: 0 | P24: 0 | Q24: 0 | R24: 0 | S24: 0 | T24: 0 | U24: 0 | V24: 0 | W24: 0 | X24: 0 | Y24: =+W24+S24+O24+K24 -> 0 | Z24: =+X24+T24+P24+L24 -> 0
A25: 10 | B25: Нодавлат нотижорат ташкилотлар | C25: =E25+I25+M25+Q25+U25 -> 1605566 | D25: =F25+J25+N25+R25+V25 -> 0 | E25: 1467441 | F25: 0 | G25: 14674 | H25: 0 | I25: 0 | J25: 0 | K25: 0 | L25: 0 | M25: 138125 | N25: 0 | O25: 34531 | P25: 0 | Q25: 0 | R25: 0 | S25: 0 | T25: 0 | U25: 0 | V25: 0 | W25: 0 | X25: 0 | Y25: =+W25+S25+O25+K25 -> 34531 | Z25: =+X25+T25+P25+L25 -> 0 | AA25: 0 | AB25: 0 | AC25: =+'Aging Analysis'!C18 -> 1605566 | AD25: =+C25-AC25 -> 0
B26: шундан, таъминланмаган қисми | C26: =E26+I26+M26+Q26+U26 -> 0 | D26: =F26+J26+N26+R26+V26 -> 0 | Y26: =+W26+S26+O26+K26 -> 0 | Z26: =+X26+T26+P26+L26 -> 0
A27: 11 | B27: Бюджет ташкилотлари | C27: =E27+I27+M27+Q27+U27 -> 0 | D27: =F27+J27+N27+R27+V27 -> 0 | Y27: =+W27+S27+O27+K27 -> 0 | Z27: =+X27+T27+P27+L27 -> 0 | AA27: 0 | AB27: 0 | AC27: =+'Aging Analysis'!C19 -> 0 | AD27: =+C27-AC27 -> 0
B28: шундан, таъминланмаган қисми | C28: =E28+I28+M28+Q28+U28 -> 0 | D28: =F28+J28+N28+R28+V28 -> 0 | Y28: =+W28+S28+O28+K28 -> 0 | Z28: =+X28+T28+P28+L28 -> 0
A29: 12 | B29: Бошқалар | C29: =E29+I29+M29+Q29+U29 -> 0 | D29: =F29+J29+N29+R29+V29 -> 0 | Y29: =+W29+S29+O29+K29 -> 0 | Z29: =+X29+T29+P29+L29 -> 0 | AA29: 1800000 | AB29: 0 | AC29: =+'Aging Analysis'!C20 -> 0 | AD29: =+C29-AC29 -> 0
B30: шундан, таъминланмаган қисми | C30: =E30+I30+M30+Q30+U30 -> 0 | D30: =F30+J30+N30+R30+V30 -> 0 | Y30: =+W30+S30+O30+K30 -> 0 | Z30: =+X30+T30+P30+L30 -> 0
A31: 13 | B31: Жами кредит ва лизинг суммаси | C31: =+C7+C9+C11+C13+C15+C17+C19+C21+C23+C25+C27+C29 -> 57124403912 | D31: =+D7+D9+D11+D13+D15+D17+D19+D21+D23+D25+D27+D29 -> 38012960642 | E31: =+E7+E9+E11+E13+E15+E17+E19+E21+E23+E25+E27+E29 -> 49548751261 | F31: =+F7+F9+F11+F13+F15+F17+F19+F21+F23+F25+F27+F29 -> 32899887295 | G31: =+G7+G9+G11+G13+G15+G17+G19+G21+G23+G25+G27+G29 -> 504953973 | H31: =+H7+H9+H11+H13+H15+H17+H19+H21+H23+H25+H27+H29 -> 0 | I31: =+I7+I9+I11+I13+I15+I17+I19+I21+I23+I25+I27+I29 -> 6292476722 | J31: =+J7+J9+J11+J13+J15+J17+J19+J21+J23+J25+J27+J29 -> 4289653575 | ... AB31: =+AB7+AB9+AB11+AB13+AB15+AB17+AB19+AB21+AB23+AB25+AB27+AB29 -> 16609312 | AC31: =+'Loans Receivable'!C85 -> 57124403912 | AD31: =+C31-AC31 -> 0
B32: шундан, таъминланмаган қисми | C32: =+C8+C10+C12+C14+C16+C18+C20+C22+C24+C26+C28+C30 -> 0 | D32: =+D8+D10+D12+D14+D16+D18+D20+D22+D24+D26+D28+D30 -> 0 | E32: =+E8+E10+E12+E14+E16+E18+E20+E22+E24+E26+E28+E30 -> 0 | F32: =+F8+F10+F12+F14+F16+F18+F20+F22+F24+F26+F28+F30 -> 0 | G32: =+G8+G10+G12+G14+G16+G18+G20+G22+G24+G26+G28+G30 -> 0 | H32: =+H8+H10+H12+H14+H16+H18+H20+H22+H24+H26+H28+H30 -> 0 | I32: =+I8+I10+I12+I14+I16+I18+I20+I22+I24+I26+I28+I30 -> 0 | J32: =+J8+J10+J12+J14+J16+J18+J20+J22+J24+J26+J28+J30 -> 0 | ... Z32: =+Z8+Z10+Z12+Z14+Z16+Z18+Z20+Z22+Z24+Z26+Z28+Z30 -> 0
B33: Иқтисодиёт соҳалари бўйича
A35: 14 | B35: Саноат | C35: =E35+I35+M35+Q35+U35 -> 29912501071 | D35: =F35+J35+N35+R35+V35 -> 25149127213 | E35: 25737314100 | F35: 21765633152 | G35: 266839601 | H35: 0 | I35: 3674332106 | J35: 2980287888 | K35: 358079441 | L35: 288675019 | M35: 201641115 | N35: 137499976 | O35: 50410279 | P35: 34374994 | Q35: 289245258 | R35: 255737705 | S35: 144622629 | T35: 127868853 | U35: 9968492 | V35: 9968492 | W35: 9968492 | X35: 9968492 | Y35: =+W35+S35+O35+K35 -> 563080841 | Z35: =+X35+T35+P35+L35 -> 460887358 | AA35: 119994736 | AB35: 3808526 | AC35: =+'Aging Analysis'!C25 -> 29912501071 | AD35: =+C35-AC35 -> 0
B36: шундан, таъминланмаган қисми | C36: =E36+I36+M36+Q36+U36 -> 0 | D36: =F36+J36+N36+R36+V36 -> 0 | E36: 0 | F36: 0 | G36: 0 | H36: 0 | I36: 0 | J36: 0 | K36: 0 | L36: 0 | M36: 0 | N36: 0 | O36: 0 | P36: 0 | Q36: 0 | R36: 0 | S36: 0 | T36: 0 | U36: 0 | V36: 0 | W36: 0 | X36: 0 | Y36: =+W36+S36+O36+K36 -> 0 | Z36: =+X36+T36+P36+L36 -> 0
A37: 15 | B37: Қишлоқ хўжалиги | C37: =E37+I37+M37+Q37+U37 -> 4926336219 | D37: =F37+J37+N37+R37+V37 -> 2565841116 | E37: 3549549874 | F37: 2221465659 | G37: 35495499 | H37: 0 | I37: 1099095807 | J37: 160927246 | K37: 110139615 | L37: 16092725 | M37: 109207519 | N37: 20364628 | O37: 27301880 | P37: 5091157 | Q37: 168483019 | R37: 163083583 | S37: 84241510 | T37: 81541792 | U37: 0 | V37: 0 | W37: 0 | X37: 0 | Y37: =+W37+S37+O37+K37 -> 221683005 | Z37: =+X37+T37+P37+L37 -> 102725674 | AA37: 78099323 | AB37: 2035699 | AC37: =+'Aging Analysis'!C26 -> 4926336219 | AD37: =+C37-AC37 -> 0
B38: шундан, таъминланмаган қисми | C38: =E38+I38+M38+Q38+U38 -> 0 | D38: =F38+J38+N38+R38+V38 -> 0 | E38: 0 | F38: 0 | G38: 0 | H38: 0 | I38: 0 | J38: 0 | K38: 0 | L38: 0 | M38: 0 | N38: 0 | O38: 0 | P38: 0 | Q38: 0 | R38: 0 | S38: 0 | T38: 0 | U38: 0 | V38: 0 | W38: 0 | X38: 0 | Y38: =+W38+S38+O38+K38 -> 0 | Z38: =+X38+T38+P38+L38 -> 0
A39: 16 | B39: Транспорт ва коммуникация | C39: =E39+I39+M39+Q39+U39 -> 3968113322 | D39: =F39+J39+N39+R39+V39 -> 3847597829 | E39: 3879856301 | F39: 3779257642 | G39: 38798563 | H39: 0 | I39: 19500899 | J39: 17908156 | K39: 1950090 | L39: 1790816 | M39: 63274014 | N39: 50432031 | O39: 15818503 | P39: 12608008 | Q39: 3800001 | R39: 0 | S39: 1900001 | T39: 0 | U39: 1682107 | V39: 0 | W39: 1682107 | X39: 0 | Y39: =+W39+S39+O39+K39 -> 21350701 | Z39: =+X39+T39+P39+L39 -> 14398824 | AA39: 2990000 | AB39: 299102 | AC39: =+'Aging Analysis'!C27 -> 3968113322 | AD39: =+C39-AC39 -> 0
B40: шундан, таъминланмаган қисми | C40: =E40+I40+M40+Q40+U40 -> 0 | D40: =F40+J40+N40+R40+V40 -> 0 | E40: 0 | F40: 0 | G40: 0 | H40: 0 | I40: 0 | J40: 0 | K40: 0 | L40: 0 | M40: 0 | N40: 0 | O40: 0 | P40: 0 | Q40: 0 | R40: 0 | S40: 0 | T40: 0 | U40: 0 | V40: 0 | W40: 0 | X40: 0 | Y40: =+W40+S40+O40+K40 -> 0 | Z40: =+X40+T40+P40+L40 -> 0
A41: 17 | B41: Қурилиш соҳаси | C41: =E41+I41+M41+Q41+U41 -> 1311758376 | D41: =F41+J41+N41+R41+V41 -> 942129303 | E41: 1168102135 | F41: 903217007 | G41: 11681021 | H41: 0 | I41: 48928444 | J41: 14901457 | K41: 4892844 | L41: 1490146 | M41: 42918452 | N41: 1772113 | O41: 10729613 | P41: 443028 | Q41: 51809345 | R41: 22238726 | S41: 25904673 | T41: 11119363 | U41: 0 | V41: 0 | W41: 0 | X41: 0 | Y41: =+W41+S41+O41+K41 -> 41527130 | Z41: =+X41+T41+P41+L41 -> 13052537 | AA41: 52430587 | AB41: 0 | AC41: =+'Aging Analysis'!C28 -> 1311758376 | AD41: =+C41-AC41 -> 0
B42: шундан, таъминланмаган қисми | C42: =E42+I42+M42+Q42+U42 -> 0 | D42: =F42+J42+N42+R42+V42 -> 0 | E42: 0 | F42: 0 | G42: 0 | H42: 0 | I42: 0 | J42: 0 | K42: 0 | L42: 0 | M42: 0 | N42: 0 | O42: 0 | P42: 0 | Q42: 0 | R42: 0 | S42: 0 | T42: 0 | U42: 0 | V42: 0 | W42: 0 | X42: 0 | Y42: =+W42+S42+O42+K42 -> 0 | Z42: =+X42+T42+P42+L42 -> 0
A43: 18 | B43: Савдо ва умумий хизмат | C43: =E43+I43+M43+Q43+U43 -> 3466439372 | D43: =F43+J43+N43+R43+V43 -> 2756436726 | E43: 2960164849 | F43: 2404774456 | G43: 29601648 | H43: 0 | I43: 241286988 | J43: 200437929 | K43: 24128699 | L43: 20043793 | M43: 60676560 | N43: 52568517 | O43: 15169140 | P43: 13142129 | Q43: 193760975 | R43: 98655824 | S43: 96880488 | T43: 49327912 | U43: 10550000 | V43: 0 | W43: 10550000 | X43: 0 | Y43: =+W43+S43+O43+K43 -> 146728327 | Z43: =+X43+T43+P43+L43 -> 82513834 | AA43: 16096874 | AB43: 8896959 | AC43: =+'Aging Analysis'!C29 -> 3466439372 | AD43: =+C43-AC43 -> 0
B44: шундан, таъминланмаган қисми | C44: =E44+I44+M44+Q44+U44 -> 0 | D44: =F44+J44+N44+R44+V44 -> 0 | E44: 0 | F44: 0 | G44: 0 | H44: 0 | I44: 0 | J44: 0 | K44: 0 | L44: 0 | M44: 0 | N44: 0 | O44: 0 | P44: 0 | Q44: 0 | R44: 0 | S44: 0 | T44: 0 | U44: 0 | V44: 0 | W44: 0 | X44: 0 | Y44: =+W44+S44+O44+K44 -> 0 | Z44: =+X44+T44+P44+L44 -> 0
A45: 19 | B45: Моддий ва техник таъминотни ривожлантириш | C45: =E45+I45+M45+Q45+U45 -> 2157776262 | D45: =F45+J45+N45+R45+V45 -> 300207520 | E45: 2139811852 | F45: 295271972 | G45: 21398119 | H45: 0 | I45: 12647724 | J45: 0 | K45: 1264772 | L45: 0 | M45: 246815 | N45: 246815 | O45: 61704 | P45: 61704 | Q45: 31138 | R45: 0 | S45: 15569 | T45: 0 | U45: 5038733 | V45: 4688733 | W45: 5038733 | X45: 4688733 | Y45: =+W45+S45+O45+K45 -> 6380778 | Z45: =+X45+T45+P45+L45 -> 4750437 | AA45: 6820513 | AB45: 0 | AC45: =+'Aging Analysis'!C30 -> 2157776262 | AD45: =+C45-AC45 -> 0
B46: шундан, таъминланмаган қисми | C46: =E46+I46+M46+Q46+U46 -> 0 | D46: =F46+J46+N46+R46+V46 -> 0 | E46: 0 | F46: 0 | G46: 0 | H46: 0 | I46: 0 | J46: 0 | K46: 0 | L46: 0 | M46: 0 | N46: 0 | O46: 0 | P46: 0 | Q46: 0 | R46: 0 | S46: 0 | T46: 0 | U46: 0 | V46: 0 | W46: 0 | X46: 0 | Y46: =+W46+S46+O46+K46 -> 0 | Z46: =+X46+T46+P46+L46 -> 0
A47: 20 | B47: Уй-жой коммунал хизмати | C47: =E47+I47+M47+Q47+U47 -> 1605566 | D47: =F47+J47+N47+R47+V47 -> 0 | E47: 1467441 | F47: 0 | G47: 14674 | H47: 0 | I47: 0 | J47: 0 | K47: 0 | L47: 0 | M47: 138125 | N47: 0 | O47: 34531 | P47: 0 | Q47: 0 | R47: 0 | S47: 0 | T47: 0 | U47: 0 | V47: 0 | W47: 0 | X47: 0 | Y47: =+W47+S47+O47+K47 -> 34531 | Z47: =+X47+T47+P47+L47 -> 0 | AA47: 0 | AB47: 0 | AC47: =+'Aging Analysis'!C31 -> 1605566 | AD47: =+C47-AC47 -> 0
B48: шундан, таъминланмаган қисми | C48: =E48+I48+M48+Q48+U48 -> 0 | D48: =F48+J48+N48+R48+V48 -> 0 | E48: 0 | F48: 0 | G48: 0 | H48: 0 | I48: 0 | J48: 0 | K48: 0 | L48: 0 | M48: 0 | N48: 0 | O48: 0 | P48: 0 | Q48: 0 | R48: 0 | S48: 0 | T48: 0 | U48: 0 | V48: 0 | W48: 0 | X48: 0 | Y48: =+W48+S48+O48+K48 -> 0 | Z48: =+X48+T48+P48+L48 -> 0
A49: 21 | B49: Бошқа соҳалар | C49: =E49+I49+M49+Q49+U49 -> 3565380938 | D49: =F49+J49+N49+R49+V49 -> 2451620935 | E49: 2486832479 | F49: 1530267407 | G49: 24868326 | H49: 0 | I49: 1048838111 | J49: 915190899 | K49: 104883812 | L49: 91519090 | M49: 8839572 | N49: 254355 | O49: 2209893 | P49: 63590 | Q49: 20870776 | R49: 5908274 | S49: 10435388 | T49: 2954138 | U49: 0 | V49: 0 | W49: 0 | X49: 0 | Y49: =+W49+S49+O49+K49 -> 117529093 | Z49: =+X49+T49+P49+L49 -> 94536818 | AA49: 16597505 | AB49: 7001 | AC49: =+'Aging Analysis'!C32 -> 3565380938 | AD49: =+C49-AC49 -> 0
B50: шундан, таъминланмаган қисми | C50: =E50+I50+M50+Q50+U50 -> 0 | D50: =F50+J50+N50+R50+V50 -> 0 | E50: 0 | F50: 0 | G50: 0 | H50: 0 | I50: 0 | J50: 0 | K50: 0 | L50: 0 | M50: 0 | N50: 0 | O50: 0 | P50: 0 | Q50: 0 | R50: 0 | S50: 0 | T50: 0 | U50: 0 | V50: 0 | W50: 0 | X50: 0 | Y50: =+W50+S50+O50+K50 -> 0 | Z50: =+X50+T50+P50+L50 -> 0
A51: 22 | B51: Жисмоний шахслар | C51: =E51+I51+M51+Q51+U51 -> 7814492786 | D51: =F51+J51+N51+R51+V51 -> 0 | E51: 7625652230 | F51: 0 | G51: 76256522 | H51: 0 | I51: 147846643 | J51: 0 | K51: 14782772 | L51: 0 | M51: 19062315 | N51: 0 | O51: 4765590 | P51: 0 | Q51: 21931598 | R51: 0 | S51: 10965799 | T51: 0 | U51: 0 | V51: 0 | W51: 0 | X51: 0 | Y51: =+W51+S51+O51+K51 -> 30514161 | Z51: =+X51+T51+P51+L51 -> 0 | AA51: 1722561 | AB51: 1562025 | AC51: =+'Aging Analysis'!C33 -> 7814492786 | AD51: =+C51-AC51 -> 0
B52: шундан, таъминланмаган қисми | C52: =E52+I52+M52+Q52+U52 -> 0 | D52: =F52+J52+N52+R52+V52 -> 0 | E52: 0 | G52: 0 | Y52: =+W52+S52+O52+K52 -> 0 | Z52: =+X52+T52+P52+L52 -> 0
A53: 23 | B53: Жами кредит ва лизинг суммаси | C53: =+C35+C37+C39+C41+C43+C45+C47+C49+C51 -> 57124403912 | D53: =+D35+D37+D39+D41+D43+D45+D47+D49+D51 -> 38012960642 | E53: =+E35+E37+E39+E41+E43+E45+E47+E49+E51 -> 49548751261 | F53: =+F35+F37+F39+F41+F43+F45+F47+F49+F51 -> 32899887295 | G53: =+G35+G37+G39+G41+G43+G45+G47+G49+G51 -> 504953973 | H53: =+H35+H37+H39+H41+H43+H45+H47+H49+H51 -> 0 | I53: =+I35+I37+I39+I41+I43+I45+I47+I49+I51 -> 6292476722 | J53: =+J35+J37+J39+J41+J43+J45+J47+J49+J51 -> 4289653575 | ... AB53: =+AB35+AB37+AB39+AB41+AB43+AB45+AB47+AB49+AB51 -> 16609312 | AC53: =+'Aging Analysis'!C35 -> 57124403912 | AD53: =+C53-AC53 -> 0
B54: шундан, таъминланмаган қисми | C54: =E54+I54+M54+Q54+U54 -> 0 | D54: =+D36+D38+D40+D42+D44+D46+D48+D50+D52 -> 0 | E54: 0 | F54: 0 | G54: =+G36+G38+G40+G42+G44+G46+G48+G50+G52 -> 0 | H54: =+H36+H38+H40+H42+H44+H46+H48+H50+H52 -> 0 | I54: =+I36+I38+I40+I42+I44+I46+I48+I50+I52 -> 0 | J54: =+J36+J38+J40+J42+J44+J46+J48+J50+J52 -> 0 | K54: =+K36+K38+K40+K42+K44+K46+K48+K50+K52 -> 0 | L54: =+L36+L38+L40+L42+L44+L46+L48+L50+L52 -> 0 | M54: =+M36+M38+M40+M42+M44+M46+M48+M50+M52 -> 0 | N54: =+N36+N38+N40+N42+N44+N46+N48+N50+N52 -> 0 | ... AB54: =+AB36+AB38+AB40+AB42+AB44+AB46+AB48+AB50+AB52 -> 0
B55: Ҳудудлар қирқимида
A57: 24 | B57: Қорақалпоғистон Республикаси | C57: =E57+I57+M57+Q57+U57 -> 1932270015 | D57: =F57+J57+N57+R57+V57 -> 857624905 | E57: 1874411554 | F57: 824920399 | G57: 11072659 | H57: 0 | I57: 43250729 | J57: 21635388 | K57: 4322768 | L57: 2163539 | M57: 2227600 | N57: 0 | O57: 556900 | P57: 0 | Q57: 12380132 | R57: 11069118 | S57: 6190066 | T57: 5534559 | U57: 0 | V57: 0 | W57: 0 | X57: 0 | Y57: =+W57+S57+O57+K57 -> 11069734 | Z57: =+X57+T57+P57+L57 -> 7698098 | AA57: 92665 | AB57: 297652
A58: 25 | B58: Андижон вилояти | C58: =E58+I58+M58+Q58+U58 -> 1624354054 | D58: =F58+J58+N58+R58+V58 -> 1024737071 | E58: 1528489311 | F58: 979420203 | G58: 10254993 | H58: 0 | I58: 44728038 | J58: 7015679 | K58: 4472804 | L58: 701568 | M58: 4727552 | N58: 2539485 | O58: 1181888 | P58: 634871 | Q58: 46409153 | R58: 35761704 | S58: 23204576 | T58: 17880852 | U58: 0 | V58: 0 | W58: 0 | X58: 0 | Y58: =+W58+S58+O58+K58 -> 28859268 | Z58: =+X58+T58+P58+L58 -> 19217291 | AA58: 1523713 | AB58: 872098
A59: 26 | B59: Бухоро вилояти | C59: =E59+I59+M59+Q59+U59 -> 1543780452 | D59: =F59+J59+N59+R59+V59 -> 1043441361 | E59: 1230872943 | F59: 775653188 | G59: 11745891 | H59: 0 | I59: 146407337 | J59: 130296364 | K59: 14640734 | L59: 13029636 | M59: 71220860 | N59: 55655823 | O59: 17805215 | P59: 13913956 | Q59: 90240580 | R59: 77147253 | S59: 45120290 | T59: 38573627 | U59: 5038732 | V59: 4688733 | W59: 5038732 | X59: 4688733 | Y59: =+W59+S59+O59+K59 -> 82604971 | Z59: =+X59+T59+P59+L59 -> 70205952 | AA59: 30735961 | AB59: 3862733
A60: 27 | B60: Жиззах вилояти | C60: =E60+I60+M60+Q60+U60 -> 1588226570 | D60: =F60+J60+N60+R60+V60 -> 1189724174 | E60: 1570281102 | F60: 1176863602 | G60: 10609211 | H60: 0 | I60: 10567813 | J60: 7482668 | K60: 1056781 | L60: 748267 | M60: 4615651 | N60: 3800341 | O60: 1153913 | P60: 950085 | Q60: 2762004 | R60: 1577563 | S60: 1381002 | T60: 788782 | U60: 0 | V60: 0 | W60: 0 | X60: 0 | Y60: =+W60+S60+O60+K60 -> 3591696 | Z60: =+X60+T60+P60+L60 -> 2487134 | AA60: 4830013 | AB60: 500961
A61: 28 | B61: Қашқадарё вилояти | C61: =E61+I61+M61+Q61+U61 -> 1376806860 | D61: =F61+J61+N61+R61+V61 -> 240268756 | E61: 1115866566 | F61: 218807565 | G61: 14498781 | H61: 0 | I61: 212723119 | J61: 15284814 | K61: 21502346 | L61: 1528481 | M61: 40705179 | N61: 158035 | O61: 10176295 | P61: 39509 | Q61: 7511996 | R61: 6018342 | S61: 3755998 | T61: 3009171 | U61: 0 | V61: 0 | W61: 0 | X61: 0 | Y61: =+W61+S61+O61+K61 -> 35434639 | Z61: =+X61+T61+P61+L61 -> 4577161 | AA61: 1650003 | AB61: 44421
A62: 29 | B62: Навоий вилояти | C62: =E62+I62+M62+Q62+U62 -> 1374148502 | D62: =F62+J62+N62+R62+V62 -> 642939126 | E62: 1277764880 | F62: 595764381 | G62: 11790777 | H62: 0 | I62: 91358258 | J62: 47174745 | K62: 9135826 | L62: 4717475 | M62: 1675898 | N62: 0 | O62: 418975 | P62: 0 | Q62: 3349466 | R62: 0 | S62: 1674733 | T62: 0 | U62: 0 | V62: 0 | W62: 0 | X62: 0 | Y62: =+W62+S62+O62+K62 -> 11229534 | Z62: =+X62+T62+P62+L62 -> 4717475 | AA62: 0 | AB62: 13426
A63: 30 | B63: Наманган вилояти | C63: =E63+I63+M63+Q63+U63 -> 757090397 | D63: =F63+J63+N63+R63+V63 -> 429761206 | E63: 587397636 | F63: 261323790 | G63: 4925718 | H63: 0 | I63: 165531267 | J63: 164275922 | K63: 16553127 | L63: 16427592 | M63: 3838715 | N63: 3838715 | O63: 959679 | P63: 959679 | Q63: 322779 | R63: 322779 | S63: 161389 | T63: 161389 | U63: 0 | V63: 0 | W63: 0 | X63: 0 | Y63: =+W63+S63+O63+K63 -> 17674195 | Z63: =+X63+T63+P63+L63 -> 17548660 | AA63: 13277367 | AB63: 427677
A64: 31 | B64: Самарқанд вилояти | C64: =E64+I64+M64+Q64+U64 -> 2420982190 | D64: =F64+J64+N64+R64+V64 -> 1648522478 | E64: 2264138921 | F64: 1518504487 | G64: 12742160 | H64: 0 | I64: 108600204 | J64: 96351118 | K64: 10860020 | L64: 9635112 | M64: 18060682 | N64: 15799240 | O64: 4515171 | P64: 3949810 | Q64: 7981783 | R64: 7899141 | S64: 3990891 | T64: 3949570 | U64: 22200600 | V64: 9968492 | W64: 22200600 | X64: 9968492 | Y64: =+W64+S64+O64+K64 -> 41566682 | Z64: =+X64+T64+P64+L64 -> 27502984 | AA64: 155244 | AB64: 6345
A65: 32 | B65: Сурхондарё вилояти | C65: =E65+I65+M65+Q65+U65 -> 999816047 | D65: =F65+J65+N65+R65+V65 -> 259963334 | E65: 792529739 | F65: 85767529 | G65: 5848868 | H65: 0 | I65: 92595748 | J65: 68026598 | K65: 9259575 | L65: 6802660 | M65: 8841301 | N65: 2718723 | O65: 2210325 | P65: 679681 | Q65: 105849259 | R65: 103450484 | S65: 52924630 | T65: 51725242 | U65: 0 | V65: 0 | W65: 0 | X65: 0 | Y65: =+W65+S65+O65+K65 -> 64394530 | Z65: =+X65+T65+P65+L65 -> 59207583 | AA65: 81517653 | AB65: 3909077
A66: 33 | B66: Сирдарё вилояти | C66: =E66+I66+M66+Q66+U66 -> 2265852466 | D66: =F66+J66+N66+R66+V66 -> 1540817976 | E66: 610269867 | F66: 318117594 | G66: 18700461 | H66: 0 | I66: 1542004957 | J66: 1185870898 | K66: 154200496 | L66: 118587090 | M66: 75916115 | N66: 24677540 | O66: 18979029 | P66: 6169385 | Q66: 37661527 | R66: 12151944 | S66: 18830763 | T66: 6075972 | U66: 0 | V66: 0 | W66: 0 | X66: 0 | Y66: =+W66+S66+O66+K66 -> 192010288 | Z66: =+X66+T66+P66+L66 -> 130832447 | AA66: 25708968 | AB66: 32193
A67: 34 | B67: Тошкент шаҳар | C67: =E67+I67+M67+Q67+U67 -> 32506091616 | D67: =F67+J67+N67+R67+V67 -> 23667576837 | E67: 28730287318 | F67: 21164359918 | G67: 349522662 | H67: 0 | I67: 3338153844 | J67: 2241537435 | K67: 324462027 | L67: 214799974 | M67: 187359052 | N67: 84699946 | O67: 46839761 | P67: 21174987 | Q67: 250291402 | R67: 176979538 | S67: 125145703 | T67: 88489770 | U67: 0 | V67: 0 | W67: 0 | X67: 0 | Y67: =+W67+S67+O67+K67 -> 496447491 | Z67: =+X67+T67+P67+L67 -> 324464731 | AA67: 106385984 | AB67: 3456641
A68: 35 | B68: Тошкент вилояти | C68: =E68+I68+M68+Q68+U68 -> 3919137898 | D68: =F68+J68+N68+R68+V68 -> 2325748995 | E68: 3667550057 | F68: 2140950655 | G68: 23872359 | H68: 0 | I68: 173763559 | J68: 140532042 | K68: 17376356 | L68: 14053204 | M68: 49304323 | N68: 43616456 | O68: 12326081 | P68: 10904114 | Q68: 28519959 | R68: 649842 | S68: 14259980 | T68: 324921 | U68: 0 | V68: 0 | W68: 0 | X68: 0 | Y68: =+W68+S68+O68+K68 -> 43962417 | Z68: =+X68+T68+P68+L68 -> 25282239 | AA68: 1048549 | AB68: 9497
... A70: 37 | B70: Хоразм вилояти | C70: =E70+I70+M70+Q70+U70 -> 1160551535 | D70: =F70+J70+N70+R70+V70 -> 759251326 | E70: 888287892 | F70: 619471000 | G70: 7014727 | H70: 0 | I70: 141666238 | J70: 39649655 | K70: 14166624 | L70: 3964966 | M70: 13086240 | N70: 8332774 | O70: 3271571 | P70: 2083194 | Q70: 117511165 | R70: 91797897 | S70: 58755583 | T70: 45898949 | U70: 0 | V70: 0 | W70: 0 | X70: 0 | Y70: =+W70+S70+O70+K70 -> 76193778 | Z70: =+X70+T70+P70+L70 -> 51947109 | AA70: 17761529 | AB70: 2710360
A71: 38 | B71: Жами кредит ва лизинг суммаси | C71: =SUM(C57:C70) -> 57124403912 | D71: =SUM(D57:D70) -> 38012960642 | E71: =SUM(E57:E70) -> 49548751261 | F71: =SUM(F57:F70) -> 32899887295 | G71: =SUM(G57:G70) -> 504953973 | H71: =SUM(H57:H70) -> 0 | I71: =SUM(I57:I70) -> 6292476722 | J71: =SUM(J57:J70) -> 4289653575 | ... AB71: =SUM(AB57:AB70) -> 16609312 | AC71: =+'Loans Receivable'!C85 -> 57124403912 | AD71: =+C71-AC71 -> 0
A72: 39 | B72: Бошқа таснифланган активлар | C72: =E72+I72+M72+Q72+U72 -> 14832384791 | D72: =F72+J72+N72+R72+V72 -> 0 | E72: ='Asset quality'!D12+'Asset quality'!D17+'Asset quality'!D47+'Asset quality'!D48+'Asset quality'!D49+'Asset quality'!D50+'Asset quality'!D53+'Asset quality'!D54+'Asset quality'!D58+'Asset quality'!D60+'Asset quality'!D62 -> 13100409935 | G72: ='Asset quality'!P12+'Asset quality'!P17+'Asset quality'!P47+'Asset quality'!P48+'Asset quality'!P49+'Asset quality'!P50+'Asset quality'!P53+'Asset quality'!P54+'Asset quality'!P58+'Asset quality'!P60+'Asset quality'!P62+9 -> 126313827 | I72: ='Asset quality'!E12+'Asset quality'!E17+'Asset quality'!E47+'Asset quality'!E48+'Asset quality'!E49+'Asset quality'!E50+'Asset quality'!E53+'Asset quality'!E54+'Asset quality'!E58+'Asset quality'!E60+'Asset quality'!E62 -> 892260841 | K72: ='Asset quality'!Q12+'Asset quality'!Q17+'Asset quality'!Q47+'Asset quality'!Q48+'Asset quality'!Q49+'Asset quality'!Q50+'Asset quality'!Q53+'Asset quality'!Q54+'Asset quality'!Q58+'Asset quality'!Q60+'Asset quality'!Q62 -> 175966885 | M72: ='Asset quality'!F12+'Asset quality'!F17+'Asset quality'!F47+'Asset quality'!F48+'Asset quality'!F49+'Asset quality'!F50+'Asset quality'!F53+'Asset quality'!F54+'Asset quality'!F58+'Asset quality'!F60+'Asset quality'!F62 -> 91982157 | O72: ='Asset quality'!R12+'Asset quality'!R17+'Asset quality'!R47+'Asset quality'!R48+'Asset quality'!R49+'Asset quality'!R50+'Asset quality'!R53+'Asset quality'!R54+'Asset quality'!R58+'Asset quality'!R60+'Asset quality'!R62 -> 1287411 | Q72: ='Asset quality'!G12+'Asset quality'!G17+'Asset quality'!G47+'Asset quality'!G48+'Asset quality'!G49+'Asset quality'!G50+'Asset quality'!G53+'Asset quality'!G54+'Asset quality'!G58+'Asset quality'!G60+'Asset quality'!G62 -> 174183476 | S72: ='Asset quality'!S12+'Asset quality'!S17+'Asset quality'!S47+'Asset quality'!S48+'Asset quality'!S49+'Asset quality'!S50+'Asset quality'!S53+'Asset quality'!S54+'Asset quality'!S58+'Asset quality'!S60+'Asset quality'!S62 -> 7397831 | U72: ='Asset quality'!H12+'Asset quality'!H17+'Asset quality'!H47+'Asset quality'!H48+'Asset quality'!H49+'Asset quality'!H50+'Asset quality'!H53+'Asset quality'!H54+'Asset quality'!H58+'Asset quality'!H60+'Asset quality'!H62 -> 573548382 | W72: ='Asset quality'!T12+'Asset quality'!T17+'Asset quality'!T47+'Asset quality'!T48+'Asset quality'!T49+'Asset quality'!T50+'Asset quality'!T53+'Asset quality'!T54+'Asset quality'!T58+'Asset quality'!T60+'Asset quality'!T62 -> 277037073 | Y72: =+W72+S72+O72+K72 -> 461689200 | Z72: =+X72+T72+P72+L72 -> 0
B73: шундан, таъминланмаган қисми | C73: =E73+I73+M73+Q73+U73 -> 0 | D73: =F73+J73+N73+R73+V73 -> 0 | Y73: =+W73+S73+O73+K73 -> 0 | Z73: =+X73+T73+P73+L73 -> 0
A74: 40 | B74: Жами таснифланган активлар суммаси | C74: =+C53+C72 -> 71956788703 | D74: =+D53+D72 -> 38012960642 | E74: =+E53+E72 -> 62649161196 | F74: =+F53+F72 -> 32899887295 | G74: =+G53+G72 -> 631267800 | H74: =+H53+H72 -> 0 | I74: =+I53+I72 -> 7184737563 | J74: =+J53+J72 -> 4289653575 | ... AB74: =+AB53+AB72 -> 16609312
B76: Бошқарув Раис имзоси:
B78: Бош бухгалтер имзоси:
E80: =SUM('Asset quality'!D20:D46)+'Asset quality'!D16 -> 49548751261 | G80: =SUM('Asset quality'!P20:P46)+'Asset quality'!P16 -> 504953973 | I80: =SUM('Asset quality'!E20:E46)+'Asset quality'!E16 -> 6292476722 | K80: =SUM('Asset quality'!Q20:Q46)+'Asset quality'!Q16 -> 620122045 | M80: =SUM('Asset quality'!F20:F46)+'Asset quality'!F16 -> 506004487 | O80: =SUM('Asset quality'!R20:R46)+'Asset quality'!R16 -> 126501133 | Q80: =SUM('Asset quality'!G20:G46)+'Asset quality'!G16 -> 749932110 | S80: =SUM('Asset quality'!S20:S46)+'Asset quality'!S16 -> 374966057 | U80: =SUM('Asset quality'!H20:H46)+'Asset quality'!H16 -> 27239332 | W80: =SUM('Asset quality'!T20:T46)+'Asset quality'!T16 -> 27239332 | Y80: =+W80+S80+O80+K80 -> 1148828567
G81: =+'Asset quality'!P9+'Asset quality'!P62 -> 631267800 | K81: =+'Asset quality'!Q9+'Asset quality'!Q62 -> 796088930 | O81: =+'Asset quality'!R9+'Asset quality'!R62 -> 127788544 | S81: =+'Asset quality'!S9+'Asset quality'!S62 -> 382363888 | W81: =+'Asset quality'!T9+'Asset quality'!T62 -> 304276405 | Y81: =+W81+S81+O81+K81 -> 1610517767
E82: =+E80-E53 -> 0 | G82: =+G80-G53 -> 0 | I82: =+I80-I53 -> 0 | K82: =+K80-K53 -> 0 | M82: =+M80-M53 -> 0 | O82: =+O80-O53 -> 0 | Q82: =+Q80-Q53 -> 0 | S82: =+S80-S53 -> 0 | U82: =+U80-U53 -> 0 | W82: =+W80-W53 -> 0 | Y82: =+Y80-Y53 -> 0
G83: =+G81-G74 -> 0 | K83: =+K81-K74 -> 0 | O83: =+O81-O74 -> 0 | S83: =+S81-S74 -> 0 | W83: =+W81-W74 -> 0 | Y83: =+Y81-Y74 -> 0

Sheet Asset Provisioning
A1: АКТИВЛАР ВА УЛАРНИНГ ТАСНИФИ БЎЙИЧА ШАКЛЛАНТИРИЛГАН ЗАХИРАЛАР | AT1: 10 А-жадвал
B3: =+'Asset quality'!B3 -> "Ўзсаноатқурилишибанк" АТБ | AH3: =+'Asset quality'!Q3 -> 45289 | AU3: =+'Asset quality'!T3 -> минг. сўмда
A4: № | B4: Кўрсаткичлар | C4: Жами суммаси | D4: шундан, хорижий валютада (экв. сўмда) | E4: Стандарт | F4: шундан, хорижий валютада (экв. сўмда) | G4: Стандарт активлар бўйича яратилган захиралар (мин 1%) | J4: Субстандарт | K4: шундан, хорижий валютада (экв. сўмда) | L4: Субстандарт активлар бўйича яратилган захиралар (мин 10%) | O4: шундан, хорижий валютада (экв. сўмда) | R4: Қониқарсиз | S4: шундан, хорижий валютада (экв. сўмда) | T4: Қониқарсиз активлар бўйича яратилган захиралар (мин 25%) | W4: шундан, хорижий валютада (экв. сўмда) | Z4: Шубҳали | AA4: шундан, хорижий валютада (экв. сўмда) | AB4: Шубҳали активлар бўйича яратилган захиралар (мин 50%) | AE4: шундан, хорижий валютада (экв. сўмда) | AH4: Умидсиз | AI4: шундан, хорижий валютада (экв. сўмда) | AJ4: Умидсиз активлар бўйича яратилган захиралар (мин 100%) | AM4: шундан, хорижий валютада (экв. сўмда) | AP4: Жами махсус захиралар суммаси | AS4: шундан, хорижий валютада (экв. сўмда)
G5: Ҳақиқатдан яратилган заҳира | H5: Яратилиши лозим бўлган заҳира | I5: Фарқи | L5: Ҳақиқатдан яратилган заҳира | M5: Яратилиши лозим бўлган заҳира | N5: Фарқи | O5: Ҳақиқатдан яратилган заҳира | P5: Яратилиши лозим бўлган заҳира | Q5: Фарқи | T5: Ҳақиқатдан яратилган заҳира | U5: Яратилиши лозим бўлган заҳира | V5: Фарқи | W5: Ҳақиқатдан яратилган заҳира | X5: Яратилиши лозим бўлган заҳира | Y5: Фарқи | AB5: Ҳақиқатдан яратилган заҳира | AC5: Яратилиши лозим бўлган заҳира | AD5: Фарқи | AE5: Ҳақиқатдан яратилган заҳира | AF5: Яратилиши лозим бўлган заҳира | AG5: Фарқи | AJ5: Ҳақиқатдан яратилган заҳира | AK5: Яратилиши лозим бўлган заҳира | AL5: Фарқи | AM5: Ҳақиқатдан яратилган заҳира | AN5: Яратилиши лозим бўлган заҳира | AO5: Фарқи | AP5: Ҳақиқатдан яратилган заҳира | AQ5: Яратилиши лозим бўлган заҳира | AR5: Фарқи | AS5: Ҳақиқатдан яратилган заҳира | AT5: Яратилиши лозим бўлган заҳира | AU5: Фарқи
B6: Мижозлар тури бўйича
A7: 1 | B7: Марказий банк | C7: =+'Asset Classification'!C7 -> 0 | D7: =+'Asset Classification'!D7 -> 0 | E7: =+'Asset Classification'!E7 -> 0 | F7: =+'Asset Classification'!F7 -> 0 | G7: =+'Asset Classification'!G7 -> 0 | H7: =+E7*1% -> 0 | I7: =+G7-H7 -> 0 | J7: =+'Asset Classification'!I7 -> 0 | K7: =+'Asset Classification'!J7 -> 0 | L7: =+'Asset Classification'!K7 -> 0 | M7: =+J7*10% -> 0 | N7: =+L7-M7 -> 0 | O7: =+'Asset Classification'!L7 -> 0 | P7: =+K7*10% -> 0 | Q7: =+O7-P7 -> 0 | R7: =+'Asset Classification'!M7 -> 0 | S7: =+'Asset Classification'!N7 -> 0 | T7: =+'Asset Classification'!O7 -> 0 | U7: =+R7*25% -> 0 | V7: =+T7-U7 -> 0 | W7: =+'Asset Classification'!P7 -> 0 | X7: =+S7*25% -> 0 | Y7: =+W7-X7 -> 0 | Z7: =+'Asset Classification'!Q7 -> 0 | AA7: =+'Asset Classification'!R7 -> 0 | AB7: =+'Asset Classification'!S7 -> 0 | AC7: =+Z7*50% -> 0 | AD7: =+AB7-AC7 -> 0 | AE7: =+'Asset Classification'!T7 -> 0 | AF7: =+AA7*50% -> 0 | AG7: =+AE7-AF7 -> 0 | AH7: =+'Asset Classification'!U7 -> 0 | AI7: =+'Asset Classification'!V7 -> 0 | AJ7: =+'Asset Classification'!W7 -> 0 | AK7: =+AH7*100% -> 0 | AL7: =+AJ7-AK7 -> 0 | AM7: =+'Asset Classification'!X7 -> 0 | AN7: =+AI7*100% -> 0 | AO7: =+AM7-AN7 -> 0 | AP7: =+L7+T7+AB7+AJ7 -> 0 | AQ7: =+M7+U7+AC7+AK7 -> 0 | AR7: =+AP7-AQ7 -> 0 | AS7: =+O7+W7+AE7+AM7 -> 0 | AT7: =+P7+X7+AF7+AN7 -> 0 | AU7: =+AS7-AT7 -> 0 | AV7: =+'Aging Analysis'!C9 -> 0
B8: шундан, таъминланмаган қисми | C8: =+'Asset Classification'!C8 -> 0 | D8: =+'Asset Classification'!D8 -> 0 | E8: =+'Asset Classification'!E8 -> 0 | F8: =+'Asset Classification'!F8 -> 0 | G8: =+'Asset Classification'!G8 -> 0 | H8: =+E8*1% -> 0 | I8: =+G8-H8 -> 0 | J8: =+'Asset Classification'!I8 -> 0 | K8: =+'Asset Classification'!J8 -> 0 | L8: =+'Asset Classification'!K8 -> 0 | M8: =+J8*10% -> 0 | N8: =+L8-M8 -> 0 | O8: =+'Asset Classification'!L8 -> 0 | P8: =+K8*10% -> 0 | Q8: =+O8-P8 -> 0 | R8: =+'Asset Classification'!M8 -> 0 | S8: =+'Asset Classification'!N8 -> 0 | T8: =+'Asset Classification'!O8 -> 0 | U8: =+R8*25% -> 0 | V8: =+T8-U8 -> 0 | W8: =+'Asset Classification'!P8 -> 0 | X8: =+S8*25% -> 0 | Y8: =+W8-X8 -> 0 | Z8: =+'Asset Classification'!Q8 -> 0 | AA8: =+'Asset Classification'!R8 -> 0 | AB8: =+'Asset Classification'!S8 -> 0 | AC8: =+Z8*50% -> 0 | AD8: =+AB8-AC8 -> 0 | AE8: =+'Asset Classification'!T8 -> 0 | AF8: =+AA8*50% -> 0 | AG8: =+AE8-AF8 -> 0 | AH8: =+'Asset Classification'!U8 -> 0 | AI8: =+'Asset Classification'!V8 -> 0 | AJ8: =+'Asset Classification'!W8 -> 0 | AK8: =+AH8*100% -> 0 | AL8: =+AJ8-AK8 -> 0 | AM8: =+'Asset Classification'!X8 -> 0 | AN8: =+AI8*100% -> 0 | AO8: =+AM8-AN8 -> 0 | AP8: =+L8+T8+AB8+AJ8 -> 0 | AQ8: =+M8+U8+AC8+AK8 -> 0 | AR8: =+AP8-AQ8 -> 0 | AS8: =+O8+W8+AE8+AM8 -> 0 | AT8: =+P8+X8+AF8+AN8 -> 0 | AU8: =+AS8-AT8 -> 0
A9: 2 | B9: Бошқа банклар | C9: =+'Asset Classification'!C9 -> 0 | D9: =+'Asset Classification'!D9 -> 0 | E9: =+'Asset Classification'!E9 -> 0 | F9: =+'Asset Classification'!F9 -> 0 | G9: =+'Asset Classification'!G9 -> 0 | H9: =+E9*1% -> 0 | I9: =+G9-H9 -> 0 | J9: =+'Asset Classification'!I9 -> 0 | K9: =+'Asset Classification'!J9 -> 0 | L9: =+'Asset Classification'!K9 -> 0 | M9: =+J9*10% -> 0 | N9: =+L9-M9 -> 0 | O9: =+'Asset Classification'!L9 -> 0 | P9: =+K9*10% -> 0 | Q9: =+O9-P9 -> 0 | R9: =+'Asset Classification'!M9 -> 0 | S9: =+'Asset Classification'!N9 -> 0 | T9: =+'Asset Classification'!O9 -> 0 | U9: =+R9*25% -> 0 | V9: =+T9-U9 -> 0 | W9: =+'Asset Classification'!P9 -> 0 | X9: =+S9*25% -> 0 | Y9: =+W9-X9 -> 0 | Z9: =+'Asset Classification'!Q9 -> 0 | AA9: =+'Asset Classification'!R9 -> 0 | AB9: =+'Asset Classification'!S9 -> 0 | AC9: =+Z9*50% -> 0 | AD9: =+AB9-AC9 -> 0 | AE9: =+'Asset Classification'!T9 -> 0 | AF9: =+AA9*50% -> 0 | AG9: =+AE9-AF9 -> 0 | AH9: =+'Asset Classification'!U9 -> 0 | AI9: =+'Asset Classification'!V9 -> 0 | AJ9: =+'Asset Classification'!W9 -> 0 | AK9: =+AH9*100% -> 0 | AL9: =+AJ9-AK9 -> 0 | AM9: =+'Asset Classification'!X9 -> 0 | AN9: =+AI9*100% -> 0 | AO9: =+AM9-AN9 -> 0 | AP9: =+L9+T9+AB9+AJ9 -> 0 | AQ9: =+M9+U9+AC9+AK9 -> 0 | AR9: =+AP9-AQ9 -> 0 | AS9: =+O9+W9+AE9+AM9 -> 0 | AT9: =+P9+X9+AF9+AN9 -> 0 | AU9: =+AS9-AT9 -> 0 | AV9: =+'Aging Analysis'!C10 -> 0
B10: шундан, таъминланмаган қисми | C10: =+'Asset Classification'!C10 -> 0 | D10: =+'Asset Classification'!D10 -> 0 | E10: =+'Asset Classification'!E10 -> 0 | F10: =+'Asset Classification'!F10 -> 0 | G10: =+'Asset Classification'!G10 -> 0 | H10: =+E10*1% -> 0 | I10: =+G10-H10 -> 0 | J10: =+'Asset Classification'!I10 -> 0 | K10: =+'Asset Classification'!J10 -> 0 | L10: =+'Asset Classification'!K10 -> 0 | M10: =+J10*10% -> 0 | N10: =+L10-M10 -> 0 | O10: =+'Asset Classification'!L10 -> 0 | P10: =+K10*10% -> 0 | Q10: =+O10-P10 -> 0 | R10: =+'Asset Classification'!M10 -> 0 | S10: =+'Asset Classification'!N10 -> 0 | T10: =+'Asset Classification'!O10 -> 0 | U10: =+R10*25% -> 0 | V10: =+T10-U10 -> 0 | W10: =+'Asset Classification'!P10 -> 0 | X10: =+S10*25% -> 0 | Y10: =+W10-X10 -> 0 | Z10: =+'Asset Classification'!Q10 -> 0 | AA10: =+'Asset Classification'!R10 -> 0 | AB10: =+'Asset Classification'!S10 -> 0 | AC10: =+Z10*50% -> 0 | AD10: =+AB10-AC10 -> 0 | AE10: =+'Asset Classification'!T10 -> 0 | AF10: =+AA10*50% -> 0 | AG10: =+AE10-AF10 -> 0 | AH10: =+'Asset Classification'!U10 -> 0 | AI10: =+'Asset Classification'!V10 -> 0 | AJ10: =+'Asset Classification'!W10 -> 0 | AK10: =+AH10*100% -> 0 | AL10: =+AJ10-AK10 -> 0 | AM10: =+'Asset Classification'!X10 -> 0 | AN10: =+AI10*100% -> 0 | AO10: =+AM10-AN10 -> 0 | AP10: =+L10+T10+AB10+AJ10 -> 0 | AQ10: =+M10+U10+AC10+AK10 -> 0 | AR10: =+AP10-AQ10 -> 0 | AS10: =+O10+W10+AE10+AM10 -> 0 | AT10: =+P10+X10+AF10+AN10 -> 0 | AU10: =+AS10-AT10 -> 0
A11: 3 | B11: Ҳукумат | C11: =+'Asset Classification'!C11 -> 0 | D11: =+'Asset Classification'!D11 -> 0 | E11: =+'Asset Classification'!E11 -> 0 | F11: =+'Asset Classification'!F11 -> 0 | G11: =+'Asset Classification'!G11 -> 0 | H11: =+E11*1% -> 0 | I11: =+G11-H11 -> 0 | J11: =+'Asset Classification'!I11 -> 0 | K11: =+'Asset Classification'!J11 -> 0 | L11: =+'Asset Classification'!K11 -> 0 | M11: =+J11*10% -> 0 | N11: =+L11-M11 -> 0 | O11: =+'Asset Classification'!L11 -> 0 | P11: =+K11*10% -> 0 | Q11: =+O11-P11 -> 0 | R11: =+'Asset Classification'!M11 -> 0 | S11: =+'Asset Classification'!N11 -> 0 | T11: =+'Asset Classification'!O11 -> 0 | U11: =+R11*25% -> 0 | V11: =+T11-U11 -> 0 | W11: =+'Asset Classification'!P11 -> 0 | X11: =+S11*25% -> 0 | Y11: =+W11-X11 -> 0 | Z11: =+'Asset Classification'!Q11 -> 0 | AA11: =+'Asset Classification'!R11 -> 0 | AB11: =+'Asset Classification'!S11 -> 0 | AC11: =+Z11*50% -> 0 | AD11: =+AB11-AC11 -> 0 | AE11: =+'Asset Classification'!T11 -> 0 | AF11: =+AA11*50% -> 0 | AG11: =+AE11-AF11 -> 0 | AH11: =+'Asset Classification'!U11 -> 0 | AI11: =+'Asset Classification'!V11 -> 0 | AJ11: =+'Asset Classification'!W11 -> 0 | AK11: =+AH11*100% -> 0 | AL11: =+AJ11-AK11 -> 0 | AM11: =+'Asset Classification'!X11 -> 0 | AN11: =+AI11*100% -> 0 | AO11: =+AM11-AN11 -> 0 | AP11: =+L11+T11+AB11+AJ11 -> 0 | AQ11: =+M11+U11+AC11+AK11 -> 0 | AR11: =+AP11-AQ11 -> 0 | AS11: =+O11+W11+AE11+AM11 -> 0 | AT11: =+P11+X11+AF11+AN11 -> 0 | AU11: =+AS11-AT11 -> 0 | AV11: =+'Aging Analysis'!C11 -> 0
B12: шундан, таъминланмаган қисми | C12: =+'Asset Classification'!C12 -> 0 | D12: =+'Asset Classification'!D12 -> 0 | E12: =+'Asset Classification'!E12 -> 0 | F12: =+'Asset Classification'!F12 -> 0 | G12: =+'Asset Classification'!G12 -> 0 | H12: =+E12*1% -> 0 | I12: =+G12-H12 -> 0 | J12: =+'Asset Classification'!I12 -> 0 | K12: =+'Asset Classification'!J12 -> 0 | L12: =+'Asset Classification'!K12 -> 0 | M12: =+J12*10% -> 0 | N12: =+L12-M12 -> 0 | O12: =+'Asset Classification'!L12 -> 0 | P12: =+K12*10% -> 0 | Q12: =+O12-P12 -> 0 | R12: =+'Asset Classification'!M12 -> 0 | S12: =+'Asset Classification'!N12 -> 0 | T12: =+'Asset Classification'!O12 -> 0 | U12: =+R12*25% -> 0 | V12: =+T12-U12 -> 0 | W12: =+'Asset Classification'!P12 -> 0 | X12: =+S12*25% -> 0 | Y12: =+W12-X12 -> 0 | Z12: =+'Asset Classification'!Q12 -> 0 | AA12: =+'Asset Classification'!R12 -> 0 | AB12: =+'Asset Classification'!S12 -> 0 | AC12: =+Z12*50% -> 0 | AD12: =+AB12-AC12 -> 0 | AE12: =+'Asset Classification'!T12 -> 0 | AF12: =+AA12*50% -> 0 | AG12: =+AE12-AF12 -> 0 | AH12: =+'Asset Classification'!U12 -> 0 | AI12: =+'Asset Classification'!V12 -> 0 | AJ12: =+'Asset Classification'!W12 -> 0 | AK12: =+AH12*100% -> 0 | AL12: =+AJ12-AK12 -> 0 | AM12: =+'Asset Classification'!X12 -> 0 | AN12: =+AI12*100% -> 0 | AO12: =+AM12-AN12 -> 0 | AP12: =+L12+T12+AB12+AJ12 -> 0 | AQ12: =+M12+U12+AC12+AK12 -> 0 | AR12: =+AP12-AQ12 -> 0 | AS12: =+O12+W12+AE12+AM12 -> 0 | AT12: =+P12+X12+AF12+AN12 -> 0 | AU12: =+AS12-AT12 -> 0
A13: 4 | B13: Жисмоний шахслар | C13: =+'Asset Classification'!C13 -> 7814492786 | D13: =+'Asset Classification'!D13 -> 0 | E13: =+'Asset Classification'!E13 -> 7625652230 | F13: =+'Asset Classification'!F13 -> 0 | G13: =+'Asset Classification'!G13 -> 76256522 | H13: =+E13*1% -> 76256522 | I13: =+G13-H13 -> -0.3 | J13: =+'Asset Classification'!I13 -> 147846643 | K13: =+'Asset Classification'!J13 -> 0 | L13: =+'Asset Classification'!K13 -> 14782772 | M13: =+J13*10% -> 14784664 | N13: =+L13-M13 -> -1892.3 | O13: =+'Asset Classification'!L13 -> 0 | P13: =+K13*10% -> 0 | Q13: =+O13-P13 -> 0 | R13: =+'Asset Classification'!M13 -> 19062315 | S13: =+'Asset Classification'!N13 -> 0 | T13: =+'Asset Classification'!O13 -> 4765590 | U13: =+R13*25% -> 4765578.8 | V13: =+T13-U13 -> 11.25 | W13: =+'Asset Classification'!P13 -> 0 | X13: =+S13*25% -> 0 | Y13: =+W13-X13 -> 0 | Z13: =+'Asset Classification'!Q13 -> 21931598 | AA13: =+'Asset Classification'!R13 -> 0 | AB13: =+'Asset Classification'!S13 -> 10965799 | AC13: =+Z13*50% -> 10965799 | AD13: =+AB13-AC13 -> 0 | AE13: =+'Asset Classification'!T13 -> 0 | AF13: =+AA13*50% -> 0 | AG13: =+AE13-AF13 -> 0 | AH13: =+'Asset Classification'!U13 -> 0 | AI13: =+'Asset Classification'!V13 -> 0 | AJ13: =+'Asset Classification'!W13 -> 0 | AK13: =+AH13*100% -> 0 | AL13: =+AJ13-AK13 -> 0 | AM13: =+'Asset Classification'!X13 -> 0 | AN13: =+AI13*100% -> 0 | AO13: =+AM13-AN13 -> 0 | AP13: =+L13+T13+AB13+AJ13 -> 30514161 | AQ13: =+M13+U13+AC13+AK13 -> 30516042 | AR13: =+AP13-AQ13 -> -1881.05 | AS13: =+O13+W13+AE13+AM13 -> 0 | AT13: =+P13+X13+AF13+AN13 -> 0 | AU13: =+AS13-AT13 -> 0 | AV13: =+'Aging Analysis'!C12 -> 7814492786
B14: шундан, таъминланмаган қисми | C14: =+'Asset Classification'!C14 -> 0 | D14: =+'Asset Classification'!D14 -> 0 | E14: =+'Asset Classification'!E14 -> 0 | F14: =+'Asset Classification'!F14 -> 0 | G14: =+'Asset Classification'!G14 -> 0 | H14: =+E14*1% -> 0 | I14: =+G14-H14 -> 0 | J14: =+'Asset Classification'!I14 -> 0 | K14: =+'Asset Classification'!J14 -> 0 | L14: =+'Asset Classification'!K14 -> 0 | M14: =+J14*10% -> 0 | N14: =+L14-M14 -> 0 | O14: =+'Asset Classification'!L14 -> 0 | P14: =+K14*10% -> 0 | Q14: =+O14-P14 -> 0 | R14: =+'Asset Classification'!M14 -> 0 | S14: =+'Asset Classification'!N14 -> 0 | T14: =+'Asset Classification'!O14 -> 0 | U14: =+R14*25% -> 0 | V14: =+T14-U14 -> 0 | W14: =+'Asset Classification'!P14 -> 0 | X14: =+S14*25% -> 0 | Y14: =+W14-X14 -> 0 | Z14: =+'Asset Classification'!Q14 -> 0 | AA14: =+'Asset Classification'!R14 -> 0 | AB14: =+'Asset Classification'!S14 -> 0 | AC14: =+Z14*50% -> 0 | AD14: =+AB14-AC14 -> 0 | AE14: =+'Asset Classification'!T14 -> 0 | AF14: =+AA14*50% -> 0 | AG14: =+AE14-AF14 -> 0 | AH14: =+'Asset Classification'!U14 -> 0 | AI14: =+'Asset Classification'!V14 -> 0 | AJ14: =+'Asset Classification'!W14 -> 0 | AK14: =+AH14*100% -> 0 | AL14: =+AJ14-AK14 -> 0 | AM14: =+'Asset Classification'!X14 -> 0 | AN14: =+AI14*100% -> 0 | AO14: =+AM14-AN14 -> 0 | AP14: =+L14+T14+AB14+AJ14 -> 0 | AQ14: =+M14+U14+AC14+AK14 -> 0 | AR14: =+AP14-AQ14 -> 0 | AS14: =+O14+W14+AE14+AM14 -> 0 | AT14: =+P14+X14+AF14+AN14 -> 0 | AU14: =+AS14-AT14 -> 0
A15: 5 | B15: Давлат корхоналари | C15: =+'Asset Classification'!C15 -> 14102735134 | D15: =+'Asset Classification'!D15 -> 9901199639 | E15: =+'Asset Classification'!E15 -> 14098238653 | F15: =+'Asset Classification'!F15 -> 9901199639 | G15: =+'Asset Classification'!G15 -> 150448847 | H15: =+E15*1% -> 1.4098239e+08 | I15: =+G15-H15 -> 9466460.5 | J15: =+'Asset Classification'!I15 -> 4496481 | K15: =+'Asset Classification'!J15 -> 0 | L15: =+'Asset Classification'!K15 -> 449648 | M15: =+J15*10% -> 449648.1 | N15: =+L15-M15 -> -0.1 | O15: =+'Asset Classification'!L15 -> 0 | P15: =+K15*10% -> 0 | Q15: =+O15-P15 -> 0 | R15: =+'Asset Classification'!M15 -> 0 | S15: =+'Asset Classification'!N15 -> 0 | T15: =+'Asset Classification'!O15 -> 0 | U15: =+R15*25% -> 0 | V15: =+T15-U15 -> 0 | W15: =+'Asset Classification'!P15 -> 0 | X15: =+S15*25% -> 0 | Y15: =+W15-X15 -> 0 | Z15: =+'Asset Classification'!Q15 -> 0 | AA15: =+'Asset Classification'!R15 -> 0 | AB15: =+'Asset Classification'!S15 -> 0 | AC15: =+Z15*50% -> 0 | AD15: =+AB15-AC15 -> 0 | AE15: =+'Asset Classification'!T15 -> 0 | AF15: =+AA15*50% -> 0 | AG15: =+AE15-AF15 -> 0 | AH15: =+'Asset Classification'!U15 -> 0 | AI15: =+'Asset Classification'!V15 -> 0 | AJ15: =+'Asset Classification'!W15 -> 0 | AK15: =+AH15*100% -> 0 | AL15: =+AJ15-AK15 -> 0 | AM15: =+'Asset Classification'!X15 -> 0 | AN15: =+AI15*100% -> 0 | AO15: =+AM15-AN15 -> 0 | AP15: =+L15+T15+AB15+AJ15 -> 449648 | AQ15: =+M15+U15+AC15+AK15 -> 449648.1 | AR15: =+AP15-AQ15 -> -0.1 | AS15: =+O15+W15+AE15+AM15 -> 0 | AT15: =+P15+X15+AF15+AN15 -> 0 | AU15: =+AS15-AT15 -> 0 | AV15: =+'Aging Analysis'!C13 -> 14102735134
B16: шундан, таъминланмаган қисми | C16: =+'Asset Classification'!C16 -> 0 | D16: =+'Asset Classification'!D16 -> 0 | E16: =+'Asset Classification'!E16 -> 0 | F16: =+'Asset Classification'!F16 -> 0 | G16: =+'Asset Classification'!G16 -> 0 | H16: =+E16*1% -> 0 | I16: =+G16-H16 -> 0 | J16: =+'Asset Classification'!I16 -> 0 | K16: =+'Asset Classification'!J16 -> 0 | L16: =+'Asset Classification'!K16 -> 0 | M16: =+J16*10% -> 0 | N16: =+L16-M16 -> 0 | O16: =+'Asset Classification'!L16 -> 0 | P16: =+K16*10% -> 0 | Q16: =+O16-P16 -> 0 | R16: =+'Asset Classification'!M16 -> 0 | S16: =+'Asset Classification'!N16 -> 0 | T16: =+'Asset Classification'!O16 -> 0 | U16: =+R16*25% -> 0 | V16: =+T16-U16 -> 0 | W16: =+'Asset Classification'!P16 -> 0 | X16: =+S16*25% -> 0 | Y16: =+W16-X16 -> 0 | Z16: =+'Asset Classification'!Q16 -> 0 | AA16: =+'Asset Classification'!R16 -> 0 | AB16: =+'Asset Classification'!S16 -> 0 | AC16: =+Z16*50% -> 0 | AD16: =+AB16-AC16 -> 0 | AE16: =+'Asset Classification'!T16 -> 0 | AF16: =+AA16*50% -> 0 | AG16: =+AE16-AF16 -> 0 | AH16: =+'Asset Classification'!U16 -> 0 | AI16: =+'Asset Classification'!V16 -> 0 | AJ16: =+'Asset Classification'!W16 -> 0 | AK16: =+AH16*100% -> 0 | AL16: =+AJ16-AK16 -> 0 | AM16: =+'Asset Classification'!X16 -> 0 | AN16: =+AI16*100% -> 0 | AO16: =+AM16-AN16 -> 0 | AP16: =+L16+T16+AB16+AJ16 -> 0 | AQ16: =+M16+U16+AC16+AK16 -> 0 | AR16: =+AP16-AQ16 -> 0 | AS16: =+O16+W16+AE16+AM16 -> 0 | AT16: =+P16+X16+AF16+AN16 -> 0 | AU16: =+AS16-AT16 -> 0
A17: 6 | B17: Қўшма ва чет эл капитали иштирокидаги корхоналар | C17: =+'Asset Classification'!C17 -> 10296625676 | D17: =+'Asset Classification'!D17 -> 9399133697 | E17: =+'Asset Classification'!E17 -> 7302774414 | F17: =+'Asset Classification'!F17 -> 6846681407 | G17: =+'Asset Classification'!G17 -> 73027744 | H17: =+E17*1% -> 73027744 | I17: =+G17-H17 -> -0.14 | J17: =+'Asset Classification'!I17 -> 2936824466 | K17: =+'Asset Classification'!J17 -> 2498999738 | L17: =+'Asset Classification'!K17 -> 293682447 | M17: =+J17*10% -> 2.9368245e+08 | N17: =+L17-M17 -> 0.39999998 | O17: =+'Asset Classification'!L17 -> 249899974 | P17: =+K17*10% -> 2.4989997e+08 | Q17: =+O17-P17 -> 0.19999999 | R17: =+'Asset Classification'!M17 -> 810756 | S17: =+'Asset Classification'!N17 -> 0 | T17: =+'Asset Classification'!O17 -> 202689 | U17: =+R17*25% -> 202689 | V17: =+T17-U17 -> 0 | W17: =+'Asset Classification'!P17 -> 0 | X17: =+S17*25% -> 0 | Y17: =+W17-X17 -> 0 | Z17: =+'Asset Classification'!Q17 -> 46247548 | AA17: =+'Asset Classification'!R17 -> 43484060 | AB17: =+'Asset Classification'!S17 -> 23123774 | AC17: =+Z17*50% -> 23123774 | AD17: =+AB17-AC17 -> 0 | AE17: =+'Asset Classification'!T17 -> 21742030 | AF17: =+AA17*50% -> 21742030 | AG17: =+AE17-AF17 -> 0 | AH17: =+'Asset Classification'!U17 -> 9968492 | AI17: =+'Asset Classification'!V17 -> 9968492 | AJ17: =+'Asset Classification'!W17 -> 9968492 | AK17: =+AH17*100% -> 9968492 | AL17: =+AJ17-AK17 -> 0 | AM17: =+'Asset Classification'!X17 -> 9968492 | AN17: =+AI17*100% -> 9968492 | AO17: =+AM17-AN17 -> 0 | AP17: =+L17+T17+AB17+AJ17 -> 326977402 | AQ17: =+M17+U17+AC17+AK17 -> 3.269774e+08 | AR17: =+AP17-AQ17 -> 0.39999998 | AS17: =+O17+W17+AE17+AM17 -> 281610496 | AT17: =+P17+X17+AF17+AN17 -> 2.816105e+08 | AU17: =+AS17-AT17 -> 0.19999999 | AV17: =+'Aging Analysis'!C14 -> 10296625676
B18: шундан, таъминланмаган қисми | C18: =+'Asset Classification'!C18 -> 0 | D18: =+'Asset Classification'!D18 -> 0 | E18: =+'Asset Classification'!E18 -> 0 | F18: =+'Asset Classification'!F18 -> 0 | G18: =+'Asset Classification'!G18 -> 0 | H18: =+E18*1% -> 0 | I18: =+G18-H18 -> 0 | J18: =+'Asset Classification'!I18 -> 0 | K18: =+'Asset Classification'!J18 -> 0 | L18: =+'Asset Classification'!K18 -> 0 | M18: =+J18*10% -> 0 | N18: =+L18-M18 -> 0 | O18: =+'Asset Classification'!L18 -> 0 | P18: =+K18*10% -> 0 | Q18: =+O18-P18 -> 0 | R18: =+'Asset Classification'!M18 -> 0 | S18: =+'Asset Classification'!N18 -> 0 | T18: =+'Asset Classification'!O18 -> 0 | U18: =+R18*25% -> 0 | V18: =+T18-U18 -> 0 | W18: =+'Asset Classification'!P18 -> 0 | X18: =+S18*25% -> 0 | Y18: =+W18-X18 -> 0 | Z18: =+'Asset Classification'!Q18 -> 0 | AA18: =+'Asset Classification'!R18 -> 0 | AB18: =+'Asset Classification'!S18 -> 0 | AC18: =+Z18*50% -> 0 | AD18: =+AB18-AC18 -> 0 | AE18: =+'Asset Classification'!T18 -> 0 | AF18: =+AA18*50% -> 0 | AG18: =+AE18-AF18 -> 0 | AH18: =+'Asset Classification'!U18 -> 0 | AI18: =+'Asset Classification'!V18 -> 0 | AJ18: =+'Asset Classification'!W18 -> 0 | AK18: =+AH18*100% -> 0 | AL18: =+AJ18-AK18 -> 0 | AM18: =+'Asset Classification'!X18 -> 0 | AN18: =+AI18*100% -> 0 | AO18: =+AM18-AN18 -> 0 | AP18: =+L18+T18+AB18+AJ18 -> 0 | AQ18: =+M18+U18+AC18+AK18 -> 0 | AR18: =+AP18-AQ18 -> 0 | AS18: =+O18+W18+AE18+AM18 -> 0 | AT18: =+P18+X18+AF18+AN18 -> 0 | AU18: =+AS18-AT18 -> 0
A19: 7 | B19: Хусусий корхоналар | C19: =+'Asset Classification'!C19 -> 24784649546 | D19: =+'Asset Classification'!D19 -> 18619483630 | E19: =+'Asset Classification'!E19 -> 20465632095 | F19: =+'Asset Classification'!F19 -> 16120791382 | G19: =+'Asset Classification'!G19 -> 204656322 | H19: =+E19*1% -> 2.0465632e+08 | I19: =+G19-H19 -> 1.05 | J19: =+'Asset Classification'!I19 -> 3151391318 | K19: =+'Asset Classification'!J19 -> 1742099388 | L19: =+'Asset Classification'!K19 -> 306015397 | M19: =+J19*10% -> 3.1513913e+08 | N19: =+L19-M19 -> -9123734.8 | O19: =+'Asset Classification'!L19 -> 164856170 | P19: =+K19*10% -> 1.7420994e+08 | Q19: =+O19-P19 -> -9353768.8 | R19: =+'Asset Classification'!M19 -> 484458884 | S19: =+'Asset Classification'!N19 -> 263138435 | T19: =+'Asset Classification'!O19 -> 121114721 | U19: =+R19*25% -> 121114721 | V19: =+T19-U19 -> 0 | W19: =+'Asset Classification'!P19 -> 65784610 | X19: =+S19*25% -> 65784609 | Y19: =+W19-X19 -> 1.25 | Z19: =+'Asset Classification'!Q19 -> 665896409 | AA19: =+'Asset Classification'!R19 -> 488765692 | AB19: =+'Asset Classification'!S19 -> 332948207 | AC19: =+Z19*50% -> 3.329482e+08 | AD19: =+AB19-AC19 -> 2.5 | AE19: =+'Asset Classification'!T19 -> 244382848 | AF19: =+AA19*50% -> 244382846 | AG19: =+AE19-AF19 -> 2 | AH19: =+'Asset Classification'!U19 -> 17270840 | AI19: =+'Asset Classification'!V19 -> 4688733 | AJ19: =+'Asset Classification'!W19 -> 17270840 | AK19: =+AH19*100% -> 17270840 | AL19: =+AJ19-AK19 -> 0 | AM19: =+'Asset Classification'!X19 -> 4688733 | AN19: =+AI19*100% -> 4688733 | AO19: =+AM19-AN19 -> 0 | AP19: =+L19+T19+AB19+AJ19 -> 777349165 | AQ19: =+M19+U19+AC19+AK19 -> 7.864729e+08 | AR19: =+AP19-AQ19 -> -9123732.3 | AS19: =+O19+W19+AE19+AM19 -> 479712361 | AT19: =+P19+X19+AF19+AN19 -> 4.8906613e+08 | AU19: =+AS19-AT19 -> -9353765.6 | AV19: =+'Aging Analysis'!C15 -> 24784649546
B20: шундан, таъминланмаган қисми | C20: =+'Asset Classification'!C20 -> 0 | D20: =+'Asset Classification'!D20 -> 0 | E20: =+'Asset Classification'!E20 -> 0 | F20: =+'Asset Classification'!F20 -> 0 | G20: =+'Asset Classification'!G20 -> 0 | H20: =+E20*1% -> 0 | I20: =+G20-H20 -> 0 | J20: =+'Asset Classification'!I20 -> 0 | K20: =+'Asset Classification'!J20 -> 0 | L20: =+'Asset Classification'!K20 -> 0 | M20: =+J20*10% -> 0 | N20: =+L20-M20 -> 0 | O20: =+'Asset Classification'!L20 -> 0 | P20: =+K20*10% -> 0 | Q20: =+O20-P20 -> 0 | R20: =+'Asset Classification'!M20 -> 0 | S20: =+'Asset Classification'!N20 -> 0 | T20: =+'Asset Classification'!O20 -> 0 | U20: =+R20*25% -> 0 | V20: =+T20-U20 -> 0 | W20: =+'Asset Classification'!P20 -> 0 | X20: =+S20*25% -> 0 | Y20: =+W20-X20 -> 0 | Z20: =+'Asset Classification'!Q20 -> 0 | AA20: =+'Asset Classification'!R20 -> 0 | AB20: =+'Asset Classification'!S20 -> 0 | AC20: =+Z20*50% -> 0 | AD20: =+AB20-AC20 -> 0 | AE20: =+'Asset Classification'!T20 -> 0 | AF20: =+AA20*50% -> 0 | AG20: =+AE20-AF20 -> 0 | AH20: =+'Asset Classification'!U20 -> 0 | AI20: =+'Asset Classification'!V20 -> 0 | AJ20: =+'Asset Classification'!W20 -> 0 | AK20: =+AH20*100% -> 0 | AL20: =+AJ20-AK20 -> 0 | AM20: =+'Asset Classification'!X20 -> 0 | AN20: =+AI20*100% -> 0 | AO20: =+AM20-AN20 -> 0 | AP20: =+L20+T20+AB20+AJ20 -> 0 | AQ20: =+M20+U20+AC20+AK20 -> 0 | AR20: =+AP20-AQ20 -> 0 | AS20: =+O20+W20+AE20+AM20 -> 0 | AT20: =+P20+X20+AF20+AN20 -> 0 | AU20: =+AS20-AT20 -> 0
A21: 8 | B21: Фермер хўжалиги | C21: =+'Asset Classification'!C21 -> 121348475 | D21: =+'Asset Classification'!D21 -> 93143676 | E21: =+'Asset Classification'!E21 -> 52486428 | F21: =+'Asset Classification'!F21 -> 31214867 | G21: =+'Asset Classification'!G21 -> 524864 | H21: =+E21*1% -> 524864.28 | I21: =+G21-H21 -> -0.28 | J21: =+'Asset Classification'!I21 -> 51917814 | K21: =+'Asset Classification'!J21 -> 48554449 | L21: =+'Asset Classification'!K21 -> 5191781 | M21: =+J21*10% -> 5191781.4 | N21: =+L21-M21 -> -0.4 | O21: =+'Asset Classification'!L21 -> 4855445 | P21: =+K21*10% -> 4855444.9 | Q21: =+O21-P21 -> 0.1 | R21: =+'Asset Classification'!M21 -> 1534407 | S21: =+'Asset Classification'!N21 -> 0 | T21: =+'Asset Classification'!O21 -> 383602 | U21: =+R21*25% -> 383601.75 | V21: =+T21-U21 -> 0.25 | W21: =+'Asset Classification'!P21 -> 0 | X21: =+S21*25% -> 0 | Y21: =+W21-X21 -> 0 | Z21: =+'Asset Classification'!Q21 -> 15409826 | AA21: =+'Asset Classification'!R21 -> 13374360 | AB21: =+'Asset Classification'!S21 -> 7704913 | AC21: =+Z21*50% -> 7704913 | AD21: =+AB21-AC21 -> 0 | AE21: =+'Asset Classification'!T21 -> 6687180 | AF21: =+AA21*50% -> 6687180 | AG21: =+AE21-AF21 -> 0 | AH21: =+'Asset Classification'!U21 -> 0 | AI21: =+'Asset Classification'!V21 -> 0 | AJ21: =+'Asset Classification'!W21 -> 0 | AK21: =+AH21*100% -> 0 | AL21: =+AJ21-AK21 -> 0 | AM21: =+'Asset Classification'!X21 -> 0 | AN21: =+AI21*100% -> 0 | AO21: =+AM21-AN21 -> 0 | AP21: =+L21+T21+AB21+AJ21 -> 13280296 | AQ21: =+M21+U21+AC21+AK21 -> 13280296 | AR21: =+AP21-AQ21 -> -0.15 | AS21: =+O21+W21+AE21+AM21 -> 11542625 | AT21: =+P21+X21+AF21+AN21 -> 11542625 | AU21: =+AS21-AT21 -> 0.1 | AV21: =+'Aging Analysis'!C16 -> 121348475
B22: шундан, таъминланмаган қисми | C22: =+'Asset Classification'!C22 -> 0 | D22: =+'Asset Classification'!D22 -> 0 | E22: =+'Asset Classification'!E22 -> 0 | F22: =+'Asset Classification'!F22 -> 0 | G22: =+'Asset Classification'!G22 -> 0 | H22: =+E22*1% -> 0 | I22: =+G22-H22 -> 0 | J22: =+'Asset Classification'!I22 -> 0 | K22: =+'Asset Classification'!J22 -> 0 | L22: =+'Asset Classification'!K22 -> 0 | M22: =+J22*10% -> 0 | N22: =+L22-M22 -> 0 | O22: =+'Asset Classification'!L22 -> 0 | P22: =+K22*10% -> 0 | Q22: =+O22-P22 -> 0 | R22: =+'Asset Classification'!M22 -> 0 | S22: =+'Asset Classification'!N22 -> 0 | T22: =+'Asset Classification'!O22 -> 0 | U22: =+R22*25% -> 0 | V22: =+T22-U22 -> 0 | W22: =+'Asset Classification'!P22 -> 0 | X22: =+S22*25% -> 0 | Y22: =+W22-X22 -> 0 | Z22: =+'Asset Classification'!Q22 -> 0 | AA22: =+'Asset Classification'!R22 -> 0 | AB22: =+'Asset Classification'!S22 -> 0 | AC22: =+Z22*50% -> 0 | AD22: =+AB22-AC22 -> 0 | AE22: =+'Asset Classification'!T22 -> 0 | AF22: =+AA22*50% -> 0 | AG22: =+AE22-AF22 -> 0 | AH22: =+'Asset Classification'!U22 -> 0 | AI22: =+'Asset Classification'!V22 -> 0 | AJ22: =+'Asset Classification'!W22 -> 0 | AK22: =+AH22*100% -> 0 | AL22: =+AJ22-AK22 -> 0 | AM22: =+'Asset Classification'!X22 -> 0 | AN22: =+AI22*100% -> 0 | AO22: =+AM22-AN22 -> 0 | AP22: =+L22+T22+AB22+AJ22 -> 0 | AQ22: =+M22+U22+AC22+AK22 -> 0 | AR22: =+AP22-AQ22 -> 0 | AS22: =+O22+W22+AE22+AM22 -> 0 | AT22: =+P22+X22+AF22+AN22 -> 0 | AU22: =+AS22-AT22 -> 0
A23: 9 | B23: Нобанк молиявий институтлар | C23: =+'Asset Classification'!C23 -> 2946729 | D23: =+'Asset Classification'!D23 -> 0 | E23: =+'Asset Classification'!E23 -> 2500000 | F23: =+'Asset Classification'!F23 -> 0 | G23: =+'Asset Classification'!G23 -> 25000 | H23: =+E23*1% -> 25000 | I23: =+G23-H23 -> 0 | J23: =+'Asset Classification'!I23 -> 0 | K23: =+'Asset Classification'!J23 -> 0 | L23: =+'Asset Classification'!K23 -> 0 | M23: =+J23*10% -> 0 | N23: =+L23-M23 -> 0 | O23: =+'Asset Classification'!L23 -> 0 | P23: =+K23*10% -> 0 | Q23: =+O23-P23 -> 0 | R23: =+'Asset Classification'!M23 -> 0 | S23: =+'Asset Classification'!N23 -> 0 | T23: =+'Asset Classification'!O23 -> 0 | U23: =+R23*25% -> 0 | V23: =+T23-U23 -> 0 | W23: =+'Asset Classification'!P23 -> 0 | X23: =+S23*25% -> 0 | Y23: =+W23-X23 -> 0 | Z23: =+'Asset Classification'!Q23 -> 446729 | AA23: =+'Asset Classification'!R23 -> 0 | AB23: =+'Asset Classification'!S23 -> 223364 | AC23: =+Z23*50% -> 223364.5 | AD23: =+AB23-AC23 -> -0.5 | AE23: =+'Asset Classification'!T23 -> 0 | AF23: =+AA23*50% -> 0 | AG23: =+AE23-AF23 -> 0 | AH23: =+'Asset Classification'!U23 -> 0 | AI23: =+'Asset Classification'!V23 -> 0 | AJ23: =+'Asset Classification'!W23 -> 0 | AK23: =+AH23*100% -> 0 | AL23: =+AJ23-AK23 -> 0 | AM23: =+'Asset Classification'!X23 -> 0 | AN23: =+AI23*100% -> 0 | AO23: =+AM23-AN23 -> 0 | AP23: =+L23+T23+AB23+AJ23 -> 223364 | AQ23: =+M23+U23+AC23+AK23 -> 223364.5 | AR23: =+AP23-AQ23 -> -0.5 | AS23: =+O23+W23+AE23+AM23 -> 0 | AT23: =+P23+X23+AF23+AN23 -> 0 | AU23: =+AS23-AT23 -> 0 | AV23: =+'Aging Analysis'!C17 -> 2946729
B24: шундан, таъминланмаган қисми | C24: =+'Asset Classification'!C24 -> 0 | D24: =+'Asset Classification'!D24 -> 0 | E24: =+'Asset Classification'!E24 -> 0 | F24: =+'Asset Classification'!F24 -> 0 | G24: =+'Asset Classification'!G24 -> 0 | H24: =+E24*1% -> 0 | I24: =+G24-H24 -> 0 | J24: =+'Asset Classification'!I24 -> 0 | K24: =+'Asset Classification'!J24 -> 0 | L24: =+'Asset Classification'!K24 -> 0 | M24: =+J24*10% -> 0 | N24: =+L24-M24 -> 0 | O24: =+'Asset Classification'!L24 -> 0 | P24: =+K24*10% -> 0 | Q24: =+O24-P24 -> 0 | R24: =+'Asset Classification'!M24 -> 0 | S24: =+'Asset Classification'!N24 -> 0 | T24: =+'Asset Classification'!O24 -> 0 | U24: =+R24*25% -> 0 | V24: =+T24-U24 -> 0 | W24: =+'Asset Classification'!P24 -> 0 | X24: =+S24*25% -> 0 | Y24: =+W24-X24 -> 0 | Z24: =+'Asset Classification'!Q24 -> 0 | AA24: =+'Asset Classification'!R24 -> 0 | AB24: =+'Asset Classification'!S24 -> 0 | AC24: =+Z24*50% -> 0 | AD24: =+AB24-AC24 -> 0 | AE24: =+'Asset Classification'!T24 -> 0 | AF24: =+AA24*50% -> 0 | AG24: =+AE24-AF24 -> 0 | AH24: =+'Asset Classification'!U24 -> 0 | AI24: =+'Asset Classification'!V24 -> 0 | AJ24: =+'Asset Classification'!W24 -> 0 | AK24: =+AH24*100% -> 0 | AL24: =+AJ24-AK24 -> 0 | AM24: =+'Asset Classification'!X24 -> 0 | AN24: =+AI24*100% -> 0 | AO24: =+AM24-AN24 -> 0 | AP24: =+L24+T24+AB24+AJ24 -> 0 | AQ24: =+M24+U24+AC24+AK24 -> 0 | AR24: =+AP24-AQ24 -> 0 | AS24: =+O24+W24+AE24+AM24 -> 0 | AT24: =+P24+X24+AF24+AN24 -> 0 | AU24: =+AS24-AT24 -> 0
A25: 10 | B25: Нодавлат нотижорат ташкилотлар | C25: =+'Asset Classification'!C25 -> 1605566 | D25: =+'Asset Classification'!D25 -> 0 | E25: =+'Asset Classification'!E25 -> 1467441 | F25: =+'Asset Classification'!F25 -> 0 | G25: =+'Asset Classification'!G25 -> 14674 | H25: =+E25*1% -> 14674.41 | I25: =+G25-H25 -> -0.41 | J25: =+'Asset Classification'!I25 -> 0 | K25: =+'Asset Classification'!J25 -> 0 | L25: =+'Asset Classification'!K25 -> 0 | M25: =+J25*10% -> 0 | N25: =+L25-M25 -> 0 | O25: =+'Asset Classification'!L25 -> 0 | P25: =+K25*10% -> 0 | Q25: =+O25-P25 -> 0 | R25: =+'Asset Classification'!M25 -> 138125 | S25: =+'Asset Classification'!N25 -> 0 | T25: =+'Asset Classification'!O25 -> 34531 | U25: =+R25*25% -> 34531.25 | V25: =+T25-U25 -> -0.25 | W25: =+'Asset Classification'!P25 -> 0 | X25: =+S25*25% -> 0 | Y25: =+W25-X25 -> 0 | Z25: =+'Asset Classification'!Q25 -> 0 | AA25: =+'Asset Classification'!R25 -> 0 | AB25: =+'Asset Classification'!S25 -> 0 | AC25: =+Z25*50% -> 0 | AD25: =+AB25-AC25 -> 0 | AE25: =+'Asset Classification'!T25 -> 0 | AF25: =+AA25*50% -> 0 | AG25: =+AE25-AF25 -> 0 | AH25: =+'Asset Classification'!U25 -> 0 | AI25: =+'Asset Classification'!V25 -> 0 | AJ25: =+'Asset Classification'!W25 -> 0 | AK25: =+AH25*100% -> 0 | AL25: =+AJ25-AK25 -> 0 | AM25: =+'Asset Classification'!X25 -> 0 | AN25: =+AI25*100% -> 0 | AO25: =+AM25-AN25 -> 0 | AP25: =+L25+T25+AB25+AJ25 -> 34531 | AQ25: =+M25+U25+AC25+AK25 -> 34531.25 | AR25: =+AP25-AQ25 -> -0.25 | AS25: =+O25+W25+AE25+AM25 -> 0 | AT25: =+P25+X25+AF25+AN25 -> 0 | AU25: =+AS25-AT25 -> 0 | AV25: =+'Aging Analysis'!C18 -> 1605566
B26: шундан, таъминланмаган қисми | C26: =+'Asset Classification'!C26 -> 0 | D26: =+'Asset Classification'!D26 -> 0 | E26: =+'Asset Classification'!E26 -> 0 | F26: =+'Asset Classification'!F26 -> 0 | G26: =+'Asset Classification'!G26 -> 0 | H26: =+E26*1% -> 0 | I26: =+G26-H26 -> 0 | J26: =+'Asset Classification'!I26 -> 0 | K26: =+'Asset Classification'!J26 -> 0 | L26: =+'Asset Classification'!K26 -> 0 | M26: =+J26*10% -> 0 | N26: =+L26-M26 -> 0 | O26: =+'Asset Classification'!L26 -> 0 | P26: =+K26*10% -> 0 | Q26: =+O26-P26 -> 0 | R26: =+'Asset Classification'!M26 -> 0 | S26: =+'Asset Classification'!N26 -> 0 | T26: =+'Asset Classification'!O26 -> 0 | U26: =+R26*25% -> 0 | V26: =+T26-U26 -> 0 | W26: =+'Asset Classification'!P26 -> 0 | X26: =+S26*25% -> 0 | Y26: =+W26-X26 -> 0 | Z26: =+'Asset Classification'!Q26 -> 0 | AA26: =+'Asset Classification'!R26 -> 0 | AB26: =+'Asset Classification'!S26 -> 0 | AC26: =+Z26*50% -> 0 | AD26: =+AB26-AC26 -> 0 | AE26: =+'Asset Classification'!T26 -> 0 | AF26: =+AA26*50% -> 0 | AG26: =+AE26-AF26 -> 0 | AH26: =+'Asset Classification'!U26 -> 0 | AI26: =+'Asset Classification'!V26 -> 0 | AJ26: =+'Asset Classification'!W26 -> 0 | AK26: =+AH26*100% -> 0 | AL26: =+AJ26-AK26 -> 0 | AM26: =+'Asset Classification'!X26 -> 0 | AN26: =+AI26*100% -> 0 | AO26: =+AM26-AN26 -> 0 | AP26: =+L26+T26+AB26+AJ26 -> 0 | AQ26: =+M26+U26+AC26+AK26 -> 0 | AR26: =+AP26-AQ26 -> 0 | AS26: =+O26+W26+AE26+AM26 -> 0 | AT26: =+P26+X26+AF26+AN26 -> 0 | AU26: =+AS26-AT26 -> 0
A27: 11 | B27: Бюджет ташкилотлари | C27: =+'Asset Classification'!C27 -> 0 | D27: =+'Asset Classification'!D27 -> 0 | E27: =+'Asset Classification'!E27 -> 0 | F27: =+'Asset Classification'!F27 -> 0 | G27: =+'Asset Classification'!G27 -> 0 | H27: =+E27*1% -> 0 | I27: =+G27-H27 -> 0 | J27: =+'Asset Classification'!I27 -> 0 | K27: =+'Asset Classification'!J27 -> 0 | L27: =+'Asset Classification'!K27 -> 0 | M27: =+J27*10% -> 0 | N27: =+L27-M27 -> 0 | O27: =+'Asset Classification'!L27 -> 0 | P27: =+K27*10% -> 0 | Q27: =+O27-P27 -> 0 | R27: =+'Asset Classification'!M27 -> 0 | S27: =+'Asset Classification'!N27 -> 0 | T27: =+'Asset Classification'!O27 -> 0 | U27: =+R27*25% -> 0 | V27: =+T27-U27 -> 0 | W27: =+'Asset Classification'!P27 -> 0 | X27: =+S27*25% -> 0 | Y27: =+W27-X27 -> 0 | Z27: =+'Asset Classification'!Q27 -> 0 | AA27: =+'Asset Classification'!R27 -> 0 | AB27: =+'Asset Classification'!S27 -> 0 | AC27: =+Z27*50% -> 0 | AD27: =+AB27-AC27 -> 0 | AE27: =+'Asset Classification'!T27 -> 0 | AF27: =+AA27*50% -> 0 | AG27: =+AE27-AF27 -> 0 | AH27: =+'Asset Classification'!U27 -> 0 | AI27: =+'Asset Classification'!V27 -> 0 | AJ27: =+'Asset Classification'!W27 -> 0 | AK27: =+AH27*100% -> 0 | AL27: =+AJ27-AK27 -> 0 | AM27: =+'Asset Classification'!X27 -> 0 | AN27: =+AI27*100% -> 0 | AO27: =+AM27-AN27 -> 0 | AP27: =+L27+T27+AB27+AJ27 -> 0 | AQ27: =+M27+U27+AC27+AK27 -> 0 | AR27: =+AP27-AQ27 -> 0 | AS27: =+O27+W27+AE27+AM27 -> 0 | AT27: =+P27+X27+AF27+AN27 -> 0 | AU27: =+AS27-AT27 -> 0 | AV27: =+'Aging Analysis'!C19 -> 0
B28: шундан, таъминланмаган қисми | C28: =+'Asset Classification'!C28 -> 0 | D28: =+'Asset Classification'!D28 -> 0 | E28: =+'Asset Classification'!E28 -> 0 | F28: =+'Asset Classification'!F28 -> 0 | G28: =+'Asset Classification'!G28 -> 0 | H28: =+E28*1% -> 0 | I28: =+G28-H28 -> 0 | J28: =+'Asset Classification'!I28 -> 0 | K28: =+'Asset Classification'!J28 -> 0 | L28: =+'Asset Classification'!K28 -> 0 | M28: =+J28*10% -> 0 | N28: =+L28-M28 -> 0 | O28: =+'Asset Classification'!L28 -> 0 | P28: =+K28*10% -> 0 | Q28: =+O28-P28 -> 0 | R28: =+'Asset Classification'!M28 -> 0 | S28: =+'Asset Classification'!N28 -> 0 | T28: =+'Asset Classification'!O28 -> 0 | U28: =+R28*25% -> 0 | V28: =+T28-U28 -> 0 | W28: =+'Asset Classification'!P28 -> 0 | X28: =+S28*25% -> 0 | Y28: =+W28-X28 -> 0 | Z28: =+'Asset Classification'!Q28 -> 0 | AA28: =+'Asset Classification'!R28 -> 0 | AB28: =+'Asset Classification'!S28 -> 0 | AC28: =+Z28*50% -> 0 | AD28: =+AB28-AC28 -> 0 | AE28: =+'Asset Classification'!T28 -> 0 | AF28: =+AA28*50% -> 0 | AG28: =+AE28-AF28 -> 0 | AH28: =+'Asset Classification'!U28 -> 0 | AI28: =+'Asset Classification'!V28 -> 0 | AJ28: =+'Asset Classification'!W28 -> 0 | AK28: =+AH28*100% -> 0 | AL28: =+AJ28-AK28 -> 0 | AM28: =+'Asset Classification'!X28 -> 0 | AN28: =+AI28*100% -> 0 | AO28: =+AM28-AN28 -> 0 | AP28: =+L28+T28+AB28+AJ28 -> 0 | AQ28: =+M28+U28+AC28+AK28 -> 0 | AR28: =+AP28-AQ28 -> 0 | AS28: =+O28+W28+AE28+AM28 -> 0 | AT28: =+P28+X28+AF28+AN28 -> 0 | AU28: =+AS28-AT28 -> 0
A29: 12 | B29: Бошқалар | C29: =+'Asset Classification'!C29 -> 0 | D29: =+'Asset Classification'!D29 -> 0 | E29: =+'Asset Classification'!E29 -> 0 | F29: =+'Asset Classification'!F29 -> 0 | G29: =+'Asset Classification'!G29 -> 0 | H29: =+E29*1% -> 0 | I29: =+G29-H29 -> 0 | J29: =+'Asset Classification'!I29 -> 0 | K29: =+'Asset Classification'!J29 -> 0 | L29: =+'Asset Classification'!K29 -> 0 | M29: =+J29*10% -> 0 | N29: =+L29-M29 -> 0 | O29: =+'Asset Classification'!L29 -> 0 | P29: =+K29*10% -> 0 | Q29: =+O29-P29 -> 0 | R29: =+'Asset Classification'!M29 -> 0 | S29: =+'Asset Classification'!N29 -> 0 | T29: =+'Asset Classification'!O29 -> 0 | U29: =+R29*25% -> 0 | V29: =+T29-U29 -> 0 | W29: =+'Asset Classification'!P29 -> 0 | X29: =+S29*25% -> 0 | Y29: =+W29-X29 -> 0 | Z29: =+'Asset Classification'!Q29 -> 0 | AA29: =+'Asset Classification'!R29 -> 0 | AB29: =+'Asset Classification'!S29 -> 0 | AC29: =+Z29*50% -> 0 | AD29: =+AB29-AC29 -> 0 | AE29: =+'Asset Classification'!T29 -> 0 | AF29: =+AA29*50% -> 0 | AG29: =+AE29-AF29 -> 0 | AH29: =+'Asset Classification'!U29 -> 0 | AI29: =+'Asset Classification'!V29 -> 0 | AJ29: =+'Asset Classification'!W29 -> 0 | AK29: =+AH29*100% -> 0 | AL29: =+AJ29-AK29 -> 0 | AM29: =+'Asset Classification'!X29 -> 0 | AN29: =+AI29*100% -> 0 | AO29: =+AM29-AN29 -> 0 | AP29: =+L29+T29+AB29+AJ29 -> 0 | AQ29: =+M29+U29+AC29+AK29 -> 0 | AR29: =+AP29-AQ29 -> 0 | AS29: =+O29+W29+AE29+AM29 -> 0 | AT29: =+P29+X29+AF29+AN29 -> 0 | AU29: =+AS29-AT29 -> 0 | AV29: =+'Aging Analysis'!C20 -> 0
B30: шундан, таъминланмаган қисми | C30: =+'Asset Classification'!C30 -> 0 | D30: =+'Asset Classification'!D30 -> 0 | E30: =+'Asset Classification'!E30 -> 0 | F30: =+'Asset Classification'!F30 -> 0 | G30: =+'Asset Classification'!G30 -> 0 | H30: =+E30*1% -> 0 | I30: =+G30-H30 -> 0 | J30: =+'Asset Classification'!I30 -> 0 | K30: =+'Asset Classification'!J30 -> 0 | L30: =+'Asset Classification'!K30 -> 0 | M30: =+J30*10% -> 0 | N30: =+L30-M30 -> 0 | O30: =+'Asset Classification'!L30 -> 0 | P30: =+K30*10% -> 0 | Q30: =+O30-P30 -> 0 | R30: =+'Asset Classification'!M30 -> 0 | S30: =+'Asset Classification'!N30 -> 0 | T30: =+'Asset Classification'!O30 -> 0 | U30: =+R30*25% -> 0 | V30: =+T30-U30 -> 0 | W30: =+'Asset Classification'!P30 -> 0 | X30: =+S30*25% -> 0 | Y30: =+W30-X30 -> 0 | Z30: =+'Asset Classification'!Q30 -> 0 | AA30: =+'Asset Classification'!R30 -> 0 | AB30: =+'Asset Classification'!S30 -> 0 | AC30: =+Z30*50% -> 0 | AD30: =+AB30-AC30 -> 0 | AE30: =+'Asset Classification'!T30 -> 0 | AF30: =+AA30*50% -> 0 | AG30: =+AE30-AF30 -> 0 | AH30: =+'Asset Classification'!U30 -> 0 | AI30: =+'Asset Classification'!V30 -> 0 | AJ30: =+'Asset Classification'!W30 -> 0 | AK30: =+AH30*100% -> 0 | AL30: =+AJ30-AK30 -> 0 | AM30: =+'Asset Classification'!X30 -> 0 | AN30: =+AI30*100% -> 0 | AO30: =+AM30-AN30 -> 0 | AP30: =+L30+T30+AB30+AJ30 -> 0 | AQ30: =+M30+U30+AC30+AK30 -> 0 | AR30: =+AP30-AQ30 -> 0 | AS30: =+O30+W30+AE30+AM30 -> 0 | AT30: =+P30+X30+AF30+AN30 -> 0 | AU30: =+AS30-AT30 -> 0
A31: 13 | B31: Жами кредит ва лизинг суммаси | C31: =+'Asset Classification'!C31 -> 57124403912 | D31: =+'Asset Classification'!D31 -> 38012960642 | E31: =+'Asset Classification'!E31 -> 49548751261 | F31: =+'Asset Classification'!F31 -> 32899887295 | G31: =+'Asset Classification'!G31 -> 504953973 | H31: =+H7+H9+H11+H13+H15+H17+H19+H21+H23+H25+H27+H29 -> 4.9548751e+08 | I31: =+I7+I9+I11+I13+I15+I17+I19+I21+I23+I25+I27+I29 -> 9466460.4 | J31: =+'Asset Classification'!I31 -> 6292476722 | K31: =+'Asset Classification'!J31 -> 4289653575 | L31: =+'Asset Classification'!K31 -> 620122045 | M31: =+M7+M9+M11+M13+M15+M17+M19+M21+M23+M25+M27+M29 -> 6.2924767e+08 | N31: =+N7+N9+N11+N13+N15+N17+N19+N21+N23+N25+N27+N29 -> -9125627.2 | O31: =+'Asset Classification'!L31 -> 419611589 | P31: =+P7+P9+P11+P13+P15+P17+P19+P21+P23+P25+P27+P29 -> 4.2896536e+08 | Q31: =+Q7+Q9+Q11+Q13+Q15+Q17+Q19+Q21+Q23+Q25+Q27+Q29 -> -9353768.5 | R31: =+'Asset Classification'!M31 -> 506004487 | S31: =+'Asset Classification'!N31 -> 263138435 | T31: =+'Asset Classification'!O31 -> 126501133 | U31: =+U7+U9+U11+U13+U15+U17+U19+U21+U23+U25+U27+U29 -> 1.2650112e+08 | V31: =+V7+V9+V11+V13+V15+V17+V19+V21+V23+V25+V27+V29 -> 11.25 | W31: =+'Asset Classification'!P31 -> 65784610 | X31: =+X7+X9+X11+X13+X15+X17+X19+X21+X23+X25+X27+X29 -> 65784609 | Y31: =+Y7+Y9+Y11+Y13+Y15+Y17+Y19+Y21+Y23+Y25+Y27+Y29 -> 1.25 | Z31: =+'Asset Classification'!Q31 -> 749932110 | AA31: =+'Asset Classification'!R31 -> 545624112 | AB31: =+'Asset Classification'!S31 -> 374966057 | AC31: =+AC7+AC9+AC11+AC13+AC15+AC17+AC19+AC21+AC23+AC25+AC27+AC29 -> 374966055 | AD31: =+AD7+AD9+AD11+AD13+AD15+AD17+AD19+AD21+AD23+AD25+AD27+AD29 -> 2 | AE31: =+'Asset Classification'!T31 -> 272812058 | AF31: =+AF7+AF9+AF11+AF13+AF15+AF17+AF19+AF21+AF23+AF25+AF27+AF29 -> 272812056 | AG31: =+AG7+AG9+AG11+AG13+AG15+AG17+AG19+AG21+AG23+AG25+AG27+AG29 -> 2 | AH31: =+'Asset Classification'!U31 -> 27239332 | AI31: =+'Asset Classification'!V31 -> 14657225 | AJ31: =+'Asset Classification'!W31 -> 27239332 | AK31: =+AK7+AK9+AK11+AK13+AK15+AK17+AK19+AK21+AK23+AK25+AK27+AK29 -> 27239332 | AL31: =+AL7+AL9+AL11+AL13+AL15+AL17+AL19+AL21+AL23+AL25+AL27+AL29 -> 0 | AM31: =+'Asset Classification'!X31 -> 14657225 | AN31: =+AN7+AN9+AN11+AN13+AN15+AN17+AN19+AN21+AN23+AN25+AN27+AN29 -> 14657225 | AO31: =+AO7+AO9+AO11+AO13+AO15+AO17+AO19+AO21+AO23+AO25+AO27+AO29 -> 0 | AP31: =+AP7+AP9+AP11+AP13+AP15+AP17+AP19+AP21+AP23+AP25+AP27+AP29 -> 1148828567 | AQ31: =+AQ7+AQ9+AQ11+AQ13+AQ15+AQ17+AQ19+AQ21+AQ23+AQ25+AQ27+AQ29 -> 1.1579542e+09 | AR31: =+AR7+AR9+AR11+AR13+AR15+AR17+AR19+AR21+AR23+AR25+AR27+AR29 -> -9125613.9 | AS31: =+AS7+AS9+AS11+AS13+AS15+AS17+AS19+AS21+AS23+AS25+AS27+AS29 -> 772865482 | AT31: =+AT7+AT9+AT11+AT13+AT15+AT17+AT19+AT21+AT23+AT25+AT27+AT29 -> 7.8221925e+08 | AU31: =+AU7+AU9+AU11+AU13+AU15+AU17+AU19+AU21+AU23+AU25+AU27+AU29 -> -9353765.3 | AV31: =+'Loans Receivable'!C85 -> 57124403912
B32: шундан, таъминланмаган қисми | C32: =+'Asset Classification'!C32 -> 0 | D32: =+'Asset Classification'!D32 -> 0 | E32: =+'Asset Classification'!E32 -> 0 | F32: =+'Asset Classification'!F32 -> 0 | G32: =+'Asset Classification'!G32 -> 0 | H32: =+E32*1% -> 0 | I32: =+G32-H32 -> 0 | J32: =+'Asset Classification'!I32 -> 0 | K32: =+'Asset Classification'!J32 -> 0 | L32: =+'Asset Classification'!K32 -> 0 | M32: =+J32*10% -> 0 | N32: =+L32-M32 -> 0 | O32: =+'Asset Classification'!L32 -> 0 | P32: =+K32*10% -> 0 | Q32: =+O32-P32 -> 0 | R32: =+'Asset Classification'!M32 -> 0 | S32: =+'Asset Classification'!N32 -> 0 | T32: =+'Asset Classification'!O32 -> 0 | U32: =+R32*25% -> 0 | V32: =+T32-U32 -> 0 | W32: =+'Asset Classification'!P32 -> 0 | X32: =+S32*25% -> 0 | Y32: =+W32-X32 -> 0 | Z32: =+'Asset Classification'!Q32 -> 0 | AA32: =+'Asset Classification'!R32 -> 0 | AB32: =+'Asset Classification'!S32 -> 0 | AC32: =+Z32*50% -> 0 | AD32: =+AB32-AC32 -> 0 | AE32: =+'Asset Classification'!T32 -> 0 | AF32: =+AA32*50% -> 0 | AG32: =+AE32-AF32 -> 0 | AH32: =+'Asset Classification'!U32 -> 0 | AI32: =+'Asset Classification'!V32 -> 0 | AJ32: =+'Asset Classification'!W32 -> 0 | AK32: =+AH32*100% -> 0 | AL32: =+AJ32-AK32 -> 0 | AM32: =+'Asset Classification'!X32 -> 0 | AN32: =+AI32*100% -> 0 | AO32: =+AM32-AN32 -> 0 | AP32: =+L32+T32+AB32+AJ32 -> 0 | AQ32: =+M32+U32+AC32+AK32 -> 0 | AR32: =+AP32-AQ32 -> 0 | AS32: =+O32+W32+AE32+AM32 -> 0 | AT32: =+P32+X32+AF32+AN32 -> 0 | AU32: =+AS32-AT32 -> 0
B33: Иқтисодиёт соҳалари бўйича
A35: 14 | B35: Саноат | C35: =+'Asset Classification'!C35 -> 29912501071 | D35: =+'Asset Classification'!D35 -> 25149127213 | E35: =+'Asset Classification'!E35 -> 25737314100 | F35: =+'Asset Classification'!F35 -> 21765633152 | G35: =+'Asset Classification'!G35 -> 266839601 | H35: =+E35*1% -> 257373141 | I35: =+G35-H35 -> 9466460 | J35: =+'Asset Classification'!I35 -> 3674332106 | K35: =+'Asset Classification'!J35 -> 2980287888 | L35: =+'Asset Classification'!K35 -> 358079441 | M35: =+J35*10% -> 3.6743321e+08 | N35: =+L35-M35 -> -9353769.6 | O35: =+'Asset Classification'!L35 -> 288675019 | P35: =+K35*10% -> 2.9802879e+08 | Q35: =+O35-P35 -> -9353769.8 | R35: =+'Asset Classification'!M35 -> 201641115 | S35: =+'Asset Classification'!N35 -> 137499976 | T35: =+'Asset Classification'!O35 -> 50410279 | U35: =+R35*25% -> 50410279 | V35: =+T35-U35 -> 0.25 | W35: =+'Asset Classification'!P35 -> 34374994 | X35: =+S35*25% -> 34374994 | Y35: =+W35-X35 -> 0 | Z35: =+'Asset Classification'!Q35 -> 289245258 | AA35: =+'Asset Classification'!R35 -> 255737705 | AB35: =+'Asset Classification'!S35 -> 144622629 | AC35: =+Z35*50% -> 144622629 | AD35: =+AB35-AC35 -> 0 | AE35: =+'Asset Classification'!T35 -> 127868853 | AF35: =+AA35*50% -> 1.2786885e+08 | AG35: =+AE35-AF35 -> 0.5 | AH35: =+'Asset Classification'!U35 -> 9968492 | AI35: =+'Asset Classification'!V35 -> 9968492 | AJ35: =+'Asset Classification'!W35 -> 9968492 | AK35: =+AH35*100% -> 9968492 | AL35: =+AJ35-AK35 -> 0 | AM35: =+'Asset Classification'!X35 -> 9968492 | AN35: =+AI35*100% -> 9968492 | AO35: =+AM35-AN35 -> 0 | AP35: =+L35+T35+AB35+AJ35 -> 563080841 | AQ35: =+M35+U35+AC35+AK35 -> 5.7243461e+08 | AR35: =+AP35-AQ35 -> -9353769.4 | AS35: =+O35+W35+AE35+AM35 -> 460887358 | AT35: =+P35+X35+AF35+AN35 -> 4.7024113e+08 | AU35: =+AS35-AT35 -> -9353769.3 | AV35: =+'Aging Analysis'!C25 -> 29912501071
B36: шундан, таъминланмаган қисми | C36: =+'Asset Classification'!C36 -> 0 | D36: =+'Asset Classification'!D36 -> 0 | E36: =+'Asset Classification'!E36 -> 0 | F36: =+'Asset Classification'!F36 -> 0 | G36: =+'Asset Classification'!G36 -> 0 | H36: =+E36*1% -> 0 | I36: =+G36-H36 -> 0 | J36: =+'Asset Classification'!I36 -> 0 | K36: =+'Asset Classification'!J36 -> 0 | L36: =+'Asset Classification'!K36 -> 0 | M36: =+J36*10% -> 0 | N36: =+L36-M36 -> 0 | O36: =+'Asset Classification'!L36 -> 0 | P36: =+K36*10% -> 0 | Q36: =+O36-P36 -> 0 | R36: =+'Asset Classification'!M36 -> 0 | S36: =+'Asset Classification'!N36 -> 0 | T36: =+'Asset Classification'!O36 -> 0 | U36: =+R36*25% -> 0 | V36: =+T36-U36 -> 0 | W36: =+'Asset Classification'!P36 -> 0 | X36: =+S36*25% -> 0 | Y36: =+W36-X36 -> 0 | Z36: =+'Asset Classification'!Q36 -> 0 | AA36: =+'Asset Classification'!R36 -> 0 | AB36: =+'Asset Classification'!S36 -> 0 | AC36: =+Z36*50% -> 0 | AD36: =+AB36-AC36 -> 0 | AE36: =+'Asset Classification'!T36 -> 0 | AF36: =+AA36*50% -> 0 | AG36: =+AE36-AF36 -> 0 | AH36: =+'Asset Classification'!U36 -> 0 | AI36: =+'Asset Classification'!V36 -> 0 | AJ36: =+'Asset Classification'!W36 -> 0 | AK36: =+AH36*100% -> 0 | AL36: =+AJ36-AK36 -> 0 | AM36: =+'Asset Classification'!X36 -> 0 | AN36: =+AI36*100% -> 0 | AO36: =+AM36-AN36 -> 0 | AP36: =+L36+T36+AB36+AJ36 -> 0 | AQ36: =+M36+U36+AC36+AK36 -> 0 | AR36: =+AP36-AQ36 -> 0 | AS36: =+O36+W36+AE36+AM36 -> 0 | AT36: =+P36+X36+AF36+AN36 -> 0 | AU36: =+AS36-AT36 -> 0
A37: 15 | B37: Қишлоқ хўжалиги | C37: =+'Asset Classification'!C37 -> 4926336219 | D37: =+'Asset Classification'!D37 -> 2565841116 | E37: =+'Asset Classification'!E37 -> 3549549874 | F37: =+'Asset Classification'!F37 -> 2221465659 | G37: =+'Asset Classification'!G37 -> 35495499 | H37: =+E37*1% -> 35495499 | I37: =+G37-H37 -> 0.26 | J37: =+'Asset Classification'!I37 -> 1099095807 | K37: =+'Asset Classification'!J37 -> 160927246 | L37: =+'Asset Classification'!K37 -> 110139615 | M37: =+J37*10% -> 1.0990958e+08 | N37: =+L37-M37 -> 230034.3 | O37: =+'Asset Classification'!L37 -> 16092725 | P37: =+K37*10% -> 16092725 | Q37: =+O37-P37 -> 0.4 | R37: =+'Asset Classification'!M37 -> 109207519 | S37: =+'Asset Classification'!N37 -> 20364628 | T37: =+'Asset Classification'!O37 -> 27301880 | U37: =+R37*25% -> 27301880 | V37: =+T37-U37 -> 0.25 | W37: =+'Asset Classification'!P37 -> 5091157 | X37: =+S37*25% -> 5091157 | Y37: =+W37-X37 -> 0 | Z37: =+'Asset Classification'!Q37 -> 168483019 | AA37: =+'Asset Classification'!R37 -> 163083583 | AB37: =+'Asset Classification'!S37 -> 84241510 | AC37: =+Z37*50% -> 84241510 | AD37: =+AB37-AC37 -> 0.5 | AE37: =+'Asset Classification'!T37 -> 81541792 | AF37: =+AA37*50% -> 81541792 | AG37: =+AE37-AF37 -> 0.5 | AH37: =+'Asset Classification'!U37 -> 0 | AI37: =+'Asset Classification'!V37 -> 0 | AJ37: =+'Asset Classification'!W37 -> 0 | AK37: =+AH37*100% -> 0 | AL37: =+AJ37-AK37 -> 0 | AM37: =+'Asset Classification'!X37 -> 0 | AN37: =+AI37*100% -> 0 | AO37: =+AM37-AN37 -> 0 | AP37: =+L37+T37+AB37+AJ37 -> 221683005 | AQ37: =+M37+U37+AC37+AK37 -> 2.2145297e+08 | AR37: =+AP37-AQ37 -> 230035.05 | AS37: =+O37+W37+AE37+AM37 -> 102725674 | AT37: =+P37+X37+AF37+AN37 -> 1.0272567e+08 | AU37: =+AS37-AT37 -> 0.90000001 | AV37: =+'Aging Analysis'!C26 -> 4926336219
B38: шундан, таъминланмаган қисми | C38: =+'Asset Classification'!C38 -> 0 | D38: =+'Asset Classification'!D38 -> 0 | E38: =+'Asset Classification'!E38 -> 0 | F38: =+'Asset Classification'!F38 -> 0 | G38: =+'Asset Classification'!G38 -> 0 | H38: =+E38*1% -> 0 | I38: =+G38-H38 -> 0 | J38: =+'Asset Classification'!I38 -> 0 | K38: =+'Asset Classification'!J38 -> 0 | L38: =+'Asset Classification'!K38 -> 0 | M38: =+J38*10% -> 0 | N38: =+L38-M38 -> 0 | O38: =+'Asset Classification'!L38 -> 0 | P38: =+K38*10% -> 0 | Q38: =+O38-P38 -> 0 | R38: =+'Asset Classification'!M38 -> 0 | S38: =+'Asset Classification'!N38 -> 0 | T38: =+'Asset Classification'!O38 -> 0 | U38: =+R38*25% -> 0 | V38: =+T38-U38 -> 0 | W38: =+'Asset Classification'!P38 -> 0 | X38: =+S38*25% -> 0 | Y38: =+W38-X38 -> 0 | Z38: =+'Asset Classification'!Q38 -> 0 | AA38: =+'Asset Classification'!R38 -> 0 | AB38: =+'Asset Classification'!S38 -> 0 | AC38: =+Z38*50% -> 0 | AD38: =+AB38-AC38 -> 0 | AE38: =+'Asset Classification'!T38 -> 0 | AF38: =+AA38*50% -> 0 | AG38: =+AE38-AF38 -> 0 | AH38: =+'Asset Classification'!U38 -> 0 | AI38: =+'Asset Classification'!V38 -> 0 | AJ38: =+'Asset Classification'!W38 -> 0 | AK38: =+AH38*100% -> 0 | AL38: =+AJ38-AK38 -> 0 | AM38: =+'Asset Classification'!X38 -> 0 | AN38: =+AI38*100% -> 0 | AO38: =+AM38-AN38 -> 0 | AP38: =+L38+T38+AB38+AJ38 -> 0 | AQ38: =+M38+U38+AC38+AK38 -> 0 | AR38: =+AP38-AQ38 -> 0 | AS38: =+O38+W38+AE38+AM38 -> 0 | AT38: =+P38+X38+AF38+AN38 -> 0 | AU38: =+AS38-AT38 -> 0
A39: 16 | B39: Транспорт ва коммуникация | C39: =+'Asset Classification'!C39 -> 3968113322 | D39: =+'Asset Classification'!D39 -> 3847597829 | E39: =+'Asset Classification'!E39 -> 3879856301 | F39: =+'Asset Classification'!F39 -> 3779257642 | G39: =+'Asset Classification'!G39 -> 38798563 | H39: =+E39*1% -> 38798563 | I39: =+G39-H39 -> -0.0099999979 | J39: =+'Asset Classification'!I39 -> 19500899 | K39: =+'Asset Classification'!J39 -> 17908156 | L39: =+'Asset Classification'!K39 -> 1950090 | M39: =+J39*10% -> 1950089.9 | N39: =+L39-M39 -> 0.1 | O39: =+'Asset Classification'!L39 -> 1790816 | P39: =+K39*10% -> 1790815.6 | Q39: =+O39-P39 -> 0.4 | R39: =+'Asset Classification'!M39 -> 63274014 | S39: =+'Asset Classification'!N39 -> 50432031 | T39: =+'Asset Classification'!O39 -> 15818503 | U39: =+R39*25% -> 15818504 | V39: =+T39-U39 -> -0.5 | W39: =+'Asset Classification'!P39 -> 12608008 | X39: =+S39*25% -> 12608008 | Y39: =+W39-X39 -> 0.25 | Z39: =+'Asset Classification'!Q39 -> 3800001 | AA39: =+'Asset Classification'!R39 -> 0 | AB39: =+'Asset Classification'!S39 -> 1900001 | AC39: =+Z39*50% -> 1900000.5 | AD39: =+AB39-AC39 -> 0.5 | AE39: =+'Asset Classification'!T39 -> 0 | AF39: =+AA39*50% -> 0 | AG39: =+AE39-AF39 -> 0 | AH39: =+'Asset Classification'!U39 -> 1682107 | AI39: =+'Asset Classification'!V39 -> 0 | AJ39: =+'Asset Classification'!W39 -> 1682107 | AK39: =+AH39*100% -> 1682107 | AL39: =+AJ39-AK39 -> 0 | AM39: =+'Asset Classification'!X39 -> 0 | AN39: =+AI39*100% -> 0 | AO39: =+AM39-AN39 -> 0 | AP39: =+L39+T39+AB39+AJ39 -> 21350701 | AQ39: =+M39+U39+AC39+AK39 -> 21350701 | AR39: =+AP39-AQ39 -> 0.1 | AS39: =+O39+W39+AE39+AM39 -> 14398824 | AT39: =+P39+X39+AF39+AN39 -> 14398823 | AU39: =+AS39-AT39 -> 0.65 | AV39: =+'Aging Analysis'!C27 -> 3968113322
B40: шундан, таъминланмаган қисми | C40: =+'Asset Classification'!C40 -> 0 | D40: =+'Asset Classification'!D40 -> 0 | E40: =+'Asset Classification'!E40 -> 0 | F40: =+'Asset Classification'!F40 -> 0 | G40: =+'Asset Classification'!G40 -> 0 | H40: =+E40*1% -> 0 | I40: =+G40-H40 -> 0 | J40: =+'Asset Classification'!I40 -> 0 | K40: =+'Asset Classification'!J40 -> 0 | L40: =+'Asset Classification'!K40 -> 0 | M40: =+J40*10% -> 0 | N40: =+L40-M40 -> 0 | O40: =+'Asset Classification'!L40 -> 0 | P40: =+K40*10% -> 0 | Q40: =+O40-P40 -> 0 | R40: =+'Asset Classification'!M40 -> 0 | S40: =+'Asset Classification'!N40 -> 0 | T40: =+'Asset Classification'!O40 -> 0 | U40: =+R40*25% -> 0 | V40: =+T40-U40 -> 0 | W40: =+'Asset Classification'!P40 -> 0 | X40: =+S40*25% -> 0 | Y40: =+W40-X40 -> 0 | Z40: =+'Asset Classification'!Q40 -> 0 | AA40: =+'Asset Classification'!R40 -> 0 | AB40: =+'Asset Classification'!S40 -> 0 | AC40: =+Z40*50% -> 0 | AD40: =+AB40-AC40 -> 0 | AE40: =+'Asset Classification'!T40 -> 0 | AF40: =+AA40*50% -> 0 | AG40: =+AE40-AF40 -> 0 | AH40: =+'Asset Classification'!U40 -> 0 | AI40: =+'Asset Classification'!V40 -> 0 | AJ40: =+'Asset Classification'!W40 -> 0 | AK40: =+AH40*100% -> 0 | AL40: =+AJ40-AK40 -> 0 | AM40: =+'Asset Classification'!X40 -> 0 | AN40: =+AI40*100% -> 0 | AO40: =+AM40-AN40 -> 0 | AP40: =+L40+T40+AB40+AJ40 -> 0 | AQ40: =+M40+U40+AC40+AK40 -> 0 | AR40: =+AP40-AQ40 -> 0 | AS40: =+O40+W40+AE40+AM40 -> 0 | AT40: =+P40+X40+AF40+AN40 -> 0 | AU40: =+AS40-AT40 -> 0
A41: 17 | B41: Қурилиш соҳаси | C41: =+'Asset Classification'!C41 -> 1311758376 | D41: =+'Asset Classification'!D41 -> 942129303 | E41: =+'Asset Classification'!E41 -> 1168102135 | F41: =+'Asset Classification'!F41 -> 903217007 | G41: =+'Asset Classification'!G41 -> 11681021 | H41: =+E41*1% -> 11681021 | I41: =+G41-H41 -> -0.35 | J41: =+'Asset Classification'!I41 -> 48928444 | K41: =+'Asset Classification'!J41 -> 14901457 | L41: =+'Asset Classification'!K41 -> 4892844 | M41: =+J41*10% -> 4892844.4 | N41: =+L41-M41 -> -0.4 | O41: =+'Asset Classification'!L41 -> 1490146 | P41: =+K41*10% -> 1490145.7 | Q41: =+O41-P41 -> 0.3 | R41: =+'Asset Classification'!M41 -> 42918452 | S41: =+'Asset Classification'!N41 -> 1772113 | T41: =+'Asset Classification'!O41 -> 10729613 | U41: =+R41*25% -> 10729613 | V41: =+T41-U41 -> 0 | W41: =+'Asset Classification'!P41 -> 443028 | X41: =+S41*25% -> 443028.25 | Y41: =+W41-X41 -> -0.25 | Z41: =+'Asset Classification'!Q41 -> 51809345 | AA41: =+'Asset Classification'!R41 -> 22238726 | AB41: =+'Asset Classification'!S41 -> 25904673 | AC41: =+Z41*50% -> 25904672 | AD41: =+AB41-AC41 -> 0.5 | AE41: =+'Asset Classification'!T41 -> 11119363 | AF41: =+AA41*50% -> 11119363 | AG41: =+AE41-AF41 -> 0 | AH41: =+'Asset Classification'!U41 -> 0 | AI41: =+'Asset Classification'!V41 -> 0 | AJ41: =+'Asset Classification'!W41 -> 0 | AK41: =+AH41*100% -> 0 | AL41: =+AJ41-AK41 -> 0 | AM41: =+'Asset Classification'!X41 -> 0 | AN41: =+AI41*100% -> 0 | AO41: =+AM41-AN41 -> 0 | AP41: =+L41+T41+AB41+AJ41 -> 41527130 | AQ41: =+M41+U41+AC41+AK41 -> 41527130 | AR41: =+AP41-AQ41 -> 0.1 | AS41: =+O41+W41+AE41+AM41 -> 13052537 | AT41: =+P41+X41+AF41+AN41 -> 13052537 | AU41: =+AS41-AT41 -> 0.050000001 | AV41: =+'Aging Analysis'!C28 -> 1311758376
B42: шундан, таъминланмаган қисми | C42: =+'Asset Classification'!C42 -> 0 | D42: =+'Asset Classification'!D42 -> 0 | E42: =+'Asset Classification'!E42 -> 0 | F42: =+'Asset Classification'!F42 -> 0 | G42: =+'Asset Classification'!G42 -> 0 | H42: =+E42*1% -> 0 | I42: =+G42-H42 -> 0 | J42: =+'Asset Classification'!I42 -> 0 | K42: =+'Asset Classification'!J42 -> 0 | L42: =+'Asset Classification'!K42 -> 0 | M42: =+J42*10% -> 0 | N42: =+L42-M42 -> 0 | O42: =+'Asset Classification'!L42 -> 0 | P42: =+K42*10% -> 0 | Q42: =+O42-P42 -> 0 | R42: =+'Asset Classification'!M42 -> 0 | S42: =+'Asset Classification'!N42 -> 0 | T42: =+'Asset Classification'!O42 -> 0 | U42: =+R42*25% -> 0 | V42: =+T42-U42 -> 0 | W42: =+'Asset Classification'!P42 -> 0 | X42: =+S42*25% -> 0 | Y42: =+W42-X42 -> 0 | Z42: =+'Asset Classification'!Q42 -> 0 | AA42: =+'Asset Classification'!R42 -> 0 | AB42: =+'Asset Classification'!S42 -> 0 | AC42: =+Z42*50% -> 0 | AD42: =+AB42-AC42 -> 0 | AE42: =+'Asset Classification'!T42 -> 0 | AF42: =+AA42*50% -> 0 | AG42: =+AE42-AF42 -> 0 | AH42: =+'Asset Classification'!U42 -> 0 | AI42: =+'Asset Classification'!V42 -> 0 | AJ42: =+'Asset Classification'!W42 -> 0 | AK42: =+AH42*100% -> 0 | AL42: =+AJ42-AK42 -> 0 | AM42: =+'Asset Classification'!X42 -> 0 | AN42: =+AI42*100% -> 0 | AO42: =+AM42-AN42 -> 0 | AP42: =+L42+T42+AB42+AJ42 -> 0 | AQ42: =+M42+U42+AC42+AK42 -> 0 | AR42: =+AP42-AQ42 -> 0 | AS42: =+O42+W42+AE42+AM42 -> 0 | AT42: =+P42+X42+AF42+AN42 -> 0 | AU42: =+AS42-AT42 -> 0
A43: 18 | B43: Савдо ва умумий хизмат | C43: =+'Asset Classification'!C43 -> 3466439372 | D43: =+'Asset Classification'!D43 -> 2756436726 | E43: =+'Asset Classification'!E43 -> 2960164849 | F43: =+'Asset Classification'!F43 -> 2404774456 | G43: =+'Asset Classification'!G43 -> 29601648 | H43: =+E43*1% -> 29601648 | I43: =+G43-H43 -> -0.49 | J43: =+'Asset Classification'!I43 -> 241286988 | K43: =+'Asset Classification'!J43 -> 200437929 | L43: =+'Asset Classification'!K43 -> 24128699 | M43: =+J43*10% -> 24128699 | N43: =+L43-M43 -> 0.2 | O43: =+'Asset Classification'!L43 -> 20043793 | P43: =+K43*10% -> 20043793 | Q43: =+O43-P43 -> 0.099999998 | R43: =+'Asset Classification'!M43 -> 60676560 | S43: =+'Asset Classification'!N43 -> 52568517 | T43: =+'Asset Classification'!O43 -> 15169140 | U43: =+R43*25% -> 15169140 | V43: =+T43-U43 -> 0 | W43: =+'Asset Classification'!P43 -> 13142129 | X43: =+S43*25% -> 13142129 | Y43: =+W43-X43 -> -0.25 | Z43: =+'Asset Classification'!Q43 -> 193760975 | AA43: =+'Asset Classification'!R43 -> 98655824 | AB43: =+'Asset Classification'!S43 -> 96880488 | AC43: =+Z43*50% -> 96880488 | AD43: =+AB43-AC43 -> 0.5 | AE43: =+'Asset Classification'!T43 -> 49327912 | AF43: =+AA43*50% -> 49327912 | AG43: =+AE43-AF43 -> 0 | AH43: =+'Asset Classification'!U43 -> 10550000 | AI43: =+'Asset Classification'!V43 -> 0 | AJ43: =+'Asset Classification'!W43 -> 10550000 | AK43: =+AH43*100% -> 10550000 | AL43: =+AJ43-AK43 -> 0 | AM43: =+'Asset Classification'!X43 -> 0 | AN43: =+AI43*100% -> 0 | AO43: =+AM43-AN43 -> 0 | AP43: =+L43+T43+AB43+AJ43 -> 146728327 | AQ43: =+M43+U43+AC43+AK43 -> 1.4672833e+08 | AR43: =+AP43-AQ43 -> 0.69999999 | AS43: =+O43+W43+AE43+AM43 -> 82513834 | AT43: =+P43+X43+AF43+AN43 -> 82513834 | AU43: =+AS43-AT43 -> -0.15000001 | AV43: =+'Aging Analysis'!C29 -> 3466439372
B44: шундан, таъминланмаган қисми | C44: =+'Asset Classification'!C44 -> 0 | D44: =+'Asset Classification'!D44 -> 0 | E44: =+'Asset Classification'!E44 -> 0 | F44: =+'Asset Classification'!F44 -> 0 | G44: =+'Asset Classification'!G44 -> 0 | H44: =+E44*1% -> 0 | I44: =+G44-H44 -> 0 | J44: =+'Asset Classification'!I44 -> 0 | K44: =+'Asset Classification'!J44 -> 0 | L44: =+'Asset Classification'!K44 -> 0 | M44: =+J44*10% -> 0 | N44: =+L44-M44 -> 0 | O44: =+'Asset Classification'!L44 -> 0 | P44: =+K44*10% -> 0 | Q44: =+O44-P44 -> 0 | R44: =+'Asset Classification'!M44 -> 0 | S44: =+'Asset Classification'!N44 -> 0 | T44: =+'Asset Classification'!O44 -> 0 | U44: =+R44*25% -> 0 | V44: =+T44-U44 -> 0 | W44: =+'Asset Classification'!P44 -> 0 | X44: =+S44*25% -> 0 | Y44: =+W44-X44 -> 0 | Z44: =+'Asset Classification'!Q44 -> 0 | AA44: =+'Asset Classification'!R44 -> 0 | AB44: =+'Asset Classification'!S44 -> 0 | AC44: =+Z44*50% -> 0 | AD44: =+AB44-AC44 -> 0 | AE44: =+'Asset Classification'!T44 -> 0 | AF44: =+AA44*50% -> 0 | AG44: =+AE44-AF44 -> 0 | AH44: =+'Asset Classification'!U44 -> 0 | AI44: =+'Asset Classification'!V44 -> 0 | AJ44: =+'Asset Classification'!W44 -> 0 | AK44: =+AH44*100% -> 0 | AL44: =+AJ44-AK44 -> 0 | AM44: =+'Asset Classification'!X44 -> 0 | AN44: =+AI44*100% -> 0 | AO44: =+AM44-AN44 -> 0 | AP44: =+L44+T44+AB44+AJ44 -> 0 | AQ44: =+M44+U44+AC44+AK44 -> 0 | AR44: =+AP44-AQ44 -> 0 | AS44: =+O44+W44+AE44+AM44 -> 0 | AT44: =+P44+X44+AF44+AN44 -> 0 | AU44: =+AS44-AT44 -> 0
A45: 19 | B45: Моддий ва техник таъминотни ривожлантириш | C45: =+'Asset Classification'!C45 -> 2157776262 | D45: =+'Asset Classification'!D45 -> 300207520 | E45: =+'Asset Classification'!E45 -> 2139811852 | F45: =+'Asset Classification'!F45 -> 295271972 | G45: =+'Asset Classification'!G45 -> 21398119 | H45: =+E45*1% -> 21398119 | I45: =+G45-H45 -> 0.48 | J45: =+'Asset Classification'!I45 -> 12647724 | K45: =+'Asset Classification'!J45 -> 0 | L45: =+'Asset Classification'!K45 -> 1264772 | M45: =+J45*10% -> 1264772.4 | N45: =+L45-M45 -> -0.4 | O45: =+'Asset Classification'!L45 -> 0 | P45: =+K45*10% -> 0 | Q45: =+O45-P45 -> 0 | R45: =+'Asset Classification'!M45 -> 246815 | S45: =+'Asset Classification'!N45 -> 246815 | T45: =+'Asset Classification'!O45 -> 61704 | U45: =+R45*25% -> 61703.75 | V45: =+T45-U45 -> 0.25 | W45: =+'Asset Classification'!P45 -> 61704 | X45: =+S45*25% -> 61703.75 | Y45: =+W45-X45 -> 0.25 | Z45: =+'Asset Classification'!Q45 -> 31138 | AA45: =+'Asset Classification'!R45 -> 0 | AB45: =+'Asset Classification'!S45 -> 15569 | AC45: =+Z45*50% -> 15569 | AD45: =+AB45-AC45 -> 0 | AE45: =+'Asset Classification'!T45 -> 0 | AF45: =+AA45*50% -> 0 | AG45: =+AE45-AF45 -> 0 | AH45: =+'Asset Classification'!U45 -> 5038733 | AI45: =+'Asset Classification'!V45 -> 4688733 | AJ45: =+'Asset Classification'!W45 -> 5038733 | AK45: =+AH45*100% -> 5038733 | AL45: =+AJ45-AK45 -> 0 | AM45: =+'Asset Classification'!X45 -> 4688733 | AN45: =+AI45*100% -> 4688733 | AO45: =+AM45-AN45 -> 0 | AP45: =+L45+T45+AB45+AJ45 -> 6380778 | AQ45: =+M45+U45+AC45+AK45 -> 6380778.2 | AR45: =+AP45-AQ45 -> -0.15 | AS45: =+O45+W45+AE45+AM45 -> 4750437 | AT45: =+P45+X45+AF45+AN45 -> 4750436.8 | AU45: =+AS45-AT45 -> 0.25 | AV45: =+'Aging Analysis'!C30 -> 2157776262
B46: шундан, таъминланмаган қисми | C46: =+'Asset Classification'!C46 -> 0 | D46: =+'Asset Classification'!D46 -> 0 | E46: =+'Asset Classification'!E46 -> 0 | F46: =+'Asset Classification'!F46 -> 0 | G46: =+'Asset Classification'!G46 -> 0 | H46: =+E46*1% -> 0 | I46: =+G46-H46 -> 0 | J46: =+'Asset Classification'!I46 -> 0 | K46: =+'Asset Classification'!J46 -> 0 | L46: =+'Asset Classification'!K46 -> 0 | M46: =+J46*10% -> 0 | N46: =+L46-M46 -> 0 | O46: =+'Asset Classification'!L46 -> 0 | P46: =+K46*10% -> 0 | Q46: =+O46-P46 -> 0 | R46: =+'Asset Classification'!M46 -> 0 | S46: =+'Asset Classification'!N46 -> 0 | T46: =+'Asset Classification'!O46 -> 0 | U46: =+R46*25% -> 0 | V46: =+T46-U46 -> 0 | W46: =+'Asset Classification'!P46 -> 0 | X46: =+S46*25% -> 0 | Y46: =+W46-X46 -> 0 | Z46: =+'Asset Classification'!Q46 -> 0 | AA46: =+'Asset Classification'!R46 -> 0 | AB46: =+'Asset Classification'!S46 -> 0 | AC46: =+Z46*50% -> 0 | AD46: =+AB46-AC46 -> 0 | AE46: =+'Asset Classification'!T46 -> 0 | AF46: =+AA46*50% -> 0 | AG46: =+AE46-AF46 -> 0 | AH46: =+'Asset Classification'!U46 -> 0 | AI46: =+'Asset Classification'!V46 -> 0 | AJ46: =+'Asset Classification'!W46 -> 0 | AK46: =+AH46*100% -> 0 | AL46: =+AJ46-AK46 -> 0 | AM46: =+'Asset Classification'!X46 -> 0 | AN46: =+AI46*100% -> 0 | AO46: =+AM46-AN46 -> 0 | AP46: =+L46+T46+AB46+AJ46 -> 0 | AQ46: =+M46+U46+AC46+AK46 -> 0 | AR46: =+AP46-AQ46 -> 0 | AS46: =+O46+W46+AE46+AM46 -> 0 | AT46: =+P46+X46+AF46+AN46 -> 0 | AU46: =+AS46-AT46 -> 0
A47: 20 | B47: Уй-жой коммунал хизмати | C47: =+'Asset Classification'!C47 -> 1605566 | D47: =+'Asset Classification'!D47 -> 0 | E47: =+'Asset Classification'!E47 -> 1467441 | F47: =+'Asset Classification'!F47 -> 0 | G47: =+'Asset Classification'!G47 -> 14674 | H47: =+E47*1% -> 14674.41 | I47: =+G47-H47 -> -0.41 | J47: =+'Asset Classification'!I47 -> 0 | K47: =+'Asset Classification'!J47 -> 0 | L47: =+'Asset Classification'!K47 -> 0 | M47: =+J47*10% -> 0 | N47: =+L47-M47 -> 0 | O47: =+'Asset Classification'!L47 -> 0 | P47: =+K47*10% -> 0 | Q47: =+O47-P47 -> 0 | R47: =+'Asset Classification'!M47 -> 138125 | S47: =+'Asset Classification'!N47 -> 0 | T47: =+'Asset Classification'!O47 -> 34531 | U47: =+R47*25% -> 34531.25 | V47: =+T47-U47 -> -0.25 | W47: =+'Asset Classification'!P47 -> 0 | X47: =+S47*25% -> 0 | Y47: =+W47-X47 -> 0 | Z47: =+'Asset Classification'!Q47 -> 0 | AA47: =+'Asset Classification'!R47 -> 0 | AB47: =+'Asset Classification'!S47 -> 0 | AC47: =+Z47*50% -> 0 | AD47: =+AB47-AC47 -> 0 | AE47: =+'Asset Classification'!T47 -> 0 | AF47: =+AA47*50% -> 0 | AG47: =+AE47-AF47 -> 0 | AH47: =+'Asset Classification'!U47 -> 0 | AI47: =+'Asset Classification'!V47 -> 0 | AJ47: =+'Asset Classification'!W47 -> 0 | AK47: =+AH47*100% -> 0 | AL47: =+AJ47-AK47 -> 0 | AM47: =+'Asset Classification'!X47 -> 0 | AN47: =+AI47*100% -> 0 | AO47: =+AM47-AN47 -> 0 | AP47: =+L47+T47+AB47+AJ47 -> 34531 | AQ47: =+M47+U47+AC47+AK47 -> 34531.25 | AR47: =+AP47-AQ47 -> -0.25 | AS47: =+O47+W47+AE47+AM47 -> 0 | AT47: =+P47+X47+AF47+AN47 -> 0 | AU47: =+AS47-AT47 -> 0 | AV47: =+'Aging Analysis'!C31 -> 1605566
B48: шундан, таъминланмаган қисми | C48: =+'Asset Classification'!C48 -> 0 | D48: =+'Asset Classification'!D48 -> 0 | E48: =+'Asset Classification'!E48 -> 0 | F48: =+'Asset Classification'!F48 -> 0 | G48: =+'Asset Classification'!G48 -> 0 | H48: =+E48*1% -> 0 | I48: =+G48-H48 -> 0 | J48: =+'Asset Classification'!I48 -> 0 | K48: =+'Asset Classification'!J48 -> 0 | L48: =+'Asset Classification'!K48 -> 0 | M48: =+J48*10% -> 0 | N48: =+L48-M48 -> 0 | O48: =+'Asset Classification'!L48 -> 0 | P48: =+K48*10% -> 0 | Q48: =+O48-P48 -> 0 | R48: =+'Asset Classification'!M48 -> 0 | S48: =+'Asset Classification'!N48 -> 0 | T48: =+'Asset Classification'!O48 -> 0 | U48: =+R48*25% -> 0 | V48: =+T48-U48 -> 0 | W48: =+'Asset Classification'!P48 -> 0 | X48: =+S48*25% -> 0 | Y48: =+W48-X48 -> 0 | Z48: =+'Asset Classification'!Q48 -> 0 | AA48: =+'Asset Classification'!R48 -> 0 | AB48: =+'Asset Classification'!S48 -> 0 | AC48: =+Z48*50% -> 0 | AD48: =+AB48-AC48 -> 0 | AE48: =+'Asset Classification'!T48 -> 0 | AF48: =+AA48*50% -> 0 | AG48: =+AE48-AF48 -> 0 | AH48: =+'Asset Classification'!U48 -> 0 | AI48: =+'Asset Classification'!V48 -> 0 | AJ48: =+'Asset Classification'!W48 -> 0 | AK48: =+AH48*100% -> 0 | AL48: =+AJ48-AK48 -> 0 | AM48: =+'Asset Classification'!X48 -> 0 | AN48: =+AI48*100% -> 0 | AO48: =+AM48-AN48 -> 0 | AP48: =+L48+T48+AB48+AJ48 -> 0 | AQ48: =+M48+U48+AC48+AK48 -> 0 | AR48: =+AP48-AQ48 -> 0 | AS48: =+O48+W48+AE48+AM48 -> 0 | AT48: =+P48+X48+AF48+AN48 -> 0 | AU48: =+AS48-AT48 -> 0
A49: 21 | B49: Бошқа соҳалар | C49: =+'Asset Classification'!C49 -> 3565380938 | D49: =+'Asset Classification'!D49 -> 2451620935 | E49: =+'Asset Classification'!E49 -> 2486832479 | F49: =+'Asset Classification'!F49 -> 1530267407 | G49: =+'Asset Classification'!G49 -> 24868326 | H49: =+E49*1% -> 24868325 | I49: =+G49-H49 -> 1.21 | J49: =+'Asset Classification'!I49 -> 1048838111 | K49: =+'Asset Classification'!J49 -> 915190899 | L49: =+'Asset Classification'!K49 -> 104883812 | M49: =+J49*10% -> 1.0488381e+08 | N49: =+L49-M49 -> 0.89999999 | O49: =+'Asset Classification'!L49 -> 91519090 | P49: =+K49*10% -> 91519090 | Q49: =+O49-P49 -> 0.099999994 | R49: =+'Asset Classification'!M49 -> 8839572 | S49: =+'Asset Classification'!N49 -> 254355 | T49: =+'Asset Classification'!O49 -> 2209893 | U49: =+R49*25% -> 2209893 | V49: =+T49-U49 -> 0 | W49: =+'Asset Classification'!P49 -> 63590 | X49: =+S49*25% -> 63588.75 | Y49: =+W49-X49 -> 1.25 | Z49: =+'Asset Classification'!Q49 -> 20870776 | AA49: =+'Asset Classification'!R49 -> 5908274 | AB49: =+'Asset Classification'!S49 -> 10435388 | AC49: =+Z49*50% -> 10435388 | AD49: =+AB49-AC49 -> 0 | AE49: =+'Asset Classification'!T49 -> 2954138 | AF49: =+AA49*50% -> 2954137 | AG49: =+AE49-AF49 -> 1 | AH49: =+'Asset Classification'!U49 -> 0 | AI49: =+'Asset Classification'!V49 -> 0 | AJ49: =+'Asset Classification'!W49 -> 0 | AK49: =+AH49*100% -> 0 | AL49: =+AJ49-AK49 -> 0 | AM49: =+'Asset Classification'!X49 -> 0 | AN49: =+AI49*100% -> 0 | AO49: =+AM49-AN49 -> 0 | AP49: =+L49+T49+AB49+AJ49 -> 117529093 | AQ49: =+M49+U49+AC49+AK49 -> 1.1752909e+08 | AR49: =+AP49-AQ49 -> 0.89999999 | AS49: =+O49+W49+AE49+AM49 -> 94536818 | AT49: =+P49+X49+AF49+AN49 -> 94536816 | AU49: =+AS49-AT49 -> 2.35 | AV49: =+'Aging Analysis'!C32 -> 3565380938
B50: шундан, таъминланмаган қисми | C50: =+'Asset Classification'!C50 -> 0 | D50: =+'Asset Classification'!D50 -> 0 | E50: =+'Asset Classification'!E50 -> 0 | F50: =+'Asset Classification'!F50 -> 0 | G50: =+'Asset Classification'!G50 -> 0 | H50: =+E50*1% -> 0 | I50: =+G50-H50 -> 0 | J50: =+'Asset Classification'!I50 -> 0 | K50: =+'Asset Classification'!J50 -> 0 | L50: =+'Asset Classification'!K50 -> 0 | M50: =+J50*10% -> 0 | N50: =+L50-M50 -> 0 | O50: =+'Asset Classification'!L50 -> 0 | P50: =+K50*10% -> 0 | Q50: =+O50-P50 -> 0 | R50: =+'Asset Classification'!M50 -> 0 | S50: =+'Asset Classification'!N50 -> 0 | T50: =+'Asset Classification'!O50 -> 0 | U50: =+R50*25% -> 0 | V50: =+T50-U50 -> 0 | W50: =+'Asset Classification'!P50 -> 0 | X50: =+S50*25% -> 0 | Y50: =+W50-X50 -> 0 | Z50: =+'Asset Classification'!Q50 -> 0 | AA50: =+'Asset Classification'!R50 -> 0 | AB50: =+'Asset Classification'!S50 -> 0 | AC50: =+Z50*50% -> 0 | AD50: =+AB50-AC50 -> 0 | AE50: =+'Asset Classification'!T50 -> 0 | AF50: =+AA50*50% -> 0 | AG50: =+AE50-AF50 -> 0 | AH50: =+'Asset Classification'!U50 -> 0 | AI50: =+'Asset Classification'!V50 -> 0 | AJ50: =+'Asset Classification'!W50 -> 0 | AK50: =+AH50*100% -> 0 | AL50: =+AJ50-AK50 -> 0 | AM50: =+'Asset Classification'!X50 -> 0 | AN50: =+AI50*100% -> 0 | AO50: =+AM50-AN50 -> 0 | AP50: =+L50+T50+AB50+AJ50 -> 0 | AQ50: =+M50+U50+AC50+AK50 -> 0 | AR50: =+AP50-AQ50 -> 0 | AS50: =+O50+W50+AE50+AM50 -> 0 | AT50: =+P50+X50+AF50+AN50 -> 0 | AU50: =+AS50-AT50 -> 0
A51: 22 | B51: Жисмоний шахслар | C51: =+'Asset Classification'!C51 -> 7814492786 | D51: =+'Asset Classification'!D51 -> 0 | E51: =+'Asset Classification'!E51 -> 7625652230 | F51: =+'Asset Classification'!F51 -> 0 | G51: =+'Asset Classification'!G51 -> 76256522 | H51: =+E51*1% -> 76256522 | I51: =+G51-H51 -> -0.3 | J51: =+'Asset Classification'!I51 -> 147846643 | K51: =+'Asset Classification'!J51 -> 0 | L51: =+'Asset Classification'!K51 -> 14782772 | M51: =+J51*10% -> 14784664 | N51: =+L51-M51 -> -1892.3 | O51: =+'Asset Classification'!L51 -> 0 | P51: =+K51*10% -> 0 | Q51: =+O51-P51 -> 0 | R51: =+'Asset Classification'!M51 -> 19062315 | S51: =+'Asset Classification'!N51 -> 0 | T51: =+'Asset Classification'!O51 -> 4765590 | U51: =+R51*25% -> 4765578.8 | V51: =+T51-U51 -> 11.25 | W51: =+'Asset Classification'!P51 -> 0 | X51: =+S51*25% -> 0 | Y51: =+W51-X51 -> 0 | Z51: =+'Asset Classification'!Q51 -> 21931598 | AA51: =+'Asset Classification'!R51 -> 0 | AB51: =+'Asset Classification'!S51 -> 10965799 | AC51: =+Z51*50% -> 10965799 | AD51: =+AB51-AC51 -> 0 | AE51: =+'Asset Classification'!T51 -> 0 | AF51: =+AA51*50% -> 0 | AG51: =+AE51-AF51 -> 0 | AH51: =+'Asset Classification'!U51 -> 0 | AI51: =+'Asset Classification'!V51 -> 0 | AJ51: =+'Asset Classification'!W51 -> 0 | AK51: =+AH51*100% -> 0 | AL51: =+AJ51-AK51 -> 0 | AM51: =+'Asset Classification'!X51 -> 0 | AN51: =+AI51*100% -> 0 | AO51: =+AM51-AN51 -> 0 | AP51: =+L51+T51+AB51+AJ51 -> 30514161 | AQ51: =+M51+U51+AC51+AK51 -> 30516042 | AR51: =+AP51-AQ51 -> -1881.05 | AS51: =+O51+W51+AE51+AM51 -> 0 | AT51: =+P51+X51+AF51+AN51 -> 0 | AU51: =+AS51-AT51 -> 0 | AV51: =+'Aging Analysis'!C33 -> 7814492786
B52: шундан, таъминланмаган қисми | C52: =+'Asset Classification'!C52 -> 0 | D52: =+'Asset Classification'!D52 -> 0 | E52: =+'Asset Classification'!E52 -> 0 | F52: =+'Asset Classification'!F52 -> 0 | G52: =+'Asset Classification'!G52 -> 0 | H52: =+E52*1% -> 0 | I52: =+G52-H52 -> 0 | J52: =+'Asset Classification'!I52 -> 0 | K52: =+'Asset Classification'!J52 -> 0 | L52: =+'Asset Classification'!K52 -> 0 | M52: =+J52*10% -> 0 | N52: =+L52-M52 -> 0 | O52: =+'Asset Classification'!L52 -> 0 | P52: =+K52*10% -> 0 | Q52: =+O52-P52 -> 0 | R52: =+'Asset Classification'!M52 -> 0 | S52: =+'Asset Classification'!N52 -> 0 | T52: =+'Asset Classification'!O52 -> 0 | U52: =+R52*25% -> 0 | V52: =+T52-U52 -> 0 | W52: =+'Asset Classification'!P52 -> 0 | X52: =+S52*25% -> 0 | Y52: =+W52-X52 -> 0 | Z52: =+'Asset Classification'!Q52 -> 0 | AA52: =+'Asset Classification'!R52 -> 0 | AB52: =+'Asset Classification'!S52 -> 0 | AC52: =+Z52*50% -> 0 | AD52: =+AB52-AC52 -> 0 | AE52: =+'Asset Classification'!T52 -> 0 | AF52: =+AA52*50% -> 0 | AG52: =+AE52-AF52 -> 0 | AH52: =+'Asset Classification'!U52 -> 0 | AI52: =+'Asset Classification'!V52 -> 0 | AJ52: =+'Asset Classification'!W52 -> 0 | AK52: =+AH52*100% -> 0 | AL52: =+AJ52-AK52 -> 0 | AM52: =+'Asset Classification'!X52 -> 0 | AN52: =+AI52*100% -> 0 | AO52: =+AM52-AN52 -> 0 | AP52: =+L52+T52+AB52+AJ52 -> 0 | AQ52: =+M52+U52+AC52+AK52 -> 0 | AR52: =+AP52-AQ52 -> 0 | AS52: =+O52+W52+AE52+AM52 -> 0 | AT52: =+P52+X52+AF52+AN52 -> 0 | AU52: =+AS52-AT52 -> 0
A53: 23 | B53: Жами кредит ва лизинг суммаси | C53: =+'Asset Classification'!C53 -> 57124403912 | D53: =+'Asset Classification'!D53 -> 38012960642 | E53: =+'Asset Classification'!E53 -> 49548751261 | F53: =+'Asset Classification'!F53 -> 32899887295 | G53: =+'Asset Classification'!G53 -> 504953973 | H53: =+H35+H37+H39+H41+H43+H45+H47+H49+H51 -> 4.9548751e+08 | I53: =+I35+I37+I39+I41+I43+I45+I47+I49+I51 -> 9466460.4 | J53: =+'Asset Classification'!I53 -> 6292476722 | K53: =+'Asset Classification'!J53 -> 4289653575 | L53: =+'Asset Classification'!K53 -> 620122045 | M53: =+M35+M37+M39+M41+M43+M45+M47+M49+M51 -> 6.2924767e+08 | N53: =+N35+N37+N39+N41+N43+N45+N47+N49+N51 -> -9125627.2 | O53: =+'Asset Classification'!L53 -> 419611589 | P53: =+P35+P37+P39+P41+P43+P45+P47+P49+P51 -> 4.2896536e+08 | Q53: =+Q35+Q37+Q39+Q41+Q43+Q45+Q47+Q49+Q51 -> -9353768.5 | R53: =+'Asset Classification'!M53 -> 506004487 | S53: =+'Asset Classification'!N53 -> 263138435 | T53: =+'Asset Classification'!O53 -> 126501133 | U53: =+U35+U37+U39+U41+U43+U45+U47+U49+U51 -> 1.2650112e+08 | V53: =+V35+V37+V39+V41+V43+V45+V47+V49+V51 -> 11.25 | W53: =+'Asset Classification'!P53 -> 65784610 | X53: =+X35+X37+X39+X41+X43+X45+X47+X49+X51 -> 65784609 | Y53: =+Y35+Y37+Y39+Y41+Y43+Y45+Y47+Y49+Y51 -> 1.25 | Z53: =+'Asset Classification'!Q53 -> 749932110 | AA53: =+'Asset Classification'!R53 -> 545624112 | AB53: =+'Asset Classification'!S53 -> 374966057 | AC53: =+AC35+AC37+AC39+AC41+AC43+AC45+AC47+AC49+AC51 -> 374966055 | AD53: =+AD35+AD37+AD39+AD41+AD43+AD45+AD47+AD49+AD51 -> 2 | AE53: =+'Asset Classification'!T53 -> 272812058 | AF53: =+AF35+AF37+AF39+AF41+AF43+AF45+AF47+AF49+AF51 -> 272812056 | AG53: =+AG35+AG37+AG39+AG41+AG43+AG45+AG47+AG49+AG51 -> 2 | AH53: =+'Asset Classification'!U53 -> 27239332 | AI53: =+'Asset Classification'!V53 -> 14657225 | AJ53: =+'Asset Classification'!W53 -> 27239332 | AK53: =+AK35+AK37+AK39+AK41+AK43+AK45+AK47+AK49+AK51 -> 27239332 | AL53: =+AL35+AL37+AL39+AL41+AL43+AL45+AL47+AL49+AL51 -> 0 | AM53: =+'Asset Classification'!X53 -> 14657225 | AN53: =+AN35+AN37+AN39+AN41+AN43+AN45+AN47+AN49+AN51 -> 14657225 | AO53: =+AO35+AO37+AO39+AO41+AO43+AO45+AO47+AO49+AO51 -> 0 | AP53: =+AP35+AP37+AP39+AP41+AP43+AP45+AP47+AP49+AP51 -> 1148828567 | AQ53: =+AQ35+AQ37+AQ39+AQ41+AQ43+AQ45+AQ47+AQ49+AQ51 -> 1.1579542e+09 | AR53: =+AR35+AR37+AR39+AR41+AR43+AR45+AR47+AR49+AR51 -> -9125614 | AS53: =+AS35+AS37+AS39+AS41+AS43+AS45+AS47+AS49+AS51 -> 772865482 | AT53: =+AT35+AT37+AT39+AT41+AT43+AT45+AT47+AT49+AT51 -> 7.8221925e+08 | AU53: =+AU35+AU37+AU39+AU41+AU43+AU45+AU47+AU49+AU51 -> -9353765.3 | AV53: =+'Aging Analysis'!C35 -> 57124403912
B54: шундан, таъминланмаган қисми | C54: =+'Asset Classification'!C54 -> 0 | D54: =+'Asset Classification'!D54 -> 0 | E54: =+'Asset Classification'!E54 -> 0 | F54: =+'Asset Classification'!F54 -> 0 | G54: =+'Asset Classification'!G54 -> 0 | H54: =+E54*1% -> 0 | I54: =+G54-H54 -> 0 | J54: =+'Asset Classification'!I54 -> 0 | K54: =+'Asset Classification'!J54 -> 0 | L54: =+'Asset Classification'!K54 -> 0 | M54: =+J54*10% -> 0 | N54: =+L54-M54 -> 0 | O54: =+'Asset Classification'!L54 -> 0 | P54: =+K54*10% -> 0 | Q54: =+O54-P54 -> 0 | R54: =+'Asset Classification'!M54 -> 0 | S54: =+'Asset Classification'!N54 -> 0 | T54: =+'Asset Classification'!O54 -> 0 | U54: =+R54*25% -> 0 | V54: =+T54-U54 -> 0 | W54: =+'Asset Classification'!P54 -> 0 | X54: =+S54*25% -> 0 | Y54: =+W54-X54 -> 0 | Z54: =+'Asset Classification'!Q54 -> 0 | AA54: =+'Asset Classification'!R54 -> 0 | AB54: =+'Asset Classification'!S54 -> 0 | AC54: =+Z54*50% -> 0 | AD54: =+AB54-AC54 -> 0 | AE54: =+'Asset Classification'!T54 -> 0 | AF54: =+AA54*50% -> 0 | AG54: =+AE54-AF54 -> 0 | AH54: =+'Asset Classification'!U54 -> 0 | AI54: =+'Asset Classification'!V54 -> 0 | AJ54: =+'Asset Classification'!W54 -> 0 | AK54: =+AH54*100% -> 0 | AL54: =+AJ54-AK54 -> 0 | AM54: =+'Asset Classification'!X54 -> 0 | AN54: =+AI54*100% -> 0 | AO54: =+AM54-AN54 -> 0 | AP54: =+L54+T54+AB54+AJ54 -> 0 | AQ54: =+M54+U54+AC54+AK54 -> 0 | AR54: =+AP54-AQ54 -> 0 | AS54: =+O54+W54+AE54+AM54 -> 0 | AT54: =+P54+X54+AF54+AN54 -> 0 | AU54: =+AS54-AT54 -> 0
B55: Ҳудудлар қирқимида
A57: 24 | B57: Қорақалпоғистон Республикаси | C57: =+'Asset Classification'!C57 -> 1932270015 | D57: =+'Asset Classification'!D57 -> 857624905 | E57: =+'Asset Classification'!E57 -> 1874411554 | F57: =+'Asset Classification'!F57 -> 824920399 | G57: =+'Asset Classification'!G57 -> 11072659 | H57: =+E57*1% -> 18744116 | I57: =+G57-H57 -> -7671456.5 | J57: =+'Asset Classification'!I57 -> 43250729 | K57: =+'Asset Classification'!J57 -> 21635388 | L57: =+'Asset Classification'!K57 -> 4322768 | M57: =+J57*10% -> 4325072.9 | N57: =+L57-M57 -> -2304.9 | O57: =+'Asset Classification'!L57 -> 2163539 | P57: =+K57*10% -> 2163538.8 | Q57: =+O57-P57 -> 0.2 | R57: =+'Asset Classification'!M57 -> 2227600 | S57: =+'Asset Classification'!N57 -> 0 | T57: =+'Asset Classification'!O57 -> 556900 | U57: =+R57*25% -> 556900 | V57: =+T57-U57 -> 0 | W57: =+'Asset Classification'!P57 -> 0 | X57: =+S57*25% -> 0 | Y57: =+W57-X57 -> 0 | Z57: =+'Asset Classification'!Q57 -> 12380132 | AA57: =+'Asset Classification'!R57 -> 11069118 | AB57: =+'Asset Classification'!S57 -> 6190066 | AC57: =+Z57*50% -> 6190066 | AD57: =+AB57-AC57 -> 0 | AE57: =+'Asset Classification'!T57 -> 5534559 | AF57: =+AA57*50% -> 5534559 | AG57: =+AE57-AF57 -> 0 | AH57: =+'Asset Classification'!U57 -> 0 | AI57: =+'Asset Classification'!V57 -> 0 | AJ57: =+'Asset Classification'!W57 -> 0 | AK57: =+AH57*100% -> 0 | AL57: =+AJ57-AK57 -> 0 | AM57: =+'Asset Classification'!X57 -> 0 | AN57: =+AI57*100% -> 0 | AO57: =+AM57-AN57 -> 0 | AP57: =+L57+T57+AB57+AJ57 -> 11069734 | AQ57: =+M57+U57+AC57+AK57 -> 11072039 | AR57: =+AP57-AQ57 -> -2304.9 | AS57: =+O57+W57+AE57+AM57 -> 7698098 | AT57: =+P57+X57+AF57+AN57 -> 7698097.8 | AU57: =+AS57-AT57 -> 0.2
A58: 25 | B58: Андижон вилояти | C58: =+'Asset Classification'!C58 -> 1624354054 | D58: =+'Asset Classification'!D58 -> 1024737071 | E58: =+'Asset Classification'!E58 -> 1528489311 | F58: =+'Asset Classification'!F58 -> 979420203 | G58: =+'Asset Classification'!G58 -> 10254993 | H58: =+E58*1% -> 15284893 | I58: =+G58-H58 -> -5029900.1 | J58: =+'Asset Classification'!I58 -> 44728038 | K58: =+'Asset Classification'!J58 -> 7015679 | L58: =+'Asset Classification'!K58 -> 4472804 | M58: =+J58*10% -> 4472803.8 | N58: =+L58-M58 -> 0.2 | O58: =+'Asset Classification'!L58 -> 701568 | P58: =+K58*10% -> 701567.9 | Q58: =+O58-P58 -> 0.1 | R58: =+'Asset Classification'!M58 -> 4727552 | S58: =+'Asset Classification'!N58 -> 2539485 | T58: =+'Asset Classification'!O58 -> 1181888 | U58: =+R58*25% -> 1181888 | V58: =+T58-U58 -> 0 | W58: =+'Asset Classification'!P58 -> 634871 | X58: =+S58*25% -> 634871.25 | Y58: =+W58-X58 -> -0.25 | Z58: =+'Asset Classification'!Q58 -> 46409153 | AA58: =+'Asset Classification'!R58 -> 35761704 | AB58: =+'Asset Classification'!S58 -> 23204576 | AC58: =+Z58*50% -> 23204576 | AD58: =+AB58-AC58 -> -0.5 | AE58: =+'Asset Classification'!T58 -> 17880852 | AF58: =+AA58*50% -> 17880852 | AG58: =+AE58-AF58 -> 0 | AH58: =+'Asset Classification'!U58 -> 0 | AI58: =+'Asset Classification'!V58 -> 0 | AJ58: =+'Asset Classification'!W58 -> 0 | AK58: =+AH58*100% -> 0 | AL58: =+AJ58-AK58 -> 0 | AM58: =+'Asset Classification'!X58 -> 0 | AN58: =+AI58*100% -> 0 | AO58: =+AM58-AN58 -> 0 | AP58: =+L58+T58+AB58+AJ58 -> 28859268 | AQ58: =+M58+U58+AC58+AK58 -> 28859268 | AR58: =+AP58-AQ58 -> -0.3 | AS58: =+O58+W58+AE58+AM58 -> 19217291 | AT58: =+P58+X58+AF58+AN58 -> 19217291 | AU58: =+AS58-AT58 -> -0.15
A59: 26 | B59: Бухоро вилояти | C59: =+'Asset Classification'!C59 -> 1543780452 | D59: =+'Asset Classification'!D59 -> 1043441361 | E59: =+'Asset Classification'!E59 -> 1230872943 | F59: =+'Asset Classification'!F59 -> 775653188 | G59: =+'Asset Classification'!G59 -> 11745891 | H59: =+E59*1% -> 12308729 | I59: =+G59-H59 -> -562838.43 | J59: =+'Asset Classification'!I59 -> 146407337 | K59: =+'Asset Classification'!J59 -> 130296364 | L59: =+'Asset Classification'!K59 -> 14640734 | M59: =+J59*10% -> 14640734 | N59: =+L59-M59 -> 0.3 | O59: =+'Asset Classification'!L59 -> 13029636 | P59: =+K59*10% -> 13029636 | Q59: =+O59-P59 -> -0.4 | R59: =+'Asset Classification'!M59 -> 71220860 | S59: =+'Asset Classification'!N59 -> 55655823 | T59: =+'Asset Classification'!O59 -> 17805215 | U59: =+R59*25% -> 17805215 | V59: =+T59-U59 -> 0 | W59: =+'Asset Classification'!P59 -> 13913956 | X59: =+S59*25% -> 13913956 | Y59: =+W59-X59 -> 0.25 | Z59: =+'Asset Classification'!Q59 -> 90240580 | AA59: =+'Asset Classification'!R59 -> 77147253 | AB59: =+'Asset Classification'!S59 -> 45120290 | AC59: =+Z59*50% -> 45120290 | AD59: =+AB59-AC59 -> 0 | AE59: =+'Asset Classification'!T59 -> 38573627 | AF59: =+AA59*50% -> 38573626 | AG59: =+AE59-AF59 -> 0.5 | AH59: =+'Asset Classification'!U59 -> 5038732 | AI59: =+'Asset Classification'!V59 -> 4688733 | AJ59: =+'Asset Classification'!W59 -> 5038732 | AK59: =+AH59*100% -> 5038732 | AL59: =+AJ59-AK59 -> 0 | AM59: =+'Asset Classification'!X59 -> 4688733 | AN59: =+AI59*100% -> 4688733 | AO59: =+AM59-AN59 -> 0 | AP59: =+L59+T59+AB59+AJ59 -> 82604971 | AQ59: =+M59+U59+AC59+AK59 -> 82604971 | AR59: =+AP59-AQ59 -> 0.3 | AS59: =+O59+W59+AE59+AM59 -> 70205952 | AT59: =+P59+X59+AF59+AN59 -> 70205952 | AU59: =+AS59-AT59 -> 0.34999999
A60: 27 | B60: Жиззах вилояти | C60: =+'Asset Classification'!C60 -> 1588226570 | D60: =+'Asset Classification'!D60 -> 1189724174 | E60: =+'Asset Classification'!E60 -> 1570281102 | F60: =+'Asset Classification'!F60 -> 1176863602 | G60: =+'Asset Classification'!G60 -> 10609211 | H60: =+E60*1% -> 15702811 | I60: =+G60-H60 -> -5093600 | J60: =+'Asset Classification'!I60 -> 10567813 | K60: =+'Asset Classification'!J60 -> 7482668 | L60: =+'Asset Classification'!K60 -> 1056781 | M60: =+J60*10% -> 1056781.3 | N60: =+L60-M60 -> -0.3 | O60: =+'Asset Classification'!L60 -> 748267 | P60: =+K60*10% -> 748266.8 | Q60: =+O60-P60 -> 0.2 | R60: =+'Asset Classification'!M60 -> 4615651 | S60: =+'Asset Classification'!N60 -> 3800341 | T60: =+'Asset Classification'!O60 -> 1153913 | U60: =+R60*25% -> 1153912.8 | V60: =+T60-U60 -> 0.25 | W60: =+'Asset Classification'!P60 -> 950085 | X60: =+S60*25% -> 950085.25 | Y60: =+W60-X60 -> -0.25 | Z60: =+'Asset Classification'!Q60 -> 2762004 | AA60: =+'Asset Classification'!R60 -> 1577563 | AB60: =+'Asset Classification'!S60 -> 1381002 | AC60: =+Z60*50% -> 1381002 | AD60: =+AB60-AC60 -> 0 | AE60: =+'Asset Classification'!T60 -> 788782 | AF60: =+AA60*50% -> 788781.5 | AG60: =+AE60-AF60 -> 0.5 | AH60: =+'Asset Classification'!U60 -> 0 | AI60: =+'Asset Classification'!V60 -> 0 | AJ60: =+'Asset Classification'!W60 -> 0 | AK60: =+AH60*100% -> 0 | AL60: =+AJ60-AK60 -> 0 | AM60: =+'Asset Classification'!X60 -> 0 | AN60: =+AI60*100% -> 0 | AO60: =+AM60-AN60 -> 0 | AP60: =+L60+T60+AB60+AJ60 -> 3591696 | AQ60: =+M60+U60+AC60+AK60 -> 3591696 | AR60: =+AP60-AQ60 -> -0.05 | AS60: =+O60+W60+AE60+AM60 -> 2487134 | AT60: =+P60+X60+AF60+AN60 -> 2487133.5 | AU60: =+AS60-AT60 -> 0.45
A61: 28 | B61: Қашқадарё вилояти | C61: =+'Asset Classification'!C61 -> 1376806860 | D61: =+'Asset Classification'!D61 -> 240268756 | E61: =+'Asset Classification'!E61 -> 1115866566 | F61: =+'Asset Classification'!F61 -> 218807565 | G61: =+'Asset Classification'!G61 -> 14498781 | H61: =+E61*1% -> 11158666 | I61: =+G61-H61 -> 3340115.3 | J61: =+'Asset Classification'!I61 -> 212723119 | K61: =+'Asset Classification'!J61 -> 15284814 | L61: =+'Asset Classification'!K61 -> 21502346 | M61: =+J61*10% -> 21272312 | N61: =+L61-M61 -> 230034.1 | O61: =+'Asset Classification'!L61 -> 1528481 | P61: =+K61*10% -> 1528481.4 | Q61: =+O61-P61 -> -0.4 | R61: =+'Asset Classification'!M61 -> 40705179 | S61: =+'Asset Classification'!N61 -> 158035 | T61: =+'Asset Classification'!O61 -> 10176295 | U61: =+R61*25% -> 10176295 | V61: =+T61-U61 -> 0.25 | W61: =+'Asset Classification'!P61 -> 39509 | X61: =+S61*25% -> 39508.75 | Y61: =+W61-X61 -> 0.25 | Z61: =+'Asset Classification'!Q61 -> 7511996 | AA61: =+'Asset Classification'!R61 -> 6018342 | AB61: =+'Asset Classification'!S61 -> 3755998 | AC61: =+Z61*50% -> 3755998 | AD61: =+AB61-AC61 -> 0 | AE61: =+'Asset Classification'!T61 -> 3009171 | AF61: =+AA61*50% -> 3009171 | AG61: =+AE61-AF61 -> 0 | AH61: =+'Asset Classification'!U61 -> 0 | AI61: =+'Asset Classification'!V61 -> 0 | AJ61: =+'Asset Classification'!W61 -> 0 | AK61: =+AH61*100% -> 0 | AL61: =+AJ61-AK61 -> 0 | AM61: =+'Asset Classification'!X61 -> 0 | AN61: =+AI61*100% -> 0 | AO61: =+AM61-AN61 -> 0 | AP61: =+L61+T61+AB61+AJ61 -> 35434639 | AQ61: =+M61+U61+AC61+AK61 -> 35204605 | AR61: =+AP61-AQ61 -> 230034.35 | AS61: =+O61+W61+AE61+AM61 -> 4577161 | AT61: =+P61+X61+AF61+AN61 -> 4577161.2 | AU61: =+AS61-AT61 -> -0.15
A62: 29 | B62: Навоий вилояти | C62: =+'Asset Classification'!C62 -> 1374148502 | D62: =+'Asset Classification'!D62 -> 642939126 | E62: =+'Asset Classification'!E62 -> 1277764880 | F62: =+'Asset Classification'!F62 -> 595764381 | G62: =+'Asset Classification'!G62 -> 11790777 | H62: =+E62*1% -> 12777649 | I62: =+G62-H62 -> -986871.8 | J62: =+'Asset Classification'!I62 -> 91358258 | K62: =+'Asset Classification'!J62 -> 47174745 | L62: =+'Asset Classification'!K62 -> 9135826 | M62: =+J62*10% -> 9135825.8 | N62: =+L62-M62 -> 0.2 | O62: =+'Asset Classification'!L62 -> 4717475 | P62: =+K62*10% -> 4717474.5 | Q62: =+O62-P62 -> 0.5 | R62: =+'Asset Classification'!M62 -> 1675898 | S62: =+'Asset Classification'!N62 -> 0 | T62: =+'Asset Classification'!O62 -> 418975 | U62: =+R62*25% -> 418974.5 | V62: =+T62-U62 -> 0.5 | W62: =+'Asset Classification'!P62 -> 0 | X62: =+S62*25% -> 0 | Y62: =+W62-X62 -> 0 | Z62: =+'Asset Classification'!Q62 -> 3349466 | AA62: =+'Asset Classification'!R62 -> 0 | AB62: =+'Asset Classification'!S62 -> 1674733 | AC62: =+Z62*50% -> 1674733 | AD62: =+AB62-AC62 -> 0 | AE62: =+'Asset Classification'!T62 -> 0 | AF62: =+AA62*50% -> 0 | AG62: =+AE62-AF62 -> 0 | AH62: =+'Asset Classification'!U62 -> 0 | AI62: =+'Asset Classification'!V62 -> 0 | AJ62: =+'Asset Classification'!W62 -> 0 | AK62: =+AH62*100% -> 0 | AL62: =+AJ62-AK62 -> 0 | AM62: =+'Asset Classification'!X62 -> 0 | AN62: =+AI62*100% -> 0 | AO62: =+AM62-AN62 -> 0 | AP62: =+L62+T62+AB62+AJ62 -> 11229534 | AQ62: =+M62+U62+AC62+AK62 -> 11229533 | AR62: =+AP62-AQ62 -> 0.7 | AS62: =+O62+W62+AE62+AM62 -> 4717475 | AT62: =+P62+X62+AF62+AN62 -> 4717474.5 | AU62: =+AS62-AT62 -> 0.5
A63: 30 | B63: Наманган вилояти | C63: =+'Asset Classification'!C63 -> 757090397 | D63: =+'Asset Classification'!D63 -> 429761206 | E63: =+'Asset Classification'!E63 -> 587397636 | F63: =+'Asset Classification'!F63 -> 261323790 | G63: =+'Asset Classification'!G63 -> 4925718 | H63: =+E63*1% -> 5873976.4 | I63: =+G63-H63 -> -948258.36 | J63: =+'Asset Classification'!I63 -> 165531267 | K63: =+'Asset Classification'!J63 -> 164275922 | L63: =+'Asset Classification'!K63 -> 16553127 | M63: =+J63*10% -> 16553127 | N63: =+L63-M63 -> 0.3 | O63: =+'Asset Classification'!L63 -> 16427592 | P63: =+K63*10% -> 16427592 | Q63: =+O63-P63 -> -0.2 | R63: =+'Asset Classification'!M63 -> 3838715 | S63: =+'Asset Classification'!N63 -> 3838715 | T63: =+'Asset Classification'!O63 -> 959679 | U63: =+R63*25% -> 959678.75 | V63: =+T63-U63 -> 0.25 | W63: =+'Asset Classification'!P63 -> 959679 | X63: =+S63*25% -> 959678.75 | Y63: =+W63-X63 -> 0.25 | Z63: =+'Asset Classification'!Q63 -> 322779 | AA63: =+'Asset Classification'!R63 -> 322779 | AB63: =+'Asset Classification'!S63 -> 161389 | AC63: =+Z63*50% -> 161389.5 | AD63: =+AB63-AC63 -> -0.5 | AE63: =+'Asset Classification'!T63 -> 161389 | AF63: =+AA63*50% -> 161389.5 | AG63: =+AE63-AF63 -> -0.5 | AH63: =+'Asset Classification'!U63 -> 0 | AI63: =+'Asset Classification'!V63 -> 0 | AJ63: =+'Asset Classification'!W63 -> 0 | AK63: =+AH63*100% -> 0 | AL63: =+AJ63-AK63 -> 0 | AM63: =+'Asset Classification'!X63 -> 0 | AN63: =+AI63*100% -> 0 | AO63: =+AM63-AN63 -> 0 | AP63: =+L63+T63+AB63+AJ63 -> 17674195 | AQ63: =+M63+U63+AC63+AK63 -> 17674195 | AR63: =+AP63-AQ63 -> 0.049999997 | AS63: =+O63+W63+AE63+AM63 -> 17548660 | AT63: =+P63+X63+AF63+AN63 -> 17548660 | AU63: =+AS63-AT63 -> -0.45
A64: 31 | B64: Самарқанд вилояти | C64: =+'Asset Classification'!C64 -> 2420982190 | D64: =+'Asset Classification'!D64 -> 1648522478 | E64: =+'Asset Classification'!E64 -> 2264138921 | F64: =+'Asset Classification'!F64 -> 1518504487 | G64: =+'Asset Classification'!G64 -> 12742160 | H64: =+E64*1% -> 22641389 | I64: =+G64-H64 -> -9899229.2 | J64: =+'Asset Classification'!I64 -> 108600204 | K64: =+'Asset Classification'!J64 -> 96351118 | L64: =+'Asset Classification'!K64 -> 10860020 | M64: =+J64*10% -> 10860020 | N64: =+L64-M64 -> -0.4 | O64: =+'Asset Classification'!L64 -> 9635112 | P64: =+K64*10% -> 9635111.8 | Q64: =+O64-P64 -> 0.2 | R64: =+'Asset Classification'!M64 -> 18060682 | S64: =+'Asset Classification'!N64 -> 15799240 | T64: =+'Asset Classification'!O64 -> 4515171 | U64: =+R64*25% -> 4515170.5 | V64: =+T64-U64 -> 0.5 | W64: =+'Asset Classification'!P64 -> 3949810 | X64: =+S64*25% -> 3949810 | Y64: =+W64-X64 -> 0 | Z64: =+'Asset Classification'!Q64 -> 7981783 | AA64: =+'Asset Classification'!R64 -> 7899141 | AB64: =+'Asset Classification'!S64 -> 3990891 | AC64: =+Z64*50% -> 3990891.5 | AD64: =+AB64-AC64 -> -0.5 | AE64: =+'Asset Classification'!T64 -> 3949570 | AF64: =+AA64*50% -> 3949570.5 | AG64: =+AE64-AF64 -> -0.5 | AH64: =+'Asset Classification'!U64 -> 22200600 | AI64: =+'Asset Classification'!V64 -> 9968492 | AJ64: =+'Asset Classification'!W64 -> 22200600 | AK64: =+AH64*100% -> 22200600 | AL64: =+AJ64-AK64 -> 0 | AM64: =+'Asset Classification'!X64 -> 9968492 | AN64: =+AI64*100% -> 9968492 | AO64: =+AM64-AN64 -> 0 | AP64: =+L64+T64+AB64+AJ64 -> 41566682 | AQ64: =+M64+U64+AC64+AK64 -> 41566682 | AR64: =+AP64-AQ64 -> -0.4 | AS64: =+O64+W64+AE64+AM64 -> 27502984 | AT64: =+P64+X64+AF64+AN64 -> 27502984 | AU64: =+AS64-AT64 -> -0.3
