Workbook
Name jop: #REF!
Name kol: #REF!
Name OLE_LINK19: Balance!$D$34
Name TwentyLargestData: #REF!
Name Е: #REF!

Sheet Balance
A1: СТРУКТУРА БАЛАНСА БАНКА | E1: Таблица-1 | G1: №4
B2: =IF(C3>0," "&TEXT(C3,"д ММММ, гггг"),"Число,Месяц,Год") -> 31 Декабрь, 2021
B3: АК "АЛОКАБАНК" | C3: 44561 | E3: тыс. сум
A4: № | B4: АКТИВЫ | C4: Итого | D4: в национальной валюте | E4: в иностранной валюте (в экв. в сумах)
A5: 1 | B5: Кассовая наличность и другие платежные документы | C5: =+D5+E5 -> 275813889 | D5: =+'Bank Assets Analysis'!T7 -> 94523100 | E5: =+'Bank Assets Analysis'!U7 -> 181290789 | J5: =+C5-D5-E5 -> 0
A6: 2 | B6: К получению из ЦБРУ | C6: =+D6+E6 -> 1238811513 | D6: =+'Bank Assets Analysis'!T9+'Bank Assets Analysis'!T10 -> 988225440 | E6: =+'Bank Assets Analysis'!U9+'Bank Assets Analysis'!U10 -> 250586073 | J6: =+C6-D6-E6 -> 0
A7: 3 | B7: К получению из других банков, чистые | C7: =+'Bank Assets Analysis'!S11 -> 901416758 | D7: =+'Bank Assets Analysis'!T11 -> 168833754 | E7: =+'Bank Assets Analysis'!U11 -> 732583004 | J7: =+C7-D7-E7 -> 0
A8: 3.1. | B8: К получению из других банков, брутто | C8: =+D8+E8 -> 901416758 | D8: 168833754 | E8: 732583004 | J8: =+C8-D8-E8 -> 0
A9: 3.2. | B9: Минус: Резерв возможных убытков | C9: =+D9+E9 -> 0 | D9: 0 | J9: =+C9-D9-E9 -> 0
A10: 4 | B10: Счета купли и продажи, чистые | C10: =+D10+E10 -> 409972435 | D10: =+'Investment Securities'!C29 -> 409972435 | E10: =+'Investment Securities'!D29 -> 0 | J10: =+C10-D10-E10 -> 0
A11: 4.1. | B11: Ценные бумаги для купли продажи, брутто | C11: =+D11+E11 -> 418105000 | D11: =+'Investment Securities'!C26 -> 418105000 | E11: =+'Investment Securities'!D26 -> 0 | J11: =+C11-D11-E11 -> 0
A12: 4.2. | B12: Дисконт и премии по ценным бумагам | C12: =+D12+E12 -> -8132565 | D12: =+'Investment Securities'!C27 -> -8132565 | E12: =+'Investment Securities'!D27 -> 0
A13: 4.3. | B13: Минус: Резерв возможных убытков | C13: =+D13+E13 -> 0 | D13: =+'Investment Securities'!C28 -> 0 | E13: =+'Investment Securities'!D28 -> 0 | J13: =+C13-D13-E13 -> 0
A14: 5 | B14: Драгоценные металлы, монеты, камни, чистые | C14: =+C15-C16 -> 251 | D14: =+'Investment Securities'!C40 -> 251 | E14: =+'Investment Securities'!D40 -> 0 | J14: =+C14-D14-E14 -> 0
A15: 5.1. | B15: Драгоценные металлы, монеты, камни, брутто | C15: =+D15+E15 -> 251 | D15: =+'Investment Securities'!C38 -> 251 | E15: =+'Investment Securities'!D38 -> 0 | J15: =+C15-D15-E15 -> 0
A16: 5.2. | B16: Минус: Резерв возможных убытков | C16: =+D16+E16 -> 0 | D16: =+'Investment Securities'!C39 -> 0 | E16: =+'Investment Securities'!D39 -> 0 | J16: =+C16-D16-E16 -> 0
A17: 6 | B17: Инвестиции, чистые | C17: =+'Investment Securities'!B15 -> 98339066 | D17: =+'Investment Securities'!C15 -> 98339066 | E17: =+'Investment Securities'!D15 -> 0 | J17: =+C17-D17-E17 -> 0
A18: 6.1. | B18: Инвестиции, брутто | C18: =+D18+E18 -> 98339066 | D18: =+'Investment Securities'!C13 -> 98339066 | E18: =+'Investment Securities'!D13 -> 0 | J18: =+C18-D18-E18 -> 0
A19: 6.2. | B19: Минус: Резерв возможных убытков | C19: =+D19+E19 -> 0 | D19: =+'Investment Securities'!C14 -> 0 | E19: =+'Investment Securities'!D14 -> 0 | J19: =+C19-D19-E19 -> 0
A20: 7 | B20: Ценные бумаги купленные по соглашению c обратным выкупом, чистые | C20: =+'Bank Assets Analysis'!S35 -> 0 | D20: =+'Bank Assets Analysis'!T35 -> 0 | E20: =+'Bank Assets Analysis'!U35 -> 0 | J20: =+C20-D20-E20 -> 0
A21: 7.1. | B21: Ценные бумаги, купленные по соглашению с обратным выкупом, брутто | C21: =+D21+E21 -> 0 | D21: 0 | E21: 0 | J21: =+C21-D21-E21 -> 0
A22: 7.2. | B22: Резерв возможных убытков | C22: =+D22+E22 -> 0 | D22: 0 | E22: 0 | J22: =+C22-D22-E22 -> 0
A23: 8 | B23: Кредиты и лизинговые операции, чистые | C23: =+'Bank Assets Analysis'!S30+'Bank Assets Analysis'!S31+'Bank Assets Analysis'!S33 -> 7653319526 | D23: =+'Bank Assets Analysis'!T30+'Bank Assets Analysis'!T31+'Bank Assets Analysis'!T33 -> 4721593409 | E23: =+'Bank Assets Analysis'!U30+'Bank Assets Analysis'!U31+'Bank Assets Analysis'!U33 -> 2931726117 | J23: =+C23-D23-E23 -> 0
A24: 8.1. | B24: Кредиты и лизинговые операции, брутто | C24: =+D24+E24 -> 7754313870 | D24: 4807418969 | E24: 2946894901 | J24: =+C24-D24-E24 -> 0
A25: 8.2. | B25: Минус: Резерв возможных убытков | C25: =+D25+E25 -> 100994344 | D25: 85825560 | E25: 15168784 | J25: =+C25-D25-E25 -> 0
A26: 9 | B26: Купленные векселя, чистые | C26: =+'Bank Assets Analysis'!S26 -> 0 | D26: =+'Bank Assets Analysis'!T26 -> 0 | E26: =+'Bank Assets Analysis'!U26 -> 0 | J26: =+C26-D26-E26 -> 0
A27: 9.1. | B27: Купленные векселя, брутто | C27: =+D27+E27 -> 0 | D27: 0 | E27: 0 | J27: =+C27-D27-E27 -> 0
A28: 9.2. | B28: Минус: Резерв возможных убытков | C28: =+D28+E28 -> 0 | D28: 0 | E28: 0 | J28: =+C28-D28-E28 -> 0
A29: 10 | B29: Обязательства клиентов по финансовым инструментам, чистые | C29: =+D29+E29 -> 532887227 | D29: =+'Bank Assets Analysis'!T27+'Bank Assets Analysis'!T28 -> 0 | E29: =+'Bank Assets Analysis'!U27+'Bank Assets Analysis'!U28 -> 532887227 | J29: =+C29-D29-E29 -> 0
A30: 10.1. | B30: Обязательства клиентов по финансовым инструментам, брутто | C30: =+D30+E30 -> 533298096 | D30: 0 | E30: 533298096 | J30: =+C30-D30-E30 -> 0
A31: 10.2. | B31: Минус: Резерв возможных убытков | C31: =+D31+E31 -> 410869 | D31: 0 | E31: 410869 | J31: =+C31-D31-E31 -> 0
A32: 11 | B32: Основные средства, чистые | C32: =+'Bank Assets Analysis'!S38 -> 812267548 | D32: =+'Bank Assets Analysis'!T38 -> 812267548 | E32: =+'Bank Assets Analysis'!U38 -> 0 | J32: =+C32-D32-E32 -> 0
A33: 12 | B33: Начисленные процентные и беспроцентные доходы всего, чистые | C33: =+C34+C35-C36 -> 198065177 | D33: =+D34+D35-D36 -> 140932606 | E33: =+E34+E35-E36 -> 57132571 | J33: =+C33-D33-E33 -> 0
A34: 12.1. | B34: Начисленные проценты к получению, брутто | C34: =+'Bank Assets Analysis'!S43 -> 163425953 | D34: =+'Bank Assets Analysis'!T43 -> 113096761 | E34: =+'Bank Assets Analysis'!U43 -> 50329192 | J34: =+C34-D34-E34 -> 0
A35: 12.2. | B35: Начисленные беспроцентные доходы к получению, брутто | C35: =+D35+E35 -> 34639224 | D35: 27835845 | E35: 6803379 | J35: =+C35-D35-E35 -> 0
A36: 12.2.1. | B36: Минус: Резерв возможных убытков | C36: =+D36+E36 -> 0 | E36: 0 | J36: =+C36-D36-E36 -> 0
A37: 13 | B37: Другое собственное имущество банка, чистые | C37: =+'Bank Assets Analysis'!S39 -> 51751710 | D37: =+'Bank Assets Analysis'!T39 -> 51751710 | E37: =+'Bank Assets Analysis'!U39 -> 0 | J37: =+C37-D37-E37 -> 0
A38: 13.1. | B38: Другие собственное имущество, взысканное по кредитам и лизингу, брутто | C38: =+D38+E38 -> 49273851 | D38: 49273851 | E38: 0 | J38: =+C38-D38-E38 -> 0
A39: 13.2. | B39: Другое собственное имущество банка, брутто | C39: =+D39+E39 -> 2477859 | D39: 2477859 | E39: 0 | J39: =+C39-D39-E39 -> 0
A40: 13.3. | B40: Минус:Накопленный износ и резервы на возможные убытки | C40: =+D40+E40 -> 0 | D40: 0 | E40: 0 | J40: =+C40-D40-E40 -> 0
A41: 14 | B41: Другие активы, чистые | C41: =+C42-C43+C44 -> 465811523 | D41: =+D42-D43+D44 -> 337846608 | E41: =+E42-E43+E44 -> 127964915 | J41: =+C41-D41-E41 -> 0
A42: 14.1. | B42: Другие активы, брутто | C42: =+D42+E42 -> 466430498 | D42: =338465585-2 -> 338465583 | E42: =127964916-1 -> 127964915 | J42: =+C42-D42-E42 -> 0
A43: 14.2. | B43: Минус: Резерв возможных убытков | C43: =+D43+E43 -> 618975 | D43: 618975 | E43: 0 | J43: =+C43-D43-E43 -> 0
A44: 14.3. | B44: Купля-продажа валюты и валютные позиции | J44: =+C44-D44-E44 -> 0
A45: 15. | B45: Итого активов | C45: =+D45+E45 -> 12638456623 | D45: =+D5+D6+D7+D10+D14+D17+D20+D23+D26+D29+D32+D33+D37+D41 -> 7824285927 | E45: =+E5+E6+E7+E10+E14+E17+E20+E23+E26+E29+E32+E33+E37+E41 -> 4814170696 | F45: =+'Bank Assets Analysis'!S46 -> 12638456623 | G45: =+'Bank Assets Analysis'!T46 -> 7824285927 | H45: =+'Bank Assets Analysis'!U46 -> 4814170696 | J45: =+C45-D45-E45 -> 0
B47: ОБЯЗАТЕЛЬСТВА И СОБСТВЕННЫЙ КАПИТАЛ
B49: ОБЯЗАТЕЛЬСТВА
A50: 16. | B50: Депозиты до востребования | C50: =+'Deposits by Client'!C11 -> 2036926378 | D50: =+'Bank Liabilities Analysis'!T16+'Bank Liabilities Analysis'!T8 -> 1682838498 | E50: =+'Bank Liabilities Analysis'!U16+'Bank Liabilities Analysis'!U8 -> 354087880 | J50: =+C50-D50-E50 -> 0
A51: 17. | B51: Срочные депозиты | C51: =+'Deposits by Client'!C20 -> 4759182805 | D51: =+'Bank Liabilities Analysis'!T13 -> 3068956642 | E51: =+'Bank Liabilities Analysis'!U13 -> 1690226163 | J51: =+C51-D51-E51 -> 0
A52: 18. | B52: К оплате в ЦБРУ | C52: =+'Bank Liabilities Analysis'!S23 -> 0 | D52: =+'Bank Liabilities Analysis'!T23 -> 0 | E52: =+'Bank Liabilities Analysis'!U23 -> 0 | J52: =+C52-D52-E52 -> 0
A53: 19. | B53: К оплате в другие банки | C53: =+'Bank Liabilities Analysis'!S24 -> 1231537343 | D53: =+'Bank Liabilities Analysis'!T24 -> 413133609 | E53: =+'Bank Liabilities Analysis'!U24 -> 818403734 | J53: =+C53-D53-E53 -> 0
A54: 20. | B54: Проданные по сделкам РЕПО ценные бумаги | C54: =+'Bank Liabilities Analysis'!S34 -> 419204674 | D54: =+'Bank Liabilities Analysis'!T34 -> 419204674 | E54: =+'Bank Liabilities Analysis'!U34 -> 0 | J54: =+C54-D54-E54 -> 0
A55: 21. | B55: Кредиты и лизинговые операции к оплате | C55: =+D55+E55 -> 2271008779 | D55: 347524121 | E55: 1923484658 | J55: =+C55-D55-E55 -> 0
A56: 22. | B56: Выпущенные банком ценные бумаги | C56: =+D56+E56 -> 0 | J56: =+C56-D56-E56 -> 0
A57: 23. | B57: Субординированные долговые обязательства | C57: =+D57+E57 -> 0 | J57: =+C57-D57-E57 -> 0
A58: 24. | B58: Начисленные проценты к оплате | C58: =+'Bank Liabilities Analysis'!S37 -> 29804270 | D58: =+'Bank Liabilities Analysis'!T37 -> 17836864 | E58: =+'Bank Liabilities Analysis'!U37 -> 11967406 | J58: =+C58-D58-E58 -> 0
A59: 25. | B59: Начисленные налоги к оплате | C59: =+D59+E59 -> 973255 | D59: 973255 | J59: =+C59-D59-E59 -> 0
A60: 26. | B60: Клиринговые трансакции | C60: =+'Bank Liabilities Analysis'!S36 -> 7801403 | D60: =+'Bank Liabilities Analysis'!T36 -> 112032 | E60: =+'Bank Liabilities Analysis'!U36 -> 7689371 | J60: =+C60-D60-E60 -> 0
A61: 27. | B61: Другие обязательства | C61: =+D61+E61 -> 208511773 | D61: 85016456 | E61: 123495317 | J61: =+C61-D61-E61 -> 0
A62: 28. | B62: Итого обязательств | C62: =+D62+E62 -> 10964950680 | D62: =SUM(D50:D61) -> 6035596151 | E62: =SUM(E50:E61) -> 4929354529 | F62: =+'Bank Liabilities Analysis'!S39 -> 10964950680 | G62: =+'Bank Liabilities Analysis'!T39 -> 6035596151 | H62: =+'Bank Liabilities Analysis'!U39 -> 4929354529 | J62: =+C62-D62-E62 -> 0
J63: =+C63-D63-E63 -> 0
B64: СОБСТВЕННЫЙ КАПИТАЛ | J64: =+C64-D64-E64 -> 0
J65: =+C65-D65-E65 -> 0
A66: 29. | B66: Уставный капитал | J66: =+C66-D66-E66 -> 0
A67: 29.1. | B67: Акции - Обыкновенные | C67: =+D67+E67 -> 951406520 | D67: 951406520 | J67: =+C67-D67-E67 -> 0
A68: 29.2. | B68: Акции - Привилегированные | C68: =+D68+E68 -> 2178000 | D68: 2178000 | J68: =+C68-D68-E68 -> 0
A69: 30. | B69: Добавленный капитал | C69: =+D69+E69 -> 3906139 | D69: 3906139 | J69: =+C69-D69-E69 -> 0
A70: 31. | B70: Резервный капитал. | J70: =+C70-D70-E70 -> 0
A71: 31.1. | B71: Резервный фонд общего назначения | C71: =+D71+E71 -> 475647734 | D71: 475647734 | J71: =+C71-D71-E71 -> 0
A72: 31.2. | B72: Резервы созданные по стандартным активам | C72: =+D72+E72 -> 101782253 | D72: 101782253 | J72: =+C72-D72-E72 -> 0
A73: 31.3. | B73: Резерв на Девальвацию | C73: =+D73+E73 -> 0 | D73: 0 | J73: =+C73-D73-E73 -> 0
A74: 31.4. | B74: Другие резервы и фонды | C74: =+D74+E74 -> 26277853 | D74: 26277853 | J74: =+C74-D74-E74 -> 0
A75: 32. | B75: Нераспределенная прибыль | C75: =+D75+E75 -> 112307444 | D75: 112307444 | J75: =+C75-D75-E75 -> 0
A76: 32.1. | B76: из них, чистая прибыль (убыток) текущего года | C76: =+D76+E76 -> 107582490 | D76: 107582490 | J76: =+C76-D76-E76 -> 0
A77: 33. | B77: Итого собственного капитала | C77: =SUM(C67:C75) -> 1673505943 | D77: =SUM(D67:D75) -> 1673505943 | E77: =SUM(E67:E75) -> 0 | J77: =+C77-D77-E77 -> 0
A78: 34. | B78: Итого обязательств и собственного капитала | C78: =+D78+E78 -> 12638456623 | D78: =+D62+D77 -> 7709102094 | E78: =+E62+E77 -> 4929354529 | J78: =+C78-D78-E78 -> 0
B80: Подпись Председателя правления:
B82: Подпись Главного Бухгалтера:
C84: =+C45-C78 -> 0

Sheet Bank Capital Calc (2)
A1: РАСЧЕТ РЕГУЛЯТИВНОГО КАПИТАЛА БАНКА | C1: Таблица-5
B3: =Balance!B3 -> АК "АЛОКАБАНК" | C3: =+Balance!C3 -> 44561
A4: № | B4: Характеристики | C4: Итого капитала
A5: I. | B5: КАПИТАЛ УРОВНЯ 1
A6: 1 | B6: ОСНОВНОЙ КАПИТАЛ УРОВНЯ 1
A7: 1.1. | B7: Обыкновенные Акции, чистые | C7: Формула
A8: a | B8: Полностью оплаченные обыкновенные акции
A9: б | B9: Минус: Обратно Выкупленные обыкновенные акции
A10: 1.2. | B10: Добавленный капитал - Обыкновенные | C10: 0
A11: 1.3. | B11: Нераспределенная прибыль (убыток), в том числе капитальные резервы | C11: Формула
A12: а | B12: Капитальные резервы
A13: б | B13: Нераспределенная прибыль
A14: в | B14: Убыток за предыдущие периоды
A15: г | B15: Убыток за текущий год
A16: 1.4. | B16: Интерес меньшинства в консолидированных дочерних компаниях (согласно МБС)
A17: 1.5. | B17: Резерв на девальвацию
B18: Итого основного капитала уровня I до вычетов | C18: Формула
A19: 1.6. | B19: Вычеты из суммы основного капитала уровня I | C19: Формула
A20: а | B20: Нематериальные активы
A21: б | B21: Все инвестиции в капитал неконсолидированных хозяйствующих субъектов, в том числе в долговые обязательства, которые образуют капитал хозяйствующих субъектов
A22: в | B22: Инвестиции в капитал других банков
A23: I | B23: ВСЕГО СКОРРЕКТИРОВАННЫЙ ОСНОВНОЙ КАПИТАЛ УРОВНЯ I | C23: Формула
A24: 2 | B24: ДОБАВЛЕННЫЙ КАПИТАЛ УРОВНЯ 1
A25: 2.1. | B25: Некумулятивные бессрочные привилегированные акции | C25: =+C26+C27 -> 0
A26: а | B26: Полностью оплаченные привилегированные акции
A27: б | B27: Минус: Обратно Выкупленные привилегированные акции
A28: 2.2. | B28: Добавленный капитал - Привилегированные | C28: 0
A29: 2.3. | B29: Интерес меньшинства в консолидированных дочерних компаниях | C29: 0
A30: 2.4. | B30: Доля участия дочерних предприятий (выпущенные дочерними предприятиями и находящиеся во владении третьих лиц инструменты, приравненные к капиталу) | C30: 0
A31: II | B31: ВСЕГО ДОБАВЛЕННЫЙ КАПИТАЛ УРОВНЯ I | C31: =+C25+C28+C29+C30 -> 0
A32: III | B32: ВСЕГО СКОРРЕКТИРОВАННЫЙ КАПИТАЛ УРОВНЯ I | C32: Формула
B33: КАПИТАЛ УРОВНЯ II
A34: 3.1. | B34: Прибыль за текущий год
A35: 3.2. | B35: Резервы, создаваемые на стандартные кредиты (активы), в размере не более 1.25% от общей суммы активов, взвешенных с учетом риска | C35: =IF(Balance!C72<(C43*1.25%),Balance!C72,(C43*1.25%)) -> #REF!
A36: 3.3. | B36: Излишки оценочной стоимости прироста над первоначальной стоимостью
A37: 3.4. | B37: Другие инструменты капитала (не более 1/3 части капитала 1 уровня после вычетов)
A38: 3.5. | B38: Субординированный долг
A39: 3.6. | B39: Вычеты превышения Капитала Уровня II над Капиталом Уровня I | C39: Формула
B40: Итого капитала Уровня II | C40: =SUM(C34:C38) -> #REF!
A41: IV | B41: СКОРРЕКТИРОВАННЫЙ КАПИТАЛ УРОВНЯ II | C41: Формула
A42: V | B42: ВСЕГО РЕГУЛЯТИВНЫЙ КАПИТАЛ | C42: Формула
A43: VI | B43: ОБЩАЯ СУММА АКТИВОВ ВЗВЕШЕННЫХ С УЧЕТОМ РИСКА | C43: =+C44+C45+C46 -> #REF!
A44: а | B44: Сумма балансовых и забалансовых активов, взвешенных с учетом риска | C44: =+#REF! -> #REF!
A45: б | B45: Операционный риск | C45: =+#REF! -> #REF!
A46: в | B46: Рыночный риск | C46: =+#REF! -> #REF! | E46: =+#REF! -> #REF!
A47: VII | B47: КОЭФФИЦИЕНТ ОСНОВНОГО КАПИТАЛА УРОВНЯ I (I/VI) | C47: Формула
A48: VIII | B48: КОЭФФИЦИЕНТ КАПИТАЛА УРОВНЯ I (III/VI) | C48: Формула
A49: IX | B49: КОЭФФИЦИЕНТ ОБЩЕЙ СУММЫ КАПИТАЛА, ОСНОВАННОГО НА РИСКЕ (V/VI) | C49: Формула
A50: X | B50: Активы для расчета левеража | C50: Формула
A51: а | B51: Общие активы | C51: =+Balance!C45 -> 12638456623
A52: б | B52: Забалансовые инструменты | C52: =SUM(#REF!) -> #REF! | D52: =+#REF! -> #REF!
A53: в | B53: Деривативные (производные) инструменты | C53: =SUM(#REF!) -> #REF!
A54: г | B54: Минус: Строка 1.6. Итого вычетов из суммы основного капитала Уровня 1 | C54: =+C19 -> Формула
A55: XI | B55: Коэффициент левеража | C55: Формула
B57: Подпись Председателя правления:
B59: Подпись Главного Бухгалтера:

Sheet Liquidity Analysis
B1: АНАЛИЗ ЛИКВИДНОСТИ | E1: Таблица-16
B2: =Balance!B3 -> АК "АЛОКАБАНК" | C2: =+Balance!B2 -> 31 Декабрь, 2021 | E2: в тыс. сум
A3: № | B3: Ликвидные активы | C3: Сумма | D3: Нацвалюта | E3: Инвалюта
B5: Часть 1. Высоколиквидные активы | C5: в процентах
A6: 1.1. | B6: Наличные денежные средства | C6: =+'Bank Assets Analysis'!S7-'Bank Assets Analysis'!S8 -> 275813889 | D6: =+'Bank Assets Analysis'!T7-'Bank Assets Analysis'!T8 -> 94523100 | E6: =+'Bank Assets Analysis'!U7-'Bank Assets Analysis'!U8 -> 181290789
A7: 1.2. | B7: К получению из ЦБРУ не учитывая сумму обязательных резервов банка(ФОР) | C7: =+'Bank Assets Analysis'!S9 -> 1146165457 | D7: =+'Bank Assets Analysis'!T9 -> 895579384 | E7: =+'Bank Assets Analysis'!U9 -> 250586073
A8: 1.3. | B8: Ценные бумаги, выпущенные Правительством Республики Узбекистан и ЦБРУ | C8: =+'Bank Assets Analysis'!S20-'Bank Assets Analysis'!S21+'Bank Assets Analysis'!S36 -> 0 | D8: =+'Bank Assets Analysis'!T20-'Bank Assets Analysis'!T21+'Bank Assets Analysis'!T36 -> 0 | E8: =+'Bank Assets Analysis'!U20-'Bank Assets Analysis'!U21+'Bank Assets Analysis'!U36 -> 0
A9: 1.4. | B9: Денежные средства на корсчетах открытых в иностранных банках с рейтингом не ниже инвестиционного и в местных банках имеющих кредитный рейтинг | C9: =+E9 -> 491758852 | E9: =+'Bank Assets Analysis'!D12+'Bank Assets Analysis'!D13 -> 491758852
A10: 1.5. | B10: Депозиты размещенные на условиях овернайт в иностранной валюте с рейтингом не ниже инвестиционного | C10: =+E10 -> 0 | E10: =+'Bank Assets Analysis'!F15 -> 0
A11: 1.6. | B11: Ценные бумаги выпущенные МВФ, входящие организации в группу Всемирного банка, МФК, АБР, Азиатский банк инфроструктуры и инвестиции, ЕБРР, Европейский инвестиционный банк, Исламский банк развития и Банк развития Европейского союза | C11: =+'Bank Assets Analysis'!S23 -> 0 | D11: =+'Bank Assets Analysis'!T23 -> 0 | E11: =+'Bank Assets Analysis'!U23 -> 0
A12: 1.7. | B12: Правительственные ценные бумаги стран с низкой степенью странового риска | C12: =+'Bank Assets Analysis'!S22 -> 0 | D12: =+'Bank Assets Analysis'!T22 -> 0 | E12: =+'Bank Assets Analysis'!U22 -> 0
A13: 1.8. | B13: Безотзывные кредитные линии | C13: =+D13 -> 0 | G13: Данную строку заполнять при заключении соответствующего кредитного договора с ЦБРУ. Отражается 2% нетто остатка от общих активов банка на отчётную дату.
A14: 1.9. | B14: Высоколиквидные активы находящиеся под залогом | C14: =+'Bank Assets Analysis'!S45 -> 0 | D14: =+'Bank Assets Analysis'!T45 -> 0 | E14: =+'Bank Assets Analysis'!U45 -> 0
A15: 1.10. | B15: Всего высоколиквидных активов | C15: =SUM(C6:C13)-'Bank Liabilities Analysis'!U25-C14 -> 1892965686 | D15: =SUM(D6:D13)-D14 -> 990102484 | E15: =SUM(E6:E13)-'Bank Liabilities Analysis'!U25-E14 -> 902863202
B16: Часть 2. Экономические нормативы - Ликвидность
A17: 2.1. | B17: Расчет коэффициента высоколиквидных активов к всего активам | C17: =IFERROR((+C18/C19),0) -> 0.14977823 | D17: =IFERROR((+D18/D19),0) -> 0.12654222 | E17: =IFERROR((+E18/E19),0) -> 0.18754283 | F17: =+(('Bank Liabilities Analysis'!C35+'Bank Liabilities Analysis'!E35+'Bank Liabilities Analysis'!G35-'Bank Liabilities Analysis'!C21-'Bank Liabilities Analysis'!E21-'Bank Liabilities Analysis'!G21)-(IF(F4<0,F4,0))) -> -80970337 | G17: =+(('Bank Liabilities Analysis (нац)'!C36+'Bank Liabilities Analysis (нац)'!D36+'Bank Liabilities Analysis (нац)'!E36--'Bank Liabilities Analysis (нац)'!C22-'Bank Liabilities Analysis (нац)'!D22-'Bank Liabilities Analysis (нац)'!E22)-(IF(G4<0,G4,0))) -> 69467399 | H17: =+(('Bank Liabilities Analysis'!D35+'Bank Liabilities Analysis'!F35+'Bank Liabilities Analysis'!H35-'Bank Liabilities Analysis'!D21-'Bank Liabilities Analysis'!F21-'Bank Liabilities Analysis'!H21)-(IF(H4<0,H4,0))) -> -11502938
A18: 2.1.1. | B18: Высоколиквидные активы | C18: =+C15 -> 1892965686 | D18: =+D15 -> 990102484 | E18: =+E15 -> 902863202
A19: 2.1.2. | B19: Всего активов | C19: =+Balance!C45 -> 12638456623 | D19: =+Balance!D45 -> 7824285927 | E19: =+Balance!E45 -> 4814170696
A20: 2.2. | B20: Расчет коэффициента высоколиквидных активов к краткосрочным обязательствам | C20: =IFERROR((+C21/C22),0) -> 0.27471558 | D20: =IFERROR((+D21/D22),0) -> 0.22038272 | E20: =IFERROR((+E21/E22),0) -> 0.37650864 | F20: =+(('Bank Liabilities Analysis'!C38+'Bank Liabilities Analysis'!E38+'Bank Liabilities Analysis'!G38-'Bank Liabilities Analysis'!C24-'Bank Liabilities Analysis'!E24-'Bank Liabilities Analysis'!G24)-(IF('Liquidity Analysis'!G52<0,'Liquidity Analysis'!G52,0))) -> -29414180 | G20: =+(('Bank Liabilities Analysis (нац)'!C39+'Bank Liabilities Analysis (нац)'!D39+'Bank Liabilities Analysis (нац)'!E39--'Bank Liabilities Analysis (нац)'!C25-'Bank Liabilities Analysis (нац)'!D25-'Bank Liabilities Analysis (нац)'!E25)-(IF('Liquidity Analysis'!H52<0,'Liquidity Analysis'!H52,0))) -> 81970295 | H20: =+(('Bank Liabilities Analysis'!D38+'Bank Liabilities Analysis'!F38+'Bank Liabilities Analysis'!H38-'Bank Liabilities Analysis'!D24-'Bank Liabilities Analysis'!F24-'Bank Liabilities Analysis'!H24)-(IF('Liquidity Analysis'!I52<0,'Liquidity Analysis'!I52,0))) -> -94489497
A21: 2.2.1. | B21: Высоколиквидные активы | C21: =+C15 -> 1892965686 | D21: =+D15 -> 990102484 | E21: =+E15 -> 902863202
A22: 2.2.2. | B22: Краткосрочные обязательства | C22: =+'Bank Liabilities Analysis'!C39+'Bank Liabilities Analysis'!E39+'Bank Liabilities Analysis'!G39+'Bank Liabilities Analysis'!I39+'Bank Liabilities Analysis'!K39+'Bank Liabilities Analysis'!M39 -> 6890638208 | D22: =+C22-E22 -> 4492650236 | E22: =+'Bank Liabilities Analysis'!D39+'Bank Liabilities Analysis'!F39+'Bank Liabilities Analysis'!H39+'Bank Liabilities Analysis'!J39+'Bank Liabilities Analysis'!L39+'Bank Liabilities Analysis'!N39 -> 2397987972
A23: 2.3. | B23: Коэффициент покрытия ликвидности | C23: =IFERROR((+C24/C25),0) -> 1.108638 | D23: =IFERROR((+D24/D25),0) -> 1.1563961 | E23: =IFERROR((+E24/E25),0) -> 1.0606036
A24: 2.3.1. | B24: Высоколиквидные активы | C24: =+C15 -> 1892965686 | D24: =+D15 -> 990102484 | E24: =+E15 -> 902863202
A25: 2.3.2. | B25: Чистый отток в последующие 30 дней | C25: =+'Bank Assets Analysis'!X64 -> 1.7074696e+09 | D25: =+'Bank Assets Analysis (нац)'!P57 -> 8.5619664e+08 | E25: =+'Bank Assets Analysis'!Z64 -> 8.5127301e+08
B26: Сумма оттока за 30 дней | C26: =+'Bank Assets Analysis'!X66 -> 1.9462707e+09 | D26: =+'Bank Assets Analysis (нац)'!P59 -> 9.8277233e+08 | E26: =+'Bank Assets Analysis'!Z66 -> 9.6349836e+08
B27: Сумма притока за 30 дней | C27: =+'Bank Assets Analysis'!X69 -> 2.3880105e+08 | D27: =+'Bank Assets Analysis (нац)'!P61 -> 126575692 | E27: =+'Bank Assets Analysis'!Z69 -> 1.1222536e+08
A28: 2.4. | B28: Норма чистого стабильного финансирования | C28: =IFERROR((C29/C34),0) -> 1.0801928 | D28: =IFERROR((D29/D34),0) -> 1.0178285 | E28: =IFERROR((E29/E34),0) -> 1.181868
A29: 2.5. | B29: Доступная сумма стабильного финансирования | C29: =SUM(C30:C33) -> 7.8150099e+09 | D29: =SUM(D30:D33) -> 4.5642469e+09 | E29: =SUM(E30:E33) -> 3.2507629e+09
A30: 2.5.1. | B30: Собственный капитал | C30: =Balance!C77 -> 1673505943 | D30: =Balance!D77 -> 1673505943 | E30: =Balance!E77 -> 0
A31: 2.5.2. | B31: Обязательства свыше 1 года | C31: ='Bank Liabilities Analysis'!O39+'Bank Liabilities Analysis'!Q39 -> 4074312472 | D31: =+'Bank Liabilities Analysis (нац)'!I40+'Bank Liabilities Analysis (нац)'!J40 -> 1542945915 | E31: ='Bank Liabilities Analysis'!P39+'Bank Liabilities Analysis'!R39 -> 2531366557
A32: 2.5.3. | B32: 30% других бессрочных обязательств | C32: =+('Bank Liabilities Analysis'!C39)*0.3 -> 6.7451266e+08 | D32: =+('Bank Liabilities Analysis (нац)'!C40)*0.3 -> 531322440 | E32: =+('Bank Liabilities Analysis'!D39)*0.3 -> 1.4319022e+08
A33: 2.5.4. | B33: 30% других обязательств менее 1 года | C33: =+('Bank Liabilities Analysis'!E39+'Bank Liabilities Analysis'!G39+'Bank Liabilities Analysis'!I39+'Bank Liabilities Analysis'!K39+'Bank Liabilities Analysis'!M39)*0.3 -> 1.3926788e+09 | D33: =+('Bank Liabilities Analysis (нац)'!D40+'Bank Liabilities Analysis (нац)'!E40+'Bank Liabilities Analysis (нац)'!F40+'Bank Liabilities Analysis (нац)'!G40+'Bank Liabilities Analysis (нац)'!H40)*0.3 -> 8.1647263e+08 | E33: =+('Bank Liabilities Analysis'!F39+'Bank Liabilities Analysis'!H39+'Bank Liabilities Analysis'!J39+'Bank Liabilities Analysis'!L39+'Bank Liabilities Analysis'!N39)*0.3 -> 576206175
A34: 2.6. | B34: Необходимая сумма стабильного финансирования | C34: =SUM(C35:C40) -> 7.2348284e+09 | D34: =SUM(D35:D40) -> 4.4842987e+09 | E34: =SUM(E35:E40) -> 2.7505297e+09
A35: 2.6.1. | B35: Активы свыше 1 года | C35: =+'Bank Assets Analysis'!O46-'Bank Assets Analysis'!O38+'Bank Assets Analysis'!Q46-'Bank Assets Analysis'!Q38 -> 4765291245 | D35: =+C35-E35 -> 2710323587 | E35: =+'Bank Assets Analysis'!P46-'Bank Assets Analysis'!P41-'Bank Assets Analysis'!P38+'Bank Assets Analysis'!R46-'Bank Assets Analysis'!R41-'Bank Assets Analysis'!R38 -> 2054967658
A36: 2.6.2. | B36: Банковские помещения, мебель и оборудование, чистые | C36: =+'Bank Assets Analysis'!S38 -> 812267548 | D36: =+'Bank Assets Analysis'!T38 -> 812267548 | E36: =+'Bank Assets Analysis'!U38 -> 0
A37: 2.6.3. | B37: Кредиты, лизинги и авансы в процессе судебного разбирательства или не взысканные в установленном порядке (чистые) | C37: =+'Bank Assets Analysis'!C29+'Bank Assets Analysis'!C30+'Bank Assets Analysis'!C31+'Bank Assets Analysis'!C33 -> 61329066 | D37: =+'Bank Assets Analysis (нац)'!C29+'Bank Assets Analysis (нац)'!C30+'Bank Assets Analysis (нац)'!C31+'Bank Assets Analysis (нац)'!C33 -> 39175117 | E37: =+'Bank Assets Analysis'!D29+'Bank Assets Analysis'!D30+'Bank Assets Analysis'!D31+'Bank Assets Analysis'!D33 -> 22153949
A38: 2.6.4. | B38: Активы в процессе судебного разбирательства или не взысканные в установленном порядке, чистые (не указанные в строке 2.6.3.) | C38: =+D38+E38 -> 0 | D38: 0 | E38: 0
A39: 2.6.5. | B39: 30% других активов менее 1 го года (за исключением бессрочных и со сроком менее 1 го года ликвидных активов) | C39: =(+'Bank Assets Analysis'!S46-'Bank Assets Analysis'!O46-'Bank Assets Analysis'!Q46-'Liquidity Analysis'!C57)*0.3 -> 1.3709521e+09 | D39: =('Bank Assets Analysis (нац)'!K46-'Bank Assets Analysis (нац)'!I46-'Bank Assets Analysis (нац)'!J46-'Liquidity Analysis'!D57)*0.3 -> 8.4011825e+08 | E39: =('Bank Assets Analysis'!U46-'Bank Assets Analysis'!P46-'Bank Assets Analysis'!R46-'Liquidity Analysis'!E57)*0.3 -> 5.3083388e+08
A40: 2.6.6. | B40: 15% из забалансовых инструментов | C40: =+ROUND(SUM(Commitments!C4-Commitments!C5+Commitments!C7-Commitments!C8+Commitments!C10-'Bank Liabilities Analysis'!S19)*15%,0) -> 224988397 | D40: =+ROUND(SUM(Commitments!D4-Commitments!D5+Commitments!D7-Commitments!D8+Commitments!D10-'Bank Liabilities Analysis'!T19)*15%,0) -> 82414190 | E40: =+ROUND(SUM(Commitments!E4-Commitments!E5+Commitments!E7-Commitments!E8+Commitments!E10-'Bank Liabilities Analysis'!U19)*15%,0) -> 142574207
B43: Подпись Председателя правления:
B45: Подпись Главного Бухгалтера:
A49: № | B49: Ликвидные активы | C49: Сумма | D49: Нацвалюта | E49: Инвалюта
A50: 1. | B50: Наличные денежные средства и Драгоценные металлы | C50: =+'Bank Assets Analysis'!S7+'Investment Securities'!B40 -> 275814140 | D50: =+'Bank Assets Analysis'!T7+'Investment Securities'!C40 -> 94523351 | E50: =+'Bank Assets Analysis'!U7+'Investment Securities'!D40 -> 181290789
A51: 2. | B51: К получению из ЦБРУ | C51: =+'Bank Assets Analysis'!S9+'Bank Assets Analysis'!S10 -> 1238811513 | D51: =+'Bank Assets Analysis'!T9+'Bank Assets Analysis'!T10 -> 988225440 | E51: =+'Bank Assets Analysis'!U9+'Bank Assets Analysis'!U10 -> 250586073
A52: 3. | B52: К получению из других банков | C52: ='Bank Assets Analysis'!C12+'Bank Assets Analysis'!C13+'Bank Assets Analysis'!C14+'Bank Assets Analysis'!C17+'Bank Assets Analysis'!C18+'Bank Assets Analysis'!E18+'Bank Assets Analysis'!G18 -> 558326754 | D52: =+C52-E52 -> 446829 | E52: ='Bank Assets Analysis'!D12+'Bank Assets Analysis'!D13+'Bank Assets Analysis'!D17+'Bank Assets Analysis'!D18+'Bank Assets Analysis'!F18+'Bank Assets Analysis'!H18 -> 557879925
A53: 3.1. | B53: К получению из других банков - Депозиты (чистые) | C53: =IF(F53>0,F53,0) -> 0 | D53: =IF(G53>0,G53,0) -> 0 | E53: =IF(H53>0,H53,0) -> 0 | F53: =(('Bank Assets Analysis'!E12+'Bank Assets Analysis'!E14+'Bank Assets Analysis'!G12+'Bank Assets Analysis'!C16+'Bank Assets Analysis'!E16+'Bank Assets Analysis'!G16)-'Bank Liabilities Analysis'!C26-'Bank Liabilities Analysis'!E26-'Bank Liabilities Analysis'!G26) -> -181404769 | G53: =+('Bank Assets Analysis'!E12-'Bank Assets Analysis'!F12+'Bank Assets Analysis'!G12-'Bank Assets Analysis'!H12+'Bank Assets Analysis'!E14-'Bank Assets Analysis'!F14+'Bank Assets Analysis'!C16-'Bank Assets Analysis'!D16+'Bank Assets Analysis'!E16-'Bank Assets Analysis'!F16+'Bank Assets Analysis'!G16-'Bank Assets Analysis'!H16)-('Bank Liabilities Analysis'!C26-'Bank Liabilities Analysis'!D26+'Bank Liabilities Analysis'!E26-'Bank Liabilities Analysis'!F26+'Bank Liabilities Analysis'!G26-'Bank Liabilities Analysis'!H26) -> -15197380 | H53: =(('Bank Assets Analysis'!F12+'Bank Assets Analysis'!F14+'Bank Assets Analysis'!H12+'Bank Assets Analysis'!D16+'Bank Assets Analysis'!F16+'Bank Assets Analysis'!H16)-'Bank Liabilities Analysis'!D26-'Bank Liabilities Analysis'!F26-'Bank Liabilities Analysis'!H26) -> -166207389
A54: 4. | B54: Ценные бумаги, выпущенные Правительством Республики Узбекистан и ЦБРУ (векселя, облигации и другие долговые ценные бумаги) | C54: =+'Investment Securities'!B19+'Investment Securities'!B20+'Investment Securities'!B21 -> 418105000 | D54: =+'Investment Securities'!C19+'Investment Securities'!C20+'Investment Securities'!C21 -> 418105000 | E54: =+'Investment Securities'!D19+'Investment Securities'!D20+'Investment Securities'!D21 -> 0
A55: 5. | B55: Ценные бумаги, выпущенные странами с низким уровня риска
A56: 6. | B56: Другие легко реализуемые ценные бумаги
A57: 7. | B57: Итого ликвидных активов | C57: =SUM(C50:C56) -> 2491057407 | D57: =SUM(D50:D56) -> 1501300620 | E57: =SUM(E50:E56) -> 989756787

Sheet Bank Assets Analysis
A1: АНАЛИЗ АКТИВОВ БАНКА | X1: Таблица-17
B2: =Balance!B3 -> АК "АЛОКАБАНК" | T2: =+Balance!B2 -> 31 Декабрь, 2021 | Z2: в тыс. сум
A3: № | B3: Характеристики | C3: Срок погашения (в днях) | S3: ВСЕГО | T3: из них | V3: Расчет коэффициента покрытия ликвидности
C4: Бессрочные | E4: От 1 до 7 дней | G4: От 8 до 30 дней | I4: От 31 до 90 дней | K4: От 91 до 180 дней | M4: От 181 до 365 дней | O4: От 366 до 730 дней | Q4: Свыше 2 лет
C5: Сумма | D5: в том числе, в иностранной валюте (в экв. в сумах) | E5: Сумма | F5: в том числе, в иностранной валюте (в экв. в сумах) | G5: Сумма | H5: в том числе, в иностранной валюте (в экв. в сумах) | I5: Сумма | J5: в том числе, в иностранной валюте (в экв. в сумах) | K5: Сумма | L5: в том числе, в иностранной валюте (в экв. в сумах) | M5: Сумма | N5: в том числе, в иностранной валюте (в экв. в сумах) | O5: Сумма | P5: в том числе, в иностранной валюте (в экв. в сумах) | Q5: Сумма | R5: в том числе, в иностранной валюте (в экв. в сумах) | T5: в национальной валюте | U5: в иностранной валюте (в экв. в сумах) | V5: Коэффициент | W5: Сумма активов | X5: Высоко-ликвидные активы/приток | Y5: Сумма активов (в иностранной валюте) | Z5: Высоко-ликвидные активы/приток (в иностранной валюте)
B6: АКТИВЫ
A7: 1. | B7: Кассовая наличность и другие платежные документы | C7: 275813889 | D7: 181290789 | S7: =+C7+E7+G7+I7+K7+M7+O7+Q7 -> 275813889 | T7: =+S7-U7 -> 94523100 | U7: =+D7+F7+H7+J7+L7+N7+P7+R7 -> 181290789 | V7: 1 | W7: =+S7-S8 -> 275813889 | X7: =+W7*V7 -> 275813889 | Y7: =+U7-U8 -> 181290789 | Z7: =+Y7*V7 -> 181290789
A8: 1.1 | B8: в том числе чеки и другие платежные документы | S8: =+C8+E8+G8+I8+K8+M8+O8+Q8 -> 0 | T8: =+S8-U8 -> 0 | U8: =+E8+G8+I8+K8+M8+O8+Q8+S8 -> 0
A9: 2. | B9: К получению из ЦБРУ не учитывая сумму обязательных резервов банка(ФОР) | C9: 1146165457 | D9: 250586073 | S9: =+C9+E9+G9+I9+K9+M9+O9+Q9 -> 1146165457 | T9: =+S9-U9 -> 895579384 | U9: =+D9+F9+H9+J9+L9+N9+P9+R9 -> 250586073 | V9: 1 | W9: =S9 -> 1146165457 | X9: =+W9*V9 -> 1146165457 | Y9: =+U9 -> 250586073 | Z9: =+Y9*V9 -> 250586073
A10: 2.1 | B10: К получению из ЦБРУ (сумма обязательных резервов банка(ФОР)) | C10: 92646056 | D10: 0 | S10: =+C10+E10+G10+I10+K10+M10+O10+Q10 -> 92646056 | T10: =+S10-U10 -> 92646056 | U10: =+D10+F10+H10+J10+L10+N10+P10+R10 -> 0 | V10: 0
A11: 3. | B11: К получению из других банков | C11: =SUM(C12:C18)-C15 -> 563440061 | D11: =SUM(D12:D18)-D15 -> 562106612 | E11: =SUM(E12:E18)-E15 -> 0 | F11: =SUM(F12:F18)-F15 -> 0 | G11: =SUM(G12:G18)-G15 -> 7911492 | H11: =SUM(H12:H18)-H15 -> 7911492 | I11: =SUM(I12:I18)-I15 -> 0 | J11: =SUM(J12:J18)-J15 -> 0 | ... R11: =SUM(R12:R18)-R15 -> 162564900 | S11: =+C11+E11+G11+I11+K11+M11+O11+Q11 -> 901416758 | T11: =+S11-U11 -> 168833754 | U11: =+D11+F11+H11+J11+L11+N11+P11+R11 -> 732583004
A12: 3.1 | B12: Кор счета в банках с низким уровнем риска (ностро) | C12: 157948011 | D12: 157948011 | S12: =+C12+E12+G12+I12+K12+M12+O12+Q12 -> 157948011 | T12: =+S12-U12 -> 0 | U12: =+D12+F12+H12+J12+L12+N12+P12+R12 -> 157948011 | V12: 1 | W12: =+C12 -> 157948011 | X12: =+W12*V12 -> 157948011 | Y12: =+D12 -> 157948011 | Z12: =+Y12*V12 -> 157948011
A13: 3.2 | B13: Кор счета в местных банках (ностро) имеющих кредитный рейтинг | C13: 333810841 | D13: 333810841 | S13: =+C13 -> 333810841 | T13: =+S13-U13 -> 0 | U13: =+D13 -> 333810841 | V13: 1 | W13: =+C13 -> 333810841 | X13: =+W13*V13 -> 333810841 | Y13: =+D13 -> 333810841 | Z13: =+Y13*V13 -> 333810841
A14: 3.3 | B14: Депозиты размещенные на условиях овернайт | S14: =+E14 -> 0 | T14: =+S14-U14 -> 0 | U14: =+F14 -> 0 | V14: 1 | W14: =+E14-E15 -> 0 | X14: =+W14*V14 -> 0 | Y14: =+F14-F15 -> 0 | Z14: =+Y14*V14 -> 0
A15: 3.3.1. | B15: в том числе депозиты размещенные на условиях овернайт в иностранной валюте с рейтингом не ниже инвестиционного. | S15: =+E15 -> 0 | T15: =+S15-U15 -> 0 | U15: =+F15 -> 0 | V15: 1 | W15: =+E15 -> 0 | X15: =+W15*V15 -> 0 | Y15: =+F15 -> 0 | Z15: =+Y15*V15 -> 0
A16: 3.4 | B16: К получению из других банков - депозиты | C16: 5113307 | D16: 4226687 | E16: 0 | F16: 0 | G16: 7911492 | H16: 7911492 | I16: 0 | J16: 0 | K16: 0 | L16: 0 | M16: 0 | N16: 0 | O16: 0 | P16: 0 | Q16: 330065205 | R16: 162564900 | S16: =+C16+E16+G16+I16+K16+M16+O16+Q16 -> 343090004 | T16: =+S16-U16 -> 168386925 | U16: =+D16+F16+H16+J16+L16+N16+P16+R16 -> 174703079 | V16: 1 | W16: =+C16+E16+G16+E12+G12+E13+G13+E14-E15 -> 13024799 | X16: =+W16*V16 -> 13024799 | Y16: =+D16+F16+H16+F12+H12+F13+H13+F14-F15 -> 12138179 | Z16: =+Y16*V16 -> 12138179
A17: 3.5 | B17: К получению из других банков по расчетам пластиковых карт | C17: 841498 | D17: 615889 | E17: 0 | F17: 0 | G17: 0 | H17: 0 | I17: 0 | J17: 0 | K17: 0 | L17: 0 | M17: 0 | N17: 0 | O17: 0 | P17: 0 | Q17: 0 | R17: 0 | S17: =+C17+E17+G17+I17+K17+M17+O17+Q17 -> 841498 | T17: =+S17-U17 -> 225609 | U17: =+D17+F17+H17+J17+L17+N17+P17+R17 -> 615889 | V17: 1 | W17: =+C17+E17+G17 -> 841498 | X17: =+W17*V17 -> 841498 | Y17: =+D17+F17+H17 -> 615889 | Z17: =+Y17*V17 -> 615889
A18: 3.6 | B18: Другие статьи | C18: 65726404 | D18: 65505184 | E18: 0 | F18: 0 | G18: 0 | H18: 0 | I18: 0 | J18: 0 | K18: 0 | L18: 0 | M18: 0 | N18: 0 | O18: 0 | P18: 0 | Q18: 0 | R18: 0 | S18: =+C18+E18+G18+I18+K18+M18+O18+Q18 -> 65726404 | T18: =+S18-U18 -> 221220 | U18: =+D18+F18+H18+J18+L18+N18+P18+R18 -> 65505184 | V18: 1 | W18: =+C18+E18+G18 -> 65726404 | X18: =+W18*V18 -> 65726404 | Y18: =+D18+F18+H18 -> 65505184 | Z18: =+Y18*V18 -> 65505184
A19: 4. | B19: Счета купли и продажи, чистые | C19: =SUM(C20:C25)-C21 -> 251 | D19: =SUM(D20:D25)-D21 -> 0 | E19: =SUM(E20:E25)-E21 -> 0 | F19: =SUM(F20:F25)-F21 -> 0 | G19: =SUM(G20:G25)-G21 -> 54408699 | H19: =SUM(H20:H25)-H21 -> 0 | I19: =SUM(I20:I25)-I21 -> 355563735 | J19: =SUM(J20:J25)-J21 -> 0 | ... R19: =SUM(R20:R25)-R21 -> 0 | S19: =+C19+E19+G19+I19+K19+M19+O19+Q19 -> 409972685 | T19: =+S19-U19 -> 409972685 | U19: =+D19+F19+H19+J19+L19+N19+P19+R19 -> 0
A20: 4.1 | B20: Ценные бумаги, выпущенные Правительством Республики Узбекистан и ЦБРУ (векселя, облигации и другие долговые ценные бумаги) | G20: 54408699 | H20: 0 | I20: 355563735 | S20: =+C20+E20+G20+I20+K20+M20+O20+Q20 -> 409972434 | T20: =+S20-U20 -> 409972434 | U20: =+D20+F20+H20+J20+L20+N20+P20+R20 -> 0 | V20: 1 | W20: =+S20-S21 -> 0 | X20: =+W20*V20 -> 0 | Y20: =+U20-U21 -> 0 | Z20: =+Y20*V20 -> 0
A21: 4.1.1 | B21: в том числе, Ценные бумаги, выпущенные Правительством Республики Узбекистан и ЦБРУ (векселя, облигации и другие долговые ценные бумаги) под залогом | G21: 54408699 | H21: 0 | I21: 355563735 | S21: =+C21+E21+G21+I21+K21+M21+O21+Q21 -> 409972434 | T21: =+S21-U21 -> 409972434 | U21: =+D21+F21+H21+J21+L21+N21+P21+R21 -> 0 | V21: 1 | W21: =+C21+E21+G21 -> 54408699 | X21: =+W21*V21 -> 54408699 | Y21: =+D21+F21+H21 -> 0 | Z21: =+Y21*V21 -> 0
A22: 4.2 | B22: Правительственные ценные бумаги стран с низкой степенью странового риска | S22: =+C22+E22+G22+I22+K22+M22+O22+Q22 -> 0 | T22: =+S22-U22 -> 0 | U22: =+D22+F22+H22+J22+L22+N22+P22+R22 -> 0 | V22: 1 | W22: =+S22 -> 0 | X22: =+W22*V22 -> 0 | Y22: =+U22 -> 0 | Z22: =+Y22*V22 -> 0
A23: 4.3 | B23: Ценные бумаги выпущенные МВФ, входящие организации в группу Всемирного банка, МФК, АБР, Азиатский банк инфроструктуры и инвестиции, ЕБРР, Европейский инвестиционный банк, Исламский банк развития и Банк развития Европейского союза | S23: =+C23+E23+G23+I23+K23+M23+O23+Q23 -> 0 | T23: =+S23-U23 -> 0 | U23: =+D23+F23+H23+J23+L23+N23+P23+R23 -> 0 | V23: 1 | W23: =+S23 -> 0 | X23: =+W23*V23 -> 0 | Y23: =+U23 -> 0 | Z23: =+Y23*V23 -> 0
A24: 4.4 | B24: Ценные бумаги ведущих транснациональных компаний с рейтингом не ниже инвестиционного | S24: =+C24+E24+G24+I24+K24+M24+O24+Q24 -> 0 | T24: =+S24-U24 -> 0 | U24: =+D24+F24+H24+J24+L24+N24+P24+R24 -> 0 | V24: 1 | W24: =+S24 -> 0 | X24: =+W24*V24 -> 0 | Y24: =+U24 -> 0 | Z24: =+Y24*V24 -> 0
A25: 4.5 | B25: Другие | C25: 251 | S25: =+C25+E25+G25+I25+K25+M25+O25+Q25 -> 251 | T25: =+S25-U25 -> 251 | U25: =+D25+F25+H25+J25+L25+N25+P25+R25 -> 0 | V25: 0
A26: 5. | B26: Купленные векселя, чистые | S26: =+C26+E26+G26+I26+K26+M26+O26+Q26 -> 0 | T26: =+S26-U26 -> 0 | U26: =+D26+F26+H26+J26+L26+N26+P26+R26 -> 0 | V26: 0.3 | W26: =+E26+G26 -> 0 | X26: =+W26*V26 -> 0 | Y26: =+F26+H26 -> 0 | Z26: =+Y26*V26 -> 0
A27: 6. | B27: Обязательства клиентов по траттам под аккредитивы или трастовые документы | C27: 433662549 | D27: 433662549 | E27: 507382 | F27: 507382 | G27: 7006768 | H27: 7006768 | I27: 0 | J27: 0 | K27: 0 | L27: 0 | M27: 91710528 | N27: 91710528 | S27: =+C27+E27+G27+I27+K27+M27+O27+Q27 -> 532887227 | T27: =+S27-U27 -> 0 | U27: =+D27+F27+H27+J27+L27+N27+P27+R27 -> 532887227 | V27: 0.5 | W27: =+E27+G27 -> 7514150 | X27: =+W27*V27 -> 3757075 | Y27: =+F27+H27 -> 7514150 | Z27: =+Y27*V27 -> 3757075
A28: 7. | B28: Обязательства клиентов по непогашенным акцептам этого банка | S28: =+C28+E28+G28+I28+K28+M28+O28+Q28 -> 0 | T28: =+S28-U28 -> 0 | U28: =+D28+F28+H28+J28+L28+N28+P28+R28 -> 0 | V28: 0.3 | W28: =+E28+G28 -> 0 | X28: =+W28*V28 -> 0 | Y28: =+F28+H28 -> 0 | Z28: =+Y28*V28 -> 0
A29: 8. | B29: Кредиты и лизинги, предоставленные ЦБРУ, чистые | S29: =+C29+E29+G29+I29+K29+M29+O29+Q29 -> 0 | T29: =+S29-U29 -> 0 | U29: =+D29+F29+H29+J29+L29+N29+P29+R29 -> 0 | V29: 1 | W29: =+C29+E29+G29 -> 0 | X29: =+W29*V29 -> 0 | Y29: =+D29+F29+H29 -> 0 | Z29: =+Y29*V29 -> 0
A30: 9. | B30: Кредиты и лизинги, предоставленные другим банкам, чистые | S30: =+C30+E30+G30+I30+K30+M30+O30+Q30 -> 0 | T30: =+S30-U30 -> 0 | U30: =+D30+F30+H30+J30+L30+N30+P30+R30 -> 0 | V30: 0.5 | W30: =+E30+G30 -> 0 | X30: =+W30*V30 -> 0 | Y30: =+F30+H30 -> 0 | Z30: =+Y30*V30 -> 0
A31: 10 | B31: Кредиты и лизинги, предоставленные другим клиентам, чистые | C31: 61330105 | D31: 22153949 | E31: 21055147 | F31: 945735 | G31: 181030004 | H31: 59472328 | I31: 502330940 | J31: 192589154 | K31: 946936826 | L31: 320704588 | M31: 1630672226 | N31: 461291200 | O31: 1570064350 | P31: 607119146 | Q31: 2739900967 | R31: 1267450017 | S31: =+C31+E31+G31+I31+K31+M31+O31+Q31 -> 7653320565 | T31: =+S31-U31 -> 4721594448 | U31: =+D31+F31+H31+J31+L31+N31+P31+R31 -> 2931726117 | V31: 0.5 | W31: =+E31+G31 -> 202085151 | X31: =+W31*V31 -> 1.0104258e+08 | Y31: =+F31+H31 -> 60418063 | Z31: =+Y31*V31 -> 30209032
A32: 10.1 | B32: в том числе, кредиты и лизинги, предоставленные физическим лицам, чистые | C32: 7935128 | D32: 0 | E32: 14955082 | F32: 0 | G32: 23601942 | H32: 0 | I32: 78983936 | J32: 0 | K32: 120931809 | L32: 0 | M32: 247250051 | N32: 0 | O32: 293022871 | P32: 0 | Q32: 496168250 | R32: 0 | S32: =+C32+E32+G32+I32+K32+M32+O32+Q32 -> 1282849069 | T32: =+S32-U32 -> 1282849069 | U32: =+D32+F32+H32+J32+L32+N32+P32+R32 -> 0 | V32: 0 | W32: =+E32+G32 -> 38557024 | X32: =+W32*V32 -> 0 | Y32: =+F32+H32 -> 0 | Z32: =+Y32*V32 -> 0
A33: 11 | B33: Кредиты и лизинги и авансы в процессе судебного разбирательства, чистые | C33: -1039 | S33: =+C33+E33+G33+I33+K33+M33+O33+Q33 -> -1039 | T33: =+S33-U33 -> -1039 | U33: =+D33+F33+H33+J33+L33+N33+P33+R33 -> 0 | V33: 0
A34: 12. | B34: Инвестиции, чистые | Q34: 98339066 | S34: =+C34+E34+G34+I34+K34+M34+O34+Q34 -> 98339066 | T34: =+S34-U34 -> 98339066 | U34: =+D34+F34+H34+J34+L34+N34+P34+R34 -> 0 | V34: 0
A35: 13. | B35: Ценные бумаги купленные по соглашению с обратным выкупом | C35: =+C36+C37 -> 0 | D35: =+D36+D37 -> 0 | E35: =+E36+E37 -> 0 | F35: =+F36+F37 -> 0 | G35: =+G36+G37 -> 0 | H35: =+H36+H37 -> 0 | I35: =+I36+I37 -> 0 | J35: =+J36+J37 -> 0 | ... R35: =+R36+R37 -> 0 | S35: =+C35+E35+G35+I35+K35+M35+O35+Q35 -> 0 | T35: =+S35-U35 -> 0 | U35: =+D35+F35+H35+J35+L35+N35+P35+R35 -> 0
A36: 13.1 | B36: Ценные бумаги Правительства и ЦБ купленные по соглашению с обратным выкупом (РЕПО) | S36: =+C36+E36+G36+I36+K36+M36+O36+Q36 -> 0 | T36: =+S36-U36 -> 0 | U36: =+D36+F36+H36+J36+L36+N36+P36+R36 -> 0 | V36: 1 | W36: =+S36 -> 0 | X36: =+W36*V36 -> 0 | Y36: =+U36 -> 0 | Z36: =+Y36*V36 -> 0
A37: 13.2 | B37: Другие ценные бумаги купленные по соглашению с обратным выкупом (РЕПО) | S37: =+C37+E37+G37+I37+K37+M37+O37+Q37 -> 0 | T37: =+S37-U37 -> 0 | U37: =+D37+F37+H37+J37+L37+N37+P37+R37 -> 0 | V37: 0
A38: 14. | B38: Основные средства, чистые | Q38: 812267548 | R38: 0 | S38: =+C38+E38+G38+I38+K38+M38+O38+Q38 -> 812267548 | T38: =+S38-U38 -> 812267548 | U38: =+D38+F38+H38+J38+L38+N38+P38+R38 -> 0 | V38: 0
A39: 15. | B39: Другое собственное имущество банка, чистые | C39: 51751710 | R39: 0 | S39: =+C39+E39+G39+I39+K39+M39+O39+Q39 -> 51751710 | T39: =+S39-U39 -> 51751710 | U39: =+D39+F39+H39+J39+L39+N39+P39+R39 -> 0 | V39: 0
A40: 16. | B40: Нереализованная прибыль при ревальвации по сделкам "форвард" | C40: 5936467 | S40: =+C40+E40+G40+I40+K40+M40+O40+Q40 -> 5936467 | T40: =+S40-U40 -> 5936467 | U40: =+D40+F40+H40+J40+L40+N40+P40+R40 -> 0 | V40: 0
A41: 17. | B41: Счета купли-продажи валюты и валютные позиции | S41: =+C41+E41+G41+I41+K41+M41+O41+Q41 -> 0 | T41: =+S41-U41 -> 0 | U41: =+D41+F41+H41+J41+L41+N41+P41+R41 -> 0 | V41: 0
A42: 18. | B42: Клиринговые счета | C42: 3659 | D42: 0 | S42: =+C42+E42+G42+I42+K42+M42+O42+Q42 -> 3659 | T42: =+S42-U42 -> 3659 | U42: =+D42+F42+H42+J42+L42+N42+P42+R42 -> 0 | V42: 0
A43: 19. | B43: Начисленные проценты | C43: 163425953 | D43: 50329192 | S43: =+C43+E43+G43+I43+K43+M43+O43+Q43 -> 163425953 | T43: =+S43-U43 -> 113096761 | U43: =+D43+F43+H43+J43+L43+N43+P43+R43 -> 50329192 | V43: 0.5 | W43: =+E43+G43 -> 0 | X43: =+W43*V43 -> 0 | Y43: =+F43+H43 -> 0 | Z43: =+Y43*V43 -> 0
A44: 20. | B44: Другие активы | C44: 464043728 | D44: 116486001 | E44: 64621 | F44: 56475 | G44: 69139 | H44: 0 | I44: 383461 | J44: 2051 | K44: 1775006 | L44: 109375 | M44: 1253010 | N44: 280797 | O44: 2719920 | P44: 99142 | Q44: 24201737 | R44: 17734453 | S44: =+C44+E44+G44+I44+K44+M44+O44+Q44 -> 494510622 | T44: =+S44-U44 -> 359742328 | U44: =+D44+F44+H44+J44+L44+N44+P44+R44 -> 134768294 | V44: 0
A45: 21. | B45: Высоколиквидные активы, находящиеся под залогом кроме строки 4.1.1. | S45: =+C45+E45+G45+I45+K45+M45+O45+Q45 -> 0 | T45: =+S45-U45 -> 0 | U45: =+D45+F45+H45+J45+L45+N45+P45+R45 -> 0 | V45: 1 | W45: =+S45 -> 0 | X45: =+W45*V45 -> 0 | Y45: =+U45 -> 0 | Z45: =+Y45*V45 -> 0
A46: 22. | B46: ИТОГО АКТИВОВ | C46: =SUM(C7:C44)-C8-C11-C15-C19-C21-C32-C35 -> 3258218846 | D46: =SUM(D7:D44)-D8-D11-D15-D19-D21-D32-D35 -> 1616615165 | E46: =SUM(E7:E44)-E8-E11-E15-E19-E21-E32-E35 -> 21627150 | F46: =SUM(F7:F44)-F8-F11-F15-F19-F21-F32-F35 -> 1509592 | G46: =SUM(G7:G44)-G8-G11-G15-G19-G21-G32-G35 -> 250426102 | H46: =SUM(H7:H44)-H8-H11-H15-H19-H21-H32-H35 -> 74390588 | I46: =SUM(I7:I44)-I8-I11-I15-I19-I21-I32-I35 -> 858278136 | J46: =SUM(J7:J44)-J8-J11-J15-J19-J21-J32-J35 -> 192591205 | ... R46: =SUM(R7:R44)-R8-R11-R15-R19-R21-R32-R35 -> 1447749370 | S46: =+C46+E46+G46+I46+K46+M46+O46+Q46 -> 12638456623 | T46: =+S46-U46 -> 7824285927 | U46: =+D46+F46+H46+J46+L46+N46+P46+R46 -> 4814170696 | X46: =SUM(X7:X44)-X11-X35 -> 2.1525392e+09 | Z46: =SUM(Z7:Z44)-Z11-Z35 -> 1.0358611e+09
B47: забалансовые обязательства
A48: 1 | B48: Обязательства по выдаче кредитов (91809) | C48: 3308330 | D48: 287 | E48: 248693 | F48: 0 | G48: 2804722 | H48: 0 | I48: 13074842 | J48: 0 | K48: 18025872 | L48: 1721075 | M48: 111014342 | N48: 70210836 | O48: 104011982 | P48: 9562703 | Q48: 472173186 | R48: 93689550 | S48: =+C48+E48+G48+I48+K48+M48+O48+Q48 -> 724661969 | T48: =+S48-U48 -> 549477518 | U48: =+D48+F48+H48+J48+L48+N48+P48+R48 -> 175184451
B49: из них, обеспеченные денежными средствами (МФИ, МинФин, Фонды и депозиты других организации | C49: 0 | D49: 0 | E49: 0 | F49: 0 | G49: 0 | H49: 0 | I49: 0 | J49: 0 | K49: 24693 | L49: 24095 | M49: 112944 | N49: 43351 | O49: 4285400 | P49: 3964854 | Q49: 7575225 | R49: 4884804 | S49: =+C49+E49+G49+I49+K49+M49+O49+Q49 -> 11998262 | T49: =+S49-U49 -> 3081158 | U49: =+D49+F49+H49+J49+L49+N49+P49+R49 -> 8917104
A50: 2 | B50: Гарантии и поручительства (90993) | C50: 1999162 | D50: 0 | E50: 6914167 | F50: 6780756 | G50: 0 | H50: 0 | I50: 1643429 | J50: 744429 | K50: 25622129 | L50: 25622129 | M50: 0 | N50: 0 | O50: 7369609 | P50: 7369609 | Q50: 200141724 | R50: 200141724 | S50: =+C50+E50+G50+I50+K50+M50+O50+Q50 -> 243690220 | T50: =+S50-U50 -> 3031573 | U50: =+D50+F50+H50+J50+L50+N50+P50+R50 -> 240658647
B51: из них, гарантии и поручительства, обеспеченные денежными средствами (депозитами на отдельных блокированных счетах) | S51: =+C51+E51+G51+I51+K51+M51+O51+Q51 -> 0 | T51: =+S51-U51 -> 0 | U51: =+D51+F51+H51+J51+L51+N51+P51+R51 -> 0
A52: 3 | B52: Аккредитивы (90908-90958) | C52: 437576426 | D52: 437576426 | E52: 1095054 | F52: 1095054 | G52: 7527095 | H52: 7527095 | I52: 10325810 | J52: 10325810 | K52: 0 | L52: 0 | M52: 117224972 | N52: 117224972 | S52: =+C52+E52+G52+I52+K52+M52+O52+Q52 -> 573749357 | T52: =+S52-U52 -> 0 | U52: =+D52+F52+H52+J52+L52+N52+P52+R52 -> 573749357
B53: из них, аккредитивы, покрытые депозитами на балансовых счетах 22602 | C53: 770375 | D53: 770375 | E53: 0 | F53: 0 | G53: 0 | H53: 0 | I53: 2713923 | J53: 2713923 | K53: 0 | L53: 0 | M53: 20119708 | N53: 20119708 | S53: =+C53+E53+G53+I53+K53+M53+O53+Q53 -> 23604006 | T53: =+S53-U53 -> 0 | U53: =+D53+F53+H53+J53+L53+N53+P53+R53 -> 23604006
B56: Подпись Председателя правления:
B58: Подпись Главного Бухгалтера:
W59: По новым расчетам
W60: =+Balance!C45 -> 12638456623 | X60: =+Balance!D45 -> 7824285927 | Y60: =+Balance!E45 -> 4814170696
W61: Всего | Y61: Ин вал
W62: Приток | X62: =+X46-X63 -> 2.3880105e+08 | Y62: Приток | Z62: =+Z46-Z63 -> 1.1222536e+08
W63: Высоко-ликвидные активы | X63: =+X7+X9+X12+X13+X15+X20+X22+X23+X24+X36-X45 -> 1913738198 | Y63: Высоко-ликвидные активы | Z63: =+Z7+Z9+Z12+Z13+Z15+Z20+Z22+Z23+Z24+Z36-Z45 -> 923635714
W64: Чистый отток за 30 дней | X64: =+X66-X69 -> 1.7074696e+09 | Y64: Чистый отток за 30 дней | Z64: =+Z66-Z69 -> 8.5127301e+08
W66: Всего отток | X66: =+'Bank Liabilities Analysis'!W39+'Liquidity Analysis'!C40 -> 1.9462707e+09 | Y66: Отток | Z66: =+'Bank Liabilities Analysis'!X39+'Liquidity Analysis'!E40 -> 9.6349836e+08
W67: в том числе отток по внебалансу | X67: =+'Liquidity Analysis'!C40 -> 224988397 | Y67: в том числе отток по внебалансу | Z67: =+'Liquidity Analysis'!E40 -> 142574207
W69: Приток по положению | X69: =IF(X62>(X66*0.75),X66*0.75,X62) -> 2.3880105e+08 | Y69: Приток по положению | Z69: =IF(Z62>(Z66*0.75),Z66*0.75,Z62) -> 1.1222536e+08

Sheet Bank Assets Analysis (нац)
A2: АНАЛИЗ АКТИВОВ БАНКА В НАЦИОНАЛЬНОЙ ВАЛЮТЕ | L2: Таблица-17А
B3: =Balance!B3 -> АК "АЛОКАБАНК" | J3: =+Balance!B2 -> 31 Декабрь, 2021 | N3: =+Balance!E3 -> тыс. сум
A4: № | B4: Характеристики | C4: Срок погашения (в днях) | K4: ВСЕГО | L4: Расчет коэффициента покрытия ликвидности
C5: Бессрочные | D5: От 1 до 7 дней | E5: От 8 до 30 дней | F5: От 31 до 90 дней | G5: От 91 до 180 дней | H5: От 181 до 365 дней | I5: От 366 до 730 дней | J5: Свыше 2 лет | L5: Коэффициент | M5: Сумма активов | N5: Высоко-ликвидные активы/приток
B6: АКТИВЫ
A7: 1. | B7: Наличность и другие кассовые документы | C7: =+'Bank Assets Analysis'!C7-'Bank Assets Analysis'!D7 -> 94523100 | D7: =+'Bank Assets Analysis'!E7-'Bank Assets Analysis'!F7 -> 0 | E7: =+'Bank Assets Analysis'!G7-'Bank Assets Analysis'!H7 -> 0 | F7: =+'Bank Assets Analysis'!I7-'Bank Assets Analysis'!J7 -> 0 | G7: =+'Bank Assets Analysis'!K7-'Bank Assets Analysis'!L7 -> 0 | H7: =+'Bank Assets Analysis'!M7-'Bank Assets Analysis'!N7 -> 0 | I7: =+'Bank Assets Analysis'!O7-'Bank Assets Analysis'!P7 -> 0 | J7: =+'Bank Assets Analysis'!Q7-'Bank Assets Analysis'!R7 -> 0 | K7: =+C7+D7+E7+F7+G7+H7+I7+J7 -> 94523100 | L7: 1 | M7: =+K7-K8 -> 94523100 | N7: =+M7*L7 -> 94523100
A8: 1.1 | B8: в том числе чеки и другие платежные документы | C8: =+'Bank Assets Analysis'!C8-'Bank Assets Analysis'!D8 -> 0 | D8: =+'Bank Assets Analysis'!E8-'Bank Assets Analysis'!F8 -> 0 | E8: =+'Bank Assets Analysis'!G8-'Bank Assets Analysis'!H8 -> 0 | F8: =+'Bank Assets Analysis'!I8-'Bank Assets Analysis'!J8 -> 0 | G8: =+'Bank Assets Analysis'!K8-'Bank Assets Analysis'!L8 -> 0 | H8: =+'Bank Assets Analysis'!M8-'Bank Assets Analysis'!N8 -> 0 | I8: =+'Bank Assets Analysis'!O8-'Bank Assets Analysis'!P8 -> 0 | J8: =+'Bank Assets Analysis'!Q8-'Bank Assets Analysis'!R8 -> 0 | K8: =+C8+D8+E8+F8+G8+H8+I8+J8 -> 0 | L8: 0
A9: 2. | B9: К получению из ЦБРУ не учитывая сумму обязательных резервов банка(ФОР) | C9: =+'Bank Assets Analysis'!C9-'Bank Assets Analysis'!D9 -> 895579384 | D9: =+'Bank Assets Analysis'!E9-'Bank Assets Analysis'!F9 -> 0 | E9: =+'Bank Assets Analysis'!G9-'Bank Assets Analysis'!H9 -> 0 | F9: =+'Bank Assets Analysis'!I9-'Bank Assets Analysis'!J9 -> 0 | G9: =+'Bank Assets Analysis'!K9-'Bank Assets Analysis'!L9 -> 0 | H9: =+'Bank Assets Analysis'!M9-'Bank Assets Analysis'!N9 -> 0 | I9: =+'Bank Assets Analysis'!O9-'Bank Assets Analysis'!P9 -> 0 | J9: =+'Bank Assets Analysis'!Q9-'Bank Assets Analysis'!R9 -> 0 | K9: =+C9+D9+E9+F9+G9+H9+I9+J9 -> 895579384 | L9: 1 | M9: =+K9 -> 895579384 | N9: =+M9*L9 -> 895579384
A10: 2.1 | B10: К получению из ЦБРУ (сумма обязательных резервов банка(ФОР)) | C10: =+'Bank Assets Analysis'!C10-'Bank Assets Analysis'!D10 -> 92646056 | D10: =+'Bank Assets Analysis'!E10-'Bank Assets Analysis'!F10 -> 0 | E10: =+'Bank Assets Analysis'!G10-'Bank Assets Analysis'!H10 -> 0 | F10: =+'Bank Assets Analysis'!I10-'Bank Assets Analysis'!J10 -> 0 | G10: =+'Bank Assets Analysis'!K10-'Bank Assets Analysis'!L10 -> 0 | H10: =+'Bank Assets Analysis'!M10-'Bank Assets Analysis'!N10 -> 0 | I10: =+'Bank Assets Analysis'!O10-'Bank Assets Analysis'!P10 -> 0 | J10: =+'Bank Assets Analysis'!Q10-'Bank Assets Analysis'!R10 -> 0 | K10: =+C10+D10+E10+F10+G10+H10+I10+J10 -> 92646056 | L10: 0 | N10: =+M10*L10 -> 0
A11: 3. | B11: К получению из других банков | C11: =SUM(C12:C18)-C15 -> 1333449 | D11: =SUM(D12:D18)-D15 -> 0 | E11: =SUM(E12:E18)-E15 -> 0 | F11: =SUM(F12:F18)-F15 -> 0 | G11: =SUM(G12:G18)-G15 -> 0 | H11: =SUM(H12:H18)-H15 -> 0 | I11: =SUM(I12:I18)-I15 -> 0 | J11: =SUM(J12:J18)-J15 -> 167500305 | K11: =+C11+D11+E11+F11+G11+H11+I11+J11 -> 168833754 | N11: =+M11*L11 -> 0
A12: 3.1 | B12: К получению со счетов в банках стран с низким уровнем риска (ностро, депозиты), но размещенные не в качестве обеспечения | C12: =+'Bank Assets Analysis'!C12-'Bank Assets Analysis'!D12 -> 0 | D12: =+'Bank Assets Analysis'!E12-'Bank Assets Analysis'!F12 -> 0 | E12: =+'Bank Assets Analysis'!G12-'Bank Assets Analysis'!H12 -> 0 | F12: =+'Bank Assets Analysis'!I12-'Bank Assets Analysis'!J12 -> 0 | G12: =+'Bank Assets Analysis'!K12-'Bank Assets Analysis'!L12 -> 0 | H12: =+'Bank Assets Analysis'!M12-'Bank Assets Analysis'!N12 -> 0 | I12: =+'Bank Assets Analysis'!O12-'Bank Assets Analysis'!P12 -> 0 | J12: =+'Bank Assets Analysis'!Q12-'Bank Assets Analysis'!R12 -> 0 | K12: =+C12+D12+E12+F12+G12+H12+I12+J12 -> 0 | L12: 1 | M12: =+C12 -> 0 | N12: =+M12*L12 -> 0
A13: 3.2 | B13: Депозиты размещенные в местных банках имеющие рейтинг не ниже В- или В3 | C13: =+'Bank Assets Analysis'!C13-'Bank Assets Analysis'!D13 -> 0 | D13: =+'Bank Assets Analysis'!E13-'Bank Assets Analysis'!F13 -> 0 | E13: =+'Bank Assets Analysis'!G13-'Bank Assets Analysis'!H13 -> 0 | F13: =+'Bank Assets Analysis'!I13-'Bank Assets Analysis'!J13 -> 0 | G13: =+'Bank Assets Analysis'!K13-'Bank Assets Analysis'!L13 -> 0 | H13: =+'Bank Assets Analysis'!M13-'Bank Assets Analysis'!N13 -> 0 | I13: =+'Bank Assets Analysis'!O13-'Bank Assets Analysis'!P13 -> 0 | J13: =+'Bank Assets Analysis'!Q13-'Bank Assets Analysis'!R13 -> 0 | K13: =+C13+D13+E13+F13+G13+H13+I13+J13 -> 0 | L13: 1 | M13: =+C13 -> 0 | N13: =+M13*L13 -> 0
A14: 3.3 | B14: Депозиты размещенные на условиях овернайт | C14: =+'Bank Assets Analysis'!C14-'Bank Assets Analysis'!D14 -> 0 | D14: =+'Bank Assets Analysis'!E14-'Bank Assets Analysis'!F14 -> 0 | E14: =+'Bank Assets Analysis'!G14-'Bank Assets Analysis'!H14 -> 0 | F14: =+'Bank Assets Analysis'!I14-'Bank Assets Analysis'!J14 -> 0 | G14: =+'Bank Assets Analysis'!K14-'Bank Assets Analysis'!L14 -> 0 | H14: =+'Bank Assets Analysis'!M14-'Bank Assets Analysis'!N14 -> 0 | I14: =+'Bank Assets Analysis'!O14-'Bank Assets Analysis'!P14 -> 0 | J14: =+'Bank Assets Analysis'!Q14-'Bank Assets Analysis'!R14 -> 0 | K14: =+C14+D14+E14+F14+G14+H14+I14+J14 -> 0 | L14: 1 | M14: =+D14-D15 -> 0 | N14: =+M14*L14 -> 0
A15: 3.3.1. | B15: в том числе Депозиты размещенные на условиях овернайт в иностранной валюте с рейтингом не ниже инвестиционного. | C15: =+'Bank Assets Analysis'!C15-'Bank Assets Analysis'!D15 -> 0 | D15: =+'Bank Assets Analysis'!E15-'Bank Assets Analysis'!F15 -> 0 | E15: =+'Bank Assets Analysis'!G15-'Bank Assets Analysis'!H15 -> 0 | F15: =+'Bank Assets Analysis'!I15-'Bank Assets Analysis'!J15 -> 0 | G15: =+'Bank Assets Analysis'!K15-'Bank Assets Analysis'!L15 -> 0 | H15: =+'Bank Assets Analysis'!M15-'Bank Assets Analysis'!N15 -> 0 | I15: =+'Bank Assets Analysis'!O15-'Bank Assets Analysis'!P15 -> 0 | J15: =+'Bank Assets Analysis'!Q15-'Bank Assets Analysis'!R15 -> 0 | K15: =+C15+D15+E15+F15+G15+H15+I15+J15 -> 0 | L15: 1 | M15: =+C15 -> 0 | N15: =+M15*L15 -> 0
A16: 3.4 | B16: К получению из других банков - депозиты | C16: =+'Bank Assets Analysis'!C16-'Bank Assets Analysis'!D16 -> 886620 | D16: =+'Bank Assets Analysis'!E16-'Bank Assets Analysis'!F16 -> 0 | E16: =+'Bank Assets Analysis'!G16-'Bank Assets Analysis'!H16 -> 0 | F16: =+'Bank Assets Analysis'!I16-'Bank Assets Analysis'!J16 -> 0 | G16: =+'Bank Assets Analysis'!K16-'Bank Assets Analysis'!L16 -> 0 | H16: =+'Bank Assets Analysis'!M16-'Bank Assets Analysis'!N16 -> 0 | I16: =+'Bank Assets Analysis'!O16-'Bank Assets Analysis'!P16 -> 0 | J16: =+'Bank Assets Analysis'!Q16-'Bank Assets Analysis'!R16 -> 167500305 | K16: =+C16+D16+E16+F16+G16+H16+I16+J16 -> 168386925 | L16: 1 | M16: =+C16+D16+E16+D12+D13+D14-D15 -> 886620 | N16: =+M16*L16 -> 886620
A17: 3.5 | B17: К получению из других банков по расчетам пластиковых карт | C17: =+'Bank Assets Analysis'!C17-'Bank Assets Analysis'!D17 -> 225609 | D17: =+'Bank Assets Analysis'!E17-'Bank Assets Analysis'!F17 -> 0 | E17: =+'Bank Assets Analysis'!G17-'Bank Assets Analysis'!H17 -> 0 | F17: =+'Bank Assets Analysis'!I17-'Bank Assets Analysis'!J17 -> 0 | G17: =+'Bank Assets Analysis'!K17-'Bank Assets Analysis'!L17 -> 0 | H17: =+'Bank Assets Analysis'!M17-'Bank Assets Analysis'!N17 -> 0 | I17: =+'Bank Assets Analysis'!O17-'Bank Assets Analysis'!P17 -> 0 | J17: =+'Bank Assets Analysis'!Q17-'Bank Assets Analysis'!R17 -> 0 | K17: =+C17+D17+E17+F17+G17+H17+I17+J17 -> 225609 | L17: 1 | M17: =+C17+D17+E17 -> 225609 | N17: =+M17*L17 -> 225609
A18: 3.6 | B18: Другие статьи | C18: =+'Bank Assets Analysis'!C18-'Bank Assets Analysis'!D18 -> 221220 | D18: =+'Bank Assets Analysis'!E18-'Bank Assets Analysis'!F18 -> 0 | E18: =+'Bank Assets Analysis'!G18-'Bank Assets Analysis'!H18 -> 0 | F18: =+'Bank Assets Analysis'!I18-'Bank Assets Analysis'!J18 -> 0 | G18: =+'Bank Assets Analysis'!K18-'Bank Assets Analysis'!L18 -> 0 | H18: =+'Bank Assets Analysis'!M18-'Bank Assets Analysis'!N18 -> 0 | I18: =+'Bank Assets Analysis'!O18-'Bank Assets Analysis'!P18 -> 0 | J18: =+'Bank Assets Analysis'!Q18-'Bank Assets Analysis'!R18 -> 0 | K18: =+C18+D18+E18+F18+G18+H18+I18+J18 -> 221220 | L18: 1 | M18: =+C18+D18+E18 -> 221220 | N18: =+M18*L18 -> 221220
A19: 4. | B19: Счета купли и продажи, чистые | C19: =SUM(C20:C25)-C21 -> 251 | D19: =SUM(D20:D25)-D21 -> 0 | E19: =SUM(E20:E25)-E21 -> 54408699 | F19: =SUM(F20:F25)-F21 -> 355563735 | G19: =SUM(G20:G25)-G21 -> 0 | H19: =SUM(H20:H25)-H21 -> 0 | I19: =SUM(I20:I25)-I21 -> 0 | J19: =SUM(J20:J25)-J21 -> 0 | K19: =+C19+D19+E19+F19+G19+H19+I19+J19 -> 409972685 | N19: =+M19*L19 -> 0
A20: 4.1 | B20: Ценные бумаги, выпущенные Правительством Республики Узбекистан и ЦБРУ (векселя, облигации и другие долговые ценные бумаги) | C20: =+'Bank Assets Analysis'!C20-'Bank Assets Analysis'!D20 -> 0 | D20: =+'Bank Assets Analysis'!E20-'Bank Assets Analysis'!F20 -> 0 | E20: =+'Bank Assets Analysis'!G20-'Bank Assets Analysis'!H20 -> 54408699 | F20: =+'Bank Assets Analysis'!I20-'Bank Assets Analysis'!J20 -> 355563735 | G20: =+'Bank Assets Analysis'!K20-'Bank Assets Analysis'!L20 -> 0 | H20: =+'Bank Assets Analysis'!M20-'Bank Assets Analysis'!N20 -> 0 | I20: =+'Bank Assets Analysis'!O20-'Bank Assets Analysis'!P20 -> 0 | J20: =+'Bank Assets Analysis'!Q20-'Bank Assets Analysis'!R20 -> 0 | K20: =+C20+D20+E20+F20+G20+H20+I20+J20 -> 409972434 | L20: 1 | M20: =+K20-K21 -> 0 | N20: =+M20*L20 -> 0
A21: 4.1.1 | B21: в том числе, Ценные бумаги, выпущенные Правительством Республики Узбекистан и ЦБРУ (векселя, облигации и другие долговые ценные бумаги) под залогом | C21: =+'Bank Assets Analysis'!C21-'Bank Assets Analysis'!D21 -> 0 | D21: =+'Bank Assets Analysis'!E21-'Bank Assets Analysis'!F21 -> 0 | E21: =+'Bank Assets Analysis'!G21-'Bank Assets Analysis'!H21 -> 54408699 | F21: =+'Bank Assets Analysis'!I21-'Bank Assets Analysis'!J21 -> 355563735 | G21: =+'Bank Assets Analysis'!K21-'Bank Assets Analysis'!L21 -> 0 | H21: =+'Bank Assets Analysis'!M21-'Bank Assets Analysis'!N21 -> 0 | I21: =+'Bank Assets Analysis'!O21-'Bank Assets Analysis'!P21 -> 0 | J21: =+'Bank Assets Analysis'!Q21-'Bank Assets Analysis'!R21 -> 0 | K21: =+C21+D21+E21+F21+G21+H21+I21+J21 -> 409972434 | L21: 1 | M21: =SUM(C21:E21) -> 54408699 | N21: =+M21*L21 -> 54408699
A22: 4.2 | B22: Правительственные ценные бумаги стран с низкой степенью странового риска | C22: =+'Bank Assets Analysis'!C22-'Bank Assets Analysis'!D22 -> 0 | D22: =+'Bank Assets Analysis'!E22-'Bank Assets Analysis'!F22 -> 0 | E22: =+'Bank Assets Analysis'!G22-'Bank Assets Analysis'!H22 -> 0 | F22: =+'Bank Assets Analysis'!I22-'Bank Assets Analysis'!J22 -> 0 | G22: =+'Bank Assets Analysis'!K22-'Bank Assets Analysis'!L22 -> 0 | H22: =+'Bank Assets Analysis'!M22-'Bank Assets Analysis'!N22 -> 0 | I22: =+'Bank Assets Analysis'!O22-'Bank Assets Analysis'!P22 -> 0 | J22: =+'Bank Assets Analysis'!Q22-'Bank Assets Analysis'!R22 -> 0 | K22: =+C22+D22+E22+F22+G22+H22+I22+J22 -> 0 | L22: 1 | M22: =+K22 -> 0 | N22: =+M22*L22 -> 0
A23: 4.3 | B23: Ценные бумаги выпущенные МВФ, входящие организации в группу Всемирного банка, МФК, АБР, Азиатский банк инфроструктуры и инвестиции, ЕБРР, Европейский инвестиционный банк, Исламский банк развития и Банк развития Европейского союза | C23: =+'Bank Assets Analysis'!C23-'Bank Assets Analysis'!D23 -> 0 | D23: =+'Bank Assets Analysis'!E23-'Bank Assets Analysis'!F23 -> 0 | E23: =+'Bank Assets Analysis'!G23-'Bank Assets Analysis'!H23 -> 0 | F23: =+'Bank Assets Analysis'!I23-'Bank Assets Analysis'!J23 -> 0 | G23: =+'Bank Assets Analysis'!K23-'Bank Assets Analysis'!L23 -> 0 | H23: =+'Bank Assets Analysis'!M23-'Bank Assets Analysis'!N23 -> 0 | I23: =+'Bank Assets Analysis'!O23-'Bank Assets Analysis'!P23 -> 0 | J23: =+'Bank Assets Analysis'!Q23-'Bank Assets Analysis'!R23 -> 0 | K23: =+C23+D23+E23+F23+G23+H23+I23+J23 -> 0 | L23: 1 | M23: =+K23 -> 0 | N23: =+M23*L23 -> 0
A24: 4.4 | B24: Ценные бумаги ведущих транснациональных компаний с низким уровнем странового риска | C24: =+'Bank Assets Analysis'!C24-'Bank Assets Analysis'!D24 -> 0 | D24: =+'Bank Assets Analysis'!E24-'Bank Assets Analysis'!F24 -> 0 | E24: =+'Bank Assets Analysis'!G24-'Bank Assets Analysis'!H24 -> 0 | F24: =+'Bank Assets Analysis'!I24-'Bank Assets Analysis'!J24 -> 0 | G24: =+'Bank Assets Analysis'!K24-'Bank Assets Analysis'!L24 -> 0 | H24: =+'Bank Assets Analysis'!M24-'Bank Assets Analysis'!N24 -> 0 | I24: =+'Bank Assets Analysis'!O24-'Bank Assets Analysis'!P24 -> 0 | J24: =+'Bank Assets Analysis'!Q24-'Bank Assets Analysis'!R24 -> 0 | K24: =+C24+D24+E24+F24+G24+H24+I24+J24 -> 0 | L24: 1 | M24: =+D24+E24 -> 0 | N24: =+M24*L24 -> 0
A25: 4.5 | B25: Другие | C25: =+'Bank Assets Analysis'!C25-'Bank Assets Analysis'!D25 -> 251 | D25: =+'Bank Assets Analysis'!E25-'Bank Assets Analysis'!F25 -> 0 | E25: =+'Bank Assets Analysis'!G25-'Bank Assets Analysis'!H25 -> 0 | F25: =+'Bank Assets Analysis'!I25-'Bank Assets Analysis'!J25 -> 0 | G25: =+'Bank Assets Analysis'!K25-'Bank Assets Analysis'!L25 -> 0 | H25: =+'Bank Assets Analysis'!M25-'Bank Assets Analysis'!N25 -> 0 | I25: =+'Bank Assets Analysis'!O25-'Bank Assets Analysis'!P25 -> 0 | J25: =+'Bank Assets Analysis'!Q25-'Bank Assets Analysis'!R25 -> 0 | K25: =+C25+D25+E25+F25+G25+H25+I25+J25 -> 251 | L25: 0
A26: 5. | B26: Купленные векселя, чистые | C26: =+'Bank Assets Analysis'!C26-'Bank Assets Analysis'!D26 -> 0 | D26: =+'Bank Assets Analysis'!E26-'Bank Assets Analysis'!F26 -> 0 | E26: =+'Bank Assets Analysis'!G26-'Bank Assets Analysis'!H26 -> 0 | F26: =+'Bank Assets Analysis'!I26-'Bank Assets Analysis'!J26 -> 0 | G26: =+'Bank Assets Analysis'!K26-'Bank Assets Analysis'!L26 -> 0 | H26: =+'Bank Assets Analysis'!M26-'Bank Assets Analysis'!N26 -> 0 | I26: =+'Bank Assets Analysis'!O26-'Bank Assets Analysis'!P26 -> 0 | J26: =+'Bank Assets Analysis'!Q26-'Bank Assets Analysis'!R26 -> 0 | K26: =+C26+D26+E26+F26+G26+H26+I26+J26 -> 0 | L26: 0.3 | M26: =+D26+E26 -> 0 | N26: =+M26*L26 -> 0
A27: 6. | B27: Обязательства клиентов по траттам под аккредитивы или трастовые документы | C27: =+'Bank Assets Analysis'!C27-'Bank Assets Analysis'!D27 -> 0 | D27: =+'Bank Assets Analysis'!E27-'Bank Assets Analysis'!F27 -> 0 | E27: =+'Bank Assets Analysis'!G27-'Bank Assets Analysis'!H27 -> 0 | F27: =+'Bank Assets Analysis'!I27-'Bank Assets Analysis'!J27 -> 0 | G27: =+'Bank Assets Analysis'!K27-'Bank Assets Analysis'!L27 -> 0 | H27: =+'Bank Assets Analysis'!M27-'Bank Assets Analysis'!N27 -> 0 | I27: =+'Bank Assets Analysis'!O27-'Bank Assets Analysis'!P27 -> 0 | J27: =+'Bank Assets Analysis'!Q27-'Bank Assets Analysis'!R27 -> 0 | K27: =+C27+D27+E27+F27+G27+H27+I27+J27 -> 0 | L27: 0.3 | M27: =+D27+E27 -> 0 | N27: =+M27*L27 -> 0
A28: 7. | B28: Обязательства клиентов по непогашенным акцептам этого банка | C28: =+'Bank Assets Analysis'!C28-'Bank Assets Analysis'!D28 -> 0 | D28: =+'Bank Assets Analysis'!E28-'Bank Assets Analysis'!F28 -> 0 | E28: =+'Bank Assets Analysis'!G28-'Bank Assets Analysis'!H28 -> 0 | F28: =+'Bank Assets Analysis'!I28-'Bank Assets Analysis'!J28 -> 0 | G28: =+'Bank Assets Analysis'!K28-'Bank Assets Analysis'!L28 -> 0 | H28: =+'Bank Assets Analysis'!M28-'Bank Assets Analysis'!N28 -> 0 | I28: =+'Bank Assets Analysis'!O28-'Bank Assets Analysis'!P28 -> 0 | J28: =+'Bank Assets Analysis'!Q28-'Bank Assets Analysis'!R28 -> 0 | K28: =+C28+D28+E28+F28+G28+H28+I28+J28 -> 0 | L28: 0.3 | M28: =+D28+E28 -> 0 | N28: =+M28*L28 -> 0
A29: 8. | B29: Кредиты и лизинги, предоставленные ЦБРУ, чистые | C29: =+'Bank Assets Analysis'!C29-'Bank Assets Analysis'!D29 -> 0 | D29: =+'Bank Assets Analysis'!E29-'Bank Assets Analysis'!F29 -> 0 | E29: =+'Bank Assets Analysis'!G29-'Bank Assets Analysis'!H29 -> 0 | F29: =+'Bank Assets Analysis'!I29-'Bank Assets Analysis'!J29 -> 0 | G29: =+'Bank Assets Analysis'!K29-'Bank Assets Analysis'!L29 -> 0 | H29: =+'Bank Assets Analysis'!M29-'Bank Assets Analysis'!N29 -> 0 | I29: =+'Bank Assets Analysis'!O29-'Bank Assets Analysis'!P29 -> 0 | J29: =+'Bank Assets Analysis'!Q29-'Bank Assets Analysis'!R29 -> 0 | K29: =+C29+D29+E29+F29+G29+H29+I29+J29 -> 0 | L29: 1 | M29: =C29+D29+E29 -> 0 | N29: =+M29*L29 -> 0
A30: 9. | B30: Кредиты и лизинги, предоставленные другим банкам, чистые | C30: =+'Bank Assets Analysis'!C30-'Bank Assets Analysis'!D30 -> 0 | D30: =+'Bank Assets Analysis'!E30-'Bank Assets Analysis'!F30 -> 0 | E30: =+'Bank Assets Analysis'!G30-'Bank Assets Analysis'!H30 -> 0 | F30: =+'Bank Assets Analysis'!I30-'Bank Assets Analysis'!J30 -> 0 | G30: =+'Bank Assets Analysis'!K30-'Bank Assets Analysis'!L30 -> 0 | H30: =+'Bank Assets Analysis'!M30-'Bank Assets Analysis'!N30 -> 0 | I30: =+'Bank Assets Analysis'!O30-'Bank Assets Analysis'!P30 -> 0 | J30: =+'Bank Assets Analysis'!Q30-'Bank Assets Analysis'!R30 -> 0 | K30: =+C30+D30+E30+F30+G30+H30+I30+J30 -> 0 | L30: 0.5 | M30: =+D30+E30 -> 0 | N30: =+M30*L30 -> 0
A31: 10 | B31: Кредиты и лизинги, предоставленные другим клиентам, чистые | C31: =+'Bank Assets Analysis'!C31-'Bank Assets Analysis'!D31 -> 39176156 | D31: =+'Bank Assets Analysis'!E31-'Bank Assets Analysis'!F31 -> 20109412 | E31: =+'Bank Assets Analysis'!G31-'Bank Assets Analysis'!H31 -> 121557676 | F31: =+'Bank Assets Analysis'!I31-'Bank Assets Analysis'!J31 -> 309741786 | G31: =+'Bank Assets Analysis'!K31-'Bank Assets Analysis'!L31 -> 626232238 | H31: =+'Bank Assets Analysis'!M31-'Bank Assets Analysis'!N31 -> 1169381026 | I31: =+'Bank Assets Analysis'!O31-'Bank Assets Analysis'!P31 -> 962945204 | J31: =+'Bank Assets Analysis'!Q31-'Bank Assets Analysis'!R31 -> 1472450950 | K31: =+C31+D31+E31+F31+G31+H31+I31+J31 -> 4721594448 | L31: 0.5 | M31: =+D31+E31 -> 141667088 | N31: =+M31*L31 -> 70833544
A32: 10.1 | B32: в том числе, кредиты и лизинги, предоставленные физическим лицам, чистые | C32: =+'Bank Assets Analysis'!C32-'Bank Assets Analysis'!D32 -> 7935128 | D32: =+'Bank Assets Analysis'!E32-'Bank Assets Analysis'!F32 -> 14955082 | E32: =+'Bank Assets Analysis'!G32-'Bank Assets Analysis'!H32 -> 23601942 | F32: =+'Bank Assets Analysis'!I32-'Bank Assets Analysis'!J32 -> 78983936 | G32: =+'Bank Assets Analysis'!K32-'Bank Assets Analysis'!L32 -> 120931809 | H32: =+'Bank Assets Analysis'!M32-'Bank Assets Analysis'!N32 -> 247250051 | I32: =+'Bank Assets Analysis'!O32-'Bank Assets Analysis'!P32 -> 293022871 | J32: =+'Bank Assets Analysis'!Q32-'Bank Assets Analysis'!R32 -> 496168250 | K32: =+C32+D32+E32+F32+G32+H32+I32+J32 -> 1282849069 | L32: 0
A33: 11 | B33: Кредиты и лизинги и авансы в процессе судебного разбирательства, чистые | C33: =+'Bank Assets Analysis'!C33-'Bank Assets Analysis'!D33 -> -1039 | D33: =+'Bank Assets Analysis'!E33-'Bank Assets Analysis'!F33 -> 0 | E33: =+'Bank Assets Analysis'!G33-'Bank Assets Analysis'!H33 -> 0 | F33: =+'Bank Assets Analysis'!I33-'Bank Assets Analysis'!J33 -> 0 | G33: =+'Bank Assets Analysis'!K33-'Bank Assets Analysis'!L33 -> 0 | H33: =+'Bank Assets Analysis'!M33-'Bank Assets Analysis'!N33 -> 0 | I33: =+'Bank Assets Analysis'!O33-'Bank Assets Analysis'!P33 -> 0 | J33: =+'Bank Assets Analysis'!Q33-'Bank Assets Analysis'!R33 -> 0 | K33: =+C33+D33+E33+F33+G33+H33+I33+J33 -> -1039 | L33: 0
A34: 12. | B34: Инвестиции, чистые | C34: =+'Bank Assets Analysis'!C34-'Bank Assets Analysis'!D34 -> 0 | D34: =+'Bank Assets Analysis'!E34-'Bank Assets Analysis'!F34 -> 0 | E34: =+'Bank Assets Analysis'!G34-'Bank Assets Analysis'!H34 -> 0 | F34: =+'Bank Assets Analysis'!I34-'Bank Assets Analysis'!J34 -> 0 | G34: =+'Bank Assets Analysis'!K34-'Bank Assets Analysis'!L34 -> 0 | H34: =+'Bank Assets Analysis'!M34-'Bank Assets Analysis'!N34 -> 0 | I34: =+'Bank Assets Analysis'!O34-'Bank Assets Analysis'!P34 -> 0 | J34: =+'Bank Assets Analysis'!Q34-'Bank Assets Analysis'!R34 -> 98339066 | K34: =+C34+D34+E34+F34+G34+H34+I34+J34 -> 98339066 | L34: 0
A35: 13. | B35: Ценные бумаги купленные по соглашению с обратным выкупом | C35: =+C36+C37 -> 0 | D35: =+D36+D37 -> 0 | E35: =+E36+E37 -> 0 | F35: =+F36+F37 -> 0 | G35: =+G36+G37 -> 0 | H35: =+H36+H37 -> 0 | I35: =+I36+I37 -> 0 | J35: =+J36+J37 -> 0 | K35: =+C35+D35+E35+F35+G35+H35+I35+J35 -> 0
A36: 13.1 | B36: Ценные бумаги Правительства и ЦБ купленные по соглашению с обратным выкупом (РЕПО) | C36: =+'Bank Assets Analysis'!C36-'Bank Assets Analysis'!D36 -> 0 | D36: =+'Bank Assets Analysis'!E36-'Bank Assets Analysis'!F36 -> 0 | E36: =+'Bank Assets Analysis'!G36-'Bank Assets Analysis'!H36 -> 0 | F36: =+'Bank Assets Analysis'!I36-'Bank Assets Analysis'!J36 -> 0 | G36: =+'Bank Assets Analysis'!K36-'Bank Assets Analysis'!L36 -> 0 | H36: =+'Bank Assets Analysis'!M36-'Bank Assets Analysis'!N36 -> 0 | I36: =+'Bank Assets Analysis'!O36-'Bank Assets Analysis'!P36 -> 0 | J36: =+'Bank Assets Analysis'!Q36-'Bank Assets Analysis'!R36 -> 0 | K36: =+C36+D36+E36+F36+G36+H36+I36+J36 -> 0 | L36: 1 | M36: =+K36 -> 0 | N36: =+M36*L36 -> 0
A37: 13.2 | B37: Другие ценные бумаги купленные по соглашению с обратным выкупом (РЕПО) | C37: =+'Bank Assets Analysis'!C37-'Bank Assets Analysis'!D37 -> 0 | D37: =+'Bank Assets Analysis'!E37-'Bank Assets Analysis'!F37 -> 0 | E37: =+'Bank Assets Analysis'!G37-'Bank Assets Analysis'!H37 -> 0 | F37: =+'Bank Assets Analysis'!I37-'Bank Assets Analysis'!J37 -> 0 | G37: =+'Bank Assets Analysis'!K37-'Bank Assets Analysis'!L37 -> 0 | H37: =+'Bank Assets Analysis'!M37-'Bank Assets Analysis'!N37 -> 0 | I37: =+'Bank Assets Analysis'!O37-'Bank Assets Analysis'!P37 -> 0 | J37: =+'Bank Assets Analysis'!Q37-'Bank Assets Analysis'!R37 -> 0 | K37: =+C37+D37+E37+F37+G37+H37+I37+J37 -> 0 | L37: 0 | N37: =+M37*L37 -> 0
A38: 14. | B38: Основные средства, чистые | C38: =+'Bank Assets Analysis'!C38-'Bank Assets Analysis'!D38 -> 0 | D38: =+'Bank Assets Analysis'!E38-'Bank Assets Analysis'!F38 -> 0 | E38: =+'Bank Assets Analysis'!G38-'Bank Assets Analysis'!H38 -> 0 | F38: =+'Bank Assets Analysis'!I38-'Bank Assets Analysis'!J38 -> 0 | G38: =+'Bank Assets Analysis'!K38-'Bank Assets Analysis'!L38 -> 0 | H38: =+'Bank Assets Analysis'!M38-'Bank Assets Analysis'!N38 -> 0 | I38: =+'Bank Assets Analysis'!O38-'Bank Assets Analysis'!P38 -> 0 | J38: =+'Bank Assets Analysis'!Q38-'Bank Assets Analysis'!R38 -> 812267548 | K38: =+C38+D38+E38+F38+G38+H38+I38+J38 -> 812267548 | L38: 0 | N38: =+M38*L38 -> 0
A39: 15. | B39: Другое собственное имущество банка, чистые | C39: =+'Bank Assets Analysis'!C39-'Bank Assets Analysis'!D39 -> 51751710 | D39: =+'Bank Assets Analysis'!E39-'Bank Assets Analysis'!F39 -> 0 | E39: =+'Bank Assets Analysis'!G39-'Bank Assets Analysis'!H39 -> 0 | F39: =+'Bank Assets Analysis'!I39-'Bank Assets Analysis'!J39 -> 0 | G39: =+'Bank Assets Analysis'!K39-'Bank Assets Analysis'!L39 -> 0 | H39: =+'Bank Assets Analysis'!M39-'Bank Assets Analysis'!N39 -> 0 | I39: =+'Bank Assets Analysis'!O39-'Bank Assets Analysis'!P39 -> 0 | J39: =+'Bank Assets Analysis'!Q39-'Bank Assets Analysis'!R39 -> 0 | K39: =+C39+D39+E39+F39+G39+H39+I39+J39 -> 51751710 | L39: 0 | N39: =+M39*L39 -> 0
A40: 16. | B40: Нереализованная прибыль при ревальвации по сделкам "форвард" | C40: =+'Bank Assets Analysis'!C40-'Bank Assets Analysis'!D40 -> 5936467 | D40: =+'Bank Assets Analysis'!E40-'Bank Assets Analysis'!F40 -> 0 | E40: =+'Bank Assets Analysis'!G40-'Bank Assets Analysis'!H40 -> 0 | F40: =+'Bank Assets Analysis'!I40-'Bank Assets Analysis'!J40 -> 0 | G40: =+'Bank Assets Analysis'!K40-'Bank Assets Analysis'!L40 -> 0 | H40: =+'Bank Assets Analysis'!M40-'Bank Assets Analysis'!N40 -> 0 | I40: =+'Bank Assets Analysis'!O40-'Bank Assets Analysis'!P40 -> 0 | J40: =+'Bank Assets Analysis'!Q40-'Bank Assets Analysis'!R40 -> 0 | K40: =+C40+D40+E40+F40+G40+H40+I40+J40 -> 5936467 | L40: 0 | N40: =+M40*L40 -> 0
A41: 17. | B41: Счета купли-продажи валюты и валютные позиции | C41: =+'Bank Assets Analysis'!C41-'Bank Assets Analysis'!D41 -> 0 | K41: =+C41+D41+E41+F41+G41+H41+I41+J41 -> 0 | L41: 0 | N41: =+M41*L41 -> 0
A42: 18. | B42: Клиринговые счета | C42: =+'Bank Assets Analysis'!C42-'Bank Assets Analysis'!D42 -> 3659 | D42: =+'Bank Assets Analysis'!E42-'Bank Assets Analysis'!F42 -> 0 | E42: =+'Bank Assets Analysis'!G42-'Bank Assets Analysis'!H42 -> 0 | F42: =+'Bank Assets Analysis'!I42-'Bank Assets Analysis'!J42 -> 0 | G42: =+'Bank Assets Analysis'!K42-'Bank Assets Analysis'!L42 -> 0 | H42: =+'Bank Assets Analysis'!M42-'Bank Assets Analysis'!N42 -> 0 | I42: =+'Bank Assets Analysis'!O42-'Bank Assets Analysis'!P42 -> 0 | J42: =+'Bank Assets Analysis'!Q42-'Bank Assets Analysis'!R42 -> 0 | K42: =+C42+D42+E42+F42+G42+H42+I42+J42 -> 3659 | L42: 0 | N42: =+M42*L42 -> 0
A43: 19. | B43: Начисленные проценты | C43: =+'Bank Assets Analysis'!C43-'Bank Assets Analysis'!D43 -> 113096761 | D43: =+'Bank Assets Analysis'!E43-'Bank Assets Analysis'!F43 -> 0 | E43: =+'Bank Assets Analysis'!G43-'Bank Assets Analysis'!H43 -> 0 | F43: =+'Bank Assets Analysis'!I43-'Bank Assets Analysis'!J43 -> 0 | G43: =+'Bank Assets Analysis'!K43-'Bank Assets Analysis'!L43 -> 0 | H43: =+'Bank Assets Analysis'!M43-'Bank Assets Analysis'!N43 -> 0 | I43: =+'Bank Assets Analysis'!O43-'Bank Assets Analysis'!P43 -> 0 | J43: =+'Bank Assets Analysis'!Q43-'Bank Assets Analysis'!R43 -> 0 | K43: =+C43+D43+E43+F43+G43+H43+I43+J43 -> 113096761 | L43: 0.5 | M43: =+D43+E43 -> 0 | N43: =+M43*L43 -> 0
A44: 20. | B44: Другие активы | C44: =+'Bank Assets Analysis'!C44-'Bank Assets Analysis'!D44 -> 347557727 | D44: =+'Bank Assets Analysis'!E44-'Bank Assets Analysis'!F44 -> 8146 | E44: =+'Bank Assets Analysis'!G44-'Bank Assets Analysis'!H44 -> 69139 | F44: =+'Bank Assets Analysis'!I44-'Bank Assets Analysis'!J44 -> 381410 | G44: =+'Bank Assets Analysis'!K44-'Bank Assets Analysis'!L44 -> 1665631 | H44: =+'Bank Assets Analysis'!M44-'Bank Assets Analysis'!N44 -> 972213 | I44: =+'Bank Assets Analysis'!O44-'Bank Assets Analysis'!P44 -> 2620778 | J44: =+'Bank Assets Analysis'!Q44-'Bank Assets Analysis'!R44 -> 6467284 | K44: =+C44+D44+E44+F44+G44+H44+I44+J44 -> 359742328 | L44: 0 | N44: =+M44*L44 -> 0
A45: 21. | B45: Высоколиквидные активы, находящиеся под залогом кроме строки 4.1.1. | C45: =+'Bank Assets Analysis'!C45-'Bank Assets Analysis'!D45 -> 0 | D45: =+'Bank Assets Analysis'!E45-'Bank Assets Analysis'!F45 -> 0 | E45: =+'Bank Assets Analysis'!G45-'Bank Assets Analysis'!H45 -> 0 | F45: =+'Bank Assets Analysis'!I45-'Bank Assets Analysis'!J45 -> 0 | G45: =+'Bank Assets Analysis'!K45-'Bank Assets Analysis'!L45 -> 0 | H45: =+'Bank Assets Analysis'!M45-'Bank Assets Analysis'!N45 -> 0 | I45: =+'Bank Assets Analysis'!O45-'Bank Assets Analysis'!P45 -> 0 | J45: =+'Bank Assets Analysis'!Q45-'Bank Assets Analysis'!R45 -> 0 | K45: =+C45+D45+E45+F45+G45+H45+I45+J45 -> 0 | L45: 1 | M45: =+K45 -> 0 | N45: =+M45*L45 -> 0
A46: 22. | B46: ИТОГО АКТИВОВ | C46: =SUM(C7:C44)-C8-C11-C15-C19-C21-C32-C35 -> 1641603681 | D46: =SUM(D7:D44)-D8-D11-D15-D19-D21-D32-D35 -> 20117558 | E46: =SUM(E7:E44)-E8-E11-E15-E19-E21-E32-E35 -> 176035514 | F46: =SUM(F7:F44)-F8-F11-F15-F19-F21-F32-F35 -> 665686931 | G46: =SUM(G7:G44)-G8-G11-G15-G19-G21-G32-G35 -> 627897869 | H46: =SUM(H7:H44)-H8-H11-H15-H19-H21-H32-H35 -> 1170353239 | I46: =SUM(I7:I44)-I8-I11-I15-I19-I21-I32-I35 -> 965565982 | J46: =SUM(J7:J44)-J8-J11-J15-J19-J21-J32-J35 -> 2557025153 | K46: =SUM(C46:J46) -> 7824285927 | M46: =SUM(M7:M44)-M11-M35 -> 1187511720 | N46: =SUM(N7:N44)-N11-N35 -> 1116678176 | O46: =+Balance!D45 -> 7824285927 | P46: =+K46-O46 -> 0 | Q46: =+Balance!E45 -> 4814170696 | R46: =+O46 -> 7824285927 | S46: =+K46-R46 -> 0
B47: забалансовые обязательства
A48: 1 | B48: Обязательства по выдаче кредитов (91809) | C48: =+'Bank Assets Analysis'!C48-'Bank Assets Analysis'!D48 -> 3308043 | D48: =+'Bank Assets Analysis'!E48-'Bank Assets Analysis'!F48 -> 248693 | E48: =+'Bank Assets Analysis'!G48-'Bank Assets Analysis'!H48 -> 2804722 | F48: =+'Bank Assets Analysis'!I48-'Bank Assets Analysis'!J48 -> 13074842 | G48: =+'Bank Assets Analysis'!K48-'Bank Assets Analysis'!L48 -> 16304797 | H48: =+'Bank Assets Analysis'!M48-'Bank Assets Analysis'!N48 -> 40803506 | I48: =+'Bank Assets Analysis'!O48-'Bank Assets Analysis'!P48 -> 94449279 | J48: =+'Bank Assets Analysis'!Q48-'Bank Assets Analysis'!R48 -> 378483636 | K48: =+C48+D48+E48+F48+G48+H48+I48+J48 -> 549477518
B49: из них, обеспеченные денежными средствами (МФИ, МинФин, Фонды и депозиты других организации | C49: =+'Bank Assets Analysis'!C49-'Bank Assets Analysis'!D49 -> 0 | D49: =+'Bank Assets Analysis'!E49-'Bank Assets Analysis'!F49 -> 0 | E49: =+'Bank Assets Analysis'!G49-'Bank Assets Analysis'!H49 -> 0 | F49: =+'Bank Assets Analysis'!I49-'Bank Assets Analysis'!J49 -> 0 | G49: =+'Bank Assets Analysis'!K49-'Bank Assets Analysis'!L49 -> 598 | H49: =+'Bank Assets Analysis'!M49-'Bank Assets Analysis'!N49 -> 69593 | I49: =+'Bank Assets Analysis'!O49-'Bank Assets Analysis'!P49 -> 320546 | J49: =+'Bank Assets Analysis'!Q49-'Bank Assets Analysis'!R49 -> 2690421 | K49: =+C49+D49+E49+F49+G49+H49+I49+J49 -> 3081158
A50: 2 | B50: Гарантии и поручительства (90993) | C50: =+'Bank Assets Analysis'!C50-'Bank Assets Analysis'!D50 -> 1999162 | D50: =+'Bank Assets Analysis'!E50-'Bank Assets Analysis'!F50 -> 133411 | E50: =+'Bank Assets Analysis'!G50-'Bank Assets Analysis'!H50 -> 0 | F50: =+'Bank Assets Analysis'!I50-'Bank Assets Analysis'!J50 -> 899000 | G50: =+'Bank Assets Analysis'!K50-'Bank Assets Analysis'!L50 -> 0 | H50: =+'Bank Assets Analysis'!M50-'Bank Assets Analysis'!N50 -> 0 | I50: =+'Bank Assets Analysis'!O50-'Bank Assets Analysis'!P50 -> 0 | J50: =+'Bank Assets Analysis'!Q50-'Bank Assets Analysis'!R50 -> 0 | K50: =+C50+D50+E50+F50+G50+H50+I50+J50 -> 3031573
B51: из них, гарантии и поручительства, обеспеченные денежными средствами (депозитами на отдельных блокированных счетах) | C51: =+'Bank Assets Analysis'!C51-'Bank Assets Analysis'!D51 -> 0 | D51: =+'Bank Assets Analysis'!E51-'Bank Assets Analysis'!F51 -> 0 | E51: =+'Bank Assets Analysis'!G51-'Bank Assets Analysis'!H51 -> 0 | F51: =+'Bank Assets Analysis'!I51-'Bank Assets Analysis'!J51 -> 0 | G51: =+'Bank Assets Analysis'!K51-'Bank Assets Analysis'!L51 -> 0 | H51: =+'Bank Assets Analysis'!M51-'Bank Assets Analysis'!N51 -> 0 | I51: =+'Bank Assets Analysis'!O51-'Bank Assets Analysis'!P51 -> 0 | J51: =+'Bank Assets Analysis'!Q51-'Bank Assets Analysis'!R51 -> 0 | K51: =+C51+D51+E51+F51+G51+H51+I51+J51 -> 0
A52: 3 | B52: Аккредитивы (90908-90958) | C52: =+'Bank Assets Analysis'!C52-'Bank Assets Analysis'!D52 -> 0 | D52: =+'Bank Assets Analysis'!E52-'Bank Assets Analysis'!F52 -> 0 | E52: =+'Bank Assets Analysis'!G52-'Bank Assets Analysis'!H52 -> 0 | F52: =+'Bank Assets Analysis'!I52-'Bank Assets Analysis'!J52 -> 0 | G52: =+'Bank Assets Analysis'!K52-'Bank Assets Analysis'!L52 -> 0 | H52: =+'Bank Assets Analysis'!M52-'Bank Assets Analysis'!N52 -> 0 | I52: =+'Bank Assets Analysis'!O52-'Bank Assets Analysis'!P52 -> 0 | J52: =+'Bank Assets Analysis'!Q52-'Bank Assets Analysis'!R52 -> 0 | K52: =+C52+D52+E52+F52+G52+H52+I52+J52 -> 0
B53: из них, аккредитивы, покрытые депозитами на балансовых счетах 22602 | C53: =+'Bank Assets Analysis'!C53-'Bank Assets Analysis'!D53 -> 0 | D53: =+'Bank Assets Analysis'!E53-'Bank Assets Analysis'!F53 -> 0 | E53: =+'Bank Assets Analysis'!G53-'Bank Assets Analysis'!H53 -> 0 | F53: =+'Bank Assets Analysis'!I53-'Bank Assets Analysis'!J53 -> 0 | G53: =+'Bank Assets Analysis'!K53-'Bank Assets Analysis'!L53 -> 0 | H53: =+'Bank Assets Analysis'!M53-'Bank Assets Analysis'!N53 -> 0 | I53: =+'Bank Assets Analysis'!O53-'Bank Assets Analysis'!P53 -> 0 | J53: =+'Bank Assets Analysis'!Q53-'Bank Assets Analysis'!R53 -> 0 | K53: =+C53+D53+E53+F53+G53+H53+I53+J53 -> 0
O55: Ликвидные активы | P55: =+N46-P56 -> 126575692
B56: Подпись Председателя правления: | O56: Высоко-ликвидные активы | P56: =+N7+N9+N12+N13+N15+N20+N22+N24+N36-N45 -> 990102484
O57: Чистый отток за 30 дней | P57: =+P59-P61 -> 8.5619664e+08
B58: Подпись Главного Бухгалтера:
O59: всего отток | P59: ='Bank Liabilities Analysis (нац)'!M40+P60 -> 9.8277233e+08
O60: в том числе отток по внебалансу | P60: =+'Liquidity Analysis'!D40 -> 82414190
O61: Приток по положению | P61: =IF(P55>(P59*0.75),P59*0.75,P55) -> 126575692

Sheet Bank Liabilities Analysis
A1: АНАЛИЗ ОБЯЗАТЕЛЬСТВ БАНКА | W1: Таблица-18
B2: =Balance!B3 -> АК "АЛОКАБАНК" | T2: =+Balance!B2 -> 31 Декабрь, 2021 | X2: в тыс. сум
A3: № | B3: Характеристики | C3: Срок погашения (в днях) | S3: ВСЕГО | T3: из них | V3: Расчет коэффициента покрытия ликвидности
C4: Бессрочные | E4: От 1 до 7 дней | G4: От 8 до 30 дней | I4: От 31 до 90 дней | K4: От 91 до 180 дней | M4: От 181 до 365 дней | O4: От 366 до 730 дней | Q4: Свыше 2 лет
C5: Сумма | D5: в том числе, в иностранной валюте (в экв. в сумах) | E5: Сумма | F5: в том числе, в иностранной валюте (в экв. в сумах) | G5: Сумма | H5: в том числе, в иностранной валюте (в экв. в сумах) | I5: Сумма | J5: в том числе, в иностранной валюте (в экв. в сумах) | K5: Сумма | L5: в том числе, в иностранной валюте (в экв. в сумах) | M5: Сумма | N5: в том числе, в иностранной валюте (в экв. в сумах) | O5: Сумма | P5: в том числе, в иностранной валюте (в экв. в сумах) | Q5: Сумма | R5: в том числе, в иностранной валюте (в экв. в сумах) | T5: в национальной валюте | U5: в иностранной валюте (в экв. в сумах) | V5: Коэффициент | W5: Сумма оттока за 30 дней | X5: Сумма оттока за 30 дней (в иностранной валюте)
B6: ОБЯЗАТЕЛЬСТВА
A7: 1. | B7: ДЕПОЗИТЫ
A8: 1.1 | B8: Депозиты до востребования | C8: =SUM(C9:C12) -> 1508467497 | D8: =SUM(D9:D12) -> 253933433 | E8: =SUM(E9:E12) -> 0 | F8: =SUM(F9:F12) -> 0 | G8: =SUM(G9:G12) -> 0 | H8: =SUM(H9:H12) -> 0 | I8: =SUM(I9:I12) -> 0 | J8: =SUM(J9:J12) -> 0 | ... R8: =SUM(R9:R12) -> 0 | S8: =+C8+E8+G8+I8+K8+M8+O8+Q8 -> 1508467497 | T8: =+S8-U8 -> 1254534064 | U8: =+D8+F8+H8+J8+L8+N8+P8+R8 -> 253933433
A9: 1.1.1 | B9: Вклады физических лиц | C9: 45379581 | D9: 12197299 | S9: =+C9+E9+G9+I9+K9+M9+O9+Q9 -> 45379581 | T9: =+S9-U9 -> 33182282 | U9: =+D9+F9+H9+J9+L9+N9+P9+R9 -> 12197299
A10: 1.1.2 | B10: Вклады физических лиц - под залогом по выданным кредитам | C10: 12465713 | D10: 0 | S10: =+C10+E10+G10+I10+K10+M10+O10+Q10 -> 12465713 | T10: =+S10-U10 -> 12465713 | U10: =+D10+F10+H10+J10+L10+N10+P10+R10 -> 0
A11: 1.1.3 | B11: Другие депозиты до востребования - под залогом по выданным кредитам | C11: 0 | D11: 0 | S11: =+C11+E11+G11+I11+K11+M11+O11+Q11 -> 0 | T11: =+S11-U11 -> 0 | U11: =+D11+F11+H11+J11+L11+N11+P11+R11 -> 0
A12: 1.1.4 | B12: Другие депозиты до востребования | C12: 1450622203 | D12: 241736134 | S12: =+C12+E12+G12+I12+K12+M12+O12+Q12 -> 1450622203 | T12: =+S12-U12 -> 1208886069 | U12: =+D12+F12+H12+J12+L12+N12+P12+R12 -> 241736134
A13: 1.2 | B13: Срочные депозиты, в том числе: | C13: 0 | D13: 0 | E13: 311228376 | F13: 173402 | G13: 124862058 | H13: 584364 | I13: 251357501 | J13: 55825498 | K13: 619784088 | L13: 10227901 | M13: 1000290463 | N13: 344577863 | O13: 1661540393 | P13: 811517236 | Q13: 790119926 | R13: 467319899 | S13: =+C13+E13+G13+I13+K13+M13+O13+Q13 -> 4759182805 | T13: =+S13-U13 -> 3068956642 | U13: =+D13+F13+H13+J13+L13+N13+P13+R13 -> 1690226163
A14: 1.2.1 | B14: Вклады физических лиц | C14: 0 | D14: 0 | E14: 1693376 | F14: 173402 | G14: 6862058 | H14: 584364 | I14: 113067732 | J14: 10480729 | K14: 92334194 | L14: 474007 | M14: 86660671 | N14: 14063914 | O14: 138934072 | P14: 2354579 | Q14: 1032318 | S14: =+C14+E14+G14+I14+K14+M14+O14+Q14 -> 440584421 | T14: =+S14-U14 -> 412453426 | U14: =+D14+F14+H14+J14+L14+N14+P14+R14 -> 28130995
A15: 1.2.2 | B15: Депозитные сертификаты | S15: =+C15+E15+G15+I15+K15+M15+O15+Q15 -> 0 | T15: =+S15-U15 -> 0 | U15: =+D15+F15+H15+J15+L15+N15+P15+R15 -> 0
A16: 1.3 | B16: Другие депозиты клиентов | C16: =SUM(C17:C21) -> 528458881 | D16: =SUM(D17:D21) -> 100154447 | E16: =SUM(E17:E21) -> 0 | F16: =SUM(F17:F21) -> 0 | G16: =SUM(G17:G21) -> 0 | H16: =SUM(H17:H21) -> 0 | I16: =SUM(I17:I21) -> 0 | J16: =SUM(J17:J21) -> 0 | ... R16: =SUM(R17:R21) -> 0 | S16: =+C16+E16+G16+I16+K16+M16+O16+Q16 -> 528458881 | T16: =+S16-U16 -> 428304434 | U16: =+D16+F16+H16+J16+L16+N16+P16+R16 -> 100154447
A17: 1.3.1 | B17: Средства на банковских пластиковых карточках - физических лиц | C17: 410832303 | D17: 58307168 | S17: =+C17+E17+G17+I17+K17+M17+O17+Q17 -> 410832303 | T17: =+S17-U17 -> 352525135 | U17: =+D17+F17+H17+J17+L17+N17+P17+R17 -> 58307168
A18: 1.3.2 | B18: Средства на банковских пластиковых карточках - других клиентов | C18: 6141060 | D18: 163705 | S18: =+C18+E18+G18+I18+K18+M18+O18+Q18 -> 6141060 | T18: =+S18-U18 -> 5977355 | U18: =+D18+F18+H18+J18+L18+N18+P18+R18 -> 163705
A19: 1.3.3 | B19: Депозиты клиентов по аккредитивам | C19: 30180636 | D19: 30180636 | S19: =+C19+E19+G19+I19+K19+M19+O19+Q19 -> 30180636 | T19: =+S19-U19 -> 0 | U19: =+D19+F19+H19+J19+L19+N19+P19+R19 -> 30180636
A20: 1.3.4 | B20: Зарезервированные средства клиентов для конвертации на валютном рынке | C20: 334545 | D20: 0 | S20: =+C20+E20+G20+I20+K20+M20+O20+Q20 -> 334545 | T20: =+S20-U20 -> 334545 | U20: =+D20+F20+H20+J20+L20+N20+P20+R20 -> 0
A21: 1.3.5 | B21: Другие | C21: 80970337 | D21: 11502938 | S21: =+C21+E21+G21+I21+K21+M21+O21+Q21 -> 80970337 | T21: =+S21-U21 -> 69467399 | U21: =+D21+F21+H21+J21+L21+N21+P21+R21 -> 11502938
A22: 1.4 | B22: Итого депозитов | C22: =+C8+C13+C16 -> 2036926378 | D22: =+D8+D13+D16 -> 354087880 | E22: =+E8+E13+E16 -> 311228376 | F22: =+F8+F13+F16 -> 173402 | G22: =+G8+G13+G16 -> 124862058 | H22: =+H8+H13+H16 -> 584364 | I22: =+I8+I13+I16 -> 251357501 | J22: =+J8+J13+J16 -> 55825498 | ... R22: =+R8+R13+R16 -> 467319899 | S22: =+C22+E22+G22+I22+K22+M22+O22+Q22 -> 6796109183 | T22: =+S22-U22 -> 4751795140 | U22: =+D22+F22+H22+J22+L22+N22+P22+R22 -> 2044314043 | V22: 0.15 | W22: =+S22*V22 -> 1.0194164e+09 | X22: =U22*V22 -> 3.0664711e+08
A23: 2. | B23: К оплате в ЦБРУ | S23: =+C23+E23+G23+I23+K23+M23+O23+Q23 -> 0 | T23: =+S23-U23 -> 0 | U23: =+D23+F23+H23+J23+L23+N23+P23+R23 -> 0 | V23: 1 | W23: =(C23+E23+G23)*V23 -> 0 | X23: =(D23+F23+H23)*V23 -> 0
A24: 3. | B24: К оплате в другие банки | C24: =SUM(C25:C28) -> 39046712 | D24: =SUM(D25:D28) -> 30599223 | E24: =SUM(E25:E28) -> 1500000 | F24: =SUM(F25:F28) -> 0 | G24: =SUM(G25:G28) -> 185645568 | H24: =SUM(H25:H28) -> 178345568 | I24: =SUM(I25:I28) -> 779181720 | J24: =SUM(J25:J28) -> 455181720 | ... R24: =SUM(R25:R28) -> 108376600 | S24: =+C24+E24+G24+I24+K24+M24+O24+Q24 -> 1231537343 | T24: =+S24-U24 -> 413133609 | U24: =+D24+F24+H24+J24+L24+N24+P24+R24 -> 818403734
A25: 3.1 | B25: К оплате на корреспондентские счета других банков | C25: 21415578 | D25: 20772512 | S25: =+C25 -> 21415578 | T25: =+S25-U25 -> 643066 | U25: =+D25 -> 20772512 | V25: 1 | W25: =+T25*V25 -> 643066
A26: 3.2 | B26: К оплате в другие банки - депозиты | C26: 7284000 | D26: 0 | E26: 1500000 | F26: 0 | G26: 185645568 | H26: 178345568 | I26: 779181720 | J26: 455181720 | K26: 27094150 | L26: 27094150 | M26: 18806473 | N26: 18806473 | O26: 23720000 | P26: 0 | Q26: 156542720 | R26: 108376600 | S26: =+C26+E26+G26+I26+K26+M26+O26+Q26 -> 1199774631 | T26: =+S26-U26 -> 411970120 | U26: =+D26+F26+H26+J26+L26+N26+P26+R26 -> 787804511 | V26: 1 | W26: =(C26+E26+G26)*V26 -> 194429568 | X26: =(D26+F26+H26)*V26 -> 178345568
A27: 3.3 | B27: К оплате в другие банки по расчётам с пластиковых карт | C27: 9124646 | D27: 8604223 | H27: 0 | I27: 0 | J27: 0 | K27: 0 | L27: 0 | M27: 0 | N27: 0 | O27: 0 | P27: 0 | Q27: 0 | R27: 0 | S27: =+C27+E27+G27+I27+K27+M27+O27+Q27 -> 9124646 | T27: =+S27-U27 -> 520423 | U27: =+D27+F27+H27+J27+L27+N27+P27+R27 -> 8604223 | V27: 1 | W27: =(C27+E27+G27)*V27 -> 9124646 | X27: =(D27+F27+H27)*V27 -> 8604223
A28: 3.4 | B28: Другие статьи | C28: 1222488 | D28: 1222488 | H28: 0 | I28: 0 | J28: 0 | K28: 0 | L28: 0 | M28: 0 | N28: 0 | O28: 0 | P28: 0 | Q28: 0 | R28: 0 | S28: =+C28+E28+G28+I28+K28+M28+O28+Q28 -> 1222488 | T28: =+S28-U28 -> 0 | U28: =+D28+F28+H28+J28+L28+N28+P28+R28 -> 1222488 | V28: 1 | W28: =(C28+E28+G28)*V28 -> 1222488 | X28: =(D28+F28+H28)*V28 -> 1222488
A29: 4. | B29: Управленческие чеки | E29: 0 | F29: 0 | G29: 0 | H29: 0 | I29: 0 | J29: 0 | K29: 0 | L29: 0 | M29: 0 | N29: 0 | O29: 0 | P29: 0 | Q29: 0 | R29: 0 | S29: =+C29+E29+G29+I29+K29+M29+O29+Q29 -> 0 | T29: =+S29-U29 -> 0 | U29: =+D29+F29+H29+J29+L29+N29+P29+R29 -> 0 | V29: 1 | W29: =(C29+E29+G29)*V29 -> 0 | X29: =(D29+F29+H29)*V29 -> 0
A30: 5. | B30: Непогашенные акцепты, выполненные банком или по поручению этого банка | E30: 0 | F30: 0 | G30: 0 | H30: 0 | I30: 0 | J30: 0 | K30: 0 | L30: 0 | M30: 0 | N30: 0 | O30: 0 | P30: 0 | Q30: 0 | R30: 0 | S30: =+C30+E30+G30+I30+K30+M30+O30+Q30 -> 0 | T30: =+S30-U30 -> 0 | U30: =+D30+F30+H30+J30+L30+N30+P30+R30 -> 0 | V30: 1 | W30: =(C30+E30+G30)*V30 -> 0 | X30: =(D30+F30+H30)*V30 -> 0
A31: 6. | B31: Кредиты и лизинговые операции к оплате | E31: 200000 | F31: 0 | G31: 72062421 | H31: 71907360 | I31: 189293903 | J31: 188983782 | K31: 218563863 | L31: 217994986 | M31: 368489856 | N31: 315005258 | O31: 775043688 | P31: 751974387 | Q31: 647355048 | R31: 377618886 | S31: =+C31+E31+G31+I31+K31+M31+O31+Q31 -> 2271008779 | T31: =+S31-U31 -> 347524120 | U31: =+D31+F31+H31+J31+L31+N31+P31+R31 -> 1923484659 | V31: 0.1 | W31: =+X31+'Bank Liabilities Analysis (нац)'!M32 -> 2.0972467e+08 | X31: =(U31)*V31 -> 1.9234847e+08
A32: 7. | B32: Выпущенные банком ценные бумаги | E32: 0 | F32: 0 | G32: 0 | H32: 0 | I32: 0 | J32: 0 | K32: 0 | L32: 0 | M32: 0 | N32: 0 | O32: 0 | P32: 0 | Q32: 0 | R32: 0 | S32: =+C32+E32+G32+I32+K32+M32+O32+Q32 -> 0 | T32: =+S32-U32 -> 0 | U32: =+D32+F32+H32+J32+L32+N32+P32+R32 -> 0 | V32: 1 | W32: =(C32+E32+G32)*V32 -> 0 | X32: =(D32+F32+H32)*V32 -> 0
A33: 7a. | B33: Субординированные долговые обязательства | E33: 0 | F33: 0 | G33: 0 | H33: 0 | I33: 0 | J33: 0 | K33: 0 | L33: 0 | M33: 0 | N33: 0 | O33: 0 | P33: 0 | Q33: 0 | R33: 0 | S33: =+C33+E33+G33+I33+K33+M33+O33+Q33 -> 0 | T33: =+S33-U33 -> 0 | U33: =+D33+F33+H33+J33+L33+N33+P33+R33 -> 0 | V33: 1 | W33: =(C33+E33+G33)*V33 -> 0 | X33: =(D33+F33+H33)*V33 -> 0
A34: 8. | B34: Ценные бумаги проданные по соглашению с последующим выкупом | E34: 0 | F34: 0 | G34: 54648356 | H34: 0 | I34: 364556318 | L34: 0 | M34: 0 | N34: 0 | O34: 0 | P34: 0 | Q34: 0 | R34: 0 | S34: =+C34+E34+G34+I34+K34+M34+O34+Q34 -> 419204674 | T34: =+S34-U34 -> 419204674 | U34: =+D34+F34+H34+J34+L34+N34+P34+R34 -> 0 | V34: 1 | W34: =(C34+E34+G34)*V34 -> 54648356 | X34: =(D34+F34+H34)*V34 -> 0
A35: 9. | B35: Нереализованная прибыль или убытки по форвардным сделкам и другим отсроченным кредитам | E35: 0 | F35: 0 | G35: 0 | H35: 0 | I35: 0 | J35: 0 | K35: 0 | L35: 0 | M35: 0 | N35: 0 | O35: 0 | P35: 0 | Q35: 0 | R35: 0 | S35: =+C35+E35+G35+I35+K35+M35+O35+Q35 -> 0 | T35: =+S35-U35 -> 0 | U35: =+D35+F35+H35+J35+L35+N35+P35+R35 -> 0 | V35: 1 | W35: =(S35)*V35 -> 0 | X35: =(U35)*V35 -> 0
A36: 10. | B36: Клиринговые счета - кредитовый остаток | C36: 7801251 | D36: 7689371 | E36: 152 | H36: 0 | I36: 0 | J36: 0 | K36: 0 | L36: 0 | M36: 0 | N36: 0 | O36: 0 | P36: 0 | Q36: 0 | R36: 0 | S36: =+C36+E36+G36+I36+K36+M36+O36+Q36 -> 7801403 | T36: =+S36-U36 -> 112032 | U36: =+D36+F36+H36+J36+L36+N36+P36+R36 -> 7689371 | V36: 1 | W36: =(S36)*V36 -> 7801403 | X36: =(U36)*V36 -> 7689371
A37: 11. | B37: Начисленные проценты | C37: 11203308 | D37: 1561 | E37: 205971 | F37: 190460 | G37: 727251 | H37: 721518 | I37: 3440381 | J37: 2670836 | K37: 2147806 | L37: 1465830 | M37: 3740672 | N37: 968698 | O37: 2527499 | P37: 1252650 | Q37: 5811382 | R37: 4695853 | S37: =+C37+E37+G37+I37+K37+M37+O37+Q37 -> 29804270 | T37: =+S37-U37 -> 17836864 | U37: =+D37+F37+H37+J37+L37+N37+P37+R37 -> 11967406 | W37: =C37+E37+G37+((I37+K37+M37+O37+Q37)*15%) -> 14786691 | X37: =D37+F37+H37+((J37+L37+N37+P37+R37)*15%) -> 2571619
A38: 12. | B38: Другие обязательства | C38: 153397873 | D38: 84922687 | E38: 43362670 | F38: 29532607 | G38: 17557 | H38: 0 | I38: 248657 | J38: 182720 | K38: 303144 | L38: 220366 | M38: 503311 | N38: 25890 | O38: 1087544 | P38: 0 | Q38: 10564272 | R38: 8611046 | S38: =+C38+E38+G38+I38+K38+M38+O38+Q38 -> 209485028 | T38: =+S38-U38 -> 85989712 | U38: =+D38+F38+H38+J38+L38+N38+P38+R38 -> 123495316 | V38: 1 | W38: =(S38)*V38 -> 209485028 | X38: =(U38)*V38 -> 123495316
A39: 13. | B39: ИТОГО ОБЯЗАТЕЛЬСТВ | C39: =+C22+C29+C30+C31+C32+C33+C34+C35+C36+C37+C38+C23+C24 -> 2248375522 | D39: =+D22+D29+D30+D31+D32+D33+D34+D35+D36+D37+D38+D23+D24 -> 477300722 | E39: =+E22+E29+E30+E31+E32+E33+E34+E35+E36+E37+E38+E23+E24 -> 356497169 | F39: =+F22+F29+F30+F31+F32+F33+F34+F35+F36+F37+F38+F23+F24 -> 29896469 | G39: =+G22+G29+G30+G31+G32+G33+G34+G35+G36+G37+G38+G23+G24 -> 437963211 | H39: =+H22+H29+H30+H31+H32+H33+H34+H35+H36+H37+H38+H23+H24 -> 251558810 | I39: =+I22+I29+I30+I31+I32+I33+I34+I35+I36+I37+I38+I23+I24 -> 1588078480 | J39: =+J22+J29+J30+J31+J32+J33+J34+J35+J36+J37+J38+J23+J24 -> 702844556 | ... R39: =+R22+R29+R30+R31+R32+R33+R34+R35+R36+R37+R38+R23+R24 -> 966622284 | S39: =+S22+S23+S24+S29+S30+S31+S32+S33+S34+S35+S36+S37+S38 -> 10964950680 | T39: =+T22+T23+T24+T29+T30+T31+T32+T33+T34+T35+T36+T37+T38 -> 6035596151 | U39: =+U22+U23+U24+U29+U30+U31+U32+U33+U34+U35+U36+U37+U38 -> 4929354529 | V39: отток | W39: =SUM(W9:W38) -> 1.7212823e+09 | X39: =SUM(X9:X38) -> 8.2092416e+08 | Y39: =+Balance!C62 -> 10964950680 | Z39: =+Balance!D62 -> 6035596151 | AA39: =+Balance!E62 -> 4929354529
B40: из них, обязательства перед: | S40: =+C40+E40+G40+I40+K40+M40+O40+Q40 -> 0 | T40: =+S40-U40 -> 0 | U40: =+D40+F40+H40+J40+L40+N40+P40+R40 -> 0
B41: Министерство Финансов Республики Узбекистан, из них | C41: =+C42+C43 -> 255916 | D41: =+D42+D43 -> 0 | E41: =+E42+E43 -> 305200000 | F41: =+F42+F43 -> 0 | G41: =+G42+G43 -> 100000000 | H41: =+H42+H43 -> 0 | I41: =+I42+I43 -> 0 | J41: =+J42+J43 -> 0 | ... R41: =+R42+R43 -> 466019380 | S41: =+C41+E41+G41+I41+K41+M41+O41+Q41 -> 1756368296 | T41: =+S41-U41 -> 1290348916 | U41: =+D41+F41+H41+J41+L41+N41+P41+R41 -> 466019380
B42: Кредиты и лизинги | C42: 0 | D42: 0 | E42: 200000 | F42: 0 | G42: 0 | H42: 0 | I42: 0 | J42: 0 | K42: 0 | L42: 0 | M42: 0 | N42: 0 | O42: 0 | P42: 0 | Q42: 38593000 | R42: 0 | S42: =+C42+E42+G42+I42+K42+M42+O42+Q42 -> 38793000 | T42: =+S42-U42 -> 38793000 | U42: =+D42+F42+H42+J42+L42+N42+P42+R42 -> 0
B43: Депозитные ресурсы | C43: 255916 | D43: 0 | E43: 305000000 | F43: 0 | G43: 100000000 | H43: 0 | I43: 0 | J43: 0 | K43: 485500000 | L43: 0 | M43: 360000000 | N43: 0 | O43: 0 | P43: 0 | Q43: 466819380 | R43: 466019380 | S43: =+C43+E43+G43+I43+K43+M43+O43+Q43 -> 1717575296 | T43: =+S43-U43 -> 1251555916 | U43: =+D43+F43+H43+J43+L43+N43+P43+R43 -> 466019380
B44: Внебюджетные фонды, из них | C44: =+C45+C46 -> 0 | D44: =+D45+D46 -> 0 | E44: =+E45+E46 -> 0 | F44: =+F45+F46 -> 0 | G44: =+G45+G46 -> 0 | H44: =+H45+H46 -> 0 | I44: =+I45+I46 -> 0 | J44: =+J45+J46 -> 0 | ... R44: =+R45+R46 -> 0 | S44: =+C44+E44+G44+I44+K44+M44+O44+Q44 -> 0 | T44: =+S44-U44 -> 0 | U44: =+D44+F44+H44+J44+L44+N44+P44+R44 -> 0
B45: Кредиты и лизинги | S45: =+C45+E45+G45+I45+K45+M45+O45+Q45 -> 0 | T45: =+S45-U45 -> 0 | U45: =+D45+F45+H45+J45+L45+N45+P45+R45 -> 0
B46: Депозитные ресурсы | S46: =+C46+E46+G46+I46+K46+M46+O46+Q46 -> 0 | T46: =+S46-U46 -> 0 | U46: =+D46+F46+H46+J46+L46+N46+P46+R46 -> 0
B47: Фонд реконструкции и развития Узбекистана (ФРРУ) , из них | C47: =+C48+C49 -> 0 | D47: =+D48+D49 -> 0 | E47: =+E48+E49 -> 0 | F47: =+F48+F49 -> 0 | G47: =+G48+G49 -> 0 | H47: =+H48+H49 -> 0 | I47: =+I48+I49 -> 0 | J47: =+J48+J49 -> 0 | ... R47: =+R48+R49 -> 0 | S47: =+C47+E47+G47+I47+K47+M47+O47+Q47 -> 0 | T47: =+S47-U47 -> 0 | U47: =+D47+F47+H47+J47+L47+N47+P47+R47 -> 0
B48: Кредиты и лизинги | S48: =+C48+E48+G48+I48+K48+M48+O48+Q48 -> 0 | T48: =+S48-U48 -> 0 | U48: =+D48+F48+H48+J48+L48+N48+P48+R48 -> 0
B49: Депозитные ресурсы | S49: =+C49+E49+G49+I49+K49+M49+O49+Q49 -> 0 | T49: =+S49-U49 -> 0 | U49: =+D49+F49+H49+J49+L49+N49+P49+R49 -> 0
B50: Зарубежные банки, из них | C50: =+C51+C52 -> 0 | D50: =+D51+D52 -> 0 | E50: =+E51+E52 -> 0 | F50: =+F51+F52 -> 0 | G50: =+G51+G52 -> 17009173 | H50: =+H51+H52 -> 17009173 | I50: =+I51+I52 -> 112415619 | J50: =+J51+J52 -> 112415619 | ... R50: =+R51+R52 -> 159061674 | S50: =+C50+E50+G50+I50+K50+M50+O50+Q50 -> 1240109277 | T50: =+S50-U50 -> 0 | U50: =+D50+F50+H50+J50+L50+N50+P50+R50 -> 1240109277
B51: Кредиты и лизинги | G51: 12066165 | H51: 12066165 | I51: 112415619 | J51: 112415619 | K51: 68264903 | L51: 68264903 | M51: 175722891 | N51: 175722891 | O51: 677990884 | P51: 677990884 | Q51: 159061674 | R51: 159061674 | S51: =+C51+E51+G51+I51+K51+M51+O51+Q51 -> 1205522136 | T51: =+S51-U51 -> 0 | U51: =+D51+F51+H51+J51+L51+N51+P51+R51 -> 1205522136
B52: Депозитные ресурсы | G52: 4943008 | H52: 4943008 | I52: 0 | J52: 0 | K52: 10837660 | L52: 10837660 | M52: 18806473 | N52: 18806473 | O52: 0 | P52: 0 | Q52: 0 | R52: 0 | S52: =+C52+E52+G52+I52+K52+M52+O52+Q52 -> 34587141 | T52: =+S52-U52 -> 0 | U52: =+D52+F52+H52+J52+L52+N52+P52+R52 -> 34587141
B53: Другие зарубежные финансовые организации, из них | C53: =+C54+C55 -> 0 | D53: =+D54+D55 -> 0 | E53: =+E54+E55 -> 0 | F53: =+F54+F55 -> 0 | G53: =+G54+G55 -> 0 | H53: =+H54+H55 -> 0 | I53: =+I54+I55 -> 0 | J53: =+J54+J55 -> 0 | ... R53: =+R54+R55 -> 0 | S53: =+C53+E53+G53+I53+K53+M53+O53+Q53 -> 192467680 | T53: =+S53-U53 -> 51578100 | U53: =+D53+F53+H53+J53+L53+N53+P53+R53 -> 140889580
B54: Кредиты и лизинги | K54: 59607130 | L54: 59607130 | M54: 51578100 | N54: 0 | O54: 81282450 | P54: 81282450 | S54: =+C54+E54+G54+I54+K54+M54+O54+Q54 -> 192467680 | T54: =+S54-U54 -> 51578100 | U54: =+D54+F54+H54+J54+L54+N54+P54+R54 -> 140889580
B55: Депозитные ресурсы | S55: =+C55+E55+G55+I55+K55+M55+O55+Q55 -> 0 | T55: =+S55-U55 -> 0 | U55: =+D55+F55+H55+J55+L55+N55+P55+R55 -> 0
B57: Подпись Председателя правления:
B59: Подпись Главного Бухгалтера:

Sheet Bank Liabilities Analysis (нац)
A2: АНАЛИЗ ОБЯЗАТЕЛЬСТВ БАНКА В НАЦИОНАЛЬНОЙ ВАЛЮТЕ | L2: Таблица-18А
B3: =Balance!B3 -> АК "АЛОКАБАНК" | J3: =+Balance!B2 -> 31 Декабрь, 2021 | M3: =+Balance!E3 -> тыс. сум
A4: № | B4: Характеристики | C4: Срок погашения (в днях) | K4: ВСЕГО | L4: Расчет коэффициента покрытия ликвидности
C5: Бессрочные | D5: От 1 до 7 дней | E5: От 8 до 30 дней | F5: От 31 до 90 дней | G5: От 91 до 180 дней | H5: От 181 до 365 дней | I5: От 366 до 730 дней | J5: Свыше 2 лет
L6: Коэффициент | M6: Сумма оттока за 30 дней
B7: ОБЯЗАТЕЛЬСТВА
A8: 1. | B8: ДЕПОЗИТЫ
A9: 1.1 | B9: Депозиты до востребования | C9: =SUM(C10:C13) -> 1254534064 | D9: =SUM(D10:D13) -> 0 | E9: =SUM(E10:E13) -> 0 | F9: =SUM(F10:F13) -> 0 | G9: =SUM(G10:G13) -> 0 | H9: =SUM(H10:H13) -> 0 | I9: =SUM(I10:I13) -> 0 | J9: =SUM(J10:J13) -> 0 | K9: =+C9+D9+E9+F9+G9+H9+I9+J9 -> 1254534064
A10: 1.1.1 | B10: Вклады физических лиц | C10: =+'Bank Liabilities Analysis'!C9-'Bank Liabilities Analysis'!D9 -> 33182282 | D10: =+'Bank Liabilities Analysis'!E9-'Bank Liabilities Analysis'!F9 -> 0 | E10: =+'Bank Liabilities Analysis'!G9-'Bank Liabilities Analysis'!H9 -> 0 | F10: =+'Bank Liabilities Analysis'!I9-'Bank Liabilities Analysis'!J9 -> 0 | G10: =+'Bank Liabilities Analysis'!K9-'Bank Liabilities Analysis'!L9 -> 0 | H10: =+'Bank Liabilities Analysis'!M9-'Bank Liabilities Analysis'!N9 -> 0 | I10: =+'Bank Liabilities Analysis'!O9-'Bank Liabilities Analysis'!P9 -> 0 | J10: =+'Bank Liabilities Analysis'!Q9-'Bank Liabilities Analysis'!R9 -> 0 | K10: =+C10+D10+E10+F10+G10+H10+I10+J10 -> 33182282
A11: 1.1.2 | B11: Вклады физических лиц - под залогом по выданным кредитам | C11: =+'Bank Liabilities Analysis'!C10-'Bank Liabilities Analysis'!D10 -> 12465713 | D11: =+'Bank Liabilities Analysis'!E10-'Bank Liabilities Analysis'!F10 -> 0 | E11: =+'Bank Liabilities Analysis'!G10-'Bank Liabilities Analysis'!H10 -> 0 | F11: =+'Bank Liabilities Analysis'!I10-'Bank Liabilities Analysis'!J10 -> 0 | G11: =+'Bank Liabilities Analysis'!K10-'Bank Liabilities Analysis'!L10 -> 0 | H11: =+'Bank Liabilities Analysis'!M10-'Bank Liabilities Analysis'!N10 -> 0 | I11: =+'Bank Liabilities Analysis'!O10-'Bank Liabilities Analysis'!P10 -> 0 | J11: =+'Bank Liabilities Analysis'!Q10-'Bank Liabilities Analysis'!R10 -> 0 | K11: =+C11+D11+E11+F11+G11+H11+I11+J11 -> 12465713
A12: 1.1.3 | B12: Другие депозиты до востребования - под залогом по выданным кредитам | C12: =+'Bank Liabilities Analysis'!C11-'Bank Liabilities Analysis'!D11 -> 0 | D12: =+'Bank Liabilities Analysis'!E11-'Bank Liabilities Analysis'!F11 -> 0 | E12: =+'Bank Liabilities Analysis'!G11-'Bank Liabilities Analysis'!H11 -> 0 | F12: =+'Bank Liabilities Analysis'!I11-'Bank Liabilities Analysis'!J11 -> 0 | G12: =+'Bank Liabilities Analysis'!K11-'Bank Liabilities Analysis'!L11 -> 0 | H12: =+'Bank Liabilities Analysis'!M11-'Bank Liabilities Analysis'!N11 -> 0 | I12: =+'Bank Liabilities Analysis'!O11-'Bank Liabilities Analysis'!P11 -> 0 | J12: =+'Bank Liabilities Analysis'!Q11-'Bank Liabilities Analysis'!R11 -> 0 | K12: =+C12+D12+E12+F12+G12+H12+I12+J12 -> 0
A13: 1.1.4 | B13: Другие депозиты до востребования | C13: =+'Bank Liabilities Analysis'!C12-'Bank Liabilities Analysis'!D12 -> 1208886069 | D13: =+'Bank Liabilities Analysis'!E12-'Bank Liabilities Analysis'!F12 -> 0 | E13: =+'Bank Liabilities Analysis'!G12-'Bank Liabilities Analysis'!H12 -> 0 | F13: =+'Bank Liabilities Analysis'!I12-'Bank Liabilities Analysis'!J12 -> 0 | G13: =+'Bank Liabilities Analysis'!K12-'Bank Liabilities Analysis'!L12 -> 0 | H13: =+'Bank Liabilities Analysis'!M12-'Bank Liabilities Analysis'!N12 -> 0 | I13: =+'Bank Liabilities Analysis'!O12-'Bank Liabilities Analysis'!P12 -> 0 | J13: =+'Bank Liabilities Analysis'!Q12-'Bank Liabilities Analysis'!R12 -> 0 | K13: =+C13+D13+E13+F13+G13+H13+I13+J13 -> 1208886069
A14: 1.2 | B14: Срочные депозиты, в том числе: | C14: =+'Bank Liabilities Analysis'!C13-'Bank Liabilities Analysis'!D13 -> 0 | D14: =+'Bank Liabilities Analysis'!E13-'Bank Liabilities Analysis'!F13 -> 311054974 | E14: =+'Bank Liabilities Analysis'!G13-'Bank Liabilities Analysis'!H13 -> 124277694 | F14: =+'Bank Liabilities Analysis'!I13-'Bank Liabilities Analysis'!J13 -> 195532003 | G14: =+'Bank Liabilities Analysis'!K13-'Bank Liabilities Analysis'!L13 -> 609556187 | H14: =+'Bank Liabilities Analysis'!M13-'Bank Liabilities Analysis'!N13 -> 655712600 | I14: =+'Bank Liabilities Analysis'!O13-'Bank Liabilities Analysis'!P13 -> 850023157 | J14: =+'Bank Liabilities Analysis'!Q13-'Bank Liabilities Analysis'!R13 -> 322800027 | K14: =+C14+D14+E14+F14+G14+H14+I14+J14 -> 3068956642
A15: 1.2.1 | B15: Вклады физических лиц | C15: =+'Bank Liabilities Analysis'!C14-'Bank Liabilities Analysis'!D14 -> 0 | D15: =+'Bank Liabilities Analysis'!E14-'Bank Liabilities Analysis'!F14 -> 1519974 | E15: =+'Bank Liabilities Analysis'!G14-'Bank Liabilities Analysis'!H14 -> 6277694 | F15: =+'Bank Liabilities Analysis'!I14-'Bank Liabilities Analysis'!J14 -> 102587003 | G15: =+'Bank Liabilities Analysis'!K14-'Bank Liabilities Analysis'!L14 -> 91860187 | H15: =+'Bank Liabilities Analysis'!M14-'Bank Liabilities Analysis'!N14 -> 72596757 | I15: =+'Bank Liabilities Analysis'!O14-'Bank Liabilities Analysis'!P14 -> 136579493 | J15: =+'Bank Liabilities Analysis'!Q14-'Bank Liabilities Analysis'!R14 -> 1032318 | K15: =+C15+D15+E15+F15+G15+H15+I15+J15 -> 412453426
A16: 1.2.2 | B16: Депозитные сертификаты | C16: =+'Bank Liabilities Analysis'!C15-'Bank Liabilities Analysis'!D15 -> 0 | D16: =+'Bank Liabilities Analysis'!E15-'Bank Liabilities Analysis'!F15 -> 0 | E16: =+'Bank Liabilities Analysis'!G15-'Bank Liabilities Analysis'!H15 -> 0 | F16: =+'Bank Liabilities Analysis'!I15-'Bank Liabilities Analysis'!J15 -> 0 | G16: =+'Bank Liabilities Analysis'!K15-'Bank Liabilities Analysis'!L15 -> 0 | H16: =+'Bank Liabilities Analysis'!M15-'Bank Liabilities Analysis'!N15 -> 0 | I16: =+'Bank Liabilities Analysis'!O15-'Bank Liabilities Analysis'!P15 -> 0 | J16: =+'Bank Liabilities Analysis'!Q15-'Bank Liabilities Analysis'!R15 -> 0 | K16: =+C16+D16+E16+F16+G16+H16+I16+J16 -> 0
A17: 1.3 | B17: Другие депозиты клиентов | C17: =SUM(C18:C22) -> 428304434 | D17: =SUM(D18:D22) -> 0 | E17: =SUM(E18:E22) -> 0 | F17: =SUM(F18:F22) -> 0 | G17: =SUM(G18:G22) -> 0 | H17: =SUM(H18:H22) -> 0 | I17: =SUM(I18:I22) -> 0 | J17: =SUM(J18:J22) -> 0 | K17: =+C17+D17+E17+F17+G17+H17+I17+J17 -> 428304434
A18: 1.3.1 | B18: Средства на банковских пластиковых карточках - физических лиц | C18: =+'Bank Liabilities Analysis'!C17-'Bank Liabilities Analysis'!D17 -> 352525135 | D18: =+'Bank Liabilities Analysis'!E17-'Bank Liabilities Analysis'!F17 -> 0 | E18: =+'Bank Liabilities Analysis'!G17-'Bank Liabilities Analysis'!H17 -> 0 | F18: =+'Bank Liabilities Analysis'!I17-'Bank Liabilities Analysis'!J17 -> 0 | G18: =+'Bank Liabilities Analysis'!K17-'Bank Liabilities Analysis'!L17 -> 0 | H18: =+'Bank Liabilities Analysis'!M17-'Bank Liabilities Analysis'!N17 -> 0 | I18: =+'Bank Liabilities Analysis'!O17-'Bank Liabilities Analysis'!P17 -> 0 | J18: =+'Bank Liabilities Analysis'!Q17-'Bank Liabilities Analysis'!R17 -> 0 | K18: =+C18+D18+E18+F18+G18+H18+I18+J18 -> 352525135
A19: 1.3.2 | B19: Средства на банковских пластиковых карточках - других клиентов | C19: =+'Bank Liabilities Analysis'!C18-'Bank Liabilities Analysis'!D18 -> 5977355 | D19: =+'Bank Liabilities Analysis'!E18-'Bank Liabilities Analysis'!F18 -> 0 | E19: =+'Bank Liabilities Analysis'!G18-'Bank Liabilities Analysis'!H18 -> 0 | F19: =+'Bank Liabilities Analysis'!I18-'Bank Liabilities Analysis'!J18 -> 0 | G19: =+'Bank Liabilities Analysis'!K18-'Bank Liabilities Analysis'!L18 -> 0 | H19: =+'Bank Liabilities Analysis'!M18-'Bank Liabilities Analysis'!N18 -> 0 | I19: =+'Bank Liabilities Analysis'!O18-'Bank Liabilities Analysis'!P18 -> 0 | J19: =+'Bank Liabilities Analysis'!Q18-'Bank Liabilities Analysis'!R18 -> 0 | K19: =+C19+D19+E19+F19+G19+H19+I19+J19 -> 5977355
A20: 1.3.3 | B20: Депозиты клиентов по аккредитивам | C20: =+'Bank Liabilities Analysis'!C19-'Bank Liabilities Analysis'!D19 -> 0 | D20: =+'Bank Liabilities Analysis'!E19-'Bank Liabilities Analysis'!F19 -> 0 | E20: =+'Bank Liabilities Analysis'!G19-'Bank Liabilities Analysis'!H19 -> 0 | F20: =+'Bank Liabilities Analysis'!I19-'Bank Liabilities Analysis'!J19 -> 0 | G20: =+'Bank Liabilities Analysis'!K19-'Bank Liabilities Analysis'!L19 -> 0 | H20: =+'Bank Liabilities Analysis'!M19-'Bank Liabilities Analysis'!N19 -> 0 | I20: =+'Bank Liabilities Analysis'!O19-'Bank Liabilities Analysis'!P19 -> 0 | J20: =+'Bank Liabilities Analysis'!Q19-'Bank Liabilities Analysis'!R19 -> 0 | K20: =+C20+D20+E20+F20+G20+H20+I20+J20 -> 0
A21: 1.3.4 | B21: Зарезервированные средства клиентов для конвертации на валютном рынке | C21: =+'Bank Liabilities Analysis'!C20-'Bank Liabilities Analysis'!D20 -> 334545 | D21: =+'Bank Liabilities Analysis'!E20-'Bank Liabilities Analysis'!F20 -> 0 | E21: =+'Bank Liabilities Analysis'!G20-'Bank Liabilities Analysis'!H20 -> 0 | F21: =+'Bank Liabilities Analysis'!I20-'Bank Liabilities Analysis'!J20 -> 0 | G21: =+'Bank Liabilities Analysis'!K20-'Bank Liabilities Analysis'!L20 -> 0 | H21: =+'Bank Liabilities Analysis'!M20-'Bank Liabilities Analysis'!N20 -> 0 | I21: =+'Bank Liabilities Analysis'!O20-'Bank Liabilities Analysis'!P20 -> 0 | J21: =+'Bank Liabilities Analysis'!Q20-'Bank Liabilities Analysis'!R20 -> 0 | K21: =+C21+D21+E21+F21+G21+H21+I21+J21 -> 334545
A22: 1.3.5 | B22: Другие | C22: =+'Bank Liabilities Analysis'!C21-'Bank Liabilities Analysis'!D21 -> 69467399 | D22: =+'Bank Liabilities Analysis'!E21-'Bank Liabilities Analysis'!F21 -> 0 | E22: =+'Bank Liabilities Analysis'!G21-'Bank Liabilities Analysis'!H21 -> 0 | F22: =+'Bank Liabilities Analysis'!I21-'Bank Liabilities Analysis'!J21 -> 0 | G22: =+'Bank Liabilities Analysis'!K21-'Bank Liabilities Analysis'!L21 -> 0 | H22: =+'Bank Liabilities Analysis'!M21-'Bank Liabilities Analysis'!N21 -> 0 | I22: =+'Bank Liabilities Analysis'!O21-'Bank Liabilities Analysis'!P21 -> 0 | J22: =+'Bank Liabilities Analysis'!Q21-'Bank Liabilities Analysis'!R21 -> 0 | K22: =+C22+D22+E22+F22+G22+H22+I22+J22 -> 69467399
A23: 1.4 | B23: Итого депозитов | C23: =+C9+C14+C17 -> 1682838498 | D23: =+D9+D14+D17 -> 311054974 | E23: =+E9+E14+E17 -> 124277694 | F23: =+F9+F14+F17 -> 195532003 | G23: =+G9+G14+G17 -> 609556187 | H23: =+H9+H14+H17 -> 655712600 | I23: =+I9+I14+I17 -> 850023157 | J23: =+J9+J14+J17 -> 322800027 | K23: =+C23+D23+E23+F23+G23+H23+I23+J23 -> 4751795140 | L23: 0.15 | M23: =+K23*L23 -> 712769271
A24: 2. | B24: К оплате в ЦБРУ | C24: =+'Bank Liabilities Analysis'!C23-'Bank Liabilities Analysis'!D23 -> 0 | D24: =+'Bank Liabilities Analysis'!E23-'Bank Liabilities Analysis'!F23 -> 0 | E24: =+'Bank Liabilities Analysis'!G23-'Bank Liabilities Analysis'!H23 -> 0 | F24: =+'Bank Liabilities Analysis'!I23-'Bank Liabilities Analysis'!J23 -> 0 | G24: =+'Bank Liabilities Analysis'!K23-'Bank Liabilities Analysis'!L23 -> 0 | H24: =+'Bank Liabilities Analysis'!M23-'Bank Liabilities Analysis'!N23 -> 0 | I24: =+'Bank Liabilities Analysis'!O23-'Bank Liabilities Analysis'!P23 -> 0 | J24: =+'Bank Liabilities Analysis'!Q23-'Bank Liabilities Analysis'!R23 -> 0 | K24: =+C24+D24+E24+F24+G24+H24+I24+J24 -> 0 | L24: 1 | M24: =(C24+D24+E24)*L24 -> 0
A25: 3. | B25: К оплате в другие банки | C25: =SUM(C26:C29) -> 8447489 | D25: =SUM(D26:D29) -> 1500000 | E25: =SUM(E26:E29) -> 7300000 | F25: =SUM(F26:F29) -> 324000000 | G25: =SUM(G26:G29) -> 0 | H25: =SUM(H26:H29) -> 0 | I25: =SUM(I26:I29) -> 23720000 | J25: =SUM(J26:J29) -> 48166120 | K25: =+C25+D25+E25+F25+G25+H25+I25+J25 -> 413133609
A26: 3.1 | B26: К оплате на корреспондентские счета других банков | C26: =+'Bank Liabilities Analysis'!C25-'Bank Liabilities Analysis'!D25 -> 643066 | D26: =+'Bank Liabilities Analysis'!E25-'Bank Liabilities Analysis'!F25 -> 0 | E26: =+'Bank Liabilities Analysis'!G25-'Bank Liabilities Analysis'!H25 -> 0 | F26: =+'Bank Liabilities Analysis'!I25-'Bank Liabilities Analysis'!J25 -> 0 | G26: =+'Bank Liabilities Analysis'!K25-'Bank Liabilities Analysis'!L25 -> 0 | H26: =+'Bank Liabilities Analysis'!M25-'Bank Liabilities Analysis'!N25 -> 0 | I26: =+'Bank Liabilities Analysis'!O25-'Bank Liabilities Analysis'!P25 -> 0 | J26: =+'Bank Liabilities Analysis'!Q25-'Bank Liabilities Analysis'!R25 -> 0 | K26: =+C26+D26+E26+F26+G26+H26+I26+J26 -> 643066 | L26: 1 | M26: =+K26*L26 -> 643066
A27: 3.2 | B27: К оплате в другие банки - депозиты | C27: =+'Bank Liabilities Analysis'!C26-'Bank Liabilities Analysis'!D26 -> 7284000 | D27: =+'Bank Liabilities Analysis'!E26-'Bank Liabilities Analysis'!F26 -> 1500000 | E27: =+'Bank Liabilities Analysis'!G26-'Bank Liabilities Analysis'!H26 -> 7300000 | F27: =+'Bank Liabilities Analysis'!I26-'Bank Liabilities Analysis'!J26 -> 324000000 | G27: =+'Bank Liabilities Analysis'!K26-'Bank Liabilities Analysis'!L26 -> 0 | H27: =+'Bank Liabilities Analysis'!M26-'Bank Liabilities Analysis'!N26 -> 0 | I27: =+'Bank Liabilities Analysis'!O26-'Bank Liabilities Analysis'!P26 -> 23720000 | J27: =+'Bank Liabilities Analysis'!Q26-'Bank Liabilities Analysis'!R26 -> 48166120 | K27: =+C27+D27+E27+F27+G27+H27+I27+J27 -> 411970120 | L27: 1 | M27: =(C27+D27+E27)*L27 -> 16084000
A28: 3.3 | B28: К оплате в другие банки по расчётам с пластиковых карт | C28: =+'Bank Liabilities Analysis'!C27-'Bank Liabilities Analysis'!D27 -> 520423 | D28: =+'Bank Liabilities Analysis'!E27-'Bank Liabilities Analysis'!F27 -> 0 | E28: =+'Bank Liabilities Analysis'!G27-'Bank Liabilities Analysis'!H27 -> 0 | F28: =+'Bank Liabilities Analysis'!I27-'Bank Liabilities Analysis'!J27 -> 0 | G28: =+'Bank Liabilities Analysis'!K27-'Bank Liabilities Analysis'!L27 -> 0 | H28: =+'Bank Liabilities Analysis'!M27-'Bank Liabilities Analysis'!N27 -> 0 | I28: =+'Bank Liabilities Analysis'!O27-'Bank Liabilities Analysis'!P27 -> 0 | J28: =+'Bank Liabilities Analysis'!Q27-'Bank Liabilities Analysis'!R27 -> 0 | K28: =+C28+D28+E28+F28+G28+H28+I28+J28 -> 520423 | L28: 1 | M28: =(C28+D28+E28)*L28 -> 520423
A29: 3.4 | B29: Другие статьи | C29: =+'Bank Liabilities Analysis'!C28-'Bank Liabilities Analysis'!D28 -> 0 | D29: =+'Bank Liabilities Analysis'!E28-'Bank Liabilities Analysis'!F28 -> 0 | E29: =+'Bank Liabilities Analysis'!G28-'Bank Liabilities Analysis'!H28 -> 0 | F29: =+'Bank Liabilities Analysis'!I28-'Bank Liabilities Analysis'!J28 -> 0 | G29: =+'Bank Liabilities Analysis'!K28-'Bank Liabilities Analysis'!L28 -> 0 | H29: =+'Bank Liabilities Analysis'!M28-'Bank Liabilities Analysis'!N28 -> 0 | I29: =+'Bank Liabilities Analysis'!O28-'Bank Liabilities Analysis'!P28 -> 0 | J29: =+'Bank Liabilities Analysis'!Q28-'Bank Liabilities Analysis'!R28 -> 0 | K29: =+C29+D29+E29+F29+G29+H29+I29+J29 -> 0 | L29: 1 | M29: =(C29+D29+E29)*L29 -> 0
A30: 4. | B30: Управленческие чеки | C30: =+'Bank Liabilities Analysis'!C29-'Bank Liabilities Analysis'!D29 -> 0 | D30: =+'Bank Liabilities Analysis'!E29-'Bank Liabilities Analysis'!F29 -> 0 | E30: =+'Bank Liabilities Analysis'!G29-'Bank Liabilities Analysis'!H29 -> 0 | F30: =+'Bank Liabilities Analysis'!I29-'Bank Liabilities Analysis'!J29 -> 0 | G30: =+'Bank Liabilities Analysis'!K29-'Bank Liabilities Analysis'!L29 -> 0 | H30: =+'Bank Liabilities Analysis'!M29-'Bank Liabilities Analysis'!N29 -> 0 | I30: =+'Bank Liabilities Analysis'!O29-'Bank Liabilities Analysis'!P29 -> 0 | J30: =+'Bank Liabilities Analysis'!Q29-'Bank Liabilities Analysis'!R29 -> 0 | K30: =+C30+D30+E30+F30+G30+H30+I30+J30 -> 0 | L30: 1 | M30: =(C30+D30+E30)*L30 -> 0
A31: 5. | B31: Непогашенные акцепты, выполненные банком или по поручению этого банка | C31: =+'Bank Liabilities Analysis'!C30-'Bank Liabilities Analysis'!D30 -> 0 | D31: =+'Bank Liabilities Analysis'!E30-'Bank Liabilities Analysis'!F30 -> 0 | E31: =+'Bank Liabilities Analysis'!G30-'Bank Liabilities Analysis'!H30 -> 0 | F31: =+'Bank Liabilities Analysis'!I30-'Bank Liabilities Analysis'!J30 -> 0 | G31: =+'Bank Liabilities Analysis'!K30-'Bank Liabilities Analysis'!L30 -> 0 | H31: =+'Bank Liabilities Analysis'!M30-'Bank Liabilities Analysis'!N30 -> 0 | I31: =+'Bank Liabilities Analysis'!O30-'Bank Liabilities Analysis'!P30 -> 0 | J31: =+'Bank Liabilities Analysis'!Q30-'Bank Liabilities Analysis'!R30 -> 0 | K31: =+C31+D31+E31+F31+G31+H31+I31+J31 -> 0 | L31: 1 | M31: =(C31+D31+E31)*L31 -> 0
A32: 6. | B32: Кредиты и лизинговые операции к оплате | C32: =+'Bank Liabilities Analysis'!C31-'Bank Liabilities Analysis'!D31 -> 0 | D32: =+'Bank Liabilities Analysis'!E31-'Bank Liabilities Analysis'!F31 -> 200000 | E32: =+'Bank Liabilities Analysis'!G31-'Bank Liabilities Analysis'!H31 -> 155061 | F32: =+'Bank Liabilities Analysis'!I31-'Bank Liabilities Analysis'!J31 -> 310121 | G32: =+'Bank Liabilities Analysis'!K31-'Bank Liabilities Analysis'!L31 -> 568877 | H32: =+'Bank Liabilities Analysis'!M31-'Bank Liabilities Analysis'!N31 -> 53484598 | I32: =+'Bank Liabilities Analysis'!O31-'Bank Liabilities Analysis'!P31 -> 23069301 | J32: =+'Bank Liabilities Analysis'!Q31-'Bank Liabilities Analysis'!R31 -> 269736162 | K32: =+C32+D32+E32+F32+G32+H32+I32+J32 -> 347524120 | L32: 0.05 | M32: =+K32*L32 -> 17376206
A33: 7. | B33: Выпущенные банком ценные бумаги | C33: =+'Bank Liabilities Analysis'!C32-'Bank Liabilities Analysis'!D32 -> 0 | D33: =+'Bank Liabilities Analysis'!E32-'Bank Liabilities Analysis'!F32 -> 0 | E33: =+'Bank Liabilities Analysis'!G32-'Bank Liabilities Analysis'!H32 -> 0 | F33: =+'Bank Liabilities Analysis'!I32-'Bank Liabilities Analysis'!J32 -> 0 | G33: =+'Bank Liabilities Analysis'!K32-'Bank Liabilities Analysis'!L32 -> 0 | H33: =+'Bank Liabilities Analysis'!M32-'Bank Liabilities Analysis'!N32 -> 0 | I33: =+'Bank Liabilities Analysis'!O32-'Bank Liabilities Analysis'!P32 -> 0 | J33: =+'Bank Liabilities Analysis'!Q32-'Bank Liabilities Analysis'!R32 -> 0 | K33: =+C33+D33+E33+F33+G33+H33+I33+J33 -> 0 | L33: 1 | M33: =(C33+D33+E33)*L33 -> 0
A34: 7a. | B34: Субординированные долговые обязательства | C34: =+'Bank Liabilities Analysis'!C33-'Bank Liabilities Analysis'!D33 -> 0 | D34: =+'Bank Liabilities Analysis'!E33-'Bank Liabilities Analysis'!F33 -> 0 | E34: =+'Bank Liabilities Analysis'!G33-'Bank Liabilities Analysis'!H33 -> 0 | F34: =+'Bank Liabilities Analysis'!I33-'Bank Liabilities Analysis'!J33 -> 0 | G34: =+'Bank Liabilities Analysis'!K33-'Bank Liabilities Analysis'!L33 -> 0 | H34: =+'Bank Liabilities Analysis'!M33-'Bank Liabilities Analysis'!N33 -> 0 | I34: =+'Bank Liabilities Analysis'!O33-'Bank Liabilities Analysis'!P33 -> 0 | J34: =+'Bank Liabilities Analysis'!Q33-'Bank Liabilities Analysis'!R33 -> 0 | K34: =+C34+D34+E34+F34+G34+H34+I34+J34 -> 0 | L34: 1 | M34: =(C34+D34+E34)*L34 -> 0
A35: 8. | B35: Ценные бумаги проданные по соглашению с последующим выкупом | C35: =+'Bank Liabilities Analysis'!C34-'Bank Liabilities Analysis'!D34 -> 0 | D35: =+'Bank Liabilities Analysis'!E34-'Bank Liabilities Analysis'!F34 -> 0 | E35: =+'Bank Liabilities Analysis'!G34-'Bank Liabilities Analysis'!H34 -> 54648356 | F35: =+'Bank Liabilities Analysis'!I34-'Bank Liabilities Analysis'!J34 -> 364556318 | G35: =+'Bank Liabilities Analysis'!K34-'Bank Liabilities Analysis'!L34 -> 0 | H35: =+'Bank Liabilities Analysis'!M34-'Bank Liabilities Analysis'!N34 -> 0 | I35: =+'Bank Liabilities Analysis'!O34-'Bank Liabilities Analysis'!P34 -> 0 | J35: =+'Bank Liabilities Analysis'!Q34-'Bank Liabilities Analysis'!R34 -> 0 | K35: =+C35+D35+E35+F35+G35+H35+I35+J35 -> 419204674 | L35: 1 | M35: =(C35+D35+E35)*L35 -> 54648356
A36: 9. | B36: Нереализованная прибыль или убытки по форвардным сделкам и другим отсроченным кредитам | C36: =+'Bank Liabilities Analysis'!C35-'Bank Liabilities Analysis'!D35 -> 0 | D36: =+'Bank Liabilities Analysis'!E35-'Bank Liabilities Analysis'!F35 -> 0 | E36: =+'Bank Liabilities Analysis'!G35-'Bank Liabilities Analysis'!H35 -> 0 | F36: =+'Bank Liabilities Analysis'!I35-'Bank Liabilities Analysis'!J35 -> 0 | G36: =+'Bank Liabilities Analysis'!K35-'Bank Liabilities Analysis'!L35 -> 0 | H36: =+'Bank Liabilities Analysis'!M35-'Bank Liabilities Analysis'!N35 -> 0 | I36: =+'Bank Liabilities Analysis'!O35-'Bank Liabilities Analysis'!P35 -> 0 | J36: =+'Bank Liabilities Analysis'!Q35-'Bank Liabilities Analysis'!R35 -> 0 | K36: =+C36+D36+E36+F36+G36+H36+I36+J36 -> 0 | L36: 1 | M36: =+K36*L36 -> 0
A37: 10. | B37: Клиринговые счета - кредитовый остаток | C37: =+'Bank Liabilities Analysis'!C36-'Bank Liabilities Analysis'!D36 -> 111880 | D37: =+'Bank Liabilities Analysis'!E36-'Bank Liabilities Analysis'!F36 -> 152 | E37: =+'Bank Liabilities Analysis'!G36-'Bank Liabilities Analysis'!H36 -> 0 | F37: =+'Bank Liabilities Analysis'!I36-'Bank Liabilities Analysis'!J36 -> 0 | G37: =+'Bank Liabilities Analysis'!K36-'Bank Liabilities Analysis'!L36 -> 0 | H37: =+'Bank Liabilities Analysis'!M36-'Bank Liabilities Analysis'!N36 -> 0 | I37: =+'Bank Liabilities Analysis'!O36-'Bank Liabilities Analysis'!P36 -> 0 | J37: =+'Bank Liabilities Analysis'!Q36-'Bank Liabilities Analysis'!R36 -> 0 | K37: =+C37+D37+E37+F37+G37+H37+I37+J37 -> 112032 | L37: 1 | M37: =+K37*L37 -> 112032
A38: 11. | B38: Начисленные проценты | C38: =+'Bank Liabilities Analysis'!C37-'Bank Liabilities Analysis'!D37 -> 11201747 | D38: =+'Bank Liabilities Analysis'!E37-'Bank Liabilities Analysis'!F37 -> 15511 | E38: =+'Bank Liabilities Analysis'!G37-'Bank Liabilities Analysis'!H37 -> 5733 | F38: =+'Bank Liabilities Analysis'!I37-'Bank Liabilities Analysis'!J37 -> 769545 | G38: =+'Bank Liabilities Analysis'!K37-'Bank Liabilities Analysis'!L37 -> 681976 | H38: =+'Bank Liabilities Analysis'!M37-'Bank Liabilities Analysis'!N37 -> 2771974 | I38: =+'Bank Liabilities Analysis'!O37-'Bank Liabilities Analysis'!P37 -> 1274849 | J38: =+'Bank Liabilities Analysis'!Q37-'Bank Liabilities Analysis'!R37 -> 1115529 | K38: =+C38+D38+E38+F38+G38+H38+I38+J38 -> 17836864 | M38: =C38+D38+E38+((F38+G38+H38+I38+J38)*15%) -> 12215072
A39: 12. | B39: Другие обязательства | C39: =+'Bank Liabilities Analysis'!C38-'Bank Liabilities Analysis'!D38 -> 68475186 | D39: =+'Bank Liabilities Analysis'!E38-'Bank Liabilities Analysis'!F38 -> 13830063 | E39: =+'Bank Liabilities Analysis'!G38-'Bank Liabilities Analysis'!H38 -> 17557 | F39: =+'Bank Liabilities Analysis'!I38-'Bank Liabilities Analysis'!J38 -> 65937 | G39: =+'Bank Liabilities Analysis'!K38-'Bank Liabilities Analysis'!L38 -> 82778 | H39: =+'Bank Liabilities Analysis'!M38-'Bank Liabilities Analysis'!N38 -> 477421 | I39: =+'Bank Liabilities Analysis'!O38-'Bank Liabilities Analysis'!P38 -> 1087544 | J39: =+'Bank Liabilities Analysis'!Q38-'Bank Liabilities Analysis'!R38 -> 1953226 | K39: =+C39+D39+E39+F39+G39+H39+I39+J39 -> 85989712 | L39: 1 | M39: =+K39*L39 -> 85989712
A40: 13. | B40: ИТОГО ОБЯЗАТЕЛЬСТВ | C40: =+C23+C30+C31+C32+C33+C34+C35+C36+C37+C38+C39+C24+C25 -> 1771074800 | D40: =+D23+D30+D31+D32+D33+D34+D35+D36+D37+D38+D39+D24+D25 -> 326600700 | E40: =+E23+E30+E31+E32+E33+E34+E35+E36+E37+E38+E39+E24+E25 -> 186404401 | F40: =+F23+F30+F31+F32+F33+F34+F35+F36+F37+F38+F39+F24+F25 -> 885233924 | G40: =+G23+G30+G31+G32+G33+G34+G35+G36+G37+G38+G39+G24+G25 -> 610889818 | H40: =+H23+H30+H31+H32+H33+H34+H35+H36+H37+H38+H39+H24+H25 -> 712446593 | I40: =+I23+I30+I31+I32+I33+I34+I35+I36+I37+I38+I39+I24+I25 -> 899174851 | J40: =+J23+J30+J31+J32+J33+J34+J35+J36+J37+J38+J39+J24+J25 -> 643771064 | K40: =+K23+K30+K31+K32+K33+K34+K35+K36+K37+K38+K39+K24+K25 -> 6035596151 | L40: отток | M40: =SUM(M9:M39) -> 9.0035814e+08 | N40: =+Balance!D62 -> 6035596151
B41: из них, обязательства перед: | K41: =+C41+D41+E41+F41+G41+H41+I41+J41 -> 0 | N41: =+Balance!C63 -> 0
B42: Министерство Финансов Республики Узбекистан, из них | C42: =+C43+C44 -> 255916 | D42: =+D43+D44 -> 305200000 | E42: =+E43+E44 -> 100000000 | F42: =+F43+F44 -> 0 | G42: =+G43+G44 -> 485500000 | H42: =+H43+H44 -> 360000000 | I42: =+I43+I44 -> 0 | J42: =+J43+J44 -> 39393000 | K42: =+C42+D42+E42+F42+G42+H42+I42+J42 -> 1290348916
B43: Кредиты и лизинги | C43: =+'Bank Liabilities Analysis'!C42-'Bank Liabilities Analysis'!D42 -> 0 | D43: =+'Bank Liabilities Analysis'!E42-'Bank Liabilities Analysis'!F42 -> 200000 | E43: =+'Bank Liabilities Analysis'!G42-'Bank Liabilities Analysis'!H42 -> 0 | F43: =+'Bank Liabilities Analysis'!I42-'Bank Liabilities Analysis'!J42 -> 0 | G43: =+'Bank Liabilities Analysis'!K42-'Bank Liabilities Analysis'!L42 -> 0 | H43: =+'Bank Liabilities Analysis'!M42-'Bank Liabilities Analysis'!N42 -> 0 | I43: =+'Bank Liabilities Analysis'!O42-'Bank Liabilities Analysis'!P42 -> 0 | J43: =+'Bank Liabilities Analysis'!Q42-'Bank Liabilities Analysis'!R42 -> 38593000 | K43: =+C43+D43+E43+F43+G43+H43+I43+J43 -> 38793000
B44: Депозитные ресурсы | C44: =+'Bank Liabilities Analysis'!C43-'Bank Liabilities Analysis'!D43 -> 255916 | D44: =+'Bank Liabilities Analysis'!E43-'Bank Liabilities Analysis'!F43 -> 305000000 | E44: =+'Bank Liabilities Analysis'!G43-'Bank Liabilities Analysis'!H43 -> 100000000 | F44: =+'Bank Liabilities Analysis'!I43-'Bank Liabilities Analysis'!J43 -> 0 | G44: =+'Bank Liabilities Analysis'!K43-'Bank Liabilities Analysis'!L43 -> 485500000 | H44: =+'Bank Liabilities Analysis'!M43-'Bank Liabilities Analysis'!N43 -> 360000000 | I44: =+'Bank Liabilities Analysis'!O43-'Bank Liabilities Analysis'!P43 -> 0 | J44: =+'Bank Liabilities Analysis'!Q43-'Bank Liabilities Analysis'!R43 -> 800000 | K44: =+C44+D44+E44+F44+G44+H44+I44+J44 -> 1251555916
B45: Внебюджетные фонды, из них | C45: =+C46+C47 -> 0 | D45: =+D46+D47 -> 0 | E45: =+E46+E47 -> 0 | F45: =+F46+F47 -> 0 | G45: =+G46+G47 -> 0 | H45: =+H46+H47 -> 0 | I45: =+I46+I47 -> 0 | J45: =+J46+J47 -> 0 | K45: =+C45+D45+E45+F45+G45+H45+I45+J45 -> 0
B46: Кредиты и лизинги | C46: =+'Bank Liabilities Analysis'!C45-'Bank Liabilities Analysis'!D45 -> 0 | D46: =+'Bank Liabilities Analysis'!E45-'Bank Liabilities Analysis'!F45 -> 0 | E46: =+'Bank Liabilities Analysis'!G45-'Bank Liabilities Analysis'!H45 -> 0 | F46: =+'Bank Liabilities Analysis'!I45-'Bank Liabilities Analysis'!J45 -> 0 | G46: =+'Bank Liabilities Analysis'!K45-'Bank Liabilities Analysis'!L45 -> 0 | H46: =+'Bank Liabilities Analysis'!M45-'Bank Liabilities Analysis'!N45 -> 0 | I46: =+'Bank Liabilities Analysis'!O45-'Bank Liabilities Analysis'!P45 -> 0 | J46: =+'Bank Liabilities Analysis'!Q45-'Bank Liabilities Analysis'!R45 -> 0 | K46: =+C46+D46+E46+F46+G46+H46+I46+J46 -> 0
B47: Депозитные ресурсы | C47: =+'Bank Liabilities Analysis'!C46-'Bank Liabilities Analysis'!D46 -> 0 | D47: =+'Bank Liabilities Analysis'!E46-'Bank Liabilities Analysis'!F46 -> 0 | E47: =+'Bank Liabilities Analysis'!G46-'Bank Liabilities Analysis'!H46 -> 0 | F47: =+'Bank Liabilities Analysis'!I46-'Bank Liabilities Analysis'!J46 -> 0 | G47: =+'Bank Liabilities Analysis'!K46-'Bank Liabilities Analysis'!L46 -> 0 | H47: =+'Bank Liabilities Analysis'!M46-'Bank Liabilities Analysis'!N46 -> 0 | I47: =+'Bank Liabilities Analysis'!O46-'Bank Liabilities Analysis'!P46 -> 0 | J47: =+'Bank Liabilities Analysis'!Q46-'Bank Liabilities Analysis'!R46 -> 0 | K47: =+C47+D47+E47+F47+G47+H47+I47+J47 -> 0
B48: Фонд реконструкции и развития Узбекистана (ФРРУ) , из них | C48: =+C49+C50 -> 0 | D48: =+D49+D50 -> 0 | E48: =+E49+E50 -> 0 | F48: =+F49+F50 -> 0 | G48: =+G49+G50 -> 0 | H48: =+H49+H50 -> 0 | I48: =+I49+I50 -> 0 | J48: =+J49+J50 -> 0 | K48: =+C48+D48+E48+F48+G48+H48+I48+J48 -> 0
B49: Кредиты и лизинги | C49: =+'Bank Liabilities Analysis'!C48-'Bank Liabilities Analysis'!D48 -> 0 | D49: =+'Bank Liabilities Analysis'!E48-'Bank Liabilities Analysis'!F48 -> 0 | E49: =+'Bank Liabilities Analysis'!G48-'Bank Liabilities Analysis'!H48 -> 0 | F49: =+'Bank Liabilities Analysis'!I48-'Bank Liabilities Analysis'!J48 -> 0 | G49: =+'Bank Liabilities Analysis'!K48-'Bank Liabilities Analysis'!L48 -> 0 | H49: =+'Bank Liabilities Analysis'!M48-'Bank Liabilities Analysis'!N48 -> 0 | I49: =+'Bank Liabilities Analysis'!O48-'Bank Liabilities Analysis'!P48 -> 0 | J49: =+'Bank Liabilities Analysis'!Q48-'Bank Liabilities Analysis'!R48 -> 0 | K49: =+C49+D49+E49+F49+G49+H49+I49+J49 -> 0
B50: Депозитные ресурсы | C50: =+'Bank Liabilities Analysis'!C49-'Bank Liabilities Analysis'!D49 -> 0 | D50: =+'Bank Liabilities Analysis'!E49-'Bank Liabilities Analysis'!F49 -> 0 | E50: =+'Bank Liabilities Analysis'!G49-'Bank Liabilities Analysis'!H49 -> 0 | F50: =+'Bank Liabilities Analysis'!I49-'Bank Liabilities Analysis'!J49 -> 0 | G50: =+'Bank Liabilities Analysis'!K49-'Bank Liabilities Analysis'!L49 -> 0 | H50: =+'Bank Liabilities Analysis'!M49-'Bank Liabilities Analysis'!N49 -> 0 | I50: =+'Bank Liabilities Analysis'!O49-'Bank Liabilities Analysis'!P49 -> 0 | J50: =+'Bank Liabilities Analysis'!Q49-'Bank Liabilities Analysis'!R49 -> 0 | K50: =+C50+D50+E50+F50+G50+H50+I50+J50 -> 0
B51: Зарубежные банки, из них | C51: =+C52+C53 -> 0 | D51: =+D52+D53 -> 0 | E51: =+E52+E53 -> 0 | F51: =+F52+F53 -> 0 | G51: =+G52+G53 -> 0 | H51: =+H52+H53 -> 0 | I51: =+I52+I53 -> 0 | J51: =+J52+J53 -> 0 | K51: =+C51+D51+E51+F51+G51+H51+I51+J51 -> 0
B52: Кредиты и лизинги | C52: =+'Bank Liabilities Analysis'!C51-'Bank Liabilities Analysis'!D51 -> 0 | D52: =+'Bank Liabilities Analysis'!E51-'Bank Liabilities Analysis'!F51 -> 0 | E52: =+'Bank Liabilities Analysis'!G51-'Bank Liabilities Analysis'!H51 -> 0 | F52: =+'Bank Liabilities Analysis'!I51-'Bank Liabilities Analysis'!J51 -> 0 | G52: =+'Bank Liabilities Analysis'!K51-'Bank Liabilities Analysis'!L51 -> 0 | H52: =+'Bank Liabilities Analysis'!M51-'Bank Liabilities Analysis'!N51 -> 0 | I52: =+'Bank Liabilities Analysis'!O51-'Bank Liabilities Analysis'!P51 -> 0 | J52: =+'Bank Liabilities Analysis'!Q51-'Bank Liabilities Analysis'!R51 -> 0 | K52: =+C52+D52+E52+F52+G52+H52+I52+J52 -> 0
B53: Депозитные ресурсы | C53: =+'Bank Liabilities Analysis'!C52-'Bank Liabilities Analysis'!D52 -> 0 | D53: =+'Bank Liabilities Analysis'!E52-'Bank Liabilities Analysis'!F52 -> 0 | E53: =+'Bank Liabilities Analysis'!G52-'Bank Liabilities Analysis'!H52 -> 0 | F53: =+'Bank Liabilities Analysis'!I52-'Bank Liabilities Analysis'!J52 -> 0 | G53: =+'Bank Liabilities Analysis'!K52-'Bank Liabilities Analysis'!L52 -> 0 | H53: =+'Bank Liabilities Analysis'!M52-'Bank Liabilities Analysis'!N52 -> 0 | I53: =+'Bank Liabilities Analysis'!O52-'Bank Liabilities Analysis'!P52 -> 0 | J53: =+'Bank Liabilities Analysis'!Q52-'Bank Liabilities Analysis'!R52 -> 0 | K53: =+C53+D53+E53+F53+G53+H53+I53+J53 -> 0
B54: Другие зарубежные финансовые организации, из них | C54: =+C55+C56 -> 0 | D54: =+D55+D56 -> 0 | E54: =+E55+E56 -> 0 | F54: =+F55+F56 -> 0 | G54: =+G55+G56 -> 0 | H54: =+H55+H56 -> 51578100 | I54: =+I55+I56 -> 0 | J54: =+J55+J56 -> 0 | K54: =+C54+D54+E54+F54+G54+H54+I54+J54 -> 51578100
B55: Кредиты и лизинги | C55: =+'Bank Liabilities Analysis'!C54-'Bank Liabilities Analysis'!D54 -> 0 | D55: =+'Bank Liabilities Analysis'!E54-'Bank Liabilities Analysis'!F54 -> 0 | E55: =+'Bank Liabilities Analysis'!G54-'Bank Liabilities Analysis'!H54 -> 0 | F55: =+'Bank Liabilities Analysis'!I54-'Bank Liabilities Analysis'!J54 -> 0 | G55: =+'Bank Liabilities Analysis'!K54-'Bank Liabilities Analysis'!L54 -> 0 | H55: =+'Bank Liabilities Analysis'!M54-'Bank Liabilities Analysis'!N54 -> 51578100 | I55: =+'Bank Liabilities Analysis'!O54-'Bank Liabilities Analysis'!P54 -> 0 | J55: =+'Bank Liabilities Analysis'!Q54-'Bank Liabilities Analysis'!R54 -> 0 | K55: =+C55+D55+E55+F55+G55+H55+I55+J55 -> 51578100
B56: Депозитные ресурсы | C56: =+'Bank Liabilities Analysis'!C55-'Bank Liabilities Analysis'!D55 -> 0 | D56: =+'Bank Liabilities Analysis'!E55-'Bank Liabilities Analysis'!F55 -> 0 | E56: =+'Bank Liabilities Analysis'!G55-'Bank Liabilities Analysis'!H55 -> 0 | F56: =+'Bank Liabilities Analysis'!I55-'Bank Liabilities Analysis'!J55 -> 0 | G56: =+'Bank Liabilities Analysis'!K55-'Bank Liabilities Analysis'!L55 -> 0 | H56: =+'Bank Liabilities Analysis'!M55-'Bank Liabilities Analysis'!N55 -> 0 | I56: =+'Bank Liabilities Analysis'!O55-'Bank Liabilities Analysis'!P55 -> 0 | J56: =+'Bank Liabilities Analysis'!Q55-'Bank Liabilities Analysis'!R55 -> 0 | K56: =+C56+D56+E56+F56+G56+H56+I56+J56 -> 0
B58: Подпись Председателя правления:
B60: Подпись Главного Бухгалтера:

Sheet Commitments
A1: ОТЧЕТ О СЧЕТАХ ОБЯЗАТЕЛЬСТВ И НЕПРЕДВИДЕННЫХ ОБСТОЯТЕЛЬСТВ | E1: Таблица-19
B2: =Balance!B3 -> АК "АЛОКАБАНК" | C2: =+Balance!B2 -> 31 Декабрь, 2021 | E2: =+Balance!E3 -> тыс. сум
A3: № | B3: Категории | C3: Итого | D3: в национальной валюте | E3: в иностранной валюте (в экв. в сумах)
A4: 1. | B4: Обязательства по выдачи кредитов | C4: =+D4+E4 -> 724661970 | D4: 549477519 | E4: 175184451
A5: 1.1. | B5: в том числе, за счет кредитных линий (с особыми условиями) | C5: =+D5+E5 -> 11998262 | D5: 3081158 | E5: 8917104
A7: 2. | B7: Гарантии и поручительства | C7: =+D7+E7 -> 243690220 | D7: 3031573 | E7: 240658647
A8: 2.1. | B8: в том числе, обеспеченные депозитами | C8: =+D8+E8 -> 0 | D8: 0 | E8: 0
A10: 3. | B10: Итого аккредитивы | C10: =+D10+E10 -> 573749357 | D10: =SUM(D11:D14) -> 0 | E10: =SUM(E11:E14) -> 573749357
A11: 3.1. | B11: Покрытый аккредитив, открытый в банках плательщиком | C11: =+D11+E11 -> 22833631 | D11: 0 | E11: 22833631
A12: 3.2. | B12: Непогашенные аккредитивы на импорт с оплатой тратт на предъявителя | C12: =+D12+E12 -> 16326927 | D12: 0 | E12: 16326927
A13: 3.3. | B13: Непогашенные аккредитивы на импорт против выставления срочных тратт | C13: =+D13+E13 -> 0 | D13: 0
A14: 3.4. | B14: Другие аккредитивы | C14: =+D14+E14 -> 534588799 | D14: 0 | E14: 534588799
A16: 4. | B16: Факторинг, инкассо и другие торговые финансирование | C16: =+D16+E16 -> 0 | D16: 0 | E16: 0
A18: 5. | B18: Итого других статей непредвиденных обстоятельств | C18: =+D18+E18 -> 951829282 | D18: =SUM(D19:D23) -> 627582989 | E18: =SUM(E19:E23) -> 324246293
A19: 5.1. | B19: Условная стоимость процентного свопа | C19: =+D19+E19 -> 0 | D19: 0 | E19: 0
A20: 5.2. | B20: Условная стоимость обменного свопа (Валютный своп) | C20: =+D20+E20 -> 369490971 | D20: 184370440 | E20: 185120531
A21: 5.3. | B21: Фьючерсные, Форвардные и Опционные контракты | C21: =+D21+E21 -> 0
A22: 5.4. | B22: Обязательства по покупке кредитов, ценных бумаг или других активов | C22: =+D22+E22 -> 418105000 | D22: 418105000
A23: 5.5. | B23: Другие счета непредвиденных обстоятельств | C23: =+D23+E23 -> 164233311 | D23: 25107549 | E23: 139125762
A25: 6. | B25: Итого статей непредвиденных обстоятельств | C25: =+C4+C7+C10+C16+C18 -> 2493930829 | D25: =+D4+D7+D10+D16+D18 -> 1180092081 | E25: =+E4+E7+E10+E16+E18 -> 1313838748
B28: Подпись Председателя правления:
B30: Подпись Главного Бухгалтера:

Sheet Deposits by Client
A1: ОТЧЕТ О ДЕПОЗИТАХ ПО ТИПАМ КЛИЕНТОВ | D1: Таблица-14
B2: =+Balance!B3 -> АК "АЛОКАБАНК" | C2: =+Balance!B2 -> 31 Декабрь, 2021 | D2: в тыс. сум
A3: № | B3: Категории | C3: Итого | D3: из них, в иностранной валюте (в экв. в сумах)
A4: 1. | B4: Депозиты до востребования
A5: а. | B5: Правительство | C5: 84005450 | D5: 6507488
A6: б. | B6: Физические лица | C6: 468677597 | D6: 70504468
A7: в. | B7: Государственные предприятия | C7: 366724772 | D7: 72976974
A8: г. | B8: Совместные и иностранные предприятия | C8: 97364394 | D8: 10806486
A9: д. | B9: Частные товарищества и корпорации | C9: 702461055 | D9: 41011156
A10: е. | B10: Другие депозиты до востребования | C10: 317693110 | D10: 152281308
A11: ж. | B11: Итого депозитов до востребования | C11: =SUM(C5:C10) -> 2036926378 | D11: =SUM(D5:D10) -> 354087880 | E11: =+'Bank Liabilities Analysis'!S16+'Bank Liabilities Analysis'!S8 -> 2036926378 | F11: =+'Bank Liabilities Analysis'!T16+'Bank Liabilities Analysis'!T8 -> 1682838498 | G11: =+'Bank Liabilities Analysis'!U16+'Bank Liabilities Analysis'!U8 -> 354087880
A13: 2. | B13: Срочные депозиты
A14: а. | B14: Правительство | C14: 2470819201 | D14: 628584280
A15: б. | B15: Физические лица | C15: 440584422 | D15: 28130995
A16: в. | B16: Государственные предприятия | C16: 229197322 | D16: 41183108
A17: г. | B17: Совместные и иностранные предприятия | C17: 9818830 | D17: 5418830
A18: д. | B18: Частные товарищества и корпорации | C18: 367985246 | D18: 13102731
A19: е. | B19: Другие cрочные депозиты | C19: 1240777784 | D19: 973806219
A20: ж. | B20: Итого срочных депозитов | C20: =SUM(C14:C19) -> 4759182805 | D20: =SUM(D14:D19) -> 1690226163 | E20: =+'Bank Liabilities Analysis'!S13 -> 4759182805 | F20: =+'Bank Liabilities Analysis'!T13 -> 3068956642 | G20: =+'Bank Liabilities Analysis'!U13 -> 1690226163
A22: 3. | B22: Итого депозитов | C22: =+C11+C20 -> 6796109183 | D22: =+D11+D20 -> 2044314043 | E22: =+'Bank Liabilities Analysis'!S22 -> 6796109183 | F22: =+'Bank Liabilities Analysis'!T22 -> 4751795140 | G22: =+'Bank Liabilities Analysis'!U22 -> 2044314043
B25: Подпись Председателя правления:
B27: Подпись Главного Бухгалтера:

Sheet Investment Securities
A1: ОТЧЕТ ОБ ИНВЕСТИЦИЯХ В ЦЕННЫЕ БУМАГИ И СЧЕТА КУПЛИ-ПРОДАЖИ АКТИВОВ | E1: Таблица-15
A2: =Balance!B3 -> АК "АЛОКАБАНК" | C2: =+Balance!B2 -> 31 Декабрь, 2021 | E2: =+Balance!E3 -> тыс. сум
A3: Часть 1 - Инвестиции в ценные бумаги | B3: Балансовая стоимость | C3: Балансовая стоимость | E3: Рыночная стоимость
C4: в национальной валюте | D4: в иностранной валюте (в экв. в сумах)
A6: 1. Инвестиции в государственные облигации | B6: =+C6+D6 -> 0 | C6: 0 | D6: 0 | E6: 0
A7: 2. Инвестиции в ценные бумаги и облигации ЦБРУ | B7: =+C7+D7 -> 0 | C7: 0 | D7: 0 | E7: 0
A8: 3. Инвестиции в частные облигации | B8: =+C8+D8 -> 0 | C8: 0 | D8: 0 | E8: 0
A9: 4. Инвестиции в еврооблигации | B9: =+C9+D9 -> 0 | C9: 0 | D9: 0 | E9: 0
A10: 5. Инвестиции в акции гос предприятий | B10: =+C10+D10 -> 49999997 | C10: 49999997 | D10: 0 | E10: 49999997
A11: 6. Инвестиции в акции частных предприятий | B11: =+C11+D11 -> 5603011 | C11: 5603011 | D11: 0 | E11: 5603011
A12: 7. Инвестиции в другие ценные бумаги | B12: =+C12+D12 -> 42736058 | C12: 42736058 | D12: 0 | E12: 42736058
A13: 8. Итого инвестиций | B13: =+C13+D13 -> 98339066 | C13: =SUM(C6:C12) -> 98339066 | D13: =SUM(D6:D12) -> 0 | E13: =SUM(E6:E12) -> 98339066
A14: 9. Минус: Резерв возможных убытков | B14: =+C14+D14 -> 0
A15: 10. Чистая балансовая стоимость инвестиций | B15: =+C15+D15 -> 98339066 | C15: =C13-C14 -> 98339066 | D15: =D13-D14 -> 0
A17: Часть 2 - Счета купли-продажи ценных бумаг | B17: Балансовая стоимость | C17: в национальной валюте | D17: в иностранной валюте (в экв. в сумах) | E17: Рыночная стоимость
A19: 1. Государственные казначейские векселя | B19: =+C19+D19 -> 0 | D19: 0 | E19: 0
A20: 2. Государственные облигации | B20: =+C20+D20 -> 20000000 | C20: 20000000 | E20: 20000000
A21: 3. Ценные бумаги и облигации ЦБРУ | B21: =+C21+D21 -> 398105000 | C21: 398105000 | E21: 398105000
A22: 4. Ценные бумаги гос корпораций | B22: =+C22+D22 -> 0 | D22: 0 | E22: 0
A23: 5. Еврооблигации | B23: =+C23+D23 -> 0 | C23: 0 | D23: 0 | E23: 0
A24: 6. Частные ценные бумаги | B24: =+C24+D24 -> 0 | C24: 0 | D24: 0 | E24: 0
A25: 7. Другие ценные бумаги | B25: =+C25+D25 -> 0 | D25: 0
A26: 8. Итого по счетам купли-продажи ценных бумаг | B26: =+C26+D26 -> 418105000 | C26: =SUM(C19:C25) -> 418105000 | D26: =SUM(D19:D25) -> 0 | E26: =SUM(E19:E25) -> 418105000
A27: 9. Дисконт и премии по ценным бумагам | B27: =+C27+D27 -> -8132565 | C27: -8132565 | E27: -8132565
A28: 10. Минус: Резерв возможных убытков | B28: =+C28+D28 -> 0 | C28: 0 | D28: 0
A29: 11. Чистая балансовая стоимость по счетам купли-продажи ц/б | B29: =+C29+D29 -> 409972435 | C29: =+C26+C27-C28 -> 409972435 | D29: =+D26+D27-D28 -> 0
A33: Часть 3 - Счета купли и продажи драгоценных металлов | B33: Первоначальная стоимость | C33: в национальной валюте | D33: в иностранной валюте (в экв. в сумах) | E33: Рыночная стоимость
A35: 1. Драгоценные металлы | B35: =+C35+D35 -> 0 | C35: 0 | D35: 0 | E35: 0
A36: 2. Драгоценные камни | B36: =+C36+D36 -> 0 | C36: 0 | D36: 0 | E36: 0
A37: 3. Драгоценные монеты | B37: =+C37+D37 -> 251 | C37: 251 | D37: 0 | E37: 251
A38: 4. Итого драгоценных металлов | B38: =+C38+D38 -> 251 | C38: =SUM(C35:C37) -> 251 | D38: =SUM(D35:D37) -> 0 | E38: =SUM(E35:E37) -> 251
A39: 5. Минус: Резерв возможных убытков | B39: =+C39+D39 -> 0
A40: 6. Чистая балансовая стоимость по счетам купли и продажи д/м | B40: =+C40+D40 -> 251 | C40: =C38-C39 -> 251 | D40: =D38-D39 -> 0
A42: Примечание:
A43: Итого ценных бумаг заложенных для общественных депозитов
A44: Портфель инвестиций в ценные бумаги
A45: Увеличение (Снижение) стоимости | B45: =E13-B13 -> 0
A46: Счета купли-продажи ценных бумаг
A47: Увеличение (Снижение) стоимости | B47: =E26-B26 -> 0
A48: Счета купли-продажи драгоценных предметов
A49: Увеличение (Снижение) стоимости | B49: =E38-B38 -> 0
A52: Подпись Председателя правления:
A54: Подпись Главного Бухгалтера:
