Workbook
Name jop: #REF!
Name kol: #REF!
Name RISKTOTASS: SUM('[6]Calculation of Risk Weighted As'!$C$38:$F$38)
Name RISKTOTASS: SUM('[7]Calculation of Risk Weighted As'!$C$41:$G$41)
Name TwentyLargestData: #REF!
Name Е: #REF!

Sheet Asset quality
A1: ИНФОРМАЦИЯ О КАЧЕСТВЕ АКТИВОВ, ОЦЕНИВАЕМЫХ В ЦЕЛЯХ СОЗДАНИЯ РЕЗЕРВА НА ВОЗМОЖНЫЕ ПОТЕРИ | R1: Таблица-2 | U1: №4
B3: АК "АЛОКАБАНК" | P3: 44561 | S3: тыс. сум
A4: № | B4: Состав активов* | C4: Остаток | D4: Категория качества | I4: Просроченная задолженность (брутто) | N4: Резерв на возможные потери
I5: итого | J5: до 30 дней | K5: от 31 до 90 дней | L5: от 91 до 180 дней | M5: свыше 180 дней | N5: фактически сформированный
N6: итого | O6: по категориям качества
D7: I | E7: II | F7: III | G7: IV | H7: V | O7: I | P7: II | Q7: III | R7: IV | S7: V
A8: А | B8: Б | C8: В | D8: Г | E8: Д | F8: Е | G8: Ж | H8: З | I8: И | J8: К | K8: Л | L8: М | M8: Н | N8: О | O8: П | P8: Р | Q8: С | R8: Т | S8: У
B9: ВСЕГО АКТИВОВ | C9: =SUM(C10:C60) -> 12638456623 | D9: =SUM(D10:D60) -> 11780546199 | E9: =SUM(E10:E60) -> 624369631 | F9: =SUM(F10:F60) -> 74161881 | G9: =SUM(G10:G60) -> 80999105 | H9: =SUM(H10:H60) -> 180403995 | I9: =SUM(I10:I60) -> 98862165 | J9: =SUM(J10:J60) -> 7405420 | ... S9: =SUM(S10:S60) -> 58343002
A10: 1 | B10: Кассовая наличность и другие платежные документы | C10: =SUM(D10:H10)-N10+O10 -> 275813889 | D10: 275813889 | E10: 0 | F10: 0 | G10: 0 | H10: 0 | I10: =SUM(J10:M10) -> 0 | J10: 0 | K10: 0 | L10: 0 | M10: 0 | N10: =SUM(O10:S10) -> 2382993 | O10: 2382993 | P10: 0 | Q10: 0 | R10: 0 | S10: 0 | T10: 10100
A11: 2 | B11: К получению из ЦБРУ | C11: =SUM(D11:H11)-N11+O11 -> 1238811513 | D11: 1238811513 | E11: 0 | F11: 0 | G11: 0 | H11: 0 | I11: =SUM(J11:M11) -> 0 | J11: 0 | K11: 0 | L11: 0 | M11: 0 | N11: =SUM(O11:S11) -> 10703156 | O11: 10703156 | P11: 0 | Q11: 0 | R11: 0 | S11: 0 | T11: 10300
A12: 3 | B12: К получению из других банков | C12: =SUM(D12:H12)-N12+O12 -> 901416758 | D12: 901416758 | E12: 0 | F12: 0 | G12: 0 | H12: 0 | I12: =SUM(J12:M12) -> 0 | J12: 0 | K12: 0 | L12: 0 | M12: 0 | N12: =SUM(O12:S12) -> 7788113 | O12: 7788113 | P12: 0 | Q12: 0 | R12: 0 | S12: 0 | T12: 10500
A13: 4 | B13: Ценные бумаги для купли и продажи | C13: =SUM(D13:H13)-N13+O13 -> 409972435 | D13: 409972435 | E13: 0 | F13: 0 | G13: 0 | H13: 0 | I13: =SUM(J13:M13) -> 0 | J13: 0 | K13: 0 | L13: 0 | M13: 0 | N13: =SUM(O13:S13) -> 3542104 | O13: 3542104 | P13: 0 | Q13: 0 | R13: 0 | S13: 0 | T13: 10700
A14: 5 | B14: Инвестиции в ценные бумаги, имеющиеся в наличии для продажи | C14: =SUM(D14:H14)-N14+O14 -> 0 | D14: 0 | E14: 0 | F14: 0 | G14: 0 | H14: 0 | I14: =SUM(J14:M14) -> 0 | J14: 0 | K14: 0 | L14: 0 | M14: 0 | N14: =SUM(O14:S14) -> 0 | O14: 0 | P14: 0 | Q14: 0 | R14: 0 | S14: 0 | T14: 10800
A15: 6 | B15: Драгоценные металлы, камни и монеты для купли и продажи | C15: =SUM(D15:H15)-N15+O15 -> 251 | D15: 251 | E15: 0 | F15: 0 | G15: 0 | H15: 0 | I15: =SUM(J15:M15) -> 0 | J15: 0 | K15: 0 | L15: 0 | M15: 0 | N15: =SUM(O15:S15) -> 2 | O15: 2 | P15: 0 | Q15: 0 | R15: 0 | S15: 0 | T15: 10900
A16: 7 | B16: Купленные дебиторские задолженности - Факторинг | C16: =SUM(D16:H16)-N16+O16 -> 0 | D16: 0 | E16: 0 | F16: 0 | G16: 0 | H16: 0 | I16: =SUM(J16:M16) -> 0 | J16: 0 | K16: 0 | L16: 0 | M16: 0 | N16: =SUM(O16:S16) -> 0 | O16: 0 | P16: 0 | Q16: 0 | R16: 0 | S16: 0 | T16: 11100
A17: 8 | B17: Купленные векселя | C17: =SUM(D17:H17)-N17+O17 -> 0 | D17: 0 | E17: 0 | F17: 0 | G17: 0 | H17: 0 | I17: =SUM(J17:M17) -> 0 | J17: 0 | K17: 0 | L17: 0 | M17: 0 | N17: =SUM(O17:S17) -> 0 | O17: 0 | P17: 0 | Q17: 0 | R17: 0 | S17: 0 | T17: 11300
A18: 9 | B18: Обязательства клиентов по траттам под аккредитив и/или трастовые документы | C18: =SUM(D18:H18)-N18+O18 -> 532887227 | D18: 533298096 | E18: 0 | F18: 0 | G18: 0 | H18: 0 | I18: =SUM(J18:M18) -> 0 | J18: 0 | K18: 0 | L18: 0 | M18: 0 | N18: =SUM(O18:S18) -> 5018489 | O18: 4607620 | P18: 410869 | Q18: 0 | R18: 0 | S18: 0 | T18: 11500
A19: 10 | B19: Обязательства лиентов по непогашенным акцептам банка | C19: =SUM(D19:H19)-N19+O19 -> 0 | D19: 0 | E19: 0 | F19: 0 | G19: 0 | H19: 0 | I19: =SUM(J19:M19) -> 0 | J19: 0 | K19: 0 | L19: 0 | M19: 0 | N19: =SUM(O19:S19) -> 0 | O19: 0 | P19: 0 | Q19: 0 | R19: 0 | S19: 0 | T19: 11700
A20: 11 | B20: Купленные по сделкам РЕПО ценные бумаги | C20: =SUM(D20:H20)-N20+O20 -> 0 | D20: 0 | E20: 0 | F20: 0 | G20: 0 | H20: 0 | I20: =SUM(J20:M20) -> 0 | J20: 0 | K20: 0 | L20: 0 | M20: 0 | N20: =SUM(O20:S20) -> 0 | O20: 0 | P20: 0 | Q20: 0 | R20: 0 | S20: 0 | T20: 11800
A21: 12 | B21: Краткосрочные кредиты, предоставленные ЦБРУ | C21: =SUM(D21:H21)-N21+O21 -> 0 | D21: 0 | E21: 0 | F21: 0 | G21: 0 | H21: 0 | I21: =SUM(J21:M21) -> 0 | J21: 0 | K21: 0 | L21: 0 | M21: 0 | N21: =SUM(O21:S21) -> 0 | O21: 0 | P21: 0 | Q21: 0 | R21: 0 | S21: 0 | T21: 11900
... A38: 29 | B38: Долгосрочные кредиты, предоставленные бюджетным организациям | C38: =SUM(D38:H38)-N38+O38 -> 0 | D38: 0 | E38: 0 | F38: 0 | G38: 0 | H38: 0 | I38: =SUM(J38:M38) -> 0 | J38: 0 | K38: 0 | L38: 0 | M38: 0 | N38: =SUM(O38:S38) -> 0 | O38: 0 | P38: 0 | Q38: 0 | R38: 0 | S38: 0 | T38: 14800
A39: 30 | B39: Долгосрочные кредиты, предоставленные физическим лицам | C39: =SUM(D39:H39)-N39+O39 -> 1248806200 | D39: =1179541171 -> 1179541171 | E39: 51636184 | F39: 12051203 | G39: 17851792 | H39: 31442317 | I39: =SUM(J39:M39) -> 0 | J39: 0 | K39: 0 | L39: 0 | M39: 0 | N39: =SUM(O39:S39) -> 53907536 | O39: 10191069 | P39: 4843416 | Q39: 2617679 | R39: 10173191 | S39: 26082181 | T39: 14900
A40: 31 | B40: Долгосрочные кредиты, предоставленные индивидуальным предпринимателям | C40: =SUM(D40:H40)-N40+O40 -> 70586477 | D40: 68153947 | E40: 3647182 | F40: 720146 | G40: 178333 | H40: 0 | I40: =SUM(J40:M40) -> 0 | J40: 0 | K40: 0 | L40: 0 | M40: 0 | N40: =SUM(O40:S40) -> 2701971 | O40: 588840 | P40: 349760 | Q40: 159157 | R40: 212474 | S40: 1391740 | T40: 15000
A41: 32 | B41: Долгосрочные кредиты, предоставленные государственным предприятиям, организациям и учреждениям | C41: =SUM(D41:H41)-N41+O41 -> 1005737506 | D41: 945738348 | E41: 59999158 | F41: 0 | G41: 0 | H41: 0 | I41: =SUM(J41:M41) -> 0 | J41: 0 | K41: 0 | L41: 0 | M41: 0 | N41: =SUM(O41:S41) -> 8171046 | O41: 8171046 | P41: 0 | Q41: 0 | R41: 0 | S41: 0 | T41: 15100
A42: 33 | B42: Долгосрочные кредиты, предоставленные негосударственным некоммерческим организациям | C42: =SUM(D42:H42)-N42+O42 -> 6455581 | D42: 1825554 | E42: 140812 | F42: 4069479 | G42: 706833 | H42: 4568220 | I42: =SUM(J42:M42) -> 0 | J42: 0 | K42: 0 | L42: 0 | M42: 0 | N42: =SUM(O42:S42) -> 4871090 | O42: 15773 | P42: 13315 | Q42: 85620 | R42: 194662 | S42: 4561720 | T42: 15200
A43: 34 | B43: Долгосрочные кредиты, предоставленные предприятиям с участием иностранного капитала | C43: =SUM(D43:H43)-N43+O43 -> 312868771 | D43: 313030551 | E43: 0 | F43: 0 | G43: 0 | H43: 0 | I43: =SUM(J43:M43) -> 0 | J43: 0 | K43: 0 | L43: 0 | M43: 0 | N43: =SUM(O43:S43) -> 2866320 | O43: 2704540 | P43: 0 | Q43: 161780 | R43: 0 | S43: 0 | T43: 15300
A44: 35 | B44: Долгосрочные кредиты, предоставленные небанковским финансовым институтам | C44: =SUM(D44:H44)-N44+O44 -> 17380000 | D44: 17380000 | E44: 0 | F44: 0 | G44: 0 | H44: 0 | I44: =SUM(J44:M44) -> 0 | J44: 0 | K44: 0 | L44: 0 | M44: 0 | N44: =SUM(O44:S44) -> 150161 | O44: 150161 | P44: 0 | Q44: 0 | R44: 0 | S44: 0 | T44: 15400
A45: 36 | B45: Долгосрочные кредиты, предоставленные частным предприятиям, хозяйственным товариществам и обществам | C45: =SUM(D45:H45)-N45+O45 -> 4020550690 | D45: 3398119655 | E45: 483794946 | F45: 33090604 | G45: 38841324 | H45: 100705647 | I45: =SUM(J45:M45) -> 0 | J45: 0 | K45: 0 | L45: 0 | M45: 0 | N45: =SUM(O45:S45) -> 63360759 | O45: 29359273 | P45: 14916144 | Q45: 3285403 | R45: 1101377 | S45: 14698562 | T45: 15500
A46: 37 | B46: Лизинг (Финансовая аренда) | C46: =SUM(D46:H46)-N46+O46 -> 305556 | D46: 305556 | E46: 0 | F46: 0 | G46: 0 | H46: 0 | I46: =SUM(J46:M46) -> 0 | J46: 0 | K46: 0 | L46: 0 | M46: 0 | N46: =SUM(O46:S46) -> 2640 | O46: 2640 | P46: 0 | Q46: 0 | R46: 0 | S46: 0 | T46: 15600
A47: 38 | B47: Кредиты и лизинг, находящиеся в процессе судебного разбирательства | C47: =SUM(D47:H47)-N47+O47 -> -1039 | D47: 0 | E47: 0 | F47: 0 | G47: 468212 | H47: 8113272 | I47: =SUM(J47:M47) -> 8581484 | J47: 0 | K47: 0 | L47: 642859 | M47: 7938625 | N47: =SUM(O47:S47) -> 8582523 | O47: 0 | P47: 0 | Q47: 0 | R47: 284106 | S47: 8298417 | T47: 15700
A48: 39 | B48: Инвестиции в зависимые хозяйственные общества, совместные предприятия и дочерние хозяйственные общества | C48: =SUM(D48:H48)-N48+O48 -> 98339066 | D48: 98339066 | E48: 0 | F48: 0 | G48: 0 | H48: 0 | I48: =SUM(J48:M48) -> 0 | J48: 0 | K48: 0 | L48: 0 | M48: 0 | N48: =SUM(O48:S48) -> 849636 | O48: 849636 | P48: 0 | Q48: 0 | R48: 0 | S48: 0 | T48: 15800
A49: 40 | B49: Инвестиции в долговые ценные бумаги, удерживаемые до погашения | C49: =SUM(D49:H49)-N49+O49 -> 0 | D49: 0 | E49: 0 | F49: 0 | G49: 0 | H49: 0 | I49: =SUM(J49:M49) -> 0 | J49: 0 | K49: 0 | L49: 0 | M49: 0 | N49: =SUM(O49:S49) -> 0 | O49: 0 | P49: 0 | Q49: 0 | R49: 0 | S49: 0 | T49: 15900
A50: 41 | B50: Начисленные проценты к получению | C50: =SUM(D50:H50)-N50+O50 -> 163425953 | D50: 142095308 | E50: 6876791 | F50: 1741342 | G50: 5526012 | H50: 7186500 | I50: =SUM(J50:M50) -> 0 | J50: 0 | K50: 0 | L50: 0 | M50: 0 | N50: =SUM(O50:S50) -> 1227683 | O50: 1227683 | P50: 0 | Q50: 0 | R50: 0 | S50: 0 | T50: 16300
A51: 42 | B51: Начисленные беспроцентные доходы к получению | C51: =SUM(D51:H51)-N51+O51 -> 34639224 | D51: 26977595 | E51: 883486 | F51: 744619 | G51: 1712066 | H51: 4321458 | I51: =SUM(J51:M51) -> 0 | J51: 0 | K51: 0 | L51: 0 | M51: 0 | N51: =SUM(O51:S51) -> 233083 | O51: 233083 | P51: 0 | Q51: 0 | R51: 0 | S51: 0 | T51: 16400
... A59: 50 | B59: Транзитные счета по средствам к списанию с пластиковых карт клиентов | C59: =SUM(D59:H59)-N59+O59 -> 71190523 | D59: 71190523 | E59: 0 | F59: 0 | G59: 0 | H59: 0 | I59: =SUM(J59:M59) -> 0 | J59: 0 | K59: 0 | L59: 0 | M59: 0 | N59: =SUM(O59:S59) -> 615076 | O59: 615076 | P59: 0 | Q59: 0 | R59: 0 | S59: 0 | T59: 17400
A60: 51 | B60: Другие активы | C60: =SUM(D60:H60)-N60+O60 -> 388680874 | D60: =389299851-2 -> 389299849 | E60: 0 | F60: 0 | G60: 0 | H60: 0 | I60: =SUM(J60:M60) -> 0 | J60: 0 | K60: 0 | L60: 0 | M60: 0 | N60: =SUM(O60:S60) -> 3982471 | O60: 3363496 | P60: 0 | Q60: 0 | R60: 0 | S60: 618975 | T60: 19900
B62: ЗАБАЛАНСОВЫЕ СТАТЬИ | C62: =SUM(D62:H62) -> 817439577 | D62: =SUM(D63:D64) -> 817439577 | E62: =SUM(E63:E64) -> 0 | F62: =SUM(F63:F64) -> 0 | G62: =SUM(G63:G64) -> 0 | H62: =SUM(H63:H64) -> 0 | I62: =SUM(J62:M62) -> 0 | J62: =SUM(J63:J64) -> 0 | K62: =SUM(K63:K64) -> 0 | L62: =SUM(L63:L64) -> 0 | M62: =SUM(M63:M64) -> 0 | N62: =SUM(N63:N64) -> 0 | O62: =SUM(O63:O64) -> 0 | P62: =SUM(P63:P64) -> 0 | Q62: =SUM(Q63:Q64) -> 0 | ... S62: =SUM(S63:S64) -> 0
A63: 1 | B63: Аккредитивы | C63: =SUM(D63:H63)-N63+O63 -> 573749357 | D63: 573749357 | I63: =SUM(J63:M63) -> 0 | N63: =SUM(O63:S63) -> 0 | T63: 90908-90958
A64: 2 | B64: Гарантии и поручетельства | C64: =SUM(D64:H64)-N64+O64 -> 243690220 | D64: 243690220 | I64: =SUM(J64:M64) -> 0 | N64: =SUM(O64:S64) -> 0 | T64: 90993
B67: Подпись Председателя правления:
B69: Подпись Главного Бухгалтера:
B71: Состав активов банка формируется в соответсвии с Планом счетов
C72: =+[8]Balance!$C$45 -> 12638456623

Sheet Income 
B1: ОТЧЕТ О ФИНАНСОВЫХ РЕЗУЛЬТАТАХ | D1: Таблица-3
B3: =+'Asset quality'!B3 -> АК "АЛОКАБАНК" | C3: =+'Asset quality'!P3 -> 44561 | E3: в тыс. сум
A4: № | B4: Категории | C4: Итого | D4: в национальной валюте | E4: в иностранной валюте (в экв. в сумах)
A5: 1. | B5: 1. ПРОЦЕНТНЫЕ ДОХОДЫ
A6: a. | B6: Процентные доходы по счетам в ЦБРУ | C6: =+D6+E6 -> 701232 | D6: 701232 | E6: 0
A7: б. | B7: Процентные доходы по счетам в других банках | C7: =+D7+E7 -> 15859918 | D7: 8925070 | E7: 6934848
A8: в. | B8: Процентные доходы по купленным векселям | C8: =+D8+E8 -> 0 | D8: 0 | E8: 0
A9: г. | B9: Процентные доходы по инвестициям | C9: =+D9+E9 -> 0 | D9: 0 | E9: 0
A10: д. | B10: Процентные доходы по счетам купли-продажи ценных бумаг | C10: =+D10+E10 -> 46951376 | D10: 46951376 | E10: 0
A11: е. | B11: Процентные доходы по обязательствам клиентов | C11: =+D11+E11 -> 0 | D11: 0 | E11: 0
A12: ж. | B12: Процентные доходы по обяз-вам клиентов по непогашенным акцептам этого банка | C12: =+D12+E12 -> 24017775 | D12: 26468 | E12: 23991307
A13: з. | B13: Процент, Дисконт (Скидки) и взносы по кредитным и лизинговым операциям | C13: =+D13+E13 -> 923550337 | D13: 751711404 | E13: 171838933
A14: и. | B14: Процентные доходы по соглашениям о покупке ценных бумаг с обратным выкупом | C14: =+D14+E14 -> 0 | D14: 0 | E14: 0
A15: к. | B15: Другие процентные доходы | C15: =+D15+E15 -> 195609379 | D15: 195609379 | E15: 0
A16: л. | B16: Итого процентных доходов | C16: =SUM(C6:C15) -> 1206690017 | D16: =SUM(D6:D15) -> 1003924929 | E16: =SUM(E6:E15) -> 202765088 | G16: =+'Analysis of Interest'!C42 -> 1206690017
A18: 2. | B18: ПРОЦЕНТНЫЕ РАСХОДЫ
A19: а. | B19: Процентные расходы по депозитам до востребования | C19: =+D19+E19 -> 4353573 | D19: 4265417 | E19: 88156
A20: б. | B20: Процентные расходы по срочным депозитам | C20: =+D20+E20 -> 394517794 | D20: 356025755 | E20: 38492039
A21: в. | B21: Процентные расходы по счетам к оплате в ЦБРУ | C21: =+D21+E21 -> 0 | D21: 0 | E21: 0
A22: г. | B22: Процентные расходы по счетам к оплате в другие банки | C22: =+D22+E22 -> 109768909 | D22: 88564625 | E22: 21204284
A23: д. | B23: Итого процентных расходов по депозитам | C23: =SUM(C19:C22) -> 508640276 | D23: =SUM(D19:D22) -> 448855797 | E23: =SUM(E19:E22) -> 59784479
A24: е. | B24: Процентные расходы по кредитам к оплате | C24: =+D24+E24 -> 67695285 | D24: 24323774 | E24: 43371511
A25: ж. | B25: Процентные расходы по соглашениям о продаже ц/б с последующим выкупом | C25: =+D25+E25 -> 8059008 | D25: 8059008 | E25: 0
A26: з. | B26: Другие процентные расходы | C26: =+D26+E26 -> 213913966 | D26: 163463770 | E26: 50450196
A27: и. | B27: Итого процентных расходов по займам | C27: =SUM(C24:C26) -> 289668259 | D27: =SUM(D24:D26) -> 195846552 | E27: =SUM(E24:E26) -> 93821707
A28: л. | B28: Итого процентных расходов | C28: =C27+C23 -> 798308535 | D28: =D27+D23 -> 644702349 | E28: =E27+E23 -> 153606186 | G28: =+'Analysis of Interest'!C72 -> 798308535
A30: 3. | B30: ЧИСТЫЕ ПРОЦЕНТНЫЕ ДОХОДЫ ДО ОЦЕНКИ ВОЗМОЖНЫХ УБЫТКОВ ПО АКТИВАМ | C30: =C16-C28 -> 408381482 | D30: =D16-D28 -> 359222580 | E30: =E16-E28 -> 49158902
A31: а. | B31: Минус: Оценка возможных убытков по кредитам и лизингу | C31: =+D31+E31 -> 119121377 | D31: 102654089 | E31: 16467288
A32: б. | B32: Минус: Оценка возможных убытков по в ценным бумагам | C32: =+D32+E32 -> 0 | D32: 0 | E32: 0
A33: в. | B33: Минус: Оценка возможных убытков по инвестициям | C33: =+D33+E33 -> 0 | D33: 0 | E33: 0
A34: г. | B34: Минус: Оценка возможных убытков по другим активам | C34: =+D34+E34 -> 1763430 | D34: 1357315 | E34: 406115
A35: д. | B35: Чистые процентные доходы после оценки возможных убытков по кредитам и лизингу | C35: =C30-C31-C32-C33-C34 -> 287496675 | D35: =D30-D31-D32-D33-D34 -> 255211176 | E35: =E30-E31-E32-E33-E34 -> 32285499
A37: 4. | B37: БЕСПРОЦЕНТНЫЕ ДОХОДЫ
A38: а. | B38: Доходы от комиссий и платы за услуги | C38: =+D38+E38 -> 271963488 | D38: 264439404 | E38: 7524084
A39: б. | B39: Прибыль в иностранной валюте | C39: =+D39+E39 -> 72227659 | D39: 4365084 | E39: 67862575
A40: в. | B40: Прибыль от коммерческих операций | C40: =+D40+E40 -> 0 | D40: 0 | E40: 0
A41: г. | B41: Прибыль и дивиденды от инвестиций | C41: =+D41+E41 -> 9624086 | D41: 9624086 | E41: 0
A42: д. | B42: Другие беспроцентные доходы | C42: =+D42+E42 -> 73338139 | D42: 61461455 | E42: 11876684
B43: в том числе
A44: д1. | B44: Возврат резервов, с формированных на покрытие потерь по активам | C44: =+D44+E44 -> 786600 | D44: 786600 | E44: 0
A45: д2. | B45: Возврат списанных кредитов | C45: =+D45+E45 -> 6746825 | D45: 6746825 | E45: 0
A46: е. | B46: Итого беспроцентных доходов | C46: =SUM(C38:C42) -> 427153372 | D46: =SUM(D38:D42) -> 339890029 | E46: =SUM(E38:E42) -> 87263343
A48: 5. | B48: БЕСПРОЦЕНТНЫЕ РАСХОДЫ
A49: а. | B49: Комиссионные расходы и расходы за услуги | C49: =+D49+E49 -> 160851375 | D49: 155618791 | E49: 5232584
A50: б. | B50: Убытки в иностранной валюте | C50: =+D50+E50 -> 49770959 | D50: 417309 | E50: 49353650
A51: в. | B51: Убытки по счетам купли-продажи | C51: =+D51+E51 -> 775252 | D51: 775252 | E51: 0
A52: г. | B52: Убытки от инвестиций | C52: =+D52+E52 -> 0 | D52: 0 | E52: 0
A53: д. | B53: Другие беспроцентные расходы | C53: =+D53+E53 -> 572995 | D53: 571927 | E53: 1068
A54: е. | B54: Итого беспроцентных расходов | C54: =SUM(C49:C53) -> 211970581 | D54: =SUM(D49:D53) -> 157383279 | E54: =SUM(E49:E53) -> 54587302
A56: 6. | B56: ЧИСТЫЙ ДОХОД ДО ОПЕРАЦИОННЫХ РАСХОДОВ | C56: =C35+C46-C54 -> 502679466 | D56: =D35+D46-D54 -> 437717926 | E56: =E35+E46-E54 -> 64961540
A58: 7. | B58: ОПЕРАЦИОННЫЕ РАСХОДЫ
A59: а. | B59: Заработная плата и другие расходы на сотрудников | C59: 236892420 | D59: 236892420
A60: а1) | B60: из них, выплаты основному руководящему персоналу | C60: 13967296 | D60: 13967296
A61: б. | B61: Аренда и содержание | C61: 27288388 | D61: 27288388
A62: в. | B62: Командировочные и транспортные расходы | C62: 2657109 | D62: 2657109
A63: г. | B63: Административные расходы | C63: 20125565 | D63: 20125565
A64: д. | B64: Репрезентация и благотворительность | C64: 39145479 | D64: 39145479
A65: е. | B65: Расходы на износ | C65: 29320032 | D65: 29320032
A66: ж. | B66: Страхование | C66: 562656 | D66: 562656
A67: з. | B67: Налоги | C67: 3260184 | D67: 3260184
A68: и. | B68: Штрафы и пеня | C68: 214137 | D68: 214137
A69: к. | B69: Другие операционные расходы | C69: 3182917 | D69: 3182917
A70: л. | B70: Итого операционных расходов | C70: =SUM(C59:C69)-C60 -> 362648887 | D70: =SUM(D59:D69)-D60 -> 362648887
A72: 8. | B72: ЧИСТАЯ ПРИБЫЛЬ ДО УПЛАТЫ НАЛОГОВ И ДРУГИХ ПОПРАВОК | C72: =C56-C70 -> 140030579 | D72: =D56-D70 -> 75069039 | E72: =+E56-(C70-D70) -> 64961540
A73: а. | B73: Оценка налога на прибыль | C73: =+D73 -> 32448089 | D73: 32448089
A75: 9. | B75: ДОХОД ДО ВВЕДЕНИЯ ПОПРАВОК | C75: =C72-C73 -> 107582490 | D75: =D72-D73 -> 42620950 | E75: =E72-E73 -> 64961540
A76: а. | B76: Непредвиденные доходы или убытки, чистые | C76: =+D76+E76 -> 0 | D76: 0 | E76: 0
A77: б. | B77: Другие поправки к прибыли, чистые | C77: =+D77+E77 -> 0 | D77: 0 | E77: 0
A79: 10. | B79: ЧИСТАЯ ПРИБЫЛЬ (УБЫТКИ) | C79: =C75+C76+C77 -> 107582490 | D79: =D75+D76+D77 -> 42620950 | E79: =E75+E76+E77 -> 64961540
B81: Подпись Председателя правления:
B83: Подпись Главного Бухгалтера:

Sheet Analysis of Interest
B1: АНАЛИЗ ПРОЦЕНТНЫХ ДОХОДОВ И РАСХОДОВ | C1: Таблица-4
B3: =+'Asset quality'!B3 -> АК "АЛОКАБАНК" | C3: =+'Asset quality'!P3 -> 44561
A4: № | B4: Категория | C4: в тыс. сум
A5: 1 . | B5: ПРОЦЕНТНЫЕ ДОХОДЫ ПО КРЕДИТНЫМ И ЛИЗИНГОВЫМ ОПЕРАЦИЯМ
A6: a. | B6: Кредиты и лизинговые операции ЦБРУ
A7: б. | B7: Кредиты и лизинговые операции другим банкам | C7: 75366
A8: в. | B8: Кредиты и лизинговые операции Правительству
A9: г. | B9: Кредиты и лизинговые операции физическим лицам | C9: 221788259
A10: д. | B10: Кредиты и лизинговые операции государственным предприятиям | C10: 79865132
A11: е. | B11: Кредиты и лизинговые операции совместным и иностранным предприятиям | C11: 55430278
A12: ж. | B12: Кредиты и лизинговые операции частным товариществам и корпорациям | C12: 548198425
A13: з. | B13: Другие кредиты и лизинговые операции | C13: 18192876
A14: и. | B14: ИТОГО ПРОЦЕНТНЫХ ДОХОДОВ ПО КРЕДИТНЫМ И ЛИЗИНГОВЫМ ОПЕРАЦИЯМ | C14: =SUM(C6:C13) -> 923550336
A16: 2. | B16: ПРОЦЕНТНЫЕ ДОХОДЫ ПО КОРРЕСПОНДЕНТСКИМ СЧЕТАМ
A17: a. | B17: К получению из ЦБРУ | C17: 701233
A18: б. | B18: К получению из других банков | C18: 15859918
B19: ИТОГО ПРОЦЕНТНЫХ ДОХОДОВ ПО КОРРЕСПОНДЕНТСКИМ СЧЕТАМ | C19: =SUM(C17:C18) -> 16561151
A21: 3. | B21: ПРОЦЕНТНЫЕ ДОХОДЫ ПО СЧЕТАМ КУПЛИ-ПРОДАЖИ Ц/Б
A22: a. | B22: Государственные казначейские ценные бумаги | C22: 7552603
A23: б. | B23: Облигации и ценные бумаги ЦБРУ | C23: 39398773
A24: в. | B24: Ценные бумаги государственных корпораций
A25: г. | B25: Еврооблигации | C25: 0
A26: д. | B26: Частные ценные бумаги | C26: 0
A27: е. | B27: Другие ценные бумаги | C27: 0
A28: ж. | B28: ИТОГО ПРОЦЕНТНЫХ ДОХОДОВ ПО СЧЕТАМ КУПЛИ-ПРОДАЖИ Ц/Б | C28: =SUM(C22:C27) -> 46951376
A30: 4. | B30: ПРОЦЕНТНЫЕ ДОХОДЫ ПО ИНВЕСТИЦИЯМ
A31: a. | B31: Государственные облигации | C31: 0
A32: б. | B32: Облигации и ценные бумаги ЦБРУ | C32: 0
A33: в. | B33: Частные облигации | C33: 0
A34: г. | B34: Еврооблигации | C34: 0
A35: д. | B35: Другие ценные бумаги
A36: е. | B36: ИТОГО ПРОЦЕНТНЫХ ДОХОДОВ ПО ИНВЕСТИЦИЯМ | C36: =SUM(C31:C35) -> 0
A38: 5. | B38: ДРУГИЕ ПРОЦЕНТНЫЕ ДОХОДЫ
A39: a. | B39: Процентные доходы по соглашениям о покупке ц/б c обратным выкупом | C39: 0
A40: б. | B40: Другие процентные доходы | C40: 219627154
A42: 6. | B42: ИТОГО ПРОЦЕНТНЫХ ДОХОДОВ | C42: =C14+C19+C28+C36+C39+C40 -> 1206690017
A44: 7. | B44: ПРОЦЕНТНЫЕ РАСХОДЫ ПО ДЕПОЗИТАМ
A45: A. | B45: Депозиты до востребования
A46: a. | B46: Правительство | C46: 1560575
A47: б. | B47: Физические лица | C47: 4230
A48: в. | B48: Государственные предприятия | C48: 2626774
A49: г. | B49: Совместные и иностранные предприятия | C49: 0
A50: д. | B50: Частные товарищества и корпорации | C50: 161521
A51: е. | B51: Другие депозиты | C51: 473
A52: ж. | B52: Итого процентных расходов по депозитам до востребования | C52: =SUM(C46:C51) -> 4353573
A54: Б. | B54: Срочные депозиты
A55: a. | B55: Правительство | C55: 190709535
A56: б. | B56: Физические лица | C56: 68028982
A57: в. | B57: Государственные предприятия | C57: 34083063
A58: г. | B58: Совместные и иностранные предприятия | C58: 10826752
A59: д. | B59: Частные товарищества и корпорации | C59: 47000266
A60: е. | B60: Другие депозиты | C60: 43869195
A61: ж. | B61: Итого процентных расходов по срочным депозитам | C61: =SUM(C55:C60) -> 394517793
A63: В. | B63: ИТОГО ПРОЦЕНТНЫХ РАСХОДОВ ПО ДЕПОЗИТАМ | C63: =C52+C61 -> 398871366
A65: 8. | B65: ПРОЦЕНТНЫЕ РАСХОДЫ ПО ДРУГИМ ОБЯЗАТЕЛЬСТВАМ
A66: а. | B66: Процентные расходы по непогашенным акцептам | C66: 5970833
A67: б. | B67: Процентные расходы по кредитам к оплате | C67: 67695285
A68: в. | B68: Процентные расходы по соглашениям о продаже ц/б с последующим выкупом | C68: 8059008
A69: г. | B69: Другие процентные расходы | C69: 317712043
A70: д. | B70: ИТОГО ПРОЦЕНТНЫХ РАСХОДОВ ПО ДРУГИМ ОБЯЗАТЕЛЬСТВАМ | C70: =SUM(C66:C69) -> 399437169
A72: 9. | B72: ИТОГО ПРОЦЕНТНЫХ РАСХОДОВ | C72: =C63+C70 -> 798308535
B74: Подпись Председателя правления:
B76: Подпись Главного Бухгалтера:

Sheet Changes in Equity
B1: ИЗМЕНЕНИЯ В СОБСТВЕННОМ КАПИТАЛЕ | C1: Таблица-7
B3: =+'Asset quality'!B3 -> АК "АЛОКАБАНК" | C3: =+'Asset quality'!P3 -> 44561
A4: № | B4: Категория | C4: в тыс. сум
A5: 1. | B5: Итого собственного капитала первоначально определенного за прошлый год | C5: 1568529812
A6: 2. | B6: Исправления в собственном капитале не показанные в отчете за прошлый год, чистые | C6: 0
A7: 3. | B7: Исправленный баланс на конец прошлого календарного года (сумма строк 1 и 2) | C7: =SUM(C5:C6) -> 1568529812
A8: 4. | B8: Чистый прибыль (убыток) по состоянию на дату от начала года | C8: =+'Income '!C79 -> 107582490 | D8: =+[8]Balance!$C$76 -> 107582490
A9: 5. | B9: Продажа, Обмен, Приобретение или выкуп акций, за текущий год (чистая выручка) | C9: 0
A10: 6. | B10: Изменения в оценочной стоимости прироста над первонач. стоимостью, за текущий год (чистые) | C10: -294261
A11: 7. | B11: МИНУС: Денежные дивиденды объявленные по привилегированным акциям | C11: 0
A12: 8. | B12: МИНУС: Денежные дивиденды объявленные по обыкновенным акциям | C12: 0
A13: 9. | B13: Другие статьи влияющие на собственный капитал за текущий год (чистые) | C13: -2312098
A14: 10. | B14: Итого собственного капитала на конец текущего периода (сумма строк с 3 по 10) | C14: =C7+SUM(C8:C10)-SUM(C11:C12)+C13 -> 1673505943 | D14: =+[8]Balance!$C$77 -> 1673505943
B16: Подпись Председателя правления:
B18: Подпись Главного Бухгалтера:

Sheet Loans Receivable
A1: КРЕДИТЫ И ЛИЗИНГИ К ПОЛУЧЕНИЮ ПО ОТРАСЛЯМ ЭКОНОМИКИ, ТИПАМ КЛИЕНТОВ И ПО ТИПУ ОБЕСПЕЧЕНИЯ | W1: Таблица-8
B3: =+'Asset quality'!B3 -> АК "АЛОКАБАНК" | T3: =+'Asset quality'!P3 -> 44561 | X3: тыс. сум
A4: № | B4: Отрасль экономики | C4: Сумма кредита | D4: в национальной валюте | F4: в иностранной валюте (в экв. в сумах) | H4: из них | J4: из них
D5: Сумма | E5: средне-взвешенные процентные ставки | F5: Сумма | G5: средне-взвешенные процентные ставки | H5: Начисляемые кредиты | I5: Кредиты переведённые в статус ненаращивания процентов | J5: Депозиты | K5: Гарантированные Правительством Республики Узбекистан | L5: из них | M5: Транспортные средства | N5: Инвентарь | O5: Недвижимость | P5: из них | R5: Оборудование | S5: Векселя (облигации) | T5: Акции | U5: Гарантия третьей стороны | V5: Поручительства третьей стороны | W5: Страховой полис | X5: Необеспеченные | Y5: Другое обеспечение
L6: Гарантированные Правительством Республики Узбекистан в иностранной валюте (экв.сум) | P6: жилая недвижимость | Q6: коммерческая недвижимость
A7: Код | B7: (А) | C7: (Б) | D7: (Б1) | E7: (Б2) | F7: (Б3) | G7: (Б4) | H7: (В) | I7: (Г) | J7: (Д) | K7: (Е) | L7: (Е1) | M7: (Ж) | N7: (З) | O7: (И) | P7: (И1) | Q7: (И2) | R7: (К) | S7: (Л) | T7: (М) | U7: (Н) | V7: (О) | W7: (П) | X7: (Р) | Y7: (С)
B8: Промышленность
A9: 10 | B9: Физические лица | C9: =SUM(J9:Y9)-L9-P9-Q9 -> 0 | D9: 0 | E9: 0 | F9: 0 | G9: 0 | H9: 0 | I9: 0 | J9: 0 | K9: 0 | L9: 0 | M9: 0 | N9: 0 | O9: =+P9+Q9 -> 0 | P9: 0 | Q9: 0 | R9: 0 | S9: 0 | T9: 0 | U9: 0 | V9: 0 | W9: 0 | X9: 0 | Y9: 0
A10: =A9+10 -> 20 | B10: Государственные предприятия | C10: =SUM(J10:Y10)-L10-P10-Q10 -> 403756555 | D10: 70127862 | E10: 0.2288737 | F10: 333628693 | G10: 0.061691647 | H10: 403756555 | I10: 0 | J10: 0 | K10: 0 | L10: 0 | M10: 14625170 | N10: 0 | O10: =+P10+Q10 -> 61467427 | P10: 717453 | Q10: 60749974 | R10: 0 | S10: 0 | T10: 0 | U10: 0 | V10: 2534158 | W10: 325129800 | X10: 0 | Y10: 0
A11: =A10+10 -> 30 | B11: Совместные и иностранные предприятия | C11: =SUM(J11:Y11)-L11-P11-Q11 -> 201843182 | D11: 47604623 | E11: 0.1876824 | F11: 154238559 | G11: 0.089490306 | H11: 200214799 | I11: 1628383 | J11: 0 | K11: 1617795 | L11: 0 | M11: 79947303 | N11: 0 | O11: =+P11+Q11 -> 120278084 | P11: 29848430 | Q11: 90429654 | R11: 0 | S11: 0 | T11: 0 | U11: 0 | V11: 0 | W11: 0 | X11: 0 | Y11: 0
A12: =A11+10 -> 40 | B12: Частные товарищества и корпорации | C12: =SUM(J12:Y12)-L12-P12-Q12 -> 2069879983 | D12: 807943187 | E12: 0.1893187 | F12: 1261936796 | G12: 0.078118988 | H12: 2033929692 | I12: 35950291 | J12: 4003421 | K12: 29116313 | L12: 0 | M12: 578477589 | N12: 0 | O12: =+P12+Q12 -> 1396459937 | P12: 199792818 | Q12: 1196667119 | R12: 0 | S12: 0 | T12: 0 | U12: 0 | V12: 4731736 | W12: 2011318 | X12: 0 | Y12: 55079669
A13: =A12+10 -> 50 | B13: Правительство | C13: =SUM(J13:Y13)-L13-P13-Q13 -> 0 | D13: 0 | E13: 0 | F13: 0 | G13: 0 | H13: 0 | I13: 0 | J13: 0 | K13: 0 | L13: 0 | M13: 0 | N13: 0 | O13: =+P13+Q13 -> 0 | P13: 0 | Q13: 0 | R13: 0 | S13: 0 | T13: 0 | U13: 0 | V13: 0 | W13: 0 | X13: 0 | Y13: 0
A14: =A13+10 -> 60 | B14: Прочие | C14: =SUM(J14:Y14)-L14-P14-Q14 -> 19872982 | D14: 9189694 | E14: 0.20100042 | F14: 10683288 | G14: 0.071424944 | H14: 19235678 | I14: 637304 | J14: 0 | K14: 897333 | L14: 0 | M14: 5061885 | N14: 0 | O14: =+P14+Q14 -> 13910432 | P14: 291159 | Q14: 13619273 | R14: 0 | S14: 0 | T14: 0 | U14: 0 | V14: 0 | W14: 3332 | X14: 0 | Y14: 0
A15: =A14+10 -> 70 | B15: Итого по промышленности | C15: =SUM(J15:Y15)-L15-P15-Q15 -> 2695352702 | D15: =SUM(D9:D14) -> 934865366 | E15: =IFERROR(((D9*E9)/D15)+((D10*E10)/D15)+((D11*E11)/D15)+((D12*E12)/D15)+((D13*E13)/D15)+((D14*E14)/D15),0) -> 0.19231738 | F15: =SUM(F9:F14) -> 1760487336 | G15: =IFERROR(((F9*G9)/F15)+((F10*G10)/F15)+((F11*G11)/F15)+((F12*G12)/F15)+((F13*G13)/F15)+((F14*G14)/F15),0) -> 0.075961489 | H15: =SUM(H9:H14) -> 2657136724 | I15: =SUM(I9:I14) -> 38215978 | J15: =SUM(J9:J14) -> 4003421 | K15: =SUM(K9:K14) -> 31631441 | L15: =SUM(L9:L14) -> 0 | M15: =SUM(M9:M14) -> 678111947 | N15: =SUM(N9:N14) -> 0 | O15: =SUM(O9:O14) -> 1592115880 | ... Y15: =SUM(Y9:Y14) -> 55079669
B16: Сельское хозяйство
A17: =A15+10 -> 80 | B17: Физические лица | C17: =SUM(J17:Y17)-L17-P17-Q17 -> 0 | D17: 0 | E17: 0 | F17: 0 | G17: 0 | H17: 0 | I17: 0 | J17: 0 | K17: 0 | L17: 0 | M17: 0 | N17: 0 | O17: =+P17+Q17 -> 0 | P17: 0 | Q17: 0 | R17: 0 | S17: 0 | T17: 0 | U17: 0 | V17: 0 | W17: 0 | X17: 0 | Y17: 0
A18: =A17+10 -> 90 | B18: Государственные предприятия | C18: =SUM(J18:Y18)-L18-P18-Q18 -> 0 | D18: 0 | E18: 0 | F18: 0 | G18: 0 | H18: 0 | I18: 0 | J18: 0 | K18: 0 | L18: 0 | M18: 0 | N18: 0 | O18: =+P18+Q18 -> 0 | P18: 0 | Q18: 0 | R18: 0 | S18: 0 | T18: 0 | U18: 0 | V18: 0 | W18: 0 | X18: 0 | Y18: 0
A19: =A18+10 -> 100 | B19: Совместные и иностранные предприятия | C19: =SUM(J19:Y19)-L19-P19-Q19 -> 69765 | D19: 69765 | E19: 0.18 | F19: 0 | G19: 0 | H19: 69765 | I19: 0 | J19: 0 | K19: 0 | L19: 0 | M19: 69765 | N19: 0 | O19: =+P19+Q19 -> 0 | P19: 0 | Q19: 0 | R19: 0 | S19: 0 | T19: 0 | U19: 0 | V19: 0 | W19: 0 | X19: 0 | Y19: 0
A20: =A19+10 -> 110 | B20: Частные товарищества и корпорации | C20: =SUM(J20:Y20)-L20-P20-Q20 -> 199500477 | D20: 76507718 | E20: 0.20364522 | F20: 122992759 | G20: 0.076216619 | H20: 192831536 | I20: 6668941 | J20: 2483169 | K20: 16229450 | L20: 0 | M20: 51552038 | N20: 0 | O20: =+P20+Q20 -> 125700152 | P20: 25580483 | Q20: 100119669 | R20: 0 | S20: 0 | T20: 0 | U20: 0 | V20: 1684668 | W20: 0 | X20: 0 | Y20: 1851000
A21: =A20+10 -> 120 | B21: Фермерское хозяйство | C21: =SUM(J21:Y21)-L21-P21-Q21 -> 31561978 | D21: 8275439 | E21: 0.38188963 | F21: 23286539 | G21: 0.11917625 | H21: 31068728 | I21: 493250 | J21: 0 | K21: 493250 | L21: 0 | M21: 2609468 | N21: 0 | O21: =+P21+Q21 -> 28459260 | P21: 533333 | Q21: 27925927 | R21: 0 | S21: 0 | T21: 0 | U21: 0 | V21: 0 | W21: 0 | X21: 0 | Y21: 0
A22: =A21+10 -> 130 | B22: Правительство | C22: =SUM(J22:Y22)-L22-P22-Q22 -> 0 | D22: 0 | E22: 0 | F22: 0 | G22: 0 | H22: 0 | I22: 0 | J22: 0 | K22: 0 | L22: 0 | M22: 0 | N22: 0 | O22: =+P22+Q22 -> 0 | P22: 0 | Q22: 0 | R22: 0 | S22: 0 | T22: 0 | U22: 0 | V22: 0 | W22: 0 | X22: 0 | Y22: 0
A23: =A22+10 -> 140 | B23: Прочие | C23: =SUM(J23:Y23)-L23-P23-Q23 -> 2752863 | D23: 2752863 | E23: 0.20597575 | F23: 0 | G23: 0 | H23: 2118878 | I23: 633985 | J23: 0 | K23: 0 | L23: 0 | M23: 2179986 | N23: 0 | O23: =+P23+Q23 -> 342574 | P23: 59988 | Q23: 282586 | R23: 0 | S23: 0 | T23: 0 | U23: 0 | V23: 230303 | W23: 0 | X23: 0 | Y23: 0
A24: =A23+10 -> 150 | B24: Итого по сельскому хозяйству | C24: =SUM(J24:Y24)-L24-P24-Q24 -> 233885083 | D24: =SUM(D17:D23) -> 87605785 | E24: =IFERROR(((D17*E17)/D24)+((D18*E18)/D24)+((D19*E19)/D24)+((D20*E20)/D24)+((D21*E21)/D24)+((D22*E22)/D24)+((D23*E23)/D24),0) -> 0.22053699 | F24: =SUM(F17:F23) -> 146279298 | G24: =IFERROR(((F17*G17)/F24)+((F18*G18)/F24)+((F19*G19)/F24)+((F20*G20)/F24)+((F21*G21)/F24)+((F22*G22)/F24)+((F23*G23)/F24),0) -> 0.083055461 | H24: =SUM(H17:H23) -> 226088907 | I24: =SUM(I17:I23) -> 7796176 | J24: =SUM(J17:J23) -> 2483169 | K24: =SUM(K17:K23) -> 16722700 | L24: =SUM(L17:L23) -> 0 | M24: =SUM(M17:M23) -> 56411257 | N24: =SUM(N17:N23) -> 0 | O24: =SUM(O17:O23) -> 154501986 | ... Y24: =SUM(Y17:Y23) -> 1851000
B25: Транспорт и коммуникации
A26: =A24+10 -> 160 | B26: Физические лица | C26: =SUM(J26:Y26)-L26-P26-Q26 -> 0 | D26: 0 | E26: 0 | F26: 0 | G26: 0 | H26: 0 | I26: 0 | J26: 0 | K26: 0 | L26: 0 | M26: 0 | N26: 0 | O26: =+P26+Q26 -> 0 | P26: 0 | Q26: 0 | R26: 0 | S26: 0 | T26: 0 | U26: 0 | V26: 0 | W26: 0 | X26: 0 | Y26: 0
A27: =A26+10 -> 170 | B27: Государственные предприятия | C27: =SUM(J27:Y27)-L27-P27-Q27 -> 589323858 | D27: 567756915 | E27: 0.14567962 | F27: 21566943 | G27: 0.07 | H27: 589323858 | I27: 0 | J27: 216263967 | K27: 0 | L27: 0 | M27: 0 | N27: 0 | O27: =+P27+Q27 -> 126566943 | P27: 0 | Q27: 126566943 | R27: 0 | S27: 0 | T27: 0 | U27: 0 | V27: 246492948 | W27: 0 | X27: 0 | Y27: 0
A28: =A27+10 -> 180 | B28: Совместные и иностранные предприятия | C28: =SUM(J28:Y28)-L28-P28-Q28 -> 42849254 | D28: 42849254 | E28: 0.15 | F28: 0 | G28: 0 | H28: 42849254 | I28: 0 | J28: 0 | K28: 0 | L28: 0 | M28: 0 | N28: 0 | O28: =+P28+Q28 -> 42849254 | P28: 0 | Q28: 42849254 | R28: 0 | S28: 0 | T28: 0 | U28: 0 | V28: 0 | W28: 0 | X28: 0 | Y28: 0
A29: =A28+10 -> 190 | B29: Частные товарищества и корпорации | C29: =SUM(J29:Y29)-L29-P29-Q29 -> 172565751 | D29: 152567525 | E29: 0.21039498 | F29: 19998226 | G29: 0.097161077 | H29: 153739240 | I29: 18826511 | J29: 71947 | K29: 2116193 | L29: 0 | M29: 147518330 | N29: 0 | O29: =+P29+Q29 -> 22859281 | P29: 3977288 | Q29: 18881993 | R29: 0 | S29: 0 | T29: 0 | U29: 0 | V29: 0 | W29: 0 | X29: 0 | Y29: 0
A30: =A29+10 -> 200 | B30: Правительство | C30: =SUM(J30:Y30)-L30-P30-Q30 -> 0 | D30: 0 | E30: 0 | F30: 0 | G30: 0 | H30: 0 | I30: 0 | J30: 0 | K30: 0 | L30: 0 | M30: 0 | N30: 0 | O30: =+P30+Q30 -> 0 | P30: 0 | Q30: 0 | R30: 0 | S30: 0 | T30: 0 | U30: 0 | V30: 0 | W30: 0 | X30: 0 | Y30: 0
A31: =A30+10 -> 210 | B31: Прочие | C31: =SUM(J31:Y31)-L31-P31-Q31 -> 22064805 | D31: 22064805 | E31: 0.22706416 | F31: 0 | G31: 0 | H31: 22004191 | I31: 60614 | J31: 0 | K31: 0 | L31: 0 | M31: 21530497 | N31: 0 | O31: =+P31+Q31 -> 440369 | P31: 0 | Q31: 440369 | R31: 0 | S31: 0 | T31: 0 | U31: 0 | V31: 0 | W31: 93939 | X31: 0 | Y31: 0
A32: =A31+10 -> 220 | B32: Итого по транспорту и коммуникациям | C32: =SUM(J32:Y32)-L32-P32-Q32 -> 826803668 | D32: =SUM(D26:D31) -> 785238499 | E32: =IFERROR(((D26*E26)/D32)+((D27*E27)/D32)+((D28*E28)/D32)+((D29*E29)/D32)+((D30*E30)/D32)+((D31*E31)/D32),0) -> 0.16077608 | F32: =SUM(F26:F31) -> 41565169 | G32: =IFERROR(((F26*G26)/F32)+((F27*G27)/F32)+((F28*G28)/F32)+((F29*G29)/F32)+((F30*G30)/F32)+((F31*G31)/F32),0) -> 0.083067994 | H32: =SUM(H26:H31) -> 807916543 | I32: =SUM(I26:I31) -> 18887125 | J32: =SUM(J26:J31) -> 216335914 | K32: =SUM(K26:K31) -> 2116193 | L32: =SUM(L26:L31) -> 0 | M32: =SUM(M26:M31) -> 169048827 | N32: =SUM(N26:N31) -> 0 | O32: =SUM(O26:O31) -> 192715847 | ... Y32: =SUM(Y26:Y31) -> 0
B33: Строительство
A34: =A32+10 -> 230 | B34: Физические лица | C34: =SUM(J34:Y34)-L34-P34-Q34 -> 0 | D34: 0 | E34: 0 | F34: 0 | G34: 0 | H34: 0 | I34: 0 | J34: 0 | K34: 0 | L34: 0 | M34: 0 | N34: 0 | O34: =+P34+Q34 -> 0 | P34: 0 | Q34: 0 | R34: 0 | S34: 0 | T34: 0 | U34: 0 | V34: 0 | W34: 0 | X34: 0 | Y34: 0
A35: =A34+10 -> 240 | B35: Государственные предприятия | C35: =SUM(J35:Y35)-L35-P35-Q35 -> 2105944 | D35: 2105944 | E35: 0.23744138 | F35: 0 | G35: 0 | H35: 2105944 | I35: 0 | J35: 0 | K35: 0 | L35: 0 | M35: 2105944 | N35: 0 | O35: =+P35+Q35 -> 0 | P35: 0 | Q35: 0 | R35: 0 | S35: 0 | T35: 0 | U35: 0 | V35: 0 | W35: 0 | X35: 0 | Y35: 0
A36: =A35+10 -> 250 | B36: Совместные и иностранные предприятия | C36: =SUM(J36:Y36)-L36-P36-Q36 -> 41659965 | D36: 0 | E36: 0 | F36: 41659965 | G36: 0.0799 | H36: 41659965 | I36: 0 | J36: 0 | K36: 0 | L36: 0 | M36: 41659965 | N36: 0 | O36: =+P36+Q36 -> 0 | P36: 0 | Q36: 0 | R36: 0 | S36: 0 | T36: 0 | U36: 0 | V36: 0 | W36: 0 | X36: 0 | Y36: 0
A37: =A36+10 -> 260 | B37: Частные товарищества и корпорации | C37: =SUM(J37:Y37)-L37-P37-Q37 -> 488679857 | D37: 230310927 | E37: 0.19702013 | F37: 258368930 | G37: 0.073487435 | H37: 479037882 | I37: 9641975 | J37: 479711 | K37: 14985938 | L37: 0 | M37: 145672059 | N37: 0 | O37: =+P37+Q37 -> 325951531 | P37: 135817554 | Q37: 190133977 | R37: 0 | S37: 0 | T37: 0 | U37: 0 | V37: 305556 | W37: 1285062 | X37: 0 | Y37: 0
A38: =A37+10 -> 270 | B38: Правительство | C38: =SUM(J38:Y38)-L38-P38-Q38 -> 414350 | D38: 414350 | E38: 0.25 | F38: 0 | G38: 0 | H38: 414350 | I38: 0 | J38: 0 | K38: 0 | L38: 0 | M38: 0 | N38: 0 | O38: =+P38+Q38 -> 414350 | P38: 0 | Q38: 414350 | R38: 0 | S38: 0 | T38: 0 | U38: 0 | V38: 0 | W38: 0 | X38: 0 | Y38: 0
A39: =A38+10 -> 280 | B39: Прочие | C39: =SUM(J39:Y39)-L39-P39-Q39 -> 2143019 | D39: 2143019 | E39: 0.14526414 | F39: 0 | G39: 0 | H39: 2143019 | I39: 0 | J39: 0 | K39: 0 | L39: 0 | M39: 143020 | N39: 0 | O39: =+P39+Q39 -> 1999999 | P39: 0 | Q39: 1999999 | R39: 0 | S39: 0 | T39: 0 | U39: 0 | V39: 0 | W39: 0 | X39: 0 | Y39: 0
A40: =A39+10 -> 290 | B40: Итого по строительству | C40: =SUM(J40:Y40)-L40-P40-Q40 -> 535003135 | D40: =SUM(D34:D39) -> 234974240 | E40: =IFERROR(((D34*E34)/D40)+((D35*E35)/D40)+((D36*E36)/D40)+((D37*E37)/D40)+((D38*E38)/D40)+((D39*E39)/D40),0) -> 0.1970038 | F40: =SUM(F34:F39) -> 300028895 | G40: =IFERROR(((F34*G34)/F40)+((F35*G35)/F40)+((F36*G36)/F40)+((F37*G37)/F40)+((F38*G38)/F40)+((F39*G39)/F40),0) -> 0.07437784 | H40: =SUM(H34:H39) -> 525361160 | I40: =SUM(I34:I39) -> 9641975 | J40: =SUM(J34:J39) -> 479711 | K40: =SUM(K34:K39) -> 14985938 | L40: =SUM(L34:L39) -> 0 | M40: =SUM(M34:M39) -> 189580988 | N40: =SUM(N34:N39) -> 0 | O40: =SUM(O34:O39) -> 328365880 | ... Y40: =SUM(Y34:Y39) -> 0
B41: Торговля и общественное питание
A42: =A40+10 -> 300 | B42: Физические лица | C42: =SUM(J42:Y42)-L42-P42-Q42 -> 0 | D42: 0 | E42: 0 | F42: 0 | G42: 0 | H42: 0 | I42: 0 | J42: 0 | K42: 0 | L42: 0 | M42: 0 | N42: 0 | O42: =+P42+Q42 -> 0 | P42: 0 | Q42: 0 | R42: 0 | S42: 0 | T42: 0 | U42: 0 | V42: 0 | W42: 0 | X42: 0 | Y42: 0
A43: =A42+10 -> 310 | B43: Государственные предприятия | C43: =SUM(J43:Y43)-L43-P43-Q43 -> 5071998 | D43: 5071998 | E43: 0.2085962 | F43: 0 | G43: 0 | H43: 5071998 | I43: 0 | J43: 0 | K43: 0 | L43: 0 | M43: 71998 | N43: 0 | O43: =+P43+Q43 -> 5000000 | P43: 0 | Q43: 5000000 | R43: 0 | S43: 0 | T43: 0 | U43: 0 | V43: 0 | W43: 0 | X43: 0 | Y43: 0
A44: =A43+10 -> 320 | B44: Совместные и иностранные предприятия | C44: =SUM(J44:Y44)-L44-P44-Q44 -> 0 | D44: 0 | E44: 0 | F44: 0 | G44: 0 | H44: 0 | I44: 0 | J44: 0 | K44: 0 | L44: 0 | M44: 0 | N44: 0 | O44: =+P44+Q44 -> 0 | P44: 0 | Q44: 0 | R44: 0 | S44: 0 | T44: 0 | U44: 0 | V44: 0 | W44: 0 | X44: 0 | Y44: 0
A45: =A44+10 -> 330 | B45: Частные товарищества и корпорации | C45: =SUM(J45:Y45)-L45-P45-Q45 -> 674532081 | D45: 507118802 | E45: 0.20986831 | F45: 167413279 | G45: 0.074364622 | H45: 643075225 | I45: 31456856 | J45: 326521 | K45: 8783732 | L45: 0 | M45: 128090308 | N45: 0 | O45: =+P45+Q45 -> 448292166 | P45: 45119507 | Q45: 403172659 | R45: 0 | S45: 0 | T45: 0 | U45: 0 | V45: 65230967 | W45: 2623109 | X45: 0 | Y45: 21185278
A46: =A45+10 -> 340 | B46: Правительство | C46: =SUM(J46:Y46)-L46-P46-Q46 -> 245777 | D46: 245777 | E46: 0.24 | F46: 0 | G46: 0 | H46: 245777 | I46: 0 | J46: 0 | K46: 0 | L46: 0 | M46: 245777 | N46: 0 | O46: =+P46+Q46 -> 0 | P46: 0 | Q46: 0 | R46: 0 | S46: 0 | T46: 0 | U46: 0 | V46: 0 | W46: 0 | X46: 0 | Y46: 0
A47: =A46+10 -> 350 | B47: Прочие | C47: =SUM(J47:Y47)-L47-P47-Q47 -> 26844529 | D47: 26844529 | E47: 0.47888306 | F47: 0 | G47: 0 | H47: 24843154 | I47: 2001375 | J47: 203427 | K47: 0 | L47: 0 | M47: 16780863 | N47: 0 | O47: =+P47+Q47 -> 9001715 | P47: 652385 | Q47: 8349330 | R47: 0 | S47: 0 | T47: 0 | U47: 0 | V47: 5000 | W47: 54024 | X47: 0 | Y47: 799500
A48: =A47+10 -> 360 | B48: Итого по торговле и общественному питанию | C48: =SUM(J48:Y48)-L48-P48-Q48 -> 706694385 | D48: =SUM(D42:D47) -> 539281106 | E48: =IFERROR(((D42*E42)/D48)+((D43*E43)/D48)+((D44*E44)/D48)+((D45*E45)/D48)+((D46*E46)/D48)+((D47*E47)/D48),0) -> 0.22326119 | F48: =SUM(F42:F47) -> 167413279 | G48: =IFERROR(((F42*G42)/F48)+((F43*G43)/F48)+((F44*G44)/F48)+((F45*G45)/F48)+((F46*G46)/F48)+((F47*G47)/F48),0) -> 0.074364622 | H48: =SUM(H42:H47) -> 673236154 | I48: =SUM(I42:I47) -> 33458231 | J48: =SUM(J42:J47) -> 529948 | K48: =SUM(K42:K47) -> 8783732 | L48: =SUM(L42:L47) -> 0 | M48: =SUM(M42:M47) -> 145188946 | N48: =SUM(N42:N47) -> 0 | O48: =SUM(O42:O47) -> 462293881 | ... Y48: =SUM(Y42:Y47) -> 21984778
B49: Материально-техническое снабжение и сбыт
A50: =A48+10 -> 370 | B50: Физические лица | C50: =SUM(J50:Y50)-L50-P50-Q50 -> 0 | D50: 0 | E50: 0 | F50: 0 | G50: 0 | H50: 0 | I50: 0 | J50: 0 | K50: 0 | L50: 0 | M50: 0 | N50: 0 | O50: =+P50+Q50 -> 0 | P50: 0 | Q50: 0 | R50: 0 | S50: 0 | T50: 0 | U50: 0 | V50: 0 | W50: 0 | X50: 0 | Y50: 0
A51: =A50+10 -> 380 | B51: Государственные предприятия | C51: =SUM(J51:Y51)-L51-P51-Q51 -> 4388532 | D51: 4388532 | E51: 0.24 | F51: 0 | G51: 0 | H51: 4388532 | I51: 0 | J51: 0 | K51: 0 | L51: 0 | M51: 4388532 | N51: 0 | O51: =+P51+Q51 -> 0 | P51: 0 | Q51: 0 | R51: 0 | S51: 0 | T51: 0 | U51: 0 | V51: 0 | W51: 0 | X51: 0 | Y51: 0
A52: =A51+10 -> 390 | B52: Совместные и иностранные предприятия | C52: =SUM(J52:Y52)-L52-P52-Q52 -> 0 | D52: 0 | E52: 0 | F52: 0 | G52: 0 | H52: 0 | I52: 0 | J52: 0 | K52: 0 | L52: 0 | M52: 0 | N52: 0 | O52: =+P52+Q52 -> 0 | P52: 0 | Q52: 0 | R52: 0 | S52: 0 | T52: 0 | U52: 0 | V52: 0 | W52: 0 | X52: 0 | Y52: 0
A53: =A52+10 -> 400 | B53: Частные товарищества и корпорации | C53: =SUM(J53:Y53)-L53-P53-Q53 -> 78699415 | D53: 42009060 | E53: 0.19650915 | F53: 36690355 | G53: 0.080270605 | H53: 34280784 | I53: 44418631 | J53: 55661 | K53: 0 | L53: 0 | M53: 65805099 | N53: 0 | O53: =+P53+Q53 -> 6836498 | P53: 0 | Q53: 6836498 | R53: 0 | S53: 0 | T53: 0 | U53: 0 | V53: 6002157 | W53: 0 | X53: 0 | Y53: 0
A54: =A53+10 -> 410 | B54: Правительство | C54: =SUM(J54:Y54)-L54-P54-Q54 -> 0 | D54: 0 | E54: 0 | F54: 0 | G54: 0 | H54: 0 | I54: 0 | J54: 0 | K54: 0 | L54: 0 | M54: 0 | N54: 0 | O54: =+P54+Q54 -> 0 | P54: 0 | Q54: 0 | R54: 0 | S54: 0 | T54: 0 | U54: 0 | V54: 0 | W54: 0 | X54: 0 | Y54: 0
A55: =A54+10 -> 420 | B55: Прочие | C55: =SUM(J55:Y55)-L55-P55-Q55 -> 218328 | D55: 218328 | E55: 0.21106035 | F55: 0 | G55: 0 | H55: 218328 | I55: 0 | J55: 0 | K55: 0 | L55: 0 | M55: 172873 | N55: 0 | O55: =+P55+Q55 -> 45455 | P55: 45455 | Q55: 0 | R55: 0 | S55: 0 | T55: 0 | U55: 0 | V55: 0 | W55: 0 | X55: 0 | Y55: 0
A56: =A55+10 -> 430 | B56: Итого по материально-техническому снабжению и сбыту | C56: =SUM(J56:Y56)-L56-P56-Q56 -> 83306275 | D56: =SUM(D50:D55) -> 46615920 | E56: =IFERROR(((D50*E50)/D56)+((D51*E51)/D56)+((D52*E52)/D56)+((D53*E53)/D56)+((D54*E54)/D56)+((D55*E55)/D56),0) -> 0.20067163 | F56: =SUM(F50:F55) -> 36690355 | G56: =IFERROR(((F50*G50)/F56)+((F51*G51)/F56)+((F52*G52)/F56)+((F53*G53)/F56)+((F54*G54)/F56)+((F55*G55)/F56),0) -> 0.080270605 | H56: =SUM(H50:H55) -> 38887644 | I56: =SUM(I50:I55) -> 44418631 | J56: =SUM(J50:J55) -> 55661 | K56: =SUM(K50:K55) -> 0 | L56: =SUM(L50:L55) -> 0 | M56: =SUM(M50:M55) -> 70366504 | N56: =SUM(N50:N55) -> 0 | O56: =SUM(O50:O55) -> 6881953 | ... Y56: =SUM(Y50:Y55) -> 0
B57: Жилищно-коммунальные услуги
A58: =A56+10 -> 440 | B58: Физические лица | C58: =SUM(J58:Y58)-L58-P58-Q58 -> 0 | D58: 0 | E58: 0 | F58: 0 | G58: 0 | H58: 0 | I58: 0 | J58: 0 | K58: 0 | L58: 0 | M58: 0 | N58: 0 | O58: =+P58+Q58 -> 0 | P58: 0 | Q58: 0 | R58: 0 | S58: 0 | T58: 0 | U58: 0 | V58: 0 | W58: 0 | X58: 0 | Y58: 0
A59: =A58+10 -> 450 | B59: Государственные предприятия | C59: =SUM(J59:Y59)-L59-P59-Q59 -> 0 | D59: 0 | E59: 0 | F59: 0 | G59: 0 | H59: 0 | I59: 0 | J59: 0 | K59: 0 | L59: 0 | M59: 0 | N59: 0 | O59: =+P59+Q59 -> 0 | P59: 0 | Q59: 0 | R59: 0 | S59: 0 | T59: 0 | U59: 0 | V59: 0 | W59: 0 | X59: 0 | Y59: 0
A60: =A59+10 -> 460 | B60: Совместные и иностранные предприятия | C60: =SUM(J60:Y60)-L60-P60-Q60 -> 0 | D60: 0 | E60: 0 | F60: 0 | G60: 0 | H60: 0 | I60: 0 | J60: 0 | K60: 0 | L60: 0 | M60: 0 | N60: 0 | O60: =+P60+Q60 -> 0 | P60: 0 | Q60: 0 | R60: 0 | S60: 0 | T60: 0 | U60: 0 | V60: 0 | W60: 0 | X60: 0 | Y60: 0
A61: =A60+10 -> 470 | B61: Частные товарищества и корпорации | C61: =SUM(J61:Y61)-L61-P61-Q61 -> 48676081 | D61: 45424783 | E61: 0.17730749 | F61: 3251298 | G61: 0.12 | H61: 46563008 | I61: 2113073 | J61: 19171 | K61: 643387 | L61: 0 | M61: 4757555 | N61: 0 | O61: =+P61+Q61 -> 41729383 | P61: 7149990 | Q61: 34579393 | R61: 0 | S61: 0 | T61: 0 | U61: 0 | V61: 80000 | W61: 1446585 | X61: 0 | Y61: 0
A62: =A61+10 -> 480 | B62: Правительство | C62: =SUM(J62:Y62)-L62-P62-Q62 -> 0 | D62: 0 | E62: 0 | F62: 0 | G62: 0 | H62: 0 | I62: 0 | J62: 0 | K62: 0 | L62: 0 | M62: 0 | N62: 0 | O62: =+P62+Q62 -> 0 | P62: 0 | Q62: 0 | R62: 0 | S62: 0 | T62: 0 | U62: 0 | V62: 0 | W62: 0 | X62: 0 | Y62: 0
A63: 485 | B63: Негосударственные некоммерческие организации | C63: =SUM(J63:Y63)-L63-P63-Q63 -> 2786822 | D63: 2786822 | E63: 0.15582972 | F63: 0 | G63: 0 | H63: 146205 | I63: 2640617 | J63: 0 | K63: 2349375 | L63: 0 | M63: 0 | N63: 0 | O63: =+P63+Q63 -> 0 | P63: 0 | Q63: 0 | R63: 0 | S63: 0 | T63: 0 | U63: 0 | V63: 0 | W63: 437447 | X63: 0 | Y63: 0
A64: =A62+10 -> 490 | B64: Прочие | C64: =SUM(J64:Y64)-L64-P64-Q64 -> 10679650 | D64: 10679650 | E64: 0.11993223 | F64: 0 | G64: 0 | H64: 1219623 | I64: 9460027 | J64: 0 | K64: 1315727 | L64: 0 | M64: 162155 | N64: 0 | O64: =+P64+Q64 -> 106021 | P64: 0 | Q64: 106021 | R64: 0 | S64: 0 | T64: 0 | U64: 0 | V64: 80321 | W64: 9015426 | X64: 0 | Y64: 0
A65: =A64+10 -> 500 | B65: Итого по жилищно-коммунальным услугам | C65: =SUM(J65:Y65)-L65-P65-Q65 -> 62142553 | D65: =SUM(D58:D64) -> 58891255 | E65: =IFERROR(((D58*E58)/D65)+((D59*E59)/D65)+((D60*E60)/D65)+((D61*E61)/D65)+((D62*E62)/D65)+((D63*E63)/D65)+((D64*E64)/D65),0) -> 0.1658864 | F65: =SUM(F58:F64) -> 3251298 | G65: =IFERROR(((F58*G58)/F65)+((F59*G59)/F65)+((F60*G60)/F65)+((F61*G61)/F65)+((F62*G62)/F65)+((F63*G63)/F65)+((F64*G64)/F65),0) -> 0.12 | H65: =SUM(H58:H64) -> 47928836 | I65: =SUM(I58:I64) -> 14213717 | J65: =SUM(J58:J64) -> 19171 | K65: =SUM(K58:K64) -> 4308489 | L65: =SUM(L58:L64) -> 0 | M65: =SUM(M58:M64) -> 4919710 | N65: =SUM(N58:N64) -> 0 | O65: =SUM(O58:O64) -> 41835404 | ... Y65: =SUM(Y58:Y64) -> 0
B66: Другие отрасли
A67: =A65+10 -> 510 | B67: Физические лица | C67: =SUM(J67:Y67)-L67-P67-Q67 -> 1328984229 | D67: 1328984229 | E67: 0.22435409 | F67: 0 | G67: 0 | H67: 1315454057 | I67: 13530172 | J67: 244766475 | K67: 0 | L67: 0 | M67: 127172340 | N67: 0 | O67: =+P67+Q67 -> 395548854 | P67: 372559617 | Q67: 22989237 | R67: 0 | S67: 0 | T67: 0 | U67: 0 | V67: 529199588 | W67: 29128808 | X67: 0 | Y67: 3168164
A68: =A67+10 -> 520 | B68: Государственные предприятия | C68: =SUM(J68:Y68)-L68-P68-Q68 -> 8201367 | D68: 8201367 | E68: 0.15198629 | F68: 0 | G68: 0 | H68: 8201367 | I68: 0 | J68: 0 | K68: 6562967 | L68: 0 | M68: 1638400 | N68: 0 | O68: =+P68+Q68 -> 0 | P68: 0 | Q68: 0 | R68: 0 | S68: 0 | T68: 0 | U68: 0 | V68: 0 | W68: 0 | X68: 0 | Y68: 0
A69: =A68+10 -> 530 | B69: Совместные и иностранные предприятия | C69: =SUM(J69:Y69)-L69-P69-Q69 -> 0 | D69: 0 | E69: 0 | F69: 0 | G69: 0 | H69: 0 | I69: 0 | J69: 0 | K69: 0 | L69: 0 | M69: 0 | N69: 0 | O69: =+P69+Q69 -> 0 | P69: 0 | Q69: 0 | R69: 0 | S69: 0 | T69: 0 | U69: 0 | V69: 0 | W69: 0 | X69: 0 | Y69: 0
A70: =A69+10 -> 540 | B70: Частные товарищества и корпорации | C70: =SUM(J70:Y70)-L70-P70-Q70 -> 1166839842 | D70: 724014314 | E70: 0.19048625 | F70: 442825528 | G70: 0.05837294 | H70: 1153738586 | I70: 13101256 | J70: 154983581 | K70: 25492842 | L70: 0 | M70: 238015801 | N70: 0 | O70: =+P70+Q70 -> 596915725 | P70: 19755544 | Q70: 577160181 | R70: 0 | S70: 0 | T70: 0 | U70: 0 | V70: 67483668 | W70: 27026827 | X70: 0 | Y70: 56921398
A71: =A70+10 -> 550 | B71: Центральный банк | C71: =SUM(J71:Y71)-L71-P71-Q71 -> 0 | D71: 0 | E71: 0 | F71: 0 | G71: 0 | H71: 0 | I71: 0 | J71: 0 | K71: 0 | L71: 0 | M71: 0 | N71: 0 | O71: =+P71+Q71 -> 0 | P71: 0 | Q71: 0 | R71: 0 | S71: 0 | T71: 0 | U71: 0 | V71: 0 | W71: 0 | X71: 0 | Y71: 0
A72: =A71+10 -> 560 | B72: Другие банки | C72: =SUM(J72:Y72)-L72-P72-Q72 -> 0 | D72: 0 | E72: 0 | F72: 0 | G72: 0 | H72: 0 | I72: 0 | J72: 0 | K72: 0 | L72: 0 | M72: 0 | N72: 0 | O72: =+P72+Q72 -> 0 | P72: 0 | Q72: 0 | R72: 0 | S72: 0 | T72: 0 | U72: 0 | V72: 0 | W72: 0 | X72: 0 | Y72: 0
A73: =A72+10 -> 570 | B73: Правительство | C73: =SUM(J73:Y73)-L73-P73-Q73 -> 0 | D73: 0 | E73: 0 | F73: 0 | G73: 0 | H73: 0 | I73: 0 | J73: 0 | K73: 0 | L73: 0 | M73: 0 | N73: 0 | O73: =+P73+Q73 -> 0 | P73: 0 | Q73: 0 | R73: 0 | S73: 0 | T73: 0 | U73: 0 | V73: 0 | W73: 0 | X73: 0 | Y73: 0
A74: =A73+10 -> 580 | B74: Небанковские финансовые институты | C74: =SUM(J74:Y74)-L74-P74-Q74 -> 64423145 | D74: 22516363 | E74: 0.21251615 | F74: 41906782 | G74: 0.075 | H74: 64423145 | I74: 0 | J74: 0 | K74: 0 | L74: 0 | M74: 0 | N74: 0 | O74: =+P74+Q74 -> 22516363 | P74: 0 | Q74: 22516363 | R74: 0 | S74: 0 | T74: 0 | U74: 0 | V74: 41906782 | W74: 0 | X74: 0 | Y74: 0
A75: =A74+10 -> 590 | B75: Негосударственные некоммерческие организации | C75: =SUM(J75:Y75)-L75-P75-Q75 -> 11138459 | D75: 4691500 | E75: 0.11540694 | F75: 6446959 | G75: 0.0799 | H75: 11138459 | I75: 0 | J75: 0 | K75: 0 | L75: 0 | M75: 1233333 | N75: 0 | O75: =+P75+Q75 -> 9138459 | P75: 0 | Q75: 9138459 | R75: 0 | S75: 0 | T75: 0 | U75: 0 | V75: 766667 | W75: 0 | X75: 0 | Y75: 0
A76: =A75+10 -> 600 | B76: Бюджетные организации | C76: =SUM(J76:Y76)-L76-P76-Q76 -> 0 | D76: 0 | E76: 0 | F76: 0 | G76: 0 | H76: 0 | I76: 0 | J76: 0 | K76: 0 | L76: 0 | M76: 0 | N76: 0 | O76: =+P76+Q76 -> 0 | P76: 0 | Q76: 0 | R76: 0 | S76: 0 | T76: 0 | U76: 0 | V76: 0 | W76: 0 | X76: 0 | Y76: 0
A77: =A76+10 -> 610 | B77: Прочие | C77: =SUM(J77:Y77)-L77-P77-Q77 -> 31539027 | D77: 31539027 | E77: 0.49813966 | F77: 0 | G77: 0 | H77: 31539027 | I77: 0 | J77: 0 | K77: 0 | L77: 0 | M77: 27001931 | N77: 0 | O77: =+P77+Q77 -> 4511642 | P77: 66989 | Q77: 4444653 | R77: 0 | S77: 0 | T77: 0 | U77: 0 | V77: 25454 | W77: 0 | X77: 0 | Y77: 0
A78: =A77+10 -> 620 | B78: Итого по другим отраслям | C78: =SUM(J78:Y78)-L78-P78-Q78 -> 2611126069 | D78: =SUM(D67:D77) -> 2119946800 | E78: =IFERROR(((D67*E67)/D78)+((D68*E68)/D78)+((D69*E69)/D78)+((D70*E70)/D78)+((D71*E71)/D78)+((D72*E72)/D78)+((D73*E73)/D78)+((D74*E74)/D78)+((D75*E75)/D78)+((D76*E76)/D78)+((D77*E77)/D78),0) -> 0.21621377 | F78: =SUM(F67:F77) -> 491179269 | G78: =IFERROR(((F67*G67)/F78)+((F68*G68)/F78)+((F69*G69)/F78)+((F70*G70)/F78)+((F71*G71)/F78)+((F72*G72)/F78)+((F73*G73)/F78)+((F74*G74)/F78)+((F75*G75)/F78)+((F76*G76)/F78)+((F77*G77)/F78),0) -> 0.060074092 | H78: =SUM(H67:H77) -> 2584494641 | I78: =SUM(I67:I77) -> 26631428 | J78: =SUM(J67:J77) -> 399750056 | K78: =SUM(K67:K77) -> 32055809 | L78: =SUM(L67:L77) -> 0 | M78: =SUM(M67:M77) -> 395061805 | N78: =SUM(N67:N77) -> 0 | O78: =SUM(O67:O77) -> 1028631043 | ... Y78: =SUM(Y67:Y77) -> 60089562
B79: Кредитные и лизинговые операции
A80: =A78+10 -> 630 | B80: Физические лица | C80: =SUM(J80:Y80)-L80-P80-Q80 -> 1328984229 | D80: =D9+D17+D26+D34+D42+D50+D58+D67 -> 1328984229 | E80: =IFERROR(((D9*E9)/D80)+((D17*E17)/D80)+((D26*E26)/D80)+((D34*E34)/D80)+((D42*E42)/D80)+((D50*E50)/D80)+((D58*E58)/D80)+((D67*E67)/D80),0) -> 0.22435409 | F80: =F9+F17+F26+F34+F42+F50+F58+F67 -> 0 | G80: =IFERROR(((F9*G9)/F80)+((F17*G17)/F80)+((F26*G26)/F80)+((F34*G34)/F80)+((F42*G42)/F80)+((F50*G50)/F80)+((F58*G58)/F80)+((F67*G67)/F80),0) -> 0 | H80: =H9+H17+H26+H34+H42+H50+H58+H67 -> 1315454057 | I80: =I9+I17+I26+I34+I42+I50+I58+I67 -> 13530172 | J80: =J9+J17+J26+J34+J42+J50+J58+J67 -> 244766475 | K80: =K9+K17+K26+K34+K42+K50+K58+K67 -> 0 | L80: =L9+L17+L26+L34+L42+L50+L58+L67 -> 0 | M80: =M9+M17+M26+M34+M42+M50+M58+M67 -> 127172340 | N80: =N9+N17+N26+N34+N42+N50+N58+N67 -> 0 | O80: =O9+O17+O26+O34+O42+O50+O58+O67 -> 395548854 | ... Y80: =Y9+Y17+Y26+Y34+Y42+Y50+Y58+Y67 -> 3168164
A81: =A80+10 -> 640 | B81: Государственные предприятия | C81: =SUM(J81:Y81)-L81-P81-Q81 -> 1012848254 | D81: =D10+D18+D27+D35+D43+D51+D59+D68 -> 657652618 | E81: =IFERROR(((D10*E10)/D81)+((D18*E18)/D81)+((D27*E27)/D81)+((D35*E35)/D81)+((D43*E43)/D81)+((D51*E51)/D81)+((D59*E59)/D81)+((D68*E68)/D81),0) -> 0.15603803 | F81: =F10+F18+F27+F35+F43+F51+F59+F68 -> 355195636 | G81: =IFERROR(((F10*G10)/F81)+((F18*G18)/F81)+((F27*G27)/F81)+((F35*G35)/F81)+((F43*G43)/F81)+((F51*G51)/F81)+((F59*G59)/F81)+((F68*G68)/F81),0) -> 0.062196118 | H81: =H10+H18+H27+H35+H43+H51+H59+H68 -> 1012848254 | I81: =I10+I18+I27+I35+I43+I51+I59+I68 -> 0 | J81: =J10+J18+J27+J35+J43+J51+J59+J68 -> 216263967 | K81: =K10+K18+K27+K35+K43+K51+K59+K68 -> 6562967 | L81: =L10+L18+L27+L35+L43+L51+L59+L68 -> 0 | M81: =M10+M18+M27+M35+M43+M51+M59+M68 -> 22830044 | N81: =N10+N18+N27+N35+N43+N51+N59+N68 -> 0 | O81: =O10+O18+O27+O35+O43+O51+O59+O68 -> 193034370 | ... Y81: =Y10+Y18+Y27+Y35+Y43+Y51+Y59+Y68 -> 0
A82: =A81+10 -> 650 | B82: Совместные и иностранные предприятия | C82: =SUM(J82:Y82)-L82-P82-Q82 -> 286422166 | D82: =D11+D19+D28+D36+D44+D52+D60+D69 -> 90523642 | E82: =IFERROR(((D11*E11)/D82)+((D19*E19)/D82)+((D28*E28)/D82)+((D36*E36)/D82)+((D44*E44)/D82)+((D52*E52)/D82)+((D60*E60)/D82)+((D69*E69)/D82),0) -> 0.16983956 | F82: =F11+F19+F28+F36+F44+F52+F60+F69 -> 195898524 | G82: =IFERROR(((F11*G11)/F82)+((F19*G19)/F82)+((F28*G28)/F82)+((F36*G36)/F82)+((F44*G44)/F82)+((F52*G52)/F82)+((F60*G60)/F82)+((F69*G69)/F82),0) -> 0.087450822 | H82: =H11+H19+H28+H36+H44+H52+H60+H69 -> 284793783 | I82: =I11+I19+I28+I36+I44+I52+I60+I69 -> 1628383 | J82: =J11+J19+J28+J36+J44+J52+J60+J69 -> 0 | K82: =K11+K19+K28+K36+K44+K52+K60+K69 -> 1617795 | L82: =L11+L19+L28+L36+L44+L52+L60+L69 -> 0 | M82: =M11+M19+M28+M36+M44+M52+M60+M69 -> 121677033 | N82: =N11+N19+N28+N36+N44+N52+N60+N69 -> 0 | O82: =O11+O19+O28+O36+O44+O52+O60+O69 -> 163127338 | ... Y82: =Y11+Y19+Y28+Y36+Y44+Y52+Y60+Y69 -> 0
A83: =A82+10 -> 660 | B83: Частные товарищества и корпорации | C83: =SUM(J83:Y83)-L83-P83-Q83 -> 4899373487 | D83: =D12+D20+D29+D37+D45+D53+D61+D70 -> 2585896316 | E83: =IFERROR(((D12*E12)/D83)+((D20*E20)/D83)+((D29*E29)/D83)+((D37*E37)/D83)+((D45*E45)/D83)+((D53*E53)/D83)+((D61*E61)/D83)+((D70*E70)/D83),0) -> 0.19593468 | F83: =F12+F20+F29+F37+F45+F53+F61+F70 -> 2313477171 | G83: =IFERROR(((F12*G12)/F83)+((F20*G20)/F83)+((F29*G29)/F83)+((F37*G37)/F83)+((F45*G45)/F83)+((F53*G53)/F83)+((F61*G61)/F83)+((F70*G70)/F83),0) -> 0.073706888 | H83: =H12+H20+H29+H37+H45+H53+H61+H70 -> 4737195953 | I83: =I12+I20+I29+I37+I45+I53+I61+I70 -> 162177534 | J83: =J12+J20+J29+J37+J45+J53+J61+J70 -> 162423182 | K83: =K12+K20+K29+K37+K45+K53+K61+K70 -> 97367855 | L83: =L12+L20+L29+L37+L45+L53+L61+L70 -> 0 | M83: =M12+M20+M29+M37+M45+M53+M61+M70 -> 1359888779 | N83: =N12+N20+N29+N37+N45+N53+N61+N70 -> 0 | O83: =O12+O20+O29+O37+O45+O53+O61+O70 -> 2964744673 | ... Y83: =Y12+Y20+Y29+Y37+Y45+Y53+Y61+Y70 -> 135037345
A84: =A83+10 -> 670 | B84: Фермерское хозяйство | C84: =SUM(J84:Y84)-L84-P84-Q84 -> 31561978 | D84: =D21 -> 8275439 | E84: =IFERROR(E21,0) -> 0.38188963 | F84: =F21 -> 23286539 | G84: =IFERROR(G21,0) -> 0.11917625 | H84: =H21 -> 31068728 | I84: =I21 -> 493250 | J84: =J21 -> 0 | K84: =K21 -> 493250 | L84: =L21 -> 0 | M84: =M21 -> 2609468 | N84: =N21 -> 0 | O84: =O21 -> 28459260 | ... Y84: =Y21 -> 0
A85: =A84+10 -> 680 | B85: Другие банки | C85: =SUM(J85:Y85)-L85-P85-Q85 -> 0 | D85: =D72 -> 0 | E85: =E72 -> 0 | F85: =F72 -> 0 | G85: =G72 -> 0 | H85: =H72 -> 0 | I85: =I72 -> 0 | J85: =J72 -> 0 | K85: =K72 -> 0 | ... Y85: =Y72 -> 0
A86: =A85+10 -> 690 | B86: Центральный банк | C86: =SUM(J86:Y86)-L86-P86-Q86 -> 0 | D86: =D71 -> 0 | E86: =E71 -> 0 | F86: =F71 -> 0 | G86: =G71 -> 0 | H86: =H71 -> 0 | I86: =I71 -> 0 | J86: =J71 -> 0 | K86: =K71 -> 0 | ... Y86: =Y71 -> 0
A87: =A86+10 -> 700 | B87: Правительство | C87: =SUM(J87:Y87)-L87-P87-Q87 -> 660127 | D87: =D13+D22+D30+D38+D46+D54+D62+D73 -> 660127 | E87: =IFERROR(((D13*E13)/D87)+((D22*E22)/D87)+((D30*E30)/D87)+((D38*E38)/D87)+((D46*E46)/D87)+((D54*E54)/D87)+((D62*E62)/D87)+((D73*E73)/D87),0) -> 0.24627682 | F87: =F13+F22+F30+F38+F46+F54+F62+F73 -> 0 | G87: =IFERROR(((F13*G13)/F87)+((F22*G22)/F87)+((F30*G30)/F87)+((F38*G38)/F87)+((F46*G46)/F87)+((F54*G54)/F87)+((F62*G62)/F87)+((F73*G73)/F87),0) -> 0 | H87: =H13+H22+H30+H38+H46+H54+H62+H73 -> 660127 | I87: =I13+I22+I30+I38+I46+I54+I62+I73 -> 0 | J87: =J13+J22+J30+J38+J46+J54+J62+J73 -> 0 | K87: =K13+K22+K30+K38+K46+K54+K62+K73 -> 0 | L87: =L13+L22+L30+L38+L46+L54+L62+L73 -> 0 | M87: =M13+M22+M30+M38+M46+M54+M62+M73 -> 245777 | N87: =N13+N22+N30+N38+N46+N54+N62+N73 -> 0 | O87: =O13+O22+O30+O38+O46+O54+O62+O73 -> 414350 | ... Y87: =Y13+Y22+Y30+Y38+Y46+Y54+Y62+Y73 -> 0
A88: =A87+10 -> 710 | B88: Небанковские финансовые институты | C88: =SUM(J88:Y88)-L88-P88-Q88 -> 64423145 | D88: =D74 -> 22516363 | E88: =E74 -> 0.21251615 | F88: =F74 -> 41906782 | G88: =G74 -> 0.075 | H88: =H74 -> 64423145 | I88: =I74 -> 0 | J88: =J74 -> 0 | K88: =K74 -> 0 | ... Y88: =Y74 -> 0
A89: =A88+10 -> 720 | B89: Негосударственные некоммерческие организации | C89: =SUM(J89:Y89)-L89-P89-Q89 -> 13925281 | D89: =+D63+D75 -> 7478322 | E89: =IFERROR(((D75*E75)/D78)+((D63*E63)/D65),0) -> 0.0076294936 | F89: =+F63+F75 -> 6446959 | G89: =IFERROR(((F75*G75)/F78)+((F63*G63)/F65),0) -> 0.0010487251 | H89: =+H63+H75 -> 11284664 | I89: =+I63+I75 -> 2640617 | J89: =+J63+J75 -> 0 | K89: =+K63+K75 -> 2349375 | L89: =+L63+L75 -> 0 | M89: =+M63+M75 -> 1233333 | N89: =+N63+N75 -> 0 | O89: =+O63+O75 -> 9138459 | ... Y89: =+Y63+Y75 -> 0
A90: =A89+10 -> 730 | B90: Бюджетные организации | C90: =SUM(J90:Y90)-L90-P90-Q90 -> 0 | D90: =D76 -> 0 | E90: =E76 -> 0 | F90: =F76 -> 0 | G90: =G76 -> 0 | H90: =H76 -> 0 | I90: =I76 -> 0 | J90: =J76 -> 0 | K90: =K76 -> 0 | ... Y90: =Y76 -> 0
A91: =A90+10 -> 740 | B91: Прочие | C91: =SUM(J91:Y91)-L91-P91-Q91 -> 116115203 | D91: =D14+D23+D31+D39+D47+D55+D64+D77 -> 105431915 | E91: =IFERROR(((D14*E14)/D91)+((D23*E23)/D91)+((D31*E31)/D91)+((D39*E39)/D91)+((D47*E47)/D91)+((D55*E55)/D91)+((D64*E64)/D91)+((D77*E77)/D91),0) -> 0.35690076 | F91: =F14+F23+F31+F39+F47+F55+F64+F77 -> 10683288 | G91: =IFERROR(((F14*G14)/F91)+((F23*G23)/F91)+((F31*G31)/F91)+((F39*G39)/F91)+((F47*G47)/F91)+((F55*G55)/F91)+((F64*G64)/F91)+((F77*G77)/F91),0) -> 0.071424944 | H91: =H14+H23+H31+H39+H47+H55+H64+H77 -> 103321898 | I91: =I14+I23+I31+I39+I47+I55+I64+I77 -> 12793305 | J91: =J14+J23+J31+J39+J47+J55+J64+J77 -> 203427 | K91: =K14+K23+K31+K39+K47+K55+K64+K77 -> 2213060 | L91: =L14+L23+L31+L39+L47+L55+L64+L77 -> 0 | M91: =M14+M23+M31+M39+M47+M55+M64+M77 -> 73033210 | N91: =N14+N23+N31+N39+N47+N55+N64+N77 -> 0 | O91: =O14+O23+O31+O39+O47+O55+O64+O77 -> 30358207 | ... Y91: =Y14+Y23+Y31+Y39+Y47+Y55+Y64+Y77 -> 799500
A92: =A91+10 -> 750 | B92: Итого кредита и лизинга | C92: =SUM(J92:Y92)-L92-P92-Q92 -> 7754313870 | D92: =SUM(D80:D91) -> 4807418971 | E92: =IFERROR(((D80*E80)/D92)+((D81*E81)/D92)+((D82*E82)/D92)+((D83*E83)/D92)+((D84*E84)/D92)+((D85*E85)/D92)+((D86*E86)/D92)+((D87*E87)/D92)+((D88*E88)/D92)+((D89*E89)/D92)+((D90*E90)/D92)+((D91*E91)/D92),0) -> 0.20148377 | F92: =SUM(F80:F91) -> 2946894899 | G92: =IFERROR(((F80*G80)/F92)+((F81*G81)/F92)+((F82*G82)/F92)+((F83*G83)/F92)+((F84*G84)/F92)+((F85*G85)/F92)+((F86*G86)/F92)+((F87*G87)/F92)+((F88*G88)/F92)+((F89*G89)/F92)+((F90*G90)/F92)+((F91*G91)/F92),0) -> 0.073443578 | H92: =SUM(H80:H91) -> 7561050609 | I92: =SUM(I80:I91) -> 193263261 | J92: =SUM(J80:J91) -> 623657051 | K92: =SUM(K80:K91) -> 110604302 | L92: =SUM(L80:L91) -> 0 | M92: =SUM(M80:M91) -> 1708689984 | N92: =SUM(N80:N91) -> 0 | O92: =SUM(O80:O91) -> 3807341874 | ... Y92: =SUM(Y80:Y91) -> 139005009
B95: Подпись Председателя правления:
B97: Подпись Главного Бухгалтера:
C99: =+[8]Balance!$C$24 -> 7754313870
C100: =+C92-C99 -> 0

Sheet Aging Analysis
A1: АНАЛИЗ ПРОСРОЧЕННЫХ КРЕДИТОВ И ФИНАНСОВОГО ЛИЗИНГА К ПОЛУЧЕНИЮ | X1: Таблица-9
B3: =+'Asset quality'!B3 -> АК "АЛОКАБАНК" | T3: =+'Asset quality'!P3 -> 44561 | X3: тыс. сум
A4: № | B4: Характеристики | C4: Всего задолжность по кредитам | D4: % | E4: Реструктуризированные кредиты | F4: % | G4: В ходе судебного разбирательства | H4: % | I4: Просроченная задолжность | K4: % | L4: в том числе, анализ временной задолженности
L5: 1-30 дней | N5: 31-60 дней | P5: 61-90 дней | R5: 91-180 дней | T5: 181-365 дней | V5: 366-730 дней | X5: Свыше 2 лет
I6: основной долг | J6: процент | L6: основной долг | M6: процент | N6: основной долг | O6: процент | P6: основной долг | Q6: процент | R6: основной долг | S6: процент | T6: основной долг | U6: процент | V6: основной долг | W6: процент | X6: основной долг | Y6: процент
B7: (А) | C7: (Б) | D7: (В) | E7: (Г) | F7: (Д) | G7: (Е) | H7: (Ж) | I7: (З) | J7: (З1) | K7: (И) | L7: (К) | M7: (К1) | N7: (Л) | O7: (Л1) | P7: (М) | Q7: (М1) | R7: (Н) | S7: (Н1) | T7: (О) | U7: (О1) | V7: (П) | W7: (П1) | X7: (Р) | Y7: (Р1)
B8: По типу клиента
A9: 1 | B9: Центральный банк | C9: =+'Loans Receivable'!C86 -> 0 | D9: =IF(C$22=0,"",C9/C$22) -> 0 | F9: =IF(E$22=0,"",E9/E$22) -> 0 | H9: =IF($G$22=0,"",G9/$G$22) -> 0 | I9: =+L9+N9+P9+R9+T9+V9+X9 -> 0 | J9: =+M9+O9+T9+S9+U9+W9+Y9 -> 0 | K9: =IF($Z$22=0,"",Z9/$Z$22) -> 0 | Z9: =+I9+J9 -> 0
A10: 2 | B10: Другие банки | C10: =+'Loans Receivable'!C85 -> 0 | D10: =IF(C$22=0,"",C10/C$22) -> 0 | F10: =IF(E$22=0,"",E10/E$22) -> 0 | H10: =IF($G$22=0,"",G10/$G$22) -> 0 | I10: =+L10+N10+P10+R10+T10+V10+X10 -> 0 | J10: =+M10+O10+Q10+S10+U10+W10+Y10 -> 0 | K10: =IF($Z$22=0,"",Z10/$Z$22) -> 0 | Z10: =+I10+J10 -> 0
A11: 3 | B11: Правительство | C11: =+'Loans Receivable'!C87 -> 660127 | D11: =IF(C$22=0,"",C11/C$22) -> 8.5130291e-05 | F11: =IF(E$22=0,"",E11/E$22) -> 0 | H11: =IF($G$22=0,"",G11/$G$22) -> 0 | I11: =+L11+N11+P11+R11+T11+V11+X11 -> 0 | J11: =+M11+O11+Q11+S11+U11+W11+Y11 -> 0 | K11: =IF($Z$22=0,"",Z11/$Z$22) -> 0 | Z11: =+I11+J11 -> 0
A12: 4 | B12: Физические лица | C12: =+'Loans Receivable'!C80 -> 1328984229 | D12: =IF(C$22=0,"",C12/C$22) -> 0.17138644 | F12: =IF(E$22=0,"",E12/E$22) -> 0 | H12: =IF($G$22=0,"",G12/$G$22) -> 0 | I12: =+L12+N12+P12+R12+T12+V12+X12 -> 21416469 | J12: =+M12+O12+Q12+S12+U12+W12+Y12 -> 8847933 | K12: =IF($Z$22=0,"",Z12/$Z$22) -> 0.26250251 | L12: 6983807 | M12: 1007743 | N12: 1852911 | O12: 469828 | P12: 1107576 | Q12: 326707 | R12: 3971731 | S12: 1389783 | T12: 3354745 | U12: 1563169 | V12: 3240354 | W12: 3808972 | X12: 905345 | Y12: 281731 | Z12: =+I12+J12 -> 30264402
A13: 5 | B13: Государственные предприятия | C13: =+'Loans Receivable'!C81 -> 1012848254 | D13: =IF(C$22=0,"",C13/C$22) -> 0.13061739 | F13: =IF(E$22=0,"",E13/E$22) -> 0 | H13: =IF($G$22=0,"",G13/$G$22) -> 0 | I13: =+L13+N13+P13+R13+T13+V13+X13 -> 750816 | J13: =+M13+O13+Q13+S13+U13+W13+Y13 -> 2258225 | K13: =IF($Z$22=0,"",Z13/$Z$22) -> 0.026099336 | L13: 750816 | M13: 33284 | N13: 0 | O13: 2224941 | R13: 0 | S13: 0 | Z13: =+I13+J13 -> 3009041
A14: 6 | B14: Совместные и иностранные предприятия | C14: =+'Loans Receivable'!C82 -> 286422166 | D14: =IF(C$22=0,"",C14/C$22) -> 0.036937139 | F14: =IF(E$22=0,"",E14/E$22) -> 0 | G14: 10587 | H14: =IF($G$22=0,"",G14/$G$22) -> 0.0012337027 | I14: =+L14+N14+P14+R14+T14+V14+X14 -> 342795 | J14: =+M14+O14+Q14+S14+U14+W14+Y14 -> 514 | K14: =IF($Z$22=0,"",Z14/$Z$22) -> 0.0029777384 | L14: 0 | M14: 0 | N14: 0 | O14: 0 | R14: 0 | S14: 514 | T14: 342795 | U14: 0 | X14: 0 | Y14: 0 | Z14: =+I14+J14 -> 343309
A15: 7 | B15: Частные товарищества и корпорации | C15: =+'Loans Receivable'!C83 -> 4899373487 | D15: =IF(C$22=0,"",C15/C$22) -> 0.63182553 | E15: 44554200 | F15: =IF(E$22=0,"",E15/E$22) -> 1 | G15: 7163339 | H15: =IF($G$22=0,"",G15/$G$22) -> 0.83474362 | I15: =+L15+N15+P15+R15+T15+V15+X15 -> 62040029 | J15: =+M15+O15+Q15+S15+U15+W15+Y15 -> 13553810 | K15: =IF($Z$22=0,"",Z15/$Z$22) -> 0.65567369 | L15: 9371337 | M15: 2211377 | N15: 2621766 | O15: 1412828 | P15: 1168166 | Q15: 294455 | R15: 22342065 | S15: 5456020 | T15: 15886265 | U15: 3082944 | V15: 8414225 | W15: 599682 | X15: 2236205 | Y15: 496504 | Z15: =+I15+J15 -> 75593839
A16: 8 | B16: Фермерское хозяйство | C16: =+'Loans Receivable'!C84 -> 31561978 | D16: =IF(C$22=0,"",C16/C$22) -> 0.0040702477 | F16: =IF(E$22=0,"",E16/E$22) -> 0 | H16: =IF($G$22=0,"",G16/$G$22) -> 0 | I16: =+L16+N16+P16+R16+T16+V16+X16 -> 506408 | J16: =+M16+O16+Q16+S16+U16+W16+Y16 -> 29567 | K16: =IF($Z$22=0,"",Z16/$Z$22) -> 0.0046488538 | L16: 13158 | M16: 20014 | P16: 0 | Q16: 9553 | X16: 493250 | Y16: 0 | Z16: =+I16+J16 -> 535975
A17: 9 | B17: Небанковские финансовые институты | C17: =+'Loans Receivable'!C88 -> 64423145 | D17: =IF(C$22=0,"",C17/C$22) -> 0.0083080394 | F17: =IF(E$22=0,"",E17/E$22) -> 0 | H17: =IF($G$22=0,"",G17/$G$22) -> 0 | I17: =+L17+N17+P17+R17+T17+V17+X17 -> 0 | J17: =+M17+O17+Q17+S17+U17+W17+Y17 -> 0 | K17: =IF($Z$22=0,"",Z17/$Z$22) -> 0 | L17: 0 | M17: 0 | Z17: =+I17+J17 -> 0
A18: 10 | B18: Негосударственные некоммерческие организации | C18: =+'Loans Receivable'!C89 -> 13925281 | D18: =IF(C$22=0,"",C18/C$22) -> 0.0017958109 | F18: =IF(E$22=0,"",E18/E$22) -> 0 | H18: =IF($G$22=0,"",G18/$G$22) -> 0 | I18: =+L18+N18+P18+R18+T18+V18+X18 -> 15570 | J18: =+M18+O18+Q18+S18+U18+W18+Y18 -> 1314 | K18: =IF($Z$22=0,"",Z18/$Z$22) -> 0.00014644573 | L18: 0 | M18: 50 | N18: 982 | O18: 1264 | R18: 0 | S18: 0 | T18: 0 | U18: 0 | V18: 14588 | W18: 0 | X18: 0 | Y18: 0 | Z18: =+I18+J18 -> 16884
A19: 11 | B19: Бюджетные организации | C19: =+'Loans Receivable'!C90 -> 0 | D19: =IF(C$22=0,"",C19/C$22) -> 0 | F19: =IF(E$22=0,"",E19/E$22) -> 0 | H19: =IF($G$22=0,"",G19/$G$22) -> 0 | I19: =+L19+N19+P19+R19+T19+V19+X19 -> 0 | J19: =+M19+O19+Q19+S19+U19+W19+Y19 -> 0 | K19: =IF($Z$22=0,"",Z19/$Z$22) -> 0 | Z19: =+I19+J19 -> 0
A20: 12 | B20: Прочие | C20: =+'Loans Receivable'!C91 -> 116115203 | D20: =IF(C$22=0,"",C20/C$22) -> 0.014974272 | F20: =IF(E$22=0,"",E20/E$22) -> 0 | G20: 1407558 | H20: =IF($G$22=0,"",G20/$G$22) -> 0.16402268 | I20: =+L20+N20+P20+R20+T20+V20+X20 -> 5208594 | J20: =+M20+O20+Q20+S20+U20+W20+Y20 -> 319815 | K20: =IF($Z$22=0,"",Z20/$Z$22) -> 0.047951426 | L20: 762450 | M20: 63465 | N20: 28511 | O20: 4219 | P20: 46545 | Q20: 21801 | R20: 769363 | S20: 187238 | T20: 1073592 | U20: 39440 | V20: 2012376 | W20: 3652 | X20: 515757 | Y20: 0 | Z20: =+I20+J20 -> 5528409
Z21: =+I21+J21 -> 0
A22: 13 | B22: Итого кредита и лизинга | C22: =SUM(C9:C20) -> 7754313870 | D22: =IF(C$22=0,"",C22/C$22) -> 1 | E22: =SUM(E9:E20) -> 44554200 | F22: =IF(E$22=0,"",E22/E$22) -> 1 | G22: =SUM(G9:G20) -> 8581484 | H22: =IF($G$22=0,"",G22/$G$22) -> 1 | I22: =SUM(I9:I20) -> 90280681 | J22: =SUM(J9:J20) -> 25011178 | K22: =IF($Z$22=0,"",Z22/$Z$22) -> 1 | L22: =SUM(L9:L20) -> 17881568 | M22: =SUM(M9:M20) -> 3335933 | N22: =SUM(N9:N20) -> 4504170 | O22: =SUM(O9:O20) -> 4113080 | P22: =SUM(P9:P20) -> 2322287 | Q22: =SUM(Q9:Q20) -> 652516 | R22: =SUM(R9:R20) -> 27083159 | S22: =SUM(S9:S20) -> 7033555 | ... Y22: =SUM(Y9:Y20) -> 778235 | Z22: =+I22+J22 -> 115291859
Z23: =+I23+J23 -> 0
B24: По сектору экономики | F24: =IF(E$22=0,"",E24/E$22) -> 0 | Z24: =+I24+J24 -> 0
A25: 14 | B25: Промышленность | C25: =+'Loans Receivable'!C15 -> 2695352702 | D25: =IF(C$34=0,"",C25/C$34) -> 0.34759396 | E25: 17028003 | F25: =IF($E$34=0,"",E25/$E$34) -> 0.38218626 | G25: 1908777 | H25: =IF($G$34=0,"",G25/$G$34) -> 0.22242971 | I25: =+L25+N25+P25+R25+T25+V25+X25 -> 21315945 | J25: =+M25+O25+Q25+S25+U25+W25+Y25 -> 7824082 | K25: =IF($Z$34=0,"",Z25/$Z$34) -> 0.25275008 | L25: 4989820 | M25: 694619 | N25: 1400145 | O25: 2576206 | P25: 440362 | Q25: 51690 | R25: 4898554 | S25: 1094983 | T25: 8124909 | U25: 2525435 | V25: 478870 | W25: 384644 | X25: 983285 | Y25: 496505 | Z25: =+I25+J25 -> 29140027
A26: 15 | B26: Сельское хозяйство | C26: =+'Loans Receivable'!C24 -> 233885083 | D26: =IF(C$34=0,"",C26/C$34) -> 0.030161931 | E26: 53826 | F26: =IF($E$34=0,"",E26/$E$34) -> 0.0012081016 | G26: 570157 | H26: =IF($G$34=0,"",G26/$G$34) -> 0.066440373 | I26: =+L26+N26+P26+R26+T26+V26+X26 -> 4198127 | J26: =+M26+O26+Q26+S26+U26+W26+Y26 -> 544168 | K26: =IF($Z$34=0,"",Z26/$Z$34) -> 0.041132956 | L26: 777206 | M26: 193249 | N26: 90242 | O26: 90340 | P26: 71734 | Q26: 45482 | R26: 736520 | S26: 203626 | T26: 2029175 | U26: 7819 | V26: 0 | W26: 3652 | X26: 493250 | Y26: 0 | Z26: =+I26+J26 -> 4742295
A27: 16 | B27: Транспорт и коммуникации | C27: =+'Loans Receivable'!C32 -> 826803668 | D27: =IF(C$34=0,"",C27/C$34) -> 0.10662499 | E27: 0 | F27: =IF($E$34=0,"",E27/$E$34) -> 0 | G27: 127871 | H27: =IF($G$34=0,"",G27/$G$34) -> 0.014900803 | I27: =+L27+N27+P27+R27+T27+V27+X27 -> 5107551 | J27: =+M27+O27+Q27+S27+U27+W27+Y27 -> 841528 | K27: =IF($Z$34=0,"",Z27/$Z$34) -> 0.051600165 | L27: 1727340 | M27: 316039 | N27: 11416 | O27: 43719 | P27: 466434 | Q27: 118847 | R27: 654740 | S27: 195014 | T27: 2247621 | U27: 167909 | V27: 0 | W27: 0 | X27: 0 | Y27: 0 | Z27: =+I27+J27 -> 5949079
A28: 17 | B28: Строительство | C28: =+'Loans Receivable'!C40 -> 535003135 | D28: =IF(C$34=0,"",C28/C$34) -> 0.068994258 | E28: 0 | F28: =IF($E$34=0,"",E28/$E$34) -> 0 | G28: 1252173 | H28: =IF($G$34=0,"",G28/$G$34) -> 0.14591567 | I28: =+L28+N28+P28+R28+T28+V28+X28 -> 5072127 | J28: =+M28+O28+Q28+S28+U28+W28+Y28 -> 1219058 | K28: =IF($Z$34=0,"",Z28/$Z$34) -> 0.05456747 | L28: 938081 | M28: 181817 | N28: 471607 | O28: 519589 | P28: 0 | Q28: 94718 | R28: 3217995 | S28: 422934 | T28: 444444 | U28: 0 | V28: 0 | W28: 0 | Z28: =+I28+J28 -> 6291185
A29: 18 | B29: Торговля и общественное питание | C29: =+'Loans Receivable'!C48 -> 706694385 | D29: =IF(C$34=0,"",C29/C$34) -> 0.091135644 | E29: 27472371 | F29: =IF($E$34=0,"",E29/$E$34) -> 0.61660564 | G29: 1206335 | H29: =IF($G$34=0,"",G29/$G$34) -> 0.14057417 | I29: =+L29+N29+P29+R29+T29+V29+X29 -> 20242736 | J29: =+M29+O29+Q29+S29+U29+W29+Y29 -> 4444074 | K29: =IF($Z$34=0,"",Z29/$Z$34) -> 0.21412449 | L29: 2069452 | M29: 742853 | N29: 199978 | O29: 28722 | P29: 236182 | Q29: 14806 | R29: 12456044 | S29: 3524791 | T29: 2314382 | U29: 132902 | V29: 2337303 | W29: 0 | X29: 629395 | Y29: 0 | Z29: =+I29+J29 -> 24686810
A30: 19 | B30: Материально-техническое снабжение и сбыт | C30: =+'Loans Receivable'!C56 -> 83306275 | D30: =IF(C$34=0,"",C30/C$34) -> 0.010743217 | F30: =IF($E$34=0,"",E30/$E$34) -> 0 | G30: 0 | H30: =IF($G$34=0,"",G30/$G$34) -> 0 | I30: =+L30+N30+P30+R30+T30+V30+X30 -> 8649925 | J30: =+M30+O30+Q30+S30+U30+W30+Y30 -> 71914 | K30: =IF($Z$34=0,"",Z30/$Z$34) -> 0.075650086 | L30: 38286 | M30: 3992 | N30: 476780 | O30: 0 | T30: 1175000 | U30: 67922 | V30: 6959859 | W30: 0 | X30: 0 | Y30: 0 | Z30: =+I30+J30 -> 8721839
A31: 20 | B31: Жилищно-коммунальные услуги | C31: =+'Loans Receivable'!C65 -> 62142553 | D31: =IF(C$34=0,"",C31/C$34) -> 0.0080139332 | F31: =IF($E$34=0,"",E31/$E$34) -> 0 | G31: 1553987 | H31: =IF($G$34=0,"",G31/$G$34) -> 0.18108605 | I31: =+L31+N31+P31+R31+T31+V31+X31 -> 1430600 | J31: =+M31+O31+Q31+S31+U31+W31+Y31 -> 220342 | K31: =IF($Z$34=0,"",Z31/$Z$34) -> 0.014319675 | L31: 19834 | M31: 2199 | N31: 1090 | O31: 1426 | R31: 59141 | S31: 1679 | T31: 169621 | U31: 0 | V31: 665157 | W31: 215038 | X31: 515757 | Y31: 0 | Z31: =+I31+J31 -> 1650942
A32: 21 | B32: Другие сектора | C32: =+'Loans Receivable'!C78 -> 2611126069 | D32: =IF(C$34=0,"",C32/C$34) -> 0.33673206 | F32: =IF($E$34=0,"",E32/$E$34) -> 0 | G32: 1962184 | H32: =IF($G$34=0,"",G32/$G$34) -> 0.22865323 | I32: =+L32+N32+P32+R32+T32+V32+X32 -> 24263670 | J32: =+M32+O32+Q32+S32+U32+W32+Y32 -> 9846012 | K32: =IF($Z$34=0,"",Z32/$Z$34) -> 0.29585508 | L32: 7321549 | M32: 1201165 | N32: 1852912 | O32: 853078 | P32: 1107575 | Q32: 326973 | R32: 5060165 | S32: 1590528 | T32: 4152245 | U32: 1783566 | V32: 3240354 | W32: 3808972 | X32: 1528870 | Y32: 281730 | Z32: =+I32+J32 -> 34109682
Z33: =+I33+J33 -> 0
A34: 22 | B34: Итого кредита и лизинга | C34: =SUM(C25:C32) -> 7754313870 | D34: =IF(C$34=0,"",C34/C$34) -> 1 | E34: =SUM(E25:E32) -> 44554200 | F34: =IF($E$34=0,"",E34/$E$34) -> 1 | G34: =SUM(G25:G32) -> 8581484 | H34: =IF($G$34=0,"",G34/$G$34) -> 1 | I34: =SUM(I25:I32) -> 90280681 | J34: =SUM(J25:J32) -> 25011178 | K34: =IF($Z$34=0,"",Z34/$Z$34) -> 1 | L34: =SUM(L25:L32) -> 17881568 | M34: =SUM(M25:M32) -> 3335933 | N34: =SUM(N25:N32) -> 4504170 | O34: =SUM(O25:O32) -> 4113080 | P34: =SUM(P25:P32) -> 2322287 | Q34: =SUM(Q25:Q32) -> 652516 | R34: =SUM(R25:R32) -> 27083159 | S34: =SUM(S25:S32) -> 7033555 | ... Y34: =SUM(Y25:Y32) -> 778235 | Z34: =+I34+J34 -> 115291859
B37: Подпись Председателя правления:
B39: Подпись Главного Бухгалтера:

Sheet Asset Classification
A1: ОТЧЕТ О КЛАССИФИКАЦИИ АКТИВОВ ПО СТЕПЕНИ РИСКА | W1: Таблица-10
B2: =+'Asset quality'!B3 -> АК "АЛОКАБАНК" | U2: =+'Asset quality'!P3 -> 44561 | Z2: тыс. сум
A3: № | B3: Статьи баланса | C3: Общая сумма | D3: из них, в иностранной валюте (в экв. в сумах) | E3: Стандартные | F3: из них, в иностранной валюте (в экв. в сумах) | G3: Общие резервы (1%) | H3: из них, в иностранной валюте (в экв. в сумах) | I3: Субстандартные | J3: из них, в иностранной валюте (в экв. в сумах) | K3: Специальные резервы (мин 10%) | L3: из них, в иностранной валюте (в экв. в сумах) | M3: Неудовлетворительные | N3: из них, в иностранной валюте (в экв. в сумах) | O3: Специальные резервы (мин 25%) | P3: из них, в иностранной валюте (в экв. в сумах) | Q3: Сомнительные | R3: из них, в иностранной валюте (в экв. в сумах) | S3: Специальные резервы (мин 50%) | T3: из них, в иностранной валюте (в экв. в сумах) | U3: Безнадежные | V3: из них, в иностранной валюте (в экв. в сумах) | W3: Специальные резервы (100%) | X3: из них, в иностранной валюте (в экв. в сумах) | Y3: Совокупная сумма специальных резервов | Z3: из них, в иностранной валюте (в экв. в сумах) | AA3: списанные кредиты за баланс в отчётном месяце | AB3: возврат списанных кредитов в отчётном месяце
A4: (А) | B4: (Б) | C4: (В) | D4: (В1) | E4: (Г) | F4: (Г1) | G4: (Д) | H4: (Д1) | I4: (Е) | J4: (Е1) | K4: (Ж) | L4: (Ж1) | M4: (З) | N4: (З1) | O4: (И) | P4: (И1) | Q4: (К) | R4: (К1) | S4: (Л) | T4: (Л1) | U4: (М) | V4: (М1) | W4: (Н) | X4: (Н1) | Y4: О=Ж+И+Л+Н | Z4: (О1)=(Ж1)+(И1)+(Л1)+(Н1) | AA4: П | AB4: Р
B5: По типу клиента
A6: 1 | B6: Центральный банк | C6: =E6+I6+M6+Q6+U6 -> 0 | D6: =F6+J6+N6+R6+V6 -> 0 | Y6: =+W6+S6+O6+K6 -> 0 | Z6: =+X6+T6+P6+L6 -> 0 | AC6: =+'Aging Analysis'!C9 -> 0
B7: из них необеспеченные | C7: =E7+I7+M7+Q7+U7 -> 0 | D7: =F7+J7+N7+R7+V7 -> 0 | Y7: =+W7+S7+O7+K7 -> 0 | Z7: =+X7+T7+P7+L7 -> 0
A8: 2 | B8: Другие банки | C8: =E8+I8+M8+Q8+U8 -> 0 | D8: =F8+J8+N8+R8+V8 -> 0 | Y8: =+W8+S8+O8+K8 -> 0 | Z8: =+X8+T8+P8+L8 -> 0 | AC8: =+'Aging Analysis'!C10 -> 0
B9: из них необеспеченные | C9: =E9+I9+M9+Q9+U9 -> 0 | D9: =F9+J9+N9+R9+V9 -> 0 | Y9: =+W9+S9+O9+K9 -> 0 | Z9: =+X9+T9+P9+L9 -> 0
A10: 3 | B10: Правительство | C10: =E10+I10+M10+Q10+U10 -> 660127 | D10: =F10+J10+N10+R10+V10 -> 0 | E10: 660127 | F10: 0 | G10: 5703 | H10: 0 | I10: 0 | J10: 0 | K10: 0 | L10: 0 | M10: 0 | N10: 0 | O10: 0 | P10: 0 | Q10: 0 | R10: 0 | S10: 0 | T10: 0 | U10: 0 | V10: 0 | W10: 0 | X10: 0 | Y10: =+W10+S10+O10+K10 -> 0 | Z10: =+X10+T10+P10+L10 -> 0 | AC10: =+'Aging Analysis'!C11 -> 660127
B11: из них необеспеченные | C11: =E11+I11+M11+Q11+U11 -> 0 | D11: =F11+J11+N11+R11+V11 -> 0 | E11: 0 | F11: 0 | G11: 0 | H11: 0 | I11: 0 | J11: 0 | K11: 0 | L11: 0 | M11: 0 | N11: 0 | O11: 0 | P11: 0 | Q11: 0 | R11: 0 | S11: 0 | T11: 0 | U11: 0 | V11: 0 | W11: 0 | X11: 0 | Y11: =+W11+S11+O11+K11 -> 0 | Z11: =+X11+T11+P11+L11 -> 0
A12: 4 | B12: Физические лица | C12: =E12+I12+M12+Q12+U12 -> 1328984229 | D12: =F12+J12+N12+R12+V12 -> 0 | E12: 1196175378 | F12: 0 | G12: 10334786 | H12: 0 | I12: 54715259 | J12: 0 | K12: 4895843 | L12: 0 | M12: 13772216 | N12: 0 | O12: 2687207 | P12: 0 | Q12: 22457893 | R12: 0 | S12: =10444374+145542 -> 10589916 | T12: 0 | U12: 41863483 | V12: 0 | W12: 27962194 | X12: 0 | Y12: =+W12+S12+O12+K12 -> 46135160 | Z12: =+X12+T12+P12+L12 -> 0 | AA12: 10700384 | AC12: =+'Aging Analysis'!C12 -> 1328984229
B13: из них необеспеченные | C13: =E13+I13+M13+Q13+U13 -> 0 | D13: =F13+J13+N13+R13+V13 -> 0 | E13: 0 | F13: 0 | G13: 0 | H13: 0 | I13: 0 | J13: 0 | K13: 0 | L13: 0 | M13: 0 | N13: 0 | O13: 0 | P13: 0 | Q13: 0 | R13: 0 | S13: 0 | T13: 0 | U13: 0 | V13: 0 | W13: 0 | X13: 0 | Y13: =+W13+S13+O13+K13 -> 0 | Z13: =+X13+T13+P13+L13 -> 0
A14: 5 | B14: Государственные предприятия | C14: =E14+I14+M14+Q14+U14 -> 1012848254 | D14: =F14+J14+N14+R14+V14 -> 355195636 | E14: 952098280 | F14: 355195636 | G14: 8225994 | H14: 0 | I14: 60749974 | J14: 0 | K14: 75082 | L14: 0 | M14: 0 | N14: 0 | O14: 0 | P14: 0 | Q14: 0 | R14: 0 | S14: 0 | T14: 0 | U14: 0 | V14: 0 | W14: 0 | X14: 0 | Y14: =+W14+S14+O14+K14 -> 75082 | Z14: =+X14+T14+P14+L14 -> 0 | AA14: 25644 | AC14: =+'Aging Analysis'!C13 -> 1012848254
B15: из них необеспеченные | C15: =E15+I15+M15+Q15+U15 -> 0 | D15: =F15+J15+N15+R15+V15 -> 0 | E15: 0 | F15: 0 | G15: 0 | H15: 0 | I15: 0 | J15: 0 | K15: 0 | L15: 0 | M15: 0 | N15: 0 | O15: 0 | P15: 0 | Q15: 0 | R15: 0 | S15: 0 | T15: 0 | U15: 0 | V15: 0 | W15: 0 | X15: 0 | Y15: =+W15+S15+O15+K15 -> 0 | Z15: =+X15+T15+P15+L15 -> 0
A16: 6 | B16: Совместные и иностранные предприятия | C16: =E16+I16+M16+Q16+U16 -> 286422166 | D16: =F16+J16+N16+R16+V16 -> 195898524 | E16: 239967236 | F16: 195898524 | G16: 2073283 | H16: 0 | I16: 44826548 | J16: 0 | K16: 0 | L16: 0 | M16: 1617795 | N16: 0 | O16: 161780 | P16: 0 | Q16: 0 | R16: 0 | S16: 0 | T16: 0 | U16: 10587 | V16: 0 | W16: 35587 | X16: 0 | Y16: =+W16+S16+O16+K16 -> 197367 | Z16: =+X16+T16+P16+L16 -> 0 | AC16: =+'Aging Analysis'!C14 -> 286422166
B17: из них необеспеченные | C17: =E17+I17+M17+Q17+U17 -> 0 | D17: =F17+J17+N17+R17+V17 -> 0 | E17: 0 | F17: 0 | G17: 0 | H17: 0 | I17: 0 | J17: 0 | K17: 0 | L17: 0 | M17: 0 | N17: 0 | O17: 0 | P17: 0 | Q17: 0 | R17: 0 | S17: 0 | T17: 0 | U17: 0 | V17: 0 | W17: 0 | X17: 0 | Y17: =+W17+S17+O17+K17 -> 0 | Z17: =+X17+T17+P17+L17 -> 0
A18: 7 | B18: Частные товарищества и корпорации | C18: =E18+I18+M18+Q18+U18 -> 4899373487 | D18: =F18+J18+N18+R18+V18 -> 2313477171 | E18: 4232045735 | F18: 2123010132 | G18: 36564277 | H18: 387773 | I18: 448813216 | J18: 101657876 | K18: 14065802 | L18: 8960696 | M18: 55373590 | N18: 48446241 | O18: 3354946 | P18: 2080260 | Q18: 50166487 | R18: 5277170 | S18: =5348256-145542 -> 5202714 | T18: 626974 | U18: 112974459 | V18: 35085752 | W18: =20374591+1397824 -> 21772415 | X18: 2951959 | Y18: =+W18+S18+O18+K18 -> 44395877 | Z18: =+X18+T18+P18+L18 -> 14619889 | AA18: 11159578 | AC18: =+'Aging Analysis'!C15 -> 4899373487
B19: из них необеспеченные | C19: =E19+I19+M19+Q19+U19 -> 0 | D19: =F19+J19+N19+R19+V19 -> 0 | E19: 0 | F19: 0 | G19: 0 | H19: 0 | I19: 0 | J19: 0 | K19: 0 | L19: 0 | M19: 0 | N19: 0 | O19: 0 | P19: 0 | Q19: 0 | R19: 0 | S19: 0 | T19: 0 | U19: 0 | V19: 0 | W19: 0 | X19: 0 | Y19: =+W19+S19+O19+K19 -> 0 | Z19: =+X19+T19+P19+L19 -> 0
A20: 8 | B20: Фермерское хозяйство | C20: =E20+I20+M20+Q20+U20 -> 31561978 | D20: =F20+J20+N20+R20+V20 -> 23828423 | E20: =30097106-850791 -> 29246315 | F20: 22217203 | G20: 252684 | H20: 0 | I20: 1822413 | J20: 1611220 | K20: 182241 | L20: 161122 | M20: 0 | N20: 0 | O20: 0 | P20: 0 | Q20: 0 | R20: 0 | S20: 0 | T20: 0 | U20: 493250 | V20: 0 | W20: 493250 | X20: 0 | Y20: =+W20+S20+O20+K20 -> 675491 | Z20: =+X20+T20+P20+L20 -> 161122 | AC20: =+'Aging Analysis'!C16 -> 31561978
B21: из них необеспеченные | C21: =E21+I21+M21+Q21+U21 -> 0 | D21: =F21+J21+N21+R21+V21 -> 0 | E21: 0 | F21: 0 | G21: 0 | H21: 0 | I21: 0 | J21: 0 | K21: 0 | L21: 0 | M21: 0 | N21: 0 | O21: 0 | P21: 0 | Q21: 0 | R21: 0 | S21: 0 | T21: 0 | U21: 0 | V21: 0 | W21: 0 | X21: 0 | Y21: =+W21+S21+O21+K21 -> 0 | Z21: =+X21+T21+P21+L21 -> 0
A22: 9 | B22: Небанковские финансовые институты | C22: =E22+I22+M22+Q22+U22 -> 64423145 | D22: =F22+J22+N22+R22+V22 -> 41906782 | E22: 64423145 | F22: 41906782 | G22: 556607 | H22: 0 | I22: 0 | J22: 0 | K22: 0 | L22: 0 | M22: 0 | N22: 0 | O22: 0 | P22: 0 | Q22: 0 | R22: 0 | S22: 0 | T22: 0 | U22: 0 | V22: 0 | W22: 0 | X22: 0 | Y22: =+W22+S22+O22+K22 -> 0 | Z22: =+X22+T22+P22+L22 -> 0 | AC22: =+'Aging Analysis'!C17 -> 64423145
B23: из них необеспеченные | C23: =E23+I23+M23+Q23+U23 -> 0 | D23: =F23+J23+N23+R23+V23 -> 0 | E23: 0 | F23: 0 | G23: 0 | H23: 0 | I23: 0 | J23: 0 | K23: 0 | L23: 0 | M23: 0 | N23: 0 | O23: 0 | P23: 0 | Q23: 0 | R23: 0 | S23: 0 | T23: 0 | U23: 0 | V23: 0 | W23: 0 | X23: 0 | Y23: =+W23+S23+O23+K23 -> 0 | Z23: =+X23+T23+P23+L23 -> 0
A24: 10 | B24: Негосударственные некоммерческие организации | C24: =E24+I24+M24+Q24+U24 -> 13925281 | D24: =F24+J24+N24+R24+V24 -> 6446959 | E24: =12166088-950000 -> 11216088 | F24: 6446959 | G24: 96905 | H24: 0 | I24: 730999 | J24: 0 | K24: 282308 | L24: 0 | M24: 0 | N24: 0 | O24: 0 | P24: 0 | Q24: 0 | R24: 0 | S24: 0 | T24: 0 | U24: 1978194 | V24: 0 | W24: 342200 | X24: 0 | Y24: =+W24+S24+O24+K24 -> 624508 | Z24: =+X24+T24+P24+L24 -> 0 | AA24: 3028371 | AC24: =+'Aging Analysis'!C18 -> 13925281
B25: из них необеспеченные | C25: =E25+I25+M25+Q25+U25 -> 0 | D25: =F25+J25+N25+R25+V25 -> 0 | E25: 0 | F25: 0 | G25: 0 | H25: 0 | I25: 0 | J25: 0 | K25: 0 | L25: 0 | M25: 0 | N25: 0 | O25: 0 | P25: 0 | Q25: 0 | R25: 0 | S25: 0 | T25: 0 | U25: 0 | V25: 0 | W25: 0 | X25: 0 | Y25: =+W25+S25+O25+K25 -> 0 | Z25: =+X25+T25+P25+L25 -> 0
A26: 11 | B26: Бюджетные организации | C26: =E26+I26+M26+Q26+U26 -> 0 | D26: =F26+J26+N26+R26+V26 -> 0 | E26: 0 | F26: 0 | G26: 0 | H26: 0 | I26: 0 | J26: 0 | K26: 0 | L26: 0 | M26: 0 | N26: 0 | O26: 0 | P26: 0 | Q26: 0 | R26: 0 | S26: 0 | T26: 0 | U26: 0 | V26: 0 | W26: 0 | X26: 0 | Y26: =+W26+S26+O26+K26 -> 0 | Z26: =+X26+T26+P26+L26 -> 0 | AC26: =+'Aging Analysis'!C19 -> 0
B27: из них необеспеченные | C27: =E27+I27+M27+Q27+U27 -> 0 | D27: =F27+J27+N27+R27+V27 -> 0 | E27: 0 | F27: 0 | G27: 0 | H27: 0 | I27: 0 | J27: 0 | K27: 0 | L27: 0 | M27: 0 | N27: 0 | O27: 0 | P27: 0 | Q27: 0 | R27: 0 | S27: 0 | T27: 0 | U27: 0 | V27: 0 | W27: 0 | X27: 0 | Y27: =+W27+S27+O27+K27 -> 0 | Z27: =+X27+T27+P27+L27 -> 0
A28: 12 | B28: Прочие | C28: =E28+I28+M28+Q28+U28 -> 116115203 | D28: =F28+J28+N28+R28+V28 -> 10141407 | E28: =95738441+1800786+1 -> 97539228 | F28: =10141405+2 -> 10141407 | G28: 842726 | H28: 0 | I28: =4950944+1 -> 4950945 | J28: 0 | K28: =1241279-1 -> 1241278 | L28: 0 | M28: 912319 | N28: 0 | O28: 279869 | P28: 0 | Q28: 1136647 | R28: 0 | S28: 251331 | T28: 0 | U28: 11576064 | V28: 0 | W28: 7118381 | X28: 0 | Y28: =+W28+S28+O28+K28 -> 8890859 | Z28: =+X28+T28+P28+L28 -> 0 | AA28: 831401 | AC28: =+'Aging Analysis'!C20 -> 116115203
B29: из них необеспеченные | C29: =E29+I29+M29+Q29+U29 -> 0 | D29: =F29+J29+N29+R29+V29 -> 0 | Y29: =+W29+S29+O29+K29 -> 0 | Z29: =+X29+T29+P29+L29 -> 0
A30: 13 | B30: Итого кредита и лизинга | C30: =+C6+C8+C10+C12+C14+C16+C18+C20+C22+C24+C26+C28 -> 7754313870 | D30: =+D6+D8+D10+D12+D14+D16+D18+D20+D22+D24+D26+D28 -> 2946894902 | E30: =+E6+E8+E10+E12+E14+E16+E18+E20+E22+E24+E26+E28 -> 6823371532 | F30: =+F6+F8+F10+F12+F14+F16+F18+F20+F22+F24+F26+F28 -> 2754816643 | G30: =+G6+G8+G10+G12+G14+G16+G18+G20+G22+G24+G26+G28 -> 58952965 | H30: =+H6+H8+H10+H12+H14+H16+H18+H20+H22+H24+H26+H28 -> 387773 | I30: =+I6+I8+I10+I12+I14+I16+I18+I20+I22+I24+I26+I28 -> 616609354 | J30: =+J6+J8+J10+J12+J14+J16+J18+J20+J22+J24+J26+J28 -> 103269096 | ... AB30: =+AB6+AB8+AB10+AB12+AB14+AB16+AB18+AB20+AB22+AB24+AB26+AB28 -> 0
B31: из них необеспеченные | C31: =+C7+C9+C11+C13+C15+C17+C19+C21+C23+C25+C27+C29 -> 0 | D31: =+D7+D9+D11+D13+D15+D17+D19+D21+D23+D25+D27+D29 -> 0 | E31: =+E7+E9+E11+E13+E15+E17+E19+E21+E23+E25+E27+E29 -> 0 | F31: =+F7+F9+F11+F13+F15+F17+F19+F21+F23+F25+F27+F29 -> 0 | G31: =+G7+G9+G11+G13+G15+G17+G19+G21+G23+G25+G27+G29 -> 0 | H31: =+H7+H9+H11+H13+H15+H17+H19+H21+H23+H25+H27+H29 -> 0 | I31: =+I7+I9+I11+I13+I15+I17+I19+I21+I23+I25+I27+I29 -> 0 | J31: =+J7+J9+J11+J13+J15+J17+J19+J21+J23+J25+J27+J29 -> 0 | ... Z31: =+Z7+Z9+Z11+Z13+Z15+Z17+Z19+Z21+Z23+Z25+Z27+Z29 -> 0
B32: По сектору экономики
A34: 14 | B34: Промышленность | C34: =E34+I34+M34+Q34+U34 -> 2695352702 | D34: =F34+J34+N34+R34+V34 -> 1760487337 | E34: 2279715182 | F34: 1643945482 | G34: 19696417 | H34: 0 | I34: 315188074 | J34: 36287914 | K34: 1618242 | L34: 172960 | M34: 48002941 | N34: 45168189 | O34: 356512 | P34: 0 | Q34: 3135982 | R34: 0 | S34: 690973 | T34: 0 | U34: 49310523 | V34: 35085752 | W34: =9240081+1397824 -> 10637905 | X34: 2951959 | Y34: =+W34+S34+O34+K34 -> 13303632 | Z34: =+X34+T34+P34+L34 -> 3124919 | AA34: 413675 | AC34: =+'Aging Analysis'!C25 -> 2695352702
B35: из них необеспеченные | C35: =E35+I35+M35+Q35+U35 -> 0 | D35: =F35+J35+N35+R35+V35 -> 0 | E35: 0 | F35: 0 | G35: 0 | H35: 0 | I35: 0 | J35: 0 | K35: 0 | L35: 0 | M35: 0 | N35: 0 | O35: 0 | P35: 0 | Q35: 0 | R35: 0 | S35: 0 | T35: 0 | U35: 0 | V35: 0 | W35: 0 | X35: 0 | Y35: =+W35+S35+O35+K35 -> 0 | Z35: =+X35+T35+P35+L35 -> 0
A36: 15 | B36: Сельское хозяйство | C36: =E36+I36+M36+Q36+U36 -> 233885083 | D36: =F36+J36+N36+R36+V36 -> 146279298 | E36: 185470746 | F36: 130192263 | G36: 1602441 | H36: 166782 | I36: 37547420 | J36: 14489979 | K36: 263171 | L36: 161122 | M36: 4182287 | N36: 1597056 | O36: 720633 | P36: 399264 | Q36: 1605227 | R36: 0 | S36: 485621 | T36: 0 | U36: 5079403 | V36: 0 | W36: 1788577 | X36: 0 | Y36: =+W36+S36+O36+K36 -> 3258002 | Z36: =+X36+T36+P36+L36 -> 560386 | AA36: 949693 | AC36: =+'Aging Analysis'!C26 -> 233885083
B37: из них необеспеченные | C37: =E37+I37+M37+Q37+U37 -> 0 | D37: =F37+J37+N37+R37+V37 -> 0 | E37: 0 | F37: 0 | G37: 0 | H37: 0 | I37: 0 | J37: 0 | K37: 0 | L37: 0 | M37: 0 | N37: 0 | O37: 0 | P37: 0 | Q37: 0 | R37: 0 | S37: 0 | T37: 0 | U37: 0 | V37: 0 | W37: 0 | X37: 0 | Y37: =+W37+S37+O37+K37 -> 0 | Z37: =+X37+T37+P37+L37 -> 0
A38: 16 | B38: Транспорт и коммуникации | C38: =E38+I38+M38+Q38+U38 -> 826803668 | D38: =F38+J38+N38+R38+V38 -> 41565170 | E38: =788901478-1 -> 788901477 | F38: 39235905 | G38: 6815997 | H38: 220991 | I38: 12905689 | J38: 1075317 | K38: 682641 | L38: 268829 | M38: 1814186 | N38: 0 | O38: 387864 | P38: 0 | Q38: 3443223 | R38: 1253948 | S38: 1565817 | T38: 626974 | U38: 19739093 | V38: 0 | W38: 1108585 | X38: 0 | Y38: =+W38+S38+O38+K38 -> 3744907 | Z38: =+X38+T38+P38+L38 -> 895803 | AA38: 175451 | AC38: =+'Aging Analysis'!C27 -> 826803668
B39: из них необеспеченные | C39: =E39+I39+M39+Q39+U39 -> 0 | D39: =F39+J39+N39+R39+V39 -> 0 | E39: 0 | F39: 0 | G39: 0 | H39: 0 | I39: 0 | J39: 0 | K39: 0 | L39: 0 | M39: 0 | N39: 0 | O39: 0 | P39: 0 | Q39: 0 | R39: 0 | S39: 0 | T39: 0 | U39: 0 | V39: 0 | W39: 0 | X39: 0 | Y39: =+W39+S39+O39+K39 -> 0 | Z39: =+X39+T39+P39+L39 -> 0
A40: 17 | B40: Строительство | C40: =E40+I40+M40+Q40+U40 -> 535003135 | D40: =F40+J40+N40+R40+V40 -> 300028895 | E40: =468449447+2 -> 468449449 | F40: 282688639 | G40: 4047337 | H40: 0 | I40: 60535377 | J40: 17340256 | K40: 163114 | L40: 0 | M40: 27701 | N40: 0 | O40: 6970 | P40: 0 | Q40: 2916332 | R40: 0 | S40: 915073 | T40: 0 | U40: 3074276 | V40: 0 | W40: 1765520 | X40: 0 | Y40: =+W40+S40+O40+K40 -> 2850677 | Z40: =+X40+T40+P40+L40 -> 0 | AA40: 1340662 | AC40: =+'Aging Analysis'!C28 -> 535003135
B41: из них необеспеченные | C41: =E41+I41+M41+Q41+U41 -> 0 | D41: =F41+J41+N41+R41+V41 -> 0 | E41: 0 | F41: 0 | G41: 0 | H41: 0 | I41: 0 | J41: 0 | K41: 0 | L41: 0 | M41: 0 | N41: 0 | O41: 0 | P41: 0 | Q41: 0 | R41: 0 | S41: 0 | T41: 0 | U41: 0 | V41: 0 | W41: 0 | X41: 0 | Y41: =+W41+S41+O41+K41 -> 0 | Z41: =+X41+T41+P41+L41 -> 0
A42: 18 | B42: Торговля и общественное питание | C42: =E42+I42+M42+Q42+U42 -> 706694385 | D42: =F42+J42+N42+R42+V42 -> 167413280 | E42: =588335261+2 -> 588335263 | F42: 163390058 | G42: 5083133 | H42: 0 | I42: 64469242 | J42: 0 | K42: 1062933 | L42: 0 | M42: 2052984 | N42: 0 | O42: 516613 | P42: 0 | Q42: 40202369 | R42: 4023222 | S42: 1942103 | T42: 0 | U42: 11634527 | V42: 0 | W42: 4677625 | X42: 0 | Y42: =+W42+S42+O42+K42 -> 8199274 | Z42: =+X42+T42+P42+L42 -> 0 | AA42: 10661645 | AC42: =+'Aging Analysis'!C29 -> 706694385
B43: из них необеспеченные | C43: =E43+I43+M43+Q43+U43 -> 0 | D43: =F43+J43+N43+R43+V43 -> 0 | E43: 0 | F43: 0 | G43: 0 | H43: 0 | I43: 0 | J43: 0 | K43: 0 | L43: 0 | M43: 0 | N43: 0 | O43: 0 | P43: 0 | Q43: 0 | R43: 0 | S43: 0 | T43: 0 | U43: 0 | V43: 0 | W43: 0 | X43: 0 | Y43: =+W43+S43+O43+K43 -> 0 | Z43: =+X43+T43+P43+L43 -> 0
A44: 19 | B44: Материально-техническое снабжение и сбыт | C44: =E44+I44+M44+Q44+U44 -> 83306275 | D44: =F44+J44+N44+R44+V44 -> 36690355 | E44: =36599610+1 -> 36599611 | F44: 933729 | G44: 316215 | H44: 0 | I44: 34448715 | J44: 34075630 | K44: 8610831 | L44: 8518907 | M44: 1680996 | N44: 1680996 | O44: 1680996 | P44: 1680996 | Q44: 0 | R44: 0 | S44: 0 | T44: 0 | U44: 10576953 | V44: 0 | W44: 1425000 | X44: 0 | Y44: =+W44+S44+O44+K44 -> 11716827 | Z44: =+X44+T44+P44+L44 -> 10199903 | AA44: 320576 | AC44: =+'Aging Analysis'!C30 -> 83306275
B45: из них необеспеченные | C45: =E45+I45+M45+Q45+U45 -> 0 | D45: =F45+J45+N45+R45+V45 -> 0 | E45: 0 | F45: 0 | G45: 0 | H45: 0 | I45: 0 | J45: 0 | K45: 0 | L45: 0 | M45: 0 | N45: 0 | O45: 0 | P45: 0 | Q45: 0 | R45: 0 | S45: 0 | T45: 0 | U45: 0 | V45: 0 | W45: 0 | X45: 0 | Y45: =+W45+S45+O45+K45 -> 0 | Z45: =+X45+T45+P45+L45 -> 0
A46: 20 | B46: Жилищно-коммунальные услуги | C46: =E46+I46+M46+Q46+U46 -> 62142553 | D46: =F46+J46+N46+R46+V46 -> 3251298 | E46: 44372852 | F46: 3251298 | G46: 383375 | H46: 0 | I46: 5888028 | J46: 0 | K46: 1375026 | L46: 0 | M46: 142609 | N46: 0 | O46: 127006 | P46: 0 | Q46: 0 | R46: 0 | S46: 0 | T46: 0 | U46: 11739064 | V46: 0 | W46: 6265473 | X46: 0 | Y46: =+W46+S46+O46+K46 -> 7767505 | Z46: =+X46+T46+P46+L46 -> 0 | AA46: 1150304 | AC46: =+'Aging Analysis'!C31 -> 62142553
B47: из них необеспеченные | C47: =E47+I47+M47+Q47+U47 -> 0 | D47: =F47+J47+N47+R47+V47 -> 0 | E47: 0 | F47: 0 | G47: 0 | H47: 0 | I47: 0 | J47: 0 | K47: 0 | L47: 0 | M47: 0 | N47: 0 | O47: 0 | P47: 0 | Q47: 0 | R47: 0 | S47: 0 | T47: 0 | U47: 0 | V47: 0 | W47: 0 | X47: 0 | Y47: =+W47+S47+O47+K47 -> 0 | Z47: =+X47+T47+P47+L47 -> 0
A48: 21 | B48: Другие сектора | C48: =E48+I48+M48+Q48+U48 -> 2611126069 | D48: =F48+J48+N48+R48+V48 -> 491179269 | E48: =2431526955+1-5+1 -> 2431526952 | F48: 491179269 | G48: 21008050 | H48: 0 | I48: =85626808+1 -> 85626809 | J48: 0 | K48: =6966597-1 -> 6966596 | L48: 0 | M48: 13772216 | N48: 0 | O48: =2687207+1 -> 2687208 | P48: 0 | Q48: =22457893+1 -> 22457894 | R48: 0 | S48: 10444374 | T48: 0 | U48: 57742198 | V48: 0 | W48: 30055342 | X48: 0 | Y48: =+W48+S48+O48+K48 -> 50153520 | Z48: =+X48+T48+P48+L48 -> 0 | AA48: 10733372 | AC48: =+'Aging Analysis'!C32 -> 2611126069
B49: из них необеспеченные | C49: =E49+I49+M49+Q49+U49 -> 0 | D49: =F49+J49+N49+R49+V49 -> 0 | Y49: =+W49+S49+O49+K49 -> 0 | Z49: =+X49+T49+P49+L49 -> 0
A50: 22 | B50: Итого кредита и лизинга | C50: =+C34+C36+C38+C40+C42+C44+C46+C48 -> 7754313870 | D50: =+D34+D36+D38+D40+D42+D44+D46+D48 -> 2946894902 | E50: =+E34+E36+E38+E40+E42+E44+E46+E48 -> 6823371532 | F50: =+F34+F36+F38+F40+F42+F44+F46+F48 -> 2754816643 | G50: =+G34+G36+G38+G40+G42+G44+G46+G48 -> 58952965 | H50: =+H34+H36+H38+H40+H42+H44+H46+H48 -> 387773 | I50: =+I34+I36+I38+I40+I42+I44+I46+I48 -> 616609354 | J50: =+J34+J36+J38+J40+J42+J44+J46+J48 -> 103269096 | ... AB50: =+AB34+AB36+AB38+AB40+AB42+AB44+AB46+AB48 -> 0
B51: из них необеспеченные | C51: =+C35+C37+C39+C41+C43+C45+C47+C49 -> 0 | D51: =+D35+D37+D39+D41+D43+D45+D47+D49 -> 0 | E51: =+E35+E37+E39+E41+E43+E45+E47+E49 -> 0 | F51: =+F35+F37+F39+F41+F43+F45+F47+F49 -> 0 | G51: =+G35+G37+G39+G41+G43+G45+G47+G49 -> 0 | H51: =+H35+H37+H39+H41+H43+H45+H47+H49 -> 0 | I51: =+I35+I37+I39+I41+I43+I45+I47+I49 -> 0 | J51: =+J35+J37+J39+J41+J43+J45+J47+J49 -> 0 | ... AB51: =+AB35+AB37+AB39+AB41+AB43+AB45+AB47+AB49 -> 0
B52: По регионам
A54: 23 | B54: Республика Каракалпакстан | C54: =E54+I54+M54+Q54+U54 -> 248038582 | D54: =F54+J54+N54+R54+V54 -> 30683156 | E54: 212955180 | F54: 30683156 | G54: 1839903 | H54: 0 | I54: 12528806 | J54: 0 | K54: 609629 | L54: 0 | M54: 1524083 | N54: 0 | O54: 332080 | P54: 0 | Q54: 15306919 | R54: 0 | S54: 1159586 | T54: 0 | U54: 5723594 | V54: 0 | W54: 4357870 | X54: 0 | Y54: =+W54+S54+O54+K54 -> 6459165 | Z54: =+X54+T54+P54+L54 -> 0 | AA54: 1649719
A55: 24 | B55: Андижанская область | C55: =E55+I55+M55+Q55+U55 -> 515485797 | D55: =F55+J55+N55+R55+V55 -> 351244344 | E55: 471704001 | F55: 330639984 | G55: 4075456 | H55: 0 | I55: 13206871 | J55: 826818 | K55: 430058 | L55: 82682 | M55: 990583 | N55: 0 | O55: 184439 | P55: 0 | Q55: 1187989 | R55: 0 | S55: 498436 | T55: 0 | U55: 28396353 | V55: 19777542 | W55: 3022075 | X55: 0 | Y55: =+W55+S55+O55+K55 -> 4135008 | Z55: =+X55+T55+P55+L55 -> 82682 | AA55: 4506152
A56: 25 | B56: Бухарская область | C56: =E56+I56+M56+Q56+U56 -> 458154927 | D56: =F56+J56+N56+R56+V56 -> 151023304 | E56: 345507170 | F56: 149947987 | G56: 2985133 | H56: 0 | I56: 93169378 | J56: 1075317 | K56: 1903931 | L56: 268829 | M56: 1046691 | N56: 0 | O56: 257283 | P56: 0 | Q56: 15396239 | R56: 0 | S56: 640129 | T56: 0 | U56: 3035449 | V56: 0 | W56: 1242516 | X56: 0 | Y56: =+W56+S56+O56+K56 -> 4043859 | Z56: =+X56+T56+P56+L56 -> 268829 | AA56: 451678
A57: 26 | B57: Джизакская область | C57: =E57+I57+M57+Q57+U57 -> 402745367 | D57: =F57+J57+N57+R57+V57 -> 103514349 | E57: 353961485 | F57: 101364351 | G57: 3058177 | H57: 0 | I57: 13391711 | J57: 0 | K57: 3016770 | L57: 0 | M57: 2119343 | N57: 0 | O57: 317171 | P57: 0 | Q57: 6452246 | R57: 0 | S57: 2595697 | T57: 0 | U57: 26820582 | V57: 2149998 | W57: 10664137 | X57: 215000 | Y57: =+W57+S57+O57+K57 -> 16593775 | Z57: =+X57+T57+P57+L57 -> 215000 | AA57: 1193939
A58: 27 | B58: Кашкадарьинская область | C58: =E58+I58+M58+Q58+U58 -> 350783767 | D58: =F58+J58+N58+R58+V58 -> 112072409 | E58: 278966963 | F58: 112072409 | G58: 2410235 | H58: 0 | I58: 67523781 | J58: 0 | K58: 717703 | L58: 0 | M58: 797559 | N58: 0 | O58: 159540 | P58: 0 | Q58: 910919 | R58: 0 | S58: 433414 | T58: 0 | U58: 2584545 | V58: 0 | W58: 2547857 | X58: 0 | Y58: =+W58+S58+O58+K58 -> 3858514 | Z58: =+X58+T58+P58+L58 -> 0 | AA58: 972543
A59: 28 | B59: Навоийская область | C59: =E59+I59+M59+Q59+U59 -> 617240452 | D59: =F59+J59+N59+R59+V59 -> 388263707 | E59: 602369264 | F59: 388263707 | G59: 5204385 | H59: 9371 | I59: 7256898 | J59: 0 | K59: 582586 | L59: 0 | M59: 3771496 | N59: 0 | O59: 802142 | P59: 0 | Q59: 1584259 | R59: 0 | S59: 781972 | T59: 0 | U59: 2258535 | V59: 0 | W59: 2220536 | X59: 0 | Y59: =+W59+S59+O59+K59 -> 4387236 | Z59: =+X59+T59+P59+L59 -> 0 | AA59: 625565
A60: 29 | B60: Наманганская область | C60: =E60+I60+M60+Q60+U60 -> 433774617 | D60: =F60+J60+N60+R60+V60 -> 156243742 | E60: 384164061 | F60: 142758689 | G60: 3319123 | H60: 0 | I60: 42195035 | J60: 13485053 | K60: 166904 | L60: 0 | M60: 1746592 | N60: 0 | O60: 436549 | P60: 0 | Q60: 2397716 | R60: 0 | S60: 1064519 | T60: 0 | U60: 3271213 | V60: 0 | W60: 1763542 | X60: 0 | Y60: =+W60+S60+O60+K60 -> 3431514 | Z60: =+X60+T60+P60+L60 -> 0 | AA60: 758996
A61: 30 | B61: Самаркандская область | C61: =E61+I61+M61+Q61+U61 -> 565860084 | D61: =F61+J61+N61+R61+V61 -> 331840737 | E61: 464850409 | F61: 265934872 | G61: 4016242 | H61: 166783 | I61: 90289916 | J61: 65905865 | K61: 9620493 | L61: 8680029 | M61: 1545479 | N61: 0 | O61: 345915 | P61: 0 | Q61: 5569855 | R61: 0 | S61: 2268409 | T61: 0 | U61: 3604425 | V61: 0 | W61: 2643853 | X61: 0 | Y61: =+W61+S61+O61+K61 -> 14878670 | Z61: =+X61+T61+P61+L61 -> 8680029 | AA61: 2819061
A62: 31 | B62: Сурхандарьинская область | C62: =E62+I62+M62+Q62+U62 -> 457438578 | D62: =F62+J62+N62+R62+V62 -> 60743739 | E62: 266993578 | F62: 13191265 | G62: 2306787 | H62: 0 | I62: 125654833 | J62: 0 | K62: 1584178 | L62: 0 | M62: 47774645 | N62: 45168189 | O62: 465966 | P62: 0 | Q62: 7931965 | R62: 2384285 | S62: 2727422 | T62: 0 | U62: 9083557 | V62: 0 | W62: 6529929 | X62: 0 | Y62: =+W62+S62+O62+K62 -> 11307495 | Z62: =+X62+T62+P62+L62 -> 0 | AA62: 5153096
A63: 32 | B63: Сырдарьинская область | C63: =E63+I63+M63+Q63+U63 -> 0 | D63: =F63+J63+N63+R63+V63 -> 0 | E63: 0 | F63: 0 | G63: 0 | H63: 0 | I63: 0 | J63: 0 | K63: 0 | L63: 0 | M63: 0 | N63: 0 | O63: 0 | P63: 0 | Q63: 0 | R63: 0 | S63: 0 | T63: 0 | U63: 0 | V63: 0 | W63: 0 | X63: 0 | Y63: =+W63+S63+O63+K63 -> 0 | Z63: =+X63+T63+P63+L63 -> 0
A64: 33 | B64: г. Ташкент | C64: =E64+I64+M64+Q64+U64 -> 2532372458 | D64: =F64+J64+N64+R64+V64 -> 776838718 | E64: =2395227486+1 -> 2395227487 | F64: 765115907 | G64: 20694427 | H64: 211619 | I64: 52125835 | J64: 0 | K64: 806541 | L64: 0 | M64: 7458592 | N64: 1597056 | O64: 1167071 | P64: 399264 | Q64: 8179315 | R64: 1253948 | S64: 3149323 | T64: 626974 | U64: 69381229 | V64: 8871807 | W64: =12904799+1397824 -> 14302623 | X64: 0 | Y64: =+W64+S64+O64+K64 -> 19425558 | Z64: =+X64+T64+P64+L64 -> 1026238 | AA64: 6937109
A65: 34 | B65: Ташкентская область | C65: =E65+I65+M65+Q65+U65 -> 46747528 | D65: =F65+J65+N65+R65+V65 -> 0 | E65: 42460958 | F65: 0 | G65: 366857 | H65: 0 | I65: 863329 | J65: 0 | K65: 80789 | L65: 0 | M65: 628475 | N65: 0 | O65: 157119 | P65: 0 | Q65: 605846 | R65: 0 | S65: 303693 | T65: 0 | U65: 2188920 | V65: 0 | W65: 2191564 | X65: 0 | Y65: =+W65+S65+O65+K65 -> 2733165 | Z65: =+X65+T65+P65+L65 -> 0
A66: 35 | B66: Ферганская область | C66: =E66+I66+M66+Q66+U66 -> 848735361 | D66: =F66+J66+N66+R66+V66 -> 391705665 | E66: 739515579 | F66: 362147168 | G66: 6389310 | H66: 0 | I66: 96133666 | J66: 21976043 | K66: 703978 | L66: 90278 | M66: 2043761 | N66: 1680996 | O66: 1709911 | P66: 1680996 | Q66: 6299577 | R66: =1638936+1 -> 1638937 | S66: 327321 | T66: 0 | U66: 4742778 | V66: 4262521 | W66: 3193331 | X66: 2713074 | Y66: =+W66+S66+O66+K66 -> 5934541 | Z66: =+X66+T66+P66+L66 -> 4484348 | AA66: 346003
A67: 36 | B67: Хорезмская область | C67: =E67+I67+M67+Q67+U67 -> 276936352 | D67: =F67+J67+N67+R67+V67 -> 92721032 | E67: =264695398-1 -> 264695397 | F67: 92697148 | G67: 2286930 | H67: 0 | I67: =2269294+1 -> 2269295 | J67: 0 | K67: =518996-1-1 -> 518994 | L67: 0 | M67: =228622-1 -> 228621 | N67: 0 | O67: =148617-1 -> 148616 | P67: 0 | Q67: 1938182 | R67: 0 | S67: =94039+1 -> 94040 | T67: 0 | U67: =7804856+1 -> 7804857 | V67: =23885-1 -> 23884 | W67: =3044195-1 -> 3044194 | X67: 23885 | Y67: =+W67+S67+O67+K67 -> 3805844 | Z67: =+X67+T67+P67+L67 -> 23885 | AA67: 331517
A68: 37 | B68: Итого кредита и лизинга | C68: =SUM(C54:C67) -> 7754313870 | D68: =SUM(D54:D67) -> 2946894902 | E68: =SUM(E54:E67) -> 6823371532 | F68: =SUM(F54:F67) -> 2754816643 | G68: =SUM(G54:G67) -> 58952965 | H68: =SUM(H54:H67) -> 387773 | I68: =SUM(I54:I67) -> 616609354 | J68: =SUM(J54:J67) -> 103269096 | ... AB68: =SUM(AB54:AB67) -> 0
A69: 38 | B69: Другие классифицированные активы | C69: =E69+I69+M69+Q69+U69 -> 4884142754 | D69: =F69+J69+N69+R69+V69 -> 1867275793 | E69: =12638456624-C68-I69-U69 -> 4879415087 | F69: =4814170695-D68-J69-V69 -> 1863167101 | G69: =41979652+849636 -> 42829288 | I69: 4108692 | J69: 4108692 | K69: 410869 | U69: 618975 | W69: 618975 | X69: 0 | Y69: =+W69+S69+O69+K69 -> 1029844 | Z69: =+X69+T69+P69+L69 -> 0
B70: из них необеспеченные | C70: =E70+I70+M70+Q70+U70 -> 0 | D70: =F70+J70+N70+R70+V70 -> 0 | Y70: =+W70+S70+O70+K70 -> 0 | Z70: =+X70+T70+P70+L70 -> 0
A71: 39 | B71: Всего классифицированных активов | C71: =+C50+C69 -> 12638456624 | D71: =+D50+D69 -> 4814170695 | E71: =+E50+E69 -> 11702786619 | F71: =+F50+F69 -> 4617983744 | G71: =+G50+G69 -> 101782253 | H71: =+H50+H69 -> 387773 | I71: =+I50+I69 -> 620718046 | J71: =+J50+J69 -> 107377788 | ... AB71: =+AB50+AB69 -> 0
B74: Подпись Председателя правления:
B76: Подпись Главного Бухгалтера:
E77: =SUM('Asset quality'!D21:D47)+'Asset quality'!D16 -> 6823371532 | G77: =SUM('Asset quality'!O21:O47)+'Asset quality'!O16 -> 58952965 | I77: =SUM('Asset quality'!E21:E47)+'Asset quality'!E16 -> 616609354 | K77: =SUM('Asset quality'!P21:P47)+'Asset quality'!P16 -> 20742554 | M77: =SUM('Asset quality'!F21:F47) -> 71675920 | O77: =SUM('Asset quality'!Q21:Q47)+'Asset quality'!Q16 -> 6483802 | Q77: =SUM('Asset quality'!G21:G47) -> 73761027 | S77: =SUM('Asset quality'!R21:R47)+'Asset quality'!R16 -> 16043961 | U77: =SUM('Asset quality'!H21:H47) -> 168896037 | W77: =SUM('Asset quality'!S21:S47)+'Asset quality'!S16 -> 57724027 | Y77: =+W77+S77+O77+K77 -> 100994344
G78: =+'Asset quality'!O9+'Asset quality'!O62 -> 101782253 | K78: =+'Asset quality'!P9+'Asset quality'!P62 -> 21153423 | O78: =+'Asset quality'!Q9+'Asset quality'!Q62 -> 6483802 | S78: =+'Asset quality'!R9+'Asset quality'!R62 -> 16043961 | W78: =+'Asset quality'!S9+'Asset quality'!S62 -> 58343002 | Y78: =+W78+S78+O78+K78 -> 102024188
E79: =+E77-E50 -> 0 | G79: =+G77-G50 -> 0 | I79: =+I77-I50 -> 0 | K79: =+K77-K50 -> 0 | M79: =+M77-M50 -> 0 | O79: =+O77-O50 -> 0 | Q79: =+Q77-Q50 -> 0 | S79: =+S77-S50 -> 0 | U79: =+U77-U50 -> 0 | W79: =+W77-W50 -> 0 | Y79: =+Y77-Y50 -> 0
G80: =+G78-G71 -> 0 | K80: =+K78-K71 -> 0 | O80: =+O78-O71 -> 0 | S80: =+S78-S71 -> 0 | W80: =+W78-W71 -> 0 | Y80: =+Y78-Y71 -> 0

Sheet Transactions of related parties
A1: ОТЧЕТ О СДЕЛКАХ, ЗАКЛЮЧЕННЫХ СО СВЯЗАННЫМИ ЛИЦАМИ | Y1: Таблица-11
B3: =+'Asset quality'!B3 -> АК "АЛОКАБАНК" | U3: =+'Asset quality'!P3 -> 44561 | V3: =+#REF! -> #REF! | Y3: тыс. сум
A4: № | B4: Наименования клиента | C4: ИНН | D4: Вид деятельности | E4: Код валюты | F4: Номер группы | G4: Текущая задолженность, брутто | H4: из них | T4: Пересмотрения | U4: Вычеты из норматива | W4: Классификация | X4: Резерв | Y4: Источник кредита | Z4: Текущая задолженность, нетто
H5: балансовые | L5: внебалансовые
H6: Межбанковские кредиты и депозиты, остатки на кор счетах, средства для межбанковских взаиморасчетов, другие размещенные средства (кроме овернайта и клиринговых операций) и доходы по ним | I6: Кредиты/лизинги/факторинги и доходы по ним | J6: Инвестиции и доходы по ним | K6: Другие активы доходы по ним | L6: Аккредитивы и доходы по ним | N6: Гарантии/поручительства и доходы по ним | P6: Неиспользованные кредитные линии/безотзывные обязательства/ другие обязательства по выдаче кредитов доходы по ним | R6: Другие активы доходы по ним | U6: Вид обеспечения | V6: Сумма
L7: остаток | M7: по степени риска | N7: остаток | O7: по степени риска | P7: остаток | Q7: по степени риска | R7: остаток | S7: по степени риска
B8: А | C8: Б | D8: В | E8: Г | F8: Д | G8: Е | H8: Е1 | I8: Е2 | J8: Е3 | K8: Е4 | L8: Е5 | N8: Е6 | P8: Е7 | R8: Е8 | T8: Ж | U8: З | V8: И | W8: К | X8: Л | Y8: М | Z8: Н
A9: 1 | B9: "Ўзбектелеком" АЖ | C9: 203366731 | D9: 61100 | E9: 860 | F9: 1 | G9: =+H9+I9+J9+K9+M9+O9+Q9+S9 -> 584524462 | I9: 584524462 | N9: 108376600 | U9: 2 | V9: 429776700 | W9: 1 | Z9: =+G9-V9-X9 -> 154747762 | AA9: =SUMIF($F$9:$F$63,$F9,$Z$9:$Z$63) -> 154747762
A10: 2 | B10: "Нано Лизинг Компанияси" МЧЖ | C10: 207137166 | D10: 64910 | E10: 860 | F10: 2 | G10: =+H10+I10+J10+K10+M10+O10+Q10+S10 -> 161383437 | I10: 161383437 | W10: 1 | Z10: =+G10-V10-X10 -> 161383437 | AA10: =SUMIF($F$9:$F$63,$F10,$Z$9:$Z$63) -> 163050104
A11: 3 | B11: "ИТ-Инвест" МЧЖ | C11: 305059128 | D11: 62020 | E11: 860 | F11: 2 | G11: =+H11+I11+J11+K11+M11+O11+Q11+S11 -> 1666667 | I11: 1666667 | W11: 1 | Z11: =+G11-V11-X11 -> 1666667 | AA11: =SUMIF($F$9:$F$63,$F12,$Z$9:$Z$63) -> 50000000
A12: 4 | B12: "Ўзбекистон почтаси" АЖ | C12: 200833833 | D12: 53100 | E12: 860 | F12: 3 | G12: =+H12+I12+J12+K12+M12+O12+Q12+S12 -> 50000000 | J12: 50000000 | W12: 1 | Z12: =+G12-V12-X12 -> 50000000 | AA12: =SUMIF($F$9:$F$63,$F13,$Z$9:$Z$63) -> 25000000
A13: 5 | B13: "Алоквенчурс" МЧЖ | C13: 308921880 | D13: 64300 | E13: 860 | F13: 4 | G13: =+H13+I13+J13+K13+M13+O13+Q13+S13 -> 25000000 | J13: 25000000 | W13: 1 | Z13: =+G13-V13-X13 -> 25000000 | AA13: =SUMIF($F$9:$F$63,$F20,$Z$9:$Z$63) -> 22621
A14: 6 | B14: "Aлоқа актив" МЧЖ | C14: 305186248 | D14: 96190 | E14: 860 | F14: 5 | G14: =+H14+I14+J14+K14+M14+O14+Q14+S14 -> 12665000 | J14: 12665000 | W14: 1 | Z14: =+G14-V14-X14 -> 12665000 | AA14: =SUMIF($F$9:$F$63,$F21,$Z$9:$Z$63) -> 0
A15: 7 | B15: СК "Алском" АЖ | C15: 201941144 | D15: 65120 | E15: 860 | F15: 6 | G15: =+H15+I15+J15+K15+M15+O15+Q15+S15 -> 5603011 | J15: 5603011 | W15: 1 | Z15: =+G15-V15-X15 -> 5603011 | AA15: =SUMIF($F$9:$F$63,$F22,$Z$9:$Z$63) -> 0
A16: 8 | B16: "Алокализинг" МЧЖ | C16: 305186248 | D16: 64990 | E16: 860 | F16: 7 | G16: =+H16+I16+J16+K16+M16+O16+Q16+S16 -> 1298000 | J16: 1298000 | W16: 4 | Z16: =+G16-V16-X16 -> 1298000 | AA16: =SUMIF($F$9:$F$63,#REF!,$Z$9:$Z$63) -> 0
A17: 9 | B17: "Уздижитал ТВ" МЧЖ | C17: 207027936 | D17: 52300 | E17: 860 | F17: 8 | G17: =+H17+I17+J17+K17+M17+O17+Q17+S17 -> 1136155 | J17: 1136155 | W17: 1 | Z17: =+G17-V17-X17 -> 1136155 | AA17: =SUMIF($F$9:$F$63,$F23,$Z$9:$Z$63) -> 0
A18: 10 | B18: Тураев Шавкат Абдузоирович | C18: 496318340 | D18: 99950 | E18: 860 | F18: 8 | G18: =+H18+I18+J18+K18+M18+O18+Q18+S18 -> 135000 | I18: 135000 | W18: 1 | Z18: =+G18-V18-X18 -> 135000 | AA18: =SUMIF($F$9:$F$63,$F24,$Z$9:$Z$63) -> 0
A19: 11 | B19: Набиев Умиджон Бобоқулович | C19: 498617291 | D19: 99950 | E19: 860 | F19: 7 | G19: =+H19+I19+J19+K19+M19+O19+Q19+S19 -> 24843 | I19: 24843 | W19: 1 | Z19: =+G19-V19-X19 -> 24843 | AA19: =SUMIF($F$9:$F$63,$F25,$Z$9:$Z$63) -> 0
A20: 12 | B20: Мукумов Орифжон Абдурозикович | C20: 501640297 | D20: 99950 | E20: 860 | F20: 9 | G20: =+H20+I20+J20+K20+M20+O20+Q20+S20 -> 22621 | I20: 22621 | W20: 1 | Z20: =+G20-V20-X20 -> 22621 | AA20: =SUMIF($F$9:$F$63,#REF!,$Z$9:$Z$63) -> 0
A21: 13 | G21: =+H21+I21+J21+K21+M21+O21+Q21+S21 -> 0 | W21: 1 | Z21: =+G21-V21-X21 -> 0 | AA21: =SUMIF($F$9:$F$63,#REF!,$Z$9:$Z$63) -> 0
A22: 14 | G22: =+H22+I22+J22+K22+M22+O22+Q22+S22 -> 0 | Z22: =+G22-V22-X22 -> 0 | AA22: =SUMIF($F$9:$F$63,#REF!,$Z$9:$Z$63) -> 0
A23: 15 | G23: =+H23+I23+J23+K23+M23+O23+Q23+S23 -> 0 | Z23: =+G23-V23-X23 -> 0 | AA23: =SUMIF($F$9:$F$63,#REF!,$Z$9:$Z$63) -> 0
A24: 16 | G24: =+H24+I24+J24+K24+M24+O24+Q24+S24 -> 0 | Z24: =+G24-V24-X24 -> 0 | AA24: =SUMIF($F$9:$F$63,#REF!,$Z$9:$Z$63) -> 0
A25: 17 | G25: =+H25+I25+J25+K25+M25+O25+Q25+S25 -> 0 | Z25: =+G25-V25-X25 -> 0 | AA25: =SUMIF($F$9:$F$63,#REF!,$Z$9:$Z$63) -> 0
A26: 18 | G26: =+H26+I26+J26+K26+M26+O26+Q26+S26 -> 0 | Z26: =+G26-V26-X26 -> 0 | AA26: =SUMIF($F$9:$F$63,$F26,$Z$9:$Z$63) -> 0
A27: 19 | G27: =+H27+I27+J27+K27+M27+O27+Q27+S27 -> 0 | Z27: =+G27-V27-X27 -> 0 | AA27: =SUMIF($F$9:$F$63,$F27,$Z$9:$Z$63) -> 0
A28: 20 | G28: =+H28+I28+J28+K28+M28+O28+Q28+S28 -> 0 | Z28: =+G28-V28-X28 -> 0 | AA28: =SUMIF($F$9:$F$63,$F28,$Z$9:$Z$63) -> 0
A29: 21 | G29: =+H29+I29+J29+K29+M29+O29+Q29+S29 -> 0 | Z29: =+G29-V29-X29 -> 0 | AA29: =SUMIF($F$9:$F$63,$F29,$Z$9:$Z$63) -> 0
A30: 22 | G30: =+H30+I30+J30+K30+M30+O30+Q30+S30 -> 0 | Z30: =+G30-V30-X30 -> 0 | AA30: =SUMIF($F$9:$F$63,$F30,$Z$9:$Z$63) -> 0
A31: 23 | G31: =+H31+I31+J31+K31+M31+O31+Q31+S31 -> 0 | Z31: =+G31-V31-X31 -> 0 | AA31: =SUMIF($F$9:$F$63,$F31,$Z$9:$Z$63) -> 0
A32: 24 | G32: =+H32+I32+J32+K32+M32+O32+Q32+S32 -> 0 | Z32: =+G32-V32-X32 -> 0 | AA32: =SUMIF($F$9:$F$63,$F32,$Z$9:$Z$63) -> 0
A33: 25 | G33: =+H33+I33+J33+K33+M33+O33+Q33+S33 -> 0 | Z33: =+G33-V33-X33 -> 0 | AA33: =SUMIF($F$9:$F$63,$F33,$Z$9:$Z$63) -> 0
A34: 26 | G34: =+H34+I34+J34+K34+M34+O34+Q34+S34 -> 0 | Z34: =+G34-V34-X34 -> 0 | AA34: =SUMIF($F$9:$F$63,$F34,$Z$9:$Z$63) -> 0
A35: 27 | G35: =+H35+I35+J35+K35+M35+O35+Q35+S35 -> 0 | Z35: =+G35-V35-X35 -> 0 | AA35: =SUMIF($F$9:$F$63,$F35,$Z$9:$Z$63) -> 0
A36: 28 | G36: =+H36+I36+J36+K36+M36+O36+Q36+S36 -> 0 | Z36: =+G36-V36-X36 -> 0 | AA36: =SUMIF($F$9:$F$63,$F36,$Z$9:$Z$63) -> 0
A37: 29 | G37: =+H37+I37+J37+K37+M37+O37+Q37+S37 -> 0 | Z37: =+G37-V37-X37 -> 0 | AA37: =SUMIF($F$9:$F$63,$F37,$Z$9:$Z$63) -> 0
... A63: 55 | G63: =+H63+I63+J63+K63+M63+O63+Q63+S63 -> 0 | Z63: =+G63-V63-X63 -> 0 | AA63: =SUMIF($F$9:$F$63,$F63,$Z$9:$Z$63) -> 0
A64: ИТОГО СДЕЛКИ СО СВЯЗАННЫМИ ЛИЦАМИ | G64: =SUM(G9:G63) -> 843459196 | H64: =SUM(H9:H63) -> 0 | I64: =SUM(I9:I63) -> 747757030 | J64: =SUM(J9:J63) -> 95702166 | K64: =SUM(K9:K63) -> 0 | L64: =SUM(L9:L63) -> 0 | M64: =SUM(M9:M63) -> 0 | N64: =SUM(N9:N63) -> 108376600 | ... T64: =SUM(T9:T63) -> 0 | V64: =SUM(V9:V63) -> 429776700 | X64: =SUM(X9:X63) -> 0 | Y64: =SUM(Y9:Y63) -> 0 | Z64: =SUM(Z9:Z63) -> 413682496
A65: САМАЯ КРУПНАЯ СДЕЛКА, ЗАКЛЮЧЁННАЯ С ОДНИМ СВЯЗАННЫМ ЛИЦОМ | G65: =+SUMIF($F$9:$F$63,$AA$65,$G$9:$G$63) -> 163050104 | H65: =+SUMIF($F$9:$F$63,$AA$65,$H$9:$H$63) -> 0 | I65: =+SUMIF($F$9:$F$63,$AA$65,$I$9:$I$63) -> 163050104 | J65: =+SUMIF($F$9:$F$63,$AA$65,$J$9:$J$63) -> 0 | K65: =+SUMIF($F$9:$F$63,$AA$65,$K$9:$K$63) -> 0 | L65: =+SUMIF($F$9:$F$63,$AA$65,$L$9:$L$63) -> 0 | M65: =+SUMIF($F$9:$F$63,$AA$65,$M$9:$M$63) -> 0 | N65: =+SUMIF($F$9:$F$63,$AA$65,$N$9:$N$63) -> 0 | O65: =+SUMIF($F$9:$F$63,$AA$65,$O$9:$O$63) -> 0 | P65: =+SUMIF($F$9:$F$63,$AA$65,$P$9:$P$63) -> 0 | Q65: =+SUMIF($F$9:$F$63,$AA$65,$Q$9:$Q$63) -> 0 | R65: =+SUMIF($F$9:$F$63,$AA$65,$R$9:$R$63) -> 0 | S65: =+SUMIF($F$9:$F$63,$AA$65,$S$9:$S$63) -> 0 | T65: =+SUMIF($F$9:$F$63,$AA$65,$T$9:$T$63) -> 0 | V65: =+SUMIF($F$9:$F$63,$AA$65,$V$9:$V$63) -> 0 | X65: =+SUMIF($F$9:$F$63,$AA$65,$X$9:$X$63) -> 0 | Y65: =+SUMIF($F$9:$F$63,$AA$65,$Y$9:$Y$63) -> 0 | Z65: =+MAX(AA9:AA63) -> 163050104 | AA65: =INDEX($F$9:$F$63,MATCH($Z65,$AA$9:$AA$63,0)) -> 2
B68: Подпись Председателя Правления:
B70: Подпись Главного Бухгалтера:

Sheet  Largest risk
A1: ОТЧЕТ О КРУПНЫХ РИСКАХ | Y1: Таблица-12
B3: =+'Asset quality'!B3 -> АК "АЛОКАБАНК" | U3: =+'Asset quality'!P3 -> 44561 | V3: =+#REF! -> #REF! | Y3: тыс. сум
A4: № | B4: Наименования клиента | C4: ИНН | D4: Вид деятельности | E4: Код валюты | F4: Номер группы | G4: Текущая задолженность, брутто | H4: из них | T4: Пересмотрения | U4: Вычеты из норматива | W4: Классификация | X4: Резерв | Y4: Источник кредита | Z4: Текущая задолженность, нетто
H5: балансовые | L5: внебалансовые
H6: Межбанковские кредиты и депозиты, остатки на кор счетах, средства для межбанковских взаиморасчетов, другие размещенные средства (кроме овернайта и клиринговых операций) и доходы по ним | I6: Кредиты/лизинги/факторинги и доходы по ним | J6: Инвестиции и доходы по ним | K6: Другие активы доходы по ним | L6: Аккредитивы и доходы по ним | N6: Гарантии/поручительства и доходы по ним | P6: Неиспользованные кредитные линии/безотзывные обязательства/ другие обязательства по выдаче кредитов доходы по ним | R6: Другие активы доходы по ним | U6: Вид обеспечения | V6: Сумма
L7: остаток | M7: по степени риска | N7: остаток | O7: по степени риска | P7: остаток | Q7: по степени риска | R7: остаток | S7: по степени риска
B8: А | C8: Б | D8: В | E8: Г | F8: Д | G8: Е | H8: Е1 | I8: Е2 | J8: Е3 | K8: Е4 | L8: Е5 | N8: Е6 | P8: Е7 | R8: Е8 | T8: Ж | U8: З | V8: И | W8: К | X8: Л | Y8: М | Z8: Н
A9: 1 | B9: АК "Ўзбектелеком" | C9: 203366731 | D9: 52300 | E9: 860 | F9: 1 | G9: =+H9+I9+J9+K9+M9+O9+Q9+S9 -> 692901062 | I9: 584524462 | N9: 108376600 | O9: 108376600 | U9: 2 | V9: 429776700 | Z9: =+G9-V9-X9 -> 263124362 | AA9: =SUMIF($F$9:$F$63,$F9,$Z$9:$Z$63) -> 263124362
A10: 2 | B10: Навоийский горно-метал. ком. | C10: 201204514 | D10: 12411 | E10: 840 | F10: 2 | G10: =+H10+I10+J10+K10+M10+O10+Q10+S10 -> 332900848 | I10: 332900848 | Z10: =+G10-V10-X10 -> 332900848 | AA10: =SUMIF($F$9:$F$63,$F10,$Z$9:$Z$63) -> 332900848
A11: 3 | B11: "Арт Фарфор" МЧЖ | C11: 308440870 | D11: 23490 | E11: 860 | F11: 3 | G11: =+H11+I11+J11+K11+M11+O11+Q11+S11 -> 161935462 | I11: 161935462 | Z11: =+G11-V11-X11 -> 161935462 | AA11: =SUMIF($F$9:$F$63,$F11,$Z$9:$Z$63) -> 161935462
A12: 4 | B12: "Нано Лизинг Компанияси" МЧЖ | C12: 207137166 | D12: 64910 | E12: 860 | F12: 4 | G12: =+H12+I12+J12+K12+M12+O12+Q12+S12 -> 161383437 | I12: 161383437 | Z12: =+G12-V12-X12 -> 161383437 | AA12: =SUMIF($F$9:$F$63,$F12,$Z$9:$Z$63) -> 163050104
A13: 5 | B13: "ИТ-Инвест" МЧЖ | C13: 305059128 | D13: 62020 | E13: 860 | F13: 4 | G13: =+H13+I13+J13+K13+M13+O13+Q13+S13 -> 1666667 | I13: 1666667 | Z13: =+G13-V13-X13 -> 1666667 | AA13: =SUMIF($F$9:$F$63,$F13,$Z$9:$Z$63) -> 163050104
A14: 6 | B14: "Жиззах-тоштепа текстил" МЧЖ | C14: 301945413 | D14: 14140 | E14: 860, 840 | F14: 5 | G14: =+H14+I14+J14+K14+M14+O14+Q14+S14 -> 144799281 | I14: 144799281 | Z14: =+G14-V14-X14 -> 144799281 | AA14: =SUMIF($F$9:$F$63,$F14,$Z$9:$Z$63) -> 144799281
A15: 7 | B15: "Мароқанд семент инвест" МЯЖ ҚК | C15: 304457725 | D15: 23510 | E15: 840 | F15: 6 | G15: =+H15+I15+J15+K15+M15+O15+Q15+S15 -> 143524167 | I15: 143524167 | Z15: =+G15-V15-X15 -> 143524167 | AA15: =SUMIF($F$9:$F$63,$F15,$Z$9:$Z$63) -> 143524167
A16: 8 | B16: “Ўзбекистон Республикаси Ташқи иқтисодий фаолият миллий банки” АЖ | C16: 200836354 | D16: 64190 | E16: 392, 643, 756, 826, 840, 978, 860 | F16: 7 | G16: =+H16+I16+J16+K16+M16+O16+Q16+S16 -> 3.0086375e+08 | H16: 3.0086375e+08 | Z16: =+G16-V16-X16 -> 3.0086375e+08 | AA16: =SUMIF($F$9:$F$63,$F16,$Z$9:$Z$63) -> 3.0086375e+08
A17: 9 | B17: ХЁАТ "Ориент Финанс банк" | C17: 207086151 | D17: 96120 | E17: 840 | F17: 8 | G17: =+H17+I17+J17+K17+M17+O17+Q17+S17 -> 162564900 | H17: 162564900 | Z17: =+G17-V17-X17 -> 162564900 | AA17: =SUMIF($F$9:$F$63,$F17,$Z$9:$Z$63) -> 162564900
A18: 10 | G18: =+H18+I18+J18+K18+M18+O18+Q18+S18 -> 0 | Z18: =+G18-V18-X18 -> 0 | AA18: =SUMIF($F$9:$F$63,$F18,$Z$9:$Z$63) -> 0
A19: 11 | G19: =+H19+I19+J19+K19+M19+O19+Q19+S19 -> 0 | Z19: =+G19-V19-X19 -> 0 | AA19: =SUMIF($F$9:$F$63,$F19,$Z$9:$Z$63) -> 0
A20: 12 | G20: =+H20+I20+J20+K20+M20+O20+Q20+S20 -> 0 | Z20: =+G20-V20-X20 -> 0 | AA20: =SUMIF($F$9:$F$63,$F20,$Z$9:$Z$63) -> 0
A21: 13 | G21: =+H21+I21+J21+K21+M21+O21+Q21+S21 -> 0 | Z21: =+G21-V21-X21 -> 0 | AA21: =SUMIF($F$9:$F$63,$F21,$Z$9:$Z$63) -> 0
A22: 14 | G22: =+H22+I22+J22+K22+M22+O22+Q22+S22 -> 0 | Z22: =+G22-V22-X22 -> 0 | AA22: =SUMIF($F$9:$F$63,$F22,$Z$9:$Z$63) -> 0
A23: 15 | G23: =+H23+I23+J23+K23+M23+O23+Q23+S23 -> 0 | Z23: =+G23-V23-X23 -> 0 | AA23: =SUMIF($F$9:$F$63,$F23,$Z$9:$Z$63) -> 0
A24: 16 | G24: =+H24+I24+J24+K24+M24+O24+Q24+S24 -> 0 | Z24: =+G24-V24-X24 -> 0 | AA24: =SUMIF($F$9:$F$63,$F24,$Z$9:$Z$63) -> 0
A25: 17 | G25: =+H25+I25+J25+K25+M25+O25+Q25+S25 -> 0 | Z25: =+G25-V25-X25 -> 0 | AA25: =SUMIF($F$9:$F$63,$F25,$Z$9:$Z$63) -> 0
A26: 18 | G26: =+H26+I26+J26+K26+M26+O26+Q26+S26 -> 0 | Z26: =+G26-V26-X26 -> 0 | AA26: =SUMIF($F$9:$F$63,$F26,$Z$9:$Z$63) -> 0
A27: 19 | G27: =+H27+I27+J27+K27+M27+O27+Q27+S27 -> 0 | Z27: =+G27-V27-X27 -> 0 | AA27: =SUMIF($F$9:$F$63,$F27,$Z$9:$Z$63) -> 0
A28: 20 | G28: =+H28+I28+J28+K28+M28+O28+Q28+S28 -> 0 | Z28: =+G28-V28-X28 -> 0 | AA28: =SUMIF($F$9:$F$63,$F28,$Z$9:$Z$63) -> 0
A29: 21 | G29: =+H29+I29+J29+K29+M29+O29+Q29+S29 -> 0 | Z29: =+G29-V29-X29 -> 0 | AA29: =SUMIF($F$9:$F$63,$F29,$Z$9:$Z$63) -> 0
... A63: 55 | G63: =+H63+I63+J63+K63+M63+O63+Q63+S63 -> 0 | Z63: =+G63-V63-X63 -> 0 | AA63: =SUMIF($F$9:$F$63,$F63,$Z$9:$Z$63) -> 0
B64: ИТОГО КРУПНЫХ АКТИВОВ | G64: =SUM(G9:G63) -> 2.1025396e+09 | H64: =SUM(H9:H63) -> 4.6342865e+08 | I64: =SUM(I9:I63) -> 1530734324 | J64: =SUM(J9:J63) -> 0 | K64: =SUM(K9:K63) -> 0 | L64: =SUM(L9:L63) -> 0 | M64: =SUM(M9:M63) -> 0 | N64: =SUM(N9:N63) -> 108376600 | ... T64: =SUM(T9:T63) -> 0 | V64: =SUM(V9:V63) -> 429776700 | X64: =SUM(X9:X63) -> 0 | Y64: =SUM(Y9:Y63) -> 0 | Z64: =SUM(Z9:Z63) -> 1.6727629e+09
B65: САМЫЙ КРУПНЫЙ АКТИВ, ВЫДАННЫЙ БАНКОМ | G65: =+SUMIF($F$9:$F$63,$AA$65,$G$9:$G$63) -> 332900848 | H65: =+SUMIF($F$9:$F$63,$AA$65,$H$9:$H$63) -> 0 | I65: =+SUMIF($F$9:$F$63,$AA$65,$I$9:$I$63) -> 332900848 | J65: =+SUMIF($F$9:$F$63,$AA$65,$J$9:$J$63) -> 0 | K65: =+SUMIF($F$9:$F$63,$AA$65,$K$9:$K$63) -> 0 | L65: =+SUMIF($F$9:$F$63,$AA$65,$L$9:$L$63) -> 0 | M65: =+SUMIF($F$9:$F$63,$AA$65,$M$9:$M$63) -> 0 | N65: =+SUMIF($F$9:$F$63,$AA$65,$N$9:$N$63) -> 0 | O65: =+SUMIF($F$9:$F$63,$AA$65,$O$9:$O$63) -> 0 | P65: =+SUMIF($F$9:$F$63,$AA$65,$P$9:$P$63) -> 0 | Q65: =+SUMIF($F$9:$F$63,$AA$65,$Q$9:$Q$63) -> 0 | R65: =+SUMIF($F$9:$F$63,$AA$65,$R$9:$R$63) -> 0 | S65: =+SUMIF($F$9:$F$63,$AA$65,$S$9:$S$63) -> 0 | T65: =+SUMIF($F$9:$F$63,$AA$65,$T$9:$T$63) -> 0 | V65: =+SUMIF($F$9:$F$63,$AA$65,$V$9:$V$63) -> 0 | X65: =+SUMIF($F$9:$F$63,$AA$65,$X$9:$X$63) -> 0 | Y65: =+SUMIF($F$9:$F$63,$AA$65,$Y$9:$Y$63) -> 0 | Z65: =+MAX(AA9:AA63) -> 332900848 | AA65: =INDEX($F$9:$F$63,MATCH($Z65,$AA$9:$AA$63,0)) -> 2
B68: Подпись Председателя правления:
B70: Подпись Главного Бухгалтера:

Sheet Charge-offs and Recoveries
A1: ОТЧЕТ О CПИСАННЫХ И ВОЗВРАЩЕННЫХ КРЕДИТАХ И ЛИЗИНГАХ, А ТАКЖЕ РЕЗЕРВАХ ПО НИМ | J1: Таблица-13
A3: Часть 1 Списания и возврат сумму кредитов и лизинга за последние 12 месяцев | I3: =+'Asset quality'!P3 -> 44561
A4: № | B4: Отрасли экономики и виды кредитования | C4: ="Остаток списаных кредита и лизинга на"&" "&DAY(I3)&"."&IF(LEN(MONTH(I3))<2,"0"&MONTH(I3),MONTH(I3))&"."&YEAR(I3)-1&"г" -> Остаток списаных кредита и лизинга на 31.12.2020г | D4: Списания и возврат кредитов и лизингов | J4: ="Остаток списаных кредита и лизинга на"&" "&DAY(I3)&"."&IF(LEN(MONTH(I3))<2,"0"&MONTH(I3),MONTH(I3))&"."&YEAR(I3)&"г" -> Остаток списаных кредита и лизинга на 31.12.2021г
D5: Списанние на забалансовый счет | F5: Возврат из забалансового счета | H5: Итоговое списанние из забалансового счета
D6: Всего | E6: в иностранной валюте | F6: Всего | G6: в иностранной валюте | H6: Всего | I6: в иностранной валюте
B7: А | C7: Б | D7: В | E7: Г | F7: Д | G7: Е | H7: Ж | I7: З | J7: И
A8: 1 | B8: Юридические лица | C8: =SUM(C10:C17) -> 743185 | D8: =SUM(D10:D17) -> 0 | E8: =SUM(E10:E17) -> 0 | F8: =SUM(F10:F17) -> 0 | G8: =SUM(G10:G17) -> 0 | H8: =SUM(H10:H17) -> 0 | I8: =SUM(I10:I17) -> 0 | J8: =SUM(J10:J17) -> 15044994
B9: из них
A10: 1.1. | B10: Промышленность | E10: 0 | F10: 0 | G10: 0 | J10: 413675
A11: 1.2. | B11: Сельское хозяйство | D11: 0 | E11: 0 | F11: 0 | G11: 0 | J11: 949693
A12: 1.3. | B12: Транспорт и коммуникации | D12: 0 | E12: 0 | F12: 0 | G12: 0 | J12: 175451
A13: 1.4. | B13: Строительство | E13: 0 | F13: 0 | G13: 0 | J13: 1340662
A14: 1.5. | B14: Торговля и общественное питание | E14: 0 | F14: 0 | G14: 0 | J14: 10661645
A15: 1.6. | B15: Материально-техническое снабжение и сбыт | J15: 320576
A16: 1.7. | B16: Жилищно-коммунальные услуги | E16: 0 | F16: 0 | G16: 0 | J16: 1150304
A17: 1.8. | B17: Другие сектора | C17: 743185 | D17: 0 | E17: 0 | F17: 0 | G17: 0 | J17: =10733372-10700384 -> 32988
A18: 2 | B18: Физические лица | C18: =SUM(C20:C24) -> 201513.75 | D18: =SUM(D20:D24) -> 0 | E18: =SUM(E20:E24) -> 0 | F18: =SUM(F20:F24) -> 0 | G18: =SUM(G20:G24) -> 0 | H18: =SUM(H20:H24) -> 0 | I18: =SUM(I20:I24) -> 0 | J18: =SUM(J20:J24) -> 10700384
B19: из них
A20: 2.1. | B20: Ипотечный кредит | C20: 0 | D20: 0 | E20: 0 | F20: 0 | G20: 0
A21: 2.2. | B21: Автокредит
A22: 2.3. | B22: Микрозаймы и овердрафты (все нецелевые кредиты)
A23: 2.4. | B23: потребительские кредиты | C23: 41559.149
A24: 2.5. | B24: другие кредиты физическим лицам | C24: 159954.6 | J24: 10700384
A25: 3 | B25: Итого | C25: =+C18+C8 -> 944698.75 | D25: =+D18+D8 -> 0 | E25: =+E18+E8 -> 0 | F25: =+F18+F8 -> 0 | G25: =+G18+G8 -> 0 | H25: =+H18+H8 -> 0 | I25: =+I18+I8 -> 0 | J25: =+J18+J8 -> 25745378
A27: Часть 2 Списанные и возвращенные резервы по кредитам и лизингам за последние 12 месяцев
A28: № | B28: Отрасли экономики и виды кредитования | C28: ="Резервы возможных потерь по кредитам и лизингу на"&" "&DAY(I3)&"."&IF(LEN(MONTH(I3))<2,"0"&MONTH(I3),MONTH(I3))&"."&YEAR(I3)-1&"г" -> Резервы возможных потерь по кредитам и лизингу на 31.12.2020г | D28: Списания и возврат резервов по кредитам и лизингам | H28: Движение по резервам за последние 12 месяцев | I28: ="Резервы возможных потерь по кредитам и лизингу на"&" "&DAY(I3)&"."&IF(LEN(MONTH(I3))<2,"0"&MONTH(I3),MONTH(I3))&"."&YEAR(I3)&"г" -> Резервы возможных потерь по кредитам и лизингу на 31.12.2021г
D29: Списание резервов | F29: Возврат резервов
D30: Всего | E30: в иностранной валюте | F30: Всего | G30: в иностранной валюте
B31: А | C31: Б | D31: В | E31: Г | F31: Д | G31: Е | H31: Ж | I31: З
A32: 1 | B32: Юридические лица | C32: =SUM(C34:C41) -> 6729637 | D32: =SUM(D34:D41) -> 0 | E32: =SUM(E34:E41) -> 0 | F32: =SUM(F34:F41) -> 0 | G32: =SUM(G34:G41) -> 0 | H32: =SUM(H34:H41) -> 0 | I32: =SUM(I34:I41) -> 54859184
B33: из них
A34: 1.1. | B34: Промышленность | C34: 833239 | E34: 0 | I34: 13303632
A35: 1.2. | B35: Сельское хозяйство | C35: 2108992 | D35: 0 | E35: 0 | I35: 3258002
A36: 1.3. | B36: Транспорт и коммуникации | C36: 14747 | D36: 0 | E36: 0 | I36: 3744907
A37: 1.4. | B37: Строительство | C37: 233213 | E37: 0 | I37: 2850677
A38: 1.5. | B38: Торговля и общественное питание | C38: 179623 | E38: 0 | I38: 8199274
A39: 1.6. | B39: Материально-техническое снабжение и сбыт | E39: 0 | I39: 11716827
A40: 1.7. | B40: Жилищно-коммунальные услуги | C40: 694592 | E40: 0 | I40: 7767505
A41: 1.8. | B41: Другие сектора | C41: =5012762-2347531 -> 2665231 | D41: 0 | E41: 0 | I41: =50153520-46135160 -> 4018360
A42: 2 | B42: Физические лица | C42: =SUM(C44:C48) -> 2347531 | D42: =SUM(D44:D48) -> 0 | E42: =SUM(E44:E48) -> 0 | F42: =SUM(F44:F48) -> 0 | G42: =SUM(G44:G48) -> 0 | H42: =SUM(H44:H48) -> 0 | I42: =SUM(I44:I48) -> 46135160
B43: из них
A44: 2.1. | B44: Ипотечный кредит | C44: 0 | I44: 20189790
A45: 2.2. | B45: Автокредит | I45: 7813202
A46: 2.3. | B46: Микрозаймы и овердрафты (все нецелевые кредиты) | I46: 7603550
A47: 2.4. | B47: потребительские кредиты | C47: 2347531 | I47: 5900189
A48: 2.5. | B48: другие кредиты физическим лицам | I48: 4628429
A49: 3 | B49: Итого | C49: =+C42+C32 -> 9077168 | D49: =+D42+D32 -> 0 | E49: =+E42+E32 -> 0 | F49: =+F42+F32 -> 0 | G49: =+G42+G32 -> 0 | H49: =+H42+H32 -> 0 | I49: =+I42+I32 -> 100994344
B51: Подпись Председателя правления:
B53: Подпись Главного Бухгалтера:

Sheet loans_av rate
A1: ДАННЫЕ О СРЕДНЕВЗВЕШЕННЫХ ПРОЦЕНТНЫХ СТАВКАХ ПО КРЕДИТАМ | H1: Таблица-20
B3: =+'Asset quality'!B3 -> АК "АЛОКАБАНК" | F3: =+'Asset quality'!P3 -> 44561 | H3: тыс. сум
A4: № | B4: Виды кредитования | C4: всего | E4: в том числе
E5: в национальный валюте | G5: в иностранной валюте
C6: остаток всего | D6: средневзвешенные процентные ставки | E6: остаток всего | F6: средневзвешенные процентные ставки | G6: остаток всего | H6: средневзвешенные процентные ставки
B7: А | C7: Б | D7: В | E7: Г | F7: Д | G7: Е | H7: Ж
A8: 1 | B8: Физические лица (льготные кредиты) | C8: =SUM(C10:C14) -> 91630014 | D8: =IFERROR(((C10*D10)/C8)+((C11*D11)/C8)+((C12*D12)/C8)+((C13*D13)/C8)+((C14*D14)/C8),0) -> 0.10670147 | E8: =SUM(E10:E14) -> 91630014 | F8: =IFERROR(((E10*F10)/E8)+((E11*F11)/E8)+((E12*F12)/E8)+((E13*F13)/E8)+((E14*F14)/E8),0) -> 0.10670147 | G8: =SUM(G10:G14) -> 0 | H8: =IFERROR(((G10*H10)/G8)+((G11*H11)/G8)+((G12*H12)/G8)+((G13*H13)/G8)+((G14*H14)/G8),0) -> 0 | J8: =+C8+C16+C24+C33 -> 7754313870 | K8: =+E8+E16+E24+E33 -> 4807418968 | L8: =+G8+G16+G24+G33 -> 2946894902
B9: в том числе | J9: =+'loans type'!C8 -> 7754313870 | K9: =+'loans type'!E8 -> 4807418968 | L9: =+'loans type'!G8 -> 2946894902
A10: 1.1. | B10: ипотечный кредит | C10: =+E10+G10 -> 59138478 | D10: 0.11363801 | E10: 59138478 | F10: 0.11363801 | J10: =+J8-J9 -> 0 | K10: =+K8-K9 -> 0 | L10: =+L8-L9 -> 0
A11: 1.2. | B11: автокредит | C11: =+E11+G11 -> 45341 | D11: 0.14 | E11: 45341 | F11: 0.14
A12: 1.3. | B12: микрозайм (все нецелевые кредиты) | C12: =+E12+G12 -> 0
A13: 1.4. | B13: потребительские кредиты | C13: =+E13+G13 -> 5506710 | D13: 0.065457859 | E13: 5506710 | F13: 0.065457859
A14: 1.5. | B14: другие кредиты физическим лицам | C14: =+E14+G14 -> 26939485 | D14: 0.099848724 | E14: 26939485 | F14: 0.099848724
A16: 2 | B16: Физические лица (коммерческие кредиты) | C16: =SUM(C18:C22) -> 1237354215 | D16: =IFERROR(((C18*D18)/C16)+((C19*D19)/C16)+((C20*D20)/C16)+((C21*D21)/C16)+((C22*D22)/C16),0) -> 0.23306664 | E16: =SUM(E18:E22) -> 1237354215 | F16: =IFERROR(((E18*F18)/E16)+((E19*F19)/E16)+((E20*F20)/E16)+((E21*F21)/E16)+((E22*F22)/E16),0) -> 0.23306664 | G16: =SUM(G18:G22) -> 0 | H16: =IFERROR(((G18*H18)/G16)+((G19*H19)/G16)+((G20*H20)/G16)+((G21*H21)/G16)+((G22*H22)/G16),0) -> 0
B17: в том числе
A18: 2.1. | B18: ипотечный кредит | C18: =+E18+G18 -> 339218462 | D18: 0.18101866 | E18: 339218462 | F18: 0.18101866
A19: 2.2. | B19: автокредит | C19: =+E19+G19 -> 362753040 | D19: 0.23311926 | E19: 362753040 | F19: 0.23311926
A20: 2.3. | B20: микрозайм (все нецелевые кредиты) | C20: =+E20+G20 -> 513443354 | D20: 0.26706628 | E20: 513443354 | F20: 0.26706628
A21: 2.4. | B21: потребительские кредиты | C21: =+E21+G21 -> 17138978 | D21: 0.26651473 | E21: 17138978 | F21: 0.26651473
A22: 2.5. | B22: другие кредиты физическим лицам | C22: =+E22+G22 -> 4800381 | D22: 0.15107285 | E22: 4800381 | F22: 0.15107285
A24: 3 | B24: Юридические лица (льготные кредиты) | C24: =SUM(C26:C31) -> 1143197050 | D24: =IFERROR(((C26*D26)/C24)+((C27*D27)/C24)+((C28*D28)/C24)+((C29*D29)/C24)+((C30*D30)/C24)+((C31*D31)/C24),0) -> 0.087918903 | E24: =SUM(E26:E31) -> 751196483 | F24: =IFERROR(((E26*F26)/E24)+((E27*F27)/E24)+((E28*F28)/E24)+((E29*F29)/E24)+((E30*F30)/E24)+((E31*F31)/E24),0) -> 0.11515433 | G24: =SUM(G26:G31) -> 392000567 | H24: =IFERROR(((G26*H26)/G24)+((G27*H27)/G24)+((G28*H28)/G24)+((G29*H29)/G24)+((G30*H30)/G24)+((G31*H31)/G24),0) -> 0.035727259
B25: в том числе
A26: 3.1. | B26: микрокредит | C26: =+E26+G26 -> 5859843 | D26: 0.091134155 | E26: 5859843 | F26: 0.091134155 | G26: 0 | H26: 0
A27: 3.2. | B27: синдицированные кредит | C27: =+E27+G27 -> 0
A28: 3.3. | B28: лизинг | C28: =+E28+G28 -> 305556 | D28: 0 | E28: 305556 | F28: 0 | G28: 0 | H28: 0
A29: 3.4. | B29: факторинг | C29: =+E29+G29 -> 0
A30: 3.5. | B30: межбанковский кредит | C30: =+E30+G30 -> 0
A31: 3.6. | B31: другие кредиты юридическим лицам | C31: =+E31+G31 -> 1137031651 | D31: 0.08792596 | E31: 745031084 | F31: 0.11539048 | G31: 392000567 | H31: 0.035727259
A33: 4 | B33: Юридические лица (коммерческие кредиты) | C33: =SUM(C35:C40) -> 5282132591 | D33: =IFERROR(((C35*D35)/C33)+((C36*D36)/C33)+((C37*D37)/C33)+((C38*D38)/C33)+((C39*D39)/C33)+((C40*D40)/C33),0) -> 0.14579483 | E33: =SUM(E35:E40) -> 2727238256 | F33: =IFERROR(((E35*F35)/E33)+((E36*F36)/E33)+((E37*F37)/E33)+((E38*F38)/E33)+((E39*F39)/E33)+((E40*F40)/E33),0) -> 0.20856436 | G33: =SUM(G35:G40) -> 2554894335 | H33: =IFERROR(((G35*H35)/G33)+((G36*H36)/G33)+((G37*H37)/G33)+((G38*H38)/G33)+((G39*H39)/G33)+((G40*H40)/G33),0) -> 0.078791094
B34: в том числе
A35: 4.1. | B35: микрокредит | C35: =+E35+G35 -> 40510094 | D35: 0.23083763 | E35: 37518726 | F35: 0.24044691 | G35: 2991368 | H35: 0.11031489
A36: 4.2. | B36: синдицированные кредит | C36: =+E36+G36 -> 0
A37: 4.3. | B37: лизинг | C37: =+E37+G37 -> 0
A38: 4.4. | B38: факторинг | C38: =+E38+G38 -> 0
A39: 4.5. | B39: межбанковский кредит | C39: =+E39+G39 -> 0
A40: 4.6. | B40: другие кредиты юридическим лицам | C40: =+E40+G40 -> 5241622497 | D40: 0.14513757 | E40: 2689719530 | F40: 0.20811963 | G40: 2551902967 | H40: 0.078754142
B43: Подпись Председателя правления:
B45: Подпись Главного Бухгалтера:
B47: Всего | C47: =+C8+C16+C24+C33 -> 7754313870 | E47: =+E8+E16+E24+E33 -> 4807418968 | G47: =+G8+G16+G24+G33 -> 2946894902
C48: =+C50+C54 -> 7754313870 | E48: =+E9+E17+E25+E34 -> 0 | G48: =+G50+G54 -> 2946894902
B50: Физлица | C50: =+'Asset Classification'!C12 -> 1328984229 | G50: =+'Asset Classification'!D12 -> 0
C51: =C8+C16 -> 1328984229 | G51: =G8+G16 -> 0
C52: =+C50-C51 -> 0 | G52: =+G50-G51 -> 0
B54: Юрзлица | C54: =+'Asset Classification'!C30-'Asset Classification'!C12 -> 6425329641 | G54: =+'Asset Classification'!D30-'Asset Classification'!D12 -> 2946894902
C55: =C24+C33 -> 6425329641 | G55: =G24+G33 -> 2946894902
C56: =+C54-C55 -> 0 | G56: =+G54-G55 -> 0

Sheet loans type
Z1: Таблица-20 А
A2: Информация о структуре кредитного портфеля
B3: =+'Asset quality'!B3 -> АК "АЛОКАБАНК" | V3: =+'Asset quality'!P3 -> 44561 | Z3: тыс. сум
A4: № | B4: Виды кредитования | C4: всего | I4: Сроки | N4: Категория качества | S4: Резерв на возможные потери | Y4: Списанные на внебаланс | Z4: Реструктуризи-рованные кредиты
I5: до 1 года | J5: От 1 до 5 лет | K5: От 5 до 10 лет | L5: От 10 до 15 лет | M5: Свыше 15 лет | S5: итого | T5: по категориям качества
C6: Остаток | D6: средневзвешенные % ставки | E6: в нацвалюте | F6: средневзвешенные % ставки | G6: в инвалюте | H6: средневзвешенные % ставки | N6: I | O6: II | P6: III | Q6: IV | R6: V | T6: I | U6: II | V6: III | W6: IV | X6: V | AB6: I | AC6: II | AD6: III | AE6: IV | AF6: V
B7: А | C7: Б | D7: В | E7: Г | F7: Д | G7: Е | H7: Ж | I7: З | J7: И | K7: К | L7: Л | M7: М | N7: Н | O7: О | P7: П | Q7: Р | R7: С | S7: Т | T7: У | U7: Ф | V7: Х | W7: Ц | X7: Ч | Y7: Ш | Z7: Щ
B8: ВСЕГО | C8: =+C9+C25 -> 7754313870 | D8: =IFERROR(((C9*D9)/C8)+((C25*D25)/C8),0) -> 0 | E8: =+E9+E25 -> 4807418968 | F8: =IFERROR(((E9*F9)/E8)+((E25*F25)/E8),0) -> 0.20140533 | G8: =+G9+G25 -> 2946894902 | H8: =IFERROR(((G9*H9)/G8)+((G25*H25)/G8),0) -> 0.073062676 | I8: =+I9+I25 -> 7585304009 | J8: =+J9+J25 -> 165774170 | K8: =+K9+K25 -> 15586 | L8: =+L9+L25 -> 3220105 | M8: =+M9+M25 -> 0 | N8: =+N9+N25 -> 6823371532 | O8: =+O9+O25 -> 616609354 | P8: =+P9+P25 -> 71675920 | ... Z8: =+Z9+Z25 -> 44554200 | AA8: =+'Loans Receivable'!C92 -> 7754313870 | AB8: =+'Asset Classification'!G30 -> 58952965 | AC8: =+'Asset Classification'!K30 -> 20742554 | AD8: =+'Asset Classification'!O50 -> 6483802 | AE8: =+'Asset Classification'!S50 -> 16043961 | AF8: =+'Asset Classification'!W50 -> 57724027
A9: I | B9: Физические лица | C9: =+C11+C16+C21+C22+C24 -> 1328984229 | D9: =IFERROR(((C11*D11)/C9)+((C16*D16)/C9)+((C21*D21)/C9)+((C22*D22)/C9)+((C24*D24)/C9),0) -> 0 | E9: =+E11+E16+E21+E22+E24 -> 1328984229 | F9: =IFERROR(((E11*F11)/E9)+((E16*F16)/E9)+((E21*F21)/E9)+((E22*F22)/E9)+((E24*F24)/E9),0) -> 0.23546674 | G9: =+G11+G16+G21+G22+G24 -> 0 | H9: =IFERROR(((G11*H11)/G9)+((G16*H16)/G9)+((G21*H21)/G9)+((G22*H22)/G9)+((G24*H24)/G9),0) -> 0 | I9: =+I11+I16+I21+I22+I24 -> 1280888885 | J9: =+J11+J16+J21+J22+J24 -> 45242414 | K9: =+K11+K16+K21+K22+K24 -> 15586 | L9: =+L11+L16+L21+L22+L24 -> 2837344 | M9: =+M11+M16+M21+M22+M24 -> 0 | N9: =+N11+N16+N21+N22+N24 -> 1196175378 | O9: =+O11+O16+O21+O22+O24 -> 54715259 | P9: =+P11+P16+P21+P22+P24 -> 13772216 | ... Z9: =+Z11+Z16+Z21+Z22+Z24 -> 0 | AA9: =+'Loans Receivable'!C80 -> 1328984229 | AB9: =+'Asset Classification'!E30 -> 6823371532 | AC9: =+'Asset Classification'!I30 -> 616609354 | AD9: =+'Asset Classification'!M30 -> 71675920 | AE9: =+'Asset Classification'!Q30 -> 73761027 | AF9: =+'Asset Classification'!U30 -> 168896037
B10: в том числе | AB10: =+N8-AB9 -> 0 | AC10: =+O8-AC9 -> 0 | AD10: =+P8-AD9 -> 0 | AE10: =+Q8-AE9 -> 0 | AF10: =+R8-AF9 -> 0
A11: 1 | B11: Ипотечные кредиты (льготные) в том числе: | C11: =SUM(C12:C15) -> 59138478 | D11: =IFERROR(((C12*D12)/C11)+((C13*D13)/C11)+((C14*D14)/C11)+((C15*D15)/C11),0) -> 0 | E11: =SUM(E12:E15) -> 59138478 | F11: =IFERROR(((E12*F12)/E11)+((E13*F13)/E11)+((E14*F14)/E11)+((E15*F15)/E11),0) -> 0.1146116 | G11: =SUM(G12:G15) -> 0 | H11: =IFERROR(((G12*H12)/G11)+((G13*H13)/G11)+((G14*H14)/G11)+((G15*H15)/G11),0) -> 0 | I11: =SUM(I12:I15) -> 38711873 | J11: =SUM(J12:J15) -> 18106283 | K11: =SUM(K12:K15) -> 15586 | L11: =SUM(L12:L15) -> 2304736 | M11: =SUM(M12:M15) -> 0 | N11: =SUM(N12:N15) -> 52858872 | O11: =SUM(O12:O15) -> 3603126 | P11: =SUM(P12:P15) -> 863174 | ... Z11: =SUM(Z12:Z15) -> 0 | AA11: =+'loans_av rate'!C10 -> 59138478 | AB11: =+'loans_av rate'!E10 -> 59138478 | AC11: =+'loans_av rate'!G10 -> 0
A12: 1.1. | B12: на приобретение недвижимого имущества | C12: =+E12+G12 -> 17640776 | E12: 17640776 | F12: 0.1695 | G12: 0 | H12: 0 | I12: 6976040 | J12: 10631345 | K12: 15586 | L12: 17805 | M12: 0 | N12: 16102312 | O12: 910838 | P12: 348970 | Q12: 189452 | R12: 89204 | S12: =SUM(T12:X12) -> 450217 | T12: 139122 | U12: 52360 | V12: 74805 | W12: 94726 | X12: 89204
A13: 1.2. | B13: на ремонт недвижимого имущества | C13: =+E13+G13 -> 40645568 | E13: 40645568 | F13: 0.09 | G13: 0 | H13: 0 | I13: 31100499 | J13: 7284805 | K13: 0 | L13: 2260264 | M13: 0 | N13: 35931093 | O13: 2665621 | P13: 514204 | Q13: 464123 | R13: 1070527 | S13: =SUM(T13:X13) -> 1995665 | T13: 310440 | U13: 375487 | V13: 78082 | W13: 217268 | X13: 1014388
A14: 1.3. | B14: на реконструкцию недвижимого имущества | C14: =+E14+G14 -> 390467 | E14: 390467 | F14: 0.1619 | G14: 0 | H14: 0 | I14: 173667 | J14: 190133 | K14: 0 | L14: 26667 | M14: 0 | N14: 363800 | O14: 26667 | P14: 0 | Q14: 0 | R14: 0 | S14: =SUM(T14:X14) -> 5810 | T14: 3143 | U14: 2667 | V14: 0 | W14: 0 | X14: 0
A15: 1.4. | B15: на строительство недвижимого имущества | C15: =+E15+G15 -> 461667 | E15: 461667 | F15: 0.1441 | G15: 0 | H15: 0 | I15: 461667 | J15: 0 | K15: 0 | L15: 0 | M15: 0 | N15: 461667 | O15: 0 | P15: 0 | Q15: 0 | R15: 0 | S15: =SUM(T15:X15) -> 3989 | T15: 3989 | U15: 0 | V15: 0 | W15: 0 | X15: 0
A16: 2 | B16: Ипотечные кредиты (коммерческие) в том числе: | C16: =SUM(C17:C20) -> 339218462 | D16: =IFERROR(((C17*D17)/C16)+((C18*D18)/C16)+((C19*D19)/C16)+((C20*D20)/C16),0) -> 0 | E16: =SUM(E17:E20) -> 339218462 | F16: =IFERROR(((E17*F17)/E16)+((E18*F18)/E16)+((E19*F19)/E16)+((E20*F20)/E16),0) -> 0.1808804 | G16: =SUM(G17:G20) -> 0 | H16: =IFERROR(((G17*H17)/G16)+((G18*H18)/G16)+((G19*H19)/G16)+((G20*H20)/G16),0) -> 0 | I16: =SUM(I17:I20) -> 322881239 | J16: =SUM(J17:J20) -> 15948646 | K16: =SUM(K17:K20) -> 0 | L16: =SUM(L17:L20) -> 388577 | M16: =SUM(M17:M20) -> 0 | N16: =SUM(N17:N20) -> 276712547 | O16: =SUM(O17:O20) -> 22064291 | P16: =SUM(P17:P20) -> 6872812 | ... Z16: =SUM(Z17:Z20) -> 0 | AA16: =+'loans_av rate'!C18 -> 339218462 | AB16: =+'loans_av rate'!E18 -> 339218462 | AC16: =+'loans_av rate'!G18 -> 0
A17: 2.1. | B17: на приобретение недвижимого имущества | C17: =+E17+G17 -> 26578425 | E17: 26578425 | F17: 0.1836 | G17: 0 | H17: 0 | I17: 25106738 | J17: 1445766 | K17: 0 | L17: 25921 | M17: 0 | N17: 24496247 | O17: 1453222 | P17: 0 | Q17: 628956 | R17: 0 | S17: =SUM(T17:X17) -> 799340 | T17: 211644 | U17: 273218 | V17: 0 | W17: 314478 | X17: 0 | Y17: 1991091
A18: 2.2. | B18: на ремонт недвижимого имущества | C18: =+E18+G18 -> 298773391 | E18: 298773391 | F18: 0.181 | G18: 0 | H18: 0 | I18: 283989047 | J18: 14421688 | K18: 0 | L18: 362656 | M18: 0 | N18: 238445487 | O18: 20515236 | P18: 6872812 | Q18: 7829099 | R18: 25110757 | S18: =SUM(T18:X18) -> 19663242 | T18: 2060135 | U18: 1665857 | V18: 1072962 | W18: 3313872 | X18: 11550416
A19: 2.3. | B19: на реконструкцию недвижимого имущества | C19: =+E19+G19 -> 13223568 | E19: 13223568 | F19: 0.1747 | G19: 0 | H19: 0 | I19: 13223568 | J19: 0 | K19: 0 | L19: 0 | M19: 0 | N19: 13127735 | O19: 95833 | P19: 0 | Q19: 0 | R19: 0 | S19: =SUM(T19:X19) -> 113422 | T19: 113422 | U19: 0 | V19: 0 | W19: 0 | X19: 0
A20: 2.4. | B20: на строительство недвижимого имущества | C20: =+E20+G20 -> 643078 | E20: 643078 | F20: 14% | G20: 0 | H20: 0 | I20: 561886 | J20: 81192 | K20: 0 | L20: 0 | M20: 0 | N20: 643078 | O20: 0 | P20: 0 | Q20: 0 | R20: 0 | S20: =SUM(T20:X20) -> 5556 | T20: 5556 | U20: 0 | V20: 0 | W20: 0 | X20: 0
A21: 3 | B21: микрозайм (все нецелевые кредиты) | C21: =+E21+G21 -> 513443354 | E21: 513443354 | F21: 0.267 | G21: 0 | H21: 0 | I21: 513345024 | J21: 98330 | K21: 0 | L21: 0 | M21: 0 | N21: 491653338 | O21: 10582767 | P21: 2005853 | Q21: 5767292 | R21: 3434104 | S21: =SUM(T21:X21) -> 11851365 | T21: 4247815 | U21: 946700 | V21: 483884 | W21: 2844833 | X21: 3328133 | Y21: 138877 | AA21: =+'loans_av rate'!C12+'loans_av rate'!C20 -> 513443354 | AB21: =+'loans_av rate'!E12+'loans_av rate'!E20 -> 513443354 | AC21: =+'loans_av rate'!G12+'loans_av rate'!G20 -> 0
A22: 4 | B22: потребительские кредиты | C22: =+E22+G22 -> 385444069 | E22: 385444069 | F22: 0.267 | G22: 0 | H22: 0 | I22: 375777186 | J22: 9522852 | K22: 0 | L22: 144031 | M22: 0 | N22: 352726931 | O22: 14836590 | P22: 3047974 | Q22: 5582402 | R22: 9250172 | S22: =SUM(T22:X22) -> 16760902 | T22: 3047511 | U22: 1241316 | V22: 742750 | W22: 2659379 | X22: 9069946 | Y22: 607756 | AA22: =+'loans_av rate'!C11+'loans_av rate'!C13+'loans_av rate'!C19+'loans_av rate'!C21 -> 385444069 | AB22: =+'loans_av rate'!E11+'loans_av rate'!E13+'loans_av rate'!E19+'loans_av rate'!E21 -> 385444069
A23: 4.1. | B23: из них на приобретения автомобиля | C23: =+E23+G23 -> 362798381 | E23: 362798381 | F23: 0.233 | G23: 0 | H23: 0 | I23: 353789278 | J23: 9009103 | K23: 0 | L23: 0 | M23: 0 | N23: 338369594 | O23: 13452823 | P23: 2606503 | Q23: 3976844 | R23: 4392617 | S23: =SUM(T23:X23) -> 10736667 | T23: 2923465 | U23: 1117352 | V23: 636130 | W23: 1862254 | X23: 4197466 | Y23: 517656 | AA23: =+'loans_av rate'!C11+'loans_av rate'!C19 -> 362798381 | AB23: =+'loans_av rate'!E11+'loans_av rate'!E19 -> 362798381 | AC23: =+'loans_av rate'!G11+'loans_av rate'!G19 -> 0
A24: 5 | B24: другие кредиты физическим лицам | C24: =+E24+G24 -> 31739866 | E24: 31739866 | F24: 0.151 | G24: 0 | H24: 0 | I24: 30173563 | J24: 1566303 | K24: 0 | L24: 0 | M24: 0 | N24: 22223690 | O24: 3628485 | P24: 982403 | Q24: 1996569 | R24: 2908719 | S24: =SUM(T24:X24) -> 4820438 | T24: 192009 | U24: 338238 | V24: 234724 | W24: 1145360 | X24: 2910107 | AA24: =+'loans_av rate'!C14+'loans_av rate'!C22 -> 31739866 | AB24: =+'loans_av rate'!E14+'loans_av rate'!E22 -> 31739866
A25: II | B25: Юридические лица | C25: =+C26 -> 6425329641 | D25: =IFERROR(((C27*D27)/C25)+((C28*D28)/C25)+((C29*D29)/C25)+((C30*D30)/C25)+((C31*D31)/C25)+((C32*D32)/C25),0) -> 0 | E25: =+E26 -> 3478434739 | F25: =IFERROR(((E27*F27)/E25)+((E28*F28)/E25)+((E29*F29)/E25)+((E30*F30)/E25)+((E31*F31)/E25)+((E32*F32)/E25),0) -> 0.1883917 | G25: =+G26 -> 2946894902 | H25: =IFERROR(((G27*H27)/G25)+((G28*H28)/G25)+((G29*H29)/G25)+((G30*H30)/G25)+((G31*H31)/G25)+((G32*H32)/G25),0) -> 0.073062676 | I25: =+I26 -> 6304415124 | J25: =+J26 -> 120531756 | K25: =+K26 -> 0 | L25: =+L26 -> 382761 | M25: =+M26 -> 0 | N25: =+N26 -> 5627196154 | O25: =+O26 -> 561894095 | P25: =+P26 -> 57903704 | ... Z25: =+Z26 -> 44554200 | AA25: =+'loans_av rate'!C24+'loans_av rate'!C33 -> 6425329641 | AB25: =+'loans_av rate'!E24+'loans_av rate'!E33 -> 3478434739 | AC25: =+'loans_av rate'!G24+'loans_av rate'!G33 -> 2946894902
B26: в том числе по видам кредитования | C26: =SUM(C27:C32) -> 6425329641 | D26: =IFERROR(((C28*D28)/C26)+((C29*D29)/C26)+((C30*D30)/C26)+((C31*D31)/C26)+((C32*D32)/C26),0) -> 0 | E26: =SUM(E27:E32) -> 3478434739 | F26: =IFERROR(((E28*F28)/E26)+((E29*F29)/E26)+((E30*F30)/E26)+((E31*F31)/E26)+((E32*F32)/E26),0) -> 0.18564469 | G26: =SUM(G27:G32) -> 2946894902 | H26: =IFERROR(((G28*H28)/G26)+((G29*H29)/G26)+((G30*H30)/G26)+((G31*H31)/G26)+((G32*H32)/G26),0) -> 0.072950696 | I26: =SUM(I27:I32) -> 6304415124 | J26: =SUM(J27:J32) -> 120531756 | K26: =SUM(K27:K32) -> 0 | L26: =SUM(L27:L32) -> 382761 | M26: =SUM(M27:M32) -> 0 | N26: =SUM(N27:N32) -> 5627196154 | O26: =SUM(O27:O32) -> 561894095 | P26: =SUM(P27:P32) -> 57903704 | ... Z26: =SUM(Z27:Z32) -> 44554200
A27: 1 | B27: микрокредит | C27: =+E27+G27 -> 46369937 | E27: 43378569 | F27: 0.22027682 | G27: 2991368 | H27: 0.11031489 | I27: 45631533 | J27: 738404 | K27: 0 | L27: 0 | M27: 0 | N27: 41703130 | O27: 1384987 | P27: 450150 | Q27: 761235 | R27: 2070435 | S27: =SUM(T27:X27) -> 2850576 | T27: 360309 | U27: 324400 | V27: 100825 | W27: 372802 | X27: 1692240 | Y27: 8256395 | AA27: =+'loans_av rate'!C26+'loans_av rate'!C35 -> 46369937 | AB27: =+'loans_av rate'!E26+'loans_av rate'!E35 -> 43378569 | AC27: =+'loans_av rate'!G26+'loans_av rate'!G35 -> 2991368
A28: 2 | B28: синдицированные кредит | C28: =+E28+G28 -> 0 | E28: 0 | F28: 0 | G28: 0 | H28: 0 | I28: 0 | J28: 0 | K28: 0 | L28: 0 | M28: 0 | N28: 0 | O28: 0 | P28: 0 | Q28: 0 | R28: 0 | S28: =SUM(T28:X28) -> 0 | T28: 0 | U28: 0 | V28: 0 | W28: 0 | X28: 0 | AA28: =+'loans_av rate'!C27+'loans_av rate'!C36 -> 0 | AB28: =+'loans_av rate'!E27+'loans_av rate'!E36 -> 0 | AC28: =+'loans_av rate'!G27+'loans_av rate'!G36 -> 0
A29: 3 | B29: лизинг | C29: =+E29+G29 -> 305556 | E29: 305556 | F29: 0 | G29: 0 | H29: 0 | I29: 305556 | J29: 0 | K29: 0 | L29: 0 | M29: 0 | N29: 305556 | O29: 0 | P29: 0 | Q29: 0 | R29: 0 | S29: =SUM(T29:X29) -> 2640 | T29: 2640 | U29: 0 | V29: 0 | W29: 0 | X29: 0 | AA29: =+'loans_av rate'!C28+'loans_av rate'!C37 -> 305556 | AB29: =+'loans_av rate'!E28+'loans_av rate'!E37 -> 305556 | AC29: =+'loans_av rate'!G28+'loans_av rate'!G37 -> 0
A30: 4 | B30: факторинг | C30: =+E30+G30 -> 0 | E30: 0 | F30: 0 | G30: 0 | H30: 0 | I30: 0 | J30: 0 | K30: 0 | L30: 0 | M30: 0 | N30: 0 | O30: 0 | P30: 0 | Q30: 0 | R30: 0 | S30: =SUM(T30:X30) -> 0 | T30: 0 | U30: 0 | V30: 0 | W30: 0 | X30: 0 | AA30: =+'loans_av rate'!C29+'loans_av rate'!C38 -> 0 | AB30: =+'loans_av rate'!E29+'loans_av rate'!E38 -> 0 | AC30: =+'loans_av rate'!G29+'loans_av rate'!G38 -> 0
A31: 5 | B31: межбанковский кредит | C31: =+E31+G31 -> 0 | E31: 0 | F31: 0 | G31: 0 | H31: 0 | I31: 0 | J31: 0 | K31: 0 | L31: 0 | M31: 0 | N31: 0 | O31: 0 | P31: 0 | Q31: 0 | R31: 0 | S31: =SUM(T31:X31) -> 0 | T31: 0 | U31: 0 | V31: 0 | W31: 0 | X31: 0 | AA31: =+'loans_av rate'!C30+'loans_av rate'!C39 -> 0 | AB31: =+'loans_av rate'!E30+'loans_av rate'!E39 -> 0 | AC31: =+'loans_av rate'!G30+'loans_av rate'!G39 -> 0
A32: 6 | B32: другие виды кредитования | C32: =+E32+G32 -> 6378654148 | E32: 3434750614 | F32: 0.18800577 | G32: 2943903534 | H32: 0.073024823 | I32: 6258478035 | J32: 119793352 | K32: 0 | L32: 382761 | M32: 0 | N32: 5585187468 | O32: 560509108 | P32: 57453554 | Q32: 50541899 | R32: 124962119 | S32: =SUM(T32:X32) -> 100624147 | T32: 48255230 | U32: 15522311 | V32: 3695770 | W32: 5081243 | X32: 28069593 | Y32: 14751259 | Z32: 44554200 | AA32: =+'loans_av rate'!C31+'loans_av rate'!C40 -> 6378654148 | AB32: =+'loans_av rate'!E31+'loans_av rate'!E40 -> 3434750614 | AC32: =+'loans_av rate'!G31+'loans_av rate'!G40 -> 2943903534
B33: в том числе по цели кредитования | C33: =SUM(C34:C39) -> 6425329641 | D33: =IFERROR(((C35*D35)/C33)+((C36*D36)/C33)+((C37*D37)/C33)+((C38*D38)/C33)+((C39*D39)/C33),0) -> 0 | E33: =SUM(E34:E39) -> 3478434739 | F33: =IFERROR(((E35*F35)/E33)+((E36*F36)/E33)+((E37*F37)/E33)+((E38*F38)/E33)+((E39*F39)/E33),0) -> 0.18590623 | G33: =SUM(G34:G39) -> 2946894902 | H33: =IFERROR(((G35*H35)/G33)+((G36*H36)/G33)+((G37*H37)/G33)+((G38*H38)/G33)+((G39*H39)/G33),0) -> 0.072791704 | I33: =SUM(I34:I39) -> 6304415124 | J33: =SUM(J34:J39) -> 120531756 | K33: =SUM(K34:K39) -> 0 | L33: =SUM(L34:L39) -> 382761 | M33: =SUM(M34:M39) -> 0 | N33: =SUM(N34:N39) -> 5627196154 | O33: =SUM(O34:O39) -> 561894095 | P33: =SUM(P34:P39) -> 57903704 | ... Z33: =SUM(Z34:Z39) -> 44554200
A34: 1 | B34: кредиты, выданные на формирование стартового капитала | C34: =+E34+G34 -> 0 | E34: 0 | F34: 0 | G34: 0 | H34: 0 | I34: 0 | J34: 0 | K34: 0 | L34: 0 | M34: 0 | N34: 0 | O34: 0 | P34: 0 | Q34: 0 | R34: 0 | S34: =SUM(T34:X34) -> 0 | T34: 0 | U34: 0 | V34: 0 | W34: 0 | X34: 0
A35: 2 | B35: кредиты на пополнение оборотных средств | C35: =+E35+G35 -> 1767059262 | E35: 1087722678 | F35: 0.194 | G35: 679336584 | H35: 0.078 | I35: 1767059262 | J35: 0 | K35: 0 | L35: 0 | M35: 0 | N35: 1484768825 | O35: 240868101 | P35: 939930 | Q35: 22789348 | R35: 17693058 | S35: =SUM(T35:X35) -> 24957895 | T35: 12828193 | U35: 2132286 | V35: 206375 | W35: 1983977 | X35: 7807064
A36: 3 | B36: кредиты, выданные на приобретение, модернизацию или приватизацию основных средств | C36: =+E36+G36 -> 2636724336 | E36: 1415510512 | F36: 0.181 | G36: 1221213824 | H36: 0.074 | I36: 2612235142 | J36: 24106433 | K36: 0 | L36: 382761 | M36: 0 | N36: 2327508831 | O36: 147794380 | P36: 50912310 | Q36: 24696286 | R36: 85812529 | S36: =SUM(T36:X36) -> 48163721 | T36: 20109347 | U36: 12504208 | V36: 801953 | W36: 2203923 | X36: 12544290 | Z36: 34341419
A37: 4 | B37: кредиты, выданные на покрытие затрат, связанных с импортом и экспортом продукции | C37: =+E37+G37 -> 0 | E37: 0 | F37: 0 | G37: 0 | H37: 0 | I37: 0 | J37: 0 | K37: 0 | L37: 0 | M37: 0 | N37: 0 | O37: 0 | P37: 0 | Q37: 0 | R37: 0 | S37: =SUM(T37:X37) -> 0 | T37: 0 | U37: 0 | V37: 0 | W37: 0 | X37: 0
A38: 5 | B38: кредиты, выданные по отдельным решениям правительства | C38: =+E38+G38 -> 0 | E38: 0 | F38: 0 | G38: 0 | H38: 0 | I38: 0 | J38: 0 | K38: 0 | L38: 0 | M38: 0 | N38: 0 | O38: 0 | P38: 0 | Q38: 0 | R38: 0 | S38: =SUM(T38:X38) -> 0 | T38: 0 | U38: 0 | V38: 0 | W38: 0 | X38: 0
A39: 6 | B39: другие цели кредитования | C39: =+E39+G39 -> 2021546043 | E39: 975201549 | F39: 0.184 | G39: 1046344494 | H39: 0.068 | I39: 1925120720 | J39: 96425323 | K39: 0 | L39: 0 | M39: 0 | N39: 1814918498 | O39: 173231614 | P39: 6051464 | Q39: 3817500 | R39: 23526967 | S39: =SUM(T39:X39) -> 30355747 | T39: 15680639 | U39: 1210217 | V39: 2788267 | W39: 1266145 | X39: 9410479 | Y39: 23007654 | Z39: 10212781
B41: Подпись Председателя правления:
B43: Подпись Главного Бухгалтера:

Sheet Bank Capital Calc (2)
A1: РАСЧЕТ РЕГУЛЯТИВНОГО КАПИТАЛА БАНКА | C1: Таблица-5
B3: =#REF! -> #REF! | C3: =+#REF! -> #REF!
A4: № | B4: Характеристики | C4: Итого капитала
A5: I. | B5: КАПИТАЛ УРОВНЯ 1
A6: 1 | B6: ОСНОВНОЙ КАПИТАЛ УРОВНЯ 1
A7: 1.1. | B7: Обыкновенные Акции, чистые | C7: Формула
A8: a | B8: Полностью оплаченные обыкновенные акции
A9: б | B9: Минус: Обратно Выкупленные обыкновенные акции
A10: 1.2. | B10: Добавленный капитал - Обыкновенные | C10: 0
A11: 1.3. | B11: Нераспределенная прибыль (убыток), в том числе капитальные резервы | C11: Формула
A12: а | B12: Капитальные резервы
A13: б | B13: Нераспределенная прибыль
A14: в | B14: Убыток за предыдущие периоды
A15: г | B15: Убыток за текущий год
A16: 1.4. | B16: Интерес меньшинства в консолидированных дочерних компаниях (согласно МБС)
A17: 1.5. | B17: Резерв на девальвацию
B18: Итого основного капитала уровня I до вычетов | C18: Формула
A19: 1.6. | B19: Вычеты из суммы основного капитала уровня I | C19: Формула
A20: а | B20: Нематериальные активы
A21: б | B21: Все инвестиции в капитал неконсолидированных хозяйствующих субъектов, в том числе в долговые обязательства, которые образуют капитал хозяйствующих субъектов
A22: в | B22: Инвестиции в капитал других банков
A23: I | B23: ВСЕГО СКОРРЕКТИРОВАННЫЙ ОСНОВНОЙ КАПИТАЛ УРОВНЯ I | C23: Формула
A24: 2 | B24: ДОБАВЛЕННЫЙ КАПИТАЛ УРОВНЯ 1
A25: 2.1. | B25: Некумулятивные бессрочные привилегированные акции | C25: =+C26+C27 -> 0
A26: а | B26: Полностью оплаченные привилегированные акции
A27: б | B27: Минус: Обратно Выкупленные привилегированные акции
A28: 2.2. | B28: Добавленный капитал - Привилегированные | C28: 0
A29: 2.3. | B29: Интерес меньшинства в консолидированных дочерних компаниях | C29: 0
A30: 2.4. | B30: Доля участия дочерних предприятий (выпущенные дочерними предприятиями и находящиеся во владении третьих лиц инструменты, приравненные к капиталу) | C30: 0
A31: II | B31: ВСЕГО ДОБАВЛЕННЫЙ КАПИТАЛ УРОВНЯ I | C31: =+C25+C28+C29+C30 -> 0
A32: III | B32: ВСЕГО СКОРРЕКТИРОВАННЫЙ КАПИТАЛ УРОВНЯ I | C32: Формула
B33: КАПИТАЛ УРОВНЯ II
A34: 3.1. | B34: Прибыль за текущий год
A35: 3.2. | B35: Резервы, создаваемые на стандартные кредиты (активы), в размере не более 1.25% от общей суммы активов, взвешенных с учетом риска | C35: =IF(#REF!<(C43*1.25%),#REF!,(C43*1.25%)) -> #REF!
A36: 3.3. | B36: Излишки оценочной стоимости прироста над первоначальной стоимостью
A37: 3.4. | B37: Другие инструменты капитала (не более 1/3 части капитала 1 уровня после вычетов)
A38: 3.5. | B38: Субординированный долг
A39: 3.6. | B39: Вычеты превышения Капитала Уровня II над Капиталом Уровня I | C39: Формула
B40: Итого капитала Уровня II | C40: =SUM(C34:C38) -> #REF!
A41: IV | B41: СКОРРЕКТИРОВАННЫЙ КАПИТАЛ УРОВНЯ II | C41: Формула
A42: V | B42: ВСЕГО РЕГУЛЯТИВНЫЙ КАПИТАЛ | C42: Формула
A43: VI | B43: ОБЩАЯ СУММА АКТИВОВ ВЗВЕШЕННЫХ С УЧЕТОМ РИСКА | C43: =+C44+C45+C46 -> #REF!
A44: а | B44: Сумма балансовых и забалансовых активов, взвешенных с учетом риска | C44: =+#REF! -> #REF!
A45: б | B45: Операционный риск | C45: =+#REF! -> #REF!
A46: в | B46: Рыночный риск | C46: =+#REF! -> #REF! | E46: =+#REF! -> #REF!
A47: VII | B47: КОЭФФИЦИЕНТ ОСНОВНОГО КАПИТАЛА УРОВНЯ I (I/VI) | C47: Формула
A48: VIII | B48: КОЭФФИЦИЕНТ КАПИТАЛА УРОВНЯ I (III/VI) | C48: Формула
A49: IX | B49: КОЭФФИЦИЕНТ ОБЩЕЙ СУММЫ КАПИТАЛА, ОСНОВАННОГО НА РИСКЕ (V/VI) | C49: Формула
A50: X | B50: Активы для расчета левеража | C50: Формула
A51: а | B51: Общие активы | C51: =+#REF! -> #REF!
A52: б | B52: Забалансовые инструменты | C52: =SUM(#REF!) -> #REF! | D52: =+#REF! -> #REF!
A53: в | B53: Деривативные (производные) инструменты | C53: =SUM(#REF!) -> #REF!
A54: г | B54: Минус: Строка 1.6. Итого вычетов из суммы основного капитала Уровня 1 | C54: =+C19 -> Формула
A55: XI | B55: Коэффициент левеража | C55: Формула
B57: Подпись Председателя правления:
B59: Подпись Главного Бухгалтера:

Sheet Deposits_av rate
A1: ДАННЫЕ О СРЕДНЕВЗВЕШЕННЫХ ПРОЦЕНТНЫХ СТАВКАХ ПО ПРИВЛЕЧЕННЫМ ДЕПОЗИТАМ БАНКОВ | N1: Таблица-21
B2: =+'Asset quality'!B3 -> АК "АЛОКАБАНК" | K2: =+'loans_av rate'!F3 -> 44561 | N2: тыс. сум
A3: № | B3: Сроки, погашения средств | C3: Вклады (депозиты) физических лиц | I3: Вклады (депозиты) юридических лиц
C4: общая сумма (тыс. сум) | D4: средневзвешенные процентные ставки | E4: в том числе | I4: общая сумма (тыс. сум) | J4: средневзвешенные процентные ставки | K4: в том числе
E5: в национальный валюте | G5: в иностранной валюте | K5: в национальный валюте | M5: в иностранной валюте
E6: остаток всего | F6: средневзвешенные процентные ставки | G6: остаток всего | H6: средневзвешенные процентные ставки | K6: остаток всего | L6: средневзвешенные процентные ставки | M6: остаток всего | N6: средневзвешенные процентные ставки
B7: А | C7: Б | D7: В | E7: Г | F7: Д | G7: Е | H7: Ж | I7: З | J7: И | K7: К | L7: Л | M7: М | N7: Н
A8: 1 | B8: Бессрочные | C8: =+E8+G8 -> 468677597 | D8: 0% | E8: 398173130 | F8: 0% | G8: 70504467 | H8: 0% | I8: =+K8+M8 -> 1568248781 | J8: 0% | K8: 1284665368 | L8: 0% | M8: 283583413 | N8: 0% | P8: =+'[8]Bank Liabilities Analysis'!$C$22 -> 2036926378 | Q8: =+P8-C8-I8 -> 0
A9: 2 | B9: От 1 до 7 дней | C9: =+E9+G9 -> 1693376 | D9: 0.122 | E9: 1519974 | F9: 0.184 | G9: 173402 | H9: 4% | I9: =+K9+M9 -> 309535000 | J9: 0.015 | K9: 309535000 | L9: 0.004 | M9: 0 | N9: 0 | P9: =+'[8]Bank Liabilities Analysis'!$E$22 -> 311228376 | Q9: =+P9-C9-I9 -> 0
A10: 3 | B10: От 8 до 30 дней | C10: =+E10+G10 -> 6862058 | D10: 0.172 | E10: 6277694 | F10: 0.183 | G10: 584364 | H10: 4% | I10: =+K10+M10 -> 118000000 | J10: 16% | K10: 118000000 | L10: 16% | M10: 0 | N10: 0% | P10: =+'[8]Bank Liabilities Analysis'!$G$22 -> 124862058 | Q10: =+P10-C10-I10 -> 0
A11: 4 | B11: От 31 до 90 дней | C11: =+E11+G11 -> 113067732 | D11: 0.191 | E11: 102587003 | F11: 0.197 | G11: 10480729 | H11: 4% | I11: =+K11+M11 -> 138289769 | J11: 0.148 | K11: 92945000 | L11: 0.163 | M11: 45344769 | N11: 6% | P11: =+'[8]Bank Liabilities Analysis'!$I$22 -> 251357501 | Q11: =+P11-C11-I11 -> 0
A12: 5 | B12: От 91 до 180 дней | C12: =+E12+G12 -> 92334194 | D12: 0.195 | E12: 91860187 | F12: 0.209 | G12: 474007 | H12: 4% | I12: =+K12+M12 -> 527449894 | J12: 0.145 | K12: 517696000 | L12: 0.166 | M12: 9753894 | N12: 0.041 | P12: =+'[8]Bank Liabilities Analysis'!$K$22 -> 619784088 | Q12: =+P12-C12-I12 -> 0
A13: 6 | B13: От 181 до 365 дней | C13: =+E13+G13 -> 86660671 | D13: 0.183 | E13: 72596757 | F13: 20% | G13: 14063914 | H13: 0.048 | I13: =+K13+M13 -> 913629792 | J13: 0.129 | K13: 583115843 | L13: 0.165 | M13: 330513949 | N13: 0.012 | P13: =+'[8]Bank Liabilities Analysis'!$M$22 -> 1000290463 | Q13: =+P13-C13-I13 -> 0
A14: 7 | B14: От 366 до 730 дней | C14: =+E14+G14 -> 138934073 | D14: 0.197 | E14: 136579493 | F14: 0.199 | G14: 2354580 | H14: 0.049 | I14: =+K14+M14 -> 1522606320 | J14: 0.078 | K14: 713443664 | L14: 0.179 | M14: 809162656 | N14: 2% | P14: =+'[8]Bank Liabilities Analysis'!$O$22 -> 1661540393 | Q14: =+P14-C14-I14 -> 0
A15: 8 | B15: Свыше 2 лет | C15: =+E15+G15 -> 1032318 | D15: 0.171 | E15: 1032318 | F15: 0.171 | H15: 0% | I15: =+K15+M15 -> 789087608 | J15: 0.067 | K15: 321767709 | L15: 0.089 | M15: 467319899 | N15: 0.055 | P15: =+'[8]Bank Liabilities Analysis'!$Q$22 -> 790119926 | Q15: =+P15-C15-I15 -> 0
A16: 9 | B16: Итого (сумма строк 1, 2, 3, 4, 5, 6, 7, 8 ) | C16: =SUM(C8:C15) -> 909262019 | D16: =IFERROR(((C8*D8)/C16)+((C9*D9)/C16)+((C10*D10)/C16)+((C11*D11)/C16)+((C12*D12)/C16)+((C13*D13)/C16)+((C14*D14)/C16)+((C15*D15)/C16),0) -> 0.092815283 | E16: =SUM(E8:E15) -> 810626556 | F16: =IFERROR(((E8*F8)/E16)+((E9*F9)/E16)+((E10*F10)/E16)+((E11*F11)/E16)+((E12*F12)/E16)+((E13*F13)/E16)+((E14*F14)/E16)+((E15*F15)/E16),0) -> 0.10203479 | G16: =SUM(G8:G15) -> 98635463 | H16: =IFERROR(((G8*H8)/G16)+((G9*H9)/G16)+((G10*H10)/G16)+((G11*H11)/G16)+((G12*H12)/G16)+((G13*H13)/G16)+((G14*H14)/G16)+((G15*H15)/G16),0) -> 0.012763588 | I16: =SUM(I8:I15) -> 5886847164 | J16: =IFERROR(((I8*J8)/I16)+((I9*J9)/I16)+((I10*J10)/I16)+((I11*J11)/I16)+((I12*J12)/I16)+((I13*J13)/I16)+((I14*J14)/I16)+((I15*J15)/I16),0) -> 0.069640087 | K16: =SUM(K8:K15) -> 3941168584 | L16: =IFERROR(((K8*L8)/K16)+((K9*L9)/K16)+((K10*L10)/K16)+((K11*L11)/K16)+((K12*L12)/K16)+((K13*L13)/K16)+((K14*L14)/K16)+((K15*L15)/K16),0) -> 0.094835722 | M16: =SUM(M8:M15) -> 1945678580 | N16: =IFERROR(((M8*N8)/M16)+((M9*N9)/M16)+((M10*N10)/M16)+((M11*N11)/M16)+((M12*N12)/M16)+((M13*N13)/M16)+((M14*N14)/M16)+((M15*N15)/M16),0) -> 0.025169939 | P16: =+'[8]Bank Liabilities Analysis'!$S$22 -> 6796109183 | Q16: =+P16-C16-I16 -> 0
B19: Подпись Председателя правления:
B21: Подпись Главного Бухгалтера:
B24: Физлица | C24: =+'[8]Deposits by Client'!$C$6+'[8]Deposits by Client'!$C$15 -> 909262019 | G24: =+'[8]Deposits by Client'!$D$6+'[8]Deposits by Client'!$D$15 -> 98635463
C25: =+C16 -> 909262019 | G25: =+G16 -> 98635463
C26: =+C24-C25 -> 0 | G26: =+G24-G25 -> 0
B27: Юрзлица | I27: =+'[8]Deposits by Client'!$C$22-'[8]Deposits by Client'!$C$6-'[8]Deposits by Client'!$C$15 -> 5886847164 | M27: =+'[8]Deposits by Client'!$D$22-'[8]Deposits by Client'!$D$6-'[8]Deposits by Client'!$D$15 -> 1945678580
I28: =+I16 -> 5886847164 | M28: =+M16 -> 1945678580
I29: =+I27-I28 -> 0 | M29: =+M27-M28 -> 0

Sheet Economic Normatives
A1: РАСЧЕТ ПРУДЕНЦИАЛЬНЫХ НОРМАТИВОВ | I1: Таблица-22
B2: =+'Asset quality'!B3 -> АК "АЛОКАБАНК" | I2: =+'Asset quality'!P3 -> 44561
A4: № | B4: Наименование экономического норматива | F4: Формула | I4: Фактическое значение | J4: Нормативное значение | K4: Отклонение
B5: A | F5: Б | I5: В | J5: Г | K5: Д
A6: 1 | B6: Показатели достаточности капитала
A7: 1.1 | B7: Коэффициент достаточности капитала | F7: Скорректированная общая капитала, основанного на риске | I7: =+'[9]Bank Capital Calc'!$C$51 -> 0.13209546 | J7: Мин | K7: =IF(I7="",0-J8,(IF((I7-J8)>0,"",I7-J8)))
F8: Активы с учетом риска | J8: 0.13
A9: 1.2 | B9: Коэффициент достаточности Капитала Уровня 1 | F9: Капитал Уровня I | I9: =+'[9]Bank Capital Calc'!$C$50 -> 0.11425105 | J9: Мин | K9: =IF(I9="",0-J10,(IF((I9-J10)>0,"",I9-J10)))
F10: Активы с учетом риска | J10: 0.1
A11: 1.3 | B11: Коэффициент достаточности основного Капитала Уровня 1 | F11: Основной капитал Уровня I | I11: =+'[9]Bank Capital Calc'!$C$49 -> 0.11406463 | J11: Мин | K11: =IF(I11="",0-J12,(IF((I11-J12)>0,"",I11-J12)))
F12: Активы с учетом риска | J12: 0.08
A13: 1.4 | B13: Левераж | F13: Капитал Уровня I | I13: =+'[9]Bank Capital Calc'!$C$57 -> 0.093587296 | J13: Мин | K13: =IF(I13="",0-J14,(IF((I13-J14)>0,"",I13-J14)))
F14: Активы + забалансовые инструменты+ деривативные (производные) инструменты - вычеты из суммы основного капитала уровня I | J14: 0.06
A15: 2 | B15: Показатели ликвидности
A16: 2.1 | B16: Коэффициент покрытия ликвидности | E16: Всего | F16: Высоколиквидные активы | I16: =IFERROR((+'[8]Liquidity Analysis'!$C$23),0) -> 1.108638 | J16: Мин | K16: =IF(I16="",0-$J$18,(IF((I16-$J$18)>0,"",I16-$J$18)))
E17: в национальной валюте | I17: =IFERROR((+'[8]Liquidity Analysis'!$D$23),0) -> 1.1563961 | K17: =IF(I17="",0-$J$18,(IF((I17-$J$18)>0,"",I17-$J$18)))
E18: в иностранной валюте | F18: Чистый отток в последующие 30 дней | I18: =IFERROR((+'[8]Liquidity Analysis'!$E$23),0) -> 1.0606036 | J18: 1 | K18: =IF(I18="",0-$J$18,(IF((I18-$J$18)>0,"",I18-$J$18)))
A19: 2.2 | B19: Норма чистого стабильного финансирования | E19: Всего | F19: Доступная сумма стабильного финансирования | I19: =IFERROR((+'[8]Liquidity Analysis'!$C$28),0) -> 1.0801928 | J19: Мин | K19: =IF(I19="",0-$J$21,(IF((I19-$J$21)>0,"",I19-$J$21)))
E20: в национальной валюте | I20: =IFERROR((+'[8]Liquidity Analysis'!$D$28),0) -> 1.0178285 | K20: =IF(I20="",0-$J$21,(IF((I20-$J$21)>0,"",I20-$J$21)))
E21: в иностранной валюте | F21: Необходимая сумма стабильного финансирования | I21: =IFERROR((+'[8]Liquidity Analysis'!$E$28),0) -> 1.181868 | J21: 1 | K21: =IF(I21="",0-$J$21,(IF((I21-$J$21)>0,"",I21-$J$21)))
A22: 3 | B22: Нормативы по операциям с заемщиками
A23: 3.1 | B23: Максимальный размер риска на одного заемщика или группу взаимосвязанных заемщиков, обеспеченные | F23: Максимальный размер риска на одного заемщика или группу взаимосвязанных заемщиков,обеспеченные | I23: =IFERROR((+' Largest risk'!Z65/'[9]Bank Capital Calc'!$C$34),0) -> 0.24533523 | J23: Макс | K23: =IF(I23="","",IF(I23<0,"ОТР",IF((I23-J24)<0,"",I23-J24)))
F24: Капитал Уровня I | J24: 0.25
A25: 3.2 | B25: Максимальный размер риска на один банк или группу взаимосвязанных банков-заемщиков по межбанковским операциям | F25: Максимальный размер риска на один банк или группу взаимосвязанных банков-заемщиков по межбанковским операциям | I25: =IFERROR((' Largest risk'!H16/+'[9]Bank Capital Calc'!$C$34),0) -> 0.22172511 | J25: Макс | K25: =IF(I25<0,"ОТР",IF((I25-J26)<0,"",I25-J26)) | M25: Заполняется в ручную
F26: Капитал Уровня I | J26: 0.25
A27: 3.3 | B27: Максимальный размер необеспеченного актива на одного заемщика или группу взаимосвязанных заемщиков (не включая риски по межбанковским операциям) | F27: Максимальный размер необеспеченного актива на одного заемщика или группу взаимосвязанных заемщиков (не включая риски по межбанковским операциям) | I27: =IFERROR((0/'[9]Bank Capital Calc'!$C$34),0) -> 0 | J27: Макс | K27: =IF(I27<0,"ОТР",IF((I27-J28)<0,"",I27-J28)) | M27: Заполняется в ручную
F28: Капитал Уровня I | J28: 0.05
A29: 3.4 | B29: Совокупная сумма всех крупных рисков | F29: Совокупная сумма всех крупных рисков | I29: =IFERROR((+' Largest risk'!Z64/'[9]Bank Capital Calc'!$C$34),0) -> 1.2327624 | J29: Макс | K29: =IF(I29="","",IF(I29<0,"ОТР",IF((I29-J30)<0,"",I29-J30)))
F30: Капитал Уровня I | J30: 5
A31: 4 | B31: Нормативы по операциям с ценными бумагами
A32: 4.1 | B32: Максимальный размер инвестиций в ценные бумаги одного эмитента | F32: Инвестиции в негосударственные ценные бумаги одного эмитента | I32: =IFERROR((50000000/+'[9]Bank Capital Calc'!$C$34),0) -> 0.036848093 | J32: Макс | K32: =IF(I32<0,"ОТР",IF((I32-J33)<0,"",I32-J33)) | M32: Заполняется в ручную
F33: Капитал Уровня I | J33: 0.15
A34: 4.2 | B34: Максимальный общий размер инвестиций в ценные бумаги для купли- продажи | F34: Общий размер инвестиций в ценные бумаги для купли- продажи | I34: =IFERROR((+('[8]Investment Securities'!$B$22+'[8]Investment Securities'!$B$23+'[8]Investment Securities'!$B$24+'[8]Investment Securities'!$B$25-'[8]Investment Securities'!$B$28)/'[9]Bank Capital Calc'!$C$34),0) -> 0 | J34: Макс | K34: =IF(I34="","",IF(I34<0,"ОТР",IF((I34-J35)<0,"",I34-J35)))
F35: Капитал Уровня I | J35: 0.25
A36: 4.3 | B36: Максимальный общий размер инвестиций в уставной капитал и другие ценные бумаги всех эмитентов | F36: Общий размер инвестиций в уставной капитал и другие ценные бумаги всех эмитентов | I36: =IFERROR((+(+'[8]Investment Securities'!$B$15-'[8]Investment Securities'!$B$6-'[8]Investment Securities'!$B$7+'[8]Investment Securities'!$B$22+'[8]Investment Securities'!$B$23+'[8]Investment Securities'!$B$24+'[8]Investment Securities'!$B$25-'[8]Investment Securities'!$B$28)/'[9]Bank Capital Calc'!$C$34),0) -> 0.072472141 | J36: Макс | K36: =IF(I36="","",IF(I36<0,"ОТР",IF((I36-J37)<0,"",I36-J37)))
F37: Капитал Уровня I | J37: 0.5
A38: 5 | B38: Нормативы по операциям со связанными с банком лицами
A39: 5.1 | B39: Максимальный размер риска на одного связанного с банком лица, обеспеченные | F39: Максимальный размер риска на одного связанного с банком лица, обеспеченные | I39: =IFERROR(((+'Transactions of related parties'!Z65-'[9]Bank Capital Calc'!$C$24)/'[9]Bank Capital Calc'!$C$34),0) -> 0.12016171 | J39: Макс | K39: =IF(I39="","",IF(I39<0,"ОТР",IF((I39-J40)<0,"",I39-J40)))
F40: Капитал Уровня I | J40: 0.25
A41: 5.2 | B41: Совокупная сумма рисков по всем связанным с банком лицам | F41: Совокупная сумма рисков по всем связанным с банком лицам | I41: =IFERROR(((+'Transactions of related parties'!Z64-'[9]Bank Capital Calc'!$C$24)/'[9]Bank Capital Calc'!$C$34),0) -> 0.30486822 | J41: Макс | K41: =IF(I41="","",IF(I41<0,"ОТР",IF((I41-J42)<0,"",I41-J42)))
F42: Капитал Уровня I | J42: 0.5
A43: 6 | B43: Нормативный показатель по инвестициям банка в недвижимость
A44: 6.1 | B44: Совокупная сумма всех инвестиций банка в недвижимость | F44: Сумма всех инвестиций банка в недвижимость | I44: =IFERROR(((1213800044)/+'[9]Bank Capital Calc'!$C$34),0) -> 0.89452434 | J44: Макс | K44: =IF(I44="","",IF(I44<0,"ОТР",IF((I44-J45)<0,"",I44-J45))) | M44: Заполняется в ручную
F45: Капитал Уровня I | J45: 1
D47: Подпись Председателя правления:
D49: Подпись Главного Бухгалтера:

Sheet Miscellaneous
B1: РАЗНАЯ ИНФОРМАЦИЯ | C1: Таблица-23
B2: =+'Asset quality'!B3 -> АК "АЛОКАБАНК" | C2: тыс. сум
A3: 1. | B3: Численность работников банка, включая административный, филиалы, и представительства банка.
A4: а | B4: Численность работников банка по штатному расписанию | C4: 1467
A5: б | B5: Фактическая численность работников банка | C5: 1380
A6: 2. | B6: Общее количество отделений банка, включая административный, филиалы, и представительства банка.
B7: из них,
A8: а | B8: Количество филиалов | C8: 0
A9: б | B9: Количество мини банков | C9: 0
A10: в | B10: Количество розничных касс вне банка (филиалы) | C10: 105
A11: г | B11: Количество центров банковских услуг | C11: 87
A12: 3. | B12: Клиенская база банка | C12: =C14+C15+C16 -> 1298774
B13: из них,
A14: а | B14: Физические лица | C14: 1264097
A15: б | B15: Индивидуальные предприниматели | C15: 9207
A16: в | B16: Юридические лица | C16: =+C18+C19+C20+C21+C22 -> 25470 | E16: в этой строке указываются количество всех юридических лиц
B17: в том числе имеющие основной счет в банке | E17: в этой строке указываются количество юридических лиц, которые имеют основной счет в банке
A18: - | B18: Государственные предприятия | C18: 673
A19: - | B19: Частные товарищества и корпорации | C19: 23 426
A20: - | B20: Фермерское хозяйство | C20: 791
A21: - | B21: Правительство | C21: 8
A22: - | B22: Прочие | C22: =2332-1760 -> 572
A23: 4. | B23: Рейтинг банка
A24: а | B24: Названия рейтинговой компании | C24: Moody's
A25: б | B25: Оценка рейтинга банка | C25: B1/NP, B1/NP, Stable
B28: Подпись Председателя правления:
B30: Подпись Главного Бухгалтера:

Sheet ПФУ
A1: Показатели финансовой устойчивости
A2: =+'Asset quality'!B3 -> АК "АЛОКАБАНК" | B2: тыс. сум | C2: Месяц
A3: Основные показатели | B3: =+'Asset quality'!P3 -> 44561 | K3: Месяц | L3: Актив | M3: Капитал | O3: Всего активы (средний за период) | P3: Совокупный капитал (средний за период)
A4: Регулятивный капитал к активам взвешанных с учетом риска | B4: =IFERROR((B5/B6),0) -> 0.13209546 | J4: 1 января | K4: 1 | L4: 8108166331 | M4: 1568529812
A5: Всего Регулятивный капитал | B5: =+'[9]Bank Capital Calc'!$C$44 -> 1568854517 | J5: 1 февраль | K5: 2 | L5: 8197503266 | M5: 1589698112 | N5: 1 | O5: =+(L4+L5)/2 -> 8.1528348e+09 | P5: =+(M4+M5)/2 -> 1579113962
A6: Активы взвешанные с учетом риска | B6: =+'[9]Bank Capital Calc'!$C$45 -> 1.1876673e+10 | J6: 1 март | K6: 3 | L6: 8252689648 | M6: 1606410581 | N6: 2 | O6: =+(L4+L5+L6)/3 -> 8.1861197e+09 | P6: =+(M4+M5+M6)/3 -> 1588212835
A7: Регулятивный капитал 1 - уровня к Активам взвешанных с учетом риска | B7: =IFERROR((B8/B9),0) -> 0.11425105 | J7: 1 апрель | K7: 4 | L7: 8511503564 | M7: 1619990176 | N7: 3 | O7: =+(L4+L7)/2 -> 8.3098349e+09 | P7: =+(M4+M7)/2 -> 1594259994
A8: Регулятивный капитал 1- уровня | B8: =+'[9]Bank Capital Calc'!$C$34 -> 1356922323 | J8: 1 май | K8: 5 | L8: 8760607774 | M8: 1580998108 | N8: 4 | O8: =+(+L4+L5+L6+L7+L8)/5 -> 8.3660941e+09 | P8: =+(+M4+M5+M6+M7+M8)/5 -> 1.5931254e+09
A9: Активы взвешанные с учетом риска | B9: =+'[9]Bank Capital Calc'!$C$45 -> 1.1876673e+10 | J9: 1 июнь | K9: 6 | L9: 9026704527 | M9: 1587998848 | N9: 5 | O9: =+(+L4+L5+L6+L7+L8+L9)/6 -> 8.4761959e+09 | P9: =+(+M4+M5+M6+M7+M8+M9)/6 -> 1.5922709e+09
A10: Недействующие ссуды за вычетом резервов/общий объем капитала | B10: =IFERROR((B11/B12),0) -> 0.13987473 | J10: 1 июль | K10: 7 | L10: 9047039799 | M10: 1608201435 | N10: 6 | O10: =+(L4+L7+L10)/3 -> 8555569898 | P10: =+(M4+M7+M10)/3 -> 1598907141
A11: Недействующие ссуды за вычетом резервов | B11: =+('Asset Classification'!M50-'Asset Classification'!O50+'Asset Classification'!Q50-'Asset Classification'!S50+'Asset Classification'!U50-'Asset Classification'!W50) -> 234081194 | J11: 1 август | K11: 8 | L11: 9260791292 | M11: 1593050322 | N11: 7 | O11: =(L4+L5+L6+L7+L8+L9+L10+L11)/8 -> 8.6456258e+09 | P11: =(M4+M5+M6+M7+M8+M9+M10+M11)/8 -> 1.5943597e+09
A12: Совокупный капитал на конец периода | B12: =+B35 -> 1673505943 | J12: 1 сентябрь | K12: 9 | L12: 9532266721 | M12: 1629349225 | N12: 8 | O12: =(L4+L5+L6+L7+L8+L9+L10+L11+L12)/9 -> 8.7441414e+09 | P12: =(M4+M5+M6+M7+M8+M9+M10+M11+M12)/9 -> 1.5982474e+09
A13: Недействующие ссуды/общая сумма ссуд | B13: =IFERROR((B14/B15),0) -> 0.040536531 | J13: 1 октябрь | K13: 10 | L13: 10041392673 | M13: 1666992405 | N13: 9 | O13: =+(L4+L7+L10+L13)/4 -> 8.9270256e+09 | P13: =+(M4+M7+M10+M13)/4 -> 1615928457
A14: Недействующие ссуды | B14: =+('Asset Classification'!M50+'Asset Classification'!Q50+'Asset Classification'!U50) -> 314332984 | J14: 1 ноябрь | K14: 11 | L14: 10985677372 | M14: 1687121784 | N14: 10 | O14: =(+L4+L5+L6+L7+L8+L9+L10+L11+L12+L13+L14)/11 -> 9.0658494e+09 | P14: =(+M4+M5+M6+M7+M8+M9+M10+M11+M12+M13+M14)/11 -> 1.6125764e+09
A15: Общая сумма ссуд | B15: =+'Loans Receivable'!C92 -> 7754313870 | J15: 1 декабрь | K15: 12 | L15: 11344587789 | M15: 1704882568 | N15: 11 | O15: =(+L4+L5+L6+L7+L8+L9+L10+L11+L12+L13+L14+L15)/12 -> 9.2557442e+09 | P15: =(+M4+M5+M6+M7+M8+M9+M10+M11+M12+M13+M14+M15)/12 -> 1.6202686e+09
A16: Рентабельность активов | B16: =IFERROR((B17/B18),0) -> 0.014481959 | J16: 1 январь | K16: 13 | L16: 12638456624 | M16: 1673505943 | N16: 12 | O16: =+(L4+L7+L10+L13+L16)/5 -> 9.6693118e+09 | P16: =+(M4+M7+M10+M13+M16)/5 -> 1.627444e+09
A17: Чистая прибыль до уплаты налогов | B17: =(+'Income '!C72)/MONTH(B3)*12 -> 140030579
A18: Всего активы (средний за период) | B18: =VLOOKUP(MONTH(B3),$N$4:$P$16,2,0) -> 9.6693118e+09
A19: Рентабельность капитала | B19: =IFERROR((B20/B21),0) -> 0.066105189
A20: Чистая прибыль | B20: =(+'Income '!C79)/MONTH(B3)*12 -> 107582490
A21: Совокупный капитал (средний за период) | B21: =VLOOKUP(MONTH(B3),$N$4:$P$16,3,0) -> 1.627444e+09
A22: Процентная маржа/валовой доход | B22: =IFERROR((B23/B24),0) -> 0.48876654
A23: Процентная маржа | B23: =+'Income '!C30 -> 408381482
A24: Валовой доход | B24: =+B27 -> 835534854
A25: Непроцентные расходы/валовой доход | B25: =IFERROR((B26/B27),0) -> 0.68772651
A26: Непроцентные расходы | B26: =+'Income '!C54+'Income '!C70 -> 574619468
A27: Валовой доход | B27: =+'Income '!C30+'Income '!C46 -> 835534854
A28: Ликвидные активы/всего активы | B28: =IFERROR((B29/B30),0) -> 0.19710139
A29: Ликвидные активы | B29: =+B32 -> 2491057407
A30: Всего активы | B30: =+B36 -> 12638456623
A31: Ликвидные активы/краткосрочные обязательства | B31: =IFERROR((B29/B33),0) -> 0.36151331
A32: Ликвидные активы | B32: =+B54 -> 2491057407
A33: Краткосрочные обязательства | B33: =+('[8]Bank Liabilities Analysis'!$C$39+'[8]Bank Liabilities Analysis'!$E$39+'[8]Bank Liabilities Analysis'!$G$39+'[8]Bank Liabilities Analysis'!$I$39+'[8]Bank Liabilities Analysis'!$K$39+'[8]Bank Liabilities Analysis'!$M$39) -> 6890638208
A34: Совокупный капитал на конец периода/Всего активы | B34: =IFERROR((B35/B36),0) -> 0.13241379
A35: Совокупный капитал на конец периода | B35: =+[8]Balance!$C$77 -> 1673505943
A36: Всего активы | B36: =+[8]Balance!$C$45 -> 12638456623
A37: Чистая открытая валютная позиция /Совокупный капитал на конец периода | B37: =IFERROR((B38/B39),0) -> 0.069276075
A38: Чистая открытая валютная позиция | B38: =+'[9]Calculation of Risk'!$C$26 -> 115933923
A39: Совокупный капитал на конец периода | B39: =+B35 -> 1673505943
A42: Подпись Председателя правления:
A44: Подпись Главного Бухгалтера:
A46: Ликвидные активы | B46: Сумма | C46: Нацвалюта | D46: Инвалюта
A47: Наличные денежные средства и Драгоценные металлы | B47: =+'[8]Liquidity Analysis'!C50 -> 275814140 | C47: =+'[8]Liquidity Analysis'!D50 -> 94523351 | D47: =+'[8]Liquidity Analysis'!E50 -> 181290789 | E47: 1.
A48: К получению из ЦБРУ | B48: =+'[8]Liquidity Analysis'!C51 -> 1238811513 | C48: =+'[8]Liquidity Analysis'!D51 -> 988225440 | D48: =+'[8]Liquidity Analysis'!E51 -> 250586073 | E48: 2.
A49: К получению из других банков | B49: =+'[8]Liquidity Analysis'!C52 -> 558326754 | C49: =+'[8]Liquidity Analysis'!D52 -> 446829 | D49: =+'[8]Liquidity Analysis'!E52 -> 557879925 | E49: 3.
A50: К получению из других банков - Депозиты (чистые) | B50: =+'[8]Liquidity Analysis'!C53 -> 0 | C50: =+'[8]Liquidity Analysis'!D53 -> 0 | D50: =+'[8]Liquidity Analysis'!E53 -> 0 | E50: 3.1.
A51: Ценные бумаги, выпущенные Правительством Республики Узбекистан и ЦБРУ (векселя, облигации и другие долговые ценные бумаги) | B51: =+'[8]Liquidity Analysis'!C54 -> 418105000 | C51: =+'[8]Liquidity Analysis'!D54 -> 418105000 | D51: =+'[8]Liquidity Analysis'!E54 -> 0 | E51: 4.
A52: Ценные бумаги, выпущенные странами с низким уровня риска | B52: =+'[8]Liquidity Analysis'!C55 -> 0 | C52: =+'[8]Liquidity Analysis'!D55 -> 0 | D52: =+'[8]Liquidity Analysis'!E55 -> 0 | E52: 5.
A53: Другие легко реализуемые ценные бумаги | B53: =+'[8]Liquidity Analysis'!C56 -> 0 | C53: =+'[8]Liquidity Analysis'!D56 -> 0 | D53: =+'[8]Liquidity Analysis'!E56 -> 0 | E53: 6.
A54: Итого ликвидных активов | B54: =+'[8]Liquidity Analysis'!C57 -> 2491057407 | C54: =+'[8]Liquidity Analysis'!D57 -> 1501300620 | D54: =+'[8]Liquidity Analysis'!E57 -> 989756787 | E54: 7.
