Workbook
Name jop: #REF!
Name kol: #REF!
Name RISKTOTASS: SUM('[6]Calculation of Risk Weighted As'!$C$38:$F$38)
Name RISKTOTASS: SUM('[7]Calculation of Risk Weighted As'!$C$41:$G$41)
Name TwentyLargestData: #REF!
Name Е: #REF!

Sheet Asset quality
A1: ИНФОРМАЦИЯ О КАЧЕСТВЕ АКТИВОВ, ОЦЕНИВАЕМЫХ В ЦЕЛЯХ СОЗДАНИЯ РЕЗЕРВА НА ВОЗМОЖНЫЕ ПОТЕРИ | R1: Таблица-2 | U1: №4
B3: "Ўзсаноатқурилишбанк" АТБ | P3: 44560 | S3: тыс. сум
A4: № | B4: Состав активов* | C4: Остаток | D4: Категория качества | I4: Просроченная задолженность (брутто) | N4: Резерв на возможные потери
I5: итого | J5: до 30 дней | K5: от 31 до 90 дней | L5: от 91 до 180 дней | M5: свыше 180 дней | N5: фактически сформированный
N6: итого | O6: по категориям качества
D7: I | E7: II | F7: III | G7: IV | H7: V | O7: I | P7: II | Q7: III | R7: IV | S7: V
A8: А | B8: Б | C8: В | D8: Г | E8: Д | F8: Е | G8: Ж | H8: З | I8: И | J8: К | K8: Л | L8: М | M8: Н | N8: О | O8: П | P8: Р | Q8: С | R8: Т | S8: У
B9: ВСЕГО АКТИВОВ | C9: =SUM(C10:C60) -> 56511320290 | D9: =SUM(D10:D60) -> 53317941289 | E9: =SUM(E10:E60) -> 2660324543 | F9: =SUM(F10:F60) -> 904022544 | G9: =SUM(G10:G60) -> 209365860 | H9: =SUM(H10:H60) -> 610267679 | I9: =SUM(I10:I60) -> 444927648 | J9: =SUM(J10:J60) -> 82167000 | ... S9: =SUM(S10:S60) -> 608828633
A10: 1 | B10: Кассовая наличность и другие платежные документы | C10: =SUM(D10:H10)-N10+O10 -> 882034858 | D10: 882034858 | I10: =SUM(J10:M10) -> 0 | N10: =SUM(O10:S10) -> 0 | T10: 10100
A11: 2 | B11: К получению из ЦБРУ | C11: =SUM(D11:H11)-N11+O11 -> 3258433287 | D11: 3258433287 | I11: =SUM(J11:M11) -> 0 | N11: =SUM(O11:S11) -> 0 | T11: 10300
A12: 3 | B12: К получению из других банков | C12: =SUM(D12:H12)-N12+O12 -> 5865748703 | D12: 5865748703 | H12: 32812980 | I12: =SUM(J12:M12) -> 0 | N12: =SUM(O12:S12) -> 32812980 | S12: 32812980 | T12: 10500
A13: 4 | B13: Ценные бумаги для купли и продажи | C13: =SUM(D13:H13)-N13+O13 -> 1057702047 | D13: 1057702047 | I13: =SUM(J13:M13) -> 0 | N13: =SUM(O13:S13) -> 0 | T13: 10700
A14: 5 | B14: Инвестиции в ценные бумаги, имеющиеся в наличии для продажи | C14: =SUM(D14:H14)-N14+O14 -> 0 | I14: =SUM(J14:M14) -> 0 | N14: =SUM(O14:S14) -> 0 | T14: 10800
A15: 6 | B15: Драгоценные металлы, камни и монеты для купли и продажи | C15: =SUM(D15:H15)-N15+O15 -> 875 | D15: 875 | I15: =SUM(J15:M15) -> 0 | N15: =SUM(O15:S15) -> 0 | T15: 10900
A16: 7 | B16: Купленные дебиторские задолженности - Факторинг | C16: =SUM(D16:H16)-N16+O16 -> 179149000 | D16: 177213000 | E16: 0 | F16: 0 | G16: 4136000 | H16: 0 | I16: =SUM(J16:M16) -> 0 | J16: 0 | K16: 0 | L16: 0 | M16: 0 | N16: =SUM(O16:S16) -> 3319400 | O16: 1119400 | P16: 0 | Q16: 0 | R16: 2200000 | S16: 0 | T16: 11100
A17: 8 | B17: Купленные векселя | C17: =SUM(D17:H17)-N17+O17 -> 0 | D17: 0 | E17: 0 | F17: 0 | G17: 0 | H17: 0 | I17: =SUM(J17:M17) -> 0 | J17: 0 | K17: 0 | L17: 0 | M17: 0 | N17: =SUM(O17:S17) -> 0 | T17: 11300
A18: 9 | B18: Обязательства клиентов по траттам под аккредитив и/или трастовые документы | C18: =SUM(D18:H18)-N18+O18 -> 0 | D18: 0 | E18: 0 | F18: 0 | G18: 0 | H18: 0 | I18: =SUM(J18:M18) -> 0 | J18: 0 | K18: 0 | L18: 0 | M18: 0 | N18: =SUM(O18:S18) -> 0 | T18: 11500
A19: 10 | B19: Обязательства лиентов по непогашенным акцептам банка | C19: =SUM(D19:H19)-N19+O19 -> 0 | D19: 0 | E19: 0 | F19: 0 | G19: 0 | H19: 0 | I19: =SUM(J19:M19) -> 0 | J19: 0 | K19: 0 | L19: 0 | M19: 0 | N19: =SUM(O19:S19) -> 0 | T19: 11700
A20: 11 | B20: Купленные по сделкам РЕПО ценные бумаги | C20: =SUM(D20:H20)-N20+O20 -> 0 | D20: 0 | E20: 0 | F20: 0 | G20: 0 | H20: 0 | I20: =SUM(J20:M20) -> 0 | J20: 0 | K20: 0 | L20: 0 | M20: 0 | N20: =SUM(O20:S20) -> 0 | T20: 11800
A21: 12 | B21: Краткосрочные кредиты, предоставленные ЦБРУ | C21: =SUM(D21:H21)-N21+O21 -> 0 | D21: 0 | E21: 0 | F21: 0 | G21: 0 | H21: 0 | I21: =SUM(J21:M21) -> 0 | J21: 0 | K21: 0 | L21: 0 | M21: 0 | N21: =SUM(O21:S21) -> 0 | T21: 11900
A22: 13 | B22: Краткосрочные кредиты, предоставленные другим банкам | C22: =SUM(D22:H22)-N22+O22 -> 0 | D22: 0 | E22: 0 | F22: 0 | G22: 0 | H22: 0 | I22: =SUM(J22:M22) -> 0 | J22: 0 | K22: 0 | L22: 0 | M22: 0 | N22: =SUM(O22:S22) -> 0 | T22: 12100
A23: 14 | B23: Краткосрочные кредиты, предоставленные правительству | C23: =SUM(D23:H23)-N23+O23 -> 0 | D23: 0 | E23: 0 | F23: 0 | G23: 0 | H23: 0 | I23: =SUM(J23:M23) -> 0 | J23: 0 | K23: 0 | L23: 0 | M23: 0 | N23: =SUM(O23:S23) -> 0 | T23: 12300
A24: 15 | B24: Краткосрочные кредиты, предоставленные бюджетным организациям | C24: =SUM(D24:H24)-N24+O24 -> 0 | D24: 0 | E24: 0 | F24: 0 | G24: 0 | H24: 0 | I24: =SUM(J24:M24) -> 0 | J24: 0 | K24: 0 | L24: 0 | M24: 0 | N24: =SUM(O24:S24) -> 0 | T24: 12400
A25: 16 | B25: Краткосрочные кредиты, предоставленные физическим лицам | C25: =SUM(D25:H25)-N25+O25 -> 270725377 | D25: 260422937 | E25: 6723460 | F25: 3689520 | G25: 2878431 | H25: 12801703 | I25: =SUM(J25:M25) -> 19975764 | J25: 1125486 | K25: 3230490 | L25: 4195995 | M25: 11423793 | N25: =SUM(O25:S25) -> 19906610 | O25: 4115936 | P25: 675257 | Q25: 849815 | R25: 1440508 | S25: 12825094 | T25: 12500
A26: 17 | B26: Краткосрочные кредиты, предоставленные индивидуальным предпринимателям | C26: =SUM(D26:H26)-N26+O26 -> 5178513 | D26: 5178513 | E26: 0 | F26: 0 | G26: 0 | H26: 0 | I26: =SUM(J26:M26) -> 72191 | J26: 72191 | K26: 0 | L26: 0 | M26: 0 | N26: =SUM(O26:S26) -> 51548 | O26: 51548 | P26: 0 | Q26: 0 | R26: 0 | S26: 0 | T26: 12600
A27: 18 | B27: Краткосрочные кредиты, предоставленные государственным предприятиям, организациям и учреждениям | C27: =SUM(D27:H27)-N27+O27 -> 1172822365 | D27: 1157780426 | E27: 0 | F27: 20055918 | G27: 0 | H27: 0 | I27: =SUM(J27:M27) -> 2830414 | J27: 638933 | K27: 2191481 | L27: 0 | M27: 0 | N27: =SUM(O27:S27) -> 15701024 | O27: 10687045 | P27: 0 | Q27: 5013979 | R27: 0 | S27: 0 | T27: 12700
A28: 19 | B28: Краткосрочные кредиты, предоставленные при содействии Государственного фонда поддержки развития предпринимательской деятельности | C28: =SUM(D28:H28)-N28+O28 -> 385566106 | D28: 352934374 | E28: 23456657 | F28: 10007302 | G28: 8030530 | H28: 5624921 | I28: =SUM(J28:M28) -> 19766502 | J28: 595181 | K28: 8588158 | L28: 4958242 | M28: 5624921 | N28: =SUM(O28:S28) -> 18098290 | O28: 3610612 | P28: 2345666 | Q28: 2501826 | R28: 4015265 | S28: 5624921 | T28: 12800
A29: 20 | B29: Краткосрочные кредиты, предоставленные предприятиям с участием иностранного капитала | C29: =SUM(D29:H29)-N29+O29 -> 1255721060 | D29: 1248300235 | E29: 8245361 | F29: 0 | G29: 0 | H29: 0 | I29: =SUM(J29:M29) -> 0 | J29: 0 | K29: 0 | L29: 0 | M29: 0 | N29: =SUM(O29:S29) -> 9115961 | O29: 8291425 | P29: 824536 | Q29: 0 | R29: 0 | S29: 0 | T29: 12900
A30: 21 | B30: Краткосрочные кредиты, предоставленные негосударственным некоммерческим организациям | C30: =SUM(D30:H30)-N30+O30 -> 4955032 | D30: 4955032 | E30: 0 | F30: 0 | G30: 0 | H30: 17751 | I30: =SUM(J30:M30) -> 17751 | J30: 0 | K30: 0 | L30: 0 | M30: 17751 | N30: =SUM(O30:S30) -> 54898 | O30: 37147 | P30: 0 | Q30: 0 | R30: 0 | S30: 17751 | T30: 13000
A31: 22 | B31: Краткосрочные кредиты, предоставленные частным предприятиям, хозяйственным товариществам и обществам | C31: =SUM(D31:H31)-N31+O31 -> 2222258963 | D31: 2145337513 | E31: 31622585 | F31: 58080297 | G31: 10254530 | H31: 22399936 | I31: =SUM(J31:M31) -> 67443751 | J31: 8950479 | K31: 32910447 | L31: 9112217 | M31: 16470608 | N31: =SUM(O31:S31) -> 64393203 | O31: 18957305 | P31: 3388623 | Q31: 14520074 | R31: 5127265 | S31: 22399936 | T31: 13100
A32: 23 | B32: Краткосрочные кредиты, предоставленные небанковским финансовым институтам | C32: =SUM(D32:H32)-N32+O32 -> 0 | D32: 0 | E32: 0 | F32: 0 | G32: 0 | H32: 0 | I32: =SUM(J32:M32) -> 0 | J32: 0 | K32: 0 | L32: 0 | M32: 0 | N32: =SUM(O32:S32) -> 7332 | O32: 7332 | P32: 0 | Q32: 0 | R32: 0 | S32: 0 | T32: 13200
A33: 24 | B33: Краткосрочные кредиты, предоставленные для производства сельскохозяйственной продукции, закупаемой для государственных нужд | C33: =SUM(D33:H33)-N33+O33 -> 0 | D33: 0 | E33: 0 | F33: 0 | G33: 0 | H33: 0 | I33: =SUM(J33:M33) -> 0 | J33: 0 | K33: 0 | L33: 0 | M33: 0 | N33: =SUM(O33:S33) -> 0 | O33: 0 | P33: 0 | Q33: 0 | R33: 0 | S33: 0 | T33: 13300
A34: 25 | B34: Долгосрочные кредиты, предоставленные для производства сельскохозяйственной продукции, закупаемой для государственных нужд | C34: =SUM(D34:H34)-N34+O34 -> 0 | D34: 0 | E34: 0 | F34: 0 | G34: 0 | H34: 0 | I34: =SUM(J34:M34) -> 0 | J34: 0 | K34: 0 | L34: 0 | M34: 0 | N34: =SUM(O34:S34) -> 0 | O34: 0 | P34: 0 | Q34: 0 | R34: 0 | S34: 0 | T34: 14300
A35: 26 | B35: Долгосрочные кредиты, предоставленные при содействии Государственного фонда поддержки развития предпринимательской деятельности | C35: =SUM(D35:H35)-N35+O35 -> 3689745918 | D35: 2765184094 | E35: 678063715 | F35: 342934995 | G35: 90797045 | H35: 90790490 | I35: =SUM(J35:M35) -> 106023347 | J35: 19007471 | K35: 51203507 | L35: 15199133 | M35: 20613236 | N35: =SUM(O35:S35) -> 311577393 | O35: 33552972 | P35: 65759234 | Q35: 80343503 | R35: 41131194 | S35: 90790490 | T35: 14400
A36: 27 | B36: Долгосрочные кредиты, предоставленные другим банкам | C36: =SUM(D36:H36)-N36+O36 -> 0 | D36: 0 | E36: 0 | F36: 0 | G36: 0 | H36: 0 | I36: =SUM(J36:M36) -> 0 | J36: 0 | K36: 0 | L36: 0 | M36: 0 | N36: =SUM(O36:S36) -> 0 | O36: 0 | P36: 0 | Q36: 0 | R36: 0 | S36: 0 | T36: 14500
... A45: 36 | B45: Долгосрочные кредиты, предоставленные частным предприятиям, хозяйственным товариществам и обществам | C45: =SUM(D45:H45)-N45+O45 -> 10761924846 | D45: 9062510601 | E45: 1602208219 | F45: 289281856 | G45: 58966434 | H45: 263105172 | I45: =SUM(J45:M45) -> 131122318 | J45: 16577137 | K45: 31634183 | L45: 20023445 | M45: 62887553 | N45: =SUM(O45:S45) -> 594978537 | O45: 80831101 | P45: 155889606 | Q45: 68021241 | R45: 28133217 | S45: 262103372 | T45: 15500
A46: 37 | B46: Лизинг (Финансовая аренда) | C46: =SUM(D46:H46)-N46+O46 -> 428270722 | D46: 349829545 | E46: 96421569 | F46: 0 | G46: 0 | H46: 0 | I46: =SUM(J46:M46) -> 0 | N46: =SUM(O46:S46) -> 18160948 | O46: 180556 | P46: 17980392 | Q46: 0 | R46: 0 | S46: 0 | T46: 15600
A47: 38 | B47: Кредиты и лизинг, находящиеся в процессе судебного разбирательства | C47: =SUM(D47:H47)-N47+O47 -> 0 | D47: 0 | E47: 0 | F47: 0 | G47: 0 | H47: 1910833 | I47: =SUM(J47:M47) -> 0 | N47: =SUM(O47:S47) -> 1910833 | O47: 0 | P47: 0 | Q47: 0 | R47: 0 | S47: 1910833 | T47: 15700
A48: 39 | B48: Инвестиции в зависимые хозяйственные общества, совместные предприятия и дочерние хозяйственные общества | C48: =SUM(D48:H48)-N48+O48 -> 143665561 | D48: 143665561 | E48: 0 | F48: 0 | G48: 0 | H48: 8768330 | I48: =SUM(J48:M48) -> 0 | N48: =SUM(O48:S48) -> 8768330 | O48: 0 | P48: 0 | Q48: 0 | R48: 0 | S48: 8768330 | T48: 15800
A49: 40 | B49: Инвестиции в долговые ценные бумаги, удерживаемые до погашения | C49: =SUM(D49:H49)-N49+O49 -> 5850400 | D49: 5850400 | E49: 0 | F49: 0 | G49: 0 | H49: 0 | I49: =SUM(J49:M49) -> 0 | N49: =SUM(O49:S49) -> 0 | T49: 15900
A50: 41 | B50: Начисленные проценты к получению | C50: =SUM(D50:H50)-N50+O50 -> 1312009307 | D50: 1312009307 | E50: 0 | F50: 0 | G50: 0 | H50: 0 | I50: =SUM(J50:M50) -> 70051214 | J50: 33794659 | K50: 18590479 | L50: 10165286 | M50: 7500790 | N50: =SUM(O50:S50) -> 0 | T50: 16300
A51: 42 | B51: Начисленные беспроцентные доходы к получению | C51: =SUM(D51:H51)-N51+O51 -> 8214191 | D51: 8214191 | E51: 0 | F51: 0 | G51: 0 | H51: 1740332 | I51: =SUM(J51:M51) -> 0 | N51: =SUM(O51:S51) -> 1740332 | S51: 1740332 | T51: 16400
A52: 43 | B52: Основные средства | C52: =SUM(D52:H52)-N52+O52 -> 1181891713 | D52: 1181891713 | E52: 0 | F52: 0 | G52: 0 | H52: 0 | I52: =SUM(J52:M52) -> 0 | N52: =SUM(O52:S52) -> 0 | T52: 16500
A53: 44 | B53: Нематериальные активы | C53: =SUM(D53:H53)-N53+O53 -> 64557643 | D53: 64557643 | E53: 0 | F53: 0 | G53: 0 | H53: 0 | I53: =SUM(J53:M53) -> 0 | N53: =SUM(O53:S53) -> 0 | T53: 16600
A54: 45 | B54: Другое собственное имущество банка | C54: =SUM(D54:H54)-N54+O54 -> 105745990 | D54: 99620560 | E54: 6467310 | F54: 489696 | G54: 28166 | H54: 29633116 | I54: =SUM(J54:M54) -> 0 | N54: =SUM(O54:S54) -> 30492858 | O54: 0 | P54: 646731 | Q54: 55507 | R54: 8230 | S54: 29782390 | T54: 16700
A55: 46 | B55: Отсроченная дебиторская задолженность | C55: =SUM(D55:H55)-N55+O55 -> 72468222 | D55: 62086072 | E55: 0 | F55: 12010997 | G55: 0 | H55: 0 | I55: =SUM(J55:M55) -> 0 | N55: =SUM(O55:S55) -> 1628847 | O55: 0 | P55: 0 | Q55: 1628847 | R55: 0 | S55: 0 | T55: 16800
A56: 47 | B56: Нереализованная прибыль при ревальвации производных инструментов | C56: =SUM(D56:H56)-N56+O56 -> 16032 | D56: 16032 | E56: 0 | F56: 0 | G56: 0 | H56: 0 | I56: =SUM(J56:M56) -> 0 | N56: =SUM(O56:S56) -> 0 | T56: 16900
A57: 48 | B57: Купля-продажа валюты и валютные позиции | C57: =SUM(D57:H57)-N57+O57 -> 0 | D57: 0 | E57: 0 | F57: 0 | G57: 0 | H57: 0 | I57: =SUM(J57:M57) -> 0 | N57: =SUM(O57:S57) -> 0 | T57: 17100
A58: 49 | B58: Транзитные счета | C58: =SUM(D58:H58)-N58+O58 -> 0 | D58: 0 | E58: 0 | F58: 0 | G58: 0 | H58: 0 | I58: =SUM(J58:M58) -> 0 | N58: =SUM(O58:S58) -> 0 | T58: 17300
A59: 50 | B59: Транзитные счета по средствам к списанию с пластиковых карт клиентов | C59: =SUM(D59:H59)-N59+O59 -> 74946691 | D59: 74946691 | E59: 0 | F59: 0 | G59: 0 | H59: 0 | I59: =SUM(J59:M59) -> 0 | N59: =SUM(O59:S59) -> 0 | T59: 17400
A60: 51 | B60: Другие активы | C60: =SUM(D60:H60)-N60+O60 -> 436745963 | D60: 436713369 | E60: 33022 | F60: 0 | G60: 2126 | H60: 8637043 | I60: =SUM(J60:M60) -> 0 | N60: =SUM(O60:S60) -> 8639597 | O60: 0 | P60: 1751 | Q60: 0 | R60: 803 | S60: 8637043 | T60: 19900
B62: ЗАБАЛАНСОВЫЕ СТАТЬИ | C62: =SUM(D62:H62) -> 3478488721 | D62: =SUM(D63:D64) -> 3478488721 | E62: =SUM(E63:E64) -> 0 | F62: =SUM(F63:F64) -> 0 | G62: =SUM(G63:G64) -> 0 | H62: =SUM(H63:H64) -> 0 | I62: =SUM(J62:M62) -> 0 | J62: =SUM(J63:J64) -> 0 | K62: =SUM(K63:K64) -> 0 | L62: =SUM(L63:L64) -> 0 | M62: =SUM(M63:M64) -> 0 | N62: =SUM(N63:N64) -> 0 | O62: =SUM(O63:O64) -> 0 | P62: =SUM(P63:P64) -> 0 | Q62: =SUM(Q63:Q64) -> 0 | ... S62: =SUM(S63:S64) -> 0
A63: 1 | B63: Аккредитивы | C63: =SUM(D63:H63)-N63+O63 -> 1644275155 | D63: 1644275155 | I63: =SUM(J63:M63) -> 0 | N63: =SUM(O63:S63) -> 0 | T63: 90908-90958
A64: 2 | B64: Гарантии и поручетельства | C64: =SUM(D64:H64)-N64+O64 -> 1834213566 | D64: 1834213566 | I64: =SUM(J64:M64) -> 0 | N64: =SUM(O64:S64) -> 0 | T64: 90993
B67: Подпись Председателя правления:
B69: Подпись Главного Бухгалтера:
B71: Состав активов банка формируется в соответсвии с Планом счетов
C72: =+[8]Balance!$C$45 -> 56511320290

Sheet Income 
B1: ОТЧЕТ О ФИНАНСОВЫХ РЕЗУЛЬТАТАХ | D1: Таблица-3
B3: =+'Asset quality'!B3 -> "Ўзсаноатқурилишбанк" АТБ | C3: =+'Asset quality'!P3 -> 44560 | E3: в тыс. сум
A4: № | B4: Категории | C4: Итого | D4: в национальной валюте | E4: в иностранной валюте (в экв. в сумах)
A5: 1. | B5: 1. ПРОЦЕНТНЫЕ ДОХОДЫ
A6: a. | B6: Процентные доходы по счетам в ЦБРУ | C6: =+D6+E6 -> 24773206 | D6: 24773206 | E6: 0
A7: б. | B7: Процентные доходы по счетам в других банках | C7: =+D7+E7 -> 111283999 | D7: 50273714 | E7: 61010285
A8: в. | B8: Процентные доходы по купленным векселям | C8: =+D8+E8 -> 0 | D8: 0 | E8: 0
A9: г. | B9: Процентные доходы по инвестициям | C9: =+D9+E9 -> 7062 | D9: 7062 | E9: 0
A10: д. | B10: Процентные доходы по счетам купли-продажи ценных бумаг | C10: =+D10+E10 -> 141257147 | D10: 141257147 | E10: 0
A11: е. | B11: Процентные доходы по обязательствам клиентов | C11: =+D11+E11 -> 0 | D11: 0 | E11: 0
A12: ж. | B12: Процентные доходы по обяз-вам клиентов по непогашенным акцептам этого банка | C12: =+D12+E12 -> 0 | D12: 0 | E12: 0
A13: з. | B13: Процент, Дисконт (Скидки) и взносы по кредитным и лизинговым операциям | C13: =+D13+E13 -> 3747119677 | D13: 2188567786 | E13: 1558551891
A14: и. | B14: Процентные доходы по соглашениям о покупке ценных бумаг с обратным выкупом | C14: =+D14+E14 -> 0 | D14: 0 | E14: 0
A15: к. | B15: Другие процентные доходы | C15: =+D15+E15 -> 459764028 | D15: 165775235 | E15: 293988793
A16: л. | B16: Итого процентных доходов | C16: =SUM(C6:C15) -> 4484205119 | D16: =SUM(D6:D15) -> 2570654150 | E16: =SUM(E6:E15) -> 1913550969 | G16: =+'Analysis of Interest'!C42 -> 4484205119
A18: 2. | B18: ПРОЦЕНТНЫЕ РАСХОДЫ
A19: а. | B19: Процентные расходы по депозитам до востребования | C19: =+D19+E19 -> 4877042 | D19: 4877042 | E19: 0
A20: б. | B20: Процентные расходы по срочным депозитам | C20: =+D20+E20 -> 570796508 | D20: 408713023 | E20: 162083485
A21: в. | B21: Процентные расходы по счетам к оплате в ЦБРУ | C21: =+D21+E21 -> 0 | D21: 0 | E21: 0
A22: г. | B22: Процентные расходы по счетам к оплате в другие банки | C22: =+D22+E22 -> 68795284 | D22: 44161279 | E22: 24634005
A23: д. | B23: Итого процентных расходов по депозитам | C23: =SUM(C19:C22) -> 644468834 | D23: =SUM(D19:D22) -> 457751344 | E23: =SUM(E19:E22) -> 186717490
A24: е. | B24: Процентные расходы по кредитам к оплате | C24: =+D24+E24 -> 1306417188 | D24: 568203179 | E24: 738214009
A25: ж. | B25: Процентные расходы по соглашениям о продаже ц/б с последующим выкупом | C25: =+D25+E25 -> 1998945 | D25: 1998945 | E25: 0
A26: з. | B26: Другие процентные расходы | C26: =+D26+E26 -> 464440298 | D26: 165136306 | E26: 299303992
A27: и. | B27: Итого процентных расходов по займам | C27: =SUM(C24:C26) -> 1772856431 | D27: =SUM(D24:D26) -> 735338430 | E27: =SUM(E24:E26) -> 1037518001
A28: л. | B28: Итого процентных расходов | C28: =C27+C23 -> 2417325265 | D28: =D27+D23 -> 1193089774 | E28: =E27+E23 -> 1224235491 | G28: =+'Analysis of Interest'!C72 -> 2417325265
A30: 3. | B30: ЧИСТЫЕ ПРОЦЕНТНЫЕ ДОХОДЫ ДО ОЦЕНКИ ВОЗМОЖНЫХ УБЫТКОВ ПО АКТИВАМ | C30: =C16-C28 -> 2066879854 | D30: =D16-D28 -> 1377564376 | E30: =E16-E28 -> 689315478
A31: а. | B31: Минус: Оценка возможных убытков по кредитам и лизингу | C31: =+D31+E31 -> 1408194349 | D31: 651352965 | E31: 756841384
A32: б. | B32: Минус: Оценка возможных убытков по в ценным бумагам | C32: =+D32+E32 -> 0 | D32: 0 | E32: 0
A33: в. | B33: Минус: Оценка возможных убытков по инвестициям | C33: =+D33+E33 -> 2520286 | D33: 2520286 | E33: 0
A34: г. | B34: Минус: Оценка возможных убытков по другим активам | C34: =+D34+E34 -> 36011316 | D34: 3649861 | E34: 32361455
A35: д. | B35: Чистые процентные доходы после оценки возможных убытков по кредитам и лизингу | C35: =C30-C31-C32-C33-C34 -> 620153903 | D35: =D30-D31-D32-D33-D34 -> 720041264 | E35: =E30-E31-E32-E33-E34 -> -99887361
A37: 4. | B37: БЕСПРОЦЕНТНЫЕ ДОХОДЫ
A38: а. | B38: Доходы от комиссий и платы за услуги | C38: =+D38+E38 -> 398095122 | D38: 338710462 | E38: 59384660
A39: б. | B39: Прибыль в иностранной валюте | C39: =+D39+E39 -> 401467426 | D39: 57673432 | E39: 343793994
A40: в. | B40: Прибыль от коммерческих операций | C40: =+D40+E40 -> 0 | D40: -15292 | E40: 15292
A41: г. | B41: Прибыль и дивиденды от инвестиций | C41: =+D41+E41 -> 20024032 | D41: 19961017 | E41: 63015
A42: д. | B42: Другие беспроцентные доходы | C42: =+D42+E42 -> 1344736998 | D42: 392678032 | E42: 952058966
B43: в том числе
A44: д1. | B44: Возврат резервов, с формированных на покрытие потерь по активам | C44: =+D44+E44 -> 1286186514 | D44: 371032293 | E44: 915154221
A45: д2. | B45: Возврат списанных кредитов | C45: =+D45+E45 -> 0
A46: е. | B46: Итого беспроцентных доходов | C46: =SUM(C38:C42) -> 2164323578 | D46: =SUM(D38:D42) -> 809007651 | E46: =SUM(E38:E42) -> 1355315927
A48: 5. | B48: БЕСПРОЦЕНТНЫЕ РАСХОДЫ
A49: а. | B49: Комиссионные расходы и расходы за услуги | C49: =+D49+E49 -> 190915805 | D49: 140212108 | E49: 50703697
A50: б. | B50: Убытки в иностранной валюте | C50: =+D50+E50 -> 240645176 | D50: 41672 | E50: 240603504
A51: в. | B51: Убытки по счетам купли-продажи | C51: =+D51+E51 -> 0 | D51: 0 | E51: 0
A52: г. | B52: Убытки от инвестиций | C52: =+D52+E52 -> 0 | D52: 0 | E52: 0
A53: д. | B53: Другие беспроцентные расходы | C53: =+D53+E53 -> 1454428 | D53: 563675 | E53: 890753
A54: е. | B54: Итого беспроцентных расходов | C54: =SUM(C49:C53) -> 433015409 | D54: =SUM(D49:D53) -> 140817455 | E54: =SUM(E49:E53) -> 292197954
A56: 6. | B56: ЧИСТЫЙ ДОХОД ДО ОПЕРАЦИОННЫХ РАСХОДОВ | C56: =C35+C46-C54 -> 2351462072 | D56: =D35+D46-D54 -> 1388231460 | E56: =E35+E46-E54 -> 963230612
A58: 7. | B58: ОПЕРАЦИОННЫЕ РАСХОДЫ
A59: а. | B59: Заработная плата и другие расходы на сотрудников | C59: =D59+E59 -> 669639454 | D59: =669589781+49673 -> 669639454
A60: а1) | B60: из них, выплаты основному руководящему персоналу | C60: =D60+E60 -> 27655501 | D60: 27655501
A61: б. | B61: Аренда и содержание | C61: =D61+E61 -> 65679109 | D61: 65679109
A62: в. | B62: Командировочные и транспортные расходы | C62: =D62+E62 -> 8933350 | D62: =7280362+1652988 -> 8933350
A63: г. | B63: Административные расходы | C63: =D63+E63 -> 36653286 | D63: 36653286
A64: д. | B64: Репрезентация и благотворительность | C64: =D64+E64 -> 79875389 | D64: 79875389
A65: е. | B65: Расходы на износ | C65: =D65+E65 -> 73889494 | D65: 73889494
A66: ж. | B66: Страхование | C66: =D66+E66 -> 1284062 | D66: 1284062
A67: з. | B67: Налоги | C67: =D67+E67 -> 36789734 | D67: 36789734
A68: и. | B68: Штрафы и пеня | C68: =D68+E68 -> 877648 | D68: =635535+242113 -> 877648
A69: к. | B69: Другие операционные расходы | C69: =D69+E69 -> 149526739 | D69: =67224730+82302009 -> 149526739
A70: л. | B70: Итого операционных расходов | C70: =SUM(C59:C69)-C60 -> 1123148265 | D70: =SUM(D59:D69)-D60 -> 1123148265
A72: 8. | B72: ЧИСТАЯ ПРИБЫЛЬ ДО УПЛАТЫ НАЛОГОВ И ДРУГИХ ПОПРАВОК | C72: =C56-C70 -> 1228313807 | D72: =D56-D70 -> 265083195 | E72: =+E56-(C70-D70) -> 963230612
A73: а. | B73: Оценка налога на прибыль | C73: =+D73 -> 230092137 | D73: 230092137
A75: 9. | B75: ДОХОД ДО ВВЕДЕНИЯ ПОПРАВОК | C75: =C72-C73 -> 998221670 | D75: =D72-D73 -> 34991058 | E75: =E72-E73 -> 963230612
A76: а. | B76: Непредвиденные доходы или убытки, чистые | C76: =+D76+E76 -> 0 | D76: 0 | E76: 0
A77: б. | B77: Другие поправки к прибыли, чистые | C77: =+D77+E77 -> 0 | D77: 0 | E77: 0
A79: 10. | B79: ЧИСТАЯ ПРИБЫЛЬ (УБЫТКИ) | C79: =C75+C76+C77 -> 998221670 | D79: =D75+D76+D77 -> 34991058 | E79: =E75+E76+E77 -> 963230612
B81: Подпись Председателя правления:
B83: Подпись Главного Бухгалтера:

Sheet Analysis of Interest
B1: АНАЛИЗ ПРОЦЕНТНЫХ ДОХОДОВ И РАСХОДОВ | C1: Таблица-4
B3: =+'Asset quality'!B3 -> "Ўзсаноатқурилишбанк" АТБ | C3: =+'Asset quality'!P3 -> 44560
A4: № | B4: Категория | C4: в тыс. сум
A5: 1 . | B5: ПРОЦЕНТНЫЕ ДОХОДЫ ПО КРЕДИТНЫМ И ЛИЗИНГОВЫМ ОПЕРАЦИЯМ
A6: a. | B6: Кредиты и лизинговые операции ЦБРУ | C6: 0
A7: б. | B7: Кредиты и лизинговые операции другим банкам | C7: 19
A8: в. | B8: Кредиты и лизинговые операции Правительству | C8: 12007
A9: г. | B9: Кредиты и лизинговые операции физическим лицам | C9: 578565623
A10: д. | B10: Кредиты и лизинговые операции государственным предприятиям | C10: 902424692
A11: е. | B11: Кредиты и лизинговые операции совместным и иностранным предприятиям | C11: 529303119
A12: ж. | B12: Кредиты и лизинговые операции частным товариществам и корпорациям | C12: 1715606267
A13: з. | B13: Другие кредиты и лизинговые операции | C13: 21207950
A14: и. | B14: ИТОГО ПРОЦЕНТНЫХ ДОХОДОВ ПО КРЕДИТНЫМ И ЛИЗИНГОВЫМ ОПЕРАЦИЯМ | C14: =SUM(C6:C13) -> 3747119677
A16: 2. | B16: ПРОЦЕНТНЫЕ ДОХОДЫ ПО КОРРЕСПОНДЕНТСКИМ СЧЕТАМ
A17: a. | B17: К получению из ЦБРУ | C17: 24773206
A18: б. | B18: К получению из других банков | C18: 111283999
B19: ИТОГО ПРОЦЕНТНЫХ ДОХОДОВ ПО КОРРЕСПОНДЕНТСКИМ СЧЕТАМ | C19: =SUM(C17:C18) -> 136057205
A21: 3. | B21: ПРОЦЕНТНЫЕ ДОХОДЫ ПО СЧЕТАМ КУПЛИ-ПРОДАЖИ Ц/Б
A22: a. | B22: Государственные казначейские ценные бумаги | C22: 42674492
A23: б. | B23: Облигации и ценные бумаги ЦБРУ | C23: 98582655
A24: в. | B24: Ценные бумаги государственных корпораций | C24: 0
A25: г. | B25: Еврооблигации | C25: 0
A26: д. | B26: Частные ценные бумаги | C26: 0
A27: е. | B27: Другие ценные бумаги | C27: 0
A28: ж. | B28: ИТОГО ПРОЦЕНТНЫХ ДОХОДОВ ПО СЧЕТАМ КУПЛИ-ПРОДАЖИ Ц/Б | C28: =SUM(C22:C27) -> 141257147
A30: 4. | B30: ПРОЦЕНТНЫЕ ДОХОДЫ ПО ИНВЕСТИЦИЯМ
A31: a. | B31: Государственные облигации | C31: 0
A32: б. | B32: Облигации и ценные бумаги ЦБРУ | C32: 0
A33: в. | B33: Частные облигации | C33: 7062
A34: г. | B34: Еврооблигации | C34: 0
A35: д. | B35: Другие ценные бумаги | C35: 0
A36: е. | B36: ИТОГО ПРОЦЕНТНЫХ ДОХОДОВ ПО ИНВЕСТИЦИЯМ | C36: =SUM(C31:C35) -> 7062
A38: 5. | B38: ДРУГИЕ ПРОЦЕНТНЫЕ ДОХОДЫ
A39: a. | B39: Процентные доходы по соглашениям о покупке ц/б c обратным выкупом | C39: 0
A40: б. | B40: Другие процентные доходы | C40: 459764028
A42: 6. | B42: ИТОГО ПРОЦЕНТНЫХ ДОХОДОВ | C42: =C14+C19+C28+C36+C39+C40 -> 4484205119
A44: 7. | B44: ПРОЦЕНТНЫЕ РАСХОДЫ ПО ДЕПОЗИТАМ
A45: A. | B45: Депозиты до востребования
A46: a. | B46: Правительство | C46: 3067071
A47: б. | B47: Физические лица | C47: 0
A48: в. | B48: Государственные предприятия | C48: 0
A49: г. | B49: Совместные и иностранные предприятия | C49: 0
A50: д. | B50: Частные товарищества и корпорации | C50: 1809971
A51: е. | B51: Другие депозиты | C51: 0
A52: ж. | B52: Итого процентных расходов по депозитам до востребования | C52: =SUM(C46:C51) -> 4877042
A54: Б. | B54: Срочные депозиты
A55: a. | B55: Правительство | C55: 176136183
A56: б. | B56: Физические лица | C56: 320032201
A57: в. | B57: Государственные предприятия | C57: 13625071
A58: г. | B58: Совместные и иностранные предприятия | C58: 31867051
A59: д. | B59: Частные товарищества и корпорации | C59: 14713027
A60: е. | B60: Другие депозиты | C60: 14422975
A61: ж. | B61: Итого процентных расходов по срочным депозитам | C61: =SUM(C55:C60) -> 570796508
A63: В. | B63: ИТОГО ПРОЦЕНТНЫХ РАСХОДОВ ПО ДЕПОЗИТАМ | C63: =C52+C61 -> 575673550
A65: 8. | B65: ПРОЦЕНТНЫЕ РАСХОДЫ ПО ДРУГИМ ОБЯЗАТЕЛЬСТВАМ
A66: а. | B66: Процентные расходы по непогашенным акцептам | C66: 0
A67: б. | B67: Процентные расходы по кредитам к оплате | C67: 1306417188
A68: в. | B68: Процентные расходы по соглашениям о продаже ц/б с последующим выкупом | C68: 1998945
A69: г. | B69: Другие процентные расходы | C69: 533235582
A70: д. | B70: ИТОГО ПРОЦЕНТНЫХ РАСХОДОВ ПО ДРУГИМ ОБЯЗАТЕЛЬСТВАМ | C70: =SUM(C66:C69) -> 1841651715
A72: 9. | B72: ИТОГО ПРОЦЕНТНЫХ РАСХОДОВ | C72: =C63+C70 -> 2417325265
B74: Подпись Председателя правления:
B76: Подпись Главного Бухгалтера:

Sheet Changes in Equity
B1: ИЗМЕНЕНИЯ В СОБСТВЕННОМ КАПИТАЛЕ | C1: Таблица-7
B3: =+'Asset quality'!B3 -> "Ўзсаноатқурилишбанк" АТБ | C3: =+'Asset quality'!P3 -> 44560
A4: № | B4: Категория | C4: в тыс. сум
A5: 1. | B5: Итого собственного капитала первоначально определенного за прошлый год | C5: 6704348045
A6: 2. | B6: Исправления в собственном капитале не показанные в отчете за прошлый год, чистые | C6: 0
A7: 3. | B7: Исправленный баланс на конец прошлого календарного года (сумма строк 1 и 2) | C7: =SUM(C5:C6) -> 6704348045
A8: 4. | B8: Чистый прибыль (убыток) по состоянию на дату от начала года | C8: =+'Income '!C79 -> 998221670 | D8: =+[8]Balance!$C$76 -> 998221670
A9: 5. | B9: Продажа, Обмен, Приобретение или выкуп акций, за текущий год (чистая выручка) | C9: 0
A10: 6. | B10: Изменения в оценочной стоимости прироста над первонач. стоимостью, за текущий год (чистые) | C10: -967983
A11: 7. | B11: МИНУС: Денежные дивиденды объявленные по привилегированным акциям | C11: 1616900
A12: 8. | B12: МИНУС: Денежные дивиденды объявленные по обыкновенным акциям
A13: 9. | B13: Другие статьи влияющие на собственный капитал за текущий год (чистые) | C13: 928274
A14: 10. | B14: Итого собственного капитала на конец текущего периода (сумма строк с 3 по 10) | C14: =C7+SUM(C8:C10)-SUM(C11:C12)+C13 -> 7700913106 | D14: =+[8]Balance!$C$77 -> 7700913106
B16: Подпись Председателя правления:
B18: Подпись Главного Бухгалтера:

Sheet Loans Receivable
A1: КРЕДИТЫ И ЛИЗИНГИ К ПОЛУЧЕНИЮ ПО ОТРАСЛЯМ ЭКОНОМИКИ, ТИПАМ КЛИЕНТОВ И ПО ТИПУ ОБЕСПЕЧЕНИЯ | W1: Таблица-8
B3: =+'Asset quality'!B3 -> "Ўзсаноатқурилишбанк" АТБ | T3: =+'Asset quality'!P3 -> 44560 | X3: тыс. сум
A4: № | B4: Отрасль экономики | C4: Сумма кредита | D4: в национальной валюте | F4: в иностранной валюте (в экв. в сумах) | H4: из них | J4: из них
D5: Сумма | E5: средне-взвешенные процентные ставки | F5: Сумма | G5: средне-взвешенные процентные ставки | H5: Начисляемые кредиты | I5: Кредиты переведённые в статус ненаращивания процентов | J5: Депозиты | K5: Гарантированные Правительством Республики Узбекистан | L5: из них | M5: Транспортные средства | N5: Инвентарь | O5: Недвижимость | P5: из них | R5: Оборудование | S5: Векселя (облигации) | T5: Акции | U5: Гарантия третьей стороны | V5: Поручительства третьей стороны | W5: Страховой полис | X5: Необеспеченные | Y5: Другое обеспечение
L6: Гарантированные Правительством Республики Узбекистан в иностранной валюте (экв.сум) | P6: жилая недвижимость | Q6: коммерческая недвижимость
A7: Код | B7: (А) | C7: (Б) | D7: (Б1) | E7: (Б2) | F7: (Б3) | G7: (Б4) | H7: (В) | I7: (Г) | J7: (Д) | K7: (Е) | L7: (Е1) | M7: (Ж) | N7: (З) | O7: (И) | P7: (И1) | Q7: (И2) | R7: (К) | S7: (Л) | T7: (М) | U7: (Н) | V7: (О) | W7: (П) | X7: (Р) | Y7: (С)
B8: Промышленность
A9: 10 | B9: Физические лица | C9: =SUM(J9:Y9)-L9-P9-Q9 -> 0 | D9: 0 | E9: 0 | F9: 0 | G9: 0 | H9: 0 | I9: 0 | J9: 0 | K9: 0 | L9: 0 | M9: 0 | N9: 0 | O9: =+P9+Q9 -> 0 | P9: 0 | Q9: 0 | R9: 0 | S9: 0 | T9: 0 | U9: 0 | V9: 0 | W9: 0 | X9: 0 | Y9: 0
A10: =A9+10 -> 20 | B10: Государственные предприятия | C10: =SUM(J10:Y10)-L10-P10-Q10 -> 10901588448 | D10: 3225091450 | E10: 0.1529786 | F10: 7676496998 | G10: 0.033415913 | H10: 10901588448 | I10: 0 | J10: 0 | K10: 5663025588 | L10: 4780389581 | M10: 28300887 | N10: 2700513 | O10: =+P10+Q10 -> 104702325 | P10: 0 | Q10: 104702325 | R10: 593340361 | S10: 0 | T10: 149473257 | U10: 0 | V10: 2196889788 | W10: 8872939 | X10: 184355457 | Y10: 1969927333
A11: =A10+10 -> 30 | B11: Совместные и иностранные предприятия | C11: =SUM(J11:Y11)-L11-P11-Q11 -> 5719876540 | D11: 826864403 | E11: 0.20247594 | F11: 4893012137 | G11: 0.061378042 | H11: 5619043697 | I11: 100832843 | J11: 0 | K11: 0 | L11: 0 | M11: 21345269 | N11: 126401211 | O11: =+P11+Q11 -> 1075928868 | P11: 0 | Q11: 1075928868 | R11: 2358648641 | S11: 0 | T11: 0 | U11: 0 | V11: 732365716 | W11: 780466338 | X11: 0 | Y11: 624720497
A12: =A11+10 -> 40 | B12: Частные товарищества и корпорации | C12: =SUM(J12:Y12)-L12-P12-Q12 -> 9718269506 | D12: 2598006651 | E12: 0.18609702 | F12: 7120262855 | G12: 0.065061377 | H12: 9453685941 | I12: 264583565 | J12: 807588 | K12: 0 | L12: 0 | M12: 72269850 | N12: 24051674 | O12: =+P12+Q12 -> 2565857985 | P12: 0 | Q12: 2565857985 | R12: 1292967858 | S12: 0 | T12: 0 | U12: 0 | V12: 4420062843 | W12: 772189080 | X12: 4136000 | Y12: 565926628
A13: =A12+10 -> 50 | B13: Правительство | C13: =SUM(J13:Y13)-L13-P13-Q13 -> 0 | D13: 0 | E13: 0 | F13: 0 | G13: 0 | H13: 0 | I13: 0 | J13: 0 | K13: 0 | L13: 0 | M13: 0 | N13: 0 | O13: =+P13+Q13 -> 0 | P13: 0 | Q13: 0 | R13: 0 | S13: 0 | T13: 0 | U13: 0 | V13: 0 | W13: 0 | X13: 0 | Y13: 0
A14: =A13+10 -> 60 | B14: Прочие | C14: =SUM(J14:Y14)-L14-P14-Q14 -> 0 | D14: 0 | E14: 0 | F14: 0 | G14: 0 | H14: 0 | I14: 0 | J14: 0 | K14: 0 | L14: 0 | M14: 0 | N14: 0 | O14: =+P14+Q14 -> 0 | P14: 0 | Q14: 0 | R14: 0 | S14: 0 | T14: 0 | U14: 0 | V14: 0 | W14: 0 | X14: 0 | Y14: 0
A15: =A14+10 -> 70 | B15: Итого по промышленности | C15: =SUM(J15:Y15)-L15-P15-Q15 -> 26339734494 | D15: =SUM(D9:D14) -> 6649962504 | E15: =IFERROR(((D9*E9)/D15)+((D10*E10)/D15)+((D11*E11)/D15)+((D12*E12)/D15)+((D13*E13)/D15)+((D14*E14)/D15),0) -> 0.17207186 | F15: =SUM(F9:F14) -> 19689771990 | G15: =IFERROR(((F9*G9)/F15)+((F10*G10)/F15)+((F11*G11)/F15)+((F12*G12)/F15)+((F13*G13)/F15)+((F14*G14)/F15),0) -> 0.051808358 | H15: =SUM(H9:H14) -> 25974318086 | I15: =SUM(I9:I14) -> 365416408 | J15: =SUM(J9:J14) -> 807588 | K15: =SUM(K9:K14) -> 5663025588 | L15: =SUM(L9:L14) -> 4780389581 | M15: =SUM(M9:M14) -> 121916006 | N15: =SUM(N9:N14) -> 153153398 | O15: =SUM(O9:O14) -> 3746489178 | ... Y15: =SUM(Y9:Y14) -> 3160574458
B16: Сельское хозяйство
A17: =A15+10 -> 80 | B17: Физические лица | C17: =SUM(J17:Y17)-L17-P17-Q17 -> 0 | D17: 0 | E17: 0 | F17: 0 | G17: 0 | H17: 0 | I17: 0 | J17: 0 | K17: 0 | L17: 0 | M17: 0 | N17: 0 | O17: =+P17+Q17 -> 0 | P17: 0 | Q17: 0 | R17: 0 | S17: 0 | T17: 0 | U17: 0 | V17: 0 | W17: 0 | X17: 0 | Y17: 0
A18: =A17+10 -> 90 | B18: Государственные предприятия | C18: =SUM(J18:Y18)-L18-P18-Q18 -> 0 | D18: 0 | E18: 0 | F18: 0 | G18: 0 | H18: 0 | I18: 0 | J18: 0 | K18: 0 | L18: 0 | M18: 0 | N18: 0 | O18: =+P18+Q18 -> 0 | P18: 0 | Q18: 0 | R18: 0 | S18: 0 | T18: 0 | U18: 0 | V18: 0 | W18: 0 | X18: 0 | Y18: 0
A19: =A18+10 -> 100 | B19: Совместные и иностранные предприятия | C19: =SUM(J19:Y19)-L19-P19-Q19 -> 467428932 | D19: 167783624 | E19: 0.20540486 | F19: 299645308 | G19: 0.080407866 | H19: 467428932 | I19: 0 | J19: 20271520 | K19: 0 | L19: 0 | M19: 13902225 | N19: 0 | O19: =+P19+Q19 -> 77377698 | P19: 0 | Q19: 77377698 | R19: 54239546 | S19: 0 | T19: 0 | U19: 0 | V19: 18489453 | W19: 283148490 | X19: 0 | Y19: 0
A20: =A19+10 -> 110 | B20: Частные товарищества и корпорации | C20: =SUM(J20:Y20)-L20-P20-Q20 -> 2450112877 | D20: 1103868617 | E20: 0.15172089 | F20: 1346244260 | G20: 0.064523828 | H20: 2378832994 | I20: 71279883 | J20: 201368 | K20: 0 | L20: 0 | M20: 53811738 | N20: 0 | O20: =+P20+Q20 -> 612560342 | P20: 0 | Q20: 612560342 | R20: 132025690 | S20: 0 | T20: 0 | U20: 0 | V20: 1208907558 | W20: 442606181 | X20: 0 | Y20: 0
A21: =A20+10 -> 120 | B21: Фермерское хозяйство | C21: =SUM(J21:Y21)-L21-P21-Q21 -> 225782941 | D21: 95332387 | E21: 0.20482658 | F21: 130450554 | G21: 0.063385128 | H21: 207991833 | I21: 17791108 | J21: 0 | K21: 0 | L21: 0 | M21: 4137819 | N21: 0 | O21: =+P21+Q21 -> 91963803 | P21: 0 | Q21: 91963803 | R21: 39403711 | S21: 0 | T21: 0 | U21: 0 | V21: 87239195 | W21: 3038413 | X21: 0 | Y21: 0
A22: =A21+10 -> 130 | B22: Правительство | C22: =SUM(J22:Y22)-L22-P22-Q22 -> 0 | D22: 0 | E22: 0 | F22: 0 | G22: 0 | H22: 0 | I22: 0 | J22: 0 | K22: 0 | L22: 0 | M22: 0 | N22: 0 | O22: =+P22+Q22 -> 0 | P22: 0 | Q22: 0 | R22: 0 | S22: 0 | T22: 0 | U22: 0 | V22: 0 | W22: 0 | X22: 0 | Y22: 0
A23: =A22+10 -> 140 | B23: Прочие | C23: =SUM(J23:Y23)-L23-P23-Q23 -> 0 | D23: 0 | E23: 0 | F23: 0 | G23: 0 | H23: 0 | I23: 0 | J23: 0 | K23: 0 | L23: 0 | M23: 0 | N23: 0 | O23: =+P23+Q23 -> 0 | P23: 0 | Q23: 0 | R23: 0 | S23: 0 | T23: 0 | U23: 0 | V23: 0 | W23: 0 | X23: 0 | Y23: 0
A24: =A23+10 -> 150 | B24: Итого по сельскому хозяйству | C24: =SUM(J24:Y24)-L24-P24-Q24 -> 3143324750 | D24: =SUM(D17:D23) -> 1366984628 | E24: =IFERROR(((D17*E17)/D24)+((D18*E18)/D24)+((D19*E19)/D24)+((D20*E20)/D24)+((D21*E21)/D24)+((D22*E22)/D24)+((D23*E23)/D24),0) -> 0.16201361 | F24: =SUM(F17:F23) -> 1776340122 | G24: =IFERROR(((F17*G17)/F24)+((F18*G18)/F24)+((F19*G19)/F24)+((F20*G20)/F24)+((F21*G21)/F24)+((F22*G22)/F24)+((F23*G23)/F24),0) -> 0.067119634 | H24: =SUM(H17:H23) -> 3054253759 | I24: =SUM(I17:I23) -> 89070991 | J24: =SUM(J17:J23) -> 20472888 | K24: =SUM(K17:K23) -> 0 | L24: =SUM(L17:L23) -> 0 | M24: =SUM(M17:M23) -> 71851782 | N24: =SUM(N17:N23) -> 0 | O24: =SUM(O17:O23) -> 781901843 | ... Y24: =SUM(Y17:Y23) -> 0
B25: Транспорт и коммуникации
A26: =A24+10 -> 160 | B26: Физические лица | C26: =SUM(J26:Y26)-L26-P26-Q26 -> 0 | D26: 0 | E26: 0 | F26: 0 | G26: 0 | H26: 0 | I26: 0 | J26: 0 | K26: 0 | L26: 0 | M26: 0 | N26: 0 | O26: =+P26+Q26 -> 0 | P26: 0 | Q26: 0 | R26: 0 | S26: 0 | T26: 0 | U26: 0 | V26: 0 | W26: 0 | X26: 0 | Y26: 0
A27: =A26+10 -> 170 | B27: Государственные предприятия | C27: =SUM(J27:Y27)-L27-P27-Q27 -> 2661090173 | D27: 149896707 | E27: 0.15552445 | F27: 2511193466 | G27: 0.045970914 | H27: 2661090173 | I27: 0 | J27: 925716792 | K27: 1419745546 | L27: 1419745546 | M27: 0 | N27: 0 | O27: =+P27+Q27 -> 0 | P27: 0 | Q27: 0 | R27: 40151764 | S27: 0 | T27: 0 | U27: 0 | V27: 140492605 | W27: 0 | X27: 0 | Y27: 134983466
A28: =A27+10 -> 180 | B28: Совместные и иностранные предприятия | C28: =SUM(J28:Y28)-L28-P28-Q28 -> 0 | D28: 0 | E28: 0 | F28: 0 | G28: 0 | H28: 0 | I28: 0 | J28: 0 | K28: 0 | L28: 0 | M28: 0 | N28: 0 | O28: =+P28+Q28 -> 0 | P28: 0 | Q28: 0 | R28: 0 | S28: 0 | T28: 0 | U28: 0 | V28: 0 | W28: 0 | X28: 0 | Y28: 0
A29: =A28+10 -> 190 | B29: Частные товарищества и корпорации | C29: =SUM(J29:Y29)-L29-P29-Q29 -> 802602741 | D29: 232327864 | E29: 0.19310281 | F29: 570274877 | G29: 0.070537949 | H29: 795277354 | I29: 7325387 | J29: 286367 | K29: 0 | L29: 0 | M29: 50781760 | N29: 0 | O29: =+P29+Q29 -> 446610676 | P29: 0 | Q29: 446610676 | R29: 39370581 | S29: 0 | T29: 0 | U29: 0 | V29: 235772789 | W29: 29780568 | X29: 0 | Y29: 0
A30: =A29+10 -> 200 | B30: Правительство | C30: =SUM(J30:Y30)-L30-P30-Q30 -> 0 | D30: 0 | E30: 0 | F30: 0 | G30: 0 | H30: 0 | I30: 0 | J30: 0 | K30: 0 | L30: 0 | M30: 0 | N30: 0 | O30: =+P30+Q30 -> 0 | P30: 0 | Q30: 0 | R30: 0 | S30: 0 | T30: 0 | U30: 0 | V30: 0 | W30: 0 | X30: 0 | Y30: 0
A31: =A30+10 -> 210 | B31: Прочие | C31: =SUM(J31:Y31)-L31-P31-Q31 -> 0 | D31: 0 | E31: 0 | F31: 0 | G31: 0 | H31: 0 | I31: 0 | J31: 0 | K31: 0 | L31: 0 | M31: 0 | N31: 0 | O31: =+P31+Q31 -> 0 | P31: 0 | Q31: 0 | R31: 0 | S31: 0 | T31: 0 | U31: 0 | V31: 0 | W31: 0 | X31: 0 | Y31: 0
A32: =A31+10 -> 220 | B32: Итого по транспорту и коммуникациям | C32: =SUM(J32:Y32)-L32-P32-Q32 -> 3463692914 | D32: =SUM(D26:D31) -> 382224571 | E32: =IFERROR(((D26*E26)/D32)+((D27*E27)/D32)+((D28*E28)/D32)+((D29*E29)/D32)+((D30*E30)/D32)+((D31*E31)/D32),0) -> 0.17836574 | F32: =SUM(F26:F31) -> 3081468343 | G32: =IFERROR(((F26*G26)/F32)+((F27*G27)/F32)+((F28*G28)/F32)+((F29*G29)/F32)+((F30*G30)/F32)+((F31*G31)/F32),0) -> 0.050517436 | H32: =SUM(H26:H31) -> 3456367527 | I32: =SUM(I26:I31) -> 7325387 | J32: =SUM(J26:J31) -> 926003159 | K32: =SUM(K26:K31) -> 1419745546 | L32: =SUM(L26:L31) -> 1419745546 | M32: =SUM(M26:M31) -> 50781760 | N32: =SUM(N26:N31) -> 0 | O32: =SUM(O26:O31) -> 446610676 | ... Y32: =SUM(Y26:Y31) -> 134983466
B33: Строительство
A34: =A32+10 -> 230 | B34: Физические лица | C34: =SUM(J34:Y34)-L34-P34-Q34 -> 0 | D34: 0 | E34: 0 | F34: 0 | G34: 0 | H34: 0 | I34: 0 | J34: 0 | K34: 0 | L34: 0 | M34: 0 | N34: 0 | O34: =+P34+Q34 -> 0 | P34: 0 | Q34: 0 | R34: 0 | S34: 0 | T34: 0 | U34: 0 | V34: 0 | W34: 0 | X34: 0 | Y34: 0
A35: =A34+10 -> 240 | B35: Государственные предприятия | C35: =SUM(J35:Y35)-L35-P35-Q35 -> 6882287 | D35: 6882287 | E35: 0.20801222 | F35: 0 | G35: 0 | H35: 6882287 | I35: 0 | J35: 0 | K35: 0 | L35: 0 | M35: 63160 | N35: 0 | O35: =+P35+Q35 -> 749542 | P35: 0 | Q35: 749542 | R35: 151943 | S35: 0 | T35: 0 | U35: 0 | V35: 5917642 | W35: 0 | X35: 0 | Y35: 0
A36: =A35+10 -> 250 | B36: Совместные и иностранные предприятия | C36: =SUM(J36:Y36)-L36-P36-Q36 -> 61669227 | D36: 135253 | E36: 0.14722624 | F36: 61533974 | G36: 0.091082347 | H36: 61669227 | I36: 0 | J36: 0 | K36: 0 | L36: 0 | M36: 7370880 | N36: 0 | O36: =+P36+Q36 -> 15104184 | P36: 0 | Q36: 15104184 | R36: 10569920 | S36: 0 | T36: 0 | U36: 0 | V36: 28607405 | W36: 16838 | X36: 0 | Y36: 0
A37: =A36+10 -> 260 | B37: Частные товарищества и корпорации | C37: =SUM(J37:Y37)-L37-P37-Q37 -> 755129016 | D37: 337185987 | E37: 0.21626595 | F37: 417943029 | G37: 0.071381125 | H37: 740014039 | I37: 15114977 | J37: 62345 | K37: 0 | L37: 0 | M37: 22713795 | N37: 262779 | O37: =+P37+Q37 -> 234546898 | P37: 0 | Q37: 234546898 | R37: 15497448 | S37: 0 | T37: 0 | U37: 700000 | V37: 443622129 | W37: 37723622 | X37: 0 | Y37: 0
A38: =A37+10 -> 270 | B38: Правительство | C38: =SUM(J38:Y38)-L38-P38-Q38 -> 0 | D38: 0 | E38: 0 | F38: 0 | G38: 0 | H38: 0 | I38: 0 | J38: 0 | K38: 0 | L38: 0 | M38: 0 | N38: 0 | O38: =+P38+Q38 -> 0 | P38: 0 | Q38: 0 | R38: 0 | S38: 0 | T38: 0 | U38: 0 | V38: 0 | W38: 0 | X38: 0 | Y38: 0
A39: =A38+10 -> 280 | B39: Прочие | C39: =SUM(J39:Y39)-L39-P39-Q39 -> 0 | D39: 0 | E39: 0 | F39: 0 | G39: 0 | H39: 0 | I39: 0 | J39: 0 | K39: 0 | L39: 0 | M39: 0 | N39: 0 | O39: =+P39+Q39 -> 0 | P39: 0 | Q39: 0 | R39: 0 | S39: 0 | T39: 0 | U39: 0 | V39: 0 | W39: 0 | X39: 0 | Y39: 0
A40: =A39+10 -> 290 | B40: Итого по строительству | C40: =SUM(J40:Y40)-L40-P40-Q40 -> 823680530 | D40: =SUM(D34:D39) -> 344203527 | E40: =IFERROR(((D34*E34)/D40)+((D35*E35)/D40)+((D36*E36)/D40)+((D37*E37)/D40)+((D38*E38)/D40)+((D39*E39)/D40),0) -> 0.21607379 | F40: =SUM(F34:F39) -> 479477003 | G40: =IFERROR(((F34*G34)/F40)+((F35*G35)/F40)+((F36*G36)/F40)+((F37*G37)/F40)+((F38*G38)/F40)+((F39*G39)/F40),0) -> 0.073909494 | H40: =SUM(H34:H39) -> 808565553 | I40: =SUM(I34:I39) -> 15114977 | J40: =SUM(J34:J39) -> 62345 | K40: =SUM(K34:K39) -> 0 | L40: =SUM(L34:L39) -> 0 | M40: =SUM(M34:M39) -> 30147835 | N40: =SUM(N34:N39) -> 262779 | O40: =SUM(O34:O39) -> 250400624 | ... Y40: =SUM(Y34:Y39) -> 0
B41: Торговля и общественное питание
A42: =A40+10 -> 300 | B42: Физические лица | C42: =SUM(J42:Y42)-L42-P42-Q42 -> 0 | D42: 0 | E42: 0 | F42: 0 | G42: 0 | H42: 0 | I42: 0 | J42: 0 | K42: 0 | L42: 0 | M42: 0 | N42: 0 | O42: =+P42+Q42 -> 0 | P42: 0 | Q42: 0 | R42: 0 | S42: 0 | T42: 0 | U42: 0 | V42: 0 | W42: 0 | X42: 0 | Y42: 0
A43: =A42+10 -> 310 | B43: Государственные предприятия | C43: =SUM(J43:Y43)-L43-P43-Q43 -> 133770 | D43: 133770 | E43: 0.28 | F43: 0 | G43: 0 | H43: 133770 | I43: 0 | J43: 0 | K43: 0 | L43: 0 | M43: 0 | N43: 0 | O43: =+P43+Q43 -> 133770 | P43: 0 | Q43: 133770 | R43: 0 | S43: 0 | T43: 0 | U43: 0 | V43: 0 | W43: 0 | X43: 0 | Y43: 0
A44: =A43+10 -> 320 | B44: Совместные и иностранные предприятия | C44: =SUM(J44:Y44)-L44-P44-Q44 -> 532805854 | D44: 4129667 | E44: 0.21181371 | F44: 528676187 | G44: 0.066965054 | H44: 532805854 | I44: 0 | J44: 0 | K44: 0 | L44: 0 | M44: 1754899 | N44: 0 | O44: =+P44+Q44 -> 247603695 | P44: 0 | Q44: 247603695 | R44: 9836191 | S44: 0 | T44: 0 | U44: 1737972 | V44: 242737302 | W44: 29135795 | X44: 0 | Y44: 0
A45: =A44+10 -> 330 | B45: Частные товарищества и корпорации | C45: =SUM(J45:Y45)-L45-P45-Q45 -> 1918100208 | D45: 658068015 | E45: 0.20337923 | F45: 1260032193 | G45: 0.074940954 | H45: 1875018519 | I45: 43081689 | J45: 471082 | K45: 0 | L45: 0 | M45: 35996671 | N45: 97313184 | O45: =+P45+Q45 -> 784169192 | P45: 0 | Q45: 784169192 | R45: 146077279 | S45: 0 | T45: 0 | U45: 0 | V45: 647487302 | W45: 205726498 | X45: 859000 | Y45: 0
A46: =A45+10 -> 340 | B46: Правительство | C46: =SUM(J46:Y46)-L46-P46-Q46 -> 0 | D46: 0 | E46: 0 | F46: 0 | G46: 0 | H46: 0 | I46: 0 | J46: 0 | K46: 0 | L46: 0 | M46: 0 | N46: 0 | O46: =+P46+Q46 -> 0 | P46: 0 | Q46: 0 | R46: 0 | S46: 0 | T46: 0 | U46: 0 | V46: 0 | W46: 0 | X46: 0 | Y46: 0
A47: =A46+10 -> 350 | B47: Прочие | C47: =SUM(J47:Y47)-L47-P47-Q47 -> 0 | D47: 0 | E47: 0 | F47: 0 | G47: 0 | H47: 0 | I47: 0 | J47: 0 | K47: 0 | L47: 0 | M47: 0 | N47: 0 | O47: =+P47+Q47 -> 0 | P47: 0 | Q47: 0 | R47: 0 | S47: 0 | T47: 0 | U47: 0 | V47: 0 | W47: 0 | X47: 0 | Y47: 0
A48: =A47+10 -> 360 | B48: Итого по торговле и общественному питанию | C48: =SUM(J48:Y48)-L48-P48-Q48 -> 2451039832 | D48: =SUM(D42:D47) -> 662331452 | E48: =IFERROR(((D42*E42)/D48)+((D43*E43)/D48)+((D44*E44)/D48)+((D45*E45)/D48)+((D46*E46)/D48)+((D47*E47)/D48),0) -> 0.20344729 | F48: =SUM(F42:F47) -> 1788708380 | G48: =IFERROR(((F42*G42)/F48)+((F43*G43)/F48)+((F44*G44)/F48)+((F45*G45)/F48)+((F46*G46)/F48)+((F47*G47)/F48),0) -> 0.072583572 | H48: =SUM(H42:H47) -> 2407958143 | I48: =SUM(I42:I47) -> 43081689 | J48: =SUM(J42:J47) -> 471082 | K48: =SUM(K42:K47) -> 0 | L48: =SUM(L42:L47) -> 0 | M48: =SUM(M42:M47) -> 37751570 | N48: =SUM(N42:N47) -> 97313184 | O48: =SUM(O42:O47) -> 1031906657 | ... Y48: =SUM(Y42:Y47) -> 0
B49: Материально-техническое снабжение и сбыт
A50: =A48+10 -> 370 | B50: Физические лица | C50: =SUM(J50:Y50)-L50-P50-Q50 -> 0 | D50: 0 | E50: 0 | F50: 0 | G50: 0 | H50: 0 | I50: 0 | J50: 0 | K50: 0 | L50: 0 | M50: 0 | N50: 0 | O50: =+P50+Q50 -> 0 | P50: 0 | Q50: 0 | R50: 0 | S50: 0 | T50: 0 | U50: 0 | V50: 0 | W50: 0 | X50: 0 | Y50: 0
A51: =A50+10 -> 380 | B51: Государственные предприятия | C51: =SUM(J51:Y51)-L51-P51-Q51 -> 16775066 | D51: 16775066 | E51: 0.2119839 | F51: 0 | G51: 0 | H51: 16775066 | I51: 0 | J51: 0 | K51: 0 | L51: 0 | M51: 0 | N51: 0 | O51: =+P51+Q51 -> 0 | P51: 0 | Q51: 0 | R51: 15247399 | S51: 0 | T51: 0 | U51: 0 | V51: 1527667 | W51: 0 | X51: 0 | Y51: 0
A52: =A51+10 -> 390 | B52: Совместные и иностранные предприятия | C52: =SUM(J52:Y52)-L52-P52-Q52 -> 73169631 | D52: 0 | E52: 0 | F52: 73169631 | G52: 0.086646195 | H52: 73169631 | I52: 0 | J52: 0 | K52: 0 | L52: 0 | M52: 0 | N52: 0 | O52: =+P52+Q52 -> 27496898 | P52: 0 | Q52: 27496898 | R52: 22670161 | S52: 0 | T52: 0 | U52: 0 | V52: 23002572 | W52: 0 | X52: 0 | Y52: 0
A53: =A52+10 -> 400 | B53: Частные товарищества и корпорации | C53: =SUM(J53:Y53)-L53-P53-Q53 -> 221734590 | D53: 144427236 | E53: 0.13668841 | F53: 77307354 | G53: 0.089114408 | H53: 212571288 | I53: 9163302 | J53: 8113 | K53: 0 | L53: 0 | M53: 13191795 | N53: 0 | O53: =+P53+Q53 -> 47611776 | P53: 0 | Q53: 47611776 | R53: 8871446 | S53: 0 | T53: 0 | U53: 0 | V53: 58332848 | W53: 93718612 | X53: 0 | Y53: 0
A54: =A53+10 -> 410 | B54: Правительство | C54: =SUM(J54:Y54)-L54-P54-Q54 -> 0 | D54: 0 | E54: 0 | F54: 0 | G54: 0 | H54: 0 | I54: 0 | J54: 0 | K54: 0 | L54: 0 | M54: 0 | N54: 0 | O54: =+P54+Q54 -> 0 | P54: 0 | Q54: 0 | R54: 0 | S54: 0 | T54: 0 | U54: 0 | V54: 0 | W54: 0 | X54: 0 | Y54: 0
A55: =A54+10 -> 420 | B55: Прочие | C55: =SUM(J55:Y55)-L55-P55-Q55 -> 0 | D55: 0 | E55: 0 | F55: 0 | G55: 0 | H55: 0 | I55: 0 | J55: 0 | K55: 0 | L55: 0 | M55: 0 | N55: 0 | O55: =+P55+Q55 -> 0 | P55: 0 | Q55: 0 | R55: 0 | S55: 0 | T55: 0 | U55: 0 | V55: 0 | W55: 0 | X55: 0 | Y55: 0
A56: =A55+10 -> 430 | B56: Итого по материально-техническому снабжению и сбыту | C56: =SUM(J56:Y56)-L56-P56-Q56 -> 311679287 | D56: =SUM(D50:D55) -> 161202302 | E56: =IFERROR(((D50*E50)/D56)+((D51*E51)/D56)+((D52*E52)/D56)+((D53*E53)/D56)+((D54*E54)/D56)+((D55*E55)/D56),0) -> 0.14452383 | F56: =SUM(F50:F55) -> 150476985 | G56: =IFERROR(((F50*G50)/F56)+((F51*G51)/F56)+((F52*G52)/F56)+((F53*G53)/F56)+((F54*G54)/F56)+((F55*G55)/F56),0) -> 0.087914236 | H56: =SUM(H50:H55) -> 302515985 | I56: =SUM(I50:I55) -> 9163302 | J56: =SUM(J50:J55) -> 8113 | K56: =SUM(K50:K55) -> 0 | L56: =SUM(L50:L55) -> 0 | M56: =SUM(M50:M55) -> 13191795 | N56: =SUM(N50:N55) -> 0 | O56: =SUM(O50:O55) -> 75108674 | ... Y56: =SUM(Y50:Y55) -> 0
B57: Жилищно-коммунальные услуги
A58: =A56+10 -> 440 | B58: Физические лица | C58: =SUM(J58:Y58)-L58-P58-Q58 -> 0 | D58: 0 | E58: 0 | F58: 0 | G58: 0 | H58: 0 | I58: 0 | J58: 0 | K58: 0 | L58: 0 | M58: 0 | N58: 0 | O58: =+P58+Q58 -> 0 | P58: 0 | Q58: 0 | R58: 0 | S58: 0 | T58: 0 | U58: 0 | V58: 0 | W58: 0 | X58: 0 | Y58: 0
A59: =A58+10 -> 450 | B59: Государственные предприятия | C59: =SUM(J59:Y59)-L59-P59-Q59 -> 0 | D59: 0 | E59: 0 | F59: 0 | G59: 0 | H59: 0 | I59: 0 | J59: 0 | K59: 0 | L59: 0 | M59: 0 | N59: 0 | O59: =+P59+Q59 -> 0 | P59: 0 | Q59: 0 | R59: 0 | S59: 0 | T59: 0 | U59: 0 | V59: 0 | W59: 0 | X59: 0 | Y59: 0
A60: =A59+10 -> 460 | B60: Совместные и иностранные предприятия | C60: =SUM(J60:Y60)-L60-P60-Q60 -> 0 | D60: 0 | E60: 0 | F60: 0 | G60: 0 | H60: 0 | I60: 0 | J60: 0 | K60: 0 | L60: 0 | M60: 0 | N60: 0 | O60: =+P60+Q60 -> 0 | P60: 0 | Q60: 0 | R60: 0 | S60: 0 | T60: 0 | U60: 0 | V60: 0 | W60: 0 | X60: 0 | Y60: 0
A61: =A60+10 -> 470 | B61: Частные товарищества и корпорации | C61: =SUM(J61:Y61)-L61-P61-Q61 -> 0 | D61: 0 | E61: 0 | F61: 0 | G61: 0 | H61: 0 | I61: 0 | J61: 0 | K61: 0 | L61: 0 | M61: 0 | N61: 0 | O61: =+P61+Q61 -> 0 | P61: 0 | Q61: 0 | R61: 0 | S61: 0 | T61: 0 | U61: 0 | V61: 0 | W61: 0 | X61: 0 | Y61: 0
A62: =A61+10 -> 480 | B62: Правительство | C62: =SUM(J62:Y62)-L62-P62-Q62 -> 0 | D62: 0 | E62: 0 | F62: 0 | G62: 0 | H62: 0 | I62: 0 | J62: 0 | K62: 0 | L62: 0 | M62: 0 | N62: 0 | O62: =+P62+Q62 -> 0 | P62: 0 | Q62: 0 | R62: 0 | S62: 0 | T62: 0 | U62: 0 | V62: 0 | W62: 0 | X62: 0 | Y62: 0
A63: 485 | B63: Негосударственные некоммерческие организации | C63: =SUM(J63:Y63)-L63-P63-Q63 -> 120092235 | D63: 120092235 | E63: 0.11454722 | F63: 0 | G63: 0 | H63: 113597017 | I63: 6495218 | J63: 698 | K63: 0 | L63: 0 | M63: 0 | N63: 0 | O63: =+P63+Q63 -> 9302 | P63: 0 | Q63: 9302 | R63: 0 | S63: 0 | T63: 0 | U63: 17481960 | V63: 27990708 | W63: 74609567 | X63: 0 | Y63: 0
A64: =A62+10 -> 490 | B64: Прочие | C64: =SUM(J64:Y64)-L64-P64-Q64 -> 0 | D64: 0 | E64: 0 | F64: 0 | G64: 0 | H64: 0 | I64: 0 | J64: 0 | K64: 0 | L64: 0 | M64: 0 | N64: 0 | O64: =+P64+Q64 -> 0 | P64: 0 | Q64: 0 | R64: 0 | S64: 0 | T64: 0 | U64: 0 | V64: 0 | W64: 0 | X64: 0 | Y64: 0
A65: =A64+10 -> 500 | B65: Итого по жилищно-коммунальным услугам | C65: =SUM(J65:Y65)-L65-P65-Q65 -> 120092235 | D65: =SUM(D58:D64) -> 120092235 | E65: =IFERROR(((D58*E58)/D65)+((D59*E59)/D65)+((D60*E60)/D65)+((D61*E61)/D65)+((D62*E62)/D65)+((D63*E63)/D65)+((D64*E64)/D65),0) -> 0.11454722 | F65: =SUM(F58:F64) -> 0 | G65: =IFERROR(((F58*G58)/F65)+((F59*G59)/F65)+((F60*G60)/F65)+((F61*G61)/F65)+((F62*G62)/F65)+((F63*G63)/F65)+((F64*G64)/F65),0) -> 0 | H65: =SUM(H58:H64) -> 113597017 | I65: =SUM(I58:I64) -> 6495218 | J65: =SUM(J58:J64) -> 698 | K65: =SUM(K58:K64) -> 0 | L65: =SUM(L58:L64) -> 0 | M65: =SUM(M58:M64) -> 0 | N65: =SUM(N58:N64) -> 0 | O65: =SUM(O58:O64) -> 9302 | ... Y65: =SUM(Y58:Y64) -> 0
B66: Другие отрасли
A67: =A65+10 -> 510 | B67: Физические лица | C67: =SUM(J67:Y67)-L67-P67-Q67 -> 4259879328 | D67: 4259879328 | E67: 0.13514314 | F67: 0 | G67: 0 | H67: 4248701045 | I67: 11178283 | J67: 3216751 | K67: 0 | L67: 0 | M67: 133920499 | N67: 0 | O67: =+P67+Q67 -> 2961819895 | P67: 2961819895 | Q67: 0 | R67: 0 | S67: 0 | T67: 0 | U67: 6268 | V67: 598929477 | W67: 560118301 | X67: 777492 | Y67: 1090645
A68: =A67+10 -> 520 | B68: Государственные предприятия | C68: =SUM(J68:Y68)-L68-P68-Q68 -> 399831364 | D68: 380323576 | E68: 0.14521508 | F68: 19507788 | G68: 0.055 | H68: 398682028 | I68: 1149336 | J68: 0 | K68: 236525796 | L68: 0 | M68: 56752456 | N68: 0 | O68: =+P68+Q68 -> 27388005 | P68: 0 | Q68: 27388005 | R68: 0 | S68: 0 | T68: 0 | U68: 0 | V68: 75069039 | W68: 1904585 | X68: 2191483 | Y68: 0
A69: =A68+10 -> 530 | B69: Совместные и иностранные предприятия | C69: =SUM(J69:Y69)-L69-P69-Q69 -> 216746582 | D69: 38994912 | E69: 0.2312456 | F69: 177751670 | G69: 0.055035448 | H69: 216746582 | I69: 0 | J69: 0 | K69: 0 | L69: 0 | M69: 46990677 | N69: 0 | O69: =+P69+Q69 -> 1604473 | P69: 0 | Q69: 1604473 | R69: 0 | S69: 0 | T69: 0 | U69: 0 | V69: 167995158 | W69: 156274 | X69: 0 | Y69: 0
A70: =A69+10 -> 540 | B70: Частные товарищества и корпорации | C70: =SUM(J70:Y70)-L70-P70-Q70 -> 1614790249 | D70: 703463377 | E70: 0.14839756 | F70: 911326872 | G70: 0.074405469 | H70: 1555553281 | I70: 59236968 | J70: 134615 | K70: 0 | L70: 0 | M70: 45632104 | N70: 262797 | O70: =+P70+Q70 -> 791324236 | P70: 0 | Q70: 791324236 | R70: 212039116 | S70: 0 | T70: 0 | U70: 7155130 | V70: 389391723 | W70: 155452505 | X70: 6359429 | Y70: 7038594
A71: =A70+10 -> 550 | B71: Центральный банк | C71: =SUM(J71:Y71)-L71-P71-Q71 -> 0 | D71: 0 | E71: 0 | F71: 0 | G71: 0 | H71: 0 | I71: 0 | J71: 0 | K71: 0 | L71: 0 | M71: 0 | N71: 0 | O71: =+P71+Q71 -> 0 | P71: 0 | Q71: 0 | R71: 0 | S71: 0 | T71: 0 | U71: 0 | V71: 0 | W71: 0 | X71: 0 | Y71: 0
A72: =A71+10 -> 560 | B72: Другие банки | C72: =SUM(J72:Y72)-L72-P72-Q72 -> 0 | D72: 0 | E72: 0 | F72: 0 | G72: 0 | H72: 0 | I72: 0 | J72: 0 | K72: 0 | L72: 0 | M72: 0 | N72: 0 | O72: =+P72+Q72 -> 0 | P72: 0 | Q72: 0 | R72: 0 | S72: 0 | T72: 0 | U72: 0 | V72: 0 | W72: 0 | X72: 0 | Y72: 0
A73: =A72+10 -> 570 | B73: Правительство | C73: =SUM(J73:Y73)-L73-P73-Q73 -> 0 | D73: 0 | E73: 0 | F73: 0 | G73: 0 | H73: 0 | I73: 0 | J73: 0 | K73: 0 | L73: 0 | M73: 0 | N73: 0 | O73: =+P73+Q73 -> 0 | P73: 0 | Q73: 0 | R73: 0 | S73: 0 | T73: 0 | U73: 0 | V73: 0 | W73: 0 | X73: 0 | Y73: 0
A74: =A73+10 -> 580 | B74: Небанковские финансовые институты | C74: =SUM(J74:Y74)-L74-P74-Q74 -> 3315923 | D74: 3315923 | E74: 0.19291317 | F74: 0 | G74: 0 | H74: 3315923 | I74: 0 | J74: 127113 | K74: 0 | L74: 0 | M74: 1619962 | N74: 0 | O74: =+P74+Q74 -> 1327848 | P74: 0 | Q74: 1327848 | R74: 189671 | S74: 0 | T74: 0 | U74: 0 | V74: 9098 | W74: 42231 | X74: 0 | Y74: 0
A75: =A74+10 -> 590 | B75: Негосударственные некоммерческие организации | C75: =SUM(J75:Y75)-L75-P75-Q75 -> 0 | D75: 0 | E75: 0.11718828 | F75: 0 | G75: 0 | H75: 0 | I75: 0 | J75: 0 | K75: 0 | L75: 0 | M75: 0 | N75: 0 | O75: =+P75+Q75 -> 0 | P75: 0 | Q75: 0 | R75: 0 | S75: 0 | T75: 0 | U75: 0 | V75: 0 | W75: 0 | X75: 0 | Y75: 0
A76: =A75+10 -> 600 | B76: Бюджетные организации | C76: =SUM(J76:Y76)-L76-P76-Q76 -> 0 | D76: 0 | E76: 0 | F76: 0 | G76: 0 | H76: 0 | I76: 0 | J76: 0 | K76: 0 | L76: 0 | M76: 0 | N76: 0 | O76: =+P76+Q76 -> 0 | P76: 0 | Q76: 0 | R76: 0 | S76: 0 | T76: 0 | U76: 0 | V76: 0 | W76: 0 | X76: 0 | Y76: 0
A77: =A76+10 -> 610 | B77: Прочие | C77: =SUM(J77:Y77)-L77-P77-Q77 -> 0 | D77: 0 | E77: 0 | F77: 0 | G77: 0 | H77: 0 | I77: 0 | J77: 0 | K77: 0 | L77: 0 | M77: 0 | N77: 0 | O77: =+P77+Q77 -> 0 | P77: 0 | Q77: 0 | R77: 0 | S77: 0 | T77: 0 | U77: 0 | V77: 0 | W77: 0 | X77: 0 | Y77: 0
A78: =A77+10 -> 620 | B78: Итого по другим отраслям | C78: =SUM(J78:Y78)-L78-P78-Q78 -> 6494563446 | D78: =SUM(D67:D77) -> 5385977116 | E78: =IFERROR(((D67*E67)/D78)+((D68*E68)/D78)+((D69*E69)/D78)+((D70*E70)/D78)+((D71*E71)/D78)+((D72*E72)/D78)+((D73*E73)/D78)+((D74*E74)/D78)+((D75*E75)/D78)+((D76*E76)/D78)+((D77*E77)/D78),0) -> 0.13831688 | F78: =SUM(F67:F77) -> 1108586330 | G78: =IFERROR(((F67*G67)/F78)+((F68*G68)/F78)+((F69*G69)/F78)+((F70*G70)/F78)+((F71*G71)/F78)+((F72*G72)/F78)+((F73*G73)/F78)+((F74*G74)/F78)+((F75*G75)/F78)+((F76*G76)/F78)+((F77*G77)/F78),0) -> 0.070958186 | H78: =SUM(H67:H77) -> 6422998859 | I78: =SUM(I67:I77) -> 71564587 | J78: =SUM(J67:J77) -> 3478479 | K78: =SUM(K67:K77) -> 236525796 | L78: =SUM(L67:L77) -> 0 | M78: =SUM(M67:M77) -> 284915698 | N78: =SUM(N67:N77) -> 262797 | O78: =SUM(O67:O77) -> 3783464457 | ... Y78: =SUM(Y67:Y77) -> 8129239
B79: Кредитные и лизинговые операции
A80: =A78+10 -> 630 | B80: Физические лица | C80: =SUM(J80:Y80)-L80-P80-Q80 -> 4259879328 | D80: =D9+D17+D26+D34+D42+D50+D58+D67 -> 4259879328 | E80: =IFERROR(((D9*E9)/D80)+((D17*E17)/D80)+((D26*E26)/D80)+((D34*E34)/D80)+((D42*E42)/D80)+((D50*E50)/D80)+((D58*E58)/D80)+((D67*E67)/D80),0) -> 0.13514314 | F80: =F9+F17+F26+F34+F42+F50+F58+F67 -> 0 | G80: =IFERROR(((F9*G9)/F80)+((F17*G17)/F80)+((F26*G26)/F80)+((F34*G34)/F80)+((F42*G42)/F80)+((F50*G50)/F80)+((F58*G58)/F80)+((F67*G67)/F80),0) -> 0 | H80: =H9+H17+H26+H34+H42+H50+H58+H67 -> 4248701045 | I80: =I9+I17+I26+I34+I42+I50+I58+I67 -> 11178283 | J80: =J9+J17+J26+J34+J42+J50+J58+J67 -> 3216751 | K80: =K9+K17+K26+K34+K42+K50+K58+K67 -> 0 | L80: =L9+L17+L26+L34+L42+L50+L58+L67 -> 0 | M80: =M9+M17+M26+M34+M42+M50+M58+M67 -> 133920499 | N80: =N9+N17+N26+N34+N42+N50+N58+N67 -> 0 | O80: =O9+O17+O26+O34+O42+O50+O58+O67 -> 2961819895 | ... Y80: =Y9+Y17+Y26+Y34+Y42+Y50+Y58+Y67 -> 1090645
A81: =A80+10 -> 640 | B81: Государственные предприятия | C81: =SUM(J81:Y81)-L81-P81-Q81 -> 13986301108 | D81: =D10+D18+D27+D35+D43+D51+D59+D68 -> 3779102856 | E81: =IFERROR(((D10*E10)/D81)+((D18*E18)/D81)+((D27*E27)/D81)+((D35*E35)/D81)+((D43*E43)/D81)+((D51*E51)/D81)+((D59*E59)/D81)+((D68*E68)/D81),0) -> 0.15266491 | F81: =F10+F18+F27+F35+F43+F51+F59+F68 -> 10207198252 | G81: =IFERROR(((F10*G10)/F81)+((F18*G18)/F81)+((F27*G27)/F81)+((F35*G35)/F81)+((F43*G43)/F81)+((F51*G51)/F81)+((F59*G59)/F81)+((F68*G68)/F81),0) -> 0.036545968 | H81: =H10+H18+H27+H35+H43+H51+H59+H68 -> 13985151772 | I81: =I10+I18+I27+I35+I43+I51+I59+I68 -> 1149336 | J81: =J10+J18+J27+J35+J43+J51+J59+J68 -> 925716792 | K81: =K10+K18+K27+K35+K43+K51+K59+K68 -> 7319296930 | L81: =L10+L18+L27+L35+L43+L51+L59+L68 -> 6200135127 | M81: =M10+M18+M27+M35+M43+M51+M59+M68 -> 85116503 | N81: =N10+N18+N27+N35+N43+N51+N59+N68 -> 2700513 | O81: =O10+O18+O27+O35+O43+O51+O59+O68 -> 132973642 | ... Y81: =Y10+Y18+Y27+Y35+Y43+Y51+Y59+Y68 -> 2104910799
A82: =A81+10 -> 650 | B82: Совместные и иностранные предприятия | C82: =SUM(J82:Y82)-L82-P82-Q82 -> 7071696766 | D82: =D11+D19+D28+D36+D44+D52+D60+D69 -> 1037907859 | E82: =IFERROR(((D11*E11)/D82)+((D19*E19)/D82)+((D28*E28)/D82)+((D36*E36)/D82)+((D44*E44)/D82)+((D52*E52)/D82)+((D60*E60)/D82)+((D69*E69)/D82),0) -> 0.20406027 | F82: =F11+F19+F28+F36+F44+F52+F60+F69 -> 6033788907 | G82: =IFERROR(((F11*G11)/F82)+((F19*G19)/F82)+((F28*G28)/F82)+((F36*G36)/F82)+((F44*G44)/F82)+((F52*G52)/F82)+((F60*G60)/F82)+((F69*G69)/F82),0) -> 0.063235116 | H82: =H11+H19+H28+H36+H44+H52+H60+H69 -> 6970863923 | I82: =I11+I19+I28+I36+I44+I52+I60+I69 -> 100832843 | J82: =J11+J19+J28+J36+J44+J52+J60+J69 -> 20271520 | K82: =K11+K19+K28+K36+K44+K52+K60+K69 -> 0 | L82: =L11+L19+L28+L36+L44+L52+L60+L69 -> 0 | M82: =M11+M19+M28+M36+M44+M52+M60+M69 -> 91363950 | N82: =N11+N19+N28+N36+N44+N52+N60+N69 -> 126401211 | O82: =O11+O19+O28+O36+O44+O52+O60+O69 -> 1445115816 | ... Y82: =Y11+Y19+Y28+Y36+Y44+Y52+Y60+Y69 -> 624720497
A83: =A82+10 -> 660 | B83: Частные товарищества и корпорации | C83: =SUM(J83:Y83)-L83-P83-Q83 -> 17480739187 | D83: =D12+D20+D29+D37+D45+D53+D61+D70 -> 5777347747 | E83: =IFERROR(((D12*E12)/D83)+((D20*E20)/D83)+((D29*E29)/D83)+((D37*E37)/D83)+((D45*E45)/D83)+((D53*E53)/D83)+((D61*E61)/D83)+((D70*E70)/D83),0) -> 0.17771431 | F83: =F12+F20+F29+F37+F45+F53+F61+F70 -> 11703391440 | G83: =IFERROR(((F12*G12)/F83)+((F20*G20)/F83)+((F29*G29)/F83)+((F37*G37)/F83)+((F45*G45)/F83)+((F53*G53)/F83)+((F61*G61)/F83)+((F70*G70)/F83),0) -> 0.067442256 | H83: =H12+H20+H29+H37+H45+H53+H61+H70 -> 17010953416 | I83: =I12+I20+I29+I37+I45+I53+I61+I70 -> 469785771 | J83: =J12+J20+J29+J37+J45+J53+J61+J70 -> 1971478 | K83: =K12+K20+K29+K37+K45+K53+K61+K70 -> 0 | L83: =L12+L20+L29+L37+L45+L53+L61+L70 -> 0 | M83: =M12+M20+M29+M37+M45+M53+M61+M70 -> 294397713 | N83: =N12+N20+N29+N37+N45+N53+N61+N70 -> 121890434 | O83: =O12+O20+O29+O37+O45+O53+O61+O70 -> 5482681105 | ... Y83: =Y12+Y20+Y29+Y37+Y45+Y53+Y61+Y70 -> 572965222
A84: =A83+10 -> 670 | B84: Фермерское хозяйство | C84: =SUM(J84:Y84)-L84-P84-Q84 -> 225782941 | D84: =D21 -> 95332387 | E84: =IFERROR(E21,0) -> 0.20482658 | F84: =F21 -> 130450554 | G84: =IFERROR(G21,0) -> 0.063385128 | H84: =H21 -> 207991833 | I84: =I21 -> 17791108 | J84: =J21 -> 0 | K84: =K21 -> 0 | L84: =L21 -> 0 | M84: =M21 -> 4137819 | N84: =N21 -> 0 | O84: =O21 -> 91963803 | ... Y84: =Y21 -> 0
A85: =A84+10 -> 680 | B85: Другие банки | C85: =SUM(J85:Y85)-L85-P85-Q85 -> 0 | D85: =D72 -> 0 | E85: =E72 -> 0 | F85: =F72 -> 0 | G85: =G72 -> 0 | H85: =H72 -> 0 | I85: =I72 -> 0 | J85: =J72 -> 0 | K85: =K72 -> 0 | ... Y85: =Y72 -> 0
A86: =A85+10 -> 690 | B86: Центральный банк | C86: =SUM(J86:Y86)-L86-P86-Q86 -> 0 | D86: =D71 -> 0 | E86: =E71 -> 0 | F86: =F71 -> 0 | G86: =G71 -> 0 | H86: =H71 -> 0 | I86: =I71 -> 0 | J86: =J71 -> 0 | K86: =K71 -> 0 | ... Y86: =Y71 -> 0
A87: =A86+10 -> 700 | B87: Правительство | C87: =SUM(J87:Y87)-L87-P87-Q87 -> 0 | D87: =D13+D22+D30+D38+D46+D54+D62+D73 -> 0 | E87: =IFERROR(((D13*E13)/D87)+((D22*E22)/D87)+((D30*E30)/D87)+((D38*E38)/D87)+((D46*E46)/D87)+((D54*E54)/D87)+((D62*E62)/D87)+((D73*E73)/D87),0) -> 0 | F87: =F13+F22+F30+F38+F46+F54+F62+F73 -> 0 | G87: =IFERROR(((F13*G13)/F87)+((F22*G22)/F87)+((F30*G30)/F87)+((F38*G38)/F87)+((F46*G46)/F87)+((F54*G54)/F87)+((F62*G62)/F87)+((F73*G73)/F87),0) -> 0 | H87: =H13+H22+H30+H38+H46+H54+H62+H73 -> 0 | I87: =I13+I22+I30+I38+I46+I54+I62+I73 -> 0 | J87: =J13+J22+J30+J38+J46+J54+J62+J73 -> 0 | K87: =K13+K22+K30+K38+K46+K54+K62+K73 -> 0 | L87: =L13+L22+L30+L38+L46+L54+L62+L73 -> 0 | M87: =M13+M22+M30+M38+M46+M54+M62+M73 -> 0 | N87: =N13+N22+N30+N38+N46+N54+N62+N73 -> 0 | O87: =O13+O22+O30+O38+O46+O54+O62+O73 -> 0 | ... Y87: =Y13+Y22+Y30+Y38+Y46+Y54+Y62+Y73 -> 0
A88: =A87+10 -> 710 | B88: Небанковские финансовые институты | C88: =SUM(J88:Y88)-L88-P88-Q88 -> 3315923 | D88: =D74 -> 3315923 | E88: =E74 -> 0.19291317 | F88: =F74 -> 0 | G88: =G74 -> 0 | H88: =H74 -> 3315923 | I88: =I74 -> 0 | J88: =J74 -> 127113 | K88: =K74 -> 0 | ... Y88: =Y74 -> 0
A89: =A88+10 -> 720 | B89: Негосударственные некоммерческие организации | C89: =SUM(J89:Y89)-L89-P89-Q89 -> 120092235 | D89: =+D63+D75 -> 120092235 | E89: =IFERROR(((D75*E75)/D78)+((D63*E63)/D65),0) -> 0.11454722 | F89: =+F63+F75 -> 0 | G89: =IFERROR(((F75*G75)/F78)+((F63*G63)/F65),0) -> 0 | H89: =+H63+H75 -> 113597017 | I89: =+I63+I75 -> 6495218 | J89: =+J63+J75 -> 698 | K89: =+K63+K75 -> 0 | L89: =+L63+L75 -> 0 | M89: =+M63+M75 -> 0 | N89: =+N63+N75 -> 0 | O89: =+O63+O75 -> 9302 | ... Y89: =+Y63+Y75 -> 0
A90: =A89+10 -> 730 | B90: Бюджетные организации | C90: =SUM(J90:Y90)-L90-P90-Q90 -> 0 | D90: =D76 -> 0 | E90: =E76 -> 0 | F90: =F76 -> 0 | G90: =G76 -> 0 | H90: =H76 -> 0 | I90: =I76 -> 0 | J90: =J76 -> 0 | K90: =K76 -> 0 | ... Y90: =Y76 -> 0
A91: =A90+10 -> 740 | B91: Прочие | C91: =SUM(J91:Y91)-L91-P91-Q91 -> 0 | D91: =D14+D23+D31+D39+D47+D55+D64+D77 -> 0 | E91: =IFERROR(((D14*E14)/D91)+((D23*E23)/D91)+((D31*E31)/D91)+((D39*E39)/D91)+((D47*E47)/D91)+((D55*E55)/D91)+((D64*E64)/D91)+((D77*E77)/D91),0) -> 0 | F91: =F14+F23+F31+F39+F47+F55+F64+F77 -> 0 | G91: =IFERROR(((F14*G14)/F91)+((F23*G23)/F91)+((F31*G31)/F91)+((F39*G39)/F91)+((F47*G47)/F91)+((F55*G55)/F91)+((F64*G64)/F91)+((F77*G77)/F91),0) -> 0 | H91: =H14+H23+H31+H39+H47+H55+H64+H77 -> 0 | I91: =I14+I23+I31+I39+I47+I55+I64+I77 -> 0 | J91: =J14+J23+J31+J39+J47+J55+J64+J77 -> 0 | K91: =K14+K23+K31+K39+K47+K55+K64+K77 -> 0 | L91: =L14+L23+L31+L39+L47+L55+L64+L77 -> 0 | M91: =M14+M23+M31+M39+M47+M55+M64+M77 -> 0 | N91: =N14+N23+N31+N39+N47+N55+N64+N77 -> 0 | O91: =O14+O23+O31+O39+O47+O55+O64+O77 -> 0 | ... Y91: =Y14+Y23+Y31+Y39+Y47+Y55+Y64+Y77 -> 0
A92: =A91+10 -> 750 | B92: Итого кредита и лизинга | C92: =SUM(J92:Y92)-L92-P92-Q92 -> 43147807488 | D92: =SUM(D80:D91) -> 15072978335 | E92: =IFERROR(((D80*E80)/D92)+((D81*E81)/D92)+((D82*E82)/D92)+((D83*E83)/D92)+((D84*E84)/D92)+((D85*E85)/D92)+((D86*E86)/D92)+((D87*E87)/D92)+((D88*E88)/D92)+((D89*E89)/D92)+((D90*E90)/D92)+((D91*E91)/D92),0) -> 0.16088828 | F92: =SUM(F80:F91) -> 28074829153 | G92: =IFERROR(((F80*G80)/F92)+((F81*G81)/F92)+((F82*G82)/F92)+((F83*G83)/F92)+((F84*G84)/F92)+((F85*G85)/F92)+((F86*G86)/F92)+((F87*G87)/F92)+((F88*G88)/F92)+((F89*G89)/F92)+((F90*G90)/F92)+((F91*G91)/F92),0) -> 0.055286215 | H92: =SUM(H80:H91) -> 42540574929 | I92: =SUM(I80:I91) -> 607232559 | J92: =SUM(J80:J91) -> 951304352 | K92: =SUM(K80:K91) -> 7319296930 | L92: =SUM(L80:L91) -> 6200135127 | M92: =SUM(M80:M91) -> 610556446 | N92: =SUM(N80:N91) -> 250992158 | O92: =SUM(O80:O91) -> 10115891411 | ... Y92: =SUM(Y80:Y91) -> 3303687163
B95: Подпись Председателя правления:
B97: Подпись Главного Бухгалтера:
C99: =+[8]Balance!$C$24 -> 43147807488
C100: =+C92-C99 -> 0

Sheet Aging Analysis
A1: АНАЛИЗ ПРОСРОЧЕННЫХ КРЕДИТОВ И ФИНАНСОВОГО ЛИЗИНГА К ПОЛУЧЕНИЮ | X1: Таблица-9
B3: =+'Asset quality'!B3 -> "Ўзсаноатқурилишбанк" АТБ | T3: =+'Asset quality'!P3 -> 44560 | X3: тыс. сум
A4: № | B4: Характеристики | C4: Всего задолжность по кредитам | D4: % | E4: Реструктуризированные кредиты | F4: % | G4: В ходе судебного разбирательства | H4: % | I4: Просроченная задолжность | K4: % | L4: в том числе, анализ временной задолженности
L5: 1-30 дней | N5: 31-60 дней | P5: 61-90 дней | R5: 91-180 дней | T5: 181-365 дней | V5: 366-730 дней | X5: Свыше 2 лет
I6: основной долг | J6: процент | L6: основной долг | M6: процент | N6: основной долг | O6: процент | P6: основной долг | Q6: процент | R6: основной долг | S6: процент | T6: основной долг | U6: процент | V6: основной долг | W6: процент | X6: основной долг | Y6: процент
B7: (А) | C7: (Б) | D7: (В) | E7: (Г) | F7: (Д) | G7: (Е) | H7: (Ж) | I7: (З) | J7: (З1) | K7: (И) | L7: (К) | M7: (К1) | N7: (Л) | O7: (Л1) | P7: (М) | Q7: (М1) | R7: (Н) | S7: (Н1) | T7: (О) | U7: (О1) | V7: (П) | W7: (П1) | X7: (Р) | Y7: (Р1)
B8: По типу клиента
A9: 1 | B9: Центральный банк | C9: =+'Loans Receivable'!C86 -> 0 | D9: =IF(C$22=0,"",C9/C$22) -> 0 | E9: 0 | F9: =IF(E$22=0,"",E9/E$22) -> 0 | G9: 0 | H9: =IF($G$22=0,"",G9/$G$22) -> 0 | I9: =+L9+N9+P9+R9+T9+V9+X9 -> 0 | J9: =+M9+O9+T9+S9+U9+W9+Y9 -> 0 | K9: =IF($Z$22=0,"",Z9/$Z$22) -> 0 | Z9: =+I9+J9 -> 0
A10: 2 | B10: Другие банки | C10: =+'Loans Receivable'!C85 -> 0 | D10: =IF(C$22=0,"",C10/C$22) -> 0 | E10: 0 | F10: =IF(E$22=0,"",E10/E$22) -> 0 | G10: 0 | H10: =IF($G$22=0,"",G10/$G$22) -> 0 | I10: =+L10+N10+P10+R10+T10+V10+X10 -> 0 | J10: =+M10+O10+Q10+S10+U10+W10+Y10 -> 0 | K10: =IF($Z$22=0,"",Z10/$Z$22) -> 0 | Z10: =+I10+J10 -> 0
A11: 3 | B11: Правительство | C11: =+'Loans Receivable'!C87 -> 0 | D11: =IF(C$22=0,"",C11/C$22) -> 0 | E11: 0 | F11: =IF(E$22=0,"",E11/E$22) -> 0 | G11: 0 | H11: =IF($G$22=0,"",G11/$G$22) -> 0 | I11: =+L11+N11+P11+R11+T11+V11+X11 -> 0 | J11: =+M11+O11+Q11+S11+U11+W11+Y11 -> 0 | K11: =IF($Z$22=0,"",Z11/$Z$22) -> 0 | Z11: =+I11+J11 -> 0
A12: 4 | B12: Физические лица | C12: =+'Loans Receivable'!C80 -> 4259879328 | D12: =IF(C$22=0,"",C12/C$22) -> 0.098727597 | E12: 14416216 | F12: =IF(E$22=0,"",E12/E$22) -> 0.04009696 | G12: 1010074 | H12: =IF($G$22=0,"",G12/$G$22) -> 0.52860402 | I12: =+L12+N12+P12+R12+T12+V12+X12 -> 41545823 | J12: =+M12+O12+Q12+S12+U12+W12+Y12 -> 14225284 | K12: =IF($Z$22=0,"",Z12/$Z$22) -> 0.12602418 | L12: 2422411 | M12: 4376870 | N12: 3093690 | O12: 441474 | P12: 3657488 | Q12: 581374 | R12: 8089091 | S12: 1243620 | T12: 21833121 | U12: 5717566 | V12: 2450022 | W12: 1864380 | X12: 0 | Y12: 0 | Z12: =+I12+J12 -> 55771107
A13: 5 | B13: Государственные предприятия | C13: =+'Loans Receivable'!C81 -> 13986301108 | D13: =IF(C$22=0,"",C13/C$22) -> 0.32414859 | E13: 15200503 | F13: =IF(E$22=0,"",E13/E$22) -> 0.042278359 | G13: 0 | H13: =IF($G$22=0,"",G13/$G$22) -> 0 | I13: =+L13+N13+P13+R13+T13+V13+X13 -> 3352746 | J13: =+M13+O13+Q13+S13+U13+W13+Y13 -> 206207 | K13: =IF($Z$22=0,"",Z13/$Z$22) -> 0.0080420515 | L13: 638933 | M13: 206207 | N13: 0 | O13: 0 | P13: 2191481 | Q13: 0 | R13: 0 | S13: 0 | T13: 522332 | U13: 0 | V13: 0 | W13: 0 | X13: 0 | Y13: 0 | Z13: =+I13+J13 -> 3558953
A14: 6 | B14: Совместные и иностранные предприятия | C14: =+'Loans Receivable'!C82 -> 7071696766 | D14: =IF(C$22=0,"",C14/C$22) -> 0.1638947 | E14: 55656225 | F14: =IF(E$22=0,"",E14/E$22) -> 0.15480105 | G14: 0 | H14: =IF($G$22=0,"",G14/$G$22) -> 0 | I14: =+L14+N14+P14+R14+T14+V14+X14 -> 20549450 | J14: =+M14+O14+Q14+S14+U14+W14+Y14 -> 14767210 | K14: =IF($Z$22=0,"",Z14/$Z$22) -> 0.07980392 | L14: 1486 | M14: 14696435 | N14: 9162150 | O14: 1255 | P14: 10754210 | Q14: 0 | R14: 290992 | S14: 69520 | T14: 340612 | U14: 0 | V14: 0 | W14: 0 | X14: 0 | Y14: 0 | Z14: =+I14+J14 -> 35316660
A15: 7 | B15: Частные товарищества и корпорации | C15: =+'Loans Receivable'!C83 -> 17480739187 | D15: =IF(C$22=0,"",C15/C$22) -> 0.40513621 | E15: 265749354 | F15: =IF(E$22=0,"",E15/E$22) -> 0.73914966 | G15: 817058 | H15: =IF($G$22=0,"",G15/$G$22) -> 0.42759257 | I15: =+L15+N15+P15+R15+T15+V15+X15 -> 294908933 | J15: =+M15+O15+Q15+S15+U15+W15+Y15 -> 33659713 | K15: =IF($Z$22=0,"",Z15/$Z$22) -> 0.74245599 | L15: 43298462 | M15: 15922447 | N15: 16434605 | O15: 2440215 | P15: 86797188 | Q15: 6704140 | R15: 44734418 | S15: 3534306 | T15: 98971352 | U15: 4890801 | V15: 4672908 | W15: 167804 | X15: 0 | Y15: 0 | Z15: =+I15+J15 -> 328568646
A16: 8 | B16: Фермерское хозяйство | C16: =+'Loans Receivable'!C84 -> 225782941 | D16: =IF(C$22=0,"",C16/C$22) -> 0.005232779 | E16: 4938596 | F16: =IF(E$22=0,"",E16/E$22) -> 0.013736107 | G16: 83701 | H16: =IF($G$22=0,"",G16/$G$22) -> 0.043803409 | I16: =+L16+N16+P16+R16+T16+V16+X16 -> 9546698 | J16: =+M16+O16+Q16+S16+U16+W16+Y16 -> 758176 | K16: =IF($Z$22=0,"",Z16/$Z$22) -> 0.023285592 | L16: 1911952 | M16: 143591 | N16: 2252 | O16: 0 | P16: 1366575 | Q16: 209274 | R16: 4304889 | S16: 379826 | T16: 1961030 | U16: 25485 | V16: 0 | W16: 0 | X16: 0 | Y16: 0 | Z16: =+I16+J16 -> 10304874
A17: 9 | B17: Небанковские финансовые институты | C17: =+'Loans Receivable'!C88 -> 3315923 | D17: =IF(C$22=0,"",C17/C$22) -> 7.6850324e-05 | E17: 294767 | F17: =IF(E$22=0,"",E17/E$22) -> 0.00081985873 | G17: 0 | H17: =IF($G$22=0,"",G17/$G$22) -> 0 | I17: =+L17+N17+P17+R17+T17+V17+X17 -> 0 | J17: =+M17+O17+Q17+S17+U17+W17+Y17 -> 0 | K17: =IF($Z$22=0,"",Z17/$Z$22) -> 0 | L17: 0 | M17: 0 | N17: 0 | O17: 0 | P17: 0 | Q17: 0 | R17: 0 | S17: 0 | T17: 0 | U17: 0 | V17: 0 | W17: 0 | X17: 0 | Y17: 0 | Z17: =+I17+J17 -> 0
A18: 10 | B18: Негосударственные некоммерческие организации | C18: =+'Loans Receivable'!C89 -> 120092235 | D18: =IF(C$22=0,"",C18/C$22) -> 0.0027832755 | E18: 3278233 | F18: =IF(E$22=0,"",E18/E$22) -> 0.0091180082 | G18: 0 | H18: =IF($G$22=0,"",G18/$G$22) -> 0 | I18: =+L18+N18+P18+R18+T18+V18+X18 -> 4972783 | J18: =+M18+O18+Q18+S18+U18+W18+Y18 -> 4049901 | K18: =IF($Z$22=0,"",Z18/$Z$22) -> 0.020388269 | L18: 99097 | M18: 1797825 | N18: 56414 | O18: 91361 | P18: 183848 | Q18: 187415 | R18: 391544 | S18: 327523 | T18: 1914340 | U18: 735577 | V18: 2327540 | W18: 910200 | X18: 0 | Y18: 0 | Z18: =+I18+J18 -> 9022684
A19: 11 | B19: Бюджетные организации | C19: =+'Loans Receivable'!C90 -> 0 | D19: =IF(C$22=0,"",C19/C$22) -> 0 | E19: 0 | F19: =IF(E$22=0,"",E19/E$22) -> 0 | G19: 0 | H19: =IF($G$22=0,"",G19/$G$22) -> 0 | I19: =+L19+N19+P19+R19+T19+V19+X19 -> 0 | J19: =+M19+O19+Q19+S19+U19+W19+Y19 -> 0 | K19: =IF($Z$22=0,"",Z19/$Z$22) -> 0 | L19: 0 | M19: 0 | N19: 0 | O19: 0 | P19: 0 | Q19: 0 | R19: 0 | S19: 0 | T19: 0 | U19: 0 | V19: 0 | W19: 0 | X19: 0 | Y19: 0 | Z19: =+I19+J19 -> 0
A20: 12 | B20: Прочие | C20: =+'Loans Receivable'!C91 -> 0 | D20: =IF(C$22=0,"",C20/C$22) -> 0 | E20: 0 | F20: =IF(E$22=0,"",E20/E$22) -> 0 | G20: 0 | H20: =IF($G$22=0,"",G20/$G$22) -> 0 | I20: =+L20+N20+P20+R20+T20+V20+X20 -> 0 | J20: =+M20+O20+Q20+S20+U20+W20+Y20 -> 0 | K20: =IF($Z$22=0,"",Z20/$Z$22) -> 0 | L20: 0 | M20: 0 | O20: 0 | P20: 0 | Q20: 0 | R20: 0 | S20: 0 | T20: 0 | U20: 0 | V20: 0 | W20: 0 | X20: 0 | Y20: 0 | Z20: =+I20+J20 -> 0
Z21: =+I21+J21 -> 0
A22: 13 | B22: Итого кредита и лизинга | C22: =SUM(C9:C20) -> 43147807488 | D22: =IF(C$22=0,"",C22/C$22) -> 1 | E22: =SUM(E9:E20) -> 359533894 | F22: =IF(E$22=0,"",E22/E$22) -> 1 | G22: =SUM(G9:G20) -> 1910833 | H22: =IF($G$22=0,"",G22/$G$22) -> 1 | I22: =SUM(I9:I20) -> 374876433 | J22: =SUM(J9:J20) -> 67666491 | K22: =IF($Z$22=0,"",Z22/$Z$22) -> 1 | L22: =SUM(L9:L20) -> 48372341 | M22: =SUM(M9:M20) -> 37143375 | N22: =SUM(N9:N20) -> 28749111 | O22: =SUM(O9:O20) -> 2974305 | P22: =SUM(P9:P20) -> 104950790 | Q22: =SUM(Q9:Q20) -> 7682203 | R22: =SUM(R9:R20) -> 57810934 | S22: =SUM(S9:S20) -> 5554795 | ... Y22: =SUM(Y9:Y20) -> 0 | Z22: =+I22+J22 -> 442542924
Z23: =+I23+J23 -> 0
B24: По сектору экономики | F24: =IF(E$22=0,"",E24/E$22) -> 0 | Z24: =+I24+J24 -> 0
A25: 14 | B25: Промышленность | C25: =+'Loans Receivable'!C15 -> 26339734494 | D25: =IF(C$34=0,"",C25/C$34) -> 0.6104536 | E25: 162697434 | F25: =IF($E$34=0,"",E25/$E$34) -> 0.45252322 | G25: 0 | H25: =IF($G$34=0,"",G25/$G$34) -> 0 | I25: =+L25+N25+P25+R25+T25+V25+X25 -> 142787007 | J25: =+M25+O25+Q25+S25+U25+W25+Y25 -> 28489847 | K25: =IF($Z$34=0,"",Z25/$Z$34) -> 0.38702879 | L25: 19327454 | M25: 21645443 | N25: 20399655 | O25: 1712079 | P25: 42166720 | Q25: 3458672 | R25: 17697899 | S25: 416002 | T25: 40459007 | U25: 1257651 | V25: 2736272 | W25: 0 | X25: 0 | Y25: 0 | Z25: =+I25+J25 -> 171276854
A26: 15 | B26: Сельское хозяйство | C26: =+'Loans Receivable'!C24 -> 3143324750 | D26: =IF(C$34=0,"",C26/C$34) -> 0.072850162 | E26: 62157529 | F26: =IF($E$34=0,"",E26/$E$34) -> 0.17288364 | G26: 345558 | H26: =IF($G$34=0,"",G26/$G$34) -> 0.18084155 | I26: =+L26+N26+P26+R26+T26+V26+X26 -> 59650799 | J26: =+M26+O26+Q26+S26+U26+W26+Y26 -> 6430208 | K26: =IF($Z$34=0,"",Z26/$Z$34) -> 0.14932112 | L26: 8199895 | M26: 3230304 | N26: 1118128 | O26: 318527 | P26: 25939037 | Q26: 740384 | R26: 14910570 | S26: 1870108 | T26: 8991357 | U26: 270885 | V26: 491812 | W26: 0 | X26: 0 | Y26: 0 | Z26: =+I26+J26 -> 66081007
A27: 16 | B27: Транспорт и коммуникации | C27: =+'Loans Receivable'!C32 -> 3463692914 | D27: =IF(C$34=0,"",C27/C$34) -> 0.080275062 | E27: 47628932 | F27: =IF($E$34=0,"",E27/$E$34) -> 0.13247411 | G27: 0 | H27: =IF($G$34=0,"",G27/$G$34) -> 0 | I27: =+L27+N27+P27+R27+T27+V27+X27 -> 15859341 | J27: =+M27+O27+Q27+S27+U27+W27+Y27 -> 2086690 | K27: =IF($Z$34=0,"",Z27/$Z$34) -> 0.040552069 | L27: 2158501 | M27: 98797 | N27: 1726885 | O27: 161400 | P27: 3508592 | Q27: 101404 | R27: 2108367 | S27: 196784 | T27: 6356996 | U27: 1528305 | V27: 0 | W27: 0 | X27: 0 | Y27: 0 | Z27: =+I27+J27 -> 17946031
A28: 17 | B28: Строительство | C28: =+'Loans Receivable'!C40 -> 823680530 | D28: =IF(C$34=0,"",C28/C$34) -> 0.019089742 | E28: 12457482 | F28: =IF($E$34=0,"",E28/$E$34) -> 0.034648978 | G28: 555201 | H28: =IF($G$34=0,"",G28/$G$34) -> 0.29055443 | I28: =+L28+N28+P28+R28+T28+V28+X28 -> 24888555 | J28: =+M28+O28+Q28+S28+U28+W28+Y28 -> 2994552 | K28: =IF($Z$34=0,"",Z28/$Z$34) -> 0.063006559 | L28: 976461 | M28: 839521 | N28: 1308333 | O28: 235345 | P28: 12806005 | Q28: 1542179 | R28: 3540259 | S28: 296169 | T28: 6129374 | U28: 67367 | V28: 128123 | W28: 13971 | X28: 0 | Y28: 0 | Z28: =+I28+J28 -> 27883107
A29: 18 | B29: Торговля и общественное питание | C29: =+'Loans Receivable'!C48 -> 2451039832 | D29: =IF(C$34=0,"",C29/C$34) -> 0.056805663 | E29: 37380930 | F29: =IF($E$34=0,"",E29/$E$34) -> 0.10397053 | G29: 0 | H29: =IF($G$34=0,"",G29/$G$34) -> 0 | I29: =+L29+N29+P29+R29+T29+V29+X29 -> 51982203 | J29: =+M29+O29+Q29+S29+U29+W29+Y29 -> 5151526 | K29: =IF($Z$34=0,"",Z29/$Z$34) -> 0.12910325 | L29: 13432825 | M29: 2609801 | N29: 941227 | O29: 5156 | P29: 11268177 | Q29: 285755 | R29: 6249392 | S29: 742580 | T29: 19129031 | U29: 1354401 | V29: 961551 | W29: 153833 | X29: 0 | Y29: 0 | Z29: =+I29+J29 -> 57133729
A30: 19 | B30: Материально-техническое снабжение и сбыт | C30: =+'Loans Receivable'!C56 -> 311679287 | D30: =IF(C$34=0,"",C30/C$34) -> 0.0072235255 | E30: 2461485 | F30: =IF($E$34=0,"",E30/$E$34) -> 0.0068463225 | G30: 0 | H30: =IF($G$34=0,"",G30/$G$34) -> 0 | I30: =+L30+N30+P30+R30+T30+V30+X30 -> 4711401 | J30: =+M30+O30+Q30+S30+U30+W30+Y30 -> 274514 | K30: =IF($Z$34=0,"",Z30/$Z$34) -> 0.011266512 | L30: 10179 | M30: 10824 | N30: 0 | O30: 0 | P30: 213196 | Q30: 117712 | R30: 1437544 | S30: 145978 | T30: 3050482 | U30: 0 | V30: 0 | W30: 0 | X30: 0 | Y30: 0 | Z30: =+I30+J30 -> 4985915
A31: 20 | B31: Жилищно-коммунальные услуги | C31: =+'Loans Receivable'!C65 -> 120092235 | D31: =IF(C$34=0,"",C31/C$34) -> 0.0027832755 | E31: 3278233 | F31: =IF($E$34=0,"",E31/$E$34) -> 0.0091180082 | G31: 0 | H31: =IF($G$34=0,"",G31/$G$34) -> 0 | I31: =+L31+N31+P31+R31+T31+V31+X31 -> 4972783 | J31: =+M31+O31+Q31+S31+U31+W31+Y31 -> 4049901 | K31: =IF($Z$34=0,"",Z31/$Z$34) -> 0.020388269 | L31: 99097 | M31: 1797825 | N31: 56414 | O31: 91361 | P31: 183848 | Q31: 187415 | R31: 391544 | S31: 327523 | T31: 1914340 | U31: 735577 | V31: 2327540 | W31: 910200 | X31: 0 | Y31: 0 | Z31: =+I31+J31 -> 9022684
A32: 21 | B32: Другие сектора | C32: =+'Loans Receivable'!C78 -> 6494563446 | D32: =IF(C$34=0,"",C32/C$34) -> 0.15051897 | E32: 31471869 | F32: =IF($E$34=0,"",E32/$E$34) -> 0.087535194 | G32: 1010074 | H32: =IF($G$34=0,"",G32/$G$34) -> 0.52860402 | I32: =+L32+N32+P32+R32+T32+V32+X32 -> 70024344 | J32: =+M32+O32+Q32+S32+U32+W32+Y32 -> 18189253 | K32: =IF($Z$34=0,"",Z32/$Z$34) -> 0.19933343 | L32: 4167929 | M32: 6910860 | N32: 3198469 | O32: 450437 | P32: 8865215 | Q32: 1248682 | R32: 11475359 | S32: 1559651 | T32: 39512200 | U32: 6155243 | V32: 2805172 | W32: 1864380 | X32: 0 | Y32: 0 | Z32: =+I32+J32 -> 88213597
Z33: =+I33+J33 -> 0
A34: 22 | B34: Итого кредита и лизинга | C34: =SUM(C25:C32) -> 43147807488 | D34: =IF(C$34=0,"",C34/C$34) -> 1 | E34: =SUM(E25:E32) -> 359533894 | F34: =IF($E$34=0,"",E34/$E$34) -> 1 | G34: =SUM(G25:G32) -> 1910833 | H34: =IF($G$34=0,"",G34/$G$34) -> 1 | I34: =SUM(I25:I32) -> 374876433 | J34: =SUM(J25:J32) -> 67666491 | K34: =IF($Z$34=0,"",Z34/$Z$34) -> 1 | L34: =SUM(L25:L32) -> 48372341 | M34: =SUM(M25:M32) -> 37143375 | N34: =SUM(N25:N32) -> 28749111 | O34: =SUM(O25:O32) -> 2974305 | P34: =SUM(P25:P32) -> 104950790 | Q34: =SUM(Q25:Q32) -> 7682203 | R34: =SUM(R25:R32) -> 57810934 | S34: =SUM(S25:S32) -> 5554795 | ... Y34: =SUM(Y25:Y32) -> 0 | Z34: =+I34+J34 -> 442542924
B37: Подпись Председателя правления:
B39: Подпись Главного Бухгалтера:

Sheet Asset Classification
A1: ОТЧЕТ О КЛАССИФИКАЦИИ АКТИВОВ ПО СТЕПЕНИ РИСКА | W1: Таблица-10
B2: =+'Asset quality'!B3 -> "Ўзсаноатқурилишбанк" АТБ | U2: =+'Asset quality'!P3 -> 44560 | Z2: тыс. сум
A3: № | B3: Статьи баланса | C3: Общая сумма | D3: из них, в иностранной валюте (в экв. в сумах) | E3: Стандартные | F3: из них, в иностранной валюте (в экв. в сумах) | G3: Общие резервы (1%) | H3: из них, в иностранной валюте (в экв. в сумах) | I3: Субстандартные | J3: из них, в иностранной валюте (в экв. в сумах) | K3: Специальные резервы (мин 10%) | L3: из них, в иностранной валюте (в экв. в сумах) | M3: Неудовлетворительные | N3: из них, в иностранной валюте (в экв. в сумах) | O3: Специальные резервы (мин 25%) | P3: из них, в иностранной валюте (в экв. в сумах) | Q3: Сомнительные | R3: из них, в иностранной валюте (в экв. в сумах) | S3: Специальные резервы (мин 50%) | T3: из них, в иностранной валюте (в экв. в сумах) | U3: Безнадежные | V3: из них, в иностранной валюте (в экв. в сумах) | W3: Специальные резервы (100%) | X3: из них, в иностранной валюте (в экв. в сумах) | Y3: Совокупная сумма специальных резервов | Z3: из них, в иностранной валюте (в экв. в сумах) | AA3: списанные кредиты за баланс в отчётном месяце | AB3: возврат списанных кредитов в отчётном месяце
A4: (А) | B4: (Б) | C4: (В) | D4: (В1) | E4: (Г) | F4: (Г1) | G4: (Д) | H4: (Д1) | I4: (Е) | J4: (Е1) | K4: (Ж) | L4: (Ж1) | M4: (З) | N4: (З1) | O4: (И) | P4: (И1) | Q4: (К) | R4: (К1) | S4: (Л) | T4: (Л1) | U4: (М) | V4: (М1) | W4: (Н) | X4: (Н1) | Y4: О=Ж+И+Л+Н | Z4: (О1)=(Ж1)+(И1)+(Л1)+(Н1) | AA4: П | AB4: Р
B5: По типу клиента
A6: 1 | B6: Центральный банк | C6: =E6+I6+M6+Q6+U6 -> 0 | D6: =F6+J6+N6+R6+V6 -> 0 | Y6: =+W6+S6+O6+K6 -> 0 | Z6: =+X6+T6+P6+L6 -> 0 | AA6: 0 | AB6: 0 | AC6: =+'Aging Analysis'!C9 -> 0
B7: из них необеспеченные | C7: =E7+I7+M7+Q7+U7 -> 0 | D7: =F7+J7+N7+R7+V7 -> 0 | Y7: =+W7+S7+O7+K7 -> 0 | Z7: =+X7+T7+P7+L7 -> 0 | AA7: 0 | AB7: 0
A8: 2 | B8: Другие банки | C8: =E8+I8+M8+Q8+U8 -> 0 | D8: =F8+J8+N8+R8+V8 -> 0 | Y8: =+W8+S8+O8+K8 -> 0 | Z8: =+X8+T8+P8+L8 -> 0 | AA8: 0 | AB8: 0 | AC8: =+'Aging Analysis'!C10 -> 0
B9: из них необеспеченные | C9: =E9+I9+M9+Q9+U9 -> 0 | D9: =F9+J9+N9+R9+V9 -> 0 | Y9: =+W9+S9+O9+K9 -> 0 | Z9: =+X9+T9+P9+L9 -> 0 | AA9: 0 | AB9: 0
A10: 3 | B10: Правительство | C10: =E10+I10+M10+Q10+U10 -> 0 | D10: =F10+J10+N10+R10+V10 -> 0 | Y10: =+W10+S10+O10+K10 -> 0 | Z10: =+X10+T10+P10+L10 -> 0 | AA10: 0 | AB10: 0 | AC10: =+'Aging Analysis'!C11 -> 0
B11: из них необеспеченные | C11: =E11+I11+M11+Q11+U11 -> 0 | D11: =F11+J11+N11+R11+V11 -> 0 | Y11: =+W11+S11+O11+K11 -> 0 | Z11: =+X11+T11+P11+L11 -> 0 | AA11: 0 | AB11: 0
A12: 4 | B12: Физические лица | C12: =E12+I12+M12+Q12+U12 -> 4259879328 | D12: =F12+J12+N12+R12+V12 -> 0 | E12: 3964467868 | F12: 0 | G12: 36423995 | H12: 0 | I12: 132505895 | J12: 0 | K12: 13315831 | L12: 0 | M12: 38467478 | N12: 0 | O12: 9316699 | P12: 0 | Q12: 32190471 | R12: 0 | S12: 16097430 | T12: 0 | U12: 92247616 | V12: 0 | W12: 91661095 | X12: 0 | Y12: =+W12+S12+O12+K12 -> 130391055 | Z12: =+X12+T12+P12+L12 -> 0 | AA12: 30970096 | AB12: 402106 | AC12: =+'Aging Analysis'!C12 -> 4259879328
B13: из них необеспеченные | C13: =E13+I13+M13+Q13+U13 -> 0 | D13: =F13+J13+N13+R13+V13 -> 0 | E13: 0 | F13: 0 | G13: 0 | H13: 0 | I13: 0 | J13: 0 | K13: 0 | L13: 0 | M13: 0 | N13: 0 | O13: 0 | P13: 0 | Q13: 0 | R13: 0 | S13: 0 | T13: 0 | U13: 0 | V13: 0 | W13: 0 | X13: 0 | Y13: =+W13+S13+O13+K13 -> 0 | Z13: =+X13+T13+P13+L13 -> 0 | AA13: 0 | AB13: 0
A14: 5 | B14: Государственные предприятия | C14: =E14+I14+M14+Q14+U14 -> 13986301108 | D14: =F14+J14+N14+R14+V14 -> 10207198252 | E14: 13965095854 | F14: 10207198252 | G14: 132622973 | H14: 0 | I14: 0 | J14: 0 | K14: 0 | L14: 0 | M14: 20055918 | N14: 0 | O14: 5013979 | P14: 0 | Q14: 0 | R14: 0 | S14: 0 | T14: 0 | U14: 1149336 | V14: 0 | W14: 1149336 | X14: 0 | Y14: =+W14+S14+O14+K14 -> 6163315 | Z14: =+X14+T14+P14+L14 -> 0 | AA14: 0 | AB14: 0 | AC14: =+'Aging Analysis'!C13 -> 13986301108
B15: из них необеспеченные | C15: =E15+I15+M15+Q15+U15 -> 0 | D15: =F15+J15+N15+R15+V15 -> 0 | E15: 0 | F15: 0 | G15: 0 | H15: 0 | I15: 0 | J15: 0 | K15: 0 | L15: 0 | M15: 0 | N15: 0 | O15: 0 | P15: 0 | Q15: 0 | R15: 0 | S15: 0 | T15: 0 | U15: 0 | V15: 0 | W15: 0 | X15: 0 | Y15: =+W15+S15+O15+K15 -> 0 | Z15: =+X15+T15+P15+L15 -> 0 | AA15: 0 | AB15: 0
A16: 6 | B16: Совместные и иностранные предприятия | C16: =E16+I16+M16+Q16+U16 -> 7071696766 | D16: =F16+J16+N16+R16+V16 -> 6033788908 | E16: 6694459117 | F16: 5692233005 | G16: 48403599 | H16: 0 | I16: 176072246 | J16: 141524574 | K16: 17607225 | L16: 14152457 | M16: 198923925 | N16: 198839186 | O16: 49730981 | P16: 49709797 | Q16: 1049335 | R16: 0 | S16: 524668 | T16: 0 | U16: 1192143 | V16: 1192143 | W16: 1192143 | X16: 1192143 | Y16: =+W16+S16+O16+K16 -> 69055017 | Z16: =+X16+T16+P16+L16 -> 65054397 | AA16: 0 | AB16: 0 | AC16: =+'Aging Analysis'!C14 -> 7071696766
B17: из них необеспеченные | C17: =E17+I17+M17+Q17+U17 -> 0 | D17: =F17+J17+N17+R17+V17 -> 0 | E17: 0 | F17: 0 | G17: 0 | H17: 0 | I17: 0 | J17: 0 | K17: 0 | L17: 0 | M17: 0 | N17: 0 | O17: 0 | P17: 0 | Q17: 0 | R17: 0 | S17: 0 | T17: 0 | U17: 0 | V17: 0 | W17: 0 | X17: 0 | Y17: =+W17+S17+O17+K17 -> 0 | Z17: =+X17+T17+P17+L17 -> 0 | AA17: 0 | AB17: 0
A18: 7 | B18: Частные товарищества и корпорации | C18: =E18+I18+M18+Q18+U18 -> 17480739187 | D18: =F18+J18+N18+R18+V18 -> 11703391440 | E18: 14026216736 | F18: 8984077621 | G18: 132046504 | H18: 0 | I18: 2311354917 | J18: 1958802939 | K18: 233321646 | L18: 189722638 | M18: 609379340 | N18: 400667794 | O18: 142655367 | P18: 90730354 | Q18: 161870514 | R18: 105016204 | S18: 75449928 | T18: 48240773 | U18: 371917680 | V18: 254826882 | W18: 370915880 | X18: 254826882 | Y18: =+W18+S18+O18+K18 -> 822342821 | Z18: =+X18+T18+P18+L18 -> 583520647 | AA18: 0 | AB18: 0 | AC18: =+'Aging Analysis'!C15 -> 17480739187
B19: из них необеспеченные | C19: =E19+I19+M19+Q19+U19 -> 0 | D19: =F19+J19+N19+R19+V19 -> 0 | E19: 0 | F19: 0 | G19: 0 | H19: 0 | I19: 0 | J19: 0 | K19: 0 | L19: 0 | M19: 0 | N19: 0 | O19: 0 | P19: 0 | Q19: 0 | R19: 0 | S19: 0 | T19: 0 | U19: 0 | V19: 0 | W19: 0 | X19: 0 | Y19: =+W19+S19+O19+K19 -> 0 | Z19: =+X19+T19+P19+L19 -> 0 | AA19: 0 | AB19: 0
A20: 8 | B20: Фермерское хозяйство | C20: =E20+I20+M20+Q20+U20 -> 225782941 | D20: =F20+J20+N20+R20+V20 -> 130450552 | E20: 165041155 | F20: 97566132 | G20: 1419646 | H20: 0 | I20: 24195070 | J20: 8931220 | K20: 2419599 | L20: 893123 | M20: 16312042 | N20: 6396193 | O20: 4078010 | P20: 1599049 | Q20: 9503755 | R20: 7044478 | S20: 4751877 | T20: 3522240 | U20: 10730919 | V20: 10512529 | W20: 10730919 | X20: 10512530 | Y20: =+W20+S20+O20+K20 -> 21980405 | Z20: =+X20+T20+P20+L20 -> 16526942 | AA20: 0 | AB20: 0 | AC20: =+'Aging Analysis'!C16 -> 225782941
B21: из них необеспеченные | C21: =E21+I21+M21+Q21+U21 -> 0 | D21: =F21+J21+N21+R21+V21 -> 0 | E21: 0 | F21: 0 | G21: 0 | H21: 0 | I21: 0 | J21: 0 | K21: 0 | L21: 0 | M21: 0 | N21: 0 | O21: 0 | P21: 0 | Q21: 0 | R21: 0 | S21: 0 | T21: 0 | U21: 0 | V21: 0 | W21: 0 | X21: 0 | Y21: =+W21+S21+O21+K21 -> 0 | Z21: =+X21+T21+P21+L21 -> 0 | AA21: 0 | AB21: 0
A22: 9 | B22: Небанковские финансовые институты | C22: =E22+I22+M22+Q22+U22 -> 3315923 | D22: =F22+J22+N22+R22+V22 -> 0 | E22: 0 | F22: 0 | G22: 61194 | H22: 0 | I22: 3315923 | J22: 0 | K22: 331592 | L22: 0 | M22: 0 | N22: 0 | O22: 0 | P22: 0 | Q22: 0 | R22: 0 | S22: 0 | T22: 0 | U22: 0 | V22: 0 | W22: 0 | X22: 0 | Y22: =+W22+S22+O22+K22 -> 331592 | Z22: =+X22+T22+P22+L22 -> 0 | AA22: 0 | AB22: 0 | AC22: =+'Aging Analysis'!C17 -> 3315923
B23: из них необеспеченные | C23: =E23+I23+M23+Q23+U23 -> 0 | D23: =F23+J23+N23+R23+V23 -> 0 | E23: 0 | F23: 0 | G23: 0 | H23: 0 | I23: 0 | J23: 0 | K23: 0 | L23: 0 | M23: 0 | N23: 0 | O23: 0 | P23: 0 | Q23: 0 | R23: 0 | S23: 0 | T23: 0 | U23: 0 | V23: 0 | W23: 0 | X23: 0 | Y23: =+W23+S23+O23+K23 -> 0 | Z23: =+X23+T23+P23+L23 -> 0 | AA23: 0 | AB23: 0
A24: 10 | B24: Негосударственные некоммерческие организации | C24: =E24+I24+M24+Q24+U24 -> 120092235 | D24: =F24+J24+N24+R24+V24 -> 0 | E24: 49169250 | F24: 0 | G24: 531430 | H24: 0 | I24: 6380160 | J24: 0 | K24: 638016 | L24: 0 | M24: 8383148 | N24: 0 | O24: 1817528 | P24: 0 | Q24: 4721493 | R24: 0 | S24: 2360747 | T24: 0 | U24: 51438184 | V24: 0 | W24: 51438185 | X24: 0 | Y24: =+W24+S24+O24+K24 -> 56254476 | Z24: =+X24+T24+P24+L24 -> 0 | AA24: 0 | AB24: 0 | AC24: =+'Aging Analysis'!C18 -> 120092235
B25: из них необеспеченные | C25: =E25+I25+M25+Q25+U25 -> 0 | D25: =F25+J25+N25+R25+V25 -> 0 | E25: 0 | F25: 0 | G25: 0 | H25: 0 | I25: 0 | J25: 0 | K25: 0 | L25: 0 | M25: 0 | N25: 0 | O25: 0 | P25: 0 | Q25: 0 | R25: 0 | S25: 0 | T25: 0 | U25: 0 | V25: 0 | W25: 0 | X25: 0 | Y25: =+W25+S25+O25+K25 -> 0 | Z25: =+X25+T25+P25+L25 -> 0 | AA25: 0 | AB25: 0
A26: 11 | B26: Бюджетные организации | C26: =E26+I26+M26+Q26+U26 -> 0 | D26: =F26+J26+N26+R26+V26 -> 0 | E26: 0 | F26: 0 | G26: 0 | H26: 0 | I26: 0 | J26: 0 | K26: 0 | L26: 0 | M26: 0 | N26: 0 | O26: 0 | P26: 0 | Q26: 0 | R26: 0 | S26: 0 | T26: 0 | U26: 0 | V26: 0 | W26: 0 | X26: 0 | Y26: =+W26+S26+O26+K26 -> 0 | Z26: =+X26+T26+P26+L26 -> 0 | AA26: 0 | AB26: 0 | AC26: =+'Aging Analysis'!C19 -> 0
B27: из них необеспеченные | C27: =E27+I27+M27+Q27+U27 -> 0 | D27: =F27+J27+N27+R27+V27 -> 0 | E27: 0 | F27: 0 | G27: 0 | H27: 0 | I27: 0 | J27: 0 | K27: 0 | L27: 0 | M27: 0 | N27: 0 | O27: 0 | P27: 0 | Q27: 0 | R27: 0 | S27: 0 | T27: 0 | U27: 0 | V27: 0 | W27: 0 | X27: 0 | Y27: =+W27+S27+O27+K27 -> 0 | Z27: =+X27+T27+P27+L27 -> 0 | AA27: 0 | AB27: 0
A28: 12 | B28: Прочие | C28: =E28+I28+M28+Q28+U28 -> 0 | D28: =F28+J28+N28+R28+V28 -> 0 | E28: 0 | F28: 0 | G28: 0 | H28: 0 | I28: 0 | J28: 0 | K28: 0 | L28: 0 | M28: 0 | N28: 0 | O28: 0 | P28: 0 | Q28: 0 | R28: 0 | S28: 0 | T28: 0 | U28: 0 | V28: 0 | W28: 0 | X28: 0 | Y28: =+W28+S28+O28+K28 -> 0 | Z28: =+X28+T28+P28+L28 -> 0 | AA28: 297298225 | AB28: 4322078 | AC28: =+'Aging Analysis'!C20 -> 0
B29: из них необеспеченные | C29: =E29+I29+M29+Q29+U29 -> 0 | D29: =F29+J29+N29+R29+V29 -> 0 | E29: 0 | F29: 0 | G29: 0 | H29: 0 | I29: 0 | J29: 0 | K29: 0 | L29: 0 | M29: 0 | N29: 0 | O29: 0 | P29: 0 | Q29: 0 | R29: 0 | S29: 0 | T29: 0 | U29: 0 | V29: 0 | W29: 0 | X29: 0 | Y29: =+W29+S29+O29+K29 -> 0 | Z29: =+X29+T29+P29+L29 -> 0 | AA29: 0 | AB29: 0
A30: 13 | B30: Итого кредита и лизинга | C30: =+C6+C8+C10+C12+C14+C16+C18+C20+C22+C24+C26+C28 -> 43147807488 | D30: =+D6+D8+D10+D12+D14+D16+D18+D20+D22+D24+D26+D28 -> 28074829152 | E30: =+E6+E8+E10+E12+E14+E16+E18+E20+E22+E24+E26+E28 -> 38864449980 | F30: =+F6+F8+F10+F12+F14+F16+F18+F20+F22+F24+F26+F28 -> 24981075010 | G30: =+G6+G8+G10+G12+G14+G16+G18+G20+G22+G24+G26+G28 -> 351509341 | H30: =+H6+H8+H10+H12+H14+H16+H18+H20+H22+H24+H26+H28 -> 0 | I30: =+I6+I8+I10+I12+I14+I16+I18+I20+I22+I24+I26+I28 -> 2653824211 | J30: =+J6+J8+J10+J12+J14+J16+J18+J20+J22+J24+J26+J28 -> 2109258733 | ... AB30: =+AB6+AB8+AB10+AB12+AB14+AB16+AB18+AB20+AB22+AB24+AB26+AB28 -> 4724184
B31: из них необеспеченные | C31: =+C7+C9+C11+C13+C15+C17+C19+C21+C23+C25+C27+C29 -> 0 | D31: =+D7+D9+D11+D13+D15+D17+D19+D21+D23+D25+D27+D29 -> 0 | E31: =+E7+E9+E11+E13+E15+E17+E19+E21+E23+E25+E27+E29 -> 0 | F31: =+F7+F9+F11+F13+F15+F17+F19+F21+F23+F25+F27+F29 -> 0 | G31: =+G7+G9+G11+G13+G15+G17+G19+G21+G23+G25+G27+G29 -> 0 | H31: =+H7+H9+H11+H13+H15+H17+H19+H21+H23+H25+H27+H29 -> 0 | I31: =+I7+I9+I11+I13+I15+I17+I19+I21+I23+I25+I27+I29 -> 0 | J31: =+J7+J9+J11+J13+J15+J17+J19+J21+J23+J25+J27+J29 -> 0 | ... Z31: =+Z7+Z9+Z11+Z13+Z15+Z17+Z19+Z21+Z23+Z25+Z27+Z29 -> 0
B32: По сектору экономики
A34: 14 | B34: Промышленность | C34: =E34+I34+M34+Q34+U34 -> 26339734494 | D34: =F34+J34+N34+R34+V34 -> 19689771990 | E34: 24017676507 | F34: 17657450884 | G34: 212769065 | H34: 0 | I34: 1540155198 | J34: 1383019941 | K34: 156602830 | L34: 132551069 | M34: 510574835 | N34: 436119781 | O34: 122228464 | P34: 103639700 | Q34: 91900978 | R34: 61659840 | S34: 40465160 | T34: 26562592 | U34: 179426976 | V34: 151521544 | W34: 179426976 | X34: 151521544 | Y34: =+W34+S34+O34+K34 -> 498723430 | Z34: =+X34+T34+P34+L34 -> 414274905 | AA34: 7502064 | AB34: 0 | AC34: =+'Aging Analysis'!C25 -> 26339734494
B35: из них необеспеченные | C35: =E35+I35+M35+Q35+U35 -> 0 | D35: =F35+J35+N35+R35+V35 -> 0 | E35: 0 | F35: 0 | G35: 0 | H35: 0 | I35: 0 | J35: 0 | K35: 0 | L35: 0 | M35: 0 | N35: 0 | O35: 0 | P35: 0 | Q35: 0 | R35: 0 | S35: 0 | T35: 0 | U35: 0 | V35: 0 | W35: 0 | X35: 0 | Y35: =+W35+S35+O35+K35 -> 0 | Z35: =+X35+T35+P35+L35 -> 0 | AA35: 0 | AB35: 0
A36: 15 | B36: Сельское хозяйство | C36: =E36+I36+M36+Q36+U36 -> 3143324750 | D36: =F36+J36+N36+R36+V36 -> 1776340122 | E36: 2501407678 | F36: 1336822403 | G36: 25454769 | H36: 0 | I36: 345980999 | J36: 271964312 | K36: 34630705 | L36: 27228944 | M36: 209016168 | N36: 101422966 | O36: 52254042 | P36: 25355742 | Q36: 41104177 | R36: 34546725 | S36: 20552089 | T36: 17273363 | U36: 45815728 | V36: 31583716 | W36: 45815728 | X36: 31583716 | Y36: =+W36+S36+O36+K36 -> 153252564 | Z36: =+X36+T36+P36+L36 -> 101441765 | AA36: 2888856 | AB36: 0 | AC36: =+'Aging Analysis'!C26 -> 3143324750
B37: из них необеспеченные | C37: =E37+I37+M37+Q37+U37 -> 0 | D37: =F37+J37+N37+R37+V37 -> 0 | E37: 0 | F37: 0 | G37: 0 | H37: 0 | I37: 0 | J37: 0 | K37: 0 | L37: 0 | M37: 0 | N37: 0 | O37: 0 | P37: 0 | Q37: 0 | R37: 0 | S37: 0 | T37: 0 | U37: 0 | V37: 0 | W37: 0 | X37: 0 | Y37: =+W37+S37+O37+K37 -> 0 | Z37: =+X37+T37+P37+L37 -> 0 | AA37: 0 | AB37: 0
A38: 16 | B38: Транспорт и коммуникации | C38: =E38+I38+M38+Q38+U38 -> 3463692914 | D38: =F38+J38+N38+R38+V38 -> 3081468343 | E38: 3136975834 | F38: 2825496464 | G38: 35487390 | H38: 0 | I38: 281411015 | J38: 224331010 | K38: 28146677 | L38: 22433101 | M38: 5914551 | N38: 3153709 | O38: 1478638 | P38: 788427 | Q38: 14300178 | R38: 9561677 | S38: 7150089 | T38: 4780838 | U38: 25091336 | V38: 18925483 | W38: 25091336 | X38: 18925483 | Y38: =+W38+S38+O38+K38 -> 61866740 | Z38: =+X38+T38+P38+L38 -> 46927849 | AA38: 26352895 | AB38: 52300 | AC38: =+'Aging Analysis'!C27 -> 3463692914
B39: из них необеспеченные | C39: =E39+I39+M39+Q39+U39 -> 0 | D39: =F39+J39+N39+R39+V39 -> 0 | E39: 0 | F39: 0 | G39: 0 | H39: 0 | I39: 0 | J39: 0 | K39: 0 | L39: 0 | M39: 0 | N39: 0 | O39: 0 | P39: 0 | Q39: 0 | R39: 0 | S39: 0 | T39: 0 | U39: 0 | V39: 0 | W39: 0 | X39: 0 | Y39: =+W39+S39+O39+K39 -> 0 | Z39: =+X39+T39+P39+L39 -> 0 | AA39: 0 | AB39: 0
A40: 17 | B40: Строительство | C40: =E40+I40+M40+Q40+U40 -> 823680530 | D40: =F40+J40+N40+R40+V40 -> 479477004 | E40: 706711007 | F40: 431625747 | G40: 6400543 | H40: 0 | I40: 62200072 | J40: 34220974 | K40: 6220007 | L40: 3422097 | M40: 37622836 | N40: 13630283 | O40: 9405709 | P40: 3407571 | Q40: 8646686 | R40: 0 | S40: 4323343 | T40: 0 | U40: 8499929 | V40: 0 | W40: 8499929 | X40: 0 | Y40: =+W40+S40+O40+K40 -> 28448988 | Z40: =+X40+T40+P40+L40 -> 6829668 | AA40: 41846231 | AB40: 0 | AC40: =+'Aging Analysis'!C28 -> 823680530
B41: из них необеспеченные | C41: =E41+I41+M41+Q41+U41 -> 0 | D41: =F41+J41+N41+R41+V41 -> 0 | E41: 0 | F41: 0 | G41: 0 | H41: 0 | I41: 0 | J41: 0 | K41: 0 | L41: 0 | M41: 0 | N41: 0 | O41: 0 | P41: 0 | Q41: 0 | R41: 0 | S41: 0 | T41: 0 | U41: 0 | V41: 0 | W41: 0 | X41: 0 | Y41: =+W41+S41+O41+K41 -> 0 | Z41: =+X41+T41+P41+L41 -> 0 | AA41: 0 | AB41: 0
A42: 18 | B42: Торговля и общественное питание | C42: =E42+I42+M42+Q42+U42 -> 2451039832 | D42: =F42+J42+N42+R42+V42 -> 1788708379 | E42: 2202046681 | F42: 1610472987 | G42: 18567931 | H42: 0 | I42: 157819231 | J42: 142774459 | K42: 15342679 | L42: 13838202 | M42: 28847030 | N42: 24275054 | O42: 3165409 | P42: 2022415 | Q42: 7333677 | R42: 873367 | S42: 3666838 | T42: 436684 | U42: 54993213 | V42: 10312512 | W42: 54993213 | X42: 10312512 | Y42: =+W42+S42+O42+K42 -> 77168139 | Z42: =+X42+T42+P42+L42 -> 26609813 | AA42: 34369424 | AB42: 0 | AC42: =+'Aging Analysis'!C29 -> 2451039832
B43: из них необеспеченные | C43: =E43+I43+M43+Q43+U43 -> 0 | D43: =F43+J43+N43+R43+V43 -> 0 | E43: 0 | F43: 0 | G43: 0 | H43: 0 | I43: 0 | J43: 0 | K43: 0 | L43: 0 | M43: 0 | N43: 0 | O43: 0 | P43: 0 | Q43: 0 | R43: 0 | S43: 0 | T43: 0 | U43: 0 | V43: 0 | W43: 0 | X43: 0 | Y43: =+W43+S43+O43+K43 -> 0 | Z43: =+X43+T43+P43+L43 -> 0 | AA43: 0 | AB43: 0
A44: 19 | B44: Материально-техническое снабжение и сбыт | C44: =E44+I44+M44+Q44+U44 -> 311679287 | D44: =F44+J44+N44+R44+V44 -> 150476985 | E44: 265903575 | F44: 124953523 | G44: 1734562 | H44: 0 | I44: 32380846 | J44: 18972679 | K44: 3238085 | L44: 1897268 | M44: 6671223 | N44: 6550783 | O44: 1667806 | P44: 1637696 | Q44: 0 | R44: 0 | S44: 0 | T44: 0 | U44: 6723643 | V44: 0 | W44: 6723643 | X44: 0 | Y44: =+W44+S44+O44+K44 -> 11629534 | Z44: =+X44+T44+P44+L44 -> 3534964 | AA44: 0 | AB44: 0 | AC44: =+'Aging Analysis'!C30 -> 311679287
B45: из них необеспеченные | C45: =E45+I45+M45+Q45+U45 -> 0 | D45: =F45+J45+N45+R45+V45 -> 0 | E45: 0 | F45: 0 | G45: 0 | H45: 0 | I45: 0 | J45: 0 | K45: 0 | L45: 0 | M45: 0 | N45: 0 | O45: 0 | P45: 0 | Q45: 0 | R45: 0 | S45: 0 | T45: 0 | U45: 0 | V45: 0 | W45: 0 | X45: 0 | Y45: =+W45+S45+O45+K45 -> 0 | Z45: =+X45+T45+P45+L45 -> 0 | AA45: 0 | AB45: 0
A46: 20 | B46: Жилищно-коммунальные услуги | C46: =E46+I46+M46+Q46+U46 -> 120092235 | D46: =F46+J46+N46+R46+V46 -> 0 | E46: 49169252 | F46: 0 | G46: 531430 | H46: 0 | I46: 6380158 | J46: 0 | K46: 638016 | L46: 0 | M46: 8383148 | N46: 0 | O46: 1817528 | P46: 0 | Q46: 4721494 | R46: 0 | S46: 2360747 | T46: 0 | U46: 51438183 | V46: 0 | W46: 51438183 | X46: 0 | Y46: =+W46+S46+O46+K46 -> 56254474 | Z46: =+X46+T46+P46+L46 -> 0 | AA46: 0 | AB46: 0 | AC46: =+'Aging Analysis'!C31 -> 120092235
B47: из них необеспеченные | C47: =E47+I47+M47+Q47+U47 -> 0 | D47: =F47+J47+N47+R47+V47 -> 0 | E47: 0 | F47: 0 | G47: 0 | H47: 0 | I47: 0 | J47: 0 | K47: 0 | L47: 0 | M47: 0 | N47: 0 | O47: 0 | P47: 0 | Q47: 0 | R47: 0 | S47: 0 | T47: 0 | U47: 0 | V47: 0 | W47: 0 | X47: 0 | Y47: =+W47+S47+O47+K47 -> 0 | Z47: =+X47+T47+P47+L47 -> 0 | AA47: 0 | AB47: 0
A48: 21 | B48: Другие сектора | C48: =E48+I48+M48+Q48+U48 -> 6494563446 | D48: =F48+J48+N48+R48+V48 -> 1108586329 | E48: 5984559446 | F48: 994253002 | G48: 50563651 | H48: 0 | I48: 227496692 | J48: 33975358 | K48: 22814910 | L48: 3397537 | M48: 84492060 | N48: 20750597 | O48: 20594968 | P48: 5187649 | Q48: 41328378 | R48: 5419073 | S48: 20666384 | T48: 2709536 | U48: 156686870 | V48: 54188299 | W48: 155098550 | X48: 54188300 | Y48: =+W48+S48+O48+K48 -> 219174812 | Z48: =+X48+T48+P48+L48 -> 65483022 | AA48: =184338755+30970096 -> 215308851 | AB48: =4269778+402106 -> 4671884 | AC48: =+'Aging Analysis'!C32 -> 6494563446
B49: из них необеспеченные | C49: =E49+I49+M49+Q49+U49 -> 0 | D49: =F49+J49+N49+R49+V49 -> 0 | E49: 0 | F49: 0 | G49: 0 | H49: 0 | I49: 0 | J49: 0 | K49: 0 | L49: 0 | M49: 0 | N49: 0 | O49: 0 | P49: 0 | Q49: 0 | R49: 0 | S49: 0 | T49: 0 | U49: 0 | V49: 0 | W49: 0 | X49: 0 | Y49: =+W49+S49+O49+K49 -> 0 | Z49: =+X49+T49+P49+L49 -> 0 | AA49: 0 | AB49: 0
A50: 22 | B50: Итого кредита и лизинга | C50: =+C34+C36+C38+C40+C42+C44+C46+C48 -> 43147807488 | D50: =+D34+D36+D38+D40+D42+D44+D46+D48 -> 28074829152 | E50: =+E34+E36+E38+E40+E42+E44+E46+E48 -> 38864449980 | F50: =+F34+F36+F38+F40+F42+F44+F46+F48 -> 24981075010 | G50: =+G34+G36+G38+G40+G42+G44+G46+G48 -> 351509341 | H50: =+H34+H36+H38+H40+H42+H44+H46+H48 -> 0 | I50: =+I34+I36+I38+I40+I42+I44+I46+I48 -> 2653824211 | J50: =+J34+J36+J38+J40+J42+J44+J46+J48 -> 2109258733 | ... AB50: =+AB34+AB36+AB38+AB40+AB42+AB44+AB46+AB48 -> 4724184
B51: из них необеспеченные | C51: =+C35+C37+C39+C41+C43+C45+C47+C49 -> 0 | D51: =+D35+D37+D39+D41+D43+D45+D47+D49 -> 0 | E51: =+E35+E37+E39+E41+E43+E45+E47+E49 -> 0 | F51: =+F35+F37+F39+F41+F43+F45+F47+F49 -> 0 | G51: =+G35+G37+G39+G41+G43+G45+G47+G49 -> 0 | H51: =+H35+H37+H39+H41+H43+H45+H47+H49 -> 0 | I51: =+I35+I37+I39+I41+I43+I45+I47+I49 -> 0 | J51: =+J35+J37+J39+J41+J43+J45+J47+J49 -> 0 | ... AB51: =+AB35+AB37+AB39+AB41+AB43+AB45+AB47+AB49 -> 0
B52: По регионам
A54: 23 | B54: Республика Каракалпакстан | C54: =E54+I54+M54+Q54+U54 -> 1233994354 | D54: =F54+J54+N54+R54+V54 -> 550813636 | E54: 1054055169 | F54: 475959678 | G54: 9376423 | H54: 0 | I54: 102079313 | J54: 71485895 | K54: 10208144 | L54: 7148590 | M54: 61615613 | N54: 3368063 | O54: 15400448 | P54: 842016 | Q54: 5433129 | R54: 0 | S54: 2716564 | T54: 0 | U54: 10811130 | V54: 0 | W54: 10811130 | X54: 0 | Y54: =+W54+S54+O54+K54 -> 39136286 | Z54: =+X54+T54+P54+L54 -> 7990606 | AA54: 20565598 | AB54: 33593
A55: 24 | B55: Андижанская область | C55: =E55+I55+M55+Q55+U55 -> 1028919634 | D55: =F55+J55+N55+R55+V55 -> 596342262 | E55: 674383738 | F55: 296822870 | G55: 8124906 | H55: 0 | I55: 291912973 | J55: 283679249 | K55: 29197849 | L55: 28367925 | M55: 25033534 | N55: 3153709 | O55: 6245219 | P55: 788427 | Q55: 9883139 | R55: 5805828 | S55: 4941569 | T55: 2902914 | U55: 27706250 | V55: 6880606 | W55: 27708571 | X55: 6880606 | Y55: =+W55+S55+O55+K55 -> 68093208 | Z55: =+X55+T55+P55+L55 -> 38939872 | AA55: 5882145 | AB55: 35737
A56: 25 | B56: Бухарская область | C56: =E56+I56+M56+Q56+U56 -> 1604976173 | D56: =F56+J56+N56+R56+V56 -> 1173103213 | E56: 1237214559 | F56: 834839112 | G56: 12595756 | H56: 0 | I56: 173817107 | J56: 160931231 | K56: 17381213 | L56: 16093123 | M56: 125381330 | N56: 124850428 | O56: 31317827 | P56: 31212607 | Q56: 40311108 | R56: 35689369 | S56: 20155554 | T56: 17844685 | U56: 28252069 | V56: 16793073 | W56: 28256985 | X56: 16793073 | Y56: =+W56+S56+O56+K56 -> 97111579 | Z56: =+X56+T56+P56+L56 -> 81943488 | AA56: 77025073 | AB56: 29882
A57: 26 | B57: Джизакская область | C57: =E57+I57+M57+Q57+U57 -> 1108440375 | D57: =F57+J57+N57+R57+V57 -> 770452903 | E57: 1067370283 | F57: 758406899 | G57: 9044718 | H57: 0 | I57: 13079626 | J57: 6269803 | K57: 1307963 | L57: 626980 | M57: 6616590 | N57: 2466137 | O57: 1646783 | P57: 616534 | Q57: 5082826 | R57: 3310064 | S57: 2541413 | T57: 1655032 | U57: 16291050 | V57: 0 | W57: 16291050 | X57: 0 | Y57: =+W57+S57+O57+K57 -> 21787209 | Z57: =+X57+T57+P57+L57 -> 2898546 | AA57: 27855009 | AB57: 40540
A58: 27 | B58: Кашкадарьинская область | C58: =E58+I58+M58+Q58+U58 -> 1608480891 | D58: =F58+J58+N58+R58+V58 -> 872263136 | E58: 1465252706 | F58: 800938163 | G58: 10809156 | H58: 0 | I58: 119653217 | J58: 69898441 | K58: 11965607 | L58: 6989844 | M58: 9437688 | N58: 625091 | O58: 2346304 | P58: 156273 | Q58: 5014952 | R58: 0 | S58: 2508657 | T58: 0 | U58: 9122328 | V58: 801441 | W58: 9122328 | X58: 801441 | Y58: =+W58+S58+O58+K58 -> 25942896 | Z58: =+X58+T58+P58+L58 -> 7947558 | AA58: 969918 | AB58: 185650
A59: 28 | B59: Навоийская область | C59: =E59+I59+M59+Q59+U59 -> 1238544253 | D59: =F59+J59+N59+R59+V59 -> 913503463 | E59: 1193307998 | F59: 877385726 | G59: 11308749 | H59: 0 | I59: 39230915 | J59: 36117737 | K59: 3923091 | L59: 3611774 | M59: 2539208 | N59: 0 | O59: 595048 | P59: 0 | Q59: 694174 | R59: 0 | S59: 347087 | T59: 0 | U59: 2771958 | V59: 0 | W59: 2771958 | X59: 0 | Y59: =+W59+S59+O59+K59 -> 7637184 | Z59: =+X59+T59+P59+L59 -> 3611774 | AA59: 3243143 | AB59: 27474
A60: 29 | B60: Наманганская область | C60: =E60+I60+M60+Q60+U60 -> 622244650 | D60: =F60+J60+N60+R60+V60 -> 362503774 | E60: 501947722 | F60: 272045386 | G60: 5288565 | H60: 0 | I60: 44609482 | J60: 23235369 | K60: 4460948 | L60: 2323537 | M60: 69263793 | N60: 65868311 | O60: 17031747 | P60: 16467078 | Q60: 3022032 | R60: 1354708 | S60: 1511016 | T60: 677354 | U60: 3401621 | V60: 0 | W60: 3401621 | X60: 0 | Y60: =+W60+S60+O60+K60 -> 26405332 | Z60: =+X60+T60+P60+L60 -> 19467969 | AA60: 15647989 | AB60: 1018
A61: 30 | B61: Самаркандская область | C61: =E61+I61+M61+Q61+U61 -> 1430932742 | D61: =F61+J61+N61+R61+V61 -> 923644070 | E61: 1272732201 | F61: 790772106 | G61: 14095535 | H61: 0 | I61: 129462518 | J61: 117404067 | K61: 12978924 | L61: 11772920 | M61: 21833367 | N61: 11010391 | O61: 5457487 | P61: 2752598 | Q61: 554719 | R61: 0 | S61: 277359 | T61: 0 | U61: 6349937 | V61: 4457506 | W61: 6349937 | X61: 4457506 | Y61: =+W61+S61+O61+K61 -> 25063707 | Z61: =+X61+T61+P61+L61 -> 18983024 | AA61: 4623882 | AB61: 5469
A62: 31 | B62: Сурхандарьинская область | C62: =E62+I62+M62+Q62+U62 -> 902467898 | D62: =F62+J62+N62+R62+V62 -> 346119709 | E62: 727246682 | F62: 239083377 | G62: 7124392 | H62: 0 | I62: 86520279 | J62: 67490188 | K62: 8652118 | L62: 6749019 | M62: 64587293 | N62: 30829891 | O62: 16141222 | P62: 7707473 | Q62: 4162431 | R62: 0 | S62: 2082118 | T62: 0 | U62: 19951213 | V62: 8716253 | W62: 19313016 | X62: 8716253 | Y62: =+W62+S62+O62+K62 -> 46188474 | Z62: =+X62+T62+P62+L62 -> 23172745 | AA62: 9436708 | AB62: 59338
A63: 32 | B63: Сырдарьинская область | C63: =E63+I63+M63+Q63+U63 -> 1954483696 | D63: =F63+J63+N63+R63+V63 -> 1084618112 | E63: 1855943269 | F63: 1020033398 | G63: 7551664 | H63: 0 | I63: 72085569 | J63: 62368995 | K63: 7208557 | L63: 6236900 | M63: 4436313 | N63: 2215719 | O63: 1105966 | P63: 553930 | Q63: 2481748 | R63: 0 | S63: 1240874 | T63: 0 | U63: 19536797 | V63: 0 | W63: 19536797 | X63: 0 | Y63: =+W63+S63+O63+K63 -> 29092194 | Z63: =+X63+T63+P63+L63 -> 6790830 | AA63: 6765218 | AB63: 1498788
A64: 33 | B64: г. Ташкент | C64: =E64+I64+M64+Q64+U64 -> 25421384613 | D64: =F64+J64+N64+R64+V64 -> 17980396684 | E64: 23558805628 | F64: 16612735345 | G64: 7775442 | H64: 0 | I64: 1153270458 | J64: 882356365 | K64: 117476659 | L64: 82045467 | M64: 355856118 | N64: 300283620 | O64: 79221884 | P64: 65634311 | Q64: 65523375 | R64: 18024710 | S64: 32761800 | T64: 9012355 | U64: 287929034 | V64: 166996644 | W64: 286957235 | X64: 166996645 | Y64: =+W64+S64+O64+K64 -> 516417578 | Z64: =+X64+T64+P64+L64 -> 323688778 | AA64: 86241533 | AB64: 1448935
A65: 34 | B65: Ташкентская область | C65: =E65+I65+M65+Q65+U65 -> 2678889120 | D65: =F65+J65+N65+R65+V65 -> 1186410453 | E65: 2501033874 | F65: 1129109718 | G65: 215562541 | H65: 0 | I65: 92528091 | J65: 30272222 | K65: 9315095 | L65: 3027222 | M65: 46392370 | N65: 9182721 | O65: 11482954 | P65: 2295680 | Q65: 27060741 | R65: 17845792 | S65: 8045042 | T65: 4655567 | U65: 11874044 | V65: 0 | W65: 11874196 | X65: 0 | Y65: =+W65+S65+O65+K65 -> 40717287 | Z65: =+X65+T65+P65+L65 -> 9978469 | AA65: 4864532 | AB65: 1078712
... A67: 36 | B67: Хорезмская область | C67: =E67+I67+M67+Q67+U67 -> 914555711 | D67: =F67+J67+N67+R67+V67 -> 531221336 | E67: 541384699 | F67: 213534540 | G67: 10813969 | H67: 0 | I67: 267079063 | J67: 248578421 | K67: 26708033 | L67: 24857842 | M67: 55590524 | N67: 30833143 | O67: 13896131 | P67: 7708286 | Q67: 26252938 | R67: 21910365 | S67: 13126469 | T67: 10955183 | U67: 24248487 | V67: 16364867 | W67: 24248487 | X67: 16364867 | Y67: =+W67+S67+O67+K67 -> 77979120 | Z67: =+X67+T67+P67+L67 -> 59886178 | AA67: 44421528 | AB67: 6723
A68: 37 | B68: Итого кредита и лизинга | C68: =SUM(C54:C67) -> 43147807488 | D68: =SUM(D54:D67) -> 28074829152 | E68: =SUM(E54:E67) -> 38864449980 | F68: =SUM(F54:F67) -> 24981075010 | G68: =SUM(G54:G67) -> 351509341 | H68: =SUM(H54:H67) -> 0 | I68: =SUM(I54:I67) -> 2653824211 | J68: =SUM(J54:J67) -> 2109258733 | ... AB68: =SUM(AB54:AB67) -> 4724184
A69: 38 | B69: Другие классифицированные активы | C69: =E69+I69+M69+Q69+U69 -> 6716669448 | D69: =F69+J69+N69+R69+V69 -> 4739967024 | E69: ='Asset quality'!D12+'Asset quality'!D48+'Asset quality'!D51+'Asset quality'!D54+'Asset quality'!D55+'Asset quality'!D60 -> 6616048456 | F69: 4701208930 | G69: 0 | H69: 0 | I69: ='Asset quality'!E48+'Asset quality'!E54+'Asset quality'!E55+'Asset quality'!E60 -> 6500332 | J69: 0 | K69: ='Asset quality'!P48+'Asset quality'!P54+'Asset quality'!P55+'Asset quality'!P60 -> 648482 | L69: 0 | M69: ='Asset quality'!F54+'Asset quality'!F55 -> 12500693 | N69: 0 | O69: ='Asset quality'!Q54+'Asset quality'!Q55+'Asset quality'!Q60 -> 1684354 | P69: 0 | Q69: ='Asset quality'!G54 -> 28166 | R69: 0 | S69: ='Asset quality'!R54+803 -> 9033 | T69: 0 | U69: ='Asset quality'!H12+'Asset quality'!H48+'Asset quality'!H51+'Asset quality'!H54+'Asset quality'!H60 -> 81591801 | V69: 38758094 | W69: ='Asset quality'!S12+'Asset quality'!S48+'Asset quality'!S51+'Asset quality'!S54+'Asset quality'!S60 -> 81741075 | X69: 38758094 | Y69: =+W69+S69+O69+K69 -> 84082944 | Z69: =+X69+T69+P69+L69 -> 38758094 | AB69: 0
B70: из них необеспеченные | C70: =E70+I70+M70+Q70+U70 -> 0 | D70: =F70+J70+N70+R70+V70 -> 0 | Y70: =+W70+S70+O70+K70 -> 0 | Z70: =+X70+T70+P70+L70 -> 0 | AB70: 0
A71: 39 | B71: Всего классифицированных активов | C71: =+C50+C69 -> 49864476936 | D71: =+D50+D69 -> 32814796176 | E71: =+E50+E69 -> 45480498436 | F71: =+F50+F69 -> 29682283940 | G71: =+G50+G69 -> 351509341 | H71: =+H50+H69 -> 0 | I71: =+I50+I69 -> 2660324543 | J71: =+J50+J69 -> 2109258733 | ... AB71: =+AB50+AB69 -> 4724184
B74: Подпись Председателя правления:
B76: Подпись Главного Бухгалтера:
E77: =SUM('Asset quality'!D21:D47)+'Asset quality'!D16 -> 38864449980 | G77: =SUM('Asset quality'!O21:O47)+'Asset quality'!O16 -> 351509341 | I77: =SUM('Asset quality'!E21:E47)+'Asset quality'!E16 -> 2653824211 | K77: =SUM('Asset quality'!P21:P47)+'Asset quality'!P16 -> 267633909 | M77: =SUM('Asset quality'!F21:F47)+'Asset quality'!F16 -> 891521851 | O77: =SUM('Asset quality'!Q21:Q47)+'Asset quality'!Q16 -> 212612564 | Q77: =SUM('Asset quality'!G21:G47)+'Asset quality'!G16 -> 209335568 | S77: =SUM('Asset quality'!R21:R47)+'Asset quality'!R16 -> 99184650 | U77: =SUM('Asset quality'!H21:H47)+'Asset quality'!H16 -> 528675878 | W77: =SUM('Asset quality'!S21:S47)+'Asset quality'!S16 -> 527087558 | Y77: =+W77+S77+O77+K77 -> 1106518681
G78: =+'Asset quality'!O9+'Asset quality'!O62 -> 351509341 | K78: =+'Asset quality'!P9+'Asset quality'!P62 -> 268282391 | O78: =+'Asset quality'!Q9+'Asset quality'!Q62 -> 214296918 | S78: =+'Asset quality'!R9+'Asset quality'!R62 -> 99193683 | W78: =+'Asset quality'!S9+'Asset quality'!S62 -> 608828633 | Y78: =+W78+S78+O78+K78 -> 1190601625
E79: =+E77-E50 -> 0 | G79: =+G77-G50 -> 0 | I79: =+I77-I50 -> 0 | K79: =+K77-K50 -> 0 | M79: =+M77-M50 -> 0 | O79: =+O77-O50 -> 0 | Q79: =+Q77-Q50 -> 0 | S79: =+S77-S50 -> 0 | U79: =+U77-U50 -> 0 | W79: =+W77-W50 -> 0 | Y79: =+Y77-Y50 -> 0
G80: =+G78-G71 -> 0 | K80: =+K78-K71 -> 0 | O80: =+O78-O71 -> 0 | S80: =+S78-S71 -> 0 | W80: =+W78-W71 -> 0 | Y80: =+Y78-Y71 -> 0

Sheet Transactions of related parties
A1: ОТЧЕТ О СДЕЛКАХ, ЗАКЛЮЧЕННЫХ СО СВЯЗАННЫМИ ЛИЦАМИ | Y1: Таблица-11
B3: =+'Asset quality'!B3 -> "Ўзсаноатқурилишбанк" АТБ | U3: =+'Asset quality'!P3 -> 44560 | V3: =+#REF! -> #REF! | Y3: тыс. сум
A4: № | B4: Наименования клиента | C4: ИНН | D4: Вид деятельности | E4: Код валюты | F4: Номер группы | G4: Текущая задолженность, брутто | H4: из них | T4: Пересмотрения | U4: Вычеты из норматива | W4: Классификация | X4: Резерв | Y4: Источник кредита | Z4: Текущая задолженность, нетто
H5: балансовые | L5: внебалансовые
H6: Межбанковские кредиты и депозиты, остатки на кор счетах, средства для межбанковских взаиморасчетов, другие размещенные средства (кроме овернайта и клиринговых операций) и доходы по ним | I6: Кредиты/лизинги/факторинги и доходы по ним | J6: Инвестиции и доходы по ним | K6: Другие активы доходы по ним | L6: Аккредитивы и доходы по ним | N6: Гарантии/поручительства и доходы по ним | P6: Неиспользованные кредитные линии/безотзывные обязательства/ другие обязательства по выдаче кредитов доходы по ним | R6: Другие активы доходы по ним | U6: Вид обеспечения | V6: Сумма
L7: остаток | M7: по степени риска | N7: остаток | O7: по степени риска | P7: остаток | Q7: по степени риска | R7: остаток | S7: по степени риска
B8: А | C8: Б | D8: В | E8: Г | F8: Д | G8: Е | H8: Е1 | I8: Е2 | J8: Е3 | K8: Е4 | L8: Е5 | N8: Е6 | P8: Е7 | R8: Е8 | T8: Ж | U8: З | V8: И | W8: К | X8: Л | Y8: М | Z8: Н
A9: 1 | B9: MCHJ "PSB CAPITAL" | C9: 305678140 | D9: 70220 | E9: 000 | F9: 1 | G9: =+H9+I9+J9+K9+M9+O9+Q9+S9 -> 83362868 | J9: 83362868 | P9: 0 | Q9: 0 | W9: 1 | X9: 0 | Z9: =+G9-V9-X9 -> 83362868 | AA9: =SUMIF($F$9:$F$63,$F9,$Z$9:$Z$63) -> 83362868
A10: 2 | B10: CK MCHJ "PSB INSURANCE" | C10: 305880294 | D10: 65120 | E10: 000 | F10: 2 | G10: =+H10+I10+J10+K10+M10+O10+Q10+S10 -> 38600000 | J10: 38600000 | P10: 0 | Q10: 0 | W10: 1 | X10: 0 | Z10: =+G10-V10-X10 -> 38600000 | AA10: =SUMIF($F$9:$F$63,$F10,$Z$9:$Z$63) -> 38600000
A11: 3 | B11: Палванов Акмал Самандарович | C11: AA0250598 | E11: 000 | F11: 3 | G11: =+H11+I11+J11+K11+M11+O11+Q11+S11 -> 310169 | I11: 260170 | P11: 49999 | Q11: 49999 | W11: 1 | X11: 0 | Z11: =+G11-V11-X11 -> 310169 | AA11: =SUMIF($F$9:$F$63,$F11,$Z$9:$Z$63) -> 310169
A12: 4 | B12: Худайберганов Илхом Неъматуллаевич | C12: AA1466102 | E12: 000 | F12: 4 | G12: =+H12+I12+J12+K12+M12+O12+Q12+S12 -> 282291 | I12: 232291 | P12: 50000 | Q12: 50000 | W12: 1 | X12: 0 | Z12: =+G12-V12-X12 -> 282291 | AA12: =SUMIF($F$9:$F$63,$F12,$Z$9:$Z$63) -> 282291
A13: 5 | B13: Норхужаев Бахритдин Нуритдинович | C13: AA0844662 | E13: 000 | F13: 5 | G13: =+H13+I13+J13+K13+M13+O13+Q13+S13 -> 50021 | I13: 6669 | P13: 43352 | Q13: 43352 | W13: 1 | X13: 0 | Z13: =+G13-V13-X13 -> 50021 | AA13: =SUMIF($F$9:$F$63,$F13,$Z$9:$Z$63) -> 269276
A14: 6 | B14: Норхужаева Дилфуза Бахритдиновна | C14: AA0047510 | E14: 000 | F14: 5 | G14: =+H14+I14+J14+K14+M14+O14+Q14+S14 -> 219255 | I14: 219255 | P14: 0 | Q14: 0 | W14: 1 | X14: 0 | Z14: =+G14-V14-X14 -> 219255 | AA14: =SUMIF($F$9:$F$63,$F14,$Z$9:$Z$63) -> 269276
A15: 7 | B15: Шамирзаев Диёр Худоёрович | C15: AA0220815 | E15: 000 | F15: 6 | G15: =+H15+I15+J15+K15+M15+O15+Q15+S15 -> 125841 | I15: 75841 | P15: 50000 | Q15: 50000 | W15: 1 | X15: 0 | Z15: =+G15-V15-X15 -> 125841 | AA15: =SUMIF($F$9:$F$63,$F15,$Z$9:$Z$63) -> 135644
A16: 8 | B16: Шамирзаева Гузал Бердиёровна | C16: AB1611653 | E16: 000 | F16: 6 | G16: =+H16+I16+J16+K16+M16+O16+Q16+S16 -> 9803 | I16: 9803 | P16: 0 | Q16: 0 | W16: 1 | X16: 0 | Z16: =+G16-V16-X16 -> 9803 | AA16: =SUMIF($F$9:$F$63,$F16,$Z$9:$Z$63) -> 135644
A17: 9 | B17: Абдурахманов Фаррух Талипжанович | C17: AA5426058 | E17: 000 | F17: 7 | G17: =+H17+I17+J17+K17+M17+O17+Q17+S17 -> 87500 | I17: 0 | P17: 87500 | Q17: 87500 | W17: 1 | X17: 0 | Z17: =+G17-V17-X17 -> 87500 | AA17: =SUMIF($F$9:$F$63,$F17,$Z$9:$Z$63) -> 87500
A18: 10 | B18: Акбаржонов Азиз Акбаржон ўғли | C18: AA5776834 | E18: 000 | F18: 8 | G18: =+H18+I18+J18+K18+M18+O18+Q18+S18 -> 84355 | I18: 12054 | K18: 9821 | P18: 62480 | Q18: 62480 | W18: 1 | X18: 0 | Z18: =+G18-V18-X18 -> 84355 | AA18: =SUMIF($F$9:$F$63,$F18,$Z$9:$Z$63) -> 84355
A19: 11 | B19: Машарипов Шоназар Жуманазарович | C19: AA3038139 | E19: 000 | F19: 9 | G19: =+H19+I19+J19+K19+M19+O19+Q19+S19 -> 56080 | I19: 6080 | P19: 50000 | Q19: 50000 | W19: 1 | X19: 0 | Z19: =+G19-V19-X19 -> 56080 | AA19: =SUMIF($F$9:$F$63,$F19,$Z$9:$Z$63) -> 79174
A20: 12 | B20: Машарипов Акрам Жуманазарович | C20: AB0741303 | E20: 000 | F20: 9 | G20: =+H20+I20+J20+K20+M20+O20+Q20+S20 -> 23094 | I20: 20594 | P20: 2500 | Q20: 2500 | W20: 1 | X20: 0 | Z20: =+G20-V20-X20 -> 23094 | AA20: =SUMIF($F$9:$F$63,$F20,$Z$9:$Z$63) -> 79174
A21: 13 | B21: Якубов Шухрат Исраилович | C21: AB4565542 | E21: 000 | F21: 10 | G21: =+H21+I21+J21+K21+M21+O21+Q21+S21 -> 71901 | I21: 71901 | P21: 0 | Q21: 0 | W21: 1 | X21: 0 | Z21: =+G21-V21-X21 -> 71901 | AA21: =SUMIF($F$9:$F$63,$F21,$Z$9:$Z$63) -> 71901
A22: 14 | B22: Шерматов Мансур Нигматович | C22: AA1638688 | E22: 000 | F22: 11 | G22: =+H22+I22+J22+K22+M22+O22+Q22+S22 -> 50000 | I22: 0 | P22: 50000 | Q22: 50000 | W22: 1 | X22: 0 | Z22: =+G22-V22-X22 -> 50000 | AA22: =SUMIF($F$9:$F$63,$F22,$Z$9:$Z$63) -> 50000
A23: 15 | B23: Вохидов Ойбек Розикович | C23: AA1359299 | E23: 000 | F23: 12 | G23: =+H23+I23+J23+K23+M23+O23+Q23+S23 -> 50000 | I23: 0 | P23: 50000 | Q23: 50000 | W23: 1 | X23: 0 | Z23: =+G23-V23-X23 -> 50000 | AA23: =SUMIF($F$9:$F$63,$F23,$Z$9:$Z$63) -> 50000
A24: 16 | B24: Мухамедов Фазлиддин Кучкарович | C24: AA4591898 | E24: 000 | F24: 13 | G24: =+H24+I24+J24+K24+M24+O24+Q24+S24 -> 34981 | I24: 28997 | P24: 5984 | Q24: 5984 | W24: 1 | X24: 0 | Z24: =+G24-V24-X24 -> 34981 | AA24: =SUMIF($F$9:$F$63,$F24,$Z$9:$Z$63) -> 34981
A25: 17 | B25: Юсупов Юсуфбой Косимович | C25: AA3104243 | E25: 000 | F25: 14 | G25: =+H25+I25+J25+K25+M25+O25+Q25+S25 -> 33630 | I25: 3630 | P25: 30000 | Q25: 30000 | W25: 1 | X25: 0 | Z25: =+G25-V25-X25 -> 33630 | AA25: =SUMIF($F$9:$F$63,$F25,$Z$9:$Z$63) -> 33630
A26: 18 | B26: Сулаймонов Одил Яхёевич | C26: AA7231621 | E26: 000 | F26: 15 | G26: =+H26+I26+J26+K26+M26+O26+Q26+S26 -> 25000 | I26: 0 | P26: 25000 | Q26: 25000 | W26: 1 | X26: 0 | Z26: =+G26-V26-X26 -> 25000 | AA26: =SUMIF($F$9:$F$63,$F26,$Z$9:$Z$63) -> 25000
A27: 19 | B27: Эргашева Нигора Абдумажитовна | C27: AA2014244 | E27: 000 | F27: 16 | G27: =+H27+I27+J27+K27+M27+O27+Q27+S27 -> 13600 | I27: 13600 | P27: 0 | Q27: 0 | W27: 1 | X27: 0 | Z27: =+G27-V27-X27 -> 13600 | AA27: =SUMIF($F$9:$F$63,$F27,$Z$9:$Z$63) -> 13600
A28: 20 | B28: Рахматов Бахтиёр Алиевич | C28: AA1941203 | E28: 000 | F28: 17 | G28: =+H28+I28+J28+K28+M28+O28+Q28+S28 -> 9576 | I28: 9576 | P28: 0 | Q28: 0 | W28: 1 | X28: 0 | Z28: =+G28-V28-X28 -> 9576 | AA28: =SUMIF($F$9:$F$63,$F28,$Z$9:$Z$63) -> 9576
A29: 21 | B29: Аннакличев Султан Сапармухамедович | C29: KA0404902 | E29: 000 | F29: 18 | G29: =+H29+I29+J29+K29+M29+O29+Q29+S29 -> 6573 | I29: 6573 | P29: 0 | Q29: 0 | W29: 1 | X29: 0 | Z29: =+G29-V29-X29 -> 6573 | AA29: =SUMIF($F$9:$F$63,$F29,$Z$9:$Z$63) -> 6573
A30: 22 | G30: =+H30+I30+J30+K30+M30+O30+Q30+S30 -> 0 | Z30: =+G30-V30-X30 -> 0 | AA30: =SUMIF($F$9:$F$63,$F30,$Z$9:$Z$63) -> 0
A31: 23 | G31: =+H31+I31+J31+K31+M31+O31+Q31+S31 -> 0 | Z31: =+G31-V31-X31 -> 0 | AA31: =SUMIF($F$9:$F$63,$F31,$Z$9:$Z$63) -> 0
A32: 24 | G32: =+H32+I32+J32+K32+M32+O32+Q32+S32 -> 0 | Z32: =+G32-V32-X32 -> 0 | AA32: =SUMIF($F$9:$F$63,$F32,$Z$9:$Z$63) -> 0
A33: 25 | G33: =+H33+I33+J33+K33+M33+O33+Q33+S33 -> 0 | Z33: =+G33-V33-X33 -> 0 | AA33: =SUMIF($F$9:$F$63,$F33,$Z$9:$Z$63) -> 0
A34: 26 | G34: =+H34+I34+J34+K34+M34+O34+Q34+S34 -> 0 | Z34: =+G34-V34-X34 -> 0 | AA34: =SUMIF($F$9:$F$63,$F34,$Z$9:$Z$63) -> 0
A35: 27 | G35: =+H35+I35+J35+K35+M35+O35+Q35+S35 -> 0 | Z35: =+G35-V35-X35 -> 0 | AA35: =SUMIF($F$9:$F$63,$F35,$Z$9:$Z$63) -> 0
A36: 28 | G36: =+H36+I36+J36+K36+M36+O36+Q36+S36 -> 0 | Z36: =+G36-V36-X36 -> 0 | AA36: =SUMIF($F$9:$F$63,$F36,$Z$9:$Z$63) -> 0
A37: 29 | G37: =+H37+I37+J37+K37+M37+O37+Q37+S37 -> 0 | Z37: =+G37-V37-X37 -> 0 | AA37: =SUMIF($F$9:$F$63,$F37,$Z$9:$Z$63) -> 0
A38: 30 | G38: =+H38+I38+J38+K38+M38+O38+Q38+S38 -> 0 | Z38: =+G38-V38-X38 -> 0 | AA38: =SUMIF($F$9:$F$63,$F38,$Z$9:$Z$63) -> 0
A39: 31 | G39: =+H39+I39+J39+K39+M39+O39+Q39+S39 -> 0 | Z39: =+G39-V39-X39 -> 0 | AA39: =SUMIF($F$9:$F$63,$F39,$Z$9:$Z$63) -> 0
A40: 32 | G40: =+H40+I40+J40+K40+M40+O40+Q40+S40 -> 0 | Z40: =+G40-V40-X40 -> 0 | AA40: =SUMIF($F$9:$F$63,$F40,$Z$9:$Z$63) -> 0
A41: 33 | G41: =+H41+I41+J41+K41+M41+O41+Q41+S41 -> 0 | Z41: =+G41-V41-X41 -> 0 | AA41: =SUMIF($F$9:$F$63,$F41,$Z$9:$Z$63) -> 0
... A63: 55 | G63: =+H63+I63+J63+K63+M63+O63+Q63+S63 -> 0 | Z63: =+G63-V63-X63 -> 0 | AA63: =SUMIF($F$9:$F$63,$F63,$Z$9:$Z$63) -> 0
A64: ИТОГО СДЕЛКИ СО СВЯЗАННЫМИ ЛИЦАМИ | G64: =SUM(G9:G63) -> 123506538 | H64: =SUM(H9:H63) -> 0 | I64: =SUM(I9:I63) -> 977034 | J64: =SUM(J9:J63) -> 121962868 | K64: =SUM(K9:K63) -> 9821 | L64: =SUM(L9:L63) -> 0 | M64: =SUM(M9:M63) -> 0 | N64: =SUM(N9:N63) -> 0 | ... T64: =SUM(T9:T63) -> 0 | V64: =SUM(V9:V63) -> 0 | X64: =SUM(X9:X63) -> 0 | Y64: =SUM(Y9:Y63) -> 0 | Z64: =SUM(Z9:Z63) -> 123506538
A65: САМАЯ КРУПНАЯ СДЕЛКА, ЗАКЛЮЧЁННАЯ С ОДНИМ СВЯЗАННЫМ ЛИЦОМ | G65: =+SUMIF($F$9:$F$63,$AA$65,$G$9:$G$63) -> 83362868 | H65: =+SUMIF($F$9:$F$63,$AA$65,$H$9:$H$63) -> 0 | I65: =+SUMIF($F$9:$F$63,$AA$65,$I$9:$I$63) -> 0 | J65: =+SUMIF($F$9:$F$63,$AA$65,$J$9:$J$63) -> 83362868 | K65: =+SUMIF($F$9:$F$63,$AA$65,$K$9:$K$63) -> 0 | L65: =+SUMIF($F$9:$F$63,$AA$65,$L$9:$L$63) -> 0 | M65: =+SUMIF($F$9:$F$63,$AA$65,$M$9:$M$63) -> 0 | N65: =+SUMIF($F$9:$F$63,$AA$65,$N$9:$N$63) -> 0 | O65: =+SUMIF($F$9:$F$63,$AA$65,$O$9:$O$63) -> 0 | P65: =+SUMIF($F$9:$F$63,$AA$65,$P$9:$P$63) -> 0 | Q65: =+SUMIF($F$9:$F$63,$AA$65,$Q$9:$Q$63) -> 0 | R65: =+SUMIF($F$9:$F$63,$AA$65,$R$9:$R$63) -> 0 | S65: =+SUMIF($F$9:$F$63,$AA$65,$S$9:$S$63) -> 0 | T65: =+SUMIF($F$9:$F$63,$AA$65,$T$9:$T$63) -> 0 | V65: =+SUMIF($F$9:$F$63,$AA$65,$V$9:$V$63) -> 0 | X65: =+SUMIF($F$9:$F$63,$AA$65,$X$9:$X$63) -> 0 | Y65: =+SUMIF($F$9:$F$63,$AA$65,$Y$9:$Y$63) -> 0 | Z65: =+MAX(AA9:AA63) -> 83362868 | AA65: =INDEX($F$9:$F$63,MATCH($Z65,$AA$9:$AA$63,0)) -> 1
B68: Подпись Председателя Правления:
B70: Подпись Главного Бухгалтера:

Sheet  Largest risk
A1: ОТЧЕТ О КРУПНЫХ РИСКАХ | Y1: Таблица-12
B3: =+'Asset quality'!B3 -> "Ўзсаноатқурилишбанк" АТБ | U3: =+'Asset quality'!P3 -> 44560 | V3: =+#REF! -> #REF! | Y3: тыс. сум
A4: № | B4: Наименования клиента | C4: ИНН | D4: Вид деятельности | E4: Код валюты | F4: Номер группы | G4: Текущая задолженность, брутто | H4: из них | T4: Пересмотрения | U4: Вычеты из норматива | W4: Классификация | X4: Резерв | Y4: Источник кредита | Z4: Текущая задолженность, нетто
H5: балансовые | L5: внебалансовые
H6: Межбанковские кредиты и депозиты, остатки на кор счетах, средства для межбанковских взаиморасчетов, другие размещенные средства (кроме овернайта и клиринговых операций) и доходы по ним | I6: Кредиты/лизинги/факторинги и доходы по ним | J6: Инвестиции и доходы по ним | K6: Другие активы доходы по ним | L6: Аккредитивы и доходы по ним | N6: Гарантии/поручительства и доходы по ним | P6: Неиспользованные кредитные линии/безотзывные обязательства/ другие обязательства по выдаче кредитов доходы по ним | R6: Другие активы доходы по ним | U6: Вид обеспечения | V6: Сумма
L7: остаток | M7: по степени риска | N7: остаток | O7: по степени риска | P7: остаток | Q7: по степени риска | R7: остаток | S7: по степени риска
B8: А | C8: Б | D8: В | E8: Г | F8: Д | G8: Е | H8: Е1 | I8: Е2 | J8: Е3 | K8: Е4 | L8: Е5 | N8: Е6 | P8: Е7 | R8: Е8 | T8: Ж | U8: З | V8: И | W8: К | X8: Л | Y8: М | Z8: Н
A9: 1 | B9: АО НАВОИАЗОТ | C9: 200002933 | D9: 20151 | E9: 000 840 | F9: 1 | G9: =+H9+I9+J9+K9+M9+O9+Q9+S9 -> 1810093061 | H9: 0 | I9: 1757533591 | K9: 52559470 | L9: 0 | M9: 0 | N9: 0 | O9: 0 | P9: 0 | Q9: 0 | U9: 3 | V9: 1734933237 | W9: 1 | X9: 0 | Z9: =+G9-V9-X9 -> 75159824 | AA9: =SUMIF($F$9:$F$63,$F9,$Z$9:$Z$63) -> 200321277
A10: 2 | B10: "Dehqonobod kaliy zavodi" AJ | C10: 206887857 | D10: 20151 | E10: 000 840 | F10: 1 | G10: =+H10+I10+J10+K10+M10+O10+Q10+S10 -> 1001983001 | H10: 0 | I10: 1001701186 | K10: 281815 | L10: 0 | M10: 0 | N10: 0 | O10: 0 | P10: 0 | Q10: 0 | U10: 3 | V10: 999368974 | W10: 1 | X10: 0 | Z10: =+G10-V10-X10 -> 2614027 | AA10: =SUMIF($F$9:$F$63,$F10,$Z$9:$Z$63) -> 200321277
A11: 3 | B11: "QO'NG'IROT SODA ZAVODI" MCHJ QK | C11: 200949269 | D11: 20130 | E11: 000 840 | F11: 1 | G11: =+H11+I11+J11+K11+M11+O11+Q11+S11 -> 624945188 | H11: 0 | I11: 624945188 | K11: 0 | L11: 0 | M11: 0 | N11: 0 | O11: 0 | P11: 0 | Q11: 0 | U11: 3 | V11: 624945188 | W11: 1 | X11: 0 | Z11: =+G11-V11-X11 -> 0 | AA11: =SUMIF($F$9:$F$63,$F11,$Z$9:$Z$63) -> 200321277
A12: 4 | B12: MCHJ shaklidagi SAMARKAND-NPK QUSHMA KORXONASI | C12: 303295841 | D12: 20130 | E12: 840 | F12: 1 | G12: =+H12+I12+J12+K12+M12+O12+Q12+S12 -> 90442741 | H12: 0 | I12: 90442741 | K12: 0 | L12: 0 | M12: 0 | N12: 0 | O12: 0 | P12: 0 | Q12: 0 | T12: 1 | V12: 0 | W12: 3 | X12: 22610685 | Z12: =+G12-V12-X12 -> 67832056 | AA12: =SUMIF($F$9:$F$63,$F12,$Z$9:$Z$63) -> 200321277
A13: 5 | B13: OAO АММОФОС | C13: 200599579 | D13: 20151 | E13: 840 | F13: 1 | G13: =+H13+I13+J13+K13+M13+O13+Q13+S13 -> 50302394 | H13: 0 | I13: 50302259 | K13: 135 | L13: 0 | M13: 0 | N13: 0 | O13: 0 | P13: 0 | Q13: 0 | V13: 0 | W13: 1 | X13: 0 | Z13: =+G13-V13-X13 -> 50302394 | AA13: =SUMIF($F$9:$F$63,$F13,$Z$9:$Z$63) -> 200321277
A14: 6 | B14: Samarkandkimyo ОАО 200613251 | C14: 200613251 | D14: 20151 | E14: 000 | F14: 1 | G14: =+H14+I14+J14+K14+M14+O14+Q14+S14 -> 4412976 | H14: 0 | I14: 4412962 | K14: 14 | L14: 0 | M14: 0 | N14: 0 | O14: 0 | P14: 0 | Q14: 0 | V14: 0 | W14: 1 | X14: 0 | Z14: =+G14-V14-X14 -> 4412976 | AA14: =SUMIF($F$9:$F$63,$F14,$Z$9:$Z$63) -> 200321277
A15: 7 | B15: UZBEKISTON TEMIR YULLARI AJ | C15: 201051951 | D15: 49200 | E15: 840 | F15: 2 | G15: =+H15+I15+J15+K15+M15+O15+Q15+S15 -> 1469622849 | H15: 0 | I15: 1429892480 | K15: 577762 | L15: 0 | M15: 0 | N15: 0 | O15: 0 | P15: 195763034 | Q15: 39152607 | U15: 3 | V15: 1469045087 | W15: 1 | X15: 0 | Z15: =+G15-V15-X15 -> 577762 | AA15: =SUMIF($F$9:$F$63,$F15,$Z$9:$Z$63) -> 277189861
A16: 8 | B16: "О`ZBEKKO`MIR" AJ | C16: 200899410 | D16: 05200 | E16: 000 840 | F16: 2 | G16: =+H16+I16+J16+K16+M16+O16+Q16+S16 -> 794065223 | H16: 0 | I16: 781449149 | K16: 476074 | L16: 0 | M16: 0 | N16: 0 | O16: 0 | P16: 12140000 | Q16: 12140000 | U16: 3 | V16: 748627808 | W16: 1 | X16: 0 | Z16: =+G16-V16-X16 -> 45437415 | AA16: =SUMIF($F$9:$F$63,$F16,$Z$9:$Z$63) -> 277189861
A17: 9 | B17: AJ OZTEMIRYOLYOLOVCHI | C17: 202472894 | D17: 49100 | E17: 840 | F17: 2 | G17: =+H17+I17+J17+K17+M17+O17+Q17+S17 -> 141500986 | H17: 0 | I17: 132566657 | K17: 8934329 | L17: 0 | M17: 0 | N17: 0 | O17: 0 | P17: 0 | Q17: 0 | V17: 0 | W17: 1 | X17: 0 | Z17: =+G17-V17-X17 -> 141500986 | AA17: =SUMIF($F$9:$F$63,$F17,$Z$9:$Z$63) -> 277189861
A18: 10 | B18: "QO'QON BIOKIMYO" АЖ | C18: 200126834 | D18: 11010 | E18: 000 978 | F18: 2 | G18: =+H18+I18+J18+K18+M18+O18+Q18+S18 -> 50102269 | H18: 0 | I18: 50102269 | K18: 0 | L18: 0 | M18: 0 | N18: 0 | O18: 0 | P18: 0 | Q18: 0 | V18: 0 | W18: 1 | X18: 0 | Z18: =+G18-V18-X18 -> 50102269 | AA18: =SUMIF($F$9:$F$63,$F18,$Z$9:$Z$63) -> 277189861
A19: 11 | B19: "OZTEMIRYOLKONTEYNER" AJ | C19: 203607858 | D19: 52100 | E19: 000 | F19: 2 | G19: =+H19+I19+J19+K19+M19+O19+Q19+S19 -> 38571429 | H19: 0 | I19: 38571429 | K19: 0 | L19: 0 | M19: 0 | N19: 0 | O19: 0 | P19: 0 | Q19: 0 | V19: 0 | W19: 1 | X19: 0 | Z19: =+G19-V19-X19 -> 38571429 | AA19: =SUMIF($F$9:$F$63,$F19,$Z$9:$Z$63) -> 277189861
A20: 12 | B20: УП Ekskavatorlar va gusenitsali texnikani ta"mirlash zavodi | C20: 304172875 | D20: 33120 | E20: 000 | F20: 2 | G20: =+H20+I20+J20+K20+M20+O20+Q20+S20 -> 1000000 | H20: 0 | I20: 1000000 | K20: 0 | L20: 0 | M20: 0 | N20: 0 | O20: 0 | P20: 0 | Q20: 0 | V20: 0 | W20: 1 | X20: 0 | Z20: =+G20-V20-X20 -> 1000000 | AA20: =SUMIF($F$9:$F$63,$F20,$Z$9:$Z$63) -> 277189861
A21: 13 | B21: AO O ZBEKNEFTGAZ | C21: 200837914 | D21: 84111 | E21: 000 840 978 | F21: 3 | G21: =+H21+I21+J21+K21+M21+O21+Q21+S21 -> 2133854552 | H21: 0 | I21: 1988269265 | K21: 141713632 | L21: 3871655 | M21: 3871655 | N21: 0 | O21: 0 | P21: 0 | Q21: 0 | U21: 6 | V21: 1745842599 | W21: 1 | X21: 0 | Z21: =+G21-V21-X21 -> 388011953 | AA21: =SUMIF($F$9:$F$63,$F21,$Z$9:$Z$63) -> 522683791
A22: 14 | B22: Бухарский нефтеперерабатывающий завод | C22: 202080378 | D22: 19200 | E22: 000 | F22: 3 | G22: =+H22+I22+J22+K22+M22+O22+Q22+S22 -> 120048082 | H22: 0 | I22: 107169082 | K22: 0 | L22: 0 | M22: 0 | N22: 12879000 | O22: 12879000 | P22: 0 | Q22: 0 | V22: 0 | W22: 1 | X22: 0 | Z22: =+G22-V22-X22 -> 120048082 | AA22: =SUMIF($F$9:$F$63,$F22,$Z$9:$Z$63) -> 522683791
A23: 15 | B23: ООО"Ферганский нефтеперерабатывающий завод" | E23: 000 | F23: 3 | G23: =+H23+I23+J23+K23+M23+O23+Q23+S23 -> 14623756 | H23: 0 | I23: 0 | K23: 0 | L23: 0 | M23: 0 | N23: 14623756 | O23: 14623756 | P23: 0 | Q23: 0 | V23: 0 | X23: 0 | Z23: =+G23-V23-X23 -> 14623756 | AA23: =SUMIF($F$9:$F$63,$F23,$Z$9:$Z$63) -> 522683791
A24: 16 | B24: " ANGREN ISSIQLIK ELEKTR STANSIYASI" акциядорлик жамияти | C24: 200595949 | D24: 35111 | E24: 840 | F24: 4 | G24: =+H24+I24+J24+K24+M24+O24+Q24+S24 -> 1455439278 | H24: 0 | I24: 1455439278 | K24: 0 | L24: 0 | M24: 0 | N24: 0 | O24: 0 | P24: 0 | Q24: 0 | U24: 3 | V24: 1455439278 | W24: 1 | X24: 0 | Z24: =+G24-V24-X24 -> 0 | AA24: =SUMIF($F$9:$F$63,$F24,$Z$9:$Z$63) -> 600454095
A25: 17 | B25: Yangi Angren Issiqlik Elektr Stansiyasi Aksiyadorlik Jamiyati | C25: 200595838 | D25: 35111 | E25: 000 840 978 | F25: 4 | G25: =+H25+I25+J25+K25+M25+O25+Q25+S25 -> 377309672 | H25: 0 | I25: 377309672 | K25: 0 | L25: 0 | M25: 0 | N25: 0 | O25: 0 | P25: 0 | Q25: 0 | U25: 3 | V25: 270061 | W25: 1 | X25: 0 | Z25: =+G25-V25-X25 -> 377039611 | AA25: =SUMIF($F$9:$F$63,$F25,$Z$9:$Z$63) -> 600454095
A26: 18 | B26: АО "SIRDARYO ISSIQLIK ELEKTR STANSIYASI" | C26: 201169179 | D26: 35111 | E26: 000 840 978 | F26: 4 | G26: =+H26+I26+J26+K26+M26+O26+Q26+S26 -> 248376264 | H26: 0 | I26: 248255716 | K26: 120548 | L26: 0 | M26: 0 | N26: 0 | O26: 0 | P26: 0 | Q26: 0 | U26: 3 | V26: 150143418 | W26: 1 | X26: 0 | Z26: =+G26-V26-X26 -> 98232846 | AA26: =SUMIF($F$9:$F$63,$F26,$Z$9:$Z$63) -> 600454095
A27: 19 | B27: АО " TOSHKENT ISSIQLIK ELEKTR STANSIYA " | C27: 200605388 | D27: 35111 | E27: 000 978 | F27: 4 | G27: =+H27+I27+J27+K27+M27+O27+Q27+S27 -> 108402230 | H27: 0 | I27: 108402230 | K27: 0 | L27: 0 | M27: 0 | N27: 0 | O27: 0 | P27: 0 | Q27: 0 | V27: 0 | W27: 1 | X27: 0 | Z27: =+G27-V27-X27 -> 108402230 | AA27: =SUMIF($F$9:$F$63,$F27,$Z$9:$Z$63) -> 600454095
A28: 20 | B28: FARGONA ISSIQLIQ ELEQTR MARKAZI ОЧИК АКЦИОНЕРЛИК ЖАМИЯТИ | C28: 200202146 | D28: 35300 | E28: 000 | F28: 4 | G28: =+H28+I28+J28+K28+M28+O28+Q28+S28 -> 16779408 | H28: 0 | I28: 16779078 | K28: 330 | L28: 0 | M28: 0 | N28: 0 | O28: 0 | P28: 0 | Q28: 0 | V28: 0 | W28: 1 | X28: 0 | Z28: =+G28-V28-X28 -> 16779408 | AA28: =SUMIF($F$9:$F$63,$F28,$Z$9:$Z$63) -> 600454095
A29: 21 | B29: СП ООО "SIRDARYO MEGA LUKS" | C29: 301024585 | D29: 22220 | E29: 000 840 978 | F29: 5 | G29: =+H29+I29+J29+K29+M29+O29+Q29+S29 -> 1503499186 | H29: 0 | I29: 1179515483 | K29: 102974413 | L29: 221009290 | M29: 221009290 | N29: 0 | O29: 0 | P29: 0 | Q29: 0 | V29: 0 | W29: 1 | X29: 0 | Z29: =+G29-V29-X29 -> 1503499186 | AA29: =SUMIF($F$9:$F$63,$F29,$Z$9:$Z$63) -> 1503499186
A30: 22 | B30: "TOSHKENT METALLURGIYA ZAVODI" MChJ QK | C30: 304574612 | D30: 28910 | E30: 840 | F30: 6 | G30: =+H30+I30+J30+K30+M30+O30+Q30+S30 -> 1175605826 | H30: 0 | I30: 1171270335 | K30: 0 | L30: 0 | M30: 0 | N30: 0 | O30: 0 | P30: 21677454 | Q30: 4335491 | V30: 0 | W30: 1 | X30: 0 | Z30: =+G30-V30-X30 -> 1175605826 | AA30: =SUMIF($F$9:$F$63,$F30,$Z$9:$Z$63) -> 1175605826
A31: 23 | B31: АЖ "O'ZTRANSGAZ" | C31: 200626188 | D31: 49500 | E31: 840 | F31: 7 | G31: =+H31+I31+J31+K31+M31+O31+Q31+S31 -> 1130180482 | H31: 0 | I31: 1063461832 | K31: 66718650 | L31: 0 | M31: 0 | N31: 0 | O31: 0 | P31: 0 | Q31: 0 | U31: 3 | V31: 0 | W31: 1 | X31: 0 | Z31: =+G31-V31-X31 -> 1130180482 | AA31: =SUMIF($F$9:$F$63,#REF!,$Z$9:$Z$63) -> 0
A32: 24 | B32: CITIBANK N.A. | E32: 840 | F32: 8 | G32: =+H32+I32+J32+K32+M32+O32+Q32+S32 -> 1038872118 | H32: 1038872118 | I32: 0 | K32: 0 | L32: 0 | M32: 0 | N32: 0 | O32: 0 | P32: 0 | Q32: 0 | V32: 0 | X32: 0 | Z32: =+G32-V32-X32 -> 1038872118 | AA32: =SUMIF($F$9:$F$63,$F31,$Z$9:$Z$63) -> 1130180482
A33: 25 | B33: G'UZOR TEKSTIL IMPEKS МЧЖ | C33: 304720106 | D33: 13201 | E33: 000 840 978 | F33: 9 | G33: =+H33+I33+J33+K33+M33+O33+Q33+S33 -> 1034111403 | H33: 0 | I33: 896175768 | K33: 38604818 | L33: 0 | M33: 0 | N33: 99330817 | O33: 99330817 | P33: 0 | Q33: 0 | V33: 0 | W33: 1 | X33: 0 | Z33: =+G33-V33-X33 -> 1034111403 | AA33: =SUMIF($F$9:$F$63,$F32,$Z$9:$Z$63) -> 1038872118
A34: 26 | B34: "APK BUKA" МЧЖ | C34: 307240259 | D34: 01161 | E34: 000 | F34: 10 | G34: =+H34+I34+J34+K34+M34+O34+Q34+S34 -> 291987972 | H34: 0 | I34: 188023930 | K34: 0 | L34: 0 | M34: 0 | N34: 0 | O34: 0 | P34: 103964042 | Q34: 103964042 | V34: 0 | W34: 1 | X34: 0 | Z34: =+G34-V34-X34 -> 291987972 | AA34: =SUMIF($F$9:$F$63,$F34,$Z$9:$Z$63) -> 1232377640
A35: 27 | B35: "APK BEKABOD" МЧЖ | C35: 306912173 | D35: 13101 | E35: 000 | F35: 10 | G35: =+H35+I35+J35+K35+M35+O35+Q35+S35 -> 290364053 | H35: 0 | I35: 186613247 | K35: 1276 | L35: 0 | M35: 0 | N35: 0 | O35: 0 | P35: 103749530 | Q35: 103749530 | V35: 0 | W35: 1 | X35: 0 | Z35: =+G35-V35-X35 -> 290364053 | AA35: =SUMIF($F$9:$F$63,$F35,$Z$9:$Z$63) -> 1232377640
A36: 28 | B36: МЧЖ "TEXTILE TECHNOLOGIES GROUP" ХК. | C36: 207071646 | D36: 13101 | E36: 000 840 978 | F36: 10 | G36: =+H36+I36+J36+K36+M36+O36+Q36+S36 -> 258762872 | H36: 0 | I36: 85429939 | K36: 805313 | L36: 0 | M36: 0 | N36: 172527620 | O36: 172527620 | P36: 0 | Q36: 0 | V36: 0 | W36: 1 | X36: 0 | Z36: =+G36-V36-X36 -> 258762872 | AA36: =SUMIF($F$9:$F$63,$F36,$Z$9:$Z$63) -> 1232377640
A37: 29 | B37: УП "APK OQOLTIN" | C37: 306980240 | D37: 01161 | E37: 000 | F37: 10 | G37: =+H37+I37+J37+K37+M37+O37+Q37+S37 -> 226061986 | H37: 0 | I37: 124229333 | K37: 0 | L37: 0 | M37: 0 | N37: 0 | O37: 0 | P37: 101832653 | Q37: 101832653 | V37: 0 | W37: 1 | X37: 0 | Z37: =+G37-V37-X37 -> 226061986 | AA37: =SUMIF($F$9:$F$63,$F37,$Z$9:$Z$63) -> 1232377640
A38: 30 | B38: УП "APK CHINOZ" | C38: 306713871 | D38: 10610 | E38: 000 | F38: 10 | G38: =+H38+I38+J38+K38+M38+O38+Q38+S38 -> 165200757 | H38: 0 | I38: 110584132 | K38: 0 | L38: 0 | M38: 0 | N38: 0 | O38: 0 | P38: 54616625 | Q38: 54616625 | V38: 0 | W38: 1 | X38: 0 | Z38: =+G38-V38-X38 -> 165200757 | AA38: =SUMIF($F$9:$F$63,$F38,$Z$9:$Z$63) -> 1232377640
A39: 31 | B39: JPMORGAN CHASE BANK, N.A. | E39: 840 | F39: 11 | G39: =+H39+I39+J39+K39+M39+O39+Q39+S39 -> 1014765816 | H39: 1014765816 | I39: 0 | K39: 0 | L39: 0 | M39: 0 | N39: 0 | O39: 0 | P39: 0 | Q39: 0 | V39: 0 | X39: 0 | Z39: =+G39-V39-X39 -> 1014765816 | AA39: =SUMIF($F$9:$F$63,$F39,$Z$9:$Z$63) -> 1014765816
A40: 32 | B40: ИП ООО "EPSILON DEVELOPMENT COMPANY" | C40: 305922787 | D40: 06200 | E40: 000 840 978 | F40: 12 | G40: =+H40+I40+J40+K40+M40+O40+Q40+S40 -> 981420226 | H40: 0 | I40: 936637947 | K40: 44782279 | L40: 0 | M40: 0 | N40: 0 | O40: 0 | P40: 0 | Q40: 0 | V40: 0 | W40: 1 | X40: 0 | Z40: =+G40-V40-X40 -> 981420226 | AA40: =SUMIF($F$9:$F$63,$F40,$Z$9:$Z$63) -> 981420226
A41: 33 | B41: "TEXNOPARK" MCHJ | C41: 306493973 | D41: 27510 | E41: 000 840 978 | F41: 13 | G41: =+H41+I41+J41+K41+M41+O41+Q41+S41 -> 835286286 | H41: 0 | I41: 782692702 | K41: 35330346 | L41: 17220626 | M41: 17220626 | N41: 0 | O41: 0 | P41: 213059 | Q41: 42612 | V41: 0 | W41: 1 | X41: 0 | Z41: =+G41-V41-X41 -> 835286286 | AA41: =SUMIF($F$9:$F$63,$F41,$Z$9:$Z$63) -> 835286286
A42: 34 | B42: ООО "GLOBAL TEXTILE INFINITY" | E42: 978 | F42: 14 | G42: =+H42+I42+J42+K42+M42+O42+Q42+S42 -> 757388198 | H42: 0 | I42: 0 | K42: 0 | L42: 757388198 | M42: 757388198 | N42: 0 | O42: 0 | P42: 0 | Q42: 0 | V42: 0 | X42: 0 | Z42: =+G42-V42-X42 -> 757388198 | AA42: =SUMIF($F$9:$F$63,$F42,$Z$9:$Z$63) -> 757388198
A43: 35 | B43: ГП НАВОИ ГОРНОМЕТАЛЛУРГИЧЕСК.КОМБИНАТ | C43: 201204514 | D43: 07290 | E43: 840 | F43: 15 | G43: =+H43+I43+J43+K43+M43+O43+Q43+S43 -> 748550371 | H43: 0 | I43: 748550371 | K43: 0 | L43: 0 | M43: 0 | N43: 0 | O43: 0 | P43: 0 | Q43: 0 | V43: 0 | W43: 1 | X43: 0 | Z43: =+G43-V43-X43 -> 748550371 | AA43: =SUMIF($F$9:$F$63,$F43,$Z$9:$Z$63) -> 748550371
A44: 36 | B44: АСАКА БАНК | E44: 840 | F44: 16 | G44: =+H44+I44+J44+K44+M44+O44+Q44+S44 -> 694845289 | H44: 0 | I44: 0 | K44: 0 | L44: 0 | M44: 0 | N44: 694845289 | O44: 694845289 | P44: 0 | Q44: 0 | V44: 0 | X44: 0 | Z44: =+G44-V44-X44 -> 694845289 | AA44: =SUMIF($F$9:$F$63,$F44,$Z$9:$Z$63) -> 694845289
A45: 37 | B45: ООО "AMIRSOY" | C45: 305152772 | D45: 93290 | E45: 000 840 978 | F45: 17 | G45: =+H45+I45+J45+K45+M45+O45+Q45+S45 -> 690786224 | H45: 0 | I45: 659170596 | K45: 31087245 | L45: 528383 | M45: 528383 | N45: 0 | O45: 0 | P45: 0 | Q45: 0 | V45: 0 | W45: 1 | X45: 0 | Z45: =+G45-V45-X45 -> 690786224 | AA45: =SUMIF($F$9:$F$63,$F45,$Z$9:$Z$63) -> 690786224
A46: 38 | G46: =+H46+I46+J46+K46+M46+O46+Q46+S46 -> 0 | Z46: =+G46-V46-X46 -> 0 | AA46: =SUMIF($F$9:$F$63,$F46,$Z$9:$Z$63) -> 0
A47: 39 | G47: =+H47+I47+J47+K47+M47+O47+Q47+S47 -> 0 | Z47: =+G47-V47-X47 -> 0 | AA47: =SUMIF($F$9:$F$63,$F47,$Z$9:$Z$63) -> 0
A48: 40 | G48: =+H48+I48+J48+K48+M48+O48+Q48+S48 -> 0 | Z48: =+G48-V48-X48 -> 0 | AA48: =SUMIF($F$9:$F$63,$F48,$Z$9:$Z$63) -> 0
A49: 41 | G49: =+H49+I49+J49+K49+M49+O49+Q49+S49 -> 0 | Z49: =+G49-V49-X49 -> 0 | AA49: =SUMIF($F$9:$F$63,$F49,$Z$9:$Z$63) -> 0
A50: 42 | G50: =+H50+I50+J50+K50+M50+O50+Q50+S50 -> 0 | Z50: =+G50-V50-X50 -> 0 | AA50: =SUMIF($F$9:$F$63,$F50,$Z$9:$Z$63) -> 0
A51: 43 | G51: =+H51+I51+J51+K51+M51+O51+Q51+S51 -> 0 | Z51: =+G51-V51-X51 -> 0 | AA51: =SUMIF($F$9:$F$63,$F51,$Z$9:$Z$63) -> 0
A52: 44 | G52: =+H52+I52+J52+K52+M52+O52+Q52+S52 -> 0 | Z52: =+G52-V52-X52 -> 0 | AA52: =SUMIF($F$9:$F$63,$F52,$Z$9:$Z$63) -> 0
A53: 45 | G53: =+H53+I53+J53+K53+M53+O53+Q53+S53 -> 0 | Z53: =+G53-V53-X53 -> 0 | AA53: =SUMIF($F$9:$F$63,$F53,$Z$9:$Z$63) -> 0
A54: 46 | G54: =+H54+I54+J54+K54+M54+O54+Q54+S54 -> 0 | Z54: =+G54-V54-X54 -> 0 | AA54: =SUMIF($F$9:$F$63,$F54,$Z$9:$Z$63) -> 0
A55: 47 | G55: =+H55+I55+J55+K55+M55+O55+Q55+S55 -> 0 | Z55: =+G55-V55-X55 -> 0 | AA55: =SUMIF($F$9:$F$63,$F55,$Z$9:$Z$63) -> 0
A56: 48 | G56: =+H56+I56+J56+K56+M56+O56+Q56+S56 -> 0 | Z56: =+G56-V56-X56 -> 0 | AA56: =SUMIF($F$9:$F$63,$F56,$Z$9:$Z$63) -> 0
A57: 49 | G57: =+H57+I57+J57+K57+M57+O57+Q57+S57 -> 0 | Z57: =+G57-V57-X57 -> 0 | AA57: =SUMIF($F$9:$F$63,$F57,$Z$9:$Z$63) -> 0
... A63: 55 | G63: =+H63+I63+J63+K63+M63+O63+Q63+S63 -> 0 | Z63: =+G63-V63-X63 -> 0 | AA63: =SUMIF($F$9:$F$63,$F63,$Z$9:$Z$63) -> 0
B64: ИТОГО КРУПНЫХ АКТИВОВ | G64: =SUM(G9:G63) -> 23389564424 | H64: =SUM(H9:H63) -> 2053637934 | I64: =SUM(I9:I63) -> 18396899847 | J64: =SUM(J9:J63) -> 0 | K64: =SUM(K9:K63) -> 524968449 | L64: =SUM(L9:L63) -> 1000018152 | M64: =SUM(M9:M63) -> 1000018152 | N64: =SUM(N9:N63) -> 994206482 | ... T64: =SUM(T9:T63) -> 1 | V64: =SUM(V9:V63) -> 8928615650 | X64: =SUM(X9:X63) -> 22610685 | Y64: =SUM(Y9:Y63) -> 0 | Z64: =SUM(Z9:Z63) -> 14438338089
B65: САМЫЙ КРУПНЫЙ АКТИВ, ВЫДАННЫЙ БАНКОМ | G65: =+SUMIF($F$9:$F$63,$AA$65,$G$9:$G$63) -> 1503499186 | H65: =+SUMIF($F$9:$F$63,$AA$65,$H$9:$H$63) -> 0 | I65: =+SUMIF($F$9:$F$63,$AA$65,$I$9:$I$63) -> 1179515483 | J65: =+SUMIF($F$9:$F$63,$AA$65,$J$9:$J$63) -> 0 | K65: =+SUMIF($F$9:$F$63,$AA$65,$K$9:$K$63) -> 102974413 | L65: =+SUMIF($F$9:$F$63,$AA$65,$L$9:$L$63) -> 221009290 | M65: =+SUMIF($F$9:$F$63,$AA$65,$M$9:$M$63) -> 221009290 | N65: =+SUMIF($F$9:$F$63,$AA$65,$N$9:$N$63) -> 0 | O65: =+SUMIF($F$9:$F$63,$AA$65,$O$9:$O$63) -> 0 | P65: =+SUMIF($F$9:$F$63,$AA$65,$P$9:$P$63) -> 0 | Q65: =+SUMIF($F$9:$F$63,$AA$65,$Q$9:$Q$63) -> 0 | R65: =+SUMIF($F$9:$F$63,$AA$65,$R$9:$R$63) -> 0 | S65: =+SUMIF($F$9:$F$63,$AA$65,$S$9:$S$63) -> 0 | T65: =+SUMIF($F$9:$F$63,$AA$65,$T$9:$T$63) -> 0 | V65: =+SUMIF($F$9:$F$63,$AA$65,$V$9:$V$63) -> 0 | X65: =+SUMIF($F$9:$F$63,$AA$65,$X$9:$X$63) -> 0 | Y65: =+SUMIF($F$9:$F$63,$AA$65,$Y$9:$Y$63) -> 0 | Z65: =+MAX(AA9:AA63) -> 1503499186 | AA65: =INDEX($F$9:$F$63,MATCH($Z65,$AA$9:$AA$63,0)) -> 5
B68: Подпись Председателя правления:
B70: Подпись Главного Бухгалтера:

Sheet Charge-offs and Recoveries
A1: ОТЧЕТ О CПИСАННЫХ И ВОЗВРАЩЕННЫХ КРЕДИТАХ И ЛИЗИНГАХ, А ТАКЖЕ РЕЗЕРВАХ ПО НИМ | J1: Таблица-13
A3: Часть 1 Списания и возврат сумму кредитов и лизинга за последние 12 месяцев | I3: =+'Asset quality'!P3 -> 44560
A4: № | B4: Отрасли экономики и виды кредитования | C4: ="Остаток списаных кредита и лизинга на"&" "&DAY(I3)&"."&IF(LEN(MONTH(I3))<2,"0"&MONTH(I3),MONTH(I3))&"."&YEAR(I3)-1&"г" -> Остаток списаных кредита и лизинга на 30.12.2020г | D4: Списания и возврат кредитов и лизингов | J4: ="Остаток списаных кредита и лизинга на"&" "&DAY(I3)&"."&IF(LEN(MONTH(I3))<2,"0"&MONTH(I3),MONTH(I3))&"."&YEAR(I3)&"г" -> Остаток списаных кредита и лизинга на 30.12.2021г
D5: Списанние на забалансовый счет | F5: Возврат из забалансового счета | H5: Итоговое списанние из забалансового счета
D6: Всего | E6: в иностранной валюте | F6: Всего | G6: в иностранной валюте | H6: Всего | I6: в иностранной валюте
B7: А | C7: Б | D7: В | E7: Г | F7: Д | G7: Е | H7: Ж | I7: З | J7: И
A8: 1 | B8: Юридические лица | C8: =SUM(C10:C17) -> 52295031 | D8: =SUM(D10:D17) -> 343824716 | E8: =SUM(E10:E17) -> 125046314 | F8: =SUM(F10:F17) -> 4653231 | G8: =SUM(G10:G17) -> 0 | H8: =SUM(H10:H17) -> 343824716 | I8: =SUM(I10:I17) -> 125046314 | J8: =SUM(J10:J17) -> 392003417
B9: из них
A10: 1.1. | B10: Промышленность | C10: 119857 | D10: 9556460 | E10: 2890046 | F10: 0 | G10: 0 | H10: 9556460 | I10: 2890046 | J10: 9676317
A11: 1.2. | B11: Сельское хозяйство | C11: 721270 | D11: 13005222 | E11: 8011870 | F11: 0 | G11: 0 | H11: 13005222 | I11: 8011870 | J11: 13726492
A12: 1.3. | B12: Транспорт и коммуникации | C12: 0 | D12: 30104804 | E12: 21103710 | F12: 0 | G12: 0 | H12: 30104804 | I12: 21103710 | J12: 30104804
A13: 1.4. | B13: Строительство | C13: 7987120 | D13: 48299985 | E13: 18940248 | F13: 0 | G13: 0 | H13: 48299985 | I13: 18940248 | J13: 56287105
A14: 1.5. | B14: Торговля и общественное питание | C14: 1229128 | D14: 35140403 | E14: 4803693 | F14: 0 | G14: 0 | H14: 35140403 | I14: 4803693 | J14: 36411088
A15: 1.6. | B15: Материально-техническое снабжение и сбыт | C15: 0 | D15: 0 | E15: 0 | F15: 0 | G15: 0 | H15: 0 | I15: 0 | J15: 0
A16: 1.7. | B16: Жилищно-коммунальные услуги | C16: 0 | D16: 0 | E16: 0 | F16: 0 | G16: 0 | H16: 0 | I16: 0 | J16: 0
A17: 1.8. | B17: Другие сектора | C17: 42237656 | D17: 207717842 | E17: 69296747 | F17: 4653231 | G17: 0 | H17: 207717842 | I17: 69296747 | J17: 245797611
A18: 2 | B18: Физические лица | C18: =SUM(C20:C24) -> 24675 | D18: =SUM(D20:D24) -> 47191486 | E18: =SUM(E20:E24) -> 0 | F18: =SUM(F20:F24) -> 4510 | G18: =SUM(G20:G24) -> 0 | H18: =SUM(H20:H24) -> 0 | I18: =SUM(I20:I24) -> 0 | J18: =SUM(J20:J24) -> 47211621
B19: из них
A20: 2.1. | B20: Ипотечный кредит | C20: 24675 | D20: 0 | E20: 0 | F20: 4510 | G20: 0 | H20: 0 | I20: 0 | J20: 20165
A21: 2.2. | B21: Автокредит | C21: 0 | D21: 1164070 | E21: 0 | F21: 0 | G21: 0 | H21: 0 | I21: 0 | J21: 1164040
A22: 2.3. | B22: Микрозаймы и овердрафты (все нецелевые кредиты) | C22: 0 | D22: 17428724 | E22: 0 | F22: 0 | G22: 0 | H22: 0 | I22: 0 | J22: 17428724
A23: 2.4. | B23: потребительские кредиты | C23: 0 | D23: 12228348 | E23: 0 | F23: 0 | G23: 0 | H23: 0 | I23: 0 | J23: 12228348
A24: 2.5. | B24: другие кредиты физическим лицам | C24: 0 | D24: 16370344 | E24: 0 | F24: 0 | G24: 0 | H24: 0 | I24: 0 | J24: 16370344
A25: 3 | B25: Итого | C25: =+C18+C8 -> 52319706 | D25: =+D18+D8 -> 391016202 | E25: =+E18+E8 -> 125046314 | F25: =+F18+F8 -> 4657741 | G25: =+G18+G8 -> 0 | H25: =+H18+H8 -> 343824716 | I25: =+I18+I8 -> 125046314 | J25: =+J18+J8 -> 439215038
A27: Часть 2 Списанные и возвращенные резервы по кредитам и лизингам за последние 12 месяцев
A28: № | B28: Отрасли экономики и виды кредитования | C28: ="Резервы возможных потерь по кредитам и лизингу на"&" "&DAY(I3)&"."&IF(LEN(MONTH(I3))<2,"0"&MONTH(I3),MONTH(I3))&"."&YEAR(I3)-1&"г" -> Резервы возможных потерь по кредитам и лизингу на 30.12.2020г | D28: Списания и возврат резервов по кредитам и лизингам | H28: Движение по резервам за последние 12 месяцев | I28: ="Резервы возможных потерь по кредитам и лизингу на"&" "&DAY(I3)&"."&IF(LEN(MONTH(I3))<2,"0"&MONTH(I3),MONTH(I3))&"."&YEAR(I3)&"г" -> Резервы возможных потерь по кредитам и лизингу на 30.12.2021г
D29: Списание резервов | F29: Возврат резервов
D30: Всего | E30: в иностранной валюте | F30: Всего | G30: в иностранной валюте
B31: А | C31: Б | D31: В | E31: Г | F31: Д | G31: Е | H31: Ж | I31: З
A32: 1 | B32: Юридические лица | C32: =SUM(C34:C41) -> 1230977819 | D32: =SUM(D34:D41) -> 0 | E32: =SUM(E34:E41) -> 0 | F32: =SUM(F34:F41) -> 0 | G32: =SUM(G34:G41) -> 0 | H32: =SUM(H34:H41) -> 0 | I32: =SUM(I34:I41) -> 976127626
B33: из них
A34: 1.1. | B34: Промышленность | C34: 818297319 | I34: 498723431
A35: 1.2. | B35: Сельское хозяйство | C35: 103009625 | I35: 153252564
A36: 1.3. | B36: Транспорт и коммуникации | C36: 138640659 | I36: 61866739
A37: 1.4. | B37: Строительство | C37: 35869509 | I37: 28448988
A38: 1.5. | B38: Торговля и общественное питание | C38: 58906369 | I38: 77168139
A39: 1.6. | B39: Материально-техническое снабжение и сбыт | C39: 12249247 | I39: 11629533
A40: 1.7. | B40: Жилищно-коммунальные услуги | C40: 22019688 | I40: 56254474
A41: 1.8. | B41: Другие сектора | C41: 41985403 | I41: 88783758
A42: 2 | B42: Физические лица | C42: =SUM(C44:C48) -> 66034761 | D42: =SUM(D44:D48) -> 0 | E42: =SUM(E44:E48) -> 0 | F42: =SUM(F44:F48) -> 0 | G42: =SUM(G44:G48) -> 0 | H42: =SUM(H44:H48) -> 0 | I42: =SUM(I44:I48) -> 130391055
B43: из них
A44: 2.1. | B44: Ипотечный кредит | C44: 22056001 | I44: 88355158
A45: 2.2. | B45: Автокредит | C45: 5708038 | I45: 7624891
A46: 2.3. | B46: Микрозаймы и овердрафты (все нецелевые кредиты) | C46: 24287112 | I46: 19089072
A47: 2.4. | B47: потребительские кредиты | C47: 8853281 | I47: 13027278
A48: 2.5. | B48: другие кредиты физическим лицам | C48: 5130329 | I48: 2294656
A49: 3 | B49: Итого | C49: =+C42+C32 -> 1297012580 | D49: =+D42+D32 -> 0 | E49: =+E42+E32 -> 0 | F49: =+F42+F32 -> 0 | G49: =+G42+G32 -> 0 | H49: =+H42+H32 -> 0 | I49: =+I42+I32 -> 1106518681
B51: Подпись Председателя правления:
B53: Подпись Главного Бухгалтера:

Sheet loans_av rate
A1: ДАННЫЕ О СРЕДНЕВЗВЕШЕННЫХ ПРОЦЕНТНЫХ СТАВКАХ ПО КРЕДИТАМ | H1: Таблица-20
B3: =+'Asset quality'!B3 -> "Ўзсаноатқурилишбанк" АТБ | F3: =+'Asset quality'!P3 -> 44560 | H3: тыс. сум
A4: № | B4: Виды кредитования | C4: всего | E4: в том числе
E5: в национальный валюте | G5: в иностранной валюте
C6: остаток всего | D6: средневзвешенные процентные ставки | E6: остаток всего | F6: средневзвешенные процентные ставки | G6: остаток всего | H6: средневзвешенные процентные ставки
B7: А | C7: Б | D7: В | E7: Г | F7: Д | G7: Е | H7: Ж
A8: 1 | B8: Физические лица (льготные кредиты) | C8: =SUM(C10:C14) -> 2600627150 | D8: =IFERROR(((C10*D10)/C8)+((C11*D11)/C8)+((C12*D12)/C8)+((C13*D13)/C8)+((C14*D14)/C8),0) -> 0.082677528 | E8: =SUM(E10:E14) -> 2600627150 | F8: =IFERROR(((E10*F10)/E8)+((E11*F11)/E8)+((E12*F12)/E8)+((E13*F13)/E8)+((E14*F14)/E8),0) -> 0.082677528 | G8: =SUM(G10:G14) -> 0 | H8: =IFERROR(((G10*H10)/G8)+((G11*H11)/G8)+((G12*H12)/G8)+((G13*H13)/G8)+((G14*H14)/G8),0) -> 0 | J8: =+C8+C16+C24+C33 -> 43147807488 | K8: =+E8+E16+E24+E33 -> 15072978336 | L8: =+G8+G16+G24+G33 -> 28074829152
B9: в том числе | J9: =+'loans type'!C8 -> 43147807488 | K9: =+'loans type'!E8 -> 15072978336 | L9: =+'loans type'!G8 -> 28074829152
A10: 1.1. | B10: ипотечный кредит | C10: =+E10+G10 -> 2476313760 | D10: 0.080040954 | E10: 2476313760 | F10: 0.080040954 | G10: 0 | H10: 0 | J10: =+J8-J9 -> 0 | K10: =+K8-K9 -> 0 | L10: =+L8-L9 -> 0
A11: 1.2. | B11: автокредит | C11: =+E11+G11 -> 84856149 | D11: 0.15439924 | E11: 84856149 | F11: 0.15439924 | G11: 0 | H11: 0
A12: 1.3. | B12: микрозайм (все нецелевые кредиты) | C12: =+E12+G12 -> 71589 | D12: 0.13735836 | E12: 71589 | F12: 0.13735836 | G12: 0 | H12: 0
A13: 1.4. | B13: потребительские кредиты | C13: =+E13+G13 -> 2667442 | D13: 0.058657484 | E13: 2667442 | F13: 0.058657484 | G13: 0 | H13: 0
A14: 1.5. | B14: другие кредиты физическим лицам | C14: =+E14+G14 -> 36718210 | D14: 0.096379595 | E14: 36718210 | F14: 0.096379595 | G14: 0 | H14: 0
A16: 2 | B16: Физические лица (коммерческие кредиты) | C16: =SUM(C18:C22) -> 1659252178 | D16: =IFERROR(((C18*D18)/C16)+((C19*D19)/C16)+((C20*D20)/C16)+((C21*D21)/C16)+((C22*D22)/C16),0) -> 0.21737507 | E16: =SUM(E18:E22) -> 1659252178 | F16: =IFERROR(((E18*F18)/E16)+((E19*F19)/E16)+((E20*F20)/E16)+((E21*F21)/E16)+((E22*F22)/E16),0) -> 0.21737507 | G16: =SUM(G18:G22) -> 0 | H16: =IFERROR(((G18*H18)/G16)+((G19*H19)/G16)+((G20*H20)/G16)+((G21*H21)/G16)+((G22*H22)/G16),0) -> 0
B17: в том числе
A18: 2.1. | B18: ипотечный кредит | C18: =+E18+G18 -> 795280014 | D18: 0.17584162 | E18: 795280014 | F18: 0.17584162 | G18: 0 | H18: 0
A19: 2.2. | B19: автокредит | C19: =+E19+G19 -> 360802638 | D19: 0.23689947 | E19: 360802638 | F19: 0.23689947 | G19: 0 | H19: 0
A20: 2.3. | B20: микрозайм (все нецелевые кредиты) | C20: =+E20+G20 -> 445050303 | D20: 0.26433031 | E20: 445050303 | F20: 0.26433031 | G20: 0 | H20: 0
A21: 2.4. | B21: потребительские кредиты | C21: =+E21+G21 -> 57119421 | D21: 0.30692769 | E21: 57119421 | F21: 0.30692769 | G21: 0 | H21: 0
A22: 2.5. | B22: другие кредиты физическим лицам | C22: =+E22+G22 -> 999802 | D22: 0.19100457 | E22: 999802 | F22: 0.19100457 | G22: 0 | H22: 0
A24: 3 | B24: Юридические лица (льготные кредиты) | C24: =SUM(C26:C31) -> 13380452842 | D24: =IFERROR(((C26*D26)/C24)+((C27*D27)/C24)+((C28*D28)/C24)+((C29*D29)/C24)+((C30*D30)/C24)+((C31*D31)/C24),0) -> 0.062633395 | E24: =SUM(E26:E31) -> 4472913165 | F24: =IFERROR(((E26*F26)/E24)+((E27*F27)/E24)+((E28*F28)/E24)+((E29*F29)/E24)+((E30*F30)/E24)+((E31*F31)/E24),0) -> 0.1151046 | G24: =SUM(G26:G31) -> 8907539677 | H24: =IFERROR(((G26*H26)/G24)+((G27*H27)/G24)+((G28*H28)/G24)+((G29*H29)/G24)+((G30*H30)/G24)+((G31*H31)/G24),0) -> 0.036285026
B25: в том числе
A26: 3.1. | B26: микрокредит | C26: =+E26+G26 -> 369386 | D26: 0.098572784 | E26: 369386 | F26: 0.098572784 | G26: 0 | H26: 0
A27: 3.2. | B27: синдицированные кредит | C27: =+E27+G27 -> 0 | D27: 0 | E27: 0 | F27: 0 | G27: 0 | H27: 0
A28: 3.3. | B28: лизинг | C28: =+E28+G28 -> 0 | D28: 0 | E28: 0 | F28: 0 | G28: 0 | H28: 0
A29: 3.4. | B29: факторинг | C29: =+E29+G29 -> 181613000 | D29: 0.035 | E29: 181613000 | F29: 0.035 | G29: 0 | H29: 0
A30: 3.5. | B30: межбанковский кредит | C30: =+E30+G30 -> 0 | D30: 0 | E30: 0 | F30: 0 | G30: 0 | H30: 0
A31: 3.6. | B31: другие кредиты юридическим лицам | C31: =+E31+G31 -> 13198470456 | D31: 0.063012629 | E31: 4290930779 | F31: 0.11849644 | G31: 8907539677 | H31: 0.036285026
A33: 4 | B33: Юридические лица (коммерческие кредиты) | C33: =SUM(C35:C40) -> 25507475318 | D33: =IFERROR(((C35*D35)/C33)+((C36*D36)/C33)+((C37*D37)/C33)+((C38*D38)/C33)+((C39*D39)/C33)+((C40*D40)/C33),0) -> 0.10049838 | E33: =SUM(E35:E40) -> 6340185843 | F33: =IFERROR(((E35*F35)/E33)+((E36*F36)/E33)+((E37*F37)/E33)+((E38*F38)/E33)+((E39*F39)/E33)+((E40*F40)/E33),0) -> 0.21048581 | G33: =SUM(G35:G40) -> 19167289475 | H33: =IFERROR(((G35*H35)/G33)+((G36*H36)/G33)+((G37*H37)/G33)+((G38*H38)/G33)+((G39*H39)/G33)+((G40*H40)/G33),0) -> 0.065154918
B34: в том числе
A35: 4.1. | B35: микрокредит | C35: =+E35+G35 -> 0 | D35: 0 | E35: 0 | F35: 0 | G35: 0 | H35: 0
A36: 4.2. | B36: синдицированные кредит | C36: =+E36+G36 -> 984198411 | D36: 0.041150024 | E36: 0 | F36: 0 | G36: 984198411 | H36: 0.041047941
A37: 4.3. | B37: лизинг | C37: =+E37+G37 -> 446251113 | D37: 0.087533664 | E37: 111699346 | F37: 0.17 | G37: 334551767 | H37: 0.06
A38: 4.4. | B38: факторинг | C38: =+E38+G38 -> 0 | D38: 0 | E38: 0 | F38: 0 | G38: 0 | H38: 0
A39: 4.5. | B39: межбанковский кредит | C39: =+E39+G39 -> 0 | D39: 0 | E39: 0 | F39: 0 | G39: 0 | H39: 0
A40: 4.6. | B40: другие кредиты юридическим лицам | C40: =+E40+G40 -> 24077025794 | D40: 0.10316466 | E40: 6228486497 | F40: 0.21121187 | G40: 17848539297 | H40: 0.06658084
B43: Подпись Председателя правления:
B45: Подпись Главного Бухгалтера:
B47: Всего | C47: =+C8+C16+C24+C33 -> 43147807488 | E47: =+E8+E16+E24+E33 -> 15072978336 | G47: =+G8+G16+G24+G33 -> 28074829152
C48: =+C50+C54 -> 43147807488 | E48: =+E9+E17+E25+E34 -> 0 | G48: =+G50+G54 -> 28074829152
B50: Физлица | C50: =+'Asset Classification'!C12 -> 4259879328 | G50: =+'Asset Classification'!D12 -> 0
C51: =C8+C16 -> 4259879328 | G51: =G8+G16 -> 0
C52: =+C50-C51 -> 0 | G52: =+G50-G51 -> 0
B54: Юрзлица | C54: =+'Asset Classification'!C30-'Asset Classification'!C12 -> 38887928160 | G54: =+'Asset Classification'!D30-'Asset Classification'!D12 -> 28074829152
C55: =C24+C33 -> 38887928160 | G55: =G24+G33 -> 28074829152
C56: =+C54-C55 -> 0 | G56: =+G54-G55 -> 0

Sheet loans type
Z1: Таблица-20 А
A2: Информация о структуре кредитного портфеля
B3: =+'Asset quality'!B3 -> "Ўзсаноатқурилишбанк" АТБ | V3: =+'Asset quality'!P3 -> 44560 | Z3: тыс. сум
A4: № | B4: Виды кредитования | C4: всего | I4: Сроки | N4: Категория качества | S4: Резерв на возможные потери | Y4: Списанные на внебаланс | Z4: Реструктуризи-рованные кредиты
I5: до 1 года | J5: От 1 до 5 лет | K5: От 5 до 10 лет | L5: От 10 до 15 лет | M5: Свыше 15 лет | S5: итого | T5: по категориям качества
C6: Остаток | D6: средневзвешенные % ставки | E6: в нацвалюте | F6: средневзвешенные % ставки | G6: в инвалюте | H6: средневзвешенные % ставки | N6: I | O6: II | P6: III | Q6: IV | R6: V | T6: I | U6: II | V6: III | W6: IV | X6: V | AB6: I | AC6: II | AD6: III | AE6: IV | AF6: V
B7: А | C7: Б | D7: В | E7: Г | F7: Д | G7: Е | H7: Ж | I7: З | J7: И | K7: К | L7: Л | M7: М | N7: Н | O7: О | P7: П | Q7: Р | R7: С | S7: Т | T7: У | U7: Ф | V7: Х | W7: Ц | X7: Ч | Y7: Ш | Z7: Щ
B8: ВСЕГО | C8: =+C9+C25 -> 43147807488 | D8: =IFERROR(((C9*D9)/C8)+((C25*D25)/C8),0) -> 0.092176563 | E8: =+E9+E25 -> 15072978336 | F8: =IFERROR(((E9*F9)/E8)+((E25*F25)/E8),0) -> 0.16088828 | G8: =+G9+G25 -> 28074829152 | H8: =IFERROR(((G9*H9)/G8)+((G25*H25)/G8),0) -> 0.055286215 | I8: =+I9+I25 -> 14566842845 | J8: =+J9+J25 -> 20716815034 | K8: =+K9+K25 -> 5606862393 | L8: =+L9+L25 -> 1566836687 | M8: =+M9+M25 -> 690450529 | N8: =+N9+N25 -> 38864449980 | O8: =+O9+O25 -> 2653824211 | P8: =+P9+P25 -> 891521851 | ... Z8: =+Z9+Z25 -> 359533894 | AA8: =+'Loans Receivable'!C92 -> 43147807488 | AB8: =+'Asset Classification'!G30 -> 351509341 | AC8: =+'Asset Classification'!K30 -> 267633909 | AD8: =+'Asset Classification'!O50 -> 212612564 | AE8: =+'Asset Classification'!S50 -> 99184650 | AF8: =+'Asset Classification'!W50 -> 527087558
A9: I | B9: Физические лица | C9: =+C11+C16+C21+C22+C24 -> 4259879328 | D9: =IFERROR(((C11*D11)/C9)+((C16*D16)/C9)+((C21*D21)/C9)+((C22*D22)/C9)+((C24*D24)/C9),0) -> 0.13514314 | E9: =+E11+E16+E21+E22+E24 -> 4259879328 | F9: =IFERROR(((E11*F11)/E9)+((E16*F16)/E9)+((E21*F21)/E9)+((E22*F22)/E9)+((E24*F24)/E9),0) -> 0.13514314 | G9: =+G11+G16+G21+G22+G24 -> 0 | H9: =IFERROR(((G11*H11)/G9)+((G16*H16)/G9)+((G21*H21)/G9)+((G22*H22)/G9)+((G24*H24)/G9),0) -> 0 | I9: =+I11+I16+I21+I22+I24 -> 753640079 | J9: =+J11+J16+J21+J22+J24 -> 1115342754 | K9: =+K11+K16+K21+K22+K24 -> 980327937 | L9: =+L11+L16+L21+L22+L24 -> 784830668 | M9: =+M11+M16+M21+M22+M24 -> 625737890 | N9: =+N11+N16+N21+N22+N24 -> 3964467868 | O9: =+O11+O16+O21+O22+O24 -> 132505895 | P9: =+P11+P16+P21+P22+P24 -> 38467479 | ... Z9: =+Z11+Z16+Z21+Z22+Z24 -> 14416215 | AA9: =+'Loans Receivable'!C80 -> 4259879328 | AB9: =+'Asset Classification'!E30 -> 38864449980 | AC9: =+'Asset Classification'!I30 -> 2653824211 | AD9: =+'Asset Classification'!M30 -> 891521851 | AE9: =+'Asset Classification'!Q30 -> 209335568 | AF9: =+'Asset Classification'!U30 -> 528675878
B10: в том числе | AB10: =+N8-AB9 -> 0 | AC10: =+O8-AC9 -> 0 | AD10: =+P8-AD9 -> 0 | AE10: =+Q8-AE9 -> 0 | AF10: =+R8-AF9 -> 0
A11: 1 | B11: Ипотечные кредиты (льготные) в том числе: | C11: =SUM(C12:C15) -> 2476313760 | D11: =IFERROR(((C12*D12)/C11)+((C13*D13)/C11)+((C14*D14)/C11)+((C15*D15)/C11),0) -> 0.080040954 | E11: =SUM(E12:E15) -> 2476313760 | F11: =IFERROR(((E12*F12)/E11)+((E13*F13)/E11)+((E14*F14)/E11)+((E15*F15)/E11),0) -> 0.080040954 | G11: =SUM(G12:G15) -> 0 | H11: =IFERROR(((G12*H12)/G11)+((G13*H13)/G11)+((G14*H14)/G11)+((G15*H15)/G11),0) -> 0 | I11: =SUM(I12:I15) -> 83735701 | J11: =SUM(J12:J15) -> 643583045 | K11: =SUM(K12:K15) -> 807291865 | L11: =SUM(L12:L15) -> 623369603 | M11: =SUM(M12:M15) -> 318333546 | N11: =SUM(N12:N15) -> 2309636721 | O11: =SUM(O12:O15) -> 85657007 | P11: =SUM(P12:P15) -> 22038827 | ... Z11: =SUM(Z12:Z15) -> 5888049 | AA11: =+'loans_av rate'!C10 -> 2476313760 | AB11: =+'loans_av rate'!E10 -> 2476313760 | AC11: =+'loans_av rate'!G10 -> 0
A12: 1.1. | B12: на приобретение недвижимого имущества | C12: =+E12+G12 -> 1932496861 | D12: 0.082176668 | E12: 1932496861 | F12: 0.082176668 | G12: 0 | H12: 0 | I12: 47778735 | J12: 478339571 | K12: 605898921 | L12: 514720172 | M12: 285759462 | N12: 1803819788 | O12: 65105320 | P12: 17006654 | Q12: 13966213 | R12: 32598886 | S12: =SUM(T12:X12) -> 67070105 | T12: 17487088 | U12: 6510656 | V12: 4128566 | W12: 6983107 | X12: 31960688 | Y12: 0 | Z12: 3833512
A13: 1.2. | B13: на ремонт недвижимого имущества | C13: =+E13+G13 -> 0 | D13: 0 | E13: 0 | F13: 0 | G13: 0 | H13: 0 | I13: 0 | J13: 0 | K13: 0 | L13: 0 | M13: 0 | N13: 0 | O13: 0 | P13: 0 | Q13: 0 | R13: 0 | S13: =SUM(T13:X13) -> 0 | T13: 0 | U13: 0 | V13: 0 | W13: 0 | X13: 0 | Y13: 0 | Z13: 0
A14: 1.3. | B14: на реконструкцию недвижимого имущества | C14: =+E14+G14 -> 4584552 | D14: 0.14593547 | E14: 4584552 | F14: 0.14593547 | G14: 0 | H14: 0 | I14: 323237 | J14: 1660616 | K14: 1818130 | L14: 782569 | M14: 0 | N14: 4367477 | O14: 0 | P14: 0 | Q14: 0 | R14: 217075 | S14: =SUM(T14:X14) -> 251295 | T14: 34220 | U14: 0 | V14: 0 | W14: 0 | X14: 217075 | Y14: 0 | Z14: 0
A15: 1.4. | B15: на строительство недвижимого имущества | C15: =+E15+G15 -> 539232347 | D15: 0.071826761 | E15: 539232347 | F15: 0.071826761 | G15: 0 | H15: 0 | I15: 35633729 | J15: 163582858 | K15: 199574814 | L15: 107866862 | M15: 32574084 | N15: 501449456 | O15: 20551687 | P15: 5032173 | Q15: 4692843 | R15: 7506188 | S15: =SUM(T15:X15) -> 18165919 | T15: 4951279 | U15: 2117529 | V15: 1244501 | W15: 2346422 | X15: 7506188 | Y15: 0 | Z15: 2054537
A16: 2 | B16: Ипотечные кредиты (коммерческие) в том числе: | C16: =SUM(C17:C20) -> 795280014 | D16: =IFERROR(((C17*D17)/C16)+((C18*D18)/C16)+((C19*D19)/C16)+((C20*D20)/C16),0) -> 0.17584162 | E16: =SUM(E17:E20) -> 795280014 | F16: =IFERROR(((E17*F17)/E16)+((E18*F18)/E16)+((E19*F19)/E16)+((E20*F20)/E16),0) -> 0.17584162 | G16: =SUM(G17:G20) -> 0 | H16: =IFERROR(((G17*H17)/G16)+((G18*H18)/G16)+((G19*H19)/G16)+((G20*H20)/G16),0) -> 0 | I16: =SUM(I17:I20) -> 34608349 | J16: =SUM(J17:J20) -> 158006024 | K16: =SUM(K17:K20) -> 134351713 | L16: =SUM(L17:L20) -> 160909584 | M16: =SUM(M17:M20) -> 307404344 | N16: =SUM(N17:N20) -> 743803619 | O16: =SUM(O17:O20) -> 20289219 | P16: =SUM(P17:P20) -> 6950142 | ... Z16: =SUM(Z17:Z20) -> 5252210 | AA16: =+'loans_av rate'!C18 -> 795280014 | AB16: =+'loans_av rate'!E18 -> 795280014 | AC16: =+'loans_av rate'!G18 -> 0
A17: 2.1. | B17: на приобретение недвижимого имущества | C17: =+E17+G17 -> 791727170 | D17: 0.17578517 | E17: 791727170 | F17: 0.17578517 | G17: 0 | H17: 0 | I17: 34301504 | J17: 156343594 | K17: 133096765 | L17: 160675684 | M17: 307309623 | N17: 741014243 | O17: 20214064 | P17: 6950142 | Q17: 5326129 | R17: 18222592 | S17: =SUM(T17:X17) -> 29816299 | T17: 5171703 | U17: 2021406 | V17: 1737535 | W17: 2663064 | X17: 18222591 | Y17: 20165 | Z17: 5252210
A18: 2.2. | B18: на ремонт недвижимого имущества | C18: =+E18+G18 -> 0 | D18: 0 | E18: 0 | F18: 0 | G18: 0 | H18: 0 | I18: 0 | J18: 0 | K18: 0 | L18: 0 | M18: 0 | N18: 0 | O18: 0 | P18: 0 | Q18: 0 | R18: 0 | S18: =SUM(T18:X18) -> 0 | T18: 0 | U18: 0 | V18: 0 | W18: 0 | X18: 0 | Y18: 0 | Z18: 0
A19: 2.3. | B19: на реконструкцию недвижимого имущества | C19: =+E19+G19 -> 2965745 | D19: 0.18403098 | E19: 2965745 | F19: 0.18403098 | G19: 0 | H19: 0 | I19: 239603 | J19: 1388021 | K19: 1105333 | L19: 138067 | M19: 94721 | N19: 2202277 | O19: 75155 | P19: 0 | Q19: 0 | R19: 688313 | S19: =SUM(T19:X19) -> 712730 | T19: 16902 | U19: 7515 | V19: 0 | W19: 0 | X19: 688313 | Y19: 0 | Z19: 0
A20: 2.4. | B20: на строительство недвижимого имущества | C20: =+E20+G20 -> 587099 | D20: 0.2106052 | E20: 587099 | F20: 0.2106052 | G20: 0 | H20: 0 | I20: 67242 | J20: 274409 | K20: 149615 | L20: 95833 | M20: 0 | N20: 587099 | O20: 0 | P20: 0 | Q20: 0 | R20: 0 | S20: =SUM(T20:X20) -> 5038 | T20: 5038 | U20: 0 | V20: 0 | W20: 0 | X20: 0 | Y20: 0 | Z20: 0
A21: 3 | B21: микрозайм (все нецелевые кредиты) | C21: =+E21+G21 -> 445121892 | D21: 0.26430989 | E21: 445121892 | F21: 0.26430989 | G21: 0 | H21: 0 | I21: 360309024 | J21: 84062441 | K21: 750054 | L21: 373 | M21: 0 | N21: 414470165 | O21: 7701984 | P21: 4014580 | Q21: 3163284 | R21: 15771879 | S21: =SUM(T21:X21) -> 23147182 | T21: 4058110 | U21: 773345 | V21: 920389 | W21: 1583837 | X21: 15811501 | Y21: 17277388 | Z21: 63926 | AA21: =+'loans_av rate'!C12+'loans_av rate'!C20 -> 445121892 | AB21: =+'loans_av rate'!E12+'loans_av rate'!E20 -> 445121892 | AC21: =+'loans_av rate'!G12+'loans_av rate'!G20 -> 0
A22: 4 | B22: потребительские кредиты | C22: =+E22+G22 -> 505445650 | D22: 0.23002211 | E22: 505445650 | F22: 0.23002211 | G22: 0 | H22: 0 | I22: 246504067 | J22: 225497684 | K22: 33443899 | L22: 0 | M22: 0 | N22: 466053615 | O22: 15370248 | P22: 4296401 | Q22: 3241490 | R22: 16483896 | S22: =SUM(T22:X22) -> 24931377 | T22: 4279207 | U22: 1536217 | V22: 1003593 | W22: 1620745 | X22: 16491615 | Y22: 12228348 | Z22: 3051381 | AA22: =+'loans_av rate'!C11+'loans_av rate'!C13+'loans_av rate'!C19+'loans_av rate'!C21 -> 505445650 | AB22: =+'loans_av rate'!E11+'loans_av rate'!E13+'loans_av rate'!E19+'loans_av rate'!E21 -> 505445650
A23: 4.1. | B23: из них на приобретения автомобиля | C23: =+E23+G23 -> 445658787 | D23: 0.22119092 | E23: 445658787 | F23: 0.22119092 | G23: 0 | H23: 0 | I23: 190868676 | J23: 221349772 | K23: 33440339 | L23: 0 | M23: 0 | N23: 424522697 | O23: 11639926 | P23: 2972220 | Q23: 1525570 | R23: 4998374 | S23: =SUM(T23:X23) -> 11291798 | T23: 3666906 | U23: 1162750 | V23: 700983 | W23: 762785 | X23: 4998374 | Y23: 1164070 | Z23: 2414443 | AA23: =+'loans_av rate'!C11+'loans_av rate'!C19 -> 445658787 | AB23: =+'loans_av rate'!E11+'loans_av rate'!E19 -> 445658787 | AC23: =+'loans_av rate'!G11+'loans_av rate'!G19 -> 0
A24: 5 | B24: другие кредиты физическим лицам | C24: =+E24+G24 -> 37718012 | D24: 0.098887846 | E24: 37718012 | F24: 0.098887846 | G24: 0 | H24: 0 | I24: 28482938 | J24: 4193560 | K24: 4490406 | L24: 551108 | M24: 0 | N24: 30503748 | O24: 3487437 | P24: 1167529 | Q24: 1800511 | R24: 758787 | S24: =SUM(T24:X24) -> 2715104 | T24: 420448 | U24: 349161 | V24: 282115 | W24: 900256 | X24: 763124 | Y24: 16521680 | Z24: 160649 | AA24: =+'loans_av rate'!C14+'loans_av rate'!C22 -> 37718012 | AB24: =+'loans_av rate'!E14+'loans_av rate'!E22 -> 37718012
A25: II | B25: Юридические лица | C25: =+C26 -> 38887928160 | D25: =IFERROR(((C27*D27)/C25)+((C28*D28)/C25)+((C29*D29)/C25)+((C30*D30)/C25)+((C31*D31)/C25)+((C32*D32)/C25),0) -> 0.087469897 | E25: =+E26 -> 10813099008 | F25: =IFERROR(((E27*F27)/E25)+((E28*F28)/E25)+((E29*F29)/E25)+((E30*F30)/E25)+((E31*F31)/E25)+((E32*F32)/E25),0) -> 0.17103072 | G25: =+G26 -> 28074829152 | H25: =IFERROR(((G27*H27)/G25)+((G28*H28)/G25)+((G29*H29)/G25)+((G30*H30)/G25)+((G31*H31)/G25)+((G32*H32)/G25),0) -> 0.055286215 | I25: =+I26 -> 13813202766 | J25: =+J26 -> 19601472280 | K25: =+K26 -> 4626534456 | L25: =+L26 -> 782006019 | M25: =+M26 -> 64712639 | N25: =+N26 -> 34899982112 | O25: =+O26 -> 2521318316 | P25: =+P26 -> 853054372 | ... Z25: =+Z26 -> 345117679 | AA25: =+'loans_av rate'!C24+'loans_av rate'!C33 -> 38887928160 | AB25: =+'loans_av rate'!E24+'loans_av rate'!E33 -> 10813099008 | AC25: =+'loans_av rate'!G24+'loans_av rate'!G33 -> 28074829152
B26: в том числе по видам кредитования | C26: =SUM(C27:C32) -> 38887928160 | D26: =IFERROR(((C28*D28)/C26)+((C29*D29)/C26)+((C30*D30)/C26)+((C31*D31)/C26)+((C32*D32)/C26),0) -> 0.087468961 | E26: =SUM(E27:E32) -> 10813099008 | F26: =IFERROR(((E28*F28)/E26)+((E29*F29)/E26)+((E30*F30)/E26)+((E31*F31)/E26)+((E32*F32)/E26),0) -> 0.17102735 | G26: =SUM(G27:G32) -> 28074829152 | H26: =IFERROR(((G28*H28)/G26)+((G29*H29)/G26)+((G30*H30)/G26)+((G31*H31)/G26)+((G32*H32)/G26),0) -> 0.055286215 | I26: =SUM(I27:I32) -> 13813202766 | J26: =SUM(J27:J32) -> 19601472280 | K26: =SUM(K27:K32) -> 4626534456 | L26: =SUM(L27:L32) -> 782006019 | M26: =SUM(M27:M32) -> 64712639 | N26: =SUM(N27:N32) -> 34899982112 | O26: =SUM(O27:O32) -> 2521318316 | P26: =SUM(P27:P32) -> 853054372 | ... Z26: =SUM(Z27:Z32) -> 345117679
A27: 1 | B27: микрокредит | C27: =+E27+G27 -> 369386 | D27: 0.098572784 | E27: 369386 | F27: 0.098572784 | G27: 0 | H27: 0 | I27: 207246 | J27: 148807 | K27: 13333 | L27: 0 | M27: 0 | N27: 79644 | O27: 63333 | P27: 0 | Q27: 0 | R27: 226409 | S27: =SUM(T27:X27) -> 233898 | T27: 1156 | U27: 6333 | V27: 0 | W27: 0 | X27: 226409 | Y27: 276533 | Z27: 166377 | AA27: =+'loans_av rate'!C26+'loans_av rate'!C35 -> 369386 | AB27: =+'loans_av rate'!E26+'loans_av rate'!E35 -> 369386 | AC27: =+'loans_av rate'!G26+'loans_av rate'!G35 -> 0
A28: 2 | B28: синдицированные кредит | C28: =+E28+G28 -> 984198411 | D28: 0.041150024 | E28: 0 | F28: 0 | G28: 984198411 | H28: 0.041150024 | I28: 122001467 | J28: 574797963 | K28: 287398981 | L28: 0 | M28: 0 | N28: 984198411 | O28: 0 | P28: 0 | Q28: 0 | R28: 0 | S28: =SUM(T28:X28) -> 9888687 | T28: 9888687 | U28: 0 | V28: 0 | W28: 0 | X28: 0 | Y28: 877152 | Z28: 0 | AA28: =+'loans_av rate'!C27+'loans_av rate'!C36 -> 984198411 | AB28: =+'loans_av rate'!E27+'loans_av rate'!E36 -> 0 | AC28: =+'loans_av rate'!G27+'loans_av rate'!G36 -> 984198411
A29: 3 | B29: лизинг | C29: =+E29+G29 -> 446251113 | D29: 0.087533664 | E29: 111699346 | F29: 0.17 | G29: 334551767 | H29: 0.06 | I29: 63431372 | J29: 382819741 | K29: 0 | L29: 0 | M29: 0 | N29: 349829544 | O29: 96421569 | P29: 0 | Q29: 0 | R29: 0 | S29: =SUM(T29:X29) -> 18160948 | T29: 180556 | U29: 17980392 | V29: 0 | W29: 0 | X29: 0 | Y29: 0 | Z29: 0 | AA29: =+'loans_av rate'!C28+'loans_av rate'!C37 -> 446251113 | AB29: =+'loans_av rate'!E28+'loans_av rate'!E37 -> 111699346 | AC29: =+'loans_av rate'!G28+'loans_av rate'!G37 -> 334551767
A30: 4 | B30: факторинг | C30: =+E30+G30 -> 181613000 | D30: 0.035 | E30: 181613000 | F30: 0.035 | G30: 0 | H30: 0 | I30: 181613000 | J30: 0 | K30: 0 | L30: 0 | M30: 0 | N30: 181613000 | O30: 0 | P30: 0 | Q30: 0 | R30: 0 | S30: =SUM(T30:X30) -> 1119400 | T30: 1119400 | U30: 0 | V30: 0 | W30: 0 | X30: 0 | Y30: 0 | Z30: 0 | AA30: =+'loans_av rate'!C29+'loans_av rate'!C38 -> 181613000 | AB30: =+'loans_av rate'!E29+'loans_av rate'!E38 -> 181613000 | AC30: =+'loans_av rate'!G29+'loans_av rate'!G38 -> 0
A31: 5 | B31: межбанковский кредит | C31: =+E31+G31 -> 0 | D31: 0 | E31: 0 | F31: 0 | G31: 0 | H31: 0 | I31: 0 | J31: 0 | K31: 0 | L31: 0 | M31: 0 | N31: 0 | O31: 0 | P31: 0 | Q31: 0 | R31: 0 | S31: =SUM(T31:X31) -> 0 | T31: 0 | U31: 0 | V31: 0 | W31: 0 | X31: 0 | Y31: 0 | Z31: 0 | AA31: =+'loans_av rate'!C30+'loans_av rate'!C39 -> 0 | AB31: =+'loans_av rate'!E30+'loans_av rate'!E39 -> 0 | AC31: =+'loans_av rate'!G30+'loans_av rate'!G39 -> 0
A32: 6 | B32: другие виды кредитования | C32: =+E32+G32 -> 37275496250 | D32: 0.088947667 | E32: 10519417276 | F32: 0.17339271 | G32: 26756078974 | H32: 0.055747262 | I32: 13445949681 | J32: 18643705769 | K32: 4339122142 | L32: 782006019 | M32: 64712639 | N32: 33384261513 | O32: 2424833414 | P32: 853054372 | Q32: 177145098 | R32: 436201853 | S32: =SUM(T32:X32) -> 1261810040 | T32: 303895547 | U32: 236331355 | V32: 203295865 | W32: 83087219 | X32: 435200054 | Y32: 390849732 | Z32: 344951302 | AA32: =+'loans_av rate'!C31+'loans_av rate'!C40 -> 37275496250 | AB32: =+'loans_av rate'!E31+'loans_av rate'!E40 -> 10519417276 | AC32: =+'loans_av rate'!G31+'loans_av rate'!G40 -> 26756078974
B33: в том числе по цели кредитования | C33: =SUM(C34:C39) -> 38887928160 | D33: =IFERROR(((C35*D35)/C33)+((C36*D36)/C33)+((C37*D37)/C33)+((C38*D38)/C33)+((C39*D39)/C33),0) -> 0.087168625 | E33: =SUM(E34:E39) -> 10813099008 | F33: =IFERROR(((E35*F35)/E33)+((E36*F36)/E33)+((E37*F37)/E33)+((E38*F38)/E33)+((E39*F39)/E33),0) -> 0.1701885 | G33: =SUM(G34:G39) -> 28074829152 | H33: =IFERROR(((G35*H35)/G33)+((G36*H36)/G33)+((G37*H37)/G33)+((G38*H38)/G33)+((G39*H39)/G33),0) -> 0.055193287 | I33: =SUM(I34:I39) -> 13813202766 | J33: =SUM(J34:J39) -> 19601472280 | K33: =SUM(K34:K39) -> 4626534456 | L33: =SUM(L34:L39) -> 782006019 | M33: =SUM(M34:M39) -> 64712639 | N33: =SUM(N34:N39) -> 34899982112 | O33: =SUM(O34:O39) -> 2521318316 | P33: =SUM(P34:P39) -> 853054372 | ... Z33: =SUM(Z34:Z39) -> 345117679
A34: 1 | B34: кредиты, выданные на формирование стартового капитала | C34: =+E34+G34 -> 88736769 | D34: 0.13202943 | E34: 55505160 | F34: 0.16407391 | G34: 33231609 | H34: 0.078507064 | I34: 16902937 | J34: 65405261 | K34: 6428571 | L34: 0 | M34: 0 | N34: 88736769 | O34: 0 | P34: 0 | Q34: 0 | R34: 0 | S34: =SUM(T34:X34) -> 966253 | T34: 966253 | U34: 0 | V34: 0 | W34: 0 | X34: 0 | Y34: 0 | Z34: 0
A35: 2 | B35: кредиты на пополнение оборотных средств | C35: =+E35+G35 -> 2665495701 | D35: 0.1358446 | E35: 1228459218 | F35: 0.2114352 | G35: 1437036483 | H35: 0.071225534 | I35: 2145026051 | J35: 486449509 | K35: 30874682 | L35: 3142640 | M35: 2819 | N35: 2552582984 | O35: 37801730 | P35: 33211084 | Q35: 10657194 | R35: 31242709 | S35: =SUM(T35:X35) -> 68081645 | T35: 19392639 | U35: 3814928 | V35: 8302771 | W35: 5328597 | X35: 31242710 | Y35: 58069968 | Z35: 15139592
A36: 3 | B36: кредиты, выданные на приобретение, модернизацию или приватизацию основных средств | C36: =+E36+G36 -> 1369593029 | D36: 0.15527701 | E36: 814607425 | F36: 0.21492963 | G36: 554985604 | H36: 0.067718945 | I36: 139053572 | J36: 1155928203 | K36: 74611254 | L36: 0 | M36: 0 | N36: 1106404616 | O36: 245279003 | P36: 6408036 | Q36: 0 | R36: 11501374 | S36: =SUM(T36:X36) -> 42867561 | T36: 6238078 | U36: 24527900 | V36: 1602009 | W36: 0 | X36: 10499574 | Y36: 0 | Z36: 4348930
A37: 4 | B37: кредиты, выданные на покрытие затрат, связанных с импортом и экспортом продукции | C37: =+E37+G37 -> 3473731 | D37: 0.14499999 | E37: 3473731 | F37: 0.14499999 | G37: 0 | H37: 0 | I37: 2241330 | J37: 1232401 | K37: 0 | L37: 0 | M37: 0 | N37: 3473731 | O37: 0 | P37: 0 | Q37: 0 | R37: 0 | S37: =SUM(T37:X37) -> 42208 | T37: 42208 | U37: 0 | V37: 0 | W37: 0 | X37: 0 | Y37: 0 | Z37: 0
A38: 5 | B38: кредиты, выданные по отдельным решениям правительства | C38: =+E38+G38 -> 0 | D38: 0 | E38: 0 | F38: 0 | G38: 0 | H38: 0 | I38: 0 | J38: 0 | K38: 0 | L38: 0 | M38: 0 | N38: 0 | O38: 0 | P38: 0 | Q38: 0 | R38: 0 | S38: =SUM(T38:X38) -> 0 | T38: 0 | U38: 0 | V38: 0 | W38: 0 | X38: 0 | Y38: 0 | Z38: 0
A39: 6 | B39: другие цели кредитования | C39: =+E39+G39 -> 34760628930 | D39: 0.080969306 | E39: 8711053474 | F39: 0.16128229 | G39: 26049575456 | H39: 0.054112413 | I39: 11509978876 | J39: 17892456906 | K39: 4514619949 | L39: 778863379 | M39: 64709820 | N39: 31148784012 | O39: 2238237583 | P39: 813435252 | Q39: 166487904 | R39: 393684179 | S39: =SUM(T39:X39) -> 1179255306 | T39: 288446168 | U39: 225975252 | V39: 193391085 | W39: 77758622 | X39: 393684179 | Y39: 333933449 | Z39: 325629157
B41: Подпись Председателя правления:
B43: Подпись Главного Бухгалтера:

Sheet Bank Capital Calc (2)
A1: РАСЧЕТ РЕГУЛЯТИВНОГО КАПИТАЛА БАНКА | C1: Таблица-5
B3: =#REF! -> #REF! | C3: =+#REF! -> #REF!
A4: № | B4: Характеристики | C4: Итого капитала
A5: I. | B5: КАПИТАЛ УРОВНЯ 1
A6: 1 | B6: ОСНОВНОЙ КАПИТАЛ УРОВНЯ 1
A7: 1.1. | B7: Обыкновенные Акции, чистые | C7: Формула
A8: a | B8: Полностью оплаченные обыкновенные акции
A9: б | B9: Минус: Обратно Выкупленные обыкновенные акции
A10: 1.2. | B10: Добавленный капитал - Обыкновенные | C10: 0
A11: 1.3. | B11: Нераспределенная прибыль (убыток), в том числе капитальные резервы | C11: Формула
A12: а | B12: Капитальные резервы
A13: б | B13: Нераспределенная прибыль
A14: в | B14: Убыток за предыдущие периоды
A15: г | B15: Убыток за текущий год
A16: 1.4. | B16: Интерес меньшинства в консолидированных дочерних компаниях (согласно МБС)
A17: 1.5. | B17: Резерв на девальвацию
B18: Итого основного капитала уровня I до вычетов | C18: Формула
A19: 1.6. | B19: Вычеты из суммы основного капитала уровня I | C19: Формула
A20: а | B20: Нематериальные активы
A21: б | B21: Все инвестиции в капитал неконсолидированных хозяйствующих субъектов, в том числе в долговые обязательства, которые образуют капитал хозяйствующих субъектов
A22: в | B22: Инвестиции в капитал других банков
A23: I | B23: ВСЕГО СКОРРЕКТИРОВАННЫЙ ОСНОВНОЙ КАПИТАЛ УРОВНЯ I | C23: Формула
A24: 2 | B24: ДОБАВЛЕННЫЙ КАПИТАЛ УРОВНЯ 1
A25: 2.1. | B25: Некумулятивные бессрочные привилегированные акции | C25: =+C26+C27 -> 0
A26: а | B26: Полностью оплаченные привилегированные акции
A27: б | B27: Минус: Обратно Выкупленные привилегированные акции
A28: 2.2. | B28: Добавленный капитал - Привилегированные | C28: 0
A29: 2.3. | B29: Интерес меньшинства в консолидированных дочерних компаниях | C29: 0
A30: 2.4. | B30: Доля участия дочерних предприятий (выпущенные дочерними предприятиями и находящиеся во владении третьих лиц инструменты, приравненные к капиталу) | C30: 0
A31: II | B31: ВСЕГО ДОБАВЛЕННЫЙ КАПИТАЛ УРОВНЯ I | C31: =+C25+C28+C29+C30 -> 0
A32: III | B32: ВСЕГО СКОРРЕКТИРОВАННЫЙ КАПИТАЛ УРОВНЯ I | C32: Формула
B33: КАПИТАЛ УРОВНЯ II
A34: 3.1. | B34: Прибыль за текущий год
A35: 3.2. | B35: Резервы, создаваемые на стандартные кредиты (активы), в размере не более 1.25% от общей суммы активов, взвешенных с учетом риска | C35: =IF(#REF!<(C43*1.25%),#REF!,(C43*1.25%)) -> #REF!
A36: 3.3. | B36: Излишки оценочной стоимости прироста над первоначальной стоимостью
A37: 3.4. | B37: Другие инструменты капитала (не более 1/3 части капитала 1 уровня после вычетов)
A38: 3.5. | B38: Субординированный долг
A39: 3.6. | B39: Вычеты превышения Капитала Уровня II над Капиталом Уровня I | C39: Формула
B40: Итого капитала Уровня II | C40: =SUM(C34:C38) -> #REF!
A41: IV | B41: СКОРРЕКТИРОВАННЫЙ КАПИТАЛ УРОВНЯ II | C41: Формула
A42: V | B42: ВСЕГО РЕГУЛЯТИВНЫЙ КАПИТАЛ | C42: Формула
A43: VI | B43: ОБЩАЯ СУММА АКТИВОВ ВЗВЕШЕННЫХ С УЧЕТОМ РИСКА | C43: =+C44+C45+C46 -> #REF!
A44: а | B44: Сумма балансовых и забалансовых активов, взвешенных с учетом риска | C44: =+#REF! -> #REF!
A45: б | B45: Операционный риск | C45: =+#REF! -> #REF!
A46: в | B46: Рыночный риск | C46: =+#REF! -> #REF! | E46: =+#REF! -> #REF!
A47: VII | B47: КОЭФФИЦИЕНТ ОСНОВНОГО КАПИТАЛА УРОВНЯ I (I/VI) | C47: Формула
A48: VIII | B48: КОЭФФИЦИЕНТ КАПИТАЛА УРОВНЯ I (III/VI) | C48: Формула
A49: IX | B49: КОЭФФИЦИЕНТ ОБЩЕЙ СУММЫ КАПИТАЛА, ОСНОВАННОГО НА РИСКЕ (V/VI) | C49: Формула
A50: X | B50: Активы для расчета левеража | C50: Формула
A51: а | B51: Общие активы | C51: =+#REF! -> #REF!
A52: б | B52: Забалансовые инструменты | C52: =SUM(#REF!) -> #REF! | D52: =+#REF! -> #REF!
A53: в | B53: Деривативные (производные) инструменты | C53: =SUM(#REF!) -> #REF!
A54: г | B54: Минус: Строка 1.6. Итого вычетов из суммы основного капитала Уровня 1 | C54: =+C19 -> Формула
A55: XI | B55: Коэффициент левеража | C55: Формула
B57: Подпись Председателя правления:
B59: Подпись Главного Бухгалтера:

Sheet Deposits_av rate
A1: ДАННЫЕ О СРЕДНЕВЗВЕШЕННЫХ ПРОЦЕНТНЫХ СТАВКАХ ПО ПРИВЛЕЧЕННЫМ ДЕПОЗИТАМ БАНКОВ | N1: Таблица-21
B2: =+'Asset quality'!B3 -> "Ўзсаноатқурилишбанк" АТБ | K2: =+'loans_av rate'!F3 -> 44560 | N2: тыс. сум
A3: № | B3: Сроки, погашения средств | C3: Вклады (депозиты) физических лиц | I3: Вклады (депозиты) юридических лиц
C4: общая сумма (тыс. сум) | D4: средневзвешенные процентные ставки | E4: в том числе | I4: общая сумма (тыс. сум) | J4: средневзвешенные процентные ставки | K4: в том числе
E5: в национальный валюте | G5: в иностранной валюте | K5: в национальный валюте | M5: в иностранной валюте
E6: остаток всего | F6: средневзвешенные процентные ставки | G6: остаток всего | H6: средневзвешенные процентные ставки | K6: остаток всего | L6: средневзвешенные процентные ставки | M6: остаток всего | N6: средневзвешенные процентные ставки
B7: А | C7: Б | D7: В | E7: Г | F7: Д | G7: Е | H7: Ж | I7: З | J7: И | K7: К | L7: Л | M7: М | N7: Н
A8: 1 | B8: Бессрочные | C8: =+E8+G8 -> 988537293 | D8: 0 | E8: ='[8]Bank Liabilities Analysis (нац)'!$C$10+'[8]Bank Liabilities Analysis (нац)'!$C$15+'[8]Bank Liabilities Analysis (нац)'!$C$18+2369 -> 817442039 | F8: 0 | G8: ='[8]Bank Liabilities Analysis'!$D$9+'[8]Bank Liabilities Analysis'!$D$14+'[8]Bank Liabilities Analysis'!$D$17 -> 171095254 | H8: 0 | I8: =+K8+M8 -> 4905224231 | J8: 0 | K8: ='[8]Bank Liabilities Analysis (нац)'!$C$9+'[8]Bank Liabilities Analysis (нац)'!$C$14+'[8]Bank Liabilities Analysis (нац)'!$C$17-E8 -> 2270282625 | L8: 0 | M8: ='[8]Bank Liabilities Analysis'!$D$8+'[8]Bank Liabilities Analysis'!$D$13+'[8]Bank Liabilities Analysis'!$D$16-G8 -> 2634941606 | N8: 0 | P8: =+'[8]Bank Liabilities Analysis'!$C$22 -> 5893761524 | Q8: =+P8-C8-I8 -> 0
A9: 2 | B9: От 1 до 7 дней | C9: =+E9+G9 -> 19613397 | D9: 0.057 | E9: ='[8]Bank Liabilities Analysis (нац)'!$D$15 -> 5892919 | F9: 0.0744 | G9: ='[8]Bank Liabilities Analysis'!$F$14 -> 13720478 | H9: 0.04 | I9: =+K9+M9 -> 35494602 | J9: 0.011583286 | K9: ='[8]Bank Liabilities Analysis (нац)'!$D$14-E9 -> 1000000 | L9: 0.015048544 | M9: ='[8]Bank Liabilities Analysis'!$F$13+'[8]Bank Liabilities Analysis'!$F$16-G9 -> 34494602 | N9: 0 | P9: =+'[8]Bank Liabilities Analysis'!$E$22 -> 55107999 | Q9: =+P9-C9-I9 -> 0
A10: 3 | B10: От 8 до 30 дней | C10: =+E10+G10 -> 49384845 | D10: 0.0787 | E10: ='[8]Bank Liabilities Analysis (нац)'!$E$15 -> 13360463 | F10: 0.1236 | G10: ='[8]Bank Liabilities Analysis'!$H$14 -> 36024382 | H10: 0.04 | I10: =+K10+M10 -> 101154988 | J10: 0.0018371223 | K10: ='[8]Bank Liabilities Analysis (нац)'!$E$14-E10+740448 -> 6180448 | L10: 0.029484566 | M10: ='[8]Bank Liabilities Analysis'!$H$13+'[8]Bank Liabilities Analysis'!$H$16-G10 -> 94974540 | N10: 0 | P10: =+'[8]Bank Liabilities Analysis'!$G$22 -> 150539833 | Q10: =+P10-C10-I10 -> 0
A11: 4 | B11: От 31 до 90 дней | C11: =+E11+G11 -> 158747509 | D11: 0.0694 | E11: ='[8]Bank Liabilities Analysis (нац)'!$F$15 -> 42015073 | F11: 0.1294 | G11: ='[8]Bank Liabilities Analysis'!$J$14 -> 116732436 | H11: 0.04 | I11: =+K11+M11 -> 320940087 | J11: 0.041629881 | K11: ='[8]Bank Liabilities Analysis (нац)'!$F$14-E11 -> 13351089 | L11: 0.21560577 | M11: ='[8]Bank Liabilities Analysis'!$J$13+'[8]Bank Liabilities Analysis'!$J$16-G11 -> 307588998 | N11: 0 | P11: =+'[8]Bank Liabilities Analysis'!$I$22 -> 479687596 | Q11: =+P11-C11-I11 -> 0
A12: 5 | B12: От 91 до 180 дней | C12: =+E12+G12 -> 1156289111 | D12: 0.0632 | E12: ='[8]Bank Liabilities Analysis (нац)'!$G$15 -> 1028827392 | F12: 0.0895 | G12: ='[8]Bank Liabilities Analysis'!$L$14 -> 127461719 | H12: 0.04 | I12: =+K12+M12 -> 613841642 | J12: 0.02369086 | K12: ='[8]Bank Liabilities Analysis (нац)'!$G$14-E12 -> 80377452 | L12: 0.12061121 | M12: ='[8]Bank Liabilities Analysis'!$L$13+'[8]Bank Liabilities Analysis'!$L$16-G12 -> 533464190 | N12: 0 | P12: =+'[8]Bank Liabilities Analysis'!$K$22 -> 1770130753 | Q12: =+P12-C12-I12 -> 0
A13: 6 | B13: От 181 до 365 дней | C13: =+E13+G13 -> 884457698 | D13: 0.1675 | E13: ='[8]Bank Liabilities Analysis (нац)'!$H$15 -> 884457698 | F13: 0.1708 | G13: ='[8]Bank Liabilities Analysis'!$N$14 -> 0 | H13: 0.0171 | I13: =+K13+M13 -> 883901689 | J13: 0.030914491 | K13: ='[8]Bank Liabilities Analysis (нац)'!$H$14+'[8]Bank Liabilities Analysis (нац)'!$H$20-E13 -> 607331217 | L13: 0.13880038 | M13: ='[8]Bank Liabilities Analysis'!$N$13+'[8]Bank Liabilities Analysis'!$N$16-G13 -> 276570472 | N13: 0.019062126 | P13: =+'[8]Bank Liabilities Analysis'!$M$22 -> 1768359387 | Q13: =+P13-C13-I13 -> 0
A14: 7 | B14: От 366 до 730 дней | C14: =+E14+G14 -> 59467463 | D14: 0.2058 | E14: ='[8]Bank Liabilities Analysis (нац)'!$I$15 -> 59467463 | F14: 0.2058 | G14: ='[8]Bank Liabilities Analysis'!$P$14 -> 0 | H14: 0 | I14: =+K14+M14 -> 388641844 | J14: 0.073202508 | K14: ='[8]Bank Liabilities Analysis (нац)'!$I$14-E14 -> 59622955 | L14: 0.19171229 | M14: ='[8]Bank Liabilities Analysis'!$P$13+'[8]Bank Liabilities Analysis'!$P$16-G14 -> 329018889 | N14: 0.0080206501 | P14: =+'[8]Bank Liabilities Analysis'!$O$22 -> 448109307 | Q14: =+P14-C14-I14 -> 0
A15: 8 | B15: Свыше 2 лет | C15: =+E15+G15 -> 2224159 | D15: 0.0543 | E15: ='[8]Bank Liabilities Analysis (нац)'!$J$15 -> 2224159 | F15: 0.0543 | G15: ='[8]Bank Liabilities Analysis'!$R$14 -> 0 | H15: 0 | I15: =+K15+M15 -> 2039399521 | J15: 0.067917015 | K15: ='[8]Bank Liabilities Analysis (нац)'!$J$14-E15 -> 151659772 | L15: 0.13215444 | M15: ='[8]Bank Liabilities Analysis'!$R$13-G15 -> 1887739749 | N15: 0.06441265 | P15: =+'[8]Bank Liabilities Analysis'!$Q$22 -> 2041623680 | Q15: =+P15-C15-I15 -> 0
A16: 9 | B16: Итого (сумма строк 1, 2, 3, 4, 5, 6, 7, 8 ) | C16: =SUM(C8:C15) -> 3318721475 | D16: =IFERROR(((C8*D8)/C16)+((C9*D9)/C16)+((C10*D10)/C16)+((C11*D11)/C16)+((C12*D12)/C16)+((C13*D13)/C16)+((C14*D14)/C16)+((C15*D15)/C16),0) -> 0.075211175 | E16: =SUM(E8:E15) -> 2853687206 | F16: =IFERROR(((E8*F8)/E16)+((E9*F9)/E16)+((E10*F10)/E16)+((E11*F11)/E16)+((E12*F12)/E16)+((E13*F13)/E16)+((E14*F14)/E16)+((E15*F15)/E16),0) -> 0.092172379 | G16: =SUM(G8:G15) -> 465034269 | H16: =IFERROR(((G8*H8)/G16)+((G9*H9)/G16)+((G10*H10)/G16)+((G11*H11)/G16)+((G12*H12)/G16)+((G13*H13)/G16)+((G14*H14)/G16)+((G15*H15)/G16),0) -> 0.025283213 | I16: =SUM(I8:I15) -> 9288598604 | J16: =IFERROR(((I8*J8)/I16)+((I9*J9)/I16)+((I10*J10)/I16)+((I11*J11)/I16)+((I12*J12)/I16)+((I13*J13)/I16)+((I14*J14)/I16)+((I15*J15)/I16),0) -> 0.023984777 | K16: =SUM(K8:K15) -> 3189805558 | L16: =IFERROR(((K8*L8)/K16)+((K9*L9)/K16)+((K10*L10)/K16)+((K11*L11)/K16)+((K12*L12)/K16)+((K13*L13)/K16)+((K14*L14)/K16)+((K15*L15)/K16),0) -> 0.040297453 | M16: =SUM(M8:M15) -> 6098793046 | N16: =IFERROR(((M8*N8)/M16)+((M9*N9)/M16)+((M10*N10)/M16)+((M11*N11)/M16)+((M12*N12)/M16)+((M13*N13)/M16)+((M14*N14)/M16)+((M15*N15)/M16),0) -> 0.021234576 | P16: =+'[8]Bank Liabilities Analysis'!$S$22 -> 12607320079 | Q16: =+P16-C16-I16 -> 0
B19: Подпись Председателя правления:
B21: Подпись Главного Бухгалтера:
B24: Физлица | C24: =+'[8]Deposits by Client'!$C$6+'[8]Deposits by Client'!$C$15 -> 3318721475 | G24: =+'[8]Deposits by Client'!$D$6+'[8]Deposits by Client'!$D$15 -> 465034269
C25: =+C16 -> 3318721475 | G25: =+G16 -> 465034269
C26: =+C24-C25 -> 0 | G26: =+G24-G25 -> 0
B27: Юрзлица | I27: =+'[8]Deposits by Client'!$C$22-'[8]Deposits by Client'!$C$6-'[8]Deposits by Client'!$C$15 -> 9288598604 | M27: =+'[8]Deposits by Client'!$D$22-'[8]Deposits by Client'!$D$6-'[8]Deposits by Client'!$D$15 -> 6098793046
I28: =+I16 -> 9288598604 | M28: =+M16 -> 6098793046
I29: =+I27-I28 -> 0 | M29: =+M27-M28 -> 0

Sheet Economic Normatives
A1: РАСЧЕТ ПРУДЕНЦИАЛЬНЫХ НОРМАТИВОВ | I1: Таблица-22
B2: =+'Asset quality'!B3 -> "Ўзсаноатқурилишбанк" АТБ | I2: =+'Asset quality'!P3 -> 44560
A4: № | B4: Наименование экономического норматива | F4: Формула | I4: Фактическое значение | J4: Нормативное значение | K4: Отклонение
B5: A | F5: Б | I5: В | J5: Г | K5: Д
A6: 1 | B6: Показатели достаточности капитала
A7: 1.1 | B7: Коэффициент достаточности капитала | F7: Скорректированная общая капитала, основанного на риске | I7: =+'[9]Bank Capital Calc'!$C$51 -> 0.15838641 | J7: Мин | K7: =IF(I7="",0-J8,(IF((I7-J8)>0,"",I7-J8)))
F8: Активы с учетом риска | J8: 0.13
A9: 1.2 | B9: Коэффициент достаточности Капитала Уровня 1 | F9: Капитал Уровня I | I9: =+'[9]Bank Capital Calc'!$C$50 -> 0.11878981 | J9: Мин | K9: =IF(I9="",0-J10,(IF((I9-J10)>0,"",I9-J10)))
F10: Активы с учетом риска | J10: 0.1
A11: 1.3 | B11: Коэффициент достаточности основного Капитала Уровня 1 | F11: Основной капитал Уровня I | I11: =+'[9]Bank Capital Calc'!$C$49 -> 0.11863873 | J11: Мин | K11: =IF(I11="",0-J12,(IF((I11-J12)>0,"",I11-J12)))
F12: Активы с учетом риска | J12: 0.08
A13: 1.4 | B13: Левераж | F13: Капитал Уровня I | I13: =+'[9]Bank Capital Calc'!$C$57 -> 0.099794247 | J13: Мин | K13: =IF(I13="",0-J14,(IF((I13-J14)>0,"",I13-J14)))
F14: Активы + забалансовые инструменты+ деривативные (производные) инструменты - вычеты из суммы основного капитала уровня I | J14: 0.06
A15: 2 | B15: Показатели ликвидности
A16: 2.1 | B16: Коэффициент покрытия ликвидности | E16: Всего | F16: Высоколиквидные активы | I16: =IFERROR((+'[8]Liquidity Analysis'!$C$23),0) -> 1.6453692 | J16: Мин | K16: =IF(I16="",0-$J$18,(IF((I16-$J$18)>0,"",I16-$J$18)))
E17: в национальной валюте | I17: =IFERROR((+'[8]Liquidity Analysis'!$D$23),0) -> 2.0955565 | K17: =IF(I17="",0-$J$18,(IF((I17-$J$18)>0,"",I17-$J$18)))
E18: в иностранной валюте | F18: Чистый отток в последующие 30 дней | I18: =IFERROR((+'[8]Liquidity Analysis'!$E$23),0) -> 1.4374103 | J18: 1 | K18: =IF(I18="",0-$J$18,(IF((I18-$J$18)>0,"",I18-$J$18)))
A19: 2.2 | B19: Норма чистого стабильного финансирования | E19: Всего | F19: Доступная сумма стабильного финансирования | I19: =IFERROR((+'[8]Liquidity Analysis'!$C$28),0) -> 1.1502506 | J19: Мин | K19: =IF(I19="",0-$J$21,(IF((I19-$J$21)>0,"",I19-$J$21)))
E20: в национальной валюте | I20: =IFERROR((+'[8]Liquidity Analysis'!$D$28),0) -> 1.2139657 | K20: =IF(I20="",0-$J$21,(IF((I20-$J$21)>0,"",I20-$J$21)))
E21: в иностранной валюте | F21: Необходимая сумма стабильного финансирования | I21: =IFERROR((+'[8]Liquidity Analysis'!$E$28),0) -> 1.1131865 | J21: 1 | K21: =IF(I21="",0-$J$21,(IF((I21-$J$21)>0,"",I21-$J$21)))
A22: 3 | B22: Нормативы по операциям с заемщиками
A23: 3.1 | B23: Максимальный размер риска на одного заемщика или группу взаимосвязанных заемщиков, обеспеченные | F23: Максимальный размер риска на одного заемщика или группу взаимосвязанных заемщиков,обеспеченные | I23: =IFERROR((+' Largest risk'!Z65/'[9]Bank Capital Calc'!$C$34),0) -> 0.24750262 | J23: Макс | K23: =IF(I23="","",IF(I23<0,"ОТР",IF((I23-J24)<0,"",I23-J24)))
F24: Капитал Уровня I | J24: 0.25
A25: 3.2 | B25: Максимальный размер риска на один банк или группу взаимосвязанных банков-заемщиков по межбанковским операциям | F25: Максимальный размер риска на один банк или группу взаимосвязанных банков-заемщиков по межбанковским операциям | I25: =IFERROR((+' Largest risk'!Z39/'[9]Bank Capital Calc'!$C$34),0) -> 0.16704845 | J25: Макс | K25: =IF(I25<0,"ОТР",IF((I25-J26)<0,"",I25-J26)) | M25: Заполняется в ручную
F26: Капитал Уровня I | J26: 0.25
A27: 3.3 | B27: Максимальный размер необеспеченного актива на одного заемщика или группу взаимосвязанных заемщиков (не включая риски по межбанковским операциям) | F27: Максимальный размер необеспеченного актива на одного заемщика или группу взаимосвязанных заемщиков (не включая риски по межбанковским операциям) | I27: =181613000/'[9]Bank Capital Calc'!$C$34 -> 0.02989672 | J27: Макс | K27: =IF(I27<0,"ОТР",IF((I27-J28)<0,"",I27-J28)) | M27: Заполняется в ручную
F28: Капитал Уровня I | J28: 0.05
A29: 3.4 | B29: Совокупная сумма всех крупных рисков | F29: Совокупная сумма всех крупных рисков | I29: =IFERROR((+' Largest risk'!Z64/'[9]Bank Capital Calc'!$C$34),0) -> 2.3768065 | J29: Макс | K29: =IF(I29="","",IF(I29<0,"ОТР",IF((I29-J30)<0,"",I29-J30)))
F30: Капитал Уровня I | J30: 5
A31: 4 | B31: Нормативы по операциям с ценными бумагами
A32: 4.1 | B32: Максимальный размер инвестиций в ценные бумаги одного эмитента | F32: Инвестиции в негосударственные ценные бумаги одного эмитента | I32: =83362868/'[9]Bank Capital Calc'!$C$34 -> 0.013723006 | J32: Макс | K32: =IF(I32<0,"ОТР",IF((I32-J33)<0,"",I32-J33)) | M32: Заполняется в ручную
F33: Капитал Уровня I | J33: 0.15
A34: 4.2 | B34: Максимальный общий размер инвестиций в ценные бумаги для купли- продажи | F34: Общий размер инвестиций в ценные бумаги для купли- продажи | I34: =IFERROR((+('[8]Investment Securities'!$B$22+'[8]Investment Securities'!$B$23+'[8]Investment Securities'!$B$24+'[8]Investment Securities'!$B$25-'[8]Investment Securities'!$B$28)/'[9]Bank Capital Calc'!$C$34),0) -> 0 | J34: Макс | K34: =IF(I34="","",IF(I34<0,"ОТР",IF((I34-J35)<0,"",I34-J35)))
F35: Капитал Уровня I | J35: 0.25
A36: 4.3 | B36: Максимальный общий размер инвестиций в уставной капитал и другие ценные бумаги всех эмитентов | F36: Общий размер инвестиций в уставной капитал и другие ценные бумаги всех эмитентов | I36: =IFERROR((+(+'[8]Investment Securities'!$B$15-'[8]Investment Securities'!$B$6-'[8]Investment Securities'!$B$7+'[8]Investment Securities'!$B$22+'[8]Investment Securities'!$B$23+'[8]Investment Securities'!$B$24+'[8]Investment Securities'!$B$25-'[8]Investment Securities'!$B$28)/'[9]Bank Capital Calc'!$C$34),0) -> 0.024612978 | J36: Макс | K36: =IF(I36="","",IF(I36<0,"ОТР",IF((I36-J37)<0,"",I36-J37)))
F37: Капитал Уровня I | J37: 0.5
A38: 5 | B38: Нормативы по операциям со связанными с банком лицами
A39: 5.1 | B39: Максимальный размер риска на одного связанного с банком лица, обеспеченные | F39: Максимальный размер риска на одного связанного с банком лица, обеспеченные | I39: =IFERROR(((+'Transactions of related parties'!Z65-'[9]Bank Capital Calc'!$C$24)/'[9]Bank Capital Calc'!$C$34),0) -> 0.013723006 | J39: Макс | K39: =IF(I39="","",IF(I39<0,"ОТР",IF((I39-J40)<0,"",I39-J40)))
F40: Капитал Уровня I | J40: 0.25
A41: 5.2 | B41: Совокупная сумма рисков по всем связанным с банком лицам | F41: Совокупная сумма рисков по всем связанным с банком лицам | I41: =IFERROR(((+'Transactions of related parties'!Z64-'[9]Bank Capital Calc'!$C$24)/'[9]Bank Capital Calc'!$C$34),0) -> 0.020331366 | J41: Макс | K41: =IF(I41="","",IF(I41<0,"ОТР",IF((I41-J42)<0,"",I41-J42)))
F42: Капитал Уровня I | J42: 0.5
A43: 6 | B43: Нормативный показатель по инвестициям банка в недвижимость
A44: 6.1 | B44: Совокупная сумма всех инвестиций банка в недвижимость | F44: Сумма всех инвестиций банка в недвижимость | I44: 0 | J44: Макс | K44: =IF(I44="","",IF(I44<0,"ОТР",IF((I44-J45)<0,"",I44-J45))) | M44: Заполняется в ручную
F45: Капитал Уровня I | J45: 1
D47: Подпись Председателя правления:
D49: Подпись Главного Бухгалтера:

Sheet Miscellaneous
B1: РАЗНАЯ ИНФОРМАЦИЯ | C1: Таблица-23
B2: =+'Asset quality'!B3 -> "Ўзсаноатқурилишбанк" АТБ | C2: тыс. сум
A3: 1. | B3: Численность работников банка, включая административный, филиалы, и представительства банка.
A4: а | B4: Численность работников банка по штатному расписанию | C4: 3994
A5: б | B5: Фактическая численность работников банка | C5: 3841
A6: 2. | B6: Общее количество отделений банка, включая административный, филиалы, и представительства банка. | C6: =C8+C9+C10+C11 -> 152
B7: из них,
A8: а | B8: Количество филиалов | C8: 44
A9: б | B9: Количество мини банков | C9: 2
A10: в | B10: Количество розничных касс вне банка (филиалы) | C10: 60
A11: г | B11: Количество центров банковских услуг | C11: 46
A12: 3. | B12: Клиенская база банка | C12: =C14+C15+C16 -> 1204516
B13: из них,
A14: а | B14: Физические лица | C14: 1140965
A15: б | B15: Индивидуальные предприниматели | C15: 28908
A16: в | B16: Юридические лица | C16: =+C18+C19+C20+C21+C22 -> 34643 | E16: в этой строке указываются количество всех юридических лиц
B17: в том числе имеющие основной счет в банке | E17: в этой строке указываются количество юридических лиц, которые имеют основной счет в банке
A18: - | B18: Государственные предприятия | C18: 830
A19: - | B19: Частные товарищества и корпорации | C19: 30017
A20: - | B20: Фермерское хозяйство | C20: 1450
A21: - | B21: Правительство | C21: 37
A22: - | B22: Прочие | C22: 2309
A23: 4. | B23: Рейтинг банка
A24: а | B24: Названия рейтинговой компании | C24: Fitch Ratings, S&P
A25: б | B25: Оценка рейтинга банка | C25: ВВ-, ВВ-, прогноз "Стабильный"
B28: Подпись Председателя правления:
B30: Подпись Главного Бухгалтера:

Sheet ПФУ
A1: Показатели финансовой устойчивости
A2: =+'Asset quality'!B3 -> "Ўзсаноатқурилишбанк" АТБ | B2: тыс. сум | C2: Месяц
A3: Основные показатели | B3: =+'Asset quality'!P3 -> 44560 | K3: Месяц | L3: Актив | M3: Капитал | O3: Всего активы (средний за период) | P3: Совокупный капитал (средний за период)
A4: Регулятивный капитал к активам взвешанных с учетом риска | B4: =IFERROR((B5/B6),0) -> 0.15838641 | J4: 1 января | K4: 1 | L4: 49044620123 | M4: 6704348045
A5: Всего Регулятивный капитал | B5: =+'[9]Bank Capital Calc'!$C$44 -> 8099573040 | J5: 1 февраль | K5: 2 | L5: 48176742405 | M5: 6932887195 | N5: 1 | O5: =+(L4+L5)/2 -> 48610681264 | P5: =+(M4+M5)/2 -> 6818617620
A6: Активы взвешанные с учетом риска | B6: =+'[9]Bank Capital Calc'!$C$45 -> 5.1138054e+10 | J6: 1 март | K6: 3 | L6: 49272519171 | M6: 6959181187 | N6: 2 | O6: =+(L4+L5+L6)/3 -> 4.8831294e+10 | P6: =+(M4+M5+M6)/3 -> 6.8654721e+09
A7: Регулятивный капитал 1 - уровня к Активам взвешанных с учетом риска | B7: =IFERROR((B8/B9),0) -> 0.11878981 | J7: 1 апрель | K7: 4 | L7: 48228728315 | M7: 6962954169 | N7: 3 | O7: =+(L4+L7)/2 -> 48636674219 | P7: =+(M4+M7)/2 -> 6833651107
A8: Регулятивный капитал 1- уровня | B8: =+'[9]Bank Capital Calc'!$C$34 -> 6074679780 | J8: 1 май | K8: 5 | L8: 49746251991 | M8: 7037017395 | N8: 4 | O8: =+(+L4+L5+L6+L7+L8)/5 -> 48893772401 | P8: =+(+M4+M5+M6+M7+M8)/5 -> 6.9192776e+09
A9: Активы взвешанные с учетом риска | B9: =+'[9]Bank Capital Calc'!$C$45 -> 5.1138054e+10 | J9: 1 июнь | K9: 6 | L9: 50302102752 | M9: 7153273541 | N9: 5 | O9: =+(+L4+L5+L6+L7+L8+L9)/6 -> 4.9128494e+10 | P9: =+(+M4+M5+M6+M7+M8+M9)/6 -> 6958276922
A10: Недействующие ссуды за вычетом резервов/общий объем капитала | B10: =IFERROR((B11/B12),0) -> 0.10266945 | J10: 1 июль | K10: 7 | L10: 51087101270 | M10: 7259450266 | N10: 6 | O10: =+(L4+L7+L10)/3 -> 49453483236 | P10: =+(M4+M7+M10)/3 -> 6975584160
A11: Недействующие ссуды за вычетом резервов | B11: =+('Asset Classification'!M50-'Asset Classification'!O50+'Asset Classification'!Q50-'Asset Classification'!S50+'Asset Classification'!U50-'Asset Classification'!W50) -> 790648525 | J11: 1 август | K11: 8 | L11: 52224806702 | M11: 7307210599 | N11: 7 | O11: =(L4+L5+L6+L7+L8+L9+L10+L11)/8 -> 4.9760359e+10 | P11: =(M4+M5+M6+M7+M8+M9+M10+M11)/8 -> 7.0395403e+09
A12: Совокупный капитал на конец периода | B12: =+B35 -> 7700913106 | J12: 1 сентябрь | K12: 9 | L12: 52250823449 | M12: 7378246143 | N12: 8 | O12: =(L4+L5+L6+L7+L8+L9+L10+L11+L12)/9 -> 5.0037077e+10 | P12: =(M4+M5+M6+M7+M8+M9+M10+M11+M12)/9 -> 7.0771743e+09
A13: Недействующие ссуды/общая сумма ссуд | B13: =IFERROR((B14/B15),0) -> 0.037766306 | J13: 1 октябрь | K13: 10 | L13: 51690587249 | M13: 7490055451 | N13: 9 | O13: =+(L4+L7+L10+L13)/4 -> 5.0012759e+10 | P13: =+(M4+M7+M10+M13)/4 -> 7.104202e+09
A14: Недействующие ссуды | B14: =+('Asset Classification'!M50+'Asset Classification'!Q50+'Asset Classification'!U50) -> 1629533297 | J14: 1 ноябрь | K14: 11 | L14: 52850278724 | M14: 7556684556 | N14: 10 | O14: =(+L4+L5+L6+L7+L8+L9+L10+L11+L12+L13+L14)/11 -> 5.0443142e+10 | P14: =(+M4+M5+M6+M7+M8+M9+M10+M11+M12+M13+M14)/11 -> 7158300777
A15: Общая сумма ссуд | B15: =+'Loans Receivable'!C92 -> 43147807488 | J15: 1 декабрь | K15: 12 | L15: 53046003273 | M15: 7621325158 | N15: 11 | O15: =(+L4+L5+L6+L7+L8+L9+L10+L11+L12+L13+L14+L15)/12 -> 5.0660047e+10 | P15: =(+M4+M5+M6+M7+M8+M9+M10+M11+M12+M13+M14+M15)/12 -> 7.1968861e+09
A16: Рентабельность активов | B16: =IFERROR((B17/B18),0) -> 0.023937919 | J16: 1 январь | K16: 13 | L16: 56511320290 | M16: 7700913106 | N16: 12 | O16: =+(L4+L7+L10+L13+L16)/5 -> 5.1312471e+10 | P16: =+(M4+M7+M10+M13+M16)/5 -> 7.2235442e+09
A17: Чистая прибыль до уплаты налогов | B17: =(+'Income '!C72)/MONTH(B3)*12 -> 1228313807
A18: Всего активы (средний за период) | B18: =VLOOKUP(MONTH(B3),$N$4:$P$16,2,0) -> 5.1312471e+10
A19: Рентабельность капитала | B19: =IFERROR((B20/B21),0) -> 0.13819001
A20: Чистая прибыль | B20: =(+'Income '!C79)/MONTH(B3)*12 -> 998221670
A21: Совокупный капитал (средний за период) | B21: =VLOOKUP(MONTH(B3),$N$4:$P$16,3,0) -> 7.2235442e+09
A22: Процентная маржа/валовой доход | B22: =IFERROR((B23/B24),0) -> 0.48848511
A23: Процентная маржа | B23: =+'Income '!C30 -> 2066879854
A24: Валовой доход | B24: =+B27 -> 4231203432
A25: Непроцентные расходы/валовой доход | B25: =IFERROR((B26/B27),0) -> 0.36778276
A26: Непроцентные расходы | B26: =+'Income '!C54+'Income '!C70 -> 1556163674
A27: Валовой доход | B27: =+'Income '!C30+'Income '!C46 -> 4231203432
A28: Ликвидные активы/всего активы | B28: =IFERROR((B29/B30),0) -> 0.16454483
A29: Ликвидные активы | B29: =+B32 -> 9298645785
A30: Всего активы | B30: =+B36 -> 56511320290
A31: Ликвидные активы/краткосрочные обязательства | B31: =IFERROR((B29/B33),0) -> 0.42627134
A32: Ликвидные активы | B32: =+B54 -> 9298645785
A33: Краткосрочные обязательства | B33: =+('[8]Bank Liabilities Analysis'!$C$39+'[8]Bank Liabilities Analysis'!$E$39+'[8]Bank Liabilities Analysis'!$G$39+'[8]Bank Liabilities Analysis'!$I$39+'[8]Bank Liabilities Analysis'!$K$39+'[8]Bank Liabilities Analysis'!$M$39) -> 21813912715
A34: Совокупный капитал на конец периода/Всего активы | B34: =IFERROR((B35/B36),0) -> 0.13627204
A35: Совокупный капитал на конец периода | B35: =+[8]Balance!$C$77 -> 7700913106
A36: Всего активы | B36: =+[8]Balance!$C$45 -> 56511320290
A37: Чистая открытая валютная позиция /Совокупный капитал на конец периода | B37: =IFERROR((B38/B39),0) -> 0.036092413
A38: Чистая открытая валютная позиция | B38: =+'[9]Calculation of Risk'!$C$26 -> 277944540
A39: Совокупный капитал на конец периода | B39: =+B35 -> 7700913106
A42: Подпись Председателя правления:
A44: Подпись Главного Бухгалтера:
A46: Ликвидные активы | B46: Сумма | C46: Нацвалюта | D46: Инвалюта
A47: Наличные денежные средства и Драгоценные металлы | B47: =+'[8]Liquidity Analysis'!C50 -> 882035733 | C47: =+'[8]Liquidity Analysis'!D50 -> 250900761 | D47: =+'[8]Liquidity Analysis'!E50 -> 631134972 | E47: 1.
A48: К получению из ЦБРУ | B48: =+'[8]Liquidity Analysis'!C51 -> 3258433287 | C48: =+'[8]Liquidity Analysis'!D51 -> 2481708653 | D48: =+'[8]Liquidity Analysis'!E51 -> 776724634 | E48: 2.
A49: К получению из других банков | B49: =+'[8]Liquidity Analysis'!C52 -> 3603375784 | C49: =+'[8]Liquidity Analysis'!D52 -> 9969936 | D49: =+'[8]Liquidity Analysis'!E52 -> 3593405848 | E49: 3.
A50: К получению из других банков - Депозиты (чистые) | B50: =+'[8]Liquidity Analysis'!C53 -> 485000981 | C50: =+'[8]Liquidity Analysis'!D53 -> 0 | D50: =+'[8]Liquidity Analysis'!E53 -> 488302017 | E50: 3.1.
A51: Ценные бумаги, выпущенные Правительством Республики Узбекистан и ЦБРУ (векселя, облигации и другие долговые ценные бумаги) | B51: =+'[8]Liquidity Analysis'!C54 -> 1069800000 | C51: =+'[8]Liquidity Analysis'!D54 -> 1069800000 | D51: =+'[8]Liquidity Analysis'!E54 -> 0 | E51: 4.
A52: Ценные бумаги, выпущенные странами с низким уровня риска | B52: =+'[8]Liquidity Analysis'!C55 -> 0 | C52: =+'[8]Liquidity Analysis'!D55 -> 0 | D52: =+'[8]Liquidity Analysis'!E55 -> 0 | E52: 5.
A53: Другие легко реализуемые ценные бумаги | B53: =+'[8]Liquidity Analysis'!C56 -> 0 | C53: =+'[8]Liquidity Analysis'!D56 -> 0 | D53: =+'[8]Liquidity Analysis'!E56 -> 0 | E53: 6.
A54: Итого ликвидных активов | B54: =+'[8]Liquidity Analysis'!C57 -> 9298645785 | C54: =+'[8]Liquidity Analysis'!D57 -> 3812379350 | D54: =+'[8]Liquidity Analysis'!E57 -> 5489567471 | E54: 7.
