Workbook
Name jop: #REF!
Name kol: #REF!
Name TwentyLargestData: #REF!
Name Е: #REF!

Sheet Bank Capital Calc
A1: РАСЧЕТ РЕГУЛЯТИВНОГО КАПИТАЛА БАНКА | C1: Таблица-5 | E1: №4
B3: АТБ "Ўзсаноатқурилишбанк" | C3: 44560
A4: № | B4: Характеристики | C4: Итого капитала
A5: I. | B5: КАПИТАЛ УРОВНЯ 1
A6: 1 | B6: ОСНОВНОЙ КАПИТАЛ УРОВНЯ 1
A7: 1.1. | B7: Обыкновенные Акции, чистые | C7: =+C8+C9 -> 4627483904
A8: a | B8: Полностью оплаченные обыкновенные акции | C8: 4627483904
A9: б | B9: Минус: Обратно Выкупленные обыкновенные акции | C9: 0
A10: 1.2. | B10: Добавленный капитал - Обыкновенные
A11: 1.3. | B11: Нераспределенная прибыль (убыток), в том числе капитальные резервы | C11: =+C12+C13-C14-C15 -> 1596218610
A12: а | B12: Капитальные резервы | C12: 1595250627
A13: б | B13: Нераспределенная прибыль | C13: 967983
A14: в | B14: Убыток за предыдущие периоды | C14: 0
A15: г | B15: Убыток за текущий год | C15: 0
A16: 1.4. | B16: Интерес меньшинства в консолидированных дочерних компаниях (согласно МБС) | C16: 0
A17: 1.5. | B17: Резерв на девальвацию | C17: 0 | E17: =+'[6]Transactions of related parties'!$Z$64 -> 83886999
B18: Итого основного капитала уровня I до вычетов | C18: =+C7+C10+C11+C16+C17 -> 6223702514
A19: 1.6. | B19: Вычеты из суммы основного капитала уровня I | C19: =C20+C21+C22+C23+C24 -> 156748855
A20: а | B20: Нематериальные активы за вычетом программных обеспечений | C20: 13083294
A21: б | B21: Все инвестиции в капитал неконсолидированных хозяйствующих субъектов, в том числе в долговые обязательства, которые образуют капитал хозяйствующих субъектов | C21: 143665561
A22: в | B22: Инвестиции в капитал других банков | C22: 0
A23: г | B23: Резервы формируемые в соответствии с предписанием Центрального банка | C23: 0
A24: д | B24: Сумма превышения максимального размера риска по одному или всем связанным с банком лицами | C24: 0
A25: I | B25: ВСЕГО СКОРРЕКТИРОВАННЫЙ ОСНОВНОЙ КАПИТАЛ УРОВНЯ I | C25: =+C18-C19 -> 6066953659 | E25: =C18-C20-C21-C22-C23 -> 6066953659
A26: 2 | B26: ДОБАВЛЕННЫЙ КАПИТАЛ УРОВНЯ 1
A27: 2.1. | B27: Некумулятивные бессрочные привилегированные акции | C27: =+C28+C29 -> 7030000
A28: а | B28: Полностью оплаченные привилегированные акции | C28: 7030000
A29: б | B29: Минус: Обратно Выкупленные привилегированные акции | C29: 0
A30: 2.2. | B30: Добавленный капитал - Привилегированные | C30: 696121
A31: 2.3. | B31: Интерес меньшинства в консолидированных дочерних компаниях | C31: 0
A32: 2.4. | B32: Доля участия дочерних предприятий (выпущенные дочерними предприятиями и находящиеся во владении третьих лиц инструменты, приравненные к капиталу) | C32: 0
A33: II | B33: ВСЕГО ДОБАВЛЕННЫЙ КАПИТАЛ УРОВНЯ I | C33: =+C27+C30+C31+C32 -> 7726121
A34: III | B34: ВСЕГО СКОРРЕКТИРОВАННЫЙ КАПИТАЛ УРОВНЯ I | C34: =+C25+C33 -> 6074679780
B35: КАПИТАЛ УРОВНЯ II
A36: 3.1. | B36: Прибыль за текущий год | C36: 998221670
A37: 3.2. | B37: Резервы, создаваемые на стандартные кредиты (активы), в размере не более 1.25% от общей суммы активов, взвешенных с учетом риска | C37: =IF(F37<(C45*1.25%),F37,(C45*1.25%)) -> 454928207 | E37: Резервы созданные по стандартным активам | F37: 454928207
A38: 3.3. | B38: Излишки оценочной стоимости прироста над первоначальной стоимостью | C38: 7350567 | F38: =+[7]Balance!$C$72 -> 454928207
A39: 3.4. | B39: Другие инструменты капитала (не более 1/3 части капитала 1 уровня после вычетов) | C39: 0 | F39: =+F37-F38 -> 0
A40: 3.5. | B40: Субординированный долг | C40: 566095403
A41: 3.6. | B41: Вычеты превышения Капитала Уровня II над Капиталом Уровня I | C41: =IF(C42<(C34/3),0,(C42-C34/3)*-1) -> -1702587
B42: Итого капитала Уровня II | C42: =SUM(C36:C40) -> 2026595847
A43: IV | B43: СКОРРЕКТИРОВАННЫЙ КАПИТАЛ УРОВНЯ II | C43: =+C41+C42 -> 2024893260
A44: V | B44: ВСЕГО РЕГУЛЯТИВНЫЙ КАПИТАЛ | C44: =+C34+C41+C42 -> 8099573040
A45: VI | B45: ОБЩАЯ СУММА АКТИВОВ ВЗВЕШЕННЫХ С УЧЕТОМ РИСКА | C45: =+C46+C47+C48 -> 5.1138054e+10
A46: а | B46: Сумма балансовых и забалансовых активов, взвешенных с учетом риска | C46: =+'Calculation of Risk Weighted As'!I70 -> 4.8459344e+10
A47: б | B47: Операционный риск | C47: =+'Calculation of Risk'!C21 -> 2.4649069e+09
A48: в | B48: Рыночный риск | C48: =+'Calculation of Risk'!C27 -> 2.1380349e+08
A49: VII | B49: КОЭФФИЦИЕНТ ОСНОВНОГО КАПИТАЛА УРОВНЯ I (I/VI) | C49: =IFERROR((+C25/C45),0) -> 0.11863873
A50: VIII | B50: КОЭФФИЦИЕНТ КАПИТАЛА УРОВНЯ I (III/VI) | C50: =IFERROR((+C34/C45),0) -> 0.11878981
A51: IX | B51: КОЭФФИЦИЕНТ ОБЩЕЙ СУММЫ КАПИТАЛА, ОСНОВАННОГО НА РИСКЕ (V/VI) | C51: =IFERROR((+C44/C45),0) -> 0.15838641
A52: X | B52: Активы для расчета левеража | C52: =SUM(C53:C55)-C56 -> 6.0872044e+10
A53: а | B53: Общие активы | C53: 56511320290
A54: б | B54: Забалансовые инструменты | C54: =SUM('Calculation of Risk Weighted As'!E50:H58)-'Calculation of Risk Weighted As'!E52 -> 4517465969 | D54: =+'Calculation of Risk Weighted As'!I70 -> 4.8459344e+10
A55: в | B55: Деривативные (производные) инструменты | C55: =SUM('Calculation of Risk Weighted As'!I61:I67) -> 6535.42
A56: г | B56: Минус: Строка 1.6. Итого вычетов из суммы основного капитала Уровня 1 | C56: =+C19 -> 156748855
A57: XI | B57: Коэффициент левеража | C57: =IFERROR((+C34/C52),0) -> 0.099794247
B59: Подпись Председателя правления:
B61: Подпись Главного Бухгалтера:

Sheet Bank Capital Calc (2)
A1: РАСЧЕТ РЕГУЛЯТИВНОГО КАПИТАЛА БАНКА | C1: Таблица-5
B3: =#REF! -> #REF! | C3: =+#REF! -> #REF!
A4: № | B4: Характеристики | C4: Итого капитала
A5: I. | B5: КАПИТАЛ УРОВНЯ 1
A6: 1 | B6: ОСНОВНОЙ КАПИТАЛ УРОВНЯ 1
A7: 1.1. | B7: Обыкновенные Акции, чистые | C7: Формула
A8: a | B8: Полностью оплаченные обыкновенные акции
A9: б | B9: Минус: Обратно Выкупленные обыкновенные акции
A10: 1.2. | B10: Добавленный капитал - Обыкновенные | C10: 0
A11: 1.3. | B11: Нераспределенная прибыль (убыток), в том числе капитальные резервы | C11: Формула
A12: а | B12: Капитальные резервы
A13: б | B13: Нераспределенная прибыль
A14: в | B14: Убыток за предыдущие периоды
A15: г | B15: Убыток за текущий год
A16: 1.4. | B16: Интерес меньшинства в консолидированных дочерних компаниях (согласно МБС)
A17: 1.5. | B17: Резерв на девальвацию
B18: Итого основного капитала уровня I до вычетов | C18: Формула
A19: 1.6. | B19: Вычеты из суммы основного капитала уровня I | C19: Формула
A20: а | B20: Нематериальные активы
A21: б | B21: Все инвестиции в капитал неконсолидированных хозяйствующих субъектов, в том числе в долговые обязательства, которые образуют капитал хозяйствующих субъектов
A22: в | B22: Инвестиции в капитал других банков
A23: I | B23: ВСЕГО СКОРРЕКТИРОВАННЫЙ ОСНОВНОЙ КАПИТАЛ УРОВНЯ I | C23: Формула
A24: 2 | B24: ДОБАВЛЕННЫЙ КАПИТАЛ УРОВНЯ 1
A25: 2.1. | B25: Некумулятивные бессрочные привилегированные акции | C25: =+C26+C27 -> 0
A26: а | B26: Полностью оплаченные привилегированные акции
A27: б | B27: Минус: Обратно Выкупленные привилегированные акции
A28: 2.2. | B28: Добавленный капитал - Привилегированные | C28: 0
A29: 2.3. | B29: Интерес меньшинства в консолидированных дочерних компаниях | C29: 0
A30: 2.4. | B30: Доля участия дочерних предприятий (выпущенные дочерними предприятиями и находящиеся во владении третьих лиц инструменты, приравненные к капиталу) | C30: 0
A31: II | B31: ВСЕГО ДОБАВЛЕННЫЙ КАПИТАЛ УРОВНЯ I | C31: =+C25+C28+C29+C30 -> 0
A32: III | B32: ВСЕГО СКОРРЕКТИРОВАННЫЙ КАПИТАЛ УРОВНЯ I | C32: Формула
B33: КАПИТАЛ УРОВНЯ II
A34: 3.1. | B34: Прибыль за текущий год
A35: 3.2. | B35: Резервы, создаваемые на стандартные кредиты (активы), в размере не более 1.25% от общей суммы активов, взвешенных с учетом риска | C35: =IF(#REF!<(C43*1.25%),#REF!,(C43*1.25%)) -> #REF!
A36: 3.3. | B36: Излишки оценочной стоимости прироста над первоначальной стоимостью
A37: 3.4. | B37: Другие инструменты капитала (не более 1/3 части капитала 1 уровня после вычетов)
A38: 3.5. | B38: Субординированный долг
A39: 3.6. | B39: Вычеты превышения Капитала Уровня II над Капиталом Уровня I | C39: Формула
B40: Итого капитала Уровня II | C40: =SUM(C34:C38) -> #REF!
A41: IV | B41: СКОРРЕКТИРОВАННЫЙ КАПИТАЛ УРОВНЯ II | C41: Формула
A42: V | B42: ВСЕГО РЕГУЛЯТИВНЫЙ КАПИТАЛ | C42: Формула
A43: VI | B43: ОБЩАЯ СУММА АКТИВОВ ВЗВЕШЕННЫХ С УЧЕТОМ РИСКА | C43: =+C44+C45+C46 -> 5.1138054e+10
A44: а | B44: Сумма балансовых и забалансовых активов, взвешенных с учетом риска | C44: =+'Calculation of Risk Weighted As'!I70 -> 4.8459344e+10
A45: б | B45: Операционный риск | C45: =+'Calculation of Risk'!C21 -> 2.4649069e+09
A46: в | B46: Рыночный риск | C46: =+'Calculation of Risk'!C27 -> 2.1380349e+08 | E46: =+'Calculation of Risk'!G11 -> 0
A47: VII | B47: КОЭФФИЦИЕНТ ОСНОВНОГО КАПИТАЛА УРОВНЯ I (I/VI) | C47: Формула
A48: VIII | B48: КОЭФФИЦИЕНТ КАПИТАЛА УРОВНЯ I (III/VI) | C48: Формула
A49: IX | B49: КОЭФФИЦИЕНТ ОБЩЕЙ СУММЫ КАПИТАЛА, ОСНОВАННОГО НА РИСКЕ (V/VI) | C49: Формула
A50: X | B50: Активы для расчета левеража | C50: Формула
A51: а | B51: Общие активы | C51: =+#REF! -> #REF!
A52: б | B52: Забалансовые инструменты | C52: =SUM('Calculation of Risk Weighted As'!E50:H58) -> 4517465969 | D52: =+'Calculation of Risk Weighted As'!I70 -> 4.8459344e+10
A53: в | B53: Деривативные (производные) инструменты | C53: =SUM('Calculation of Risk Weighted As'!I61:I67) -> 6535.42
A54: г | B54: Минус: Строка 1.6. Итого вычетов из суммы основного капитала Уровня 1 | C54: =+C19 -> Формула
A55: XI | B55: Коэффициент левеража | C55: Формула
B57: Подпись Председателя правления:
B59: Подпись Главного Бухгалтера:

Sheet Calculation of Risk Weighted As
A1: РАСЧЕТ АКТИВОВ ВЗВЕШЕННЫХ С УЧЕТОМ РИСКА | I1: Таблица-6
B2: =+'Bank Capital Calc'!B3 -> АТБ "Ўзсаноатқурилишбанк" | G2: =+'Bank Capital Calc'!C3 -> 44560 | I2: тыс. сум
A3: № | B3: Характеристики | C3: 0 | D3: 0.2 | E3: 0.35 | F3: 0.5 | G3: 1 | H3: 1.5 | I3: 2
C4: Риск | D4: Риск | E4: Риск | F4: Риск | G4: Риск | H4: Риск | I4: Риск
C5: I группа | D5: II группа | E5: III группа | F5: IV группа | G5: V группа | H5: VI группа | I5: VII группа
B6: (A) | C6: (Б) | D6: (В) | E6: (Г) | F6: (Д) | G6: (Е) | H6: (Ж) | I6: (З)
B7: Балансовые Активы
A8: 1. | B8: Касса (наличность и монеты) и Драгоценные металлы | C8: 731962011
A9: 2. | B9: Денежная наличность и другие платежные документы в пути | D9: 150073722
A10: 3. | B10: Корреспондентские и резервные счета в ЦБРУ | C10: 2481708653 | D10: 776724634
A11: 4. | B11: Корреспондентские счета, кредиты и другие требования к банкам | D11: 4160105268 | F11: 202390748 | G11: 1483175084 | H11: 20077603
A12: 5. | B12: Ценные бумаги, чистые
A13: а) | B13: Ценные бумаги, выпущенные Правительством Республики Узбекистан и ЦБРУ | C13: 1057702046
A14: б) | B14: Ценные бумаги, выпущенные правительствами и центральными банками зарубежных стран, а также другие требования к центральным банкам и правительствам этих стран
A15: в) | B15: Другие ценные бумаги, выпущенные на территории Республики Узбекистан
A16: г) | B16: Другие ценные бумаги, выпущенные зарубежными странами
A17: 6. | B17: Активы, не деноминированные в национальную валюту и превышающие сумму финансирования в национальной валюте
A18: 7. | B18: Требования банка к государственным секторам зарубежных стран (кроме Правительств и Центральных банков) и зарубежным компаниям, а также активы, обеспеченные или гарантированные их ценными бумагами (кроме кредитов и ценных бумаг)
A19: 8. | B19: Кредиты и лизинги, чистые
A20: а) | B20: Прямые требования к Правительству и Центральному банку Республики Узбекистан | C20: 0
A21: б) | B21: Кредиты международным финансовым организациям; кредиты, обеспеченные ценными бумагами международных финансовых организаций или гарантированные ими | C21: 0
A22: в) | B22: Кредиты или их части, обеспеченные депозитами | C22: 936994207 | D22: 1472156
A23: г) | B23: Кредиты/их части, обеспеченные ценными бумагами, оцененными по текущей рыночной стоимости и выпущенными или гарантированными Правительством, Центральным банком РУз, а также кредиты/их части, гарантированные Правительством, Центральным банком Руз | D23: 7319296930
A24: д) | B24: Кредиты, по которым банк не имеет приоритетного права на залог | G24: 185217039
A25: е) | B25: Кредиты, выданные населению на приобретения недвижимости и обеспеченные приобретаемым или строящимся домом (квартирой) | E25: 232273508 | F25: 870670600 | G25: 1688241186 | H25: 25414291
A26: ж) | B26: Другие кредиты, выданные населению | G26: 579616439 | H26: 174419766 | I26: 169432171
A27: з) | B27: Все другие кредиты и лизинги | G27: 21913129416 | H27: 2794544226 | I27: 2136251747
A28: и) | B28: Кредиты и лизинги в судебном разбирательстве, просроченные, пересмотренные и в статусе «не наращивания», чистые | H28: 2503543998 | I28: 510771127
A29: 9. | B29: Основные средства и другое собственное имущество банка
A30: а | B30: Основные средства, используемые в банковской деятельности (минус амортизация) | G30: 1181891713
A31: б | B31: Другое банковское собственное имущество | G31: =105745990-H32-H33 -> 47184123
A32: в | B32: Недвижимое имущество принятое на баланс банка в целях полного или частичного погащения задолженности | H32: 58522043
A33: г | B33: Недвижимое имущество банка, которым банк не пользуется более двух лет | H33: 39824
A34: 10. | B34: Все инвестиции в капитал неконсолидированных хозяйствующих субъектов, в том числе в долговые обязательства, которые образуют капитал хозяйствующих субъектов, инвестиции в капитал других банков, чистые | C34: 143665561
A35: 11. | B35: Все другие инвестиции, чистые | G35: =5850400 -> 5850400
A36: 12. | B36: Нематериальные активы, чистые | C36: ='Bank Capital Calc'!C20 -> 13083294 | G36: =64557643-C36 -> 51474349
A37: 13. | B37: Другие активы в судебном разбирательстве, пересмотренные активы, а также не взысканные в установленном порядке | H37: 617158
A38: 14. | B38: Другие активы, чистые | C38: 0 | D38: 0 | F38: 0 | G38: =1904400407-H37 -> 1903783249 | H38: 0
A39: 15. | B39: Общая сумма балансовых активов согласно инструкции | C39: =SUM(C8:C38) -> 5365115772 | D39: =SUM(D8:D38) -> 12407672710 | E39: =SUM(E8:E38) -> 232273508 | F39: =SUM(F8:F38) -> 1073061348 | G39: =SUM(G8:G38) -> 29039562998 | H39: =SUM(H8:H38) -> 5577178909 | I39: =SUM(I8:I38) -> 2816455045 | J39: =SUM(C39:I39) -> 56511320290 | K39: =+[7]Balance!$C$45 -> 56511320290 | L39: =+J39-K39 -> 0
A40: 16. | B40: Общая сумма балансовых рисковых активов, по группам риска | D40: =D39*D3 -> 2481534542 | E40: =E39*E3 -> 81295728 | F40: =F39*F3 -> 536530674 | G40: =G39*G3 -> 29039562998 | H40: =H39*H3 -> 8.3657684e+09 | I40: =I39*I3 -> 5632910090
A41: 17. | B41: Общая сумма балансовых рисковых активов | I41: =SUM(D40:I40) -> 4.6137602e+10
A44: № | B44: Характеристики | D44: Фактор пересчета кредита | E44: 0 | F44: 0.2 | G44: 0.5 | H44: 1 | I44: Значение риска
E46: Риск | F46: Риск | G46: Риск | H46: Риск
B47: (A) | D47: (Б) | E47: (В) | F47: (Г) | G47: (Д) | H47: (Е) | I47: (Ж)
A48: Забалансовые Активы
A49: 1 | B49: Обязательства по выдаче кредита
A50: a | B50: Более одного года | D50: 0.5 | I50: =(F50*0.1)+(G50*0.25)+(H50*0.5) -> 0
A51: б | B51: Год и менее | D51: 0.2 | F51: 297135410 | H51: 741841838 | I51: =(F51*0.04)+(G51*0.1)+(H51*0.2) -> 160253784
A52: 2 | B52: Обязательства по приобретению ценных бумаг и других активов (включая активы, проданные в соответствии с соглашениями об обратном выкупе) | D52: 1 | I52: =(F52*0.2)+(G52*0.5)+(H52*1) -> 0
A53: 3 | B53: Гарантии и поручительства | D53: 1 | E53: 1587605 | H53: =1834213566-E53 -> 1832625961 | I53: =(F53*0.2)+(G53*0.5)+(H53*1) -> 1832625961
A54: 4 | B54: Аккредитивы
A55: a | B55: Прямые кредитные заменители | D55: 1 | I55: =(F55*0.2)+(G55*0.5)+(H55*1) -> 0
A56: б | B56: Связанные со сделками | D56: 0.5 | I56: =(F56*0.1)+(G56*0.25)+(H56*0.5) -> 0
A57: в | B57: Связанные с торговлей (краткосрочные, самоликвидирующиеся, обеспеченные поставкой товара) | D57: 0.2 | H57: 1644275155 | I57: =(F57*0.04)+(G57*0.1)+(H57*0.2) -> 328855031
A58: г | B58: Другие аккредитивы | D58: 1 | I58: =(F58*0.2)+(G58*0.5)+(H58*1) -> 0
A59: 5 | B59: Форврдные котракты, свопы, опционы и подобные обязательства
A60: a | B60: Контракты по процентной ставке
A61: а1 | B61: Со сроком погашения до одного года | D61: 0.005 | I61: =(F61*0.001)+(G61*0.0025)+(H61*0.005) -> 0
A62: а2 | B62: Со сроком погашения от одного года до двух лет | D62: 0.01 | I62: =(F62*0.002)+(G62*0.005)+(H62*0.01) -> 0
A63: а3 | B63: Со сроком погашения от двух до трех лет | D63: 0.02 | I63: =(F63*0.004)+(G63*0.01)+(H63*0.02) -> 0
A64: б | B64: Валютные контракты и золото
A65: б1 | B65: Со сроком погашения до одного года | D65: 0.02 | H65: =325417+1354 -> 326771 | I65: =(F65*0.004)+(G65*0.01)+(H65*0.02) -> 6535.42
A66: б2 | B66: Со сроком погашения от одного года до двух лет | D66: 0.05 | I66: =(F66*0.01)+(G66*0.025)+(H66*0.05) -> 0
A67: б3 | B67: Со сроком погашения от двух до трех лет | D67: 0.08 | I67: =(F67*0.016)+(G67*0.04)+(H67*0.08) -> 0
A68: 6 | B68: Общая сумма забалансовых активов | E68: =SUM(E50:E67) -> 1587605 | F68: =SUM(F50:F67) -> 297135410 | G68: =SUM(G50:G67) -> 0 | H68: =SUM(H50:H67) -> 4219069725 | J68: =SUM(E68:H68) -> 4517792740 | K68: =+[7]Commitments!$C$4+[7]Commitments!$C$7+[7]Commitments!$C$10+[7]Commitments!$C$19+[7]Commitments!$C$20+[7]Commitments!$C$21+[7]Commitments!$C$22 -> 4517792740 | L68: =+J68-K68 -> 0
A69: 7 | B69: Общая сумма забалансовых активов, взвешенных с учетом риска | I69: =SUM(I50:I67) -> 2.3217413e+09
A70: 8 | B70: Общая сумма активов, взвешенных с учетом риска | I70: =SUM(I69+I41) -> 4.8459344e+10 | J70: =+I70*0.15 -> 7.2689016e+09
B72: Подпись Председателя правления:
B74: Подпись Главного Бухгалтера:

Sheet Calculation of Risk Weighte нац
A1: РАСЧЕТ АКТИВОВ ВЗВЕШЕННЫХ С УЧЕТОМ РИСКА В НАЦИОНАЛЬНОЙ ВАЛЮТЕ | I1: Таблица-6.1
B2: =+'Bank Capital Calc'!B3 -> АТБ "Ўзсаноатқурилишбанк" | G2: =+'Bank Capital Calc'!C3 -> 44560 | I2: тыс. сум
A3: № | B3: Характеристики | C3: 0 | D3: 0.2 | E3: 0.35 | F3: 0.5 | G3: 1 | H3: 1.5 | I3: 2
C4: Риск | D4: Риск | E4: Риск | F4: Риск | G4: Риск | H4: Риск | I4: Риск
C5: I группа | D5: II группа | E5: III группа | F5: IV группа | G5: V группа | H5: VI группа | I5: VII группа
B6: (A) | C6: (Б) | D6: (В) | E6: (Г) | F6: (Д) | G6: (Е) | H6: (Ж) | I6: (З)
B7: Балансовые Активы
A8: 1. | B8: Касса (наличность и монеты) и Драгоценные металлы | C8: 180134495
A9: 2. | B9: Денежная наличность и другие платежные документы в пути | D9: 70766266
A10: 3. | B10: Корреспондентские и резервные счета в ЦБРУ | C10: 2481708653 | D10: 0
A11: 4. | B11: Корреспондентские счета, кредиты и другие требования к банкам | D11: 0 | F11: 10019936 | G11: 662284205 | H11: 0
A12: 5. | B12: Ценные бумаги, чистые
A13: а) | B13: Ценные бумаги, выпущенные Правительством Республики Узбекистан и ЦБРУ | C13: 1057702047
A14: б) | B14: Ценные бумаги, выпущенные правительствами и центральными банками зарубежных стран, а также другие требования к центральным банкам и правительствам этих стран | C14: 0 | D14: 0 | F14: 0 | G14: 0 | H14: 0
A15: в) | B15: Другие ценные бумаги, выпущенные на территории Республики Узбекистан | D15: 0 | F15: 0 | G15: 0 | H15: 0
A16: г) | B16: Другие ценные бумаги, выпущенные зарубежными странами | C16: 0 | D16: 0 | F16: 0 | G16: 0 | H16: 0
A17: 6. | B17: Активы, не деноминированные в национальную валюту и превышающие сумму финансирования в национальной валюте | G17: 0
A18: 7. | B18: Требования банка к государственным секторам зарубежных стран (кроме Правительств и Центральных банков) и зарубежным компаниям, а также активы, обеспеченные или гарантированные их ценными бумагами (кроме кредитов и ценных бумаг) | C18: 0 | D18: 0 | F18: 0 | G18: 0 | H18: 0
A19: 8. | B19: Кредиты и лизинги, чистые
A20: а) | B20: Прямые требования к Правительству и Центральному банку Республики Узбекистан | C20: 0
A21: б) | B21: Кредиты международным финансовым организациям; кредиты, обеспеченные ценными бумагами международных финансовых организаций или гарантированные ими | C21: 0
A22: в) | B22: Кредиты или их части, обеспеченные депозитами | C22: 8110486 | D22: 13339
A23: г) | B23: Кредиты/их части, обеспеченные ценными бумагами, оцененными по текущей рыночной стоимости и выпущенными или гарантированными Правительством, Центральным банком РУз, а также кредиты/их части, гарантированные Правительством, Центральным банком Руз | D23: 1119161803
A24: д) | B24: Кредиты, по которым банк не имеет приоритетного права на залог | G24: 185217039
A25: е) | B25: Кредиты, выданные населению на приобретения недвижимости и обеспеченные приобретаемым или строящимся домом (квартирой) | E25: 232273508 | F25: 870670600 | G25: 1688241186 | H25: 25414291
A26: ж) | B26: Другие кредиты, выданные населению | G26: 579616439 | H26: 174419766 | I26: 169432171
A27: з) | B27: Все другие кредиты и лизинги | G27: 6590170108 | H27: 1253708190 | I27: 784627453
A28: и) | B28: Кредиты и лизинги в судебном разбирательстве, просроченные, пересмотренные и в статусе «не наращивания», чистые | H28: 513118821 | I28: 437366438
A29: 9. | B29: Основные средства и другое собственное имущество банка
A30: а | B30: Основные средства, используемые в банковской деятельности (минус амортизация) | G30: 1181891713
A31: б | B31: Другое банковское собственное имущество | G31: =105745990-H32-H33 -> 47184123
A32: в | B32: Недвижимое имущество принятое на баланс банка в целях полного или частичного погащения задолженности | H32: 58522043
A33: г | B33: Недвижимое имущество банка, которым банк не пользуется более двух лет | H33: 39824
A34: 10. | B34: Все инвестиции в капитал неконсолидированных хозяйствующих субъектов, в том числе в долговые обязательства, которые образуют капитал хозяйствующих субъектов, инвестиции в капитал других банков, чистые | C34: 140885962
A35: 11. | B35: Все другие инвестиции, чистые | G35: 5850400
A36: 12. | B36: Нематериальные активы, чистые | C36: 13083294 | G36: 51474349
A37: 13. | B37: Другие активы в судебном разбирательстве, пересмотренные активы, а также не взысканные в установленном порядке | H37: 617158
A38: 14. | B38: Другие активы, чистые | C38: 0 | D38: 0 | F38: 0 | G38: =1071135054-H37 -> 1070517896 | H38: 0
A39: 15. | B39: Общая сумма балансовых активов согласно инструкции | C39: =SUM(C8:C38) -> 3881624937 | D39: =SUM(D8:D38) -> 1189941408 | E39: =SUM(E8:E38) -> 232273508 | F39: =SUM(F8:F38) -> 880690536 | G39: =SUM(G8:G38) -> 12062447458 | H39: =SUM(H8:H38) -> 2025840093 | I39: =SUM(I8:I38) -> 1391426062 | J39: =SUM(C39:I39) -> 21664244002 | K39: =+[7]Balance!$D$45 -> 21664244002 | L39: =+J39-K39 -> 0
A40: 16. | B40: Общая сумма балансовых рисковых активов, по группам риска | D40: =D39*D3 -> 2.3798828e+08 | E40: =E39*E3 -> 81295728 | F40: =F39*F3 -> 440345268 | G40: =G39*G3 -> 12062447458 | H40: =H39*H3 -> 3.0387601e+09 | I40: =I39*I3 -> 2782852124
A41: 17. | B41: Общая сумма балансовых рисковых активов | I41: =SUM(D40:I40) -> 1.8643689e+10
A44: № | B44: Характеристики | D44: Фактор пересчета кредита | E44: 0 | F44: 0.2 | G44: 0.5 | H44: 1 | I44: Значение риска
E46: Риск | F46: Риск | G46: Риск | H46: Риск
B47: (A) | D47: (Б) | E47: (В) | F47: (Г) | G47: (Д) | H47: (Е) | I47: (Ж)
A48: Забалансовые Активы
A49: 1 | B49: Обязательства по выдаче кредита
A50: a | B50: Более одного года | D50: 0.5 | I50: =(F50*0.1)+(G50*0.25)+(H50*0.5) -> 0
A51: б | B51: Год и менее | D51: 0.2 | H51: 741841838 | I51: =(F51*0.04)+(G51*0.1)+(H51*0.2) -> 1.4836837e+08
A52: 2 | B52: Обязательства по приобретению ценных бумаг и других активов (включая активы, проданные в соответствии с соглашениями об обратном выкупе) | D52: 1 | I52: =(F52*0.2)+(G52*0.5)+(H52*1) -> 0
A53: 3 | B53: Гарантии и поручительства | D53: 1 | E53: 1587605 | H53: =30401838-E53 -> 28814233 | I53: =(F53*0.2)+(G53*0.5)+(H53*1) -> 28814233
A54: 4 | B54: Аккредитивы
A55: a | B55: Прямые кредитные заменители | D55: 1 | I55: =(F55*0.2)+(G55*0.5)+(H55*1) -> 0
A56: б | B56: Связанные со сделками | D56: 0.5 | I56: =(F56*0.1)+(G56*0.25)+(H56*0.5) -> 0
A57: в | B57: Связанные с торговлей (краткосрочные, самоликвидирующиеся, обеспеченные поставкой товара) | D57: 0.2 | I57: =(F57*0.04)+(G57*0.1)+(H57*0.2) -> 0
A58: г | B58: Другие аккредитивы | D58: 1 | I58: =(F58*0.2)+(G58*0.5)+(H58*1) -> 0
A59: 5 | B59: Форврдные котракты, свопы, опционы и подобные обязательства
A60: a | B60: Контракты по процентной ставке
A61: а1 | B61: Со сроком погашения до одного года | D61: 0.005 | I61: =(F61*0.001)+(G61*0.0025)+(H61*0.005) -> 0
A62: а2 | B62: Со сроком погашения от одного года до двух лет | D62: 0.01 | I62: =(F62*0.002)+(G62*0.005)+(H62*0.01) -> 0
A63: а3 | B63: Со сроком погашения от двух до трех лет | D63: 0.02 | I63: =(F63*0.004)+(G63*0.01)+(H63*0.02) -> 0
A64: б | B64: Валютные контракты и золото
A65: б1 | B65: Со сроком погашения до одного года | D65: 0.02 | E65: 0 | I65: =(F65*0.004)+(G65*0.01)+(H65*0.02) -> 0
A66: б2 | B66: Со сроком погашения от одного года до двух лет | D66: 0.05 | I66: =(F66*0.01)+(G66*0.025)+(H66*0.05) -> 0
A67: б3 | B67: Со сроком погашения от двух до трех лет | D67: 0.08 | I67: =(F67*0.016)+(G67*0.04)+(H67*0.08) -> 0
A68: 6 | B68: Общая сумма забалансовых активов | E68: =SUM(E50:E67) -> 1587605 | F68: =SUM(F50:F67) -> 0 | G68: =SUM(G50:G67) -> 0 | H68: =SUM(H50:H67) -> 770656071 | J68: =SUM(E68:H68) -> 772243676 | K68: =+[7]Commitments!$D$4+[7]Commitments!$D$7+[7]Commitments!$D$10+[7]Commitments!$D$19+[7]Commitments!$D$20+[7]Commitments!$D$21+[7]Commitments!$D$22 -> 772243676 | L68: =+J68-K68 -> 0
A69: 7 | B69: Общая сумма забалансовых активов, взвешенных с учетом риска | I69: =SUM(I50:I67) -> 1.771826e+08
A70: 8 | B70: Общая сумма активов, взвешенных с учетом риска | I70: =SUM(I69+I41) -> 1.8820872e+10 | J70: =+I70*0.15 -> 2.8231307e+09
B72: Подпись Председателя правления:
B74: Подпись Главного Бухгалтера:

Sheet Calculation of Risk Weighte ин
A1: РАСЧЕТ АКТИВОВ ВЗВЕШЕННЫХ С УЧЕТОМ РИСКА В ИНОСТРАННОЙ ВАЛЮТЕ | I1: Таблица-6.2
B2: =+'Bank Capital Calc'!B3 -> АТБ "Ўзсаноатқурилишбанк" | G2: =+'Bank Capital Calc'!C3 -> 44560 | I2: тыс. сум
A3: № | B3: Характеристики | C3: 0 | D3: 0.2 | E3: 0.35 | F3: 0.5 | G3: 1 | H3: 1.5 | I3: 2
C4: Риск | D4: Риск | E4: Риск | F4: Риск | G4: Риск | H4: Риск | I4: Риск
C5: I группа | D5: II группа | E5: III группа | F5: IV группа | G5: V группа | H5: VI группа | I5: VII группа
B6: (A) | C6: (Б) | D6: (В) | E6: (Г) | F6: (Д) | G6: (Е) | H6: (Ж) | I6: (З)
B7: Балансовые Активы
A8: 1. | B8: Касса (наличность и монеты) и Драгоценные металлы | C8: =+'Calculation of Risk Weighted As'!C8-'Calculation of Risk Weighte нац'!C8 -> 551827516
A9: 2. | B9: Денежная наличность и другие платежные документы в пути | D9: =+'Calculation of Risk Weighted As'!D9-'Calculation of Risk Weighte нац'!D9 -> 79307456
A10: 3. | B10: Корреспондентские и резервные счета в ЦБРУ | C10: =+'Calculation of Risk Weighted As'!C10-'Calculation of Risk Weighte нац'!C10 -> 0 | D10: =+'Calculation of Risk Weighted As'!D10-'Calculation of Risk Weighte нац'!D10 -> 776724634
A11: 4. | B11: Корреспондентские счета, кредиты и другие требования к банкам | D11: =+'Calculation of Risk Weighted As'!D11-'Calculation of Risk Weighte нац'!D11 -> 4160105268 | F11: =+'Calculation of Risk Weighted As'!F11-'Calculation of Risk Weighte нац'!F11 -> 192370812 | G11: =+'Calculation of Risk Weighted As'!G11-'Calculation of Risk Weighte нац'!G11 -> 820890879 | H11: =+'Calculation of Risk Weighted As'!H11-'Calculation of Risk Weighte нац'!H11 -> 20077603
A12: 5. | B12: Ценные бумаги, чистые
A13: а) | B13: Ценные бумаги, выпущенные Правительством Республики Узбекистан и ЦБРУ | C13: =+'Calculation of Risk Weighted As'!C13-'Calculation of Risk Weighte нац'!C13 -> -1
A14: б) | B14: Ценные бумаги, выпущенные правительствами и центральными банками зарубежных стран, а также другие требования к центральным банкам и правительствам этих стран | C14: =+'Calculation of Risk Weighted As'!C14-'Calculation of Risk Weighte нац'!C14 -> 0 | D14: =+'Calculation of Risk Weighted As'!D14-'Calculation of Risk Weighte нац'!D14 -> 0 | F14: =+'Calculation of Risk Weighted As'!F14-'Calculation of Risk Weighte нац'!F14 -> 0 | G14: =+'Calculation of Risk Weighted As'!G14-'Calculation of Risk Weighte нац'!G14 -> 0 | H14: =+'Calculation of Risk Weighted As'!H14-'Calculation of Risk Weighte нац'!H14 -> 0
A15: в) | B15: Другие ценные бумаги, выпущенные на территории Республики Узбекистан | D15: =+'Calculation of Risk Weighted As'!D15-'Calculation of Risk Weighte нац'!D15 -> 0 | F15: =+'Calculation of Risk Weighted As'!F15-'Calculation of Risk Weighte нац'!F15 -> 0 | G15: =+'Calculation of Risk Weighted As'!G15-'Calculation of Risk Weighte нац'!G15 -> 0 | H15: =+'Calculation of Risk Weighted As'!H15-'Calculation of Risk Weighte нац'!H15 -> 0
A16: г) | B16: Другие ценные бумаги, выпущенные зарубежными странами | C16: =+'Calculation of Risk Weighted As'!C16-'Calculation of Risk Weighte нац'!C16 -> 0 | D16: =+'Calculation of Risk Weighted As'!D16-'Calculation of Risk Weighte нац'!D16 -> 0 | F16: =+'Calculation of Risk Weighted As'!F16-'Calculation of Risk Weighte нац'!F16 -> 0 | G16: =+'Calculation of Risk Weighted As'!G16-'Calculation of Risk Weighte нац'!G16 -> 0 | H16: =+'Calculation of Risk Weighted As'!H16-'Calculation of Risk Weighte нац'!H16 -> 0
A17: 6. | B17: Активы, не деноминированные в национальную валюту и превышающие сумму финансирования в национальной валюте | G17: =+'Calculation of Risk Weighted As'!G17-'Calculation of Risk Weighte нац'!G17 -> 0
A18: 7. | B18: Требования банка к государственным секторам зарубежных стран (кроме Правительств и Центральных банков) и зарубежным компаниям, а также активы, обеспеченные или гарантированные их ценными бумагами (кроме кредитов и ценных бумаг) | C18: =+'Calculation of Risk Weighted As'!C18-'Calculation of Risk Weighte нац'!C18 -> 0 | D18: =+'Calculation of Risk Weighted As'!D18-'Calculation of Risk Weighte нац'!D18 -> 0 | F18: =+'Calculation of Risk Weighted As'!F18-'Calculation of Risk Weighte нац'!F18 -> 0 | G18: =+'Calculation of Risk Weighted As'!G18-'Calculation of Risk Weighte нац'!G18 -> 0 | H18: =+'Calculation of Risk Weighted As'!H18-'Calculation of Risk Weighte нац'!H18 -> 0
A19: 8. | B19: Кредиты и лизинги, чистые
A20: а) | B20: Прямые требования к Правительству и Центральному банку Республики Узбекистан | C20: =+'Calculation of Risk Weighted As'!C20-'Calculation of Risk Weighte нац'!C20 -> 0
A21: б) | B21: Кредиты международным финансовым организациям; кредиты, обеспеченные ценными бумагами международных финансовых организаций или гарантированные ими | C21: =+'Calculation of Risk Weighted As'!C21-'Calculation of Risk Weighte нац'!C21 -> 0
A22: в) | B22: Кредиты или их части, обеспеченные депозитами | C22: =+'Calculation of Risk Weighted As'!C22-'Calculation of Risk Weighte нац'!C22 -> 928883721 | D22: =+'Calculation of Risk Weighted As'!D22-'Calculation of Risk Weighte нац'!D22 -> 1458817
A23: г) | B23: Кредиты/их части, обеспеченные ценными бумагами, оцененными по текущей рыночной стоимости и выпущенными или гарантированными Правительством, Центральным банком РУз, а также кредиты/их части, гарантированные Правительством, Центральным банком Руз | D23: =+'Calculation of Risk Weighted As'!D23-'Calculation of Risk Weighte нац'!D23 -> 6200135127
A24: д) | B24: Кредиты, по которым банк не имеет приоритетного права на залог | G24: =+'Calculation of Risk Weighted As'!G24-'Calculation of Risk Weighte нац'!G24 -> 0
A25: е) | B25: Кредиты, выданные населению на приобретения недвижимости и обеспеченные приобретаемым или строящимся домом (квартирой) | E25: =+'Calculation of Risk Weighted As'!E25-'Calculation of Risk Weighte нац'!E25 -> 0 | F25: =+'Calculation of Risk Weighted As'!F25-'Calculation of Risk Weighte нац'!F25 -> 0 | G25: =+'Calculation of Risk Weighted As'!G25-'Calculation of Risk Weighte нац'!G25 -> 0 | H25: =+'Calculation of Risk Weighted As'!H25-'Calculation of Risk Weighte нац'!H25 -> 0
A26: ж) | B26: Другие кредиты, выданные населению | G26: =+'Calculation of Risk Weighted As'!G26-'Calculation of Risk Weighte нац'!G26 -> 0 | H26: =+'Calculation of Risk Weighted As'!H26-'Calculation of Risk Weighte нац'!H26 -> 0 | I26: =+'Calculation of Risk Weighted As'!I26-'Calculation of Risk Weighte нац'!I26 -> 0
A27: з) | B27: Все другие кредиты и лизинги | G27: =+'Calculation of Risk Weighted As'!G27-'Calculation of Risk Weighte нац'!G27 -> 15322959308 | H27: =+'Calculation of Risk Weighted As'!H27-'Calculation of Risk Weighte нац'!H27 -> 1540836036 | I27: =+'Calculation of Risk Weighted As'!I27-'Calculation of Risk Weighte нац'!I27 -> 1351624294
A28: и) | B28: Кредиты и лизинги в судебном разбирательстве, просроченные, пересмотренные и в статусе «не наращивания», чистые | H28: =+'Calculation of Risk Weighted As'!H28-'Calculation of Risk Weighte нац'!H28 -> 1990425177 | I28: =+'Calculation of Risk Weighted As'!I28-'Calculation of Risk Weighte нац'!I28 -> 73404689
A29: 9. | B29: Основные средства и другое собственное имущество банка
A30: а | B30: Основные средства, используемые в банковской деятельности (минус амортизация) | G30: =+'Calculation of Risk Weighted As'!G30-'Calculation of Risk Weighte нац'!G30 -> 0
A31: б | B31: Другое банковское собственное имущество | G31: =+'Calculation of Risk Weighted As'!G31-'Calculation of Risk Weighte нац'!G31 -> 0
A32: в | B32: Недвижимое имущество принятое на баланс банка в целях полного или частичного погащения задолженности | H32: =+'Calculation of Risk Weighted As'!H32-'Calculation of Risk Weighte нац'!H32 -> 0
A33: г | B33: Недвижимое имущество банка, которым банк не пользуется более двух лет | H33: =+'Calculation of Risk Weighted As'!H33-'Calculation of Risk Weighte нац'!H33 -> 0
A34: 10. | B34: Все инвестиции в капитал неконсолидированных хозяйствующих субъектов, в том числе в долговые обязательства, которые образуют капитал хозяйствующих субъектов, инвестиции в капитал других банков, чистые | C34: =+'Calculation of Risk Weighted As'!C34-'Calculation of Risk Weighte нац'!C34 -> 2779599
A35: 11. | B35: Все другие инвестиции, чистые | G35: =+'Calculation of Risk Weighted As'!G35-'Calculation of Risk Weighte нац'!G35 -> 0
A36: 12. | B36: Нематериальные активы, чистые | C36: =+'Calculation of Risk Weighted As'!C36-'Calculation of Risk Weighte нац'!C36 -> 0 | G36: =+'Calculation of Risk Weighted As'!G36-'Calculation of Risk Weighte нац'!G36 -> 0
A37: 13. | B37: Другие активы в судебном разбирательстве, пересмотренные активы, а также не взысканные в установленном порядке | H37: =+'Calculation of Risk Weighted As'!H37-'Calculation of Risk Weighte нац'!H37 -> 0
A38: 14. | B38: Другие активы, чистые | C38: =+'Calculation of Risk Weighted As'!C38-'Calculation of Risk Weighte нац'!C38 -> 0 | D38: =+'Calculation of Risk Weighted As'!D38-'Calculation of Risk Weighte нац'!D38 -> 0 | F38: =+'Calculation of Risk Weighted As'!F38-'Calculation of Risk Weighte нац'!F38 -> 0 | G38: =+'Calculation of Risk Weighted As'!G38-'Calculation of Risk Weighte нац'!G38 -> 833265353 | H38: =+'Calculation of Risk Weighted As'!H38-'Calculation of Risk Weighte нац'!H38 -> 0
A39: 15. | B39: Общая сумма балансовых активов согласно инструкции | C39: =SUM(C8:C38) -> 1483490835 | D39: =SUM(D8:D38) -> 11217731302 | E39: =SUM(E8:E38) -> 0 | F39: =SUM(F8:F38) -> 192370812 | G39: =SUM(G8:G38) -> 16977115540 | H39: =SUM(H8:H38) -> 3551338816 | I39: =SUM(I8:I38) -> 1425028983 | J39: =SUM(C39:I39) -> 34847076288 | K39: =+[7]Balance!$E$45 -> 34847076288 | L39: =+J39-K39 -> 0
A40: 16. | B40: Общая сумма балансовых рисковых активов, по группам риска | D40: =D39*D3 -> 2.2435463e+09 | E40: =E39*E3 -> 0 | F40: =F39*F3 -> 96185406 | G40: =G39*G3 -> 16977115540 | H40: =H39*H3 -> 5327008224 | I40: =I39*I3 -> 2850057966
A41: 17. | B41: Общая сумма балансовых рисковых активов | I41: =SUM(D40:I40) -> 2.7493913e+10
A44: № | B44: Характеристики | D44: Фактор пересчета кредита | E44: 0 | F44: 0.2 | G44: 0.5 | H44: 1 | I44: Значение риска
E46: Риск | F46: Риск | G46: Риск | H46: Риск
B47: (A) | D47: (Б) | E47: (В) | F47: (Г) | G47: (Д) | H47: (Е) | I47: (Ж)
A48: Забалансовые Активы
A49: 1 | B49: Обязательства по выдаче кредита
A50: a | B50: Более одного года | D50: 0.5 | E50: =+'Calculation of Risk Weighted As'!E50-'Calculation of Risk Weighte нац'!E50 -> 0 | F50: =+'Calculation of Risk Weighted As'!F50-'Calculation of Risk Weighte нац'!F50 -> 0 | G50: =+'Calculation of Risk Weighted As'!G50-'Calculation of Risk Weighte нац'!G50 -> 0 | H50: =+'Calculation of Risk Weighted As'!H50-'Calculation of Risk Weighte нац'!H50 -> 0 | I50: =(F50*0.1)+(G50*0.25)+(H50*0.5) -> 0
A51: б | B51: Год и менее | D51: 0.2 | E51: =+'Calculation of Risk Weighted As'!E51-'Calculation of Risk Weighte нац'!E51 -> 0 | F51: =+'Calculation of Risk Weighted As'!F51-'Calculation of Risk Weighte нац'!F51 -> 297135410 | G51: =+'Calculation of Risk Weighted As'!G51-'Calculation of Risk Weighte нац'!G51 -> 0 | H51: =+'Calculation of Risk Weighted As'!H51-'Calculation of Risk Weighte нац'!H51 -> 0 | I51: =(F51*0.04)+(G51*0.1)+(H51*0.2) -> 11885416
A52: 2 | B52: Обязательства по приобретению ценных бумаг и других активов (включая активы, проданные в соответствии с соглашениями об обратном выкупе) | D52: 1 | E52: =+'Calculation of Risk Weighted As'!E52-'Calculation of Risk Weighte нац'!E52 -> 0 | F52: =+'Calculation of Risk Weighted As'!F52-'Calculation of Risk Weighte нац'!F52 -> 0 | G52: =+'Calculation of Risk Weighted As'!G52-'Calculation of Risk Weighte нац'!G52 -> 0 | H52: =+'Calculation of Risk Weighted As'!H52-'Calculation of Risk Weighte нац'!H52 -> 0 | I52: =(F52*0.2)+(G52*0.5)+(H52*1) -> 0
A53: 3 | B53: Гарантии и поручительства | D53: 1 | E53: =+'Calculation of Risk Weighted As'!E53-'Calculation of Risk Weighte нац'!E53 -> 0 | F53: =+'Calculation of Risk Weighted As'!F53-'Calculation of Risk Weighte нац'!F53 -> 0 | H53: =+'Calculation of Risk Weighted As'!H53-'Calculation of Risk Weighte нац'!H53 -> 1803811728 | I53: =(F53*0.2)+(G53*0.5)+(H53*1) -> 1803811728
A54: 4 | B54: Аккредитивы
A55: a | B55: Прямые кредитные заменители | D55: 1 | E55: =+'Calculation of Risk Weighted As'!E55-'Calculation of Risk Weighte нац'!E55 -> 0 | F55: =+'Calculation of Risk Weighted As'!F55-'Calculation of Risk Weighte нац'!F55 -> 0 | G55: =+'Calculation of Risk Weighted As'!G55-'Calculation of Risk Weighte нац'!G55 -> 0 | H55: =+'Calculation of Risk Weighted As'!H55-'Calculation of Risk Weighte нац'!H55 -> 0 | I55: =(F55*0.2)+(G55*0.5)+(H55*1) -> 0
A56: б | B56: Связанные со сделками | D56: 0.5 | E56: =+'Calculation of Risk Weighted As'!E56-'Calculation of Risk Weighte нац'!E56 -> 0 | F56: =+'Calculation of Risk Weighted As'!F56-'Calculation of Risk Weighte нац'!F56 -> 0 | G56: =+'Calculation of Risk Weighted As'!G56-'Calculation of Risk Weighte нац'!G56 -> 0 | H56: =+'Calculation of Risk Weighted As'!H56-'Calculation of Risk Weighte нац'!H56 -> 0 | I56: =(F56*0.1)+(G56*0.25)+(H56*0.5) -> 0
A57: в | B57: Связанные с торговлей (краткосрочные, самоликвидирующиеся, обеспеченные поставкой товара) | D57: 0.2 | E57: =+'Calculation of Risk Weighted As'!E57-'Calculation of Risk Weighte нац'!E57 -> 0 | F57: =+'Calculation of Risk Weighted As'!F57-'Calculation of Risk Weighte нац'!F57 -> 0 | G57: =+'Calculation of Risk Weighted As'!G57-'Calculation of Risk Weighte нац'!G57 -> 0 | H57: =+'Calculation of Risk Weighted As'!H57-'Calculation of Risk Weighte нац'!H57 -> 1644275155 | I57: =(F57*0.04)+(G57*0.1)+(H57*0.2) -> 328855031
A58: г | B58: Другие аккредитивы | D58: 1 | E58: =+'Calculation of Risk Weighted As'!E58-'Calculation of Risk Weighte нац'!E58 -> 0 | F58: =+'Calculation of Risk Weighted As'!F58-'Calculation of Risk Weighte нац'!F58 -> 0 | H58: =+'Calculation of Risk Weighted As'!H58-'Calculation of Risk Weighte нац'!H58 -> 0 | I58: =(F58*0.2)+(G58*0.5)+(H58*1) -> 0
A59: 5 | B59: Форврдные котракты, свопы, опционы и подобные обязательства
A60: a | B60: Контракты по процентной ставке
A61: а1 | B61: Со сроком погашения до одного года | D61: 0.005 | E61: =+'Calculation of Risk Weighted As'!E61-'Calculation of Risk Weighte нац'!E61 -> 0 | F61: =+'Calculation of Risk Weighted As'!F61-'Calculation of Risk Weighte нац'!F61 -> 0 | G61: =+'Calculation of Risk Weighted As'!G61-'Calculation of Risk Weighte нац'!G61 -> 0 | H61: =+'Calculation of Risk Weighted As'!H61-'Calculation of Risk Weighte нац'!H61 -> 0 | I61: =(F61*0.001)+(G61*0.0025)+(H61*0.005) -> 0
A62: а2 | B62: Со сроком погашения от одного года до двух лет | D62: 0.01 | E62: =+'Calculation of Risk Weighted As'!E62-'Calculation of Risk Weighte нац'!E62 -> 0 | F62: =+'Calculation of Risk Weighted As'!F62-'Calculation of Risk Weighte нац'!F62 -> 0 | G62: =+'Calculation of Risk Weighted As'!G62-'Calculation of Risk Weighte нац'!G62 -> 0 | H62: =+'Calculation of Risk Weighted As'!H62-'Calculation of Risk Weighte нац'!H62 -> 0 | I62: =(F62*0.002)+(G62*0.005)+(H62*0.01) -> 0
A63: а3 | B63: Со сроком погашения от двух до трех лет | D63: 0.02 | E63: =+'Calculation of Risk Weighted As'!E63-'Calculation of Risk Weighte нац'!E63 -> 0 | F63: =+'Calculation of Risk Weighted As'!F63-'Calculation of Risk Weighte нац'!F63 -> 0 | G63: =+'Calculation of Risk Weighted As'!G63-'Calculation of Risk Weighte нац'!G63 -> 0 | H63: =+'Calculation of Risk Weighted As'!H63-'Calculation of Risk Weighte нац'!H63 -> 0 | I63: =(F63*0.004)+(G63*0.01)+(H63*0.02) -> 0
A64: б | B64: Валютные контракты и золото
A65: б1 | B65: Со сроком погашения до одного года | D65: 0.02 | E65: =+'Calculation of Risk Weighted As'!E65-'Calculation of Risk Weighte нац'!E65 -> 0 | F65: =+'Calculation of Risk Weighted As'!F65-'Calculation of Risk Weighte нац'!F65 -> 0 | G65: =+'Calculation of Risk Weighted As'!G65-'Calculation of Risk Weighte нац'!G65 -> 0 | H65: =+'Calculation of Risk Weighted As'!H65-'Calculation of Risk Weighte нац'!H65 -> 326771 | I65: =(F65*0.004)+(G65*0.01)+(H65*0.02) -> 6535.42
A66: б2 | B66: Со сроком погашения от одного года до двух лет | D66: 0.05 | E66: =+'Calculation of Risk Weighted As'!E66-'Calculation of Risk Weighte нац'!E66 -> 0 | F66: =+'Calculation of Risk Weighted As'!F66-'Calculation of Risk Weighte нац'!F66 -> 0 | G66: =+'Calculation of Risk Weighted As'!G66-'Calculation of Risk Weighte нац'!G66 -> 0 | H66: =+'Calculation of Risk Weighted As'!H66-'Calculation of Risk Weighte нац'!H66 -> 0 | I66: =(F66*0.01)+(G66*0.025)+(H66*0.05) -> 0
A67: б3 | B67: Со сроком погашения от двух до трех лет | D67: 0.08 | E67: =+'Calculation of Risk Weighted As'!E67-'Calculation of Risk Weighte нац'!E67 -> 0 | F67: =+'Calculation of Risk Weighted As'!F67-'Calculation of Risk Weighte нац'!F67 -> 0 | G67: =+'Calculation of Risk Weighted As'!G67-'Calculation of Risk Weighte нац'!G67 -> 0 | H67: =+'Calculation of Risk Weighted As'!H67-'Calculation of Risk Weighte нац'!H67 -> 0 | I67: =(F67*0.016)+(G67*0.04)+(H67*0.08) -> 0
A68: 6 | B68: Общая сумма забалансовых активов | E68: =SUM(E50:E67) -> 0 | F68: =SUM(F50:F67) -> 297135410 | G68: =SUM(G50:G67) -> 0 | H68: =SUM(H50:H67) -> 3448413654 | J68: =+E68+F68+G68+H68 -> 3745549064 | K68: =+[7]Commitments!$E$4+[7]Commitments!$E$7+[7]Commitments!$E$10+[7]Commitments!$E$19+[7]Commitments!$E$20+[7]Commitments!$E$21+[7]Commitments!$E$22 -> 3745549064 | L68: =+J68-K68 -> 0
A69: 7 | B69: Общая сумма забалансовых активов, взвешенных с учетом риска | I69: =SUM(I50:I67) -> 2.1445587e+09
A70: 8 | B70: Общая сумма активов, взвешенных с учетом риска | I70: =SUM(I69+I41) -> 2.9638472e+10 | J70: =+I70*0.15 -> 4.4457708e+09
B72: Подпись Председателя правления:
B74: Подпись Главного Бухгалтера:

Sheet Calculation of Risk
A1: РАСЧЕТ ПО ОПЕРАЦИОННЫМ И РЫНОЧНЫМ РИСКАМ
B2: =IF(C3>0," "&TEXT(C3,"д ММММ, гггг"),"Число,Месяц,Год") -> 30 Декабрь, 2021 | C2: Таблица-6А
B3: =+'Bank Capital Calc'!B3 -> АТБ "Ўзсаноатқурилишбанк" | C3: =+'Bank Capital Calc'!C3 -> 44560
A4: № | B4: Наименование показателя | C4: в тыс. сум
A5: 1. | B5: =+"Валовый доход банка за "&(E$7-3)&" год" -> Валовый доход банка за 2018 год | C5: =+C6+C8-C7-C9 -> 1084453436
A6: а. | B6: процентные доходы | C6: 1506434727
A7: б. | B7: процентные расходы | C7: 858326973 | E7: =RIGHT(B2,4) -> 2021
A8: в. | B8: беспроцентные доходы | C8: 579890138
A9: г. | B9: беспроцентные расходы | C9: 143544456
A10: 2. | B10: =+"Валовый доход банка за "&(E$7-2)&" год" -> Валовый доход банка за 2019 год | C10: =+C11+C13-C12-C14 -> 2294837028
A11: а. | B11: процентные доходы | C11: 2516104196
A12: б. | B12: процентные расходы | C12: 1458728381
A13: в. | B13: беспроцентные доходы | C13: 1422129026
A14: г. | B14: беспроцентные расходы | C14: 184667813
A15: 3. | B15: =+"Валовый доход банка за "&(E$7-1)&" год" -> Валовый доход банка за 2020 год | C15: =+C16+C18-C17-C19 -> 3029467361
A16: а. | B16: процентные доходы | C16: 3646197554
A17: б. | B17: процентные расходы | C17: 2022130996
A18: в. | B18: беспроцентные доходы | C18: 1690672392
A19: г. | B19: беспроцентные расходы | C19: 285271589
A20: 4. | B20: Средний валовый доход банка (за последние три года) | C20: =(C5+C10+C15)/3 -> 2.1362526e+09
A21: 5. | B21: Сумма операционных рисков | C21: =+(100/C28)*C20*15% -> 2.4649069e+09
A23: 6. | B23: Счета валютной позиции (счет 17101 (сумавая часть)) | C23: 278271311
A24: 7. | B24: Продажа на условиях Своп и Форвард (счет 92709, 92732) | C24: 0
A25: 8. | B25: Покупка на условиях Своп и Форвард (счет 92716, 92736) | C25: 326771
A26: 9. | B26: Открытая валютная позиция, всего | C26: =ABS(C23+(C24-C25)) -> 277944540 | D26: =+C26*0.1 -> 27794454
A27: 10. | B27: Сумма рыночных рисков | C27: =+(100/C28)*(C26*10%) -> 2.1380349e+08
A28: 11. | B28: Действуюший минимальное требование к достаточности капитала | C28: 13
A30: Подпись Председателя правления:
A32: Подпись Главного Бухгалтера:
