Workbook
Name jop: #REF!
Name kol: #REF!
Name RISKTOTASS: SUM('[6]Calculation of Risk Weighted As'!$C$38:$F$38)
Name RISKTOTASS: SUM('[7]Calculation of Risk Weighted As'!$C$41:$G$41)
Name TwentyLargestData: #REF!
Name Е: #REF!

Sheet Asset quality
A1: ИНФОРМАЦИЯ О КАЧЕСТВЕ АКТИВОВ, ОЦЕНИВАЕМЫХ В ЦЕЛЯХ СОЗДАНИЯ РЕЗЕРВА НА ВОЗМОЖНЫЕ ПОТЕРИ | R1: Таблица-2 | U1: №3
B3: АКБ "Микрокредитбанк" | P3: 44196 | S3: тыс. сум
A4: № | B4: Состав активов* | C4: Остаток | D4: Категория качества | I4: Просроченная задолженность (брутто) | N4: Резерв на возможные потери
I5: итого | J5: до 30 дней | K5: от 31 до 90 дней | L5: от 91 до 180 дней | M5: свыше 180 дней | N5: фактически сформированный
N6: итого | O6: по категориям качества
D7: I | E7: II | F7: III | G7: IV | H7: V | O7: I | P7: II | Q7: III | R7: IV | S7: V
A8: А | B8: Б | C8: В | D8: Г | E8: Д | F8: Е | G8: Ж | H8: З | I8: И | J8: К | K8: Л | L8: М | M8: Н | N8: О | O8: П | P8: Р | Q8: С | R8: Т | S8: У
B9: ВСЕГО АКТИВОВ | C9: =SUM(C10:C60) -> 10282915665 | D9: =SUM(D10:D60) -> 8864423041 | E9: =SUM(E10:E60) -> 1540989857 | F9: =SUM(F10:F60) -> 34473291 | G9: =SUM(G10:G60) -> 35919024 | H9: =SUM(H10:H60) -> 16214626 | I9: =SUM(I10:I60) -> 165011663 | J9: =SUM(J10:J60) -> 58106162 | ... S9: =SUM(S10:S60) -> 16214626
A10: 1 | B10: Кассовая наличность и другие платежные документы | C10: =SUM(D10:H10)-N10+O10 -> 220312147 | D10: 220312147 | E10: 0 | F10: 0 | G10: 0 | H10: 0 | I10: =SUM(J10:M10) -> 0 | J10: 0 | K10: 0 | L10: 0 | M10: 0 | N10: =SUM(O10:S10) -> 0 | O10: 0 | P10: 0 | Q10: 0 | R10: 0 | S10: 0 | T10: 10100
A11: 2 | B11: К получению из ЦБРУ | C11: =SUM(D11:H11)-N11+O11 -> 380783393 | D11: 380783393 | E11: 0 | F11: 0 | G11: 0 | H11: 0 | I11: =SUM(J11:M11) -> 0 | J11: 0 | K11: 0 | L11: 0 | M11: 0 | N11: =SUM(O11:S11) -> 0 | O11: 0 | P11: 0 | Q11: 0 | R11: 0 | S11: 0 | T11: 10300
A12: 3 | B12: К получению из других банков | C12: =SUM(D12:H12)-N12+O12 -> 666431396 | D12: 667134940 | E12: 0 | F12: 0 | G12: 0 | H12: 0 | I12: =SUM(J12:M12) -> 0 | J12: 0 | K12: 0 | L12: 0 | M12: 0 | N12: =SUM(O12:S12) -> 703544 | O12: 0 | P12: 703544 | Q12: 0 | R12: 0 | S12: 0 | T12: 10500
A13: 4 | B13: Ценные бумаги для купли и продажи | C13: =SUM(D13:H13)-N13+O13 -> 202938240 | D13: 202938240 | E13: 0 | F13: 0 | G13: 0 | H13: 0 | I13: =SUM(J13:M13) -> 0 | J13: 0 | K13: 0 | L13: 0 | M13: 0 | N13: =SUM(O13:S13) -> 0 | O13: 0 | P13: 0 | Q13: 0 | R13: 0 | S13: 0 | T13: 10700
A14: 5 | B14: Инвестиции в ценные бумаги, имеющиеся в наличии для продажи | C14: =SUM(D14:H14)-N14+O14 -> 0 | D14: 0 | E14: 0 | F14: 0 | G14: 0 | H14: 0 | I14: =SUM(J14:M14) -> 0 | J14: 0 | K14: 0 | L14: 0 | M14: 0 | N14: =SUM(O14:S14) -> 0 | O14: 0 | P14: 0 | Q14: 0 | R14: 0 | S14: 0 | T14: 10800
A15: 6 | B15: Драгоценные металлы, камни и монеты для купли и продажи | C15: =SUM(D15:H15)-N15+O15 -> 175 | D15: 175 | E15: 0 | F15: 0 | G15: 0 | H15: 0 | I15: =SUM(J15:M15) -> 0 | J15: 0 | K15: 0 | L15: 0 | M15: 0 | N15: =SUM(O15:S15) -> 0 | O15: 0 | P15: 0 | Q15: 0 | R15: 0 | S15: 0 | T15: 10900
A16: 7 | B16: Купленные дебиторские задолженности - Факторинг | C16: =SUM(D16:H16)-N16+O16 -> 17769574 | D16: 18077238 | E16: 0 | F16: 0 | G16: 0 | H16: 0 | I16: =SUM(J16:M16) -> 992738 | J16: 302846 | K16: 189564 | L16: 500328 | M16: 0 | N16: =SUM(O16:S16) -> 307664 | O16: 0 | P16: 0 | Q16: 0 | R16: 307664 | S16: 0 | T16: 11100
A17: 8 | B17: Купленные векселя | C17: =SUM(D17:H17)-N17+O17 -> 0 | D17: 0 | E17: 0 | F17: 0 | G17: 0 | H17: 0 | I17: =SUM(J17:M17) -> 0 | J17: 0 | K17: 0 | L17: 0 | M17: 0 | N17: =SUM(O17:S17) -> 0 | O17: 0 | P17: 0 | Q17: 0 | R17: 0 | S17: 0 | T17: 11300
A18: 9 | B18: Обязательства клиентов по траттам под аккредитив и/или трастовые документы | C18: =SUM(D18:H18)-N18+O18 -> 0 | D18: 0 | E18: 0 | F18: 0 | G18: 0 | H18: 0 | I18: =SUM(J18:M18) -> 0 | J18: 0 | K18: 0 | L18: 0 | M18: 0 | N18: =SUM(O18:S18) -> 0 | O18: 0 | P18: 0 | Q18: 0 | R18: 0 | S18: 0 | T18: 11500
A19: 10 | B19: Обязательства лиентов по непогашенным акцептам банка | C19: =SUM(D19:H19)-N19+O19 -> 0 | D19: 0 | E19: 0 | F19: 0 | G19: 0 | H19: 0 | I19: =SUM(J19:M19) -> 0 | J19: 0 | K19: 0 | L19: 0 | M19: 0 | N19: =SUM(O19:S19) -> 0 | O19: 0 | P19: 0 | Q19: 0 | R19: 0 | S19: 0 | T19: 11700
A20: 11 | B20: Купленные по сделкам РЕПО ценные бумаги | C20: =SUM(D20:H20)-N20+O20 -> 0 | D20: 0 | E20: 0 | F20: 0 | G20: 0 | H20: 0 | I20: =SUM(J20:M20) -> 0 | J20: 0 | K20: 0 | L20: 0 | M20: 0 | N20: =SUM(O20:S20) -> 0 | O20: 0 | P20: 0 | Q20: 0 | R20: 0 | S20: 0 | T20: 11800
A21: 12 | B21: Краткосрочные кредиты, предоставленные ЦБРУ | C21: =SUM(D21:H21)-N21+O21 -> 0 | D21: 0 | E21: 0 | F21: 0 | G21: 0 | H21: 0 | I21: =SUM(J21:M21) -> 0 | J21: 0 | K21: 0 | L21: 0 | M21: 0 | N21: =SUM(O21:S21) -> 0 | O21: 0 | P21: 0 | Q21: 0 | R21: 0 | S21: 0 | T21: 11900
... A60: 51 | B60: Другие активы | C60: =SUM(D60:H60)-N60+O60 -> 73631502 | D60: 82457871 | E60: 0 | F60: 0 | G60: 0 | H60: 0 | I60: =SUM(J60:M60) -> 0 | J60: 0 | K60: 0 | L60: 0 | M60: 0 | N60: =SUM(O60:S60) -> 8826369 | O60: 0 | P60: 8826369 | Q60: 0 | R60: 0 | S60: 0 | T60: 19900
B62: ЗАБАЛАНСОВЫЕ СТАТЬИ | C62: =SUM(D62:H62) -> 126598793 | D62: =SUM(D63:D64) -> 126598793 | E62: =SUM(E63:E64) -> 0 | F62: =SUM(F63:F64) -> 0 | G62: =SUM(G63:G64) -> 0 | H62: =SUM(H63:H64) -> 0 | I62: =SUM(J62:M62) -> 0 | J62: =SUM(J63:J64) -> 0 | K62: =SUM(K63:K64) -> 0 | L62: =SUM(L63:L64) -> 0 | M62: =SUM(M63:M64) -> 0 | N62: =SUM(N63:N64) -> 0 | O62: =SUM(O63:O64) -> 0 | P62: =SUM(P63:P64) -> 0 | Q62: =SUM(Q63:Q64) -> 0 | ... S62: =SUM(S63:S64) -> 0
A63: 1 | B63: Аккредитивы | C63: =SUM(D63:H63)-N63+O63 -> 5891080 | D63: 5891080 | I63: =SUM(J63:M63) -> 0 | N63: =SUM(O63:S63) -> 0 | T63: 90908-90958
A64: 2 | B64: Гарантии и поручетельства | C64: =SUM(D64:H64)-N64+O64 -> 120707713 | D64: 120707713 | I64: =SUM(J64:M64) -> 0 | N64: =SUM(O64:S64) -> 0 | T64: 90993
B67: Подпись Председателя правления:
B69: Подпись Главного Бухгалтера:
B71: Состав активов банка формируется в соответсвии с Планом счетов
C72: =+[8]Balance!$C$45 -> 10282915665

Sheet Income 
B1: ОТЧЕТ О ФИНАНСОВЫХ РЕЗУЛЬТАТАХ | D1: Таблица-3
B3: =+'Asset quality'!B3 -> АКБ "Микрокредитбанк" | C3: =+'Asset quality'!P3 -> 44196 | E3: в тыс. сум
A4: № | B4: Категории | C4: Итого | D4: в национальной валюте | E4: в иностранной валюте (в экв. в сумах)
A5: 1. | B5: 1. ПРОЦЕНТНЫЕ ДОХОДЫ
A6: a. | B6: Процентные доходы по счетам в ЦБРУ | C6: =+D6+E6 -> 997178 | D6: 997178
A7: б. | B7: Процентные доходы по счетам в других банках | C7: =+D7+E7 -> 44869998 | D7: 44869998
A8: в. | B8: Процентные доходы по купленным векселям | C8: =+D8+E8 -> 0 | D8: 0
A9: г. | B9: Процентные доходы по инвестициям | C9: =+D9+E9 -> 439759 | D9: 439759
A10: д. | B10: Процентные доходы по счетам купли-продажи ценных бумаг | C10: =+D10+E10 -> 22827406 | D10: 22827406
A11: е. | B11: Процентные доходы по обязательствам клиентов | C11: =+D11+E11 -> 0 | D11: 0
A12: ж. | B12: Процентные доходы по обяз-вам клиентов по непогашенным акцептам этого банка | C12: =+D12+E12 -> 0 | D12: 0
A13: з. | B13: Процент, Дисконт (Скидки) и взносы по кредитным и лизинговым операциям | C13: =+D13+E13 -> 970220612 | D13: 970220612
A14: и. | B14: Процентные доходы по соглашениям о покупке ценных бумаг с обратным выкупом | C14: =+D14+E14 -> 0 | D14: 0
A15: к. | B15: Другие процентные доходы | C15: =+D15+E15 -> 361508054 | D15: 361508054
A16: л. | B16: Итого процентных доходов | C16: =SUM(C6:C15) -> 1400863007 | D16: =SUM(D6:D15) -> 1400863007 | E16: =SUM(E6:E15) -> 0 | G16: =+'Analysis of Interest'!C42 -> 1400863007
A18: 2. | B18: ПРОЦЕНТНЫЕ РАСХОДЫ
A19: а. | B19: Процентные расходы по депозитам до востребования | C19: =+D19+E19 -> 5884243 | D19: 5884243
A20: б. | B20: Процентные расходы по срочным депозитам | C20: =+D20+E20 -> 190404626 | D20: 190404626
A21: в. | B21: Процентные расходы по счетам к оплате в ЦБРУ | C21: =+D21+E21 -> 0 | D21: 0
A22: г. | B22: Процентные расходы по счетам к оплате в другие банки | C22: =+D22+E22 -> 113814181 | D22: 113814181
A23: д. | B23: Итого процентных расходов по депозитам | C23: =SUM(C19:C22) -> 310103050 | D23: =SUM(D19:D22) -> 310103050 | E23: =SUM(E19:E22) -> 0
A24: е. | B24: Процентные расходы по кредитам к оплате | C24: =+D24+E24 -> 199829463 | D24: 199829463
A25: ж. | B25: Процентные расходы по соглашениям о продаже ц/б с последующим выкупом | C25: =+D25+E25 -> 2222268 | D25: 2222268
A26: з. | B26: Другие процентные расходы | C26: =+D26+E26 -> 361849530 | D26: 361849530
A27: и. | B27: Итого процентных расходов по займам | C27: =SUM(C24:C26) -> 563901261 | D27: =SUM(D24:D26) -> 563901261 | E27: =SUM(E24:E26) -> 0
A28: л. | B28: Итого процентных расходов | C28: =C27+C23 -> 874004311 | D28: =D27+D23 -> 874004311 | E28: =E27+E23 -> 0 | G28: =+'Analysis of Interest'!C72 -> 874004311
A30: 3. | B30: ЧИСТЫЕ ПРОЦЕНТНЫЕ ДОХОДЫ ДО ОЦЕНКИ ВОЗМОЖНЫХ УБЫТКОВ ПО АКТИВАМ | C30: =C16-C28 -> 526858696 | D30: =D16-D28 -> 526858696 | E30: =E16-E28 -> 0
A31: а. | B31: Минус: Оценка возможных убытков по кредитам и лизингу | C31: =+D31+E31 -> 199222532 | D31: 199222532
A32: б. | B32: Минус: Оценка возможных убытков по в ценным бумагам | C32: =+D32+E32 -> 0 | D32: 0
A33: в. | B33: Минус: Оценка возможных убытков по инвестициям | C33: =+D33+E33 -> 0 | D33: 0
A34: г. | B34: Минус: Оценка возможных убытков по другим активам | C34: =+D34+E34 -> 1852889 | D34: 1852889
A35: д. | B35: Чистые процентные доходы после оценки возможных убытков по кредитам и лизингу | C35: =C30-C31-C32-C33-C34 -> 325783275 | D35: =D30-D31-D32-D33-D34 -> 325783275 | E35: =E30-E31-E32-E33-E34 -> 0
A37: 4. | B37: БЕСПРОЦЕНТНЫЕ ДОХОДЫ
A38: а. | B38: Доходы от комиссий и платы за услуги | C38: =+D38+E38 -> 96683089 | D38: 96683089
A39: б. | B39: Прибыль в иностранной валюте | C39: =+D39+E39 -> 114855708 | D39: 0 | E39: 114855708
A40: в. | B40: Прибыль от коммерческих операций | C40: =+D40+E40 -> 2182 | D40: 2182
A41: г. | B41: Прибыль и дивиденды от инвестиций | C41: =+D41+E41 -> 158968 | D41: 158968
A42: д. | B42: Другие беспроцентные доходы | C42: =+D42+E42 -> 111447456 | D42: 111447456
A43: е. | B43: Итого беспроцентных доходов | C43: =SUM(C38:C42) -> 323147403 | D43: =SUM(D38:D42) -> 208291695 | E43: =SUM(E38:E42) -> 114855708
A45: 5. | B45: БЕСПРОЦЕНТНЫЕ РАСХОДЫ
A46: а. | B46: Комиссионные расходы и расходы за услуги | C46: =+D46+E46 -> 27125840 | D46: 27125840
A47: б. | B47: Убытки в иностранной валюте | C47: =+D47+E47 -> 103552965 | D47: 0 | E47: 103552965
A48: в. | B48: Убытки по счетам купли-продажи | C48: =+D48+E48 -> 9168587 | D48: 9168587
A49: г. | B49: Убытки от инвестиций | C49: =+D49+E49 -> 0 | D49: 0
A50: д. | B50: Другие беспроцентные расходы | C50: =+D50+E50 -> 2466127 | D50: 2466127
A51: е. | B51: Итого беспроцентных расходов | C51: =SUM(C46:C50) -> 142313519 | D51: =SUM(D46:D50) -> 38760554 | E51: =SUM(E46:E50) -> 103552965
A53: 6. | B53: ЧИСТЫЙ ДОХОД ДО ОПЕРАЦИОННЫХ РАСХОДОВ | C53: =C35+C43-C51 -> 506617159 | D53: =D35+D43-D51 -> 495314416 | E53: =E35+E43-E51 -> 11302743
A55: 7. | B55: ОПЕРАЦИОННЫЕ РАСХОДЫ
A56: а. | B56: Заработная плата и другие расходы на сотрудников | C56: =+D56+E56 -> 259646712 | D56: 259646712
A57: а1) | B57: из них, выплаты основному руководящему персоналу | C57: =+D57+E57 -> 0 | D57: 0
A58: б. | B58: Аренда и содержание | C58: =+D58+E58 -> 39409598 | D58: 39409598
A59: в. | B59: Командировочные и транспортные расходы | C59: =+D59+E59 -> 4687544 | D59: 4687544
A60: г. | B60: Административные расходы | C60: =+D60+E60 -> 9991741 | D60: 9991741
A61: д. | B61: Репрезентация и благотворительность | C61: =+D61+E61 -> 8595488 | D61: 8595488
A62: е. | B62: Расходы на износ | C62: =+D62+E62 -> 29495582 | D62: 29495582
A63: ж. | B63: Страхование | C63: =+D63+E63 -> 12164535 | D63: 12164535
A64: з. | B64: Налоги | C64: =+D64+E64 -> 6959456 | D64: 6959456
A65: и. | B65: Штрафы и пеня | C65: =+D65+E65 -> 16500 | D65: 16500
A66: к. | B66: Другие операционные расходы | C66: =+D66+E66 -> 12129588 | D66: 12129588
A67: л. | B67: Итого операционных расходов | C67: =SUM(C56:C66)-C57 -> 383096744 | D67: =SUM(D56:D66)-D57 -> 383096744
A69: 8. | B69: ЧИСТАЯ ПРИБЫЛЬ ДО УПЛАТЫ НАЛОГОВ И ДРУГИХ ПОПРАВОК | C69: =C53-C67 -> 123520415 | D69: =D53-D67 -> 112217672 | E69: =+E53-(C67-D67) -> 11302743
A70: а. | B70: Оценка налога на прибыль | C70: =+D70 -> 23491557 | D70: 23491557
A72: 9. | B72: ДОХОД ДО ВВЕДЕНИЯ ПОПРАВОК | C72: =C69-C70 -> 100028858 | D72: =D69-D70 -> 88726115 | E72: =E69-E70 -> 11302743
A73: а. | B73: Непредвиденные доходы или убытки, чистые | C73: =+D73+E73 -> 0 | D73: 0
A74: б. | B74: Другие поправки к прибыли, чистые | C74: =+D74+E74 -> 0 | D74: 0
A76: 10. | B76: ЧИСТАЯ ПРИБЫЛЬ (УБЫТКИ) | C76: =C72+C73+C74 -> 100028858 | D76: =D72+D73+D74 -> 88726115 | E76: =E72+E73+E74 -> 11302743
B78: Подпись Председателя правления:
B80: Подпись Главного Бухгалтера:

Sheet Analysis of Interest
B1: АНАЛИЗ ПРОЦЕНТНЫХ ДОХОДОВ И РАСХОДОВ | C1: Таблица-4
B3: =+'Asset quality'!B3 -> АКБ "Микрокредитбанк" | C3: =+'Asset quality'!P3 -> 44196
A4: № | B4: Категория | C4: в тыс. сум
A5: 1 . | B5: ПРОЦЕНТНЫЕ ДОХОДЫ ПО КРЕДИТНЫМ И ЛИЗИНГОВЫМ ОПЕРАЦИЯМ
A6: a. | B6: Кредиты и лизинговые операции ЦБРУ | C6: 0
A7: б. | B7: Кредиты и лизинговые операции другим банкам | C7: 8033
A8: в. | B8: Кредиты и лизинговые операции Правительству | C8: 2091
A9: г. | B9: Кредиты и лизинговые операции физическим лицам | C9: 334380571
A10: д. | B10: Кредиты и лизинговые операции государственным предприятиям | C10: 8873283
A11: е. | B11: Кредиты и лизинговые операции совместным и иностранным предприятиям | C11: 30511822
A12: ж. | B12: Кредиты и лизинговые операции частным товариществам и корпорациям | C12: 550675830
A13: з. | B13: Другие кредиты и лизинговые операции | C13: 45768982
A14: и. | B14: ИТОГО ПРОЦЕНТНЫХ ДОХОДОВ ПО КРЕДИТНЫМ И ЛИЗИНГОВЫМ ОПЕРАЦИЯМ | C14: =SUM(C6:C13) -> 970220612
A16: 2. | B16: ПРОЦЕНТНЫЕ ДОХОДЫ ПО КОРРЕСПОНДЕНТСКИМ СЧЕТАМ
A17: a. | B17: К получению из ЦБРУ | C17: 997178
A18: б. | B18: К получению из других банков | C18: 44869998
B19: ИТОГО ПРОЦЕНТНЫХ ДОХОДОВ ПО КОРРЕСПОНДЕНТСКИМ СЧЕТАМ | C19: =SUM(C17:C18) -> 45867176
A21: 3. | B21: ПРОЦЕНТНЫЕ ДОХОДЫ ПО СЧЕТАМ КУПЛИ-ПРОДАЖИ Ц/Б
A22: a. | B22: Государственные казначейские ценные бумаги | C22: 22827406
A23: б. | B23: Облигации и ценные бумаги ЦБРУ | C23: 0
A24: в. | B24: Ценные бумаги государственных корпораций | C24: 0
A25: г. | B25: Еврооблигации | C25: 0
A26: д. | B26: Частные ценные бумаги | C26: 0
A27: е. | B27: Другие ценные бумаги | C27: 0
A28: ж. | B28: ИТОГО ПРОЦЕНТНЫХ ДОХОДОВ ПО СЧЕТАМ КУПЛИ-ПРОДАЖИ Ц/Б | C28: =SUM(C22:C27) -> 22827406
A30: 4. | B30: ПРОЦЕНТНЫЕ ДОХОДЫ ПО ИНВЕСТИЦИЯМ
A31: a. | B31: Государственные облигации | C31: 0
A32: б. | B32: Облигации и ценные бумаги ЦБРУ | C32: 0
A33: в. | B33: Частные облигации | C33: 0
A34: г. | B34: Еврооблигации | C34: 0
A35: д. | B35: Другие ценные бумаги | C35: 439759
A36: е. | B36: ИТОГО ПРОЦЕНТНЫХ ДОХОДОВ ПО ИНВЕСТИЦИЯМ | C36: =SUM(C31:C35) -> 439759
A38: 5. | B38: ДРУГИЕ ПРОЦЕНТНЫЕ ДОХОДЫ
A39: a. | B39: Процентные доходы по соглашениям о покупке ц/б c обратным выкупом | C39: 0
A40: б. | B40: Другие процентные доходы | C40: 361508054
A42: 6. | B42: ИТОГО ПРОЦЕНТНЫХ ДОХОДОВ | C42: =C14+C19+C28+C36+C39+C40 -> 1400863007
A44: 7. | B44: ПРОЦЕНТНЫЕ РАСХОДЫ ПО ДЕПОЗИТАМ
A45: A. | B45: Депозиты до востребования
A46: a. | B46: Правительство | C46: 40000
A47: б. | B47: Физические лица | C47: 100779
A48: в. | B48: Государственные предприятия | C48: 2647651
A49: г. | B49: Совместные и иностранные предприятия | C49: 0
A50: д. | B50: Частные товарищества и корпорации | C50: 0
A51: е. | B51: Другие депозиты | C51: 3095813
A52: ж. | B52: Итого процентных расходов по депозитам до востребования | C52: =SUM(C46:C51) -> 5884243
A54: Б. | B54: Срочные депозиты
A55: a. | B55: Правительство | C55: 72512486
A56: б. | B56: Физические лица | C56: 65450966
A57: в. | B57: Государственные предприятия | C57: 24628624
A58: г. | B58: Совместные и иностранные предприятия | C58: 843449
A59: д. | B59: Частные товарищества и корпорации | C59: 8295322
A60: е. | B60: Другие депозиты | C60: 18673777
A61: ж. | B61: Итого процентных расходов по срочным депозитам | C61: =SUM(C55:C60) -> 190404624
A63: В. | B63: ИТОГО ПРОЦЕНТНЫХ РАСХОДОВ ПО ДЕПОЗИТАМ | C63: =C52+C61 -> 196288867
A65: 8. | B65: ПРОЦЕНТНЫЕ РАСХОДЫ ПО ДРУГИМ ОБЯЗАТЕЛЬСТВАМ
A66: а. | B66: Процентные расходы по непогашенным акцептам | C66: 0
A67: б. | B67: Процентные расходы по кредитам к оплате | C67: 199829463
A68: в. | B68: Процентные расходы по соглашениям о продаже ц/б с последующим выкупом | C68: 2222268
A69: г. | B69: Другие процентные расходы | C69: 475663713
A70: д. | B70: ИТОГО ПРОЦЕНТНЫХ РАСХОДОВ ПО ДРУГИМ ОБЯЗАТЕЛЬСТВАМ | C70: =SUM(C66:C69) -> 677715444
A72: 9. | B72: ИТОГО ПРОЦЕНТНЫХ РАСХОДОВ | C72: =C63+C70 -> 874004311
B74: Подпись Председателя правления:
B76: Подпись Главного Бухгалтера:

Sheet Changes in Equity
B1: ИЗМЕНЕНИЯ В СОБСТВЕННОМ КАПИТАЛЕ | C1: Таблица-7
B3: =+'Asset quality'!B3 -> АКБ "Микрокредитбанк" | C3: =+'Asset quality'!P3 -> 44196
A4: № | B4: Категория | C4: в тыс. сум
A5: 1. | B5: Итого собственного капитала первоначально определенного за прошлый год | C5: 1625105476
A6: 2. | B6: Исправления в собственном капитале не показанные в отчете за прошлый год, чистые | C6: 0
A7: 3. | B7: Исправленный баланс на конец прошлого календарного года (сумма строк 1 и 2) | C7: =SUM(C5:C6) -> 1625105476
A8: 4. | B8: Чистый прибыль (убыток) по состоянию на дату от начала года | C8: =+'Income '!C76 -> 100028858 | D8: =+[8]Balance!$C$76 -> 100028858
A9: 5. | B9: Продажа, Обмен, Приобретение или выкуп акций, за текущий год (чистая выручка) | C9: 0
A10: 6. | B10: Изменения в оценочной стоимости прироста над первонач. стоимостью, за текущий год (чистые) | C10: 0
A11: 7. | B11: МИНУС: Денежные дивиденды объявленные по привилегированным акциям | C11: 0
A12: 8. | B12: МИНУС: Денежные дивиденды объявленные по обыкновенным акциям | C12: 0
A13: 9. | B13: Другие статьи влияющие на собственный капитал за текущий год (чистые) | C13: 13155198
A14: 10. | B14: Итого собственного капитала на конец текущего периода (сумма строк с 3 по 10) | C14: =C7+SUM(C8:C10)-SUM(C11:C12)+C13 -> 1738289532 | D14: =+[8]Balance!$C$77 -> 1738289532
B16: Подпись Председателя правления:
B18: Подпись Главного Бухгалтера:

Sheet Loans Receivable
A1: КРЕДИТЫ И ЛИЗИНГИ К ПОЛУЧЕНИЮ ПО ОТРАСЛЯМ ЭКОНОМИКИ, ТИПАМ КЛИЕНТОВ И ПО ТИПУ ОБЕСПЕЧЕНИЯ | W1: Таблица-8
B3: =+'Asset quality'!B3 -> АКБ "Микрокредитбанк" | T3: =+'Asset quality'!P3 -> 44196 | X3: тыс. сум
A4: № | B4: Отрасль экономики | C4: Сумма кредита | D4: в национальной валюте | F4: в иностранной валюте (в экв. в сумах) | H4: из них | J4: из них
D5: Сумма | E5: средне-взвешенные процентные ставки | F5: Сумма | G5: средне-взвешенные процентные ставки | H5: Начисляемые кредиты | I5: Кредиты переведённые в статус ненаращивания процентов | J5: Депозиты | K5: Гарантированные Правительством Республики Узбекистан | L5: из них | M5: Транспортные средства | N5: Инвентарь | O5: Недвижимость | P5: из них | R5: Оборудование | S5: Векселя (облигации) | T5: Акции | U5: Гарантия третьей стороны | V5: Поручительства третьей стороны | W5: Страховой полис | X5: Необеспеченные | Y5: Другое обеспечение
L6: Гарантированные Правительством Республики Узбекистан в иностранной валюте (экв.сум) | P6: жилая недвижимость | Q6: коммерческая недвижимость
A7: Код | B7: (А) | C7: (Б) | D7: (Б1) | E7: (Б2) | F7: (Б3) | G7: (Б4) | H7: (В) | I7: (Г) | J7: (Д) | K7: (Е) | L7: (Е1) | M7: (Ж) | N7: (З) | O7: (И) | P7: (И1) | Q7: (И2) | R7: (К) | S7: (Л) | T7: (М) | U7: (Н) | V7: (О) | W7: (П) | X7: (Р) | Y7: (С)
B8: Промышленность
A9: 10 | B9: Физические лица | C9: =SUM(J9:Y9)-L9-P9-Q9 -> 211918805 | D9: 211918805 | E9: 0.12276754 | H9: 211918805 | J9: 0 | K9: 0 | L9: 0 | M9: 55167 | N9: 0 | O9: =+P9+Q9 -> 46537 | P9: 0 | Q9: 46537 | R9: 0 | S9: 0 | T9: 0 | U9: 0 | V9: 24421212 | W9: 187395889 | X9: 0 | Y9: 0
A10: =A9+10 -> 20 | B10: Государственные предприятия | C10: =SUM(J10:Y10)-L10-P10-Q10 -> 799470 | D10: 799470 | E10: 0.18317147 | H10: 799470 | I10: 0 | J10: 0 | K10: 0 | L10: 0 | M10: 0 | N10: 0 | O10: =+P10+Q10 -> 799470 | P10: 0 | Q10: 799470 | R10: 0 | S10: 0 | T10: 0 | U10: 0 | V10: 0 | W10: 0 | X10: 0 | Y10: 0
A11: =A10+10 -> 30 | B11: Совместные и иностранные предприятия | C11: =SUM(J11:Y11)-L11-P11-Q11 -> 116384043 | D11: 62870858 | E11: 0.19490422 | F11: 53513185 | G11: 0.11969436 | H11: 116384043 | I11: 0 | J11: 0 | K11: 0 | L11: 0 | M11: 3800684 | N11: 0 | O11: =+P11+Q11 -> 76278245 | P11: 0 | Q11: 76278245 | R11: 0 | S11: 0 | T11: 0 | U11: 0 | V11: 8852168 | W11: 27452946 | X11: 0 | Y11: 0
A12: =A11+10 -> 40 | B12: Частные товарищества и корпорации | C12: =SUM(J12:Y12)-L12-P12-Q12 -> 1908584088 | D12: 663743584 | E12: 0.15119777 | F12: 1244840504 | G12: 0.097011272 | H12: 1901887166 | I12: 6696922 | J12: 126667 | K12: 0 | L12: 0 | M12: 145201308 | N12: 0 | O12: =+P12+Q12 -> 1278159383 | P12: 0 | Q12: 1278159383 | R12: 13401538 | S12: 0 | T12: 0 | U12: 0 | V12: 142412896 | W12: 328990798 | X12: 0 | Y12: 291498
A13: =A12+10 -> 50 | B13: Правительство | C13: =SUM(J13:Y13)-L13-P13-Q13 -> 0 | O13: =+P13+Q13 -> 0
A14: =A13+10 -> 60 | B14: Прочие | C14: =SUM(J14:Y14)-L14-P14-Q14 -> 0 | O14: =+P14+Q14 -> 0
A15: =A14+10 -> 70 | B15: Итого по промышленности | C15: =SUM(J15:Y15)-L15-P15-Q15 -> 2237686406 | D15: =SUM(D9:D14) -> 939332717 | E15: =IFERROR(((D9*E9)/D15)+((D10*E10)/D15)+((D11*E11)/D15)+((D12*E12)/D15)+((D13*E13)/D15)+((D14*E14)/D15),0) -> 0.14773629 | F15: =SUM(F9:F14) -> 1298353689 | G15: =IFERROR(((F9*G9)/F15)+((F10*G10)/F15)+((F11*G11)/F15)+((F12*G12)/F15)+((F13*G13)/F15)+((F14*G14)/F15),0) -> 0.097946183 | H15: =SUM(H9:H14) -> 2230989484 | I15: =SUM(I9:I14) -> 6696922 | J15: =SUM(J9:J14) -> 126667 | K15: =SUM(K9:K14) -> 0 | L15: =SUM(L9:L14) -> 0 | M15: =SUM(M9:M14) -> 149057159 | N15: =SUM(N9:N14) -> 0 | O15: =SUM(O9:O14) -> 1355283635 | ... Y15: =SUM(Y9:Y14) -> 291498
B16: Сельское хозяйство
A17: =A15+10 -> 80 | B17: Физические лица | C17: =SUM(J17:Y17)-L17-P17-Q17 -> 1039851491 | D17: 1039851491 | E17: 0.11880396 | H17: 1039851491 | J17: 0 | K17: 0 | L17: 0 | M17: 941199 | N17: 0 | O17: =+P17+Q17 -> 251128 | P17: 0 | Q17: 251128 | R17: 0 | S17: 0 | T17: 0 | U17: 0 | V17: 115285355 | W17: 923341148 | X17: 0 | Y17: 32661
A18: =A17+10 -> 90 | B18: Государственные предприятия | C18: =SUM(J18:Y18)-L18-P18-Q18 -> 65047852 | D18: 65047852 | E18: 0.061996959 | H18: 65047852 | J18: 0 | K18: 0 | L18: 0 | M18: 72171 | N18: 0 | O18: =+P18+Q18 -> 556000 | P18: 0 | Q18: 556000 | R18: 0 | S18: 0 | T18: 0 | U18: 0 | V18: 64419681 | W18: 0 | X18: 0 | Y18: 0
A19: =A18+10 -> 100 | B19: Совместные и иностранные предприятия | C19: =SUM(J19:Y19)-L19-P19-Q19 -> 38351368 | D19: 35488486 | E19: 0.20300851 | F19: 2862882 | G19: 0.07 | H19: 38351368 | J19: 0 | K19: 0 | L19: 0 | M19: 210082 | N19: 0 | O19: =+P19+Q19 -> 37885958 | P19: 0 | Q19: 37885958 | R19: 0 | S19: 0 | T19: 0 | U19: 0 | V19: 255328 | W19: 0 | X19: 0 | Y19: 0
A20: =A19+10 -> 110 | B20: Частные товарищества и корпорации | C20: =SUM(J20:Y20)-L20-P20-Q20 -> 870395796 | D20: 547710613 | E20: 0.18156176 | F20: 322685183 | G20: 0.078188891 | H20: 808522910 | I20: 61872886 | J20: 0 | K20: 0 | L20: 0 | M20: 69718048 | N20: 0 | O20: =+P20+Q20 -> 710462133 | P20: 0 | Q20: 710462133 | R20: 3515348 | S20: 0 | T20: 0 | U20: 0 | V20: 15382151 | W20: 71318116 | X20: 0 | Y20: 0
A21: =A20+10 -> 120 | B21: Фермерское хозяйство | C21: =SUM(J21:Y21)-L21-P21-Q21 -> 153457167 | D21: 126122456 | E21: 0.18882059 | F21: 27334711 | G21: 0.062484242 | H21: 150414802 | I21: 3042365 | J21: 131000 | K21: 0 | L21: 0 | M21: 21241525 | N21: 0 | O21: =+P21+Q21 -> 128231217 | P21: 200000 | Q21: 128031217 | R21: 26285 | S21: 0 | T21: 0 | U21: 0 | V21: 2550294 | W21: 1214521 | X21: 62325 | Y21: 0
A22: =A21+10 -> 130 | B22: Правительство | C22: =SUM(J22:Y22)-L22-P22-Q22 -> 0 | O22: =+P22+Q22 -> 0
A23: =A22+10 -> 140 | B23: Прочие | C23: =SUM(J23:Y23)-L23-P23-Q23 -> 0 | O23: =+P23+Q23 -> 0
A24: =A23+10 -> 150 | B24: Итого по сельскому хозяйству | C24: =SUM(J24:Y24)-L24-P24-Q24 -> 2167103674 | D24: =SUM(D17:D23) -> 1814220898 | E24: =IFERROR(((D17*E17)/D24)+((D18*E18)/D24)+((D19*E19)/D24)+((D20*E20)/D24)+((D21*E21)/D24)+((D22*E22)/D24)+((D23*E23)/D24),0) -> 0.14222829 | F24: =SUM(F17:F23) -> 352882776 | G24: =IFERROR(((F17*G17)/F24)+((F18*G18)/F24)+((F19*G19)/F24)+((F20*G20)/F24)+((F21*G21)/F24)+((F22*G22)/F24)+((F23*G23)/F24),0) -> 0.076905955 | H24: =SUM(H17:H23) -> 2102188423 | I24: =SUM(I17:I23) -> 64915251 | J24: =SUM(J17:J23) -> 131000 | K24: =SUM(K17:K23) -> 0 | L24: =SUM(L17:L23) -> 0 | M24: =SUM(M17:M23) -> 92183025 | N24: =SUM(N17:N23) -> 0 | O24: =SUM(O17:O23) -> 877386436 | ... Y24: =SUM(Y17:Y23) -> 32661
B25: Транспорт и коммуникации
A26: =A24+10 -> 160 | B26: Физические лица | C26: =SUM(J26:Y26)-L26-P26-Q26 -> 169202559 | D26: 169202559 | E26: 0.27309122 | H26: 169202559 | J26: 0 | K26: 0 | L26: 0 | M26: 163337476 | N26: 0 | O26: =+P26+Q26 -> 0 | P26: 0 | Q26: 0 | R26: 0 | S26: 0 | T26: 0 | U26: 0 | V26: 4692 | W26: 5860391 | X26: 0 | Y26: 0
A27: =A26+10 -> 170 | B27: Государственные предприятия | C27: =SUM(J27:Y27)-L27-P27-Q27 -> 703537 | D27: 703537 | E27: 0.24318862 | H27: 703537 | J27: 0 | K27: 0 | L27: 0 | M27: 477801 | N27: 0 | O27: =+P27+Q27 -> 225736 | P27: 0 | Q27: 225736 | R27: 0 | S27: 0 | T27: 0 | U27: 0 | V27: 0 | W27: 0 | X27: 0 | Y27: 0
A28: =A27+10 -> 180 | B28: Совместные и иностранные предприятия | C28: =SUM(J28:Y28)-L28-P28-Q28 -> 57926044 | D28: 5541444 | E28: 0.25014936 | F28: 52384600 | G28: 0.09 | H28: 57926044 | J28: 0 | K28: 0 | L28: 0 | M28: 957280 | N28: 0 | O28: =+P28+Q28 -> 56953831 | P28: 0 | Q28: 56953831 | R28: 0 | S28: 0 | T28: 0 | U28: 0 | V28: 14933 | W28: 0 | X28: 0 | Y28: 0
A29: =A28+10 -> 190 | B29: Частные товарищества и корпорации | C29: =SUM(J29:Y29)-L29-P29-Q29 -> 307907993 | D29: 163638859 | E29: 0.2350322 | F29: 144269134 | G29: 0.11349141 | H29: 307612768 | I29: 295225 | J29: 1296105 | K29: 0 | L29: 0 | M29: 114210528 | N29: 0 | O29: =+P29+Q29 -> 184454517 | P29: 0 | Q29: 184454517 | R29: 0 | S29: 0 | T29: 0 | U29: 0 | V29: 2498073 | W29: 5448770 | X29: 0 | Y29: 0
A30: =A29+10 -> 200 | B30: Правительство | C30: =SUM(J30:Y30)-L30-P30-Q30 -> 0 | J30: 0 | K30: 0 | L30: 0 | M30: 0 | N30: 0 | O30: =+P30+Q30 -> 0 | P30: 0 | Q30: 0 | R30: 0 | S30: 0 | T30: 0 | U30: 0 | V30: 0 | W30: 0 | X30: 0 | Y30: 0
A31: =A30+10 -> 210 | B31: Прочие | C31: =SUM(J31:Y31)-L31-P31-Q31 -> 0 | J31: 0 | K31: 0 | L31: 0 | M31: 0 | N31: 0 | O31: =+P31+Q31 -> 0 | P31: 0 | Q31: 0 | R31: 0 | S31: 0 | T31: 0 | U31: 0 | V31: 0 | W31: 0 | X31: 0 | Y31: 0
A32: =A31+10 -> 220 | B32: Итого по транспорту и коммуникациям | C32: =SUM(J32:Y32)-L32-P32-Q32 -> 535740133 | D32: =SUM(D26:D31) -> 339086399 | E32: =IFERROR(((D26*E26)/D32)+((D27*E27)/D32)+((D28*E28)/D32)+((D29*E29)/D32)+((D30*E30)/D32)+((D31*E31)/D32),0) -> 0.25428744 | F32: =SUM(F26:F31) -> 196653734 | G32: =IFERROR(((F26*G26)/F32)+((F27*G27)/F32)+((F28*G28)/F32)+((F29*G29)/F32)+((F30*G30)/F32)+((F31*G31)/F32),0) -> 0.10723377 | H32: =SUM(H26:H31) -> 535444908 | I32: =SUM(I26:I31) -> 295225 | J32: =SUM(J26:J31) -> 1296105 | K32: =SUM(K26:K31) -> 0 | L32: =SUM(L26:L31) -> 0 | M32: =SUM(M26:M31) -> 278983085 | N32: =SUM(N26:N31) -> 0 | O32: =SUM(O26:O31) -> 241634084 | ... Y32: =SUM(Y26:Y31) -> 0
B33: Строительство
A34: =A32+10 -> 230 | B34: Физические лица | C34: =SUM(J34:Y34)-L34-P34-Q34 -> 146864 | D34: 146864 | E34: 0.15 | H34: 146864 | J34: 0 | K34: 0 | L34: 0 | M34: 0 | N34: 0 | O34: =+P34+Q34 -> 0 | P34: 0 | Q34: 0 | R34: 0 | S34: 0 | T34: 0 | U34: 0 | V34: 0 | W34: 146864 | X34: 0 | Y34: 0
A35: =A34+10 -> 240 | B35: Государственные предприятия | C35: =SUM(J35:Y35)-L35-P35-Q35 -> 455247 | D35: 455247 | E35: 0.28 | H35: 455247 | J35: 0 | K35: 0 | L35: 0 | M35: 0 | N35: 0 | O35: =+P35+Q35 -> 40432 | P35: 0 | Q35: 40432 | R35: 0 | S35: 0 | T35: 0 | U35: 0 | V35: 414815 | W35: 0 | X35: 0 | Y35: 0
A36: =A35+10 -> 250 | B36: Совместные и иностранные предприятия | C36: =SUM(J36:Y36)-L36-P36-Q36 -> 4108321 | D36: 4108321 | E36: 0.21080974 | H36: 4108321 | J36: 0 | K36: 0 | L36: 0 | M36: 0 | N36: 0 | O36: =+P36+Q36 -> 4108321 | P36: 0 | Q36: 4108321 | R36: 0 | S36: 0 | T36: 0 | U36: 0 | V36: 0 | W36: 0 | X36: 0 | Y36: 0
A37: =A36+10 -> 260 | B37: Частные товарищества и корпорации | C37: =SUM(J37:Y37)-L37-P37-Q37 -> 369639589 | D37: 350014939 | E37: 0.14704973 | F37: 19624650 | G37: 0.08 | H37: 357280620 | I37: 12358969 | J37: 0 | K37: 0 | L37: 0 | M37: 5581390 | N37: 0 | O37: =+P37+Q37 -> 352547603 | P37: 0 | Q37: 352547603 | R37: 1242236 | S37: 0 | T37: 0 | U37: 0 | V37: 6677214 | W37: 3591146 | X37: 0 | Y37: 0
A38: =A37+10 -> 270 | B38: Правительство | C38: =SUM(J38:Y38)-L38-P38-Q38 -> 0 | O38: =+P38+Q38 -> 0
A39: =A38+10 -> 280 | B39: Прочие | C39: =SUM(J39:Y39)-L39-P39-Q39 -> 0 | O39: =+P39+Q39 -> 0
A40: =A39+10 -> 290 | B40: Итого по строительству | C40: =SUM(J40:Y40)-L40-P40-Q40 -> 374350021 | D40: =SUM(D34:D39) -> 354725371 | E40: =IFERROR(((D34*E34)/D40)+((D35*E35)/D40)+((D36*E36)/D40)+((D37*E37)/D40)+((D38*E38)/D40)+((D39*E39)/D40),0) -> 0.14796003 | F40: =SUM(F34:F39) -> 19624650 | G40: =IFERROR(((F34*G34)/F40)+((F35*G35)/F40)+((F36*G36)/F40)+((F37*G37)/F40)+((F38*G38)/F40)+((F39*G39)/F40),0) -> 0.08 | H40: =SUM(H34:H39) -> 361991052 | I40: =SUM(I34:I39) -> 12358969 | J40: =SUM(J34:J39) -> 0 | K40: =SUM(K34:K39) -> 0 | L40: =SUM(L34:L39) -> 0 | M40: =SUM(M34:M39) -> 5581390 | N40: =SUM(N34:N39) -> 0 | O40: =SUM(O34:O39) -> 356696356 | ... Y40: =SUM(Y34:Y39) -> 0
B41: Торговля и общественное питание
A42: =A40+10 -> 300 | B42: Физические лица | C42: =SUM(J42:Y42)-L42-P42-Q42 -> 0 | O42: =+P42+Q42 -> 0
A43: =A42+10 -> 310 | B43: Государственные предприятия | C43: =SUM(J43:Y43)-L43-P43-Q43 -> 128440135 | D43: 23670935 | E43: 0.18339082 | F43: 104769200 | G43: 0.06 | H43: 128440135 | J43: 0 | K43: 0 | L43: 0 | M43: 80000 | N43: 0 | O43: =+P43+Q43 -> 11135379 | P43: 0 | Q43: 11135379 | R43: 9900000 | S43: 0 | T43: 0 | U43: 0 | V43: 2555556 | W43: 0 | X43: 0 | Y43: 104769200
A44: =A43+10 -> 320 | B44: Совместные и иностранные предприятия | C44: =SUM(J44:Y44)-L44-P44-Q44 -> 10641640 | D44: 10641640 | E44: 0.24302069 | H44: 10641640 | J44: 0 | K44: 0 | L44: 0 | M44: 0 | N44: 0 | O44: =+P44+Q44 -> 9916640 | P44: 0 | Q44: 9916640 | R44: 0 | S44: 0 | T44: 0 | U44: 0 | V44: 25000 | W44: 700000 | X44: 0 | Y44: 0
A45: =A44+10 -> 330 | B45: Частные товарищества и корпорации | C45: =SUM(J45:Y45)-L45-P45-Q45 -> 618678436 | D45: 442797117 | E45: 0.23188888 | F45: 175881319 | G45: 0.098798457 | H45: 604913652 | I45: 13764784 | J45: 231104 | K45: 0 | L45: 0 | M45: 51270584 | N45: 0 | O45: =+P45+Q45 -> 371697064 | P45: 0 | Q45: 371697064 | R45: 9548568 | S45: 0 | T45: 0 | U45: 0 | V45: 18231554 | W45: 158110880 | X45: 9365533 | Y45: 223149
A46: =A45+10 -> 340 | B46: Правительство | C46: =SUM(J46:Y46)-L46-P46-Q46 -> 0 | J46: 0 | K46: 0 | L46: 0 | M46: 0 | N46: 0 | O46: =+P46+Q46 -> 0 | P46: 0 | Q46: 0 | R46: 0 | S46: 0 | T46: 0 | U46: 0 | V46: 0 | W46: 0 | X46: 0 | Y46: 0
A47: =A46+10 -> 350 | B47: Прочие | C47: =SUM(J47:Y47)-L47-P47-Q47 -> 0 | J47: 0 | K47: 0 | L47: 0 | M47: 0 | N47: 0 | O47: =+P47+Q47 -> 0 | P47: 0 | Q47: 0 | R47: 0 | S47: 0 | T47: 0 | U47: 0 | V47: 0 | W47: 0 | X47: 0 | Y47: 0
A48: =A47+10 -> 360 | B48: Итого по торговле и общественному питанию | C48: =SUM(J48:Y48)-L48-P48-Q48 -> 757760211 | D48: =SUM(D42:D47) -> 477109692 | E48: =IFERROR(((D42*E42)/D48)+((D43*E43)/D48)+((D44*E44)/D48)+((D45*E45)/D48)+((D46*E46)/D48)+((D47*E47)/D48),0) -> 0.22973102 | F48: =SUM(F42:F47) -> 280650519 | G48: =IFERROR(((F42*G42)/F48)+((F43*G43)/F48)+((F44*G44)/F48)+((F45*G45)/F48)+((F46*G46)/F48)+((F47*G47)/F48),0) -> 0.084314666 | H48: =SUM(H42:H47) -> 743995427 | I48: =SUM(I42:I47) -> 13764784 | J48: =SUM(J42:J47) -> 231104 | K48: =SUM(K42:K47) -> 0 | L48: =SUM(L42:L47) -> 0 | M48: =SUM(M42:M47) -> 51350584 | N48: =SUM(N42:N47) -> 0 | O48: =SUM(O42:O47) -> 392749083 | ... Y48: =SUM(Y42:Y47) -> 104992349
B49: Материально-техническое снабжение и сбыт
A50: =A48+10 -> 370 | B50: Физические лица | C50: =SUM(J50:Y50)-L50-P50-Q50 -> 14476741 | D50: 14476741 | E50: 0.12276302 | H50: 14476741 | J50: 0 | K50: 0 | L50: 0 | M50: 0 | N50: 0 | O50: =+P50+Q50 -> 6393 | P50: 0 | Q50: 6393 | R50: 0 | S50: 0 | T50: 0 | U50: 0 | V50: 1750236 | W50: 12720112 | X50: 0 | Y50: 0
A51: =A50+10 -> 380 | B51: Государственные предприятия | C51: =SUM(J51:Y51)-L51-P51-Q51 -> 199400 | D51: 199400 | E51: 0.24 | H51: 199400 | J51: 0 | K51: 0 | L51: 0 | M51: 0 | N51: 0 | O51: =+P51+Q51 -> 199400 | P51: 0 | Q51: 199400 | R51: 0 | S51: 0 | T51: 0 | U51: 0 | V51: 0 | W51: 0 | X51: 0 | Y51: 0
A52: =A51+10 -> 390 | B52: Совместные и иностранные предприятия | C52: =SUM(J52:Y52)-L52-P52-Q52 -> 6406503 | D52: 6406503 | E52: 0.22987279 | H52: 6406503 | J52: 0 | K52: 0 | L52: 0 | M52: 234500 | N52: 0 | O52: =+P52+Q52 -> 5286299 | P52: 0 | Q52: 5286299 | R52: 0 | S52: 0 | T52: 0 | U52: 0 | V52: 695709 | W52: 189995 | X52: 0 | Y52: 0
A53: =A52+10 -> 400 | B53: Частные товарищества и корпорации | C53: =SUM(J53:Y53)-L53-P53-Q53 -> 1350798408 | D53: 583444156 | E53: 0.17656447 | F53: 767354252 | G53: 0.098074263 | H53: 1350798408 | J53: 0 | K53: 0 | L53: 0 | M53: 80183611 | N53: 0 | O53: =+P53+Q53 -> 758544347 | P53: 366667 | Q53: 758177680 | R53: 5238460 | S53: 0 | T53: 0 | U53: 0 | V53: 44542535 | W53: 462289455 | X53: 0 | Y53: 0
A54: =A53+10 -> 410 | B54: Правительство | C54: =SUM(J54:Y54)-L54-P54-Q54 -> 0 | H54: 0 | J54: 0 | K54: 0 | L54: 0 | M54: 0 | N54: 0 | O54: =+P54+Q54 -> 0 | P54: 0 | Q54: 0 | R54: 0 | S54: 0 | T54: 0 | U54: 0 | V54: 0 | W54: 0 | X54: 0 | Y54: 0
A55: =A54+10 -> 420 | B55: Прочие | C55: =SUM(J55:Y55)-L55-P55-Q55 -> 174977 | D55: 174977 | E55: 0.28 | H55: 174977 | J55: 0 | K55: 0 | L55: 0 | M55: 0 | N55: 0 | O55: =+P55+Q55 -> 174977 | P55: 0 | Q55: 174977 | R55: 0 | S55: 0 | T55: 0 | U55: 0 | V55: 0 | W55: 0 | X55: 0 | Y55: 0
A56: =A55+10 -> 430 | B56: Итого по материально-техническому снабжению и сбыту | C56: =SUM(J56:Y56)-L56-P56-Q56 -> 1372056029 | D56: =SUM(D50:D55) -> 604701777 | E56: =IFERROR(((D50*E50)/D56)+((D51*E51)/D56)+((D52*E52)/D56)+((D53*E53)/D56)+((D54*E54)/D56)+((D55*E55)/D56),0) -> 0.17589207 | F56: =SUM(F50:F55) -> 767354252 | G56: =IFERROR(((F50*G50)/F56)+((F51*G51)/F56)+((F52*G52)/F56)+((F53*G53)/F56)+((F54*G54)/F56)+((F55*G55)/F56),0) -> 0.098074263 | H56: =SUM(H50:H55) -> 1372056029 | I56: =SUM(I50:I55) -> 0 | J56: =SUM(J50:J55) -> 0 | K56: =SUM(K50:K55) -> 0 | L56: =SUM(L50:L55) -> 0 | M56: =SUM(M50:M55) -> 80418111 | N56: =SUM(N50:N55) -> 0 | O56: =SUM(O50:O55) -> 764211416 | ... Y56: =SUM(Y50:Y55) -> 0
B57: Жилищно-коммунальные услуги
A58: =A56+10 -> 440 | B58: Физические лица | C58: =SUM(J58:Y58)-L58-P58-Q58 -> 0 | O58: =+P58+Q58 -> 0
A59: =A58+10 -> 450 | B59: Государственные предприятия | C59: =SUM(J59:Y59)-L59-P59-Q59 -> 9685529 | D59: 9685529 | E59: 0.1342813 | H59: 4647326 | I59: 5038203 | J59: 0 | K59: 0 | L59: 0 | M59: 0 | N59: 0 | O59: =+P59+Q59 -> 0 | P59: 0 | Q59: 0 | R59: 0 | S59: 0 | T59: 0 | U59: 0 | V59: 2179410 | W59: 7506119 | X59: 0 | Y59: 0
A60: =A59+10 -> 460 | B60: Совместные и иностранные предприятия | C60: =SUM(J60:Y60)-L60-P60-Q60 -> 0 | J60: 0 | K60: 0 | L60: 0 | M60: 0 | N60: 0 | O60: =+P60+Q60 -> 0 | P60: 0 | Q60: 0 | R60: 0 | S60: 0 | T60: 0 | U60: 0 | V60: 0 | W60: 0 | X60: 0 | Y60: 0
A61: =A60+10 -> 470 | B61: Частные товарищества и корпорации | C61: =SUM(J61:Y61)-L61-P61-Q61 -> 56850431 | D61: 56850431 | E61: 0.14139662 | H61: 9832051 | I61: 47018380 | J61: 0 | K61: 0 | L61: 0 | M61: 0 | N61: 0 | O61: =+P61+Q61 -> 0 | P61: 0 | Q61: 0 | R61: 0 | S61: 0 | T61: 0 | U61: 0 | V61: 21014548 | W61: 35835883 | X61: 0 | Y61: 0
A62: =A61+10 -> 480 | B62: Правительство | C62: =SUM(J62:Y62)-L62-P62-Q62 -> 0 | J62: 0 | K62: 0 | L62: 0 | M62: 0 | N62: 0 | O62: =+P62+Q62 -> 0 | P62: 0 | Q62: 0 | R62: 0 | S62: 0 | T62: 0 | U62: 0 | V62: 0 | W62: 0 | X62: 0 | Y62: 0
A63: 485 | B63: Негосударственные некоммерческие организации | C63: =SUM(J63:Y63)-L63-P63-Q63 -> 41090705 | D63: 41090705 | E63: 0.1415554 | H63: 4133349 | I63: 36957356 | J63: 0 | K63: 0 | L63: 0 | M63: 393662 | N63: 0 | O63: =+P63+Q63 -> 0 | P63: 0 | Q63: 0 | R63: 0 | S63: 0 | T63: 0 | U63: 0 | V63: 11952470 | W63: 28744573 | X63: 0 | Y63: 0
A64: =A62+10 -> 490 | B64: Прочие | C64: =SUM(J64:Y64)-L64-P64-Q64 -> 0 | O64: =+P64+Q64 -> 0
A65: =A64+10 -> 500 | B65: Итого по жилищно-коммунальным услугам | C65: =SUM(J65:Y65)-L65-P65-Q65 -> 107626665 | D65: =SUM(D58:D64) -> 107626665 | E65: =IFERROR(((D58*E58)/D65)+((D59*E59)/D65)+((D60*E60)/D65)+((D61*E61)/D65)+((D62*E62)/D65)+((D63*E63)/D65)+((D64*E64)/D65),0) -> 0.14081692 | F65: =SUM(F58:F64) -> 0 | G65: =IFERROR(((F58*G58)/F65)+((F59*G59)/F65)+((F60*G60)/F65)+((F61*G61)/F65)+((F62*G62)/F65)+((F63*G63)/F65)+((F64*G64)/F65),0) -> 0 | H65: =SUM(H58:H64) -> 18612726 | I65: =SUM(I58:I64) -> 89013939 | J65: =SUM(J58:J64) -> 0 | K65: =SUM(K58:K64) -> 0 | L65: =SUM(L58:L64) -> 0 | M65: =SUM(M58:M64) -> 393662 | N65: =SUM(N58:N64) -> 0 | O65: =SUM(O58:O64) -> 0 | ... Y65: =SUM(Y58:Y64) -> 0
B66: Другие отрасли
A67: =A65+10 -> 510 | B67: Физические лица | C67: =SUM(J67:Y67)-L67-P67-Q67 -> 960214287 | D67: 960214287 | E67: 0.23442811 | H67: 948968119 | I67: 11246168 | J67: 76582 | K67: 0 | L67: 0 | M67: 7463813 | N67: 0 | O67: =+P67+Q67 -> 311029008 | P67: 310051101 | Q67: 977907 | R67: 0 | S67: 0 | T67: 0 | U67: 0 | V67: 612960101 | W67: 13847013 | X67: 14824213 | Y67: 13557
A68: =A67+10 -> 520 | B68: Государственные предприятия | C68: =SUM(J68:Y68)-L68-P68-Q68 -> 2502557 | D68: 2502557 | E68: 0.10006131 | H68: 2502557 | J68: 0 | K68: 0 | L68: 0 | M68: 0 | N68: 0 | O68: =+P68+Q68 -> 0 | P68: 0 | Q68: 0 | R68: 0 | S68: 0 | T68: 0 | U68: 0 | V68: 0 | W68: 2557 | X68: 0 | Y68: 2500000
A69: =A68+10 -> 530 | B69: Совместные и иностранные предприятия | C69: =SUM(J69:Y69)-L69-P69-Q69 -> 0 | J69: 0 | K69: 0 | L69: 0 | M69: 0 | N69: 0 | O69: =+P69+Q69 -> 0 | P69: 0 | Q69: 0 | R69: 0 | S69: 0 | T69: 0 | U69: 0 | V69: 0 | W69: 0 | X69: 0 | Y69: 0
A70: =A69+10 -> 540 | B70: Частные товарищества и корпорации | C70: =SUM(J70:Y70)-L70-P70-Q70 -> 24122487 | D70: 18348531 | E70: 0.071578241 | F70: 5773956 | G70: 0.09 | H70: 16621985 | I70: 7500502 | J70: 1759 | K70: 0 | L70: 0 | M70: 698032 | N70: 0 | O70: =+P70+Q70 -> 7505075 | P70: 0 | Q70: 7505075 | R70: 0 | S70: 0 | T70: 0 | U70: 0 | V70: 18442 | W70: 109825 | X70: 0 | Y70: 15789354
A71: =A70+10 -> 550 | B71: Центральный банк | C71: =SUM(J71:Y71)-L71-P71-Q71 -> 0 | J71: 0 | K71: 0 | L71: 0 | M71: 0 | N71: 0 | O71: =+P71+Q71 -> 0 | P71: 0 | Q71: 0 | R71: 0 | S71: 0 | T71: 0 | U71: 0 | V71: 0 | W71: 0 | X71: 0 | Y71: 0
A72: =A71+10 -> 560 | B72: Другие банки | C72: =SUM(J72:Y72)-L72-P72-Q72 -> 0 | J72: 0 | K72: 0 | L72: 0 | M72: 0 | N72: 0 | O72: =+P72+Q72 -> 0 | P72: 0 | Q72: 0 | R72: 0 | S72: 0 | T72: 0 | U72: 0 | V72: 0 | W72: 0 | X72: 0 | Y72: 0
A73: =A72+10 -> 570 | B73: Правительство | C73: =SUM(J73:Y73)-L73-P73-Q73 -> 0 | J73: 0 | K73: 0 | L73: 0 | M73: 0 | N73: 0 | O73: =+P73+Q73 -> 0 | P73: 0 | Q73: 0 | R73: 0 | S73: 0 | T73: 0 | U73: 0 | V73: 0 | W73: 0 | X73: 0 | Y73: 0
A74: =A73+10 -> 580 | B74: Небанковские финансовые институты | C74: =SUM(J74:Y74)-L74-P74-Q74 -> 0 | J74: 0 | K74: 0 | L74: 0 | M74: 0 | N74: 0 | O74: =+P74+Q74 -> 0 | P74: 0 | Q74: 0 | R74: 0 | S74: 0 | T74: 0 | U74: 0 | V74: 0 | W74: 0 | X74: 0 | Y74: 0
A75: =A74+10 -> 590 | B75: Негосударственные некоммерческие организации | C75: =SUM(J75:Y75)-L75-P75-Q75 -> 636086 | D75: 636086 | E75: 0.16355297 | H75: 460068 | I75: 176018 | J75: 0 | K75: 0 | L75: 0 | M75: 6341 | N75: 0 | O75: =+P75+Q75 -> 621544 | P75: 0 | Q75: 621544 | R75: 0 | S75: 0 | T75: 0 | U75: 0 | V75: 8201 | W75: 0 | X75: 0 | Y75: 0
A76: =A75+10 -> 600 | B76: Бюджетные организации | C76: =SUM(J76:Y76)-L76-P76-Q76 -> 0 | O76: =+P76+Q76 -> 0
A77: =A76+10 -> 610 | B77: Прочие | C77: =SUM(J77:Y77)-L77-P77-Q77 -> 0 | O77: =+P77+Q77 -> 0
A78: =A77+10 -> 620 | B78: Итого по другим отраслям | C78: =SUM(J78:Y78)-L78-P78-Q78 -> 987475417 | D78: =SUM(D67:D77) -> 981701461 | E78: =IFERROR(((D67*E67)/D78)+((D68*E68)/D78)+((D69*E69)/D78)+((D70*E70)/D78)+((D71*E71)/D78)+((D72*E72)/D78)+((D73*E73)/D78)+((D74*E74)/D78)+((D75*E75)/D78)+((D76*E76)/D78)+((D77*E77)/D78),0) -> 0.2309959 | F78: =SUM(F67:F77) -> 5773956 | G78: =IFERROR(((F67*G67)/F78)+((F68*G68)/F78)+((F69*G69)/F78)+((F70*G70)/F78)+((F71*G71)/F78)+((F72*G72)/F78)+((F73*G73)/F78)+((F74*G74)/F78)+((F75*G75)/F78)+((F76*G76)/F78)+((F77*G77)/F78),0) -> 0.09 | H78: =SUM(H67:H77) -> 968552729 | I78: =SUM(I67:I77) -> 18922688 | J78: =SUM(J67:J77) -> 78341 | K78: =SUM(K67:K77) -> 0 | L78: =SUM(L67:L77) -> 0 | M78: =SUM(M67:M77) -> 8168186 | N78: =SUM(N67:N77) -> 0 | O78: =SUM(O67:O77) -> 319155627 | ... Y78: =SUM(Y67:Y77) -> 18302911
B79: Кредитные и лизинговые операции
A80: =A78+10 -> 630 | B80: Физические лица | C80: =SUM(J80:Y80)-L80-P80-Q80 -> 2395810747 | D80: =D9+D17+D26+D34+D42+D50+D58+D67 -> 2395810747 | E80: =IFERROR(((D9*E9)/D80)+((D17*E17)/D80)+((D26*E26)/D80)+((D34*E34)/D80)+((D42*E42)/D80)+((D50*E50)/D80)+((D58*E58)/D80)+((D67*E67)/D80),0) -> 0.1764177 | F80: =F9+F17+F26+F34+F42+F50+F58+F67 -> 0 | G80: =IFERROR(((F9*G9)/F80)+((F17*G17)/F80)+((F26*G26)/F80)+((F34*G34)/F80)+((F42*G42)/F80)+((F50*G50)/F80)+((F58*G58)/F80)+((F67*G67)/F80),0) -> 0 | H80: =H9+H17+H26+H34+H42+H50+H58+H67 -> 2384564579 | I80: =I9+I17+I26+I34+I42+I50+I58+I67 -> 11246168 | J80: =J9+J17+J26+J34+J42+J50+J58+J67 -> 76582 | K80: =K9+K17+K26+K34+K42+K50+K58+K67 -> 0 | L80: =L9+L17+L26+L34+L42+L50+L58+L67 -> 0 | M80: =M9+M17+M26+M34+M42+M50+M58+M67 -> 171797655 | N80: =N9+N17+N26+N34+N42+N50+N58+N67 -> 0 | O80: =O9+O17+O26+O34+O42+O50+O58+O67 -> 311333066 | ... Y80: =Y9+Y17+Y26+Y34+Y42+Y50+Y58+Y67 -> 46218
A81: =A80+10 -> 640 | B81: Государственные предприятия | C81: =SUM(J81:Y81)-L81-P81-Q81 -> 207833727 | D81: =D10+D18+D27+D35+D43+D51+D59+D68 -> 103064527 | E81: =IFERROR(((D10*E10)/D81)+((D18*E18)/D81)+((D27*E27)/D81)+((D35*E35)/D81)+((D43*E43)/D81)+((D51*E51)/D81)+((D59*E59)/D81)+((D68*E68)/D81),0) -> 0.10107894 | F81: =F10+F18+F27+F35+F43+F51+F59+F68 -> 104769200 | G81: =IFERROR(((F10*G10)/F81)+((F18*G18)/F81)+((F27*G27)/F81)+((F35*G35)/F81)+((F43*G43)/F81)+((F51*G51)/F81)+((F59*G59)/F81)+((F68*G68)/F81),0) -> 0.06 | H81: =H10+H18+H27+H35+H43+H51+H59+H68 -> 202795524 | I81: =I10+I18+I27+I35+I43+I51+I59+I68 -> 5038203 | J81: =J10+J18+J27+J35+J43+J51+J59+J68 -> 0 | K81: =K10+K18+K27+K35+K43+K51+K59+K68 -> 0 | L81: =L10+L18+L27+L35+L43+L51+L59+L68 -> 0 | M81: =M10+M18+M27+M35+M43+M51+M59+M68 -> 629972 | N81: =N10+N18+N27+N35+N43+N51+N59+N68 -> 0 | O81: =O10+O18+O27+O35+O43+O51+O59+O68 -> 12956417 | ... Y81: =Y10+Y18+Y27+Y35+Y43+Y51+Y59+Y68 -> 107269200
A82: =A81+10 -> 650 | B82: Совместные и иностранные предприятия | C82: =SUM(J82:Y82)-L82-P82-Q82 -> 233817919 | D82: =D11+D19+D28+D36+D44+D52+D60+D69 -> 125057252 | E82: =IFERROR(((D11*E11)/D82)+((D19*E19)/D82)+((D28*E28)/D82)+((D36*E36)/D82)+((D44*E44)/D82)+((D52*E52)/D82)+((D60*E60)/D82)+((D69*E69)/D82),0) -> 0.20606036 | F82: =F11+F19+F28+F36+F44+F52+F60+F69 -> 108760667 | G82: =IFERROR(((F11*G11)/F82)+((F19*G19)/F82)+((F28*G28)/F82)+((F36*G36)/F82)+((F44*G44)/F82)+((F52*G52)/F82)+((F60*G60)/F82)+((F69*G69)/F82),0) -> 0.10408397 | H82: =H11+H19+H28+H36+H44+H52+H60+H69 -> 233817919 | I82: =I11+I19+I28+I36+I44+I52+I60+I69 -> 0 | J82: =J11+J19+J28+J36+J44+J52+J60+J69 -> 0 | K82: =K11+K19+K28+K36+K44+K52+K60+K69 -> 0 | L82: =L11+L19+L28+L36+L44+L52+L60+L69 -> 0 | M82: =M11+M19+M28+M36+M44+M52+M60+M69 -> 5202546 | N82: =N11+N19+N28+N36+N44+N52+N60+N69 -> 0 | O82: =O11+O19+O28+O36+O44+O52+O60+O69 -> 190429294 | ... Y82: =Y11+Y19+Y28+Y36+Y44+Y52+Y60+Y69 -> 0
A83: =A82+10 -> 660 | B83: Частные товарищества и корпорации | C83: =SUM(J83:Y83)-L83-P83-Q83 -> 5506977228 | D83: =D12+D20+D29+D37+D45+D53+D61+D70 -> 2826548230 | E83: =IFERROR(((D12*E12)/D83)+((D20*E20)/D83)+((D29*E29)/D83)+((D37*E37)/D83)+((D45*E45)/D83)+((D53*E53)/D83)+((D61*E61)/D83)+((D70*E70)/D83),0) -> 0.17858422 | F83: =F12+F20+F29+F37+F45+F53+F61+F70 -> 2680428998 | G83: =IFERROR(((F12*G12)/F83)+((F20*G20)/F83)+((F29*G29)/F83)+((F37*G37)/F83)+((F45*G45)/F83)+((F53*G53)/F83)+((F61*G61)/F83)+((F70*G70)/F83),0) -> 0.095914273 | H83: =H12+H20+H29+H37+H45+H53+H61+H70 -> 5357469560 | I83: =I12+I20+I29+I37+I45+I53+I61+I70 -> 149507668 | J83: =J12+J20+J29+J37+J45+J53+J61+J70 -> 1655635 | K83: =K12+K20+K29+K37+K45+K53+K61+K70 -> 0 | L83: =L12+L20+L29+L37+L45+L53+L61+L70 -> 0 | M83: =M12+M20+M29+M37+M45+M53+M61+M70 -> 466863501 | N83: =N12+N20+N29+N37+N45+N53+N61+N70 -> 0 | O83: =O12+O20+O29+O37+O45+O53+O61+O70 -> 3663370122 | ... Y83: =Y12+Y20+Y29+Y37+Y45+Y53+Y61+Y70 -> 16304001
A84: =A83+10 -> 670 | B84: Фермерское хозяйство | C84: =SUM(J84:Y84)-L84-P84-Q84 -> 153457167 | D84: =D21 -> 126122456 | E84: =IFERROR(E21,0) -> 0.18882059 | F84: =F21 -> 27334711 | G84: =IFERROR(G21,0) -> 0.062484242 | H84: =H21 -> 150414802 | I84: =I21 -> 3042365 | J84: =J21 -> 131000 | K84: =K21 -> 0 | L84: =L21 -> 0 | M84: =M21 -> 21241525 | N84: =N21 -> 0 | O84: =O21 -> 128231217 | ... Y84: =Y21 -> 0
A85: =A84+10 -> 680 | B85: Другие банки | C85: =SUM(J85:Y85)-L85-P85-Q85 -> 0 | D85: =D72 -> 0 | E85: =E72 -> 0 | F85: =F72 -> 0 | G85: =G72 -> 0 | H85: =H72 -> 0 | I85: =I72 -> 0 | J85: =J72 -> 0 | K85: =K72 -> 0 | ... Y85: =Y72 -> 0
A86: =A85+10 -> 690 | B86: Центральный банк | C86: =SUM(J86:Y86)-L86-P86-Q86 -> 0 | D86: =D71 -> 0 | E86: =E71 -> 0 | F86: =F71 -> 0 | G86: =G71 -> 0 | H86: =H71 -> 0 | I86: =I71 -> 0 | J86: =J71 -> 0 | K86: =K71 -> 0 | ... Y86: =Y71 -> 0
A87: =A86+10 -> 700 | B87: Правительство | C87: =SUM(J87:Y87)-L87-P87-Q87 -> 0 | D87: =D13+D22+D30+D38+D46+D54+D62+D73 -> 0 | E87: =IFERROR(((D13*E13)/D87)+((D22*E22)/D87)+((D30*E30)/D87)+((D38*E38)/D87)+((D46*E46)/D87)+((D54*E54)/D87)+((D62*E62)/D87)+((D73*E73)/D87),0) -> 0 | F87: =F13+F22+F30+F38+F46+F54+F62+F73 -> 0 | G87: =IFERROR(((F13*G13)/F87)+((F22*G22)/F87)+((F30*G30)/F87)+((F38*G38)/F87)+((F46*G46)/F87)+((F54*G54)/F87)+((F62*G62)/F87)+((F73*G73)/F87),0) -> 0 | H87: =H13+H22+H30+H38+H46+H54+H62+H73 -> 0 | I87: =I13+I22+I30+I38+I46+I54+I62+I73 -> 0 | J87: =J13+J22+J30+J38+J46+J54+J62+J73 -> 0 | K87: =K13+K22+K30+K38+K46+K54+K62+K73 -> 0 | L87: =L13+L22+L30+L38+L46+L54+L62+L73 -> 0 | M87: =M13+M22+M30+M38+M46+M54+M62+M73 -> 0 | N87: =N13+N22+N30+N38+N46+N54+N62+N73 -> 0 | O87: =O13+O22+O30+O38+O46+O54+O62+O73 -> 0 | ... Y87: =Y13+Y22+Y30+Y38+Y46+Y54+Y62+Y73 -> 0
A88: =A87+10 -> 710 | B88: Небанковские финансовые институты | C88: =SUM(J88:Y88)-L88-P88-Q88 -> 0 | D88: =D74 -> 0 | E88: =E74 -> 0 | F88: =F74 -> 0 | G88: =G74 -> 0 | H88: =H74 -> 0 | I88: =I74 -> 0 | J88: =J74 -> 0 | K88: =K74 -> 0 | ... Y88: =Y74 -> 0
A89: =A88+10 -> 720 | B89: Негосударственные некоммерческие организации | C89: =SUM(J89:Y89)-L89-P89-Q89 -> 41726791 | D89: =+D63+D75 -> 41726791 | E89: =IFERROR(((D75*E75)/D78)+((D63*E63)/D65),0) -> 0.054150303 | F89: =+F63+F75 -> 0 | G89: =IFERROR(((F75*G75)/F78)+((F63*G63)/F65),0) -> 0 | H89: =+H63+H75 -> 4593417 | I89: =+I63+I75 -> 37133374 | J89: =+J63+J75 -> 0 | K89: =+K63+K75 -> 0 | L89: =+L63+L75 -> 0 | M89: =+M63+M75 -> 400003 | N89: =+N63+N75 -> 0 | O89: =+O63+O75 -> 621544 | ... Y89: =+Y63+Y75 -> 0
A90: =A89+10 -> 730 | B90: Бюджетные организации | C90: =SUM(J90:Y90)-L90-P90-Q90 -> 0 | D90: =D76 -> 0 | E90: =E76 -> 0 | F90: =F76 -> 0 | G90: =G76 -> 0 | H90: =H76 -> 0 | I90: =I76 -> 0 | J90: =J76 -> 0 | K90: =K76 -> 0 | ... Y90: =Y76 -> 0
A91: =A90+10 -> 740 | B91: Прочие | C91: =SUM(J91:Y91)-L91-P91-Q91 -> 174977 | D91: =D14+D23+D31+D39+D47+D55+D64+D77 -> 174977 | E91: =IFERROR(((D14*E14)/D91)+((D23*E23)/D91)+((D31*E31)/D91)+((D39*E39)/D91)+((D47*E47)/D91)+((D55*E55)/D91)+((D64*E64)/D91)+((D77*E77)/D91),0) -> 0.28 | F91: =F14+F23+F31+F39+F47+F55+F64+F77 -> 0 | G91: =IFERROR(((F14*G14)/F91)+((F23*G23)/F91)+((F31*G31)/F91)+((F39*G39)/F91)+((F47*G47)/F91)+((F55*G55)/F91)+((F64*G64)/F91)+((F77*G77)/F91),0) -> 0 | H91: =H14+H23+H31+H39+H47+H55+H64+H77 -> 174977 | I91: =I14+I23+I31+I39+I47+I55+I64+I77 -> 0 | J91: =J14+J23+J31+J39+J47+J55+J64+J77 -> 0 | K91: =K14+K23+K31+K39+K47+K55+K64+K77 -> 0 | L91: =L14+L23+L31+L39+L47+L55+L64+L77 -> 0 | M91: =M14+M23+M31+M39+M47+M55+M64+M77 -> 0 | N91: =N14+N23+N31+N39+N47+N55+N64+N77 -> 0 | O91: =O14+O23+O31+O39+O47+O55+O64+O77 -> 174977 | ... Y91: =Y14+Y23+Y31+Y39+Y47+Y55+Y64+Y77 -> 0
A92: =A91+10 -> 750 | B92: Итого кредита и лизинга | C92: =SUM(J92:Y92)-L92-P92-Q92 -> 8539798556 | D92: =SUM(D80:D91) -> 5618504980 | E92: =IFERROR(((D80*E80)/D92)+((D81*E81)/D92)+((D82*E82)/D92)+((D83*E83)/D92)+((D84*E84)/D92)+((D85*E85)/D92)+((D86*E86)/D92)+((D87*E87)/D92)+((D88*E88)/D92)+((D89*E89)/D92)+((D90*E90)/D92)+((D91*E91)/D92),0) -> 0.17615902 | F92: =SUM(F80:F91) -> 2921293576 | G92: =IFERROR(((F80*G80)/F92)+((F81*G81)/F92)+((F82*G82)/F92)+((F83*G83)/F92)+((F84*G84)/F92)+((F85*G85)/F92)+((F86*G86)/F92)+((F87*G87)/F92)+((F88*G88)/F92)+((F89*G89)/F92)+((F90*G90)/F92)+((F91*G91)/F92),0) -> 0.094617598 | H92: =SUM(H80:H91) -> 8333830778 | I92: =SUM(I80:I91) -> 205967778 | J92: =SUM(J80:J91) -> 1863217 | K92: =SUM(K80:K91) -> 0 | L92: =SUM(L80:L91) -> 0 | M92: =SUM(M80:M91) -> 666135202 | N92: =SUM(N80:N91) -> 0 | O92: =SUM(O80:O91) -> 4307116637 | ... Y92: =SUM(Y80:Y91) -> 123619419
B95: Подпись Председателя правления:
B97: Подпись Главного Бухгалтера:
C99: =+[8]Balance!$C$24 -> 8539798556
C100: =+C92-C99 -> 0

Sheet Aging Analysis
A1: АНАЛИЗ ПРОСРОЧЕННЫХ КРЕДИТОВ И ФИНАНСОВОГО ЛИЗИНГА К ПОЛУЧЕНИЮ | X1: Таблица-9
B3: =+'Asset quality'!B3 -> АКБ "Микрокредитбанк" | T3: =+'Asset quality'!P3 -> 44196 | X3: тыс. сум
A4: № | B4: Характеристики | C4: Всего задолжность по кредитам | D4: % | E4: Реструктуризированные кредиты | F4: % | G4: В ходе судебного разбирательства | H4: % | I4: Просроченная задолжность | K4: % | L4: в том числе, анализ временной задолженности
L5: 1-30 дней | N5: 31-60 дней | P5: 61-90 дней | R5: 91-180 дней | T5: 181-365 дней | V5: 366-730 дней | X5: Свыше 2 лет
I6: основной долг | J6: процент | L6: основной долг | M6: процент | N6: основной долг | O6: процент | P6: основной долг | Q6: процент | R6: основной долг | S6: процент | T6: основной долг | U6: процент | V6: основной долг | W6: процент | X6: основной долг | Y6: процент
B7: (А) | C7: (Б) | D7: (В) | E7: (Г) | F7: (Д) | G7: (Е) | H7: (Ж) | I7: (З) | J7: (З1) | K7: (И) | L7: (К) | M7: (К1) | N7: (Л) | O7: (Л1) | P7: (М) | Q7: (М1) | R7: (Н) | S7: (Н1) | T7: (О) | U7: (О1) | V7: (П) | W7: (П1) | X7: (Р) | Y7: (Р1)
B8: По типу клиента
A9: 1 | B9: Центральный банк | C9: =+'Loans Receivable'!C86 -> 0 | D9: =IF(C$22=0,"",C9/C$22) -> 0 | E9: 0 | F9: =IF(E$22=0,"",E9/E$22) | G9: 0 | H9: =IF($G$22=0,"",G9/$G$22) -> 0 | I9: =+L9+N9+P9+R9+T9+V9+X9 -> 0 | J9: =+M9+O9+T9+S9+U9+W9+Y9 -> 0 | K9: =IF($Z$22=0,"",Z9/$Z$22) -> 0 | L9: 0 | M9: 0 | N9: 0 | O9: 0 | P9: 0 | Q9: 0 | R9: 0 | S9: 0 | T9: 0 | U9: 0 | V9: 0 | W9: 0 | X9: 0 | Y9: 0 | Z9: =+I9+J9 -> 0
A10: 2 | B10: Другие банки | C10: =+'Loans Receivable'!C85 -> 0 | D10: =IF(C$22=0,"",C10/C$22) -> 0 | E10: 0 | F10: =IF(E$22=0,"",E10/E$22) | G10: 0 | H10: =IF($G$22=0,"",G10/$G$22) -> 0 | I10: =+L10+N10+P10+R10+T10+V10+X10 -> 0 | J10: =+M10+O10+Q10+S10+U10+W10+Y10 -> 0 | K10: =IF($Z$22=0,"",Z10/$Z$22) -> 0 | L10: 0 | M10: 0 | N10: 0 | O10: 0 | P10: 0 | Q10: 0 | R10: 0 | S10: 0 | T10: 0 | U10: 0 | V10: 0 | W10: 0 | X10: 0 | Y10: 0 | Z10: =+I10+J10 -> 0
A11: 3 | B11: Правительство | C11: =+'Loans Receivable'!C87 -> 0 | D11: =IF(C$22=0,"",C11/C$22) -> 0 | E11: 0 | F11: =IF(E$22=0,"",E11/E$22) | G11: 0 | H11: =IF($G$22=0,"",G11/$G$22) -> 0 | I11: =+L11+N11+P11+R11+T11+V11+X11 -> 5751 | J11: =+M11+O11+Q11+S11+U11+W11+Y11 -> 1078 | K11: =IF($Z$22=0,"",Z11/$Z$22) -> 4.1384955e-05 | L11: 1989 | M11: 566 | N11: 1989 | O11: 512 | P11: 1773 | Q11: 0 | R11: 0 | S11: 0 | T11: 0 | U11: 0 | V11: 0 | W11: 0 | X11: 0 | Y11: 0 | Z11: =+I11+J11 -> 6829
A12: 4 | B12: Физические лица | C12: =+'Loans Receivable'!C80 -> 2395810747 | D12: =IF(C$22=0,"",C12/C$22) -> 0.28054652 | E12: 0 | F12: =IF(E$22=0,"",E12/E$22) | G12: 848725 | H12: =IF($G$22=0,"",G12/$G$22) -> 0.11999923 | I12: =+L12+N12+P12+R12+T12+V12+X12 -> 17658686 | J12: =+M12+O12+Q12+S12+U12+W12+Y12 -> 19250098 | K12: =IF($Z$22=0,"",Z12/$Z$22) -> 0.2236738 | L12: 8250480 | M12: 7195079 | N12: 5125149 | O12: 5018387 | P12: 2971331 | Q12: 3134135 | R12: 1172271 | S12: 3620387 | T12: 130480 | U12: 168414 | V12: 8975 | W12: 105425 | X12: 0 | Y12: 8271 | Z12: =+I12+J12 -> 36908784
A13: 5 | B13: Государственные предприятия | C13: =+'Loans Receivable'!C81 -> 207833727 | D13: =IF(C$22=0,"",C13/C$22) -> 0.024337076 | E13: 0 | F13: =IF(E$22=0,"",E13/E$22) | G13: 0 | H13: =IF($G$22=0,"",G13/$G$22) -> 0 | I13: =+L13+N13+P13+R13+T13+V13+X13 -> 529357 | J13: =+M13+O13+Q13+S13+U13+W13+Y13 -> 52478 | K13: =IF($Z$22=0,"",Z13/$Z$22) -> 0.0035260236 | L13: 108412 | M13: 34389 | N13: 74218 | O13: 1183 | P13: 56777 | Q13: 1223 | R13: 74758 | S13: 8045 | T13: 135242 | U13: 4417 | V13: 79950 | W13: 3221 | X13: 0 | Y13: 0 | Z13: =+I13+J13 -> 581835
A14: 6 | B14: Совместные и иностранные предприятия | C14: =+'Loans Receivable'!C82 -> 233817919 | D14: =IF(C$22=0,"",C14/C$22) -> 0.027379793 | E14: 0 | F14: =IF(E$22=0,"",E14/E$22) | G14: 0 | H14: =IF($G$22=0,"",G14/$G$22) -> 0 | I14: =+L14+N14+P14+R14+T14+V14+X14 -> 226577 | J14: =+M14+O14+Q14+S14+U14+W14+Y14 -> 1629798 | K14: =IF($Z$22=0,"",Z14/$Z$22) -> 0.011249963 | L14: 103212 | M14: 528880 | N14: 123365 | O14: 476468 | P14: 0 | Q14: 457688 | R14: 0 | S14: 166762 | T14: 0 | U14: 0 | V14: 0 | W14: 0 | X14: 0 | Y14: 0 | Z14: =+I14+J14 -> 1856375
A15: 7 | B15: Частные товарищества и корпорации | C15: =+'Loans Receivable'!C83 -> 5506977228 | D15: =IF(C$22=0,"",C15/C$22) -> 0.64486032 | E15: 0 | F15: =IF(E$22=0,"",E15/E$22) | G15: 3209962 | H15: =IF($G$22=0,"",G15/$G$22) -> 0.45384895 | I15: =+L15+N15+P15+R15+T15+V15+X15 -> 64207482 | J15: =+M15+O15+Q15+S15+U15+W15+Y15 -> 46997390 | K15: =IF($Z$22=0,"",Z15/$Z$22) -> 0.6739213 | L15: 16359917 | M15: 19010115 | N15: 22782498 | O15: 13854234 | P15: 16751608 | Q15: 7357666 | R15: 5355996 | S15: 5334510 | T15: 2362103 | U15: 1247993 | V15: 593006 | W15: 192872 | X15: 2354 | Y15: 0 | Z15: =+I15+J15 -> 111204872
A16: 8 | B16: Фермерское хозяйство | C16: =+'Loans Receivable'!C84 -> 153457167 | D16: =IF(C$22=0,"",C16/C$22) -> 0.017969647 | E16: 0 | F16: =IF(E$22=0,"",E16/E$22) | G16: 2815255 | H16: =IF($G$22=0,"",G16/$G$22) -> 0.39804226 | I16: =+L16+N16+P16+R16+T16+V16+X16 -> 1986760 | J16: =+M16+O16+Q16+S16+U16+W16+Y16 -> 2460150 | K16: =IF($Z$22=0,"",Z16/$Z$22) -> 0.026949065 | L16: 806880 | M16: 1305542 | N16: 547279 | O16: 795238 | P16: 472202 | Q16: 303177 | R16: 34592 | S16: 11855 | T16: 58065 | U16: 34913 | V16: 67742 | W16: 9425 | X16: 0 | Y16: 0 | Z16: =+I16+J16 -> 4446910
A17: 9 | B17: Небанковские финансовые институты | C17: =+'Loans Receivable'!C88 -> 0 | D17: =IF(C$22=0,"",C17/C$22) -> 0 | E17: 0 | F17: =IF(E$22=0,"",E17/E$22) | G17: 0 | H17: =IF($G$22=0,"",G17/$G$22) -> 0 | I17: =+L17+N17+P17+R17+T17+V17+X17 -> 0 | J17: =+M17+O17+Q17+S17+U17+W17+Y17 -> 0 | K17: =IF($Z$22=0,"",Z17/$Z$22) -> 0 | L17: 0 | M17: 0 | N17: 0 | O17: 0 | P17: 0 | Q17: 0 | R17: 0 | S17: 0 | T17: 0 | U17: 0 | V17: 0 | W17: 0 | X17: 0 | Y17: 0 | Z17: =+I17+J17 -> 0
A18: 10 | B18: Негосударственные некоммерческие организации | C18: =+'Loans Receivable'!C89 -> 41726791 | D18: =IF(C$22=0,"",C18/C$22) -> 0.0048861564 | F18: =IF(E$22=0,"",E18/E$22) | G18: 0 | H18: =IF($G$22=0,"",G18/$G$22) -> 0 | I18: =+L18+N18+P18+R18+T18+V18+X18 -> 1243160 | J18: =+M18+O18+Q18+S18+U18+W18+Y18 -> 134026 | K18: =IF($Z$22=0,"",Z18/$Z$22) -> 0.0083459921 | L18: 249862 | M18: 38052 | N18: 220533 | O18: 63579 | P18: 166501 | Q18: 30850 | R18: 118914 | S18: 1545 | T18: 183900 | U18: 0 | V18: 284241 | W18: 0 | X18: 19209 | Y18: 0 | Z18: =+I18+J18 -> 1377186
A19: 11 | B19: Бюджетные организации | C19: =+'Loans Receivable'!C90 -> 0 | D19: =IF(C$22=0,"",C19/C$22) -> 0 | E19: 0 | F19: =IF(E$22=0,"",E19/E$22) | G19: 0 | H19: =IF($G$22=0,"",G19/$G$22) -> 0 | I19: =+L19+N19+P19+R19+T19+V19+X19 -> 0 | J19: =+M19+O19+Q19+S19+U19+W19+Y19 -> 0 | K19: =IF($Z$22=0,"",Z19/$Z$22) -> 0 | L19: 0 | M19: 0 | N19: 0 | O19: 0 | P19: 0 | Q19: 0 | R19: 0 | S19: 0 | T19: 0 | U19: 0 | V19: 0 | W19: 0 | X19: 0 | Y19: 0 | Z19: =+I19+J19 -> 0
A20: 12 | B20: Прочие | C20: =+'Loans Receivable'!C91 -> 174977 | D20: =IF(C$22=0,"",C20/C$22) -> 2.0489593e-05 | E20: 0 | F20: =IF(E$22=0,"",E20/E$22) | G20: 198812 | H20: =IF($G$22=0,"",G20/$G$22) -> 0.02810956 | I20: =+L20+N20+P20+R20+T20+V20+X20 -> 5976709 | J20: =+M20+O20+Q20+S20+U20+W20+Y20 -> 2652159 | K20: =IF($Z$22=0,"",Z20/$Z$22) -> 0.052292475 | L20: 2903961 | M20: 1208828 | N20: 1679873 | O20: 857537 | P20: 848353 | Q20: 483721 | R20: 434038 | S20: 78463 | T20: 88854 | U20: 15337 | V20: 17912 | W20: 8273 | X20: 3718 | Y20: 0 | Z20: =+I20+J20 -> 8628868
Z21: =+I21+J21 -> 0
A22: 13 | B22: Итого кредита и лизинга | C22: =SUM(C9:C20) -> 8539798556 | D22: =IF(C$22=0,"",C22/C$22) -> 1 | E22: =SUM(E9:E20) -> 0 | F22: =IF(E$22=0,"",E22/E$22) | G22: =SUM(G9:G20) -> 7072754 | H22: =IF($G$22=0,"",G22/$G$22) -> 1 | I22: =SUM(I9:I20) -> 91834482 | J22: =SUM(J9:J20) -> 73177177 | K22: =IF($Z$22=0,"",Z22/$Z$22) -> 1 | L22: =SUM(L9:L20) -> 28784713 | M22: =SUM(M9:M20) -> 29321451 | N22: =SUM(N9:N20) -> 30554904 | O22: =SUM(O9:O20) -> 21067138 | P22: =SUM(P9:P20) -> 21268545 | Q22: =SUM(Q9:Q20) -> 11768460 | R22: =SUM(R9:R20) -> 7190569 | S22: =SUM(S9:S20) -> 9221567 | ... Y22: =SUM(Y9:Y20) -> 8271 | Z22: =+I22+J22 -> 165011659
Z23: =+I23+J23 -> 0
B24: По сектору экономики | F24: =IF(E$22=0,"",E24/E$22) | Z24: =+I24+J24 -> 0
A25: 14 | B25: Промышленность | C25: =+'Loans Receivable'!C15 -> 2237686406 | D25: =IF(C$34=0,"",C25/C$34) -> 0.26203035 | E25: 0 | F25: =IF($E$34=0,"",E25/$E$34) | G25: 1053977 | H25: =IF($G$34=0,"",G25/$G$34) -> 0.14901932 | I25: =+L25+N25+P25+R25+T25+V25+X25 -> 9870898 | J25: =+M25+O25+Q25+S25+U25+W25+Y25 -> 11856464 | K25: =IF($Z$34=0,"",Z25/$Z$34) -> 0.13167168 | L25: 3979407 | M25: 4581182 | N25: 2480363 | O25: 4247484 | P25: 1396318 | Q25: 2247797 | R25: 1039185 | S25: 217711 | T25: 611917 | U25: 430458 | V25: 359990 | W25: 131832 | X25: 3718 | Y25: 0 | Z25: =+I25+J25 -> 21727362
A26: 15 | B26: Сельское хозяйство | C26: =+'Loans Receivable'!C24 -> 2167103674 | D26: =IF(C$34=0,"",C26/C$34) -> 0.2537652 | E26: 0 | F26: =IF($E$34=0,"",E26/$E$34) | G26: 3161247 | H26: =IF($G$34=0,"",G26/$G$34) -> 0.44696125 | I26: =+L26+N26+P26+R26+T26+V26+X26 -> 27967422 | J26: =+M26+O26+Q26+S26+U26+W26+Y26 -> 17378250 | K26: =IF($Z$34=0,"",Z26/$Z$34) -> 0.27480284 | L26: 2919044 | M26: 7588627 | N26: 11990024 | O26: 3835362 | P26: 11016967 | Q26: 1932022 | R26: 1091666 | S26: 3937979 | T26: 830237 | U26: 73033 | V26: 119484 | W26: 11227 | X26: 0 | Y26: 0 | Z26: =+I26+J26 -> 45345672
A27: 16 | B27: Транспорт и коммуникации | C27: =+'Loans Receivable'!C32 -> 535740133 | D27: =IF(C$34=0,"",C27/C$34) -> 0.062734516 | E27: 0 | F27: =IF($E$34=0,"",E27/$E$34) | G27: 185225 | H27: =IF($G$34=0,"",G27/$G$34) -> 0.026188526 | I27: =+L27+N27+P27+R27+T27+V27+X27 -> 2514458 | J27: =+M27+O27+Q27+S27+U27+W27+Y27 -> 1447277 | K27: =IF($Z$34=0,"",Z27/$Z$34) -> 0.024008819 | L27: 736688 | M27: 704612 | N27: 543592 | O27: 522090 | P27: 400291 | Q27: 174123 | R27: 348218 | S27: 24859 | T27: 485669 | U27: 21593 | V27: 0 | W27: 0 | X27: 0 | Y27: 0 | Z27: =+I27+J27 -> 3961735
A28: 17 | B28: Строительство | C28: =+'Loans Receivable'!C40 -> 374350021 | D28: =IF(C$34=0,"",C28/C$34) -> 0.043835931 | E28: 0 | F28: =IF($E$34=0,"",E28/$E$34) | G28: 0 | H28: =IF($G$34=0,"",G28/$G$34) -> 0 | I28: =+L28+N28+P28+R28+T28+V28+X28 -> 5747912 | J28: =+M28+O28+Q28+S28+U28+W28+Y28 -> 6034074 | K28: =IF($Z$34=0,"",Z28/$Z$34) -> 0.071400931 | L28: 2294193 | M28: 2516824 | N28: 1487154 | O28: 1586669 | P28: 1005957 | Q28: 1271010 | R28: 936838 | S28: 52988 | T28: 23770 | U28: 584991 | V28: 0 | W28: 21592 | X28: 0 | Y28: 0 | Z28: =+I28+J28 -> 11781986
A29: 18 | B29: Торговля и общественное питание | C29: =+'Loans Receivable'!C48 -> 757760211 | D29: =IF(C$34=0,"",C29/C$34) -> 0.088732797 | E29: 0 | F29: =IF($E$34=0,"",E29/$E$34) | G29: 654374 | H29: =IF($G$34=0,"",G29/$G$34) -> 0.092520396 | I29: =+L29+N29+P29+R29+T29+V29+X29 -> 16889227 | J29: =+M29+O29+Q29+S29+U29+W29+Y29 -> 8884322 | K29: =IF($Z$34=0,"",Z29/$Z$34) -> 0.15619229 | L29: 6252572 | M29: 3389961 | N29: 5812791 | O29: 3393686 | P29: 2783827 | Q29: 1732023 | R29: 1451689 | S29: 283534 | T29: 321717 | U29: 47716 | V29: 266631 | W29: 37402 | X29: 0 | Y29: 0 | Z29: =+I29+J29 -> 25773549
A30: 19 | B30: Материально-техническое снабжение и сбыт | C30: =+'Loans Receivable'!C56 -> 1372056029 | D30: =IF(C$34=0,"",C30/C$34) -> 0.16066609 | E30: 0 | F30: =IF($E$34=0,"",E30/$E$34) | G30: 0 | H30: =IF($G$34=0,"",G30/$G$34) -> 0 | I30: =+L30+N30+P30+R30+T30+V30+X30 -> 2500 | J30: =+M30+O30+Q30+S30+U30+W30+Y30 -> 454150 | K30: =IF($Z$34=0,"",Z30/$Z$34) -> 0.0027673802 | L30: 2500 | M30: 6175 | N30: 0 | O30: 2553 | P30: 0 | Q30: 6896 | R30: 0 | S30: 438526 | T30: 0 | U30: 0 | V30: 0 | W30: 0 | X30: 0 | Y30: 0 | Z30: =+I30+J30 -> 456650
A31: 20 | B31: Жилищно-коммунальные услуги | C31: =+'Loans Receivable'!C65 -> 107626665 | D31: =IF(C$34=0,"",C31/C$34) -> 0.012602951 | E31: 0 | F31: =IF($E$34=0,"",E31/$E$34) | G31: 0 | H31: =IF($G$34=0,"",G31/$G$34) -> 0 | I31: =+L31+N31+P31+R31+T31+V31+X31 -> 59969 | J31: =+M31+O31+Q31+S31+U31+W31+Y31 -> 9308 | K31: =IF($Z$34=0,"",Z31/$Z$34) -> 0.00041983094 | L31: 26578 | M31: 2110 | N31: 11169 | O31: 3430 | P31: 8889 | Q31: 3705 | R31: 13333 | S31: 63 | T31: 0 | U31: 0 | V31: 0 | W31: 0 | X31: 0 | Y31: 0 | Z31: =+I31+J31 -> 69277
A32: 21 | B32: Другие сектора | C32: =+'Loans Receivable'!C78 -> 987475417 | D32: =IF(C$34=0,"",C32/C$34) -> 0.11563217 | E32: 0 | F32: =IF($E$34=0,"",E32/$E$34) | G32: 2017931 | H32: =IF($G$34=0,"",G32/$G$34) -> 0.2853105 | I32: =+L32+N32+P32+R32+T32+V32+X32 -> 28782096 | J32: =+M32+O32+Q32+S32+U32+W32+Y32 -> 27113332 | K32: =IF($Z$34=0,"",Z32/$Z$34) -> 0.33873623 | L32: 12573731 | M32: 10531960 | N32: 8229811 | O32: 7475864 | P32: 4656296 | Q32: 4400884 | R32: 2309640 | S32: 4265907 | T32: 685334 | U32: 313283 | V32: 305721 | W32: 117163 | X32: 21563 | Y32: 8271 | Z32: =+I32+J32 -> 55895428
Z33: =+I33+J33 -> 0
A34: 22 | B34: Итого кредита и лизинга | C34: =SUM(C25:C32) -> 8539798556 | D34: =IF(C$34=0,"",C34/C$34) -> 1 | E34: =SUM(E25:E32) -> 0 | F34: =IF($E$34=0,"",E34/$E$34) | G34: =SUM(G25:G32) -> 7072754 | H34: =IF($G$34=0,"",G34/$G$34) -> 1 | I34: =SUM(I25:I32) -> 91834482 | J34: =SUM(J25:J32) -> 73177177 | K34: =IF($Z$34=0,"",Z34/$Z$34) -> 1 | L34: =SUM(L25:L32) -> 28784713 | M34: =SUM(M25:M32) -> 29321451 | N34: =SUM(N25:N32) -> 30554904 | O34: =SUM(O25:O32) -> 21067138 | P34: =SUM(P25:P32) -> 21268545 | Q34: =SUM(Q25:Q32) -> 11768460 | R34: =SUM(R25:R32) -> 7190569 | S34: =SUM(S25:S32) -> 9221567 | ... Y34: =SUM(Y25:Y32) -> 8271 | Z34: =+I34+J34 -> 165011659
B37: Подпись Председателя правления:
B39: Подпись Главного Бухгалтера:

Sheet Asset Classification
A1: ОТЧЕТ О КЛАССИФИКАЦИИ АКТИВОВ ПО СТЕПЕНИ РИСКА | W1: Таблица-10
B2: =+'Asset quality'!B3 -> АКБ "Микрокредитбанк" | U2: =+'Asset quality'!P3 -> 44196 | Z2: тыс. сум
A3: № | B3: Статьи баланса | C3: Общая сумма | D3: из них, в иностранной валюте (в экв. в сумах) | E3: Стандартные | F3: из них, в иностранной валюте (в экв. в сумах) | G3: Общие резервы (1%) | H3: из них, в иностранной валюте (в экв. в сумах) | I3: Субстандартные | J3: из них, в иностранной валюте (в экв. в сумах) | K3: Специальные резервы (мин 10%) | L3: из них, в иностранной валюте (в экв. в сумах) | M3: Неудовлетворительные | N3: из них, в иностранной валюте (в экв. в сумах) | O3: Специальные резервы (мин 25%) | P3: из них, в иностранной валюте (в экв. в сумах) | Q3: Сомнительные | R3: из них, в иностранной валюте (в экв. в сумах) | S3: Специальные резервы (мин 50%) | T3: из них, в иностранной валюте (в экв. в сумах) | U3: Безнадежные | V3: из них, в иностранной валюте (в экв. в сумах) | W3: Специальные резервы (100%) | X3: из них, в иностранной валюте (в экв. в сумах) | Y3: Совокупная сумма специальных резервов | Z3: из них, в иностранной валюте (в экв. в сумах)
A4: (А) | B4: (Б) | C4: (В) | D4: (В1) | E4: (Г) | F4: (Г1) | G4: (Д) | H4: (Д1) | I4: (Е) | J4: (Е1) | K4: (Ж) | L4: (Ж1) | M4: (З) | N4: (З1) | O4: (И) | P4: (И1) | Q4: (К) | R4: (К1) | S4: (Л) | T4: (Л1) | U4: (М) | V4: (М1) | W4: (Н) | X4: (Н1) | Y4: О=Ж+И+Л+Н | Z4: (О1)=(Ж1)+(И1)+(Л1)+(Н1)
B5: По типу клиента
A6: 1 | B6: Центральный банк | C6: =E6+I6+M6+Q6+U6 -> 0 | D6: =F6+J6+N6+R6+V6 -> 0 | Y6: =+W6+S6+O6+K6 -> 0 | Z6: =+X6+T6+P6+L6 -> 0 | AA6: =+'Aging Analysis'!C9 -> 0
B7: из них необеспеченные | C7: =E7+I7+M7+Q7+U7 -> 0 | D7: =F7+J7+N7+R7+V7 -> 0 | Y7: =+W7+S7+O7+K7 -> 0 | Z7: =+X7+T7+P7+L7 -> 0 | AA7: =+AA6-C6 -> 0
A8: 2 | B8: Другие банки | C8: =E8+I8+M8+Q8+U8 -> 0 | D8: =F8+J8+N8+R8+V8 -> 0 | Y8: =+W8+S8+O8+K8 -> 0 | Z8: =+X8+T8+P8+L8 -> 0 | AA8: =+'Aging Analysis'!C10 -> 0
B9: из них необеспеченные | C9: =E9+I9+M9+Q9+U9 -> 0 | D9: =F9+J9+N9+R9+V9 -> 0 | Y9: =+W9+S9+O9+K9 -> 0 | Z9: =+X9+T9+P9+L9 -> 0 | AA9: =+AA8-C8 -> 0
A10: 3 | B10: Правительство | C10: =E10+I10+M10+Q10+U10 -> 0 | D10: =F10+J10+N10+R10+V10 -> 0 | Y10: =+W10+S10+O10+K10 -> 0 | Z10: =+X10+T10+P10+L10 -> 0 | AA10: =+'Aging Analysis'!C11 -> 0
B11: из них необеспеченные | C11: =E11+I11+M11+Q11+U11 -> 0 | D11: =F11+J11+N11+R11+V11 -> 0 | Y11: =+W11+S11+O11+K11 -> 0 | Z11: =+X11+T11+P11+L11 -> 0 | AA11: =+AA10-C10 -> 0
A12: 4 | B12: Физические лица | C12: =E12+I12+M12+Q12+U12 -> 2395810747 | D12: =F12+J12+N12+R12+V12 -> 0 | E12: 1988169241 | F12: 0 | G12: 0 | H12: 0 | I12: 377969015 | J12: 0 | K12: 37816072 | L12: 0 | M12: 22359606 | N12: 0 | O12: 5589901 | P12: 0 | Q12: 5061752 | R12: 0 | S12: 2530876 | T12: 0 | U12: 2251133 | V12: 0 | W12: 2251133 | X12: 0 | Y12: =+W12+S12+O12+K12 -> 48187982 | Z12: =+X12+T12+P12+L12 -> 0 | AA12: =+'Aging Analysis'!C12 -> 2395810747
B13: из них необеспеченные | C13: =E13+I13+M13+Q13+U13 -> 0 | D13: =F13+J13+N13+R13+V13 -> 0 | Y13: =+W13+S13+O13+K13 -> 0 | Z13: =+X13+T13+P13+L13 -> 0 | AA13: =+AA12-C12 -> 0
A14: 5 | B14: Государственные предприятия | C14: =E14+I14+M14+Q14+U14 -> 207833727 | D14: =F14+J14+N14+R14+V14 -> 0 | E14: 196933727 | F14: 0 | G14: 0 | H14: 0 | I14: 10900000 | J14: 0 | K14: 1090000 | L14: 0 | M14: 0 | N14: 0 | O14: 0 | P14: 0 | Q14: 0 | R14: 0 | S14: 0 | T14: 0 | U14: 0 | V14: 0 | W14: 0 | X14: 0 | Y14: =+W14+S14+O14+K14 -> 1090000 | Z14: =+X14+T14+P14+L14 -> 0 | AA14: =+'Aging Analysis'!C13 -> 207833727
B15: из них необеспеченные | C15: =E15+I15+M15+Q15+U15 -> 0 | D15: =F15+J15+N15+R15+V15 -> 0 | Y15: =+W15+S15+O15+K15 -> 0 | Z15: =+X15+T15+P15+L15 -> 0 | AA15: =+AA14-C14 -> 0
A16: 6 | B16: Совместные и иностранные предприятия | C16: =E16+I16+M16+Q16+U16 -> 233817919 | D16: =F16+J16+N16+R16+V16 -> 108760666 | E16: 149637525 | F16: 29919367 | G16: 0 | H16: 0 | I16: 84062247 | J16: 78841299 | K16: 8406225 | L16: 7884130 | M16: 0 | N16: 0 | O16: 0 | P16: 0 | Q16: 118147 | R16: 0 | S16: 59074 | T16: 0 | U16: 0 | V16: 0 | W16: 0 | X16: 0 | Y16: =+W16+S16+O16+K16 -> 8465299 | Z16: =+X16+T16+P16+L16 -> 7884130 | AA16: =+'Aging Analysis'!C14 -> 233817919
B17: из них необеспеченные | C17: =E17+I17+M17+Q17+U17 -> 0 | D17: =F17+J17+N17+R17+V17 -> 0 | Y17: =+W17+S17+O17+K17 -> 0 | Z17: =+X17+T17+P17+L17 -> 0 | AA17: =+AA16-C16 -> 0
A18: 7 | B18: Частные товарищества и корпорации | C18: =E18+I18+M18+Q18+U18 -> 5506977228 | D18: =F18+J18+N18+R18+V18 -> 2680428998 | E18: 4425383897 | F18: 2260308333 | G18: 0 | H18: 0 | I18: 1027438960 | J18: 420120665 | K18: 103169931 | L18: 41934742 | M18: 12110446 | N18: 0 | O18: 3027611 | P18: 0 | Q18: 30739125 | R18: 0 | S18: 15427063 | T18: 0 | U18: 11304800 | V18: 0 | W18: 11304800 | X18: 0 | Y18: =+W18+S18+O18+K18 -> 132929405 | Z18: =+X18+T18+P18+L18 -> 41934742 | AA18: =+'Aging Analysis'!C15 -> 5506977228
B19: из них необеспеченные | C19: =E19+I19+M19+Q19+U19 -> 0 | D19: =F19+J19+N19+R19+V19 -> 0 | Y19: =+W19+S19+O19+K19 -> 0 | Z19: =+X19+T19+P19+L19 -> 0 | AA19: =+AA18-C18 -> 0
A20: 8 | B20: Фермерское хозяйство | C20: =E20+I20+M20+Q20+U20 -> 153457167 | D20: =F20+J20+N20+R20+V20 -> 27334711 | E20: 110183801 | F20: 15021469 | G20: 0 | H20: 0 | I20: 40611434 | J20: 12313242 | K20: 4061143 | L20: 1231324 | M20: 3239 | N20: 0 | O20: 810 | P20: 0 | Q20: 0 | S20: 0 | T20: 0 | U20: 2658693 | V20: 0 | W20: 2658693 | X20: 0 | Y20: =+W20+S20+O20+K20 -> 6720646 | Z20: =+X20+T20+P20+L20 -> 1231324 | AA20: =+'Aging Analysis'!C16 -> 153457167
B21: из них необеспеченные | C21: =E21+I21+M21+Q21+U21 -> 0 | D21: =F21+J21+N21+R21+V21 -> 0 | Y21: =+W21+S21+O21+K21 -> 0 | Z21: =+X21+T21+P21+L21 -> 0 | AA21: =+AA20-C20 -> 0
A22: 9 | B22: Небанковские финансовые институты | C22: =E22+I22+M22+Q22+U22 -> 0 | D22: =F22+J22+N22+R22+V22 -> 0 | E22: 0 | F22: 0 | G22: 0 | H22: 0 | I22: 0 | J22: 0 | K22: 0 | L22: 0 | M22: 0 | N22: 0 | O22: 0 | P22: 0 | Q22: 0 | R22: 0 | S22: 0 | T22: 0 | U22: 0 | V22: 0 | W22: 0 | X22: 0 | Y22: =+W22+S22+O22+K22 -> 0 | Z22: =+X22+T22+P22+L22 -> 0 | AA22: =+'Aging Analysis'!C17 -> 0
B23: из них необеспеченные | C23: =E23+I23+M23+Q23+U23 -> 0 | D23: =F23+J23+N23+R23+V23 -> 0 | Y23: =+W23+S23+O23+K23 -> 0 | Z23: =+X23+T23+P23+L23 -> 0 | AA23: =+AA22-C22 -> 0
A24: 10 | B24: Негосударственные некоммерческие организации | C24: =E24+I24+M24+Q24+U24 -> 41726791 | D24: =F24+J24+N24+R24+V24 -> 0 | E24: 41718590 | F24: 0 | G24: 0 | H24: 0 | I24: 8201 | J24: 0 | K24: 820 | L24: 0 | M24: 0 | N24: 0 | O24: 0 | P24: 0 | Q24: 0 | R24: 0 | S24: 0 | T24: 0 | U24: 0 | V24: 0 | W24: 0 | X24: 0 | Y24: =+W24+S24+O24+K24 -> 820 | Z24: =+X24+T24+P24+L24 -> 0 | AA24: =+'Aging Analysis'!C18 -> 41726791
B25: из них необеспеченные | C25: =E25+I25+M25+Q25+U25 -> 0 | D25: =F25+J25+N25+R25+V25 -> 0 | Y25: =+W25+S25+O25+K25 -> 0 | Z25: =+X25+T25+P25+L25 -> 0 | AA25: =+AA24-C24 -> 0
A26: 11 | B26: Бюджетные организации | C26: =E26+I26+M26+Q26+U26 -> 0 | D26: =F26+J26+N26+R26+V26 -> 0 | E26: 0 | F26: 0 | G26: 0 | H26: 0 | I26: 0 | J26: 0 | K26: 0 | L26: 0 | M26: 0 | N26: 0 | O26: 0 | P26: 0 | Q26: 0 | R26: 0 | S26: 0 | T26: 0 | U26: 0 | V26: 0 | W26: 0 | X26: 0 | Y26: =+W26+S26+O26+K26 -> 0 | Z26: =+X26+T26+P26+L26 -> 0 | AA26: =+'Aging Analysis'!C19 -> 0
B27: из них необеспеченные | C27: =E27+I27+M27+Q27+U27 -> 0 | D27: =F27+J27+N27+R27+V27 -> 0 | Y27: =+W27+S27+O27+K27 -> 0 | Z27: =+X27+T27+P27+L27 -> 0 | AA27: =+AA26-C26 -> 0
A28: 12 | B28: Прочие | C28: =E28+I28+M28+Q28+U28 -> 174977 | D28: =F28+J28+N28+R28+V28 -> 0 | E28: 174977 | F28: 0 | G28: 0 | H28: 0 | I28: 0 | J28: 0 | K28: 0 | L28: 0 | M28: 0 | N28: 0 | O28: 0 | Q28: 0 | R28: 0 | S28: 0 | T28: 0 | U28: 0 | V28: 0 | W28: 0 | X28: 0 | Y28: =+W28+S28+O28+K28 -> 0 | Z28: =+X28+T28+P28+L28 -> 0 | AA28: =+'Aging Analysis'!C20 -> 174977
B29: из них необеспеченные | C29: =E29+I29+M29+Q29+U29 -> 0 | D29: =F29+J29+N29+R29+V29 -> 0 | Y29: =+W29+S29+O29+K29 -> 0 | Z29: =+X29+T29+P29+L29 -> 0 | AA29: =+AA28-C28 -> 0
A30: 13 | B30: Итого кредита и лизинга | C30: =+C6+C8+C10+C12+C14+C16+C18+C20+C22+C24+C26+C28 -> 8539798556 | D30: =+D6+D8+D10+D12+D14+D16+D18+D20+D22+D24+D26+D28 -> 2816524375 | E30: =+E6+E8+E10+E12+E14+E16+E18+E20+E22+E24+E26+E28 -> 6912201758 | F30: =+F6+F8+F10+F12+F14+F16+F18+F20+F22+F24+F26+F28 -> 2305249169 | G30: =+G6+G8+G10+G12+G14+G16+G18+G20+G22+G24+G26+G28 -> 0 | H30: =+H6+H8+H10+H12+H14+H16+H18+H20+H22+H24+H26+H28 -> 0 | I30: =+I6+I8+I10+I12+I14+I16+I18+I20+I22+I24+I26+I28 -> 1540989857 | J30: =+J6+J8+J10+J12+J14+J16+J18+J20+J22+J24+J26+J28 -> 511275206 | ... Z30: =+Z6+Z8+Z10+Z12+Z14+Z16+Z18+Z20+Z22+Z24+Z26+Z28 -> 51050196
B31: из них необеспеченные | C31: =+C7+C9+C11+C13+C15+C17+C19+C21+C23+C25+C27+C29 -> 0 | D31: =+D7+D9+D11+D13+D15+D17+D19+D21+D23+D25+D27+D29 -> 0 | E31: =+E7+E9+E11+E13+E15+E17+E19+E21+E23+E25+E27+E29 -> 0 | F31: =+F7+F9+F11+F13+F15+F17+F19+F21+F23+F25+F27+F29 -> 0 | G31: =+G7+G9+G11+G13+G15+G17+G19+G21+G23+G25+G27+G29 -> 0 | H31: =+H7+H9+H11+H13+H15+H17+H19+H21+H23+H25+H27+H29 -> 0 | I31: =+I7+I9+I11+I13+I15+I17+I19+I21+I23+I25+I27+I29 -> 0 | J31: =+J7+J9+J11+J13+J15+J17+J19+J21+J23+J25+J27+J29 -> 0 | ... Z31: =+Z7+Z9+Z11+Z13+Z15+Z17+Z19+Z21+Z23+Z25+Z27+Z29 -> 0
B32: По сектору экономики
A34: 14 | B34: Промышленность | C34: =E34+I34+M34+Q34+U34 -> 2237686406 | D34: =F34+J34+N34+R34+V34 -> 1298353689 | E34: 1824656663 | F34: 1066841849 | G34: 0 | H34: 0 | I34: 406373276 | J34: 231511840 | K34: 40570363 | L34: 23073859 | M34: 2854310 | N34: 0 | O34: 713578 | P34: 0 | Q34: 1850822 | R34: 0 | S34: 925411 | T34: 0 | U34: 1951335 | V34: 0 | W34: 1951335 | X34: 0 | Y34: =+W34+S34+O34+K34 -> 44160687 | Z34: =+X34+T34+P34+L34 -> 23073859 | AA34: =+'Aging Analysis'!C25 -> 2237686406
B35: из них необеспеченные | C35: =E35+I35+M35+Q35+U35 -> 0 | D35: =F35+J35+N35+R35+V35 -> 0 | Y35: =+W35+S35+O35+K35 -> 0 | Z35: =+X35+T35+P35+L35 -> 0 | AA35: =+AA34-C34 -> 0
A36: 15 | B36: Сельское хозяйство | C36: =E36+I36+M36+Q36+U36 -> 2167103674 | D36: =F36+J36+N36+R36+V36 -> 352882775 | E36: 1618847517 | F36: 232810109 | G36: 0 | H36: 0 | I36: 502209375 | J36: 120072666 | K36: 50227687 | L36: 12007267 | M36: 16112426 | N36: 0 | O36: 4028106 | P36: 0 | Q36: 23574190 | R36: 0 | S36: 11787095 | T36: 0 | U36: 6360166 | V36: 0 | W36: 6360166 | X36: 0 | Y36: =+W36+S36+O36+K36 -> 72403054 | Z36: =+X36+T36+P36+L36 -> 12007267 | AA36: =+'Aging Analysis'!C26 -> 2167103674
B37: из них необеспеченные | C37: =E37+I37+M37+Q37+U37 -> 0 | D37: =F37+J37+N37+R37+V37 -> 0 | Y37: =+W37+S37+O37+K37 -> 0 | Z37: =+X37+T37+P37+L37 -> 0 | AA37: =+AA36-C36 -> 0
A38: 16 | B38: Транспорт и коммуникации | C38: =E38+I38+M38+Q38+U38 -> 535740133 | D38: =F38+J38+N38+R38+V38 -> 196653734 | E38: 395472529 | F38: 104758856 | G38: 0 | H38: 0 | I38: 135184009 | J38: 91894878 | K38: 13518401 | L38: 9189488 | M38: 560024 | N38: 0 | O38: 140006 | P38: 0 | Q38: 1310310 | R38: 0 | S38: 655155 | T38: 0 | U38: 3213261 | V38: 0 | W38: 3213261 | X38: 0 | Y38: =+W38+S38+O38+K38 -> 17526823 | Z38: =+X38+T38+P38+L38 -> 9189488 | AA38: =+'Aging Analysis'!C27 -> 535740133
B39: из них необеспеченные | C39: =E39+I39+M39+Q39+U39 -> 0 | D39: =F39+J39+N39+R39+V39 -> 0 | Y39: =+W39+S39+O39+K39 -> 0 | Z39: =+X39+T39+P39+L39 -> 0 | AA39: =+AA38-C38 -> 0
A40: 17 | B40: Строительство | C40: =E40+I40+M40+Q40+U40 -> 374350021 | D40: =F40+J40+N40+R40+V40 -> 19624650 | E40: 291994997 | F40: 19624650 | G40: 0 | H40: 0 | I40: 81509125 | J40: 0 | K40: 8650913 | L40: 0 | M40: 605658 | N40: 0 | O40: 151414 | P40: 0 | Q40: 0 | R40: 0 | S40: 0 | T40: 0 | U40: 240241 | V40: 0 | W40: 240241 | X40: 0 | Y40: =+W40+S40+O40+K40 -> 9042568 | Z40: =+X40+T40+P40+L40 -> 0 | AA40: =+'Aging Analysis'!C28 -> 374350021
B41: из них необеспеченные | C41: =E41+I41+M41+Q41+U41 -> 0 | D41: =F41+J41+N41+R41+V41 -> 0 | Y41: =+W41+S41+O41+K41 -> 0 | Z41: =+X41+T41+P41+L41 -> 0 | AA41: =+AA40-C40 -> 0
A42: 18 | B42: Торговля и общественное питание | C42: =E42+I42+M42+Q42+U42 -> 757760211 | D42: =F42+J42+N42+R42+V42 -> 280650519 | E42: 630050765 | F42: 280650519 | G42: 0 | H42: 0 | I42: 117999849 | J42: 0 | K42: 11799985 | L42: 0 | M42: 2409024 | N42: 0 | O42: 602256 | P42: 0 | Q42: 4749582 | R42: 0 | S42: 2374791 | T42: 0 | U42: 2550991 | V42: 0 | W42: 2550991 | X42: 0 | Y42: =+W42+S42+O42+K42 -> 17328023 | Z42: =+X42+T42+P42+L42 -> 0 | AA42: =+'Aging Analysis'!C29 -> 757760211
B43: из них необеспеченные | C43: =E43+I43+M43+Q43+U43 -> 0 | D43: =F43+J43+N43+R43+V43 -> 0 | Y43: =+W43+S43+O43+K43 -> 0 | Z43: =+X43+T43+P43+L43 -> 0 | AA43: =+AA42-C42 -> 0
A44: 19 | B44: Материально-техническое снабжение и сбыт | C44: =E44+I44+M44+Q44+U44 -> 1372056029 | D44: =F44+J44+N44+R44+V44 -> 662585053 | E44: 1161702733 | F44: 594789231 | G44: 0 | H44: 0 | I44: 203481814 | J44: 67795822 | K44: 20348181 | L44: 6779582 | M44: 4795921 | N44: 0 | O44: 1198980 | P44: 0 | Q44: 1125519 | R44: 0 | S44: 562760 | T44: 0 | U44: 950042 | V44: 0 | W44: 950042 | X44: 0 | Y44: =+W44+S44+O44+K44 -> 23059963 | Z44: =+X44+T44+P44+L44 -> 6779582 | AA44: =+'Aging Analysis'!C30 -> 1372056029
B45: из них необеспеченные | C45: =E45+I45+M45+Q45+U45 -> 0 | D45: =F45+J45+N45+R45+V45 -> 0 | Y45: =+W45+S45+O45+K45 -> 0 | Z45: =+X45+T45+P45+L45 -> 0 | AA45: =+AA44-C44 -> 0
A46: 20 | B46: Жилищно-коммунальные услуги | C46: =E46+I46+M46+Q46+U46 -> 107626665 | D46: =F46+J46+N46+R46+V46 -> 0 | E46: 107626665 | F46: 0 | G46: 0 | H46: 0 | I46: 0 | J46: 0 | K46: 0 | L46: 0 | M46: 0 | N46: 0 | O46: 0 | P46: 0 | Q46: 0 | R46: 0 | S46: 0 | T46: 0 | U46: 0 | V46: 0 | W46: 0 | X46: 0 | Y46: =+W46+S46+O46+K46 -> 0 | Z46: =+X46+T46+P46+L46 -> 0 | AA46: =+'Aging Analysis'!C31 -> 107626665
B47: из них необеспеченные | C47: =E47+I47+M47+Q47+U47 -> 0 | D47: =F47+J47+N47+R47+V47 -> 0 | Y47: =+W47+S47+O47+K47 -> 0 | Z47: =+X47+T47+P47+L47 -> 0 | AA47: =+AA46-C46 -> 0
A48: 21 | B48: Другие сектора | C48: =E48+I48+M48+Q48+U48 -> 987475417 | D48: =F48+J48+N48+R48+V48 -> 5773955 | E48: 881849889 | F48: 5773955 | G48: 0 | H48: 0 | I48: 94232409 | J48: 0 | K48: 9428661 | L48: 0 | M48: 7135928 | N48: 0 | O48: 1783982 | P48: 0 | Q48: 3308601 | R48: 0 | S48: 1711801 | T48: 0 | U48: 948590 | V48: 0 | W48: 948590 | X48: 0 | Y48: =+W48+S48+O48+K48 -> 13873034 | Z48: =+X48+T48+P48+L48 -> 0 | AA48: =+'Aging Analysis'!C32 -> 987475417
B49: из них необеспеченные | C49: =E49+I49+M49+Q49+U49 -> 0 | D49: =F49+J49+N49+R49+V49 -> 0 | Y49: =+W49+S49+O49+K49 -> 0 | Z49: =+X49+T49+P49+L49 -> 0 | AA49: =+AA48-C48 -> 0
A50: 22 | B50: Итого кредита и лизинга | C50: =+C34+C36+C38+C40+C42+C44+C46+C48 -> 8539798556 | D50: =+D34+D36+D38+D40+D42+D44+D46+D48 -> 2816524375 | E50: =+E34+E36+E38+E40+E42+E44+E46+E48 -> 6912201758 | F50: =+F34+F36+F38+F40+F42+F44+F46+F48 -> 2305249169 | G50: =+G34+G36+G38+G40+G42+G44+G46+G48 -> 0 | H50: =+H34+H36+H38+H40+H42+H44+H46+H48 -> 0 | I50: =+I34+I36+I38+I40+I42+I44+I46+I48 -> 1540989857 | J50: =+J34+J36+J38+J40+J42+J44+J46+J48 -> 511275206 | ... Z50: =+Z34+Z36+Z38+Z40+Z42+Z44+Z46+Z48 -> 51050196
B51: из них необеспеченные | C51: =+C35+C37+C39+C41+C43+C45+C47+C49 -> 0 | D51: =+D35+D37+D39+D41+D43+D45+D47+D49 -> 0 | E51: =+E35+E37+E39+E41+E43+E45+E47+E49 -> 0 | F51: =+F35+F37+F39+F41+F43+F45+F47+F49 -> 0 | G51: =+G35+G37+G39+G41+G43+G45+G47+G49 -> 0 | H51: =+H35+H37+H39+H41+H43+H45+H47+H49 -> 0 | I51: =+I35+I37+I39+I41+I43+I45+I47+I49 -> 0 | J51: =+J35+J37+J39+J41+J43+J45+J47+J49 -> 0 | ... Z51: =+Z35+Z37+Z39+Z41+Z43+Z45+Z47+Z49 -> 0
B52: По регионам
A54: 23 | B54: Республика Каракалпакстан | C54: =E54+I54+M54+Q54+U54 -> 441572218 | D54: =F54+J54+N54+R54+V54 -> 38990548 | E54: 306168447 | F54: 733384 | G54: 0 | H54: 0 | I54: 129316979 | J54: 38257164 | K54: 12931698 | L54: 3825716 | M54: 3476320 | N54: 0 | O54: 869080 | P54: 0 | Q54: 1320395 | R54: 0 | S54: 660198 | T54: 0 | U54: 1290077 | V54: 0 | W54: 1290077 | X54: 0 | Y54: =+W54+S54+O54+K54 -> 15751053 | Z54: =+X54+T54+P54+L54 -> 3825716
A55: 24 | B55: Андижанская область | C55: =E55+I55+M55+Q55+U55 -> 447148763 | D55: =F55+J55+N55+R55+V55 -> 129117715 | E55: 284254662 | F55: 66347731 | G55: 0 | H55: 0 | I55: 153677968 | J55: 62769984 | K55: 15367797 | L55: 6276998 | M55: 1063059 | N55: 0 | O55: 265765 | P55: 0 | Q55: 3452561 | R55: 0 | S55: 1726281 | T55: 0 | U55: 4700513 | V55: 0 | W55: 4700513 | X55: 0 | Y55: =+W55+S55+O55+K55 -> 22060356 | Z55: =+X55+T55+P55+L55 -> 6276998
A56: 25 | B56: Бухарская область | C56: =E56+I56+M56+Q56+U56 -> 444773413 | D56: =F56+J56+N56+R56+V56 -> 79091718 | E56: 350079189 | F56: 46301404 | G56: 0 | H56: 0 | I56: 94694224 | J56: 32790314 | K56: 9469422 | L56: 3279031 | M56: 0 | N56: 0 | O56: 0 | P56: 0 | Q56: 0 | R56: 0 | S56: 0 | T56: 0 | U56: 0 | V56: 0 | W56: 0 | X56: 0 | Y56: =+W56+S56+O56+K56 -> 9469422 | Z56: =+X56+T56+P56+L56 -> 3279031
A57: 26 | B57: Джизакская область | C57: =E57+I57+M57+Q57+U57 -> 378923818 | D57: =F57+J57+N57+R57+V57 -> 60434445 | E57: 308966767 | F57: 58140320 | G57: 0 | H57: 0 | I57: 67418247 | J57: 2294125 | K57: 7264034 | L57: 229412 | M57: 413608 | N57: 0 | O57: 103402 | P57: 0 | Q57: 1487342 | R57: 0 | S57: 743671 | T57: 0 | U57: 637854 | V57: 0 | W57: 637854 | X57: 0 | Y57: =+W57+S57+O57+K57 -> 8748961 | Z57: =+X57+T57+P57+L57 -> 229412
A58: 27 | B58: Кашкадарьинская область | C58: =E58+I58+M58+Q58+U58 -> 637101140 | D58: =F58+J58+N58+R58+V58 -> 120649454 | E58: 510836199 | F58: 113387432 | G58: 0 | H58: 0 | I58: 99765700 | J58: 7262022 | K58: 9976570 | L58: 726202 | M58: 5698871 | N58: 0 | O58: 1424718 | P58: 0 | Q58: 19646493 | R58: 0 | S58: 9823247 | T58: 0 | U58: 1153877 | V58: 0 | W58: 1153877 | X58: 0 | Y58: =+W58+S58+O58+K58 -> 22378412 | Z58: =+X58+T58+P58+L58 -> 726202
A59: 28 | B59: Навоийская область | C59: =E59+I59+M59+Q59+U59 -> 316658999 | D59: =F59+J59+N59+R59+V59 -> 17644809 | E59: 281744799 | F59: 16862496 | G59: 0 | H59: 0 | I59: 34028215 | J59: 782313 | K59: 3402821 | L59: 78231 | M59: 52064 | N59: 0 | O59: 13016 | P59: 0 | Q59: 42765 | R59: 0 | S59: 21383 | T59: 0 | U59: 791156 | V59: 0 | W59: 791156 | X59: 0 | Y59: =+W59+S59+O59+K59 -> 4228376 | Z59: =+X59+T59+P59+L59 -> 78231
A60: 29 | B60: Наманганская область | C60: =E60+I60+M60+Q60+U60 -> 574912155 | D60: =F60+J60+N60+R60+V60 -> 72790068 | E60: 448988194 | F60: 61890259 | G60: 0 | H60: 0 | I60: 118131405 | J60: 10899809 | K60: 11813140 | L60: 1089981 | M60: 5363154 | N60: 0 | O60: 1340789 | P60: 0 | Q60: 1833639 | R60: 0 | S60: 916820 | T60: 0 | U60: 595763 | V60: 0 | W60: 595763 | X60: 0 | Y60: =+W60+S60+O60+K60 -> 14666512 | Z60: =+X60+T60+P60+L60 -> 1089981
A61: 30 | B61: Самаркандская область | C61: =E61+I61+M61+Q61+U61 -> 685033778 | D61: =F61+J61+N61+R61+V61 -> 32184469 | E61: 545713307 | F61: 26430755 | G61: 0 | H61: 0 | I61: 127200703 | J61: 5753714 | K61: 12720070 | L61: 575371 | M61: 9468101 | N61: 0 | O61: 2367025 | P61: 0 | Q61: 1502499 | R61: 0 | S61: 751249 | T61: 0 | U61: 1149168 | V61: 0 | W61: 1149168 | X61: 0 | Y61: =+W61+S61+O61+K61 -> 16987512 | Z61: =+X61+T61+P61+L61 -> 575371
A62: 31 | B62: Сурхандарьинская область | C62: =E62+I62+M62+Q62+U62 -> 959218563 | D62: =F62+J62+N62+R62+V62 -> 361805678 | E62: 713071400 | F62: 227983901 | G62: 0 | H62: 0 | I62: 244301387 | J62: 133821777 | K62: 24499469 | L62: 13476465 | M62: 1586461 | N62: 0 | O62: 396615 | P62: 0 | Q62: 0 | R62: 0 | S62: 0 | T62: 0 | U62: 259315 | V62: 0 | W62: 259315 | X62: 0 | Y62: =+W62+S62+O62+K62 -> 25155399 | Z62: =+X62+T62+P62+L62 -> 13476465
A63: 32 | B63: Сырдарьинская область | C63: =E63+I63+M63+Q63+U63 -> 442727784 | D63: =F63+J63+N63+R63+V63 -> 157159141 | E63: 322423486 | F63: 116026411 | G63: 0 | H63: 0 | I63: 114268086 | J63: 41132730 | K63: 11426809 | L63: 4113273 | M63: 583130 | N63: 0 | O63: 145782 | P63: 0 | Q63: 2619526 | R63: 0 | S63: 1309763 | T63: 0 | U63: 2833556 | V63: 0 | W63: 2833556 | X63: 0 | Y63: =+W63+S63+O63+K63 -> 15715910 | Z63: =+X63+T63+P63+L63 -> 4113273
A64: 33 | B64: г. Ташкент | C64: =E64+I64+M64+Q64+U64 -> 1605934332 | D64: =F64+J64+N64+R64+V64 -> 1126034805 | E64: 1416757006 | F64: 975796278 | G64: 0 | H64: 0 | I64: 189084334 | J64: 150238527 | K64: 18908435 | L64: 15023855 | M64: 84657 | N64: 0 | O64: 21164 | P64: 0 | Q64: 8334 | R64: 0 | S64: 4166 | T64: 0 | U64: 1 | V64: 0 | W64: 1 | X64: 0 | Y64: =+W64+S64+O64+K64 -> 18933766 | Z64: =+X64+T64+P64+L64 -> 15023855
A65: 34 | B65: Ташкентская область | C65: =E65+I65+M65+Q65+U65 -> 758868441 | D65: =F65+J65+N65+R65+V65 -> 348344121 | E65: 675336263 | F65: 332238518 | G65: 0 | H65: 0 | I65: 79171708 | J65: 16105603 | K65: 7770613 | L65: 1438948 | M65: 2882794 | N65: 0 | O65: 720698 | P65: 0 | Q65: 974319 | R65: 0 | S65: 544659 | T65: 0 | U65: 503357 | V65: 0 | W65: 503357 | X65: 0 | Y65: =+W65+S65+O65+K65 -> 9539327 | Z65: =+X65+T65+P65+L65 -> 1438948
... A67: 36 | B67: Хорезмская область | C67: =E67+I67+M67+Q67+U67 -> 425567875 | D67: =F67+J67+N67+R67+V67 -> 166497004 | E67: 380529403 | F67: 161869886 | G67: 0 | H67: 0 | I67: 39788747 | J67: 4627118 | K67: 3978875 | L67: 462712 | M67: 2397355 | N67: 0 | O67: 599339 | P67: 0 | Q67: 1551140 | R67: 0 | S67: 775570 | T67: 0 | U67: 1301230 | V67: 0 | W67: 1301230 | X67: 0 | Y67: =+W67+S67+O67+K67 -> 6655014 | Z67: =+X67+T67+P67+L67 -> 462712
A68: 37 | B68: Итого кредита и лизинга | C68: =SUM(C54:C67) -> 8539798556 | D68: =SUM(D54:D67) -> 2816524375 | E68: =SUM(E54:E67) -> 6912201758 | F68: =SUM(F54:F67) -> 2305249169 | G68: =SUM(G54:G67) -> 0 | H68: =SUM(H54:H67) -> 0 | I68: =SUM(I54:I67) -> 1540989857 | J68: =SUM(J54:J67) -> 511275206 | ... Z68: =SUM(Z54:Z67) -> 51050196
A69: 38 | B69: Другие классифицированные активы | C69: =E69+I69+M69+Q69+U69 -> 1940511261 | D69: =F69+J69+N69+R69+V69 -> 0 | E69: =+SUM('Asset quality'!C10:C15)+SUM('Asset quality'!C48:C60) -> 1940511261 | G69: 0 | K69: 11710022 | V69: 0 | X69: 0 | Y69: =+W69+S69+O69+K69 -> 11710022 | Z69: =+X69+T69+P69+L69 -> 0
B70: из них необеспеченные | C70: =E70+I70+M70+Q70+U70 -> 0 | D70: =F70+J70+N70+R70+V70 -> 0 | Y70: =+W70+S70+O70+K70 -> 0 | Z70: =+X70+T70+P70+L70 -> 0
A71: 39 | B71: Всего классифицированных активов | C71: =+C50+C69 -> 10480309817 | D71: =+D50+D69 -> 2816524375 | E71: =+E50+E69 -> 8852713019 | F71: =+F50+F69 -> 2305249169 | G71: =+G50+G69 -> 0 | H71: =+H50+H69 -> 0 | I71: =+I50+I69 -> 1540989857 | J71: =+J50+J69 -> 511275206 | ... Z71: =+Z50+Z69 -> 51050196
B74: Подпись Председателя правления:
B76: Подпись Главного Бухгалтера:
E77: =SUM('Asset quality'!D21:D47)+'Asset quality'!D16 -> 6912201758 | G77: =SUM('Asset quality'!O21:O47)+'Asset quality'!O16 -> 0 | I77: =SUM('Asset quality'!E21:E47)+'Asset quality'!E16 -> 1540989857 | K77: =SUM('Asset quality'!P21:P47)+'Asset quality'!P16 -> 154544191 | M77: =SUM('Asset quality'!F21:F47) -> 34473291 | O77: =SUM('Asset quality'!Q21:Q47)+'Asset quality'!Q16 -> 8618322 | Q77: =SUM('Asset quality'!G21:G47) -> 35919024 | S77: =SUM('Asset quality'!R21:R47)+'Asset quality'!R16 -> 18017013 | U77: =SUM('Asset quality'!H21:H47) -> 16214626 | W77: =SUM('Asset quality'!S21:S47)+'Asset quality'!S16 -> 16214626 | Y77: =+W77+S77+O77+K77 -> 197394152
G78: =+'Asset quality'!O9+'Asset quality'!O62 -> 0 | K78: =+'Asset quality'!P9+'Asset quality'!P62 -> 166254213 | O78: =+'Asset quality'!Q9+'Asset quality'!Q62 -> 8618322 | S78: =+'Asset quality'!R9+'Asset quality'!R62 -> 18017013 | W78: =+'Asset quality'!S9+'Asset quality'!S62 -> 16214626 | Y78: =+W78+S78+O78+K78 -> 209104174
E79: =+E77-E50 -> 0 | G79: =+G77-G50 -> 0 | I79: =+I77-I50 -> 0 | K79: =+K77-K50 -> 0 | M79: =+M77-M50 -> 0 | O79: =+O77-O50 -> 0 | Q79: =+Q77-Q50 -> 0 | S79: =+S77-S50 -> 0 | U79: =+U77-U50 -> 0 | W79: =+W77-W50 -> 0 | Y79: =+Y77-Y50 -> 0
G80: =+G78-G71 -> 0 | K80: =+K78-K71 -> 0 | O80: =+O78-O71 -> 0 | S80: =+S78-S71 -> 0 | W80: =+W78-W71 -> 0 | Y80: =+Y78-Y71 -> 0

Sheet Loans to Affiliated P.
A1: ОТЧЕТ О СДЕЛКАХ, ЗАКЛЮЧЕННЫХ СО СВЯЗАННЫМИ ЛИЦАМИ | S1: Таблица-11
B3: =+'Asset quality'!B3 -> АКБ "Микрокредитбанк" | N3: =+'Asset quality'!P3 -> 44196 | S3: тыс. сум
A4: № | B4: Наименования клиента | C4: ИНН | D4: Вид деятельности | E4: Код валюты | F4: Номер группы | G4: Текущая задолженность | H4: из них | N4: Пересмотрения | O4: Обеспечения | Q4: Классификация | R4: Резерв | S4: Источник кредита
H5: Кредиты и лизинги | I5: Инвестиции | J5: Аккредитивы | K5: Гарантии | L5: Межбанковские кредиты и депозиты | M5: другие активы* | O5: Вид залога | P5: Сумма залога
B6: А | C6: Б | D6: В | E6: Г | F6: Д | G6: Е | H6: Е1 | I6: Е2 | J6: Е3 | K6: Е4 | L6: Е5 | M6: Е6 | N6: Ж | O6: З | P6: И | Q6: К | R6: Л | S6: М
A7: 1 | B7: Исматуллоев Акрам Акмалович | C7: AA5013105 | D7: Физические лица | E7: 000 | F7: 1 | G7: =SUM(H7:M7) -> 243460.56 | H7: 243460.56 | R7: 0 | S7: 11-Собственные
A8: 2 | B8: Гуччиев Илхом Турсункулович | C8: CT1907643 | D8: Физические лица | E8: 000 | F8: 2 | G8: =SUM(H8:M8) -> 0 | H8: 0 | R8: 0 | S8: 11-Собственные
A9: 3 | B9: Пулатова Муниса Тоировна | C9: AA1343647 | D9: Физические лица | E9: 000 | F9: 3 | G9: =SUM(H9:M9) -> 46095.409 | H9: 46095.409 | R9: 0 | S9: 11-Собственные
A10: 4 | B10: Умаров Сарвар Салахиддинович | C10: AB5528260 | D10: Физические лица | E10: 000 | F10: 4 | G10: =SUM(H10:M10) -> 48348.292 | H10: 48348.292 | R10: 0 | S10: 11-Собственные
A11: 5 | B11: Ахмаджонов Абдулазиз Абдусатторович | C11: AA1266275 | D11: Физические лица | E11: 000 | F11: 5 | G11: =SUM(H11:M11) -> 0 | H11: 0 | R11: 0 | S11: 11-Собственные
A12: 6 | B12: Тогаев Даврон Дусмамат уғли | C12: CT1881274 | D12: Физические лица | E12: 000 | F12: 6 | G12: =SUM(H12:M12) -> 34527.646 | H12: 34527.646 | R12: 0 | S12: 11-Собственные
A13: 7 | B13: Саматов Юнус Уралович | C13: CS0384112 | D13: Физические лица | E13: 000 | F13: 7 | G13: =SUM(H13:M13) -> 20913.278 | H13: 20913.278 | R13: 0 | S13: 11-Собственные
A14: 8 | B14: Каримкулов Хикматулло | C14: BG0108618 | D14: Физические лица | E14: 000 | F14: 8 | G14: =SUM(H14:M14) -> 16632.785 | H14: 16632.785 | R14: 0 | S14: 11-Собственные
A15: 9 | B15: Саксонов Азизбек Нурбобоевич | C15: CE2612031 | D15: Физические лица | E15: 000 | F15: 9 | G15: =SUM(H15:M15) -> 14826.673 | H15: 14826.673 | R15: 0 | S15: 11-Собственные
A16: 10 | B16: Бабаджанов Шухрат Адилбекович | C16: AA1901433 | D16: Физические лица | E16: 000 | F16: 10 | G16: =SUM(H16:M16) -> 20124.334 | H16: 20124.334 | R16: 0 | S16: 11-Собственные
A17: 11 | B17: Бегматов Бобур Яхшиевич | C17: CN2398457 | D17: Физические лица | E17: 000 | F17: 11 | G17: =SUM(H17:M17) -> 10073.722 | H17: 10073.722 | R17: 0 | S17: 11-Собственные
A18: 12 | B18: Муминов Юсуп Машарипович | C18: CE2162465 | D18: Физические лица | E18: 000 | F18: 12 | G18: =SUM(H18:M18) -> 7080 | H18: 7080 | R18: 0 | S18: 11-Собственные
... A31: 25 | B31: Эрдонаев Олим Тожиевич | C31: CS1661937 | D31: Физические лица | E31: 000 | F31: 30 | G31: =SUM(H31:M31) -> 19320.954 | H31: 19320.954 | R31: 0 | S31: 11-Собственные
A32: 26 | B32: OCHILOV SARVAR NURMANOVICH | C32: AA1176596 | D32: Физические лица | E32: 000 | F32: 65 | G32: 1000 | H32: 0 | R32: 0 | S32: 11-Собственные
A33: 27 | B33: Кушназаров Акбар Нарханович | C33: AA1814951 | D33: Физические лица | E33: 000 | F33: 32 | G33: =SUM(H33:M33) -> 28460.47 | H33: 28460.47 | R33: 0 | S33: 11-Собственные
A34: 28 | B34: Mamarakhimov Abror Xaldarovich | C34: AA1545194 | D34: Физические лица | E34: 000 | F34: 34 | G34: =SUM(H34:M34) -> 26125 | H34: 26125 | R34: 0 | S34: 11-Собственные
A35: 29 | B35: KHOLOV TAKHIR SADULLAYEVICH | C35: AA1598158 | D35: Физические лица | E35: 000 | F35: 35 | G35: =SUM(H35:M35) -> 200445.8 | H35: 200445.8 | R35: 0 | S35: 11-Собственные
A36: 30 | B36: ARAMOV RASHID RAVSHANOVICH | C36: AA1574588 | D36: Физические лица | E36: 000 | F36: 36 | G36: =SUM(H36:M36) -> 105680.96 | H36: 105680.96 | R36: 0 | S36: 11-Собственные
A37: 31 | B37: SOLIEV SARDORBEK XOLMIRZAYEVICH | C37: AA1507783 | D37: Физические лица | E37: 000 | F37: 37 | G37: =SUM(H37:M37) -> 110377.89 | H37: 110377.89 | R37: 0 | S37: 11-Собственные
A38: 32 | B38: SIDDIKOV SHOKHRUKH IBRAGIMJONOVICH | C38: AA0281567 | D38: Физические лица | E38: 000 | F38: 38 | G38: =SUM(H38:M38) -> 117000.57 | H38: 117000.57 | R38: 0 | S38: 11-Собственные
A39: 33 | B39: JURAYEV ZARIPJAN YULDASHEVICH | C39: AA0727084 | D39: Физические лица | E39: 000 | F39: 39 | G39: =SUM(H39:M39) -> 0 | H39: 0 | R39: 0 | S39: 11-Собственные
A40: 34 | B40: OMONOV OTAJON JURAQULOVICH | C40: AA8332674 | D40: Физические лица | E40: 000 | F40: 40 | G40: =SUM(H40:M40) -> 106001.82 | H40: 106001.82 | R40: 0 | S40: 11-Собственные
A41: 35 | B41: Пардаев Эшдавлат Абдумуминович | C41: CS0139454 | D41: Физические лица | E41: 000 | F41: 63 | G41: 826929.28 | H41: 80266.109 | R41: 0 | S41: 11-Собственные
A42: 36 | B42: ISKANOV ILKHOMJON XOLDOROVICH | C42: AA1086982 | D42: Физические лица | E42: 000 | F42: 42 | G42: =SUM(H42:M42) -> 15978 | H42: 15978 | R42: 0 | S42: 11-Собственные
A43: 37 | B43: MUQIMOV AZAMAT SAIDOVICH | C43: AA0093700 | D43: Физические лица | E43: 000 | F43: 43 | G43: =SUM(H43:M43) -> 4052.7821 | H43: 4052.7821 | R43: 0 | S43: 11-Собственные
A44: 38 | B44: BESHIMOV AZAMAT XAMROBOYEVICH | C44: AB9725681 | D44: Физические лица | E44: 000 | F44: 45 | G44: =SUM(H44:M44) -> 107994.24 | H44: 107994.24 | R44: 0 | S44: 11-Собственные
A45: 39 | B45: NARZULLAYEV YAKUB BOBOMURODOVICH | C45: AB9773826 | D45: Физические лица | E45: 000 | F45: 46 | G45: =SUM(H45:M45) -> 2000.0794 | H45: 2000.0794 | R45: 0 | S45: 11-Собственные
A46: 40 | B46: TOPILOV SHERZOD SAIDKARIMOVICH | C46: AA1771771 | D46: Физические лица | E46: 000 | F46: 47 | G46: =SUM(H46:M46) -> 1903.9384 | H46: 1903.9384 | R46: 0 | S46: 11-Собственные
A47: 41 | B47: AZLAROV ABDULLA ABDULXAYEVICH | C47: AB0145415 | D47: Физические лица | E47: 000 | F47: 48 | G47: =SUM(H47:M47) -> 98193.866 | H47: 98193.866 | R47: 0 | S47: 11-Собственные
A48: 42 | B48: MADUMAROV XUSNIDDIN KOMILOVICH | C48: AA0620069 | D48: Физические лица | E48: 000 | F48: 49 | G48: =SUM(H48:M48) -> 104123.76 | H48: 104123.76 | R48: 0 | S48: 11-Собственные
A49: 43 | B49: ESHMATOV MASRUR QURBONOVICH | C49: AA1344338 | D49: Физические лица | E49: 000 | F49: 50 | G49: =SUM(H49:M49) -> 9971.3918 | H49: 9971.3918 | R49: 0 | S49: 11-Собственные
A50: 44 | B50: TAYLAKOV ISMOIL RAMIZOVICH | C50: AA4589423 | D50: Физические лица | E50: 000 | F50: 51 | G50: =SUM(H50:M50) -> 4054.5336 | H50: 4054.5336 | R50: 0 | S50: 11-Собственные
A51: 45 | B51: MIRZAEV BAKHODIR XUSANOVICH | C51: AA6739140 | D51: Физические лица | E51: 000 | F51: 52 | G51: =SUM(H51:M51) -> 89852.353 | H51: 89852.353 | R51: 0 | S51: 11-Собственные
A52: 46 | B52: JUMAYEV NURALI ISOXONOVICH | C52: AA1395310 | D52: Физические лица | E52: 000 | F52: 53 | G52: =SUM(H52:M52) -> 99999.155 | H52: 99999.155 | R52: 0 | S52: 11-Собственные
A53: 47 | B53: OTAQOZIYEV ABRORJON ABDULLAYEVICH | C53: AB6494562 | D53: Физические лица | E53: 000 | F53: 54 | G53: =SUM(H53:M53) -> 113987.83 | H53: 113987.83 | R53: 0 | S53: 11-Собственные
... A61: 55 | B61: BURIYEV ESHTUKTAR SATTAROVICH | C61: AA8622548 | D61: Физические лица | E61: 000 | F61: 62 | G61: =SUM(H61:M61) -> 74761.622 | H61: 74761.622 | R61: 0 | S61: 11-Собственные
G63: =SUM(H63:M63) -> 0
A64: ИТОГО АКТИВОВ ПО СВЯЗАННЫМ ЛИЦАМ | G64: =SUM(G7:G63) -> 3128439.7 | H64: =SUM(H7:H63) -> 2380776.5 | I64: =SUM(I7:I63) -> 0 | J64: =SUM(J7:J63) -> 0 | K64: =SUM(K7:K63) -> 0 | L64: =SUM(L7:L63) -> 0 | M64: =SUM(M7:M63) -> 0 | P64: =SUM(P7:P63) -> 0
A65: САМЫЙ КРУПНЫЙ АКТИВ, ВЫДАННЫЙ БАНКОМ ОДНОМУ ИНСАЙДЕРУ | G65: =MAX(G7:G63) -> 826929.28 | H65: =MAX(H7:H63) -> 243460.56 | I65: =MAX(I7:I63) -> 0 | J65: =MAX(J7:J63) -> 0 | K65: =MAX(K7:K63) -> 0 | L65: =MAX(L7:L63) -> 0 | M65: =MAX(M7:M63) -> 0 | P65: =MAX(P7:P63) -> 0
B68: Подпись Председателя Правления:
B70: Подпись Главного Бухгалтера:

Sheet  Largest risk
A1: ОТЧЕТ О КРУПНЫХ РИСКАХ | S1: Таблица-12
B3: =+'Asset quality'!B3 -> АКБ "Микрокредитбанк" | N3: =+'Asset quality'!P3 -> 44196 | O3: =+#REF! -> #REF! | S3: тыс. сум
A4: № | B4: Наименования клиента | C4: ИНН | D4: Вид деятельности | E4: Код валюты | F4: Номер группы | G4: Текущая задолженность | H4: из них | N4: Пересмотрения | O4: Обеспечения | Q4: Классификация | R4: Резерв | S4: Источник кредита
H5: Кредиты и лизинги | I5: Инвестиции | J5: Аккредитивы | K5: Гарантии | L5: Межбанковские кредиты и депозиты | M5: другие активы* | O5: Вид залога | P5: Сумма залога
B6: А | C6: Б | D6: В | E6: Г | F6: Д | G6: Е | H6: Е1 | I6: Е2 | J6: Е3 | K6: Е4 | L6: Е5 | M6: Е6 | N6: Ж | O6: З | P6: И | Q6: К | R6: Л | S6: М
A7: 1 | B7: ИП ООО "EPSILON DEVELOPMENT COMPANY" | C7: 305922787 | D7: нефт | E7: 840 | F7: 2 | G7: =+H7+M7 -> 372356820 | H7: 369646200 | M7: 2710620 | U7: 0
A8: 2 | B8: ООО "SESAME" | C8: 306892604 | D8: нефт | E8: 840 | F8: 1 | G8: =+H8+M8 -> 460153398 | H8: 456822406 | M8: 3330992
A9: 3 | G9: =SUM(H9:M9) -> 0
A10: 4 | G10: 0
A11: 5 | G11: =SUM(H11:M11) -> 0
A12: 6 | G12: =SUM(H12:M12) -> 0
A13: 7 | G13: =SUM(H13:M13) -> 0
A14: 8 | G14: =SUM(H14:M14) -> 0
A15: 9 | G15: =SUM(H15:M15) -> 0
A16: 10 | G16: =SUM(H16:M16) -> 0
A17: 11 | G17: =SUM(H17:M17) -> 0
A18: 12 | G18: =SUM(H18:M18) -> 0
A19: 13 | G19: =SUM(H19:M19) -> 0
A20: 14 | G20: =SUM(H20:M20) -> 0
A21: 15 | G21: =SUM(H21:M21) -> 0
A22: 16 | G22: =SUM(H22:M22) -> 0
... A66: 60 | G66: =SUM(H66:M66) -> 0
B67: ИТОГО КРУПНЫХ АКТИВОВ | G67: =SUM(G7:G66) -> 832510218 | H67: =SUM(H7:H66) -> 826468606 | I67: =SUM(I7:I66) -> 0 | J67: =SUM(J7:J66) -> 0 | K67: =SUM(K7:K66) -> 0 | L67: =SUM(L7:L66) -> 0 | M67: =SUM(M7:M66) -> 6041612 | P67: =SUM(P7:P66) -> 0
B68: САМЫЙ КРУПНЫЙ АКТИВ, ВЫДАННЫЙ БАНКОМ | G68: =MAX(G7:G66) -> 460153398 | H68: =MAX(H7:H66) -> 456822406 | I68: =MAX(I7:I66) -> 0 | J68: =MAX(J7:J66) -> 0 | K68: =MAX(K7:K66) -> 0 | L68: =MAX(L7:L66) -> 0 | M68: =MAX(M7:M66) -> 3330992 | P68: =MAX(P7:P66) -> 0
B71: Подпись Председателя правления:
B73: Подпись Главного Бухгалтера:

Sheet Charge-offs and Recoveries
A1: ОТЧЕТ О CПИСАННЫХ И ВОЗВРАЩЕННЫХ ПЛАТЕЖАХ ИЗ РЕЗЕРВА ВОЗМОЖНЫХ ПОТЕРЬ ПО КРЕДИТАМ И ЛИЗИНГУ | E1: Таблица-13
A3: Часть 1 Списания и возврат | B3: =+'Asset quality'!B3 -> АКБ "Микрокредитбанк" | E3: =+'Asset quality'!P3 -> 44196
A4: Отрасль экономики | B4: Списание - А | D4: Возврат - Б
B5: Всего | C5: в иностранной валюте | D5: Всего | E5: в иностранной валюте
A6: А | B6: Б | C6: В | D6: Г | E6: Д
A7: 1. Промышленность | B7: 1110282 | C7: 0 | D7: 198745 | E7: 0
A8: 2. Сельское хозяйство | B8: 2759996 | C8: 0 | D8: 738137 | E8: 0
A9: 3. Транспорт и коммуникации | B9: 5845263 | C9: 0 | D9: 909893 | E9: 0
A10: 4. Строительство | B10: 2355357 | C10: 0 | D10: 48614 | E10: 0
A11: 5. Торговля и общественное питание | B11: 7635815 | C11: 0 | D11: 2025420 | E11: 0
A12: 6. Материально-техническое снабжение и сбыт | B12: 0 | C12: 0 | D12: 0 | E12: 0
A13: 7. Жилищно-коммунальные услуги | B13: 0 | C13: 0 | D13: 0 | E13: 0
A14: 8. Другие сектора | B14: 3125301 | C14: 0 | D14: 393776 | E14: 0
A15: 9. Итого | B15: =SUM(B7:B14) -> 22832014 | C15: =SUM(C7:C14) -> 0 | D15: =SUM(D7:D14) -> 4314585 | E15: =SUM(E7:E14) -> 0
A18: Часть 2
A19: Изменения в резерве возможных убытков по кредитам и лизингу
A20: 1. Остаток на начало текущего года | C20: 119925695
A21: 2. Плюс: Возвращенные платежи | C21: =D15 -> 4314585
A22: 3. Минус: Списанные кредиты и лизинги | B22: 0 | C22: =B15 -> 22832014
A23: 4. Отчисления в резерв по состоянию на дату от начала года | C23: =+'Income '!C31 -> 199222532
A24: 5. Поправки | C24: -103236646
A25: 6. Текущий баланс | C25: =SUM(C20:C21)-C22+SUM(C23:C24) -> 197394152 | F25: =+'Asset Classification'!Y50 -> 197394152
A28: Подпись Председателя правления:
A30: Подпись Главного Бухгалтера:

Sheet loans_av rate
A1: ДАННЫЕ О СРЕДНЕВЗВЕШЕННЫХ ПРОЦЕНТНЫХ СТАВКАХ ПО КРЕДИТАМ | H1: Таблица-20
B3: =+'Asset quality'!B3 -> АКБ "Микрокредитбанк" | F3: =+'Asset quality'!P3 -> 44196 | H3: тыс. сум
A4: № | B4: Виды кредитования | C4: всего | E4: в том числе
E5: в национальный валюте | G5: в иностранной валюте
C6: остаток всего | D6: средневзвешенные процентные ставки | E6: остаток всего | F6: средневзвешенные процентные ставки | G6: остаток всего | H6: средневзвешенные процентные ставки
B7: А | C7: Б | D7: В | E7: Г | F7: Д | G7: Е | H7: Ж
A8: 1 | B8: Физические лица (льготные кредиты) | C8: =SUM(C10:C14) -> 1419345990 | D8: =IFERROR(((C10*D10)/C8)+((C11*D11)/C8)+((C12*D12)/C8)+((C13*D13)/C8)+((C14*D14)/C8),0) -> 0.12218275 | E8: =SUM(E10:E14) -> 1419345990 | F8: =IFERROR(((E10*F10)/E8)+((E11*F11)/E8)+((E12*F12)/E8)+((E13*F13)/E8)+((E14*F14)/E8),0) -> 0.12218275 | G8: =SUM(G10:G14) -> 0 | H8: =IFERROR(((G10*H10)/G8)+((G11*H11)/G8)+((G12*H12)/G8)+((G13*H13)/G8)+((G14*H14)/G8),0) -> 0 | J8: =+C8+C16+C24+C33 -> 8539798556 | K8: =+E8+E16+E24+E33 -> 5723274181 | L8: =+G8+G16+G24+G33 -> 2816524375
B9: в том числе | J9: =+'loans type'!C8 -> 8539798556 | K9: =+'loans type'!E8 -> 5723274181 | L9: =+'loans type'!G8 -> 2816524375
A10: 1.1. | B10: ипотечный кредит | C10: =+E10+G10 -> 126837780 | D10: 0.1470376 | E10: 126837780 | F10: 0.1470376 | J10: =+J8-J9 -> 0 | K10: =+K8-K9 -> 0 | L10: =+L8-L9 -> 0
A11: 1.2. | B11: автокредит | C11: =+E11+G11 -> 29174 | D11: 0.16 | E11: 29174 | F11: 0.16
A12: 1.3. | B12: микрозайм (все нецелевые кредиты) | C12: =+E12+G12 -> 244675 | D12: 0.15599469 | E12: 244675 | F12: 0.15599469
A13: 1.4. | B13: потребительские кредиты | C13: =+E13+G13 -> 6500772 | D13: 0.087984683 | E13: 6500772 | F13: 0.087984683
A14: 1.5. | B14: другие кредиты физическим лицам | C14: =+E14+G14 -> 1285733589 | D14: 0.11989643 | E14: 1285733589 | F14: 0.11989643
A16: 2 | B16: Физические лица (коммерческие кредиты) | C16: =SUM(C18:C22) -> 976464757 | D16: =IFERROR(((C18*D18)/C16)+((C19*D19)/C16)+((C20*D20)/C16)+((C21*D21)/C16)+((C22*D22)/C16),0) -> 0.25525122 | E16: =SUM(E18:E22) -> 976464757 | F16: =IFERROR(((E18*F18)/E16)+((E19*F19)/E16)+((E20*F20)/E16)+((E21*F21)/E16)+((E22*F22)/E16),0) -> 0.25525122 | G16: =SUM(G18:G22) -> 0 | H16: =IFERROR(((G18*H18)/G16)+((G19*H19)/G16)+((G20*H20)/G16)+((G21*H21)/G16)+((G22*H22)/G16),0) -> 0
B17: в том числе
A18: 2.1. | B18: ипотечный кредит | C18: =+E18+G18 -> 183289903 | D18: 0.17927133 | E18: 183289903 | F18: 0.17927133
A19: 2.2. | B19: автокредит | C19: =+E19+G19 -> 163308302 | D19: 0.27887114 | E19: 163308302 | F19: 0.27887114
A20: 2.3. | B20: микрозайм (все нецелевые кредиты) | C20: =+E20+G20 -> 298967055 | D20: 0.26226288 | E20: 298967055 | F20: 0.26226288
A21: 2.4. | B21: потребительские кредиты | C21: =+E21+G21 -> 328470837 | D21: 0.27964001 | E21: 328470837 | F21: 0.27964001
A22: 2.5. | B22: другие кредиты физическим лицам | C22: =+E22+G22 -> 2428660 | D22: 0.23950416 | E22: 2428660 | F22: 0.23950416
A24: 3 | B24: Юридические лица (льготные кредиты) | C24: =SUM(C26:C31) -> 4434005893 | D24: =IFERROR(((C26*D26)/C24)+((C27*D27)/C24)+((C28*D28)/C24)+((C29*D29)/C24)+((C30*D30)/C24)+((C31*D31)/C24),0) -> 0.10145629 | E24: =SUM(E26:E31) -> 1617481518 | F24: =IFERROR(((E26*F26)/E24)+((E27*F27)/E24)+((E28*F28)/E24)+((E29*F29)/E24)+((E30*F30)/E24)+((E31*F31)/E24),0) -> 0.11360976 | G24: =SUM(G26:G31) -> 2816524375 | H24: =IFERROR(((G26*H26)/G24)+((G27*H27)/G24)+((G28*H28)/G24)+((G29*H29)/G24)+((G30*H30)/G24)+((G31*H31)/G24),0) -> 0.09461774
B25: в том числе
A26: 3.1. | B26: микрокредит | C26: =+E26+G26 -> 726831258 | D26: 0.13327878 | E26: 725606060 | F26: 0.13339318 | G26: 1225198 | H26: 0.065530408
A27: 3.2. | B27: синдицированные кредит | C27: =+E27+G27 -> 0
A28: 3.3. | B28: лизинг | C28: =+E28+G28 -> 9105574 | D28: 0.10200005 | E28: 421716 | F28: 0.14318452 | G28: 8683858 | H28: 0.1
A29: 3.4. | B29: факторинг | C29: =+E29+G29 -> 19292739 | D29: 0.056308359 | E29: 19292739 | F29: 0.056308359
A30: 3.5. | B30: межбанковский кредит | C30: =+E30+G30 -> 0
A31: 3.6. | B31: другие кредиты юридическим лицам | C31: =+E31+G31 -> 3678776322 | D31: 0.095404408 | E31: 872161003 | F31: 0.098403929 | G31: 2806615319 | H31: 0.094613785
A33: 4 | B33: Юридические лица (коммерческие кредиты) | C33: =SUM(C35:C40) -> 1709981916 | D33: =IFERROR(((C35*D35)/C33)+((C36*D36)/C33)+((C37*D37)/C33)+((C38*D38)/C33)+((C39*D39)/C33)+((C40*D40)/C33),0) -> 0.2322271 | E33: =SUM(E35:E40) -> 1709981916 | F33: =IFERROR(((E35*F35)/E33)+((E36*F36)/E33)+((E37*F37)/E33)+((E38*F38)/E33)+((E39*F39)/E33)+((E40*F40)/E33),0) -> 0.2322271 | G33: =SUM(G35:G40) -> 0 | H33: =IFERROR(((G35*H35)/G33)+((G36*H36)/G33)+((G37*H37)/G33)+((G38*H38)/G33)+((G39*H39)/G33)+((G40*H40)/G33),0) -> 0
B34: в том числе
A35: 4.1. | B35: микрокредит | C35: =+E35+G35 -> 172984852 | D35: 0.25718162 | E35: 172984852 | F35: 0.25718162
A36: 4.2. | B36: синдицированные кредит | C36: =+E36+G36 -> 0
A37: 4.3. | B37: лизинг | C37: =+E37+G37 -> 2550632 | D37: 0.19534902 | E37: 2550632 | F37: 0.19534902
A38: 4.4. | B38: факторинг | C38: =+E38+G38 -> 0
A39: 4.5. | B39: межбанковский кредит | C39: =+E39+G39 -> 0
A40: 4.6. | B40: другие кредиты юридическим лицам | C40: =+E40+G40 -> 1534446432 | D40: 0.22947517 | E40: 1534446432 | F40: 0.22947517
B43: Подпись Председателя правления:
B45: Подпись Главного Бухгалтера:
B47: Всего | C47: =+C8+C16+C24+C33 -> 8539798556 | E47: =+E8+E16+E24+E33 -> 5723274181 | G47: =+G8+G16+G24+G33 -> 2816524375
C48: =+C50+C54 -> 8539798556 | E48: =+E9+E17+E25+E34 -> 0 | G48: =+G50+G54 -> 2816524375
B50: Физлица | C50: =+'Asset Classification'!C12 -> 2395810747 | G50: =+'Asset Classification'!D12 -> 0
C51: =C8+C16 -> 2395810747 | G51: =G8+G16 -> 0
C52: =+C50-C51 -> 0 | G52: =+G50-G51 -> 0
B54: Юрзлица | C54: =+'Asset Classification'!C30-'Asset Classification'!C12 -> 6143987809 | G54: =+'Asset Classification'!D30-'Asset Classification'!D12 -> 2816524375
C55: =C24+C33 -> 6143987809 | G55: =G24+G33 -> 2816524375
C56: =+C54-C55 -> 0 | G56: =+G54-G55 -> 0

Sheet loans type
Z1: Таблица-20 А
A2: Информация о структуре кредитного портфеля
B3: =+'Asset quality'!B3 -> АКБ "Микрокредитбанк" | V3: =+'Asset quality'!P3 -> 44196 | Z3: тыс. сум
A4: № | B4: Виды кредитования | C4: всего | I4: Сроки | N4: Категория качества | S4: Резерв на возможные потери | Y4: Списанные на внебаланс | Z4: Реструктуризи-рованные кредиты
I5: до 1 года | J5: От 1 до 5 лет | K5: От 5 до 10 лет | L5: От 10 до 15 лет | M5: Свыше 15 лет | S5: итого | T5: по категориям качества
C6: Остаток | D6: средневзвешенные % ставки | E6: в нацвалюте | F6: средневзвешенные % ставки | G6: в инвалюте | H6: средневзвешенные % ставки | N6: I | O6: II | P6: III | Q6: IV | R6: V | T6: I | U6: II | V6: III | W6: IV | X6: V | AB6: I | AC6: II | AD6: III | AE6: IV | AF6: V
B7: А | C7: Б | D7: В | E7: Г | F7: Д | G7: Е | H7: Ж | I7: З | J7: И | K7: К | L7: Л | M7: М | N7: Н | O7: О | P7: П | Q7: Р | R7: С | S7: Т | T7: У | U7: Ф | V7: Х | W7: Ц | X7: Ч | Y7: Ш | Z7: Щ
B8: ВСЕГО | C8: =+C9+C25 -> 8539798556 | D8: =IFERROR(((C9*D9)/C8)+((C25*D25)/C8),0) -> 0.14868579 | E8: =+E9+E25 -> 5723274181 | F8: =IFERROR(((E9*F9)/E8)+((E25*F25)/E8),0) -> 0.17695209 | G8: =+G9+G25 -> 2816524375 | H8: =IFERROR(((G9*H9)/G8)+((G25*H25)/G8),0) -> 0.09461774 | I8: =+I9+I25 -> 827187330 | J8: =+J9+J25 -> 6518440927 | K8: =+K9+K25 -> 793591060 | L8: =+L9+L25 -> 314564695 | M8: =+M9+M25 -> 86014544 | N8: =+N9+N25 -> 6912201758 | O8: =+O9+O25 -> 1540989857 | P8: =+P9+P25 -> 34473291 | ... Z8: =+Z9+Z25 -> 0 | AA8: =+'Loans Receivable'!C92 -> 8539798556 | AB8: =+'Asset Classification'!G30 -> 0 | AC8: =+'Asset Classification'!K30 -> 154544191 | AD8: =+'Asset Classification'!O50 -> 8618322 | AE8: =+'Asset Classification'!S50 -> 18017013 | AF8: =+'Asset Classification'!W50 -> 16214626
A9: I | B9: Физические лица | C9: =+C11+C16+C21+C22+C24 -> 2395810747 | D9: =IFERROR(((C11*D11)/C9)+((C16*D16)/C9)+((C21*D21)/C9)+((C22*D22)/C9)+((C24*D24)/C9),0) -> 0.17642037 | E9: =+E11+E16+E21+E22+E24 -> 2395810747 | F9: =IFERROR(((E11*F11)/E9)+((E16*F16)/E9)+((E21*F21)/E9)+((E22*F22)/E9)+((E24*F24)/E9),0) -> 0.17642037 | G9: =+G11+G16+G21+G22+G24 -> 0 | H9: =IFERROR(((G11*H11)/G9)+((G16*H16)/G9)+((G21*H21)/G9)+((G22*H22)/G9)+((G24*H24)/G9),0) -> 0 | I9: =+I11+I16+I21+I22+I24 -> 157303369 | J9: =+J11+J16+J21+J22+J24 -> 1927995043 | K9: =+K11+K16+K21+K22+K24 -> 47824663 | L9: =+L11+L16+L21+L22+L24 -> 176673128 | M9: =+M11+M16+M21+M22+M24 -> 86014544 | N9: =+N11+N16+N21+N22+N24 -> 1988169241 | O9: =+O11+O16+O21+O22+O24 -> 377969015 | P9: =+P11+P16+P21+P22+P24 -> 22359606 | ... Z9: =+Z11+Z16+Z21+Z22+Z24 -> 0 | AA9: =+'Loans Receivable'!C80 -> 2395810747 | AB9: =+'Asset Classification'!E30 -> 6912201758 | AC9: =+'Asset Classification'!I30 -> 1540989857 | AD9: =+'Asset Classification'!M30 -> 34473291 | AE9: =+'Asset Classification'!Q30 -> 35919024 | AF9: =+'Asset Classification'!U30 -> 16214626
B10: в том числе | AB10: =+N8-AB9 -> 0 | AC10: =+O8-AC9 -> 0 | AD10: =+P8-AD9 -> 0 | AE10: =+Q8-AE9 -> 0 | AF10: =+R8-AF9 -> 0
A11: 1 | B11: Ипотечные кредиты (льготные) в том числе: | C11: =SUM(C12:C15) -> 126837780 | D11: =IFERROR(((C12*D12)/C11)+((C13*D13)/C11)+((C14*D14)/C11)+((C15*D15)/C11),0) -> 0.14705791 | E11: =SUM(E12:E15) -> 126837780 | F11: =IFERROR(((E12*F12)/E11)+((E13*F13)/E11)+((E14*F14)/E11)+((E15*F15)/E11),0) -> 0.14705791 | G11: =SUM(G12:G15) -> 0 | H11: =IFERROR(((G12*H12)/G11)+((G13*H13)/G11)+((G14*H14)/G11)+((G15*H15)/G11),0) -> 0 | I11: =SUM(I12:I15) -> 0 | J11: =SUM(J12:J15) -> 0 | K11: =SUM(K12:K15) -> 20400324 | L11: =SUM(L12:L15) -> 88191825 | M11: =SUM(M12:M15) -> 18245631 | N11: =SUM(N12:N15) -> 103657558 | O11: =SUM(O12:O15) -> 19124365 | P11: =SUM(P12:P15) -> 2481663 | ... Z11: =SUM(Z12:Z15) -> 0 | AA11: =+'loans_av rate'!C10 -> 126837780 | AB11: =+'loans_av rate'!E10 -> 126837780 | AC11: =+'loans_av rate'!G10 -> 0
A12: 1.1. | B12: на приобретение недвижимого имущества | C12: =+E12+G12 -> 126837780 | D12: 0.14705791 | E12: 126837780 | F12: 0.14705791 | I12: 0 | J12: 0 | K12: 20400324 | L12: 88191825 | M12: 18245631 | N12: 103657558 | O12: 19124365 | P12: 2481663 | Q12: 924273 | R12: 649921 | S12: =SUM(T12:X12) -> 3689866 | U12: 1957393 | V12: 620416 | W12: 462136 | X12: 649921
A13: 1.2. | B13: на ремонт недвижимого имущества | C13: =+E13+G13 -> 0 | K13: 0 | S13: =SUM(T13:X13) -> 0
A14: 1.3. | B14: на реконструкцию недвижимого имущества | C14: =+E14+G14 -> 0 | S14: =SUM(T14:X14) -> 0
A15: 1.4. | B15: на строительство недвижимого имущества | C15: =+E15+G15 -> 0 | S15: =SUM(T15:X15) -> 0
A16: 2 | B16: Ипотечные кредиты (коммерческие) в том числе: | C16: =SUM(C17:C20) -> 183289903 | D16: =IFERROR(((C17*D17)/C16)+((C18*D18)/C16)+((C19*D19)/C16)+((C20*D20)/C16),0) -> 0.17929228 | E16: =SUM(E17:E20) -> 183289903 | F16: =IFERROR(((E17*F17)/E16)+((E18*F18)/E16)+((E19*F19)/E16)+((E20*F20)/E16),0) -> 0.17929228 | G16: =SUM(G17:G20) -> 0 | H16: =IFERROR(((G17*H17)/G16)+((G18*H18)/G16)+((G19*H19)/G16)+((G20*H20)/G16),0) -> 0 | I16: =SUM(I17:I20) -> 0 | J16: =SUM(J17:J20) -> 250549 | K16: =SUM(K17:K20) -> 26830371 | L16: =SUM(L17:L20) -> 88440070 | M16: =SUM(M17:M20) -> 67768913 | N16: =SUM(N17:N20) -> 148882813 | O16: =SUM(O17:O20) -> 30374795 | P16: =SUM(P17:P20) -> 3812241 | ... Z16: =SUM(Z17:Z20) -> 0 | AA16: =+'loans_av rate'!C18 -> 183289903 | AB16: =+'loans_av rate'!E18 -> 183289903 | AC16: =+'loans_av rate'!G18 -> 0
A17: 2.1. | B17: на приобретение недвижимого имущества | C17: =+E17+G17 -> 183289903 | D17: 0.17929228 | E17: 183289903 | F17: 0.17929228 | I17: 0 | J17: 250549 | K17: 26830371 | L17: 88440070 | M17: 67768913 | N17: 148882813 | O17: 30374795 | P17: 3812241 | Q17: 220054 | R17: 0 | S17: =SUM(T17:X17) -> 4100567 | T17: 0 | U17: 0 | V17: 3037480 | W17: 953060 | X17: 110027
A18: 2.2. | B18: на ремонт недвижимого имущества | C18: =+E18+G18 -> 0 | S18: =SUM(T18:X18) -> 0
A19: 2.3. | B19: на реконструкцию недвижимого имущества | C19: =+E19+G19 -> 0 | S19: =SUM(T19:X19) -> 0
A20: 2.4. | B20: на строительство недвижимого имущества | C20: =+E20+G20 -> 0 | S20: =SUM(T20:X20) -> 0
A21: 3 | B21: микрозайм (все нецелевые кредиты) | C21: =+E21+G21 -> 299211730 | D21: 0.26217598 | E21: 299211730 | F21: 0.26217598 | I21: 142720327 | J21: 156491403 | K21: 0 | L21: 0 | M21: 0 | N21: 281822580 | O21: 16077335 | P21: 359254 | Q21: 828496 | R21: 124065 | S21: =SUM(T21:X21) -> 2240961 | T21: 0 | U21: 1612834 | V21: 89814 | W21: 414248 | X21: 124065 | AA21: =+'loans_av rate'!C12+'loans_av rate'!C20 -> 299211730 | AB21: =+'loans_av rate'!E12+'loans_av rate'!E20 -> 299211730 | AC21: =+'loans_av rate'!G12+'loans_av rate'!G20 -> 0
A22: 4 | B22: потребительские кредиты | C22: =+E22+G22 -> 498309085 | D22: 0.27688075 | E22: 498309085 | F22: 0.27688075 | I22: 10713016 | J22: 487596069 | K22: 0 | L22: 0 | M22: 0 | N22: 460560108 | O22: 36022993 | P22: 449998 | Q22: 1056703 | R22: 219283 | S22: =SUM(T22:X22) -> 4462656 | T22: 0 | U22: 3602522 | V22: 112499 | W22: 528352 | X22: 219283 | AA22: =+'loans_av rate'!C11+'loans_av rate'!C13+'loans_av rate'!C19+'loans_av rate'!C21 -> 498309085 | AB22: =+'loans_av rate'!E11+'loans_av rate'!E13+'loans_av rate'!E19+'loans_av rate'!E21 -> 498309085
A23: 4.1. | B23: из них на приобретения автомобиля | C23: =+E23+G23 -> 163337476 | E23: 163337476 | J23: 163337476 | N23: 163337476 | O23: 0 | P23: 0 | Q23: 0 | R23: 0 | S23: =SUM(T23:X23) -> 0 | AA23: =+'loans_av rate'!C11+'loans_av rate'!C19 -> 163337476 | AB23: =+'loans_av rate'!E11+'loans_av rate'!E19 -> 163337476 | AC23: =+'loans_av rate'!G11+'loans_av rate'!G19 -> 0
A24: 5 | B24: другие кредиты физическим лицам | C24: =+E24+G24 -> 1288162249 | D24: 0.12012193 | E24: 1288162249 | F24: 0.12012193 | I24: 3870026 | J24: 1283657022 | K24: 593968 | L24: 41233 | M24: 0 | N24: 993246182 | O24: 276369527 | P24: 15256450 | Q24: 2032226 | R24: 1257864 | S24: =SUM(T24:X24) -> 33693932 | T24: 0 | U24: 30643323 | V24: 1729692 | W24: 173080 | X24: 1147837 | AA24: =+'loans_av rate'!C14+'loans_av rate'!C22 -> 1288162249 | AB24: =+'loans_av rate'!E14+'loans_av rate'!E22 -> 1288162249
A25: II | B25: Юридические лица | C25: =+C26 -> 6143987809 | D25: =IFERROR(((C27*D27)/C25)+((C28*D28)/C25)+((C29*D29)/C25)+((C30*D30)/C25)+((C31*D31)/C25)+((C32*D32)/C25),0) -> 0.13787086 | E25: =+E26 -> 3327463434 | F25: =IFERROR(((E27*F27)/E25)+((E28*F28)/E25)+((E29*F29)/E25)+((E30*F30)/E25)+((E31*F31)/E25)+((E32*F32)/E25),0) -> 0.17733493 | G25: =+G26 -> 2816524375 | H25: =IFERROR(((G27*H27)/G25)+((G28*H28)/G25)+((G29*H29)/G25)+((G30*H30)/G25)+((G31*H31)/G25)+((G32*H32)/G25),0) -> 0.09461774 | I25: =+I26 -> 669883961 | J25: =+J26 -> 4590445884 | K25: =+K26 -> 745766397 | L25: =+L26 -> 137891567 | M25: =+M26 -> 0 | N25: =+N26 -> 4924032517 | O25: =+O26 -> 1163020842 | P25: =+P26 -> 12113685 | ... Z25: =+Z26 -> 0 | AA25: =+'loans_av rate'!C24+'loans_av rate'!C33 -> 6143987809 | AB25: =+'loans_av rate'!E24+'loans_av rate'!E33 -> 3327463434 | AC25: =+'loans_av rate'!G24+'loans_av rate'!G33 -> 2816524375
B26: в том числе по видам кредитования | C26: =SUM(C27:C32) -> 6143987809 | D26: =IFERROR(((C28*D28)/C26)+((C29*D29)/C26)+((C30*D30)/C26)+((C31*D31)/C26)+((C32*D32)/C26),0) -> 0.11486305 | E26: =SUM(E27:E32) -> 3327463434 | F26: =IFERROR(((E28*F28)/E26)+((E29*F29)/E26)+((E30*F30)/E26)+((E31*F31)/E26)+((E32*F32)/E26),0) -> 0.13487633 | G26: =SUM(G27:G32) -> 2816524375 | H26: =IFERROR(((G28*H28)/G26)+((G29*H29)/G26)+((G30*H30)/G26)+((G31*H31)/G26)+((G32*H32)/G26),0) -> 0.094589234 | I26: =SUM(I27:I32) -> 669883961 | J26: =SUM(J27:J32) -> 4590445884 | K26: =SUM(K27:K32) -> 745766397 | L26: =SUM(L27:L32) -> 137891567 | M26: =SUM(M27:M32) -> 0 | N26: =SUM(N27:N32) -> 4924032517 | O26: =SUM(O27:O32) -> 1163020842 | P26: =SUM(P27:P32) -> 12113685 | ... Z26: =SUM(Z27:Z32) -> 0
A27: 1 | B27: микрокредит | C27: =+E27+G27 -> 899816110 | D27: 0.15709844 | E27: 898590912 | F27: 0.15722329 | G27: 1225198 | H27: 0.065530408 | I27: 53115555 | J27: 845180017 | K27: 150038 | L27: 1370500 | M27: 0 | N27: 750456499 | O27: 142457435 | P27: 231284 | Q27: 3373385 | R27: 3297507 | S27: =SUM(T27:X27) -> 19291026 | T27: 0 | U27: 14249006 | V27: 57821 | W27: 1686692 | X27: 3297507 | AA27: =+'loans_av rate'!C26+'loans_av rate'!C35 -> 899816110 | AB27: =+'loans_av rate'!E26+'loans_av rate'!E35 -> 898590912 | AC27: =+'loans_av rate'!G26+'loans_av rate'!G35 -> 1225198
A28: 2 | B28: синдицированные кредит | C28: =+E28+G28 -> 0 | I28: 0 | J28: 0 | K28: 0 | L28: 0 | M28: 0 | N28: 0 | O28: 0 | P28: 0 | Q28: 0 | R28: 0 | S28: =SUM(T28:X28) -> 0 | AA28: =+'loans_av rate'!C27+'loans_av rate'!C36 -> 0 | AB28: =+'loans_av rate'!E27+'loans_av rate'!E36 -> 0 | AC28: =+'loans_av rate'!G27+'loans_av rate'!G36 -> 0
A29: 3 | B29: лизинг | C29: =+E29+G29 -> 11656206 | D29: 0.12242684 | E29: 2972348 | F29: 0.18794794 | G29: 8683858 | H29: 0.1 | I29: 0 | J29: 11652936 | K29: 3270 | L29: 0 | M29: 0 | N29: 10637682 | O29: 397894 | P29: 293097 | Q29: 0 | R29: 327533 | S29: =SUM(T29:X29) -> 440596 | T29: 0 | U29: 39789 | V29: 73274 | X29: 327533 | AA29: =+'loans_av rate'!C28+'loans_av rate'!C37 -> 11656206 | AB29: =+'loans_av rate'!E28+'loans_av rate'!E37 -> 2972348 | AC29: =+'loans_av rate'!G28+'loans_av rate'!G37 -> 8683858
A30: 4 | B30: факторинг | C30: =+E30+G30 -> 19292739 | D30: 0.056308359 | E30: 19292739 | F30: 0.056308359 | I30: 19292739 | J30: 0 | K30: 0 | L30: 0 | M30: 0 | N30: 18542848 | O30: 249563 | P30: 0 | Q30: 500328 | R30: 0 | S30: =SUM(T30:X30) -> 307664 | U30: 0 | V30: 0 | W30: 307664 | X30: 0 | AA30: =+'loans_av rate'!C29+'loans_av rate'!C38 -> 19292739 | AB30: =+'loans_av rate'!E29+'loans_av rate'!E38 -> 19292739 | AC30: =+'loans_av rate'!G29+'loans_av rate'!G38 -> 0
A31: 5 | B31: межбанковский кредит | C31: =+E31+G31 -> 0 | I31: 0 | J31: 0 | K31: 0 | L31: 0 | M31: 0 | S31: =SUM(T31:X31) -> 0 | AA31: =+'loans_av rate'!C30+'loans_av rate'!C39 -> 0 | AB31: =+'loans_av rate'!E30+'loans_av rate'!E39 -> 0 | AC31: =+'loans_av rate'!G30+'loans_av rate'!G39 -> 0
A32: 6 | B32: другие виды кредитования | C32: =+E32+G32 -> 5213222754 | D32: 0.1348885 | E32: 2406607435 | F32: 0.18580142 | G32: 2806615319 | H32: 0.094613785 | I32: 597475667 | J32: 3733612931 | K32: 745613089 | L32: 136521067 | M32: 0 | N32: 4144395488 | O32: 1019915950 | P32: 11589304 | Q32: 26983559 | R32: 10338453 | S32: =SUM(T32:X32) -> 129166884 | T32: 0 | U32: 102439324 | V32: 2897326 | W32: 13491781 | X32: 10338453 | AA32: =+'loans_av rate'!C31+'loans_av rate'!C40 -> 5213222754 | AB32: =+'loans_av rate'!E31+'loans_av rate'!E40 -> 2406607435 | AC32: =+'loans_av rate'!G31+'loans_av rate'!G40 -> 2806615319
B33: в том числе по цели кредитования | C33: =SUM(C34:C39) -> 6143987809 | D33: =IFERROR(((C35*D35)/C33)+((C36*D36)/C33)+((C37*D37)/C33)+((C38*D38)/C33)+((C39*D39)/C33),0) -> 0.12737617 | E33: =SUM(E34:E39) -> 3327463434 | F33: =IFERROR(((E35*F35)/E33)+((E36*F36)/E33)+((E37*F37)/E33)+((E38*F38)/E33)+((E39*F39)/E33),0) -> 0.14966015 | G33: =SUM(G34:G39) -> 2816524375 | H33: =IFERROR(((G35*H35)/G33)+((G36*H36)/G33)+((G37*H37)/G33)+((G38*H38)/G33)+((G39*H39)/G33),0) -> 0.097783782 | I33: =SUM(I34:I39) -> 669883961 | J33: =SUM(J34:J39) -> 4590445884 | K33: =SUM(K34:K39) -> 745766397 | L33: =SUM(L34:L39) -> 137891567 | M33: =SUM(M34:M39) -> 0 | N33: =SUM(N34:N39) -> 4924032517 | O33: =SUM(O34:O39) -> 1163020842 | P33: =SUM(P34:P39) -> 12113685 | ... Z33: =SUM(Z34:Z39) -> 0
A34: 1 | B34: кредиты, выданные на формирование стартового капитала | C34: =+E34+G34 -> 817291404 | D34: 0.11003156 | E34: 817291404 | F34: 0 | G34: 0 | H34: 0 | I34: 920469 | J34: 705175762 | K34: 1368756 | L34: 109826417 | M34: 0 | N34: 681377825 | O34: 129815919 | P34: 593540 | Q34: 4417430 | R34: 1086690 | S34: =SUM(T34:X34) -> 19003878 | T34: 0 | U34: 16445284 | V34: 201494 | W34: 148385 | X34: 2208715
A35: 2 | B35: кредиты на пополнение оборотных средств | C35: =+E35+G35 -> 924996782 | D35: 0.19527214 | E35: 503716457 | F35: 0.24548083 | G35: 421280325 | H35: 0.10445052 | I35: 325363091 | J35: 599633691 | K35: 0 | L35: 0 | M35: 0 | N35: 750468065 | O35: 147024244 | P35: 1073423 | Q35: 22133472 | R35: 4297578 | S35: =SUM(T35:X35) -> 41749967 | T35: 0 | U35: 30835094 | V35: 1102424 | W35: 268356 | X35: 9544093
A36: 3 | B36: кредиты, выданные на приобретение, модернизацию или приватизацию основных средств | C36: =+E36+G36 -> 2095612043 | D36: 0.12499898 | E36: 714443996 | F36: 0.1760901 | G36: 1381168047 | H36: 0.098262236 | I36: 24815483 | J36: 1815458544 | K36: 255338016 | L36: 0 | M36: 0 | N36: 1658592286 | O36: 426643687 | P36: 1859828 | Q36: 2861623 | R36: 5654619 | S36: =SUM(T36:X36) -> 53069991 | T36: 0 | U36: 50409854 | V36: 764369 | W36: 464957 | X36: 1430811
A37: 4 | B37: кредиты, выданные на покрытие затрат, связанных с импортом и экспортом продукции | C37: =+E37+G37 -> 0 | D37: 0 | E37: 0 | F37: 0 | G37: 0 | H37: 0 | I37: 0 | S37: =SUM(T37:X37) -> 0 | T37: 0 | U37: 0 | V37: 0 | W37: 0 | X37: 0
A38: 5 | B38: кредиты, выданные по отдельным решениям правительства | C38: =+E38+G38 -> 9900000 | D38: 0.16 | E38: 9900000 | F38: 0.16 | G38: 0 | H38: 0 | I38: 0 | J38: 0 | K38: 9900000 | L38: 0 | M38: 0 | N38: 0 | O38: 9900000 | P38: 0 | Q38: 0 | R38: 0 | S38: =SUM(T38:X38) -> 990000 | T38: 0 | U38: 990000 | V38: 0 | W38: 0 | X38: 0
A39: 6 | B39: другие цели кредитования | C39: =+E39+G39 -> 2296187580 | D39: 0.14739133 | E39: 1282111577 | F39: 0.19260839 | G39: 1014076003 | H39: 0.094362547 | I39: 318784918 | J39: 1470177887 | K39: 479159625 | L39: 28065150 | M39: 0 | N39: 1833594341 | O39: 449636992 | P39: 8586894 | Q39: 1444747 | R39: 2924606 | S39: =SUM(T39:X39) -> 34392334 | T39: 0 | U39: 18047887 | V39: 960134 | W39: 14604439 | X39: 779874
B41: Подпись Председателя правления:
B43: Подпись Главного Бухгалтера:

Sheet Bank Capital Calc (2)
A1: РАСЧЕТ РЕГУЛЯТИВНОГО КАПИТАЛА БАНКА | C1: Таблица-5
B3: =#REF! -> #REF! | C3: =+#REF! -> #REF!
A4: № | B4: Характеристики | C4: Итого капитала
A5: I. | B5: КАПИТАЛ УРОВНЯ 1
A6: 1 | B6: ОСНОВНОЙ КАПИТАЛ УРОВНЯ 1
A7: 1.1. | B7: Обыкновенные Акции, чистые | C7: Формула
A8: a | B8: Полностью оплаченные обыкновенные акции
A9: б | B9: Минус: Обратно Выкупленные обыкновенные акции
A10: 1.2. | B10: Добавленный капитал - Обыкновенные | C10: 0
A11: 1.3. | B11: Нераспределенная прибыль (убыток), в том числе капитальные резервы | C11: Формула
A12: а | B12: Капитальные резервы
A13: б | B13: Нераспределенная прибыль
A14: в | B14: Убыток за предыдущие периоды
A15: г | B15: Убыток за текущий год
A16: 1.4. | B16: Интерес меньшинства в консолидированных дочерних компаниях (согласно МБС)
A17: 1.5. | B17: Резерв на девальвацию
B18: Итого основного капитала уровня I до вычетов | C18: Формула
A19: 1.6. | B19: Вычеты из суммы основного капитала уровня I | C19: Формула
A20: а | B20: Нематериальные активы
A21: б | B21: Все инвестиции в капитал неконсолидированных хозяйствующих субъектов, в том числе в долговые обязательства, которые образуют капитал хозяйствующих субъектов
A22: в | B22: Инвестиции в капитал других банков
A23: I | B23: ВСЕГО СКОРРЕКТИРОВАННЫЙ ОСНОВНОЙ КАПИТАЛ УРОВНЯ I | C23: Формула
A24: 2 | B24: ДОБАВЛЕННЫЙ КАПИТАЛ УРОВНЯ 1
A25: 2.1. | B25: Некумулятивные бессрочные привилегированные акции | C25: =+C26+C27 -> 0
A26: а | B26: Полностью оплаченные привилегированные акции
A27: б | B27: Минус: Обратно Выкупленные привилегированные акции
A28: 2.2. | B28: Добавленный капитал - Привилегированные | C28: 0
A29: 2.3. | B29: Интерес меньшинства в консолидированных дочерних компаниях | C29: 0
A30: 2.4. | B30: Доля участия дочерних предприятий (выпущенные дочерними предприятиями и находящиеся во владении третьих лиц инструменты, приравненные к капиталу) | C30: 0
A31: II | B31: ВСЕГО ДОБАВЛЕННЫЙ КАПИТАЛ УРОВНЯ I | C31: =+C25+C28+C29+C30 -> 0
A32: III | B32: ВСЕГО СКОРРЕКТИРОВАННЫЙ КАПИТАЛ УРОВНЯ I | C32: Формула
B33: КАПИТАЛ УРОВНЯ II
A34: 3.1. | B34: Прибыль за текущий год
A35: 3.2. | B35: Резервы, создаваемые на стандартные кредиты (активы), в размере не более 1.25% от общей суммы активов, взвешенных с учетом риска | C35: =IF(#REF!<(C43*1.25%),#REF!,(C43*1.25%)) -> #REF!
A36: 3.3. | B36: Излишки оценочной стоимости прироста над первоначальной стоимостью
A37: 3.4. | B37: Другие инструменты капитала (не более 1/3 части капитала 1 уровня после вычетов)
A38: 3.5. | B38: Субординированный долг
A39: 3.6. | B39: Вычеты превышения Капитала Уровня II над Капиталом Уровня I | C39: Формула
B40: Итого капитала Уровня II | C40: =SUM(C34:C38) -> #REF!
A41: IV | B41: СКОРРЕКТИРОВАННЫЙ КАПИТАЛ УРОВНЯ II | C41: Формула
A42: V | B42: ВСЕГО РЕГУЛЯТИВНЫЙ КАПИТАЛ | C42: Формула
A43: VI | B43: ОБЩАЯ СУММА АКТИВОВ ВЗВЕШЕННЫХ С УЧЕТОМ РИСКА | C43: =+C44+C45+C46 -> #REF!
A44: а | B44: Сумма балансовых и забалансовых активов, взвешенных с учетом риска | C44: =+#REF! -> #REF!
A45: б | B45: Операционный риск | C45: =+#REF! -> #REF!
A46: в | B46: Рыночный риск | C46: =+#REF! -> #REF! | E46: =+#REF! -> #REF!
A47: VII | B47: КОЭФФИЦИЕНТ ОСНОВНОГО КАПИТАЛА УРОВНЯ I (I/VI) | C47: Формула
A48: VIII | B48: КОЭФФИЦИЕНТ КАПИТАЛА УРОВНЯ I (III/VI) | C48: Формула
A49: IX | B49: КОЭФФИЦИЕНТ ОБЩЕЙ СУММЫ КАПИТАЛА, ОСНОВАННОГО НА РИСКЕ (V/VI) | C49: Формула
A50: X | B50: Активы для расчета левеража | C50: Формула
A51: а | B51: Общие активы | C51: =+#REF! -> #REF!
A52: б | B52: Забалансовые инструменты | C52: =SUM(#REF!) -> #REF! | D52: =+#REF! -> #REF!
A53: в | B53: Деривативные (производные) инструменты | C53: =SUM(#REF!) -> #REF!
A54: г | B54: Минус: Строка 1.6. Итого вычетов из суммы основного капитала Уровня 1 | C54: =+C19 -> Формула
A55: XI | B55: Коэффициент левеража | C55: Формула
B57: Подпись Председателя правления:
B59: Подпись Главного Бухгалтера:

Sheet Deposits_av rate
A1: ДАННЫЕ О СРЕДНЕВЗВЕШЕННЫХ ПРОЦЕНТНЫХ СТАВКАХ ПО ПРИВЛЕЧЕННЫМ ДЕПОЗИТАМ БАНКОВ | N1: Таблица-21
B2: =+'Asset quality'!B3 -> АКБ "Микрокредитбанк" | K2: =+'loans_av rate'!F3 -> 44196 | N2: тыс. сум
A3: № | B3: Сроки, погашения средств | C3: Вклады (депозиты) физических лиц | I3: Вклады (депозиты) юридических лиц
C4: общая сумма (тыс. сум) | D4: средневзвешенные процентные ставки | E4: в том числе | I4: общая сумма (тыс. сум) | J4: средневзвешенные процентные ставки | K4: в том числе
E5: в национальный валюте | G5: в иностранной валюте | K5: в национальный валюте | M5: в иностранной валюте
E6: остаток всего | F6: средневзвешенные процентные ставки | G6: остаток всего | H6: средневзвешенные процентные ставки | K6: остаток всего | L6: средневзвешенные процентные ставки | M6: остаток всего | N6: средневзвешенные процентные ставки
B7: А | C7: Б | D7: В | E7: Г | F7: Д | G7: Е | H7: Ж | I7: З | J7: И | K7: К | L7: Л | M7: М | N7: Н
A8: 1 | B8: Бессрочные | C8: =+E8+G8 -> 163360536 | D8: 0.0017811742 | E8: 155044502 | F8: 0.001874339 | G8: 8316034 | H8: 4.4205272e-05 | I8: =+K8+M8 -> 460771917 | J8: 0.027194376 | K8: 391575154 | L8: 0.032702723 | M8: 69196763 | N8: 0 | P8: =+'[8]Bank Liabilities Analysis'!$C$22 -> 624132453 | Q8: =+P8-C8-I8 -> 0
A9: 2 | B9: От 1 до 7 дней | C9: =+E9+G9 -> 30163688 | D9: 0.19116888 | E9: 29218647 | F9: 0.19557209 | G9: 945041 | H9: 0.055031148 | I9: =+K9+M9 -> 203629201 | J9: 0.1100044 | K9: 98860000 | L9: 0.15245499 | M9: 104769201 | N9: 0.07 | P9: =+'[8]Bank Liabilities Analysis'!$E$22 -> 233792889 | Q9: =+P9-C9-I9 -> 0
A10: 3 | B10: От 8 до 30 дней | C10: =+E10+G10 -> 57214611 | D10: 0.20843786 | E10: 54562317 | F10: 0.21609325 | G10: 2652294 | H10: 0.050953241 | I10: =+K10+M10 -> 123797693 | J10: 0.16748262 | K10: 122750002 | L10: 0.16840326 | M10: 1047691 | N10: 0.06 | P10: =+'[8]Bank Liabilities Analysis'!$G$22 -> 181012304 | Q10: =+P10-C10-I10 -> 0
A11: 4 | B11: От 31 до 90 дней | C11: =+E11+G11 -> 112908752 | D11: 0.16066949 | E11: 90550131 | F11: 0.18683588 | G11: 22358621 | H11: 0.054698286 | I11: =+K11+M11 -> 147422106 | J11: 0.148864 | K11: 135897494 | L11: 0.1564992 | M11: 11524612 | N11: 0.06 | P11: =+'[8]Bank Liabilities Analysis'!$I$22 -> 260330858 | Q11: =+P11-C11-I11 -> 0
A12: 5 | B12: От 91 до 180 дней | C12: =+E12+G12 -> 100968787 | D12: 0.18119219 | E12: 74196480 | F12: 0.22815082 | G12: 26772307 | H12: 0.051051568 | I12: =+K12+M12 -> 153561946 | J12: 0.13476903 | K12: 152681885 | L12: 0.13523349 | M12: 880061 | N12: 0.06 | P12: =+'[8]Bank Liabilities Analysis'!$K$22 -> 254530733 | Q12: =+P12-C12-I12 -> 0
A13: 6 | B13: От 181 до 365 дней | C13: =+E13+G13 -> 111359166 | D13: 0.18190388 | E13: 102332684 | F13: 0.19332539 | G13: 9026482 | H13: 0.052418909 | I13: =+K13+M13 -> 399786907 | J13: 0.13907756 | K13: 389938603 | L13: 0.14114981 | M13: 9848304 | N13: 0.059095745 | P13: =+'[8]Bank Liabilities Analysis'!$M$22 -> 511146073 | Q13: =+P13-C13-I13 -> 0
A14: 7 | B14: От 366 до 730 дней | C14: =+E14+G14 -> 20208570 | D14: 0.17334587 | E14: 18936528 | F14: 0.18112196 | G14: 1272042 | H14: 0.05758526 | I14: =+K14+M14 -> 43249999 | J14: 0.19773096 | K14: 43249999 | L14: 0.19908671 | M14: 0 | P14: =+'[8]Bank Liabilities Analysis'!$O$22 -> 63458569 | Q14: =+P14-C14-I14 -> 0
A15: 8 | B15: Свыше 2 лет | C15: =+E15+G15 -> 2174301 | D15: 0.18639352 | E15: 2174301 | F15: 0.18639352 | G15: 0 | H15: 0 | I15: =+K15+M15 -> 252165645 | J15: 0.083776075 | K15: 95011845 | L15: 0.13226097 | M15: 157153800 | N15: 0.054583333 | P15: =+'[8]Bank Liabilities Analysis'!$Q$22 -> 254339946 | Q15: =+P15-C15-I15 -> 0
A16: 9 | B16: Итого (сумма строк 1, 2, 3, 4, 5, 6, 7, 8 ) | C16: =SUM(C8:C15) -> 598358411 | D16: =IFERROR(((C8*D8)/C16)+((C9*D9)/C16)+((C10*D10)/C16)+((C11*D11)/C16)+((C12*D12)/C16)+((C13*D13)/C16)+((C14*D14)/C16)+((C15*D15)/C16),0) -> 0.13133229 | E16: =SUM(E8:E15) -> 527015590 | F16: =IFERROR(((E8*F8)/E16)+((E9*F9)/E16)+((E10*F10)/E16)+((E11*F11)/E16)+((E12*F12)/E16)+((E13*F13)/E16)+((E14*F14)/E16)+((E15*F15)/E16),0) -> 0.14280433 | G16: =SUM(G8:G15) -> 71342821 | H16: =IFERROR(((G8*H8)/G16)+((G9*H9)/G16)+((G10*H10)/G16)+((G11*H11)/G16)+((G12*H12)/G16)+((G13*H13)/G16)+((G14*H14)/G16)+((G15*H15)/G16),0) -> 0.04658735 | I16: =SUM(I8:I15) -> 1784385414 | J16: =IFERROR(((I8*J8)/I16)+((I9*J9)/I16)+((I10*J10)/I16)+((I11*J11)/I16)+((I12*J12)/I16)+((I13*J13)/I16)+((I14*J14)/I16)+((I15*J15)/I16),0) -> 0.10288383 | K16: =SUM(K8:K15) -> 1429964982 | L16: =IFERROR(((K8*L8)/K16)+((K9*L9)/K16)+((K10*L10)/K16)+((K11*L11)/K16)+((K12*L12)/K16)+((K13*L13)/K16)+((K14*L14)/K16)+((K15*L15)/K16),0) -> 0.11656296 | M16: =SUM(M8:M15) -> 354420432 | N16: =IFERROR(((M8*N8)/M16)+((M9*N9)/M16)+((M10*N10)/M16)+((M11*N11)/M16)+((M12*N12)/M16)+((M13*N13)/M16)+((M14*N14)/M16)+((M15*N15)/M16),0) -> 0.048814785 | P16: =+'[8]Bank Liabilities Analysis'!$S$22 -> 2382743825 | Q16: =+P16-C16-I16 -> 0
B19: Подпись Председателя правления:
B21: Подпись Главного Бухгалтера:
B24: Физлица | C24: =+'[8]Deposits by Client'!$C$6+'[8]Deposits by Client'!$C$15 -> 598358411 | G24: =+'[8]Deposits by Client'!$D$6+'[8]Deposits by Client'!$D$15 -> 71342821
C25: =+C16 -> 598358411 | G25: =+G16 -> 71342821
C26: =+C24-C25 -> 0 | G26: =+G24-G25 -> 0
B27: Юрзлица | I27: =+'[8]Deposits by Client'!$C$22-'[8]Deposits by Client'!$C$6-'[8]Deposits by Client'!$C$15 -> 1784385414 | M27: =+'[8]Deposits by Client'!$D$22-'[8]Deposits by Client'!$D$6-'[8]Deposits by Client'!$D$15 -> 354420432
I28: =+I16 -> 1784385414 | M28: =+M16 -> 354420432
I29: =+I27-I28 -> 0 | M29: =+M27-M28 -> 0

Sheet Economic Normatives
A1: РАСЧЕТ ПРУДЕНЦИАЛЬНЫХ НОРМАТИВОВ | I1: Таблица-22
B2: =+'Asset quality'!B3 -> АКБ "Микрокредитбанк" | I2: =+'Asset quality'!P3 -> 44196
A4: № | B4: Наименование экономического норматива | F4: Формула | I4: Фактическое значение | J4: Нормативное значение | K4: Отклонение
B5: A | F5: Б | I5: В | J5: Г | K5: Д
A6: 1 | B6: Показатели достаточности капитала
A7: 1.1 | B7: Коэффициент достаточности капитала | F7: Скорректированная общая капитала, основанного на риске | I7: ='[9]Bank Capital Calc'!$C$48 -> 0.14575899 | J7: Мин | K7: =IF(I7="",0-J8,(IF((I7-J8)>0,"",I7-J8)))
F8: Активы с учетом риска | J8: 0.13
A9: 1.2 | B9: Коэффициент достаточности Капитала Уровня 1 | F9: Капитал Уровня I | I9: ='[9]Bank Capital Calc'!$C$49 -> 0.14577182 | J9: Мин | K9: =IF(I9="",0-J10,(IF((I9-J10)>0,"",I9-J10)))
F10: Активы с учетом риска | J10: 0.1
A11: 1.3 | B11: Коэффициент достаточности основного Капитала Уровня 1 | F11: Основной капитал Уровня I | I11: ='[9]Bank Capital Calc'!$C$50 -> 0.15467294 | J11: Мин | K11: =IF(I11="",0-J12,(IF((I11-J12)>0,"",I11-J12)))
F12: Активы с учетом риска | J12: 0.08
A13: 1.4 | B13: Левераж | F13: Капитал Уровня I | I13: ='[9]Bank Capital Calc'!$C$56 -> 0.14511607 | J13: Мин | K13: =IF(I13="",0-J14,(IF((I13-J14)>0,"",I13-J14)))
F14: Активы + забалансовые инструменты+ деривативные (производные) инструменты - вычеты из суммы основного капитала уровня I | J14: 0.06
A15: 2 | B15: Показатели ликвидности
A16: 2.1 | B16: Коэффициент покрытия ликвидности | E16: Всего | F16: Высоколиквидные активы | I16: =IFERROR('[8]Liquidity Analysis'!$C$21,0) -> 2.3646901 | J16: Мин | K16: =IF(I16="",0-$J$18,(IF((I16-$J$18)>0,"",I16-$J$18)))
E17: в национальной валюте | I17: =IFERROR('[8]Liquidity Analysis'!$D$21,0) -> 1.8285311 | K17: =IF(I17="",0-$J$18,(IF((I17-$J$18)>0,"",I17-$J$18)))
E18: в иностранной валюте | F18: Чистый отток в последующие 30 дней | I18: =IFERROR('[8]Liquidity Analysis'!$E$21,0) -> 3.8786024 | J18: 1 | K18: =IF(I18="",0-$J$18,(IF((I18-$J$18)>0,"",I18-$J$18)))
A19: 2.2 | B19: Норма чистого стабильного финансирования | E19: Всего | F19: Доступная сумма стабильного финансирования | I19: =IFERROR('[8]Liquidity Analysis'!$C$31,0) -> 1.188397 | J19: Мин | K19: =IF(I19="",0-$J$21,(IF((I19-$J$21)>0,"",I19-$J$21)))
E20: в национальной валюте | I20: =IFERROR('[8]Liquidity Analysis'!$D$31,0) -> 1.2444545 | K20: =IF(I20="",0-$J$21,(IF((I20-$J$21)>0,"",I20-$J$21)))
E21: в иностранной валюте | F21: Необходимая сумма стабильного финансирования | I21: =IFERROR('[8]Liquidity Analysis'!$E$31,0) -> 1.0806276 | J21: 1 | K21: =IF(I21="",0-$J$21,(IF((I21-$J$21)>0,"",I21-$J$21)))
A22: 3 | B22: Нормативы по операциям с заемщиками
A23: 3.1 | B23: Максимальный размер риска на одного заемщика или группу взаимосвязанных заемщиков, Обеспеченные активами | F23: Максимальный размер риска на одного заемщика или группу взаимосвязанных заемщиков,Обеспеченные активами | I23: =+' Largest risk'!G8/'[9]Bank Capital Calc'!$C$33 -> 0.28089761 | J23: Макс | K23: =IF(I23="","",IF(I23<0,"ОТР",IF((I23-J24)<0,"",I23-J24))) -> 0.030897615
F24: Капитал Уровня I | J24: 0.25
A25: 3.2 | B25: Максимальный размер риска на один банк или группу взаимосвязанных заемщиков банков по межбанковским кредитам и депозитам | F25: Максимальный размер риска на один банк или группу взаимосвязанных заемщиков банков по межбанковским кредитам и депозитам | I25: 0 | J25: Макс | K25: =IF(I25<0,"ОТР",IF((I25-J26)<0,"",I25-J26))
F26: Капитал Уровня I | J26: 0.25
A27: 3.3 | B27: Максимальный размер риска на одного заемщика или группу взаимосвязанных заемщиков, Необеспеченные активы | F27: Максимальный размер риска на одного заемщика или группу взаимосвязанных заемщиков, Необеспеченные активы | I27: 0 | J27: Макс | K27: =IF(I27<0,"ОТР",IF((I27-J28)<0,"",I27-J28))
F28: Капитал Уровня I | J28: 0.05
A29: 3.4 | B29: Максимальный размер риска для всех крупных активов | F29: Совокупная сумма крупных активов | I29: =IFERROR((+' Largest risk'!G67/'[9]Bank Capital Calc'!$C$33),0) -> 0.50820039 | J29: Макс | K29: =IF(I29="","",IF(I29<0,"ОТР",IF((I29-J30)<0,"",I29-J30)))
F30: Капитал Уровня I | J30: 8
A31: 4 | B31: Нормативы по операциям с ценными бумагами
A32: 4.1 | B32: Максимальный размер инвестиций в ценные бумаги одного эмитента | F32: Инвестиции в негосударственные ценные бумаги одного эмитента | J32: Макс | K32: =IF(I32<0,"ОТР",IF((I32-J33)<0,"",I32-J33))
F33: Капитал Уровня I | J33: 0.15
A34: 4.2 | B34: Максимальный общий размер инвестиций в ценные бумаги для купли- продажи | F34: Общий размер инвестиций в ценные бумаги для купли- продажи | I34: =IFERROR((+(#REF!+#REF!+#REF!+#REF!-#REF!)/'[9]Bank Capital Calc'!$C$33),0) -> 0 | J34: Макс | K34: =IF(I34="","",IF(I34<0,"ОТР",IF((I34-J35)<0,"",I34-J35)))
F35: Капитал Уровня I | J35: 0.25
A36: 4.3 | B36: Максимальный общий размер инвестиций в уставной капитал и другие ценные бумаги всех эмитентов | F36: Общий размер инвестиций в уставной капитал и другие ценные бумаги всех эмитентов | I36: =IFERROR((+(+#REF!-#REF!-#REF!+#REF!+#REF!+#REF!+#REF!-#REF!)/'[9]Bank Capital Calc'!$C$33),0) -> 0 | J36: Макс | K36: =IF(I36="","",IF(I36<0,"ОТР",IF((I36-J37)<0,"",I36-J37)))
F37: Капитал Уровня I | J37: 0.5
A38: 5 | B38: Нормативы показателей по операциям со связанными лицами (инсайдерами)
A39: 5.1 | B39: Сумма выданным активам одному инсайдеру или группе связанных лиц, Обеспеченные активы | F39: Сумма выданным активам одному инсайдеру или группе связанных лиц, Обеспеченный активом | I39: 0 | J39: Макс | K39: =IF(I39="","",IF(I39<0,"ОТР",IF((I39-J40)<0,"",I39-J40)))
F40: Капитал Уровня I | J40: 0.25
A41: 5.2 | B41: Совокупная сумма активов предоставленых банком всем инсайдерам | F41: Совокупная сумма активов выданных инсайдерам | I41: =IFERROR((+'Loans to Affiliated P.'!G64/'[9]Bank Capital Calc'!$C$33),0) -> 0.0019097354 | J41: Макс | K41: =IF(I41="","",IF(I41<0,"ОТР",IF((I41-J42)<0,"",I41-J42)))
F42: Капитал Уровня I | J42: 1
A43: 6 | B43: Нормативный показатель по инвестициям банка в недвижимость
A44: 6.1 | B44: Совокупная сумма всех инвестиций банка в недвижимость | F44: Сумма всех инвестиций банка в недвижимость | I44: 0 | J44: Макс | K44: =IF(I44="","",IF(I44<0,"ОТР",IF((I44-J45)<0,"",I44-J45)))
F45: Капитал Уровня I | J45: 1
D47: Подпись Председателя правления:
D49: Подпись Главного Бухгалтера:

Sheet Miscellaneous
B1: РАЗНАЯ ИНФОРМАЦИЯ | C1: Таблица-23
B2: =+'Asset quality'!B3 -> АКБ "Микрокредитбанк" | C2: тыс. сум
A3: 1. | B3: Численность работников банка, включая административный, филиалы, и представительства банка.
A4: а | B4: Численность работников банка по штатному расписанию | C4: 3442
A5: б | B5: Фактическая численность работников банка | C5: 3015
A6: 2. | B6: Общее количество отделений банка, включая административный, филиалы, и представительства банка.
B7: из них,
A8: а | B8: Количество филиалов | C8: 71
A9: б | B9: Количество мини банков | C9: 31
A10: в | B10: Количество розничных касс вне банка (филиалы) | C10: 23
A11: г | B11: Количество центров банковских услуг | C11: 78
A12: 3. | B12: Клиенская база банка | C12: =+C14+C15+C16 -> 1067634
B13: из них,
A14: а | B14: Физические лица | C14: 833712
A15: б | B15: Индивидуальные предприниматели | C15: 123989
A16: в | B16: Юридические лица | C16: =+C18+C19+C20+C22 -> 109933
B17: в том числе имеющие основной счет в банке
A18: - | B18: Государственные предприятия | C18: 1018
A19: - | B19: Частные товарищества и корпорации | C19: 104141
A20: - | B20: Фермерское хозяйство | C20: 4014
A21: - | B21: Правительство | C21: 0
A22: - | B22: Прочие | C22: 760
A23: 4. | B23: Рейтинг банка | C23: ВВ-
A24: а | B24: Названия рейтинговой компании | C24: Фитч Рейтингс
A25: б | B25: Оценка рейтинга банка | C25: ВВ-
B28: Подпись Председателя правления:
B30: Подпись Главного Бухгалтера:

Sheet ПФУ
A1: Показатели финансовой устойчивости
A2: =+'Asset quality'!B3 -> АКБ "Микрокредитбанк" | B2: тыс. сум | C2: Месяц
A3: Основные показатели | B3: =+'Asset quality'!P3 -> 44196 | K3: Месяц | L3: Актив | M3: Капитал | O3: Всего активы (средний за период) | P3: Совокупный капитал (средний за период)
A4: Регулятивный капитал к активам взвешанных с учетом риска | B4: =IFERROR((B5/B6),0) -> 0.15467294 | J4: 1 января | K4: 1 | L4: 5890272405 | M4: 1625105476
A5: Всего Регулятивный капитал | B5: ='[9]Bank Capital Calc'!$C$43 -> 1738182312 | J5: 1 февраль | K5: 2 | L5: 5780265236 | M5: 1634342354 | N5: 1 | O5: =+(L4+L5)/2 -> 5.8352688e+09 | P5: =+(M4+M5)/2 -> 1629723915
A6: Активы взвешанные с учетом риска | B6: ='[9]Bank Capital Calc'!$C$44 -> 1.1237792e+10 | J6: 1 март | K6: 3 | L6: 5739416696 | M6: 1612958003 | N6: 2 | O6: =+(L4+L5+L6)/3 -> 5.8033181e+09 | P6: =+(M4+M5+M6)/3 -> 1.6241353e+09
A7: Регулятивный капитал 1 - уровня к Активам взвешанных с учетом риска | B7: =IFERROR((B8/B9),0) -> 0.14577182 | J7: 1 апрель | K7: 4 | L7: 6400904753 | M7: 1565343475 | N7: 3 | O7: =+(L4+L7)/2 -> 6145588579 | P7: =+(M4+M7)/2 -> 1.5952245e+09
A8: Регулятивный капитал 1- уровня | B8: ='[9]Bank Capital Calc'!$C$33 -> 1638153454 | J8: 1 май | K8: 5 | L8: 6698313888 | M8: 1612101194 | N8: 4 | O8: =+(+L4+L5+L6+L7+L8)/5 -> 6.1018346e+09 | P8: =+(+M4+M5+M6+M7+M8)/5 -> 1.6099701e+09
A9: Активы взвешанные с учетом риска | B9: =B6 -> 1.1237792e+10 | J9: 1 июнь | K9: 6 | L9: 7102133905 | M9: 1644988073 | N9: 5 | O9: =+(+L4+L5+L6+L7+L8+L9)/6 -> 6.2685511e+09 | P9: =+(+M4+M5+M6+M7+M8+M9)/6 -> 1.6158064e+09
A10: Недействующие ссуды за вычетом резервов/общий объем капитала | B10: =IFERROR((B11/B12),0) -> 0.025172435 | J10: 1 июль | K10: 7 | L10: 7730755237 | M10: 1664824409 | N10: 6 | O10: =+(L4+L7+L10)/3 -> 6673977465 | P10: =+(M4+M7+M10)/3 -> 1.6184245e+09
A11: Недействующие ссуды за вычетом резервов | B11: =+('Asset Classification'!M50-'Asset Classification'!O50+'Asset Classification'!Q50-'Asset Classification'!S50+'Asset Classification'!U50-'Asset Classification'!W50) -> 43756980 | J11: 1 август | K11: 8 | L11: 8763112470 | M11: 1679311774 | N11: 7 | O11: =(L4+L5+L6+L7+L8+L9+L10+L11)/8 -> 6.7631468e+09 | P11: =(M4+M5+M6+M7+M8+M9+M10+M11)/8 -> 1.6298718e+09
A12: Совокупный капитал на конец периода | B12: =+B35 -> 1738289532 | J12: 1 сентябрь | K12: 9 | L12: 8860704084 | M12: 1705833408 | N12: 8 | O12: =(L4+L5+L6+L7+L8+L9+L10+L11+L12)/9 -> 6.9962087e+09 | P12: =(M4+M5+M6+M7+M8+M9+M10+M11+M12)/9 -> 1.638312e+09
A13: Недействующие ссуды/общая сумма ссуд | B13: =IFERROR((B14/B15),0) -> 0.010141567 | J13: 1 октябрь | K13: 10 | L13: 9271115800 | M13: 1722497556 | N13: 9 | O13: =+(L4+L7+L10+L13)/4 -> 7.323262e+09 | P13: =+(M4+M7+M10+M13)/4 -> 1644442729
A14: Недействующие ссуды | B14: =+('Asset Classification'!M50+'Asset Classification'!Q50+'Asset Classification'!U50) -> 86606941 | J14: 1 ноябрь | K14: 11 | L14: 9506619721 | M14: 1760055235 | N14: 10 | O14: =(+L4+L5+L6+L7+L8+L9+L10+L11+L12+L13+L14)/11 -> 7.4312377e+09 | P14: =(+M4+M5+M6+M7+M8+M9+M10+M11+M12+M13+M14)/11 -> 1.6570328e+09
A15: Общая сумма ссуд | B15: =+'Loans Receivable'!C92 -> 8539798556 | J15: 1 декабрь | K15: 12 | L15: 9735843833 | M15: 1761881830 | N15: 11 | O15: =(+L4+L5+L6+L7+L8+L9+L10+L11+L12+L13+L14+L15)/12 -> 7623288169 | P15: =(+M4+M5+M6+M7+M8+M9+M10+M11+M12+M13+M14+M15)/12 -> 1.6657702e+09
A16: Рентабельность активов | B16: =IFERROR((B17/B18),0) -> 0.015605484 | J16: 1 январь | K16: 13 | L16: 10282915665 | M16: 1738289532 | N16: 12 | O16: =+(L4+L7+L10+L13+L16)/5 -> 7915192772 | P16: =+(M4+M7+M10+M13+M16)/5 -> 1.6632121e+09
A17: Чистая прибыль до уплаты налогов | B17: =(+'Income '!C69)/MONTH(B3)*12 -> 123520415
A18: Всего активы (средний за период) | B18: =VLOOKUP(MONTH(B3),$N$4:$P$16,2,0) -> 7915192772
A19: Рентабельность капитала | B19: =IFERROR((B20/B21),0) -> 0.060141974
A20: Чистая прибыль | B20: =(+'Income '!C76)/MONTH(B3)*12 -> 100028858
A21: Совокупный капитал (средний за период) | B21: =VLOOKUP(MONTH(B3),$N$4:$P$16,3,0) -> 1.6632121e+09
A22: Процентная маржа/валовой доход | B22: =IFERROR((B23/B24),0) -> 0.61982931
A23: Процентная маржа | B23: =+'Income '!C30 -> 526858696
A24: Валовой доход | B24: =+B27 -> 850006099
A25: Непроцентные расходы/валовой доход | B25: =IFERROR((B26/B27),0) -> 0.61812529
A26: Непроцентные расходы | B26: =+'Income '!C51+'Income '!C67 -> 525410263
A27: Валовой доход | B27: =+'Income '!C30+'Income '!C43 -> 850006099
A28: Ликвидные активы/всего активы | B28: =IFERROR((B29/B30),0) -> 0.12074663
A29: Ликвидные активы | B29: =B54 -> 1241627363
A30: Всего активы | B30: =[8]Balance!$C$45 -> 10282915665
A31: Ликвидные активы/краткосрочные обязательства | B31: =IFERROR((B29/B33),0) -> 0.33418879
A32: Ликвидные активы | B32: =+B54 -> 1241627363
A33: Краткосрочные обязательства | B33: ='[8]Bank Liabilities Analysis'!$C$39+'[8]Bank Liabilities Analysis'!$E$39+'[8]Bank Liabilities Analysis'!$G$39+'[8]Bank Liabilities Analysis'!$I$39+'[8]Bank Liabilities Analysis'!$K$39+'[8]Bank Liabilities Analysis'!$M$39 -> 3715347186
A34: Совокупный капитал на конец периода/Всего активы | B34: =IFERROR((B35/B36),0) -> 0.16904637
A35: Совокупный капитал на конец периода | B35: =[8]Balance!$C$77 -> 1738289532
A36: Всего активы | B36: =B30 -> 10282915665
A37: Чистая открытая валютная позиция /Совокупный капитал на конец периода | B37: =IFERROR((B38/B39),0) -> 0.10846577
A38: Чистая открытая валютная позиция | B38: ='[9]Calculation of Risk'!$C$26 -> 188544911
A39: Совокупный капитал на конец периода | B39: =+B35 -> 1738289532
A42: Подпись Председателя правления:
A44: Подпись Главного Бухгалтера:
A46: Ликвидные активы | B46: Сумма | C46: Нацвалюта | D46: Инвалюта
A47: Наличные денежные средства и Драгоценные металлы | B47: ='[8]Liquidity Analysis'!C57 -> 220312322 | C47: ='[8]Liquidity Analysis'!D57 -> 92534623 | D47: ='[8]Liquidity Analysis'!E57 -> 127777699 | E47: 1.
A48: К получению из ЦБРУ | B48: ='[8]Liquidity Analysis'!C58 -> 380783393 | C48: ='[8]Liquidity Analysis'!D58 -> 335334692 | D48: ='[8]Liquidity Analysis'!E58 -> 45448701 | E48: 2.
A49: К получению из других банков | B49: ='[8]Liquidity Analysis'!C59 -> 433866579 | C49: ='[8]Liquidity Analysis'!D59 -> 5226346 | D49: ='[8]Liquidity Analysis'!E59 -> 428640233 | E49: 3.
A50: К получению из других банков - Депозиты (чистые) | B50: ='[8]Liquidity Analysis'!C60 -> 6665069 | C50: ='[8]Liquidity Analysis'!D60 -> 52007 | D50: ='[8]Liquidity Analysis'!E60 -> 6613062 | E50: 3.1. | F50: =+#REF! -> #REF! | G50: =+#REF! -> #REF! | H50: =+#REF! -> #REF!
A51: Ценные бумаги, выпущенные Правительством Республики Узбекистан и ЦБРУ (векселя, облигации и другие долговые ценные бумаги) | B51: ='[8]Liquidity Analysis'!C61 -> 200000000 | C51: ='[8]Liquidity Analysis'!D61 -> 200000000 | D51: ='[8]Liquidity Analysis'!E61 -> 0 | E51: 4.
A52: Ценные бумаги, выпущенные странами с низким уровня риска | B52: ='[8]Liquidity Analysis'!C62 -> 0 | C52: ='[8]Liquidity Analysis'!D62 -> 0 | D52: ='[8]Liquidity Analysis'!E62 -> 0 | E52: 5.
A53: Другие легко реализуемые ценные бумаги | B53: ='[8]Liquidity Analysis'!C63 -> 0 | C53: ='[8]Liquidity Analysis'!D63 -> 0 | D53: ='[8]Liquidity Analysis'!E63 -> 0 | E53: 6.
A54: Итого ликвидных активов | B54: ='[8]Liquidity Analysis'!C64 -> 1241627363 | C54: ='[8]Liquidity Analysis'!D64 -> 633147668 | D54: ='[8]Liquidity Analysis'!E64 -> 608479695 | E54: 7.
