Workbook
Name jop: #REF!
Name kol: #REF!
Name OLE_LINK19: Balance!$D$34
Name TwentyLargestData: #REF!
Name Е: #REF!

Sheet Balance
A1: СТРУКТУРА БАЛАНСА БАНКА | E1: Таблица-1 | G1: №3
B2: =IF(C3>0," "&TEXT(C3,"д ММММ, гггг"),"Число,Месяц,Год") -> 31 Декабрь, 2020
B3: АКБ"Микрокредитбанк" | C3: 44196 | E3: тыс. сум
A4: № | B4: АКТИВЫ | C4: Итого | D4: в национальной валюте | E4: в иностранной валюте (в экв. в сумах)
A5: 1 | B5: Кассовая наличность и другие платежные документы | C5: =+D5+E5 -> 220312147 | D5: =+'Bank Assets Analysis'!T7 -> 92534448 | E5: =+'Bank Assets Analysis'!U7 -> 127777699 | J5: =+C5-D5-E5 -> 0
A6: 2 | B6: К получению из ЦБРУ | C6: =+D6+E6 -> 380783393 | D6: =+'Bank Assets Analysis'!T9+'Bank Assets Analysis'!T10 -> 335334692 | E6: =+'Bank Assets Analysis'!U9+'Bank Assets Analysis'!U10 -> 45448701 | J6: =+C6-D6-E6 -> 0
A7: 3 | B7: К получению из других банков, чистые | C7: =+'Bank Assets Analysis'!S11 -> 666431398 | D7: =+'Bank Assets Analysis'!T11 -> 231178103 | E7: =+'Bank Assets Analysis'!U11 -> 435253295 | J7: =+C7-D7-E7 -> 0
A8: 3.1. | B8: К получению из других банков, брутто | C8: =+D8+E8 -> 667134942 | D8: 231178103 | E8: 435956839 | J8: =+C8-D8-E8 -> 0
A9: 3.2. | B9: Минус: Резерв возможных убытков | C9: =+D9+E9 -> 703544 | D9: 0 | E9: 703544 | J9: =+C9-D9-E9 -> 0
A10: 4 | B10: Счета купли и продажи, чистые | C10: =+D10+E10 -> 202938240 | D10: =+'Investment Securities'!C29 -> 202938240 | E10: =+'Investment Securities'!D29 -> 0 | J10: =+C10-D10-E10 -> 0
A11: 4.1. | B11: Ценные бумаги для купли продажи, брутто | C11: =+D11+E11 -> 200000000 | D11: =+'Investment Securities'!C26 -> 200000000 | E11: =+'Investment Securities'!D26 -> 0 | J11: =+C11-D11-E11 -> 0
A12: 4.2. | B12: Дисконт и премии по ценным бумагам | C12: =+D12+E12 -> 2938240 | D12: =+'Investment Securities'!C27 -> 2938240 | E12: =+'Investment Securities'!D27 -> 0
A13: 4.3. | B13: Минус: Резерв возможных убытков | C13: =+D13+E13 -> 0 | D13: =+'Investment Securities'!C28 -> 0 | E13: =+'Investment Securities'!D28 -> 0 | J13: =+C13-D13-E13 -> 0
A14: 5 | B14: Драгоценные металлы, монеты, камни, чистые | C14: =+C15-C16 -> 175 | D14: =+'Investment Securities'!C40 -> 175 | E14: =+'Investment Securities'!D40 -> 0 | J14: =+C14-D14-E14 -> 0
A15: 5.1. | B15: Драгоценные металлы, монеты, камни, брутто | C15: =+D15+E15 -> 175 | D15: =+'Investment Securities'!C38 -> 175 | E15: =+'Investment Securities'!D38 -> 0 | J15: =+C15-D15-E15 -> 0
A16: 5.2. | B16: Минус: Резерв возможных убытков | C16: =+D16+E16 -> 0 | D16: =+'Investment Securities'!C39 -> 0 | E16: =+'Investment Securities'!D39 -> 0 | J16: =+C16-D16-E16 -> 0
A17: 6 | B17: Инвестиции, чистые | C17: =+'Investment Securities'!B15 -> 107220 | D17: =+'Investment Securities'!C15 -> 107220 | E17: =+'Investment Securities'!D15 -> 0 | J17: =+C17-D17-E17 -> 0
A18: 6.1. | B18: Инвестиции, брутто | C18: =+D18+E18 -> 107220 | D18: =+'Investment Securities'!C13 -> 107220 | E18: =+'Investment Securities'!D13 -> 0 | J18: =+C18-D18-E18 -> 0
A19: 6.2. | B19: Минус: Резерв возможных убытков | C19: =+D19+E19 -> 0 | D19: =+'Investment Securities'!C14 -> 0 | E19: =+'Investment Securities'!D14 -> 0 | J19: =+C19-D19-E19 -> 0
A20: 7 | B20: Ценные бумаги купленные по соглашению c обратным выкупом, чистые | C20: =+'Bank Assets Analysis'!S35 -> 0 | D20: =+'Bank Assets Analysis'!T35 -> 0 | E20: =+'Bank Assets Analysis'!U35 -> 0 | J20: =+C20-D20-E20 -> 0
A21: 7.1. | B21: Ценные бумаги, купленные по соглашению с обратным выкупом, брутто | C21: =+D21+E21 -> 0 | D21: 0 | E21: 0 | J21: =+C21-D21-E21 -> 0
A22: 7.2. | B22: Резерв возможных убытков | C22: =+D22+E22 -> 0 | D22: 0 | E22: 0 | J22: =+C22-D22-E22 -> 0
A23: 8 | B23: Кредиты и лизинговые операции, чистые | C23: =+'Bank Assets Analysis'!S30+'Bank Assets Analysis'!S31+'Bank Assets Analysis'!S33 -> 8342404404 | D23: =+'Bank Assets Analysis'!T30+'Bank Assets Analysis'!T31+'Bank Assets Analysis'!T33 -> 5472161024 | E23: =+'Bank Assets Analysis'!U30+'Bank Assets Analysis'!U31+'Bank Assets Analysis'!U33 -> 2870243380 | J23: =+C23-D23-E23 -> 0
A24: 8.1. | B24: Кредиты и лизинговые операции, брутто | C24: =+D24+E24 -> 8539798556 | D24: 5618504980 | E24: 2921293576 | J24: =+C24-D24-E24 -> 0
A25: 8.2. | B25: Минус: Резерв возможных убытков | C25: =+D25+E25 -> 197394152 | D25: 146343956 | E25: 51050196 | J25: =+C25-D25-E25 -> 0
A26: 9 | B26: Купленные векселя, чистые | C26: =+'Bank Assets Analysis'!S26 -> 0 | D26: =+'Bank Assets Analysis'!T26 -> 0 | E26: =+'Bank Assets Analysis'!U26 -> 0 | J26: =+C26-D26-E26 -> 0
A27: 9.1. | B27: Купленные векселя, брутто | C27: =+D27+E27 -> 0 | D27: 0 | E27: 0 | J27: =+C27-D27-E27 -> 0
A28: 9.2. | B28: Минус: Резерв возможных убытков | C28: =+D28+E28 -> 0 | D28: 0 | E28: 0 | J28: =+C28-D28-E28 -> 0
A29: 10 | B29: Обязательства клиентов по финансовым инструментам, чистые | C29: =+D29+E29 -> 0 | D29: =+'Bank Assets Analysis'!T27+'Bank Assets Analysis'!T28 -> 0 | E29: =+'Bank Assets Analysis'!U27+'Bank Assets Analysis'!U28 -> 0 | J29: =+C29-D29-E29 -> 0
A30: 10.1. | B30: Обязательства клиентов по финансовым инструментам, брутто | C30: =+D30+E30 -> 0 | D30: 0 | E30: 0 | J30: =+C30-D30-E30 -> 0
A31: 10.2. | B31: Минус: Резерв возможных убытков | C31: =+D31+E31 -> 0 | D31: 0 | E31: 0 | J31: =+C31-D31-E31 -> 0
A32: 11 | B32: Основные средства, чистые | C32: =+'Bank Assets Analysis'!S38 -> 201801025 | D32: =+'Bank Assets Analysis'!T38 -> 201801025 | E32: =+'Bank Assets Analysis'!U38 -> 0 | J32: =+C32-D32-E32 -> 0
A33: 12 | B33: Начисленные процентные и беспроцентные доходы всего, чистые | C33: =+C34+C35-C36 -> 186779795 | D33: =+D34+D35-D36 -> 134890678 | E33: =+E34+E35-E36 -> 51889117 | J33: =+C33-D33-E33 -> 0
A34: 12.1. | B34: Начисленные проценты к получению, брутто | C34: =+'Bank Assets Analysis'!S43 -> 186692854 | D34: =+'Bank Assets Analysis'!T43 -> 134803737 | E34: =+'Bank Assets Analysis'!U43 -> 51889117 | J34: =+C34-D34-E34 -> 0
A35: 12.2. | B35: Начисленные беспроцентные доходы к получению, брутто | C35: =+D35+E35 -> 86941 | D35: 86941 | E35: 0 | J35: =+C35-D35-E35 -> 0
A36: 12.2.1. | B36: Минус: Резерв возможных убытков | C36: =+D36+E36 -> 0 | D36: 0 | E36: 0 | J36: =+C36-D36-E36 -> 0
A37: 13 | B37: Другое собственное имущество банка, чистые | C37: =+'Bank Assets Analysis'!S39 -> 0 | D37: =+'Bank Assets Analysis'!T39 -> 0 | E37: =+'Bank Assets Analysis'!U39 -> 0 | J37: =+C37-D37-E37 -> 0
A38: 13.1. | B38: Другие собственное имущество, взысканное по кредитам и лизингу, брутто | C38: =+D38+E38 -> 0 | D38: 0 | E38: 0 | J38: =+C38-D38-E38 -> 0
A39: 13.2. | B39: Другое собственное имущество банка, брутто | C39: =+D39+E39 -> 0 | D39: 0 | E39: 0 | J39: =+C39-D39-E39 -> 0
A40: 13.3. | B40: Минус:Накопленный износ и резервы на возможные убытки | C40: =+D40+E40 -> 0 | D40: 0 | E40: 0 | J40: =+C40-D40-E40 -> 0
A41: 14 | B41: Другие активы, чистые | C41: =+C42-C43+C44 -> 81357868 | D41: =+D42-D43+D44 -> 40187815 | E41: =+E42-E43+E44 -> 41170053 | J41: =+C41-D41-E41 -> 0
A42: 14.1. | B42: Другие активы, брутто | C42: =+D42+E42 -> 94973587 | D42: =41467610+1624624+2562616 -> 45654850 | E42: 49318737 | J42: =+C42-D42-E42 -> 0
A43: 14.2. | B43: Минус: Резерв возможных убытков | C43: =+D43+E43 -> 11053103 | D43: 2904419 | E43: 8148684 | J43: =+C43-D43-E43 -> 0
A44: 14.3. | B44: Купля-продажа валюты и валютные позиции | C44: -2562616 | D44: -2562616 | J44: =+C44-D44-E44 -> 0
A45: 15. | B45: Итого активов | C45: =+C5+C6+C7+C10+C14+C17+C20+C23+C26+C29+C32+C33+C37+C41 -> 10282915665 | D45: =+D5+D6+D7+D10+D14+D17+D20+D23+D26+D29+D32+D33+D37+D41 -> 6711133420 | E45: =+E5+E6+E7+E10+E14+E17+E20+E23+E26+E29+E32+E33+E37+E41 -> 3571782245 | F45: =+'Bank Assets Analysis'!S45 -> 10282915665 | G45: =+'Bank Assets Analysis'!T45 -> 6711133420 | H45: =+'Bank Assets Analysis'!U45 -> 3571782245 | J45: =+C45-D45-E45 -> 0
B47: ОБЯЗАТЕЛЬСТВА И СОБСТВЕННЫЙ КАПИТАЛ | F47: =+F45-C45 -> 0 | G47: =+G45-D45 -> 0 | H47: =+H45-E45 -> 0
B49: ОБЯЗАТЕЛЬСТВА
A50: 16. | B50: Депозиты до востребования | C50: =+'Deposits by Client'!C11 -> 621497920 | D50: =+'Bank Liabilities Analysis'!T16+'Bank Liabilities Analysis'!T8 -> 544017464 | E50: =+'Bank Liabilities Analysis'!U16+'Bank Liabilities Analysis'!U8 -> 77480456 | J50: =+C50-D50-E50 -> 0
A51: 17. | B51: Срочные депозиты | C51: =+'Deposits by Client'!C20 -> 1761245905 | D51: =+'Bank Liabilities Analysis'!T13 -> 1412963108 | E51: =+'Bank Liabilities Analysis'!U13 -> 348282797 | J51: =+C51-D51-E51 -> 0
A52: 18. | B52: К оплате в ЦБРУ | C52: =+'Bank Liabilities Analysis'!S23 -> 0 | D52: =+'Bank Liabilities Analysis'!T23 -> 0 | E52: =+'Bank Liabilities Analysis'!U23 -> 0 | J52: =+C52-D52-E52 -> 0
A53: 19. | B53: К оплате в другие банки | C53: =+'Bank Liabilities Analysis'!S24 -> 1677401207 | D53: =+'Bank Liabilities Analysis'!T24 -> 917960723 | E53: =+'Bank Liabilities Analysis'!U24 -> 759440484 | J53: =+C53-D53-E53 -> 0
A54: 20. | B54: Проданные по сделкам РЕПО ценные бумаги | C54: =+'Bank Liabilities Analysis'!S34 -> 0 | D54: =+'Bank Liabilities Analysis'!T34 -> 0 | E54: =+'Bank Liabilities Analysis'!U34 -> 0 | J54: =+C54-D54-E54 -> 0
A55: 21. | B55: Кредиты и лизинговые операции к оплате | C55: =+D55+E55 -> 4301859637 | D55: 2169849124 | E55: 2132010513 | J55: =+C55-D55-E55 -> 0
A56: 22. | B56: Выпущенные банком ценные бумаги | C56: =+D56+E56 -> 0 | D56: 0 | E56: 0 | J56: =+C56-D56-E56 -> 0
A57: 23. | B57: Субординированные долговые обязательства | C57: =+D57+E57 -> 0 | D57: 0 | E57: 0 | J57: =+C57-D57-E57 -> 0
A58: 24. | B58: Начисленные проценты к оплате | C58: =+'Bank Liabilities Analysis'!S37 -> 65266761 | D58: =+'Bank Liabilities Analysis'!T37 -> 50677310 | E58: =+'Bank Liabilities Analysis'!U37 -> 14589451 | J58: =+C58-D58-E58 -> 0
A59: 25. | B59: Начисленные налоги к оплате | C59: =+D59+E59 -> 39600602 | D59: 39600602 | E59: 0 | J59: =+C59-D59-E59 -> 0
A60: 26. | B60: Клиринговые трансакции | C60: =+'Bank Liabilities Analysis'!S36 -> 602200 | D60: =+'Bank Liabilities Analysis'!T36 -> 497730 | E60: =+'Bank Liabilities Analysis'!U36 -> 104470 | J60: =+C60-D60-E60 -> 0
A61: 27. | B61: Другие обязательства | C61: =+D61+E61 -> 77151901 | D61: =26760733+1624624 -> 28385357 | E61: 48766544 | J61: =+C61-D61-E61 -> 0
A62: 28. | B62: Итого обязательств | C62: =+D62+E62 -> 8544626133 | D62: =SUM(D50:D61) -> 5163951418 | E62: =SUM(E50:E61) -> 3380674715 | F62: =+'Bank Liabilities Analysis'!S39 -> 8544626133 | G62: =+'Bank Liabilities Analysis'!T39 -> 5163951418 | H62: =+'Bank Liabilities Analysis'!U39 -> 3380674715 | J62: =+C62-D62-E62 -> 0
J63: =+C63-D63-E63 -> 0
B64: СОБСТВЕННЫЙ КАПИТАЛ | J64: =+C64-D64-E64 -> 0
J65: =+C65-D65-E65 -> 0
A66: 29. | B66: Уставный капитал | J66: =+C66-D66-E66 -> 0
A67: 29.1. | B67: Акции - Обыкновенные | C67: =+D67+E67 -> 1641584276 | D67: 1641584276 | E67: 0 | J67: =+C67-D67-E67 -> 0
A68: 29.2. | B68: Акции - Привилегированные | C68: =+D68+E68 -> 144180 | D68: 144180 | E68: 0 | J68: =+C68-D68-E68 -> 0
A69: 30. | B69: Добавленный капитал | C69: =+D69+E69 -> 0 | D69: 0 | E69: 0 | J69: =+C69-D69-E69 -> 0
A70: 31. | B70: Резервный капитал. | J70: =+C70-D70-E70 -> 0
A71: 31.1. | B71: Резервный фонд общего назначения | C71: =+D71+E71 -> 33388136 | D71: 33388136 | E71: 0 | J71: =+C71-D71-E71 -> 0
A72: 31.2. | B72: Резервы созданные по стандартным активам | C72: =+D72+E72 -> 0 | D72: 0 | E72: 0 | J72: =+C72-D72-E72 -> 0
A73: 31.3. | B73: Резерв на Девальвацию | C73: =+D73+E73 -> 0 | D73: 0 | E73: 0 | J73: =+C73-D73-E73 -> 0
A74: 31.4. | B74: Другие резервы и фонды | C74: =+D74+E74 -> 775975 | D74: 775975 | E74: 0 | J74: =+C74-D74-E74 -> 0
A75: 32. | B75: Нераспределенная прибыль | C75: =+D75+E75 -> 62396965 | D75: 62396965 | E75: 0 | J75: =+C75-D75-E75 -> 0
A76: 32.1. | B76: из них, чистая прибыль (убыток) текущего года | C76: =+D76+E76 -> 100028858 | D76: 100028858 | E76: 0 | J76: =+C76-D76-E76 -> 0
A77: 33. | B77: Итого собственного капитала | C77: =SUM(C67:C75) -> 1738289532 | D77: =SUM(D67:D75) -> 1738289532 | E77: =SUM(E67:E75) -> 0 | J77: =+C77-D77-E77 -> 0
A78: 34. | B78: Итого обязательств и собственного капитала | C78: =+D78+E78 -> 10282915665 | D78: =+D62+D77 -> 6902240950 | E78: =+E62+E77 -> 3380674715 | J78: =+C78-D78-E78 -> 0
B80: Подпись Председателя правления:
B82: Подпись Главного Бухгалтера:
C84: =+C45-C78 -> 0

Sheet Bank Capital Calc (2)
A1: РАСЧЕТ РЕГУЛЯТИВНОГО КАПИТАЛА БАНКА | C1: Таблица-5
B3: =Balance!B3 -> АКБ"Микрокредитбанк" | C3: =+Balance!C3 -> 44196
A4: № | B4: Характеристики | C4: Итого капитала
A5: I. | B5: КАПИТАЛ УРОВНЯ 1
A6: 1 | B6: ОСНОВНОЙ КАПИТАЛ УРОВНЯ 1
A7: 1.1. | B7: Обыкновенные Акции, чистые | C7: Формула
A8: a | B8: Полностью оплаченные обыкновенные акции
A9: б | B9: Минус: Обратно Выкупленные обыкновенные акции
A10: 1.2. | B10: Добавленный капитал - Обыкновенные | C10: 0
A11: 1.3. | B11: Нераспределенная прибыль (убыток), в том числе капитальные резервы | C11: Формула
A12: а | B12: Капитальные резервы
A13: б | B13: Нераспределенная прибыль
A14: в | B14: Убыток за предыдущие периоды
A15: г | B15: Убыток за текущий год
A16: 1.4. | B16: Интерес меньшинства в консолидированных дочерних компаниях (согласно МБС)
A17: 1.5. | B17: Резерв на девальвацию
B18: Итого основного капитала уровня I до вычетов | C18: Формула
A19: 1.6. | B19: Вычеты из суммы основного капитала уровня I | C19: Формула
A20: а | B20: Нематериальные активы
A21: б | B21: Все инвестиции в капитал неконсолидированных хозяйствующих субъектов, в том числе в долговые обязательства, которые образуют капитал хозяйствующих субъектов
A22: в | B22: Инвестиции в капитал других банков
A23: I | B23: ВСЕГО СКОРРЕКТИРОВАННЫЙ ОСНОВНОЙ КАПИТАЛ УРОВНЯ I | C23: Формула
A24: 2 | B24: ДОБАВЛЕННЫЙ КАПИТАЛ УРОВНЯ 1
A25: 2.1. | B25: Некумулятивные бессрочные привилегированные акции | C25: =+C26+C27 -> 0
A26: а | B26: Полностью оплаченные привилегированные акции
A27: б | B27: Минус: Обратно Выкупленные привилегированные акции
A28: 2.2. | B28: Добавленный капитал - Привилегированные | C28: 0
A29: 2.3. | B29: Интерес меньшинства в консолидированных дочерних компаниях | C29: 0
A30: 2.4. | B30: Доля участия дочерних предприятий (выпущенные дочерними предприятиями и находящиеся во владении третьих лиц инструменты, приравненные к капиталу) | C30: 0
A31: II | B31: ВСЕГО ДОБАВЛЕННЫЙ КАПИТАЛ УРОВНЯ I | C31: =+C25+C28+C29+C30 -> 0
A32: III | B32: ВСЕГО СКОРРЕКТИРОВАННЫЙ КАПИТАЛ УРОВНЯ I | C32: Формула
B33: КАПИТАЛ УРОВНЯ II
A34: 3.1. | B34: Прибыль за текущий год
A35: 3.2. | B35: Резервы, создаваемые на стандартные кредиты (активы), в размере не более 1.25% от общей суммы активов, взвешенных с учетом риска | C35: =IF(Balance!C72<(C43*1.25%),Balance!C72,(C43*1.25%)) -> #REF!
A36: 3.3. | B36: Излишки оценочной стоимости прироста над первоначальной стоимостью
A37: 3.4. | B37: Другие инструменты капитала (не более 1/3 части капитала 1 уровня после вычетов)
A38: 3.5. | B38: Субординированный долг
A39: 3.6. | B39: Вычеты превышения Капитала Уровня II над Капиталом Уровня I | C39: Формула
B40: Итого капитала Уровня II | C40: =SUM(C34:C38) -> #REF!
A41: IV | B41: СКОРРЕКТИРОВАННЫЙ КАПИТАЛ УРОВНЯ II | C41: Формула
A42: V | B42: ВСЕГО РЕГУЛЯТИВНЫЙ КАПИТАЛ | C42: Формула
A43: VI | B43: ОБЩАЯ СУММА АКТИВОВ ВЗВЕШЕННЫХ С УЧЕТОМ РИСКА | C43: =+C44+C45+C46 -> #REF!
A44: а | B44: Сумма балансовых и забалансовых активов, взвешенных с учетом риска | C44: =+#REF! -> #REF!
A45: б | B45: Операционный риск | C45: =+#REF! -> #REF!
A46: в | B46: Рыночный риск | C46: =+#REF! -> #REF! | E46: =+#REF! -> #REF!
A47: VII | B47: КОЭФФИЦИЕНТ ОСНОВНОГО КАПИТАЛА УРОВНЯ I (I/VI) | C47: Формула
A48: VIII | B48: КОЭФФИЦИЕНТ КАПИТАЛА УРОВНЯ I (III/VI) | C48: Формула
A49: IX | B49: КОЭФФИЦИЕНТ ОБЩЕЙ СУММЫ КАПИТАЛА, ОСНОВАННОГО НА РИСКЕ (V/VI) | C49: Формула
A50: X | B50: Активы для расчета левеража | C50: Формула
A51: а | B51: Общие активы | C51: =+Balance!C45 -> 10282915665
A52: б | B52: Забалансовые инструменты | C52: =SUM(#REF!) -> #REF! | D52: =+#REF! -> #REF!
A53: в | B53: Деривативные (производные) инструменты | C53: =SUM(#REF!) -> #REF!
A54: г | B54: Минус: Строка 1.6. Итого вычетов из суммы основного капитала Уровня 1 | C54: =+C19 -> Формула
A55: XI | B55: Коэффициент левеража | C55: Формула
B57: Подпись Председателя правления:
B59: Подпись Главного Бухгалтера:

Sheet Liquidity Analysis
B1: АНАЛИЗ ЛИКВИДНОСТИ | E1: Таблица-16
B2: =Balance!B3 -> АКБ"Микрокредитбанк" | C2: =+Balance!B2 -> 31 Декабрь, 2020 | E2: в тыс. сум
A3: № | B3: Ликвидные активы | C3: Сумма | D3: Нацвалюта | E3: Инвалюта
B5: Часть 1. Высоколиквидные активы | C5: в процентах
A6: 1.1. | B6: Наличные денежные средства | C6: =+'Bank Assets Analysis'!S7-'Bank Assets Analysis'!S8 -> 220312147 | D6: =+'Bank Assets Analysis'!T7-'Bank Assets Analysis'!T8 -> 92534448 | E6: =+'Bank Assets Analysis'!U7-'Bank Assets Analysis'!U8 -> 127777699
A7: 1.2. | B7: К получению из ЦБРУ не учитывая сумму обязательных резервов банка(ФОР) | C7: =+'Bank Assets Analysis'!S9 -> 359385307 | D7: =+'Bank Assets Analysis'!T9 -> 313936606 | E7: =+'Bank Assets Analysis'!U9 -> 45448701
A8: 1.3. | B8: Ценные бумаги, выпущенные Правительством Республики Узбекистан и ЦБРУ | C8: =+'Bank Assets Analysis'!S20-'Bank Assets Analysis'!S21+'Bank Assets Analysis'!S36 -> 200000000 | D8: =+'Bank Assets Analysis'!T20-'Bank Assets Analysis'!T21+'Bank Assets Analysis'!T36 -> 200000000 | E8: =+'Bank Assets Analysis'!U20-'Bank Assets Analysis'!U21+'Bank Assets Analysis'!U36 -> 0
A9: 1.4. | B9: Денежные средства на корсчетах открытых в иностранных банках с рейтингом не ниже инвестиционного и в местных банках имеющих кредитный рейтинг | C9: =+E9 -> 428640233 | E9: =+'Bank Assets Analysis'!D12+'Bank Assets Analysis'!D13 -> 428640233
A10: 1.5. | B10: Депозиты размещенные на условиях овернайт в иностранной валюте с рейтингом не ниже инвестиционного | C10: =+E10 -> 0 | E10: =+'Bank Assets Analysis'!F15 -> 0
A11: 1.6. | B11: Ценные бумаги выпущенные МВФ, входящие организации в группу Всемирного банка, МФК, АБР, Азиатский банк инфроструктуры и инвестиции, ЕБРР, Европейский инвестиционный банк, Исламский банк развития и Банк развития Европейского союза | C11: =+'Bank Assets Analysis'!S23 -> 0 | D11: =+'Bank Assets Analysis'!T23 -> 0 | E11: =+'Bank Assets Analysis'!U23 -> 0
A12: 1.7. | B12: Правительственные ценные бумаги стран с низкой степенью странового риска | C12: =+'Bank Assets Analysis'!S22 -> 0 | D12: =+'Bank Assets Analysis'!T22 -> 0 | E12: =+'Bank Assets Analysis'!U22 -> 0
A13: 1.8. | B13: Всего высоколиквидных активов | C13: =SUM(C6:C12)-'Bank Liabilities Analysis'!U25+194716877 -> 1403054564 | D13: =SUM(D6:D12)+194716877 -> 801187931 | E13: =SUM(E6:E12)-'Bank Liabilities Analysis'!U25 -> 601866633 | F13: =SUM(C6:C12)-'Bank Liabilities Analysis'!U25 -> 1208337687 | G13: =SUM(D6:D12) -> 606471054 | H13: =SUM(E6:E12)-'Bank Liabilities Analysis'!U25 -> 601866633
B14: Часть 2. Экономические нормативы - Ликвидность
A15: 2.1. | B15: Расчет коэффициента высоколиквидных активов к всего активам | C15: =IFERROR((+C16/C17),0) -> 0.13644521 | D15: =IFERROR((+D16/D17),0) -> 0.11938191 | E15: =IFERROR((+E16/E17),0) -> 0.16850597
A16: 2.1.1. | B16: Высоколиквидные активы | C16: =+C13 -> 1403054564 | D16: =+D13 -> 801187931 | E16: =+E13 -> 601866633
A17: 2.1.2. | B17: Всего активов | C17: =+Balance!C45 -> 10282915665 | D17: =+Balance!D45 -> 6711133420 | E17: =+Balance!E45 -> 3571782245
A18: 2.2. | B18: Расчет коэффициента высоколиквидных активов к краткосрочным обязательствам | C18: =IFERROR((+C19/C20),0) -> 0.37763754 | D18: =IFERROR((+D19/D20),0) -> 0.34826895 | E18: =IFERROR((+E19/E20),0) -> 0.42538925
A19: 2.2.1. | B19: Высоколиквидные активы | C19: =+C13 -> 1403054564 | D19: =+D13 -> 801187931 | E19: =+E13 -> 601866633
A20: 2.2.2. | B20: Краткосрочные обязательства | C20: =+'Bank Liabilities Analysis'!C39+'Bank Liabilities Analysis'!E39+'Bank Liabilities Analysis'!G39+'Bank Liabilities Analysis'!I39+'Bank Liabilities Analysis'!K39+'Bank Liabilities Analysis'!M39 -> 3715347186 | D20: =+C20-E20 -> 2300486242 | E20: =+'Bank Liabilities Analysis'!D39+'Bank Liabilities Analysis'!F39+'Bank Liabilities Analysis'!H39+'Bank Liabilities Analysis'!J39+'Bank Liabilities Analysis'!L39+'Bank Liabilities Analysis'!N39 -> 1414860944
A21: 2.3. | B21: Коэффициент покрытия ликвидности (действующий норматив)* | C21: =IFERROR((+C22/C23),0) -> 2.3646901 | D21: =IFERROR((+D22/D23),0) -> 1.8285311 | E21: =IFERROR((+E22/E23),0) -> 3.8786024
A22: 2.3.1. | B22: Высоколиквидные активы | C22: =+C13 -> 1403054564 | D22: =+D13 -> 801187931 | E22: =+E13 -> 601866633
A23: 2.3.2. | B23: Чистый отток в последующие 30 дней | C23: =+'Bank Assets Analysis'!X61 -> 5.9333548e+08 | D23: =+'Bank Assets Analysis (нац)'!S54 -> 4.3815932e+08 | E23: =+'Bank Assets Analysis'!Z61 -> 1.5517616e+08
B24: Сумма оттока за 30 дней | C24: =+'Bank Assets Analysis'!X63 -> 7.2071359e+08 | D24: =+'Bank Assets Analysis (нац)'!S56 -> 5.2720965e+08 | E24: =+'Bank Assets Analysis'!Z63 -> 1.9350394e+08 | F24: все расходы за 30 денй умноженная на коэффициенты
B25: Сумма притока за 30 дней | C25: =+'Bank Assets Analysis'!X64 -> 1.2737811e+08 | D25: =+'Bank Assets Analysis (нац)'!S58 -> 89050327 | E25: =+'Bank Assets Analysis'!Z64 -> 38327783 | F25: Ликвидные активы за 30 дней
A26: 2.4. | B26: Коэффициент покрытия ликвидности (внедряемый норматив)** | C26: =IFERROR((+C27/C28),0) -> 1.172964 | D26: =IFERROR((+D27/D28),0) -> 1.1490837 | E26: =IFERROR((+E27/E28),0) -> 1.2063366
A27: 2.4.1. | B27: Высоколиквидные активы | C27: =+C13 -> 1403054564 | D27: =+D13 -> 801187931 | E27: =+E13 -> 601866633
A28: 2.4.2. | B28: Чистый отток в последующие 30 дней | C28: =+'Bank Assets Analysis'!AC61 -> 1.1961617e+09 | D28: =+'Bank Assets Analysis (нац)'!V54 -> 6.9724073e+08 | E28: =+'Bank Assets Analysis'!AE61 -> 4.9892098e+08
B29: Сумма оттока за 30 дней | C29: =+'Bank Assets Analysis'!AC63 -> 1.3343121e+09 | D29: =+'Bank Assets Analysis (нац)'!V56 -> 7.9395111e+08 | E29: =+'Bank Assets Analysis'!AE63 -> 5.40361e+08
B30: Сумма притока за 30 дней | C30: =+'Bank Assets Analysis'!AC66 -> 1.381504e+08 | D30: =+'Bank Assets Analysis (нац)'!V58 -> 96710380 | E30: =+'Bank Assets Analysis'!AE66 -> 41440020
A31: 2.5. | B31: Норма чистого стабильного финансирования | C31: =IFERROR((C32/C37),0) -> 1.188397 | D31: =IFERROR((D32/D37),0) -> 1.2444545 | E31: =IFERROR((E32/E37),0) -> 1.0806276
A32: 2.6. | B32: Доступная сумма стабильного финансирования | C32: =SUM(C33:C36) -> 7.6821726e+09 | D32: =SUM(D33:D36) -> 5.2919006e+09 | E32: =SUM(E33:E36) -> 2.3902721e+09
A33: 2.6.1. | B33: Собственный капитал | C33: =Balance!C77 -> 1738289532 | D33: =Balance!D77 -> 1738289532 | E33: =Balance!E77 -> 0
A34: 2.6.2. | B34: Обязательства свыше 1 года | C34: ='Bank Liabilities Analysis'!O39+'Bank Liabilities Analysis'!Q39 -> 4829278947 | D34: =+'Bank Liabilities Analysis (нац)'!I40+'Bank Liabilities Analysis (нац)'!J40 -> 2863465176 | E34: ='Bank Liabilities Analysis'!P39+'Bank Liabilities Analysis'!R39 -> 1965813771
A35: 2.6.3. | B35: 30% других бессрочных обязательств | C35: =+('Bank Liabilities Analysis'!C39)*0.3 -> 2.4420139e+08 | D35: =+('Bank Liabilities Analysis (нац)'!C40)*0.3 -> 2.0151693e+08 | E35: =+('Bank Liabilities Analysis'!D39)*0.3 -> 42684454
A36: 2.6.4. | B36: 30% других обязательств менее 1 года | C36: =+('Bank Liabilities Analysis'!E39+'Bank Liabilities Analysis'!G39+'Bank Liabilities Analysis'!I39+'Bank Liabilities Analysis'!K39+'Bank Liabilities Analysis'!M39)*0.3 -> 8.7040277e+08 | D36: =+('Bank Liabilities Analysis (нац)'!D40+'Bank Liabilities Analysis (нац)'!E40+'Bank Liabilities Analysis (нац)'!F40+'Bank Liabilities Analysis (нац)'!G40+'Bank Liabilities Analysis (нац)'!H40)*0.3 -> 4.8862894e+08 | E36: =+('Bank Liabilities Analysis'!F39+'Bank Liabilities Analysis'!H39+'Bank Liabilities Analysis'!J39+'Bank Liabilities Analysis'!L39+'Bank Liabilities Analysis'!N39)*0.3 -> 381773829
A37: 2.7. | B37: Необходимая сумма стабильного финансирования | C37: =SUM(C38:C43) -> 6464315176 | D37: =SUM(D38:D43) -> 4.2523858e+09 | E37: =SUM(E38:E43) -> 2.2119294e+09
A38: 2.7.1. | B38: Активы свыше 1 года | C38: =+'Bank Assets Analysis'!O45-'Bank Assets Analysis'!O38+'Bank Assets Analysis'!Q45-'Bank Assets Analysis'!Q38 -> 4734103612 | D38: =+C38-E38 -> 2986482565 | E38: =+'Bank Assets Analysis'!P45-'Bank Assets Analysis'!P41-'Bank Assets Analysis'!P38+'Bank Assets Analysis'!R45-'Bank Assets Analysis'!R41-'Bank Assets Analysis'!R38 -> 1747621047
A39: 2.7.2. | B39: Банковские помещения, мебель и оборудование, чистые | C39: =+'Bank Assets Analysis'!S38 -> 201801025 | D39: =+'Bank Assets Analysis'!T38 -> 201801025 | E39: =+'Bank Assets Analysis'!U38 -> 0
A40: 2.7.3. | B40: Кредиты и лизинги и авансы в процессе судебного разбирательства, чистые или не взысканные в установленном порядке | C40: =+'Bank Assets Analysis'!C29+'Bank Assets Analysis'!C30+'Bank Assets Analysis'!C31+'Bank Assets Analysis'!C33 -> 91809428 | D40: =+'Bank Assets Analysis (нац)'!C29+'Bank Assets Analysis (нац)'!C30+'Bank Assets Analysis (нац)'!C31+'Bank Assets Analysis (нац)'!C33 -> 85440009 | E40: =+'Bank Assets Analysis'!D29+'Bank Assets Analysis'!D30+'Bank Assets Analysis'!D31+'Bank Assets Analysis'!D33 -> 6369419
A41: 2.7.4. | B41: Активы в процессе судебного разбирательства или не взысканные в установленном порядке(не указанные в строке 2.7.4.) | C41: =+D41+E41 -> 0 | E41: 0
A42: 2.7.5. | B42: 30% других активов менее 1 го года (за исключением бессрочных и со сроком менее 1 го года ликвидных активов) | C42: =(+'Bank Assets Analysis'!S45-'Bank Assets Analysis'!O45-'Bank Assets Analysis'!Q45-'Liquidity Analysis'!C64)*0.3 -> 1292155407 | D42: =('Bank Assets Analysis (нац)'!K45-'Bank Assets Analysis (нац)'!I45-'Bank Assets Analysis (нац)'!J45-'Liquidity Analysis'!D64)*0.3 -> 9.2745096e+08 | E42: =('Bank Assets Analysis'!U45-'Bank Assets Analysis'!P45-'Bank Assets Analysis'!R45-'Liquidity Analysis'!E64)*0.3 -> 3.6470445e+08
A43: 2.7.6. | B43: 15% из забалансовых инструментов | C43: =+ROUND(SUM(Commitments!C4-Commitments!C5+Commitments!C7-Commitments!C8+Commitments!C10-'Bank Liabilities Analysis'!S19+Commitments!C18-Commitments!C23)*15%,0) -> 144445704 | D43: =+ROUND(SUM(Commitments!D4-Commitments!D5+Commitments!D7-Commitments!D8+Commitments!D10-'Bank Liabilities Analysis'!T19+Commitments!D18-Commitments!D23)*15%,0) -> 51211232 | E43: =+ROUND(SUM(Commitments!E4-Commitments!E5+Commitments!E7-Commitments!E8+Commitments!E10-'Bank Liabilities Analysis'!U19+Commitments!E18-Commitments!E23)*15%,0) -> 93234472
B45: Примечание
B46: *Расчитывается по действующиму номативу, которая будет действовать до 1 июля 2020 года
B47: **Расчитывается для мониторинга по новому номативу, которая вступит в силу после 1 июля 2020 года
B50: Подпись Председателя правления:
B52: Подпись Главного Бухгалтера:
A56: № | B56: Ликвидные активы | C56: Сумма | D56: Нацвалюта | E56: Инвалюта
A57: 1. | B57: Наличные денежные средства и Драгоценные металлы | C57: =+'Bank Assets Analysis'!S7+'Investment Securities'!B40 -> 220312322 | D57: =+'Bank Assets Analysis'!T7+'Investment Securities'!C40 -> 92534623 | E57: =+'Bank Assets Analysis'!U7+'Investment Securities'!D40 -> 127777699
A58: 2. | B58: К получению из ЦБРУ | C58: =+'Bank Assets Analysis'!S9+'Bank Assets Analysis'!S10 -> 380783393 | D58: =+'Bank Assets Analysis'!T9+'Bank Assets Analysis'!T10 -> 335334692 | E58: =+'Bank Assets Analysis'!U9+'Bank Assets Analysis'!U10 -> 45448701
A59: 3. | B59: К получению из других банков | C59: ='Bank Assets Analysis'!C12+'Bank Assets Analysis'!C13+'Bank Assets Analysis'!C14+'Bank Assets Analysis'!C17+'Bank Assets Analysis'!C18+'Bank Assets Analysis'!E18+'Bank Assets Analysis'!G18 -> 433866579 | D59: =+C59-E59 -> 5226346 | E59: ='Bank Assets Analysis'!D12+'Bank Assets Analysis'!D13+'Bank Assets Analysis'!D17+'Bank Assets Analysis'!D18+'Bank Assets Analysis'!F18+'Bank Assets Analysis'!H18 -> 428640233
A60: 3.1. | B60: К получению из других банков - Депозиты (чистые) | C60: =IF(F60>0,F60,0) -> 6665069 | D60: =IF(G60>0,G60,0) -> 52007 | E60: =IF(H60>0,H60,0) -> 6613062 | F60: =(('Bank Assets Analysis'!E12+'Bank Assets Analysis'!G12+'Bank Assets Analysis'!C16+'Bank Assets Analysis'!E16+'Bank Assets Analysis'!G16)-'Bank Liabilities Analysis'!C26-'Bank Liabilities Analysis'!E26-'Bank Liabilities Analysis'!G26) -> 6665069 | G60: =+('Bank Assets Analysis'!E12-'Bank Assets Analysis'!F12+'Bank Assets Analysis'!G12-'Bank Assets Analysis'!H12+'Bank Assets Analysis'!C16-'Bank Assets Analysis'!D16+'Bank Assets Analysis'!E16-'Bank Assets Analysis'!F16+'Bank Assets Analysis'!G16-'Bank Assets Analysis'!H16)-('Bank Liabilities Analysis'!C26-'Bank Liabilities Analysis'!D26+'Bank Liabilities Analysis'!E26-'Bank Liabilities Analysis'!F26+'Bank Liabilities Analysis'!G26-'Bank Liabilities Analysis'!H26) -> 52007 | H60: =(('Bank Assets Analysis'!F12+'Bank Assets Analysis'!H12+'Bank Assets Analysis'!D16+'Bank Assets Analysis'!F16+'Bank Assets Analysis'!H16)-'Bank Liabilities Analysis'!D26-'Bank Liabilities Analysis'!F26-'Bank Liabilities Analysis'!H26) -> 6613062
A61: 4. | B61: Ценные бумаги, выпущенные Правительством Республики Узбекистан и ЦБРУ (векселя, облигации и другие долговые ценные бумаги) | C61: =+'Investment Securities'!B19+'Investment Securities'!B20+'Investment Securities'!B21 -> 200000000 | D61: =+'Investment Securities'!C19+'Investment Securities'!C20+'Investment Securities'!C21 -> 200000000 | E61: =+'Investment Securities'!D19+'Investment Securities'!D20+'Investment Securities'!D21 -> 0
A62: 5. | B62: Ценные бумаги, выпущенные странами с низким уровня риска
A63: 6. | B63: Другие легко реализуемые ценные бумаги
A64: 7. | B64: Итого ликвидных активов | C64: =SUM(C57:C63) -> 1241627363 | D64: =SUM(D57:D63) -> 633147668 | E64: =SUM(E57:E63) -> 608479695

Sheet Bank Assets Analysis
A1: АНАЛИЗ АКТИВОВ БАНКА | AC1: Таблица-17
B2: =Balance!B3 -> АКБ"Микрокредитбанк" | T2: =+Balance!B2 -> 31 Декабрь, 2020 | AE2: в тыс. сум
A3: № | B3: Характеристики | C3: Срок погашения (в днях) | S3: ВСЕГО | T3: из них | V3: Расчет коэффициента покрытия ликвидности (действующий норматив) | AA3: Расчет коэффициента покрытия ликвидности (внедряемый норматив)
C4: Бессрочные | E4: От 1 до 7 дней | G4: От 8 до 30 дней | I4: От 31 до 90 дней | K4: От 91 до 180 дней | M4: От 181 до 365 дней | O4: От 366 до 730 дней | Q4: Свыше 2 лет
C5: Сумма | D5: в том числе, в иностранной валюте (в экв. в сумах) | E5: Сумма | F5: в том числе, в иностранной валюте (в экв. в сумах) | G5: Сумма | H5: в том числе, в иностранной валюте (в экв. в сумах) | I5: Сумма | J5: в том числе, в иностранной валюте (в экв. в сумах) | K5: Сумма | L5: в том числе, в иностранной валюте (в экв. в сумах) | M5: Сумма | N5: в том числе, в иностранной валюте (в экв. в сумах) | O5: Сумма | P5: в том числе, в иностранной валюте (в экв. в сумах) | Q5: Сумма | R5: в том числе, в иностранной валюте (в экв. в сумах) | T5: в национальной валюте | U5: в иностранной валюте (в экв. в сумах) | V5: Коэффициент | W5: Сумма активов | X5: Высоко-ликвидные активы/приток | Y5: Сумма активов (в иностранной валюте) | Z5: Высоко-ликвидные активы/приток (в иностранной валюте) | AA5: Коэффициент | AB5: Сумма активов | AC5: Высоко-ликвидные активы/приток | AD5: Сумма активов (в иностранной валюте) | AE5: Высоко-ликвидные активы/приток (в иностранной валюте)
B6: АКТИВЫ
A7: 1. | B7: Кассовая наличность и другие платежные документы | C7: 220312147 | D7: 127777699 | S7: =+C7+E7+G7+I7+K7+M7+O7+Q7 -> 220312147 | T7: =+S7-U7 -> 92534448 | U7: =+D7+F7+H7+J7+L7+N7+P7+R7 -> 127777699 | V7: 1 | W7: =+S7-S8 -> 220312147 | X7: =+W7*V7 -> 220312147 | Y7: =+U7-U8 -> 127777699 | Z7: =+Y7*V7 -> 127777699 | AA7: 1 | AB7: =+S7-S8 -> 220312147 | AC7: =+AB7*AA7 -> 220312147 | AD7: =+U7-U8 -> 127777699 | AE7: =+AD7*AA7 -> 127777699
A8: 1.1 | B8: в том числе чеки и другие платежные документы | S8: =+C8+E8+G8+I8+K8+M8+O8+Q8 -> 0 | T8: =+S8-U8 -> 0 | U8: =+E8+G8+I8+K8+M8+O8+Q8+S8 -> 0
A9: 2. | B9: К получению из ЦБРУ не учитывая сумму обязательных резервов банка(ФОР) | C9: 359385307 | D9: 45448701 | S9: =+C9+E9+G9+I9+K9+M9+O9+Q9 -> 359385307 | T9: =+S9-U9 -> 313936606 | U9: =+D9+F9+H9+J9+L9+N9+P9+R9 -> 45448701 | V9: 1 | W9: =+S9 -> 359385307 | X9: =+W9*V9 -> 359385307 | Y9: =+U9 -> 45448701 | Z9: =+Y9*V9 -> 45448701 | AA9: 1 | AB9: =S9 -> 359385307 | AC9: =+AB9*AA9 -> 359385307 | AD9: =+U9 -> 45448701 | AE9: =+AD9*AA9 -> 45448701
A10: 2.1 | B10: К получению из ЦБРУ (сумма обязательных резервов банка(ФОР)) | G10: 21398086 | H10: 0 | S10: =+C10+E10+G10+I10+K10+M10+O10+Q10 -> 21398086 | T10: =+S10-U10 -> 21398086 | U10: =+D10+F10+H10+J10+L10+N10+P10+R10 -> 0 | V10: 0 | AA10: 0
A11: 3. | B11: К получению из других банков | C11: =SUM(C12:C18)-C15 -> 440531648 | D11: =SUM(D12:D18)-D15 -> 435253295 | E11: =SUM(E12:E18)-E15 -> 0 | F11: =SUM(F12:F18)-F15 -> 0 | G11: =SUM(G12:G18)-G15 -> 0 | H11: =SUM(H12:H18)-H15 -> 0 | I11: =SUM(I12:I18)-I15 -> 40000000 | J11: =SUM(J12:J18)-J15 -> 0 | ... R11: =SUM(R12:R18)-R15 -> 0 | S11: =+C11+E11+G11+I11+K11+M11+O11+Q11 -> 666431398 | T11: =+S11-U11 -> 231178103 | U11: =+D11+F11+H11+J11+L11+N11+P11+R11 -> 435253295
A12: 3.1 | B12: Кор счета в банках с низким уровнем риска (ностро) | C12: 1312439 | D12: 1312439 | S12: =+C12+E12+G12+I12+K12+M12+O12+Q12 -> 1312439 | T12: =+S12-U12 -> 0 | U12: =+D12+F12+H12+J12+L12+N12+P12+R12 -> 1312439 | V12: 1 | W12: =+C12 -> 1312439 | X12: =+W12*V12 -> 1312439 | Y12: =+D12 -> 1312439 | Z12: =+Y12*V12 -> 1312439 | AA12: 1 | AB12: =+C12 -> 1312439 | AC12: =+AB12*AA12 -> 1312439 | AD12: =+D12 -> 1312439 | AE12: =+AD12*AA12 -> 1312439
A13: 3.2 | B13: Кор счета в местных банках (ностро) имеющих кредитный рейтинг | C13: 427327794 | D13: 427327794 | S13: =+C13 -> 427327794 | T13: =+S13-U13 -> 0 | U13: =+D13 -> 427327794 | V13: 1 | W13: =+C13 -> 427327794 | X13: =+W13*V13 -> 427327794 | Y13: =+D13 -> 427327794 | Z13: =+Y13*V13 -> 427327794 | AA13: 1 | AB13: =+C13 -> 427327794 | AC13: =+AB13*AA13 -> 427327794 | AD13: =+D13 -> 427327794 | AE13: =+AD13*AA13 -> 427327794
A14: 3.3 | B14: Депозиты размещенные на условиях овернайт | S14: =+E14 -> 0 | T14: =+S14-U14 -> 0 | U14: =+F14 -> 0 | V14: 1 | W14: =+E14-E15 -> 0 | X14: =+W14*V14 -> 0 | Y14: =+F14-F15 -> 0 | Z14: =+Y14*V14 -> 0 | AA14: 1 | AB14: =+E14-E15 -> 0 | AC14: =+AB14*AA14 -> 0 | AD14: =+F14-F15 -> 0 | AE14: =+AD14*AA14 -> 0
A15: 3.3.1. | B15: в том числе депозиты размещенные на условиях овернайт в иностранной валюте с рейтингом не ниже инвестиционного. | S15: =+E15 -> 0 | T15: =+S15-U15 -> 0 | U15: =+F15 -> 0 | V15: 1 | W15: =+E15 -> 0 | X15: =+W15*V15 -> 0 | Y15: =+F15 -> 0 | Z15: =+Y15*V15 -> 0 | AA15: 1 | AB15: =+E15 -> 0 | AC15: =+AB15*AA15 -> 0 | AD15: =+F15 -> 0 | AE15: =+AD15*AA15 -> 0
A16: 3.4 | B16: К получению из других банков - депозиты | C16: 6665069 | D16: 6613062 | I16: 40000000 | K16: 47569200 | M16: 101000000 | O16: 3000000 | Q16: 34330550 | S16: =+C16+E16+G16+I16+K16+M16+O16+Q16 -> 232564819 | T16: =+S16-U16 -> 225951757 | U16: =+D16+F16+H16+J16+L16+N16+P16+R16 -> 6613062 | V16: 1 | W16: =+C16+E16+G16 -> 6665069 | X16: =+W16*V16 -> 6665069 | Y16: =+D16+F16+H16 -> 6613062 | Z16: =+Y16*V16 -> 6613062 | AA16: 1 | AB16: =+C16+E16+G16+E12+G12+E13+G13+E14-E15 -> 6665069 | AC16: =+AB16*AA16 -> 6665069 | AD16: =+D16+F16+H16+F12+H12+F13+H13+F14-F15 -> 6613062 | AE16: =+AD16*AA16 -> 6613062
A17: 3.5 | B17: К получению из других банков по расчетам пластиковых карт | C17: 4724609 | D17: 0 | S17: =+C17+E17+G17+I17+K17+M17+O17+Q17 -> 4724609 | T17: =+S17-U17 -> 4724609 | U17: =+D17+F17+H17+J17+L17+N17+P17+R17 -> 0 | V17: 0.5 | W17: =+C17+E17+G17 -> 4724609 | X17: =+W17*V17 -> 2362304.5 | Y17: =+D17+F17+H17 -> 0 | Z17: =+Y17*V17 -> 0 | AA17: 1 | AB17: =+C17+E17+G17 -> 4724609 | AC17: =+AB17*AA17 -> 4724609 | AD17: =+D17+F17+H17 -> 0 | AE17: =+AD17*AA17 -> 0
A18: 3.6 | B18: Другие статьи | C18: 501737 | D18: 0 | S18: =+C18+E18+G18+I18+K18+M18+O18+Q18 -> 501737 | T18: =+S18-U18 -> 501737 | U18: =+D18+F18+H18+J18+L18+N18+P18+R18 -> 0 | V18: 0.3 | W18: =+C18+E18+G18 -> 501737 | X18: =+W18*V18 -> 150521.1 | Y18: =+D18+F18+H18 -> 0 | Z18: =+Y18*V18 -> 0 | AA18: 1 | AB18: =+C18+E18+G18 -> 501737 | AC18: =+AB18*AA18 -> 501737 | AD18: =+D18+F18+H18 -> 0 | AE18: =+AD18*AA18 -> 0
A19: 4. | B19: Счета купли и продажи, чистые | C19: =SUM(C20:C25)-C21 -> 2938414 | D19: =SUM(D20:D25)-D21 -> 0 | E19: =SUM(E20:E25)-E21 -> 0 | F19: =SUM(F20:F25)-F21 -> 0 | G19: =SUM(G20:G25)-G21 -> 48000000 | H19: =SUM(H20:H25)-H21 -> 0 | I19: =SUM(I20:I25)-I21 -> 0 | J19: =SUM(J20:J25)-J21 -> 0 | ... R19: =SUM(R20:R25)-R21 -> 0 | S19: =+C19+E19+G19+I19+K19+M19+O19+Q19 -> 202938414 | T19: =+S19-U19 -> 202938414 | U19: =+D19+F19+H19+J19+L19+N19+P19+R19 -> 0
A20: 4.1 | B20: Ценные бумаги, выпущенные Правительством Республики Узбекистан и ЦБРУ (векселя, облигации и другие долговые ценные бумаги) | C20: 0 | D20: 0 | E20: 0 | F20: 0 | G20: 48000000 | H20: 0 | I20: 0 | J20: 0 | K20: 102000000 | L20: 0 | M20: 50000000 | N20: 0 | O20: 0 | P20: 0 | Q20: 0 | R20: 0 | S20: =+C20+E20+G20+I20+K20+M20+O20+Q20 -> 200000000 | T20: =+S20-U20 -> 200000000 | U20: =+D20+F20+H20+J20+L20+N20+P20+R20 -> 0 | V20: 1 | W20: =+S20-S21 -> 200000000 | X20: =+W20*V20 -> 200000000 | Y20: =+U20-U21 -> 0 | Z20: =+Y20*V20 -> 0 | AA20: 1 | AB20: =+S20-S21 -> 200000000 | AC20: =+AB20*AA20 -> 200000000 | AD20: =+U20-U21 -> 0 | AE20: =+AD20*AA20 -> 0
A21: 4.1.1 | B21: в том числе, Ценные бумаги, выпущенные Правительством Республики Узбекистан и ЦБРУ (векселя, облигации и другие долговые ценные бумаги) под залогом | S21: =+C21+E21+G21+I21+K21+M21+O21+Q21 -> 0 | T21: =+S21-U21 -> 0 | U21: =+D21+F21+H21+J21+L21+N21+P21+R21 -> 0 | V21: 1 | W21: =+C21+E21+G21 -> 0 | X21: =+W21*V21 -> 0 | Y21: =+D21+F21+H21 -> 0 | Z21: =+Y21*V21 -> 0 | AA21: 1 | AB21: =+C21+E21+G21 -> 0 | AC21: =+AB21*AA21 -> 0 | AD21: =+D21+F21+H21 -> 0 | AE21: =+AD21*AA21 -> 0
A22: 4.2 | B22: Правительственные ценные бумаги стран с низкой степенью странового риска | S22: =+C22+E22+G22+I22+K22+M22+O22+Q22 -> 0 | T22: =+S22-U22 -> 0 | U22: =+D22+F22+H22+J22+L22+N22+P22+R22 -> 0 | V22: 1 | W22: =+S22 -> 0 | X22: =+W22*V22 -> 0 | Y22: =+U22 -> 0 | Z22: =+Y22*V22 -> 0 | AA22: 1 | AB22: =+S22 -> 0 | AC22: =+AB22*AA22 -> 0 | AD22: =+U22 -> 0 | AE22: =+AD22*AA22 -> 0
A23: 4.3 | B23: Ценные бумаги выпущенные МВФ, входящие организации в группу Всемирного банка, МФК, АБР, Азиатский банк инфроструктуры и инвестиции, ЕБРР, Европейский инвестиционный банк, Исламский банк развития и Банк развития Европейского союза | S23: =+C23+E23+G23+I23+K23+M23+O23+Q23 -> 0 | T23: =+S23-U23 -> 0 | U23: =+D23+F23+H23+J23+L23+N23+P23+R23 -> 0 | V23: 1 | W23: =+S23 -> 0 | X23: =+W23*V23 -> 0 | Y23: =+U23 -> 0 | Z23: =+Y23*V23 -> 0 | AA23: 1 | AB23: =+S23 -> 0 | AC23: =+AB23*AA23 -> 0 | AD23: =+U23 -> 0 | AE23: =+AD23*AA23 -> 0
A24: 4.4 | B24: Ценные бумаги ведущих транснациональных компаний с рейтингом не ниже инвестиционного | S24: =+C24+E24+G24+I24+K24+M24+O24+Q24 -> 0 | T24: =+S24-U24 -> 0 | U24: =+D24+F24+H24+J24+L24+N24+P24+R24 -> 0 | V24: 1 | W24: =+S24 -> 0 | X24: =+W24*V24 -> 0 | Y24: =+U24 -> 0 | Z24: =+Y24*V24 -> 0 | AA24: 1 | AB24: =+S24 -> 0 | AC24: =+AB24*AA24 -> 0 | AD24: =+U24 -> 0 | AE24: =+AD24*AA24 -> 0
A25: 4.5 | B25: Другие | C25: 2938414 | D25: 0 | S25: =+C25+E25+G25+I25+K25+M25+O25+Q25 -> 2938414 | T25: =+S25-U25 -> 2938414 | U25: =+D25+F25+H25+J25+L25+N25+P25+R25 -> 0 | V25: 0 | AA25: 0
A26: 5. | B26: Купленные векселя, чистые | S26: =+C26+E26+G26+I26+K26+M26+O26+Q26 -> 0 | T26: =+S26-U26 -> 0 | U26: =+D26+F26+H26+J26+L26+N26+P26+R26 -> 0 | V26: 0.3 | W26: =+C26+E26+G26 -> 0 | X26: =+W26*V26 -> 0 | Y26: =+D26+F26+H26 -> 0 | Z26: =+Y26*V26 -> 0 | AA26: 0.3 | AB26: =+E26+G26 -> 0 | AC26: =+AB26*AA26 -> 0 | AD26: =+F26+H26 -> 0 | AE26: =+AD26*AA26 -> 0
A27: 6. | B27: Обязательства клиентов по траттам под аккредитивы или трастовые документы | S27: =+C27+E27+G27+I27+K27+M27+O27+Q27 -> 0 | T27: =+S27-U27 -> 0 | U27: =+D27+F27+H27+J27+L27+N27+P27+R27 -> 0 | V27: 0.3 | W27: =+C27+E27+G27 -> 0 | X27: =+W27*V27 -> 0 | Y27: =+D27+F27+H27 -> 0 | Z27: =+Y27*V27 -> 0 | AA27: 0.5 | AB27: =+E27+G27 -> 0 | AC27: =+AB27*AA27 -> 0 | AD27: =+F27+H27 -> 0 | AE27: =+AD27*AA27 -> 0
A28: 7. | B28: Обязательства клиентов по непогашенным акцептам этого банка | S28: =+C28+E28+G28+I28+K28+M28+O28+Q28 -> 0 | T28: =+S28-U28 -> 0 | U28: =+D28+F28+H28+J28+L28+N28+P28+R28 -> 0 | V28: 0.3 | W28: =+C28+E28+G28 -> 0 | X28: =+W28*V28 -> 0 | Y28: =+D28+F28+H28 -> 0 | Z28: =+Y28*V28 -> 0 | AA28: 0.3 | AB28: =+E28+G28 -> 0 | AC28: =+AB28*AA28 -> 0 | AD28: =+F28+H28 -> 0 | AE28: =+AD28*AA28 -> 0
A29: 8. | B29: Кредиты и лизинги, предоставленные ЦБРУ, чистые | S29: =+C29+E29+G29+I29+K29+M29+O29+Q29 -> 0 | T29: =+S29-U29 -> 0 | U29: =+D29+F29+H29+J29+L29+N29+P29+R29 -> 0 | V29: 1 | W29: =+C29+E29+G29 -> 0 | X29: =+W29*V29 -> 0 | Y29: =+D29+F29+H29 -> 0 | Z29: =+Y29*V29 -> 0 | AA29: 1 | AB29: =+C29+E29+G29 -> 0 | AC29: =+AB29*AA29 -> 0 | AD29: =+D29+F29+H29 -> 0 | AE29: =+AD29*AA29 -> 0
A30: 9. | B30: Кредиты и лизинги, предоставленные другим банкам, чистые | S30: =+C30+E30+G30+I30+K30+M30+O30+Q30 -> 0 | T30: =+S30-U30 -> 0 | U30: =+D30+F30+H30+J30+L30+N30+P30+R30 -> 0 | V30: 0.5 | W30: =+E30+G30 -> 0 | X30: =+W30*V30 -> 0 | Y30: =F30+H30 -> 0 | Z30: =+Y30*V30 -> 0 | AA30: 0.5 | AB30: =+E30+G30 -> 0 | AC30: =+AB30*AA30 -> 0 | AD30: =+F30+H30 -> 0 | AE30: =+AD30*AA30 -> 0
A31: 10 | B31: Кредиты и лизинги, предоставленные другим клиентам, чистые | C31: 91834482 | D31: 6369419 | E31: 157359937 | F31: 26913310 | G31: 53906229 | H31: 26913310 | I31: 640161029 | J31: 188388519 | K31: 1098984494 | L31: 397510618 | M31: 1603410225 | N31: 476527157 | O31: 2239130671 | P31: 772987367 | Q31: 2457642391 | R31: 974633680 | S31: =+C31+E31+G31+I31+K31+M31+O31+Q31 -> 8342429458 | T31: =+S31-U31 -> 5472186078 | U31: =+D31+F31+H31+J31+L31+N31+P31+R31 -> 2870243380 | V31: 0.3 | W31: =+E31+G31 -> 211266166 | X31: =+W31*V31 -> 63379850 | Y31: =F31+H31 -> 53826620 | Z31: =+Y31*V31 -> 16147986 | AA31: 0.5 | AB31: =+E31+G31 -> 211266166 | AC31: =+AB31*AA31 -> 105633083 | AD31: =+F31+H31 -> 53826620 | AE31: =+AD31*AA31 -> 26913310
A32: 10.1 | B32: в том числе, кредиты и лизинги, предоставленные физическим лицам, чистые | C32: 0 | D32: 0 | E32: 56372153 | F32: 0 | G32: 16870841 | H32: 0 | I32: 184961398 | J32: 0 | K32: 313432680 | L32: 0 | M32: 533129992 | N32: 0 | O32: 682443985 | P32: 0 | Q32: 565889805 | R32: 0 | S32: =+C32+E32+G32+I32+K32+M32+O32+Q32 -> 2353100854 | T32: =+S32-U32 -> 2353100854 | U32: =+D32+F32+H32+J32+L32+N32+P32+R32 -> 0 | V32: 0 | W32: =+E32+G32 -> 73242994 | X32: =+W32*V32 -> 0 | Y32: =F32+H32 -> 0 | Z32: =+Y32*V32 -> 0 | AA32: 0 | AB32: =+E32+G32 -> 73242994 | AC32: =+AB32*AA32 -> 0 | AD32: =+F32+H32 -> 0 | AE32: =+AD32*AA32 -> 0
A33: 11 | B33: Кредиты и лизинги и авансы в процессе судебного разбирательства, чистые | C33: -25054 | D33: 0 | S33: =+C33+E33+G33+I33+K33+M33+O33+Q33 -> -25054 | T33: =+S33-U33 -> -25054 | U33: =+D33+F33+H33+J33+L33+N33+P33+R33 -> 0 | V33: 0 | AA33: 0
A34: 12. | B34: Инвестиции, чистые | C34: 107220 | R34: 0 | S34: =+C34+E34+G34+I34+K34+M34+O34+Q34 -> 107220 | T34: =+S34-U34 -> 107220 | U34: =+D34+F34+H34+J34+L34+N34+P34+R34 -> 0 | V34: 0 | AA34: 0
A35: 13. | B35: Ценные бумаги купленные по соглашению с обратным выкупом | C35: =+C36+C37 -> 0 | D35: =+D36+D37 -> 0 | E35: =+E36+E37 -> 0 | F35: =+F36+F37 -> 0 | G35: =+G36+G37 -> 0 | H35: =+H36+H37 -> 0 | I35: =+I36+I37 -> 0 | J35: =+J36+J37 -> 0 | ... R35: =+R36+R37 -> 0 | S35: =+C35+E35+G35+I35+K35+M35+O35+Q35 -> 0 | T35: =+S35-U35 -> 0 | U35: =+D35+F35+H35+J35+L35+N35+P35+R35 -> 0
A36: 13.1 | B36: Ценные бумаги Правительства и ЦБ купленные по соглашению с обратным выкупом (РЕПО) | S36: =+C36+E36+G36+I36+K36+M36+O36+Q36 -> 0 | T36: =+S36-U36 -> 0 | U36: =+D36+F36+H36+J36+L36+N36+P36+R36 -> 0 | V36: 1 | W36: =+S36 -> 0 | X36: =+W36*V36 -> 0 | Y36: =+U36 -> 0 | Z36: =+Y36*V36 -> 0 | AA36: 1 | AB36: =+S36 -> 0 | AC36: =+AB36*AA36 -> 0 | AD36: =+U36 -> 0 | AE36: =+AD36*AA36 -> 0
A37: 13.2 | B37: Другие ценные бумаги купленные по соглашению с обратным выкупом (РЕПО) | S37: =+C37+E37+G37+I37+K37+M37+O37+Q37 -> 0 | T37: =+S37-U37 -> 0 | U37: =+D37+F37+H37+J37+L37+N37+P37+R37 -> 0 | V37: 0 | AA37: 0
A38: 14. | B38: Основные средства, чистые | C38: 201801025 | D38: 0 | S38: =+C38+E38+G38+I38+K38+M38+O38+Q38 -> 201801025 | T38: =+S38-U38 -> 201801025 | U38: =+D38+F38+H38+J38+L38+N38+P38+R38 -> 0 | V38: 0 | AA38: 0
A39: 15. | B39: Другое собственное имущество банка, чистые | S39: =+C39+E39+G39+I39+K39+M39+O39+Q39 -> 0 | T39: =+S39-U39 -> 0 | U39: =+D39+F39+H39+J39+L39+N39+P39+R39 -> 0 | V39: 0 | AA39: 0
A40: 16. | B40: Нереализованная прибыль при ревальвации по сделкам "форвард" | S40: =+C40+E40+G40+I40+K40+M40+O40+Q40 -> 0 | T40: =+S40-U40 -> 0 | U40: =+D40+F40+H40+J40+L40+N40+P40+R40 -> 0 | V40: 0 | AA40: 0
A41: 17. | B41: Счета купли-продажи валюты и валютные позиции | C41: -2562616 | S41: =+C41+E41+G41+I41+K41+M41+O41+Q41 -> -2562616 | T41: =+S41-U41 -> -2562616 | U41: =+D41+F41+H41+J41+L41+N41+P41+R41 -> 0 | V41: 0 | AA41: 0
A42: 18. | B42: Клиринговые счета | S42: =+C42+E42+G42+I42+K42+M42+O42+Q42 -> 0 | T42: =+S42-U42 -> 0 | U42: =+D42+F42+H42+J42+L42+N42+P42+R42 -> 0 | V42: 0 | AA42: 0
A43: 19. | B43: Начисленные проценты | C43: 141482748 | D43: 36061821 | G43: 41251805 | H43: 15827296 | I43: 3958301 | J43: 0 | S43: =+C43+E43+G43+I43+K43+M43+O43+Q43 -> 186692854 | T43: =+S43-U43 -> 134803737 | U43: =+D43+F43+H43+J43+L43+N43+P43+R43 -> 51889117 | V43: 0.3 | W43: =+C43+E43+G43 -> 182734553 | X43: =+W43*V43 -> 54820366 | Y43: =+D43+F43+H43 -> 51889117 | Z43: =+Y43*V43 -> 15566735 | AA43: 0.5 | AB43: =+E43+G43 -> 41251805 | AC43: =+AB43*AA43 -> 20625902 | AD43: =+F43+H43 -> 15827296 | AE43: =+AD43*AA43 -> 7913648
A44: 20. | B44: Другие активы | C44: =82382802+1624624 -> 84007426 | D44: 41170053 | S44: =+C44+E44+G44+I44+K44+M44+O44+Q44 -> 84007426 | T44: =+S44-U44 -> 42837373 | U44: =+D44+F44+H44+J44+L44+N44+P44+R44 -> 41170053 | V44: 0 | AA44: 0
A45: 21. | B45: ИТОГО АКТИВОВ | C45: =SUM(C7:C44)-C8-C11-C15-C19-C21-C32-C35 -> 1539812747 | D45: =SUM(D7:D44)-D8-D11-D15-D19-D21-D32-D35 -> 692080988 | E45: =SUM(E7:E44)-E8-E11-E15-E19-E21-E32-E35 -> 157359937 | F45: =SUM(F7:F44)-F8-F11-F15-F19-F21-F32-F35 -> 26913310 | G45: =SUM(G7:G44)-G8-G11-G15-G19-G21-G32-G35 -> 164556120 | H45: =SUM(H7:H44)-H8-H11-H15-H19-H21-H32-H35 -> 42740606 | I45: =SUM(I7:I44)-I8-I11-I15-I19-I21-I32-I35 -> 684119330 | J45: =SUM(J7:J44)-J8-J11-J15-J19-J21-J32-J35 -> 188388519 | ... R45: =SUM(R7:R44)-R8-R11-R15-R19-R21-R32-R35 -> 974633680 | S45: =+C45+E45+G45+I45+K45+M45+O45+Q45 -> 10282915665 | T45: =+S45-U45 -> 6711133420 | U45: =+D45+F45+H45+J45+L45+N45+P45+R45 -> 3571782245 | X45: =SUM(X7:X44)-X11-X35 -> 1.3357158e+09 | Z45: =SUM(Z7:Z44)-Z11-Z35 -> 6.4019442e+08 | AC45: =SUM(AC7:AC44)-AC11-AC35 -> 1.3464881e+09 | AE45: =SUM(AE7:AE44)-AE11-AE35 -> 643306653
B46: забалансовые обязательства
B47: Обязательства по выдаче кредита (91809) | S47: =+C47+E47+G47+I47+K47+M47+O47+Q47 -> 0 | T47: =+S47-U47 -> 0 | U47: =+D47+F47+H47+J47+L47+N47+P47+R47 -> 0
B48: Гарантии и поручительства (90993) | S48: =+C48+E48+G48+I48+K48+M48+O48+Q48 -> 0 | T48: =+S48-U48 -> 0 | U48: =+D48+F48+H48+J48+L48+N48+P48+R48 -> 0
B49: Аккредитивы (90908-90958) | S49: =+C49+E49+G49+I49+K49+M49+O49+Q49 -> 0 | T49: =+S49-U49 -> 0 | U49: =+D49+F49+H49+J49+L49+N49+P49+R49 -> 0
B50: Форврдные котракты, свопы, опционы и подобные обязательства (92705,92716,92728,92736) | S50: =+C50+E50+G50+I50+K50+M50+O50+Q50 -> 0 | T50: =+S50-U50 -> 0 | U50: =+D50+F50+H50+J50+L50+N50+P50+R50 -> 0
B53: Подпись Председателя правления:
B55: Подпись Главного Бухгалтера:
W56: По действующим расчетам | AB56: По новым расчетам
W57: =+Balance!C45 -> 10282915665 | X57: =+Balance!D45 -> 6711133420 | Y57: =+Balance!E45 -> 3571782245 | AB57: =+Balance!C45 -> 10282915665 | AC57: =+Balance!D45 -> 6711133420 | AD57: =+Balance!E45 -> 3571782245
W58: Всего | Y58: Ин вал | AB58: Всего | AD58: Ин вал
W59: Приток | X59: =+X45-X60 -> 1.2737811e+08 | Y59: Приток | Z59: =+Z45-Z60 -> 38327783 | AB59: Приток | AC59: =+AC45-AC60 -> 1.381504e+08 | AD59: Приток | AE59: =+AE45-AE60 -> 41440020
W60: Высоко-ликвидные активы | X60: =+X7+X9+X12+X13+X15+X20+X22+X23+X24+X36 -> 1208337687 | Y60: Высоко-ликвидные активы | Z60: =+Z7+Z9+Z12+Z13+Z15+Z20+Z22+Z23+Z24+Z36 -> 601866633 | AB60: Высоко-ликвидные активы | AC60: =+AC7+AC9+AC12+AC13+AC15+AC20+AC22+AC23+AC24+AC36 -> 1208337687 | AD60: Высоко-ликвидные активы | AE60: =+AE7+AE9+AE12+AE13+AE15+AE20+AE22+AE23+AE24+AE36 -> 601866633
W61: Чистый отток за 30 дней | X61: =+X63-X64 -> 5.9333548e+08 | Y61: Чистый отток за 30 дней | Z61: =+Z63-Z64 -> 1.5517616e+08 | AB61: Чистый отток за 30 дней | AC61: =+AC63-AC66 -> 1.1961617e+09 | AD61: Чистый отток за 30 дней | AE61: =+AE63-AE66 -> 4.9892098e+08
W63: Отток | X63: =+'Bank Liabilities Analysis'!X39 -> 7.2071359e+08 | Y63: Отток | Z63: =+'Bank Liabilities Analysis'!Z39 -> 1.9350394e+08 | AB63: Всего отток | AC63: =+'Bank Liabilities Analysis'!AB39+'Liquidity Analysis'!C43 -> 1.3343121e+09 | AD63: Отток | AE63: =+'Bank Liabilities Analysis'!AC39+'Liquidity Analysis'!E43 -> 5.40361e+08
W64: Приток по положению | X64: =IF(X59>(X63*0.75),X63*0.75,X59) -> 1.2737811e+08 | Y64: Приток по положению | Z64: =IF(Z59>(Z63*0.75),Z63*0.75,Z59) -> 38327783 | AB64: в том числе отток по внебалансу | AC64: =+'Liquidity Analysis'!C43 -> 144445704 | AD64: в том числе отток по внебалансу | AE64: =+'Liquidity Analysis'!E43 -> 93234472
AB66: Приток по положению | AC66: =IF(AC59>(AC63*0.75),AC63*0.75,AC59) -> 1.381504e+08 | AD66: Приток по положению | AE66: =IF(AE59>(AE63*0.75),AE63*0.75,AE59) -> 41440020

Sheet Bank Assets Analysis (нац)
A2: АНАЛИЗ АКТИВОВ БАНКА В НАЦИОНАЛЬНОЙ ВАЛЮТЕ | O2: Таблица-17А
B3: =Balance!B3 -> АКБ"Микрокредитбанк" | J3: =+Balance!B2 -> 31 Декабрь, 2020 | Q3: =+Balance!E3 -> тыс. сум
A4: № | B4: Характеристики | C4: Срок погашения (в днях) | K4: ВСЕГО | L4: Расчет коэффициента покрытия ликвидности (действующий норматив) | O4: Расчет коэффициента покрытия ликвидности (внедряемый норматив)
C5: Бессрочные | D5: От 1 до 7 дней | E5: От 8 до 30 дней | F5: От 31 до 90 дней | G5: От 91 до 180 дней | H5: От 181 до 365 дней | I5: От 366 до 730 дней | J5: Свыше 2 лет | L5: Коэффициент | M5: Сумма активов | N5: Высоко-ликвидные активы/приток | O5: Коэффициент | P5: Сумма активов | Q5: Высоко-ликвидные активы/приток
B6: АКТИВЫ
A7: 1. | B7: Наличность и другие кассовые документы | C7: =+'Bank Assets Analysis'!C7-'Bank Assets Analysis'!D7 -> 92534448 | D7: =+'Bank Assets Analysis'!E7-'Bank Assets Analysis'!F7 -> 0 | E7: =+'Bank Assets Analysis'!G7-'Bank Assets Analysis'!H7 -> 0 | F7: =+'Bank Assets Analysis'!I7-'Bank Assets Analysis'!J7 -> 0 | G7: =+'Bank Assets Analysis'!K7-'Bank Assets Analysis'!L7 -> 0 | H7: =+'Bank Assets Analysis'!M7-'Bank Assets Analysis'!N7 -> 0 | I7: =+'Bank Assets Analysis'!O7-'Bank Assets Analysis'!P7 -> 0 | J7: =+'Bank Assets Analysis'!Q7-'Bank Assets Analysis'!R7 -> 0 | K7: =+C7+D7+E7+F7+G7+H7+I7+J7 -> 92534448 | L7: 1 | M7: =+K7-K8 -> 92534448 | N7: =+M7*L7 -> 92534448 | O7: 1 | P7: =+K7-K8 -> 92534448 | Q7: =+P7*O7 -> 92534448
A8: 1.1 | B8: в том числе чеки и другие платежные документы | C8: =+'Bank Assets Analysis'!C8-'Bank Assets Analysis'!D8 -> 0 | D8: =+'Bank Assets Analysis'!E8-'Bank Assets Analysis'!F8 -> 0 | E8: =+'Bank Assets Analysis'!G8-'Bank Assets Analysis'!H8 -> 0 | F8: =+'Bank Assets Analysis'!I8-'Bank Assets Analysis'!J8 -> 0 | G8: =+'Bank Assets Analysis'!K8-'Bank Assets Analysis'!L8 -> 0 | H8: =+'Bank Assets Analysis'!M8-'Bank Assets Analysis'!N8 -> 0 | I8: =+'Bank Assets Analysis'!O8-'Bank Assets Analysis'!P8 -> 0 | J8: =+'Bank Assets Analysis'!Q8-'Bank Assets Analysis'!R8 -> 0 | K8: =+C8+D8+E8+F8+G8+H8+I8+J8 -> 0 | L8: 0 | O8: 0
A9: 2. | B9: К получению из ЦБРУ не учитывая сумму обязательных резервов банка(ФОР) | C9: =+'Bank Assets Analysis'!C9-'Bank Assets Analysis'!D9 -> 313936606 | D9: =+'Bank Assets Analysis'!E9-'Bank Assets Analysis'!F9 -> 0 | E9: =+'Bank Assets Analysis'!G9-'Bank Assets Analysis'!H9 -> 0 | F9: =+'Bank Assets Analysis'!I9-'Bank Assets Analysis'!J9 -> 0 | G9: =+'Bank Assets Analysis'!K9-'Bank Assets Analysis'!L9 -> 0 | H9: =+'Bank Assets Analysis'!M9-'Bank Assets Analysis'!N9 -> 0 | I9: =+'Bank Assets Analysis'!O9-'Bank Assets Analysis'!P9 -> 0 | J9: =+'Bank Assets Analysis'!Q9-'Bank Assets Analysis'!R9 -> 0 | K9: =+C9+D9+E9+F9+G9+H9+I9+J9 -> 313936606 | L9: 1 | M9: =+K9 -> 313936606 | N9: =+M9*L9 -> 313936606 | O9: 1 | P9: =+K9 -> 313936606 | Q9: =+P9*O9 -> 313936606
A10: 2.1 | B10: К получению из ЦБРУ (сумма обязательных резервов банка(ФОР)) | C10: =+'Bank Assets Analysis'!C10-'Bank Assets Analysis'!D10 -> 0 | D10: =+'Bank Assets Analysis'!E10-'Bank Assets Analysis'!F10 -> 0 | E10: =+'Bank Assets Analysis'!G10-'Bank Assets Analysis'!H10 -> 21398086 | F10: =+'Bank Assets Analysis'!I10-'Bank Assets Analysis'!J10 -> 0 | G10: =+'Bank Assets Analysis'!K10-'Bank Assets Analysis'!L10 -> 0 | H10: =+'Bank Assets Analysis'!M10-'Bank Assets Analysis'!N10 -> 0 | I10: =+'Bank Assets Analysis'!O10-'Bank Assets Analysis'!P10 -> 0 | J10: =+'Bank Assets Analysis'!Q10-'Bank Assets Analysis'!R10 -> 0 | K10: =+C10+D10+E10+F10+G10+H10+I10+J10 -> 21398086 | L10: 0 | N10: =+M10*L10 -> 0 | O10: 0 | Q10: =+P10*O10 -> 0
A11: 3. | B11: К получению из других банков | C11: =SUM(C12:C18)-C15 -> 5278353 | D11: =SUM(D12:D18)-D15 -> 0 | E11: =SUM(E12:E18)-E15 -> 0 | F11: =SUM(F12:F18)-F15 -> 40000000 | G11: =SUM(G12:G18)-G15 -> 47569200 | H11: =SUM(H12:H18)-H15 -> 101000000 | I11: =SUM(I12:I18)-I15 -> 3000000 | J11: =SUM(J12:J18)-J15 -> 34330550 | K11: =+C11+D11+E11+F11+G11+H11+I11+J11 -> 231178103 | N11: =+M11*L11 -> 0 | Q11: =+P11*O11 -> 0
A12: 3.1 | B12: К получению со счетов в банках стран с низким уровнем риска (ностро, депозиты), но размещенные не в качестве обеспечения | C12: =+'Bank Assets Analysis'!C12-'Bank Assets Analysis'!D12 -> 0 | D12: =+'Bank Assets Analysis'!E12-'Bank Assets Analysis'!F12 -> 0 | E12: =+'Bank Assets Analysis'!G12-'Bank Assets Analysis'!H12 -> 0 | F12: =+'Bank Assets Analysis'!I12-'Bank Assets Analysis'!J12 -> 0 | G12: =+'Bank Assets Analysis'!K12-'Bank Assets Analysis'!L12 -> 0 | H12: =+'Bank Assets Analysis'!M12-'Bank Assets Analysis'!N12 -> 0 | I12: =+'Bank Assets Analysis'!O12-'Bank Assets Analysis'!P12 -> 0 | J12: =+'Bank Assets Analysis'!Q12-'Bank Assets Analysis'!R12 -> 0 | K12: =+C12+D12+E12+F12+G12+H12+I12+J12 -> 0 | L12: 1 | M12: =+C12 -> 0 | N12: =+M12*L12 -> 0 | O12: 1 | P12: =+C12 -> 0 | Q12: =+P12*O12 -> 0
A13: 3.2 | B13: Депозиты размещенные в местных банках имеющие рейтинг не ниже В- или В3 | C13: =+'Bank Assets Analysis'!C13-'Bank Assets Analysis'!D13 -> 0 | D13: =+'Bank Assets Analysis'!E13-'Bank Assets Analysis'!F13 -> 0 | E13: =+'Bank Assets Analysis'!G13-'Bank Assets Analysis'!H13 -> 0 | F13: =+'Bank Assets Analysis'!I13-'Bank Assets Analysis'!J13 -> 0 | G13: =+'Bank Assets Analysis'!K13-'Bank Assets Analysis'!L13 -> 0 | H13: =+'Bank Assets Analysis'!M13-'Bank Assets Analysis'!N13 -> 0 | I13: =+'Bank Assets Analysis'!O13-'Bank Assets Analysis'!P13 -> 0 | J13: =+'Bank Assets Analysis'!Q13-'Bank Assets Analysis'!R13 -> 0 | K13: =+C13+D13+E13+F13+G13+H13+I13+J13 -> 0 | L13: 1 | M13: =+C13 -> 0 | N13: =+M13*L13 -> 0 | O13: 1 | P13: =+C13 -> 0 | Q13: =+P13*O13 -> 0
A14: 3.3 | B14: Депозиты размещенные на условиях овернайт | C14: =+'Bank Assets Analysis'!C14-'Bank Assets Analysis'!D14 -> 0 | D14: =+'Bank Assets Analysis'!E14-'Bank Assets Analysis'!F14 -> 0 | E14: =+'Bank Assets Analysis'!G14-'Bank Assets Analysis'!H14 -> 0 | F14: =+'Bank Assets Analysis'!I14-'Bank Assets Analysis'!J14 -> 0 | G14: =+'Bank Assets Analysis'!K14-'Bank Assets Analysis'!L14 -> 0 | H14: =+'Bank Assets Analysis'!M14-'Bank Assets Analysis'!N14 -> 0 | I14: =+'Bank Assets Analysis'!O14-'Bank Assets Analysis'!P14 -> 0 | J14: =+'Bank Assets Analysis'!Q14-'Bank Assets Analysis'!R14 -> 0 | K14: =+C14+D14+E14+F14+G14+H14+I14+J14 -> 0 | L14: 1 | M14: =+C14-C15 -> 0 | N14: =+M14*L14 -> 0 | O14: 1 | P14: =+C14-C15 -> 0 | Q14: =+P14*O14 -> 0
A15: 3.3.1. | B15: в том числе Депозиты размещенные на условиях овернайт в иностранной валюте с рейтингом не ниже инвестиционного. | C15: =+'Bank Assets Analysis'!C15-'Bank Assets Analysis'!D15 -> 0 | D15: =+'Bank Assets Analysis'!E15-'Bank Assets Analysis'!F15 -> 0 | E15: =+'Bank Assets Analysis'!G15-'Bank Assets Analysis'!H15 -> 0 | F15: =+'Bank Assets Analysis'!I15-'Bank Assets Analysis'!J15 -> 0 | G15: =+'Bank Assets Analysis'!K15-'Bank Assets Analysis'!L15 -> 0 | H15: =+'Bank Assets Analysis'!M15-'Bank Assets Analysis'!N15 -> 0 | I15: =+'Bank Assets Analysis'!O15-'Bank Assets Analysis'!P15 -> 0 | J15: =+'Bank Assets Analysis'!Q15-'Bank Assets Analysis'!R15 -> 0 | K15: =+C15+D15+E15+F15+G15+H15+I15+J15 -> 0 | L15: 1 | M15: =+D15 -> 0 | N15: =+M15*L15 -> 0 | O15: 1 | P15: =+C15 -> 0 | Q15: =+P15*O15 -> 0
A16: 3.4 | B16: К получению из других банков - депозиты | C16: =+'Bank Assets Analysis'!C16-'Bank Assets Analysis'!D16 -> 52007 | D16: =+'Bank Assets Analysis'!E16-'Bank Assets Analysis'!F16 -> 0 | E16: =+'Bank Assets Analysis'!G16-'Bank Assets Analysis'!H16 -> 0 | F16: =+'Bank Assets Analysis'!I16-'Bank Assets Analysis'!J16 -> 40000000 | G16: =+'Bank Assets Analysis'!K16-'Bank Assets Analysis'!L16 -> 47569200 | H16: =+'Bank Assets Analysis'!M16-'Bank Assets Analysis'!N16 -> 101000000 | I16: =+'Bank Assets Analysis'!O16-'Bank Assets Analysis'!P16 -> 3000000 | J16: =+'Bank Assets Analysis'!Q16-'Bank Assets Analysis'!R16 -> 34330550 | K16: =+C16+D16+E16+F16+G16+H16+I16+J16 -> 225951757 | L16: 1 | M16: =+C16+D16+E16 -> 52007 | N16: =+M16*L16 -> 52007 | O16: 1 | P16: =+C16+D16+E16+D12+D13+D14-D15 -> 52007 | Q16: =+P16*O16 -> 52007
A17: 3.5 | B17: К получению из других банков по расчетам пластиковых карт | C17: =+'Bank Assets Analysis'!C17-'Bank Assets Analysis'!D17 -> 4724609 | D17: =+'Bank Assets Analysis'!E17-'Bank Assets Analysis'!F17 -> 0 | E17: =+'Bank Assets Analysis'!G17-'Bank Assets Analysis'!H17 -> 0 | F17: =+'Bank Assets Analysis'!I17-'Bank Assets Analysis'!J17 -> 0 | G17: =+'Bank Assets Analysis'!K17-'Bank Assets Analysis'!L17 -> 0 | H17: =+'Bank Assets Analysis'!M17-'Bank Assets Analysis'!N17 -> 0 | I17: =+'Bank Assets Analysis'!O17-'Bank Assets Analysis'!P17 -> 0 | J17: =+'Bank Assets Analysis'!Q17-'Bank Assets Analysis'!R17 -> 0 | K17: =+C17+D17+E17+F17+G17+H17+I17+J17 -> 4724609 | L17: 0.5 | M17: =+C17+D17+E17 -> 4724609 | N17: =+M17*L17 -> 2362304.5 | O17: 1 | P17: =+C17+D17+E17 -> 4724609 | Q17: =+P17*O17 -> 4724609
A18: 3.6 | B18: Другие статьи | C18: =+'Bank Assets Analysis'!C18-'Bank Assets Analysis'!D18 -> 501737 | D18: =+'Bank Assets Analysis'!E18-'Bank Assets Analysis'!F18 -> 0 | E18: =+'Bank Assets Analysis'!G18-'Bank Assets Analysis'!H18 -> 0 | F18: =+'Bank Assets Analysis'!I18-'Bank Assets Analysis'!J18 -> 0 | G18: =+'Bank Assets Analysis'!K18-'Bank Assets Analysis'!L18 -> 0 | H18: =+'Bank Assets Analysis'!M18-'Bank Assets Analysis'!N18 -> 0 | I18: =+'Bank Assets Analysis'!O18-'Bank Assets Analysis'!P18 -> 0 | J18: =+'Bank Assets Analysis'!Q18-'Bank Assets Analysis'!R18 -> 0 | K18: =+C18+D18+E18+F18+G18+H18+I18+J18 -> 501737 | L18: 0.3 | M18: =+C18+D18+E18 -> 501737 | N18: =+M18*L18 -> 150521.1 | O18: 1 | P18: =+C18+D18+E18 -> 501737 | Q18: =+P18*O18 -> 501737
A19: 4. | B19: Счета купли и продажи, чистые | C19: =SUM(C20:C25)-C21 -> 2938414 | D19: =SUM(D20:D25)-D21 -> 0 | E19: =SUM(E20:E25)-E21 -> 48000000 | F19: =SUM(F20:F25)-F21 -> 0 | G19: =SUM(G20:G25)-G21 -> 102000000 | H19: =SUM(H20:H25)-H21 -> 50000000 | I19: =SUM(I20:I25)-I21 -> 0 | J19: =SUM(J20:J25)-J21 -> 0 | K19: =+C19+D19+E19+F19+G19+H19+I19+J19 -> 202938414 | N19: =+M19*L19 -> 0 | Q19: =+P19*O19 -> 0
A20: 4.1 | B20: Ценные бумаги, выпущенные Правительством Республики Узбекистан и ЦБРУ (векселя, облигации и другие долговые ценные бумаги) | C20: =+'Bank Assets Analysis'!C20-'Bank Assets Analysis'!D20 -> 0 | D20: =+'Bank Assets Analysis'!E20-'Bank Assets Analysis'!F20 -> 0 | E20: =+'Bank Assets Analysis'!G20-'Bank Assets Analysis'!H20 -> 48000000 | F20: =+'Bank Assets Analysis'!I20-'Bank Assets Analysis'!J20 -> 0 | G20: =+'Bank Assets Analysis'!K20-'Bank Assets Analysis'!L20 -> 102000000 | H20: =+'Bank Assets Analysis'!M20-'Bank Assets Analysis'!N20 -> 50000000 | I20: =+'Bank Assets Analysis'!O20-'Bank Assets Analysis'!P20 -> 0 | J20: =+'Bank Assets Analysis'!Q20-'Bank Assets Analysis'!R20 -> 0 | K20: =+C20+D20+E20+F20+G20+H20+I20+J20 -> 200000000 | L20: 1 | M20: =+K20-K21 -> 200000000 | N20: =+M20*L20 -> 200000000 | O20: 1 | P20: =+K20-K21 -> 200000000 | Q20: =+P20*O20 -> 200000000
A21: 4.1.1 | B21: в том числе, Ценные бумаги, выпущенные Правительством Республики Узбекистан и ЦБРУ (векселя, облигации и другие долговые ценные бумаги) под залогом | C21: =+'Bank Assets Analysis'!C21-'Bank Assets Analysis'!D21 -> 0 | D21: =+'Bank Assets Analysis'!E21-'Bank Assets Analysis'!F21 -> 0 | E21: =+'Bank Assets Analysis'!G21-'Bank Assets Analysis'!H21 -> 0 | F21: =+'Bank Assets Analysis'!I21-'Bank Assets Analysis'!J21 -> 0 | G21: =+'Bank Assets Analysis'!K21-'Bank Assets Analysis'!L21 -> 0 | H21: =+'Bank Assets Analysis'!M21-'Bank Assets Analysis'!N21 -> 0 | I21: =+'Bank Assets Analysis'!O21-'Bank Assets Analysis'!P21 -> 0 | J21: =+'Bank Assets Analysis'!Q21-'Bank Assets Analysis'!R21 -> 0 | K21: =+C21+D21+E21+F21+G21+H21+I21+J21 -> 0 | L21: 1 | M21: =SUM(C21:E21) -> 0 | N21: =+M21*L21 -> 0 | O21: 1 | P21: =SUM(C21:E21) -> 0 | Q21: =+P21*O21 -> 0
A22: 4.2 | B22: Правительственные ценные бумаги стран с низкой степенью странового риска | C22: =+'Bank Assets Analysis'!C22-'Bank Assets Analysis'!D22 -> 0 | D22: =+'Bank Assets Analysis'!E22-'Bank Assets Analysis'!F22 -> 0 | E22: =+'Bank Assets Analysis'!G22-'Bank Assets Analysis'!H22 -> 0 | F22: =+'Bank Assets Analysis'!I22-'Bank Assets Analysis'!J22 -> 0 | G22: =+'Bank Assets Analysis'!K22-'Bank Assets Analysis'!L22 -> 0 | H22: =+'Bank Assets Analysis'!M22-'Bank Assets Analysis'!N22 -> 0 | I22: =+'Bank Assets Analysis'!O22-'Bank Assets Analysis'!P22 -> 0 | J22: =+'Bank Assets Analysis'!Q22-'Bank Assets Analysis'!R22 -> 0 | K22: =+C22+D22+E22+F22+G22+H22+I22+J22 -> 0 | L22: 1 | M22: =+K22 -> 0 | N22: =+M22*L22 -> 0 | O22: 1 | P22: =+K22 -> 0 | Q22: =+P22*O22 -> 0
A23: 4.3 | B23: Ценные бумаги выпущенные МВФ, входящие организации в группу Всемирного банка, МФК, АБР, Азиатский банк инфроструктуры и инвестиции, ЕБРР, Европейский инвестиционный банк, Исламский банк развития и Банк развития Европейского союза | C23: =+'Bank Assets Analysis'!C23-'Bank Assets Analysis'!D23 -> 0 | D23: =+'Bank Assets Analysis'!E23-'Bank Assets Analysis'!F23 -> 0 | E23: =+'Bank Assets Analysis'!G23-'Bank Assets Analysis'!H23 -> 0 | F23: =+'Bank Assets Analysis'!I23-'Bank Assets Analysis'!J23 -> 0 | G23: =+'Bank Assets Analysis'!K23-'Bank Assets Analysis'!L23 -> 0 | H23: =+'Bank Assets Analysis'!M23-'Bank Assets Analysis'!N23 -> 0 | I23: =+'Bank Assets Analysis'!O23-'Bank Assets Analysis'!P23 -> 0 | J23: =+'Bank Assets Analysis'!Q23-'Bank Assets Analysis'!R23 -> 0 | K23: =+C23+D23+E23+F23+G23+H23+I23+J23 -> 0 | L23: 1 | M23: =+K23 -> 0 | N23: =+M23*L23 -> 0 | O23: 1 | P23: =+K23 -> 0 | Q23: =+P23*O23 -> 0
A24: 4.4 | B24: Ценные бумаги ведущих транснациональных компаний с низким уровнем странового риска | C24: =+'Bank Assets Analysis'!C24-'Bank Assets Analysis'!D24 -> 0 | D24: =+'Bank Assets Analysis'!E24-'Bank Assets Analysis'!F24 -> 0 | E24: =+'Bank Assets Analysis'!G24-'Bank Assets Analysis'!H24 -> 0 | F24: =+'Bank Assets Analysis'!I24-'Bank Assets Analysis'!J24 -> 0 | G24: =+'Bank Assets Analysis'!K24-'Bank Assets Analysis'!L24 -> 0 | H24: =+'Bank Assets Analysis'!M24-'Bank Assets Analysis'!N24 -> 0 | I24: =+'Bank Assets Analysis'!O24-'Bank Assets Analysis'!P24 -> 0 | J24: =+'Bank Assets Analysis'!Q24-'Bank Assets Analysis'!R24 -> 0 | K24: =+C24+D24+E24+F24+G24+H24+I24+J24 -> 0 | L24: 1 | M24: =+K24 -> 0 | N24: =+M24*L24 -> 0 | O24: 1 | P24: =+D24+E24 -> 0 | Q24: =+P24*O24 -> 0
A25: 4.5 | B25: Другие | C25: =+'Bank Assets Analysis'!C25-'Bank Assets Analysis'!D25 -> 2938414 | D25: =+'Bank Assets Analysis'!E25-'Bank Assets Analysis'!F25 -> 0 | E25: =+'Bank Assets Analysis'!G25-'Bank Assets Analysis'!H25 -> 0 | F25: =+'Bank Assets Analysis'!I25-'Bank Assets Analysis'!J25 -> 0 | G25: =+'Bank Assets Analysis'!K25-'Bank Assets Analysis'!L25 -> 0 | H25: =+'Bank Assets Analysis'!M25-'Bank Assets Analysis'!N25 -> 0 | I25: =+'Bank Assets Analysis'!O25-'Bank Assets Analysis'!P25 -> 0 | J25: =+'Bank Assets Analysis'!Q25-'Bank Assets Analysis'!R25 -> 0 | K25: =+C25+D25+E25+F25+G25+H25+I25+J25 -> 2938414 | L25: 0 | O25: 0
A26: 5. | B26: Купленные векселя, чистые | C26: =+'Bank Assets Analysis'!C26-'Bank Assets Analysis'!D26 -> 0 | D26: =+'Bank Assets Analysis'!E26-'Bank Assets Analysis'!F26 -> 0 | E26: =+'Bank Assets Analysis'!G26-'Bank Assets Analysis'!H26 -> 0 | F26: =+'Bank Assets Analysis'!I26-'Bank Assets Analysis'!J26 -> 0 | G26: =+'Bank Assets Analysis'!K26-'Bank Assets Analysis'!L26 -> 0 | H26: =+'Bank Assets Analysis'!M26-'Bank Assets Analysis'!N26 -> 0 | I26: =+'Bank Assets Analysis'!O26-'Bank Assets Analysis'!P26 -> 0 | J26: =+'Bank Assets Analysis'!Q26-'Bank Assets Analysis'!R26 -> 0 | K26: =+C26+D26+E26+F26+G26+H26+I26+J26 -> 0 | L26: 0.3 | M26: =+C26+D26+E26 -> 0 | N26: =+M26*L26 -> 0 | O26: 0.3 | P26: =+D26+E26 -> 0 | Q26: =+P26*O26 -> 0
A27: 6. | B27: Обязательства клиентов по траттам под аккредитивы или трастовые документы | C27: =+'Bank Assets Analysis'!C27-'Bank Assets Analysis'!D27 -> 0 | D27: =+'Bank Assets Analysis'!E27-'Bank Assets Analysis'!F27 -> 0 | E27: =+'Bank Assets Analysis'!G27-'Bank Assets Analysis'!H27 -> 0 | F27: =+'Bank Assets Analysis'!I27-'Bank Assets Analysis'!J27 -> 0 | G27: =+'Bank Assets Analysis'!K27-'Bank Assets Analysis'!L27 -> 0 | H27: =+'Bank Assets Analysis'!M27-'Bank Assets Analysis'!N27 -> 0 | I27: =+'Bank Assets Analysis'!O27-'Bank Assets Analysis'!P27 -> 0 | J27: =+'Bank Assets Analysis'!Q27-'Bank Assets Analysis'!R27 -> 0 | K27: =+C27+D27+E27+F27+G27+H27+I27+J27 -> 0 | L27: 0.3 | M27: =+C27+D27+E27 -> 0 | N27: =+M27*L27 -> 0 | O27: 0.3 | P27: =+D27+E27 -> 0 | Q27: =+P27*O27 -> 0
A28: 7. | B28: Обязательства клиентов по непогашенным акцептам этого банка | C28: =+'Bank Assets Analysis'!C28-'Bank Assets Analysis'!D28 -> 0 | D28: =+'Bank Assets Analysis'!E28-'Bank Assets Analysis'!F28 -> 0 | E28: =+'Bank Assets Analysis'!G28-'Bank Assets Analysis'!H28 -> 0 | F28: =+'Bank Assets Analysis'!I28-'Bank Assets Analysis'!J28 -> 0 | G28: =+'Bank Assets Analysis'!K28-'Bank Assets Analysis'!L28 -> 0 | H28: =+'Bank Assets Analysis'!M28-'Bank Assets Analysis'!N28 -> 0 | I28: =+'Bank Assets Analysis'!O28-'Bank Assets Analysis'!P28 -> 0 | J28: =+'Bank Assets Analysis'!Q28-'Bank Assets Analysis'!R28 -> 0 | K28: =+C28+D28+E28+F28+G28+H28+I28+J28 -> 0 | L28: 0.3 | M28: =+C28+D28+E28 -> 0 | N28: =+M28*L28 -> 0 | O28: 0.3 | P28: =+D28+E28 -> 0 | Q28: =+P28*O28 -> 0
A29: 8. | B29: Кредиты и лизинги, предоставленные ЦБРУ, чистые | C29: =+'Bank Assets Analysis'!C29-'Bank Assets Analysis'!D29 -> 0 | D29: =+'Bank Assets Analysis'!E29-'Bank Assets Analysis'!F29 -> 0 | E29: =+'Bank Assets Analysis'!G29-'Bank Assets Analysis'!H29 -> 0 | F29: =+'Bank Assets Analysis'!I29-'Bank Assets Analysis'!J29 -> 0 | G29: =+'Bank Assets Analysis'!K29-'Bank Assets Analysis'!L29 -> 0 | H29: =+'Bank Assets Analysis'!M29-'Bank Assets Analysis'!N29 -> 0 | I29: =+'Bank Assets Analysis'!O29-'Bank Assets Analysis'!P29 -> 0 | J29: =+'Bank Assets Analysis'!Q29-'Bank Assets Analysis'!R29 -> 0 | K29: =+C29+D29+E29+F29+G29+H29+I29+J29 -> 0 | L29: 1 | M29: =+C29+D29+E29 -> 0 | N29: =+M29*L29 -> 0 | O29: 1 | P29: =C29+D29+E29 -> 0 | Q29: =+P29*O29 -> 0
A30: 9. | B30: Кредиты и лизинги, предоставленные другим банкам, чистые | C30: =+'Bank Assets Analysis'!C30-'Bank Assets Analysis'!D30 -> 0 | D30: =+'Bank Assets Analysis'!E30-'Bank Assets Analysis'!F30 -> 0 | E30: =+'Bank Assets Analysis'!G30-'Bank Assets Analysis'!H30 -> 0 | F30: =+'Bank Assets Analysis'!I30-'Bank Assets Analysis'!J30 -> 0 | G30: =+'Bank Assets Analysis'!K30-'Bank Assets Analysis'!L30 -> 0 | H30: =+'Bank Assets Analysis'!M30-'Bank Assets Analysis'!N30 -> 0 | I30: =+'Bank Assets Analysis'!O30-'Bank Assets Analysis'!P30 -> 0 | J30: =+'Bank Assets Analysis'!Q30-'Bank Assets Analysis'!R30 -> 0 | K30: =+C30+D30+E30+F30+G30+H30+I30+J30 -> 0 | L30: 0.5 | M30: =D30+E30 -> 0 | N30: =+M30*L30 -> 0 | O30: 0.5 | P30: =+D30+E30 -> 0 | Q30: =+P30*O30 -> 0
A31: 10 | B31: Кредиты и лизинги, предоставленные другим клиентам, чистые | C31: =+'Bank Assets Analysis'!C31-'Bank Assets Analysis'!D31 -> 85465063 | D31: =+'Bank Assets Analysis'!E31-'Bank Assets Analysis'!F31 -> 130446627 | E31: =+'Bank Assets Analysis'!G31-'Bank Assets Analysis'!H31 -> 26992919 | F31: =+'Bank Assets Analysis'!I31-'Bank Assets Analysis'!J31 -> 451772510 | G31: =+'Bank Assets Analysis'!K31-'Bank Assets Analysis'!L31 -> 701473876 | H31: =+'Bank Assets Analysis'!M31-'Bank Assets Analysis'!N31 -> 1126883068 | I31: =+'Bank Assets Analysis'!O31-'Bank Assets Analysis'!P31 -> 1466143304 | J31: =+'Bank Assets Analysis'!Q31-'Bank Assets Analysis'!R31 -> 1483008711 | K31: =+C31+D31+E31+F31+G31+H31+I31+J31 -> 5472186078 | L31: 0.3 | M31: =D31+E31 -> 157439546 | N31: =+M31*L31 -> 47231864 | O31: 0.5 | P31: =+D31+E31 -> 157439546 | Q31: =+P31*O31 -> 78719773
A32: 10.1 | B32: в том числе, кредиты и лизинги, предоставленные физическим лицам, чистые | C32: =+'Bank Assets Analysis'!C32-'Bank Assets Analysis'!D32 -> 0 | D32: =+'Bank Assets Analysis'!E32-'Bank Assets Analysis'!F32 -> 56372153 | E32: =+'Bank Assets Analysis'!G32-'Bank Assets Analysis'!H32 -> 16870841 | F32: =+'Bank Assets Analysis'!I32-'Bank Assets Analysis'!J32 -> 184961398 | G32: =+'Bank Assets Analysis'!K32-'Bank Assets Analysis'!L32 -> 313432680 | H32: =+'Bank Assets Analysis'!M32-'Bank Assets Analysis'!N32 -> 533129992 | I32: =+'Bank Assets Analysis'!O32-'Bank Assets Analysis'!P32 -> 682443985 | J32: =+'Bank Assets Analysis'!Q32-'Bank Assets Analysis'!R32 -> 565889805 | K32: =+C32+D32+E32+F32+G32+H32+I32+J32 -> 2353100854 | L32: 0 | O32: 0
A33: 11 | B33: Кредиты и лизинги и авансы в процессе судебного разбирательства, чистые | C33: =+'Bank Assets Analysis'!C33-'Bank Assets Analysis'!D33 -> -25054 | D33: =+'Bank Assets Analysis'!E33-'Bank Assets Analysis'!F33 -> 0 | E33: =+'Bank Assets Analysis'!G33-'Bank Assets Analysis'!H33 -> 0 | F33: =+'Bank Assets Analysis'!I33-'Bank Assets Analysis'!J33 -> 0 | G33: =+'Bank Assets Analysis'!K33-'Bank Assets Analysis'!L33 -> 0 | H33: =+'Bank Assets Analysis'!M33-'Bank Assets Analysis'!N33 -> 0 | I33: =+'Bank Assets Analysis'!O33-'Bank Assets Analysis'!P33 -> 0 | J33: =+'Bank Assets Analysis'!Q33-'Bank Assets Analysis'!R33 -> 0 | K33: =+C33+D33+E33+F33+G33+H33+I33+J33 -> -25054 | L33: 0 | O33: 0
A34: 12. | B34: Инвестиции, чистые | C34: =+'Bank Assets Analysis'!C34-'Bank Assets Analysis'!D34 -> 107220 | D34: =+'Bank Assets Analysis'!E34-'Bank Assets Analysis'!F34 -> 0 | E34: =+'Bank Assets Analysis'!G34-'Bank Assets Analysis'!H34 -> 0 | F34: =+'Bank Assets Analysis'!I34-'Bank Assets Analysis'!J34 -> 0 | G34: =+'Bank Assets Analysis'!K34-'Bank Assets Analysis'!L34 -> 0 | H34: =+'Bank Assets Analysis'!M34-'Bank Assets Analysis'!N34 -> 0 | I34: =+'Bank Assets Analysis'!O34-'Bank Assets Analysis'!P34 -> 0 | J34: =+'Bank Assets Analysis'!Q34-'Bank Assets Analysis'!R34 -> 0 | K34: =+C34+D34+E34+F34+G34+H34+I34+J34 -> 107220 | L34: 0 | O34: 0
A35: 13. | B35: Ценные бумаги купленные по соглашению с обратным выкупом | C35: =+C36+C37 -> 0 | D35: =+D36+D37 -> 0 | E35: =+E36+E37 -> 0 | F35: =+F36+F37 -> 0 | G35: =+G36+G37 -> 0 | H35: =+H36+H37 -> 0 | I35: =+I36+I37 -> 0 | J35: =+J36+J37 -> 0 | K35: =+C35+D35+E35+F35+G35+H35+I35+J35 -> 0
A36: 13.1 | B36: Ценные бумаги Правительства и ЦБ купленные по соглашению с обратным выкупом (РЕПО) | C36: =+'Bank Assets Analysis'!C36-'Bank Assets Analysis'!D36 -> 0 | D36: =+'Bank Assets Analysis'!E36-'Bank Assets Analysis'!F36 -> 0 | E36: =+'Bank Assets Analysis'!G36-'Bank Assets Analysis'!H36 -> 0 | F36: =+'Bank Assets Analysis'!I36-'Bank Assets Analysis'!J36 -> 0 | G36: =+'Bank Assets Analysis'!K36-'Bank Assets Analysis'!L36 -> 0 | H36: =+'Bank Assets Analysis'!M36-'Bank Assets Analysis'!N36 -> 0 | I36: =+'Bank Assets Analysis'!O36-'Bank Assets Analysis'!P36 -> 0 | J36: =+'Bank Assets Analysis'!Q36-'Bank Assets Analysis'!R36 -> 0 | K36: =+C36+D36+E36+F36+G36+H36+I36+J36 -> 0 | L36: 1 | M36: =+K36 -> 0 | N36: =+M36*L36 -> 0 | O36: 1 | P36: =+K36 -> 0 | Q36: =+P36*O36 -> 0
A37: 13.2 | B37: Другие ценные бумаги купленные по соглашению с обратным выкупом (РЕПО) | C37: =+'Bank Assets Analysis'!C37-'Bank Assets Analysis'!D37 -> 0 | D37: =+'Bank Assets Analysis'!E37-'Bank Assets Analysis'!F37 -> 0 | E37: =+'Bank Assets Analysis'!G37-'Bank Assets Analysis'!H37 -> 0 | F37: =+'Bank Assets Analysis'!I37-'Bank Assets Analysis'!J37 -> 0 | G37: =+'Bank Assets Analysis'!K37-'Bank Assets Analysis'!L37 -> 0 | H37: =+'Bank Assets Analysis'!M37-'Bank Assets Analysis'!N37 -> 0 | I37: =+'Bank Assets Analysis'!O37-'Bank Assets Analysis'!P37 -> 0 | J37: =+'Bank Assets Analysis'!Q37-'Bank Assets Analysis'!R37 -> 0 | K37: =+C37+D37+E37+F37+G37+H37+I37+J37 -> 0 | L37: 0 | O37: 0 | Q37: =+P37*O37 -> 0
A38: 14. | B38: Основные средства, чистые | C38: =+'Bank Assets Analysis'!C38-'Bank Assets Analysis'!D38 -> 201801025 | D38: =+'Bank Assets Analysis'!E38-'Bank Assets Analysis'!F38 -> 0 | E38: =+'Bank Assets Analysis'!G38-'Bank Assets Analysis'!H38 -> 0 | F38: =+'Bank Assets Analysis'!I38-'Bank Assets Analysis'!J38 -> 0 | G38: =+'Bank Assets Analysis'!K38-'Bank Assets Analysis'!L38 -> 0 | H38: =+'Bank Assets Analysis'!M38-'Bank Assets Analysis'!N38 -> 0 | I38: =+'Bank Assets Analysis'!O38-'Bank Assets Analysis'!P38 -> 0 | J38: =+'Bank Assets Analysis'!Q38-'Bank Assets Analysis'!R38 -> 0 | K38: =+C38+D38+E38+F38+G38+H38+I38+J38 -> 201801025 | L38: 0 | O38: 0 | Q38: =+P38*O38 -> 0
A39: 15. | B39: Другое собственное имущество банка, чистые | C39: =+'Bank Assets Analysis'!C39-'Bank Assets Analysis'!D39 -> 0 | D39: =+'Bank Assets Analysis'!E39-'Bank Assets Analysis'!F39 -> 0 | E39: =+'Bank Assets Analysis'!G39-'Bank Assets Analysis'!H39 -> 0 | F39: =+'Bank Assets Analysis'!I39-'Bank Assets Analysis'!J39 -> 0 | G39: =+'Bank Assets Analysis'!K39-'Bank Assets Analysis'!L39 -> 0 | H39: =+'Bank Assets Analysis'!M39-'Bank Assets Analysis'!N39 -> 0 | I39: =+'Bank Assets Analysis'!O39-'Bank Assets Analysis'!P39 -> 0 | J39: =+'Bank Assets Analysis'!Q39-'Bank Assets Analysis'!R39 -> 0 | K39: =+C39+D39+E39+F39+G39+H39+I39+J39 -> 0 | L39: 0 | O39: 0 | Q39: =+P39*O39 -> 0
A40: 16. | B40: Нереализованная прибыль при ревальвации по сделкам "форвард" | C40: =+'Bank Assets Analysis'!C40-'Bank Assets Analysis'!D40 -> 0 | D40: =+'Bank Assets Analysis'!E40-'Bank Assets Analysis'!F40 -> 0 | E40: =+'Bank Assets Analysis'!G40-'Bank Assets Analysis'!H40 -> 0 | F40: =+'Bank Assets Analysis'!I40-'Bank Assets Analysis'!J40 -> 0 | G40: =+'Bank Assets Analysis'!K40-'Bank Assets Analysis'!L40 -> 0 | H40: =+'Bank Assets Analysis'!M40-'Bank Assets Analysis'!N40 -> 0 | I40: =+'Bank Assets Analysis'!O40-'Bank Assets Analysis'!P40 -> 0 | J40: =+'Bank Assets Analysis'!Q40-'Bank Assets Analysis'!R40 -> 0 | K40: =+C40+D40+E40+F40+G40+H40+I40+J40 -> 0 | L40: 0 | O40: 0 | Q40: =+P40*O40 -> 0
A41: 17. | B41: Счета купли-продажи валюты и валютные позиции | C41: =+'Bank Assets Analysis'!C41-'Bank Assets Analysis'!D41 -> -2562616 | K41: =+C41+D41+E41+F41+G41+H41+I41+J41 -> -2562616 | L41: 0 | O41: 0 | Q41: =+P41*O41 -> 0
A42: 18. | B42: Клиринговые счета | C42: =+'Bank Assets Analysis'!C42-'Bank Assets Analysis'!D42 -> 0 | D42: =+'Bank Assets Analysis'!E42-'Bank Assets Analysis'!F42 -> 0 | E42: =+'Bank Assets Analysis'!G42-'Bank Assets Analysis'!H42 -> 0 | F42: =+'Bank Assets Analysis'!I42-'Bank Assets Analysis'!J42 -> 0 | G42: =+'Bank Assets Analysis'!K42-'Bank Assets Analysis'!L42 -> 0 | H42: =+'Bank Assets Analysis'!M42-'Bank Assets Analysis'!N42 -> 0 | I42: =+'Bank Assets Analysis'!O42-'Bank Assets Analysis'!P42 -> 0 | J42: =+'Bank Assets Analysis'!Q42-'Bank Assets Analysis'!R42 -> 0 | K42: =+C42+D42+E42+F42+G42+H42+I42+J42 -> 0 | L42: 0 | O42: 0 | Q42: =+P42*O42 -> 0
A43: 19. | B43: Начисленные проценты | C43: =+'Bank Assets Analysis'!C43-'Bank Assets Analysis'!D43 -> 105420927 | D43: =+'Bank Assets Analysis'!E43-'Bank Assets Analysis'!F43 -> 0 | E43: =+'Bank Assets Analysis'!G43-'Bank Assets Analysis'!H43 -> 25424509 | F43: =+'Bank Assets Analysis'!I43-'Bank Assets Analysis'!J43 -> 3958301 | G43: =+'Bank Assets Analysis'!K43-'Bank Assets Analysis'!L43 -> 0 | H43: =+'Bank Assets Analysis'!M43-'Bank Assets Analysis'!N43 -> 0 | I43: =+'Bank Assets Analysis'!O43-'Bank Assets Analysis'!P43 -> 0 | J43: =+'Bank Assets Analysis'!Q43-'Bank Assets Analysis'!R43 -> 0 | K43: =+C43+D43+E43+F43+G43+H43+I43+J43 -> 134803737 | L43: 0.3 | M43: =+C43+D43+E43 -> 130845436 | N43: =+M43*L43 -> 39253631 | O43: 0.5 | P43: =+D43+E43 -> 25424509 | Q43: =+P43*O43 -> 12712254
A44: 20. | B44: Другие активы | C44: =+'Bank Assets Analysis'!C44-'Bank Assets Analysis'!D44 -> 42837373 | D44: =+'Bank Assets Analysis'!E44-'Bank Assets Analysis'!F44 -> 0 | E44: =+'Bank Assets Analysis'!G44-'Bank Assets Analysis'!H44 -> 0 | F44: =+'Bank Assets Analysis'!I44-'Bank Assets Analysis'!J44 -> 0 | G44: =+'Bank Assets Analysis'!K44-'Bank Assets Analysis'!L44 -> 0 | H44: =+'Bank Assets Analysis'!M44-'Bank Assets Analysis'!N44 -> 0 | I44: =+'Bank Assets Analysis'!O44-'Bank Assets Analysis'!P44 -> 0 | J44: =+'Bank Assets Analysis'!Q44-'Bank Assets Analysis'!R44 -> 0 | K44: =+C44+D44+E44+F44+G44+H44+I44+J44 -> 42837373 | L44: 0 | O44: 0 | Q44: =+P44*O44 -> 0
A45: 21. | B45: ИТОГО АКТИВОВ | C45: =SUM(C7:C44)-C8-C11-C15-C19-C21-C32-C35 -> 847731759 | D45: =SUM(D7:D44)-D8-D11-D15-D19-D21-D32-D35 -> 130446627 | E45: =SUM(E7:E44)-E8-E11-E15-E19-E21-E32-E35 -> 121815514 | F45: =SUM(F7:F44)-F8-F11-F15-F19-F21-F32-F35 -> 495730811 | G45: =SUM(G7:G44)-G8-G11-G15-G19-G21-G32-G35 -> 851043076 | H45: =SUM(H7:H44)-H8-H11-H15-H19-H21-H32-H35 -> 1277883068 | I45: =SUM(I7:I44)-I8-I11-I15-I19-I21-I32-I35 -> 1469143304 | J45: =SUM(J7:J44)-J8-J11-J15-J19-J21-J32-J35 -> 1517339261 | K45: =SUM(C45:J45) -> 6711133420 | N45: =SUM(N7:N44)-N11-N35 -> 6.9552138e+08 | P45: =SUM(P7:P44)-P11-P35 -> 794613462 | Q45: =SUM(Q7:Q44)-Q11-Q35 -> 7.0318143e+08 | R45: =+Balance!D45 -> 6711133420 | S45: =+K45-R45 -> 0 | T45: =+Balance!E45 -> 3571782245 | U45: =+R45 -> 6711133420 | V45: =+K45-U45 -> 0
B46: забалансовые обязательства
B47: Обязательства по выдаче кредита (91809) | C47: =+'Bank Assets Analysis'!C47-'Bank Assets Analysis'!D47 -> 0 | D47: =+'Bank Assets Analysis'!E47-'Bank Assets Analysis'!F47 -> 0 | E47: =+'Bank Assets Analysis'!G47-'Bank Assets Analysis'!H47 -> 0 | F47: =+'Bank Assets Analysis'!I47-'Bank Assets Analysis'!J47 -> 0 | G47: =+'Bank Assets Analysis'!K47-'Bank Assets Analysis'!L47 -> 0 | H47: =+'Bank Assets Analysis'!M47-'Bank Assets Analysis'!N47 -> 0 | I47: =+'Bank Assets Analysis'!O47-'Bank Assets Analysis'!P47 -> 0 | J47: =+'Bank Assets Analysis'!Q47-'Bank Assets Analysis'!R47 -> 0 | K47: =+C47+D47+E47+F47+G47+H47+I47+J47 -> 0
B48: Гарантии и поручительства (90993) | C48: =+'Bank Assets Analysis'!C48-'Bank Assets Analysis'!D48 -> 0 | D48: =+'Bank Assets Analysis'!E48-'Bank Assets Analysis'!F48 -> 0 | E48: =+'Bank Assets Analysis'!G48-'Bank Assets Analysis'!H48 -> 0 | F48: =+'Bank Assets Analysis'!I48-'Bank Assets Analysis'!J48 -> 0 | G48: =+'Bank Assets Analysis'!K48-'Bank Assets Analysis'!L48 -> 0 | H48: =+'Bank Assets Analysis'!M48-'Bank Assets Analysis'!N48 -> 0 | I48: =+'Bank Assets Analysis'!O48-'Bank Assets Analysis'!P48 -> 0 | J48: =+'Bank Assets Analysis'!Q48-'Bank Assets Analysis'!R48 -> 0 | K48: =+C48+D48+E48+F48+G48+H48+I48+J48 -> 0
B49: Аккредитивы (90908-90958) | C49: =+'Bank Assets Analysis'!C49-'Bank Assets Analysis'!D49 -> 0 | D49: =+'Bank Assets Analysis'!E49-'Bank Assets Analysis'!F49 -> 0 | E49: =+'Bank Assets Analysis'!G49-'Bank Assets Analysis'!H49 -> 0 | F49: =+'Bank Assets Analysis'!I49-'Bank Assets Analysis'!J49 -> 0 | G49: =+'Bank Assets Analysis'!K49-'Bank Assets Analysis'!L49 -> 0 | H49: =+'Bank Assets Analysis'!M49-'Bank Assets Analysis'!N49 -> 0 | I49: =+'Bank Assets Analysis'!O49-'Bank Assets Analysis'!P49 -> 0 | J49: =+'Bank Assets Analysis'!Q49-'Bank Assets Analysis'!R49 -> 0 | K49: =+C49+D49+E49+F49+G49+H49+I49+J49 -> 0
B50: Форврдные котракты, свопы, опционы и подобные обязательства (92705,92716,92728,92736) | C50: =+'Bank Assets Analysis'!C50-'Bank Assets Analysis'!D50 -> 0 | D50: =+'Bank Assets Analysis'!E50-'Bank Assets Analysis'!F50 -> 0 | E50: =+'Bank Assets Analysis'!G50-'Bank Assets Analysis'!H50 -> 0 | F50: =+'Bank Assets Analysis'!I50-'Bank Assets Analysis'!J50 -> 0 | G50: =+'Bank Assets Analysis'!K50-'Bank Assets Analysis'!L50 -> 0 | H50: =+'Bank Assets Analysis'!M50-'Bank Assets Analysis'!N50 -> 0 | I50: =+'Bank Assets Analysis'!O50-'Bank Assets Analysis'!P50 -> 0 | J50: =+'Bank Assets Analysis'!Q50-'Bank Assets Analysis'!R50 -> 0 | K50: =+C50+D50+E50+F50+G50+H50+I50+J50 -> 0
R52: Ликвидные активы | S52: =+N45-S53 -> 89050327 | U52: Ликвидные активы | V52: =+Q45-V53 -> 96710380
B53: Подпись Председателя правления: | R53: Высоко-ликвидные активы | S53: =+N7+N9+N12+N13+N15+N20+N22+N24+N36 -> 606471054 | U53: Высоко-ликвидные активы | V53: =+Q7+Q9+Q12+Q13+Q15+Q20+Q22+Q24+Q36 -> 606471054
R54: Чистый отток за 30 дней | S54: =+S56-S58 -> 4.3815932e+08 | U54: Чистый отток за 30 дней | V54: =+V56-V58 -> 6.9724073e+08
B55: Подпись Главного Бухгалтера:
R56: всего отток | S56: ='Bank Liabilities Analysis (нац)'!M40 -> 5.2720965e+08 | U56: всего отток | V56: ='Bank Liabilities Analysis (нац)'!O40+V57 -> 7.9395111e+08
R57: в том числе отток по внебалансу | S57: =+'Liquidity Analysis'!D43 -> 51211232 | U57: в том числе отток по внебалансу | V57: =+'Liquidity Analysis'!D43 -> 51211232
R58: Приток по положению | S58: =IF(S52>(S56*0.75),S56*0.75,S52) -> 89050327 | U58: Приток по положению | V58: =IF(V52>(V56*0.75),V56*0.75,V52) -> 96710380

Sheet Bank Liabilities Analysis
A1: АНАЛИЗ ОБЯЗАТЕЛЬСТВ БАНКА | AB1: Таблица-18
B2: =Balance!B3 -> АКБ"Микрокредитбанк" | T2: =+Balance!B2 -> 31 Декабрь, 2020 | AC2: в тыс. сум
A3: № | B3: Характеристики | C3: Срок погашения (в днях) | S3: ВСЕГО | T3: из них | V3: Расчет коэффициента покрытия ликвидности (действующий норматив) | AA3: Расчет коэффициента покрытия ликвидности (внедряемый норматив)
C4: Бессрочные | E4: От 1 до 7 дней | G4: От 8 до 30 дней | I4: От 31 до 90 дней | K4: От 91 до 180 дней | M4: От 181 до 365 дней | O4: От 366 до 730 дней | Q4: Свыше 2 лет
C5: Сумма | D5: в том числе, в иностранной валюте (в экв. в сумах) | E5: Сумма | F5: в том числе, в иностранной валюте (в экв. в сумах) | G5: Сумма | H5: в том числе, в иностранной валюте (в экв. в сумах) | I5: Сумма | J5: в том числе, в иностранной валюте (в экв. в сумах) | K5: Сумма | L5: в том числе, в иностранной валюте (в экв. в сумах) | M5: Сумма | N5: в том числе, в иностранной валюте (в экв. в сумах) | O5: Сумма | P5: в том числе, в иностранной валюте (в экв. в сумах) | Q5: Сумма | R5: в том числе, в иностранной валюте (в экв. в сумах) | T5: в национальной валюте | U5: в иностранной валюте (в экв. в сумах) | V5: Коэффициент | W5: Сумма оттока за 30 дней | X5: Сумма чистого оттока за 30 дней | Y5: Сумма оттока за 30 дней (в иностранной валюте) | Z5: Сумма чистого оттока за 30 дней (в иностранной валюте) | AA5: Коэффициент | AB5: Сумма оттока за 30 дней | AC5: Сумма оттока за 30 дней (в иностранной валюте)
B6: ОБЯЗАТЕЛЬСТВА
A7: 1. | B7: ДЕПОЗИТЫ
A8: 1.1 | B8: Депозиты до востребования | C8: =SUM(C9:C12) -> 395792505 | D8: =SUM(D9:D12) -> 24398582 | E8: =SUM(E9:E12) -> 0 | F8: =SUM(F9:F12) -> 0 | G8: =SUM(G9:G12) -> 0 | H8: =SUM(H9:H12) -> 0 | I8: =SUM(I9:I12) -> 0 | J8: =SUM(J9:J12) -> 0 | ... R8: =SUM(R9:R12) -> 0 | S8: =+C8+E8+G8+I8+K8+M8+O8+Q8 -> 395792505 | T8: =+S8-U8 -> 371393923 | U8: =+D8+F8+H8+J8+L8+N8+P8+R8 -> 24398582
A9: 1.1.1 | B9: Вклады физических лиц | C9: 13733374 | D9: 2766324 | S9: =+C9+E9+G9+I9+K9+M9+O9+Q9 -> 13733374 | T9: =+S9-U9 -> 10967050 | U9: =+D9+F9+H9+J9+L9+N9+P9+R9 -> 2766324 | V9: 0.1 | W9: =+C9+E9+G9 -> 13733374 | X9: =+W9*V9 -> 1373337.4 | Y9: =+D9+F9+H9 -> 2766324 | Z9: =+Y9*V9 -> 276632.4
A10: 1.1.2 | B10: Вклады физических лиц - под залогом по выданным кредитам | S10: =+C10+E10+G10+I10+K10+M10+O10+Q10 -> 0 | T10: =+S10-U10 -> 0 | U10: =+D10+F10+H10+J10+L10+N10+P10+R10 -> 0 | V10: 0
A11: 1.1.3 | B11: Другие депозиты до востребования - под залогом по выданным кредитам | S11: =+C11+E11+G11+I11+K11+M11+O11+Q11 -> 0 | T11: =+S11-U11 -> 0 | U11: =+D11+F11+H11+J11+L11+N11+P11+R11 -> 0 | V11: 0
A12: 1.1.4 | B12: Другие депозиты до востребования | C12: 382059131 | D12: 21632258 | S12: =+C12+E12+G12+I12+K12+M12+O12+Q12 -> 382059131 | T12: =+S12-U12 -> 360426873 | U12: =+D12+F12+H12+J12+L12+N12+P12+R12 -> 21632258 | V12: 0.3 | W12: =+C12+E12+G12 -> 382059131 | X12: =+W12*V12 -> 1.1461774e+08 | Y12: =+D12+F12+H12 -> 21632258 | Z12: =+Y12*V12 -> 6489677.4
A13: 1.2 | B13: Срочные депозиты, в том числе: | C13: 2634533 | D13: 32340 | E13: 233792889 | F13: 105714241 | G13: 181012304 | H13: 3699986 | I13: 260330858 | J13: 33883233 | K13: 254530733 | L13: 27652368 | M13: 511146073 | N13: 18874787 | O13: 63458569 | P13: 1272042 | Q13: 254339946 | R13: 157153800 | S13: =+C13+E13+G13+I13+K13+M13+O13+Q13 -> 1761245905 | T13: =+S13-U13 -> 1412963108 | U13: =+D13+F13+H13+J13+L13+N13+P13+R13 -> 348282797 | V13: 1 | W13: =+C13+E13+G13 -> 417439726 | X13: =+W13*V13 -> 417439726 | Y13: =+D13+F13+H13 -> 109446567 | Z13: =+Y13*V13 -> 109446567
A14: 1.2.1 | B14: Вклады физических лиц | E14: 30163689 | F14: 945041 | G14: 57214612 | H14: 2652294 | I14: 112908752 | J14: 22358621 | K14: 100968787 | L14: 26772307 | M14: 111359166 | N14: 9026482 | O14: 20208569 | P14: 1272042 | Q14: 2174301 | R14: 0 | S14: =+C14+E14+G14+I14+K14+M14+O14+Q14 -> 434997876 | T14: =+S14-U14 -> 371971089 | U14: =+D14+F14+H14+J14+L14+N14+P14+R14 -> 63026787 | V14: 0
A15: 1.2.2 | B15: Депозитные сертификаты | G15: 26000000 | I15: 9100000 | S15: =+C15+E15+G15+I15+K15+M15+O15+Q15 -> 35100000 | T15: =+S15-U15 -> 35100000 | U15: =+D15+F15+H15+J15+L15+N15+P15+R15 -> 0 | V15: 0
A16: 1.3 | B16: Другие депозиты клиентов | C16: =SUM(C17:C21) -> 225705415 | D16: =SUM(D17:D21) -> 53081874 | E16: =SUM(E17:E21) -> 0 | F16: =SUM(F17:F21) -> 0 | G16: =SUM(G17:G21) -> 0 | H16: =SUM(H17:H21) -> 0 | I16: =SUM(I17:I21) -> 0 | J16: =SUM(J17:J21) -> 0 | ... R16: =SUM(R17:R21) -> 0 | S16: =+C16+E16+G16+I16+K16+M16+O16+Q16 -> 225705415 | T16: =+S16-U16 -> 172623541 | U16: =+D16+F16+H16+J16+L16+N16+P16+R16 -> 53081874
A17: 1.3.1 | B17: Средства на банковских пластиковых карточках - физических лиц | C17: 149627163 | D17: 5549710 | S17: =+C17+E17+G17+I17+K17+M17+O17+Q17 -> 149627163 | T17: =+S17-U17 -> 144077453 | U17: =+D17+F17+H17+J17+L17+N17+P17+R17 -> 5549710 | V17: 0.1 | W17: =+C17+E17+G17 -> 149627163 | X17: =+W17*V17 -> 14962716 | Y17: =+D17+F17+H17 -> 5549710 | Z17: =+Y17*V17 -> 554971
A18: 1.3.2 | B18: Средства на банковских пластиковых карточках - других клиентов | C18: 9478980 | D18: 67872 | S18: =+C18+E18+G18+I18+K18+M18+O18+Q18 -> 9478980 | T18: =+S18-U18 -> 9411108 | U18: =+D18+F18+H18+J18+L18+N18+P18+R18 -> 67872 | V18: 0.1 | W18: =+C18+E18+G18 -> 9478980 | X18: =+W18*V18 -> 947898 | Y18: =+D18+F18+H18 -> 67872 | Z18: =+Y18*V18 -> 6787.2
A19: 1.3.3 | B19: Депозиты клиентов по аккредитивам | C19: 42793985 | D19: 42793985 | S19: =+C19+E19+G19+I19+K19+M19+O19+Q19 -> 42793985 | T19: =+S19-U19 -> 0 | U19: =+D19+F19+H19+J19+L19+N19+P19+R19 -> 42793985 | V19: 0.3 | W19: =+C19+E19+G19 -> 42793985 | X19: =+W19*V19 -> 12838196 | Y19: =+D19+F19+H19 -> 42793985 | Z19: =+Y19*V19 -> 12838196
A20: 1.3.4 | B20: Зарезервированные средства клиентов для конвертации на валютном рынке | C20: 6492248 | D20: 0 | S20: =+C20+E20+G20+I20+K20+M20+O20+Q20 -> 6492248 | T20: =+S20-U20 -> 6492248 | U20: =+D20+F20+H20+J20+L20+N20+P20+R20 -> 0 | V20: 1 | W20: =+C20+E20+G20 -> 6492248 | X20: =+W20*V20 -> 6492248 | Y20: =+D20+F20+H20 -> 0 | Z20: =+Y20*V20 -> 0
A21: 1.3.5 | B21: Другие | C21: 17313039 | D21: 4670307 | S21: =+C21+E21+G21+I21+K21+M21+O21+Q21 -> 17313039 | T21: =+S21-U21 -> 12642732 | U21: =+D21+F21+H21+J21+L21+N21+P21+R21 -> 4670307 | V21: 0.3 | W21: =+C21+E21+G21 -> 17313039 | X21: =+W21*V21 -> 5193911.7 | Y21: =+D21+F21+H21 -> 4670307 | Z21: =+Y21*V21 -> 1401092.1
A22: 1.4 | B22: Итого депозитов | C22: =+C8+C13+C16 -> 624132453 | D22: =+D8+D13+D16 -> 77512796 | E22: =+E8+E13+E16 -> 233792889 | F22: =+F8+F13+F16 -> 105714241 | G22: =+G8+G13+G16 -> 181012304 | H22: =+H8+H13+H16 -> 3699986 | I22: =+I8+I13+I16 -> 260330858 | J22: =+J8+J13+J16 -> 33883233 | ... R22: =+R8+R13+R16 -> 157153800 | S22: =+C22+E22+G22+I22+K22+M22+O22+Q22 -> 2382743825 | T22: =+S22-U22 -> 1956980572 | U22: =+D22+F22+H22+J22+L22+N22+P22+R22 -> 425763253 | Y22: =+D22+F22+H22 -> 186927023 | Z22: =+Y22*V22 -> 0 | AA22: 0.15 | AB22: =+S22*AA22 -> 3.5741157e+08 | AC22: =U22*AA22 -> 63864488
A23: 2. | B23: К оплате в ЦБРУ | S23: =+C23+E23+G23+I23+K23+M23+O23+Q23 -> 0 | T23: =+S23-U23 -> 0 | U23: =+D23+F23+H23+J23+L23+N23+P23+R23 -> 0 | V23: 1 | W23: =+C23+E23+G23 -> 0 | X23: =+W23*V23 -> 0 | Y23: =+D23+F23+H23 -> 0 | Z23: =+Y23*V23 -> 0 | AA23: 1 | AB23: =(C23+E23+G23)*AA23 -> 0 | AC23: =(D23+F23+H23)*AA23 -> 0
A24: 3. | B24: К оплате в другие банки | C24: =SUM(C25:C28) -> 4554422 | D24: =SUM(D25:D28) -> 0 | E24: =SUM(E25:E28) -> 0 | F24: =SUM(F25:F28) -> 0 | G24: =SUM(G25:G28) -> 0 | H24: =SUM(H25:H28) -> 0 | I24: =SUM(I25:I28) -> 166895134 | J24: =SUM(J25:J28) -> 66895134 | ... R24: =SUM(R25:R28) -> 168699350 | S24: =+C24+E24+G24+I24+K24+M24+O24+Q24 -> 1677401207 | T24: =+S24-U24 -> 917960723 | U24: =+D24+F24+H24+J24+L24+N24+P24+R24 -> 759440484
A25: 3.1 | B25: К оплате на корреспондентские счета других банков | S25: =+C25 -> 0 | T25: =+S25-U25 -> 0 | U25: =+D25 -> 0 | V25: 1 | W25: =+T25 -> 0 | X25: =+W25*V25 -> 0 | AA25: 1 | AB25: =+T25*AA25 -> 0
A26: 3.2 | B26: К оплате в другие банки - депозиты | I26: 166895134 | J26: 66895134 | K26: 102384600 | L26: 52384600 | M26: 411692200 | N26: 366692200 | O26: 104769200 | P26: 104769200 | Q26: 887105651 | R26: 168699350 | S26: =+C26+E26+G26+I26+K26+M26+O26+Q26 -> 1672846785 | T26: =+S26-U26 -> 913406301 | U26: =+D26+F26+H26+J26+L26+N26+P26+R26 -> 759440484 | V26: 1 | W26: =+C26+E26+G26 -> 0 | X26: =+W26*V26 -> 0 | Y26: =+D26+F26+H26 -> 0 | Z26: =+Y26*V26 -> 0 | AA26: 1 | AB26: =(C26+E26+G26)*AA26 -> 0 | AC26: =(D26+F26+H26)*AA26 -> 0
A27: 3.3 | B27: К оплате в другие банки по расчётам с пластиковых карт | C27: 4554422 | D27: 0 | S27: =+C27+E27+G27+I27+K27+M27+O27+Q27 -> 4554422 | T27: =+S27-U27 -> 4554422 | U27: =+D27+F27+H27+J27+L27+N27+P27+R27 -> 0 | V27: 0.5 | W27: =+C27+E27+G27 -> 4554422 | X27: =+W27*V27 -> 2277211 | Y27: =+D27+F27+H27 -> 0 | Z27: =+Y27*V27 -> 0 | AA27: 1 | AB27: =(C27+E27+G27)*AA27 -> 4554422 | AC27: =(D27+F27+H27)*AA27 -> 0
A28: 3.4 | B28: Другие статьи | S28: =+C28+E28+G28+I28+K28+M28+O28+Q28 -> 0 | T28: =+S28-U28 -> 0 | U28: =+D28+F28+H28+J28+L28+N28+P28+R28 -> 0 | V28: 0.3 | W28: =+C28+E28+G28 -> 0 | X28: =+W28*V28 -> 0 | Y28: =+D28+F28+H28 -> 0 | Z28: =+Y28*V28 -> 0 | AA28: 1 | AB28: =(C28+E28+G28)*AA28 -> 0 | AC28: =(D28+F28+H28)*AA28 -> 0
A29: 4. | B29: Управленческие чеки | S29: =+C29+E29+G29+I29+K29+M29+O29+Q29 -> 0 | T29: =+S29-U29 -> 0 | U29: =+D29+F29+H29+J29+L29+N29+P29+R29 -> 0 | V29: 1 | W29: =+C29+E29+G29 -> 0 | X29: =+W29*V29 -> 0 | Y29: =+D29+F29+H29 -> 0 | Z29: =+Y29*V29 -> 0 | AA29: 1 | AB29: =(C29+E29+G29)*AA29 -> 0 | AC29: =(D29+F29+H29)*AA29 -> 0
A30: 5. | B30: Непогашенные акцепты, выполненные банком или по поручению этого банка | C30: 2586732 | D30: 2586732 | S30: =+C30+E30+G30+I30+K30+M30+O30+Q30 -> 2586732 | T30: =+S30-U30 -> 0 | U30: =+D30+F30+H30+J30+L30+N30+P30+R30 -> 2586732 | V30: 1 | W30: =+C30+E30+G30 -> 2586732 | X30: =+W30*V30 -> 2586732 | Y30: =+D30+F30+H30 -> 2586732 | Z30: =+Y30*V30 -> 2586732 | AA30: 1 | AB30: =(C30+E30+G30)*AA30 -> 2586732 | AC30: =(D30+F30+H30)*AA30 -> 2586732
A31: 6. | B31: Кредиты и лизинговые операции к оплате | C31: 2696281 | D31: 1308254 | E31: 539725 | F31: 0 | G31: 38614534 | H31: 30047171 | I31: 313584181 | J31: 288193399 | K31: 89850271 | L31: 39472055 | M31: 336969063 | N31: 239070256 | O31: 1420538163 | P31: 1142328694 | Q31: 2099067418 | R31: 391590685 | S31: =+C31+E31+G31+I31+K31+M31+O31+Q31 -> 4301859636 | T31: =+S31-U31 -> 2169849122 | U31: =+D31+F31+H31+J31+L31+N31+P31+R31 -> 2132010514 | V31: 1 | W31: =+C31+E31+G31 -> 41850540 | X31: =+W31*V31 -> 41850540 | Y31: =+D31+F31+H31 -> 31355425 | Z31: =+Y31*V31 -> 31355425 | AA31: 0.15 | AB31: =+S31*AA31 -> 6.4527895e+08 | AC31: =(U31)*AA31 -> 3.1980158e+08
A32: 7. | B32: Выпущенные банком ценные бумаги | S32: =+C32+E32+G32+I32+K32+M32+O32+Q32 -> 0 | T32: =+S32-U32 -> 0 | U32: =+D32+F32+H32+J32+L32+N32+P32+R32 -> 0 | V32: 1 | W32: =+C32+E32+G32 -> 0 | X32: =+W32*V32 -> 0 | Y32: =+D32+F32+H32 -> 0 | Z32: =+Y32*V32 -> 0 | AA32: 1 | AB32: =(C32+E32+G32)*AA32 -> 0 | AC32: =(D32+F32+H32)*AA32 -> 0
A33: 7a. | B33: Субординированные долговые обязательства | S33: =+C33+E33+G33+I33+K33+M33+O33+Q33 -> 0 | T33: =+S33-U33 -> 0 | U33: =+D33+F33+H33+J33+L33+N33+P33+R33 -> 0 | V33: 1 | W33: =+C33+E33+G33 -> 0 | X33: =+W33*V33 -> 0 | Y33: =+D33+F33+H33 -> 0 | Z33: =+Y33*V33 -> 0 | AA33: 1 | AB33: =(C33+E33+G33)*AA33 -> 0 | AC33: =(D33+F33+H33)*AA33 -> 0
A34: 8. | B34: Ценные бумаги проданные по соглашению с последующим выкупом | S34: =+C34+E34+G34+I34+K34+M34+O34+Q34 -> 0 | T34: =+S34-U34 -> 0 | U34: =+D34+F34+H34+J34+L34+N34+P34+R34 -> 0 | V34: 1 | W34: =+C34+E34+G34 -> 0 | X34: =+W34*V34 -> 0 | Y34: =+D34+F34+H34 -> 0 | Z34: =+Y34*V34 -> 0 | AA34: 1 | AB34: =(C34+E34+G34)*AA34 -> 0 | AC34: =(D34+F34+H34)*AA34 -> 0
A35: 9. | B35: Нереализованная прибыль или убытки по форвардным сделкам и другим отсроченным кредитам | C35: 20924 | D35: 0 | S35: =+C35+E35+G35+I35+K35+M35+O35+Q35 -> 20924 | T35: =+S35-U35 -> 20924 | U35: =+D35+F35+H35+J35+L35+N35+P35+R35 -> 0 | V35: 1 | W35: =+C35+E35+G35 -> 20924 | X35: =+W35*V35 -> 20924 | Y35: =+D35+F35+H35 -> 0 | Z35: =+Y35*V35 -> 0 | AA35: 1 | AB35: =(S35)*AA35 -> 20924 | AC35: =(U35)*AA35 -> 0
A36: 10. | B36: Клиринговые счета - кредитовый остаток | C36: 602200 | D36: 104470 | S36: =+C36+E36+G36+I36+K36+M36+O36+Q36 -> 602200 | T36: =+S36-U36 -> 497730 | U36: =+D36+F36+H36+J36+L36+N36+P36+R36 -> 104470 | V36: 1 | W36: =+C36+E36+G36 -> 602200 | X36: =+W36*V36 -> 602200 | Y36: =+D36+F36+H36 -> 104470 | Z36: =+Y36*V36 -> 104470 | AA36: 1 | AB36: =(S36)*AA36 -> 602200 | AC36: =(U36)*AA36 -> 104470
A37: 11. | B37: Начисленные проценты | C37: 65266761 | D37: 14589451 | S37: =+C37+E37+G37+I37+K37+M37+O37+Q37 -> 65266761 | T37: =+S37-U37 -> 50677310 | U37: =+D37+F37+H37+J37+L37+N37+P37+R37 -> 14589451 | V37: 1 | W37: =+C37+E37+G37 -> 65266761 | X37: =+W37*V37 -> 65266761 | Y37: =+D37+F37+H37 -> 14589451 | Z37: =+Y37*V37 -> 14589451 | AB37: =C37+E37+G37+((I37+K37+M37+O37+Q37)*15%) -> 65266761 | AC37: =D37+F37+H37+((J37+L37+N37+P37+R37)*15%) -> 14589451
A38: 12. | B38: Другие обязательства | C38: =112520224+1624624 -> 114144848 | D38: 46179811 | S38: =+C38+E38+G38+I38+K38+M38+O38+Q38 -> 114144848 | T38: =+S38-U38 -> 67965037 | U38: =+D38+F38+H38+J38+L38+N38+P38+R38 -> 46179811 | V38: 0.3 | W38: =+C38+E38+G38 -> 114144848 | X38: =+W38*V38 -> 34243454 | Y38: =+D38+F38+H38 -> 46179811 | Z38: =+Y38*V38 -> 13853943 | AA38: 1 | AB38: =(S38)*AA38 -> 114144848 | AC38: =(U38)*AA38 -> 46179811
A39: 13. | B39: ИТОГО ОБЯЗАТЕЛЬСТВ | C39: =+C22+C29+C30+C31+C32+C33+C34+C35+C36+C37+C38+C23+C24 -> 814004621 | D39: =+D22+D29+D30+D31+D32+D33+D34+D35+D36+D37+D38+D23+D24 -> 142281514 | E39: =+E22+E29+E30+E31+E32+E33+E34+E35+E36+E37+E38+E23+E24 -> 234332614 | F39: =+F22+F29+F30+F31+F32+F33+F34+F35+F36+F37+F38+F23+F24 -> 105714241 | G39: =+G22+G29+G30+G31+G32+G33+G34+G35+G36+G37+G38+G23+G24 -> 219626838 | H39: =+H22+H29+H30+H31+H32+H33+H34+H35+H36+H37+H38+H23+H24 -> 33747157 | I39: =+I22+I29+I30+I31+I32+I33+I34+I35+I36+I37+I38+I23+I24 -> 740810173 | J39: =+J22+J29+J30+J31+J32+J33+J34+J35+J36+J37+J38+J23+J24 -> 388971766 | ... R39: =+R22+R29+R30+R31+R32+R33+R34+R35+R36+R37+R38+R23+R24 -> 717443835 | S39: =+S22+S23+S24+S29+S30+S31+S32+S33+S34+S35+S36+S37+S38 -> 8544626133 | T39: =+T22+T23+T24+T29+T30+T31+T32+T33+T34+T35+T36+T37+T38 -> 5163951418 | U39: =+U22+U23+U24+U29+U30+U31+U32+U33+U34+U35+U36+U37+U38 -> 3380674715 | V39: отток | X39: =SUM(X9:X38) -> 7.2071359e+08 | Z39: =SUM(Z9:Z38) -> 1.9350394e+08 | AA39: отток | AB39: =SUM(AB9:AB38) -> 1.1898664e+09 | AC39: =SUM(AC9:AC38) -> 4.4712653e+08 | AD39: =+Balance!C62 -> 8544626133 | AE39: =+Balance!D62 -> 5163951418 | AF39: =+Balance!E62 -> 3380674715
B40: из них, обязательства перед: | S40: =+C40+E40+G40+I40+K40+M40+O40+Q40 -> 0 | T40: =+S40-U40 -> 0 | U40: =+D40+F40+H40+J40+L40+N40+P40+R40 -> 0
B41: Министерство Финансов Республики Узбекистан, из них | C41: =+C42+C43 -> 0 | D41: =+D42+D43 -> 0 | E41: =+E42+E43 -> 0 | F41: =+F42+F43 -> 0 | G41: =+G42+G43 -> 0 | H41: =+H42+H43 -> 0 | I41: =+I42+I43 -> 31492 | J41: =+J42+J43 -> 0 | ... R41: =+R42+R43 -> 0 | S41: =+C41+E41+G41+I41+K41+M41+O41+Q41 -> 158548482 | T41: =+S41-U41 -> 158548482 | U41: =+D41+F41+H41+J41+L41+N41+P41+R41 -> 0
B42: Кредиты и лизинги | C42: 0 | D42: 0 | E42: 0 | F42: 0 | G42: 0 | H42: 0 | I42: 31492 | J42: 0 | K42: 24978 | L42: 0 | M42: 2141532 | N42: 0 | O42: 8007273 | P42: 0 | Q42: 148343207 | R42: 0 | S42: =+C42+E42+G42+I42+K42+M42+O42+Q42 -> 158548482 | T42: =+S42-U42 -> 158548482 | U42: =+D42+F42+H42+J42+L42+N42+P42+R42 -> 0
B43: Депозитные ресурсы | S43: =+C43+E43+G43+I43+K43+M43+O43+Q43 -> 0 | T43: =+S43-U43 -> 0 | U43: =+D43+F43+H43+J43+L43+N43+P43+R43 -> 0
B44: Внебюджетные фонды, из них | C44: =+C45+C46 -> 0 | D44: =+D45+D46 -> 0 | E44: =+E45+E46 -> 0 | F44: =+F45+F46 -> 0 | G44: =+G45+G46 -> 5090682 | H44: =+H45+H46 -> 0 | I44: =+I45+I46 -> 12302436 | J44: =+J45+J46 -> 0 | ... R44: =+R45+R46 -> 0 | S44: =+C44+E44+G44+I44+K44+M44+O44+Q44 -> 299909411 | T44: =+S44-U44 -> 299909411 | U44: =+D44+F44+H44+J44+L44+N44+P44+R44 -> 0
B45: Кредиты и лизинги | C45: 0 | D45: 0 | E45: 0 | F45: 0 | G45: 5090682 | H45: 0 | I45: 12302436 | J45: 0 | K45: 19937138 | L45: 0 | M45: 41120558 | N45: 0 | O45: 59801516 | P45: 0 | Q45: 31116095 | R45: 0 | S45: =+C45+E45+G45+I45+K45+M45+O45+Q45 -> 169368425 | T45: =+S45-U45 -> 169368425 | U45: =+D45+F45+H45+J45+L45+N45+P45+R45 -> 0
B46: Депозитные ресурсы | K46: 34940986 | M46: 45400000 | O46: 35200000 | Q46: 15000000 | S46: =+C46+E46+G46+I46+K46+M46+O46+Q46 -> 130540986 | T46: =+S46-U46 -> 130540986 | U46: =+D46+F46+H46+J46+L46+N46+P46+R46 -> 0
B47: Фонд реконструкции и развития Узбекистана (ФРРУ) , из них | C47: =+C48+C49 -> 0 | D47: =+D48+D49 -> 0 | E47: =+E48+E49 -> 0 | F47: =+F48+F49 -> 0 | G47: =+G48+G49 -> 0 | H47: =+H48+H49 -> 0 | I47: =+I48+I49 -> 0 | J47: =+J48+J49 -> 0 | ... R47: =+R48+R49 -> 754338 | S47: =+C47+E47+G47+I47+K47+M47+O47+Q47 -> 1.4026162e+09 | T47: =+S47-U47 -> 1.4016733e+09 | U47: =+D47+F47+H47+J47+L47+N47+P47+R47 -> 942923
B48: Кредиты и лизинги | C48: 0 | D48: 0 | E48: 0 | F48: 0 | G48: 0 | H48: 0 | I48: 0 | J48: 0 | K48: 0 | L48: 0 | M48: 62862 | N48: 62862 | O48: 121830640 | P48: 125723 | Q48: 1245781729 | R48: 754338 | S48: =+C48+E48+G48+I48+K48+M48+O48+Q48 -> 1367675231 | T48: =+S48-U48 -> 1366732308 | U48: =+D48+F48+H48+J48+L48+N48+P48+R48 -> 942923
B49: Депозитные ресурсы | K49: 34940986 | S49: =+C49+E49+G49+I49+K49+M49+O49+Q49 -> 34940986 | T49: =+S49-U49 -> 34940986 | U49: =+D49+F49+H49+J49+L49+N49+P49+R49 -> 0
B50: Зарубежные банки, из них | C50: =+C51+C52 -> 0 | D50: =+D51+D52 -> 0 | E50: =+E51+E52 -> 0 | F50: =+F51+F52 -> 0 | G50: =+G51+G52 -> 0 | H50: =+H51+H52 -> 0 | I50: =+I51+I52 -> 1105800980 | J50: =+J51+J52 -> 1105800980 | ... R50: =+R51+R52 -> 52384600 | S50: =+C50+E50+G50+I50+K50+M50+O50+Q50 -> 1536761807 | T50: =+S50-U50 -> 0 | U50: =+D50+F50+H50+J50+L50+N50+P50+R50 -> 1536761807
B51: Кредиты и лизинги | C51: 0 | D51: 0 | E51: 0 | F51: 0 | G51: 0 | H51: 0 | I51: 1105800980 | J51: 1105800980 | K51: 38358090 | L51: 38358090 | M51: 237195090 | N51: 237195090 | O51: 103023047 | P51: 103023047 | Q51: 52384600 | R51: 52384600 | S51: =+C51+E51+G51+I51+K51+M51+O51+Q51 -> 1536761807 | T51: =+S51-U51 -> 0 | U51: =+D51+F51+H51+J51+L51+N51+P51+R51 -> 1536761807
B52: Депозитные ресурсы | S52: =+C52+E52+G52+I52+K52+M52+O52+Q52 -> 0 | T52: =+S52-U52 -> 0 | U52: =+D52+F52+H52+J52+L52+N52+P52+R52 -> 0
B53: Другие зарубежные финансовые организации, из них | C53: =+C54+C55 -> 0 | D53: =+D54+D55 -> 0 | E53: =+E54+E55 -> 0 | F53: =+F54+F55 -> 0 | G53: =+G54+G55 -> 30047171 | H53: =+H54+H55 -> 30047171 | I53: =+I54+I55 -> 0 | J53: =+J54+J55 -> 0 | ... R53: =+R54+R55 -> 0 | S53: =+C53+E53+G53+I53+K53+M53+O53+Q53 -> 217362511 | T53: =+S53-U53 -> 0 | U53: =+D53+F53+H53+J53+L53+N53+P53+R53 -> 217362511
B54: Кредиты и лизинги | C54: 0 | D54: 0 | E54: 0 | F54: 0 | G54: 30047171 | H54: 30047171 | I54: 0 | J54: 0 | K54: 0 | L54: 0 | M54: 0 | N54: 0 | O54: 187315340 | P54: 187315340 | Q54: 0 | R54: 0 | S54: =+C54+E54+G54+I54+K54+M54+O54+Q54 -> 217362511 | T54: =+S54-U54 -> 0 | U54: =+D54+F54+H54+J54+L54+N54+P54+R54 -> 217362511
B55: Депозитные ресурсы | S55: =+C55+E55+G55+I55+K55+M55+O55+Q55 -> 0 | T55: =+S55-U55 -> 0 | U55: =+D55+F55+H55+J55+L55+N55+P55+R55 -> 0
B57: Подпись Председателя правления:
B59: Подпись Главного Бухгалтера:

Sheet Bank Liabilities Analysis (нац)
A2: АНАЛИЗ ОБЯЗАТЕЛЬСТВ БАНКА В НАЦИОНАЛЬНОЙ ВАЛЮТЕ | N2: Таблица-18А
B3: =Balance!B3 -> АКБ"Микрокредитбанк" | J3: =+Balance!B2 -> 31 Декабрь, 2020 | O3: =+Balance!E3 -> тыс. сум
A4: № | B4: Характеристики | C4: Срок погашения (в днях) | K4: ВСЕГО | L4: Расчет коэффициента покрытия ликвидности (действующий норматив) | N4: Расчет коэффициента покрытия ликвидности (внедряемый норматив)
C5: Бессрочные | D5: От 1 до 7 дней | E5: От 8 до 30 дней | F5: От 31 до 90 дней | G5: От 91 до 180 дней | H5: От 181 до 365 дней | I5: От 366 до 730 дней | J5: Свыше 2 лет
L6: Коэффициент | M6: Сумма оттока за 30 дней | N6: Коэффициент | O6: Сумма оттока за 30 дней
B7: ОБЯЗАТЕЛЬСТВА
A8: 1. | B8: ДЕПОЗИТЫ
A9: 1.1 | B9: Депозиты до востребования | C9: =SUM(C10:C13) -> 371393923 | D9: =SUM(D10:D13) -> 0 | E9: =SUM(E10:E13) -> 0 | F9: =SUM(F10:F13) -> 0 | G9: =SUM(G10:G13) -> 0 | H9: =SUM(H10:H13) -> 0 | I9: =SUM(I10:I13) -> 0 | J9: =SUM(J10:J13) -> 0 | K9: =+C9+D9+E9+F9+G9+H9+I9+J9 -> 371393923
A10: 1.1.1 | B10: Вклады физических лиц | C10: =+'Bank Liabilities Analysis'!C9-'Bank Liabilities Analysis'!D9 -> 10967050 | D10: =+'Bank Liabilities Analysis'!E9-'Bank Liabilities Analysis'!F9 -> 0 | E10: =+'Bank Liabilities Analysis'!G9-'Bank Liabilities Analysis'!H9 -> 0 | F10: =+'Bank Liabilities Analysis'!I9-'Bank Liabilities Analysis'!J9 -> 0 | G10: =+'Bank Liabilities Analysis'!K9-'Bank Liabilities Analysis'!L9 -> 0 | H10: =+'Bank Liabilities Analysis'!M9-'Bank Liabilities Analysis'!N9 -> 0 | I10: =+'Bank Liabilities Analysis'!O9-'Bank Liabilities Analysis'!P9 -> 0 | J10: =+'Bank Liabilities Analysis'!Q9-'Bank Liabilities Analysis'!R9 -> 0 | K10: =+C10+D10+E10+F10+G10+H10+I10+J10 -> 10967050 | L10: 0.1 | M10: =(C10+D10+E10)*L10 -> 1096705
A11: 1.1.2 | B11: Вклады физических лиц - под залогом по выданным кредитам | C11: =+'Bank Liabilities Analysis'!C10-'Bank Liabilities Analysis'!D10 -> 0 | D11: =+'Bank Liabilities Analysis'!E10-'Bank Liabilities Analysis'!F10 -> 0 | E11: =+'Bank Liabilities Analysis'!G10-'Bank Liabilities Analysis'!H10 -> 0 | F11: =+'Bank Liabilities Analysis'!I10-'Bank Liabilities Analysis'!J10 -> 0 | G11: =+'Bank Liabilities Analysis'!K10-'Bank Liabilities Analysis'!L10 -> 0 | H11: =+'Bank Liabilities Analysis'!M10-'Bank Liabilities Analysis'!N10 -> 0 | I11: =+'Bank Liabilities Analysis'!O10-'Bank Liabilities Analysis'!P10 -> 0 | J11: =+'Bank Liabilities Analysis'!Q10-'Bank Liabilities Analysis'!R10 -> 0 | K11: =+C11+D11+E11+F11+G11+H11+I11+J11 -> 0 | L11: 0
A12: 1.1.3 | B12: Другие депозиты до востребования - под залогом по выданным кредитам | C12: =+'Bank Liabilities Analysis'!C11-'Bank Liabilities Analysis'!D11 -> 0 | D12: =+'Bank Liabilities Analysis'!E11-'Bank Liabilities Analysis'!F11 -> 0 | E12: =+'Bank Liabilities Analysis'!G11-'Bank Liabilities Analysis'!H11 -> 0 | F12: =+'Bank Liabilities Analysis'!I11-'Bank Liabilities Analysis'!J11 -> 0 | G12: =+'Bank Liabilities Analysis'!K11-'Bank Liabilities Analysis'!L11 -> 0 | H12: =+'Bank Liabilities Analysis'!M11-'Bank Liabilities Analysis'!N11 -> 0 | I12: =+'Bank Liabilities Analysis'!O11-'Bank Liabilities Analysis'!P11 -> 0 | J12: =+'Bank Liabilities Analysis'!Q11-'Bank Liabilities Analysis'!R11 -> 0 | K12: =+C12+D12+E12+F12+G12+H12+I12+J12 -> 0 | L12: 0
A13: 1.1.4 | B13: Другие депозиты до востребования | C13: =+'Bank Liabilities Analysis'!C12-'Bank Liabilities Analysis'!D12 -> 360426873 | D13: =+'Bank Liabilities Analysis'!E12-'Bank Liabilities Analysis'!F12 -> 0 | E13: =+'Bank Liabilities Analysis'!G12-'Bank Liabilities Analysis'!H12 -> 0 | F13: =+'Bank Liabilities Analysis'!I12-'Bank Liabilities Analysis'!J12 -> 0 | G13: =+'Bank Liabilities Analysis'!K12-'Bank Liabilities Analysis'!L12 -> 0 | H13: =+'Bank Liabilities Analysis'!M12-'Bank Liabilities Analysis'!N12 -> 0 | I13: =+'Bank Liabilities Analysis'!O12-'Bank Liabilities Analysis'!P12 -> 0 | J13: =+'Bank Liabilities Analysis'!Q12-'Bank Liabilities Analysis'!R12 -> 0 | K13: =+C13+D13+E13+F13+G13+H13+I13+J13 -> 360426873 | L13: 0.3 | M13: =(C13+D13+E13)*L13 -> 1.0812806e+08
A14: 1.2 | B14: Срочные депозиты, в том числе: | C14: =+'Bank Liabilities Analysis'!C13-'Bank Liabilities Analysis'!D13 -> 2602193 | D14: =+'Bank Liabilities Analysis'!E13-'Bank Liabilities Analysis'!F13 -> 128078648 | E14: =+'Bank Liabilities Analysis'!G13-'Bank Liabilities Analysis'!H13 -> 177312318 | F14: =+'Bank Liabilities Analysis'!I13-'Bank Liabilities Analysis'!J13 -> 226447625 | G14: =+'Bank Liabilities Analysis'!K13-'Bank Liabilities Analysis'!L13 -> 226878365 | H14: =+'Bank Liabilities Analysis'!M13-'Bank Liabilities Analysis'!N13 -> 492271286 | I14: =+'Bank Liabilities Analysis'!O13-'Bank Liabilities Analysis'!P13 -> 62186527 | J14: =+'Bank Liabilities Analysis'!Q13-'Bank Liabilities Analysis'!R13 -> 97186146 | K14: =+C14+D14+E14+F14+G14+H14+I14+J14 -> 1412963108 | L14: 1 | M14: =(C14+D14+E14)*L14 -> 307993159
A15: 1.2.1 | B15: Вклады физических лиц | C15: =+'Bank Liabilities Analysis'!C14-'Bank Liabilities Analysis'!D14 -> 0 | D15: =+'Bank Liabilities Analysis'!E14-'Bank Liabilities Analysis'!F14 -> 29218648 | E15: =+'Bank Liabilities Analysis'!G14-'Bank Liabilities Analysis'!H14 -> 54562318 | F15: =+'Bank Liabilities Analysis'!I14-'Bank Liabilities Analysis'!J14 -> 90550131 | G15: =+'Bank Liabilities Analysis'!K14-'Bank Liabilities Analysis'!L14 -> 74196480 | H15: =+'Bank Liabilities Analysis'!M14-'Bank Liabilities Analysis'!N14 -> 102332684 | I15: =+'Bank Liabilities Analysis'!O14-'Bank Liabilities Analysis'!P14 -> 18936527 | J15: =+'Bank Liabilities Analysis'!Q14-'Bank Liabilities Analysis'!R14 -> 2174301 | K15: =+C15+D15+E15+F15+G15+H15+I15+J15 -> 371971089 | L15: 0
A16: 1.2.2 | B16: Депозитные сертификаты | C16: =+'Bank Liabilities Analysis'!C15-'Bank Liabilities Analysis'!D15 -> 0 | D16: =+'Bank Liabilities Analysis'!E15-'Bank Liabilities Analysis'!F15 -> 0 | E16: =+'Bank Liabilities Analysis'!G15-'Bank Liabilities Analysis'!H15 -> 26000000 | F16: =+'Bank Liabilities Analysis'!I15-'Bank Liabilities Analysis'!J15 -> 9100000 | G16: =+'Bank Liabilities Analysis'!K15-'Bank Liabilities Analysis'!L15 -> 0 | H16: =+'Bank Liabilities Analysis'!M15-'Bank Liabilities Analysis'!N15 -> 0 | I16: =+'Bank Liabilities Analysis'!O15-'Bank Liabilities Analysis'!P15 -> 0 | J16: =+'Bank Liabilities Analysis'!Q15-'Bank Liabilities Analysis'!R15 -> 0 | K16: =+C16+D16+E16+F16+G16+H16+I16+J16 -> 35100000 | L16: 0
A17: 1.3 | B17: Другие депозиты клиентов | C17: =SUM(C18:C22) -> 172623541 | D17: =SUM(D18:D22) -> 0 | E17: =SUM(E18:E22) -> 0 | F17: =SUM(F18:F22) -> 0 | G17: =SUM(G18:G22) -> 0 | H17: =SUM(H18:H22) -> 0 | I17: =SUM(I18:I22) -> 0 | J17: =SUM(J18:J22) -> 0 | K17: =+C17+D17+E17+F17+G17+H17+I17+J17 -> 172623541
A18: 1.3.1 | B18: Средства на банковских пластиковых карточках - физических лиц | C18: =+'Bank Liabilities Analysis'!C17-'Bank Liabilities Analysis'!D17 -> 144077453 | D18: =+'Bank Liabilities Analysis'!E17-'Bank Liabilities Analysis'!F17 -> 0 | E18: =+'Bank Liabilities Analysis'!G17-'Bank Liabilities Analysis'!H17 -> 0 | F18: =+'Bank Liabilities Analysis'!I17-'Bank Liabilities Analysis'!J17 -> 0 | G18: =+'Bank Liabilities Analysis'!K17-'Bank Liabilities Analysis'!L17 -> 0 | H18: =+'Bank Liabilities Analysis'!M17-'Bank Liabilities Analysis'!N17 -> 0 | I18: =+'Bank Liabilities Analysis'!O17-'Bank Liabilities Analysis'!P17 -> 0 | J18: =+'Bank Liabilities Analysis'!Q17-'Bank Liabilities Analysis'!R17 -> 0 | K18: =+C18+D18+E18+F18+G18+H18+I18+J18 -> 144077453 | L18: 0.1 | M18: =(C18+D18+E18)*L18 -> 14407745
A19: 1.3.2 | B19: Средства на банковских пластиковых карточках - других клиентов | C19: =+'Bank Liabilities Analysis'!C18-'Bank Liabilities Analysis'!D18 -> 9411108 | D19: =+'Bank Liabilities Analysis'!E18-'Bank Liabilities Analysis'!F18 -> 0 | E19: =+'Bank Liabilities Analysis'!G18-'Bank Liabilities Analysis'!H18 -> 0 | F19: =+'Bank Liabilities Analysis'!I18-'Bank Liabilities Analysis'!J18 -> 0 | G19: =+'Bank Liabilities Analysis'!K18-'Bank Liabilities Analysis'!L18 -> 0 | H19: =+'Bank Liabilities Analysis'!M18-'Bank Liabilities Analysis'!N18 -> 0 | I19: =+'Bank Liabilities Analysis'!O18-'Bank Liabilities Analysis'!P18 -> 0 | J19: =+'Bank Liabilities Analysis'!Q18-'Bank Liabilities Analysis'!R18 -> 0 | K19: =+C19+D19+E19+F19+G19+H19+I19+J19 -> 9411108 | L19: 0.1 | M19: =(C19+D19+E19)*L19 -> 941110.8
A20: 1.3.3 | B20: Депозиты клиентов по аккредитивам | C20: =+'Bank Liabilities Analysis'!C19-'Bank Liabilities Analysis'!D19 -> 0 | D20: =+'Bank Liabilities Analysis'!E19-'Bank Liabilities Analysis'!F19 -> 0 | E20: =+'Bank Liabilities Analysis'!G19-'Bank Liabilities Analysis'!H19 -> 0 | F20: =+'Bank Liabilities Analysis'!I19-'Bank Liabilities Analysis'!J19 -> 0 | G20: =+'Bank Liabilities Analysis'!K19-'Bank Liabilities Analysis'!L19 -> 0 | H20: =+'Bank Liabilities Analysis'!M19-'Bank Liabilities Analysis'!N19 -> 0 | I20: =+'Bank Liabilities Analysis'!O19-'Bank Liabilities Analysis'!P19 -> 0 | J20: =+'Bank Liabilities Analysis'!Q19-'Bank Liabilities Analysis'!R19 -> 0 | K20: =+C20+D20+E20+F20+G20+H20+I20+J20 -> 0 | L20: 0.3 | M20: =(C20+D20+E20)*L20 -> 0
A21: 1.3.4 | B21: Зарезервированные средства клиентов для конвертации на валютном рынке | C21: =+'Bank Liabilities Analysis'!C20-'Bank Liabilities Analysis'!D20 -> 6492248 | D21: =+'Bank Liabilities Analysis'!E20-'Bank Liabilities Analysis'!F20 -> 0 | E21: =+'Bank Liabilities Analysis'!G20-'Bank Liabilities Analysis'!H20 -> 0 | F21: =+'Bank Liabilities Analysis'!I20-'Bank Liabilities Analysis'!J20 -> 0 | G21: =+'Bank Liabilities Analysis'!K20-'Bank Liabilities Analysis'!L20 -> 0 | H21: =+'Bank Liabilities Analysis'!M20-'Bank Liabilities Analysis'!N20 -> 0 | I21: =+'Bank Liabilities Analysis'!O20-'Bank Liabilities Analysis'!P20 -> 0 | J21: =+'Bank Liabilities Analysis'!Q20-'Bank Liabilities Analysis'!R20 -> 0 | K21: =+C21+D21+E21+F21+G21+H21+I21+J21 -> 6492248 | L21: 1 | M21: =(C21+D21+E21)*L21 -> 6492248
A22: 1.3.5 | B22: Другие | C22: =+'Bank Liabilities Analysis'!C21-'Bank Liabilities Analysis'!D21 -> 12642732 | D22: =+'Bank Liabilities Analysis'!E21-'Bank Liabilities Analysis'!F21 -> 0 | E22: =+'Bank Liabilities Analysis'!G21-'Bank Liabilities Analysis'!H21 -> 0 | F22: =+'Bank Liabilities Analysis'!I21-'Bank Liabilities Analysis'!J21 -> 0 | G22: =+'Bank Liabilities Analysis'!K21-'Bank Liabilities Analysis'!L21 -> 0 | H22: =+'Bank Liabilities Analysis'!M21-'Bank Liabilities Analysis'!N21 -> 0 | I22: =+'Bank Liabilities Analysis'!O21-'Bank Liabilities Analysis'!P21 -> 0 | J22: =+'Bank Liabilities Analysis'!Q21-'Bank Liabilities Analysis'!R21 -> 0 | K22: =+C22+D22+E22+F22+G22+H22+I22+J22 -> 12642732 | L22: 0.3 | M22: =(C22+D22+E22)*L22 -> 3792819.6
A23: 1.4 | B23: Итого депозитов | C23: =+C9+C14+C17 -> 546619657 | D23: =+D9+D14+D17 -> 128078648 | E23: =+E9+E14+E17 -> 177312318 | F23: =+F9+F14+F17 -> 226447625 | G23: =+G9+G14+G17 -> 226878365 | H23: =+H9+H14+H17 -> 492271286 | I23: =+I9+I14+I17 -> 62186527 | J23: =+J9+J14+J17 -> 97186146 | K23: =+C23+D23+E23+F23+G23+H23+I23+J23 -> 1956980572 | N23: 0.15 | O23: =+K23*N23 -> 2.9354709e+08
A24: 2. | B24: К оплате в ЦБРУ | C24: =+'Bank Liabilities Analysis'!C23-'Bank Liabilities Analysis'!D23 -> 0 | D24: =+'Bank Liabilities Analysis'!E23-'Bank Liabilities Analysis'!F23 -> 0 | E24: =+'Bank Liabilities Analysis'!G23-'Bank Liabilities Analysis'!H23 -> 0 | F24: =+'Bank Liabilities Analysis'!I23-'Bank Liabilities Analysis'!J23 -> 0 | G24: =+'Bank Liabilities Analysis'!K23-'Bank Liabilities Analysis'!L23 -> 0 | H24: =+'Bank Liabilities Analysis'!M23-'Bank Liabilities Analysis'!N23 -> 0 | I24: =+'Bank Liabilities Analysis'!O23-'Bank Liabilities Analysis'!P23 -> 0 | J24: =+'Bank Liabilities Analysis'!Q23-'Bank Liabilities Analysis'!R23 -> 0 | K24: =+C24+D24+E24+F24+G24+H24+I24+J24 -> 0 | L24: 1 | M24: =(C24+D24+E24)*L24 -> 0 | N24: 1 | O24: =(C24+D24+E24)*N24 -> 0
A25: 3. | B25: К оплате в другие банки | C25: =SUM(C26:C29) -> 4554422 | D25: =SUM(D26:D29) -> 0 | E25: =SUM(E26:E29) -> 0 | F25: =SUM(F26:F29) -> 100000000 | G25: =SUM(G26:G29) -> 50000000 | H25: =SUM(H26:H29) -> 45000000 | I25: =SUM(I26:I29) -> 0 | J25: =SUM(J26:J29) -> 718406301 | K25: =+C25+D25+E25+F25+G25+H25+I25+J25 -> 917960723
A26: 3.1 | B26: К оплате на корреспондентские счета других банков | C26: =+'Bank Liabilities Analysis'!C25-'Bank Liabilities Analysis'!D25 -> 0 | D26: =+'Bank Liabilities Analysis'!E25-'Bank Liabilities Analysis'!F25 -> 0 | E26: =+'Bank Liabilities Analysis'!G25-'Bank Liabilities Analysis'!H25 -> 0 | F26: =+'Bank Liabilities Analysis'!I25-'Bank Liabilities Analysis'!J25 -> 0 | G26: =+'Bank Liabilities Analysis'!K25-'Bank Liabilities Analysis'!L25 -> 0 | H26: =+'Bank Liabilities Analysis'!M25-'Bank Liabilities Analysis'!N25 -> 0 | I26: =+'Bank Liabilities Analysis'!O25-'Bank Liabilities Analysis'!P25 -> 0 | J26: =+'Bank Liabilities Analysis'!Q25-'Bank Liabilities Analysis'!R25 -> 0 | K26: =+C26+D26+E26+F26+G26+H26+I26+J26 -> 0 | L26: 1 | M26: =(K26)*L26 -> 0 | N26: 1 | O26: =+K26*N26 -> 0
A27: 3.2 | B27: К оплате в другие банки - депозиты | C27: =+'Bank Liabilities Analysis'!C26-'Bank Liabilities Analysis'!D26 -> 0 | D27: =+'Bank Liabilities Analysis'!E26-'Bank Liabilities Analysis'!F26 -> 0 | E27: =+'Bank Liabilities Analysis'!G26-'Bank Liabilities Analysis'!H26 -> 0 | F27: =+'Bank Liabilities Analysis'!I26-'Bank Liabilities Analysis'!J26 -> 100000000 | G27: =+'Bank Liabilities Analysis'!K26-'Bank Liabilities Analysis'!L26 -> 50000000 | H27: =+'Bank Liabilities Analysis'!M26-'Bank Liabilities Analysis'!N26 -> 45000000 | I27: =+'Bank Liabilities Analysis'!O26-'Bank Liabilities Analysis'!P26 -> 0 | J27: =+'Bank Liabilities Analysis'!Q26-'Bank Liabilities Analysis'!R26 -> 718406301 | K27: =+C27+D27+E27+F27+G27+H27+I27+J27 -> 913406301 | L27: 1 | M27: =(C27+D27+E27)*L27 -> 0 | N27: 1 | O27: =(C27+D27+E27)*N27 -> 0
A28: 3.3 | B28: К оплате в другие банки по расчётам с пластиковых карт | C28: =+'Bank Liabilities Analysis'!C27-'Bank Liabilities Analysis'!D27 -> 4554422 | D28: =+'Bank Liabilities Analysis'!E27-'Bank Liabilities Analysis'!F27 -> 0 | E28: =+'Bank Liabilities Analysis'!G27-'Bank Liabilities Analysis'!H27 -> 0 | F28: =+'Bank Liabilities Analysis'!I27-'Bank Liabilities Analysis'!J27 -> 0 | G28: =+'Bank Liabilities Analysis'!K27-'Bank Liabilities Analysis'!L27 -> 0 | H28: =+'Bank Liabilities Analysis'!M27-'Bank Liabilities Analysis'!N27 -> 0 | I28: =+'Bank Liabilities Analysis'!O27-'Bank Liabilities Analysis'!P27 -> 0 | J28: =+'Bank Liabilities Analysis'!Q27-'Bank Liabilities Analysis'!R27 -> 0 | K28: =+C28+D28+E28+F28+G28+H28+I28+J28 -> 4554422 | L28: 0.5 | M28: =(C28+D28+E28)*L28 -> 2277211 | N28: 1 | O28: =(C28+D28+E28)*N28 -> 4554422
A29: 3.4 | B29: Другие статьи | C29: =+'Bank Liabilities Analysis'!C28-'Bank Liabilities Analysis'!D28 -> 0 | D29: =+'Bank Liabilities Analysis'!E28-'Bank Liabilities Analysis'!F28 -> 0 | E29: =+'Bank Liabilities Analysis'!G28-'Bank Liabilities Analysis'!H28 -> 0 | F29: =+'Bank Liabilities Analysis'!I28-'Bank Liabilities Analysis'!J28 -> 0 | G29: =+'Bank Liabilities Analysis'!K28-'Bank Liabilities Analysis'!L28 -> 0 | H29: =+'Bank Liabilities Analysis'!M28-'Bank Liabilities Analysis'!N28 -> 0 | I29: =+'Bank Liabilities Analysis'!O28-'Bank Liabilities Analysis'!P28 -> 0 | J29: =+'Bank Liabilities Analysis'!Q28-'Bank Liabilities Analysis'!R28 -> 0 | K29: =+C29+D29+E29+F29+G29+H29+I29+J29 -> 0 | L29: 0.3 | M29: =(C29+D29+E29)*L29 -> 0 | N29: 1 | O29: =(C29+D29+E29)*N29 -> 0
A30: 4. | B30: Управленческие чеки | C30: =+'Bank Liabilities Analysis'!C29-'Bank Liabilities Analysis'!D29 -> 0 | D30: =+'Bank Liabilities Analysis'!E29-'Bank Liabilities Analysis'!F29 -> 0 | E30: =+'Bank Liabilities Analysis'!G29-'Bank Liabilities Analysis'!H29 -> 0 | F30: =+'Bank Liabilities Analysis'!I29-'Bank Liabilities Analysis'!J29 -> 0 | G30: =+'Bank Liabilities Analysis'!K29-'Bank Liabilities Analysis'!L29 -> 0 | H30: =+'Bank Liabilities Analysis'!M29-'Bank Liabilities Analysis'!N29 -> 0 | I30: =+'Bank Liabilities Analysis'!O29-'Bank Liabilities Analysis'!P29 -> 0 | J30: =+'Bank Liabilities Analysis'!Q29-'Bank Liabilities Analysis'!R29 -> 0 | K30: =+C30+D30+E30+F30+G30+H30+I30+J30 -> 0 | L30: 1 | M30: =(C30+D30+E30)*L30 -> 0 | N30: 1 | O30: =(C30+D30+E30)*N30 -> 0
A31: 5. | B31: Непогашенные акцепты, выполненные банком или по поручению этого банка | C31: =+'Bank Liabilities Analysis'!C30-'Bank Liabilities Analysis'!D30 -> 0 | D31: =+'Bank Liabilities Analysis'!E30-'Bank Liabilities Analysis'!F30 -> 0 | E31: =+'Bank Liabilities Analysis'!G30-'Bank Liabilities Analysis'!H30 -> 0 | F31: =+'Bank Liabilities Analysis'!I30-'Bank Liabilities Analysis'!J30 -> 0 | G31: =+'Bank Liabilities Analysis'!K30-'Bank Liabilities Analysis'!L30 -> 0 | H31: =+'Bank Liabilities Analysis'!M30-'Bank Liabilities Analysis'!N30 -> 0 | I31: =+'Bank Liabilities Analysis'!O30-'Bank Liabilities Analysis'!P30 -> 0 | J31: =+'Bank Liabilities Analysis'!Q30-'Bank Liabilities Analysis'!R30 -> 0 | K31: =+C31+D31+E31+F31+G31+H31+I31+J31 -> 0 | L31: 1 | M31: =(C31+D31+E31)*L31 -> 0 | N31: 1 | O31: =(C31+D31+E31)*N31 -> 0
A32: 6. | B32: Кредиты и лизинговые операции к оплате | C32: =+'Bank Liabilities Analysis'!C31-'Bank Liabilities Analysis'!D31 -> 1388027 | D32: =+'Bank Liabilities Analysis'!E31-'Bank Liabilities Analysis'!F31 -> 539725 | E32: =+'Bank Liabilities Analysis'!G31-'Bank Liabilities Analysis'!H31 -> 8567363 | F32: =+'Bank Liabilities Analysis'!I31-'Bank Liabilities Analysis'!J31 -> 25390782 | G32: =+'Bank Liabilities Analysis'!K31-'Bank Liabilities Analysis'!L31 -> 50378216 | H32: =+'Bank Liabilities Analysis'!M31-'Bank Liabilities Analysis'!N31 -> 97898807 | I32: =+'Bank Liabilities Analysis'!O31-'Bank Liabilities Analysis'!P31 -> 278209469 | J32: =+'Bank Liabilities Analysis'!Q31-'Bank Liabilities Analysis'!R31 -> 1707476733 | K32: =+C32+D32+E32+F32+G32+H32+I32+J32 -> 2169849122 | L32: 1 | M32: =(C32+D32+E32)*L32 -> 10495115 | N32: 0.15 | O32: =+K32*N32 -> 3.2547737e+08
A33: 7. | B33: Выпущенные банком ценные бумаги | C33: =+'Bank Liabilities Analysis'!C32-'Bank Liabilities Analysis'!D32 -> 0 | D33: =+'Bank Liabilities Analysis'!E32-'Bank Liabilities Analysis'!F32 -> 0 | E33: =+'Bank Liabilities Analysis'!G32-'Bank Liabilities Analysis'!H32 -> 0 | F33: =+'Bank Liabilities Analysis'!I32-'Bank Liabilities Analysis'!J32 -> 0 | G33: =+'Bank Liabilities Analysis'!K32-'Bank Liabilities Analysis'!L32 -> 0 | H33: =+'Bank Liabilities Analysis'!M32-'Bank Liabilities Analysis'!N32 -> 0 | I33: =+'Bank Liabilities Analysis'!O32-'Bank Liabilities Analysis'!P32 -> 0 | J33: =+'Bank Liabilities Analysis'!Q32-'Bank Liabilities Analysis'!R32 -> 0 | K33: =+C33+D33+E33+F33+G33+H33+I33+J33 -> 0 | L33: 1 | M33: =(C33+D33+E33)*L33 -> 0 | N33: 1 | O33: =(C33+D33+E33)*N33 -> 0
A34: 7a. | B34: Субординированные долговые обязательства | C34: =+'Bank Liabilities Analysis'!C33-'Bank Liabilities Analysis'!D33 -> 0 | D34: =+'Bank Liabilities Analysis'!E33-'Bank Liabilities Analysis'!F33 -> 0 | E34: =+'Bank Liabilities Analysis'!G33-'Bank Liabilities Analysis'!H33 -> 0 | F34: =+'Bank Liabilities Analysis'!I33-'Bank Liabilities Analysis'!J33 -> 0 | G34: =+'Bank Liabilities Analysis'!K33-'Bank Liabilities Analysis'!L33 -> 0 | H34: =+'Bank Liabilities Analysis'!M33-'Bank Liabilities Analysis'!N33 -> 0 | I34: =+'Bank Liabilities Analysis'!O33-'Bank Liabilities Analysis'!P33 -> 0 | J34: =+'Bank Liabilities Analysis'!Q33-'Bank Liabilities Analysis'!R33 -> 0 | K34: =+C34+D34+E34+F34+G34+H34+I34+J34 -> 0 | L34: 1 | M34: =(C34+D34+E34)*L34 -> 0 | N34: 1 | O34: =(C34+D34+E34)*N34 -> 0
A35: 8. | B35: Ценные бумаги проданные по соглашению с последующим выкупом | C35: =+'Bank Liabilities Analysis'!C34-'Bank Liabilities Analysis'!D34 -> 0 | D35: =+'Bank Liabilities Analysis'!E34-'Bank Liabilities Analysis'!F34 -> 0 | E35: =+'Bank Liabilities Analysis'!G34-'Bank Liabilities Analysis'!H34 -> 0 | F35: =+'Bank Liabilities Analysis'!I34-'Bank Liabilities Analysis'!J34 -> 0 | G35: =+'Bank Liabilities Analysis'!K34-'Bank Liabilities Analysis'!L34 -> 0 | H35: =+'Bank Liabilities Analysis'!M34-'Bank Liabilities Analysis'!N34 -> 0 | I35: =+'Bank Liabilities Analysis'!O34-'Bank Liabilities Analysis'!P34 -> 0 | J35: =+'Bank Liabilities Analysis'!Q34-'Bank Liabilities Analysis'!R34 -> 0 | K35: =+C35+D35+E35+F35+G35+H35+I35+J35 -> 0 | L35: 1 | M35: =(C35+D35+E35)*L35 -> 0 | N35: 1 | O35: =(C35+D35+E35)*N35 -> 0
A36: 9. | B36: Нереализованная прибыль или убытки по форвардным сделкам и другим отсроченным кредитам | C36: =+'Bank Liabilities Analysis'!C35-'Bank Liabilities Analysis'!D35 -> 20924 | D36: =+'Bank Liabilities Analysis'!E35-'Bank Liabilities Analysis'!F35 -> 0 | E36: =+'Bank Liabilities Analysis'!G35-'Bank Liabilities Analysis'!H35 -> 0 | F36: =+'Bank Liabilities Analysis'!I35-'Bank Liabilities Analysis'!J35 -> 0 | G36: =+'Bank Liabilities Analysis'!K35-'Bank Liabilities Analysis'!L35 -> 0 | H36: =+'Bank Liabilities Analysis'!M35-'Bank Liabilities Analysis'!N35 -> 0 | I36: =+'Bank Liabilities Analysis'!O35-'Bank Liabilities Analysis'!P35 -> 0 | J36: =+'Bank Liabilities Analysis'!Q35-'Bank Liabilities Analysis'!R35 -> 0 | K36: =+C36+D36+E36+F36+G36+H36+I36+J36 -> 20924 | L36: 1 | M36: =(C36+D36+E36)*L36 -> 20924 | N36: 1 | O36: =+K36*N36 -> 20924
A37: 10. | B37: Клиринговые счета - кредитовый остаток | C37: =+'Bank Liabilities Analysis'!C36-'Bank Liabilities Analysis'!D36 -> 497730 | D37: =+'Bank Liabilities Analysis'!E36-'Bank Liabilities Analysis'!F36 -> 0 | E37: =+'Bank Liabilities Analysis'!G36-'Bank Liabilities Analysis'!H36 -> 0 | F37: =+'Bank Liabilities Analysis'!I36-'Bank Liabilities Analysis'!J36 -> 0 | G37: =+'Bank Liabilities Analysis'!K36-'Bank Liabilities Analysis'!L36 -> 0 | H37: =+'Bank Liabilities Analysis'!M36-'Bank Liabilities Analysis'!N36 -> 0 | I37: =+'Bank Liabilities Analysis'!O36-'Bank Liabilities Analysis'!P36 -> 0 | J37: =+'Bank Liabilities Analysis'!Q36-'Bank Liabilities Analysis'!R36 -> 0 | K37: =+C37+D37+E37+F37+G37+H37+I37+J37 -> 497730 | L37: 1 | M37: =(C37+D37+E37)*L37 -> 497730 | N37: 1 | O37: =+K37*N37 -> 497730
A38: 11. | B38: Начисленные проценты | C38: =+'Bank Liabilities Analysis'!C37-'Bank Liabilities Analysis'!D37 -> 50677310 | D38: =+'Bank Liabilities Analysis'!E37-'Bank Liabilities Analysis'!F37 -> 0 | E38: =+'Bank Liabilities Analysis'!G37-'Bank Liabilities Analysis'!H37 -> 0 | F38: =+'Bank Liabilities Analysis'!I37-'Bank Liabilities Analysis'!J37 -> 0 | G38: =+'Bank Liabilities Analysis'!K37-'Bank Liabilities Analysis'!L37 -> 0 | H38: =+'Bank Liabilities Analysis'!M37-'Bank Liabilities Analysis'!N37 -> 0 | I38: =+'Bank Liabilities Analysis'!O37-'Bank Liabilities Analysis'!P37 -> 0 | J38: =+'Bank Liabilities Analysis'!Q37-'Bank Liabilities Analysis'!R37 -> 0 | K38: =+C38+D38+E38+F38+G38+H38+I38+J38 -> 50677310 | L38: 1 | M38: =(C38+D38+E38)*L38 -> 50677310 | O38: =C38+D38+E38+((F38+G38+H38+I38+J38)*15%) -> 50677310
A39: 12. | B39: Другие обязательства | C39: =+'Bank Liabilities Analysis'!C38-'Bank Liabilities Analysis'!D38 -> 67965037 | D39: =+'Bank Liabilities Analysis'!E38-'Bank Liabilities Analysis'!F38 -> 0 | E39: =+'Bank Liabilities Analysis'!G38-'Bank Liabilities Analysis'!H38 -> 0 | F39: =+'Bank Liabilities Analysis'!I38-'Bank Liabilities Analysis'!J38 -> 0 | G39: =+'Bank Liabilities Analysis'!K38-'Bank Liabilities Analysis'!L38 -> 0 | H39: =+'Bank Liabilities Analysis'!M38-'Bank Liabilities Analysis'!N38 -> 0 | I39: =+'Bank Liabilities Analysis'!O38-'Bank Liabilities Analysis'!P38 -> 0 | J39: =+'Bank Liabilities Analysis'!Q38-'Bank Liabilities Analysis'!R38 -> 0 | K39: =+C39+D39+E39+F39+G39+H39+I39+J39 -> 67965037 | L39: 0.3 | M39: =(C39+D39+E39)*L39 -> 20389511 | N39: 1 | O39: =+K39*N39 -> 67965037
A40: 13. | B40: ИТОГО ОБЯЗАТЕЛЬСТВ | C40: =+C23+C30+C31+C32+C33+C34+C35+C36+C37+C38+C39+C24+C25 -> 671723107 | D40: =+D23+D30+D31+D32+D33+D34+D35+D36+D37+D38+D39+D24+D25 -> 128618373 | E40: =+E23+E30+E31+E32+E33+E34+E35+E36+E37+E38+E39+E24+E25 -> 185879681 | F40: =+F23+F30+F31+F32+F33+F34+F35+F36+F37+F38+F39+F24+F25 -> 351838407 | G40: =+G23+G30+G31+G32+G33+G34+G35+G36+G37+G38+G39+G24+G25 -> 327256581 | H40: =+H23+H30+H31+H32+H33+H34+H35+H36+H37+H38+H39+H24+H25 -> 635170093 | I40: =+I23+I30+I31+I32+I33+I34+I35+I36+I37+I38+I39+I24+I25 -> 340395996 | J40: =+J23+J30+J31+J32+J33+J34+J35+J36+J37+J38+J39+J24+J25 -> 2523069180 | K40: =+K23+K30+K31+K32+K33+K34+K35+K36+K37+K38+K39+K24+K25 -> 5163951418 | L40: отток | M40: =SUM(M9:M39) -> 5.2720965e+08 | N40: отток | O40: =SUM(O9:O39) -> 7.4273988e+08 | P40: =+Balance!D62 -> 5163951418
B41: из них, обязательства перед: | K41: =+C41+D41+E41+F41+G41+H41+I41+J41 -> 0 | P41: =+Balance!C63 -> 0
B42: Министерство Финансов Республики Узбекистан, из них | C42: =+C43+C44 -> 0 | D42: =+D43+D44 -> 0 | E42: =+E43+E44 -> 0 | F42: =+F43+F44 -> 31492 | G42: =+G43+G44 -> 24978 | H42: =+H43+H44 -> 2141532 | I42: =+I43+I44 -> 8007273 | J42: =+J43+J44 -> 148343207 | K42: =+C42+D42+E42+F42+G42+H42+I42+J42 -> 158548482
B43: Кредиты и лизинги | C43: =+'Bank Liabilities Analysis'!C42-'Bank Liabilities Analysis'!D42 -> 0 | D43: =+'Bank Liabilities Analysis'!E42-'Bank Liabilities Analysis'!F42 -> 0 | E43: =+'Bank Liabilities Analysis'!G42-'Bank Liabilities Analysis'!H42 -> 0 | F43: =+'Bank Liabilities Analysis'!I42-'Bank Liabilities Analysis'!J42 -> 31492 | G43: =+'Bank Liabilities Analysis'!K42-'Bank Liabilities Analysis'!L42 -> 24978 | H43: =+'Bank Liabilities Analysis'!M42-'Bank Liabilities Analysis'!N42 -> 2141532 | I43: =+'Bank Liabilities Analysis'!O42-'Bank Liabilities Analysis'!P42 -> 8007273 | J43: =+'Bank Liabilities Analysis'!Q42-'Bank Liabilities Analysis'!R42 -> 148343207 | K43: =+C43+D43+E43+F43+G43+H43+I43+J43 -> 158548482
B44: Депозитные ресурсы | C44: =+'Bank Liabilities Analysis'!C43-'Bank Liabilities Analysis'!D43 -> 0 | D44: =+'Bank Liabilities Analysis'!E43-'Bank Liabilities Analysis'!F43 -> 0 | E44: =+'Bank Liabilities Analysis'!G43-'Bank Liabilities Analysis'!H43 -> 0 | F44: =+'Bank Liabilities Analysis'!I43-'Bank Liabilities Analysis'!J43 -> 0 | G44: =+'Bank Liabilities Analysis'!K43-'Bank Liabilities Analysis'!L43 -> 0 | H44: =+'Bank Liabilities Analysis'!M43-'Bank Liabilities Analysis'!N43 -> 0 | I44: =+'Bank Liabilities Analysis'!O43-'Bank Liabilities Analysis'!P43 -> 0 | J44: =+'Bank Liabilities Analysis'!Q43-'Bank Liabilities Analysis'!R43 -> 0 | K44: =+C44+D44+E44+F44+G44+H44+I44+J44 -> 0
B45: Внебюджетные фонды, из них | C45: =+C46+C47 -> 0 | D45: =+D46+D47 -> 0 | E45: =+E46+E47 -> 5090682 | F45: =+F46+F47 -> 12302436 | G45: =+G46+G47 -> 54878124 | H45: =+H46+H47 -> 86520558 | I45: =+I46+I47 -> 95001516 | J45: =+J46+J47 -> 46116095 | K45: =+C45+D45+E45+F45+G45+H45+I45+J45 -> 299909411
B46: Кредиты и лизинги | C46: =+'Bank Liabilities Analysis'!C45-'Bank Liabilities Analysis'!D45 -> 0 | D46: =+'Bank Liabilities Analysis'!E45-'Bank Liabilities Analysis'!F45 -> 0 | E46: =+'Bank Liabilities Analysis'!G45-'Bank Liabilities Analysis'!H45 -> 5090682 | F46: =+'Bank Liabilities Analysis'!I45-'Bank Liabilities Analysis'!J45 -> 12302436 | G46: =+'Bank Liabilities Analysis'!K45-'Bank Liabilities Analysis'!L45 -> 19937138 | H46: =+'Bank Liabilities Analysis'!M45-'Bank Liabilities Analysis'!N45 -> 41120558 | I46: =+'Bank Liabilities Analysis'!O45-'Bank Liabilities Analysis'!P45 -> 59801516 | J46: =+'Bank Liabilities Analysis'!Q45-'Bank Liabilities Analysis'!R45 -> 31116095 | K46: =+C46+D46+E46+F46+G46+H46+I46+J46 -> 169368425
B47: Депозитные ресурсы | C47: =+'Bank Liabilities Analysis'!C46-'Bank Liabilities Analysis'!D46 -> 0 | D47: =+'Bank Liabilities Analysis'!E46-'Bank Liabilities Analysis'!F46 -> 0 | E47: =+'Bank Liabilities Analysis'!G46-'Bank Liabilities Analysis'!H46 -> 0 | F47: =+'Bank Liabilities Analysis'!I46-'Bank Liabilities Analysis'!J46 -> 0 | G47: =+'Bank Liabilities Analysis'!K46-'Bank Liabilities Analysis'!L46 -> 34940986 | H47: =+'Bank Liabilities Analysis'!M46-'Bank Liabilities Analysis'!N46 -> 45400000 | I47: =+'Bank Liabilities Analysis'!O46-'Bank Liabilities Analysis'!P46 -> 35200000 | J47: =+'Bank Liabilities Analysis'!Q46-'Bank Liabilities Analysis'!R46 -> 15000000 | K47: =+C47+D47+E47+F47+G47+H47+I47+J47 -> 130540986
B48: Фонд реконструкции и развития Узбекистана (ФРРУ) , из них | C48: =+C49+C50 -> 0 | D48: =+D49+D50 -> 0 | E48: =+E49+E50 -> 0 | F48: =+F49+F50 -> 0 | G48: =+G49+G50 -> 34940986 | H48: =+H49+H50 -> 0 | I48: =+I49+I50 -> 121704917 | J48: =+J49+J50 -> 1245027391 | K48: =+C48+D48+E48+F48+G48+H48+I48+J48 -> 1.4016733e+09
B49: Кредиты и лизинги | C49: =+'Bank Liabilities Analysis'!C48-'Bank Liabilities Analysis'!D48 -> 0 | D49: =+'Bank Liabilities Analysis'!E48-'Bank Liabilities Analysis'!F48 -> 0 | E49: =+'Bank Liabilities Analysis'!G48-'Bank Liabilities Analysis'!H48 -> 0 | F49: =+'Bank Liabilities Analysis'!I48-'Bank Liabilities Analysis'!J48 -> 0 | G49: =+'Bank Liabilities Analysis'!K48-'Bank Liabilities Analysis'!L48 -> 0 | H49: =+'Bank Liabilities Analysis'!M48-'Bank Liabilities Analysis'!N48 -> 0 | I49: =+'Bank Liabilities Analysis'!O48-'Bank Liabilities Analysis'!P48 -> 121704917 | J49: =+'Bank Liabilities Analysis'!Q48-'Bank Liabilities Analysis'!R48 -> 1245027391 | K49: =+C49+D49+E49+F49+G49+H49+I49+J49 -> 1366732308
B50: Депозитные ресурсы | C50: =+'Bank Liabilities Analysis'!C49-'Bank Liabilities Analysis'!D49 -> 0 | D50: =+'Bank Liabilities Analysis'!E49-'Bank Liabilities Analysis'!F49 -> 0 | E50: =+'Bank Liabilities Analysis'!G49-'Bank Liabilities Analysis'!H49 -> 0 | F50: =+'Bank Liabilities Analysis'!I49-'Bank Liabilities Analysis'!J49 -> 0 | G50: =+'Bank Liabilities Analysis'!K49-'Bank Liabilities Analysis'!L49 -> 34940986 | H50: =+'Bank Liabilities Analysis'!M49-'Bank Liabilities Analysis'!N49 -> 0 | I50: =+'Bank Liabilities Analysis'!O49-'Bank Liabilities Analysis'!P49 -> 0 | J50: =+'Bank Liabilities Analysis'!Q49-'Bank Liabilities Analysis'!R49 -> 0 | K50: =+C50+D50+E50+F50+G50+H50+I50+J50 -> 34940986
B51: Зарубежные банки, из них | C51: =+C52+C53 -> 0 | D51: =+D52+D53 -> 0 | E51: =+E52+E53 -> 0 | F51: =+F52+F53 -> 0 | G51: =+G52+G53 -> 0 | H51: =+H52+H53 -> 0 | I51: =+I52+I53 -> 0 | J51: =+J52+J53 -> 0 | K51: =+C51+D51+E51+F51+G51+H51+I51+J51 -> 0
B52: Кредиты и лизинги | C52: =+'Bank Liabilities Analysis'!C51-'Bank Liabilities Analysis'!D51 -> 0 | D52: =+'Bank Liabilities Analysis'!E51-'Bank Liabilities Analysis'!F51 -> 0 | E52: =+'Bank Liabilities Analysis'!G51-'Bank Liabilities Analysis'!H51 -> 0 | F52: =+'Bank Liabilities Analysis'!I51-'Bank Liabilities Analysis'!J51 -> 0 | G52: =+'Bank Liabilities Analysis'!K51-'Bank Liabilities Analysis'!L51 -> 0 | H52: =+'Bank Liabilities Analysis'!M51-'Bank Liabilities Analysis'!N51 -> 0 | I52: =+'Bank Liabilities Analysis'!O51-'Bank Liabilities Analysis'!P51 -> 0 | J52: =+'Bank Liabilities Analysis'!Q51-'Bank Liabilities Analysis'!R51 -> 0 | K52: =+C52+D52+E52+F52+G52+H52+I52+J52 -> 0
B53: Депозитные ресурсы | C53: =+'Bank Liabilities Analysis'!C52-'Bank Liabilities Analysis'!D52 -> 0 | D53: =+'Bank Liabilities Analysis'!E52-'Bank Liabilities Analysis'!F52 -> 0 | E53: =+'Bank Liabilities Analysis'!G52-'Bank Liabilities Analysis'!H52 -> 0 | F53: =+'Bank Liabilities Analysis'!I52-'Bank Liabilities Analysis'!J52 -> 0 | G53: =+'Bank Liabilities Analysis'!K52-'Bank Liabilities Analysis'!L52 -> 0 | H53: =+'Bank Liabilities Analysis'!M52-'Bank Liabilities Analysis'!N52 -> 0 | I53: =+'Bank Liabilities Analysis'!O52-'Bank Liabilities Analysis'!P52 -> 0 | J53: =+'Bank Liabilities Analysis'!Q52-'Bank Liabilities Analysis'!R52 -> 0 | K53: =+C53+D53+E53+F53+G53+H53+I53+J53 -> 0
B54: Другие зарубежные финансовые организации, из них | C54: =+C55+C56 -> 0 | D54: =+D55+D56 -> 0 | E54: =+E55+E56 -> 0 | F54: =+F55+F56 -> 0 | G54: =+G55+G56 -> 0 | H54: =+H55+H56 -> 0 | I54: =+I55+I56 -> 0 | J54: =+J55+J56 -> 0 | K54: =+C54+D54+E54+F54+G54+H54+I54+J54 -> 0
B55: Кредиты и лизинги | C55: =+'Bank Liabilities Analysis'!C54-'Bank Liabilities Analysis'!D54 -> 0 | D55: =+'Bank Liabilities Analysis'!E54-'Bank Liabilities Analysis'!F54 -> 0 | E55: =+'Bank Liabilities Analysis'!G54-'Bank Liabilities Analysis'!H54 -> 0 | F55: =+'Bank Liabilities Analysis'!I54-'Bank Liabilities Analysis'!J54 -> 0 | G55: =+'Bank Liabilities Analysis'!K54-'Bank Liabilities Analysis'!L54 -> 0 | H55: =+'Bank Liabilities Analysis'!M54-'Bank Liabilities Analysis'!N54 -> 0 | I55: =+'Bank Liabilities Analysis'!O54-'Bank Liabilities Analysis'!P54 -> 0 | J55: =+'Bank Liabilities Analysis'!Q54-'Bank Liabilities Analysis'!R54 -> 0 | K55: =+C55+D55+E55+F55+G55+H55+I55+J55 -> 0
B56: Депозитные ресурсы | C56: =+'Bank Liabilities Analysis'!C55-'Bank Liabilities Analysis'!D55 -> 0 | D56: =+'Bank Liabilities Analysis'!E55-'Bank Liabilities Analysis'!F55 -> 0 | E56: =+'Bank Liabilities Analysis'!G55-'Bank Liabilities Analysis'!H55 -> 0 | F56: =+'Bank Liabilities Analysis'!I55-'Bank Liabilities Analysis'!J55 -> 0 | G56: =+'Bank Liabilities Analysis'!K55-'Bank Liabilities Analysis'!L55 -> 0 | H56: =+'Bank Liabilities Analysis'!M55-'Bank Liabilities Analysis'!N55 -> 0 | I56: =+'Bank Liabilities Analysis'!O55-'Bank Liabilities Analysis'!P55 -> 0 | J56: =+'Bank Liabilities Analysis'!Q55-'Bank Liabilities Analysis'!R55 -> 0 | K56: =+C56+D56+E56+F56+G56+H56+I56+J56 -> 0
B58: Подпись Председателя правления:
B60: Подпись Главного Бухгалтера:

Sheet Commitments
A1: ОТЧЕТ О СЧЕТАХ ОБЯЗАТЕЛЬСТВ И НЕПРЕДВИДЕННЫХ ОБСТОЯТЕЛЬСТВ | E1: Таблица-19
B2: =Balance!B3 -> АКБ"Микрокредитбанк" | C2: =+Balance!B2 -> 31 Декабрь, 2020 | E2: =+Balance!E3 -> тыс. сум
A3: № | B3: Категории | C3: Итого | D3: в национальной валюте | E3: в иностранной валюте (в экв. в сумах)
A4: 1. | B4: Обязательства по выдачи кредитов | C4: =+D4+E4 -> 879166551 | D4: 323540070 | E4: 555626481
A5: 1.1. | B5: в том числе, за счет кредитных линий (с особыми условиями) | C5: =+D5+E5 -> 0 | D5: 0 | E5: 0
A7: 2. | B7: Гарантии и поручительства | C7: =+D7+E7 -> 120707714 | D7: 17868142 | E7: 102839572
A8: 2.1. | B8: в том числе, обеспеченные депозитами | C8: =+D8+E8 -> 0 | D8: 0 | E8: 0
A10: 3. | B10: Итого аккредитивы | C10: =+D10+E10 -> 5891080 | D10: =SUM(D11:D14) -> 0 | E10: =SUM(E11:E14) -> 5891080
A11: 3.1. | B11: Покрытый аккредитив, открытый в банках плательщиком | C11: =+D11+E11 -> 5891080 | D11: 0 | E11: 5891080
A12: 3.2. | B12: Непогашенные аккредитивы на импорт с оплатой тратт на предъявителя | C12: =+D12+E12 -> 0 | D12: 0 | E12: 0
A13: 3.3. | B13: Непогашенные аккредитивы на импорт против выставления срочных тратт | C13: =+D13+E13 -> 0 | D13: 0 | E13: 0
A14: 3.4. | B14: Другие аккредитивы | C14: =+D14+E14 -> 0 | D14: 0 | E14: 0
A16: 4. | B16: Факторинг, инкассо и другие торговые финансирование | C16: =+D16+E16 -> 4701882 | D16: 4701882 | E16: 0
A18: 5. | B18: Итого других статей непредвиденных обстоятельств | C18: =+D18+E18 -> 25786484 | D18: =SUM(D19:D23) -> 23574370 | E18: =SUM(E19:E23) -> 2212114
A19: 5.1. | B19: Условная стоимость процентного свопа | C19: =+D19+E19 -> 0 | D19: 0 | E19: 0
A20: 5.2. | B20: Условная стоимость обменного свопа (Валютный своп) | C20: =+D20+E20 -> 0 | D20: 0 | E20: 0
A21: 5.3. | B21: Фьючерсные, Форвардные и Опционные контракты | C21: =+D21+E21 -> 0 | D21: 0 | E21: 0
A22: 5.4. | B22: Обязательства по покупке кредитов, ценных бумаг или других активов | C22: =+D22+E22 -> 0 | D22: 0 | E22: 0
A23: 5.5. | B23: Другие счета непредвиденных обстоятельств | C23: =+D23+E23 -> 25786484 | D23: 23574370 | E23: 2212114
A25: 6. | B25: Итого статей непредвиденных обстоятельств | C25: =+C4+C7+C10+C16+C18 -> 1036253711 | D25: =+D4+D7+D10+D16+D18 -> 369684464 | E25: =+E4+E7+E10+E16+E18 -> 666569247
B28: Подпись Председателя правления:
B30: Подпись Главного Бухгалтера:

Sheet Deposits by Client
A1: ОТЧЕТ О ДЕПОЗИТАХ ПО ТИПАМ КЛИЕНТОВ | D1: Таблица-14
B2: =+Balance!B3 -> АКБ"Микрокредитбанк" | C2: =+Balance!B2 -> 31 Декабрь, 2020 | D2: в тыс. сум
A3: № | B3: Категории | C3: Итого | D3: из них, в иностранной валюте (в экв. в сумах)
A4: 1. | B4: Депозиты до востребования
A5: а. | B5: Правительство | C5: 2991155 | D5: 30869
A6: б. | B6: Физические лица | C6: 163360536 | D6: 8316034
A7: в. | B7: Государственные предприятия | C7: 103153179 | D7: 14723325
A8: г. | B8: Совместные и иностранные предприятия | C8: 2630430 | D8: 761674
A9: д. | B9: Частные товарищества и корпорации | C9: 200269899 | D9: 5282293
A10: е. | B10: Другие депозиты до востребования | C10: 149092721 | D10: 48366261
A11: ж. | B11: Итого депозитов до востребования | C11: =SUM(C5:C10) -> 621497920 | D11: =SUM(D5:D10) -> 77480456 | E11: =+'Bank Liabilities Analysis'!S16+'Bank Liabilities Analysis'!S8 -> 621497920 | F11: =+'Bank Liabilities Analysis'!T16+'Bank Liabilities Analysis'!T8 -> 544017464 | G11: =+'Bank Liabilities Analysis'!U16+'Bank Liabilities Analysis'!U8 -> 77480456
A13: 2. | B13: Срочные депозиты
A14: а. | B14: Правительство | C14: 939658840 | D14: 157510015
A15: б. | B15: Физические лица | C15: 434997875 | D15: 63026787
A16: в. | B16: Государственные предприятия | C16: 191816390 | D16: 123555227
A17: г. | B17: Совместные и иностранные предприятия | C17: 9675000 | D17: 0
A18: д. | B18: Частные товарищества и корпорации | C18: 51642679 | D18: 2095384
A19: е. | B19: Другие cрочные депозиты | C19: 133455121 | D19: 2095384
A20: ж. | B20: Итого срочных депозитов | C20: =SUM(C14:C19) -> 1761245905 | D20: =SUM(D14:D19) -> 348282797 | E20: =+'Bank Liabilities Analysis'!S13 -> 1761245905 | F20: =+'Bank Liabilities Analysis'!T13 -> 1412963108 | G20: =+'Bank Liabilities Analysis'!U13 -> 348282797
A22: 3. | B22: Итого депозитов | C22: =+C11+C20 -> 2382743825 | D22: =+D11+D20 -> 425763253 | E22: =+'Bank Liabilities Analysis'!S22 -> 2382743825 | F22: =+'Bank Liabilities Analysis'!T22 -> 1956980572 | G22: =+'Bank Liabilities Analysis'!U22 -> 425763253
B25: Подпись Председателя правления:
B27: Подпись Главного Бухгалтера:

Sheet Investment Securities
A1: ОТЧЕТ ОБ ИНВЕСТИЦИЯХ В ЦЕННЫЕ БУМАГИ И СЧЕТА КУПЛИ-ПРОДАЖИ АКТИВОВ | E1: Таблица-15
A2: =Balance!B3 -> АКБ"Микрокредитбанк" | C2: =+Balance!B2 -> 31 Декабрь, 2020 | E2: =+Balance!E3 -> тыс. сум
A3: Часть 1 - Инвестиции в ценные бумаги | B3: Балансовая стоимость | C3: Балансовая стоимость | E3: Рыночная стоимость
C4: в национальной валюте | D4: в иностранной валюте (в экв. в сумах)
A6: 1. Инвестиции в государственные облигации | B6: =+C6+D6 -> 0 | C6: 0 | D6: 0 | E6: 0
A7: 2. Инвестиции в ценные бумаги и облигации ЦБРУ | B7: =+C7+D7 -> 0 | C7: 0 | D7: 0 | E7: 0
A8: 3. Инвестиции в частные облигации | B8: =+C8+D8 -> 0 | C8: 0 | D8: 0 | E8: 0
A9: 4. Инвестиции в еврооблигации | B9: =+C9+D9 -> 0 | C9: 0 | D9: 0 | E9: 0
A10: 5. Инвестиции в акции гос предприятий | B10: =+C10+D10 -> 0 | C10: 0 | D10: 0 | E10: 0
A11: 6. Инвестиции в акции частных предприятий | B11: =+C11+D11 -> 107220 | C11: 107220 | D11: 0 | E11: 107220
A12: 7. Инвестиции в другие ценные бумаги | B12: =+C12+D12 -> 0 | C12: 0 | D12: 0 | E12: 0
A13: 8. Итого инвестиций | B13: =+C13+D13 -> 107220 | C13: =SUM(C6:C12) -> 107220 | D13: =SUM(D6:D12) -> 0 | E13: =SUM(E6:E12) -> 107220
A14: 9. Минус: Резерв возможных убытков | B14: =+C14+D14 -> 0 | C14: 0 | D14: 0
A15: 10. Чистая балансовая стоимость инвестиций | B15: =+C15+D15 -> 107220 | C15: =C13-C14 -> 107220 | D15: =D13-D14 -> 0 | F15: =+'Bank Assets Analysis'!S34 -> 107220 | G15: =+'Bank Assets Analysis'!T34 -> 107220 | H15: =+'Bank Assets Analysis'!U34 -> 0
A17: Часть 2 - Счета купли-продажи ценных бумаг | B17: Балансовая стоимость | C17: в национальной валюте | D17: в иностранной валюте (в экв. в сумах) | E17: Рыночная стоимость | F17: =+Balance!C17 -> 107220 | G17: =+Balance!D17 -> 107220 | H17: =+Balance!E17 -> 0
A19: 1. Государственные казначейские векселя | B19: =+C19+D19 -> 0 | C19: 0 | D19: 0 | E19: 0
A20: 2. Государственные облигации | B20: =+C20+D20 -> 135000000 | C20: 135000000 | D20: 0 | E20: 135000000
A21: 3. Ценные бумаги и облигации ЦБРУ | B21: =+C21+D21 -> 65000000 | C21: 65000000 | D21: 0 | E21: 65000000
A22: 4. Ценные бумаги гос корпораций | B22: =+C22+D22 -> 0 | C22: 0 | D22: 0 | E22: 0
A23: 5. Еврооблигации | B23: =+C23+D23 -> 0 | C23: 0 | D23: 0 | E23: 0
A24: 6. Частные ценные бумаги | B24: =+C24+D24 -> 0 | C24: 0 | D24: 0 | E24: 0
A25: 7. Другие ценные бумаги | B25: =+C25+D25 -> 0 | D25: 0 | E25: 2938240
A26: 8. Итого по счетам купли-продажи ценных бумаг | B26: =+C26+D26 -> 200000000 | C26: =SUM(C19:C25) -> 200000000 | D26: =SUM(D19:D25) -> 0 | E26: =SUM(E19:E25) -> 202938240
A27: 9. Дисконт и премии по ценным бумагам | B27: =+C27+D27 -> 2938240 | C27: 2938240 | D27: 0 | E27: 0
A28: 10. Минус: Резерв возможных убытков | B28: =+C28+D28 -> 0 | C28: =+D28+E28 -> 0 | D28: 0
A29: 11. Чистая балансовая стоимость по счетам купли-продажи ц/б | B29: =+C29+D29 -> 202938240 | C29: =+C26+C27-C28 -> 202938240 | D29: =+D26+D27-D28 -> 0
A33: Часть 3 - Счета купли и продажи драгоценных металлов | B33: Первоначальная стоимость | C33: в национальной валюте | D33: в иностранной валюте (в экв. в сумах) | E33: Рыночная стоимость
A35: 1. Драгоценные металлы | B35: =+C35+D35 -> 0 | C35: 0 | D35: 0 | E35: 0
A36: 2. Драгоценные камни | B36: =+C36+D36 -> 0 | C36: 0 | D36: 0 | E36: 0
A37: 3. Драгоценные монеты | B37: =+C37+D37 -> 175 | C37: 175 | D37: 0 | E37: 175
A38: 4. Итого драгоценных металлов | B38: =+C38+D38 -> 175 | C38: =SUM(C35:C37) -> 175 | D38: =SUM(D35:D37) -> 0 | E38: =SUM(E35:E37) -> 175
A39: 5. Минус: Резерв возможных убытков | B39: =+C39+D39 -> 0
A40: 6. Чистая балансовая стоимость по счетам купли и продажи д/м | B40: =+C40+D40 -> 175 | C40: =C38-C39 -> 175 | D40: =D38-D39 -> 0
A42: Примечание:
A43: Итого ценных бумаг заложенных для общественных депозитов
A44: Портфель инвестиций в ценные бумаги
A45: Увеличение (Снижение) стоимости | B45: =E13-B13 -> 0
A46: Счета купли-продажи ценных бумаг
A47: Увеличение (Снижение) стоимости | B47: =E26-B26 -> 2938240
A48: Счета купли-продажи драгоценных предметов
A49: Увеличение (Снижение) стоимости | B49: =E38-B38 -> 0
A52: Подпись Председателя правления:
A54: Подпись Главного Бухгалтера:
